Workbook
Name _Builtin0: #N/A

Sheet Notes
B2: Bell Medical Note
B3: Fire Inspections
B5: Parking Lot
B6: Roof
B7: Vendor Changes
B14: Notes to Owner
B15: Notes for 2025
B20: Misc | C20: Management Agreement Commenced June 1, 2025

Sheet Variance
A1: Particulars | B1: 46023 | G1: 46054 | L1: 46082 | Q1: 46113 | V1: 46143 | Z1: 46199 | AF1: 46229 | AM1: YTD
B2: Budget | C2: Payment | D2: Variance | E2: Comments | G2: Budget | H2: Payment | I2: Variance | J2: Comments | L2: Budget | M2: Payment | N2: Variance | O2: Comments | Q2: Budget | R2: Payment | S2: Variance | T2: Comments | V2: Budget | W2: Payment | X2: Variance | Y2: Comments | AA2: Budget | AB2: Payment | AC2: Variance | AD2: Comments | AG2: Budget | AH2: Payment | AI2: Variance | AJ2: Comments | AL2: Budget | AM2: Payment | AN2: Variance | AO2: Comments
A3: Occupational Medicine for Business & Industry | B3: =VLOOKUP(A3,'Final Data'!$A$2:$M$5,2,) -> 14636.695 | C3: =16099.35 -> 16099.35 | D3: =C3-B3 -> 1462.6547 | E3: LAT $1,405.81 not budgeted STX $56.85 budget vs actual | G3: =VLOOKUP(A3,'Final Data'!$A$2:$M$5,3,) -> 14636.695 | H3: 14058.13 | I3: =H3-G3 -> -578.56529 | J3: NNN ($578.57) Short Payment | L3: =VLOOKUP(A3,'Final Data'!$A$2:$M$5,4,) -> 14636.695 | M3: 14636.69 | N3: =M3-L3 -> -0.0052891294 | Q3: 15046.718 | R3: 14058.13 | S3: =R3-Q3 -> -988.58769 | T3: BAS ($398.08) & NNN ($590.51) Short Pmt | V3: =VLOOKUP(A3,'Final Data'!$A$1:$M$5,6,0) -> 15046.718 | W3: 14456.21 | X3: =W3-V3 -> -590.50769 | Y3: NNN ($590.51) Short Pmt | AA3: =VLOOKUP(A3,'Final Data'!$A$1:$G$5,7,0) -> 15046.718 | AB3: 0 | AC3: =AB3-AA3 -> -15046.718 | AD3: BAS ($13,667.36) & NNN ($1,379.36) No Pmt | AG3: =VLOOKUP(A3,'Final Data'!$A$1:$H$5,8,0) -> 15046.718 | AH3: 37147.74 | AI3: =AH3-AG3 -> 22101.022 | AJ3: BAS $14,065.44 04/26 & 06/26 past due paid NNN $7,977.15 02/26 to 06/26 past due paid SLS $58.44 Budget vs Pmt | AL3: =B3+G3+L3+Q3+V3+AA3+AG3 -> 104096.96 | AM3: =C3+H3+M3+R3+W3+AB3+AH3 -> 110456.25 | AN3: =AM3-AL3 -> 6359.2934 | AO3: LAT $1,405.81 not budgeted in Jan'26 STX $115.29 Budget vs Pmt in Jan'26 & July'26 NNN $4,838.20 Budget vs Pmt in June'26 & July'26
A4: Arizona Sports & Spine Physicians | B4: =VLOOKUP(A4,'Final Data'!$A$2:$M$5,2,) -> 4893.7841 | C4: 0 | D4: =C4-B4 -> -4893.7841 | E4: no payment in 01/26 | G4: =VLOOKUP(A4,'Final Data'!$A$2:$M$5,3,) -> 4893.7841 | H4: 5000 | I4: =H4-G4 -> 106.21589 | J4: BAS $4,374.81 & NNN $537.98 for Jan'26 CAM $87.21 Over Payment BAS ($4,374.81) & NNN ($518) for Feb'26 | L4: =VLOOKUP(A4,'Final Data'!$A$2:$M$5,4,) -> 4963.3882 | M4: 6000 | N4: =M4-L4 -> 1036.6118 | O4: BAS $4,374.81 & NNN $537.98 past due paid for Feb'26 BAS($3,816.38) &NNN($79) Short Pmt S.Tax $20.00 budget vs Pmt in Mar'26 | Q4: 5028.642 | R4: =6000 -> 6000 | S4: =R4-Q4 -> 971.35799 | T4: BAS $3,816.38 03/26 past due paid STX $79.07 received BAS ($2,943.63) Short Pmt S.Tax $20.00 budget vs Pmt in Apr'26 | V4: =VLOOKUP(A4,'Final Data'!$A$1:$M$5,6,0) -> 5028.642 | W4: 0 | X4: =W4-V4 -> -5028.642 | Y4: BAS ($4,505.74) & NNN ($522.90) No Pmt | AA4: =VLOOKUP(A4,'Final Data'!$A$1:$G$5,7,0) -> 5028.642 | AB4: 2000 | AC4: =AB4-AA4 -> -3028.642 | AD4: BAS $2,000.00 04/26 past due paid BAS ($4,505.74) & NNN ($522.90) No Pmt | AG4: =VLOOKUP(A4,'Final Data'!$A$1:$H$5,8,0) -> 5028.642 | AH4: 8000 | AI4: =AH4-AG4 -> 2971.358 | AJ4: BAS $2,846.80 & NNN $240.41 04/26 & 05/26 Past due paid CAM ($48.18) Short Pmt STX $19.53 Budget vs Pmt CAM (87.00) Budget vs Pmt | AL4: =B4+G4+L4+Q4+V4+AA4+AG4 -> 34865.524 | AM4: =C4+H4+M4+R4+W4+AB4+AH4 -> 27000 | AN4: =AM4-AL4 -> -7865.5244 | AO4: BAS ($7,108.31) Short Pmt in Apr'26 to July'26 STX $96.81 Budget vs Pmt from Jan'26 to July'26 NNN ($805.39) No Pmt in May'26 to July'26 CAM ($48.18) Short Pmt in July'26
A5: Arizona Trim Clinic | Q5: 0 | R5: 2223.52 | S5: =R5-Q5 -> 2223.52 | T5: BAS $2,223.52 Not budgeted (New TT) | V5: =IFERROR(VLOOKUP(A5,'Final Data'!$A$1:$M$5,6,0),0) -> 0 | W5: 0 | X5: =W5-V5 -> 0 | AA5: 0 | AB5: 0 | AC5: =AB5-AA5 -> 0 | AG5: 0 | AH5: 3043.08 | AI5: =AH5-AG5 -> 3043.08 | AJ5: BAS $629.64 & NNN $2,413.44 Not budgeted (NEW TT) | AL5: =B5+G5+L5+Q5+V5+AA5+AG5 -> 0 | AM5: =C5+H5+M5+R5+W5+AB5+AH5 -> 5266.6 | AN5: =AM5-AL5 -> 5266.6 | AO5: BAS $2,853.16 Not budgeted (New TT) in Apr'26 & July'26 NNN $2,413.44 Not budgeted (NEW TT) in July'26
A6: Vacant | B6: =VLOOKUP(A6,'Final Data'!$A$2:$M$5,2,) -> 0 | C6: 0 | D6: =C6-B6 -> 0 | G6: =VLOOKUP(A6,'Final Data'!$A$2:$M$5,3,) -> 0 | L6: =VLOOKUP(A6,'Final Data'!$A$2:$M$5,4,) -> 0 | V6: =VLOOKUP(A6,'Final Data'!$A$1:$M$5,6,0) -> 15426.241 | W6: 0 | X6: =W6-V6 -> -15426.241 | Y6: BAS ($9,550.56) & NNN ($5,875.68) No Pmt - Vacant | AA6: =VLOOKUP(A6,'Final Data'!$A$1:$G$5,7,0) -> 15426.241 | AB6: 0 | AC6: =AB6-AA6 -> -15426.241 | AD6: BAS ($9,550.56) & NNN ($5,875.68) No Pmt - Vacant | AG6: =VLOOKUP(A6,'Final Data'!$A$1:$H$5,8,0) -> 15426.241 | AH6: 0 | AI6: =AH6-AG6 -> -15426.241 | AJ6: BAS ($9,550.56) & NNN ($5,875.68) No Pmt - Vacant | AL6: =B6+G6+L6+Q6+V6+AA6+AG6 -> 46278.722 | AM6: =C6+H6+M6+R6+W6+AB6+AH6 -> 0 | AN6: =AM6-AL6 -> -46278.722 | AO6: BAS ($28,651.70) & NNN ($17,627.00) No Pmt - Vacant in May'26 to July'26
A7: Vacant | B7: =VLOOKUP(A7,'Final Data'!$A$2:$M$5,2,) -> 0 | C7: 0 | D7: =C7-B7 -> 0 | G7: =VLOOKUP(A7,'Final Data'!$A$2:$M$5,3,) -> 0 | AG7: =VLOOKUP(A7,'Final Data'!$A$1:$H$5,8,0) -> 15426.241 | AL7: =B7 -> 0 | AM7: =C7 -> 0 | AN7: =AM7-AL7 -> 0
B9: =SUM(B3:B7) -> 19530.479 | C9: =SUM(C3:C7) -> 16099.35 | D9: =SUM(D3:D7) -> -3431.1294 | G9: =SUM(G3:G7) -> 19530.479 | H9: =SUM(H3:H7) -> 19058.13 | I9: =SUM(I3:I7) -> -472.3494 | L9: =SUM(L3:L7) -> 19600.083 | M9: =SUM(M3:M7) -> 20636.69 | N9: =SUM(N3:N7) -> 1036.6065 | Q9: =SUM(Q3:Q7) -> 20075.36 | R9: =SUM(R3:R7) -> 22281.65 | S9: =SUM(S3:S7) -> 2206.2903 | V9: =SUM(V3:V7) -> 35501.6 | W9: =SUM(W3:W7) -> 14456.21 | X9: =SUM(X3:X7) -> -21045.39 | AA9: =SUM(AA3:AA7) -> 35501.6 | AB9: =SUM(AB3:AB7) -> 2000 | AC9: =SUM(AC3:AC7) -> -33501.6 | AG9: =SUM(AG3:AG6) -> 35501.6 | AH9: =SUM(AH3:AH6) -> 48190.82 | AI9: =SUM(AI3:AI6) -> 12689.22 | AL9: =SUM(AL3:AL7) -> 185241.2 | AM9: =SUM(AM3:AM7) -> 142722.85 | AN9: =SUM(AN3:AN7) -> -42518.353
G10: 19531 | H10: 19058.13 | I10: -472.87 | L10: 19601 | M10: 20636.68 | N10: 1035.69 | Q10: 20076 | R10: 22281.65 | S10: 2205.65 | V10: 35502 | W10: 14456.21 | X10: -21045.79 | AA10: 35502 | AB10: 2000 | AC10: 33502 | AG10: 35502 | AH10: 48190.82 | AI10: 12688.82 | AL10: 185245 | AM10: 142722.85 | AN10: -42522.15
G11: =G9-G10 -> -0.52060374 | H11: =H9-H10 -> 0 | I11: =I9-I10 -> 0.52060374 | L11: =L9-L10 -> -0.91652632 | M11: =M9-M10 -> 0.01 | N11: =N9-N10 -> 0.91652632 | Q11: =Q9-Q10 -> -0.64030374 | R11: =R9-R10 -> 0 | S11: =S9-S10 -> 0.64030374 | V11: =V9-V10 -> -0.39975271 | W11: =W9-W10 -> 0 | X11: =X9-X10 -> 0.39975271 | AA11: =AA9-AA10 -> -0.39975271 | AB11: =AB9-AB10 -> 0 | AC11: =AC9+AC10 -> 0.39975271 | AG11: =AG10-AG9 -> 0.39975271 | AH11: =AH10-AH9 -> 0 | AI11: =AI10-AI9 -> -0.39975271 | AL11: =AL9-AL10 -> -3.7972957 | AM11: =AM9-AM10 -> 0 | AN11: =AN9-AN10 -> 3.7972957

Sheet Final Data
A1: Row Labels | B1: Sum of Jan | C1: Sum of Feb | D1: Sum of Mar | E1: Sum of Apr | F1: Sum of May | G1: Sum of Jun | H1: Sum of Jul | I1: Sum of Aug | J1: Sum of Sept | K1: Sum of Oct | L1: Sum of Nov | M1: Sum of Dec
A2: Arizona Sports & Spine Physicians | B2: 4893.7841 | C2: 4893.7841 | D2: 4963.3882 | E2: 5028.642 | F2: 5028.642 | G2: 5028.642 | H2: 5028.642 | I2: 5028.642 | J2: 5028.642 | K2: 5028.642 | L2: 5028.642 | M2: 5028.642
A3: Occupational Medicine for Business & Industry | B3: 14636.695 | C3: 14636.695 | D3: 14636.695 | E3: 15046.718 | F3: 15046.718 | G3: 15046.718 | H3: 15046.718 | I3: 15046.718 | J3: 15046.718 | K3: 15046.718 | L3: 15046.718 | M3: 15046.718
A4: Vacant | B4: 0 | C4: 0 | D4: 0 | E4: 0 | F4: 15426.241 | G4: 15426.241 | H4: 15426.241 | I4: 15426.241 | J4: 15426.241 | K4: 15426.241 | L4: 15426.241 | M4: 15426.241
A5: Grand Total | B5: 19530.479 | C5: 19530.479 | D5: 19600.083 | E5: 20075.36 | F5: 35501.6 | G5: 35501.6 | H5: 35501.6 | I5: 35501.6 | J5: 35501.6 | K5: 35501.6 | L5: 35501.6 | M5: 35501.6

Sheet Detail1
A1: Details for Sum of Feb - Tenant: Arizona Sports & Spine Physicians
A3: Tenant | B3: Charge | C3: Jan | D3: Feb | E3: Mar | F3: Apr | G3: May | H3: Jun | I3: Jul | J3: Aug | K3: Sept | L3: Oct | M3: Nov | N3: Dec
A4: Arizona Sports & Spine Physicians | B4: SGN | C4: 119.82 | D4: 119.82 | E4: 119.82 | F4: 119.82 | G4: 119.82 | H4: 119.82 | I4: 119.82 | J4: 119.82 | K4: 119.82 | L4: 119.82 | M4: 119.82 | N4: 119.82
A5: Arizona Sports & Spine Physicians | B5: BAS | C5: 4374.81 | D5: 4374.81 | E5: 4442.3868 | F5: 4505.74 | G5: 4505.74 | H5: 4505.74 | I5: 4505.74 | J5: 4505.74 | K5: 4505.74 | L5: 4505.74 | M5: 4505.74 | N5: 4505.74
A6: Arizona Sports & Spine Physicians | B6: INS | C6: 0 | D6: 0 | E6: 0 | F6: 0 | G6: 0 | H6: 0 | I6: 0 | J6: 0 | K6: 0 | L6: 0 | M6: 0 | N6: 0
A7: Arizona Sports & Spine Physicians | B7: RET | C7: 0 | D7: 0 | E7: 0 | F7: 0 | G7: 0 | H7: 0 | I7: 0 | J7: 0 | K7: 0 | L7: 0 | M7: 0 | N7: 0
A8: Arizona Sports & Spine Physicians | B8: ADM | C8: 0 | D8: 0 | E8: 0 | F8: 0 | G8: 0 | H8: 0 | I8: 0 | J8: 0 | K8: 0 | L8: 0 | M8: 0 | N8: 0
A9: Arizona Sports & Spine Physicians | B9: CAM | C9: 256.61671 | D9: 256.61671 | E9: 256.61671 | F9: 256.61671 | G9: 256.61671 | H9: 256.61671 | I9: 256.61671 | J9: 256.61671 | K9: 256.61671 | L9: 256.61671 | M9: 256.61671 | N9: 256.61671
A10: Arizona Sports & Spine Physicians | B10: NCA | C10: 0 | D10: 0 | E10: 0 | F10: 0 | G10: 0 | H10: 0 | I10: 0 | J10: 0 | K10: 0 | L10: 0 | M10: 0 | N10: 0
A11: Arizona Sports & Spine Physicians | B11: SLS | C11: 142.5374 | D11: 142.5374 | E11: 144.5647 | F11: 146.4653 | G11: 146.4653 | H11: 146.4653 | I11: 146.4653 | J11: 146.4653 | K11: 146.4653 | L11: 146.4653 | M11: 146.4653 | N11: 146.4653
B18: SGN | C18: 119.82 | D18: 119.82 | E18: =D18-C18 -> 0
B19: BAS | C19: 4374.81 | D19: 4374.81 | E19: =D19-C19 -> 0
B20: INS | C20: 0 | E20: =D20-C20 -> 0
B21: RET | C21: 0 | E21: =D21-C21 -> 0
B22: ADM | C22: 0 | E22: =D22-C22 -> 0
B23: CAM | C23: 256.61671 | D23: 343.83 | E23: =D23-C23 -> 87.213294
B24: NCA | C24: 0 | E24: =D24-C24 -> 0
B25: SLS | C25: 142.5374 | D25: 161.54 | E25: =D25-C25 -> 19.002599
C26: 148.74

Sheet Pivot
A3: Row Labels | B3: Sum of Jan | C3: Sum of Feb | D3: Sum of Mar | E3: Sum of Apr | F3: Sum of May | G3: Sum of Jun | H3: Sum of Jul | I3: Sum of Aug | J3: Sum of Sept | K3: Sum of Oct | L3: Sum of Nov | M3: Sum of Dec
A4: Arizona Sports & Spine Physicians | B4: 4893.7841 | C4: 4893.7841 | D4: 4963.3882 | E4: 5028.642 | F4: 5028.642 | G4: 5028.642 | H4: 5028.642 | I4: 5028.642 | J4: 5028.642 | K4: 5028.642 | L4: 5028.642 | M4: 5028.642
A5: Occupational Medicine for Business & Industry | B5: 14636.695 | C5: 14636.695 | D5: 14636.695 | E5: 15046.718 | F5: 15046.718 | G5: 15046.718 | H5: 15046.718 | I5: 15046.718 | J5: 15046.718 | K5: 15046.718 | L5: 15046.718 | M5: 15046.718
A6: Vacant | B6: 0 | C6: 0 | D6: 0 | E6: 0 | F6: 15426.241 | G6: 15426.241 | H6: 15426.241 | I6: 15426.241 | J6: 15426.241 | K6: 15426.241 | L6: 15426.241 | M6: 15426.241
A7: Grand Total | B7: 19530.479 | C7: 19530.479 | D7: 19600.083 | E7: 20075.36 | F7: 35501.6 | G7: 35501.6 | H7: 35501.6 | I7: 35501.6 | J7: 35501.6 | K7: 35501.6 | L7: 35501.6 | M7: 35501.6

Sheet DATA
A1: Tenant | B1: Charge | C1: Jan | D1: Feb | E1: Mar | F1: Apr | G1: May | H1: Jun | I1: Jul | J1: Aug | K1: Sept | L1: Oct | M1: Nov | N1: Dec
A2: Occupational Medicine for Business & Industry | B2: BAS | C2: 13269.28 | D2: 13269.28 | E2: 13269.28 | F2: 13667.36 | G2: 13667.36 | H2: 13667.36 | I2: 13667.36 | J2: 13667.36 | K2: 13667.36 | L2: 13667.36 | M2: 13667.36 | N2: 13667.36
A3: Arizona Sports & Spine Physicians | B3: BAS | C3: 4374.81 | D3: 4374.81 | E3: 4442.3868 | F3: 4505.74 | G3: 4505.74 | H3: 4505.74 | I3: 4505.74 | J3: 4505.74 | K3: 4505.74 | L3: 4505.74 | M3: 4505.74 | N3: 4505.74
A4: Vacant | B4: BAS | C4: 0 | D4: 0 | E4: 0 | F4: 0 | G4: 1217.46 | H4: 1217.46 | I4: 1217.46 | J4: 1217.46 | K4: 1217.46 | L4: 1217.46 | M4: 1217.46 | N4: 1217.46
A5: Vacant | B5: BAS | C5: 0 | D5: 0 | E5: 0 | F5: 0 | G5: 8333.1 | H5: 8333.1 | I5: 8333.1 | J5: 8333.1 | K5: 8333.1 | L5: 8333.1 | M5: 8333.1 | N5: 8333.1
A6: Occupational Medicine for Business & Industry | B6: CAM | C6: 611.19378 | D6: 611.19378 | E6: 611.19378 | F6: 611.19378 | G6: 611.19378 | H6: 611.19378 | I6: 611.19378 | J6: 611.19378 | K6: 611.19378 | L6: 611.19378 | M6: 611.19378 | N6: 611.19378
A7: Arizona Sports & Spine Physicians | B7: CAM | C7: 256.61671 | D7: 256.61671 | E7: 256.61671 | F7: 256.61671 | G7: 256.61671 | H7: 256.61671 | I7: 256.61671 | J7: 256.61671 | K7: 256.61671 | L7: 256.61671 | M7: 256.61671 | N7: 256.61671
A8: Vacant | B8: CAM | C8: 0 | D8: 0 | E8: 0 | F8: 0 | G8: 269.86053 | H8: 269.86053 | I8: 269.86053 | J8: 269.86053 | K8: 269.86053 | L8: 269.86053 | M8: 269.86053 | N8: 269.86053
A9: Vacant | B9: CAM | C9: 0 | D9: 0 | E9: 0 | F9: 0 | G9: 1847.1036 | H9: 1847.1036 | I9: 1847.1036 | J9: 1847.1036 | K9: 1847.1036 | L9: 1847.1036 | M9: 1847.1036 | N9: 1847.1036
A10: Occupational Medicine for Business & Industry | B10: SLS | C10: 426.31151 | D10: 426.31151 | E10: 426.31151 | F10: 438.25391 | G10: 438.25391 | H10: 438.25391 | I10: 438.25391 | J10: 438.25391 | K10: 438.25391 | L10: 438.25391 | M10: 438.25391 | N10: 438.25391
A11: Arizona Sports & Spine Physicians | B11: SLS | C11: 142.5374 | D11: 142.5374 | E11: 144.5647 | F11: 146.4653 | G11: 146.4653 | H11: 146.4653 | I11: 146.4653 | J11: 146.4653 | K11: 146.4653 | L11: 146.4653 | M11: 146.4653 | N11: 146.4653
A12: Vacant | B12: SLS | G12: 57.275646 | H12: 57.275646 | I12: 57.275646 | J12: 57.275646 | K12: 57.275646 | L12: 57.275646 | M12: 57.275646 | N12: 57.275646
A13: Vacant | B13: SLS | G13: 392.03233 | H13: 392.03233 | I13: 392.03233 | J13: 392.03233 | K13: 392.03233 | L13: 392.03233 | M13: 392.03233 | N13: 392.03233
A14: Occupational Medicine for Business & Industry | B14: NCA | C14: 0 | D14: 0 | E14: 0 | F14: 0 | G14: 0 | H14: 0 | I14: 0 | J14: 0 | K14: 0 | L14: 0 | M14: 0 | N14: 0
A15: Arizona Sports & Spine Physicians | B15: NCA | C15: 0 | D15: 0 | E15: 0 | F15: 0 | G15: 0 | H15: 0 | I15: 0 | J15: 0 | K15: 0 | L15: 0 | M15: 0 | N15: 0
A16: Vacant | B16: NCA | C16: 0 | D16: 0 | E16: 0 | F16: 0 | G16: 254.46363 | H16: 254.46363 | I16: 254.46363 | J16: 254.46363 | K16: 254.46363 | L16: 254.46363 | M16: 254.46363 | N16: 254.46363
A17: Vacant | B17: NCA | C17: 0 | D17: 0 | E17: 0 | F17: 0 | G17: 1741.7171 | H17: 1741.7171 | I17: 1741.7171 | J17: 1741.7171 | K17: 1741.7171 | L17: 1741.7171 | M17: 1741.7171 | N17: 1741.7171
A18: Occupational Medicine for Business & Industry | B18: ADM | C18: 0 | D18: 0 | E18: 0 | F18: 0 | G18: 0 | H18: 0 | I18: 0 | J18: 0 | K18: 0 | L18: 0 | M18: 0 | N18: 0
A19: Arizona Sports & Spine Physicians | B19: ADM | C19: 0 | D19: 0 | E19: 0 | F19: 0 | G19: 0 | H19: 0 | I19: 0 | J19: 0 | K19: 0 | L19: 0 | M19: 0 | N19: 0
A20: Vacant | B20: ADM | C20: 0 | D20: 0 | E20: 0 | F20: 0 | G20: 0 | H20: 0 | I20: 0 | J20: 0 | K20: 0 | L20: 0 | M20: 0 | N20: 0
A21: Vacant | B21: ADM | C21: 0 | D21: 0 | E21: 0 | F21: 0 | G21: 0 | H21: 0 | I21: 0 | J21: 0 | K21: 0 | L21: 0 | M21: 0 | N21: 0
A22: Occupational Medicine for Business & Industry | B22: RET | C22: 0 | D22: 0 | E22: 0 | F22: 0 | G22: 0 | H22: 0 | I22: 0 | J22: 0 | K22: 0 | L22: 0 | M22: 0 | N22: 0
A23: Arizona Sports & Spine Physicians | B23: RET | C23: 0 | D23: 0 | E23: 0 | F23: 0 | G23: 0 | H23: 0 | I23: 0 | J23: 0 | K23: 0 | L23: 0 | M23: 0 | N23: 0
A24: Vacant | B24: RET | C24: 0 | D24: 0 | E24: 0 | F24: 0 | G24: 144.20178 | H24: 144.20178 | I24: 144.20178 | J24: 144.20178 | K24: 144.20178 | L24: 144.20178 | M24: 144.20178 | N24: 144.20178
A25: Vacant | B25: RET | C25: 0 | D25: 0 | E25: 0 | F25: 0 | G25: 987.01215 | H25: 987.01215 | I25: 987.01215 | J25: 987.01215 | K25: 987.01215 | L25: 987.01215 | M25: 987.01215 | N25: 987.01215
... A33: Vacant | B33: SGN | C33: 0 | D33: 0 | E33: 0 | F33: 0 | G33: 0 | H33: 0 | I33: 0 | J33: 0 | K33: 0 | L33: 0 | M33: 0 | N33: 0
C36: 161.54 | E36: 4963.39 | F36: 245.07 | I36: 166
I37: =I36-I11 -> 19.534699
C39: =C36-C11 -> 19.002599 | F39: =F11-F36 -> -98.604699
C42: 4505.74
C43: 5378.49
C44: =C43-C42 -> 872.75

Sheet Summary
A2: ATHENA PROPERTY MANAGEMENT
A3: BELL MEDICAL
A4: PROJECT NO. 802 | T4: Date Revised: | U4: =TODAY() -> 46235
A5: 01/01/26-12/31/26
A6: 2026 OPERATING BUDGET
A8: GENERAL | O8: 2026 | P8: 2025 FORECAST TOTALS | Q8: 2025 BUDGET TOTALS | R8: VARIANCE | T8: DENOM. | U8: COST
A9: LEDGER | B9: DESCRIPTION | C9: JAN | D9: FEB | E9: MARCH | F9: APRIL | G9: MAY | H9: JUNE | I9: JULY | J9: AUGUST | K9: SEPT | L9: OCT | M9: NOV | N9: DEC | O9: BUDGET | R9: 2026 BUDGET vs. | S9: % CHANGE | T9: SQUARE | U9: PER
A10: CODE | O10: TOTALS | R10: 2025 FORECAST | T10: FOOTG. | U10: SQ. FT. | AE10: As of 9/13
B12: INCOME
A13: 40100 | B13: Rental Income | C13: =Rent!E23 -> 17644.09 | D13: =Rent!F23 -> 17644.09 | E13: =Rent!G23 -> 17711.667 | F13: =Rent!H23 -> 18173.1 | G13: =Rent!I23 -> 27723.66 | H13: =Rent!J23 -> 27723.66 | I13: =Rent!K23 -> 27723.66 | J13: =Rent!L23 -> 27723.66 | ... N13: =Rent!P23 -> 27723.66 | O13: =SUM(C13:N13) -> 292962.23 | P13: 197127 | Q13: 208938 | R13: =O13-P13 -> 95835.227 | T13: =Rent!$C$23 -> 12474 | U13: =O13/T13 -> 23.485829
A14: 40140 | B14: Common Area | C14: =CAM!E25 -> 867.81048 | D14: =CAM!F25 -> 867.81048 | E14: =CAM!G25 -> 867.81048 | F14: =CAM!H25 -> 867.81048 | G14: =CAM!I25 -> 2984.7746 | H14: =CAM!J25 -> 2984.7746 | I14: =CAM!K25 -> 2984.7746 | J14: =CAM!L25 -> 2984.7746 | ... N14: =CAM!P25 -> 2984.7746 | O14: =SUM(C14:N14) -> 27349.439 | P14: 3781 | Q14: 4044 | R14: =O14-P14 -> 23568.439 | T14: =Rent!$C$23 -> 12474 | U14: =O14/T14 -> 2.1925156
A15: 41300 | B15: State and County Rental Tax 3% | C15: ='Sales Tax'!E35 -> 568.84891 | D15: ='Sales Tax'!F35 -> 568.84891 | E15: ='Sales Tax'!G35 -> 570.87622 | F15: ='Sales Tax'!H35 -> 584.71921 | G15: ='Sales Tax'!I35 -> 1034.0272 | H15: ='Sales Tax'!J35 -> 1034.0272 | I15: ='Sales Tax'!K35 -> 1034.0272 | J15: ='Sales Tax'!L35 -> 1034.0272 | ... N15: ='Sales Tax'!P35 -> 1034.0272 | O15: =SUM(C15:N15) -> 10565.511 | P15: 5959 | Q15: 6386 | R15: =O15-P15 -> 4606.5108 | T15: =Rent!$C$23 -> 12474
A16: 40150 | B16: Prior Year CAM | C16: 0 | D16: 0 | E16: 0 | F16: 0 | G16: 0 | H16: 0 | I16: 0 | J16: 0 | K16: 0 | L16: 0 | M16: 0 | N16: 0 | O16: =SUM(C16:N16) -> 0 | P16: -831 | Q16: 0 | R16: =O16-P16 -> 831 | U16: 0
A17: 40170 | B17: Building CAM | C17: ='Building Expenses'!E26 -> 0 | D17: ='Building Expenses'!F26 -> 0 | E17: ='Building Expenses'!G26 -> 0 | F17: ='Building Expenses'!H26 -> 0 | G17: ='Building Expenses'!I26 -> 1996.1807 | H17: ='Building Expenses'!J26 -> 1996.1807 | I17: ='Building Expenses'!K26 -> 1996.1807 | J17: ='Building Expenses'!L26 -> 1996.1807 | ... N17: ='Building Expenses'!P26 -> 1996.1807 | O17: =SUM(C17:N17) -> 15969.446 | P17: 0 | Q17: 0 | R17: =O17-P17 -> 15969.446 | T17: =Rent!$C$23 -> 12474 | U17: =O17/T17 -> 1.2802185
A18: 40230 | B18: Insurance Income | C18: =Ins.!E25 -> 0 | D18: =Ins.!F25 -> 0 | E18: =Ins.!G25 -> 0 | F18: =Ins.!H25 -> 0 | G18: =Ins.!I25 -> 182.01376 | H18: =Ins.!J25 -> 182.01376 | I18: =Ins.!K25 -> 182.01376 | J18: =Ins.!L25 -> 182.01376 | ... N18: =Ins.!P25 -> 182.01376 | O18: =SUM(C18:N18) -> 1456.1101 | P18: 0 | Q18: 0 | R18: =O18-P18 -> 1456.1101 | T18: =Rent!$C$23 -> 12474 | U18: =O18/T18 -> 0.11673161
A19: 40240 | B19: Property Tax Income | C19: ='RE Tax'!E24 -> 0 | D19: ='RE Tax'!F24 -> 0 | E19: ='RE Tax'!G24 -> 0 | F19: ='RE Tax'!H24 -> 0 | G19: ='RE Tax'!I24 -> 1131.2139 | H19: ='RE Tax'!J24 -> 1131.2139 | I19: ='RE Tax'!K24 -> 1131.2139 | J19: ='RE Tax'!L24 -> 1131.2139 | ... N19: ='RE Tax'!P24 -> 1131.2139 | O19: =SUM(C19:N19) -> 9049.7114 | P19: 0 | Q19: 0 | R19: =O19-P19 -> 9049.7114 | T19: =Rent!$C$23 -> 12474 | U19: =O19/T19 -> 0.72548592
A20: 40390 | B20: Administrative Fee Income | C20: ='Admin Fee'!E26 -> 0 | D20: ='Admin Fee'!F26 -> 0 | E20: ='Admin Fee'!G26 -> 0 | F20: ='Admin Fee'!H26 -> 0 | G20: ='Admin Fee'!I26 -> 0 | H20: ='Admin Fee'!J26 -> 0 | I20: ='Admin Fee'!K26 -> 0 | J20: ='Admin Fee'!L26 -> 0 | ... N20: ='Admin Fee'!P26 -> 0 | O20: =SUM(C20:N20) -> 0 | P20: 0 | Q20: 0 | R20: =O20-P20 -> 0 | T20: =Rent!$C$23 -> 12474 | U20: =O20/T20 -> 0
A21: 40500 | B21: Sign Income | C21: =Signage!E21 -> 449.73 | D21: =Signage!F21 -> 449.73 | E21: =Signage!G21 -> 449.73 | F21: =Signage!H21 -> 449.73 | G21: =Signage!I21 -> 449.73 | H21: =Signage!J21 -> 449.73 | I21: =Signage!K21 -> 449.73 | J21: =Signage!L21 -> 449.73 | ... N21: =Signage!P21 -> 449.73 | O21: =SUM(C21:N21) -> 5396.76 | P21: 0 | Q21: 0 | R21: =O21-P21 -> 5396.76 | T21: =Rent!$C$23 -> 12474 | U21: =O21/T21 -> 0.43264069
A22: 40143 | B22: Deferred CAM Recovery | C22: ='Rent Deferral Recovery'!D30 -> 0 | D22: ='Rent Deferral Recovery'!E30 -> 0 | E22: ='Rent Deferral Recovery'!F30 -> 0 | F22: ='Rent Deferral Recovery'!G30 -> 0 | G22: ='Rent Deferral Recovery'!H30 -> 0 | H22: ='Rent Deferral Recovery'!I30 -> 0 | I22: ='Rent Deferral Recovery'!J30 -> 0 | J22: ='Rent Deferral Recovery'!K30 -> 0 | ... N22: ='Rent Deferral Recovery'!O30 -> 0 | O22: =SUM(C22:N22) -> 0 | P22: 0 | Q22: 0 | R22: =O22-P22 -> 0 | T22: =Rent!$C$23 -> 12474 | U22: =O22/T22 -> 0
A23: 40600 | B23: Late Charge Income | C23: 0 | D23: 0 | E23: 0 | F23: 0 | G23: 0 | H23: 0 | I23: 0 | J23: 0 | K23: 0 | L23: 0 | M23: 0 | N23: 0 | O23: =SUM(C23:N23) -> 0 | P23: 0 | Q23: 0 | R23: =O23-P23 -> 0 | T23: =Rent!$C$23 -> 12474 | U23: =O23/T23 -> 0
A24: 40220 | B24: Rent Abatement | O24: =SUM(C24:N24) -> 0 | P24: 0 | Q24: 0 | R24: =O24-P24 -> 0
A25: 40250 | B25: Miscellaneous Income | O25: =SUM(C25:N25) -> 0 | P25: 2857 | Q25: 0 | R25: =O25-P25 -> -2857
B27: TOTAL INCOME | C27: =SUM(C13:C25) -> 19530.479 | D27: =SUM(D13:D25) -> 19530.479 | E27: =SUM(E13:E25) -> 19600.083 | F27: =SUM(F13:F25) -> 20075.36 | G27: =SUM(G13:G25) -> 35501.6 | H27: =SUM(H13:H25) -> 35501.6 | I27: =SUM(I13:I25) -> 35501.6 | J27: =SUM(J13:J25) -> 35501.6 | ... R27: =SUM(R13:R25) -> 153856.2 | S27: =R27/O27 -> 0.42413933 | U27: =SUM(U13:U25) -> 28.233421
B29: COMMON AREA EXPENSES
A31: 50150 | B31: Landscape- Tree Trimming | C31: 0 | D31: 0 | E31: 0 | F31: 0 | G31: 0 | H31: 0 | J31: 4000 | K31: 0 | M31: 0 | N31: 0 | O31: =SUM(C31:N31) -> 4000 | P31: 3745 | Q31: 2400 | R31: =O31-P31 -> 255 | T31: =CAM!C$25 -> 12474 | U31: =O31/T31 -> 0.32066699
A32: 50160 | B32: Landscape - Consumables | C32: 125 | D32: =C32 -> 125 | E32: =D32 -> 125 | F32: =E32 -> 125 | G32: =F32 -> 125 | H32: =G32 -> 125 | I32: =H32 -> 125 | J32: =I32 -> 125 | K32: =J32 -> 125 | ... N32: =M32 -> 125 | O32: =SUM(C32:N32) -> 1500 | P32: 586 | Q32: 0 | R32: =O32-P32 -> 914
A33: 50190 | B33: Sprinkler Repairs | E33: 50 | H33: 50 | L33: 50 | O33: =SUM(C33:N33) -> 150 | P33: 36 | Q33: 150 | R33: =O33-P33 -> 114 | T33: =CAM!C$25 -> 12474 | U33: 0
A34: 50170 | B34: Landscape Maintenance | C34: 676 | D34: =C34 -> 676 | E34: =D34 -> 676 | F34: =E34 -> 676 | G34: =F34 -> 676 | H34: =G34 -> 676 | I34: =H34 -> 676 | J34: =I34 -> 676 | K34: =J34 -> 676 | ... N34: =M34 -> 676 | O34: =SUM(C34:N34) -> 8112 | P34: 7980 | Q34: 7980 | R34: =O34-P34 -> 132 | T34: =CAM!C$25 -> 12474 | U34: =O34/T34 -> 0.65031265
A35: 50510 | B35: Parking Lot Light Maintenance | C35: 0 | F35: =C35 -> 0 | I35: =F35 -> 0 | L35: 75 | O35: =SUM(C35:N35) -> 75 | P35: 700 | Q35: 0 | R35: =O35-P35 -> -625 | T35: =CAM!C$25 -> 12474 | U35: =O35/T35 -> 0.006012506
A36: 50540 | B36: Parking Lot Repairs | C36: 0 | D36: 0 | E36: 0 | F36: 0 | G36: 0 | H36: 0 | I36: 0 | J36: 0 | K36: 0 | L36: 0 | M36: 0 | N36: 0 | O36: =SUM(C36:N36) -> 0 | P36: 245 | Q36: 0 | R36: =O36-P36 -> -245 | T36: =CAM!C$25 -> 12474 | U36: =O36/T36 -> 0
A37: 50512 | B37: Building - Lighting Maint & Repairs | C37: 50 | F37: =C37 -> 50 | I37: =F37 -> 50 | L37: =I37 -> 50 | O37: =SUM(C37:N37) -> 200 | P37: 180 | Q37: 300 | R37: =O37-P37 -> 20
A38: 50530 | B38: Parking Lot Light Repairs | C38: 225 | E38: =D38 -> 0 | F38: =C38 -> 225 | I38: =F38 -> 225 | J38: 0 | K38: =J38 -> 0 | L38: =I38 -> 225 | M38: 0 | N38: =M38 -> 0 | O38: =SUM(C38:N38) -> 900 | P38: 924 | Q38: 900 | R38: =O38-P38 -> -24 | T38: =CAM!C$25 -> 12474 | U38: =O38/T38 -> 0.072150072
A39: 51030 | B39: Misc Maint & Repairs | O39: =SUM(C39:N39) -> 0 | P39: 210 | Q39: 0 | R39: =O39-P39 -> -210
A40: 51020 | B40: General Maintenance | E40: 275 | H40: =E40 -> 275 | K40: =H40 -> 275 | N40: =K40 -> 275 | O40: =SUM(C40:N40) -> 1100 | P40: 1407 | Q40: 600 | R40: =O40-P40 -> -307 | T40: =CAM!C$25 -> 12474 | U40: =O40/T40 -> 0.088183422
A41: 51040 | B41: Janitorial | C41: 650 | D41: =C41 -> 650 | E41: =D41 -> 650 | F41: =E41 -> 650 | G41: =F41 -> 650 | H41: =G41 -> 650 | I41: =H41 -> 650 | J41: =I41 -> 650 | K41: =J41 -> 650 | ... N41: =M41 -> 650 | O41: =SUM(C41:N41) -> 7800 | P41: 7800 | Q41: 7800 | R41: =O41-P41 -> 0 | T41: =CAM!C$25 -> 12474 | U41: =O41/T41 -> 0.62530063 | V41: no increase for 2026
A42: 52010 | B42: Janitorial Supplies | C42: 75 | F42: 75 | I42: 75 | L42: 75 | O42: =SUM(C42:N42) -> 300 | P42: 185 | Q42: 300 | R42: =O42-P42 -> 115 | T42: =CAM!C$25 -> 12474 | U42: =O42/T42 -> 0.024050024
A43: 51050 | B43: Pest Control | C43: 184 | D43: 85 | E43: 85 | F43: 184 | G43: 85 | H43: 85 | I43: 184 | J43: 85 | K43: 85 | L43: 184 | M43: 85 | N43: 85 | O43: =SUM(C43:N43) -> 1416 | P43: 1416 | Q43: 1416 | R43: =O43-P43 -> 0 | T43: =CAM!C$25 -> 12474 | U43: =O43/T43 -> 0.11351611 | V43: monthly pest/quarterly rodent
A44: 51160 | B44: Security | C44: =650+115 -> 765 | D44: =C44 -> 765 | E44: =D44 -> 765 | F44: =E44 -> 765 | G44: =F44 -> 765 | H44: =G44 -> 765 | I44: =H44 -> 765 | J44: =I44 -> 765 | K44: =J44 -> 765 | ... N44: =M44 -> 765 | O44: =SUM(C44:N44) -> 9180 | P44: =7888+645 -> 8533 | Q44: 7284 | R44: =O44-P44 -> 647 | T44: =CAM!C$25 -> 12474 | U44: =O44/T44 -> 0.73593074 | V44: $621 Security; $115 Internet
A45: 51080 | B45: Management Fee | C45: 1500 | D45: =C45 -> 1500 | E45: =D45 -> 1500 | F45: =E45 -> 1500 | G45: =F45 -> 1500 | H45: =G45 -> 1500 | I45: 1500 | J45: =I45 -> 1500 | K45: =J45 -> 1500 | L45: =K45 -> 1500 | M45: =L45 -> 1500 | N45: =M45 -> 1500 | O45: =SUM(C45:N45) -> 18000 | P45: 14914 | Q45: 13776 | R45: =O45-P45 -> 3086 | T45: =CAM!C$25 -> 12474 | U45: =O45/T45 -> 1.4430014 | V45: $1,500 flat fee
A46: 51100 | B46: Sidewalk Maintenance | C46: 0 | D46: 0 | E46: 875 | F46: 0 | G46: 0 | H46: =E46 -> 875 | I46: 0 | J46: 0 | K46: =H46 -> 875 | L46: 0 | M46: 0 | N46: =K46 -> 875 | O46: =SUM(C46:N46) -> 3500 | P46: 0 | Q46: 0 | R46: =O46-P46 -> 3500 | T46: =CAM!C$25 -> 12474 | U46: =O46/T46 -> 0.28058361
A47: 50550 | B47: Sign Maintenance | C47: 0 | D47: 250 | E47: 0 | F47: =E47 -> 0 | G47: =F47 -> 0 | H47: =G47 -> 0 | I47: =H47 -> 0 | J47: =I47 -> 0 | K47: =J47 -> 0 | L47: =K47 -> 0 | M47: =L47 -> 0 | N47: =M47 -> 0 | O47: =SUM(C47:N47) -> 250 | P47: 0 | Q47: 250 | R47: =O47-P47 -> 250 | T47: =CAM!C$25 -> 12474 | U47: =O47/T47 -> 0.020041687
A48: 51150 | B48: Sweeping | C48: 125 | D48: =C48 -> 125 | E48: =D48 -> 125 | F48: =E48 -> 125 | G48: =F48 -> 125 | H48: =G48 -> 125 | I48: =H48 -> 125 | J48: =I48 -> 125 | K48: =J48 -> 125 | ... N48: =M48 -> 125 | O48: =SUM(C48:N48) -> 1500 | P48: =125*6 -> 750 | Q48: 320 | R48: =O48-P48 -> 750 | T48: =CAM!C$25 -> 12474 | U48: =O48/T48 -> 0.12025012 | V48: new contract - June 2025
A49: 51200 | B49: Electrical Repairs/CAM | C49: 0 | D49: 0 | E49: 0 | F49: 0 | G49: 0 | H49: 0 | I49: 0 | J49: 0 | K49: 0 | L49: 0 | M49: 0 | N49: 0 | O49: =SUM(C49:N49) -> 0 | P49: 0 | Q49: 0 | R49: =O49-P49 -> 0 | T49: =CAM!C$25 -> 12474 | U49: =O49/T49 -> 0
A50: 51210 | B50: Plumbing Repairs | C50: 0 | D50: 150 | E50: 0 | F50: 0 | G50: 0 | H50: 0 | I50: 150 | J50: 0 | K50: 0 | L50: 0 | M50: 0 | N50: 150 | O50: =SUM(C50:N50) -> 450 | P50: 225 | Q50: 450 | R50: =O50-P50 -> 225 | T50: =CAM!C$25 -> 12474 | U50: =O50/T50 -> 0.036075036
A51: 51043 | B51: Building Maint & Repairs (window washing) | C51: 140 | D51: 0 | E51: 0 | F51: 0 | G51: 140 | H51: 0 | I51: 0 | J51: 140 | K51: 0 | L51: 0 | M51: 0 | N51: 140 | O51: =SUM(C51:N51) -> 560 | P51: 450 | Q51: 0 | R51: =O51-P51 -> 110 | T51: =CAM!C$25 -> 12474 | U51: =O51/T51 -> 0.044893378
A52: 55120 | B52: Trash Removal | C52: 350 | D52: =C52 -> 350 | E52: =D52 -> 350 | F52: =E52 -> 350 | G52: =F52 -> 350 | H52: =G52 -> 350 | I52: =H52 -> 350 | J52: =I52 -> 350 | K52: =J52 -> 350 | ... N52: =M52 -> 350 | O52: =SUM(C52:N52) -> 4200 | P52: 3933 | Q52: 3924 | R52: =O52-P52 -> 267 | T52: =CAM!C$25 -> 12474 | U52: =O52/T52 -> 0.33670034
A53: 51130 | B53: HVAC Maintenance | C53: 0 | D53: 335 | E53: 0 | F53: 0 | G53: 335 | H53: 0 | I53: 0 | J53: 335 | K53: 0 | L53: 0 | M53: 335 | N53: 0 | O53: =SUM(C53:N53) -> 1340 | P53: 1340 | Q53: 1340 | R53: =O53-P53 -> 0 | T53: =CAM!C$25 -> 12474 | U53: =O53/T53 -> 0.10742344
A54: 51140 | B54: HVAC Repairs | C54: 0 | D54: 0 | E54: 0 | F54: 0 | G54: 0 | H54: 0 | I54: 0 | J54: 0 | K54: 0 | L54: 0 | M54: 0 | N54: 0 | O54: =SUM(C54:N54) -> 0 | P54: 0 | Q54: 0 | R54: =O54-P54 -> 0 | T54: =CAM!C$25 -> 12474 | U54: =O54/T54 -> 0
A55: 55140 | B55: Water/Common Area | C55: 0 | D55: =C55 -> 0 | E55: =D55 -> 0 | F55: =E55 -> 0 | G55: =F55 -> 0 | H55: =G55 -> 0 | I55: =H55 -> 0 | J55: =I55 -> 0 | K55: =J55 -> 0 | ... N55: =M55 -> 0 | O55: =SUM(C55:N55) -> 0 | P55: 0 | Q55: 0 | R55: =O55-P55 -> 0 | T55: =CAM!C$25 -> 12474 | U55: =O55/T55 -> 0
A56: 51400 | B56: Restroom Remodel-AMORTIZATION | N56: 0 | O56: =SUM(C56:N56) -> 0 | P56: 280 | Q56: 560 | R56: =O56-P56 -> -280 | T56: =CAM!C$25 -> 12474 | U56: =O56/T56 -> 0
A57: 51220 | B57: Painting-AMORTIZATION | N57: ='Cap-EX'!F7 -> 2509 | O57: =SUM(C57:N57) -> 2509 | P57: 0 | Q57: 0 | R57: =O57-P57 -> 2509 | T57: =CAM!C$25 -> 12474 | U57: =O57/T57 -> 0.20113837
B59: SUBTOTAL COMMON AREA | C59: =SUM(C31:C58) -> 4865 | D59: =SUM(D31:D58) -> 5011 | E59: =SUM(E31:E58) -> 5476 | F59: =SUM(F31:F58) -> 4725 | G59: =SUM(G31:G58) -> 4751 | H59: =SUM(H31:H58) -> 5476 | I59: =SUM(I31:I58) -> 4875 | J59: =SUM(J31:J58) -> 8751 | ... R59: =SUM(R31:R58) -> 11203 | S59: =R59/O59 -> 0.1671042 | U59: =SUM(U31:U58) -> 5.2262306
B61: BUILDING EXPENSE
A62: 51060 | B62: Roof Maintenance | C62: 0 | D62: 0 | E62: 0 | F62: 0 | G62: 0 | H62: 0 | I62: 0 | J62: 0 | K62: 1500 | L62: 0 | M62: 0 | N62: 0 | O62: =SUM(C62:N62) -> 1500 | P62: 1500 | Q62: 0 | R62: =O62-P62 -> 0
A63: 51070 | B63: Roof Repairs | C63: 0 | D63: 0 | F63: 0 | G63: 0 | H63: 0 | I63: 0 | J63: 0 | K63: 1500 | L63: 0 | M63: 0 | N63: 0 | O63: =SUM(C63:N63) -> 1500 | P63: 2070 | Q63: 4400 | R63: =O63-P63 -> -570 | T63: =CAM!C$25 -> 12474 | U63: =IFERROR(O63/T63,0) -> 0.12025012
A64: 51110 | B64: Monitor Fire Sprinklers | C64: 0 | D64: =C64 -> 0 | E64: =D64 -> 0 | F64: =E64 -> 0 | G64: =F64 -> 0 | H64: =G64 -> 0 | I64: =H64 -> 0 | J64: =I64 -> 0 | K64: =J64 -> 0 | ... N64: =M64 -> 0 | O64: =SUM(C64:N64) -> 0 | P64: 0 | Q64: 1200 | R64: =O64-P64 -> 0 | T64: =CAM!C$25 -> 12474 | U64: =IFERROR(O64/T64,0) -> 0 | V64: Telephone
A65: 51125 | B65: Telephone/Wifi | O65: =SUM(C65:N65) -> 0 | P65: 645 | Q65: 0 | R65: =O65-P65 -> -645 | U65: =IFERROR(O65/T65,0) -> 0
A66: 51170 | B66: Locks & Keys | C66: 0 | D66: 0 | E66: 0 | F66: 0 | G66: 0 | H66: 0 | I66: 0 | J66: 0 | K66: 0 | L66: 0 | M66: 0 | N66: 0 | O66: =SUM(C66:N66) -> 0 | P66: 0 | Q66: 300 | R66: =O66-P66 -> 0 | T66: =CAM!C$25 -> 12474 | U66: =IFERROR(O66/T66,0) -> 0
A67: 52020 | B67: Backflow Maintenance | C67: 0 | E67: 0 | F67: 55 | G67: 0 | H67: 0 | I67: 0 | J67: 0 | K67: 0 | L67: 0 | M67: 0 | N67: 0 | O67: =SUM(C67:N67) -> 55 | P67: 55 | Q67: 55 | R67: =O67-P67 -> 0 | T67: =CAM!C$25 -> 12474 | U67: =IFERROR(O67/T67,0) -> 0.0044091711
A68: 52030 | B68: Backflow Repairs | C68: 0 | D68: 0 | E68: 0 | F68: 150 | G68: 0 | H68: 0 | I68: 0 | J68: 0 | K68: 0 | L68: 0 | M68: 0 | N68: 0 | O68: =SUM(C68:N68) -> 150 | P68: 0 | Q68: 0 | R68: =O68-P68 -> 150 | T68: =CAM!C$25 -> 12474 | U68: =IFERROR(O68/T68,0) -> 0.012025012
A69: 55102 | B69: Electricity/Building | C69: =2200*105% -> 2310 | D69: =C69 -> 2310 | E69: =D69 -> 2310 | F69: =E69 -> 2310 | G69: =F69 -> 2310 | H69: =G69 -> 2310 | I69: =H69 -> 2310 | J69: =I69 -> 2310 | K69: =J69 -> 2310 | ... N69: =M69 -> 2310 | O69: =SUM(C69:N69) -> 27720 | P69: 26844 | Q69: 26844 | R69: =O69-P69 -> 876 | T69: =CAM!C$25 -> 12474 | U69: =IFERROR(O69/T69,0) -> 2.2222222
A70: 55130 | B70: Water/Building | C70: =635*105% -> 666.75 | D70: =C70 -> 666.75 | E70: =D70 -> 666.75 | F70: =E70 -> 666.75 | G70: =F70 -> 666.75 | H70: =G70 -> 666.75 | I70: =H70 -> 666.75 | J70: =I70 -> 666.75 | K70: =J70 -> 666.75 | ... N70: =M70 -> 666.75 | O70: =SUM(C70:N70) -> 8001 | P70: 7491 | Q70: 7876 | R70: =O70-P70 -> 510 | T70: =CAM!C$25 -> 12474 | U70: =IFERROR(O70/T70,0) -> 0.64141414
O71: =SUM(C71:N71) -> 0
B72: SUBTOTAL BUILDING EXP. | C72: =SUM(C62:C71) -> 2976.75 | D72: =SUM(D62:D71) -> 2976.75 | E72: =SUM(E62:E71) -> 2976.75 | F72: =SUM(F62:F71) -> 3181.75 | G72: =SUM(G62:G71) -> 2976.75 | H72: =SUM(H62:H71) -> 2976.75 | I72: =SUM(I62:I71) -> 2976.75 | J72: =SUM(J62:J71) -> 2976.75 | ... R72: =SUM(R62:R71) -> 321 | S72: =R72/O72 -> 0.0082464163 | U72: =SUM(U62:U71) -> 3.0003207
B74: INSURANCE
A75: 50111 | B75: Insurance - Property | C75: 0 | D75: 0 | E75: 0 | F75: 0 | G75: 0 | H75: =5109*110% -> 5619.9 | I75: 0 | J75: 0 | K75: 0 | L75: 0 | M75: 0 | N75: 0 | O75: =SUM(C75:N75) -> 5619.9 | P75: 5109 | Q75: 5109 | R75: =O75-P75 -> 510.9 | T75: =Ins.!C$25 -> 12474 | U75: =O75/T75 -> 0.4505291
A76: 50112 | B76: Insurance - Liability | C76: 0 | D76: 0 | E76: 0 | F76: 0 | G76: 0 | H76: 0 | I76: 0 | J76: 0 | K76: 0 | L76: 0 | M76: 0 | N76: 0 | O76: =SUM(C76:N76) -> 0 | P76: 0 | Q76: 0 | R76: =O76-P76 -> 0 | T76: =Ins.!C$25 -> 12474 | U76: =O76/T76 -> 0
A77: 50130 | B77: Insurance - Umbrella | C77: 0 | D77: 0 | E77: 0 | F77: 0 | G77: 0 | H77: 0 | I77: 0 | J77: 0 | K77: 0 | L77: 0 | M77: 0 | N77: 0 | O77: =SUM(C77:N77) -> 0 | P77: 0 | Q77: 0 | R77: =O77-P77 -> 0 | T77: =Ins.!C$25 -> 12474 | U77: =O77/T77 -> 0
A78: 50140 | B78: Insurance - Flood & Earthquake | C78: 0 | D78: 0 | E78: 0 | F78: 0 | G78: 0 | H78: 0 | I78: 0 | J78: 0 | K78: 0 | L78: 0 | M78: 0 | N78: 0 | O78: =SUM(C78:N78) -> 0 | P78: 0 | Q78: 0 | R78: =O78-P78 -> 0 | T78: =Ins.!C$25 -> 12474 | U78: =O78/T78 -> 0
B80: SUBTOTAL INSURANCE | C80: =SUM(C75:C78) -> 0 | D80: =SUM(D75:D78) -> 0 | E80: =SUM(E75:E78) -> 0 | F80: =SUM(F75:F78) -> 0 | G80: =SUM(G75:G78) -> 0 | H80: =SUM(H75:H78) -> 5619.9 | I80: =SUM(I75:I78) -> 0 | J80: =SUM(J75:J78) -> 0 | ... R80: =SUM(R75:R78) -> 510.9 | S80: =R80/O80 -> 0.090909091 | U80: =SUM(U75:U78) -> 0.4505291
B82: PROPERTY TAXES
A83: 54000 | B83: Property Tax | C83: 0 | D83: 0 | E83: 0 | F83: 17037.87 | G83: 0 | H83: 0 | I83: 0 | J83: 0 | K83: 0 | L83: 17889.76 | M83: =E83*102% -> 0 | N83: 0 | O83: =SUM(C83:N83) -> 34927.63 | P83: 34928 | Q83: 34928 | R83: =O83-P83 -> -0.37 | S83: =R83/O83 -> -1.0593333e-05 | T83: =T78 -> 12474 | U83: =O83/T83 -> 2.8000345
B85: SUBTOTAL TAXES | C85: =C83 -> 0 | D85: =D83 -> 0 | E85: =E83 -> 0 | F85: =F83 -> 17037.87 | G85: =G83 -> 0 | H85: =H83 -> 0 | I85: =I83 -> 0 | J85: =J83 -> 0 | ... R85: =R83 -> -0.37 | S85: =R85/O85 -> -1.0593333e-05 | U85: =U83 -> 2.8000345
B87: Deduct Amortizations | N87: =-N57-N56 -> -2509 | O87: =N87 -> -2509 | S87: =R87/O87 -> 0
B89: TOTAL COMMON AREA | C89: =C59+C80+C85+C72 -> 7841.75 | D89: =D59+D80+D85+D72 -> 7987.75 | E89: =E59+E80+E85+E72 -> 8452.75 | F89: =F59+F80+F85+F72 -> 24944.62 | G89: =G59+G80+G85+G72 -> 7727.75 | H89: =H59+H80+H85+H72 -> 14072.65 | I89: =I59+I80+I85+I72 -> 7851.75 | J89: =J59+J80+J85+J72 -> 11727.75 | ... N89: =N59+N80+N85+N72 -> 11201.75 | O89: =O59+O80+O85+O72+O87 -> 144006.53 | P89: =P59+P80+P85+P72 -> 134481 | Q89: =Q59+Q80+Q85+Q72 -> 130462 | R89: =R59+R80+R85+R72 -> 12034.53 | S89: =R89/O89 -> 0.083569335 | U89: =U59+U80+U85+U72 -> 11.477115
B91: GROSS CASH FLOW | C91: =C27-C89 -> 11688.729 | D91: =D27-D89 -> 11542.729 | E91: =E27-E89 -> 11147.333 | F91: =F27-F89 -> -4869.2603 | G91: =G27-G89 -> 27773.85 | H91: =H27-H89 -> 21428.95 | I91: =I27-I89 -> 27649.85 | J91: =J27-J89 -> 23773.85 | ... R91: =R27-R89 -> 141821.67 | S91: =R91/O91 -> 0.64834937
B93: OWNER EXPENSE
A94: 70210 | B94: General Repairs and Maint. | C94: 0 | D94: 0 | E94: 0 | F94: 0 | G94: 0 | H94: 0 | I94: 0 | J94: 0 | K94: 0 | L94: 0 | M94: 0 | N94: 0 | O94: =SUM(C94:N94) -> 0 | P94: 0 | Q94: 0 | R94: =O94-P94 -> 0
A95: 70220 | B95: Legal Fees | C95: 0 | D95: 0 | E95: 0 | F95: 0 | G95: 0 | H95: 0 | I95: 0 | J95: 0 | K95: 0 | L95: 0 | M95: 0 | N95: 0 | O95: =SUM(C95:N95) -> 0 | P95: 0 | Q95: 0 | R95: =O95-P95 -> 0
A96: 70230 | B96: Other Professional Fees | C96: 0 | D96: 0 | E96: 0 | F96: 0 | G96: 0 | H96: 0 | I96: 0 | J96: 0 | K96: 0 | L96: 0 | M96: 0 | N96: 0 | O96: =SUM(C96:N96) -> 0 | P96: 0 | Q96: 0 | R96: =O96-P96 -> 0
A97: 70240 | B97: General and Administrative | C97: 0 | D97: 0 | E97: 0 | F97: 0 | G97: 0 | H97: 0 | I97: 0 | J97: 0 | K97: 0 | L97: 0 | M97: 0 | N97: 0 | O97: =SUM(C97:N97) -> 0 | P97: 0 | Q97: 0 | R97: =O97-P97 -> 0
A98: 70320 | B98: Utilities Expense | C98: 0 | D98: 0 | E98: 0 | F98: 0 | G98: 0 | H98: 0 | I98: 0 | J98: 0 | K98: 0 | L98: 0 | M98: 0 | N98: 0 | O98: =SUM(C98:N98) -> 0 | P98: 0 | Q98: 0 | R98: =O98-P98 -> 0
A99: 70280 | B99: Bank Charges | C99: 0 | D99: 0 | E99: 0 | F99: 0 | G99: 0 | H99: 0 | I99: 0 | J99: 0 | K99: 0 | L99: 0 | M99: 0 | N99: 0 | O99: =SUM(C99:N99) -> 0 | P99: 0 | Q99: 0 | R99: =O99-P99 -> 0
A100: 70370 | B100: License & Permit Fees | C100: 0 | D100: 0 | E100: 0 | F100: 0 | G100: 0 | H100: 0 | I100: 0 | J100: 0 | K100: 0 | L100: 0 | M100: 0 | N100: 0 | O100: =SUM(C100:N100) -> 0 | P100: 0 | Q100: 0 | R100: =O100-P100 -> 0
A101: 70250 | B101: Other Expenses | O101: =SUM(C101:N101) -> 0 | P101: 394 | Q101: 0 | R101: =O101-P101 -> -394
A102: 70410 | B102: Rental Tax Authority | C102: ='Sales Tax'!E35 -> 568.84891 | D102: ='Sales Tax'!F35 -> 568.84891 | E102: ='Sales Tax'!G35 -> 570.87622 | F102: ='Sales Tax'!H35 -> 584.71921 | G102: ='Sales Tax'!I35 -> 1034.0272 | H102: ='Sales Tax'!J35 -> 1034.0272 | I102: ='Sales Tax'!K35 -> 1034.0272 | J102: ='Sales Tax'!L35 -> 1034.0272 | ... N102: ='Sales Tax'!P35 -> 1034.0272 | O102: =SUM(C102:N102) -> 10565.511 | P102: 6236 | Q102: 6386 | R102: =O102-P102 -> 4329.5108
A103: 70400 | B103: State Franchise Taxes | C103: 0 | D103: 0 | E103: 0 | F103: 0 | G103: 0 | H103: 0 | I103: 0 | J103: 0 | K103: 0 | L103: 0 | M103: 0 | N103: 0 | O103: =SUM(C103:N103) -> 0 | P103: 0 | Q103: 0 | R103: =O103-P103 -> 0
A104: 70440 | B104: Property Tax-Owner | C104: 0 | D104: 0 | E104: 0 | F104: 0 | G104: 0 | H104: 0 | I104: 0 | J104: 0 | K104: 0 | L104: 0 | M104: 0 | N104: 0 | O104: =SUM(C104:N104) -> 0 | P104: 0 | Q104: 0 | R104: =O104-P104 -> 0
A105: 70461 | B105: Pass Through Entity Tax | C105: 0 | D105: 0 | E105: 0 | F105: 0 | G105: 0 | H105: 0 | I105: 0 | J105: 0 | K105: 0 | L105: 0 | M105: 0 | N105: 0 | O105: =SUM(C105:N105) -> 0 | P105: 0 | Q105: 0 | R105: =O105-P105 -> 0
B107: TOTAL OWNER EXPENSE | C107: =SUM(C94:C105) -> 568.84891 | D107: =SUM(D94:D105) -> 568.84891 | E107: =SUM(E94:E105) -> 570.87622 | F107: =SUM(F94:F105) -> 584.71921 | G107: =SUM(G94:G105) -> 1034.0272 | H107: =SUM(H94:H105) -> 1034.0272 | I107: =SUM(I94:I105) -> 1034.0272 | J107: =SUM(J94:J105) -> 1034.0272 | ... R107: =SUM(R94:R105) -> 3935.5108 | S107: =R107/O107 -> 0.37248656
B109: NET OPERATING INCOME | C109: =C91-C107 -> 11119.88 | D109: =D91-D107 -> 10973.88 | E109: =E91-E107 -> 10576.457 | F109: =F91-F107 -> -5453.9795 | G109: =G91-G107 -> 26739.823 | H109: =H91-H107 -> 20394.923 | I109: =I91-I107 -> 26615.823 | J109: =J91-J107 -> 22739.823 | ... R109: =R91-R107 -> 137886.16 | S109: =R109/O109 -> 0.66235009
B111: INTEREST EXPENSE
A112: 70110 | B112: Interest Expense | C112: 4585.49 | D112: 4574.95 | E112: 4122.66 | F112: 4552.25 | G112: 4395.09 | H112: 4530.4 | I112: 4373.87 | J112: 4508.4 | K112: 4497.6 | L112: 4342.02 | M112: 4475.38 | N112: 4320.44 | O112: =SUM(C112:N112) -> 53278.55 | P112: 53248 | Q112: 53276 | R112: =O112-P112 -> 30.55
A113: 70111 | B113: Interest Expense - Second Loan | O113: =SUM(C113:N113) -> 0 | P113: 0 | Q113: 0 | R113: =O113-P113 -> 0
A114: 70182 | B114: Interest Expense - Mega Bank | C114: 0 | D114: 0 | E114: 0 | F114: 0 | G114: 0 | H114: 0 | I114: 0 | J114: 0 | K114: 0 | L114: 0 | M114: 0 | N114: 0 | O114: =SUM(C114:N114) -> 0 | P114: 0 | Q114: 0 | R114: =O114-P114 -> 0
B116: INTEREST EXPENSE | C116: =SUM(C112:C114) -> 4585.49 | D116: =SUM(D112:D114) -> 4574.95 | E116: =SUM(E112:E114) -> 4122.66 | F116: =SUM(F112:F114) -> 4552.25 | G116: =SUM(G112:G114) -> 4395.09 | H116: =SUM(H112:H114) -> 4530.4 | I116: =SUM(I112:I114) -> 4373.87 | J116: =SUM(J112:J114) -> 4508.4 | ... R116: =SUM(R112:R114) -> 30.55 | S116: =R116/O116 -> 0.00057340149
B118: TOTAL INTEREST EXPENSE
B120: CAPITAL EXPENSES
A121: 10410 | B121: Escrow-Property Tax | C121: 0 | D121: =C121 -> 0 | E121: =D121 -> 0 | F121: 0 | G121: =E121 -> 0 | H121: =G121 -> 0 | I121: =H121 -> 0 | J121: =I121 -> 0 | K121: =J121 -> 0 | L121: 0 | M121: =K121 -> 0 | N121: =M121-N83 -> 0 | O121: =SUM(C121:N121) -> 0 | P121: 0 | Q121: 0 | R121: =O121-P121 -> 0
A122: 10400 | B122: Escrow - Capital Improvement | C122: 0 | D122: 0 | E122: 0 | F122: 0 | G122: 0 | H122: 0 | I122: 0 | J122: 0 | K122: 0 | L122: 0 | M122: 0 | N122: =M122-N84 -> 0 | O122: =SUM(C122:N122) -> 0 | P122: 0 | Q122: 0 | R122: =O122-P122 -> 0
...

Sheet Cap-EX
B3: AMORTIZED PROJECTS
B5: DESCRIPTION | C5: GL CODE | D5: TOTAL PROJECT COST | F5: COST PER YR | G5: # OF YEARS | H5: DATES | K5: NOTES
B6: Restroom Remodel | C6: =Summary!A56 -> 51400 | D6: =1431*5 -> 7155 | F6: =D6/G6 -> 1431 | G6: 5 | H6: 2021-2025
B7: Paint | C7: =Summary!A57 -> 51220 | D7: =2509*5 -> 12545 | F7: =D7/G7 -> 2509 | G7: 5 | H7: 2025-2029
B13: CAP-EX
C15: ACTUAL | D15: ACTUAL | E15: FORECAST | F15: BUDGET | G15: PROJECTED | H15: PROJECTED | I15: PROJECTED | J15: PROJECTED | M15: past / project future projects
B16: DESCRIPTION | C16: 2022 | D16: 2023 | E16: 2024 | F16: 2025 | G16: 2026 | H16: 2027 | I16: 2028 | J16: 2029 | K16: NOTES
B17: Monument Sign upgrade
B18: Electrical/Lighting
B19: Roof
B20: Paint
B21: Landscape
B22: HVAC
B23: Plumbing
B24: Parking lot Slurry
B28: MAINTENANCE TRACKING
B30: DESCRIPTION | D30: COMPLETED | E30: DUE | G30: VENDOR | I30: NOTES
B31: 5-Year Fire Inspection | F31: TBD
B32: Slurry Seal | F32: TBD
B33: Roof | F33: TBD
B34: Paint | F34: TBD
B35: LED | F35: TBD

Sheet Rent
P1: =Summary!T4 -> Date Revised: | Q1: =Summary!U4 -> 46235 | R1: =Summary!V4 -> 0
A2: =Summary!$A2 -> ATHENA PROPERTY MANAGEMENT
A3: =Summary!$A3 -> BELL MEDICAL
A4: =Summary!$A4 -> PROJECT NO. 802
A5: =Summary!$A5 -> 01/01/26-12/31/26
A6: =Summary!$A6 -> 2026 OPERATING BUDGET
A9: TENANT | B9: SUITE | C9: SQUARE | D9: RATE | E9: JAN | F9: FEB | G9: MARCH | H9: APRIL | I9: MAY | J9: JUNE | K9: JULY | L9: AUGUST | M9: SEPT | N9: OCT | O9: NOV | P9: DEC | Q9: TOTALS | R9: NOTES
B10: # | C10: FOOTAGE
A12: BASE RENT
A15: Occupational Medicine for Business & Industry | B15: 100A | C15: 5659 | D15: =P15*12/C15 -> 28.981855 | E15: 13269.28 | F15: =E15 -> 13269.28 | G15: =F15 -> 13269.28 | H15: 13667.36 | I15: =H15 -> 13667.36 | J15: =I15 -> 13667.36 | K15: =J15 -> 13667.36 | L15: =K15 -> 13667.36 | M15: =L15 -> 13667.36 | N15: =M15 -> 13667.36 | O15: =N15 -> 13667.36 | P15: =O15 -> 13667.36 | Q15: =SUM(E15:P15) -> 162814.08 | R15: Rent increase effective 4/1/2026 for $13,667.36 or $2.42 PSF.
A16: Arizona Sports & Spine Physicians | B16: 101A | C16: 1967 | D16: =P16*12/C16 -> 27.487992 | E16: 4374.81 | F16: =E16 -> 4374.81 | G16: =(4374.81*15/31)+(4505.74*16/31) -> 4442.3868 | H16: 4505.74 | I16: =H16 -> 4505.74 | J16: =I16 -> 4505.74 | K16: =J16 -> 4505.74 | L16: =K16 -> 4505.74 | M16: =L16 -> 4505.74 | N16: =M16 -> 4505.74 | O16: =N16 -> 4505.74 | P16: =O16 -> 4505.74 | Q16: =SUM(E16:P16) -> 53743.667 | R16: Rent increase effective 3/16/2026 for $4,505.74 or $2.29 PSF.
A17: Vacant | B17: 100B | C17: 618 | D17: =P17*12/C17 -> 23.64 | E17: 0 | F17: =E17 -> 0 | G17: =F17 -> 0 | H17: =G17 -> 0 | I17: =C17*1.97 -> 1217.46 | J17: =I17 -> 1217.46 | K17: =J17 -> 1217.46 | L17: =K17 -> 1217.46 | M17: =L17 -> 1217.46 | N17: =M17 -> 1217.46 | O17: =N17 -> 1217.46 | P17: =O17 -> 1217.46 | Q17: =SUM(E17:P17) -> 9739.68 | R17: Anticipate Rents Starting May
A18: Vacant | B18: 101B/102B | C18: 4230 | D18: =P18*12/C18 -> 23.64 | E18: 0 | F18: =E18 -> 0 | G18: =F18 -> 0 | H18: =G18 -> 0 | I18: =C18*1.97 -> 8333.1 | J18: =I18 -> 8333.1 | K18: =J18 -> 8333.1 | L18: =K18 -> 8333.1 | M18: =L18 -> 8333.1 | N18: =M18 -> 8333.1 | O18: =N18 -> 8333.1 | P18: =O18 -> 8333.1 | Q18: =SUM(E18:P18) -> 66664.8 | R18: Anticipate Rents Starting May
A23: TOTALS | C23: =SUM(C14:C22) -> 12474 | E23: =SUM(E14:E22) -> 17644.09 | F23: =SUM(F14:F22) -> 17644.09 | G23: =SUM(G14:G22) -> 17711.667 | H23: =SUM(H14:H22) -> 18173.1 | I23: =SUM(I14:I22) -> 27723.66 | J23: =SUM(J14:J22) -> 27723.66 | K23: =SUM(K14:K22) -> 27723.66 | L23: =SUM(L14:L22) -> 27723.66 | ... Q23: =SUM(Q14:Q22) -> 292962.23
D26: NMK Tie-out | E26: =E23-Summary!C13 -> 0 | F26: =F23-Summary!D13 -> 0 | G26: =G23-Summary!E13 -> 0 | H26: =H23-Summary!F13 -> 0 | I26: =I23-Summary!G13 -> 0 | J26: =J23-Summary!H13 -> 0 | K26: =K23-Summary!I13 -> 0 | L26: =L23-Summary!J13 -> 0 | ... Q26: =Q23-Summary!O13 -> 0
A28: TOTAL LESS VACANCY | C28: =C23-C17-C18 -> 7626

Sheet Rent Deferral Recovery
O1: =Summary!T4 -> Date Revised: | P1: =Summary!U4 -> 46235 | Q1: =Summary!V4 -> 0
A2: =Summary!$A2 -> ATHENA PROPERTY MANAGEMENT
A3: =Summary!$A3 -> BELL MEDICAL
A4: =Summary!$A4 -> PROJECT NO. 802
A5: =Summary!$A5 -> 01/01/26-12/31/26
A6: =Summary!$A6 -> 2026 OPERATING BUDGET
A9: TENANT | B9: SUITE | C9: SQUARE | D9: JAN | E9: FEB | F9: MARCH | G9: APRIL | H9: MAY | I9: JUNE | J9: JULY | K9: AUGUST | L9: SEPT | M9: OCT | N9: NOV | O9: DEC | P9: TOTALS
B10: # | C10: FOOTAGE
A12: DEFERRED RENT RECOVERY
A14: None at this time | D14: 0 | E14: 0 | F14: 0 | G14: 0 | H14: 0 | I14: 0 | J14: 0 | K14: 0 | L14: 0 | M14: 0 | N14: 0 | O14: 0 | P14: =SUM(D14:O14) -> 0
A19: TOTALS | C19: =SUM(C14:C14) -> 0 | D19: =SUM(D14:D14) -> 0 | E19: =SUM(E14:E14) -> 0 | F19: =SUM(F14:F14) -> 0 | G19: =SUM(G14:G14) -> 0 | H19: =SUM(H14:H14) -> 0 | I19: =SUM(I14:I14) -> 0 | J19: =SUM(J14:J14) -> 0 | ... P19: =SUM(P14:P14) -> 0
A25: TENANT | B25: SUITE | C25: SQUARE | D25: JAN | E25: FEB | F25: MARCH | G25: APRIL | H25: MAY | I25: JUNE | J25: JULY | K25: AUGUST | L25: SEPT | M25: OCT | N25: NOV | O25: DEC | P25: TOTALS
B26: # | C26: FOOTAGE
A28: DEFERRED CAM RECOVERY
A30: None at this time | D30: 0 | E30: 0 | F30: 0 | G30: 0 | H30: 0 | I30: 0 | J30: 0 | K30: 0 | L30: 0 | M30: 0 | N30: 0 | O30: 0 | P30: =SUM(D30:O30) -> 0
A35: TOTALS | C35: =SUM(C30:C30) -> 0 | D35: =SUM(D30:D30) -> 0 | E35: =SUM(E30:E30) -> 0 | F35: =SUM(F30:F30) -> 0 | G35: =SUM(G30:G30) -> 0 | H35: =SUM(H30:H30) -> 0 | I35: =SUM(I30:I30) -> 0 | J35: =SUM(J30:J30) -> 0 | ... P35: =SUM(P30:P30) -> 0

Sheet CAM
P1: =Summary!T4 -> Date Revised: | Q1: =Summary!U4 -> 46235
A2: =Summary!$A2 -> ATHENA PROPERTY MANAGEMENT
A3: =Summary!$A3 -> BELL MEDICAL
A4: =Summary!$A4 -> PROJECT NO. 802
A5: =Summary!$A5 -> 01/01/26-12/31/26
A6: =Summary!$A6 -> 2026 OPERATING BUDGET
A9: TENANT | B9: SUITE | C9: SQUARE | D9: % OF | E9: JAN | F9: FEB | G9: MARCH | H9: APRIL | I9: MAY | J9: JUNE | K9: JULY | L9: AUGUST | M9: SEPT | N9: OCT | O9: NOV | P9: DEC | Q9: TOTALS | R9: 2015 | S9: TOTALS (2014) | T9: 2014 | U9: Cost PSF
B10: # | C10: FOOTAGE | D10: TOTAL
A12: COMMON AREA MAINTENANCE
A15: =Rent!A15 -> Occupational Medicine for Business & Industry | B15: =Rent!B15 -> 100A | C15: =Rent!C15 -> 5659 | D15: =C15/$C$25 -> 0.45366362 | E15: =IF(Rent!E15=0,0,('Tenant Charges'!$F11)) -> 611.19378 | F15: =IF(Rent!F15=0,0,('Tenant Charges'!$F11)) -> 611.19378 | G15: =IF(Rent!G15=0,0,('Tenant Charges'!$F11)) -> 611.19378 | H15: =IF(Rent!H15=0,0,('Tenant Charges'!$F11)) -> 611.19378 | I15: =IF(Rent!I15=0,0,('Tenant Charges'!$F11)) -> 611.19378 | J15: =IF(Rent!J15=0,0,('Tenant Charges'!$F11)) -> 611.19378 | K15: =IF(Rent!K15=0,0,('Tenant Charges'!$F11)) -> 611.19378 | L15: =IF(Rent!L15=0,0,('Tenant Charges'!$F11)) -> 611.19378 | ... P15: =IF(Rent!P15=0,0,('Tenant Charges'!$F11)) -> 611.19378 | Q15: =SUM(E15:P15) -> 7334.3253 | R15: =Q15/C15 -> 1.2960462 | S15: =262.76*12 -> 3153.12 | T15: =S15/C15 -> 0.55718678 | U15: =Q15/C15 -> 1.2960462
A16: =Rent!A16 -> Arizona Sports & Spine Physicians | B16: =Rent!B16 -> 101A | C16: =Rent!C16 -> 1967 | D16: =C16/$C$25 -> 0.15768799 | E16: =IF(Rent!E16=0,0,('Tenant Charges'!$F12)) -> 256.61671 | F16: =IF(Rent!F16=0,0,('Tenant Charges'!$F12)) -> 256.61671 | G16: =IF(Rent!G16=0,0,('Tenant Charges'!$F12)) -> 256.61671 | H16: =IF(Rent!H16=0,0,('Tenant Charges'!$F12)) -> 256.61671 | I16: =IF(Rent!I16=0,0,('Tenant Charges'!$F12)) -> 256.61671 | J16: =IF(Rent!J16=0,0,('Tenant Charges'!$F12)) -> 256.61671 | K16: =IF(Rent!K16=0,0,('Tenant Charges'!$F12)) -> 256.61671 | L16: =IF(Rent!L16=0,0,('Tenant Charges'!$F12)) -> 256.61671 | ... P16: =IF(Rent!P16=0,0,('Tenant Charges'!$F12)) -> 256.61671 | Q16: =SUM(E16:P16) -> 3079.4005 | R16: =Q16/C16 -> 1.5655315 | S16: 0 | T16: =S16/C16 -> 0 | U16: =Q16/C16 -> 1.5655315
A17: =Rent!A17 -> Vacant | B17: =Rent!B17 -> 100B | C17: =Rent!C17 -> 618 | D17: =C17/$C$25 -> 0.04954305 | E17: =IF(Rent!E17=0,0,('Tenant Charges'!$F13)) -> 0 | F17: =IF(Rent!F17=0,0,('Tenant Charges'!$F13)) -> 0 | G17: =IF(Rent!G17=0,0,('Tenant Charges'!$F13)) -> 0 | H17: =IF(Rent!H17=0,0,('Tenant Charges'!$F13)) -> 0 | I17: =IF(Rent!I17=0,0,('Tenant Charges'!$F13)) -> 269.86053 | J17: =IF(Rent!J17=0,0,('Tenant Charges'!$F13)) -> 269.86053 | K17: =IF(Rent!K17=0,0,('Tenant Charges'!$F13)) -> 269.86053 | L17: =IF(Rent!L17=0,0,('Tenant Charges'!$F13)) -> 269.86053 | ... P17: =IF(Rent!P17=0,0,('Tenant Charges'!$F13)) -> 269.86053 | Q17: =SUM(E17:P17) -> 2158.8842 | R17: =Q17/C17 -> 3.4933402 | S17: 1 | T17: =S17/C17 -> 0.001618123 | U17: =Q17/C17 -> 3.4933402
A18: =Rent!A18 -> Vacant | B18: =Rent!B18 -> 101B/102B | C18: =Rent!C18 -> 4230 | D18: =C18/$C$25 -> 0.33910534 | E18: =IF(Rent!E18=0,0,('Tenant Charges'!$F14)) -> 0 | F18: =IF(Rent!F18=0,0,('Tenant Charges'!$F14)) -> 0 | G18: =IF(Rent!G18=0,0,('Tenant Charges'!$F14)) -> 0 | H18: =IF(Rent!H18=0,0,('Tenant Charges'!$F14)) -> 0 | I18: =IF(Rent!I18=0,0,('Tenant Charges'!$F14)) -> 1847.1036 | J18: =IF(Rent!J18=0,0,('Tenant Charges'!$F14)) -> 1847.1036 | K18: =IF(Rent!K18=0,0,('Tenant Charges'!$F14)) -> 1847.1036 | L18: =IF(Rent!L18=0,0,('Tenant Charges'!$F14)) -> 1847.1036 | ... P18: =IF(Rent!P18=0,0,('Tenant Charges'!$F14)) -> 1847.1036 | Q18: =SUM(E18:P18) -> 14776.829 | R18: =Q18/C18 -> 3.4933402 | S18: 2 | T18: =S18/C18 -> 0.00047281324 | U18: =Q18/C18 -> 3.4933402
A25: TOTALS | C25: =SUM(C14:C23) -> 12474 | D25: =SUM(D14:D23) -> 1 | E25: =SUM(E14:E23) -> 867.81048 | F25: =SUM(F14:F23) -> 867.81048 | G25: =SUM(G14:G23) -> 867.81048 | H25: =SUM(H14:H23) -> 867.81048 | I25: =SUM(I14:I23) -> 2984.7746 | J25: =SUM(J14:J23) -> 2984.7746 | ... Q25: =SUM(Q14:Q23) -> 27349.439
O27: TOTAL CAM | Q27: =Summary!O59 -> 67042
A28: TOTAL OCCUPIED | C28: =C15+C16 -> 7626 | O28: RECAPTURE | Q28: =Q25/Q27 -> 0.40794486
D31: NMK Tie-out | E31: =E25-Summary!C14 -> 0 | F31: =F25-Summary!D14 -> 0 | G31: =G25-Summary!E14 -> 0 | H31: =H25-Summary!F14 -> 0 | I31: =I25-Summary!G14 -> 0 | J31: =J25-Summary!H14 -> 0 | K31: =K25-Summary!I14 -> 0 | L31: =L25-Summary!J14 -> 0 | ... Q31: =Q25-Summary!O14 -> 0

Sheet Building Expenses
P1: =Summary!T4 -> Date Revised: | Q1: =Summary!U4 -> 46235 | R1: =Summary!V4 -> 0
A2: =Summary!$A2 -> ATHENA PROPERTY MANAGEMENT
A3: =Summary!$A3 -> BELL MEDICAL
A4: =Summary!$A4 -> PROJECT NO. 802
A5: =Summary!$A5 -> 01/01/26-12/31/26
A6: =Summary!$A6 -> 2026 OPERATING BUDGET
D8: SQ FT
A9: TENANT | B9: SUITE | C9: SQUARE | D9: % OF | E9: JAN | F9: FEB | G9: MARCH | H9: APRIL | I9: MAY | J9: JUNE | K9: JULY | L9: AUGUST | M9: SEPT | N9: OCT | O9: NOV | P9: DEC | Q9: TOTALS
B10: # | C10: FOOTAGE | D10: TOTAL | R10: Cost PSF
A12: BUILDING EXPENSES
A15: =Rent!A15 -> Occupational Medicine for Business & Industry | B15: =Rent!B15 -> 100A | C15: =Rent!C15 -> 5659 | D15: =C15/$C$26 -> 0.45366362 | E15: =IF(Rent!E15=0,0,('Tenant Charges'!$G11)) -> 0 | F15: =IF(Rent!F15=0,0,('Tenant Charges'!$G11)) -> 0 | G15: =IF(Rent!G15=0,0,('Tenant Charges'!$G11)) -> 0 | H15: =IF(Rent!H15=0,0,('Tenant Charges'!$G11)) -> 0 | I15: =IF(Rent!I15=0,0,('Tenant Charges'!$G11)) -> 0 | J15: =IF(Rent!J15=0,0,('Tenant Charges'!$G11)) -> 0 | K15: =IF(Rent!K15=0,0,('Tenant Charges'!$G11)) -> 0 | L15: =IF(Rent!L15=0,0,('Tenant Charges'!$G11)) -> 0 | ... P15: =IF(Rent!P15=0,0,('Tenant Charges'!$G11)) -> 0 | Q15: =SUM(E15:P15) -> 0 | R15: =Q15/C15 -> 0
A16: =Rent!A16 -> Arizona Sports & Spine Physicians | B16: =Rent!B16 -> 101A | C16: =Rent!C16 -> 1967 | D16: =C16/$C$26 -> 0.15768799 | E16: =IF(Rent!E16=0,0,('Tenant Charges'!$G12)) -> 0 | F16: =IF(Rent!F16=0,0,('Tenant Charges'!$G12)) -> 0 | G16: =IF(Rent!G16=0,0,('Tenant Charges'!$G12)) -> 0 | H16: =IF(Rent!H16=0,0,('Tenant Charges'!$G12)) -> 0 | I16: =IF(Rent!I16=0,0,('Tenant Charges'!$G12)) -> 0 | J16: =IF(Rent!J16=0,0,('Tenant Charges'!$G12)) -> 0 | K16: =IF(Rent!K16=0,0,('Tenant Charges'!$G12)) -> 0 | L16: =IF(Rent!L16=0,0,('Tenant Charges'!$G12)) -> 0 | ... P16: =IF(Rent!P16=0,0,('Tenant Charges'!$G12)) -> 0 | Q16: =SUM(E16:P16) -> 0 | R16: =Q16/C16 -> 0
A17: =Rent!A17 -> Vacant | B17: =Rent!B17 -> 100B | C17: =Rent!C17 -> 618 | D17: =C17/$C$26 -> 0.04954305 | E17: =IF(Rent!E17=0,0,('Tenant Charges'!$G13)) -> 0 | F17: =IF(Rent!F17=0,0,('Tenant Charges'!$G13)) -> 0 | G17: =IF(Rent!G17=0,0,('Tenant Charges'!$G13)) -> 0 | H17: =IF(Rent!H17=0,0,('Tenant Charges'!$G13)) -> 0 | I17: =IF(Rent!I17=0,0,('Tenant Charges'!$G13)) -> 254.46363 | J17: =IF(Rent!J17=0,0,('Tenant Charges'!$G13)) -> 254.46363 | K17: =IF(Rent!K17=0,0,('Tenant Charges'!$G13)) -> 254.46363 | L17: =IF(Rent!L17=0,0,('Tenant Charges'!$G13)) -> 254.46363 | ... P17: =IF(Rent!P17=0,0,('Tenant Charges'!$G13)) -> 254.46363 | Q17: =SUM(E17:P17) -> 2035.7091 | R17: =Q17/C17 -> 3.2940276
A18: =Rent!A18 -> Vacant | B18: =Rent!B18 -> 101B/102B | C18: =Rent!C18 -> 4230 | D18: =C18/$C$26 -> 0.33910534 | E18: =IF(Rent!E18=0,0,('Tenant Charges'!$G14)) -> 0 | F18: =IF(Rent!F18=0,0,('Tenant Charges'!$G14)) -> 0 | G18: =IF(Rent!G18=0,0,('Tenant Charges'!$G14)) -> 0 | H18: =IF(Rent!H18=0,0,('Tenant Charges'!$G14)) -> 0 | I18: =IF(Rent!I18=0,0,('Tenant Charges'!$G14)) -> 1741.7171 | J18: =IF(Rent!J18=0,0,('Tenant Charges'!$G14)) -> 1741.7171 | K18: =IF(Rent!K18=0,0,('Tenant Charges'!$G14)) -> 1741.7171 | L18: =IF(Rent!L18=0,0,('Tenant Charges'!$G14)) -> 1741.7171 | ... P18: =IF(Rent!P18=0,0,('Tenant Charges'!$G14)) -> 1741.7171 | Q18: =SUM(E18:P18) -> 13933.737 | R18: =Q18/C18 -> 3.2940276
A26: TOTALS | C26: =SUM(C14:C25) -> 12474 | D26: =SUM(D14:D25) -> 1 | E26: =SUM(E14:E25) -> 0 | F26: =SUM(F14:F25) -> 0 | G26: =SUM(G14:G25) -> 0 | H26: =SUM(H14:H25) -> 0 | I26: =SUM(I14:I25) -> 1996.1807 | J26: =SUM(J14:J25) -> 1996.1807 | ... Q26: =SUM(Q14:Q25) -> 15969.446
O28: TOTAL BLDG | Q28: =Summary!O72 -> 38926
O29: RECAPTURE | Q29: =Q26/Q28 -> 0.4102514
D31: NMK Tie-out | E31: =E26-Summary!C17 -> 0 | F31: =F26-Summary!D17 -> 0 | G31: =G26-Summary!E17 -> 0 | H31: =H26-Summary!F17 -> 0 | I31: =I26-Summary!G17 -> 0 | J31: =J26-Summary!H17 -> 0 | K31: =K26-Summary!I17 -> 0 | L31: =L26-Summary!J17 -> 0 | ... Q31: =Q26-Summary!O17 -> 0

Sheet Admin Fee
P1: =Summary!T4 -> Date Revised: | Q1: =Summary!U4 -> 46235
A2: =Summary!$A2 -> ATHENA PROPERTY MANAGEMENT
A3: =Summary!$A3 -> BELL MEDICAL
A4: =Summary!$A4 -> PROJECT NO. 802
A5: =Summary!$A5 -> 01/01/26-12/31/26
A6: =Summary!$A6 -> 2026 OPERATING BUDGET
A9: TENANT | B9: SUITE | C9: SQUARE | D9: RATE | E9: JAN | F9: FEB | G9: MARCH | H9: APRIL | I9: MAY | J9: JUNE | K9: JULY | L9: AUGUST | M9: SEPT | N9: OCT | O9: NOV | P9: DEC | Q9: TOTALS
B10: # | C10: FOOTAGE | R10: Cost PSF
A12: ADMINISTRATIVE FEES
A15: =Rent!A15 -> Occupational Medicine for Business & Industry | B15: =Rent!B15 -> 100A | C15: =Rent!C15 -> 5659 | D15: 0 | E15: =IF(Rent!E15=0,0,'Tenant Charges'!$H11) -> 0 | F15: =IF(Rent!F15=0,0,'Tenant Charges'!$H11) -> 0 | G15: =IF(Rent!G15=0,0,'Tenant Charges'!$H11) -> 0 | H15: =IF(Rent!H15=0,0,'Tenant Charges'!$H11) -> 0 | I15: =IF(Rent!I15=0,0,'Tenant Charges'!$H11) -> 0 | J15: =IF(Rent!J15=0,0,'Tenant Charges'!$H11) -> 0 | K15: =IF(Rent!K15=0,0,'Tenant Charges'!$H11) -> 0 | L15: =IF(Rent!L15=0,0,'Tenant Charges'!$H11) -> 0 | ... P15: =IF(Rent!P15=0,0,'Tenant Charges'!$H11) -> 0 | Q15: =SUM(E15:P15) -> 0 | R15: =Q15/C15 -> 0
A16: =Rent!A16 -> Arizona Sports & Spine Physicians | B16: =Rent!B16 -> 101A | C16: =Rent!C16 -> 1967 | D16: 0 | E16: =IF(Rent!E16=0,0,'Tenant Charges'!$H12) -> 0 | F16: =IF(Rent!F16=0,0,'Tenant Charges'!$H12) -> 0 | G16: =IF(Rent!G16=0,0,'Tenant Charges'!$H12) -> 0 | H16: =IF(Rent!H16=0,0,'Tenant Charges'!$H12) -> 0 | I16: =IF(Rent!I16=0,0,'Tenant Charges'!$H12) -> 0 | J16: =IF(Rent!J16=0,0,'Tenant Charges'!$H12) -> 0 | K16: =IF(Rent!K16=0,0,'Tenant Charges'!$H12) -> 0 | L16: =IF(Rent!L16=0,0,'Tenant Charges'!$H12) -> 0 | ... P16: =IF(Rent!P16=0,0,'Tenant Charges'!$H12) -> 0 | Q16: =SUM(E16:P16) -> 0 | R16: =Q16/C16 -> 0
A17: =Rent!A17 -> Vacant | B17: =Rent!B17 -> 100B | C17: =Rent!C17 -> 618 | D17: 1 | E17: =IF(Rent!E17=0,0,'Tenant Charges'!$H13) -> 0 | F17: =IF(Rent!F17=0,0,'Tenant Charges'!$H13) -> 0 | G17: =IF(Rent!G17=0,0,'Tenant Charges'!$H13) -> 0 | H17: =IF(Rent!H17=0,0,'Tenant Charges'!$H13) -> 0 | I17: =IF(Rent!I17=0,0,'Tenant Charges'!$H13) -> 0 | J17: =IF(Rent!J17=0,0,'Tenant Charges'!$H13) -> 0 | K17: =IF(Rent!K17=0,0,'Tenant Charges'!$H13) -> 0 | L17: =IF(Rent!L17=0,0,'Tenant Charges'!$H13) -> 0 | ... P17: =IF(Rent!P17=0,0,'Tenant Charges'!$H13) -> 0 | Q17: =SUM(E17:P17) -> 0 | R17: =Q17/C17 -> 0
A18: =Rent!A18 -> Vacant | B18: =Rent!B18 -> 101B/102B | C18: =Rent!C18 -> 4230 | D18: 2 | E18: =IF(Rent!E18=0,0,'Tenant Charges'!$H14) -> 0 | F18: =IF(Rent!F18=0,0,'Tenant Charges'!$H14) -> 0 | G18: =IF(Rent!G18=0,0,'Tenant Charges'!$H14) -> 0 | H18: =IF(Rent!H18=0,0,'Tenant Charges'!$H14) -> 0 | I18: =IF(Rent!I18=0,0,'Tenant Charges'!$H14) -> 0 | J18: =IF(Rent!J18=0,0,'Tenant Charges'!$H14) -> 0 | K18: =IF(Rent!K18=0,0,'Tenant Charges'!$H14) -> 0 | L18: =IF(Rent!L18=0,0,'Tenant Charges'!$H14) -> 0 | ... P18: =IF(Rent!P18=0,0,'Tenant Charges'!$H14) -> 0 | Q18: =SUM(E18:P18) -> 0 | R18: =Q18/C18 -> 0
A26: TOTALS | C26: =SUM(C14:C25) -> 12474 | E26: =SUM(E14:E25) -> 0 | F26: =SUM(F14:F25) -> 0 | G26: =SUM(G14:G25) -> 0 | H26: =SUM(H14:H25) -> 0 | I26: =SUM(I14:I25) -> 0 | J26: =SUM(J14:J25) -> 0 | K26: =SUM(K14:K25) -> 0 | L26: =SUM(L14:L25) -> 0 | ... Q26: =SUM(Q14:Q25) -> 0
O28: TOTAL ADM | Q28: =Summary!O20 -> 0
O29: RECAPTURE | Q29: =IFERROR(Q26/Q28,0) -> 0
D31: NMK Tie-out | E31: =E26-Summary!C20 -> 0 | F31: =F26-Summary!D20 -> 0 | G31: =G26-Summary!E20 -> 0 | H31: =H26-Summary!F20 -> 0 | I31: =I26-Summary!G20 -> 0 | J31: =J26-Summary!H20 -> 0 | K31: =K26-Summary!I20 -> 0 | L31: =L26-Summary!J20 -> 0 | ... Q31: =Q26-Summary!O20 -> 0

Sheet RE Tax
P1: =Summary!T4 -> Date Revised: | Q1: =Summary!U4 -> 46235 | R1: =Summary!V4 -> 0
A2: =Summary!$A2 -> ATHENA PROPERTY MANAGEMENT
A3: =Summary!$A3 -> BELL MEDICAL
A4: =Summary!$A4 -> PROJECT NO. 802
A5: =Summary!$A5 -> 01/01/26-12/31/26
A6: =Summary!$A6 -> 2026 OPERATING BUDGET
A9: TENANT | B9: SUITE | C9: SQUARE | D9: PRORATA | E9: JAN | F9: FEB | G9: MARCH | H9: APRIL | I9: MAY | J9: JUNE | K9: JULY | L9: AUGUST | M9: SEPT | N9: OCT | O9: NOV | P9: DEC | Q9: TOTALS
B10: # | C10: FOOTAGE | D10: SHARE | R10: Cost PSF
A12: RE Tax
A15: =Rent!A15 -> Occupational Medicine for Business & Industry | B15: =Rent!B15 -> 100A | C15: =Rent!C15 -> 5659 | D15: =C15/$C$24 -> 0.45366362 | E15: =IF(Rent!E15=0,0,('Tenant Charges'!$I11)) -> 0 | F15: =IF(Rent!F15=0,0,('Tenant Charges'!$I11)) -> 0 | G15: =IF(Rent!G15=0,0,('Tenant Charges'!$I11)) -> 0 | H15: =IF(Rent!H15=0,0,('Tenant Charges'!$I11)) -> 0 | I15: =IF(Rent!I15=0,0,('Tenant Charges'!$I11)) -> 0 | J15: =IF(Rent!J15=0,0,('Tenant Charges'!$I11)) -> 0 | K15: =IF(Rent!K15=0,0,('Tenant Charges'!$I11)) -> 0 | L15: =IF(Rent!L15=0,0,('Tenant Charges'!$I11)) -> 0 | ... P15: =IF(Rent!P15=0,0,('Tenant Charges'!$I11)) -> 0 | Q15: =SUM(E15:P15) -> 0 | R15: =Q15/C15 -> 0
A16: =Rent!A16 -> Arizona Sports & Spine Physicians | B16: =Rent!B16 -> 101A | C16: =Rent!C16 -> 1967 | D16: =C16/$C$24 -> 0.15768799 | E16: =IF(Rent!E16=0,0,('Tenant Charges'!$I12)) -> 0 | F16: =IF(Rent!F16=0,0,('Tenant Charges'!$I12)) -> 0 | G16: =IF(Rent!G16=0,0,('Tenant Charges'!$I12)) -> 0 | H16: =IF(Rent!H16=0,0,('Tenant Charges'!$I12)) -> 0 | I16: =IF(Rent!I16=0,0,('Tenant Charges'!$I12)) -> 0 | J16: =IF(Rent!J16=0,0,('Tenant Charges'!$I12)) -> 0 | K16: =IF(Rent!K16=0,0,('Tenant Charges'!$I12)) -> 0 | L16: =IF(Rent!L16=0,0,('Tenant Charges'!$I12)) -> 0 | ... P16: =IF(Rent!P16=0,0,('Tenant Charges'!$I12)) -> 0 | Q16: =SUM(E16:P16) -> 0 | R16: =Q16/C16 -> 0
A17: =Rent!A17 -> Vacant | B17: =Rent!B17 -> 100B | C17: =Rent!C17 -> 618 | D17: =C17/$C$24 -> 0.04954305 | E17: =IF(Rent!E17=0,0,('Tenant Charges'!$I13)) -> 0 | F17: =IF(Rent!F17=0,0,('Tenant Charges'!$I13)) -> 0 | G17: =IF(Rent!G17=0,0,('Tenant Charges'!$I13)) -> 0 | H17: =IF(Rent!H17=0,0,('Tenant Charges'!$I13)) -> 0 | I17: =IF(Rent!I17=0,0,('Tenant Charges'!$I13)) -> 144.20178 | J17: =IF(Rent!J17=0,0,('Tenant Charges'!$I13)) -> 144.20178 | K17: =IF(Rent!K17=0,0,('Tenant Charges'!$I13)) -> 144.20178 | L17: =IF(Rent!L17=0,0,('Tenant Charges'!$I13)) -> 144.20178 | ... P17: =IF(Rent!P17=0,0,('Tenant Charges'!$I13)) -> 144.20178 | Q17: =SUM(E17:P17) -> 1153.6142 | R17: =Q17/C17 -> 1.8666896
A18: =Rent!A18 -> Vacant | B18: =Rent!B18 -> 101B/102B | C18: =Rent!C18 -> 4230 | D18: =C18/$C$24 -> 0.33910534 | E18: =IF(Rent!E18=0,0,('Tenant Charges'!$I14)) -> 0 | F18: =IF(Rent!F18=0,0,('Tenant Charges'!$I14)) -> 0 | G18: =IF(Rent!G18=0,0,('Tenant Charges'!$I14)) -> 0 | H18: =IF(Rent!H18=0,0,('Tenant Charges'!$I14)) -> 0 | I18: =IF(Rent!I18=0,0,('Tenant Charges'!$I14)) -> 987.01215 | J18: =IF(Rent!J18=0,0,('Tenant Charges'!$I14)) -> 987.01215 | K18: =IF(Rent!K18=0,0,('Tenant Charges'!$I14)) -> 987.01215 | L18: =IF(Rent!L18=0,0,('Tenant Charges'!$I14)) -> 987.01215 | ... P18: =IF(Rent!P18=0,0,('Tenant Charges'!$I14)) -> 987.01215 | Q18: =SUM(E18:P18) -> 7896.0972 | R18: =Q18/C18 -> 1.8666896
A24: TOTALS | C24: =SUM(C14:C23) -> 12474 | D24: =SUM(D14:D23) -> 1 | E24: =SUM(E14:E23) -> 0 | F24: =SUM(F14:F23) -> 0 | G24: =SUM(G14:G23) -> 0 | H24: =SUM(H14:H23) -> 0 | I24: =SUM(I14:I23) -> 1131.2139 | J24: =SUM(J14:J23) -> 1131.2139 | ... Q24: =SUM(Q14:Q23) -> 9049.7114
O26: TOTAL RE Tax | Q26: =Summary!O85 -> 34927.63
O27: RECAPTURE | Q27: =Q24/Q26 -> 0.25909893
D29: NMK Tie-out | E29: =E24-Summary!C19 -> 0 | F29: =F24-Summary!D19 -> 0 | G29: =G24-Summary!E19 -> 0 | H29: =H24-Summary!F19 -> 0 | I29: =I24-Summary!G19 -> 0 | J29: =J24-Summary!H19 -> 0 | K29: =K24-Summary!I19 -> 0 | L29: =L24-Summary!J19 -> 0 | ... Q29: =Q24-Summary!O19 -> 0

Sheet Ins.
P1: =Summary!T4 -> Date Revised: | Q1: =Summary!U4 -> 46235 | R1: =Summary!V4 -> 0
A2: =Summary!$A2 -> ATHENA PROPERTY MANAGEMENT
A3: =Summary!$A3 -> BELL MEDICAL
A4: =Summary!$A4 -> PROJECT NO. 802
A5: =Summary!$A5 -> 01/01/26-12/31/26
A6: =Summary!$A6 -> 2026 OPERATING BUDGET
A9: TENANT | B9: SUITE | C9: SQUARE | D9: PRORATA | E9: JAN | F9: FEB | G9: MARCH | H9: APRIL | I9: MAY | J9: JUNE | K9: JULY | L9: AUGUST | M9: SEPT | N9: OCT | O9: NOV | P9: DEC | Q9: TOTALS
B10: # | C10: FOOTAGE | D10: SHARE | R10: Cost PSF
A12: INSURANCE
A15: =Rent!A15 -> Occupational Medicine for Business & Industry | B15: =Rent!B15 -> 100A | C15: =Rent!C15 -> 5659 | D15: =C15/$C$25 -> 0.45366362 | E15: =IF(Rent!E15=0,0,('Tenant Charges'!$J11)) -> 0 | F15: =IF(Rent!F15=0,0,('Tenant Charges'!$J11)) -> 0 | G15: =IF(Rent!G15=0,0,('Tenant Charges'!$J11)) -> 0 | H15: =IF(Rent!H15=0,0,('Tenant Charges'!$J11)) -> 0 | I15: =IF(Rent!I15=0,0,('Tenant Charges'!$J11)) -> 0 | J15: =IF(Rent!J15=0,0,('Tenant Charges'!$J11)) -> 0 | K15: =IF(Rent!K15=0,0,('Tenant Charges'!$J11)) -> 0 | L15: =IF(Rent!L15=0,0,('Tenant Charges'!$J11)) -> 0 | ... P15: =IF(Rent!P15=0,0,('Tenant Charges'!$J11)) -> 0 | Q15: =SUM(E15:P15) -> 0 | R15: =Q15/C15 -> 0
A16: =Rent!A16 -> Arizona Sports & Spine Physicians | B16: =Rent!B16 -> 101A | C16: =Rent!C16 -> 1967 | D16: =C16/$C$25 -> 0.15768799 | E16: =IF(Rent!E16=0,0,('Tenant Charges'!$J12)) -> 0 | F16: =IF(Rent!F16=0,0,('Tenant Charges'!$J12)) -> 0 | G16: =IF(Rent!G16=0,0,('Tenant Charges'!$J12)) -> 0 | H16: =IF(Rent!H16=0,0,('Tenant Charges'!$J12)) -> 0 | I16: =IF(Rent!I16=0,0,('Tenant Charges'!$J12)) -> 0 | J16: =IF(Rent!J16=0,0,('Tenant Charges'!$J12)) -> 0 | K16: =IF(Rent!K16=0,0,('Tenant Charges'!$J12)) -> 0 | L16: =IF(Rent!L16=0,0,('Tenant Charges'!$J12)) -> 0 | ... P16: =IF(Rent!P16=0,0,('Tenant Charges'!$J12)) -> 0 | Q16: =SUM(E16:P16) -> 0 | R16: =Q16/C16 -> 0
A17: =Rent!A17 -> Vacant | B17: =Rent!B17 -> 100B | C17: =Rent!C17 -> 618 | D17: =C17/$C$25 -> 0.04954305 | E17: =IF(Rent!E17=0,0,('Tenant Charges'!$J13)) -> 0 | F17: =IF(Rent!F17=0,0,('Tenant Charges'!$J13)) -> 0 | G17: =IF(Rent!G17=0,0,('Tenant Charges'!$J13)) -> 0 | H17: =IF(Rent!H17=0,0,('Tenant Charges'!$J13)) -> 0 | I17: =IF(Rent!I17=0,0,('Tenant Charges'!$J13)) -> 23.202249 | J17: =IF(Rent!J17=0,0,('Tenant Charges'!$J13)) -> 23.202249 | K17: =IF(Rent!K17=0,0,('Tenant Charges'!$J13)) -> 23.202249 | L17: =IF(Rent!L17=0,0,('Tenant Charges'!$J13)) -> 23.202249 | ... P17: =IF(Rent!P17=0,0,('Tenant Charges'!$J13)) -> 23.202249 | Q17: =SUM(E17:P17) -> 185.61799 | R17: =Q17/C17 -> 0.30035273
A18: =Rent!A18 -> Vacant | B18: =Rent!B18 -> 101B/102B | C18: =Rent!C18 -> 4230 | D18: =C18/$C$25 -> 0.33910534 | E18: =IF(Rent!E18=0,0,('Tenant Charges'!$J14)) -> 0 | F18: =IF(Rent!F18=0,0,('Tenant Charges'!$J14)) -> 0 | G18: =IF(Rent!G18=0,0,('Tenant Charges'!$J14)) -> 0 | H18: =IF(Rent!H18=0,0,('Tenant Charges'!$J14)) -> 0 | I18: =IF(Rent!I18=0,0,('Tenant Charges'!$J14)) -> 158.81151 | J18: =IF(Rent!J18=0,0,('Tenant Charges'!$J14)) -> 158.81151 | K18: =IF(Rent!K18=0,0,('Tenant Charges'!$J14)) -> 158.81151 | L18: =IF(Rent!L18=0,0,('Tenant Charges'!$J14)) -> 158.81151 | ... P18: =IF(Rent!P18=0,0,('Tenant Charges'!$J14)) -> 158.81151 | Q18: =SUM(E18:P18) -> 1270.4921 | R18: =Q18/C18 -> 0.30035273
A25: TOTALS | C25: =SUM(C14:C24) -> 12474 | D25: =SUM(D14:D24) -> 1 | E25: =SUM(E14:E24) -> 0 | F25: =SUM(F14:F24) -> 0 | G25: =SUM(G14:G24) -> 0 | H25: =SUM(H14:H24) -> 0 | I25: =SUM(I14:I24) -> 182.01376 | J25: =SUM(J14:J24) -> 182.01376 | ... Q25: =SUM(Q14:Q24) -> 1456.1101
O27: TOTAL INS | Q27: =Summary!O80 -> 5619.9
O28: RECAPTURE | Q28: =Q25/Q27 -> 0.25909893
D30: NMK Tie-out | E30: =E25-Summary!C18 -> 0 | F30: =F25-Summary!D18 -> 0 | G30: =G25-Summary!E18 -> 0 | H30: =H25-Summary!F18 -> 0 | I30: =I25-Summary!G18 -> 0 | J30: =J25-Summary!H18 -> 0 | K30: =K25-Summary!I18 -> 0 | L30: =L25-Summary!J18 -> 0 | ... Q30: =Q25-Summary!O18 -> 0

Sheet Signage
P1: =Summary!T4 -> Date Revised: | Q1: =Summary!U4 -> 46235 | R1: =Summary!V4 -> 0
A2: =Summary!$A2 -> ATHENA PROPERTY MANAGEMENT
A3: =Summary!$A3 -> BELL MEDICAL
A4: =Summary!$A4 -> PROJECT NO. 802
A5: =Summary!$A5 -> 01/01/26-12/31/26
A6: =Summary!$A6 -> 2026 OPERATING BUDGET
A9: TENANT | B9: SUITE | C9: SQUARE | D9: PRORATA | E9: JAN | F9: FEB | G9: MARCH | H9: APRIL | I9: MAY | J9: JUNE | K9: JULY | L9: AUGUST | M9: SEPT | N9: OCT | O9: NOV | P9: DEC | Q9: TOTALS
B10: # | C10: FOOTAGE | D10: SHARE | R10: Cost PSF
A12: RE Tax
A15: =Rent!A15 -> Occupational Medicine for Business & Industry | B15: =Rent!B15 -> 100A | C15: =Rent!C15 -> 5659 | D15: =C15/$C$21 -> 0.45366362 | E15: 329.91 | F15: =E15 -> 329.91 | G15: =F15 -> 329.91 | H15: =G15 -> 329.91 | I15: =H15 -> 329.91 | J15: =I15 -> 329.91 | K15: =J15 -> 329.91 | L15: =K15 -> 329.91 | M15: =L15 -> 329.91 | ... P15: =O15 -> 329.91 | Q15: =SUM(E15:P15) -> 3958.92 | R15: =Q15/C15 -> 0.69957943
A16: =Rent!A16 -> Arizona Sports & Spine Physicians | B16: =Rent!B16 -> 101A | C16: =Rent!C16 -> 1967 | D16: =C16/$C$21 -> 0.15768799 | E16: 119.82 | F16: =E16 -> 119.82 | G16: =F16 -> 119.82 | H16: =G16 -> 119.82 | I16: =H16 -> 119.82 | J16: =I16 -> 119.82 | K16: =J16 -> 119.82 | L16: =K16 -> 119.82 | M16: =L16 -> 119.82 | ... P16: =O16 -> 119.82 | Q16: =SUM(E16:P16) -> 1437.84 | R16: =Q16/C16 -> 0.73098119
A17: =Rent!A17 -> Vacant | B17: =Rent!B17 -> 100B | C17: =Rent!C17 -> 618 | D17: =C17/$C$21 -> 0.04954305 | E17: 0 | F17: =E17 -> 0 | G17: =F17 -> 0 | H17: =G17 -> 0 | I17: =H17 -> 0 | J17: =I17 -> 0 | K17: =J17 -> 0 | L17: =K17 -> 0 | M17: =L17 -> 0 | ... P17: =O17 -> 0 | Q17: =SUM(E17:P17) -> 0 | R17: =Q17/C17 -> 0
A18: =Rent!A18 -> Vacant | B18: =Rent!B18 -> 101B/102B | C18: =Rent!C18 -> 4230 | D18: =C18/$C$21 -> 0.33910534 | E18: 0 | F18: =E18 -> 0 | G18: =F18 -> 0 | H18: =G18 -> 0 | I18: =H18 -> 0 | J18: =I18 -> 0 | K18: =J18 -> 0 | L18: =K18 -> 0 | M18: =L18 -> 0 | ... P18: =O18 -> 0 | Q18: =SUM(E18:P18) -> 0 | R18: =Q18/C18 -> 0
A21: TOTALS | C21: =SUM(C14:C20) -> 12474 | D21: =SUM(D14:D20) -> 1 | E21: =SUM(E14:E20) -> 449.73 | F21: =SUM(F14:F20) -> 449.73 | G21: =SUM(G14:G20) -> 449.73 | H21: =SUM(H14:H20) -> 449.73 | I21: =SUM(I14:I20) -> 449.73 | J21: =SUM(J14:J20) -> 449.73 | ... Q21: =SUM(Q14:Q20) -> 5396.76
O23: TOTAL RE Tax | Q23: =Summary!O85 -> 34927.63
O24: RECAPTURE | Q24: =Q21/Q23 -> 0.15451263
D26: NMK Tie-out | E26: =E21-Summary!C21 -> 0 | F26: =F21-Summary!D21 -> 0 | G26: =G21-Summary!E21 -> 0 | H26: =H21-Summary!F21 -> 0 | I26: =I21-Summary!G21 -> 0 | J26: =J21-Summary!H21 -> 0 | K26: =K21-Summary!I21 -> 0 | L26: =L21-Summary!J21 -> 0 | ... Q26: =Q21-Summary!O21 -> 0

Sheet Occup,
O1: =Summary!T4 -> Date Revised: | P1: =Summary!U4 -> 46235 | Q1: =Summary!V4 -> 0
A2: =Summary!$A2 -> ATHENA PROPERTY MANAGEMENT
A3: =Summary!$A3 -> BELL MEDICAL
A4: =Summary!$A4 -> PROJECT NO. 802
A5: =Summary!$A5 -> 01/01/26-12/31/26
A6: =Summary!$A6 -> 2026 OPERATING BUDGET
A9: TENANT | B9: SUITE | C9: SQUARE | D9: JAN | E9: FEB | F9: MARCH | G9: APRIL | H9: MAY | I9: JUNE | J9: JULY | K9: AUGUST | L9: SEPT | M9: OCT | N9: NOV | O9: DEC | P9: TOTALS
B10: # | C10: FOOTAGE
A12: ESTIMATED MONTHLY SQUARE FOOTAGE OCCUPIED
A15: =Rent!A15 -> Occupational Medicine for Business & Industry | B15: =Rent!B15 -> 100A | C15: =Rent!C15 -> 5659 | D15: =IF(Rent!E15=0,0,($C15)) -> 5659 | E15: =IF(Rent!F15=0,0,($C15)) -> 5659 | F15: =IF(Rent!G15=0,0,($C15)) -> 5659 | G15: =IF(Rent!H15=0,0,($C15)) -> 5659 | H15: =IF(Rent!I15=0,0,($C15)) -> 5659 | I15: =IF(Rent!J15=0,0,($C15)) -> 5659 | J15: =IF(Rent!K15=0,0,($C15)) -> 5659 | K15: =IF(Rent!L15=0,0,($C15)) -> 5659 | ... O15: =IF(Rent!P15=0,0,($C15)) -> 5659 | P15: =(SUM(D15:O15)/12)/C15 -> 1
A16: =Rent!A16 -> Arizona Sports & Spine Physicians | B16: =Rent!B16 -> 101A | C16: =Rent!C16 -> 1967 | D16: =IF(Rent!E16=0,0,($C16)) -> 1967 | E16: =IF(Rent!F16=0,0,($C16)) -> 1967 | F16: =IF(Rent!G16=0,0,($C16)) -> 1967 | G16: =IF(Rent!H16=0,0,($C16)) -> 1967 | H16: =IF(Rent!I16=0,0,($C16)) -> 1967 | I16: =IF(Rent!J16=0,0,($C16)) -> 1967 | J16: =IF(Rent!K16=0,0,($C16)) -> 1967 | K16: =IF(Rent!L16=0,0,($C16)) -> 1967 | ... O16: =IF(Rent!P16=0,0,($C16)) -> 1967 | P16: =(SUM(D16:O16)/12)/C16 -> 1
A17: =Rent!A17 -> Vacant | B17: =Rent!B17 -> 100B | C17: =Rent!C17 -> 618 | D17: =IF(Rent!E17=0,0,($C17)) -> 0 | E17: =IF(Rent!F17=0,0,($C17)) -> 0 | F17: =IF(Rent!G17=0,0,($C17)) -> 0 | G17: =IF(Rent!H17=0,0,($C17)) -> 0 | H17: =IF(Rent!I17=0,0,($C17)) -> 618 | I17: =IF(Rent!J17=0,0,($C17)) -> 618 | J17: =IF(Rent!K17=0,0,($C17)) -> 618 | K17: =IF(Rent!L17=0,0,($C17)) -> 618 | ... O17: =IF(Rent!P17=0,0,($C17)) -> 618 | P17: =(SUM(D17:O17)/12)/C17 -> 0.66666667
A18: =Rent!A18 -> Vacant | B18: =Rent!B18 -> 101B/102B | C18: =Rent!C18 -> 4230 | D18: =IF(Rent!E18=0,0,($C18)) -> 0 | E18: =IF(Rent!F18=0,0,($C18)) -> 0 | F18: =IF(Rent!G18=0,0,($C18)) -> 0 | G18: =IF(Rent!H18=0,0,($C18)) -> 0 | H18: =IF(Rent!I18=0,0,($C18)) -> 4230 | I18: =IF(Rent!J18=0,0,($C18)) -> 4230 | J18: =IF(Rent!K18=0,0,($C18)) -> 4230 | K18: =IF(Rent!L18=0,0,($C18)) -> 4230 | ... O18: =IF(Rent!P18=0,0,($C18)) -> 4230 | P18: =(SUM(D18:O18)/12)/C18 -> 0.66666667
A21: TOTALS | C21: =SUM(C14:C20) -> 12474 | D21: =SUM(D14:D20) -> 7626 | E21: =SUM(E14:E20) -> 7626 | F21: =SUM(F14:F20) -> 7626 | G21: =SUM(G14:G20) -> 7626 | H21: =SUM(H14:H20) -> 12474 | I21: =SUM(I14:I20) -> 12474 | J21: =SUM(J14:J20) -> 12474 | ... O21: =SUM(O14:O20) -> 12474
D22: =D21/$C$21 -> 0.61135161 | E22: =E21/$C$21 -> 0.61135161 | F22: =F21/$C$21 -> 0.61135161 | G22: =G21/$C$21 -> 0.61135161 | H22: =H21/$C$21 -> 1 | I22: =I21/$C$21 -> 1 | J22: =J21/$C$21 -> 1 | K22: =K21/$C$21 -> 1 | ... O22: =O21/$C$21 -> 1
A24: Occupied Square Footage | C24: =C15+C16 -> 7626
A26: Gross Up Percentage | C26: =C21/C24 -> 1.6357199
A28: 95% Occupancy | C28: =C26*0.95 -> 1.5539339

Sheet Sales Tax
A2: ATHENA PROPERTY MANAGEMENT
A3: =Summary!A3 -> BELL MEDICAL
A4: =Summary!A4 -> PROJECT NO. 802
A5: =Summary!A5 -> 01/01/26-12/31/26
A6: =Summary!A6 -> 2026 OPERATING BUDGET
Q8: YEARLY TOTAL
A9: TENANT | B9: SUITE | C9: SQUARE | D9: RATE | E9: JAN | F9: FEB | G9: MARCH | H9: APRIL | I9: MAY | J9: JUNE | K9: JULY | L9: AUGUST | M9: SEPT | N9: OCT | O9: NOV | P9: DEC | R9: ANN | S9: MON
B10: # | C10: FOOTAGE
A11: Rental Sales Tax | D11: =0.5%+2.5% -> 0.03
A14: =Rent!A15 -> Occupational Medicine for Business & Industry | B14: =Rent!B15 -> 100A | C14: =Rent!C15 -> 5659 | Q14: =SUM(E14:P14) -> 0
B15: Total Monthly Charges | E15: =IF(Rent!E15=0,0,(Rent!E15+(SUM('Tenant Charges'!$F11:$K11)))) -> 14210.384 | F15: =IF(Rent!F15=0,0,(Rent!F15+(SUM('Tenant Charges'!$F11:$K11)))) -> 14210.384 | G15: =IF(Rent!G15=0,0,(Rent!G15+(SUM('Tenant Charges'!$F11:$K11)))) -> 14210.384 | H15: =IF(Rent!H15=0,0,(Rent!H15+(SUM('Tenant Charges'!$F11:$K11)))) -> 14608.464 | I15: =IF(Rent!I15=0,0,(Rent!I15+(SUM('Tenant Charges'!$F11:$K11)))) -> 14608.464 | J15: =IF(Rent!J15=0,0,(Rent!J15+(SUM('Tenant Charges'!$F11:$K11)))) -> 14608.464 | K15: =IF(Rent!K15=0,0,(Rent!K15+(SUM('Tenant Charges'!$F11:$K11)))) -> 14608.464 | L15: =IF(Rent!L15=0,0,(Rent!L15+(SUM('Tenant Charges'!$F11:$K11)))) -> 14608.464 | ... P15: =IF(Rent!P15=0,0,(Rent!P15+(SUM('Tenant Charges'!$F11:$K11)))) -> 14608.464 | Q15: =SUM(E15:P15) -> 174107.33
B16: Sales Tax | D16: =$D$11 -> 0.03 | E16: =E15*$D$16 -> 426.31151 | F16: =F15*$D$16 -> 426.31151 | G16: =G15*$D$16 -> 426.31151 | H16: =H15*$D$16 -> 438.25391 | I16: =I15*$D$16 -> 438.25391 | J16: =J15*$D$16 -> 438.25391 | K16: =K15*$D$16 -> 438.25391 | L16: =L15*$D$16 -> 438.25391 | ... P16: =P15*$D$16 -> 438.25391 | Q16: =SUM(E16:P16) -> 5223.2198
C17: Total | E17: =SUM(E16:E16) -> 426.31151 | F17: =SUM(F16:F16) -> 426.31151 | G17: =SUM(G16:G16) -> 426.31151 | H17: =SUM(H16:H16) -> 438.25391 | I17: =SUM(I16:I16) -> 438.25391 | J17: =SUM(J16:J16) -> 438.25391 | K17: =SUM(K16:K16) -> 438.25391 | L17: =SUM(L16:L16) -> 438.25391 | ... P17: =SUM(P16:P16) -> 438.25391 | Q17: =Q16 -> 5223.2198
A19: =Rent!A16 -> Arizona Sports & Spine Physicians | B19: =Rent!B16 -> 101A | C19: =Rent!C16 -> 1967 | Q19: =SUM(E19:P19) -> 0
B20: Total Monthly Charges | E20: =IF(Rent!E16=0,0,(Rent!E16+(SUM('Tenant Charges'!$F12:$K12)))) -> 4751.2467 | F20: =IF(Rent!F16=0,0,(Rent!F16+(SUM('Tenant Charges'!$F12:$K12)))) -> 4751.2467 | G20: =IF(Rent!G16=0,0,(Rent!G16+(SUM('Tenant Charges'!$F12:$K12)))) -> 4818.8235 | H20: =IF(Rent!H16=0,0,(Rent!H16+(SUM('Tenant Charges'!$F12:$K12)))) -> 4882.1767 | I20: =IF(Rent!I16=0,0,(Rent!I16+(SUM('Tenant Charges'!$F12:$K12)))) -> 4882.1767 | J20: =IF(Rent!J16=0,0,(Rent!J16+(SUM('Tenant Charges'!$F12:$K12)))) -> 4882.1767 | K20: =IF(Rent!K16=0,0,(Rent!K16+(SUM('Tenant Charges'!$F12:$K12)))) -> 4882.1767 | L20: =IF(Rent!L16=0,0,(Rent!L16+(SUM('Tenant Charges'!$F12:$K12)))) -> 4882.1767 | ... P20: =IF(Rent!P16=0,0,(Rent!P16+(SUM('Tenant Charges'!$F12:$K12)))) -> 4882.1767 | Q20: =SUM(E20:P20) -> 58260.907
B21: Sales Tax | D21: =$D$11 -> 0.03 | E21: =E20*$D$21 -> 142.5374 | F21: =F20*$D$21 -> 142.5374 | G21: =G20*$D$21 -> 144.5647 | H21: =H20*$D$21 -> 146.4653 | I21: =I20*$D$21 -> 146.4653 | J21: =J20*$D$21 -> 146.4653 | K21: =K20*$D$21 -> 146.4653 | L21: =L20*$D$21 -> 146.4653 | ... P21: =P20*$D$21 -> 146.4653 | Q21: =SUM(E21:P21) -> 1747.8272
C22: Total | E22: =E21 -> 142.5374 | F22: =F21 -> 142.5374 | G22: =G21 -> 144.5647 | H22: =H21 -> 146.4653 | I22: =I21 -> 146.4653 | J22: =J21 -> 146.4653 | K22: =K21 -> 146.4653 | L22: =L21 -> 146.4653 | ... P22: =P21 -> 146.4653 | Q22: =SUM(E22:P22) -> 1747.8272
A24: =Rent!A17 -> Vacant | B24: =Rent!B17 -> 100B | C24: =Rent!C17 -> 618 | Q24: =SUM(E24:P24) -> 0
B25: Total Monthly Charges | E25: =IF(Rent!E17=0,0,(Rent!E17+(SUM('Tenant Charges'!$F13:$K13)))) -> 0 | F25: =IF(Rent!F17=0,0,(Rent!F17+(SUM('Tenant Charges'!$F13:$K13)))) -> 0 | G25: =IF(Rent!G17=0,0,(Rent!G17+(SUM('Tenant Charges'!$F13:$K13)))) -> 0 | H25: =IF(Rent!H17=0,0,(Rent!H17+(SUM('Tenant Charges'!$F13:$K13)))) -> 0 | I25: =IF(Rent!I17=0,0,(Rent!I17+(SUM('Tenant Charges'!$F13:$K13)))) -> 1909.1882 | J25: =IF(Rent!J17=0,0,(Rent!J17+(SUM('Tenant Charges'!$F13:$K13)))) -> 1909.1882 | K25: =IF(Rent!K17=0,0,(Rent!K17+(SUM('Tenant Charges'!$F13:$K13)))) -> 1909.1882 | L25: =IF(Rent!L17=0,0,(Rent!L17+(SUM('Tenant Charges'!$F13:$K13)))) -> 1909.1882 | ... P25: =IF(Rent!P17=0,0,(Rent!P17+(SUM('Tenant Charges'!$F13:$K13)))) -> 1909.1882 | Q25: =SUM(E25:P25) -> 15273.505
B26: Sales Tax | D26: =$D$11 -> 0.03 | E26: =E25*$D$16 -> 0 | F26: =F25*$D$16 -> 0 | G26: =G25*$D$16 -> 0 | H26: =H25*$D$16 -> 0 | I26: =I25*$D$16 -> 57.275646 | J26: =J25*$D$16 -> 57.275646 | K26: =K25*$D$16 -> 57.275646 | L26: =L25*$D$16 -> 57.275646 | ... P26: =P25*$D$16 -> 57.275646 | Q26: =SUM(E26:P26) -> 458.20516
C27: Total | E27: =SUM(E26:E26) -> 0 | F27: =SUM(F26:F26) -> 0 | G27: =SUM(G26:G26) -> 0 | H27: =SUM(H26:H26) -> 0 | I27: =SUM(I26:I26) -> 57.275646 | J27: =SUM(J26:J26) -> 57.275646 | K27: =SUM(K26:K26) -> 57.275646 | L27: =SUM(L26:L26) -> 57.275646 | ... P27: =SUM(P26:P26) -> 57.275646 | Q27: =Q26 -> 458.20516
A29: =Rent!A18 -> Vacant | B29: =Rent!B18 -> 101B/102B | C29: =Rent!C18 -> 4230 | Q29: =SUM(E29:P29) -> 0
B30: Total Monthly Charges | E30: =IF(Rent!E18=0,0,(Rent!E18+(SUM('Tenant Charges'!$F14:$K14)))) -> 0 | F30: =IF(Rent!F18=0,0,(Rent!F18+(SUM('Tenant Charges'!$F14:$K14)))) -> 0 | G30: =IF(Rent!G18=0,0,(Rent!G18+(SUM('Tenant Charges'!$F14:$K14)))) -> 0 | H30: =IF(Rent!H18=0,0,(Rent!H18+(SUM('Tenant Charges'!$F14:$K14)))) -> 0 | I30: =IF(Rent!I18=0,0,(Rent!I18+(SUM('Tenant Charges'!$F14:$K14)))) -> 13067.744 | J30: =IF(Rent!J18=0,0,(Rent!J18+(SUM('Tenant Charges'!$F14:$K14)))) -> 13067.744 | K30: =IF(Rent!K18=0,0,(Rent!K18+(SUM('Tenant Charges'!$F14:$K14)))) -> 13067.744 | L30: =IF(Rent!L18=0,0,(Rent!L18+(SUM('Tenant Charges'!$F14:$K14)))) -> 13067.744 | ... P30: =IF(Rent!P18=0,0,(Rent!P18+(SUM('Tenant Charges'!$F14:$K14)))) -> 13067.744 | Q30: =SUM(E30:P30) -> 104541.96
B31: Sales Tax | D31: =$D$11 -> 0.03 | E31: =E30*$D$21 -> 0 | F31: =F30*$D$21 -> 0 | G31: =G30*$D$21 -> 0 | H31: =H30*$D$21 -> 0 | I31: =I30*$D$21 -> 392.03233 | J31: =J30*$D$21 -> 392.03233 | K31: =K30*$D$21 -> 392.03233 | L31: =L30*$D$21 -> 392.03233 | ... P31: =P30*$D$21 -> 392.03233 | Q31: =SUM(E31:P31) -> 3136.2587
C32: Total | E32: =E31 -> 0 | F32: =F31 -> 0 | G32: =G31 -> 0 | H32: =H31 -> 0 | I32: =I31 -> 392.03233 | J32: =J31 -> 392.03233 | K32: =K31 -> 392.03233 | L32: =L31 -> 392.03233 | ... P32: =P31 -> 392.03233 | Q32: =SUM(E32:P32) -> 3136.2587
A35: Grand Total | E35: =E17+E22+E27+E32 -> 568.84891 | F35: =F17+F22+F27+F32 -> 568.84891 | G35: =G17+G22+G27+G32 -> 570.87622 | H35: =H17+H22+H27+H32 -> 584.71921 | I35: =I17+I22+I27+I32 -> 1034.0272 | J35: =J17+J22+J27+J32 -> 1034.0272 | K35: =K17+K22+K27+K32 -> 1034.0272 | L35: =L17+L22+L27+L32 -> 1034.0272 | ... Q35: =Q17+Q22+Q27+Q32 -> 10565.511 | T35: See Rent Tab - Matches Total
D37: NMK Tie-out | E37: =E35-Summary!C15 -> 0 | F37: =F35-Summary!D15 -> 0 | G37: =G35-Summary!E15 -> 0 | H37: =H35-Summary!F15 -> 0 | I37: =I35-Summary!G15 -> 0 | J37: =J35-Summary!H15 -> 0 | K37: =K35-Summary!I15 -> 0 | L37: =L35-Summary!J15 -> 0 | ... Q37: =Q35-Summary!O15 -> 0

Sheet Tenant Charges
P1: =Summary!T4 -> Date Revised: | Q1: =Summary!U4 -> 46235
A2: =Summary!A2 -> ATHENA PROPERTY MANAGEMENT
A3: =Summary!A3 -> BELL MEDICAL
A4: =Summary!A4 -> PROJECT NO. 802
A5: =Summary!A5 -> 01/01/26-12/31/26
A6: =Summary!A6 -> 2026 OPERATING BUDGET
B8: TENANT | C8: LEASE ID | D8: SF | E8: RENT | F8: CAM | G8: BUILDING EXPENSES (NCA) | H8: ADMIN | I8: RE TAX | J8: INSUR | K8: SIGNAGE | L8: SALES TAX | M8: TOTAL | N8: TOTAL OTHER CHARGES (2026) | O8: CURRENT 2025 BILLINGS | P8: VARIANCE | Q8: 2025 NNN PSF
B11: =Rent!A15 -> Occupational Medicine for Business & Industry | C11: 011986 | D11: =Rent!C15 -> 5659 | E11: =Rent!E15 -> 13269.28 | F11: ='CAM TENANTS'!L70/12 -> 611.19378 | G11: 0 | H11: ='CAM TENANTS'!M67/12 -> 0 | I11: 0 | J11: 0 | K11: =Signage!E15 -> 329.91 | L11: ='Sales Tax'!E16 -> 426.31151 | M11: =SUM(E11:L11) -> 14636.695 | N11: =SUM(F11:K11) -> 941.10378 | O11: 62.74 | P11: =N11-O11 -> 878.36378 | Q11: =N11/D11 -> 0.16630213
B12: =Rent!A16 -> Arizona Sports & Spine Physicians | C12: 011987 | D12: =Rent!C16 -> 1967 | E12: =Rent!E16 -> 4374.81 | F12: ='CAM TENANTS'!W70/12 -> 256.61671 | G12: 0 | H12: ='CAM TENANTS'!V67/12 -> 0 | I12: 0 | J12: 0 | K12: =Signage!E16 -> 119.82 | L12: ='Sales Tax'!E21 -> 142.5374 | M12: =SUM(E12:L12) -> 4893.7841 | N12: =SUM(F12:K12) -> 376.43671 | O12: 254.27 | P12: =N12-O12 -> 122.16671 | Q12: =N12/D12 -> 0.19137606
B13: =Rent!A17 -> Vacant | D13: =Rent!C17 -> 618 | E13: =Rent!E17 -> 0 | F13: ='CAM TENANTS'!AD40/12 -> 269.86053 | G13: ='CAM TENANTS'!AD52/12 -> 254.46363 | H13: ='CAM TENANTS'!AE75/12 -> 0 | I13: ='CAM TENANTS'!AD65/12 -> 144.20178 | J13: ='CAM TENANTS'!AD60/12 -> 23.202249 | K13: =Signage!E17 -> 0 | L13: ='Sales Tax'!Q27/8 -> 57.275646 | M13: =SUM(E13:L13) -> 749.00383 | N13: =SUM(F13:K13) -> 691.72819 | O13: 0 | P13: =N13-O13 -> 691.72819 | Q13: =N13/D13 -> 1.1193013 | R13: DO NOT BILL - FOR LEASING ASSUMPTIONS ONLY
B14: =Rent!A18 -> Vacant | D14: =Rent!C18 -> 4230 | E14: =Rent!E18 -> 0 | F14: ='CAM TENANTS'!AM40/12 -> 1847.1036 | G14: ='CAM TENANTS'!AM52/12 -> 1741.7171 | H14: ='CAM TENANTS'!AN75/12 -> 0 | I14: ='CAM TENANTS'!AM65/12 -> 987.01215 | J14: ='CAM TENANTS'!AM60/12 -> 158.81151 | K14: =Signage!E18 -> 0 | L14: ='Sales Tax'!Q32/8 -> 392.03233 | M14: =SUM(E14:L14) -> 5126.6767 | N14: =SUM(F14:K14) -> 4734.6444 | O14: 0 | P14: =N14-O14 -> 4734.6444 | Q14: =N14/D14 -> 1.1193013 | R14: DO NOT BILL - FOR LEASING ASSUMPTIONS ONLY
D16: =SUM(D11:D15) -> 12474 | E16: =SUM(E11:E15) -> 17644.09 | F16: =SUM(F11:F15) -> 2984.7746 | G16: =SUM(G11:G15) -> 1996.1807 | H16: =SUM(H11:H15) -> 0 | I16: =SUM(I11:I15) -> 1131.2139 | J16: =SUM(J11:J15) -> 182.01376 | K16: =SUM(K11:K15) -> 449.73 | ... Q16: =SUM(Q11:Q15) -> 2.5962807
E17: =SUM(E10:E12) -> 17644.09 | F17: =SUM(F10:F12) -> 867.81048 | G17: =SUM(G10:G12) -> 0 | H17: =SUM(H10:H12) -> 0 | I17: =SUM(I10:I12) -> 0 | J17: =SUM(J10:J12) -> 0 | M17: =SUM(M10:M12) -> 19530.479 | N17: =SUM(N10:N16) -> 13487.826
B18: APPROVALS:
D19: NMK Tie-out | E19: =E16-Rent!E23 -> 0 | F19: =F16-CAM!E25 -> 2116.9642 | G19: =G16-'Building Expenses'!E26 -> 1996.1807 | H19: =H16-'Admin Fee'!E26 -> 0 | I19: =I16-'RE Tax'!E24 -> 1131.2139 | J19: =J16-Ins.!E25 -> 182.01376 | K19: =K16-Signage!E21 -> 0 | L19: =L16-'Sales Tax'!E35 -> 449.30798
B22: Janina Silva
B25: Date
B29: Accounting

Sheet Slippage
I1: =Summary!T4 -> Date Revised: | J1: =Summary!U4 -> 46235 | K1: =Summary!V4 -> 0
A2: =Summary!A2 -> ATHENA PROPERTY MANAGEMENT
A3: =Summary!$A3 -> BELL MEDICAL
A4: =Summary!A4 -> PROJECT NO. 802
A5: =Summary!A5 -> 01/01/26-12/31/26
A6: =Summary!A6 -> 2026 OPERATING BUDGET
A7: EXPENSES | B7: ANNUAL TOTAL | D7: =Rent!$A14 -> 0 | E7: =Rent!$A15 -> Occupational Medicine for Business & Industry | F7: =Rent!A16 -> Arizona Sports & Spine Physicians | G7: =Rent!A17 -> Vacant | H7: =Rent!A18 -> Vacant | I7: TOTAL RECOVERY | J7: VARIANCE | K7: % DIFFERENCE
A9: =Summary!B29 -> COMMON AREA EXPENSES
A11: ='CAM TENANTS'!B15 -> Landscape- Tree Trimming | B11: ='CAM TENANTS'!C15 -> 4000 | D11: ='CAM TENANTS'!#REF! -> #REF! | E11: ='CAM TENANTS'!L15 -> 2819.8531 | F11: ='CAM TENANTS'!U15 -> 630.75196 | I11: =SUM(D11:F11) -> #REF! | J11: =I11-B11 -> #REF! | K11: =J11/B11 -> #REF!
A12: ='CAM TENANTS'!B16 -> Sprinkler Repairs | B12: ='CAM TENANTS'!C16 -> 150 | D12: ='CAM TENANTS'!#REF! -> #REF! | E12: ='CAM TENANTS'!L16 -> 105.74449 | F12: ='CAM TENANTS'!U16 -> 23.653199 | I12: =SUM(D12:F12) -> #REF! | J12: =I12-B12 -> #REF! | K12: =J12/B12 -> #REF!
A13: ='CAM TENANTS'!B17 -> Landscape Maintenance | B13: ='CAM TENANTS'!C17 -> 8112 | D13: ='CAM TENANTS'!#REF! -> #REF! | E13: ='CAM TENANTS'!L17 -> 5718.6622 | F13: ='CAM TENANTS'!U17 -> 1279.165 | I13: =SUM(D13:F13) -> #REF! | J13: =I13-B13 -> #REF! | K13: =J13/B13 -> #REF!
A14: ='CAM TENANTS'!B18 -> Parking Lot Light Maintenance | B14: ='CAM TENANTS'!C18 -> 75 | D14: ='CAM TENANTS'!#REF! -> #REF! | E14: ='CAM TENANTS'!L18 -> 52.872246 | F14: ='CAM TENANTS'!U18 -> 11.826599 | I14: =SUM(D14:F14) -> #REF! | J14: =I14-B14 -> #REF! | K14: =J14/B14 -> #REF!
A15: ='CAM TENANTS'!B19 -> Parking Lot Repairs | B15: ='CAM TENANTS'!C19 -> 0 | D15: ='CAM TENANTS'!#REF! -> #REF! | E15: ='CAM TENANTS'!L19 -> 0 | F15: ='CAM TENANTS'!U19 -> 0 | I15: =SUM(D15:F15) -> #REF! | J15: =I15-B15 -> #REF! | K15: =IFERROR(J15/B15,0) -> 0
A16: ='CAM TENANTS'!B20 -> Parking Lot Light Repairs | B16: ='CAM TENANTS'!C20 -> 900 | D16: ='CAM TENANTS'!#REF! -> #REF! | E16: ='CAM TENANTS'!L20 -> 634.46696 | F16: ='CAM TENANTS'!U20 -> 141.91919 | I16: =SUM(D16:F16) -> #REF! | J16: =I16-B16 -> #REF! | K16: =J16/B16 -> #REF!
A17: ='CAM TENANTS'!B21 -> General Maintenance | B17: ='CAM TENANTS'!C21 -> 1100 | D17: ='CAM TENANTS'!#REF! -> #REF! | E17: ='CAM TENANTS'!L21 -> 775.45961 | F17: ='CAM TENANTS'!U21 -> 173.45679 | I17: =SUM(D17:F17) -> #REF! | J17: =I17-B17 -> #REF! | K17: =J17/B17 -> #REF!
A18: ='CAM TENANTS'!B22 -> Janitorial | B18: ='CAM TENANTS'!C22 -> 7800 | D18: ='CAM TENANTS'!#REF! -> #REF! | E18: ='CAM TENANTS'!L22 -> 5498.7136 | F18: ='CAM TENANTS'!U22 -> 1229.9663 | I18: =SUM(D18:F18) -> #REF! | J18: =I18-B18 -> #REF! | K18: =J18/B18 -> #REF!
A19: ='CAM TENANTS'!B23 -> Janitorial Supplies | B19: ='CAM TENANTS'!C23 -> 300 | D19: ='CAM TENANTS'!#REF! -> #REF! | E19: ='CAM TENANTS'!L23 -> 211.48899 | F19: ='CAM TENANTS'!U23 -> 47.306397 | I19: =SUM(D19:F19) -> #REF! | J19: =I19-B19 -> #REF! | K19: =J19/B19 -> #REF!
A20: ='CAM TENANTS'!B24 -> Pest Control | B20: ='CAM TENANTS'!C24 -> 1416 | D20: ='CAM TENANTS'!#REF! -> #REF! | E20: ='CAM TENANTS'!L24 -> 998.22801 | F20: ='CAM TENANTS'!U24 -> 223.2862 | I20: =SUM(D20:F20) -> #REF! | J20: =I20-B20 -> #REF! | K20: =J20/B20 -> #REF!
A21: ='CAM TENANTS'!B25 -> Security | B21: ='CAM TENANTS'!C25 -> 9180 | D21: ='CAM TENANTS'!#REF! -> #REF! | E21: ='CAM TENANTS'!L25 -> 6471.5629 | F21: ='CAM TENANTS'!U25 -> 1447.5758 | I21: =SUM(D21:F21) -> #REF! | J21: =I21-B21 -> #REF! | K21: =J21/B21 -> #REF!
A22: ='CAM TENANTS'!B26 -> Management Fee | B22: ='CAM TENANTS'!C26 -> 18000 | D22: ='CAM TENANTS'!#REF! -> #REF! | E22: ='CAM TENANTS'!L26 -> 12689.339 | F22: ='CAM TENANTS'!U26 -> 2838.3838 | I22: =SUM(D22:F22) -> #REF! | J22: =I22-B22 -> #REF! | K22: =J22/B22 -> #REF!
A23: ='CAM TENANTS'!B27 -> Sidewalk Maintenance | B23: ='CAM TENANTS'!C27 -> 3500 | D23: ='CAM TENANTS'!#REF! -> #REF! | E23: ='CAM TENANTS'!L27 -> 2467.3715 | F23: ='CAM TENANTS'!U27 -> 551.90797 | I23: =SUM(D23:F23) -> #REF! | J23: =I23-B23 -> #REF! | K23: =IFERROR(J23/B23,0) -> 0
A24: ='CAM TENANTS'!B28 -> Sign Maintenance | B24: ='CAM TENANTS'!C28 -> 250 | D24: ='CAM TENANTS'!#REF! -> #REF! | E24: ='CAM TENANTS'!L28 -> 176.24082 | F24: ='CAM TENANTS'!U28 -> 39.421998 | I24: =SUM(D24:F24) -> #REF! | J24: =I24-B24 -> #REF! | K24: =J24/B24 -> #REF!
A25: ='CAM TENANTS'!B29 -> Sweeping | B25: ='CAM TENANTS'!C29 -> 1500 | D25: ='CAM TENANTS'!#REF! -> #REF! | E25: ='CAM TENANTS'!L29 -> 1057.4449 | F25: ='CAM TENANTS'!U29 -> 236.53199 | I25: =SUM(D25:F25) -> #REF! | J25: =I25-B25 -> #REF! | K25: =J25/B25 -> #REF!
A26: ='CAM TENANTS'!B30 -> Electrical Repairs/CAM | B26: ='CAM TENANTS'!C30 -> 0 | D26: ='CAM TENANTS'!#REF! -> #REF! | E26: ='CAM TENANTS'!L30 -> 0 | F26: ='CAM TENANTS'!U30 -> 0 | I26: =SUM(D26:F26) -> #REF! | J26: =I26-B26 -> #REF! | K26: =IFERROR(J26/B26,0) -> 0
A27: ='CAM TENANTS'!B31 -> Plumbing Repairs | B27: ='CAM TENANTS'!C31 -> 450 | D27: ='CAM TENANTS'!#REF! -> #REF! | E27: ='CAM TENANTS'!L31 -> 317.23348 | F27: ='CAM TENANTS'!U31 -> 70.959596 | I27: =SUM(D27:F27) -> #REF! | J27: =I27-B27 -> #REF! | K27: =J27/B27 -> #REF!
A28: ='CAM TENANTS'!B32 -> Building Maint & Repairs (window washing) | B28: ='CAM TENANTS'!C32 -> 560 | D28: ='CAM TENANTS'!#REF! -> #REF! | E28: ='CAM TENANTS'!L32 -> 394.77944 | F28: ='CAM TENANTS'!U32 -> 88.305275 | I28: =SUM(D28:F28) -> #REF! | J28: =I28-B28 -> #REF! | K28: =J28/B28 -> #REF!
A29: ='CAM TENANTS'!B33 -> Trash Removal | B29: ='CAM TENANTS'!C33 -> 4200 | D29: ='CAM TENANTS'!#REF! -> #REF! | E29: ='CAM TENANTS'!L33 -> 4843.1144 | F29: ='CAM TENANTS'!U33 -> 1083.3202 | I29: =SUM(D29:F29) -> #REF! | J29: =I29-B29 -> #REF! | K29: =J29/B29 -> #REF!
A30: ='CAM TENANTS'!B34 -> HVAC Maintenance | B30: ='CAM TENANTS'!C34 -> 1340 | D30: ='CAM TENANTS'!#REF! -> #REF! | E30: ='CAM TENANTS'!L34 -> 1545.1841 | F30: ='CAM TENANTS'!U34 -> 345.63074 | I30: =SUM(D30:F30) -> #REF! | J30: =I30-B30 -> #REF! | K30: =J30/B30 -> #REF!
A31: ='CAM TENANTS'!B35 -> HVAC Repairs | B31: ='CAM TENANTS'!C35 -> 0 | D31: ='CAM TENANTS'!#REF! -> #REF! | E31: ='CAM TENANTS'!L35 -> 0 | F31: ='CAM TENANTS'!U35 -> 0 | I31: =SUM(D31:F31) -> #REF! | J31: =I31-B31 -> #REF! | K31: =IFERROR(J31/B31,0) -> 0
A32: ='CAM TENANTS'!B36 -> Water/Common Area | B32: ='CAM TENANTS'!C36 -> 0 | D32: ='CAM TENANTS'!#REF! -> #REF! | E32: ='CAM TENANTS'!L36 -> 0 | F32: ='CAM TENANTS'!U36 -> 0 | I32: =SUM(D32:F32) -> #REF! | J32: =I32-B32 -> #REF! | K32: =J32/B32 -> #REF!
A33: ='CAM TENANTS'!B37 -> Restroom Remodel-AMORTIZATION | B33: ='CAM TENANTS'!C37 -> 0 | D33: ='CAM TENANTS'!#REF! -> #REF! | E33: ='CAM TENANTS'!L37 -> 0 | F33: ='CAM TENANTS'!U37 -> 0 | I33: =SUM(D33:F33) -> #REF! | J33: =I33-B33 -> #REF! | K33: =J33/B33 -> #REF!
A34: ='CAM TENANTS'!B38 -> Painting-AMORTIZATION | B34: ='CAM TENANTS'!C38 -> 2509 | D34: ='CAM TENANTS'!#REF! -> #REF! | E34: ='CAM TENANTS'!L38 -> 1138.242 | F34: ='CAM TENANTS'!U38 -> 395.63917 | I34: =SUM(D34:F34) -> #REF! | J34: =I34-B34 -> #REF! | K34: =J34/B34 -> #REF!
A36: =Summary!B59 -> SUBTOTAL COMMON AREA | B36: =SUM(B11:B35) -> 65342 | D36: =SUM(D11:D35) -> #REF! | E36: =SUM(E11:E35) -> 47916.002 | F36: =SUM(F11:F35) -> 10859.008 | I36: =SUM(D36:F36) -> #REF! | J36: =I36-B36 -> #REF! | K36: =J36/B36 -> #REF!
A38: =Summary!B61 -> BUILDING EXPENSE
A39: =Summary!B62 -> Roof Maintenance | B39: =Summary!O62 -> 1500 | D39: ='CAM TENANTS'!#REF! -> #REF! | E39: ='CAM TENANTS'!L43 -> 1057.4449 | F39: ='CAM TENANTS'!U43 -> 236.53199 | I39: =SUM(D39:F39) -> #REF! | J39: =I39-B39 -> #REF! | K39: =IFERROR(J39/B39,0) -> 0
A40: =Summary!B63 -> Roof Repairs | B40: =Summary!O63 -> 1500 | D40: ='CAM TENANTS'!#REF! -> #REF! | E40: ='CAM TENANTS'!L44 -> 1057.4449 | F40: ='CAM TENANTS'!U44 -> 236.53199 | I40: =SUM(D40:F40) -> #REF! | J40: =I40-B40 -> #REF! | K40: =J40/B40 -> #REF!
A41: =Summary!B64 -> Monitor Fire Sprinklers | B41: =Summary!O64 -> 0 | D41: ='CAM TENANTS'!#REF! -> #REF! | E41: ='CAM TENANTS'!L45 -> 0 | F41: ='CAM TENANTS'!U45 -> 0 | I41: =SUM(D41:F41) -> #REF! | J41: =I41-B41 -> #REF! | K41: 0
A42: =Summary!B66 -> Locks & Keys | B42: =Summary!O66 -> 0 | D42: ='CAM TENANTS'!#REF! -> #REF! | E42: ='CAM TENANTS'!L46 -> 0 | F42: ='CAM TENANTS'!U46 -> 0 | I42: =SUM(D42:F42) -> #REF! | J42: =I42-B42 -> #REF! | K42: 0
A43: =Summary!B67 -> Backflow Maintenance | B43: =Summary!O67 -> 55 | D43: ='CAM TENANTS'!#REF! -> #REF! | E43: ='CAM TENANTS'!L47 -> 38.772981 | F43: ='CAM TENANTS'!U47 -> 8.6728395 | I43: =SUM(D43:F43) -> #REF! | J43: =I43-B43 -> #REF! | K43: =J43/B43 -> #REF!
A44: =Summary!B68 -> Backflow Repairs | B44: =Summary!O68 -> 150 | D44: ='CAM TENANTS'!#REF! -> #REF! | E44: ='CAM TENANTS'!L48 -> 105.74449 | F44: ='CAM TENANTS'!U48 -> 23.653199 | I44: =SUM(D44:F44) -> #REF! | J44: =I44-B44 -> #REF! | K44: =IFERROR(J44/B44,0) -> 0
A45: =Summary!B69 -> Electricity/Building | B45: =Summary!O69 -> 27720 | D45: ='CAM TENANTS'!#REF! -> #REF! | E45: ='CAM TENANTS'!L49 -> 31964.555 | F45: ='CAM TENANTS'!U49 -> 4371.1111 | I45: =SUM(D45:F45) -> #REF! | J45: =I45-B45 -> #REF! | K45: =J45/B45 -> #REF!
A46: =Summary!B70 -> Water/Building | B46: =Summary!O70 -> 8001 | D46: ='CAM TENANTS'!#REF! -> #REF! | E46: ='CAM TENANTS'!L50 -> 9226.1329 | F46: ='CAM TENANTS'!U50 -> 1261.6616 | I46: =SUM(D46:F46) -> #REF! | J46: =I46-B46 -> #REF! | K46: =J46/B46 -> #REF!
A47: CAM CAP SLIPPAGE | D47: ='CAM TENANTS'!#REF! -> #REF!
A48: =Summary!B72 -> SUBTOTAL BUILDING EXP. | B48: =SUM(B39:B47) -> 38926 | D48: =SUM(D39:D47) -> #REF! | E48: =SUM(E39:E47) -> 43450.095 | F48: =SUM(F39:F47) -> 6138.1627 | I48: =SUM(D48:F48) -> #REF! | J48: =I48-B48 -> #REF! | K48: =J48/B48 -> #REF!
A50: =Summary!B74 -> INSURANCE
A51: =Summary!B75 -> Insurance - Property | B51: =Summary!O75 -> 5619.9 | D51: ='CAM TENANTS'!#REF! -> #REF! | E51: ='CAM TENANTS'!L55 -> 3961.8232 | F51: ='CAM TENANTS'!U55 -> 886.19074 | I51: =SUM(D51:F51) -> #REF! | J51: =I51-B51 -> #REF! | K51: =J51/B51 -> #REF!
A52: =Summary!B76 -> Insurance - Liability | B52: =Summary!O76 -> 0 | D52: ='CAM TENANTS'!#REF! -> #REF! | E52: ='CAM TENANTS'!L56 -> 0 | F52: ='CAM TENANTS'!U56 -> 0 | I52: =SUM(D52:F52) -> #REF! | J52: =I52-B52 -> #REF! | K52: =IFERROR(J52/B52,0) -> 0
A53: =Summary!B77 -> Insurance - Umbrella | B53: =Summary!O77 -> 0 | D53: ='CAM TENANTS'!#REF! -> #REF! | E53: ='CAM TENANTS'!L57 -> 0 | F53: ='CAM TENANTS'!U57 -> 0 | I53: =SUM(D53:F53) -> #REF! | J53: =I53-B53 -> #REF! | K53: =IFERROR(J53/B53,0) -> 0
A54: =Summary!B78 -> Insurance - Flood & Earthquake | B54: =Summary!O78 -> 0 | D54: ='CAM TENANTS'!#REF! -> #REF! | E54: ='CAM TENANTS'!L58 -> 0 | F54: ='CAM TENANTS'!U58 -> 0 | I54: =SUM(D54:F54) -> #REF! | J54: =I54-B54 -> #REF! | K54: 0
A56: =Summary!B80 -> SUBTOTAL INSURANCE | B56: =SUM(B51:B54) -> 5619.9 | D56: =SUM(D51:D54) -> #REF! | E56: =SUM(E51:E54) -> 3961.8232 | F56: =SUM(F51:F54) -> 886.19074 | I56: =SUM(D56:F56) -> #REF! | J56: =I56-B56 -> #REF! | K56: =J56/B56 -> #REF!
A58: =Summary!B82 -> PROPERTY TAXES
A59: =Summary!B83 -> Property Tax | B59: =Summary!O83 -> 34927.63 | D59: ='CAM TENANTS'!#REF! -> #REF! | E59: ='CAM TENANTS'!L63 -> 24622.697 | F59: ='CAM TENANTS'!U63 -> 5507.6678 | I59: =SUM(D59:F59) -> #REF! | J59: =I59-B59 -> #REF! | K59: =J59/B59 -> #REF!
A61: =Summary!B85 -> SUBTOTAL TAXES | B61: =B59 -> 34927.63 | D61: =SUM(D59) -> #REF! | E61: =SUM(E59) -> 24622.697 | F61: =SUM(F59) -> 5507.6678 | I61: =SUM(D61:F61) -> #REF! | J61: =I61-B61 -> #REF! | K61: =J61/B61 -> #REF!
A63: =Summary!B89 -> TOTAL COMMON AREA | B63: =B36+B56+B61+B48 -> 144815.53 | D63: =D36+D56+D48+D61 -> #REF! | E63: =E36+E56+E48+E61 -> 119950.62 | F63: =F36+F56+F48+F61 -> 23391.029 | I63: =SUM(D63:F63) -> #REF! | J63: =I63-B63 -> #REF! | K63: =J63/B63 -> #REF!
A65: ADMIN FEES | B65: =Summary!O20 -> 0 | D65: ='CAM TENANTS'!#REF! -> #REF! | E65: ='CAM TENANTS'!M67 -> 0 | F65: ='CAM TENANTS'!V67 -> 0 | I65: =SUM(D65:F65) -> #REF! | J65: =I65-B65 -> #REF! | K65: =IFERROR(J65/B65,0) -> 0
A67: GRAND TOTAL
B68: =B63+B65 -> 144815.53 | D68: =D63+D65 -> #REF! | E68: =E63+E65 -> 119950.62 | F68: =F63+F65 -> 23391.029 | I68: =SUM(D68:F68) -> #REF! | J68: =I68-B68 -> #REF! | K68: =J68/B68 -> #REF!
A71: NMK - SUMM 2026 Budget Total (CAM, BUILDING EXP, TAX & Ins) | B71: =Summary!O59+Summary!O72+Summary!O80+Summary!O85 -> 146515.53
A72: NMK Tie-Out | B72: =B68-B71 -> -1700
A74: NMK - Total Due from TENANT CHARGES | E74: ='Tenant Charges'!N11*12 -> 11293.245 | F74: ='Tenant Charges'!N12*12 -> 4517.2405
A75: NMK Tie-Out | E75: =E68-E74 -> 108657.37 | F75: =F68-F74 -> 18873.789

Sheet CAM TENANTS
M1: =Summary!T4 -> Date Revised: | N1: =Summary!U4 -> 46235 | V1: DATE: | W1: =NOW() -> 46235.073 | AE1: DATE: | AF1: =NOW() -> 46235.073 | AN1: DATE: | AO1: =NOW() -> 46235.073
F2: =Summary!$A$3 -> BELL MEDICAL | O2: =Summary!$A$3 -> BELL MEDICAL | X2: =Summary!$A$3 -> BELL MEDICAL | AG2: =Summary!$A$3 -> BELL MEDICAL
F3: =Summary!$A$5 -> 01/01/26-12/31/26 | O3: =Summary!$A$5 -> 01/01/26-12/31/26 | X3: =Summary!$A$5 -> 01/01/26-12/31/26 | AG3: =Summary!$A$5 -> 01/01/26-12/31/26
F4: =Summary!$A$6 -> 2026 OPERATING BUDGET | O4: =Summary!$A$6 -> 2026 OPERATING BUDGET | X4: =Summary!$A$6 -> 2026 OPERATING BUDGET | AG4: =Summary!$A$6 -> 2026 OPERATING BUDGET
G6: Tenant: | H6: =Rent!A15 -> Occupational Medicine for Business & Industry | P6: Tenant: | Q6: =Rent!A16 -> Arizona Sports & Spine Physicians | Y6: Tenant: | Z6: =Rent!A17 -> Vacant | AH6: Tenant: | AI6: =Rent!A18 -> Vacant
G7: Unit Number: | H7: =Rent!B15 -> 100A | P7: Unit Number: | Q7: =Rent!B16 -> 101A | Y7: Unit Number: | Z7: =Rent!B17 -> 100B | AH7: Unit Number: | AI7: =Rent!B18 -> 101B/102B
G8: Square Footage: | H8: =Rent!C15 -> 5659 | P8: Square Footage: | Q8: =Rent!C16 -> 1967 | Y8: Square Footage: | Z8: =Rent!C17 -> 618 | AH8: Square Footage: | AI8: =Rent!C18 -> 4230
M10: Adm. | V10: Adm. | AE10: Adm. | AN10: Adm.
H11: Center | I11: GROSS UP | J11: Billable | K11: Tenant | L11: Billable | M11: Fee | N11: Total | Q11: Center | R11: Less | S11: Billable | T11: Tenant | U11: Billable | V11: Fee | W11: Total | Z11: Center | AA11: Less | AB11: Billable | AC11: Tenant | AD11: Billable | AE11: Fee | AF11: Total | AI11: Center | AJ11: Less | AK11: Billable | AL11: Tenant | AM11: Billable | AN11: Fee | AO11: Total
F12: G.L. Code | G12: Description | H12: Total | I12: 0.95 | J12: Amount | K12: Pro-Rata | L12: Amount | M12: ='Admin Fee'!D15 -> 0 | N12: Due | O12: G.L. Code | P12: Description | Q12: Total | R12: Exclusions | S12: Amount | T12: Pro-Rata | U12: Amount | V12: ='Admin Fee'!D16 -> 0 | W12: Due | X12: G.L. Code | Y12: Description | Z12: Total | AA12: Exclusions | AB12: Amount | AC12: Pro-Rata | AD12: Amount | AE12: ='Admin Fee'!M16 -> 0 | AF12: Due | AG12: G.L. Code | AH12: Description | AI12: Total | AJ12: Exclusions | AK12: Amount | AL12: Pro-Rata | AM12: Amount | AN12: ='Admin Fee'!V16 -> 0 | AO12: Due
B14: =Summary!B29 -> COMMON AREA EXPENSES | D14: Denominator | G14: ='CAM TENANTS'!$B$14 -> COMMON AREA EXPENSES | P14: ='CAM TENANTS'!$B$14 -> COMMON AREA EXPENSES | Y14: ='CAM TENANTS'!$B$14 -> COMMON AREA EXPENSES | AH14: ='CAM TENANTS'!$B$14 -> COMMON AREA EXPENSES
A15: =Summary!A31 -> 50150 | B15: =Summary!B31 -> Landscape- Tree Trimming | C15: =Summary!O31 -> 4000 | D15: =Rent!C$23 -> 12474 | F15: =Summary!A31 -> 50150 | G15: ='CAM TENANTS'!B15 -> Landscape- Tree Trimming | H15: ='CAM TENANTS'!C15 -> 4000 | I15: =H15*'Occup,'!$C$28 -> 6215.7356 | J15: =IF(I15=0,H15,I15) -> 6215.7356 | K15: =$H$8/'CAM TENANTS'!D15 -> 0.45366362 | L15: =J15*K15 -> 2819.8531 | M15: =L15*$M$12 -> 0 | N15: =L15+M15 -> 2819.8531 | O15: ='CAM TENANTS'!A15 -> 50150 | P15: ='CAM TENANTS'!B15 -> Landscape- Tree Trimming | Q15: ='CAM TENANTS'!C15 -> 4000 | R15: 0 | S15: =Q15+R15 -> 4000 | T15: =$Q$8/'CAM TENANTS'!D15 -> 0.15768799 | U15: =S15*T15 -> 630.75196 | V15: =U15*$V$12 -> 0 | W15: =U15+V15 -> 630.75196 | X15: ='CAM TENANTS'!A15 -> 50150 | Y15: ='CAM TENANTS'!B15 -> Landscape- Tree Trimming | Z15: ='CAM TENANTS'!C15 -> 4000 | AA15: 0 | AB15: =Z15+AA15 -> 4000 | AC15: =$Z$8/'CAM TENANTS'!D15 -> 0.04954305 | AD15: =AB15*AC15 -> 198.1722 | AE15: =AD15*$V$12 -> 0 | AF15: =AD15+AE15 -> 198.1722 | AG15: ='CAM TENANTS'!A15 -> 50150 | AH15: ='CAM TENANTS'!B15 -> Landscape- Tree Trimming | AI15: ='CAM TENANTS'!C15 -> 4000 | AJ15: 0 | AK15: =AI15+AJ15 -> 4000 | AL15: =$AI$8/'CAM TENANTS'!D15 -> 0.33910534 | AM15: =AK15*AL15 -> 1356.4214 | AN15: =AM15*$V$12 -> 0 | AO15: =AM15+AN15 -> 1356.4214
A16: =Summary!A33 -> 50190 | B16: =Summary!B33 -> Sprinkler Repairs | C16: =Summary!O33 -> 150 | D16: =Rent!C$23 -> 12474 | F16: =Summary!A33 -> 50190 | G16: ='CAM TENANTS'!B16 -> Sprinkler Repairs | H16: ='CAM TENANTS'!C16 -> 150 | I16: =H16*'Occup,'!$C$28 -> 233.09009 | J16: =IF(I16=0,H16,I16) -> 233.09009 | K16: =$H$8/'CAM TENANTS'!D16 -> 0.45366362 | L16: =J16*K16 -> 105.74449 | M16: =L16*$M$12 -> 0 | N16: =L16+M16 -> 105.74449 | O16: ='CAM TENANTS'!A16 -> 50190 | P16: ='CAM TENANTS'!B16 -> Sprinkler Repairs | Q16: ='CAM TENANTS'!C16 -> 150 | R16: 0 | S16: =Q16+R16 -> 150 | T16: =$Q$8/'CAM TENANTS'!D16 -> 0.15768799 | U16: =S16*T16 -> 23.653199 | V16: =U16*$V$12 -> 0 | W16: =U16+V16 -> 23.653199 | X16: ='CAM TENANTS'!A16 -> 50190 | Y16: ='CAM TENANTS'!B16 -> Sprinkler Repairs | Z16: ='CAM TENANTS'!C16 -> 150 | AA16: 0 | AB16: =Z16+AA16 -> 150 | AC16: =$Z$8/'CAM TENANTS'!D16 -> 0.04954305 | AD16: =AB16*AC16 -> 7.4314574 | AE16: =AD16*$V$12 -> 0 | AF16: =AD16+AE16 -> 7.4314574 | AG16: ='CAM TENANTS'!A16 -> 50190 | AH16: ='CAM TENANTS'!B16 -> Sprinkler Repairs | AI16: ='CAM TENANTS'!C16 -> 150 | AJ16: 0 | AK16: =AI16+AJ16 -> 150 | AL16: =$AI$8/'CAM TENANTS'!D16 -> 0.33910534 | AM16: =AK16*AL16 -> 50.865801 | AN16: =AM16*$V$12 -> 0 | AO16: =AM16+AN16 -> 50.865801
A17: =Summary!A34 -> 50170 | B17: =Summary!B34 -> Landscape Maintenance | C17: =Summary!O34 -> 8112 | D17: =Rent!C$23 -> 12474 | F17: ='CAM TENANTS'!A17 -> 50170 | G17: ='CAM TENANTS'!B17 -> Landscape Maintenance | H17: ='CAM TENANTS'!C17 -> 8112 | I17: =H17*'Occup,'!$C$28 -> 12605.512 | J17: =IF(I17=0,H17,I17) -> 12605.512 | K17: =$H$8/'CAM TENANTS'!D17 -> 0.45366362 | L17: =J17*K17 -> 5718.6622 | M17: =L17*$M$12 -> 0 | N17: =L17+M17 -> 5718.6622 | O17: ='CAM TENANTS'!A17 -> 50170 | P17: ='CAM TENANTS'!B17 -> Landscape Maintenance | Q17: ='CAM TENANTS'!C17 -> 8112 | R17: 0 | S17: =Q17+R17 -> 8112 | T17: =$Q$8/'CAM TENANTS'!D17 -> 0.15768799 | U17: =S17*T17 -> 1279.165 | V17: =U17*$V$12 -> 0 | W17: =U17+V17 -> 1279.165 | X17: ='CAM TENANTS'!A17 -> 50170 | Y17: ='CAM TENANTS'!B17 -> Landscape Maintenance | Z17: ='CAM TENANTS'!C17 -> 8112 | AA17: 0 | AB17: =Z17+AA17 -> 8112 | AC17: =$Z$8/'CAM TENANTS'!D17 -> 0.04954305 | AD17: =AB17*AC17 -> 401.89322 | AE17: =AD17*$V$12 -> 0 | AF17: =AD17+AE17 -> 401.89322 | AG17: ='CAM TENANTS'!A17 -> 50170 | AH17: ='CAM TENANTS'!B17 -> Landscape Maintenance | AI17: ='CAM TENANTS'!C17 -> 8112 | AJ17: 0 | AK17: =AI17+AJ17 -> 8112 | AL17: =$AI$8/'CAM TENANTS'!D17 -> 0.33910534 | AM17: =AK17*AL17 -> 2750.8225 | AN17: =AM17*$V$12 -> 0 | AO17: =AM17+AN17 -> 2750.8225
A18: =Summary!A35 -> 50510 | B18: =Summary!B35 -> Parking Lot Light Maintenance | C18: =Summary!O35 -> 75 | D18: =Rent!C$23 -> 12474 | F18: ='CAM TENANTS'!A18 -> 50510 | G18: ='CAM TENANTS'!B18 -> Parking Lot Light Maintenance | H18: ='CAM TENANTS'!C18 -> 75 | I18: =H18*'Occup,'!$C$28 -> 116.54504 | J18: =IF(I18=0,H18,I18) -> 116.54504 | K18: =$H$8/'CAM TENANTS'!D18 -> 0.45366362 | L18: =J18*K18 -> 52.872246 | M18: =L18*$M$12 -> 0 | N18: =L18+M18 -> 52.872246 | O18: ='CAM TENANTS'!A18 -> 50510 | P18: ='CAM TENANTS'!B18 -> Parking Lot Light Maintenance | Q18: ='CAM TENANTS'!C18 -> 75 | R18: 0 | S18: =Q18+R18 -> 75 | T18: =$Q$8/'CAM TENANTS'!D18 -> 0.15768799 | U18: =S18*T18 -> 11.826599 | V18: =U18*$V$12 -> 0 | W18: =U18+V18 -> 11.826599 | X18: ='CAM TENANTS'!A18 -> 50510 | Y18: ='CAM TENANTS'!B18 -> Parking Lot Light Maintenance | Z18: ='CAM TENANTS'!C18 -> 75 | AA18: 0 | AB18: =Z18+AA18 -> 75 | AC18: =$Z$8/'CAM TENANTS'!D18 -> 0.04954305 | AD18: =AB18*AC18 -> 3.7157287 | AE18: =AD18*$V$12 -> 0 | AF18: =AD18+AE18 -> 3.7157287 | AG18: ='CAM TENANTS'!A18 -> 50510 | AH18: ='CAM TENANTS'!B18 -> Parking Lot Light Maintenance | AI18: ='CAM TENANTS'!C18 -> 75 | AJ18: 0 | AK18: =AI18+AJ18 -> 75 | AL18: =$AI$8/'CAM TENANTS'!D18 -> 0.33910534 | AM18: =AK18*AL18 -> 25.4329 | AN18: =AM18*$V$12 -> 0 | AO18: =AM18+AN18 -> 25.4329
A19: =Summary!A36 -> 50540 | B19: =Summary!B36 -> Parking Lot Repairs | C19: =Summary!O36 -> 0 | D19: =Rent!C$23 -> 12474 | F19: ='CAM TENANTS'!A19 -> 50540 | G19: ='CAM TENANTS'!B19 -> Parking Lot Repairs | H19: ='CAM TENANTS'!C19 -> 0 | I19: =H19*'Occup,'!$C$28 -> 0 | J19: =IF(I19=0,H19,I19) -> 0 | K19: =$H$8/'CAM TENANTS'!D19 -> 0.45366362 | L19: =J19*K19 -> 0 | M19: =L19*$M$12 -> 0 | N19: =L19+M19 -> 0 | O19: ='CAM TENANTS'!A19 -> 50540 | P19: ='CAM TENANTS'!B19 -> Parking Lot Repairs | Q19: ='CAM TENANTS'!C19 -> 0 | R19: 0 | S19: =Q19+R19 -> 0 | T19: =$Q$8/'CAM TENANTS'!D19 -> 0.15768799 | U19: =S19*T19 -> 0 | V19: =U19*$V$12 -> 0 | W19: =U19+V19 -> 0 | X19: ='CAM TENANTS'!A19 -> 50540 | Y19: ='CAM TENANTS'!B19 -> Parking Lot Repairs | Z19: ='CAM TENANTS'!C19 -> 0 | AA19: 0 | AB19: =Z19+AA19 -> 0 | AC19: =$Z$8/'CAM TENANTS'!D19 -> 0.04954305 | AD19: =AB19*AC19 -> 0 | AE19: =AD19*$V$12 -> 0 | AF19: =AD19+AE19 -> 0 | AG19: ='CAM TENANTS'!A19 -> 50540 | AH19: ='CAM TENANTS'!B19 -> Parking Lot Repairs | AI19: ='CAM TENANTS'!C19 -> 0 | AJ19: 0 | AK19: =AI19+AJ19 -> 0 | AL19: =$AI$8/'CAM TENANTS'!D19 -> 0.33910534 | AM19: =AK19*AL19 -> 0 | AN19: =AM19*$V$12 -> 0 | AO19: =AM19+AN19 -> 0
A20: =Summary!A38 -> 50530 | B20: =Summary!B38 -> Parking Lot Light Repairs | C20: =Summary!O38 -> 900 | D20: =Rent!C$23 -> 12474 | F20: ='CAM TENANTS'!A20 -> 50530 | G20: ='CAM TENANTS'!B20 -> Parking Lot Light Repairs | H20: ='CAM TENANTS'!C20 -> 900 | I20: =H20*'Occup,'!$C$28 -> 1398.5405 | J20: =IF(I20=0,H20,I20) -> 1398.5405 | K20: =$H$8/'CAM TENANTS'!D20 -> 0.45366362 | L20: =J20*K20 -> 634.46696 | M20: =L20*$M$12 -> 0 | N20: =L20+M20 -> 634.46696 | O20: ='CAM TENANTS'!A20 -> 50530 | P20: ='CAM TENANTS'!B20 -> Parking Lot Light Repairs | Q20: ='CAM TENANTS'!C20 -> 900 | R20: 0 | S20: =Q20+R20 -> 900 | T20: =$Q$8/'CAM TENANTS'!D20 -> 0.15768799 | U20: =S20*T20 -> 141.91919 | V20: =U20*$V$12 -> 0 | W20: =U20+V20 -> 141.91919 | X20: ='CAM TENANTS'!A20 -> 50530 | Y20: ='CAM TENANTS'!B20 -> Parking Lot Light Repairs | Z20: ='CAM TENANTS'!C20 -> 900 | AA20: 0 | AB20: =Z20+AA20 -> 900 | AC20: =$Z$8/'CAM TENANTS'!D20 -> 0.04954305 | AD20: =AB20*AC20 -> 44.588745 | AE20: =AD20*$V$12 -> 0 | AF20: =AD20+AE20 -> 44.588745 | AG20: ='CAM TENANTS'!A20 -> 50530 | AH20: ='CAM TENANTS'!B20 -> Parking Lot Light Repairs | AI20: ='CAM TENANTS'!C20 -> 900 | AJ20: 0 | AK20: =AI20+AJ20 -> 900 | AL20: =$AI$8/'CAM TENANTS'!D20 -> 0.33910534 | AM20: =AK20*AL20 -> 305.19481 | AN20: =AM20*$V$12 -> 0 | AO20: =AM20+AN20 -> 305.19481
A21: =Summary!A40 -> 51020 | B21: =Summary!B40 -> General Maintenance | C21: =Summary!O40 -> 1100 | D21: =Rent!C$23 -> 12474 | F21: ='CAM TENANTS'!A21 -> 51020 | G21: ='CAM TENANTS'!B21 -> General Maintenance | H21: ='CAM TENANTS'!C21 -> 1100 | I21: =H21*'Occup,'!$C$28 -> 1709.3273 | J21: =IF(I21=0,H21,I21) -> 1709.3273 | K21: =$H$8/'CAM TENANTS'!D21 -> 0.45366362 | L21: =J21*K21 -> 775.45961 | M21: =L21*$M$12 -> 0 | N21: =L21+M21 -> 775.45961 | O21: ='CAM TENANTS'!A21 -> 51020 | P21: ='CAM TENANTS'!B21 -> General Maintenance | Q21: ='CAM TENANTS'!C21 -> 1100 | R21: 0 | S21: =Q21+R21 -> 1100 | T21: =$Q$8/'CAM TENANTS'!D21 -> 0.15768799 | U21: =S21*T21 -> 173.45679 | V21: =U21*$V$12 -> 0 | W21: =U21+V21 -> 173.45679 | X21: ='CAM TENANTS'!A21 -> 51020 | Y21: ='CAM TENANTS'!B21 -> General Maintenance | Z21: ='CAM TENANTS'!C21 -> 1100 | AA21: 0 | AB21: =Z21+AA21 -> 1100 | AC21: =$Z$8/'CAM TENANTS'!D21 -> 0.04954305 | AD21: =AB21*AC21 -> 54.497354 | AE21: =AD21*$V$12 -> 0 | AF21: =AD21+AE21 -> 54.497354 | AG21: ='CAM TENANTS'!A21 -> 51020 | AH21: ='CAM TENANTS'!B21 -> General Maintenance | AI21: ='CAM TENANTS'!C21 -> 1100 | AJ21: 0 | AK21: =AI21+AJ21 -> 1100 | AL21: =$AI$8/'CAM TENANTS'!D21 -> 0.33910534 | AM21: =AK21*AL21 -> 373.01587 | AN21: =AM21*$V$12 -> 0 | AO21: =AM21+AN21 -> 373.01587
A22: =Summary!A41 -> 51040 | B22: =Summary!B41 -> Janitorial | C22: =Summary!O41 -> 7800 | D22: =Rent!C$23 -> 12474 | F22: ='CAM TENANTS'!A22 -> 51040 | G22: ='CAM TENANTS'!B22 -> Janitorial | H22: ='CAM TENANTS'!C22 -> 7800 | I22: =H22*'Occup,'!$C$28 -> 12120.685 | J22: =IF(I22=0,H22,I22) -> 12120.685 | K22: =$H$8/'CAM TENANTS'!D22 -> 0.45366362 | L22: =J22*K22 -> 5498.7136 | M22: =L22*$M$12 -> 0 | N22: =L22+M22 -> 5498.7136 | O22: ='CAM TENANTS'!A22 -> 51040 | P22: ='CAM TENANTS'!B22 -> Janitorial | Q22: ='CAM TENANTS'!C22 -> 7800 | R22: 0 | S22: =Q22+R22 -> 7800 | T22: =$Q$8/'CAM TENANTS'!D22 -> 0.15768799 | U22: =S22*T22 -> 1229.9663 | V22: =U22*$V$12 -> 0 | W22: =U22+V22 -> 1229.9663 | X22: ='CAM TENANTS'!A22 -> 51040 | Y22: ='CAM TENANTS'!B22 -> Janitorial | Z22: ='CAM TENANTS'!C22 -> 7800 | AA22: 0 | AB22: =Z22+AA22 -> 7800 | AC22: =$Z$8/'CAM TENANTS'!D22 -> 0.04954305 | AD22: =AB22*AC22 -> 386.43579 | AE22: =AD22*$V$12 -> 0 | AF22: =AD22+AE22 -> 386.43579 | AG22: ='CAM TENANTS'!A22 -> 51040 | AH22: ='CAM TENANTS'!B22 -> Janitorial | AI22: ='CAM TENANTS'!C22 -> 7800 | AJ22: 0 | AK22: =AI22+AJ22 -> 7800 | AL22: =$AI$8/'CAM TENANTS'!D22 -> 0.33910534 | AM22: =AK22*AL22 -> 2645.0216 | AN22: =AM22*$V$12 -> 0 | AO22: =AM22+AN22 -> 2645.0216
A23: =Summary!A42 -> 52010 | B23: =Summary!B42 -> Janitorial Supplies | C23: =Summary!O42 -> 300 | D23: =Rent!C$23 -> 12474 | F23: ='CAM TENANTS'!A23 -> 52010 | G23: ='CAM TENANTS'!B23 -> Janitorial Supplies | H23: ='CAM TENANTS'!C23 -> 300 | I23: =H23*'Occup,'!$C$28 -> 466.18017 | J23: =IF(I23=0,H23,I23) -> 466.18017 | K23: =$H$8/'CAM TENANTS'!D23 -> 0.45366362 | L23: =J23*K23 -> 211.48899 | M23: =L23*$M$12 -> 0 | N23: =L23+M23 -> 211.48899 | O23: ='CAM TENANTS'!A23 -> 52010 | P23: ='CAM TENANTS'!B23 -> Janitorial Supplies | Q23: ='CAM TENANTS'!C23 -> 300 | R23: 0 | S23: =Q23+R23 -> 300 | T23: =$Q$8/'CAM TENANTS'!D23 -> 0.15768799 | U23: =S23*T23 -> 47.306397 | V23: =U23*$V$12 -> 0 | W23: =U23+V23 -> 47.306397 | X23: ='CAM TENANTS'!A23 -> 52010 | Y23: ='CAM TENANTS'!B23 -> Janitorial Supplies | Z23: ='CAM TENANTS'!C23 -> 300 | AA23: 0 | AB23: =Z23+AA23 -> 300 | AC23: =$Z$8/'CAM TENANTS'!D23 -> 0.04954305 | AD23: =AB23*AC23 -> 14.862915 | AE23: =AD23*$V$12 -> 0 | AF23: =AD23+AE23 -> 14.862915 | AG23: ='CAM TENANTS'!A23 -> 52010 | AH23: ='CAM TENANTS'!B23 -> Janitorial Supplies | AI23: ='CAM TENANTS'!C23 -> 300 | AJ23: 0 | AK23: =AI23+AJ23 -> 300 | AL23: =$AI$8/'CAM TENANTS'!D23 -> 0.33910534 | AM23: =AK23*AL23 -> 101.7316 | AN23: =AM23*$V$12 -> 0 | AO23: =AM23+AN23 -> 101.7316
A24: =Summary!A43 -> 51050 | B24: =Summary!B43 -> Pest Control | C24: =Summary!O43 -> 1416 | D24: =Rent!C$23 -> 12474 | F24: ='CAM TENANTS'!A24 -> 51050 | G24: ='CAM TENANTS'!B24 -> Pest Control | H24: ='CAM TENANTS'!C24 -> 1416 | I24: =H24*'Occup,'!$C$28 -> 2200.3704 | J24: =IF(I24=0,H24,I24) -> 2200.3704 | K24: =$H$8/'CAM TENANTS'!D24 -> 0.45366362 | L24: =J24*K24 -> 998.22801 | M24: =L24*$M$12 -> 0 | N24: =L24+M24 -> 998.22801 | O24: ='CAM TENANTS'!A24 -> 51050 | P24: ='CAM TENANTS'!B24 -> Pest Control | Q24: ='CAM TENANTS'!C24 -> 1416 | R24: 0 | S24: =Q24+R24 -> 1416 | T24: =$Q$8/'CAM TENANTS'!D24 -> 0.15768799 | U24: =S24*T24 -> 223.2862 | V24: =U24*$V$12 -> 0 | W24: =U24+V24 -> 223.2862 | X24: ='CAM TENANTS'!A24 -> 51050 | Y24: ='CAM TENANTS'!B24 -> Pest Control | Z24: ='CAM TENANTS'!C24 -> 1416 | AA24: 0 | AB24: =Z24+AA24 -> 1416 | AC24: =$Z$8/'CAM TENANTS'!D24 -> 0.04954305 | AD24: =AB24*AC24 -> 70.152958 | AE24: =AD24*$V$12 -> 0 | AF24: =AD24+AE24 -> 70.152958 | AG24: ='CAM TENANTS'!A24 -> 51050 | AH24: ='CAM TENANTS'!B24 -> Pest Control | AI24: ='CAM TENANTS'!C24 -> 1416 | AJ24: 0 | AK24: =AI24+AJ24 -> 1416 | AL24: =$AI$8/'CAM TENANTS'!D24 -> 0.33910534 | AM24: =AK24*AL24 -> 480.17316 | AN24: =AM24*$V$12 -> 0 | AO24: =AM24+AN24 -> 480.17316
A25: =Summary!A44 -> 51160 | B25: =Summary!B44 -> Security | C25: =Summary!O44 -> 9180 | D25: =Rent!C$23 -> 12474 | F25: ='CAM TENANTS'!A25 -> 51160 | G25: ='CAM TENANTS'!B25 -> Security | H25: ='CAM TENANTS'!C25 -> 9180 | I25: =H25*'Occup,'!$C$28 -> 14265.113 | J25: =IF(I25=0,H25,I25) -> 14265.113 | K25: =$H$8/'CAM TENANTS'!D25 -> 0.45366362 | L25: =J25*K25 -> 6471.5629 | M25: =L25*$M$12 -> 0 | N25: =L25+M25 -> 6471.5629 | O25: ='CAM TENANTS'!A25 -> 51160 | P25: ='CAM TENANTS'!B25 -> Security | Q25: ='CAM TENANTS'!C25 -> 9180 | R25: 0 | S25: =Q25+R25 -> 9180 | T25: =$Q$8/'CAM TENANTS'!D25 -> 0.15768799 | U25: =S25*T25 -> 1447.5758 | V25: =U25*$V$12 -> 0 | W25: =U25+V25 -> 1447.5758 | X25: ='CAM TENANTS'!A25 -> 51160 | Y25: ='CAM TENANTS'!B25 -> Security | Z25: ='CAM TENANTS'!C25 -> 9180 | AA25: 0 | AB25: =Z25+AA25 -> 9180 | AC25: =$Z$8/'CAM TENANTS'!D25 -> 0.04954305 | AD25: =AB25*AC25 -> 454.80519 | AE25: =AD25*$V$12 -> 0 | AF25: =AD25+AE25 -> 454.80519 | AG25: ='CAM TENANTS'!A25 -> 51160 | AH25: ='CAM TENANTS'!B25 -> Security | AI25: ='CAM TENANTS'!C25 -> 9180 | AJ25: 0 | AK25: =AI25+AJ25 -> 9180 | AL25: =$AI$8/'CAM TENANTS'!D25 -> 0.33910534 | AM25: =AK25*AL25 -> 3112.987 | AN25: =AM25*$V$12 -> 0 | AO25: =AM25+AN25 -> 3112.987
A26: =Summary!A45 -> 51080 | B26: =Summary!B45 -> Management Fee | C26: =Summary!O45 -> 18000 | D26: =Rent!C$23 -> 12474 | F26: ='CAM TENANTS'!A26 -> 51080 | G26: ='CAM TENANTS'!B26 -> Management Fee | H26: ='CAM TENANTS'!C26 -> 18000 | I26: =H26*'Occup,'!$C$28 -> 27970.81 | J26: =IF(I26=0,H26,I26) -> 27970.81 | K26: =$H$8/'CAM TENANTS'!D26 -> 0.45366362 | L26: =J26*K26 -> 12689.339 | M26: =L26*$M$12 -> 0 | N26: =L26+M26 -> 12689.339 | O26: ='CAM TENANTS'!A26 -> 51080 | P26: ='CAM TENANTS'!B26 -> Management Fee | Q26: ='CAM TENANTS'!C26 -> 18000 | R26: 0 | S26: =Q26+R26 -> 18000 | T26: =$Q$8/'CAM TENANTS'!D26 -> 0.15768799 | U26: =S26*T26 -> 2838.3838 | V26: =U26*$V$12 -> 0 | W26: =U26+V26 -> 2838.3838 | X26: ='CAM TENANTS'!A26 -> 51080 | Y26: ='CAM TENANTS'!B26 -> Management Fee | Z26: ='CAM TENANTS'!C26 -> 18000 | AA26: 0 | AB26: =Z26+AA26 -> 18000 | AC26: =$Z$8/'CAM TENANTS'!D26 -> 0.04954305 | AD26: =AB26*AC26 -> 891.77489 | AE26: =AD26*$V$12 -> 0 | AF26: =AD26+AE26 -> 891.77489 | AG26: ='CAM TENANTS'!A26 -> 51080 | AH26: ='CAM TENANTS'!B26 -> Management Fee | AI26: ='CAM TENANTS'!C26 -> 18000 | AJ26: 0 | AK26: =AI26+AJ26 -> 18000 | AL26: =$AI$8/'CAM TENANTS'!D26 -> 0.33910534 | AM26: =AK26*AL26 -> 6103.8961 | AN26: =AM26*$V$12 -> 0 | AO26: =AM26+AN26 -> 6103.8961
A27: =Summary!A46 -> 51100 | B27: =Summary!B46 -> Sidewalk Maintenance | C27: =Summary!O46 -> 3500 | D27: =Rent!C$23 -> 12474 | F27: ='CAM TENANTS'!A27 -> 51100 | G27: ='CAM TENANTS'!B27 -> Sidewalk Maintenance | H27: ='CAM TENANTS'!C27 -> 3500 | I27: =H27*'Occup,'!$C$28 -> 5438.7687 | J27: =IF(I27=0,H27,I27) -> 5438.7687 | K27: =$H$8/'CAM TENANTS'!D27 -> 0.45366362 | L27: =J27*K27 -> 2467.3715 | M27: =L27*$M$12 -> 0 | N27: =L27+M27 -> 2467.3715 | O27: ='CAM TENANTS'!A27 -> 51100 | P27: ='CAM TENANTS'!B27 -> Sidewalk Maintenance | Q27: ='CAM TENANTS'!C27 -> 3500 | R27: 0 | S27: =Q27+R27 -> 3500 | T27: =$Q$8/'CAM TENANTS'!D27 -> 0.15768799 | U27: =S27*T27 -> 551.90797 | V27: =U27*$V$12 -> 0 | W27: =U27+V27 -> 551.90797 | X27: ='CAM TENANTS'!A27 -> 51100 | Y27: ='CAM TENANTS'!B27 -> Sidewalk Maintenance | Z27: ='CAM TENANTS'!C27 -> 3500 | AA27: =-Z27 -> -3500 | AB27: =Z27+AA27 -> 0 | AC27: =$Z$8/'CAM TENANTS'!D27 -> 0.04954305 | AD27: =AB27*AC27 -> 0 | AE27: =AD27*$V$12 -> 0 | AF27: =AD27+AE27 -> 0 | AG27: ='CAM TENANTS'!A27 -> 51100 | AH27: ='CAM TENANTS'!B27 -> Sidewalk Maintenance | AI27: ='CAM TENANTS'!C27 -> 3500 | AJ27: =-AI27 -> -3500 | AK27: =AI27+AJ27 -> 0 | AL27: =$AI$8/'CAM TENANTS'!D27 -> 0.33910534 | AM27: =AK27*AL27 -> 0 | AN27: =AM27*$V$12 -> 0 | AO27: =AM27+AN27 -> 0
A28: =Summary!A47 -> 50550 | B28: =Summary!B47 -> Sign Maintenance | C28: =Summary!O47 -> 250 | D28: =Rent!C$23 -> 12474 | F28: ='CAM TENANTS'!A28 -> 50550 | G28: ='CAM TENANTS'!B28 -> Sign Maintenance | H28: ='CAM TENANTS'!C28 -> 250 | I28: =H28*'Occup,'!$C$28 -> 388.48348 | J28: =IF(I28=0,H28,I28) -> 388.48348 | K28: =$H$8/'CAM TENANTS'!D28 -> 0.45366362 | L28: =J28*K28 -> 176.24082 | M28: =L28*$M$12 -> 0 | N28: =L28+M28 -> 176.24082 | O28: ='CAM TENANTS'!A28 -> 50550 | P28: ='CAM TENANTS'!B28 -> Sign Maintenance | Q28: ='CAM TENANTS'!C28 -> 250 | R28: 0 | S28: =Q28+R28 -> 250 | T28: =$Q$8/'CAM TENANTS'!D28 -> 0.15768799 | U28: =S28*T28 -> 39.421998 | V28: =U28*$V$12 -> 0 | W28: =U28+V28 -> 39.421998 | X28: ='CAM TENANTS'!A28 -> 50550 | Y28: ='CAM TENANTS'!B28 -> Sign Maintenance | Z28: ='CAM TENANTS'!C28 -> 250 | AA28: 0 | AB28: =Z28+AA28 -> 250 | AC28: =$Z$8/'CAM TENANTS'!D28 -> 0.04954305 | AD28: =AB28*AC28 -> 12.385762 | AE28: =AD28*$V$12 -> 0 | AF28: =AD28+AE28 -> 12.385762 | AG28: ='CAM TENANTS'!A28 -> 50550 | AH28: ='CAM TENANTS'!B28 -> Sign Maintenance | AI28: ='CAM TENANTS'!C28 -> 250 | AJ28: 0 | AK28: =AI28+AJ28 -> 250 | AL28: =$AI$8/'CAM TENANTS'!D28 -> 0.33910534 | AM28: =AK28*AL28 -> 84.776335 | AN28: =AM28*$V$12 -> 0 | AO28: =AM28+AN28 -> 84.776335
A29: =Summary!A48 -> 51150 | B29: =Summary!B48 -> Sweeping | C29: =Summary!O48 -> 1500 | D29: =Rent!C$23 -> 12474 | F29: ='CAM TENANTS'!A29 -> 51150 | G29: ='CAM TENANTS'!B29 -> Sweeping | H29: ='CAM TENANTS'!C29 -> 1500 | I29: =H29*'Occup,'!$C$28 -> 2330.9009 | J29: =IF(I29=0,H29,I29) -> 2330.9009 | K29: =$H$8/'CAM TENANTS'!D29 -> 0.45366362 | L29: =J29*K29 -> 1057.4449 | M29: =L29*$M$12 -> 0 | N29: =L29+M29 -> 1057.4449 | O29: ='CAM TENANTS'!A29 -> 51150 | P29: ='CAM TENANTS'!B29 -> Sweeping | Q29: ='CAM TENANTS'!C29 -> 1500 | R29: 0 | S29: =Q29+R29 -> 1500 | T29: =$Q$8/'CAM TENANTS'!D29 -> 0.15768799 | U29: =S29*T29 -> 236.53199 | V29: =U29*$V$12 -> 0 | W29: =U29+V29 -> 236.53199 | X29: ='CAM TENANTS'!A29 -> 51150 | Y29: ='CAM TENANTS'!B29 -> Sweeping | Z29: ='CAM TENANTS'!C29 -> 1500 | AA29: 0 | AB29: =Z29+AA29 -> 1500 | AC29: =$Z$8/'CAM TENANTS'!D29 -> 0.04954305 | AD29: =AB29*AC29 -> 74.314574 | AE29: =AD29*$V$12 -> 0 | AF29: =AD29+AE29 -> 74.314574 | AG29: ='CAM TENANTS'!A29 -> 51150 | AH29: ='CAM TENANTS'!B29 -> Sweeping | AI29: ='CAM TENANTS'!C29 -> 1500 | AJ29: 0 | AK29: =AI29+AJ29 -> 1500 | AL29: =$AI$8/'CAM TENANTS'!D29 -> 0.33910534 | AM29: =AK29*AL29 -> 508.65801 | AN29: =AM29*$V$12 -> 0 | AO29: =AM29+AN29 -> 508.65801
A30: =Summary!A49 -> 51200 | B30: =Summary!B49 -> Electrical Repairs/CAM | C30: =Summary!O49 -> 0 | D30: =Rent!C$23 -> 12474 | F30: ='CAM TENANTS'!A30 -> 51200 | G30: ='CAM TENANTS'!B30 -> Electrical Repairs/CAM | H30: ='CAM TENANTS'!C30 -> 0 | I30: =H30*'Occup,'!$C$28 -> 0 | J30: =IF(I30=0,H30,I30) -> 0 | K30: =$H$8/'CAM TENANTS'!D30 -> 0.45366362 | L30: =J30*K30 -> 0 | M30: =L30*$M$12 -> 0 | N30: =L30+M30 -> 0 | O30: ='CAM TENANTS'!A30 -> 51200 | P30: ='CAM TENANTS'!B30 -> Electrical Repairs/CAM | Q30: ='CAM TENANTS'!C30 -> 0 | R30: 0 | S30: =Q30+R30 -> 0 | T30: =$Q$8/'CAM TENANTS'!D30 -> 0.15768799 | U30: =S30*T30 -> 0 | V30: =U30*$V$12 -> 0 | W30: =U30+V30 -> 0 | X30: ='CAM TENANTS'!A30 -> 51200 | Y30: ='CAM TENANTS'!B30 -> Electrical Repairs/CAM | Z30: ='CAM TENANTS'!C30 -> 0 | AA30: 0 | AB30: =Z30+AA30 -> 0 | AC30: =$Z$8/'CAM TENANTS'!D30 -> 0.04954305 | AD30: =AB30*AC30 -> 0 | AE30: =AD30*$V$12 -> 0 | AF30: =AD30+AE30 -> 0 | AG30: ='CAM TENANTS'!A30 -> 51200 | AH30: ='CAM TENANTS'!B30 -> Electrical Repairs/CAM | AI30: ='CAM TENANTS'!C30 -> 0 | AJ30: 0 | AK30: =AI30+AJ30 -> 0 | AL30: =$AI$8/'CAM TENANTS'!D30 -> 0.33910534 | AM30: =AK30*AL30 -> 0 | AN30: =AM30*$V$12 -> 0 | AO30: =AM30+AN30 -> 0
A31: =Summary!A50 -> 51210 | B31: =Summary!B50 -> Plumbing Repairs | C31: =Summary!O50 -> 450 | D31: =Rent!C$23 -> 12474 | F31: ='CAM TENANTS'!A31 -> 51210 | G31: ='CAM TENANTS'!B31 -> Plumbing Repairs | H31: ='CAM TENANTS'!C31 -> 450 | I31: =H31*'Occup,'!$C$28 -> 699.27026 | J31: =IF(I31=0,H31,I31) -> 699.27026 | K31: =$H$8/'CAM TENANTS'!D31 -> 0.45366362 | L31: =J31*K31 -> 317.23348 | M31: =L31*$M$12 -> 0 | N31: =L31+M31 -> 317.23348 | O31: ='CAM TENANTS'!A31 -> 51210 | P31: ='CAM TENANTS'!B31 -> Plumbing Repairs | Q31: ='CAM TENANTS'!C31 -> 450 | R31: 0 | S31: =Q31+R31 -> 450 | T31: =$Q$8/'CAM TENANTS'!D31 -> 0.15768799 | U31: =S31*T31 -> 70.959596 | V31: =U31*$V$12 -> 0 | W31: =U31+V31 -> 70.959596 | X31: ='CAM TENANTS'!A31 -> 51210 | Y31: ='CAM TENANTS'!B31 -> Plumbing Repairs | Z31: ='CAM TENANTS'!C31 -> 450 | AA31: 0 | AB31: =Z31+AA31 -> 450 | AC31: =$Z$8/'CAM TENANTS'!D31 -> 0.04954305 | AD31: =AB31*AC31 -> 22.294372 | AE31: =AD31*$V$12 -> 0 | AF31: =AD31+AE31 -> 22.294372 | AG31: ='CAM TENANTS'!A31 -> 51210 | AH31: ='CAM TENANTS'!B31 -> Plumbing Repairs | AI31: ='CAM TENANTS'!C31 -> 450 | AJ31: 0 | AK31: =AI31+AJ31 -> 450 | AL31: =$AI$8/'CAM TENANTS'!D31 -> 0.33910534 | AM31: =AK31*AL31 -> 152.5974 | AN31: =AM31*$V$12 -> 0 | AO31: =AM31+AN31 -> 152.5974
A32: =Summary!A51 -> 51043 | B32: =Summary!B51 -> Building Maint & Repairs (window washing) | C32: =Summary!O51 -> 560 | D32: =Rent!C$23 -> 12474 | F32: ='CAM TENANTS'!A32 -> 51043 | G32: ='CAM TENANTS'!B32 -> Building Maint & Repairs (window washing) | H32: ='CAM TENANTS'!C32 -> 560 | I32: =H32*'Occup,'!$C$28 -> 870.20299 | J32: =IF(I32=0,H32,I32) -> 870.20299 | K32: =$H$8/'CAM TENANTS'!D32 -> 0.45366362 | L32: =J32*K32 -> 394.77944 | M32: =L32*$M$12 -> 0 | N32: =L32+M32 -> 394.77944 | O32: ='CAM TENANTS'!A32 -> 51043 | P32: ='CAM TENANTS'!B32 -> Building Maint & Repairs (window washing) | Q32: ='CAM TENANTS'!C32 -> 560 | R32: 0 | S32: =Q32+R32 -> 560 | T32: =$Q$8/'CAM TENANTS'!D32 -> 0.15768799 | U32: =S32*T32 -> 88.305275 | V32: =U32*$V$12 -> 0 | W32: =U32+V32 -> 88.305275 | X32: ='CAM TENANTS'!A32 -> 51043 | Y32: ='CAM TENANTS'!B32 -> Building Maint & Repairs (window washing) | Z32: ='CAM TENANTS'!C32 -> 560 | AA32: 0 | AB32: =Z32+AA32 -> 560 | AC32: =$Z$8/'CAM TENANTS'!D32 -> 0.04954305 | AD32: =AB32*AC32 -> 27.744108 | AE32: =AD32*$V$12 -> 0 | AF32: =AD32+AE32 -> 27.744108 | AG32: ='CAM TENANTS'!A32 -> 51043 | AH32: ='CAM TENANTS'!B32 -> Building Maint & Repairs (window washing) | AI32: ='CAM TENANTS'!C32 -> 560 | AJ32: 0 | AK32: =AI32+AJ32 -> 560 | AL32: =$AI$8/'CAM TENANTS'!D32 -> 0.33910534 | AM32: =AK32*AL32 -> 189.89899 | AN32: =AM32*$V$12 -> 0 | AO32: =AM32+AN32 -> 189.89899
A33: =Summary!A52 -> 55120 | B33: =Summary!B52 -> Trash Removal | C33: =Summary!O52 -> 4200 | D33: =Rent!$C$28 -> 7626 | F33: ='CAM TENANTS'!A33 -> 55120 | G33: ='CAM TENANTS'!B33 -> Trash Removal | H33: ='CAM TENANTS'!C33 -> 4200 | I33: =H33*'Occup,'!$C$28 -> 6526.5224 | J33: =IF(I33=0,H33,I33) -> 6526.5224 | K33: =$H$8/'CAM TENANTS'!D33 -> 0.74206661 | L33: =J33*K33 -> 4843.1144 | M33: =L33*$M$12 -> 0 | N33: =L33+M33 -> 4843.1144 | O33: ='CAM TENANTS'!A33 -> 55120 | P33: ='CAM TENANTS'!B33 -> Trash Removal | Q33: ='CAM TENANTS'!C33 -> 4200 | R33: 0 | S33: =Q33+R33 -> 4200 | T33: =$Q$8/'CAM TENANTS'!D33 -> 0.25793339 | U33: =S33*T33 -> 1083.3202 | V33: =U33*$V$12 -> 0 | W33: =U33+V33 -> 1083.3202 | X33: ='CAM TENANTS'!A33 -> 55120 | Y33: ='CAM TENANTS'!B33 -> Trash Removal | Z33: ='CAM TENANTS'!C33 -> 4200 | AA33: 0 | AB33: =Z33+AA33 -> 4200 | AC33: =$Z$8/'CAM TENANTS'!D33 -> 0.081038552 | AD33: =AB33*AC33 -> 340.36192 | AE33: =AD33*$V$12 -> 0 | AF33: =AD33+AE33 -> 340.36192 | AG33: ='CAM TENANTS'!A33 -> 55120 | AH33: ='CAM TENANTS'!B33 -> Trash Removal | AI33: ='CAM TENANTS'!C33 -> 4200 | AJ33: 0 | AK33: =AI33+AJ33 -> 4200 | AL33: =$AI$8/'CAM TENANTS'!D33 -> 0.55468135 | AM33: =AK33*AL33 -> 2329.6617 | AN33: =AM33*$V$12 -> 0 | AO33: =AM33+AN33 -> 2329.6617
A34: =Summary!A53 -> 51130 | B34: =Summary!B53 -> HVAC Maintenance | C34: =Summary!O53 -> 1340 | D34: =Rent!$C$28 -> 7626 | F34: ='CAM TENANTS'!A34 -> 51130 | G34: ='CAM TENANTS'!B34 -> HVAC Maintenance | H34: ='CAM TENANTS'!C34 -> 1340 | I34: =H34*'Occup,'!$C$28 -> 2082.2714 | J34: =IF(I34=0,H34,I34) -> 2082.2714 | K34: =$H$8/'CAM TENANTS'!D34 -> 0.74206661 | L34: =J34*K34 -> 1545.1841 | M34: =L34*$M$12 -> 0 | N34: =L34+M34 -> 1545.1841 | O34: ='CAM TENANTS'!A34 -> 51130 | P34: ='CAM TENANTS'!B34 -> HVAC Maintenance | Q34: ='CAM TENANTS'!C34 -> 1340 | R34: 0 | S34: =Q34+R34 -> 1340 | T34: =$Q$8/'CAM TENANTS'!D34 -> 0.25793339 | U34: =S34*T34 -> 345.63074 | V34: =U34*$V$12 -> 0 | W34: =U34+V34 -> 345.63074 | X34: ='CAM TENANTS'!A34 -> 51130 | Y34: ='CAM TENANTS'!B34 -> HVAC Maintenance | Z34: ='CAM TENANTS'!C34 -> 1340 | AA34: 0 | AB34: =Z34+AA34 -> 1340 | AC34: =$Z$8/'CAM TENANTS'!D34 -> 0.081038552 | AD34: =AB34*AC34 -> 108.59166 | AE34: =AD34*$V$12 -> 0 | AF34: =AD34+AE34 -> 108.59166 | AG34: ='CAM TENANTS'!A34 -> 51130 | AH34: ='CAM TENANTS'!B34 -> HVAC Maintenance | AI34: ='CAM TENANTS'!C34 -> 1340 | AJ34: 0 | AK34: =AI34+AJ34 -> 1340 | AL34: =$AI$8/'CAM TENANTS'!D34 -> 0.55468135 | AM34: =AK34*AL34 -> 743.27301 | AN34: =AM34*$V$12 -> 0 | AO34: =AM34+AN34 -> 743.27301
A35: =Summary!A54 -> 51140 | B35: =Summary!B54 -> HVAC Repairs | C35: =Summary!O54 -> 0 | D35: =Rent!$C$28 -> 7626 | F35: ='CAM TENANTS'!A35 -> 51140 | G35: ='CAM TENANTS'!B35 -> HVAC Repairs | H35: ='CAM TENANTS'!C35 -> 0 | I35: =H35*'Occup,'!$C$28 -> 0 | J35: =IF(I35=0,H35,I35) -> 0 | K35: =$H$8/'CAM TENANTS'!D35 -> 0.74206661 | L35: =J35*K35 -> 0 | M35: =L35*$M$12 -> 0 | N35: =L35+M35 -> 0 | O35: ='CAM TENANTS'!A35 -> 51140 | P35: ='CAM TENANTS'!B35 -> HVAC Repairs | Q35: ='CAM TENANTS'!C35 -> 0 | R35: 0 | S35: =Q35+R35 -> 0 | T35: =$Q$8/'CAM TENANTS'!D35 -> 0.25793339 | U35: =S35*T35 -> 0 | V35: =U35*$V$12 -> 0 | W35: =U35+V35 -> 0 | X35: ='CAM TENANTS'!A35 -> 51140 | Y35: ='CAM TENANTS'!B35 -> HVAC Repairs | Z35: ='CAM TENANTS'!C35 -> 0 | AA35: 0 | AB35: =Z35+AA35 -> 0 | AC35: =$Z$8/'CAM TENANTS'!D35 -> 0.081038552 | AD35: =AB35*AC35 -> 0 | AE35: =AD35*$V$12 -> 0 | AF35: =AD35+AE35 -> 0 | AG35: ='CAM TENANTS'!A35 -> 51140 | AH35: ='CAM TENANTS'!B35 -> HVAC Repairs | AI35: ='CAM TENANTS'!C35 -> 0 | AJ35: 0 | AK35: =AI35+AJ35 -> 0 | AL35: =$AI$8/'CAM TENANTS'!D35 -> 0.55468135 | AM35: =AK35*AL35 -> 0 | AN35: =AM35*$V$12 -> 0 | AO35: =AM35+AN35 -> 0
A36: =Summary!A55 -> 55140 | B36: =Summary!B55 -> Water/Common Area | C36: =Summary!O55 -> 0 | D36: =Rent!$C$28 -> 7626 | F36: ='CAM TENANTS'!A36 -> 55140 | G36: ='CAM TENANTS'!B36 -> Water/Common Area | H36: ='CAM TENANTS'!C36 -> 0 | I36: =H36*'Occup,'!$C$28 -> 0 | J36: =IF(I36=0,H36,I36) -> 0 | K36: =$H$8/'CAM TENANTS'!D36 -> 0.74206661 | L36: =J36*K36 -> 0 | M36: =L36*$M$12 -> 0 | N36: =L36+M36 -> 0 | O36: ='CAM TENANTS'!A36 -> 55140 | P36: ='CAM TENANTS'!B36 -> Water/Common Area | Q36: ='CAM TENANTS'!C36 -> 0 | R36: 0 | S36: =Q36+R36 -> 0 | T36: =$Q$8/'CAM TENANTS'!D36 -> 0.25793339 | U36: =S36*T36 -> 0 | V36: =U36*$V$12 -> 0 | W36: =U36+V36 -> 0 | X36: ='CAM TENANTS'!A36 -> 55140 | Y36: ='CAM TENANTS'!B36 -> Water/Common Area | Z36: ='CAM TENANTS'!C36 -> 0 | AA36: 0 | AB36: =Z36+AA36 -> 0 | AC36: =$Z$8/'CAM TENANTS'!D36 -> 0.081038552 | AD36: =AB36*AC36 -> 0 | AE36: =AD36*$V$12 -> 0 | AF36: =AD36+AE36 -> 0 | AG36: ='CAM TENANTS'!A36 -> 55140 | AH36: ='CAM TENANTS'!B36 -> Water/Common Area | AI36: ='CAM TENANTS'!C36 -> 0 | AJ36: 0 | AK36: =AI36+AJ36 -> 0 | AL36: =$AI$8/'CAM TENANTS'!D36 -> 0.55468135 | AM36: =AK36*AL36 -> 0 | AN36: =AM36*$V$12 -> 0 | AO36: =AM36+AN36 -> 0
A37: =Summary!A56 -> 51400 | B37: =Summary!B56 -> Restroom Remodel-AMORTIZATION | C37: =Summary!O56 -> 0 | D37: =Rent!$C$28 -> 7626 | F37: ='CAM TENANTS'!A37 -> 51400 | G37: ='CAM TENANTS'!B37 -> Restroom Remodel-AMORTIZATION | H37: ='CAM TENANTS'!C37 -> 0 | I37: 0 | J37: =IF(I37=0,H37,I37) -> 0 | K37: =$H$8/'CAM TENANTS'!D37 -> 0.74206661 | L37: =J37*K37 -> 0 | M37: =L37*$M$12 -> 0 | N37: =L37+M37 -> 0 | O37: ='CAM TENANTS'!A37 -> 51400 | P37: ='CAM TENANTS'!B37 -> Restroom Remodel-AMORTIZATION | Q37: ='CAM TENANTS'!C37 -> 0 | R37: 0 | S37: =Q37+R37 -> 0 | T37: =$Q$8/'CAM TENANTS'!D37 -> 0.25793339 | U37: =S37*T37 -> 0 | V37: =U37*$V$12 -> 0 | W37: =U37+V37 -> 0 | X37: ='CAM TENANTS'!A37 -> 51400 | Y37: ='CAM TENANTS'!B37 -> Restroom Remodel-AMORTIZATION | Z37: ='CAM TENANTS'!C37 -> 0 | AA37: 0 | AB37: =Z37+AA37 -> 0 | AC37: =$Z$8/'CAM TENANTS'!D37 -> 0.081038552 | AD37: =AB37*AC37 -> 0 | AE37: =AD37*$V$12 -> 0 | AF37: =AD37+AE37 -> 0 | AG37: ='CAM TENANTS'!A37 -> 51400 | AH37: ='CAM TENANTS'!B37 -> Restroom Remodel-AMORTIZATION | AI37: ='CAM TENANTS'!C37 -> 0 | AJ37: 0 | AK37: =AI37+AJ37 -> 0 | AL37: =$AI$8/'CAM TENANTS'!D37 -> 0.55468135 | AM37: =AK37*AL37 -> 0 | AN37: =AM37*$V$12 -> 0 | AO37: =AM37+AN37 -> 0
A38: =Summary!A57 -> 51220 | B38: =Summary!B57 -> Painting-AMORTIZATION | C38: =Summary!O57 -> 2509 | D38: 12474 | F38: ='CAM TENANTS'!A38 -> 51220 | G38: ='CAM TENANTS'!B38 -> Painting-AMORTIZATION | H38: ='CAM TENANTS'!C38 -> 2509 | I38: 0 | J38: =IF(I38=0,H38,I38) -> 2509 | K38: =$H$8/'CAM TENANTS'!D38 -> 0.45366362 | L38: =J38*K38 -> 1138.242 | M38: =L38*$M$12 -> 0 | N38: =L38+M38 -> 1138.242 | O38: ='CAM TENANTS'!A38 -> 51220 | P38: ='CAM TENANTS'!B38 -> Painting-AMORTIZATION | Q38: ='CAM TENANTS'!C38 -> 2509 | R38: 0 | S38: =Q38+R38 -> 2509 | T38: =$Q$8/'CAM TENANTS'!D38 -> 0.15768799 | U38: =S38*T38 -> 395.63917 | V38: =U38*$V$12 -> 0 | W38: =U38+V38 -> 395.63917 | X38: ='CAM TENANTS'!A38 -> 51220 | Y38: ='CAM TENANTS'!B38 -> Painting-AMORTIZATION | Z38: ='CAM TENANTS'!C38 -> 2509 | AA38: 0 | AB38: =Z38+AA38 -> 2509 | AC38: =$Z$8/'CAM TENANTS'!D38 -> 0.04954305 | AD38: =AB38*AC38 -> 124.30351 | AE38: =AD38*$V$12 -> 0 | AF38: =AD38+AE38 -> 124.30351 | AG38: ='CAM TENANTS'!A38 -> 51220 | AH38: ='CAM TENANTS'!B38 -> Painting-AMORTIZATION | AI38: ='CAM TENANTS'!C38 -> 2509 | AJ38: 0 | AK38: =AI38+AJ38 -> 2509 | AL38: =$AI$8/'CAM TENANTS'!D38 -> 0.33910534 | AM38: =AK38*AL38 -> 850.8153 | AN38: =AM38*$V$12 -> 0 | AO38: =AM38+AN38 -> 850.8153
G40: ='CAM TENANTS'!$B$41 -> SUBTOTAL COMMON AREA | H40: =SUM(H15:H38) -> 65342 | I40: =SUM(I15:I38) -> 97638.329 | J40: =SUM(J15:J38) -> 100147.33 | L40: =SUM(L15:L38) -> 47916.002 | M40: =SUM(M15:M38) -> 0 | N40: =SUM(N15:N38) -> 47916.002 | P40: ='CAM TENANTS'!$B$41 -> SUBTOTAL COMMON AREA | Q40: =SUM(Q15:Q38) -> 65342 | R40: =SUM(R15:R38) -> 0 | S40: =SUM(S15:S38) -> 65342 | U40: =SUM(U15:U38) -> 10859.008 | V40: =SUM(V15:V38) -> 0 | W40: =SUM(W15:W38) -> 10859.008 | Y40: ='CAM TENANTS'!$B$41 -> SUBTOTAL COMMON AREA | Z40: =SUM(Z15:Z38) -> 65342 | AA40: =SUM(AA15:AA38) -> -3500 | AB40: =SUM(AB15:AB38) -> 61842 | AD40: =SUM(AD15:AD38) -> 3238.3264 | AE40: =SUM(AE15:AE38) -> 0 | AF40: =SUM(AF15:AF38) -> 3238.3264 | AH40: ='CAM TENANTS'!$B$41 -> SUBTOTAL COMMON AREA | AI40: =SUM(AI15:AI38) -> 65342 | AJ40: =SUM(AJ15:AJ38) -> -3500 | AK40: =SUM(AK15:AK38) -> 61842 | AM40: =SUM(AM15:AM38) -> 22165.243 | AN40: =SUM(AN15:AN38) -> 0 | AO40: =SUM(AO15:AO38) -> 22165.243
B41: =Summary!B59 -> SUBTOTAL COMMON AREA | C41: =SUM(C15:C38) -> 65342
G42: ='CAM TENANTS'!$B$43 -> BUILDING EXPENSE | P42: ='CAM TENANTS'!$B$43 -> BUILDING EXPENSE | Y42: ='CAM TENANTS'!$B$43 -> BUILDING EXPENSE | AH42: ='CAM TENANTS'!$B$43 -> BUILDING EXPENSE
B43: =Summary!B61 -> BUILDING EXPENSE | F43: ='CAM TENANTS'!$A$44 -> 51060 | G43: ='CAM TENANTS'!$B$44 -> Roof Maintenance | H43: ='CAM TENANTS'!$C$44 -> 1500 | I43: =H43*'Occup,'!$C$28 -> 2330.9009 | J43: =IF(I43=0,H43,I43) -> 2330.9009 | K43: =$H$8/'CAM TENANTS'!D44 -> 0.45366362 | L43: =J43*K43 -> 1057.4449 | M43: =L43*$M$12 -> 0 | N43: =L43+M43 -> 1057.4449 | O43: ='CAM TENANTS'!$A$44 -> 51060 | P43: ='CAM TENANTS'!$B$44 -> Roof Maintenance | Q43: ='CAM TENANTS'!$C$44 -> 1500 | R43: 0 | S43: =Q43+R43 -> 1500 | T43: =$Q$8/'CAM TENANTS'!$D$44 -> 0.15768799 | U43: =S43*T43 -> 236.53199 | V43: =U43*$V$12 -> 0 | W43: =U43+V43 -> 236.53199 | X43: ='CAM TENANTS'!$A$44 -> 51060 | Y43: ='CAM TENANTS'!$B$44 -> Roof Maintenance | Z43: ='CAM TENANTS'!$C$44 -> 1500 | AA43: 0 | AB43: =Z43+AA43 -> 1500 | AC43: =$Z$8/'CAM TENANTS'!D44 -> 0.04954305 | AD43: =AB43*AC43 -> 74.314574 | AE43: =AD43*$V$12 -> 0 | AF43: =AD43+AE43 -> 74.314574 | AG43: ='CAM TENANTS'!$A$44 -> 51060 | AH43: ='CAM TENANTS'!$B$44 -> Roof Maintenance | AI43: ='CAM TENANTS'!$C$44 -> 1500 | AJ43: 0 | AK43: =AI43+AJ43 -> 1500 | AL43: =$AI$8/'CAM TENANTS'!D44 -> 0.33910534 | AM43: =AK43*AL43 -> 508.65801 | AN43: =AM43*$V$12 -> 0 | AO43: =AM43+AN43 -> 508.65801
A44: =Summary!A62 -> 51060 | B44: =Summary!B62 -> Roof Maintenance | C44: =Summary!O62 -> 1500 | D44: 12474 | F44: ='CAM TENANTS'!$A$45 -> 51070 | G44: ='CAM TENANTS'!$B$45 -> Roof Repairs | H44: ='CAM TENANTS'!$C$45 -> 1500 | I44: =H44*'Occup,'!$C$28 -> 2330.9009 | J44: =IF(I44=0,H44,I44) -> 2330.9009 | K44: =$H$8/'CAM TENANTS'!D45 -> 0.45366362 | L44: =J44*K44 -> 1057.4449 | M44: =L44*$M$12 -> 0 | N44: =L44+M44 -> 1057.4449 | O44: ='CAM TENANTS'!$A$45 -> 51070 | P44: ='CAM TENANTS'!$B$45 -> Roof Repairs | Q44: ='CAM TENANTS'!$C$45 -> 1500 | R44: 0 | S44: =Q44+R44 -> 1500 | T44: =$Q$8/'CAM TENANTS'!$D$44 -> 0.15768799 | U44: =S44*T44 -> 236.53199 | V44: =U44*$V$12 -> 0 | W44: =U44+V44 -> 236.53199 | X44: ='CAM TENANTS'!$A$45 -> 51070 | Y44: ='CAM TENANTS'!$B$45 -> Roof Repairs | Z44: ='CAM TENANTS'!$C$45 -> 1500 | AA44: 0 | AB44: =Z44+AA44 -> 1500 | AC44: =$Z$8/'CAM TENANTS'!D45 -> 0.04954305 | AD44: =AB44*AC44 -> 74.314574 | AE44: =AD44*$V$12 -> 0 | AF44: =AD44+AE44 -> 74.314574 | AG44: ='CAM TENANTS'!$A$45 -> 51070 | AH44: ='CAM TENANTS'!$B$45 -> Roof Repairs | AI44: ='CAM TENANTS'!$C$45 -> 1500 | AJ44: 0 | AK44: =AI44+AJ44 -> 1500 | AL44: =$AI$8/'CAM TENANTS'!D45 -> 0.33910534 | AM44: =AK44*AL44 -> 508.65801 | AN44: =AM44*$V$12 -> 0 | AO44: =AM44+AN44 -> 508.65801
A45: =Summary!A63 -> 51070 | B45: =Summary!B63 -> Roof Repairs | C45: =Summary!O63 -> 1500 | D45: 12474 | F45: ='CAM TENANTS'!$A$46 -> 51110 | G45: ='CAM TENANTS'!$B$46 -> Monitor Fire Sprinklers | H45: ='CAM TENANTS'!$C$46 -> 0 | I45: =H45*'Occup,'!$C$28 -> 0 | J45: =IF(I45=0,H45,I45) -> 0 | K45: =$H$8/'CAM TENANTS'!D46 -> 0.45366362 | L45: =J45*K45 -> 0 | M45: =L45*$M$12 -> 0 | N45: =L45+M45 -> 0 | O45: ='CAM TENANTS'!$A$46 -> 51110 | P45: ='CAM TENANTS'!$B$46 -> Monitor Fire Sprinklers | Q45: ='CAM TENANTS'!$C$46 -> 0 | R45: 0 | S45: =Q45+R45 -> 0 | T45: =$Q$8/'CAM TENANTS'!$D$44 -> 0.15768799 | U45: =S45*T45 -> 0 | V45: =U45*$V$12 -> 0 | W45: =U45+V45 -> 0 | X45: ='CAM TENANTS'!$A$46 -> 51110 | Y45: ='CAM TENANTS'!$B$46 -> Monitor Fire Sprinklers | Z45: ='CAM TENANTS'!$C$46 -> 0 | AA45: 0 | AB45: =Z45+AA45 -> 0 | AC45: =$Z$8/'CAM TENANTS'!D46 -> 0.04954305 | AD45: =AB45*AC45 -> 0 | AE45: =AD45*$V$12 -> 0 | AF45: =AD45+AE45 -> 0 | AG45: ='CAM TENANTS'!$A$46 -> 51110 | AH45: ='CAM TENANTS'!$B$46 -> Monitor Fire Sprinklers | AI45: ='CAM TENANTS'!$C$46 -> 0 | AJ45: 0 | AK45: =AI45+AJ45 -> 0 | AL45: =$AI$8/'CAM TENANTS'!D46 -> 0.33910534 | AM45: =AK45*AL45 -> 0 | AN45: =AM45*$V$12 -> 0 | AO45: =AM45+AN45 -> 0
A46: =Summary!A64 -> 51110 | B46: =Summary!B64 -> Monitor Fire Sprinklers | C46: =Summary!O64 -> 0 | D46: =D45 -> 12474 | F46: ='CAM TENANTS'!$A$47 -> 51170 | G46: ='CAM TENANTS'!$B$47 -> Locks & Keys | H46: ='CAM TENANTS'!$C$47 -> 0 | I46: =H46*'Occup,'!$C$28 -> 0 | J46: =IF(I46=0,H46,I46) -> 0 | K46: =$H$8/'CAM TENANTS'!D47 -> 0.45366362 | L46: =J46*K46 -> 0 | M46: =L46*$M$12 -> 0 | N46: =L46+M46 -> 0 | O46: ='CAM TENANTS'!$A$47 -> 51170 | P46: ='CAM TENANTS'!$B$47 -> Locks & Keys | Q46: ='CAM TENANTS'!$C$47 -> 0 | R46: 0 | S46: =Q46+R46 -> 0 | T46: =$Q$8/'CAM TENANTS'!$D$44 -> 0.15768799 | U46: =S46*T46 -> 0 | V46: =U46*$V$12 -> 0 | W46: =U46+V46 -> 0 | X46: ='CAM TENANTS'!$A$47 -> 51170 | Y46: ='CAM TENANTS'!$B$47 -> Locks & Keys | Z46: ='CAM TENANTS'!$C$47 -> 0 | AA46: 0 | AB46: =Z46+AA46 -> 0 | AC46: =$Z$8/'CAM TENANTS'!D47 -> 0.04954305 | AD46: =AB46*AC46 -> 0 | AE46: =AD46*$V$12 -> 0 | AF46: =AD46+AE46 -> 0 | AG46: ='CAM TENANTS'!$A$47 -> 51170 | AH46: ='CAM TENANTS'!$B$47 -> Locks & Keys | AI46: ='CAM TENANTS'!$C$47 -> 0 | AJ46: 0 | AK46: =AI46+AJ46 -> 0 | AL46: =$AI$8/'CAM TENANTS'!D47 -> 0.33910534 | AM46: =AK46*AL46 -> 0 | AN46: =AM46*$V$12 -> 0 | AO46: =AM46+AN46 -> 0
A47: =Summary!A66 -> 51170 | B47: =Summary!B66 -> Locks & Keys | C47: =Summary!O66 -> 0 | D47: =D46 -> 12474 | F47: ='CAM TENANTS'!$A$48 -> 52020 | G47: ='CAM TENANTS'!$B$48 -> Backflow Maintenance | H47: ='CAM TENANTS'!$C$48 -> 55 | I47: =H47*'Occup,'!$C$28 -> 85.466365 | J47: =IF(I47=0,H47,I47) -> 85.466365 | K47: =$H$8/'CAM TENANTS'!D48 -> 0.45366362 | L47: =J47*K47 -> 38.772981 | M47: =L47*$M$12 -> 0 | N47: =L47+M47 -> 38.772981 | O47: ='CAM TENANTS'!$A$48 -> 52020 | P47: ='CAM TENANTS'!$B$48 -> Backflow Maintenance | Q47: ='CAM TENANTS'!$C$48 -> 55 | R47: 0 | S47: =Q47+R47 -> 55 | T47: =$Q$8/'CAM TENANTS'!$D$44 -> 0.15768799 | U47: =S47*T47 -> 8.6728395 | V47: =U47*$V$12 -> 0 | W47: =U47+V47 -> 8.6728395 | X47: ='CAM TENANTS'!$A$48 -> 52020 | Y47: ='CAM TENANTS'!$B$48 -> Backflow Maintenance | Z47: ='CAM TENANTS'!$C$48 -> 55 | AA47: 0 | AB47: =Z47+AA47 -> 55 | AC47: =$Z$8/'CAM TENANTS'!D48 -> 0.04954305 | AD47: =AB47*AC47 -> 2.7248677 | AE47: =AD47*$V$12 -> 0 | AF47: =AD47+AE47 -> 2.7248677 | AG47: ='CAM TENANTS'!$A$48 -> 52020 | AH47: ='CAM TENANTS'!$B$48 -> Backflow Maintenance | AI47: ='CAM TENANTS'!$C$48 -> 55 | AJ47: 0 | AK47: =AI47+AJ47 -> 55 | AL47: =$AI$8/'CAM TENANTS'!D48 -> 0.33910534 | AM47: =AK47*AL47 -> 18.650794 | AN47: =AM47*$V$12 -> 0 | AO47: =AM47+AN47 -> 18.650794
A48: =Summary!A67 -> 52020 | B48: =Summary!B67 -> Backflow Maintenance | C48: =Summary!O67 -> 55 | D48: =D47 -> 12474 | F48: ='CAM TENANTS'!$A$49 -> 52030 | G48: ='CAM TENANTS'!$B$49 -> Backflow Repairs | H48: ='CAM TENANTS'!$C$49 -> 150 | I48: =H48*'Occup,'!$C$28 -> 233.09009 | J48: =IF(I48=0,H48,I48) -> 233.09009 | K48: =$H$8/'CAM TENANTS'!D49 -> 0.45366362 | L48: =J48*K48 -> 105.74449 | M48: =L48*$M$12 -> 0 | N48: =L48+M48 -> 105.74449 | O48: ='CAM TENANTS'!$A$49 -> 52030 | P48: ='CAM TENANTS'!$B$49 -> Backflow Repairs | Q48: ='CAM TENANTS'!$C$49 -> 150 | R48: 0 | S48: =Q48+R48 -> 150 | T48: =$Q$8/'CAM TENANTS'!$D$44 -> 0.15768799 | U48: =S48*T48 -> 23.653199 | V48: =U48*$V$12 -> 0 | W48: =U48+V48 -> 23.653199 | X48: ='CAM TENANTS'!$A$49 -> 52030 | Y48: ='CAM TENANTS'!$B$49 -> Backflow Repairs | Z48: ='CAM TENANTS'!$C$49 -> 150 | AA48: 0 | AB48: =Z48+AA48 -> 150 | AC48: =$Z$8/'CAM TENANTS'!D49 -> 0.04954305 | AD48: =AB48*AC48 -> 7.4314574 | AE48: =AD48*$V$12 -> 0 | AF48: =AD48+AE48 -> 7.4314574 | AG48: ='CAM TENANTS'!$A$49 -> 52030 | AH48: ='CAM TENANTS'!$B$49 -> Backflow Repairs | AI48: ='CAM TENANTS'!$C$49 -> 150 | AJ48: 0 | AK48: =AI48+AJ48 -> 150 | AL48: =$AI$8/'CAM TENANTS'!D49 -> 0.33910534 | AM48: =AK48*AL48 -> 50.865801 | AN48: =AM48*$V$12 -> 0 | AO48: =AM48+AN48 -> 50.865801
A49: =Summary!A68 -> 52030 | B49: =Summary!B68 -> Backflow Repairs | C49: =Summary!O68 -> 150 | D49: =D48 -> 12474 | F49: ='CAM TENANTS'!$A$50 -> 55102 | G49: ='CAM TENANTS'!$B$50 -> Electricity/Building | H49: ='CAM TENANTS'!$C$50 -> 27720 | I49: =H49*'Occup,'!$C$28 -> 43075.048 | J49: =IF(I49=0,H49,I49) -> 43075.048 | K49: =$H$8/'CAM TENANTS'!D50 -> 0.74206661 | L49: =J49*K49 -> 31964.555 | M49: =L49*$M$12 -> 0 | N49: =L49+M49 -> 31964.555 | O49: ='CAM TENANTS'!$A$50 -> 55102 | P49: ='CAM TENANTS'!$B$50 -> Electricity/Building | Q49: ='CAM TENANTS'!$C$50 -> 27720 | R49: 0 | S49: =Q49+R49 -> 27720 | T49: =$Q$8/'CAM TENANTS'!$D$44 -> 0.15768799 | U49: =S49*T49 -> 4371.1111 | V49: =U49*$V$12 -> 0 | W49: =U49+V49 -> 4371.1111 | X49: ='CAM TENANTS'!$A$50 -> 55102 | Y49: ='CAM TENANTS'!$B$50 -> Electricity/Building | Z49: ='CAM TENANTS'!$C$50 -> 27720 | AA49: 0 | AB49: =Z49+AA49 -> 27720 | AC49: =$Z$8/'CAM TENANTS'!D50 -> 0.081038552 | AD49: =AB49*AC49 -> 2246.3887 | AE49: =AD49*$V$12 -> 0 | AF49: =AD49+AE49 -> 2246.3887 | AG49: ='CAM TENANTS'!$A$50 -> 55102 | AH49: ='CAM TENANTS'!$B$50 -> Electricity/Building | AI49: ='CAM TENANTS'!$C$50 -> 27720 | AJ49: 0 | AK49: =AI49+AJ49 -> 27720 | AL49: =$AI$8/'CAM TENANTS'!D50 -> 0.55468135 | AM49: =AK49*AL49 -> 15375.767 | AN49: =AM49*$V$12 -> 0 | AO49: =AM49+AN49 -> 15375.767
A50: =Summary!A69 -> 55102 | B50: =Summary!B69 -> Electricity/Building | C50: =Summary!O69 -> 27720 | D50: =Rent!C28 -> 7626 | F50: ='CAM TENANTS'!$A$51 -> 55130 | G50: ='CAM TENANTS'!$B$51 -> Water/Building | H50: ='CAM TENANTS'!$C$51 -> 8001 | I50: =H50*'Occup,'!$C$28 -> 12433.025 | J50: =IF(I50=0,H50,I50) -> 12433.025 | K50: =$H$8/'CAM TENANTS'!D51 -> 0.74206661 | L50: =J50*K50 -> 9226.1329 | M50: =L50*$M$12 -> 0 | N50: =L50+M50 -> 9226.1329 | O50: ='CAM TENANTS'!$A$51 -> 55130 | P50: ='CAM TENANTS'!$B$51 -> Water/Building | Q50: ='CAM TENANTS'!$C$51 -> 8001 | R50: 0 | S50: =Q50+R50 -> 8001 | T50: =$Q$8/'CAM TENANTS'!$D$44 -> 0.15768799 | U50: =S50*T50 -> 1261.6616 | V50: =U50*$V$12 -> 0 | W50: =U50+V50 -> 1261.6616 | X50: ='CAM TENANTS'!$A$51 -> 55130 | Y50: ='CAM TENANTS'!$B$51 -> Water/Building | Z50: ='CAM TENANTS'!$C$51 -> 8001 | AA50: 0 | AB50: =Z50+AA50 -> 8001 | AC50: =$Z$8/'CAM TENANTS'!D51 -> 0.081038552 | AD50: =AB50*AC50 -> 648.38946 | AE50: =AD50*$V$12 -> 0 | AF50: =AD50+AE50 -> 648.38946 | AG50: ='CAM TENANTS'!$A$51 -> 55130 | AH50: ='CAM TENANTS'!$B$51 -> Water/Building | AI50: ='CAM TENANTS'!$C$51 -> 8001 | AJ50: 0 | AK50: =AI50+AJ50 -> 8001 | AL50: =$AI$8/'CAM TENANTS'!D51 -> 0.55468135 | AM50: =AK50*AL50 -> 4438.0055 | AN50: =AM50*$V$12 -> 0 | AO50: =AM50+AN50 -> 4438.0055
A51: =Summary!A70 -> 55130 | B51: =Summary!B70 -> Water/Building | C51: =Summary!O70 -> 8001 | D51: =D50 -> 7626
G52: ='CAM TENANTS'!$B$53 -> SUBTOTAL BUILDING EXP. | H52: =SUM(H43:H50) -> 38926 | I52: =SUM(I43:I50) -> 60488.431 | J52: =SUM(J43:J50) -> 60488.431 | L52: =SUM(L43:L50) -> 43450.095 | M52: =SUM(M43:M50) -> 0 | N52: =SUM(N43:N50) -> 43450.095 | P52: ='CAM TENANTS'!$B$53 -> SUBTOTAL BUILDING EXP. | Q52: =SUM(Q43:Q50) -> 38926 | R52: =SUM(R43:R50) -> 0 | S52: =SUM(S43:S50) -> 38926 | U52: =SUM(U43:U50) -> 6138.1627 | V52: =SUM(V43:V50) -> 0 | W52: =SUM(W43:W50) -> 6138.1627 | Y52: ='CAM TENANTS'!$B$53 -> SUBTOTAL BUILDING EXP. | Z52: =SUM(Z43:Z50) -> 38926 | AA52: =SUM(AA43:AA50) -> 0 | AB52: =SUM(AB43:AB50) -> 38926 | AD52: =SUM(AD43:AD50) -> 3053.5636 | AE52: =SUM(AE43:AE50) -> 0 | AF52: =SUM(AF43:AF50) -> 3053.5636 | AH52: ='CAM TENANTS'!$B$53 -> SUBTOTAL BUILDING EXP. | AI52: =SUM(AI43:AI50) -> 38926 | AJ52: =SUM(AJ43:AJ50) -> 0 | AK52: =SUM(AK43:AK50) -> 38926 | AM52: =SUM(AM43:AM50) -> 20900.605 | AN52: =SUM(AN43:AN50) -> 0 | AO52: =SUM(AO43:AO50) -> 20900.605
B53: =Summary!B72 -> SUBTOTAL BUILDING EXP. | C53: =SUM(C44:C51) -> 38926
G54: ='CAM TENANTS'!$B$55 -> INSURANCE | P54: ='CAM TENANTS'!$B$55 -> INSURANCE | Y54: ='CAM TENANTS'!$B$55 -> INSURANCE | AH54: ='CAM TENANTS'!$B$55 -> INSURANCE
B55: =Summary!B74 -> INSURANCE | F55: ='CAM TENANTS'!$A$56 -> 50111 | G55: ='CAM TENANTS'!$B$56 -> Insurance - Property | H55: ='CAM TENANTS'!$C$56 -> 5619.9 | I55: =H55*'Occup,'!$C$28 -> 8732.9532 | J55: =IF(I55=0,H55,I55) -> 8732.9532 | K55: =$H$8/'CAM TENANTS'!D56 -> 0.45366362 | L55: =J55*K55 -> 3961.8232 | M55: 0 | N55: =L55+M55 -> 3961.8232 | O55: ='CAM TENANTS'!$A$56 -> 50111 | P55: ='CAM TENANTS'!$B$56 -> Insurance - Property | Q55: ='CAM TENANTS'!$C$56 -> 5619.9 | R55: 0 | S55: =Q55+R55 -> 5619.9 | T55: =$Q$8/'CAM TENANTS'!$D$56 -> 0.15768799 | U55: =S55*T55 -> 886.19074 | V55: 0 | W55: =U55+V55 -> 886.19074 | X55: ='CAM TENANTS'!$A$56 -> 50111 | Y55: ='CAM TENANTS'!$B$56 -> Insurance - Property | Z55: ='CAM TENANTS'!$C$56 -> 5619.9 | AA55: 0 | AB55: =Z55+AA55 -> 5619.9 | AC55: =$Z$8/'CAM TENANTS'!D56 -> 0.04954305 | AD55: =AB55*AC55 -> 278.42698 | AE55: 0 | AF55: =AD55+AE55 -> 278.42698 | AG55: ='CAM TENANTS'!$A$56 -> 50111 | AH55: ='CAM TENANTS'!$B$56 -> Insurance - Property | AI55: ='CAM TENANTS'!$C$56 -> 5619.9 | AJ55: 0 | AK55: =AI55+AJ55 -> 5619.9 | AL55: =$AI$8/'CAM TENANTS'!D56 -> 0.33910534 | AM55: =AK55*AL55 -> 1905.7381 | AN55: 0 | AO55: =AM55+AN55 -> 1905.7381
A56: =Summary!A75 -> 50111 | B56: =Summary!B75 -> Insurance - Property | C56: =Summary!O75 -> 5619.9 | D56: =Rent!C$23 -> 12474 | F56: ='CAM TENANTS'!$A$57 -> 50112 | G56: ='CAM TENANTS'!$B$57 -> Insurance - Liability | H56: ='CAM TENANTS'!$C$57 -> 0 | I56: =H56*'Occup,'!$C$28 -> 0 | J56: =IF(I56=0,H56,I56) -> 0 | K56: =$H$8/'CAM TENANTS'!D57 -> 0.45366362 | L56: =J56*K56 -> 0 | M56: =L56*$M$12 -> 0 | N56: =L56+M56 -> 0 | O56: ='CAM TENANTS'!$A$57 -> 50112 | P56: ='CAM TENANTS'!$B$57 -> Insurance - Liability | Q56: ='CAM TENANTS'!$C$57 -> 0 | R56: 0 | S56: =Q56+R56 -> 0 | T56: =$Q$8/'CAM TENANTS'!$D$56 -> 0.15768799 | U56: =S56*T56 -> 0 | V56: =U56*$V$12 -> 0 | W56: =U56+V56 -> 0 | X56: ='CAM TENANTS'!$A$57 -> 50112 | Y56: ='CAM TENANTS'!$B$57 -> Insurance - Liability | Z56: ='CAM TENANTS'!$C$57 -> 0 | AA56: 0 | AB56: =Z56+AA56 -> 0 | AC56: =$Z$8/'CAM TENANTS'!D57 -> 0.04954305 | AD56: =AB56*AC56 -> 0 | AE56: =AD56*$V$12 -> 0 | AF56: =AD56+AE56 -> 0 | AG56: ='CAM TENANTS'!$A$57 -> 50112 | AH56: ='CAM TENANTS'!$B$57 -> Insurance - Liability | AI56: ='CAM TENANTS'!$C$57 -> 0 | AJ56: 0 | AK56: =AI56+AJ56 -> 0 | AL56: =$AI$8/'CAM TENANTS'!D57 -> 0.33910534 | AM56: =AK56*AL56 -> 0 | AN56: =AM56*$V$12 -> 0 | AO56: =AM56+AN56 -> 0
A57: =Summary!A76 -> 50112 | B57: =Summary!B76 -> Insurance - Liability | C57: =Summary!O76 -> 0 | D57: =Rent!C$23 -> 12474 | F57: ='CAM TENANTS'!$A$58 -> 50130 | G57: ='CAM TENANTS'!$B$58 -> Insurance - Umbrella | H57: ='CAM TENANTS'!$C$58 -> 0 | I57: =H57*'Occup,'!$C$28 -> 0 | J57: =IF(I57=0,H57,I57) -> 0 | K57: =$H$8/'CAM TENANTS'!D58 -> 0.45366362 | L57: =J57*K57 -> 0 | M57: 0 | N57: =L57+M57 -> 0 | O57: ='CAM TENANTS'!$A$58 -> 50130 | P57: ='CAM TENANTS'!$B$58 -> Insurance - Umbrella | Q57: ='CAM TENANTS'!$C$58 -> 0 | R57: 0 | S57: =Q57+R57 -> 0 | T57: =$Q$8/'CAM TENANTS'!$D$56 -> 0.15768799 | U57: =S57*T57 -> 0 | V57: 0 | W57: =U57+V57 -> 0 | X57: ='CAM TENANTS'!$A$58 -> 50130 | Y57: ='CAM TENANTS'!$B$58 -> Insurance - Umbrella | Z57: ='CAM TENANTS'!$C$58 -> 0 | AA57: 0 | AB57: =Z57+AA57 -> 0 | AC57: =$Z$8/'CAM TENANTS'!D58 -> 0.04954305 | AD57: =AB57*AC57 -> 0 | AE57: 0 | AF57: =AD57+AE57 -> 0 | AG57: ='CAM TENANTS'!$A$58 -> 50130 | AH57: ='CAM TENANTS'!$B$58 -> Insurance - Umbrella | AI57: ='CAM TENANTS'!$C$58 -> 0 | AJ57: 0 | AK57: =AI57+AJ57 -> 0 | AL57: =$AI$8/'CAM TENANTS'!D58 -> 0.33910534 | AM57: =AK57*AL57 -> 0 | AN57: 0 | AO57: =AM57+AN57 -> 0
A58: =Summary!A77 -> 50130 | B58: =Summary!B77 -> Insurance - Umbrella | C58: =Summary!O77 -> 0 | D58: =Rent!C$23 -> 12474 | F58: ='CAM TENANTS'!$A$59 -> 50140 | G58: ='CAM TENANTS'!$B$59 -> Insurance - Flood & Earthquake | H58: ='CAM TENANTS'!$C$59 -> 0 | I58: =H58*'Occup,'!$C$28 -> 0 | J58: =IF(I58=0,H58,I58) -> 0 | K58: =$H$8/'CAM TENANTS'!D59 -> 0.45366362 | L58: =J58*K58 -> 0 | M58: =L58*$M$12 -> 0 | N58: =L58+M58 -> 0 | O58: ='CAM TENANTS'!$A$59 -> 50140 | P58: ='CAM TENANTS'!$B$59 -> Insurance - Flood & Earthquake | Q58: ='CAM TENANTS'!$C$59 -> 0 | R58: =-Q58 -> 0 | S58: =Q58+R58 -> 0 | T58: =$Q$8/'CAM TENANTS'!$D$56 -> 0.15768799 | U58: =S58*T58 -> 0 | V58: 0 | W58: =U58+V58 -> 0 | X58: ='CAM TENANTS'!$A$59 -> 50140 | Y58: ='CAM TENANTS'!$B$59 -> Insurance - Flood & Earthquake | Z58: ='CAM TENANTS'!$C$59 -> 0 | AA58: =-Z58 -> 0 | AB58: =Z58+AA58 -> 0 | AC58: =$Z$8/'CAM TENANTS'!D59 -> 0.04954305 | AD58: =AB58*AC58 -> 0 | AE58: 0 | AF58: =AD58+AE58 -> 0 | AG58: ='CAM TENANTS'!$A$59 -> 50140 | AH58: ='CAM TENANTS'!$B$59 -> Insurance - Flood & Earthquake | AI58: ='CAM TENANTS'!$C$59 -> 0 | AJ58: =-AI58 -> 0 | AK58: =AI58+AJ58 -> 0 | AL58: =$AI$8/'CAM TENANTS'!D59 -> 0.33910534 | AM58: =AK58*AL58 -> 0 | AN58: 0 | AO58: =AM58+AN58 -> 0
A59: =Summary!A78 -> 50140 | B59: =Summary!B78 -> Insurance - Flood & Earthquake | C59: =Summary!O78 -> 0 | D59: =Rent!C$23 -> 12474
G60: ='CAM TENANTS'!$B$61 -> SUBTOTAL INSURANCE | H60: =SUM(H55:H58) -> 5619.9 | I60: =SUM(I55:I58) -> 8732.9532 | J60: =SUM(J55:J58) -> 8732.9532 | L60: =SUM(L55:L58) -> 3961.8232 | M60: =SUM(M55:M58) -> 0 | N60: =SUM(N55:N58) -> 3961.8232 | P60: ='CAM TENANTS'!$B$61 -> SUBTOTAL INSURANCE | Q60: =SUM(Q55:Q58) -> 5619.9 | R60: =SUM(R55:R58) -> 0 | S60: =SUM(S55:S58) -> 5619.9 | U60: =SUM(U55:U58) -> 886.19074 | V60: =SUM(V55:V58) -> 0 | W60: =SUM(W55:W58) -> 886.19074 | Y60: ='CAM TENANTS'!$B$61 -> SUBTOTAL INSURANCE | Z60: =SUM(Z55:Z58) -> 5619.9 | AA60: =SUM(AA55:AA58) -> 0 | AB60: =SUM(AB55:AB58) -> 5619.9 | AD60: =SUM(AD55:AD58) -> 278.42698 | AE60: =SUM(AE55:AE58) -> 0 | AF60: =SUM(AF55:AF58) -> 278.42698 | AH60: ='CAM TENANTS'!$B$61 -> SUBTOTAL INSURANCE | AI60: =SUM(AI55:AI58) -> 5619.9 | AJ60: =SUM(AJ55:AJ58) -> 0 | AK60: =SUM(AK55:AK58) -> 5619.9 | AM60: =SUM(AM55:AM58) -> 1905.7381 | AN60: =SUM(AN55:AN58) -> 0 | AO60: =SUM(AO55:AO58) -> 1905.7381
B61: =Summary!B80 -> SUBTOTAL INSURANCE | C61: =SUM(C56:C59) -> 5619.9
G62: ='CAM TENANTS'!$B$63 -> PROPERTY TAXES | P62: ='CAM TENANTS'!$B$63 -> PROPERTY TAXES | Y62: ='CAM TENANTS'!$B$63 -> PROPERTY TAXES | AH62: ='CAM TENANTS'!$B$63 -> PROPERTY TAXES
B63: =Summary!B82 -> PROPERTY TAXES | F63: ='CAM TENANTS'!$A$64 -> 54000 | G63: ='CAM TENANTS'!$B$64 -> Property Tax | H63: ='CAM TENANTS'!$C$64 -> 34927.63 | I63: =H63*'Occup,'!$C$28 -> 54275.229 | J63: =IF(I63=0,H63,I63) -> 54275.229 | K63: =$H$8/'CAM TENANTS'!D64 -> 0.45366362 | L63: =J63*K63 -> 24622.697 | M63: 0 | N63: =L63+M63 -> 24622.697 | O63: ='CAM TENANTS'!$A$64 -> 54000 | P63: ='CAM TENANTS'!$B$64 -> Property Tax | Q63: ='CAM TENANTS'!$C$64 -> 34927.63 | R63: 0 | S63: =+Q63+R63 -> 34927.63 | T63: =$Q$8/'CAM TENANTS'!D64 -> 0.15768799 | U63: =S63*T63 -> 5507.6678 | V63: 0 | W63: =U63+V63 -> 5507.6678 | X63: ='CAM TENANTS'!$A$64 -> 54000 | Y63: ='CAM TENANTS'!$B$64 -> Property Tax | Z63: ='CAM TENANTS'!$C$64 -> 34927.63 | AA63: 0 | AB63: =+Z63+AA63 -> 34927.63 | AC63: =$Z$8/'CAM TENANTS'!D64 -> 0.04954305 | AD63: =AB63*AC63 -> 1730.4213 | AE63: 0 | AF63: =AD63+AE63 -> 1730.4213 | AG63: ='CAM TENANTS'!$A$64 -> 54000 | AH63: ='CAM TENANTS'!$B$64 -> Property Tax | AI63: ='CAM TENANTS'!$C$64 -> 34927.63 | AJ63: 0 | AK63: =+AI63+AJ63 -> 34927.63 | AL63: =$AI$8/'CAM TENANTS'!D64 -> 0.33910534 | AM63: =AK63*AL63 -> 11844.146 | AN63: 0 | AO63: =AM63+AN63 -> 11844.146
A64: =Summary!A83 -> 54000 | B64: =Summary!B83 -> Property Tax | C64: =Summary!O83 -> 34927.63 | D64: =Rent!C$23 -> 12474
G65: ='CAM TENANTS'!$B$66 -> SUBTOTAL TAXES | H65: =SUM(H63) -> 34927.63 | I65: =SUM(I63) -> 54275.229 | J65: =SUM(J63) -> 54275.229 | L65: =SUM(L63) -> 24622.697 | M65: =SUM(M63) -> 0 | N65: =SUM(N63) -> 24622.697 | P65: =$G$65 -> SUBTOTAL TAXES | Q65: =SUM(Q63) -> 34927.63 | R65: =SUM(R63) -> 0 | S65: =SUM(S63) -> 34927.63 | U65: =SUM(U63) -> 5507.6678 | V65: =SUM(V63) -> 0 | W65: =SUM(W63) -> 5507.6678 | Y65: =$G$65 -> SUBTOTAL TAXES | Z65: =SUM(Z63) -> 34927.63 | AA65: =SUM(AA63) -> 0 | AB65: =SUM(AB63) -> 34927.63 | AD65: =SUM(AD63) -> 1730.4213 | AE65: =SUM(AE63) -> 0 | AF65: =SUM(AF63) -> 1730.4213 | AH65: =$G$65 -> SUBTOTAL TAXES | AI65: =SUM(AI63) -> 34927.63 | AJ65: =SUM(AJ63) -> 0 | AK65: =SUM(AK63) -> 34927.63 | AM65: =SUM(AM63) -> 11844.146 | AN65: =SUM(AN63) -> 0 | AO65: =SUM(AO63) -> 11844.146
B66: =Summary!B85 -> SUBTOTAL TAXES | C66: =SUM(C64) -> 34927.63
G67: ='CAM TENANTS'!$B$68 -> TOTAL COMMON AREA | H67: =H40+H52+H60+H65 -> 144815.53 | I67: =I40+I52+I60+I65 -> 221134.94 | J67: =J40+J52+J60+J65 -> 223643.94 | L67: =SUM(L65,L60,L52,L40) -> 119950.62 | M67: =SUM(M65,M60,M52,M40) -> 0 | N67: =N65+N60+N52+N40 -> 119950.62 | P67: =$G$67 -> TOTAL COMMON AREA | Q67: =Q40+Q52+Q60+Q65 -> 144815.53 | R67: =R40+R52+R60+R65 -> 0 | S67: =S40+S52+S60+S65 -> 144815.53 | U67: =SUM(U65,U60,U52,U40) -> 23391.029 | V67: =SUM(V65,V60,V52,V40) -> 0 | W67: =W65+W60+W52+W40 -> 23391.029 | Y67: =$G$67 -> TOTAL COMMON AREA | Z67: =Z40+Z52+Z60+Z65 -> 144815.53 | AA67: =AA40+AA52+AA60+AA65 -> -3500 | AB67: =AB40+AB52+AB60+AB65 -> 141315.53 | AD67: =SUM(AD65,AD60,AD52,AD40) -> 8300.7382 | AE67: =SUM(AE65,AE60,AE52,AE40) -> 0 | AF67: =AF65+AF60+AF52+AF40 -> 8300.7382 | AH67: =$G$67 -> TOTAL COMMON AREA | AI67: =AI40+AI52+AI60+AI65 -> 144815.53 | AJ67: =AJ40+AJ52+AJ60+AJ65 -> -3500 | AK67: =AK40+AK52+AK60+AK65 -> 141315.53 | AM67: =SUM(AM65,AM60,AM52,AM40) -> 56815.733 | AN67: =SUM(AN65,AN60,AN52,AN40) -> 0 | AO67: =AO65+AO60+AO52+AO40 -> 56815.733
B68: =Summary!B89 -> TOTAL COMMON AREA | C68: =C41+C53+C61+C66 -> 144815.53
G70: Less Base Year | H70: =H67 -> 144815.53 | I70: -128648.65 | J70: =I70+H70 -> 16166.88 | K70: =K63 -> 0.45366362 | L70: =K70*J70 -> 7334.3253 | M70: =L70*M12 -> 0 | N70: =M70+L70 -> 7334.3253 | P70: Amount Billable to Tenant | Q70: =Q67 -> 144815.53 | R70: -125287.09 | S70: =R70+Q70 -> 19528.44 | T70: =T63 -> 0.15768799 | U70: =T70*S70 -> 3079.4005 | V70: =U70*V12 -> 0 | W70: =V70+U70 -> 3079.4005 | Y70: Amount Billable to Tenant | Z70: =Z67 -> 144815.53 | AB70: =AA70+Z70 -> 144815.53 | AC70: =AC63 -> 0.04954305 | AD70: =AC70*AB70 -> 7174.603 | AE70: =AD70*AE12 -> 0 | AF70: =AE70+AD70 -> 7174.603 | AH70: Amount Billable to Tenant | AI70: =AI67 -> 144815.53 | AK70: =AJ70+AI70 -> 144815.53 | AL70: =AL63 -> 0.33910534 | AM70: =AL70*AK70 -> 49107.719 | AN70: =AM70*AN12 -> 0 | AO70: =AN70+AM70 -> 49107.719
I72: Tenant Open | J72: Center Open | K72: % of Liability | R72: Tenant Open | S72: Center Open | T72: % of Liability | AA72: Tenant Open | AB72: Center Open | AC72: % of Liability | AJ72: Tenant Open | AK72: Center Open | AL72: % of Liability
G73: Percentage of Center Occupancy | I73: 365 | J73: 365 | K73: 1 | N73: =N70*K73 -> 7334.3253 | P73: Percentage of Center Occupancy | R73: 365 | S73: 365 | T73: 1 | W73: =W70*T73 -> 3079.4005 | Y73: Percentage of Center Occupancy | AA73: 365 | AB73: 365 | AC73: 1 | AF73: =AF70*AC73 -> 7174.603 | AH73: Percentage of Center Occupancy | AJ73: 365 | AK73: 365 | AL73: 1 | AO73: =AO70*AL73 -> 49107.719
G75: GROSS UP | K75: =N73 -> 7334.3253 | L75: 0.95 | M75: =L75*M17 -> 0 | N75: =M75+L75 -> 0.95 | P75: Amount Billable to Tenant | Q75: =Q72 -> 0 | R75: -125287.09 | S75: =R75+Q75 -> -125287.09 | T75: =T68 -> 0 | U75: =T75*S75 -> 0 | V75: =U75*V17 -> 0 | W75: =V75+U75 -> 0 | Y75: Amount Billable to Tenant | Z75: =Z72 -> 0 | AB75: =AA75+Z75 -> 0 | AC75: =AC68 -> 0 | AD75: =AC75*AB75 -> 0 | AE75: =AD75*AE17 -> 0 | AF75: =AF73 -> 7174.603 | AH75: Amount Billable to Tenant | AI75: =AI72 -> 0 | AJ75: 0 | AK75: =AJ75+AI75 -> 0 | AL75: =AL68 -> 0 | AM75: =AL75*AK75 -> 0 | AN75: =AM75*AN17 -> 0 | AO75: =AO73 -> 49107.719
G79: TOTAL EXPENSES | N79: =N73 -> 7334.3253 | P79: TOTAL EXPENSES | W79: =W73 -> 3079.4005 | Y79: TOTAL EXPENSES | AF79: =AF73 -> 7174.603 | AH79: TOTAL EXPENSES | AO79: =AO73 -> 49107.719
M80: Monthly | N80: =N79/12 -> 611.19378 | V80: Monthly | W80: =W79/12 -> 256.61671 | AE80: Monthly | AF80: =AF79/12 -> 597.88358 | AN80: Monthly | AO80: =AO79/12 -> 4092.31
N82: =N79/12 -> 611.19378 | W82: =W79/12 -> 256.61671 | AF82: =AF79/12 -> 597.88358 | AO82: =AO79/12 -> 4092.31
K83: Total NNNs | L83: =N67/12 -> 9995.8848 | T83: Total NNNs | U83: =W67/12 -> 1949.2525 | AC83: Total NNNs | AD83: =AF67/12 -> 691.72819 | AL83: Total NNNs | AM83: =AO67/12 -> 4734.6444
K84: PSF | L84: =L83/H8 -> 1.7663695 | T84: PSF | U84: =U83/Q8 -> 0.99097735 | W84: =W67/12 -> 1949.2525 | AC84: PSF | AD84: =AD83/Z8 -> 1.1193013 | AL84: PSF | AM84: =AM83/AI8 -> 1.1193013
G85: 95% GROSS UP PERMITTED | P85: LEASE DOES NOT ALLOW FOR GROSS UP | W85: =W84/Q8 -> 0.99097735
G86: SECTION 4.2© | W86: =W85*12 -> 11.891728 | AC86: Total Rents | AD86: 24.75
AC87: Annual Base | AD87: =AD86-AD84 -> 23.630699
AC88: Monthly Base | AD88: =AD87/12 -> 1.9692249

Sheet Checks and Balances
A1: Checks and Balances
A4: January
B5: Summary | C5: Tab | D5: Tenant Charges
A6: Base Rent | B6: =Summary!C13 -> 17644.09 | C6: =Rent!E23 -> 17644.09 | D6: ='Tenant Charges'!E16 -> 17644.09 | E6: {=AND(EXACT(B6:D6,B6))} -> TRUE
A7: CAM | B7: =Summary!C14 -> 867.81048 | C7: =CAM!E25 -> 867.81048 | D7: ='Tenant Charges'!F16 -> 2984.7746 | E7: {=AND(EXACT(B7:D7,B7))} -> FALSE
A8: Building Expenses | B8: =Summary!C17 -> 0 | C8: ='Building Expenses'!E26 -> 0 | D8: ='Tenant Charges'!G16 -> 1996.1807 | E8: {=AND(EXACT(B8:D8,B8))} -> FALSE
A9: Insurance | B9: =Summary!C18 -> 0 | C9: =Ins.!E25 -> 0 | D9: ='Tenant Charges'!J16 -> 182.01376 | E9: {=AND(EXACT(B9:D9,B9))} -> FALSE
A10: Tax | B10: =Summary!C19 -> 0 | C10: ='RE Tax'!E24 -> 0 | D10: ='Tenant Charges'!I16 -> 1131.2139 | E10: {=AND(EXACT(B10:D10,B10))} -> FALSE
A11: Admin Fee | B11: =Summary!C20 -> 0 | C11: ='Admin Fee'!E26 -> 0 | D11: ='Tenant Charges'!H16 -> 0 | E11: {=AND(EXACT(B11:D11,B11))} -> TRUE
D13: Budget is: | E13: =COUNTIF(E6:E11,FALSE)=0 -> FALSE
