Workbook
Name _Builtin0: #N/A

Sheet Notes
B2: Greenfield Budget Notes
B3: Fire Inspections
B5: Parking Lot
B6: Roof
B7: Vendor Changes
B14: Notes to Owner
B15: Notes for 2025
B20: Misc | C20: Management Agreement Commenced June 1, 2025

Sheet 2026
BI1: YTD - 2026
B2: MONTHLY TENANT CHARGES | C2: Budget | D2: Cash | E2: Variance | F2: Comments | H2: Budget | I2: Cash | J2: Variance | K2: Comments | M2: Budget | N2: Cash | O2: Variance | P2: Comments | R2: Budget | S2: Cash | T2: Variance | U2: Comments | V2: Budget | W2: Cash | X2: Variance | Y2: Comments | Z2: Budget | AA2: Cash | AB2: Variance | AC2: Comments | AE2: Budget | AF2: Cash | AG2: Variance | AH2: Comments | AJ2: Budget | AK2: Cash | AL2: Variance | AM2: Comments | AO2: Budget | AP2: Cash | AQ2: Variance | AR2: Comments | AT2: Budget | AU2: Cash | AV2: Variance | AW2: Comments | AX2: Budget | AY2: Cash | AZ2: Variance | BA2: Comments | BC2: Budget | BD2: Cash | BE2: Variance | BF2: Comments | BH2: Budget | BI2: Cash | BJ2: Variance | BK2: Comments
B3: TENANT | C3: 46023 | D3: 46023 | E3: 46023 | F3: 46023 | H3: 46054 | I3: 46054 | J3: 46054 | K3: 46054 | M3: 46082 | N3: 46082 | O3: 46082 | P3: 46082 | R3: 46113 | S3: 46113 | T3: 46113 | U3: 46113 | V3: 46143 | W3: 46143 | X3: 46143 | Y3: 46143 | Z3: 46198 | AA3: 46198 | AB3: 46198 | AC3: 46198 | AE3: 46228 | AF3: 46228 | AG3: 46228 | AH3: 46228 | AJ3: 46259 | AK3: 46259 | AL3: 46259 | AM3: 46259 | AO3: 46290 | AP3: 46290 | AQ3: 46290 | AR3: 46290 | AT3: 46320 | AU3: 46320 | AV3: 46320 | AW3: 46320 | AX3: 46351 | AY3: 46351 | AZ3: 46351 | BA3: 46351 | BC3: 46381 | BD3: 46381 | BE3: 46381 | BF3: 46381
A4: =Rent!B14 -> Major A | B4: =Rent!A14 -> EOS Fitness | C4: =VLOOKUP(B4,'Final Data'!A3:B27,2,0) -> 66174.826 | D4: 66725.03 | E4: =D4-C4 -> 550.20436 | F4: CAM $550.19 Over Pmt | H4: =VLOOKUP(B4,'Final Data'!A:C,3,0) -> 66174.826 | I4: 66725.03 | J4: =I4-H4 -> 550.20436 | K4: CAM $550.19 Over Pmt | M4: =VLOOKUP(B4,'Final Data'!A:D,4,0) -> 66174.826 | N4: 81513.54 | O4: =N4-M4 -> 15338.714 | P4: Applied (1,100) CAM credit to charges PYC $16,038.14 received STX $401 Paid for prior balance. | R4: =VLOOKUP(B4,'Final Data'!A:E,5,0) -> 66174.826 | S4: 66174.83 | T4: =S4-R4 -> 0.0043562544 | V4: =VLOOKUP(B4,'Final Data'!A:G,6,0) -> 66174.826 | W4: 72994.79 | X4: =W4-V4 -> 6819.9644 | Y4: PYC $6,653.61 received STX $166.34 received | Z4: =VLOOKUP(B4,'Final Data'!A:G,7,0) -> 66174.826 | AA4: 66174.84 | AB4: =AA4-Z4 -> 0.014356254 | AE4: =VLOOKUP(B4,'Final Data'!A:H,8,0) -> 66174.826 | AF4: 66174.84 | AG4: =AF4-AE4 -> 0.014356254 | AJ4: =VLOOKUP(B4,'Final Data'!A:I,9,0) -> 66174.826 | AK4: 66174.84 | AL4: =AK4-AJ4 -> 0.014356254 | BH4: =+C4+H4+M4+R4+V4+Z4+AE4+AJ4+AO4+AT4+AX4+BC4 -> 529398.61 | BI4: =+D4+I4+N4+S4+W4+AA4+AF4+AK4+AP4+AU4+AY4+BD4 -> 552657.74 | BJ4: =+E4+J4+O4+T4+X4+AB4+AG4+AL4+AQ4+AV4+AZ4+BE4 -> 23259.135 | BK4: STX $401.00 Budget vs pmt. PYC $22,691.75 received in Mar'26 & May'26 STX $166.34 received in May'26
A5: =Rent!B15 -> B101 | B5: =Rent!A15 -> Third Pasrty MVS | C5: =VLOOKUP(B5,'Final Data'!A4:B28,2,0) -> 8225.115 | D5: 8225.14 | E5: =D5-C5 -> 0.024978176 | H5: =VLOOKUP(B5,'Final Data'!A:C,3,0) -> 8225.115 | I5: 8225.12 | J5: =I5-H5 -> 0.0049781756 | M5: =VLOOKUP(B5,'Final Data'!A:D,4,0) -> 8225.115 | N5: 8225.12 | O5: =N5-M5 -> 0.0049781756 | R5: =VLOOKUP(B5,'Final Data'!A:E,5,0) -> 8225.115 | S5: 8225.14 | T5: =S5-R5 -> 0.024978176 | V5: =VLOOKUP(B5,'Final Data'!A:G,6,0) -> 8225.115 | W5: 9380.92 | X5: =W5-V5 -> 1155.805 | Y5: PYC $1,100.74 received STX $27.52 received CAM $27.52 Over Pmt | Z5: =VLOOKUP(B5,'Final Data'!A:G,7,0) -> 8225.115 | AA5: 8197.62 | AB5: =AA5-Z5 -> -27.495022 | AC5: CAM ($27.52) Over pmt applied to current charges | AE5: =VLOOKUP(B5,'Final Data'!A:H,8,0) -> 8225.115 | AF5: 8225.14 | AG5: =AF5-AE5 -> 0.024978176 | AJ5: =VLOOKUP(B5,'Final Data'!A:I,9,0) -> 8225.115 | AK5: 8225.14 | AL5: =AK5-AJ5 -> 0.024978176 | BH5: =+C5+H5+M5+R5+V5+Z5+AE5+AJ5+AO5+AT5+AX5+BC5 -> 65800.92 | BI5: =+D5+I5+N5+S5+W5+AA5+AF5+AK5+AP5+AU5+AY5+BD5 -> 66929.34 | BJ5: =+E5+J5+O5+T5+X5+AB5+AG5+AL5+AQ5+AV5+AZ5+BE5 -> 1128.4198 | BK5: PYC $1,100.74 received in May'26 STX $27.52 received in May'26
A6: =Rent!B16 -> B103 | B6: =Rent!A16 -> Sally Beauty Supply | C6: =VLOOKUP(B6,'Final Data'!A5:B29,2,0) -> 3311.5729 | D6: 3371 | E6: =D6-C6 -> 59.4271 | F6: CAM $59.43 Over Pmt | H6: =VLOOKUP(B6,'Final Data'!A:C,3,0) -> 3311.5729 | I6: 3371 | J6: =I6-H6 -> 59.4271 | K6: CAM $59.43 Over Pmt | M6: =VLOOKUP(B6,'Final Data'!A:D,4,0) -> 3311.5729 | N6: 3371 | O6: =N6-M6 -> 59.4271 | P6: CAM $59.43 Over Pmt | R6: =VLOOKUP(B6,'Final Data'!A:E,5,0) -> 3311.5729 | S6: 3371 | T6: =S6-R6 -> 59.4271 | U6: CAM $59.43 Over Pmt | V6: =VLOOKUP(B6,'Final Data'!A:G,6,0) -> 3311.5729 | W6: 3371 | X6: =W6-V6 -> 59.4271 | Y6: CAM $59.43 Over Pmt | Z6: =VLOOKUP(B6,'Final Data'!A:G,7,0) -> 3311.5729 | AA6: 3371 | AB6: =AA6-Z6 -> 59.4271 | AC6: CAM $59.43 Over Pmt | AE6: =VLOOKUP(B6,'Final Data'!A:H,8,0) -> 3311.5729 | AF6: 3371 | AG6: =AF6-AE6 -> 59.4271 | AH6: CAM $59.43 Over Pmt | AJ6: =VLOOKUP(B6,'Final Data'!A:I,9,0) -> 3311.5729 | AK6: 2895.56 | AL6: =AK6-AJ6 -> -416.0129 | AM6: CAM credit ($416.01) being applied to BAS & NNN current charges | BH6: =+C6+H6+M6+R6+V6+Z6+AE6+AJ6+AO6+AT6+AX6+BC6 -> 26492.583 | BI6: =+D6+I6+N6+S6+W6+AA6+AF6+AK6+AP6+AU6+AY6+BD6 -> 26492.56 | BJ6: =+E6+J6+O6+T6+X6+AB6+AG6+AL6+AQ6+AV6+AZ6+BE6 -> -0.023198761
A7: =Rent!B17 -> B104 | B7: =Rent!A17 -> Wild Side Smoke Shop | C7: =VLOOKUP(B7,'Final Data'!A6:B30,2,0) -> 3363.2469 | D7: 3091.9 | E7: =D7-C7 -> -271.34687 | F7: CAM ($271.35) Short Pmt | H7: =VLOOKUP(B7,'Final Data'!A:C,3,0) -> 3363.2469 | I7: 3363.25 | J7: =I7-H7 -> 0.0031312417 | M7: =VLOOKUP(B7,'Final Data'!A:D,4,0) -> 3363.2469 | N7: 3363.25 | O7: =N7-M7 -> 0.0031312417 | R7: =VLOOKUP(B7,'Final Data'!A:E,5,0) -> 3363.2469 | S7: 3363.25 | T7: =S7-R7 -> 0.0031312417 | V7: =VLOOKUP(B7,'Final Data'!A:G,6,0) -> 3439.3634 | W7: 3363.25 | X7: =W7-V7 -> -76.113369 | Y7: BAS ($74.26) & STX ($1.85) Short Pmt | Z7: =VLOOKUP(B7,'Final Data'!A:G,7,0) -> 3439.3634 | AA7: 3363.25 | AB7: =AA7-Z7 -> -76.113369 | AC7: BAS ($74.26) & STX ($1.85) Short Pmt | AE7: =VLOOKUP(B7,'Final Data'!A:H,8,0) -> 3439.3634 | AF7: 3363.25 | AG7: =AF7-AE7 -> -76.113369 | AH7: BAS ($74.26) & STX ($1.85) Short Pmt | AJ7: =VLOOKUP(B7,'Final Data'!A:I,9,0) -> 3439.3634 | AK7: 3363.25 | AL7: =AK7-AJ7 -> -76.113369 | AM7: BAS ($74.26) & STX ($1.85) Short Pmt | BH7: =+C7+H7+M7+R7+V7+Z7+AE7+AJ7+AO7+AT7+AX7+BC7 -> 27210.441 | BI7: =+D7+I7+N7+S7+W7+AA7+AF7+AK7+AP7+AU7+AY7+BD7 -> 26634.65 | BJ7: =+E7+J7+O7+T7+X7+AB7+AG7+AL7+AQ7+AV7+AZ7+BE7 -> -575.79095 | BK7: CAM ($345.61) Short Pmt in Jan'26 & June'26 BAS ($222.78) & STX ($7.40) Short Pmt in May'26, June'26 & Aug'26
A8: =Rent!B18 -> B105 | B8: =Rent!A18 -> Green Spa, LLC | C8: =VLOOKUP(B8,'Final Data'!A7:B31,2,0) -> 2815.0955 | D8: 2698.17 | E8: =D8-C8 -> -116.92554 | F8: CAM ($116.92) Short Pmt | H8: =VLOOKUP(B8,'Final Data'!A:C,3,0) -> 2815.0955 | I8: 2937.03 | J8: =I8-H8 -> 121.93446 | K8: CAM $116.92 01/26 past due paid CAM $5.02 Over Pmt | M8: =VLOOKUP(B8,'Final Data'!A:D,4,0) -> 2815.0955 | N8: 2815.1 | O8: =N8-M8 -> 0.0044613863 | R8: =VLOOKUP(B8,'Final Data'!A:E,5,0) -> 2858.2788 | S8: 2815.1 | T8: =S8-R8 -> -43.178789 | U8: BAS ($42.13) Budget vs Pmt STX ($1.70) Short Pmt | V8: =VLOOKUP(B8,'Final Data'!A:G,6,0) -> 2858.2788 | W8: 2885.1 | X8: =W8-V8 -> 26.821211 | Y8: BAS ($42.13) Budget vs Pmt STX $1.70 received PYC $68.14 received | Z8: =VLOOKUP(B8,'Final Data'!A:G,7,0) -> 2858.2788 | AA8: 2885.1 | AB8: =AA8-Z8 -> 26.821211 | AC8: BAS ($42.13) Budget vs Pmt STX ($1.05) Budget vs Pmt CAM $70.01 Over Pmt | AE8: =VLOOKUP(B8,'Final Data'!A:H,8,0) -> 2858.2788 | AF8: 2815.1 | AG8: =AF8-AE8 -> -43.178789 | AH8: BAS ($42.13) Budget vs Pmt STX ($1.05) Budget vs Pmt | AJ8: =VLOOKUP(B8,'Final Data'!A:I,9,0) -> 2858.2788 | AK8: 2815.1 | AL8: =AK8-AJ8 -> -43.178789 | AM8: BAS ($42.13) Budget vs Pmt STX ($1.05) Budget vs Pmt | BH8: =+C8+H8+M8+R8+V8+Z8+AE8+AJ8+AO8+AT8+AX8+BC8 -> 22736.681 | BI8: =+D8+I8+N8+S8+W8+AA8+AF8+AK8+AP8+AU8+AY8+BD8 -> 22665.8 | BJ8: =+E8+J8+O8+T8+X8+AB8+AG8+AL8+AQ8+AV8+AZ8+BE8 -> -70.880559 | BK8: CAM $75.03 Over Pmt in Feb'26 & June'26 BAS ($210.65) Budget vs Pmt in Apr'26 to Aug'26 PYC $68.14 received in May'26 STX ($3.15) Budget vs Pmt in June'26 to Aug'26
B9: John F. Long Foundation | C9: 15.375 | D9: 60 | E9: =D9-C9 -> 44.625 | F9: ELEC $60.00 Past due paid SGN ($15.00) No pmt STX ($0.38) No Pmt | G9: =60-15 -> 45 | H9: =VLOOKUP(B9,'Final Data'!A:C,3,0) -> 15.375 | I9: 0 | J9: =I9-H9 -> -15.375 | K9: SGN ($15.00) No pmt STX ($0.38) No Pmt | M9: =VLOOKUP(B9,'Final Data'!A:D,4,0) -> 15.375 | N9: 0 | O9: =N9-M9 -> -15.375 | P9: SGN ($15.00) No pmt STX ($0.38) No Pmt | R9: =VLOOKUP(B9,'Final Data'!A:E,5,0) -> 15.375 | S9: 60 | T9: =S9-R9 -> 44.625 | U9: SGN $45.00 01/26 to 03/26 past due paid STX ($0.38) Short Pmt | V9: =VLOOKUP(B9,'Final Data'!A:G,6,0) -> 15.375 | W9: 0 | X9: =W9-V9 -> -15.375 | Y9: SGN ($15.00) & STX ($0.38) Short Pmt | Z9: =VLOOKUP(B9,'Final Data'!A:G,7,0) -> 15.375 | AA9: 0 | AB9: =AA9-Z9 -> -15.375 | AC9: SGN ($15.00) & STX ($0.38) Short Pmt | AE9: =VLOOKUP(B9,'Final Data'!A:H,8,0) -> 15.375 | AF9: 0 | AG9: =AF9-AE9 -> -15.375 | AH9: SGN ($15.00) & STX ($0.38) Short Pmt | AJ9: =VLOOKUP(B9,'Final Data'!A:I,9,0) -> 15.375 | AK9: 45 | AL9: =AK9-AJ9 -> 29.625 | AM9: SGN $45.00 past due paid SGN ($15.00) & STX ($0.38) Short Pmt | BH9: =+C9+H9+M9+R9+V9+Z9+AE9+AJ9+AO9+AT9+AX9+BC9 -> 123 | BI9: =+D9+I9+N9+S9+W9+AA9+AF9+AK9+AP9+AU9+AY9+BD9 -> 165 | BJ9: =+E9+J9+O9+T9+X9+AB9+AG9+AL9+AQ9+AV9+AZ9+BE9 -> 42 | BK9: ELEC $60.00 Past due paid in Jan'26 SGN ($15.00) Short Pmt in Aug'26 STX ($3.64) Short Pmt in from Jan'26 to Aug'26
A10: =Rent!B19 -> B106 | B10: =Rent!A19 -> AT&T Mobility | C10: 7038.9703 | D10: 7206.85 | E10: =D10-C10 -> 167.87974 | F10: CAM $167.88 Over Pmt | H10: =VLOOKUP(B10,'Final Data'!A:C,3,0) -> 7038.9703 | I10: 6871.07 | J10: =I10-H10 -> -167.90026 | K10: CAM $167.88 01/26 past due paid | M10: =VLOOKUP(B10,'Final Data'!A:D,4,0) -> 7038.9703 | N10: 7038.96 | O10: =N10-M10 -> -0.010264859 | R10: =VLOOKUP(B10,'Final Data'!A:E,5,0) -> 7038.9703 | S10: 7038.96 | T10: =S10-R10 -> -0.010264859 | V10: =VLOOKUP(B10,'Final Data'!A:G,6,0) -> 7038.9703 | W10: 4880.81 | X10: =W10-V10 -> -2158.1603 | Y10: PYC credit applied to BAS ($613.64) & NNN ($1,491.88) STX ($52.64) Credit applied to current charges | Z10: =VLOOKUP(B10,'Final Data'!A:G,7,0) -> 7038.9703 | AA10: 7038.96 | AB10: =AA10-Z10 -> -0.010264859 | AE10: =VLOOKUP(B10,'Final Data'!A:H,8,0) -> 7038.9703 | AF10: 7038.96 | AG10: =AF10-AE10 -> -0.010264859 | AJ10: =VLOOKUP(B10,'Final Data'!A:I,9,0) -> 7038.9703 | AK10: 0 | AL10: =AK10-AJ10 -> -7038.9703 | AM10: BAS ($5,375.40) & NNN ($1,663.57) Budget vs Pmt | BH10: =+C10+H10+M10+R10+V10+Z10+AE10+AJ10+AO10+AT10+AX10+BC10 -> 56311.762 | BI10: =+D10+I10+N10+S10+W10+AA10+AF10+AK10+AP10+AU10+AY10+BD10 -> 47114.57 | BJ10: =+E10+J10+O10+T10+X10+AB10+AG10+AL10+AQ10+AV10+AZ10+BE10 -> -9197.1921 | BK10: PYC credit applied to BAS ($613.64) & NNN ($1,491.88) in May'26 STX ($52.64) Credit applied to current charges in May'26 BAS ($5,375.40) & NNN ($1,663.57) Budget vs Pmt in Aug'26
A11: =Rent!B20 -> B108 | B11: =Rent!A20 -> Discount Nutrition | C11: =VLOOKUP(B11,'Final Data'!A9:B33,2,0) -> 3381.2829 | D11: 3207.94 | E11: =D11-C11 -> -173.34295 | F11: CAM ($173.34) Short Pmt | H11: =VLOOKUP(B11,'Final Data'!A:C,3,0) -> 3381.2829 | I11: 3207.94 | J11: =I11-H11 -> -173.34295 | K11: CAM ($173.34) Short Pmt | M11: =VLOOKUP(B11,'Final Data'!A:D,4,0) -> 3381.2829 | N11: 3207.94 | O11: =N11-M11 -> -173.34295 | P11: CAM ($173.34) Short Pmt | R11: =VLOOKUP(B11,'Final Data'!A:E,5,0) -> 3431.2107 | S11: 3207.94 | T11: =S11-R11 -> -223.2707 | U11: BAS ($48.71) Short Pmt CAM ($173.34) Short Pmt STX ($1.21) Short Pmt | V11: =VLOOKUP(B11,'Final Data'!A:G,6,0) -> 3431.2107 | W11: 0 | X11: =W11-V11 -> -3431.2107 | Y11: BAS ($2,484.18) & NNN ($947.02) No Pmt | Z11: =VLOOKUP(B11,'Final Data'!A:G,7,0) -> 3431.2107 | AA11: 3207.94 | AB11: =AA11-Z11 -> -223.2707 | AC11: BAS ($48.71) & NNN ($174.55) Short Pmt | AE11: =VLOOKUP(B11,'Final Data'!A:H,8,0) -> 3431.2107 | AF11: 3207.94 | AG11: =AF11-AE11 -> -223.2707 | AH11: BAS ($48.71) & NNN ($174.55) Short Pmt | AJ11: =VLOOKUP(B11,'Final Data'!A:I,9,0) -> 3431.2107 | AK11: 8422.82 | AL11: =AK11-AJ11 -> 4991.6093 | AM11: BAS $2,630.31 & NNN $2,321.77 Past due paid LAT $39.54 received | BH11: =+C11+H11+M11+R11+V11+Z11+AE11+AJ11+AO11+AT11+AX11+BC11 -> 27299.902 | BI11: =+D11+I11+N11+S11+W11+AA11+AF11+AK11+AP11+AU11+AY11+BD11 -> 27670.46 | BJ11: =+E11+J11+O11+T11+X11+AB11+AG11+AL11+AQ11+AV11+AZ11+BE11 -> 370.55766 | BK11: NNN $331.00 Budget vs Pmt LAT $39.54 received in Aug'26
A12: =Rent!B21 -> B109 | B12: =Rent!A21 -> Adapt Chiropractic | C12: 4285.8182 | D12: 4711.62 | E12: =D12-C12 -> 425.80178 | F12: CAM $425.79 Over Pmt | H12: =VLOOKUP(B12,'Final Data'!A:C,3,0) -> 4285.8182 | I12: 3860.04 | J12: =I12-H12 -> -425.77822 | K12: CAM (425.78) Pror month credit applied this month. | M12: =VLOOKUP(B12,'Final Data'!A:D,4,0) -> 4285.8182 | N12: 4285.83 | O12: =N12-M12 -> 0.011776869 | R12: =VLOOKUP(B12,'Final Data'!A:E,5,0) -> 4285.8182 | S12: 4285.83 | T12: =S12-R12 -> 0.011776869 | V12: =VLOOKUP(B12,'Final Data'!A:G,6,0) -> 4285.8182 | W12: 173.99 | X12: =W12-V12 -> -4111.8282 | Y12: PYC credit applied to BAS ($3,699.2) & NNN ($312.35) STX ($100.29) credit applied to current charges | Z12: =VLOOKUP(B12,'Final Data'!A:G,7,0) -> 4285.8182 | AA12: 4285.83 | AB12: =AA12-Z12 -> 0.011776869 | AE12: =VLOOKUP(B12,'Final Data'!A:H,8,0) -> 4285.8182 | AF12: 4285.83 | AG12: =AF12-AE12 -> 0.011776869 | AJ12: =VLOOKUP(B12,'Final Data'!A:I,9,0) -> 4285.8182 | AK12: 4285.83 | AL12: =AK12-AJ12 -> 0.011776869 | BH12: =+C12+H12+M12+R12+V12+Z12+AE12+AJ12+AO12+AT12+AX12+BC12 -> 34286.546 | BI12: =+D12+I12+N12+S12+W12+AA12+AF12+AK12+AP12+AU12+AY12+BD12 -> 30174.8 | BJ12: =+E12+J12+O12+T12+X12+AB12+AG12+AL12+AQ12+AV12+AZ12+BE12 -> -4111.7458 | BK12: PYC credit applied to BAS ($3,699.20) & NNN ($312.35) in May'26 STX ($100.29) credit applied to current charges in May'26
A13: =Rent!B22 -> B111 | B13: =Rent!A22 -> Speakeasy Suites | C13: =VLOOKUP(B13,'Final Data'!A11:B35,2,0) -> 8299.7744 | D13: 8299.78 | E13: =D13-C13 -> 0.0056334591 | H13: =VLOOKUP(B13,'Final Data'!A:C,3,0) -> 8299.7744 | I13: 8299.78 | J13: =I13-H13 -> 0.0056334591 | M13: =VLOOKUP(B13,'Final Data'!A:D,4,0) -> 8299.7744 | N13: 8299.78 | O13: =N13-M13 -> 0.0056334591 | R13: =VLOOKUP(B13,'Final Data'!A:E,5,0) -> 8299.7744 | S13: 8299.78 | T13: =S13-R13 -> 0.0056334591 | V13: =VLOOKUP(B13,'Final Data'!A:G,6,0) -> 8299.7744 | W13: 8299.78 | X13: =W13-V13 -> 0.0056334591 | Z13: =VLOOKUP(B13,'Final Data'!A:G,7,0) -> 8299.7744 | AA13: 8299.78 | AB13: =AA13-Z13 -> 0.0056334591 | AE13: =VLOOKUP(B13,'Final Data'!A:H,8,0) -> 8299.7744 | AF13: 9868.42 | AG13: =AF13-AE13 -> 1568.6456 | AH13: PYC $1,530.38 & STX $38.26 received | AJ13: =VLOOKUP(B13,'Final Data'!A:I,9,0) -> 8299.7744 | AK13: 8299.78 | AL13: =AK13-AJ13 -> 0.0056334591 | BH13: =+C13+H13+M13+R13+V13+Z13+AE13+AJ13+AO13+AT13+AX13+BC13 -> 66398.195 | BI13: =+D13+I13+N13+S13+W13+AA13+AF13+AK13+AP13+AU13+AY13+BD13 -> 67966.88 | BJ13: =+E13+J13+O13+T13+X13+AB13+AG13+AL13+AQ13+AV13+AZ13+BE13 -> 1568.6851 | BK13: PYC $1,530.38 & STX $38.26 received in July'26
B14: Sportsman's Warehouse | C14: 1537.5 | D14: 1537.5 | E14: =D14-C14 -> 0 | H14: =VLOOKUP(B14,'Final Data'!A:C,3,0) -> 1537.5 | I14: 1537.5 | J14: =I14-H14 -> 0 | M14: =VLOOKUP(B14,'Final Data'!A:D,4,0) -> 1537.5 | N14: 1537.5 | O14: =N14-M14 -> 0 | R14: =VLOOKUP(B14,'Final Data'!A:E,5,0) -> 1537.5 | S14: 1537.5 | T14: =S14-R14 -> 0 | V14: =VLOOKUP(B14,'Final Data'!A:G,6,0) -> 1537.5 | W14: 1537.5 | X14: =W14-V14 -> 0 | Z14: =VLOOKUP(B14,'Final Data'!A:G,7,0) -> 1537.5 | AA14: 1537.5 | AB14: =AA14-Z14 -> 0 | AE14: =VLOOKUP(B14,'Final Data'!A:H,8,0) -> 1537.5 | AF14: 1537.5 | AG14: =AF14-AE14 -> 0 | AJ14: =VLOOKUP(B14,'Final Data'!A:I,9,0) -> 1537.5 | AK14: 1537.5 | AL14: =AK14-AJ14 -> 0 | BH14: =+C14+H14+M14+R14+V14+Z14+AE14+AJ14+AO14+AT14+AX14+BC14 -> 12300 | BI14: =+D14+I14+N14+S14+W14+AA14+AF14+AK14+AP14+AU14+AY14+BD14 -> 12300 | BJ14: =+E14+J14+O14+T14+X14+AB14+AG14+AL14+AQ14+AV14+AZ14+BE14 -> 0
A15: =Rent!B23 -> 101 | B15: =Rent!A23 -> Kachina Stained Glass | C15: =VLOOKUP(B15,'Final Data'!A12:B36,2,0) -> 3290.9586 | D15: 3290.87 | E15: =D15-C15 -> -0.088595125 | H15: =VLOOKUP(B15,'Final Data'!A:C,3,0) -> 3290.9586 | I15: 3290.87 | J15: =I15-H15 -> -0.088595125 | M15: =VLOOKUP(B15,'Final Data'!A:D,4,0) -> 3290.9586 | N15: 3290.87 | O15: =N15-M15 -> -0.088595125 | R15: =VLOOKUP(B15,'Final Data'!A:E,5,0) -> 3290.9586 | S15: 3290.87 | T15: =S15-R15 -> -0.088595125 | V15: =VLOOKUP(B15,'Final Data'!A:G,6,0) -> 3290.9586 | W15: 3421.98 | X15: =W15-V15 -> 131.0214 | Y15: PYC $127.91 received STX $3.20 received | Z15: =VLOOKUP(B15,'Final Data'!A:G,7,0) -> 3290.9586 | AA15: 3290.87 | AB15: =AA15-Z15 -> -0.088595125 | AE15: =VLOOKUP(B15,'Final Data'!A:H,8,0) -> 3340.5891 | AF15: 3340.5 | AG15: =AF15-AE15 -> -0.089095125 | AJ15: =VLOOKUP(B15,'Final Data'!A:I,9,0) -> 3340.5891 | AK15: 0 | AL15: =AK15-AJ15 -> -3340.5891 | AM15: BAS ($2,447.45) & NNN ($893.05) Short Pmt | BH15: =+C15+H15+M15+R15+V15+Z15+AE15+AJ15+AO15+AT15+AX15+BC15 -> 26426.93 | BI15: =+D15+I15+N15+S15+W15+AA15+AF15+AK15+AP15+AU15+AY15+BD15 -> 23216.83 | BJ15: =+E15+J15+O15+T15+X15+AB15+AG15+AL15+AQ15+AV15+AZ15+BE15 -> -3210.0998 | BK15: PYC $127.91 received in May'26 STX $3.20 received in May'26 BAS ($2,447.45) & NNN ($893.05) Short Pmt in Aug'26
A16: =Rent!B24 -> 102 | B16: =Rent!A24 -> Zanders Creations | C16: =VLOOKUP(B16,'Final Data'!A13:B37,2,0) -> 3803.2513 | D16: 3803.17 | E16: =D16-C16 -> -0.081276413 | H16: =VLOOKUP(B16,'Final Data'!A:C,3,0) -> 3803.2513 | I16: 3803.17 | J16: =I16-H16 -> -0.081276413 | M16: =VLOOKUP(B16,'Final Data'!A:D,4,0) -> 3803.2513 | N16: 3803.17 | O16: =N16-M16 -> -0.081276413 | R16: =VLOOKUP(B16,'Final Data'!A:E,5,0) -> 3886.2713 | S16: 3803.17 | T16: =S16-R16 -> -83.101276 | U16: BAS ($83.02) Short Pmt | V16: =VLOOKUP(B16,'Final Data'!A:G,6,0) -> 3886.2713 | W16: 4380.69 | X16: =W16-V16 -> 494.41872 | Y16: PYC $397.40 received BAS $83.02 04/26 past due paid STX $12.01 received | Z16: =VLOOKUP(B16,'Final Data'!A:G,7,0) -> 3886.2713 | AA16: 3888.26 | AB16: =AA16-Z16 -> 1.9887236 | AC16: STX $2.00 received | AE16: =VLOOKUP(B16,'Final Data'!A:H,8,0) -> 3886.2713 | AF16: 3888.26 | AG16: =AF16-AE16 -> 1.9887236 | AH16: STX $2.00 received | AJ16: =VLOOKUP(B16,'Final Data'!A:I,9,0) -> 3886.2713 | AK16: 3888.26 | AL16: =AK16-AJ16 -> 1.9887236 | AM16: STX $2.00 received | BH16: =+C16+H16+M16+R16+V16+Z16+AE16+AJ16+AO16+AT16+AX16+BC16 -> 30841.11 | BI16: =+D16+I16+N16+S16+W16+AA16+AF16+AK16+AP16+AU16+AY16+BD16 -> 31258.15 | BJ16: =+E16+J16+O16+T16+X16+AB16+AG16+AL16+AQ16+AV16+AZ16+BE16 -> 417.03979 | BK16: PYC $397.40 received in May'26 STX $18.01 received in May'26 to Aug'26
A17: =Rent!B25 -> 103 | B17: =Rent!A25 -> Brightnow Dental | C17: 9511.6006 | D17: 0 | E17: =D17-C17 -> -9511.6006 | F17: BAS ($7,200.00) & NNN ($2,079.61) No Pmt STX ($231.99) No Budgeted | H17: =VLOOKUP(B17,'Final Data'!A:C,3,0) -> 9511.6006 | I17: 0 | J17: =I17-H17 -> -9511.6006 | K17: BAS ($7,200.00) & NNN ($2311.60) No Pmt | M17: =VLOOKUP(B17,'Final Data'!A:D,4,0) -> 9511.6006 | N17: 0 | O17: =N17-M17 -> -9511.6006 | P17: BAS ($7,200.00) & NNN ($2311.60) No Pmt | R17: =VLOOKUP(B17,'Final Data'!A:E,5,0) -> 9511.6006 | S17: 93000 | T17: =S17-R17 -> 83488.399 | U17: STM $93,000.00 received and not Budgeted BAS ($7,200.00) 04/26 NC Adjustment NNN ($2,311.60) 04/26 NC Adjustment | V17: =VLOOKUP(B17,'Final Data'!A:G,6,0) -> 9511.6006 | W17: 0 | X17: =W17-V17 -> -9511.6006 | Y17: BAS ($7,200.00) & NNN ($2311.60) No Pmt | Z17: =VLOOKUP(B17,'Final Data'!A:G,7,0) -> 9511.6006 | AA17: 0 | AB17: =AA17-Z17 -> -9511.6006 | AC17: BAS ($7,200.00) & NNN ($2311.60) No Pmt | AE17: =VLOOKUP(B17,'Final Data'!A:H,8,0) -> 9511.6006 | AF17: 0 | AG17: =AF17-AE17 -> -9511.6006 | AH17: BAS ($7,200.00) & NNN ($2311.60) No Pmt | AJ17: =VLOOKUP(B17,'Final Data'!A:I,9,0) -> 9511.6006 | AK17: 0 | AL17: =AK17-AJ17 -> -9511.6006 | AM17: BAS ($7,200.00) & NNN ($2,311.60) No Pmt | BH17: =+C17+H17+M17+R17+V17+Z17+AE17+AJ17+AO17+AT17+AX17+BC17 -> 76092.805 | BI17: =+D17+I17+N17+S17+W17+AA17+AF17+AK17+AP17+AU17+AY17+BD17 -> 93000 | BJ17: =+E17+J17+O17+T17+X17+AB17+AG17+AL17+AQ17+AV17+AZ17+BE17 -> 16907.195 | BK17: BAS ($50,400.00) & NNN ($15,949.21) No Pmt in Jan'26 to Mar'26 & May'26 to Aug'26 STX ($231.99) No Budgeted in Jan'26 STM $93,000.00 received and not Budgeted in April'26 BAS ($7,200.00) & NNN ($2,311.60) 04/26 NC Adjustment in Apr'26
A18: =Rent!B26 -> 106 | B18: =Rent!A26 -> Carr Animal Care | C18: 3540.8255 | D18: 3540.83 | E18: =D18-C18 -> 0.0044610389 | H18: =VLOOKUP(B18,'Final Data'!A:C,3,0) -> 3540.8255 | I18: 3540.83 | J18: =I18-H18 -> 0.0044610389 | M18: =VLOOKUP(B18,'Final Data'!A:D,4,0) -> 3540.8255 | N18: 3540.83 | O18: =N18-M18 -> 0.0044610389 | R18: =VLOOKUP(B18,'Final Data'!A:E,5,0) -> 3540.8255 | S18: 3540.83 | T18: =S18-R18 -> 0.0044610389 | V18: =VLOOKUP(B18,'Final Data'!A:G,6,0) -> 3540.8255 | W18: 2457.85 | X18: =W18-V18 -> -1082.9755 | Y18: PYC credit applied to ($511.61) & NNN ($544.96) STX (26.47) credit applied to current charges | Z18: =VLOOKUP(B18,'Final Data'!A:G,7,0) -> 3540.8255 | AA18: 3540.83 | AB18: =AA18-Z18 -> 0.0044610389 | AE18: =VLOOKUP(B18,'Final Data'!A:H,8,0) -> 3540.8255 | AF18: 3540.83 | AG18: =AF18-AE18 -> 0.0044610389 | AJ18: =VLOOKUP(B18,'Final Data'!A:I,9,0) -> 3540.8255 | AK18: 3540.83 | AL18: =AK18-AJ18 -> 0.0044610389 | BH18: =+C18+H18+M18+R18+V18+Z18+AE18+AJ18+AO18+AT18+AX18+BC18 -> 28326.604 | BI18: =+D18+I18+N18+S18+W18+AA18+AF18+AK18+AP18+AU18+AY18+BD18 -> 27243.66 | BJ18: =+E18+J18+O18+T18+X18+AB18+AG18+AL18+AQ18+AV18+AZ18+BE18 -> -1082.9443 | BK18: PYC credit applied to ($511.61) & NNN ($544.96) in May'26 STX (26.47) credit applied to current charges in May'26
A19: =Rent!B27 -> 107 | B19: =Rent!A27 -> Razors Barber Shop | C19: 2723.6704 | D19: 2629.68 | E19: =D19-C19 -> -93.990438 | F19: CAM ($94.00) Short Pmt | H19: =VLOOKUP(B19,'Final Data'!A:C,3,0) -> 2723.6704 | I19: 2629.78 | J19: =I19-H19 -> -93.890438 | K19: CAM ($94.00) Short Pmt | M19: =VLOOKUP(B19,'Final Data'!A:D,4,0) -> 2723.6704 | N19: 2629.78 | O19: =N19-M19 -> -93.890438 | P19: CAM ($94.00) Short Pmt | R19: =VLOOKUP(B19,'Final Data'!A:E,5,0) -> 2783.6637 | S19: 2629.78 | T19: =S19-R19 -> -153.88369 | U19: BAS ($58.53) & STX ($1.47) Short Pmt CAM ($93.90) Short Pmt | V19: =VLOOKUP(B19,'Final Data'!A:G,6,0) -> 2783.6637 | W19: 2629.78 | X19: =W19-V19 -> -153.88369 | Y19: BAS ($58.53) & NNN ($95.37) Short Pmt | Z19: =VLOOKUP(B19,'Final Data'!A:G,7,0) -> 2783.6637 | AA19: 2629.78 | AB19: =AA19-Z19 -> -153.88369 | AC19: BAS ($58.53) & NNN ($95.37) Short Pmt | AE19: =VLOOKUP(B19,'Final Data'!A:H,8,0) -> 2783.6637 | AF19: 3000.29 | AG19: =AF19-AE19 -> 216.62631 | AH19: BAS $216.63 Over Pmt | AJ19: =VLOOKUP(B19,'Final Data'!A:I,9,0) -> 2783.6637 | AK19: 2883.68 | AL19: =AK19-AJ19 -> 100.01631 | AM19: BAS $100.00 Over Pmt | BH19: =+C19+H19+M19+R19+V19+Z19+AE19+AJ19+AO19+AT19+AX19+BC19 -> 22089.33 | BI19: =+D19+I19+N19+S19+W19+AA19+AF19+AK19+AP19+AU19+AY19+BD19 -> 21662.55 | BJ19: =+E19+J19+O19+T19+X19+AB19+AG19+AL19+AQ19+AV19+AZ19+BE19 -> -426.77975 | BK19: BAS ($175.59) Short Pmt in Apr'26 to June'26 NNN ($568.11) Short Pmt from Jan'26 to Apr'26 & June'26 BAS $316.63 Over Pmt in July'26 & Aug'26
A20: =Rent!B28 -> 108 | B20: =Rent!A28 -> CrossFit New Strength | C20: 6899.642 | D20: 6499.12 | E20: =D20-C20 -> -400.52201 | F20: NCA ($400.54) Short Pmt | H20: =VLOOKUP(B20,'Final Data'!A:C,3,0) -> 6899.642 | I20: 6499.12 | J20: =I20-H20 -> -400.52201 | K20: NCA ($400.54) Short Pmt | M20: =VLOOKUP(B20,'Final Data'!A:D,4,0) -> 6899.642 | N20: 6499.12 | O20: =N20-M20 -> -400.52201 | P20: NCA ($400.54) Short Pmt | R20: =VLOOKUP(B20,'Final Data'!A:E,5,0) -> 6899.642 | S20: 12998.24 | T20: =S20-R20 -> 6098.598 | U20: NCA ($400.54) Short Pmt BAS $6,499.12 Over Pmt | V20: =VLOOKUP(B20,'Final Data'!A:G,6,0) -> 6899.642 | W20: 0 | X20: =W20-V20 -> -6899.642 | Y20: BAS ($4,639.93) & NNN ($2,259.73) No Pmt | Z20: =VLOOKUP(B20,'Final Data'!A:G,7,0) -> 6899.642 | AA20: 6499.12 | AB20: =AA20-Z20 -> -400.52201 | AC20: NCA ($400.54) Short Pmt | AE20: =VLOOKUP(B20,'Final Data'!A:H,8,0) -> 6899.642 | AF20: 6499.12 | AG20: =AF20-AE20 -> -400.52201 | AH20: NCA ($400.54) Short Pmt | AJ20: =VLOOKUP(B20,'Final Data'!A:I,9,0) -> 6899.642 | AK20: 0 | AL20: =AK20-AJ20 -> -6899.642 | AM20: BAS ($4,639.93) & NNN ($2,259.73) No Pmt | BH20: =+C20+H20+M20+R20+V20+Z20+AE20+AJ20+AO20+AT20+AX20+BC20 -> 55197.136 | BI20: =+D20+I20+N20+S20+W20+AA20+AF20+AK20+AP20+AU20+AY20+BD20 -> 45493.84 | BJ20: =+E20+J20+O20+T20+X20+AB20+AG20+AL20+AQ20+AV20+AZ20+BE20 -> -9703.2961 | BK20: BAS $6,499.12 Over Pmt in Apr'26 BAS ($9,279.86) No Pmt in May'26 & Aug'26 NNN ($6,922.70) Short Pmt from Jan'26 to Apr'26 & June'26 to Aug'26
A21: =Rent!B29 -> 111 | B21: =Rent!A29 -> Vacant (Time Out Bar) | C21: =VLOOKUP(B21,'Final Data'!A18:B42,2,0) -> 0 | D21: 0 | E21: =D21-C21 -> 0 | H21: =VLOOKUP(B21,'Final Data'!A:C,3,0) -> 0 | I21: 0 | J21: =I21-H21 -> 0 | M21: =VLOOKUP(B21,'Final Data'!A:D,4,0) -> 0 | N21: 0 | O21: =N21-M21 -> 0 | R21: =VLOOKUP(B21,'Final Data'!A:E,5,0) -> 0 | S21: 0 | T21: =S21-R21 -> 0 | V21: =VLOOKUP(B21,'Final Data'!A:G,6,0) -> 0 | W21: 0 | X21: =W21-V21 -> 0 | Z21: =VLOOKUP(B21,'Final Data'!A:G,7,0) -> 0 | AA21: 0 | AB21: =AA21-Z21 -> 0 | AE21: =VLOOKUP(B21,'Final Data'!A:H,8,0) -> 7969.7037 | AF21: 0 | AG21: =AF21-AE21 -> -7969.7037 | AH21: BAS ($6,190.30) & NNN ($1,779.00) No Pmt | AJ21: =VLOOKUP(B21,'Final Data'!A:I,9,0) -> 7969.7037 | AK21: 0 | AL21: =AK21-AJ21 -> -7969.7037 | AM21: BAS ($6,190.30) & NNN ($1,779.00) No Pmt | BH21: =+C21+H21+M21+R21+V21+Z21+AE21+AJ21+AO21+AT21+AX21+BC21 -> 15939.407 | BI21: =+D21+I21+N21+S21+W21+AA21+AF21+AK21+AP21+AU21+AY21+BD21 -> 0 | BJ21: =+E21+J21+O21+T21+X21+AB21+AG21+AL21+AQ21+AV21+AZ21+BE21 -> -15939.407 | BK21: BAS ($12,380.60) & NNN ($3,558.00) No Pmt in July'26 & Aug'26
B22: Walmart | C22: 2050 | D22: 2050 | E22: =D22-C22 -> 0 | H22: =VLOOKUP(B22,'Final Data'!A:C,3,0) -> 2050 | I22: 2050 | J22: =I22-H22 -> 0 | M22: =VLOOKUP(B22,'Final Data'!A:D,4,0) -> 2050 | N22: 2012.5 | O22: =N22-M22 -> -37.5 | P22: SGN ($37.50) Short Pmt | R22: =VLOOKUP(B22,'Final Data'!A:E,5,0) -> 2050 | S22: 2037.5 | T22: =S22-R22 -> -12.5 | U22: STX ($12.50) Short Pmt | V22: =VLOOKUP(B22,'Final Data'!A:G,6,0) -> 2050 | W22: 2037.5 | X22: =W22-V22 -> -12.5 | Y22: STX ($12.50) Short Pmt | Z22: =VLOOKUP(B22,'Final Data'!A:G,7,0) -> 2050 | AA22: 2037.5 | AB22: =AA22-Z22 -> -12.5 | AC22: STX ($12.50) Short Pmt | AE22: =VLOOKUP(B22,'Final Data'!A:H,8,0) -> 2050 | AF22: 2037.5 | AG22: =AF22-AE22 -> -12.5 | AH22: STX ($12.50) Short Pmt | AJ22: =VLOOKUP(B22,'Final Data'!A:I,9,0) -> 2050 | AK22: 2037.5 | AL22: =AK22-AJ22 -> -12.5 | AM22: STX ($12.50) Short Pmt | BH22: =+C22+H22+M22+R22+V22+Z22+AE22+AJ22+AO22+AT22+AX22+BC22 -> 16400 | BI22: =+D22+I22+N22+S22+W22+AA22+AF22+AK22+AP22+AU22+AY22+BD22 -> 16300 | BJ22: =+E22+J22+O22+T22+X22+AB22+AG22+AL22+AQ22+AV22+AZ22+BE22 -> -100 | BK22: SGN ($37.50) Short Pmt in Mar'26 STX ($62.50) Short Pmt in Apr'26 to Aug'26
B23: Tailgate Bar and Grill LLC | J23: =I23-H23 -> 0 | AJ23: 0 | AK23: 15383.27 | AL23: =AK23-AJ23 -> 15383.27 | AM23: BAS $15,516.12 & NNN $3,618.45 Not Budgeted MISC credit ($2,500.00) applied to BAS & NNN ABA ($1,251.30) | BH23: =+C23+H23+M23+R23+V23+Z23+AE23+AJ23+AO23+AT23+AX23+BC23 -> 0 | BI23: =+D23+I23+N23+S23+W23+AA23+AF23+AK23+AP23+AU23+AY23+BD23 -> 15383.27 | BJ23: =+E23+J23+O23+T23+X23+AB23+AG23+AL23+AQ23+AV23+AZ23+BE23 -> 15383.27 | BK23: BAS $15,516.12 & NNN $3,618.45 Not Budgeted in Aug'26 MISC credit ($2,500.00) applied to BAS & NNN in Aug'26 ABA ($1,251.30) in Aug'26
E24: =D24-C24 -> 0
E25: =D25-C25 -> 0
C26: =SUM(C4:C23) -> 140268.53 | D26: =SUM(D4:D23) -> 130948.6 | E26: =SUM(E4:E23) -> -9319.9253 | H26: =SUM(H4:H23) -> 140268.53 | I26: =SUM(I4:I23) -> 130211.53 | J26: =SUM(J4:J23) -> -10056.995 | M26: =SUM(M4:M25) -> 140268.53 | N26: =SUM(N4:N25) -> 145434.29 | O26: =SUM(O4:O25) -> 5165.7647 | R26: =SUM(R4:R25) -> 140504.65 | S26: =SUM(S4:S25) -> 229679.72 | T26: =SUM(T4:T25) -> 89175.07 | V26: =SUM(V4:V25) -> 140580.77 | W26: =SUM(W4:W25) -> 121814.94 | X26: =SUM(X4:X25) -> -18765.826 | Z26: =SUM(Z4:Z23) -> 140580.77 | AA26: =SUM(AA4:AA23) -> 130248.18 | AB26: =SUM(AB4:AB23) -> -10332.586 | AE26: =SUM(AE4:AE23) -> 148600.1 | AF26: =SUM(AF4:AF23) -> 132194.48 | AG26: =SUM(AG4:AG23) -> -16405.62 | AJ26: =SUM(AJ4:AJ23) -> 148600.1 | AK26: =SUM(AK4:AK23) -> 133798.36 | AL26: =SUM(AL4:AL23) -> -14801.74 | BH26: =SUM(BH4:BH23) -> 1139672 | BI26: =SUM(BI4:BI23) -> 1154330.1 | BJ26: =SUM(BJ4:BJ23) -> 14658.142
C27: 140268 | D27: 130948.6 | E27: -9319.4 | H27: 140268 | I27: 130211.53 | J27: -10056.47 | Z27: 140581 | AA27: 130248.18 | AB27: -10332.82 | AE27: 148599 | AF27: 132194.48 | AG27: -16404.52 | AJ27: 148599 | AK27: 133798.36 | AL27: -14800.64 | BH27: 1139669 | BI27: 1154330.1 | BJ27: 14661.1
C28: =C26-C27 -> 0.52527272 | D28: =D26-D27 -> 0 | E28: =E26-E27 -> -0.52527272 | H28: =H26-H27 -> 0.52527272 | I28: =I26-I27 -> 0 | J28: =J26-J27 -> -0.52527272 | M28: 140268 | N28: 145434.29 | O28: 5166.29 | R28: 140505 | S28: 229679.72 | T28: 89174.72 | V28: 140581 | W28: 121814.94 | X28: -18766.06 | Z28: =Z27-Z26 -> 0.23397728 | AA28: =AA27-AA26 -> 0 | AB28: =AB27-AB26 -> -0.23397728 | AE28: =AE27-AE26 -> -1.1002437 | AF28: =AF27-AF26 -> 0 | AG28: =AG27-AG26 -> 1.1002437 | AJ28: =AJ27-AJ26 -> -1.1002437 | AK28: =AK27-AK26 -> 0 | AL28: =AL27-AL26 -> 1.1002437 | BH28: =BH26-BH27 -> 2.9578736 | BI28: =BI26-BI27 -> 0 | BJ28: =BJ26-BJ27 -> -2.9578736
M29: =M28-M26 -> -0.52527272 | N29: =N28-N26 -> 0 | O29: =O28-O26 -> 0.52527272 | R29: =R26-R28 -> -0.35047728 | S29: =S26-S28 -> 0 | T29: =T26-T28 -> 0.35047728 | V29: =V26-V28 -> -0.23397728 | W29: =W26-W28 -> 0 | X29: =X26-X28 -> 0.23397728

Sheet Final Data
A3: Row Labels | B3: Sum of JAN | C3: Sum of FEB | D3: Sum of MARCH | E3: Sum of APRIL | F3: Sum of MAY | G3: Sum of JUNE | H3: Sum of JULY | I3: Sum of AUGUST | J3: Sum of SEPT | K3: Sum of OCT | L3: Sum of NOV | M3: Sum of DEC
A4: Adapt Chiropractic | B4: 4285.8182 | C4: 4285.8182 | D4: 4285.8182 | E4: 4285.8182 | F4: 4285.8182 | G4: 4285.8182 | H4: 4285.8182 | I4: 4285.8182 | J4: 4285.8182 | K4: 4285.8182 | L4: 4285.8182 | M4: 4285.8182
A5: AT&T Mobility | B5: 7038.9703 | C5: 7038.9703 | D5: 7038.9703 | E5: 7038.9703 | F5: 7038.9703 | G5: 7038.9703 | H5: 7038.9703 | I5: 7038.9703 | J5: 7038.9703 | K5: 7038.9703 | L5: 7038.9703 | M5: 7038.9703
A6: Brightnow Dental | B6: 9511.6006 | C6: 9511.6006 | D6: 9511.6006 | E6: 9511.6006 | F6: 9511.6006 | G6: 9511.6006 | H6: 9511.6006 | I6: 9511.6006 | J6: 9511.6006 | K6: 9511.6006 | L6: 9511.6006 | M6: 9511.6006
A7: Carr Animal Care | B7: 3540.8255 | C7: 3540.8255 | D7: 3540.8255 | E7: 3540.8255 | F7: 3540.8255 | G7: 3540.8255 | H7: 3540.8255 | I7: 3540.8255 | J7: 3540.8255 | K7: 3839.0493 | L7: 3839.0493 | M7: 3839.0493
A8: CrossFit New Strength | B8: 6899.642 | C8: 6899.642 | D8: 6899.642 | E8: 6899.642 | F8: 6899.642 | G8: 6899.642 | H8: 6899.642 | I8: 6899.642 | J8: 6899.642 | K8: 6899.642 | L8: 6899.642 | M8: 6899.642
A9: Discount Nutrition | B9: 3381.2829 | C9: 3381.2829 | D9: 3381.2829 | E9: 3431.2107 | F9: 3431.2107 | G9: 3431.2107 | H9: 3431.2107 | I9: 3431.2107 | J9: 3431.2107 | K9: 3431.2107 | L9: 3431.2107 | M9: 3431.2107
A10: EOS Fitness | B10: 66174.826 | C10: 66174.826 | D10: 66174.826 | E10: 66174.826 | F10: 66174.826 | G10: 66174.826 | H10: 66174.826 | I10: 66174.826 | J10: 66174.826 | K10: 66174.826 | L10: 66174.826 | M10: 66174.826
A11: Green Spa, LLC | B11: 2815.0955 | C11: 2815.0955 | D11: 2815.0955 | E11: 2858.2788 | F11: 2858.2788 | G11: 2858.2788 | H11: 2858.2788 | I11: 2858.2788 | J11: 2858.2788 | K11: 2858.2788 | L11: 2858.2788 | M11: 2858.2788
A12: John F. Long Foundation | B12: 15.375 | C12: 15.375 | D12: 15.375 | E12: 15.375 | F12: 15.375 | G12: 15.375 | H12: 15.375 | I12: 15.375 | J12: 15.375 | K12: 15.375 | L12: 15.375 | M12: 129.64575
A13: Kachina Stained Glass | B13: 3290.9586 | C13: 3290.9586 | D13: 3290.9586 | E13: 3290.9586 | F13: 3290.9586 | G13: 3290.9586 | H13: 3340.5891 | I13: 3340.5891 | J13: 3340.5891 | K13: 3340.5891 | L13: 3340.5891 | M13: 3340.5891
A14: Razors Barber Shop | B14: 2723.6704 | C14: 2723.6704 | D14: 2723.6704 | E14: 2783.6637 | F14: 2783.6637 | G14: 2783.6637 | H14: 2783.6637 | I14: 2783.6637 | J14: 2783.6637 | K14: 2783.6637 | L14: 2783.6637 | M14: 2783.6637
A15: Sally Beauty Supply | B15: 3311.5729 | C15: 3311.5729 | D15: 3311.5729 | E15: 3311.5729 | F15: 3311.5729 | G15: 3311.5729 | H15: 3311.5729 | I15: 3311.5729 | J15: 3311.5729 | K15: 3311.5729 | L15: 3311.5729 | M15: 3311.5729
... A29: Difference | B29: 0 | C29: 0 | D29: 0 | E29: 0 | F29: 0 | G29: 0 | H29: 0 | I29: 0 | J29: 0 | K29: 0 | L29: 0 | M29: 0

Sheet Pivot
A3: Row Labels | B3: Sum of JAN | C3: Sum of FEB | D3: Sum of MARCH | E3: Sum of APRIL | F3: Sum of MAY | G3: Sum of JUNE | H3: Sum of JULY | I3: Sum of AUGUST | J3: Sum of SEPT | K3: Sum of OCT | L3: Sum of NOV | M3: Sum of DEC
A4: Adapt Chiropractic | B4: 4285.8182 | C4: 4285.8182 | D4: 4285.8182 | E4: 4285.8182 | F4: 4285.8182 | G4: 4285.8182 | H4: 4285.8182 | I4: 4285.8182 | J4: 4285.8182 | K4: 4285.8182 | L4: 4285.8182 | M4: 4285.8182
A5: AT&T Mobility | B5: 7038.9703 | C5: 7038.9703 | D5: 7038.9703 | E5: 7038.9703 | F5: 7038.9703 | G5: 7038.9703 | H5: 7038.9703 | I5: 7038.9703 | J5: 7038.9703 | K5: 7038.9703 | L5: 7038.9703 | M5: 7038.9703
A6: Brightnow Dental | B6: 9511.6006 | C6: 9511.6006 | D6: 9511.6006 | E6: 9511.6006 | F6: 9511.6006 | G6: 9511.6006 | H6: 9511.6006 | I6: 9511.6006 | J6: 9511.6006 | K6: 9511.6006 | L6: 9511.6006 | M6: 9511.6006
A7: Carr Animal Care | B7: 3540.8255 | C7: 3540.8255 | D7: 3540.8255 | E7: 3540.8255 | F7: 3540.8255 | G7: 3540.8255 | H7: 3540.8255 | I7: 3540.8255 | J7: 3540.8255 | K7: 3839.0493 | L7: 3839.0493 | M7: 3839.0493
A8: CrossFit New Strength | B8: 6899.642 | C8: 6899.642 | D8: 6899.642 | E8: 6899.642 | F8: 6899.642 | G8: 6899.642 | H8: 6899.642 | I8: 6899.642 | J8: 6899.642 | K8: 6899.642 | L8: 6899.642 | M8: 6899.642
A9: Discount Nutrition | B9: 3381.2829 | C9: 3381.2829 | D9: 3381.2829 | E9: 3431.2107 | F9: 3431.2107 | G9: 3431.2107 | H9: 3431.2107 | I9: 3431.2107 | J9: 3431.2107 | K9: 3431.2107 | L9: 3431.2107 | M9: 3431.2107
A10: EOS Fitness | B10: 66174.826 | C10: 66174.826 | D10: 66174.826 | E10: 66174.826 | F10: 66174.826 | G10: 66174.826 | H10: 66174.826 | I10: 66174.826 | J10: 66174.826 | K10: 66174.826 | L10: 66174.826 | M10: 66174.826
A11: Green Spa, LLC | B11: 2815.0955 | C11: 2815.0955 | D11: 2815.0955 | E11: 2858.2788 | F11: 2858.2788 | G11: 2858.2788 | H11: 2858.2788 | I11: 2858.2788 | J11: 2858.2788 | K11: 2858.2788 | L11: 2858.2788 | M11: 2858.2788
A12: John F. Long Foundation | B12: 15.375 | C12: 15.375 | D12: 15.375 | E12: 15.375 | F12: 15.375 | G12: 15.375 | H12: 15.375 | I12: 15.375 | J12: 15.375 | K12: 15.375 | L12: 15.375 | M12: 129.64575
A13: Kachina Stained Glass | B13: 3290.9586 | C13: 3290.9586 | D13: 3290.9586 | E13: 3290.9586 | F13: 3290.9586 | G13: 3290.9586 | H13: 3340.5891 | I13: 3340.5891 | J13: 3340.5891 | K13: 3340.5891 | L13: 3340.5891 | M13: 3340.5891
A14: Razors Barber Shop | B14: 2723.6704 | C14: 2723.6704 | D14: 2723.6704 | E14: 2783.6637 | F14: 2783.6637 | G14: 2783.6637 | H14: 2783.6637 | I14: 2783.6637 | J14: 2783.6637 | K14: 2783.6637 | L14: 2783.6637 | M14: 2783.6637
A15: Sally Beauty Supply | B15: 3311.5729 | C15: 3311.5729 | D15: 3311.5729 | E15: 3311.5729 | F15: 3311.5729 | G15: 3311.5729 | H15: 3311.5729 | I15: 3311.5729 | J15: 3311.5729 | K15: 3311.5729 | L15: 3311.5729 | M15: 3311.5729
... A23: Grand Total | B23: 140268.53 | C23: 140268.53 | D23: 140268.53 | E23: 140504.65 | F23: 140580.77 | G23: 140580.77 | H23: 148600.1 | I23: 148600.1 | J23: 148600.1 | K23: 149088.68 | L23: 149268.65 | M23: 149382.92

Sheet Data
A1: Tenant Name | B1: Particulars | C1: JAN | D1: FEB | E1: MARCH | F1: APRIL | G1: MAY | H1: JUNE | I1: JULY | J1: AUGUST | K1: SEPT | L1: OCT | M1: NOV | N1: DEC
A2: EOS Fitness | B2: Rent | C2: 52938 | D2: 52938 | E2: 52938 | F2: 52938 | G2: 52938 | H2: 52938 | I2: 52938 | J2: 52938 | K2: 52938 | L2: 52938 | M2: 52938 | N2: 52938
A3: Third Pasrty MVS | B3: Rent | C3: 6190.3 | D3: 6190.3 | E3: 6190.3 | F3: 6190.3 | G3: 6190.3 | H3: 6190.3 | I3: 6190.3 | J3: 6190.3 | K3: 6190.3 | L3: 6376.01 | M3: 6376.01 | N3: 6376.01
A4: Sally Beauty Supply | B4: Rent | C4: 2539.06 | D4: 2539.06 | E4: 2539.06 | F4: 2539.06 | G4: 2539.06 | H4: 2539.06 | I4: 2539.06 | J4: 2539.06 | K4: 2539.06 | L4: 2539.06 | M4: 2539.06 | N4: 2539.06
A5: Wild Side Smoke Shop | B5: Rent | C5: 2475.43 | D5: 2475.43 | E5: 2475.43 | F5: 2475.43 | G5: 2549.69 | H5: 2549.69 | I5: 2549.69 | J5: 2549.69 | K5: 2549.69 | L5: 2549.69 | M5: 2549.69 | N5: 2549.69
A6: Green Spa, LLC | B6: Rent | C6: 2106.41 | D6: 2106.41 | E6: 2106.41 | F6: 2148.54 | G6: 2148.54 | H6: 2148.54 | I6: 2148.54 | J6: 2148.54 | K6: 2148.54 | L6: 2148.54 | M6: 2148.54 | N6: 2148.54
A7: AT&T Mobility | B7: Rent | C7: 5375.4 | D7: 5375.4 | E7: 5375.4 | F7: 5375.4 | G7: 5375.4 | H7: 5375.4 | I7: 5375.4 | J7: 5375.4 | K7: 5375.4 | L7: 5375.4 | M7: 5375.4 | N7: 5375.4
A8: Discount Nutrition | B8: Rent | C8: 2435.47 | D8: 2435.47 | E8: 2435.47 | F8: 2484.18 | G8: 2484.18 | H8: 2484.18 | I8: 2484.18 | J8: 2484.18 | K8: 2484.18 | L8: 2484.18 | M8: 2484.18 | N8: 2484.18
A9: Adapt Chiropractic | B9: Rent | C9: 3699.2 | D9: 3699.2 | E9: 3699.2 | F9: 3699.2 | G9: 3699.2 | H9: 3699.2 | I9: 3699.2 | J9: 3699.2 | K9: 3699.2 | L9: 3699.2 | M9: 3699.2 | N9: 3699.2
A10: Speakeasy Suites | B10: Rent | C10: 5852.65 | D10: 5852.65 | E10: 5852.65 | F10: 5852.65 | G10: 5852.65 | H10: 5852.65 | I10: 5852.65 | J10: 5852.65 | K10: 5852.65 | L10: 5852.65 | M10: 6028.23 | N10: 6028.23
A11: Kachina Stained Glass | B11: Rent | C11: 2399.03 | D11: 2399.03 | E11: 2399.03 | F11: 2399.03 | G11: 2399.03 | H11: 2399.03 | I11: 2447.45 | J11: 2447.45 | K11: 2447.45 | L11: 2447.45 | M11: 2447.45 | N11: 2447.45
A12: Zanders Creations | B12: Rent | C12: 2767.06 | D12: 2767.06 | E12: 2767.06 | F12: 2850.08 | G12: 2850.08 | H12: 2850.08 | I12: 2850.08 | J12: 2850.08 | K12: 2850.08 | L12: 2850.08 | M12: 2850.08 | N12: 2850.08
A13: Brightnow Dental | B13: Rent | C13: 7200 | D13: 7200 | E13: 7200 | F13: 7200 | G13: 7200 | H13: 7200 | I13: 7200 | J13: 7200 | K13: 7200 | L13: 7200 | M13: 7200 | N13: 7200
... A16: CrossFit New Strength | B16: Rent | C16: 4639.93 | D16: 4639.93 | E16: 4639.93 | F16: 4639.93 | G16: 4639.93 | H16: 4639.93 | I16: 4639.93 | J16: 4639.93 | K16: 4639.93 | L16: 4639.93 | M16: 4639.93 | N16: 4639.93
A17: Vacant (Time Out Bar) | B17: Rent | I17: 6190.3 | J17: 6190.3 | K17: 6190.3 | L17: 6190.3 | M17: 6190.3 | N17: 6190.3
A18: EOS Fitness | B18: CAM | C18: 4021.8169 | D18: 4021.8169 | E18: 4021.8169 | F18: 4021.8169 | G18: 4021.8169 | H18: 4021.8169 | I18: 4021.8169 | J18: 4021.8169 | K18: 4021.8169 | L18: 4021.8169 | M18: 4021.8169 | N18: 4021.8169
A19: Third Pasrty MVS | B19: CAM | C19: 583.52592 | D19: 583.52592 | E19: 583.52592 | F19: 583.52592 | G19: 583.52592 | H19: 583.52592 | I19: 583.52592 | J19: 583.52592 | K19: 583.52592 | L19: 583.52592 | M19: 583.52592 | N19: 583.52592
A20: Sally Beauty Supply | B20: CAM | C20: 338.83978 | D20: 338.83978 | E20: 338.83978 | F20: 338.83978 | G20: 338.83978 | H20: 338.83978 | I20: 338.83978 | J20: 338.83978 | K20: 338.83978 | L20: 338.83978 | M20: 338.83978 | N20: 338.83978
A21: Wild Side Smoke Shop | B21: CAM | C21: 272.31209 | D21: 272.31209 | E21: 272.31209 | F21: 272.31209 | G21: 272.31209 | H21: 272.31209 | I21: 272.31209 | J21: 272.31209 | K21: 272.31209 | L21: 272.31209 | M21: 272.31209 | N21: 272.31209
A22: Green Spa, LLC | B22: CAM | C22: 216.29361 | D22: 216.29361 | E22: 216.29361 | F22: 216.29361 | G22: 216.29361 | H22: 216.29361 | I22: 216.29361 | J22: 216.29361 | K22: 216.29361 | L22: 216.29361 | M22: 216.29361 | N22: 216.29361
A23: AT&T Mobility | B23: CAM | C23: 450.26332 | D23: 450.26332 | E23: 450.26332 | F23: 450.26332 | G23: 450.26332 | H23: 450.26332 | I23: 450.26332 | J23: 450.26332 | K23: 450.26332 | L23: 450.26332 | M23: 450.26332 | N23: 450.26332
A24: Discount Nutrition | B24: CAM | C24: 291.76296 | D24: 291.76296 | E24: 291.76296 | F24: 291.76296 | G24: 291.76296 | H24: 291.76296 | I24: 291.76296 | J24: 291.76296 | K24: 291.76296 | L24: 291.76296 | M24: 291.76296 | N24: 291.76296
A25: Adapt Chiropractic | B25: CAM | C25: 105.51137 | D25: 105.51137 | E25: 105.51137 | F25: 105.51137 | G25: 105.51137 | H25: 105.51137 | I25: 105.51137 | J25: 105.51137 | K25: 105.51137 | L25: 105.51137 | M25: 105.51137 | N25: 105.51137
A26: Speakeasy Suites | B26: CAM | C26: 758.58369 | D26: 758.58369 | E26: 758.58369 | F26: 758.58369 | G26: 758.58369 | H26: 758.58369 | I26: 758.58369 | J26: 758.58369 | K26: 758.58369 | L26: 758.58369 | M26: 758.58369 | N26: 758.58369
A27: Kachina Stained Glass | B27: CAM | C27: 250.33262 | D27: 250.33262 | E27: 250.33262 | F27: 250.33262 | G27: 250.33262 | H27: 250.33262 | I27: 250.33262 | J27: 250.33262 | K27: 250.33262 | L27: 250.33262 | M27: 250.33262 | N27: 250.33262
A28: Zanders Creations | B28: CAM | C28: 318.79966 | D28: 318.79966 | E28: 318.79966 | F28: 318.79966 | G28: 318.79966 | H28: 318.79966 | I28: 318.79966 | J28: 318.79966 | K28: 318.79966 | L28: 318.79966 | M28: 318.79966 | N28: 318.79966
A29: Brightnow Dental | B29: CAM | C29: 797.7944 | D29: 797.7944 | E29: 797.7944 | F29: 797.7944 | G29: 797.7944 | H29: 797.7944 | I29: 797.7944 | J29: 797.7944 | K29: 797.7944 | L29: 797.7944 | M29: 797.7944 | N29: 797.7944
... A98: EOS Fitness | B98: Signage | C98: 0 | D98: 0 | E98: 0 | F98: 0 | G98: 0 | H98: 0 | I98: 0 | J98: 0 | K98: 0 | L98: 0 | M98: 0 | N98: 0
A99: Third Pasrty MVS | B99: Signage
A100: Sally Beauty Supply | B100: Signage
A101: Wild Side Smoke Shop | B101: Signage
A102: Green Spa, LLC | B102: Signage
A103: AT&T Mobility | B103: Signage | C103: 500 | D103: 500 | E103: 500 | F103: 500 | G103: 500 | H103: 500 | I103: 500 | J103: 500 | K103: 500 | L103: 500 | M103: 500 | N103: 500
A104: Discount Nutrition | B104: Signage
A105: Adapt Chiropractic | B105: Signage
A106: Speakeasy Suites | B106: Signage
A107: Kachina Stained Glass | B107: Signage | C107: 70.83 | D107: 70.83 | E107: 70.83 | F107: 70.83 | G107: 70.83 | H107: 70.83 | I107: 70.83 | J107: 70.83 | K107: 70.83 | L107: 70.83 | M107: 70.83 | N107: 70.83
A108: Zanders Creations | B108: Signage
A109: Brightnow Dental | B109: Signage | C109: 500 | D109: 500 | E109: 500 | F109: 500 | G109: 500 | H109: 500 | I109: 500 | J109: 500 | K109: 500 | L109: 500 | M109: 500 | N109: 500
A110: Carr Animal Care | B110: Signage
A111: Razors Barber Shop | B111: Signage
A112: CrossFit New Strength | B112: Signage
A113: Vacant (Time Out Bar) | B113: Signage
A114: Walmart | B114: Signage | C114: 2000 | D114: 2000 | E114: 2000 | F114: 2000 | G114: 2000 | H114: 2000 | I114: 2000 | J114: 2000 | K114: 2000 | L114: 2000 | M114: 2000 | N114: 2000
A115: Sportsman's Warehouse | B115: Signage | C115: 1500 | D115: 1500 | E115: 1500 | F115: 1500 | G115: 1500 | H115: 1500 | I115: 1500 | J115: 1500 | K115: 1500 | L115: 1500 | M115: 1500 | N115: 1500
A116: John F. Long Foundation | B116: Signage | C116: 15 | D116: 15 | E116: 15 | F116: 15 | G116: 15 | H116: 15 | I116: 15 | J116: 15 | K116: 15 | L116: 15 | M116: 15 | N116: 15
A117: EOS Fitness | B117: S Tax | C117: 1614.02 | D117: 1614.02 | E117: 1614.02 | F117: 1614.02 | G117: 1614.02 | H117: 1614.02 | I117: 1614.02 | J117: 1614.02 | K117: 1614.02 | L117: 1614.02 | M117: 1614.02 | N117: 1614.02
A118: Third Pasrty MVS | B118: S Tax | C118: 200.61256 | D118: 200.61256 | E118: 200.61256 | F118: 200.61256 | G118: 200.61256 | H118: 200.61256 | I118: 200.61256 | J118: 200.61256 | K118: 200.61256 | L118: 205.25531 | M118: 205.25531 | N118: 205.25531
A119: Sally Beauty Supply | B119: S Tax | C119: 80.770071 | D119: 80.770071 | E119: 80.770071 | F119: 80.770071 | G119: 80.770071 | H119: 80.770071 | I119: 80.770071 | J119: 80.770071 | K119: 80.770071 | L119: 80.770071 | M119: 80.770071 | N119: 80.770071
A120: Wild Side Smoke Shop | B120: S Tax | C120: 82.030411 | D120: 82.030411 | E120: 82.030411 | F120: 82.030411 | G120: 83.886911 | H120: 83.886911 | I120: 83.886911 | J120: 83.886911 | K120: 83.886911 | L120: 83.886911 | M120: 83.886911 | N120: 83.886911
A121: Green Spa, LLC | B121: S Tax | C121: 68.660867 | D121: 68.660867 | E121: 68.660867 | F121: 69.714117 | G121: 69.714117 | H121: 69.714117 | I121: 69.714117 | J121: 69.714117 | K121: 69.714117 | L121: 69.714117 | M121: 69.714117 | N121: 69.714117
A122: AT&T Mobility | B122: S Tax | C122: 171.6822 | D122: 171.6822 | E122: 171.6822 | F122: 171.6822 | G122: 171.6822 | H122: 171.6822 | I122: 171.6822 | J122: 171.6822 | K122: 171.6822 | L122: 171.6822 | M122: 171.6822 | N122: 171.6822
A123: Discount Nutrition | B123: S Tax | C123: 82.470316 | D123: 82.470316 | E123: 82.470316 | F123: 83.688066 | G123: 83.688066 | H123: 83.688066 | I123: 83.688066 | J123: 83.688066 | K123: 83.688066 | L123: 83.688066 | M123: 83.688066 | N123: 83.688066
A124: Adapt Chiropractic | B124: S Tax | C124: 104.53215 | D124: 104.53215 | E124: 104.53215 | F124: 104.53215 | G124: 104.53215 | H124: 104.53215 | I124: 104.53215 | J124: 104.53215 | K124: 104.53215 | L124: 104.53215 | M124: 104.53215 | N124: 104.53215
A125: Speakeasy Suites | B125: S Tax | C125: 202.43352 | D125: 202.43352 | E125: 202.43352 | F125: 202.43352 | G125: 202.43352 | H125: 202.43352 | I125: 202.43352 | J125: 202.43352 | K125: 202.43352 | L125: 202.43352 | M125: 206.82302 | N125: 206.82302
... A135: John F. Long Foundation | B135: S Tax | C135: 0.375 | D135: 0.375 | E135: 0.375 | F135: 0.375 | G135: 0.375 | H135: 0.375 | I135: 0.375 | J135: 0.375 | K135: 0.375 | L135: 0.375 | M135: 0.375 | N135: 114.64575
H138: 318.8
F139: =E6-F6 -> -42.13 | G139: 2106.41 | J139: 2106.41
H140: =H28-H138 -> -0.00034119664 | J140: =J6-J139 -> 42.13
G141: =G6-G139 -> 42.13 | H141: 94.84
G142: 26.82 | H142: =H127-H141 -> -2.0777737
G144: =G141-G142 -> 15.31

Sheet Summary
A2: ATHENA PROPERTY MANAGEMENT
A3: GREENFIELD GATEWAY MESA, ARIZONA
A4: PROJECT NO. 801 | T4: Date Revised: | U4: =TODAY() -> 46269
A5: 01/01/26-12/31/26
A6: 2026 OPERATING BUDGET
A8: GENERAL | O8: 2026 | P8: 2025 | Q8: 2025 | R8: BUDGET | S8: VARIANCE | T8: DENOM. | U8: COST
A9: LEDGER | B9: DESCRIPTION | C9: JAN | D9: FEB | E9: MARCH | F9: APRIL | G9: MAY | H9: JUNE | I9: JULY | J9: AUGUST | K9: SEPT | L9: OCT | M9: NOV | N9: DEC | O9: BUDGET | P9: FORECAST | Q9: BUDGET | R9: $ PSF | S9: 2026 BUDGET vs. | T9: SQUARE | U9: PER | V9: % Change
A10: CODE | O10: TOTALS | P10: TOTALS | Q10: TOTALS | S10: 2025 FORECAST | T10: FOOTG. | U10: SQ. FT. | AF10: As of 9/13
B12: INCOME
A13: 40100 | B13: Rental Income | C13: =Rent!E34 -> 105478.32 | D13: =Rent!F34 -> 105478.32 | E13: =Rent!G34 -> 105478.32 | F13: =Rent!H34 -> 105710.71 | G13: =Rent!I34 -> 105784.97 | H13: =Rent!J34 -> 105784.97 | I13: =Rent!K34 -> 112023.69 | J13: =Rent!L34 -> 112023.69 | ... N13: =Rent!P34 -> 112675.93 | O13: =SUM(C13:N13) -> 1307638.9 | P13: 1272840 | Q13: 1350412 | R13: =SUM((O13)/(Rent!#REF!+Rent!#REF!+Rent!$C$15+Rent!$C$17+Rent!$C$18+Rent!$C$19+Rent!$C$20+Rent!$C$21+Rent!$C$22)) -> #REF! | S13: =O13-P13 -> 34798.89 | T13: =Rent!$C$34 -> 67709 | U13: =O13/T13 -> 19.31263
A14: 40140 | B14: Common Area | C14: =CAM!E35 -> 9715.6352 | D14: =CAM!F35 -> 9715.6352 | E14: =CAM!G35 -> 9715.6352 | F14: =CAM!H35 -> 9715.6352 | G14: =CAM!I35 -> 9715.6352 | H14: =CAM!J35 -> 9715.6352 | I14: =CAM!K35 -> 10110.449 | J14: =CAM!L35 -> 10110.449 | ... N14: =CAM!P35 -> 10110.449 | O14: =SUM(C14:N14) -> 118956.5 | P14: 99472 | Q14: 106692 | R14: =SUM((O14)/(Rent!#REF!+Rent!#REF!+Rent!$C$15+Rent!$C$17+Rent!$C$18+Rent!$C$19+Rent!$C$20+Rent!$C$21+Rent!$C$22)) -> #REF! | S14: =P14-O14 -> -19484.504 | T14: =Rent!$C$34 -> 67709 | U14: =O14/T14 -> 1.7568788
A15: 41300 | B15: State and County Rental Tax 3% | C15: ='Sales Tax'!E109 -> 3421.1835 | D15: ='Sales Tax'!F109 -> 3421.1835 | E15: ='Sales Tax'!G109 -> 3421.1835 | F15: ='Sales Tax'!H109 -> 3424.9178 | G15: ='Sales Tax'!I109 -> 3426.7743 | H15: ='Sales Tax'!J109 -> 3426.7743 | I15: ='Sales Tax'!K109 -> 3622.3678 | J15: ='Sales Tax'!L109 -> 3622.3678 | ... N15: ='Sales Tax'!P109 -> 3752.9446 | O15: =SUM(C15:N15) -> 42435.023 | P15: 40624 | Q15: 43176 | R15: =SUM((O15)/(Rent!#REF!+Rent!#REF!+Rent!$C$15+Rent!$C$17+Rent!$C$18+Rent!$C$19+Rent!$C$20+Rent!$C$21+Rent!$C$22)) -> #REF! | S15: =P15-O15 -> -1811.0232 | T15: =Rent!$C$34 -> 67709
A16: 40150 | B16: Prior Year CAM | C16: 0 | D16: 0 | E16: 0 | F16: 0 | G16: 0 | H16: 0 | I16: 0 | J16: 0 | K16: 0 | L16: 0 | M16: 0 | N16: 0 | O16: =SUM(C16:N16) -> 0 | R16: =SUM((O16)/(Rent!#REF!+Rent!#REF!+Rent!$C$15+Rent!$C$17+Rent!$C$18+Rent!$C$19+Rent!$C$20+Rent!$C$21+Rent!$C$22)) -> #REF! | S16: =P16-O16 -> 0 | U16: 0
A17: 40170 | B17: Building CAM | C17: ='Building Expenses'!E35 -> 2845.3195 | D17: ='Building Expenses'!F35 -> 2845.3195 | E17: ='Building Expenses'!G35 -> 2845.3195 | F17: ='Building Expenses'!H35 -> 2845.3195 | G17: ='Building Expenses'!I35 -> 2845.3195 | H17: ='Building Expenses'!J35 -> 2845.3195 | I17: ='Building Expenses'!K35 -> 3338.1127 | J17: ='Building Expenses'!L35 -> 3338.1127 | ... N17: ='Building Expenses'!P35 -> 3338.1127 | O17: =SUM(C17:N17) -> 37100.593 | R17: =SUM(O17)/(Rent!#REF!+Rent!#REF!+Rent!C16+Rent!C17+Rent!C18+Rent!C19+Rent!C20+Rent!C21) -> #REF! | S17: =P17-O17 -> -37100.593 | T17: =Rent!$C$34 -> 67709 | U17: =O17/T17 -> 0.54794182
A18: 40230 | B18: Insurance Income | C18: =Ins.!E35 -> 2545.0928 | D18: =Ins.!F35 -> 2545.0928 | E18: =Ins.!G35 -> 2545.0928 | F18: =Ins.!H35 -> 2545.0928 | G18: =Ins.!I35 -> 2545.0928 | H18: =Ins.!J35 -> 2545.0928 | I18: =Ins.!K35 -> 2663.375 | J18: =Ins.!L35 -> 2663.375 | ... N18: =Ins.!P35 -> 2663.375 | O18: =SUM(C18:N18) -> 31250.807 | P18: 17496 | Q18: 18516 | R18: =SUM(O18)/(Rent!#REF!+Rent!C15+Rent!C17+Rent!C18+Rent!C19+Rent!C20+Rent!C21+Rent!C22) -> #REF! | S18: =P18-O18 -> -13754.807 | T18: =Rent!$C$34 -> 67709 | U18: =O18/T18 -> 0.46154583
A19: 40240 | B19: Property Tax Income | C19: ='RE Tax'!E37 -> 11506.312 | D19: ='RE Tax'!F37 -> 11506.312 | E19: ='RE Tax'!G37 -> 11506.312 | F19: ='RE Tax'!H37 -> 11506.312 | G19: ='RE Tax'!I37 -> 11506.312 | H19: ='RE Tax'!J37 -> 11506.312 | I19: ='RE Tax'!K37 -> 12041.063 | J19: ='RE Tax'!L37 -> 12041.063 | ... N19: ='RE Tax'!P37 -> 12041.063 | O19: =SUM(C19:N19) -> 141284.25 | P19: 157244 | Q19: 165792 | R19: =SUM(O19)/(Rent!#REF!+Rent!C16+Rent!C18+Rent!C19+Rent!C20+Rent!C21+Rent!C22+Rent!C23) -> #REF! | S19: =P19-O19 -> 15959.747 | T19: =Rent!$C$34 -> 67709 | U19: =O19/T19 -> 2.0866392
A20: 40250 | B20: Miscellaneous Income | C20: 0 | D20: 0 | E20: 0 | F20: 0 | G20: 0 | H20: 0 | I20: 0 | J20: 0 | K20: 0 | L20: 0 | M20: 0 | N20: 0 | O20: =SUM(C20:N20) -> 0 | P20: 7280 | Q20: 0 | S20: =P20-O20 -> 7280 | T20: =Rent!$C$34 -> 67709
A21: 40390 | B21: Administrative Fee Income | C21: ='Admin Fee'!E34 -> 170.83229 | D21: ='Admin Fee'!F34 -> 170.83229 | E21: ='Admin Fee'!G34 -> 170.83229 | F21: ='Admin Fee'!H34 -> 170.83229 | G21: ='Admin Fee'!I34 -> 170.83229 | H21: ='Admin Fee'!J34 -> 170.83229 | I21: ='Admin Fee'!K34 -> 215.21264 | J21: ='Admin Fee'!L34 -> 215.21264 | ... N21: ='Admin Fee'!P34 -> 215.21264 | O21: =SUM(C21:N21) -> 2316.2696 | P21: 35017 | Q21: 38976 | R21: =SUM(O21)/(Rent!#REF!+Rent!C17+Rent!C19+Rent!C20+Rent!C21+Rent!C22+Rent!C23+Rent!C24) -> #REF! | S21: =P21-O21 -> 32700.73 | T21: =Rent!$C$34 -> 67709 | U21: =O21/T21 -> 0.034209183
B22: Sign Income | C22: =Signage!E37 -> 4585.83 | D22: =Signage!F37 -> 4585.83 | E22: =Signage!G37 -> 4585.83 | F22: =Signage!H37 -> 4585.83 | G22: =Signage!I37 -> 4585.83 | H22: =Signage!J37 -> 4585.83 | I22: =Signage!K37 -> 4585.83 | J22: =Signage!L37 -> 4585.83 | ... N22: =Signage!P37 -> 4585.83 | O22: =SUM(C22:N22) -> 55029.96 | P22: 50500 | Q22: 54000 | R22: =SUM(O22)/(Rent!#REF!+Rent!C18+Rent!C20+Rent!C21+Rent!C22+Rent!C23+Rent!C24+Rent!C25) -> #REF! | S22: =P22-O22 -> -4529.96 | T22: =Rent!$C$34 -> 67709 | U22: =O22/T22 -> 0.81274218
A23: 40143 | B23: Deferred CAM Recovery | C23: ='Rent Deferral Recovery'!D30 -> 0 | D23: ='Rent Deferral Recovery'!E30 -> 0 | E23: ='Rent Deferral Recovery'!F30 -> 0 | F23: ='Rent Deferral Recovery'!G30 -> 0 | G23: ='Rent Deferral Recovery'!H30 -> 0 | H23: ='Rent Deferral Recovery'!I30 -> 0 | I23: ='Rent Deferral Recovery'!J30 -> 0 | J23: ='Rent Deferral Recovery'!K30 -> 0 | ... N23: ='Rent Deferral Recovery'!O30 -> 0 | O23: =SUM(C23:N23) -> 0 | R23: =SUM(O23)/(Rent!#REF!+Rent!C19+Rent!C21+Rent!C22+Rent!C23+Rent!C24+Rent!C25+Rent!C26) -> #REF! | S23: =P23-O23 -> 0 | T23: =Rent!$C$34 -> 67709 | U23: =O23/T23 -> 0
A24: 40600 | B24: Late Charge Income | C24: 0 | D24: 0 | E24: 0 | F24: 0 | G24: 0 | H24: 0 | I24: 0 | J24: 0 | K24: 0 | L24: 0 | M24: 0 | N24: 0 | O24: =SUM(C24:N24) -> 0 | S24: =P24-O24 -> 0 | T24: =Rent!$C$34 -> 67709 | U24: =O24/T24 -> 0
A25: 40220 | B25: Rent Abatement | C25: 0 | D25: 0 | E25: 0 | F25: 0 | G25: 0 | H25: 0 | I25: 0 | J25: 0 | K25: 0 | L25: 0 | M25: 0 | N25: 0 | O25: =SUM(C25:N25) -> 0 | S25: =P25-O25 -> 0 | T25: =Rent!$C$34 -> 67709
A26: 45000 | B26: Investment Interest | C26: 0 | D26: 0 | E26: 0 | F26: 0 | G26: 0 | H26: 0 | I26: 0 | J26: 0 | K26: 0 | L26: 0 | M26: 0 | N26: 0 | O26: =SUM(C26:N26) -> 0 | P26: 185 | Q26: 0 | S26: =P26-O26 -> 185 | T26: =Rent!$C$34 -> 67709
B27: TOTAL INCOME | C27: =SUM(C13:C25) -> 140268.53 | D27: =SUM(D13:D25) -> 140268.53 | E27: =SUM(E13:E25) -> 140268.53 | F27: =SUM(F13:F25) -> 140504.65 | G27: =SUM(G13:G25) -> 140580.77 | H27: =SUM(H13:H25) -> 140580.77 | I27: =SUM(I13:I25) -> 148600.1 | J27: =SUM(J13:J25) -> 148600.1 | ... O27: =SUM(O13:O25) -> 1736012.3 | P27: =SUM(P13:P26) -> 1680658 | Q27: =SUM(Q13:Q26) -> 1777564 | R27: =SUM(R13:R24) -> #REF! | S27: =SUM(S13:S24) -> 14058.48 | U27: =SUM(U13:U24) -> 25.012587 | V27: =S27/O27 -> 0.0080981455
B29: COMMON AREA EXPENSES
A31: 50150 | B31: Landscape- Tree Trimming | C31: 0 | D31: 0 | E31: 0 | F31: 0 | G31: 0 | H31: 0 | I31: 0 | J31: 0 | K31: 0 | L31: 17000 | M31: 0 | N31: 0 | O31: =SUM(C31:N31) -> 17000 | P31: 17000 | Q31: 17000 | R31: =O31/T31 -> 0.25107445 | S31: =P31-O31 -> 0 | T31: =CAM!C$35 -> 67709 | U31: =O31/T31 -> 0.25107445
A32: 50160 | B32: Landscape Consumables | C32: 0 | D32: 0 | E32: 0 | F32: 0 | G32: 1500 | H32: 0 | I32: 0 | J32: 0 | K32: 0 | L32: 1500 | M32: 0 | N32: 0 | O32: =SUM(C32:N32) -> 3000 | P32: 2599 | Q32: 0 | R32: 0 | S32: =P32-O32 -> -401 | T32: =CAM!C$35 -> 67709 | U32: 0
A33: 50190 | B33: Sprinkler Repairs | E33: 300 | H33: 300 | K33: 300 | N33: 300 | O33: =SUM(C33:N33) -> 1200 | P33: 1400 | Q33: 2400 | R33: =O33/T33 -> 0.017722902 | S33: =P33-O33 -> 200 | T33: =CAM!C$35 -> 67709 | U33: =O33/T33 -> 0.017722902
A34: 50170 | B34: Landscape Maintenance | C34: 1560 | D34: =C34 -> 1560 | E34: =D34 -> 1560 | F34: =E34 -> 1560 | G34: =F34 -> 1560 | H34: =G34 -> 1560 | I34: =H34 -> 1560 | J34: =I34 -> 1560 | K34: =J34 -> 1560 | ... N34: =M34 -> 1560 | O34: =SUM(C34:N34) -> 18720 | P34: 16170 | Q34: 17640 | R34: =O34/T34 -> 0.27647728 | S34: =P34-O34 -> -2550 | T34: =CAM!C$35 -> 67709 | U34: =O34/T34 -> 0.27647728
A35: 50510 | B35: Parking Lot Light Maintenance | C35: 125 | D35: 125 | E35: 125 | F35: 125 | G35: 125 | H35: 125 | I35: 125 | J35: 125 | K35: 125 | L35: 125 | M35: 125 | N35: 125 | O35: =SUM(C35:N35) -> 1500 | P35: 1375 | Q35: 1500 | R35: =O35/T35 -> 0.022153628 | S35: =P35-O35 -> -125 | T35: =CAM!C$35 -> 67709 | U35: =O35/T35 -> 0.022153628
A36: 50520 | B36: Parking Lot Repairs | C36: 0 | D36: 0 | E36: 0 | F36: 0 | G36: 5000 | H36: 0 | I36: 0 | J36: 0 | K36: 0 | L36: 0 | M36: 0 | N36: 0 | O36: =SUM(C36:N36) -> 5000 | P36: 0 | Q36: 5000 | R36: =O36/T36 -> 0.073845427 | S36: =P36-O36 -> -5000 | T36: =CAM!C$35 -> 67709 | U36: =O36/T36 -> 0.073845427
A37: 50530 | B37: Parking Lot Light Repairs | C37: 300 | D37: =C37 -> 300 | E37: =D37 -> 300 | F37: =E37 -> 300 | G37: =F37 -> 300 | H37: =G37 -> 300 | I37: =H37 -> 300 | J37: =I37 -> 300 | K37: =J37 -> 300 | ... N37: =M37 -> 300 | O37: =SUM(C37:N37) -> 3600 | P37: 4000 | Q37: 1200 | R37: =O37/T37 -> 0.053168707 | S37: =P37-O37 -> 400 | T37: =CAM!C$35 -> 67709 | U37: =O37/T37 -> 0.053168707
A38: 51020 | B38: General Maintenance | C38: 300 | D38: =C38 -> 300 | E38: =D38 -> 300 | F38: =E38 -> 300 | G38: =F38 -> 300 | H38: =G38 -> 300 | I38: =H38 -> 300 | J38: =I38 -> 300 | K38: =J38 -> 300 | ... N38: =M38 -> 300 | O38: =SUM(C38:N38) -> 3600 | P38: 3801 | Q38: 3600 | R38: =O38/T38 -> 0.053168707 | S38: =P38-O38 -> 201 | T38: =CAM!C$35 -> 67709 | U38: =O38/T38 -> 0.053168707
A39: 51030 | B39: Miscellaneous Maintenance | C39: 0 | D39: 0 | E39: 0 | F39: 0 | G39: 0 | H39: 0 | I39: 0 | J39: 0 | K39: 0 | L39: 0 | M39: 0 | N39: 0 | O39: =SUM(C39:N39) -> 0 | P39: 1630 | Q39: 0 | S39: =P39-O39 -> 1630 | T39: =CAM!C$35 -> 67709
A40: 51040 | B40: Day Porter | C40: 875 | D40: =C40 -> 875 | E40: =D40 -> 875 | F40: =E40 -> 875 | G40: =F40 -> 875 | H40: =G40 -> 875 | I40: =H40 -> 875 | J40: =I40 -> 875 | K40: =J40 -> 875 | ... N40: =M40 -> 875 | O40: =SUM(C40:N40) -> 10500 | P40: 8668 | Q40: 9456 | R40: =O40/T40 -> 0.1550754 | S40: =P40-O40 -> -1832 | T40: =CAM!C$35 -> 67709 | U40: =O40/T40 -> 0.1550754
A41: 52010 | B41: Janitorial Supplies | D41: =C41 -> 0 | E41: 50 | G41: =F41 -> 0 | H41: 50 | J41: =I41 -> 0 | K41: 50 | M41: =L41 -> 0 | N41: 50 | O41: =SUM(C41:N41) -> 200 | P41: 1045 | Q41: 1140 | R41: =O41/T41 -> 0.0029538171 | S41: =P41-O41 -> 845 | T41: =CAM!C$35 -> 67709 | U41: =O41/T41 -> 0.0029538171
A42: 51050 | B42: Pest Control | C42: 99 | D42: =C42 -> 99 | E42: =D42 -> 99 | F42: =E42 -> 99 | G42: =F42 -> 99 | H42: =G42 -> 99 | I42: =H42 -> 99 | J42: =I42 -> 99 | K42: =J42 -> 99 | ... N42: =M42 -> 99 | O42: =SUM(C42:N42) -> 1188 | P42: 990 | Q42: 1188 | R42: =O42/T42 -> 0.017545673 | S42: =P42-O42 -> -198 | T42: =CAM!C$35 -> 67709 | U42: =O42/T42 -> 0.017545673
A43: 5116 | B43: Security | C43: 0 | D43: 0 | E43: 0 | F43: 0 | G43: 0 | H43: 0 | I43: 0 | J43: 0 | K43: 0 | L43: 0 | M43: 0 | N43: 0 | O43: =SUM(C43:N43) -> 0 | R43: =O43/T43 -> 0 | S43: =P43-O43 -> 0 | T43: =CAM!C$35 -> 67709 | U43: =O43/T43 -> 0
A44: 51080 | B44: Management Fee | C44: 4267 | D44: 4267 | E44: 4267 | F44: 4274 | G44: 4277 | H44: 4277 | I44: 4278 | J44: 4278 | K44: 4278 | L44: 4296 | M44: 4298 | N44: 4302 | O44: =SUM(C44:N44) -> 51359 | P44: 56656 | Q44: 55075 | R44: =O44/T44 -> 0.75852545 | S44: =P44-O44 -> 5297 | T44: =CAM!C$35 -> 67709 | U44: =O44/T44 -> 0.75852545
A45: 51100 | B45: Sidewalk Maintenance | C45: 0 | D45: 0 | E45: 0 | F45: 0 | G45: 0 | H45: 0 | I45: 0 | J45: 0 | K45: 0 | L45: 0 | M45: 0 | N45: 0 | O45: =SUM(C45:N45) -> 0 | R45: =O45/T45 -> 0 | S45: =P45-O45 -> 0 | T45: =CAM!C$35 -> 67709 | U45: =O45/T45 -> 0
A46: 50550 | B46: Sign Maintenance | C46: 205 | D46: =C46 -> 205 | E46: =D46 -> 205 | F46: =E46 -> 205 | G46: =F46 -> 205 | H46: =G46 -> 205 | I46: =H46 -> 205 | J46: =I46 -> 205 | K46: =J46 -> 205 | ... N46: =M46 -> 205 | O46: =SUM(C46:N46) -> 2460 | P46: 2050 | Q46: 2460 | R46: =O46/T46 -> 0.03633195 | S46: =P46-O46 -> -410 | T46: =CAM!C$35 -> 67709 | U46: =O46/T46 -> 0.03633195
A47: 51150 | B47: Sweeping | C47: 590 | D47: =C47 -> 590 | E47: =D47 -> 590 | F47: =E47 -> 590 | G47: =F47 -> 590 | H47: =G47 -> 590 | I47: =H47 -> 590 | J47: =I47 -> 590 | K47: =J47 -> 590 | ... N47: =M47 -> 590 | O47: =SUM(C47:N47) -> 7080 | P47: 238 | Q47: 0 | R47: =O47/T47 -> 0.10456512 | S47: =P47-O47 -> -6842 | T47: =CAM!C$35 -> 67709 | U47: =O47/T47 -> 0.10456512
A48: 51200 | B48: Electrical Repairs/CAM | C48: 0 | D48: 0 | E48: 0 | F48: 0 | G48: 0 | H48: 0 | I48: 0 | J48: 0 | K48: 0 | L48: 0 | M48: 0 | N48: 0 | O48: =SUM(C48:N48) -> 0 | R48: =O48/T48 -> 0 | S48: =P48-O48 -> 0 | T48: =CAM!C$35 -> 67709 | U48: =O48/T48 -> 0
A49: 51220 | B49: Painting | C49: 0 | D49: 0 | E49: 0 | F49: 0 | G49: 0 | H49: 0 | I49: 0 | J49: 0 | K49: 0 | L49: 0 | M49: 0 | N49: 0 | O49: =SUM(C49:N49) -> 0 | R49: =O49/T49 -> 0 | S49: =P49-O49 -> 0 | T49: =CAM!C$35 -> 67709 | U49: =O49/T49 -> 0
A50: 55110 | B50: Electric/Common Area | C50: =1595*103% -> 1642.85 | D50: =C50 -> 1642.85 | E50: =D50 -> 1642.85 | F50: =E50 -> 1642.85 | G50: =F50 -> 1642.85 | H50: =G50 -> 1642.85 | I50: =H50 -> 1642.85 | J50: =I50 -> 1642.85 | K50: =J50 -> 1642.85 | ... N50: =M50 -> 1642.85 | O50: =SUM(C50:N50) -> 19714.2 | P50: 8851 | Q50: 9600 | R50: =O50/T50 -> 0.2911607 | S50: =P50-O50 -> -10863.2 | T50: =CAM!C$35 -> 67709 | U50: =O50/T50 -> 0.2911607
A51: 55140 | B51: Water/Common Area | D51: =C51 -> 0 | E51: =D51 -> 0 | F51: =E51 -> 0 | G51: =F51 -> 0 | H51: =G51 -> 0 | I51: =H51 -> 0 | J51: =I51 -> 0 | K51: =J51 -> 0 | ... N51: =M51 -> 0 | O51: =SUM(C51:N51) -> 0 | R51: =O51/T51 -> 0 | S51: =P51-O51 -> 0 | T51: =CAM!C$35 -> 67709 | U51: =O51/T51 -> 0
A52: 55150 | B52: Water/Fire Department | C52: 0 | D52: 0 | E52: 0 | F52: 0 | G52: 0 | H52: 0 | I52: 0 | J52: 0 | K52: 0 | L52: 0 | M52: 0 | N52: 0 | O52: =SUM(C52:N52) -> 0 | R52: =O52/T52 -> 0 | S52: =P52-O52 -> 0 | T52: =CAM!C$35 -> 67709 | U52: =O52/T52 -> 0
A53: 51070 | B53: Roof Repairs - AMORTIZATION | N53: ='Cap-EX'!F6 -> 11918.625 | O53: =SUM(C53:N53) -> 11918.625 | P53: ='Cap-EX'!F6 -> 11918.625 | R53: =O53/T53 -> 0.17602719 | S53: =P53-O53 -> 0 | T53: =CAM!C$35 -> 67709
S54: =P54-O54 -> 0
B55: SUBTOTAL COMMON AREA | C55: =SUM(C31:C53) -> 9963.85 | D55: =SUM(D31:D53) -> 9963.85 | E55: =SUM(E31:E53) -> 10313.85 | F55: =SUM(F31:F53) -> 9970.85 | G55: =SUM(G31:G53) -> 16473.85 | H55: =SUM(H31:H53) -> 10323.85 | I55: =SUM(I31:I53) -> 9974.85 | J55: =SUM(J31:J53) -> 9974.85 | ... S55: =SUM(S31:S53) -> -19648.2 | U55: =SUM(U31:U52) -> 2.1137692 | V55: =S55/O55 -> -0.12432436
B57: BUILDING EXPENSE
A58: 51060 | B58: Roof Maintenance | C58: 0 | D58: 0 | E58: 0 | F58: 5000 | G58: 0 | H58: 0 | I58: 0 | J58: 0 | K58: 0 | L58: 5000 | M58: 0 | N58: 0 | O58: =SUM(C58:N58) -> 10000 | P58: 0 | Q58: 0 | R58: =O58 -> 10000 | S58: =P58-O58 -> -10000 | T58: =Rent!C38 -> 32709 | U58: =R58/T58 -> 0.30572625
A59: 51070 | B59: Roof Repairs | C59: 0 | D59: 0 | E59: 0 | F59: 0 | G59: 0 | H59: 0 | I59: 0 | J59: 0 | K59: 0 | L59: 0 | M59: 0 | N59: 0 | O59: =SUM(C59:N59) -> 0 | P59: 0 | Q59: 12000 | R59: =O59 -> 0 | S59: =P59-O59 -> 0 | T59: =T58 -> 32709 | U59: =R59/T59 -> 0
A60: 51110 | B60: Monitor Fire Sprinklers | C60: =179*3 -> 537 | F60: =C60 -> 537 | I60: =F60 -> 537 | L60: =I60 -> 537 | O60: =SUM(C60:N60) -> 2148 | P60: 1508 | Q60: 2148 | R60: =O60 -> 2148 | S60: =P60-O60 -> -640 | T60: =T59 -> 32709 | U60: =R60/T60 -> 0.065669999
A61: 51120 | B61: Fire Protection Repairs | C61: 900 | D61: 2500 | E61: 0 | F61: 0 | G61: 0 | H61: 0 | I61: 0 | J61: 0 | K61: 0 | L61: 0 | M61: 0 | N61: 0 | O61: =SUM(C61:N61) -> 3400 | P61: 0 | Q61: 3400 | R61: =O61 -> 3400 | S61: =P61-O61 -> -3400 | T61: =T60 -> 32709 | U61: =R61/T61 -> 0.10394693
A62: 52020 | B62: Backflow Maintenance | C62: 1000 | E62: 0 | F62: 0 | G62: 0 | H62: 0 | I62: 0 | J62: 0 | K62: 0 | L62: 0 | M62: 0 | N62: 0 | O62: =SUM(C62:N62) -> 1000 | P62: 768 | Q62: 850 | R62: =O62 -> 1000 | S62: =P62-O62 -> -232 | T62: =T61 -> 32709 | U62: =R62/T62 -> 0.030572625
A63: 52030 | B63: Backflow Repairs | C63: 500 | D63: 0 | E63: 0 | F63: 0 | G63: 0 | H63: 0 | I63: 0 | J63: 0 | K63: 0 | L63: 0 | M63: 0 | N63: 0 | O63: =SUM(C63:N63) -> 500 | P63: 0 | Q63: 6000 | R63: =O63 -> 500 | S63: =P63-O63 -> -500 | T63: =T62 -> 32709 | U63: =R63/T63 -> 0.015286313
A64: 55120 | B64: Trash Removal | C64: =(479+636)*103% -> 1148.45 | D64: =C64 -> 1148.45 | E64: =D64 -> 1148.45 | F64: =E64 -> 1148.45 | G64: =F64 -> 1148.45 | H64: =G64 -> 1148.45 | I64: =H64 -> 1148.45 | J64: =I64 -> 1148.45 | K64: =J64 -> 1148.45 | ... N64: =M64 -> 1148.45 | O64: =SUM(C64:N64) -> 13781.4 | P64: 12173 | Q64: 13380 | R64: =O64 -> 13781.4 | S64: =P64-O64 -> -1608.4 | T64: =T63 -> 32709 | U64: =R64/T64 -> 0.42133358
A65: 55130 | B65: Water/Building | C65: =2710*103% -> 2791.3 | D65: =C65 -> 2791.3 | E65: =D65 -> 2791.3 | F65: =E65 -> 2791.3 | G65: =F65 -> 2791.3 | H65: =G65 -> 2791.3 | I65: =H65 -> 2791.3 | J65: =I65 -> 2791.3 | K65: =J65 -> 2791.3 | ... N65: =M65 -> 2791.3 | O65: =SUM(C65:N65) -> 33495.6 | P65: 26007 | Q65: 28800 | R65: =O65 -> 33495.6 | S65: =P65-O65 -> -7488.6 | T65: =T64 -> 32709 | U65: =R65/T65 -> 1.0240484
S66: =P66-O66 -> 0
B67: SUBTOTAL BUILDING EXP. | C67: =SUM(C58:C65) -> 6876.75 | D67: =SUM(D58:D65) -> 6439.75 | E67: =SUM(E58:E65) -> 3939.75 | F67: =SUM(F58:F65) -> 9476.75 | G67: =SUM(G58:G65) -> 3939.75 | H67: =SUM(H58:H65) -> 3939.75 | I67: =SUM(I58:I65) -> 4476.75 | J67: =SUM(J58:J65) -> 3939.75 | ... S67: =SUM(S58:S65) -> -23869 | U67: =SUM(U58:U65) -> 1.9665841 | V67: =S67/O67 -> -0.37106879
B69: INSURANCE
A70: 50111 | B70: Insurance - Property | C70: 0 | D70: 0 | E70: 0 | F70: 0 | G70: 0 | H70: 0 | I70: 0 | J70: 0 | K70: 0 | L70: =25572*110% -> 28129.2 | M70: 0 | N70: 0 | O70: =SUM(C70:N70) -> 28129.2 | P70: 0 | Q70: 25000 | R70: =O70/T70 -> 0.41544256 | S70: =O70-P70 -> 28129.2 | T70: =Ins.!C$35 -> 67709 | U70: =O70/T70 -> 0.41544256 | W70: Insurance is impounded by lender; used 2025 actual policy + 110%
A71: 50112 | B71: Insurance - Liability | C71: 0 | D71: 0 | E71: 0 | F71: 0 | G71: 0 | H71: 0 | I71: 0 | J71: 0 | K71: 0 | L71: 0 | M71: 0 | O71: =SUM(C71:N71) -> 0 | P71: 0 | R71: =O71/T71 -> 0 | S71: =O71-P71 -> 0 | T71: =Ins.!C$35 -> 67709 | U71: =O71/T71 -> 0
A72: 50130 | B72: Insurance - Umbrella | C72: 0 | D72: 0 | E72: 0 | F72: 0 | G72: 0 | H72: 0 | I72: 0 | J72: 0 | K72: 0 | L72: =3483*110% -> 3831.3 | M72: 0 | N72: 0 | O72: =SUM(C72:N72) -> 3831.3 | P72: 0 | R72: =O72/T72 -> 0.056584797 | S72: =O72-P72 -> 3831.3 | T72: =Ins.!C$35 -> 67709 | U72: =O72/T72 -> 0.056584797
A73: 50140 | B73: Insurance - Flood & Earthquake | C73: 0 | D73: 0 | E73: 0 | F73: 0 | G73: 0 | H73: 0 | I73: 0 | J73: 0 | K73: 0 | L73: 0 | M73: 0 | N73: 0 | O73: =SUM(C73:N73) -> 0 | R73: =O73/T73 -> 0 | S73: =O73-P73 -> 0 | T73: =Ins.!C$35 -> 67709 | U73: =O73/T73 -> 0
B75: SUBTOTAL INSURANCE | C75: =SUM(C70:C73) -> 0 | D75: =SUM(D70:D73) -> 0 | E75: =SUM(E70:E73) -> 0 | F75: =SUM(F70:F73) -> 0 | G75: =SUM(G70:G73) -> 0 | H75: =SUM(H70:H73) -> 0 | I75: =SUM(I70:I73) -> 0 | J75: =SUM(J70:J73) -> 0 | ... S75: =SUM(S70:S73) -> 31960.5 | U75: =SUM(U70:U73) -> 0.47202735 | V75: =S75/O75 -> 1
B77: PROPERTY TAXES
A78: 54000 | B78: Property Tax | C78: 0 | D78: 0 | E78: =(1392.14+106459.74+35210.26)/2 -> 71531.07 | F78: 0 | G78: 0 | H78: 0 | I78: 0 | J78: 0 | K78: 0 | L78: =E78*102% -> 72961.691 | M78: 0 | N78: =F78*102% -> 0 | O78: =SUM(C78:N78) -> 144492.76 | P78: 142000 | Q78: =P78 -> 142000 | R78: =O78/T78 -> 2.1340259 | S78: =O78-P78 -> 2492.7614 | T78: =T73 -> 67709 | U78: =O78/T78 -> 2.1340259 | W78: Taxes are impunded by lender
B80: SUBTOTAL TAXES | C80: =C78 -> 0 | D80: =D78 -> 0 | E80: =E78 -> 71531.07 | F80: =F78 -> 0 | G80: =G78 -> 0 | H80: =H78 -> 0 | I80: =I78 -> 0 | J80: =J78 -> 0 | ... S80: =S78 -> 2492.7614 | U80: =U78 -> 2.1340259 | V80: =S80/O80 -> 0.017251808
B82: Deduct Amortizations | N82: =-N53 -> -11918.625 | O82: =SUM(C82:N82) -> -11918.625
B84: TOTAL COMMON AREA | C84: =C55+C75+C80+C67 -> 16840.6 | D84: =D55+D75+D80+D67 -> 16403.6 | E84: =E55+E75+E80+E67 -> 85784.67 | F84: =F55+F75+F80+F67 -> 19447.6 | G84: =G55+G75+G80+G67 -> 20413.6 | H84: =H55+H75+H80+H67 -> 14263.6 | I84: =I55+I75+I80+I67 -> 14451.6 | J84: =J55+J75+J80+J67 -> 13914.6 | ... N84: =N55+N75+N80+N67 -> 26207.225 | O84: =O55+O67+O75+O80 -> 398818.09 | P84: =P55+P75+P67+P80 -> 320847.62 | Q84: =Q55+Q75+Q80+Q67 -> 360837 | R84: =R55+R75+R80 -> 4.8958497 | S84: =S55+S75+S80 -> 14805.061 | U84: =U55+U75+U80 -> 4.7198225 | V84: =S84/O84 -> 0.037122342
B86: GROSS CASH FLOW | C86: =C27-C84 -> 123427.93 | D86: =D27-D84 -> 123864.93 | E86: =E27-E84 -> 54483.855 | F86: =F27-F84 -> 121057.05 | G86: =G27-G84 -> 120167.17 | H86: =H27-H84 -> 126317.17 | I86: =I27-I84 -> 134148.5 | J86: =J27-J84 -> 134685.5 | ... M86: =M27-M84 -> 135334.05 | N86: =N27-N84-N82 -> 135094.32 | O86: =O27-O84-O82 -> 1349112.8 | P86: =P27-P84 -> 1359810.4 | Q86: =Q27-Q84 -> 1416727 | R86: =R27-R84 -> #REF! | S86: =Q27-S84 -> 1762758.9
B88: OWNER EXPENSE
A89: 70210 | B89: General Repairs and Maint. | C89: 0 | D89: 0 | E89: 0 | F89: 0 | G89: 0 | H89: 0 | I89: 0 | J89: 0 | K89: 0 | L89: 0 | M89: 0 | N89: 0 | O89: =SUM(C89:N89) -> 0 | P89: 0 | R89: =O89/CAM!$C$35 -> 0 | S89: =O89-P89 -> 0
A90: 70220 | B90: Legal Fees | C90: 0 | D90: 0 | E90: 0 | F90: 0 | G90: 0 | H90: 0 | I90: 0 | J90: 0 | K90: 0 | L90: 0 | M90: 0 | N90: 0 | O90: =SUM(C90:N90) -> 0 | P90: 0 | R90: =O90/CAM!$C$35 -> 0 | S90: =O90-P90 -> 0
A91: 70230 | B91: Other Professional Fees | C91: 0 | D91: 0 | E91: 0 | F91: 0 | G91: 0 | H91: 0 | I91: 0 | J91: 0 | K91: 0 | L91: 0 | M91: 0 | N91: 0 | O91: =SUM(C91:N91) -> 0 | P91: 0 | R91: =O91/CAM!$C$35 -> 0 | S91: =O91-P91 -> 0
A92: 70240 | B92: General and Administrative | C92: 0 | D92: 0 | E92: 0 | F92: 0 | G92: 0 | H92: 0 | I92: 0 | J92: 0 | K92: 0 | L92: 0 | M92: 0 | N92: 0 | O92: =SUM(C92:N92) -> 0 | P92: 0 | R92: =O92/CAM!$C$35 -> 0 | S92: =O92-P92 -> 0
A93: 70250 | B93: Other Expenses | C93: 0 | D93: 0 | E93: 0 | F93: 0 | G93: 0 | H93: 0 | I93: 0 | J93: 0 | K93: 0 | L93: 0 | M93: 0 | N93: 0 | O93: =SUM(C93:N93) -> 0 | P93: 1299 | Q93: 0 | S93: =O93-P93 -> -1299 | W93: NMK: Included as per Forecast Report
A94: 70320 | B94: Utilities Expense | C94: 0 | D94: 0 | E94: 0 | F94: 0 | G94: 0 | H94: 0 | I94: 0 | J94: 0 | K94: 0 | L94: 0 | M94: 0 | N94: 0 | O94: =SUM(C94:N94) -> 0 | P94: 0 | R94: =O94/CAM!$C$35 -> 0 | S94: =O94-P94 -> 0
A95: 70280 | B95: Bank Charges | C95: 2000 | D95: =C95 -> 2000 | E95: =D95 -> 2000 | F95: =E95 -> 2000 | G95: =F95 -> 2000 | H95: =G95 -> 2000 | I95: =H95 -> 2000 | J95: =I95 -> 2000 | K95: =J95 -> 2000 | ... N95: =M95 -> 2000 | O95: =SUM(C95:N95) -> 24000 | P95: 11272 | Q95: 0 | R95: =O95/CAM!$C$35 -> 0.35445805 | S95: =O95-P95 -> 12728
A96: 70370 | B96: License & Permit Fees | C96: 0 | D96: 0 | E96: 0 | F96: 0 | G96: 0 | H96: 0 | I96: 0 | J96: 0 | K96: 0 | L96: 0 | M96: 0 | N96: 0 | O96: =SUM(C96:N96) -> 0 | P96: 0 | R96: =O96/CAM!$C$35 -> 0 | S96: =O96-P96 -> 0
A97: 70380 | B97: Ground Rent | C97: 0 | D97: 0 | E97: 0 | F97: 0 | G97: 0 | H97: 0 | I97: 0 | J97: 0 | K97: 0 | L97: 0 | M97: 0 | N97: 0 | O97: =SUM(C97:N97) -> 0 | P97: 0 | R97: =O97/CAM!$C$35 -> 0 | S97: =O97-P97 -> 0
A98: 70400 | B98: State Franchise Taxes | C98: 0 | D98: 0 | E98: 0 | F98: 0 | G98: 0 | H98: 0 | I98: 0 | J98: 0 | K98: 0 | L98: 0 | M98: 0 | N98: 0 | O98: =SUM(C98:N98) -> 0 | P98: 0 | R98: =O98/CAM!$C$35 -> 0 | S98: =O98-P98 -> 0
A99: 70440 | B99: Property Tax-Owner | C99: 0 | D99: 0 | E99: 0 | F99: 0 | G99: 0 | H99: 0 | I99: 0 | J99: 0 | K99: 0 | L99: 0 | M99: 0 | N99: 0 | O99: =SUM(C99:N99) -> 0 | P99: 0 | S99: =O99-P99 -> 0
A100: 70410 | B100: CITY SALES TAX | C100: =C15 -> 3421.1835 | D100: =D15 -> 3421.1835 | E100: =E15 -> 3421.1835 | F100: =F15 -> 3424.9178 | G100: =G15 -> 3426.7743 | H100: =H15 -> 3426.7743 | I100: =I15 -> 3622.3678 | J100: =J15 -> 3622.3678 | ... N100: =N15 -> 3752.9446 | O100: =SUM(C100:N100) -> 42435.023 | P100: 22480 | Q100: 0 | S100: =O100-P100 -> 19955.023 | W100: NMK: Included as per Forecast Report
A101: 70461 | B101: Pass Through Entity Tax | C101: 0 | D101: 0 | E101: 0 | F101: 0 | G101: 0 | H101: 0 | I101: 0 | J101: 0 | K101: 0 | L101: 0 | M101: 0 | N101: 0 | O101: =SUM(C101:N101) -> 0 | P101: 0 | R101: =O101/CAM!$C$35 -> 0 | S101: =O101-P101 -> 0
B103: TOTAL OWNER EXPENSE | C103: =SUM(C89:C101) -> 5421.1835 | D103: =SUM(D89:D101) -> 5421.1835 | E103: =SUM(E89:E101) -> 5421.1835 | F103: =SUM(F89:F101) -> 5424.9178 | G103: =SUM(G89:G101) -> 5426.7743 | H103: =SUM(H89:H101) -> 5426.7743 | I103: =SUM(I89:I101) -> 5622.3678 | J103: =SUM(J89:J101) -> 5622.3678 | ... S103: =SUM(S89:S101) -> 31384.023
B105: NET OPERATING INCOME | C105: =C86-C103 -> 118006.74 | D105: =D86-D103 -> 118443.74 | E105: =E86-E103 -> 49062.672 | F105: =F86-F103 -> 115632.13 | G105: =G86-G103 -> 114740.39 | H105: =H86-H103 -> 120890.39 | I105: =I86-I103 -> 128526.13 | J105: =J86-J103 -> 129063.13 | ... S105: =S86-S103 -> 1731374.9 | V105: =S105/O105 -> 1.3498128
B107: INTEREST EXPENSE
A108: 70110 | B108: Interest Expense - PNC | C108: 33450.04 | D108: =C108 -> 33450.04 | E108: =D108 -> 33450.04 | F108: =E108 -> 33450.04 | G108: =F108 -> 33450.04 | H108: =G108 -> 33450.04 | I108: =H108 -> 33450.04 | J108: =I108 -> 33450.04 | K108: =J108 -> 33450.04 | ... N108: =M108 -> 33450.04 | O108: =SUM(C108:N108) -> 401400.48 | P108: 396029 | Q108: 401400 | S108: =O108-P108 -> 5371.48
A109: 70111 | B109: Interest Expense - Second Loan | O109: =SUM(C109:N109) -> 0 | P109: 0 | S109: =O109-P109 -> 0
A110: 70182 | B110: Interest Expense - Mega Bank | C110: 0 | D110: 0 | E110: 0 | F110: 0 | G110: 0 | H110: 0 | I110: 0 | J110: 0 | K110: 0 | L110: 0 | M110: 0 | N110: 0 | O110: =SUM(C110:N110) -> 0 | P110: 0 | S110: =O110-P110 -> 0
B112: INTEREST EXPENSE | C112: =SUM(C108:C110) -> 33450.04 | D112: =SUM(D108:D110) -> 33450.04 | E112: =SUM(E108:E110) -> 33450.04 | F112: =SUM(F108:F110) -> 33450.04 | G112: =SUM(G108:G110) -> 33450.04 | H112: =SUM(H108:H110) -> 33450.04 | I112: =SUM(I108:I110) -> 33450.04 | J112: =SUM(J108:J110) -> 33450.04 | ... Q112: =SUM(Q108:Q110) -> 401400 | S112: =SUM(S108:S110) -> 5371.48 | V112: =S112/O112 -> 0.013381847
B114: TOTAL INTEREST EXPENSE
B116: CAPITAL EXPENSES
A117: 10410 | B117: Escrow-Property Tax | C117: 12316 | D117: =C117 -> 12316 | E117: =D117-E78 -> -59215.07 | F117: =D117 -> 12316 | G117: =F117 -> 12316 | H117: =G117 -> 12316 | I117: =H117 -> 12316 | J117: =I117 -> 12316 | K117: =J117 -> 12316 | L117: =K117-L78 -> -60645.691 | M117: =K117 -> 12316 | N117: =M117 -> 12316 | O117: =SUM(C117:N117) -> 3299.2386 | P117: 115067 | Q117: 0 | S117: =O117-P117 -> -111767.76 | W117: Escrow numbers provided by Athena Accounting
A118: 10400 | B118: Escrow - Capital Improvement | C118: 0 | D118: 0 | E118: 0 | F118: 0 | G118: 0 | H118: 0 | I118: 0 | J118: 0 | K118: 0 | L118: 0 | M118: 0 | N118: =M118-N79 -> 0 | O118: =SUM(C118:N118) -> 0 | S118: =O118-P118 -> 0
A119: 10460 | B119: Escrow-Insurance | C119: 2487 | D119: =C119 -> 2487 | E119: =D119-E70 -> 2487 | F119: =D119 -> 2487 | G119: =F119 -> 2487 | H119: =G119 -> 2487 | I119: =H119 -> 2487 | J119: =I119 -> 2487 | K119: =J119-L75 -> -29473.5 | L119: =J119 -> 2487 | M119: =L119 -> 2487 | N119: =M119 -> 2487 | O119: =SUM(C119:N119) -> -2116.5 | P119: 37774 | Q119: -3 | S119: =O119-P119 -> -39890.5
A120: 10470 | B120: Escrow-Other (Reserves) | C120: 564.24 | D120: =C120 -> 564.24 | E120: =D120 -> 564.24 | F120: =E120 -> 564.24 | G120: =F120 -> 564.24 | H120: =G120 -> 564.24 | I120: =H120 -> 564.24 | J120: =I120 -> 564.24 | K120: =J120 -> 564.24 | ... N120: =M120 -> 564.24 | O120: =SUM(C120:N120) -> 6770.88 | P120: 398459 | Q120: 6768 | S120: =O120-P120 -> -391688.12
...

Sheet Cap-EX
B3: AMORTIZED PROJECTS
B5: DESCRIPTION | C5: GL CODE | D5: TOTAL PROJECT COST | F5: COST PER YR | G5: # OF YEARS | H5: DATES | K5: NOTES
B6: Roof | C6: =Summary!A53 -> 51070 | D6: 113849 | F6: =(D6-18500)/8 -> 11918.625 | G6: 9 | H6: 2020-2028 | K6: $18,500 billed in 2020;
B7: Cameras | C7: N/A | D7: 35000 | F7: =IFERROR(D7/G7,0) -> 7000 | G7: 5 | H7: 2020-2024 | K7: Project completed
F8: =IFERROR(D8/G8,0) -> 0
B13: CAP-EX
C15: ACTUAL | D15: ACTUAL | E15: FORECAST | F15: BUDGET | G15: PROJECTED | H15: PROJECTED | I15: PROJECTED | J15: PROJECTED | M15: past / project future projects
B16: DESCRIPTION | C16: 2022 | D16: 2023 | E16: 2024 | F16: 2025 | G16: 2026 | H16: 2027 | I16: 2028 | J16: 2029 | K16: NOTES
B17: Monument Sign upgrade
B18: Electrical/Lighting
B19: Roof
B20: Paint
B21: Landscape
B22: HVAC
B23: Plumbing
B24: Parking lot Slurry
B28: MAINTENANCE TRACKING
B30: DESCRIPTION | D30: COMPLETED | E30: DUE | G30: VENDOR | I30: NOTES
B31: 5-Year Fire Inspection | F31: TBD
B32: Slurry Seal | F32: TBD
B33: Roof | F33: TBD
B34: Paint | F34: TBD
B35: LED | F35: TBD

Sheet Rent
P1: =Summary!T4 -> Date Revised: | Q1: =Summary!U4 -> 46269 | R1: =Summary!W4 -> 0
A2: =Summary!$A2 -> ATHENA PROPERTY MANAGEMENT
A3: =Summary!$A3 -> GREENFIELD GATEWAY MESA, ARIZONA
A4: =Summary!$A4 -> PROJECT NO. 801
A5: =Summary!$A5 -> 01/01/26-12/31/26
A6: =Summary!$A6 -> 2026 OPERATING BUDGET
A9: TENANT | B9: SUITE | C9: SQUARE | D9: RATE | E9: JAN | F9: FEB | G9: MARCH | H9: APRIL | I9: MAY | J9: JUNE | K9: JULY | L9: AUGUST | M9: SEPT | N9: OCT | O9: NOV | P9: DEC | Q9: TOTALS | R9: NOTES
B10: # | C10: FOOTAGE
A12: BASE RENT
A14: EOS Fitness | B14: Major A | C14: 35000 | D14: =P14*12/C14 -> 18.150171 | E14: 52938 | F14: =E14 -> 52938 | G14: =F14 -> 52938 | H14: =G14 -> 52938 | I14: =H14 -> 52938 | J14: =I14 -> 52938 | K14: =J14 -> 52938 | L14: =K14 -> 52938 | M14: =L14 -> 52938 | ... P14: =O14 -> 52938 | Q14: =SUM(E14:P14) -> 635256 | R14: Next increase 5/1/2029 for $58,231.00 or 1.66 Psf
A15: Third Pasrty MVS | B15: B101 | C15: 3000 | D15: =P15*12/C15 -> 25.50404 | E15: 6190.3 | F15: =E15 -> 6190.3 | G15: =F15 -> 6190.3 | H15: =G15 -> 6190.3 | I15: =H15 -> 6190.3 | J15: =I15 -> 6190.3 | K15: =J15 -> 6190.3 | L15: =K15 -> 6190.3 | M15: =L15 -> 6190.3 | N15: 6376.01 | O15: =N15 -> 6376.01 | P15: =O15 -> 6376.01 | Q15: =SUM(E15:P15) -> 74840.73 | R15: Rent increase 10/1/2026 $6,376.01 or 2.13 Psf
A16: Sally Beauty Supply | B16: B103 | C16: 1625 | D16: =P16*12/C16 -> 18.749982 | E16: 2539.06 | F16: =E16 -> 2539.06 | G16: =F16 -> 2539.06 | H16: =G16 -> 2539.06 | I16: =H16 -> 2539.06 | J16: =I16 -> 2539.06 | K16: =J16 -> 2539.06 | L16: =K16 -> 2539.06 | M16: =L16 -> 2539.06 | ... O16: =N16 -> 2539.06 | P16: 2539.06 | Q16: =SUM(E16:P16) -> 30468.72 | R16: Next increase 12/1/2027 (fixed for 2 years)
A17: Wild Side Smoke Shop | B17: B104 | C17: 1400 | D17: =P17*12/C17 -> 21.854486 | E17: 2475.43 | F17: =E17 -> 2475.43 | G17: =F17 -> 2475.43 | H17: =G17 -> 2475.43 | I17: 2549.69 | J17: =I17 -> 2549.69 | K17: =J17 -> 2549.69 | L17: =K17 -> 2549.69 | M17: =L17 -> 2549.69 | N17: =M17 -> 2549.69 | O17: =N17 -> 2549.69 | P17: =O17 -> 2549.69 | Q17: =SUM(E17:P17) -> 30299.24 | R17: Rent increase 5/1/2026 $2,549.69 or 1.82 Psf
A18: Green Spa, LLC | B18: B105 | C18: 1112 | D18: =P18*12/C18 -> 23.185683 | E18: 2106.41 | F18: =E18 -> 2106.41 | G18: =F18 -> 2106.41 | H18: 2148.54 | I18: =H18 -> 2148.54 | J18: =I18 -> 2148.54 | K18: =J18 -> 2148.54 | L18: =K18 -> 2148.54 | M18: =L18 -> 2148.54 | N18: =M18 -> 2148.54 | O18: =N18 -> 2148.54 | P18: =O18 -> 2148.54 | Q18: =SUM(E18:P18) -> 25656.09 | R18: Lease expires 3/31/2026 OPT 4/1/2026 for $2,148.54 or 1.93 Psf
A19: AT&T Mobility | B19: B106 | C19: 2494 | D19: =P19*12/C19 -> 25.863994 | E19: 5375.4 | F19: =E19 -> 5375.4 | G19: =F19 -> 5375.4 | H19: =G19 -> 5375.4 | I19: =H19 -> 5375.4 | J19: =I19 -> 5375.4 | K19: =J19 -> 5375.4 | L19: =K19 -> 5375.4 | M19: =L19 -> 5375.4 | ... P19: =O19 -> 5375.4 | Q19: =SUM(E19:P19) -> 64504.8 | R19: Lease Expires 3/31/2026 OPT 4/1/2026 FMV
A20: Discount Nutrition | B20: B108 | C20: 1500 | D20: =P20*12/C20 -> 19.87344 | E20: 2435.47 | F20: =E20 -> 2435.47 | G20: =F20 -> 2435.47 | H20: 2484.18 | I20: =H20 -> 2484.18 | J20: =I20 -> 2484.18 | K20: =J20 -> 2484.18 | L20: =K20 -> 2484.18 | M20: =L20 -> 2484.18 | N20: =M20 -> 2484.18 | O20: =N20 -> 2484.18 | P20: =O20 -> 2484.18 | Q20: =SUM(E20:P20) -> 29664.03 | R20: Rent increase 4/1/2026 $2,484.18 or 1.66 Psf
A21: Adapt Chiropractic | B21: B109 | C21: 1734 | D21: =P21*12/C21 -> 25.6 | E21: 3699.2 | F21: =E21 -> 3699.2 | G21: =F21 -> 3699.2 | H21: =G21 -> 3699.2 | I21: =H21 -> 3699.2 | J21: =I21 -> 3699.2 | K21: =J21 -> 3699.2 | L21: 3699.2 | M21: =L21 -> 3699.2 | N21: =M21 -> 3699.2 | O21: =N21 -> 3699.2 | P21: =O21 -> 3699.2 | Q21: =SUM(E21:P21) -> 44390.4 | R21: 2nd Amendment executed; rent fixed through expiration
A22: Speakeasy Suites | B22: B111 | C22: 3900 | D22: =P22*12/C22 -> 18.5484 | E22: 5852.65 | F22: =E22 -> 5852.65 | G22: =F22 -> 5852.65 | H22: =G22 -> 5852.65 | I22: =H22 -> 5852.65 | J22: =I22 -> 5852.65 | K22: =J22 -> 5852.65 | L22: =K22 -> 5852.65 | M22: =L22 -> 5852.65 | N22: =M22 -> 5852.65 | O22: 6028.23 | P22: =O22 -> 6028.23 | Q22: =SUM(E22:P22) -> 70582.96 | R22: Expires on 10/31/2026 OPT 11/1/2026 for $6,028.23 or 1.55 Psf
A23: Kachina Stained Glass | B23: 101 | C23: 1287 | D23: =P23*12/C23 -> 22.820047 | E23: 2399.03 | F23: =E23 -> 2399.03 | G23: =F23 -> 2399.03 | H23: =G23 -> 2399.03 | I23: =H23 -> 2399.03 | J23: =I23 -> 2399.03 | K23: 2447.45 | L23: =K23 -> 2447.45 | M23: =L23 -> 2447.45 | N23: =M23 -> 2447.45 | O23: =N23 -> 2447.45 | P23: =O23 -> 2447.45 | Q23: =SUM(E23:P23) -> 29078.88 | R23: Rent increase on 7/1/2026 $2,447.45 or 1.90 Psf
A24: Zanders Creations | B24: 102 | C24: 1639 | D24: =P24*12/C24 -> 20.866968 | E24: 2767.06 | F24: =E24 -> 2767.06 | G24: =F24 -> 2767.06 | H24: 2850.08 | I24: =H24 -> 2850.08 | J24: =I24 -> 2850.08 | K24: =J24 -> 2850.08 | L24: =K24 -> 2850.08 | M24: =L24 -> 2850.08 | N24: =M24 -> 2850.08 | O24: =N24 -> 2850.08 | P24: =O24 -> 2850.08 | Q24: =SUM(E24:P24) -> 33951.9 | R24: Lease expires 3/31/2026 OPT 4/1/2026 for $2,850.08 or 1.74 Psf
A25: Brightnow Dental | B25: 103 | C25: 3600 | D25: =P25*12/C25 -> 24 | E25: 7200 | F25: =E25 -> 7200 | G25: =F25 -> 7200 | H25: =G25 -> 7200 | I25: =H25 -> 7200 | J25: =I25 -> 7200 | K25: =J25 -> 7200 | L25: =K25 -> 7200 | M25: =L25 -> 7200 | ... P25: =O25 -> 7200 | Q25: =SUM(E25:P25) -> 86400 | R25: Lease expires 12/31/2027 OPT 1/1/2028 for $7,200.00 or 2.00 Psf
A26: Carr Animal Care | B26: 106 | C26: 1587 | D26: =P26*12/C26 -> 24.2 | E26: 2909.5 | F26: =E26 -> 2909.5 | G26: =F26 -> 2909.5 | H26: =G26 -> 2909.5 | I26: =H26 -> 2909.5 | J26: =I26 -> 2909.5 | K26: =J26 -> 2909.5 | L26: =K26 -> 2909.5 | M26: =L26 -> 2909.5 | N26: 3200.45 | O26: =N26 -> 3200.45 | P26: =O26 -> 3200.45 | Q26: =SUM(E26:P26) -> 35786.85 | R26: Rent increase 10/1/2026 $3,200.45 or 2.02 Psf
A27: Razors Barber Shop | B27: 107 | C27: 1300 | D27: =P27*12/C27 -> 18.5484 | E27: 1950.88 | F27: =E27 -> 1950.88 | G27: =F27 -> 1950.88 | H27: 2009.41 | I27: =H27 -> 2009.41 | J27: =I27 -> 2009.41 | K27: =J27 -> 2009.41 | L27: =K27 -> 2009.41 | M27: =L27 -> 2009.41 | N27: =M27 -> 2009.41 | O27: =N27 -> 2009.41 | P27: =O27 -> 2009.41 | Q27: =SUM(E27:P27) -> 23937.33 | R27: Rent increase 4/1/2026 $2,009.41 or 1.55 Psf
A28: CrossFit New Strength | B28: 108 | C28: 3524 | D28: =P28*12/C28 -> 15.799989 | E28: 4639.93 | F28: =E28 -> 4639.93 | G28: =F28 -> 4639.93 | H28: =G28 -> 4639.93 | I28: =H28 -> 4639.93 | J28: =I28 -> 4639.93 | K28: =J28 -> 4639.93 | L28: =K28 -> 4639.93 | M28: =L28 -> 4639.93 | ... P28: =O28 -> 4639.93 | Q28: =SUM(E28:P28) -> 55679.16 | R28: Lease expired 8/31/2025; Tenant is MTM
A29: Vacant (Time Out Bar) | B29: 111 | C29: 3007 | D29: =P29*12/C29 -> 24.703558 | K29: 6190.3 | L29: =K29 -> 6190.3 | M29: =L29 -> 6190.3 | N29: =M29 -> 6190.3 | O29: =N29 -> 6190.3 | P29: =O29 -> 6190.3 | Q29: =SUM(E29:P29) -> 37141.8 | R29: Tenant Vacated - Assuming new tenant in July
Q30: =SUM(E30:P30) -> 0
A34: TOTALS | C34: =SUM(C14:C33) -> 67709 | E34: =SUM(E14:E33) -> 105478.32 | F34: =SUM(F14:F33) -> 105478.32 | G34: =SUM(G14:G33) -> 105478.32 | H34: =SUM(H14:H33) -> 105710.71 | I34: =SUM(I14:I33) -> 105784.97 | J34: =SUM(J14:J33) -> 105784.97 | K34: =SUM(K14:K33) -> 112023.69 | L34: =SUM(L14:L33) -> 112023.69 | ... P34: =SUM(P14:P33) -> 112675.93 | Q34: =SUM(Q14:Q29) -> 1307638.9
A38: Less EOS | C38: =C34-C14 -> 32709 | E38: =E34-E14 -> 52540.32 | F38: =F34-F14 -> 52540.32 | G38: =G34-G14 -> 52540.32 | H38: =H34-H14 -> 52772.71 | I38: =I34-I14 -> 52846.97 | J38: =J34-J14 -> 52846.97 | K38: =K34-K14 -> 59085.69 | L38: =L34-L14 -> 59085.69 | ... P38: =P34-P14 -> 59737.93
D41: NMK Tie-Out | E41: =E34-Summary!C13 -> 0 | F41: =F34-Summary!D13 -> 0 | G41: =G34-Summary!E13 -> 0 | H41: =H34-Summary!F13 -> 0 | I41: =I34-Summary!G13 -> 0 | J41: =J34-Summary!H13 -> 0 | K41: =K34-Summary!I13 -> 0 | L41: =L34-Summary!J13 -> 0 | ... P41: =P34-Summary!N13 -> 0

Sheet Rent Deferral Recovery
O1: =Summary!T4 -> Date Revised: | P1: =Summary!U4 -> 46269 | Q1: =Summary!W4 -> 0
A2: =Summary!$A2 -> ATHENA PROPERTY MANAGEMENT
A3: =Summary!$A3 -> GREENFIELD GATEWAY MESA, ARIZONA
A4: =Summary!$A4 -> PROJECT NO. 801
A5: =Summary!$A5 -> 01/01/26-12/31/26
A6: =Summary!$A6 -> 2026 OPERATING BUDGET
A9: TENANT | B9: SUITE | C9: SQUARE | D9: JAN | E9: FEB | F9: MARCH | G9: APRIL | H9: MAY | I9: JUNE | J9: JULY | K9: AUGUST | L9: SEPT | M9: OCT | N9: NOV | O9: DEC | P9: TOTALS
B10: # | C10: FOOTAGE
A12: DEFERRED RENT RECOVERY
A14: None at this time | D14: 0 | E14: 0 | F14: 0 | G14: 0 | H14: 0 | I14: 0 | J14: 0 | K14: 0 | L14: 0 | M14: 0 | N14: 0 | O14: 0 | P14: =SUM(D14:O14) -> 0
A19: TOTALS | C19: =SUM(C14:C14) -> 0 | D19: =SUM(D14:D14) -> 0 | E19: =SUM(E14:E14) -> 0 | F19: =SUM(F14:F14) -> 0 | G19: =SUM(G14:G14) -> 0 | H19: =SUM(H14:H14) -> 0 | I19: =SUM(I14:I14) -> 0 | J19: =SUM(J14:J14) -> 0 | ... P19: =SUM(P14:P14) -> 0
A25: TENANT | B25: SUITE | C25: SQUARE | D25: JAN | E25: FEB | F25: MARCH | G25: APRIL | H25: MAY | I25: JUNE | J25: JULY | K25: AUGUST | L25: SEPT | M25: OCT | N25: NOV | O25: DEC | P25: TOTALS
B26: # | C26: FOOTAGE
A28: DEFERRED CAM RECOVERY
A30: None at this time | D30: 0 | E30: 0 | F30: 0 | G30: 0 | H30: 0 | I30: 0 | J30: 0 | K30: 0 | L30: 0 | M30: 0 | N30: 0 | O30: 0 | P30: =SUM(D30:O30) -> 0
A35: TOTALS | C35: =SUM(C30:C30) -> 0 | D35: =SUM(D30:D30) -> 0 | E35: =SUM(E30:E30) -> 0 | F35: =SUM(F30:F30) -> 0 | G35: =SUM(G30:G30) -> 0 | H35: =SUM(H30:H30) -> 0 | I35: =SUM(I30:I30) -> 0 | J35: =SUM(J30:J30) -> 0 | ... P35: =SUM(P30:P30) -> 0

Sheet CAM
P1: =Summary!T4 -> Date Revised: | Q1: =Summary!U4 -> 46269 | V1: =Summary!W4 -> 0
A2: =Summary!$A2 -> ATHENA PROPERTY MANAGEMENT
A3: =Summary!$A3 -> GREENFIELD GATEWAY MESA, ARIZONA
A4: =Summary!$A4 -> PROJECT NO. 801
A5: =Summary!$A5 -> 01/01/26-12/31/26
A6: =Summary!$A6 -> 2026 OPERATING BUDGET
A9: TENANT | B9: SUITE | C9: SQUARE | D9: % OF | E9: JAN | F9: FEB | G9: MARCH | H9: APRIL | I9: MAY | J9: JUNE | K9: JULY | L9: AUGUST | M9: SEPT | N9: OCT | O9: NOV | P9: DEC | Q9: TOTALS | R9: 2015 | S9: TOTALS (2014) | T9: 2014 | U9: Current | V9: Variance
B10: # | C10: FOOTAGE | D10: TOTAL
A12: COMMON AREA MAINTENANCE
A14: =Rent!A14 -> EOS Fitness | B14: =Rent!B14 -> Major A | C14: =Rent!C14 -> 35000 | D14: =C14/($C$35) -> 0.51691799 | E14: =IF(Rent!E14=0,0,('Tenant Charges'!$F10)) -> 4021.8169 | F14: =IF(Rent!F14=0,0,('Tenant Charges'!$F10)) -> 4021.8169 | G14: =IF(Rent!G14=0,0,('Tenant Charges'!$F10)) -> 4021.8169 | H14: =IF(Rent!H14=0,0,('Tenant Charges'!$F10)) -> 4021.8169 | I14: =IF(Rent!I14=0,0,('Tenant Charges'!$F10)) -> 4021.8169 | J14: =IF(Rent!J14=0,0,('Tenant Charges'!$F10)) -> 4021.8169 | K14: =IF(Rent!K14=0,0,('Tenant Charges'!$F10)) -> 4021.8169 | L14: =IF(Rent!L14=0,0,('Tenant Charges'!$F10)) -> 4021.8169 | ... P14: =IF(Rent!P14=0,0,('Tenant Charges'!$F10)) -> 4021.8169 | Q14: =SUM(E14:P14) -> 48261.803 | S14: =SUM(F14:Q14) -> 92501.789 | U14: 3669.63 | V14: =U14-P14 -> -352.18692
A15: =Rent!A15 -> Third Pasrty MVS | B15: =Rent!B15 -> B101 | C15: =Rent!C15 -> 3000 | D15: =C15/$C$35 -> 0.044307256 | E15: =IF(Rent!E15=0,0,('Tenant Charges'!$F11)) -> 583.52592 | F15: =IF(Rent!F15=0,0,('Tenant Charges'!$F11)) -> 583.52592 | G15: =IF(Rent!G15=0,0,('Tenant Charges'!$F11)) -> 583.52592 | H15: =IF(Rent!H15=0,0,('Tenant Charges'!$F11)) -> 583.52592 | I15: =IF(Rent!I15=0,0,('Tenant Charges'!$F11)) -> 583.52592 | J15: =IF(Rent!J15=0,0,('Tenant Charges'!$F11)) -> 583.52592 | K15: =IF(Rent!K15=0,0,('Tenant Charges'!$F11)) -> 583.52592 | L15: =IF(Rent!L15=0,0,('Tenant Charges'!$F11)) -> 583.52592 | ... P15: =IF(Rent!P15=0,0,('Tenant Charges'!$F11)) -> 583.52592 | Q15: =SUM(E15:P15) -> 7002.311 | R15: =Q15/C15 -> 2.3341037 | S15: =262.76*12 -> 3153.12 | T15: =S15/C15 -> 1.05104 | U15: 478.87 | V15: =U15-P15 -> -104.65592
A16: =Rent!A16 -> Sally Beauty Supply | B16: =Rent!B16 -> B103 | C16: =Rent!C16 -> 1625 | D16: =C16/$C$35 -> 0.023999764 | E16: =IF(Rent!E16=0,0,('Tenant Charges'!$F12)) -> 338.83978 | F16: =IF(Rent!F16=0,0,('Tenant Charges'!$F12)) -> 338.83978 | G16: =IF(Rent!G16=0,0,('Tenant Charges'!$F12)) -> 338.83978 | H16: =IF(Rent!H16=0,0,('Tenant Charges'!$F12)) -> 338.83978 | I16: =IF(Rent!I16=0,0,('Tenant Charges'!$F12)) -> 338.83978 | J16: =IF(Rent!J16=0,0,('Tenant Charges'!$F12)) -> 338.83978 | K16: =IF(Rent!K16=0,0,('Tenant Charges'!$F12)) -> 338.83978 | L16: =IF(Rent!L16=0,0,('Tenant Charges'!$F12)) -> 338.83978 | ... P16: =IF(Rent!P16=0,0,('Tenant Charges'!$F12)) -> 338.83978 | Q16: =SUM(E16:P16) -> 4066.0774 | R16: =Q16/C16 -> 2.5022015 | S16: 0 | T16: =S16/C16 -> 0 | U16: 259.39 | V16: =U16-P16 -> -79.449781
A17: =Rent!A17 -> Wild Side Smoke Shop | B17: =Rent!B17 -> B104 | C17: =Rent!C17 -> 1400 | D17: =C17/$C$35 -> 0.020676719 | E17: =IF(Rent!E17=0,0,('Tenant Charges'!$F13)) -> 272.31209 | F17: =IF(Rent!F17=0,0,('Tenant Charges'!$F13)) -> 272.31209 | G17: =IF(Rent!G17=0,0,('Tenant Charges'!$F13)) -> 272.31209 | H17: =IF(Rent!H17=0,0,('Tenant Charges'!$F13)) -> 272.31209 | I17: =IF(Rent!I17=0,0,('Tenant Charges'!$F13)) -> 272.31209 | J17: =IF(Rent!J17=0,0,('Tenant Charges'!$F13)) -> 272.31209 | K17: =IF(Rent!K17=0,0,('Tenant Charges'!$F13)) -> 272.31209 | L17: =IF(Rent!L17=0,0,('Tenant Charges'!$F13)) -> 272.31209 | ... P17: =IF(Rent!P17=0,0,('Tenant Charges'!$F13)) -> 272.31209 | Q17: =SUM(E17:P17) -> 3267.7451 | U17: 223.47 | V17: =U17-P17 -> -48.842094
A18: =Rent!A18 -> Green Spa, LLC | B18: =Rent!B18 -> B105 | C18: =Rent!C18 -> 1112 | D18: =C18/$C$35 -> 0.016423223 | E18: =IF(Rent!E18=0,0,('Tenant Charges'!$F14)) -> 216.29361 | F18: =IF(Rent!F18=0,0,('Tenant Charges'!$F14)) -> 216.29361 | G18: =IF(Rent!G18=0,0,('Tenant Charges'!$F14)) -> 216.29361 | H18: =IF(Rent!H18=0,0,('Tenant Charges'!$F14)) -> 216.29361 | I18: =IF(Rent!I18=0,0,('Tenant Charges'!$F14)) -> 216.29361 | J18: =IF(Rent!J18=0,0,('Tenant Charges'!$F14)) -> 216.29361 | K18: =IF(Rent!K18=0,0,('Tenant Charges'!$F14)) -> 216.29361 | L18: =IF(Rent!L18=0,0,('Tenant Charges'!$F14)) -> 216.29361 | ... P18: =IF(Rent!P18=0,0,('Tenant Charges'!$F14)) -> 216.29361 | Q18: =SUM(E18:P18) -> 2595.5233 | R18: =Q18/C18 -> 2.3341037 | S18: =191.06*12 -> 2292.72 | T18: =S18/C18 -> 2.0617986 | U18: 177.5 | V18: =U18-P18 -> -38.793606
A19: =Rent!A19 -> AT&T Mobility | B19: =Rent!B19 -> B106 | C19: =Rent!C19 -> 2494 | D19: =C19/$C$35 -> 0.036834099 | E19: =IF(Rent!E19=0,0,('Tenant Charges'!$F15)) -> 450.26332 | F19: =IF(Rent!F19=0,0,('Tenant Charges'!$F15)) -> 450.26332 | G19: =IF(Rent!G19=0,0,('Tenant Charges'!$F15)) -> 450.26332 | H19: =IF(Rent!H19=0,0,('Tenant Charges'!$F15)) -> 450.26332 | I19: =IF(Rent!I19=0,0,('Tenant Charges'!$F15)) -> 450.26332 | J19: =IF(Rent!J19=0,0,('Tenant Charges'!$F15)) -> 450.26332 | K19: =IF(Rent!K19=0,0,('Tenant Charges'!$F15)) -> 450.26332 | L19: =IF(Rent!L19=0,0,('Tenant Charges'!$F15)) -> 450.26332 | ... P19: =IF(Rent!P19=0,0,('Tenant Charges'!$F15)) -> 450.26332 | Q19: =SUM(E19:P19) -> 5403.1599 | R19: =Q19/C19 -> 2.1664635 | S19: 0 | T19: =S19/C19 -> 0 | U19: 398.1 | V19: =U19-P19 -> -52.163324
A20: =Rent!A20 -> Discount Nutrition | B20: =Rent!B20 -> B108 | C20: =Rent!C20 -> 1500 | D20: =C20/$C$35 -> 0.022153628 | E20: =IF(Rent!E20=0,0,('Tenant Charges'!$F16)) -> 291.76296 | F20: =IF(Rent!F20=0,0,('Tenant Charges'!$F16)) -> 291.76296 | G20: =IF(Rent!G20=0,0,('Tenant Charges'!$F16)) -> 291.76296 | H20: =IF(Rent!H20=0,0,('Tenant Charges'!$F16)) -> 291.76296 | I20: =IF(Rent!I20=0,0,('Tenant Charges'!$F16)) -> 291.76296 | J20: =IF(Rent!J20=0,0,('Tenant Charges'!$F16)) -> 291.76296 | K20: =IF(Rent!K20=0,0,('Tenant Charges'!$F16)) -> 291.76296 | L20: =IF(Rent!L20=0,0,('Tenant Charges'!$F16)) -> 291.76296 | ... P20: =IF(Rent!P20=0,0,('Tenant Charges'!$F16)) -> 291.76296 | Q20: =SUM(E20:P20) -> 3501.1555 | R20: =Q20/C20 -> 2.3341037 | S20: 0 | T20: =S20/C20 -> 0 | U20: 239.43 | V20: =U20-P20 -> -52.332958
A21: =Rent!A21 -> Adapt Chiropractic | B21: =Rent!B21 -> B109 | C21: =Rent!C21 -> 1734 | D21: =C21/$C$35 -> 0.025609594 | E21: =IF(Rent!E21=0,0,('Tenant Charges'!$F17)) -> 105.51137 | F21: =IF(Rent!F21=0,0,('Tenant Charges'!$F17)) -> 105.51137 | G21: =IF(Rent!G21=0,0,('Tenant Charges'!$F17)) -> 105.51137 | H21: =IF(Rent!H21=0,0,('Tenant Charges'!$F17)) -> 105.51137 | I21: =IF(Rent!I21=0,0,('Tenant Charges'!$F17)) -> 105.51137 | J21: =IF(Rent!J21=0,0,('Tenant Charges'!$F17)) -> 105.51137 | K21: =IF(Rent!K21=0,0,('Tenant Charges'!$F17)) -> 105.51137 | L21: =IF(Rent!L21=0,0,('Tenant Charges'!$F17)) -> 105.51137 | ... P21: =IF(Rent!P21=0,0,('Tenant Charges'!$F17)) -> 105.51137 | Q21: =SUM(E21:P21) -> 1266.1365 | R21: =Q21/C21 -> 0.73018251 | S21: =206.7*12 -> 2480.4 | T21: =S21/C21 -> 1.4304498 | U21: 276.79 | V21: =U21-P21 -> 171.27863
A22: =Rent!A22 -> Speakeasy Suites | B22: =Rent!B22 -> B111 | C22: =Rent!C22 -> 3900 | D22: =C22/$C$35 -> 0.057599433 | E22: =IF(Rent!E22=0,0,('Tenant Charges'!$F18)) -> 758.58369 | F22: =IF(Rent!F22=0,0,('Tenant Charges'!$F18)) -> 758.58369 | G22: =IF(Rent!G22=0,0,('Tenant Charges'!$F18)) -> 758.58369 | H22: =IF(Rent!H22=0,0,('Tenant Charges'!$F18)) -> 758.58369 | I22: =IF(Rent!I22=0,0,('Tenant Charges'!$F18)) -> 758.58369 | J22: =IF(Rent!J22=0,0,('Tenant Charges'!$F18)) -> 758.58369 | K22: =IF(Rent!K22=0,0,('Tenant Charges'!$F18)) -> 758.58369 | L22: =IF(Rent!L22=0,0,('Tenant Charges'!$F18)) -> 758.58369 | ... P22: =IF(Rent!P22=0,0,('Tenant Charges'!$F18)) -> 758.58369 | Q22: =SUM(E22:P22) -> 9103.0043 | R22: =Q22/C22 -> 2.3341037 | S22: =206.7*12 -> 2480.4 | T22: =S22/C22 -> 0.636 | U22: 622.53 | V22: =U22-P22 -> -136.05369
A23: =Rent!A23 -> Kachina Stained Glass | B23: =Rent!B23 -> 101 | C23: =Rent!C23 -> 1287 | D23: =C23/$C$35 -> 0.019007813 | E23: =IF(Rent!E23=0,0,('Tenant Charges'!$F19)) -> 250.33262 | F23: =IF(Rent!F23=0,0,('Tenant Charges'!$F19)) -> 250.33262 | G23: =IF(Rent!G23=0,0,('Tenant Charges'!$F19)) -> 250.33262 | H23: =IF(Rent!H23=0,0,('Tenant Charges'!$F19)) -> 250.33262 | I23: =IF(Rent!I23=0,0,('Tenant Charges'!$F19)) -> 250.33262 | J23: =IF(Rent!J23=0,0,('Tenant Charges'!$F19)) -> 250.33262 | K23: =IF(Rent!K23=0,0,('Tenant Charges'!$F19)) -> 250.33262 | L23: =IF(Rent!L23=0,0,('Tenant Charges'!$F19)) -> 250.33262 | ... P23: =IF(Rent!P23=0,0,('Tenant Charges'!$F19)) -> 250.33262 | Q23: =SUM(E23:P23) -> 3003.9914 | R23: =Q23/C23 -> 2.3341037 | S23: 0 | T23: =S23/C23 -> 0 | U23: 205.43 | V23: =U23-P23 -> -44.902618
A24: =Rent!A24 -> Zanders Creations | B24: =Rent!B24 -> 102 | C24: =Rent!C24 -> 1639 | D24: =C24/$C$35 -> 0.024206531 | E24: =IF(Rent!E24=0,0,('Tenant Charges'!$F20)) -> 318.79966 | F24: =IF(Rent!F24=0,0,('Tenant Charges'!$F20)) -> 318.79966 | G24: =IF(Rent!G24=0,0,('Tenant Charges'!$F20)) -> 318.79966 | H24: =IF(Rent!H24=0,0,('Tenant Charges'!$F20)) -> 318.79966 | I24: =IF(Rent!I24=0,0,('Tenant Charges'!$F20)) -> 318.79966 | J24: =IF(Rent!J24=0,0,('Tenant Charges'!$F20)) -> 318.79966 | K24: =IF(Rent!K24=0,0,('Tenant Charges'!$F20)) -> 318.79966 | L24: =IF(Rent!L24=0,0,('Tenant Charges'!$F20)) -> 318.79966 | ... P24: =IF(Rent!P24=0,0,('Tenant Charges'!$F20)) -> 318.79966 | Q24: =SUM(E24:P24) -> 3825.5959 | U24: 261.62 | V24: =U24-P24 -> -57.179659
A25: =Rent!A25 -> Brightnow Dental | B25: =Rent!B25 -> 103 | C25: =Rent!C25 -> 3600 | D25: =C25/$C$35 -> 0.053168707 | E25: =IF(Rent!E25=0,0,('Tenant Charges'!$F21)) -> 797.7944 | F25: =IF(Rent!F25=0,0,('Tenant Charges'!$F21)) -> 797.7944 | G25: =IF(Rent!G25=0,0,('Tenant Charges'!$F21)) -> 797.7944 | H25: =IF(Rent!H25=0,0,('Tenant Charges'!$F21)) -> 797.7944 | I25: =IF(Rent!I25=0,0,('Tenant Charges'!$F21)) -> 797.7944 | J25: =IF(Rent!J25=0,0,('Tenant Charges'!$F21)) -> 797.7944 | K25: =IF(Rent!K25=0,0,('Tenant Charges'!$F21)) -> 797.7944 | L25: =IF(Rent!L25=0,0,('Tenant Charges'!$F21)) -> 797.7944 | ... P25: =IF(Rent!P25=0,0,('Tenant Charges'!$F21)) -> 797.7944 | Q25: =SUM(E25:P25) -> 9573.5328 | R25: =Q25/C25 -> 2.6593147 | S25: =218.99*12 -> 2627.88 | T25: =S25/C25 -> 0.72996667 | U25: 574.64 | V25: =U25-P25 -> -223.1544
A26: =Rent!A26 -> Carr Animal Care | B26: =Rent!B26 -> 106 | C26: =Rent!C26 -> 1587 | D26: =C26/$C$35 -> 0.023438538 | E26: =IF(Rent!E26=0,0,('Tenant Charges'!$F22)) -> 200.31339 | F26: =IF(Rent!F26=0,0,('Tenant Charges'!$F22)) -> 200.31339 | G26: =IF(Rent!G26=0,0,('Tenant Charges'!$F22)) -> 200.31339 | H26: =IF(Rent!H26=0,0,('Tenant Charges'!$F22)) -> 200.31339 | I26: =IF(Rent!I26=0,0,('Tenant Charges'!$F22)) -> 200.31339 | J26: =IF(Rent!J26=0,0,('Tenant Charges'!$F22)) -> 200.31339 | K26: =IF(Rent!K26=0,0,('Tenant Charges'!$F22)) -> 200.31339 | L26: =IF(Rent!L26=0,0,('Tenant Charges'!$F22)) -> 200.31339 | ... P26: =IF(Rent!P26=0,0,('Tenant Charges'!$F22)) -> 200.31339 | Q26: =SUM(E26:P26) -> 2403.7607 | R26: =Q26/C26 -> 1.514657 | S26: =191.06*12 -> 2292.72 | T26: =S26/C26 -> 1.4446881 | U26: 253.32 | V26: =U26-P26 -> 53.006606
A27: =Rent!A27 -> Razors Barber Shop | B27: =Rent!B27 -> 107 | C27: =Rent!C27 -> 1300 | D27: =C27/$C$35 -> 0.019199811 | E27: =IF(Rent!E27=0,0,('Tenant Charges'!$F23)) -> 424.03701 | F27: =IF(Rent!F27=0,0,('Tenant Charges'!$F23)) -> 424.03701 | G27: =IF(Rent!G27=0,0,('Tenant Charges'!$F23)) -> 424.03701 | H27: =IF(Rent!H27=0,0,('Tenant Charges'!$F23)) -> 424.03701 | I27: =IF(Rent!I27=0,0,('Tenant Charges'!$F23)) -> 424.03701 | J27: =IF(Rent!J27=0,0,('Tenant Charges'!$F23)) -> 424.03701 | K27: =IF(Rent!K27=0,0,('Tenant Charges'!$F23)) -> 424.03701 | L27: =IF(Rent!L27=0,0,('Tenant Charges'!$F23)) -> 424.03701 | ... P27: =IF(Rent!P27=0,0,('Tenant Charges'!$F23)) -> 424.03701 | Q27: =SUM(E27:P27) -> 5088.4442 | R27: =Q27/C27 -> 3.9141878 | S27: =191.06*12 -> 2292.72 | T27: =S27/C27 -> 1.7636308 | U27: 207.51 | V27: =U27-P27 -> -216.52701
A28: =Rent!A28 -> CrossFit New Strength | B28: =Rent!B28 -> 108 | C28: =Rent!C28 -> 3524 | D28: =C28/$C$35 -> 0.052046257 | E28: =IF(Rent!E28=0,0,('Tenant Charges'!$F24)) -> 685.44844 | F28: =IF(Rent!F28=0,0,('Tenant Charges'!$F24)) -> 685.44844 | G28: =IF(Rent!G28=0,0,('Tenant Charges'!$F24)) -> 685.44844 | H28: =IF(Rent!H28=0,0,('Tenant Charges'!$F24)) -> 685.44844 | I28: =IF(Rent!I28=0,0,('Tenant Charges'!$F24)) -> 685.44844 | J28: =IF(Rent!J28=0,0,('Tenant Charges'!$F24)) -> 685.44844 | K28: =IF(Rent!K28=0,0,('Tenant Charges'!$F24)) -> 685.44844 | L28: =IF(Rent!L28=0,0,('Tenant Charges'!$F24)) -> 685.44844 | ... P28: =IF(Rent!P28=0,0,('Tenant Charges'!$F24)) -> 685.44844 | Q28: =SUM(E28:P28) -> 8225.3813 | S28: 0 | T28: =S28/C28 -> 0 | V28: =U28-P28 -> -685.44844
A29: =Rent!A29 -> Vacant (Time Out Bar) | B29: =Rent!B29 -> 111 | C29: =Rent!C29 -> 3007 | D29: =C29/$C$35 -> 0.04441064 | E29: =IF(Rent!E29=0,0,('Tenant Charges'!$F25)) -> 0 | F29: =IF(Rent!F29=0,0,('Tenant Charges'!$F25)) -> 0 | G29: =IF(Rent!G29=0,0,('Tenant Charges'!$F25)) -> 0 | H29: =IF(Rent!H29=0,0,('Tenant Charges'!$F25)) -> 0 | I29: =IF(Rent!I29=0,0,('Tenant Charges'!$F25)) -> 0 | J29: =IF(Rent!J29=0,0,('Tenant Charges'!$F25)) -> 0 | K29: =IF(Rent!K29=0,0,('Tenant Charges'!$F25)) -> 394.81364 | L29: =IF(Rent!L29=0,0,('Tenant Charges'!$F25)) -> 394.81364 | ... P29: =IF(Rent!P29=0,0,('Tenant Charges'!$F25)) -> 394.81364 | Q29: =SUM(E29:P29) -> 2368.8818 | S29: 0 | V29: =U29-P29 -> -394.81364
A35: TOTALS | C35: =SUM(C14:C34) -> 67709 | D35: =SUM(D14:D34) -> 1 | E35: =SUM(E14:E29) -> 9715.6352 | F35: =SUM(F14:F29) -> 9715.6352 | G35: =SUM(G14:G29) -> 9715.6352 | H35: =SUM(H14:H29) -> 9715.6352 | I35: =SUM(I14:I29) -> 9715.6352 | J35: =SUM(J14:J29) -> 9715.6352 | K35: =SUM(K14:K29) -> 10110.449 | L35: =SUM(L14:L29) -> 10110.449 | ... Q35: =SUM(Q14:Q29) -> 118956.5
O37: TOTAL CAM | Q37: =Summary!O55 -> 158039.83
O38: RECAPTURE | Q38: =Q35/Q37 -> 0.75269954 | V38: Variance due to Vacancy and Slippage from CAM Caps for EOS, Sally's, AT&T, Adapt, Bright Now, Carr Animal Care, Razors
D41: NMK Tie-Out | E41: =E35-Summary!C14 -> 0 | F41: =F35-Summary!D14 -> 0 | G41: =G35-Summary!E14 -> 0 | H41: =H35-Summary!F14 -> 0 | I41: =I35-Summary!G14 -> 0 | J41: =J35-Summary!H14 -> 0 | K41: =K35-Summary!I14 -> 0 | L41: =L35-Summary!J14 -> 0 | ... P41: =P35-Summary!N14 -> 0

Sheet Building Expenses
P1: =Summary!T4 -> Date Revised: | Q1: =Summary!U4 -> 46269 | R1: =Summary!W4 -> 0
A2: =Summary!$A2 -> ATHENA PROPERTY MANAGEMENT
A3: =Summary!$A3 -> GREENFIELD GATEWAY MESA, ARIZONA
A4: =Summary!$A4 -> PROJECT NO. 801
A5: =Summary!$A5 -> 01/01/26-12/31/26
A6: =Summary!$A6 -> 2026 OPERATING BUDGET
D8: SQ FT
A9: TENANT | B9: SUITE | C9: SQUARE | D9: % OF | E9: JAN | F9: FEB | G9: MARCH | H9: APRIL | I9: MAY | J9: JUNE | K9: JULY | L9: AUGUST | M9: SEPT | N9: OCT | O9: NOV | P9: DEC | Q9: TOTALS
B10: # | C10: FOOTAGE | D10: TOTAL
A12: BUILDING EXPENSES
A14: =Rent!A14 -> EOS Fitness | B14: =Rent!B14 -> Major A | C14: =Rent!C14 -> 35000 | D14: =C14/($C$35) -> 0.51691799 | E14: =IF(Rent!E14=0,0,('Tenant Charges'!$G10)) -> 0 | F14: =IF(Rent!F14=0,0,('Tenant Charges'!$G10)) -> 0 | G14: =IF(Rent!G14=0,0,('Tenant Charges'!$G10)) -> 0 | H14: =IF(Rent!H14=0,0,('Tenant Charges'!$G10)) -> 0 | I14: =IF(Rent!I14=0,0,('Tenant Charges'!$G10)) -> 0 | J14: =IF(Rent!J14=0,0,('Tenant Charges'!$G10)) -> 0 | K14: =IF(Rent!K14=0,0,('Tenant Charges'!$G10)) -> 0 | L14: =IF(Rent!L14=0,0,('Tenant Charges'!$G10)) -> 0 | ... P14: =IF(Rent!P14=0,0,('Tenant Charges'!$G10)) -> 0 | Q14: =SUM(E14:P14) -> 0 | R14: =Q14/C14 -> 0
A15: =Rent!A15 -> Third Pasrty MVS | B15: =Rent!B15 -> B101 | C15: =Rent!C15 -> 3000 | D15: =C15/$C$35 -> 0.044307256 | E15: =IF(Rent!E15=0,0,('Tenant Charges'!$G11)) -> 491.64603 | F15: =IF(Rent!F15=0,0,('Tenant Charges'!$G11)) -> 491.64603 | G15: =IF(Rent!G15=0,0,('Tenant Charges'!$G11)) -> 491.64603 | H15: =IF(Rent!H15=0,0,('Tenant Charges'!$G11)) -> 491.64603 | I15: =IF(Rent!I15=0,0,('Tenant Charges'!$G11)) -> 491.64603 | J15: =IF(Rent!J15=0,0,('Tenant Charges'!$G11)) -> 491.64603 | K15: =IF(Rent!K15=0,0,('Tenant Charges'!$G11)) -> 491.64603 | L15: =IF(Rent!L15=0,0,('Tenant Charges'!$G11)) -> 491.64603 | ... P15: =IF(Rent!P15=0,0,('Tenant Charges'!$G11)) -> 491.64603 | Q15: =SUM(E15:P15) -> 5899.7524 | R15: =Q15/C15 -> 1.9665841
A16: =Rent!A16 -> Sally Beauty Supply | B16: =Rent!B16 -> B103 | C16: =Rent!C16 -> 1625 | D16: =C16/$C$35 -> 0.023999764 | E16: =IF(Rent!E16=0,0,('Tenant Charges'!$G12)) -> 0 | F16: =IF(Rent!F16=0,0,('Tenant Charges'!$G12)) -> 0 | G16: =IF(Rent!G16=0,0,('Tenant Charges'!$G12)) -> 0 | H16: =IF(Rent!H16=0,0,('Tenant Charges'!$G12)) -> 0 | I16: =IF(Rent!I16=0,0,('Tenant Charges'!$G12)) -> 0 | J16: =IF(Rent!J16=0,0,('Tenant Charges'!$G12)) -> 0 | K16: =IF(Rent!K16=0,0,('Tenant Charges'!$G12)) -> 0 | L16: =IF(Rent!L16=0,0,('Tenant Charges'!$G12)) -> 0 | ... P16: =IF(Rent!P16=0,0,('Tenant Charges'!$G12)) -> 0 | Q16: =SUM(E16:P16) -> 0 | R16: =Q16/C16 -> 0
A17: =Rent!A17 -> Wild Side Smoke Shop | B17: =Rent!B17 -> B104 | C17: =Rent!C17 -> 1400 | D17: =C17/$C$35 -> 0.020676719 | E17: =IF(Rent!E17=0,0,('Tenant Charges'!$G13)) -> 229.43481 | F17: =IF(Rent!F17=0,0,('Tenant Charges'!$G13)) -> 229.43481 | G17: =IF(Rent!G17=0,0,('Tenant Charges'!$G13)) -> 229.43481 | H17: =IF(Rent!H17=0,0,('Tenant Charges'!$G13)) -> 229.43481 | I17: =IF(Rent!I17=0,0,('Tenant Charges'!$G13)) -> 229.43481 | J17: =IF(Rent!J17=0,0,('Tenant Charges'!$G13)) -> 229.43481 | K17: =IF(Rent!K17=0,0,('Tenant Charges'!$G13)) -> 229.43481 | L17: =IF(Rent!L17=0,0,('Tenant Charges'!$G13)) -> 229.43481 | ... P17: =IF(Rent!P17=0,0,('Tenant Charges'!$G13)) -> 229.43481 | Q17: =SUM(E17:P17) -> 2753.2178 | R17: =Q17/C17 -> 1.9665841
A18: =Rent!A18 -> Green Spa, LLC | B18: =Rent!B18 -> B105 | C18: =Rent!C18 -> 1112 | D18: =C18/$C$35 -> 0.016423223 | E18: =IF(Rent!E18=0,0,('Tenant Charges'!$G14)) -> 182.2368 | F18: =IF(Rent!F18=0,0,('Tenant Charges'!$G14)) -> 182.2368 | G18: =IF(Rent!G18=0,0,('Tenant Charges'!$G14)) -> 182.2368 | H18: =IF(Rent!H18=0,0,('Tenant Charges'!$G14)) -> 182.2368 | I18: =IF(Rent!I18=0,0,('Tenant Charges'!$G14)) -> 182.2368 | J18: =IF(Rent!J18=0,0,('Tenant Charges'!$G14)) -> 182.2368 | K18: =IF(Rent!K18=0,0,('Tenant Charges'!$G14)) -> 182.2368 | L18: =IF(Rent!L18=0,0,('Tenant Charges'!$G14)) -> 182.2368 | ... P18: =IF(Rent!P18=0,0,('Tenant Charges'!$G14)) -> 182.2368 | Q18: =SUM(E18:P18) -> 2186.8415 | R18: =Q18/C18 -> 1.9665841
A19: =Rent!A19 -> AT&T Mobility | B19: =Rent!B19 -> B106 | C19: =Rent!C19 -> 2494 | D19: =C19/$C$35 -> 0.036834099 | E19: =IF(Rent!E19=0,0,('Tenant Charges'!$G15)) -> 0 | F19: =IF(Rent!F19=0,0,('Tenant Charges'!$G15)) -> 0 | G19: =IF(Rent!G19=0,0,('Tenant Charges'!$G15)) -> 0 | H19: =IF(Rent!H19=0,0,('Tenant Charges'!$G15)) -> 0 | I19: =IF(Rent!I19=0,0,('Tenant Charges'!$G15)) -> 0 | J19: =IF(Rent!J19=0,0,('Tenant Charges'!$G15)) -> 0 | K19: =IF(Rent!K19=0,0,('Tenant Charges'!$G15)) -> 0 | L19: =IF(Rent!L19=0,0,('Tenant Charges'!$G15)) -> 0 | ... P19: =IF(Rent!P19=0,0,('Tenant Charges'!$G15)) -> 0 | Q19: =SUM(E19:P19) -> 0 | R19: =Q19/C19 -> 0
A20: =Rent!A20 -> Discount Nutrition | B20: =Rent!B20 -> B108 | C20: =Rent!C20 -> 1500 | D20: =C20/$C$35 -> 0.022153628 | E20: =IF(Rent!E20=0,0,('Tenant Charges'!$G16)) -> 245.82302 | F20: =IF(Rent!F20=0,0,('Tenant Charges'!$G16)) -> 245.82302 | G20: =IF(Rent!G20=0,0,('Tenant Charges'!$G16)) -> 245.82302 | H20: =IF(Rent!H20=0,0,('Tenant Charges'!$G16)) -> 245.82302 | I20: =IF(Rent!I20=0,0,('Tenant Charges'!$G16)) -> 245.82302 | J20: =IF(Rent!J20=0,0,('Tenant Charges'!$G16)) -> 245.82302 | K20: =IF(Rent!K20=0,0,('Tenant Charges'!$G16)) -> 245.82302 | L20: =IF(Rent!L20=0,0,('Tenant Charges'!$G16)) -> 245.82302 | ... P20: =IF(Rent!P20=0,0,('Tenant Charges'!$G16)) -> 245.82302 | Q20: =SUM(E20:P20) -> 2949.8762 | R20: =Q20/C20 -> 1.9665841
A21: =Rent!A21 -> Adapt Chiropractic | B21: =Rent!B21 -> B109 | C21: =Rent!C21 -> 1734 | D21: =C21/$C$35 -> 0.025609594 | E21: =IF(Rent!E21=0,0,('Tenant Charges'!$G17)) -> 0 | F21: =IF(Rent!F21=0,0,('Tenant Charges'!$G17)) -> 0 | G21: =IF(Rent!G21=0,0,('Tenant Charges'!$G17)) -> 0 | H21: =IF(Rent!H21=0,0,('Tenant Charges'!$G17)) -> 0 | I21: =IF(Rent!I21=0,0,('Tenant Charges'!$G17)) -> 0 | J21: =IF(Rent!J21=0,0,('Tenant Charges'!$G17)) -> 0 | K21: =IF(Rent!K21=0,0,('Tenant Charges'!$G17)) -> 0 | L21: =IF(Rent!L21=0,0,('Tenant Charges'!$G17)) -> 0 | ... P21: =IF(Rent!P21=0,0,('Tenant Charges'!$G17)) -> 0 | Q21: =SUM(E21:P21) -> 0 | R21: =Q21/C21 -> 0
A22: =Rent!A22 -> Speakeasy Suites | B22: =Rent!B22 -> B111 | C22: =Rent!C22 -> 3900 | D22: =C22/$C$35 -> 0.057599433 | E22: =IF(Rent!E22=0,0,('Tenant Charges'!$G18)) -> 639.13984 | F22: =IF(Rent!F22=0,0,('Tenant Charges'!$G18)) -> 639.13984 | G22: =IF(Rent!G22=0,0,('Tenant Charges'!$G18)) -> 639.13984 | H22: =IF(Rent!H22=0,0,('Tenant Charges'!$G18)) -> 639.13984 | I22: =IF(Rent!I22=0,0,('Tenant Charges'!$G18)) -> 639.13984 | J22: =IF(Rent!J22=0,0,('Tenant Charges'!$G18)) -> 639.13984 | K22: =IF(Rent!K22=0,0,('Tenant Charges'!$G18)) -> 639.13984 | L22: =IF(Rent!L22=0,0,('Tenant Charges'!$G18)) -> 639.13984 | ... P22: =IF(Rent!P22=0,0,('Tenant Charges'!$G18)) -> 639.13984 | Q22: =SUM(E22:P22) -> 7669.6781 | R22: =Q22/C22 -> 1.9665841
A23: =Rent!A23 -> Kachina Stained Glass | B23: =Rent!B23 -> 101 | C23: =Rent!C23 -> 1287 | D23: =C23/$C$35 -> 0.019007813 | E23: =IF(Rent!E23=0,0,('Tenant Charges'!$G19)) -> 210.91615 | F23: =IF(Rent!F23=0,0,('Tenant Charges'!$G19)) -> 210.91615 | G23: =IF(Rent!G23=0,0,('Tenant Charges'!$G19)) -> 210.91615 | H23: =IF(Rent!H23=0,0,('Tenant Charges'!$G19)) -> 210.91615 | I23: =IF(Rent!I23=0,0,('Tenant Charges'!$G19)) -> 210.91615 | J23: =IF(Rent!J23=0,0,('Tenant Charges'!$G19)) -> 210.91615 | K23: =IF(Rent!K23=0,0,('Tenant Charges'!$G19)) -> 210.91615 | L23: =IF(Rent!L23=0,0,('Tenant Charges'!$G19)) -> 210.91615 | ... P23: =IF(Rent!P23=0,0,('Tenant Charges'!$G19)) -> 210.91615 | Q23: =SUM(E23:P23) -> 2530.9938 | R23: =Q23/C23 -> 1.9665841
A24: =Rent!A24 -> Zanders Creations | B24: =Rent!B24 -> 102 | C24: =Rent!C24 -> 1639 | D24: =C24/$C$35 -> 0.024206531 | E24: =IF(Rent!E24=0,0,('Tenant Charges'!$G20)) -> 268.60261 | F24: =IF(Rent!F24=0,0,('Tenant Charges'!$G20)) -> 268.60261 | G24: =IF(Rent!G24=0,0,('Tenant Charges'!$G20)) -> 268.60261 | H24: =IF(Rent!H24=0,0,('Tenant Charges'!$G20)) -> 268.60261 | I24: =IF(Rent!I24=0,0,('Tenant Charges'!$G20)) -> 268.60261 | J24: =IF(Rent!J24=0,0,('Tenant Charges'!$G20)) -> 268.60261 | K24: =IF(Rent!K24=0,0,('Tenant Charges'!$G20)) -> 268.60261 | L24: =IF(Rent!L24=0,0,('Tenant Charges'!$G20)) -> 268.60261 | ... P24: =IF(Rent!P24=0,0,('Tenant Charges'!$G20)) -> 268.60261 | Q24: =SUM(E24:P24) -> 3223.2314 | R24: =Q24/C24 -> 1.9665841
A25: =Rent!A25 -> Brightnow Dental | B25: =Rent!B25 -> 103 | C25: =Rent!C25 -> 3600 | D25: =C25/$C$35 -> 0.053168707 | E25: =IF(Rent!E25=0,0,('Tenant Charges'!$G21)) -> 0 | F25: =IF(Rent!F25=0,0,('Tenant Charges'!$G21)) -> 0 | G25: =IF(Rent!G25=0,0,('Tenant Charges'!$G21)) -> 0 | H25: =IF(Rent!H25=0,0,('Tenant Charges'!$G21)) -> 0 | I25: =IF(Rent!I25=0,0,('Tenant Charges'!$G21)) -> 0 | J25: =IF(Rent!J25=0,0,('Tenant Charges'!$G21)) -> 0 | K25: =IF(Rent!K25=0,0,('Tenant Charges'!$G21)) -> 0 | L25: =IF(Rent!L25=0,0,('Tenant Charges'!$G21)) -> 0 | ... P25: =IF(Rent!P25=0,0,('Tenant Charges'!$G21)) -> 0 | Q25: =SUM(E25:P25) -> 0 | R25: =Q25/C25 -> 0
A26: =Rent!A26 -> Carr Animal Care | B26: =Rent!B26 -> 106 | C26: =Rent!C26 -> 1587 | D26: =C26/$C$35 -> 0.023438538 | E26: =IF(Rent!E26=0,0,('Tenant Charges'!$G22)) -> 0 | F26: =IF(Rent!F26=0,0,('Tenant Charges'!$G22)) -> 0 | G26: =IF(Rent!G26=0,0,('Tenant Charges'!$G22)) -> 0 | H26: =IF(Rent!H26=0,0,('Tenant Charges'!$G22)) -> 0 | I26: =IF(Rent!I26=0,0,('Tenant Charges'!$G22)) -> 0 | J26: =IF(Rent!J26=0,0,('Tenant Charges'!$G22)) -> 0 | K26: =IF(Rent!K26=0,0,('Tenant Charges'!$G22)) -> 0 | L26: =IF(Rent!L26=0,0,('Tenant Charges'!$G22)) -> 0 | ... P26: =IF(Rent!P26=0,0,('Tenant Charges'!$G22)) -> 0 | Q26: =SUM(E26:P26) -> 0 | R26: =Q26/C26 -> 0
... A29: =Rent!A29 -> Vacant (Time Out Bar) | B29: =Rent!B29 -> 111 | C29: =Rent!C29 -> 3007 | D29: =C29/$C$35 -> 0.04441064 | E29: =IF(Rent!E29=0,0,('Tenant Charges'!$G25)) -> 0 | F29: =IF(Rent!F29=0,0,('Tenant Charges'!$G25)) -> 0 | G29: =IF(Rent!G29=0,0,('Tenant Charges'!$G25)) -> 0 | H29: =IF(Rent!H29=0,0,('Tenant Charges'!$G25)) -> 0 | I29: =IF(Rent!I29=0,0,('Tenant Charges'!$G25)) -> 0 | J29: =IF(Rent!J29=0,0,('Tenant Charges'!$G25)) -> 0 | K29: =IF(Rent!K29=0,0,('Tenant Charges'!$G25)) -> 492.7932 | L29: =IF(Rent!L29=0,0,('Tenant Charges'!$G25)) -> 492.7932 | ... P29: =IF(Rent!P29=0,0,('Tenant Charges'!$G25)) -> 492.7932 | Q29: =SUM(E29:P29) -> 2956.7592 | R29: =Q29/C29 -> 0.98329206
A35: TOTALS | C35: =SUM(C14:C34) -> 67709 | D35: =SUM(D14:D34) -> 1 | E35: =SUM(E14:E29) -> 2845.3195 | F35: =SUM(F14:F29) -> 2845.3195 | G35: =SUM(G14:G29) -> 2845.3195 | H35: =SUM(H14:H29) -> 2845.3195 | I35: =SUM(I14:I29) -> 2845.3195 | J35: =SUM(J14:J29) -> 2845.3195 | K35: =SUM(K14:K29) -> 3338.1127 | L35: =SUM(L14:L29) -> 3338.1127 | ... Q35: =SUM(Q14:Q29) -> 37100.593
O37: TOTAL BLDG | Q37: =Summary!O67 -> 64325
O38: RECAPTURE | Q38: =Q35/Q37 -> 0.57676786
O39: Building is included in CAM for tenants with Caps
O40: Sally's, AT&T, Adapt, Brightnow, Carr, Razors
A41: Vacancy rate | D41: ='Occup,'!D38 -> 0.95558936
D43: NMK Tie-Out | E43: =E35-Summary!C17 -> 0 | F43: =F35-Summary!D17 -> 0 | G43: =G35-Summary!E17 -> 0 | H43: =H35-Summary!F17 -> 0 | I43: =I35-Summary!G17 -> 0 | J43: =J35-Summary!H17 -> 0 | K43: =K35-Summary!I17 -> 0 | L43: =L35-Summary!J17 -> 0 | ... P43: =P35-Summary!N17 -> 0

Sheet Ins.
P1: =Summary!T4 -> Date Revised: | Q1: =Summary!U4 -> 46269 | R1: =Summary!W4 -> 0
A2: =Summary!$A2 -> ATHENA PROPERTY MANAGEMENT
A3: =Summary!$A3 -> GREENFIELD GATEWAY MESA, ARIZONA
A4: =Summary!$A4 -> PROJECT NO. 801
A5: =Summary!$A5 -> 01/01/26-12/31/26
A6: =Summary!$A6 -> 2026 OPERATING BUDGET
A9: TENANT | B9: SUITE | C9: SQUARE | D9: PRORATA | E9: JAN | F9: FEB | G9: MARCH | H9: APRIL | I9: MAY | J9: JUNE | K9: JULY | L9: AUGUST | M9: SEPT | N9: OCT | O9: NOV | P9: DEC | Q9: TOTALS
B10: # | C10: FOOTAGE | D10: SHARE
A12: INSURANCE
A14: =Rent!A14 -> EOS Fitness | B14: =Rent!B14 -> Major A | C14: =Rent!C14 -> 35000 | D14: =C14/$C$35 -> 0.51691799 | E14: =IF(Rent!E14=0,0,('Tenant Charges'!$J10)) -> 1376.7464 | F14: =IF(Rent!F14=0,0,('Tenant Charges'!$J10)) -> 1376.7464 | G14: =IF(Rent!G14=0,0,('Tenant Charges'!$J10)) -> 1376.7464 | H14: =IF(Rent!H14=0,0,('Tenant Charges'!$J10)) -> 1376.7464 | I14: =IF(Rent!I14=0,0,('Tenant Charges'!$J10)) -> 1376.7464 | J14: =IF(Rent!J14=0,0,('Tenant Charges'!$J10)) -> 1376.7464 | K14: =IF(Rent!K14=0,0,('Tenant Charges'!$J10)) -> 1376.7464 | L14: =IF(Rent!L14=0,0,('Tenant Charges'!$J10)) -> 1376.7464 | ... P14: =IF(Rent!P14=0,0,('Tenant Charges'!$J10)) -> 1376.7464 | Q14: =SUM(E14:P14) -> 16520.957
A15: =Rent!A15 -> Third Pasrty MVS | B15: =Rent!B15 -> B101 | C15: =Rent!C15 -> 3000 | D15: =C15/$C$35 -> 0.044307256 | E15: =IF(Rent!E15=0,0,('Tenant Charges'!$J11)) -> 118.00684 | F15: =IF(Rent!F15=0,0,('Tenant Charges'!$J11)) -> 118.00684 | G15: =IF(Rent!G15=0,0,('Tenant Charges'!$J11)) -> 118.00684 | H15: =IF(Rent!H15=0,0,('Tenant Charges'!$J11)) -> 118.00684 | I15: =IF(Rent!I15=0,0,('Tenant Charges'!$J11)) -> 118.00684 | J15: =IF(Rent!J15=0,0,('Tenant Charges'!$J11)) -> 118.00684 | K15: =IF(Rent!K15=0,0,('Tenant Charges'!$J11)) -> 118.00684 | L15: =IF(Rent!L15=0,0,('Tenant Charges'!$J11)) -> 118.00684 | ... P15: =IF(Rent!P15=0,0,('Tenant Charges'!$J11)) -> 118.00684 | Q15: =SUM(E15:P15) -> 1416.0821 | R15: =Q15/C15 -> 0.47202735
A16: =Rent!A16 -> Sally Beauty Supply | B16: =Rent!B16 -> B103 | C16: =Rent!C16 -> 1625 | D16: =C16/$C$35 -> 0.023999764 | E16: =IF(Rent!E16=0,0,('Tenant Charges'!$J12)) -> 63.920371 | F16: =IF(Rent!F16=0,0,('Tenant Charges'!$J12)) -> 63.920371 | G16: =IF(Rent!G16=0,0,('Tenant Charges'!$J12)) -> 63.920371 | H16: =IF(Rent!H16=0,0,('Tenant Charges'!$J12)) -> 63.920371 | I16: =IF(Rent!I16=0,0,('Tenant Charges'!$J12)) -> 63.920371 | J16: =IF(Rent!J16=0,0,('Tenant Charges'!$J12)) -> 63.920371 | K16: =IF(Rent!K16=0,0,('Tenant Charges'!$J12)) -> 63.920371 | L16: =IF(Rent!L16=0,0,('Tenant Charges'!$J12)) -> 63.920371 | ... P16: =IF(Rent!P16=0,0,('Tenant Charges'!$J12)) -> 63.920371 | Q16: =SUM(E16:P16) -> 767.04445 | R16: =Q16/C16 -> 0.47202735
A17: =Rent!A17 -> Wild Side Smoke Shop | B17: =Rent!B17 -> B104 | C17: =Rent!C17 -> 1400 | D17: =C17/$C$35 -> 0.020676719 | E17: =IF(Rent!E17=0,0,('Tenant Charges'!$J13)) -> 55.069858 | F17: =IF(Rent!F17=0,0,('Tenant Charges'!$J13)) -> 55.069858 | G17: =IF(Rent!G17=0,0,('Tenant Charges'!$J13)) -> 55.069858 | H17: =IF(Rent!H17=0,0,('Tenant Charges'!$J13)) -> 55.069858 | I17: =IF(Rent!I17=0,0,('Tenant Charges'!$J13)) -> 55.069858 | J17: =IF(Rent!J17=0,0,('Tenant Charges'!$J13)) -> 55.069858 | K17: =IF(Rent!K17=0,0,('Tenant Charges'!$J13)) -> 55.069858 | L17: =IF(Rent!L17=0,0,('Tenant Charges'!$J13)) -> 55.069858 | ... P17: =IF(Rent!P17=0,0,('Tenant Charges'!$J13)) -> 55.069858 | Q17: =SUM(E17:P17) -> 660.83829 | R17: =Q17/C17 -> 0.47202735
A18: =Rent!A18 -> Green Spa, LLC | B18: =Rent!B18 -> B105 | C18: =Rent!C18 -> 1112 | D18: =C18/$C$35 -> 0.016423223 | E18: =IF(Rent!E18=0,0,('Tenant Charges'!$J14)) -> 43.741201 | F18: =IF(Rent!F18=0,0,('Tenant Charges'!$J14)) -> 43.741201 | G18: =IF(Rent!G18=0,0,('Tenant Charges'!$J14)) -> 43.741201 | H18: =IF(Rent!H18=0,0,('Tenant Charges'!$J14)) -> 43.741201 | I18: =IF(Rent!I18=0,0,('Tenant Charges'!$J14)) -> 43.741201 | J18: =IF(Rent!J18=0,0,('Tenant Charges'!$J14)) -> 43.741201 | K18: =IF(Rent!K18=0,0,('Tenant Charges'!$J14)) -> 43.741201 | L18: =IF(Rent!L18=0,0,('Tenant Charges'!$J14)) -> 43.741201 | ... P18: =IF(Rent!P18=0,0,('Tenant Charges'!$J14)) -> 43.741201 | Q18: =SUM(E18:P18) -> 524.89442 | R18: =Q18/C18 -> 0.47202735
A19: =Rent!A19 -> AT&T Mobility | B19: =Rent!B19 -> B106 | C19: =Rent!C19 -> 2494 | D19: =C19/$C$35 -> 0.036834099 | E19: =IF(Rent!E19=0,0,('Tenant Charges'!$J15)) -> 98.103018 | F19: =IF(Rent!F19=0,0,('Tenant Charges'!$J15)) -> 98.103018 | G19: =IF(Rent!G19=0,0,('Tenant Charges'!$J15)) -> 98.103018 | H19: =IF(Rent!H19=0,0,('Tenant Charges'!$J15)) -> 98.103018 | I19: =IF(Rent!I19=0,0,('Tenant Charges'!$J15)) -> 98.103018 | J19: =IF(Rent!J19=0,0,('Tenant Charges'!$J15)) -> 98.103018 | K19: =IF(Rent!K19=0,0,('Tenant Charges'!$J15)) -> 98.103018 | L19: =IF(Rent!L19=0,0,('Tenant Charges'!$J15)) -> 98.103018 | ... P19: =IF(Rent!P19=0,0,('Tenant Charges'!$J15)) -> 98.103018 | Q19: =SUM(E19:P19) -> 1177.2362 | R19: =Q19/C19 -> 0.47202735
A20: =Rent!A20 -> Discount Nutrition | B20: =Rent!B20 -> B108 | C20: =Rent!C20 -> 1500 | D20: =C20/$C$35 -> 0.022153628 | E20: =IF(Rent!E20=0,0,('Tenant Charges'!$J16)) -> 59.003419 | F20: =IF(Rent!F20=0,0,('Tenant Charges'!$J16)) -> 59.003419 | G20: =IF(Rent!G20=0,0,('Tenant Charges'!$J16)) -> 59.003419 | H20: =IF(Rent!H20=0,0,('Tenant Charges'!$J16)) -> 59.003419 | I20: =IF(Rent!I20=0,0,('Tenant Charges'!$J16)) -> 59.003419 | J20: =IF(Rent!J20=0,0,('Tenant Charges'!$J16)) -> 59.003419 | K20: =IF(Rent!K20=0,0,('Tenant Charges'!$J16)) -> 59.003419 | L20: =IF(Rent!L20=0,0,('Tenant Charges'!$J16)) -> 59.003419 | ... P20: =IF(Rent!P20=0,0,('Tenant Charges'!$J16)) -> 59.003419 | Q20: =SUM(E20:P20) -> 708.04103 | R20: =Q20/C20 -> 0.47202735
A21: =Rent!A21 -> Adapt Chiropractic | B21: =Rent!B21 -> B109 | C21: =Rent!C21 -> 1734 | D21: =C21/$C$35 -> 0.025609594 | E21: =IF(Rent!E21=0,0,('Tenant Charges'!$J17)) -> 68.207952 | F21: =IF(Rent!F21=0,0,('Tenant Charges'!$J17)) -> 68.207952 | G21: =IF(Rent!G21=0,0,('Tenant Charges'!$J17)) -> 68.207952 | H21: =IF(Rent!H21=0,0,('Tenant Charges'!$J17)) -> 68.207952 | I21: =IF(Rent!I21=0,0,('Tenant Charges'!$J17)) -> 68.207952 | J21: =IF(Rent!J21=0,0,('Tenant Charges'!$J17)) -> 68.207952 | K21: =IF(Rent!K21=0,0,('Tenant Charges'!$J17)) -> 68.207952 | L21: =IF(Rent!L21=0,0,('Tenant Charges'!$J17)) -> 68.207952 | ... P21: =IF(Rent!P21=0,0,('Tenant Charges'!$J17)) -> 68.207952 | Q21: =SUM(E21:P21) -> 818.49543 | R21: =Q21/C21 -> 0.47202735
A22: =Rent!A22 -> Speakeasy Suites | B22: =Rent!B22 -> B111 | C22: =Rent!C22 -> 3900 | D22: =C22/$C$35 -> 0.057599433 | E22: =IF(Rent!E22=0,0,('Tenant Charges'!$J18)) -> 153.40889 | F22: =IF(Rent!F22=0,0,('Tenant Charges'!$J18)) -> 153.40889 | G22: =IF(Rent!G22=0,0,('Tenant Charges'!$J18)) -> 153.40889 | H22: =IF(Rent!H22=0,0,('Tenant Charges'!$J18)) -> 153.40889 | I22: =IF(Rent!I22=0,0,('Tenant Charges'!$J18)) -> 153.40889 | J22: =IF(Rent!J22=0,0,('Tenant Charges'!$J18)) -> 153.40889 | K22: =IF(Rent!K22=0,0,('Tenant Charges'!$J18)) -> 153.40889 | L22: =IF(Rent!L22=0,0,('Tenant Charges'!$J18)) -> 153.40889 | ... P22: =IF(Rent!P22=0,0,('Tenant Charges'!$J18)) -> 153.40889 | Q22: =SUM(E22:P22) -> 1840.9067 | R22: =Q22/C22 -> 0.47202735
A23: =Rent!A23 -> Kachina Stained Glass | B23: =Rent!B23 -> 101 | C23: =Rent!C23 -> 1287 | D23: =C23/$C$35 -> 0.019007813 | E23: =IF(Rent!E23=0,0,('Tenant Charges'!$J19)) -> 50.624934 | F23: =IF(Rent!F23=0,0,('Tenant Charges'!$J19)) -> 50.624934 | G23: =IF(Rent!G23=0,0,('Tenant Charges'!$J19)) -> 50.624934 | H23: =IF(Rent!H23=0,0,('Tenant Charges'!$J19)) -> 50.624934 | I23: =IF(Rent!I23=0,0,('Tenant Charges'!$J19)) -> 50.624934 | J23: =IF(Rent!J23=0,0,('Tenant Charges'!$J19)) -> 50.624934 | K23: =IF(Rent!K23=0,0,('Tenant Charges'!$J19)) -> 50.624934 | L23: =IF(Rent!L23=0,0,('Tenant Charges'!$J19)) -> 50.624934 | ... P23: =IF(Rent!P23=0,0,('Tenant Charges'!$J19)) -> 50.624934 | Q23: =SUM(E23:P23) -> 607.4992 | R23: =Q23/C23 -> 0.47202735
A24: =Rent!A24 -> Zanders Creations | B24: =Rent!B24 -> 102 | C24: =Rent!C24 -> 1639 | D24: =C24/$C$35 -> 0.024206531 | E24: =IF(Rent!E24=0,0,('Tenant Charges'!$J20)) -> 64.471069 | F24: =IF(Rent!F24=0,0,('Tenant Charges'!$J20)) -> 64.471069 | G24: =IF(Rent!G24=0,0,('Tenant Charges'!$J20)) -> 64.471069 | H24: =IF(Rent!H24=0,0,('Tenant Charges'!$J20)) -> 64.471069 | I24: =IF(Rent!I24=0,0,('Tenant Charges'!$J20)) -> 64.471069 | J24: =IF(Rent!J24=0,0,('Tenant Charges'!$J20)) -> 64.471069 | K24: =IF(Rent!K24=0,0,('Tenant Charges'!$J20)) -> 64.471069 | L24: =IF(Rent!L24=0,0,('Tenant Charges'!$J20)) -> 64.471069 | ... P24: =IF(Rent!P24=0,0,('Tenant Charges'!$J20)) -> 64.471069 | Q24: =SUM(E24:P24) -> 773.65283 | R24: =Q24/C24 -> 0.47202735
A25: =Rent!A25 -> Brightnow Dental | B25: =Rent!B25 -> 103 | C25: =Rent!C25 -> 3600 | D25: =C25/$C$35 -> 0.053168707 | E25: =IF(Rent!E25=0,0,('Tenant Charges'!$J21)) -> 141.60821 | F25: =IF(Rent!F25=0,0,('Tenant Charges'!$J21)) -> 141.60821 | G25: =IF(Rent!G25=0,0,('Tenant Charges'!$J21)) -> 141.60821 | H25: =IF(Rent!H25=0,0,('Tenant Charges'!$J21)) -> 141.60821 | I25: =IF(Rent!I25=0,0,('Tenant Charges'!$J21)) -> 141.60821 | J25: =IF(Rent!J25=0,0,('Tenant Charges'!$J21)) -> 141.60821 | K25: =IF(Rent!K25=0,0,('Tenant Charges'!$J21)) -> 141.60821 | L25: =IF(Rent!L25=0,0,('Tenant Charges'!$J21)) -> 141.60821 | ... P25: =IF(Rent!P25=0,0,('Tenant Charges'!$J21)) -> 141.60821 | Q25: =SUM(E25:P25) -> 1699.2985 | R25: =Q25/C25 -> 0.47202735
A26: =Rent!A26 -> Carr Animal Care | B26: =Rent!B26 -> 106 | C26: =Rent!C26 -> 1587 | D26: =C26/$C$35 -> 0.023438538 | E26: =IF(Rent!E26=0,0,('Tenant Charges'!$J22)) -> 62.425617 | F26: =IF(Rent!F26=0,0,('Tenant Charges'!$J22)) -> 62.425617 | G26: =IF(Rent!G26=0,0,('Tenant Charges'!$J22)) -> 62.425617 | H26: =IF(Rent!H26=0,0,('Tenant Charges'!$J22)) -> 62.425617 | I26: =IF(Rent!I26=0,0,('Tenant Charges'!$J22)) -> 62.425617 | J26: =IF(Rent!J26=0,0,('Tenant Charges'!$J22)) -> 62.425617 | K26: =IF(Rent!K26=0,0,('Tenant Charges'!$J22)) -> 62.425617 | L26: =IF(Rent!L26=0,0,('Tenant Charges'!$J22)) -> 62.425617 | ... P26: =IF(Rent!P26=0,0,('Tenant Charges'!$J22)) -> 62.425617 | Q26: =SUM(E26:P26) -> 749.10741 | R26: =Q26/C26 -> 0.47202735
A27: =Rent!A27 -> Razors Barber Shop | B27: =Rent!B27 -> 107 | C27: =Rent!C27 -> 1300 | D27: =C27/$C$35 -> 0.019199811 | E27: =IF(Rent!E27=0,0,('Tenant Charges'!$J23)) -> 51.136297 | F27: =IF(Rent!F27=0,0,('Tenant Charges'!$J23)) -> 51.136297 | G27: =IF(Rent!G27=0,0,('Tenant Charges'!$J23)) -> 51.136297 | H27: =IF(Rent!H27=0,0,('Tenant Charges'!$J23)) -> 51.136297 | I27: =IF(Rent!I27=0,0,('Tenant Charges'!$J23)) -> 51.136297 | J27: =IF(Rent!J27=0,0,('Tenant Charges'!$J23)) -> 51.136297 | K27: =IF(Rent!K27=0,0,('Tenant Charges'!$J23)) -> 51.136297 | L27: =IF(Rent!L27=0,0,('Tenant Charges'!$J23)) -> 51.136297 | ... P27: =IF(Rent!P27=0,0,('Tenant Charges'!$J23)) -> 51.136297 | Q27: =SUM(E27:P27) -> 613.63556 | R27: =Q27/C27 -> 0.47202735
A28: =Rent!A28 -> CrossFit New Strength | B28: =Rent!B28 -> 108 | C28: =Rent!C28 -> 3524 | D28: =C28/$C$35 -> 0.052046257 | E28: =IF(Rent!E28=0,0,('Tenant Charges'!$J24)) -> 138.6187 | F28: =IF(Rent!F28=0,0,('Tenant Charges'!$J24)) -> 138.6187 | G28: =IF(Rent!G28=0,0,('Tenant Charges'!$J24)) -> 138.6187 | H28: =IF(Rent!H28=0,0,('Tenant Charges'!$J24)) -> 138.6187 | I28: =IF(Rent!I28=0,0,('Tenant Charges'!$J24)) -> 138.6187 | J28: =IF(Rent!J28=0,0,('Tenant Charges'!$J24)) -> 138.6187 | K28: =IF(Rent!K28=0,0,('Tenant Charges'!$J24)) -> 138.6187 | L28: =IF(Rent!L28=0,0,('Tenant Charges'!$J24)) -> 138.6187 | ... P28: =IF(Rent!P28=0,0,('Tenant Charges'!$J24)) -> 138.6187 | Q28: =SUM(E28:P28) -> 1663.4244
A29: =Rent!A29 -> Vacant (Time Out Bar) | B29: =Rent!B29 -> 111 | C29: =Rent!C29 -> 3007 | D29: =C29/$C$35 -> 0.04441064 | E29: =IF(Rent!E29=0,0,('Tenant Charges'!$J25)) -> 0 | F29: =IF(Rent!F29=0,0,('Tenant Charges'!$J25)) -> 0 | G29: =IF(Rent!G29=0,0,('Tenant Charges'!$J25)) -> 0 | H29: =IF(Rent!H29=0,0,('Tenant Charges'!$J25)) -> 0 | I29: =IF(Rent!I29=0,0,('Tenant Charges'!$J25)) -> 0 | J29: =IF(Rent!J29=0,0,('Tenant Charges'!$J25)) -> 0 | K29: =IF(Rent!K29=0,0,('Tenant Charges'!$J25)) -> 118.28219 | L29: =IF(Rent!L29=0,0,('Tenant Charges'!$J25)) -> 118.28219 | ... P29: =IF(Rent!P29=0,0,('Tenant Charges'!$J25)) -> 118.28219 | Q29: =SUM(E29:P29) -> 709.69312
A35: TOTALS | C35: =SUM(C14:C34) -> 67709 | D35: =SUM(D14:D34) -> 1 | E35: =SUM(E14:E29) -> 2545.0928 | F35: =SUM(F14:F29) -> 2545.0928 | G35: =SUM(G14:G29) -> 2545.0928 | H35: =SUM(H14:H29) -> 2545.0928 | I35: =SUM(I14:I29) -> 2545.0928 | J35: =SUM(J14:J29) -> 2545.0928 | K35: =SUM(K14:K29) -> 2663.375 | L35: =SUM(L14:L29) -> 2663.375 | ... Q35: =SUM(Q14:Q29) -> 31250.807
O37: TOTAL INS | Q37: =Summary!O75 -> 31960.5
O38: RECAPTURE | Q38: =Q35/Q37 -> 0.97779468 | S38: Slippage due to Vacancy
D41: NMK Tie-Out | E41: =E35-Summary!C18 -> 0 | F41: =F35-Summary!D18 -> 0 | G41: =G35-Summary!E18 -> 0 | H41: =H35-Summary!F18 -> 0 | I41: =I35-Summary!G18 -> 0 | J41: =J35-Summary!H18 -> 0 | K41: =K35-Summary!I18 -> 0 | L41: =L35-Summary!J18 -> 0 | ... P41: =P35-Summary!N18 -> 0

Sheet Admin Fee
P1: =Summary!T4 -> Date Revised: | Q1: =Summary!U4 -> 46269 | R1: =Summary!W4 -> 0
A2: =Summary!$A2 -> ATHENA PROPERTY MANAGEMENT
A3: =Summary!$A3 -> GREENFIELD GATEWAY MESA, ARIZONA
A4: =Summary!$A4 -> PROJECT NO. 801
A5: =Summary!$A5 -> 01/01/26-12/31/26
A6: =Summary!$A6 -> 2026 OPERATING BUDGET
A9: TENANT | B9: SUITE | C9: SQUARE | D9: RATE | E9: JAN | F9: FEB | G9: MARCH | H9: APRIL | I9: MAY | J9: JUNE | K9: JULY | L9: AUGUST | M9: SEPT | N9: OCT | O9: NOV | P9: DEC | Q9: TOTALS
B10: # | C10: FOOTAGE
A12: ADMINISTRATIVE FEES
A14: =Rent!A14 -> EOS Fitness | B14: =Rent!B14 -> Major A | C14: =Rent!C14 -> 35000 | D14: 0.15 | E14: =IF(Rent!E14=0,0,('Tenant Charges'!$H10)) -> 0 | F14: =IF(Rent!F14=0,0,('Tenant Charges'!$H10)) -> 0 | G14: =IF(Rent!G14=0,0,('Tenant Charges'!$H10)) -> 0 | H14: =IF(Rent!H14=0,0,('Tenant Charges'!$H10)) -> 0 | I14: =IF(Rent!I14=0,0,('Tenant Charges'!$H10)) -> 0 | J14: =IF(Rent!J14=0,0,('Tenant Charges'!$H10)) -> 0 | K14: =IF(Rent!K14=0,0,('Tenant Charges'!$H10)) -> 0 | L14: =IF(Rent!L14=0,0,('Tenant Charges'!$H10)) -> 0 | ... P14: =IF(Rent!P14=0,0,('Tenant Charges'!$H10)) -> 0 | Q14: =SUM(E14:P14) -> 0 | R14: =Q14/C14 -> 0 | S14: excluding tax, ins, utilities, security
A15: =Rent!A15 -> Third Pasrty MVS | B15: =Rent!B15 -> B101 | C15: =Rent!C15 -> 3000 | D15: 0.1 | E15: =IF(Rent!E15=0,0,'Tenant Charges'!$H11) -> 107.51719 | F15: =IF(Rent!F15=0,0,'Tenant Charges'!$H11) -> 107.51719 | G15: =IF(Rent!G15=0,0,'Tenant Charges'!$H11) -> 107.51719 | H15: =IF(Rent!H15=0,0,'Tenant Charges'!$H11) -> 107.51719 | I15: =IF(Rent!I15=0,0,'Tenant Charges'!$H11) -> 107.51719 | J15: =IF(Rent!J15=0,0,'Tenant Charges'!$H11) -> 107.51719 | K15: =IF(Rent!K15=0,0,'Tenant Charges'!$H11) -> 107.51719 | L15: =IF(Rent!L15=0,0,'Tenant Charges'!$H11) -> 107.51719 | ... P15: =IF(Rent!P15=0,0,'Tenant Charges'!$H11) -> 107.51719 | Q15: =SUM(E15:P15) -> 1290.2063 | R15: =Q15/C15 -> 0.43006878
A16: =Rent!A16 -> Sally Beauty Supply | B16: =Rent!B16 -> B103 | C16: =Rent!C16 -> 1625 | D16: 0.04 | E16: =IF(Rent!E16=0,0,'Tenant Charges'!$H12) -> 0 | F16: =IF(Rent!F16=0,0,'Tenant Charges'!$H12) -> 0 | G16: =IF(Rent!G16=0,0,'Tenant Charges'!$H12) -> 0 | H16: =IF(Rent!H16=0,0,'Tenant Charges'!$H12) -> 0 | I16: =IF(Rent!I16=0,0,'Tenant Charges'!$H12) -> 0 | J16: =IF(Rent!J16=0,0,'Tenant Charges'!$H12) -> 0 | K16: =IF(Rent!K16=0,0,'Tenant Charges'!$H12) -> 0 | L16: =IF(Rent!L16=0,0,'Tenant Charges'!$H12) -> 0 | ... P16: =IF(Rent!P16=0,0,'Tenant Charges'!$H12) -> 0 | Q16: =SUM(E16:P16) -> 0
A17: =Rent!A17 -> Wild Side Smoke Shop | B17: =Rent!B17 -> B104 | C17: =Rent!C17 -> 1400 | D17: 0 | E17: =IF(Rent!E17=0,0,'Tenant Charges'!$H13) -> 0 | F17: =IF(Rent!F17=0,0,'Tenant Charges'!$H13) -> 0 | G17: =IF(Rent!G17=0,0,'Tenant Charges'!$H13) -> 0 | H17: =IF(Rent!H17=0,0,'Tenant Charges'!$H13) -> 0 | I17: =IF(Rent!I17=0,0,'Tenant Charges'!$H13) -> 0 | J17: =IF(Rent!J17=0,0,'Tenant Charges'!$H13) -> 0 | K17: =IF(Rent!K17=0,0,'Tenant Charges'!$H13) -> 0 | L17: =IF(Rent!L17=0,0,'Tenant Charges'!$H13) -> 0 | ... P17: =IF(Rent!P17=0,0,'Tenant Charges'!$H13) -> 0 | Q17: =SUM(E17:P17) -> 0 | R17: =Q17/C17 -> 0
A18: =Rent!A18 -> Green Spa, LLC | B18: =Rent!B18 -> B105 | C18: =Rent!C18 -> 1112 | D18: 0 | E18: =IF(Rent!E18=0,0,'Tenant Charges'!$H14) -> 0 | F18: =IF(Rent!F18=0,0,'Tenant Charges'!$H14) -> 0 | G18: =IF(Rent!G18=0,0,'Tenant Charges'!$H14) -> 0 | H18: =IF(Rent!H18=0,0,'Tenant Charges'!$H14) -> 0 | I18: =IF(Rent!I18=0,0,'Tenant Charges'!$H14) -> 0 | J18: =IF(Rent!J18=0,0,'Tenant Charges'!$H14) -> 0 | K18: =IF(Rent!K18=0,0,'Tenant Charges'!$H14) -> 0 | L18: =IF(Rent!L18=0,0,'Tenant Charges'!$H14) -> 0 | ... P18: =IF(Rent!P18=0,0,'Tenant Charges'!$H14) -> 0 | Q18: =SUM(E18:P18) -> 0 | R18: =Q18/C18 -> 0
A19: =Rent!A19 -> AT&T Mobility | B19: =Rent!B19 -> B106 | C19: =Rent!C19 -> 2494 | D19: 0.03 | E19: =IF(Rent!E19=0,0,'Tenant Charges'!$H15) -> 0 | F19: =IF(Rent!F19=0,0,'Tenant Charges'!$H15) -> 0 | G19: =IF(Rent!G19=0,0,'Tenant Charges'!$H15) -> 0 | H19: =IF(Rent!H19=0,0,'Tenant Charges'!$H15) -> 0 | I19: =IF(Rent!I19=0,0,'Tenant Charges'!$H15) -> 0 | J19: =IF(Rent!J19=0,0,'Tenant Charges'!$H15) -> 0 | K19: =IF(Rent!K19=0,0,'Tenant Charges'!$H15) -> 0 | L19: =IF(Rent!L19=0,0,'Tenant Charges'!$H15) -> 0 | ... P19: =IF(Rent!P19=0,0,'Tenant Charges'!$H15) -> 0 | Q19: =SUM(E19:P19) -> 0 | R19: =Q19/C19 -> 0 | S19: 3% of Minimum Annual Rent
A20: =Rent!A20 -> Discount Nutrition | B20: =Rent!B20 -> B108 | C20: =Rent!C20 -> 1500 | D20: 0 | E20: =IF(Rent!E20=0,0,'Tenant Charges'!$H16) -> 0 | F20: =IF(Rent!F20=0,0,'Tenant Charges'!$H16) -> 0 | G20: =IF(Rent!G20=0,0,'Tenant Charges'!$H16) -> 0 | H20: =IF(Rent!H20=0,0,'Tenant Charges'!$H16) -> 0 | I20: =IF(Rent!I20=0,0,'Tenant Charges'!$H16) -> 0 | J20: =IF(Rent!J20=0,0,'Tenant Charges'!$H16) -> 0 | K20: =IF(Rent!K20=0,0,'Tenant Charges'!$H16) -> 0 | L20: =IF(Rent!L20=0,0,'Tenant Charges'!$H16) -> 0 | ... P20: =IF(Rent!P20=0,0,'Tenant Charges'!$H16) -> 0 | Q20: =SUM(E20:P20) -> 0 | R20: =Q20/C20 -> 0
A21: =Rent!A21 -> Adapt Chiropractic | B21: =Rent!B21 -> B109 | C21: =Rent!C21 -> 1734 | D21: 0.05 | E21: =IF(Rent!E21=0,0,'Tenant Charges'!$H17) -> 0 | F21: =IF(Rent!F21=0,0,'Tenant Charges'!$H17) -> 0 | G21: =IF(Rent!G21=0,0,'Tenant Charges'!$H17) -> 0 | H21: =IF(Rent!H21=0,0,'Tenant Charges'!$H17) -> 0 | I21: =IF(Rent!I21=0,0,'Tenant Charges'!$H17) -> 0 | J21: =IF(Rent!J21=0,0,'Tenant Charges'!$H17) -> 0 | K21: =IF(Rent!K21=0,0,'Tenant Charges'!$H17) -> 0 | L21: =IF(Rent!L21=0,0,'Tenant Charges'!$H17) -> 0 | ... P21: =IF(Rent!P21=0,0,'Tenant Charges'!$H17) -> 0 | Q21: =SUM(E21:P21) -> 0 | R21: =Q21/C21 -> 0
A22: =Rent!A22 -> Speakeasy Suites | B22: =Rent!B22 -> B111 | C22: =Rent!C22 -> 3900 | D22: 0 | E22: =IF(Rent!E22=0,0,'Tenant Charges'!$H18) -> 0 | F22: =IF(Rent!F22=0,0,'Tenant Charges'!$H18) -> 0 | G22: =IF(Rent!G22=0,0,'Tenant Charges'!$H18) -> 0 | H22: =IF(Rent!H22=0,0,'Tenant Charges'!$H18) -> 0 | I22: =IF(Rent!I22=0,0,'Tenant Charges'!$H18) -> 0 | J22: =IF(Rent!J22=0,0,'Tenant Charges'!$H18) -> 0 | K22: =IF(Rent!K22=0,0,'Tenant Charges'!$H18) -> 0 | L22: =IF(Rent!L22=0,0,'Tenant Charges'!$H18) -> 0 | ... P22: =IF(Rent!P22=0,0,'Tenant Charges'!$H18) -> 0 | Q22: =SUM(E22:P22) -> 0 | R22: =Q22/C22 -> 0
A23: =Rent!A23 -> Kachina Stained Glass | B23: =Rent!B23 -> 101 | C23: =Rent!C23 -> 1287 | D23: 0 | E23: =IF(Rent!E23=0,0,'Tenant Charges'!$H19) -> 0.083333333 | F23: =IF(Rent!F23=0,0,'Tenant Charges'!$H19) -> 0.083333333 | G23: =IF(Rent!G23=0,0,'Tenant Charges'!$H19) -> 0.083333333 | H23: =IF(Rent!H23=0,0,'Tenant Charges'!$H19) -> 0.083333333 | I23: =IF(Rent!I23=0,0,'Tenant Charges'!$H19) -> 0.083333333 | J23: =IF(Rent!J23=0,0,'Tenant Charges'!$H19) -> 0.083333333 | K23: =IF(Rent!K23=0,0,'Tenant Charges'!$H19) -> 0.083333333 | L23: =IF(Rent!L23=0,0,'Tenant Charges'!$H19) -> 0.083333333 | ... P23: =IF(Rent!P23=0,0,'Tenant Charges'!$H19) -> 0.083333333 | Q23: =SUM(E23:P23) -> 1 | R23: =Q23/C23 -> 0.00077700078
A24: =Rent!A24 -> Zanders Creations | B24: =Rent!B24 -> 102 | C24: =Rent!C24 -> 1639 | D24: 0 | E24: =IF(Rent!E24=0,0,'Tenant Charges'!$H20) -> 0.083333333 | F24: =IF(Rent!F24=0,0,'Tenant Charges'!$H20) -> 0.083333333 | G24: =IF(Rent!G24=0,0,'Tenant Charges'!$H20) -> 0.083333333 | H24: =IF(Rent!H24=0,0,'Tenant Charges'!$H20) -> 0.083333333 | I24: =IF(Rent!I24=0,0,'Tenant Charges'!$H20) -> 0.083333333 | J24: =IF(Rent!J24=0,0,'Tenant Charges'!$H20) -> 0.083333333 | K24: =IF(Rent!K24=0,0,'Tenant Charges'!$H20) -> 0.083333333 | L24: =IF(Rent!L24=0,0,'Tenant Charges'!$H20) -> 0.083333333 | ... P24: =IF(Rent!P24=0,0,'Tenant Charges'!$H20) -> 0.083333333 | Q24: =SUM(E24:P24) -> 1 | R24: =Q24/C24 -> 0.00061012813
A25: =Rent!A25 -> Brightnow Dental | B25: =Rent!B25 -> 103 | C25: =Rent!C25 -> 3600 | D25: 0.04 | E25: =IF(Rent!E25=0,0,'Tenant Charges'!$H21) -> 0 | F25: =IF(Rent!F25=0,0,'Tenant Charges'!$H21) -> 0 | G25: =IF(Rent!G25=0,0,'Tenant Charges'!$H21) -> 0 | H25: =IF(Rent!H25=0,0,'Tenant Charges'!$H21) -> 0 | I25: =IF(Rent!I25=0,0,'Tenant Charges'!$H21) -> 0 | J25: =IF(Rent!J25=0,0,'Tenant Charges'!$H21) -> 0 | K25: =IF(Rent!K25=0,0,'Tenant Charges'!$H21) -> 0 | L25: =IF(Rent!L25=0,0,'Tenant Charges'!$H21) -> 0 | ... P25: =IF(Rent!P25=0,0,'Tenant Charges'!$H21) -> 0 | Q25: =SUM(E25:P25) -> 0 | R25: =Q25/C25 -> 0 | S25: 3% of Minimum Annual Rent
A26: =Rent!A26 -> Carr Animal Care | B26: =Rent!B26 -> 106 | C26: =Rent!C26 -> 1587 | D26: 0.1 | E26: =IF(Rent!E26=0,0,'Tenant Charges'!$H22) -> 0 | F26: =IF(Rent!F26=0,0,'Tenant Charges'!$H22) -> 0 | G26: =IF(Rent!G26=0,0,'Tenant Charges'!$H22) -> 0 | H26: =IF(Rent!H26=0,0,'Tenant Charges'!$H22) -> 0 | I26: =IF(Rent!I26=0,0,'Tenant Charges'!$H22) -> 0 | J26: =IF(Rent!J26=0,0,'Tenant Charges'!$H22) -> 0 | K26: =IF(Rent!K26=0,0,'Tenant Charges'!$H22) -> 0 | L26: =IF(Rent!L26=0,0,'Tenant Charges'!$H22) -> 0 | ... P26: =IF(Rent!P26=0,0,'Tenant Charges'!$H22) -> 0 | Q26: =SUM(E26:P26) -> 0 | R26: =Q26/C26 -> 0
A27: =Rent!A27 -> Razors Barber Shop | B27: =Rent!B27 -> 107 | C27: =Rent!C27 -> 1300 | D27: 0.15 | E27: =IF(Rent!E27=0,0,'Tenant Charges'!$H23) -> 0 | F27: =IF(Rent!F27=0,0,'Tenant Charges'!$H23) -> 0 | G27: =IF(Rent!G27=0,0,'Tenant Charges'!$H23) -> 0 | H27: =IF(Rent!H27=0,0,'Tenant Charges'!$H23) -> 0 | I27: =IF(Rent!I27=0,0,'Tenant Charges'!$H23) -> 0 | J27: =IF(Rent!J27=0,0,'Tenant Charges'!$H23) -> 0 | K27: =IF(Rent!K27=0,0,'Tenant Charges'!$H23) -> 0 | L27: =IF(Rent!L27=0,0,'Tenant Charges'!$H23) -> 0 | ... P27: =IF(Rent!P27=0,0,'Tenant Charges'!$H23) -> 0 | Q27: =SUM(E27:P27) -> 0 | R27: =Q27/C27 -> 0
A28: =Rent!A28 -> CrossFit New Strength | B28: =Rent!B28 -> 108 | C28: =Rent!C28 -> 3524 | D28: 0.05 | E28: =IF(Rent!E28=0,0,'Tenant Charges'!$H24) -> 63.148432 | F28: =IF(Rent!F28=0,0,'Tenant Charges'!$H24) -> 63.148432 | G28: =IF(Rent!G28=0,0,'Tenant Charges'!$H24) -> 63.148432 | H28: =IF(Rent!H28=0,0,'Tenant Charges'!$H24) -> 63.148432 | I28: =IF(Rent!I28=0,0,'Tenant Charges'!$H24) -> 63.148432 | J28: =IF(Rent!J28=0,0,'Tenant Charges'!$H24) -> 63.148432 | K28: =IF(Rent!K28=0,0,'Tenant Charges'!$H24) -> 63.148432 | L28: =IF(Rent!L28=0,0,'Tenant Charges'!$H24) -> 63.148432 | ... P28: =IF(Rent!P28=0,0,'Tenant Charges'!$H24) -> 63.148432 | Q28: =SUM(E28:P28) -> 757.78119 | R28: =Q28/C28 -> 0.21503439
A29: =Rent!A29 -> Vacant (Time Out Bar) | B29: =Rent!B29 -> 111 | C29: =Rent!C29 -> 3007 | D29: 0.03 | E29: =IF(Rent!E29=0,0,'Tenant Charges'!$H25) -> 0 | F29: =IF(Rent!F29=0,0,'Tenant Charges'!$H25) -> 0 | G29: =IF(Rent!G29=0,0,'Tenant Charges'!$H25) -> 0 | H29: =IF(Rent!H29=0,0,'Tenant Charges'!$H25) -> 0 | I29: =IF(Rent!I29=0,0,'Tenant Charges'!$H25) -> 0 | J29: =IF(Rent!J29=0,0,'Tenant Charges'!$H25) -> 0 | K29: =IF(Rent!K29=0,0,'Tenant Charges'!$H25) -> 44.380342 | L29: =IF(Rent!L29=0,0,'Tenant Charges'!$H25) -> 44.380342 | ... P29: =IF(Rent!P29=0,0,'Tenant Charges'!$H25) -> 44.380342 | Q29: =SUM(E29:P29) -> 266.28205 | R29: =Q29/C29 -> 0.088554058
A34: TOTALS | C34: =SUM(C14:C33) -> 67709 | E34: =SUM(E14:E33) -> 170.83229 | F34: =SUM(F14:F33) -> 170.83229 | G34: =SUM(G14:G33) -> 170.83229 | H34: =SUM(H14:H33) -> 170.83229 | I34: =SUM(I14:I33) -> 170.83229 | J34: =SUM(J14:J33) -> 170.83229 | K34: =SUM(K14:K33) -> 215.21264 | L34: =SUM(L14:L33) -> 215.21264 | ... P34: =SUM(P14:P33) -> 215.21264 | Q34: =SUM(Q14:Q29) -> 2316.2696
O36: TOTAL ADM | Q36: =Summary!O21 -> 2316.2696
O37: RECAPTURE | Q37: =Q34/Q36 -> 1
D39: NMK Tie-Out | E39: =E34-Summary!C21 -> 0 | F39: =F34-Summary!D21 -> 0 | G39: =G34-Summary!E21 -> 0 | H39: =H34-Summary!F21 -> 0 | I39: =I34-Summary!G21 -> 0 | J39: =J34-Summary!H21 -> 0 | K39: =K34-Summary!I21 -> 0 | L39: =L34-Summary!J21 -> 0 | ... P39: =P34-Summary!N21 -> 0

Sheet RE Tax
P1: =Summary!T4 -> Date Revised: | Q1: =Summary!U4 -> 46269 | R1: =Summary!W4 -> 0
A2: =Summary!$A2 -> ATHENA PROPERTY MANAGEMENT
A3: =Summary!$A3 -> GREENFIELD GATEWAY MESA, ARIZONA
A4: =Summary!$A4 -> PROJECT NO. 801
A5: =Summary!$A5 -> 01/01/26-12/31/26
A6: =Summary!$A6 -> 2026 OPERATING BUDGET
A9: TENANT | B9: SUITE | C9: SQUARE | D9: PRORATA | E9: JAN | F9: FEB | G9: MARCH | H9: APRIL | I9: MAY | J9: JUNE | K9: JULY | L9: AUGUST | M9: SEPT | N9: OCT | O9: NOV | P9: DEC | Q9: TOTALS
B10: # | C10: FOOTAGE | D10: SHARE
A12: RE Tax
A14: =Rent!A14 -> EOS Fitness | B14: =Rent!B14 -> Major A | C14: =Rent!C14 -> 35000 | D14: =C14/$C$37 -> 0.51691799 | E14: =IF(Rent!E14=0,0,('Tenant Charges'!$I10)) -> 6224.2423 | F14: =IF(Rent!F14=0,0,('Tenant Charges'!$I10)) -> 6224.2423 | G14: =IF(Rent!G14=0,0,('Tenant Charges'!$I10)) -> 6224.2423 | H14: =IF(Rent!H14=0,0,('Tenant Charges'!$I10)) -> 6224.2423 | I14: =IF(Rent!I14=0,0,('Tenant Charges'!$I10)) -> 6224.2423 | J14: =IF(Rent!J14=0,0,('Tenant Charges'!$I10)) -> 6224.2423 | K14: =IF(Rent!K14=0,0,('Tenant Charges'!$I10)) -> 6224.2423 | L14: =IF(Rent!L14=0,0,('Tenant Charges'!$I10)) -> 6224.2423 | ... P14: =IF(Rent!P14=0,0,('Tenant Charges'!$I10)) -> 6224.2423 | Q14: =SUM(E14:P14) -> 74690.907
A15: =Rent!A15 -> Third Pasrty MVS | B15: =Rent!B15 -> B101 | C15: =Rent!C15 -> 3000 | D15: =C15/$C$37 -> 0.044307256 | E15: =IF(Rent!E15=0,0,('Tenant Charges'!$I11)) -> 533.50648 | F15: =IF(Rent!F15=0,0,('Tenant Charges'!$I11)) -> 533.50648 | G15: =IF(Rent!G15=0,0,('Tenant Charges'!$I11)) -> 533.50648 | H15: =IF(Rent!H15=0,0,('Tenant Charges'!$I11)) -> 533.50648 | I15: =IF(Rent!I15=0,0,('Tenant Charges'!$I11)) -> 533.50648 | J15: =IF(Rent!J15=0,0,('Tenant Charges'!$I11)) -> 533.50648 | K15: =IF(Rent!K15=0,0,('Tenant Charges'!$I11)) -> 533.50648 | L15: =IF(Rent!L15=0,0,('Tenant Charges'!$I11)) -> 533.50648 | ... P15: =IF(Rent!P15=0,0,('Tenant Charges'!$I11)) -> 533.50648 | Q15: =SUM(E15:P15) -> 6402.0778 | R15: =Q15/C15 -> 2.1340259
A16: =Rent!A16 -> Sally Beauty Supply | B16: =Rent!B16 -> B103 | C16: =Rent!C16 -> 1625 | D16: =C16/$C$37 -> 0.023999764 | E16: =IF(Rent!E16=0,0,('Tenant Charges'!$I12)) -> 288.98268 | F16: =IF(Rent!F16=0,0,('Tenant Charges'!$I12)) -> 288.98268 | G16: =IF(Rent!G16=0,0,('Tenant Charges'!$I12)) -> 288.98268 | H16: =IF(Rent!H16=0,0,('Tenant Charges'!$I12)) -> 288.98268 | I16: =IF(Rent!I16=0,0,('Tenant Charges'!$I12)) -> 288.98268 | J16: =IF(Rent!J16=0,0,('Tenant Charges'!$I12)) -> 288.98268 | K16: =IF(Rent!K16=0,0,('Tenant Charges'!$I12)) -> 288.98268 | L16: =IF(Rent!L16=0,0,('Tenant Charges'!$I12)) -> 288.98268 | ... P16: =IF(Rent!P16=0,0,('Tenant Charges'!$I12)) -> 288.98268 | Q16: =SUM(E16:P16) -> 3467.7921
A17: =Rent!A17 -> Wild Side Smoke Shop | B17: =Rent!B17 -> B104 | C17: =Rent!C17 -> 1400 | D17: =C17/$C$37 -> 0.020676719 | E17: =IF(Rent!E17=0,0,('Tenant Charges'!$I13)) -> 248.96969 | F17: =IF(Rent!F17=0,0,('Tenant Charges'!$I13)) -> 248.96969 | G17: =IF(Rent!G17=0,0,('Tenant Charges'!$I13)) -> 248.96969 | H17: =IF(Rent!H17=0,0,('Tenant Charges'!$I13)) -> 248.96969 | I17: =IF(Rent!I17=0,0,('Tenant Charges'!$I13)) -> 248.96969 | J17: =IF(Rent!J17=0,0,('Tenant Charges'!$I13)) -> 248.96969 | K17: =IF(Rent!K17=0,0,('Tenant Charges'!$I13)) -> 248.96969 | L17: =IF(Rent!L17=0,0,('Tenant Charges'!$I13)) -> 248.96969 | ... P17: =IF(Rent!P17=0,0,('Tenant Charges'!$I13)) -> 248.96969 | Q17: =SUM(E17:P17) -> 2987.6363 | R17: =Q17/C17 -> 2.1340259
A18: =Rent!A18 -> Green Spa, LLC | B18: =Rent!B18 -> B105 | C18: =Rent!C18 -> 1112 | D18: =C18/$C$37 -> 0.016423223 | E18: =IF(Rent!E18=0,0,('Tenant Charges'!$I14)) -> 197.75307 | F18: =IF(Rent!F18=0,0,('Tenant Charges'!$I14)) -> 197.75307 | G18: =IF(Rent!G18=0,0,('Tenant Charges'!$I14)) -> 197.75307 | H18: =IF(Rent!H18=0,0,('Tenant Charges'!$I14)) -> 197.75307 | I18: =IF(Rent!I18=0,0,('Tenant Charges'!$I14)) -> 197.75307 | J18: =IF(Rent!J18=0,0,('Tenant Charges'!$I14)) -> 197.75307 | K18: =IF(Rent!K18=0,0,('Tenant Charges'!$I14)) -> 197.75307 | L18: =IF(Rent!L18=0,0,('Tenant Charges'!$I14)) -> 197.75307 | ... P18: =IF(Rent!P18=0,0,('Tenant Charges'!$I14)) -> 197.75307 | Q18: =SUM(E18:P18) -> 2373.0368 | R18: =Q18/C18 -> 2.1340259
A19: =Rent!A19 -> AT&T Mobility | B19: =Rent!B19 -> B106 | C19: =Rent!C19 -> 2494 | D19: =C19/$C$37 -> 0.036834099 | E19: =IF(Rent!E19=0,0,('Tenant Charges'!$I15)) -> 443.52172 | F19: =IF(Rent!F19=0,0,('Tenant Charges'!$I15)) -> 443.52172 | G19: =IF(Rent!G19=0,0,('Tenant Charges'!$I15)) -> 443.52172 | H19: =IF(Rent!H19=0,0,('Tenant Charges'!$I15)) -> 443.52172 | I19: =IF(Rent!I19=0,0,('Tenant Charges'!$I15)) -> 443.52172 | J19: =IF(Rent!J19=0,0,('Tenant Charges'!$I15)) -> 443.52172 | K19: =IF(Rent!K19=0,0,('Tenant Charges'!$I15)) -> 443.52172 | L19: =IF(Rent!L19=0,0,('Tenant Charges'!$I15)) -> 443.52172 | ... P19: =IF(Rent!P19=0,0,('Tenant Charges'!$I15)) -> 443.52172 | Q19: =SUM(E19:P19) -> 5322.2607 | R19: =Q19/C19 -> 2.1340259
A20: =Rent!A20 -> Discount Nutrition | B20: =Rent!B20 -> B108 | C20: =Rent!C20 -> 1500 | D20: =C20/$C$37 -> 0.022153628 | E20: =IF(Rent!E20=0,0,('Tenant Charges'!$I16)) -> 266.75324 | F20: =IF(Rent!F20=0,0,('Tenant Charges'!$I16)) -> 266.75324 | G20: =IF(Rent!G20=0,0,('Tenant Charges'!$I16)) -> 266.75324 | H20: =IF(Rent!H20=0,0,('Tenant Charges'!$I16)) -> 266.75324 | I20: =IF(Rent!I20=0,0,('Tenant Charges'!$I16)) -> 266.75324 | J20: =IF(Rent!J20=0,0,('Tenant Charges'!$I16)) -> 266.75324 | K20: =IF(Rent!K20=0,0,('Tenant Charges'!$I16)) -> 266.75324 | L20: =IF(Rent!L20=0,0,('Tenant Charges'!$I16)) -> 266.75324 | ... P20: =IF(Rent!P20=0,0,('Tenant Charges'!$I16)) -> 266.75324 | Q20: =SUM(E20:P20) -> 3201.0389 | R20: =Q20/C20 -> 2.1340259
A21: =Rent!A21 -> Adapt Chiropractic | B21: =Rent!B21 -> B109 | C21: =Rent!C21 -> 1734 | D21: =C21/$C$37 -> 0.025609594 | E21: =IF(Rent!E21=0,0,('Tenant Charges'!$I17)) -> 308.36675 | F21: =IF(Rent!F21=0,0,('Tenant Charges'!$I17)) -> 308.36675 | G21: =IF(Rent!G21=0,0,('Tenant Charges'!$I17)) -> 308.36675 | H21: =IF(Rent!H21=0,0,('Tenant Charges'!$I17)) -> 308.36675 | I21: =IF(Rent!I21=0,0,('Tenant Charges'!$I17)) -> 308.36675 | J21: =IF(Rent!J21=0,0,('Tenant Charges'!$I17)) -> 308.36675 | K21: =IF(Rent!K21=0,0,('Tenant Charges'!$I17)) -> 308.36675 | L21: =IF(Rent!L21=0,0,('Tenant Charges'!$I17)) -> 308.36675 | ... P21: =IF(Rent!P21=0,0,('Tenant Charges'!$I17)) -> 308.36675 | Q21: =SUM(E21:P21) -> 3700.401 | R21: =Q21/C21 -> 2.1340259
A22: =Rent!A22 -> Speakeasy Suites | B22: =Rent!B22 -> B111 | C22: =Rent!C22 -> 3900 | D22: =C22/$C$37 -> 0.057599433 | E22: =IF(Rent!E22=0,0,('Tenant Charges'!$I18)) -> 693.55843 | F22: =IF(Rent!F22=0,0,('Tenant Charges'!$I18)) -> 693.55843 | G22: =IF(Rent!G22=0,0,('Tenant Charges'!$I18)) -> 693.55843 | H22: =IF(Rent!H22=0,0,('Tenant Charges'!$I18)) -> 693.55843 | I22: =IF(Rent!I22=0,0,('Tenant Charges'!$I18)) -> 693.55843 | J22: =IF(Rent!J22=0,0,('Tenant Charges'!$I18)) -> 693.55843 | K22: =IF(Rent!K22=0,0,('Tenant Charges'!$I18)) -> 693.55843 | L22: =IF(Rent!L22=0,0,('Tenant Charges'!$I18)) -> 693.55843 | ... P22: =IF(Rent!P22=0,0,('Tenant Charges'!$I18)) -> 693.55843 | Q22: =SUM(E22:P22) -> 8322.7011 | R22: =Q22/C22 -> 2.1340259
A23: =Rent!A23 -> Kachina Stained Glass | B23: =Rent!B23 -> 101 | C23: =Rent!C23 -> 1287 | D23: =C23/$C$37 -> 0.019007813 | E23: =IF(Rent!E23=0,0,('Tenant Charges'!$I19)) -> 228.87428 | F23: =IF(Rent!F23=0,0,('Tenant Charges'!$I19)) -> 228.87428 | G23: =IF(Rent!G23=0,0,('Tenant Charges'!$I19)) -> 228.87428 | H23: =IF(Rent!H23=0,0,('Tenant Charges'!$I19)) -> 228.87428 | I23: =IF(Rent!I23=0,0,('Tenant Charges'!$I19)) -> 228.87428 | J23: =IF(Rent!J23=0,0,('Tenant Charges'!$I19)) -> 228.87428 | K23: =IF(Rent!K23=0,0,('Tenant Charges'!$I19)) -> 228.87428 | L23: =IF(Rent!L23=0,0,('Tenant Charges'!$I19)) -> 228.87428 | ... P23: =IF(Rent!P23=0,0,('Tenant Charges'!$I19)) -> 228.87428 | Q23: =SUM(E23:P23) -> 2746.4914
A24: =Rent!A24 -> Zanders Creations | B24: =Rent!B24 -> 102 | C24: =Rent!C24 -> 1639 | D24: =C24/$C$37 -> 0.024206531 | E24: =IF(Rent!E24=0,0,('Tenant Charges'!$I20)) -> 291.47237 | F24: =IF(Rent!F24=0,0,('Tenant Charges'!$I20)) -> 291.47237 | G24: =IF(Rent!G24=0,0,('Tenant Charges'!$I20)) -> 291.47237 | H24: =IF(Rent!H24=0,0,('Tenant Charges'!$I20)) -> 291.47237 | I24: =IF(Rent!I24=0,0,('Tenant Charges'!$I20)) -> 291.47237 | J24: =IF(Rent!J24=0,0,('Tenant Charges'!$I20)) -> 291.47237 | K24: =IF(Rent!K24=0,0,('Tenant Charges'!$I20)) -> 291.47237 | L24: =IF(Rent!L24=0,0,('Tenant Charges'!$I20)) -> 291.47237 | ... P24: =IF(Rent!P24=0,0,('Tenant Charges'!$I20)) -> 291.47237 | Q24: =SUM(E24:P24) -> 3497.6685 | R24: =Q24/C24 -> 2.1340259
A25: =Rent!A25 -> Brightnow Dental | B25: =Rent!B25 -> 103 | C25: =Rent!C25 -> 3600 | D25: =C25/$C$37 -> 0.053168707 | E25: =IF(Rent!E25=0,0,('Tenant Charges'!$I21)) -> 640.20778 | F25: =IF(Rent!F25=0,0,('Tenant Charges'!$I21)) -> 640.20778 | G25: =IF(Rent!G25=0,0,('Tenant Charges'!$I21)) -> 640.20778 | H25: =IF(Rent!H25=0,0,('Tenant Charges'!$I21)) -> 640.20778 | I25: =IF(Rent!I25=0,0,('Tenant Charges'!$I21)) -> 640.20778 | J25: =IF(Rent!J25=0,0,('Tenant Charges'!$I21)) -> 640.20778 | K25: =IF(Rent!K25=0,0,('Tenant Charges'!$I21)) -> 640.20778 | L25: =IF(Rent!L25=0,0,('Tenant Charges'!$I21)) -> 640.20778 | ... P25: =IF(Rent!P25=0,0,('Tenant Charges'!$I21)) -> 640.20778 | Q25: =SUM(E25:P25) -> 7682.4933 | R25: =Q25/C25 -> 2.1340259
A26: =Rent!A26 -> Carr Animal Care | B26: =Rent!B26 -> 106 | C26: =Rent!C26 -> 1587 | D26: =C26/$C$37 -> 0.023438538 | E26: =IF(Rent!E26=0,0,('Tenant Charges'!$I22)) -> 282.22493 | F26: =IF(Rent!F26=0,0,('Tenant Charges'!$I22)) -> 282.22493 | G26: =IF(Rent!G26=0,0,('Tenant Charges'!$I22)) -> 282.22493 | H26: =IF(Rent!H26=0,0,('Tenant Charges'!$I22)) -> 282.22493 | I26: =IF(Rent!I26=0,0,('Tenant Charges'!$I22)) -> 282.22493 | J26: =IF(Rent!J26=0,0,('Tenant Charges'!$I22)) -> 282.22493 | K26: =IF(Rent!K26=0,0,('Tenant Charges'!$I22)) -> 282.22493 | L26: =IF(Rent!L26=0,0,('Tenant Charges'!$I22)) -> 282.22493 | ... P26: =IF(Rent!P26=0,0,('Tenant Charges'!$I22)) -> 282.22493 | Q26: =SUM(E26:P26) -> 3386.6991 | R26: =Q26/C26 -> 2.1340259
A27: =Rent!A27 -> Razors Barber Shop | B27: =Rent!B27 -> 107 | C27: =Rent!C27 -> 1300 | D27: =C27/$C$37 -> 0.019199811 | E27: =IF(Rent!E27=0,0,('Tenant Charges'!$I23)) -> 231.18614 | F27: =IF(Rent!F27=0,0,('Tenant Charges'!$I23)) -> 231.18614 | G27: =IF(Rent!G27=0,0,('Tenant Charges'!$I23)) -> 231.18614 | H27: =IF(Rent!H27=0,0,('Tenant Charges'!$I23)) -> 231.18614 | I27: =IF(Rent!I27=0,0,('Tenant Charges'!$I23)) -> 231.18614 | J27: =IF(Rent!J27=0,0,('Tenant Charges'!$I23)) -> 231.18614 | K27: =IF(Rent!K27=0,0,('Tenant Charges'!$I23)) -> 231.18614 | L27: =IF(Rent!L27=0,0,('Tenant Charges'!$I23)) -> 231.18614 | ... P27: =IF(Rent!P27=0,0,('Tenant Charges'!$I23)) -> 231.18614 | Q27: =SUM(E27:P27) -> 2774.2337 | R27: =Q27/C27 -> 2.1340259
A28: =Rent!A28 -> CrossFit New Strength | B28: =Rent!B28 -> 108 | C28: =Rent!C28 -> 3524 | D28: =C28/$C$37 -> 0.052046257 | E28: =IF(Rent!E28=0,0,('Tenant Charges'!$I24)) -> 626.69228 | F28: =IF(Rent!F28=0,0,('Tenant Charges'!$I24)) -> 626.69228 | G28: =IF(Rent!G28=0,0,('Tenant Charges'!$I24)) -> 626.69228 | H28: =IF(Rent!H28=0,0,('Tenant Charges'!$I24)) -> 626.69228 | I28: =IF(Rent!I28=0,0,('Tenant Charges'!$I24)) -> 626.69228 | J28: =IF(Rent!J28=0,0,('Tenant Charges'!$I24)) -> 626.69228 | K28: =IF(Rent!K28=0,0,('Tenant Charges'!$I24)) -> 626.69228 | L28: =IF(Rent!L28=0,0,('Tenant Charges'!$I24)) -> 626.69228 | ... P28: =IF(Rent!P28=0,0,('Tenant Charges'!$I24)) -> 626.69228 | Q28: =SUM(E28:P28) -> 7520.3074 | R28: =Q28/C28 -> 2.1340259
A29: =Rent!A29 -> Vacant (Time Out Bar) | B29: =Rent!B29 -> 111 | C29: =Rent!C29 -> 3007 | D29: =C29/$C$37 -> 0.04441064 | E29: =IF(Rent!E29=0,0,('Tenant Charges'!$I25)) -> 0 | F29: =IF(Rent!F29=0,0,('Tenant Charges'!$I25)) -> 0 | G29: =IF(Rent!G29=0,0,('Tenant Charges'!$I25)) -> 0 | H29: =IF(Rent!H29=0,0,('Tenant Charges'!$I25)) -> 0 | I29: =IF(Rent!I29=0,0,('Tenant Charges'!$I25)) -> 0 | J29: =IF(Rent!J29=0,0,('Tenant Charges'!$I25)) -> 0 | K29: =IF(Rent!K29=0,0,('Tenant Charges'!$I25)) -> 534.75133 | L29: =IF(Rent!L29=0,0,('Tenant Charges'!$I25)) -> 534.75133 | ... P29: =IF(Rent!P29=0,0,('Tenant Charges'!$I25)) -> 534.75133 | Q29: =SUM(E29:P29) -> 3208.508
A37: TOTALS | C37: =SUM(C14:C36) -> 67709 | D37: =SUM(D14:D36) -> 1 | E37: =SUM(E14:E29) -> 11506.312 | F37: =SUM(F14:F29) -> 11506.312 | G37: =SUM(G14:G29) -> 11506.312 | H37: =SUM(H14:H29) -> 11506.312 | I37: =SUM(I14:I29) -> 11506.312 | J37: =SUM(J14:J29) -> 11506.312 | K37: =SUM(K14:K29) -> 12041.063 | L37: =SUM(L14:L29) -> 12041.063 | ... Q37: =SUM(Q14:Q29) -> 141284.25
O39: TOTAL RE Tax | Q39: =Summary!O80 -> 144492.76
O40: RECAPTURE | Q40: =Q37/Q39 -> 0.97779468 | S40: Slippage due to vacancy
D44: NMK Tie-Out | E44: =E37-Summary!C19 -> 0 | F44: =F37-Summary!D19 -> 0 | G44: =G37-Summary!E19 -> 0 | H44: =H37-Summary!F19 -> 0 | I44: =I37-Summary!G19 -> 0 | J44: =J37-Summary!H19 -> 0 | K44: =K37-Summary!I19 -> 0 | L44: =L37-Summary!J19 -> 0 | ... P44: =P37-Summary!N19 -> 0

Sheet Signage
P1: =Summary!T4 -> Date Revised: | Q1: =Summary!U4 -> 46269 | R1: =Summary!W4 -> 0
A2: =Summary!$A2 -> ATHENA PROPERTY MANAGEMENT
A3: =Summary!$A3 -> GREENFIELD GATEWAY MESA, ARIZONA
A4: =Summary!$A4 -> PROJECT NO. 801
A5: =Summary!$A5 -> 01/01/26-12/31/26
A6: =Summary!$A6 -> 2026 OPERATING BUDGET
A9: TENANT | B9: SUITE | C9: SQUARE | D9: PRORATA | E9: JAN | F9: FEB | G9: MARCH | H9: APRIL | I9: MAY | J9: JUNE | K9: JULY | L9: AUGUST | M9: SEPT | N9: OCT | O9: NOV | P9: DEC | Q9: TOTALS
B10: # | C10: FOOTAGE | D10: SHARE
A12: RE Tax
A14: =Rent!A14 -> EOS Fitness | B14: =Rent!B14 -> Major A | C14: =Rent!C14 -> 35000 | D14: =C14/$C$37 -> 0.51691799 | E14: 0 | F14: =E14 -> 0 | G14: =F14 -> 0 | H14: =G14 -> 0 | I14: =H14 -> 0 | J14: =I14 -> 0 | K14: =J14 -> 0 | L14: =K14 -> 0 | M14: =L14 -> 0 | ... P14: =O14 -> 0 | Q14: =SUM(E14:P14) -> 0
A15: =Rent!A15 -> Third Pasrty MVS | B15: =Rent!B15 -> B101 | C15: =Rent!C15 -> 3000 | D15: =C15/$C$37 -> 0.044307256 | Q15: =SUM(E15:P15) -> 0 | R15: =Q15/C15 -> 0
A16: =Rent!A16 -> Sally Beauty Supply | B16: =Rent!B16 -> B103 | C16: =Rent!C16 -> 1625 | D16: =C16/$C$37 -> 0.023999764 | Q16: =SUM(E16:P16) -> 0
A17: =Rent!A17 -> Wild Side Smoke Shop | B17: =Rent!B17 -> B104 | C17: =Rent!C17 -> 1400 | D17: =C17/$C$37 -> 0.020676719 | Q17: =SUM(E17:P17) -> 0 | R17: =Q17/C17 -> 0
A18: =Rent!A18 -> Green Spa, LLC | B18: =Rent!B18 -> B105 | C18: =Rent!C18 -> 1112 | D18: =C18/$C$37 -> 0.016423223 | Q18: =SUM(E18:P18) -> 0 | R18: =Q18/C18 -> 0
A19: =Rent!A19 -> AT&T Mobility | B19: =Rent!B19 -> B106 | C19: =Rent!C19 -> 2494 | D19: =C19/$C$37 -> 0.036834099 | E19: 500 | F19: =E19 -> 500 | G19: =F19 -> 500 | H19: =G19 -> 500 | I19: =H19 -> 500 | J19: =I19 -> 500 | K19: =J19 -> 500 | L19: =K19 -> 500 | M19: =L19 -> 500 | ... P19: =O19 -> 500 | Q19: =SUM(E19:P19) -> 6000 | R19: =Q19/C19 -> 2.4057739
A20: =Rent!A20 -> Discount Nutrition | B20: =Rent!B20 -> B108 | C20: =Rent!C20 -> 1500 | D20: =C20/$C$37 -> 0.022153628 | Q20: =SUM(E20:P20) -> 0 | R20: =Q20/C20 -> 0
A21: =Rent!A21 -> Adapt Chiropractic | B21: =Rent!B21 -> B109 | C21: =Rent!C21 -> 1734 | D21: =C21/$C$37 -> 0.025609594 | Q21: =SUM(E21:P21) -> 0 | R21: =Q21/C21 -> 0
A22: =Rent!A22 -> Speakeasy Suites | B22: =Rent!B22 -> B111 | C22: =Rent!C22 -> 3900 | D22: =C22/$C$37 -> 0.057599433 | Q22: =SUM(E22:P22) -> 0 | R22: =Q22/C22 -> 0
A23: =Rent!A23 -> Kachina Stained Glass | B23: =Rent!B23 -> 101 | C23: =Rent!C23 -> 1287 | D23: =C23/$C$37 -> 0.019007813 | E23: 70.83 | F23: =E23 -> 70.83 | G23: =F23 -> 70.83 | H23: =G23 -> 70.83 | I23: =H23 -> 70.83 | J23: =I23 -> 70.83 | K23: =J23 -> 70.83 | L23: =K23 -> 70.83 | M23: =L23 -> 70.83 | ... P23: =O23 -> 70.83 | Q23: =SUM(E23:P23) -> 849.96
A24: =Rent!A24 -> Zanders Creations | B24: =Rent!B24 -> 102 | C24: =Rent!C24 -> 1639 | D24: =C24/$C$37 -> 0.024206531 | Q24: =SUM(E24:P24) -> 0 | R24: =Q24/C24 -> 0
A25: =Rent!A25 -> Brightnow Dental | B25: =Rent!B25 -> 103 | C25: =Rent!C25 -> 3600 | D25: =C25/$C$37 -> 0.053168707 | E25: 500 | F25: =E25 -> 500 | G25: =F25 -> 500 | H25: =G25 -> 500 | I25: =H25 -> 500 | J25: =I25 -> 500 | K25: =J25 -> 500 | L25: =K25 -> 500 | M25: =L25 -> 500 | ... P25: =O25 -> 500 | Q25: =SUM(E25:P25) -> 6000 | R25: =Q25/C25 -> 1.6666667
A26: =Rent!A26 -> Carr Animal Care | B26: =Rent!B26 -> 106 | C26: =Rent!C26 -> 1587 | D26: =C26/$C$37 -> 0.023438538 | Q26: =SUM(E26:P26) -> 0 | R26: =Q26/C26 -> 0
A27: =Rent!A27 -> Razors Barber Shop | B27: =Rent!B27 -> 107 | C27: =Rent!C27 -> 1300 | D27: =C27/$C$37 -> 0.019199811 | Q27: =SUM(E27:P27) -> 0 | R27: =Q27/C27 -> 0
A28: =Rent!A28 -> CrossFit New Strength | B28: =Rent!B28 -> 108 | C28: =Rent!C28 -> 3524 | D28: =C28/$C$37 -> 0.052046257 | Q28: =SUM(E28:P28) -> 0 | R28: =Q28/C28 -> 0
A29: =Rent!A29 -> Vacant (Time Out Bar) | B29: =Rent!B29 -> 111 | C29: =Rent!C29 -> 3007 | D29: =C29/$C$37 -> 0.04441064 | Q29: =SUM(E29:P29) -> 0
Q30: =SUM(E30:P30) -> 0
A31: Walmart | C31: NAP | E31: 2000 | F31: =E31 -> 2000 | G31: =F31 -> 2000 | H31: =G31 -> 2000 | I31: =H31 -> 2000 | J31: =I31 -> 2000 | K31: =J31 -> 2000 | L31: =K31 -> 2000 | M31: =L31 -> 2000 | ... P31: =O31 -> 2000 | Q31: =SUM(E31:P31) -> 24000
A32: Sportsman's Warehouse | C32: NAP | E32: 1500 | F32: =E32 -> 1500 | G32: =F32 -> 1500 | H32: =G32 -> 1500 | I32: =H32 -> 1500 | J32: =I32 -> 1500 | K32: =J32 -> 1500 | L32: =K32 -> 1500 | M32: =L32 -> 1500 | ... P32: =O32 -> 1500 | Q32: =SUM(E32:P32) -> 18000
A33: John F. Long Foundation | C33: NAP | E33: 15 | F33: =E33 -> 15 | G33: =F33 -> 15 | H33: =G33 -> 15 | I33: =H33 -> 15 | J33: =I33 -> 15 | K33: =J33 -> 15 | L33: =K33 -> 15 | M33: =L33 -> 15 | ... P33: =O33 -> 15 | Q33: =SUM(E33:P33) -> 180
A37: TOTALS | C37: =SUM(C14:C36) -> 67709 | D37: =SUM(D14:D36) -> 1 | E37: =SUM(E14:E34) -> 4585.83 | F37: =SUM(F14:F34) -> 4585.83 | G37: =SUM(G14:G34) -> 4585.83 | H37: =SUM(H14:H34) -> 4585.83 | I37: =SUM(I14:I34) -> 4585.83 | J37: =SUM(J14:J34) -> 4585.83 | K37: =SUM(K14:K34) -> 4585.83 | L37: =SUM(L14:L34) -> 4585.83 | ... Q37: =SUM(Q14:Q34) -> 55029.96
O39: TOTAL Signage | Q39: =Summary!O80 -> 144492.76
O40: RECAPTURE | Q40: =Q37/Q39 -> 0.38084925
D45: NMK Tie-Out | E45: =E37-Summary!C22 -> 0 | F45: =F37-Summary!D22 -> 0 | G45: =G37-Summary!E22 -> 0 | H45: =H37-Summary!F22 -> 0 | I45: =I37-Summary!G22 -> 0 | J45: =J37-Summary!H22 -> 0 | K45: =K37-Summary!I22 -> 0 | L45: =L37-Summary!J22 -> 0 | ... P45: =P37-Summary!N22 -> 0

Sheet Sheet
A2: ATHENA PROPERTY MANAGEMENT
A3: GREENFIELD GATEWAY MESA, ARIZONA
A4: PROJECT NO. 801
A5: 01/01/26-12/31/26
A6: 2026 OPERATING BUDGET
Q8: YEARLY TOTAL
A9: TENANT | B9: SUITE | C9: SQUARE | D9: RATE | E9: JAN | F9: FEB | G9: MARCH | H9: APRIL | I9: MAY | J9: JUNE | K9: JULY | L9: AUGUST | M9: SEPT | N9: OCT | O9: NOV | P9: DEC
B10: # | C10: FOOTAGE
A11: Rental Sales Tax | D11: 0.025
A13: EOS Fitness | B13: Major A | C13: 28159 | Q13: -
B14: Total Monthly Charges | E14: 64560.81 | F14: 64560.81 | G14: 64560.81 | H14: 64560.81 | I14: 64560.81 | J14: 64560.81 | K14: 64560.81 | L14: 64560.81 | M14: 64560.81 | N14: 64560.81 | O14: 64560.81 | P14: 64560.81 | Q14: 774730
D15: 0.025 | E15: 1614.02 | F15: 1614.02 | G15: 1614.02 | H15: 1614.02 | I15: 1614.02 | J15: 1614.02 | K15: 1614.02 | L15: 1614.02 | M15: 1614.02 | N15: 1614.02 | O15: 1614.02 | P15: 1614.02 | Q15: 19368
C16: Total Tax | E16: 1614.02 | F16: 1614.02 | G16: 1614.02 | H16: 1614.02 | I16: 1614.02 | J16: 1614.02 | K16: 1614.02 | L16: 1614.02 | M16: 1614.02 | N16: 1614.02 | O16: 1614.02 | P16: 1614.02 | Q16: 19368.24
A18: Third Pasrty MVS | B18: B101 | C18: 3000 | Q18: -
B19: Total Monthly Charges | E19: 8024.5 | F19: 8024.5 | G19: 8024.5 | H19: 8024.5 | I19: 8024.5 | J19: 8024.5 | K19: 8024.5 | L19: 8024.5 | M19: 8024.5 | N19: 8210.21 | O19: 8210.21 | P19: 8210.21 | Q19: 96851
B20: Sales Tax | D20: 0.025 | E20: 200.61 | F20: 200.61 | G20: 200.61 | H20: 200.61 | I20: 200.61 | J20: 200.61 | K20: 200.61 | L20: 200.61 | M20: 200.61 | N20: 205.26 | O20: 205.26 | P20: 205.26 | Q20: 2421
C21: Total | E21: 200.61 | F21: 200.61 | G21: 200.61 | H21: 200.61 | I21: 200.61 | J21: 200.61 | K21: 200.61 | L21: 200.61 | M21: 200.61 | N21: 205.26 | O21: 205.26 | P21: 205.26 | Q21: 2421.28
A23: Sally Beauty Supply | B23: B103 | C23: 1625 | Q23: -
B24: Total Monthly Charges | E24: 3230.8 | F24: 3230.8 | G24: 3230.8 | H24: 3230.8 | I24: 3230.8 | J24: 3230.8 | K24: 3230.8 | L24: 3230.8 | M24: 3230.8 | N24: 3230.8 | O24: 3230.8 | P24: 3230.8 | Q24: 38770
B25: Sales Tax | D25: 0.025 | E25: 80.77 | F25: 80.77 | G25: 80.77 | H25: 80.77 | I25: 80.77 | J25: 80.77 | K25: 80.77 | L25: 80.77 | M25: 80.77 | N25: 80.77 | O25: 80.77 | P25: 80.77 | Q25: 969
C26: Total | E26: 80.77 | F26: 80.77 | G26: 80.77 | H26: 80.77 | I26: 80.77 | J26: 80.77 | K26: 80.77 | L26: 80.77 | M26: 80.77 | N26: 80.77 | O26: 80.77 | P26: 80.77 | Q26: 969
A28: Wild Side Smoke Shop | B28: B104 | C28: 1400 | Q28: -
B29: Total Monthly Charges | E29: 3281.22 | F29: 3281.22 | G29: 3281.22 | H29: 3281.22 | I29: 3355.48 | J29: 3355.48 | K29: 3355.48 | L29: 3355.48 | M29: 3355.48 | N29: 3355.48 | O29: 3355.48 | P29: 3355.48 | Q29: 39969
B30: Sales Tax | D30: 0.025 | E30: 82.03 | F30: 82.03 | G30: 82.03 | H30: 82.03 | I30: 83.89 | J30: 83.89 | K30: 83.89 | L30: 83.89 | M30: 83.89 | N30: 83.89 | O30: 83.89 | P30: 83.89 | Q30: 999
C31: Total | E31: 82.03 | F31: 82.03 | G31: 82.03 | H31: 82.03 | I31: 83.89 | J31: 83.89 | K31: 83.89 | L31: 83.89 | M31: 83.89 | N31: 83.89 | O31: 83.89 | P31: 83.89 | Q31: 999
A33: Green Spa, LLC | B33: B105 | C33: 1112 | Q33: -
B34: Total Monthly Charges | E34: 2746.43 | F34: 2746.43 | G34: 2746.43 | H34: 2788.56 | I34: 2788.56 | J34: 2788.56 | K34: 2788.56 | L34: 2788.56 | M34: 2788.56 | N34: 2788.56 | O34: 2788.56 | P34: 2788.56 | Q34: 33336
B35: Sales Tax | D35: 0.025 | E35: 68.66 | F35: 68.66 | G35: 68.66 | H35: 69.71 | I35: 69.71 | J35: 69.71 | K35: 69.71 | L35: 69.71 | M35: 69.71 | N35: 69.71 | O35: 69.71 | P35: 69.71 | Q35: 833
C36: Total | E36: 68.66 | F36: 68.66 | G36: 68.66 | H36: 69.71 | I36: 69.71 | J36: 69.71 | K36: 69.71 | L36: 69.71 | M36: 69.71 | N36: 69.71 | O36: 69.71 | P36: 69.71 | Q36: 833
A38: AT&T Mobility | B38: B106 | C38: 2494 | Q38: -
B39: Total Monthly Charges | E39: 6867.29 | F39: 6867.29 | G39: 6867.29 | H39: 6867.29 | I39: 6867.29 | J39: 6867.29 | K39: 6867.29 | L39: 6867.29 | M39: 6867.29 | N39: 6867.29 | O39: 6867.29 | P39: 6867.29 | Q39: 82407
B40: Sales Tax | D40: 0.025 | E40: 171.68 | F40: 171.68 | G40: 171.68 | H40: 171.68 | I40: 171.68 | J40: 171.68 | K40: 171.68 | L40: 171.68 | M40: 171.68 | N40: 171.68 | O40: 171.68 | P40: 171.68 | Q40: 2060
C41: Total | E41: 171.68 | F41: 171.68 | G41: 171.68 | H41: 171.68 | I41: 171.68 | J41: 171.68 | K41: 171.68 | L41: 171.68 | M41: 171.68 | N41: 171.68 | O41: 171.68 | P41: 171.68 | Q41: 2060
A43: Discount Nutrition | B43: B108 | C43: 1500 | Q43: -
B44: Total Monthly Charges | E44: 3298.81 | F44: 3298.81 | G44: 3298.81 | H44: 3347.52 | I44: 3347.52 | J44: 3347.52 | K44: 3347.52 | L44: 3347.52 | M44: 3347.52 | N44: 3347.52 | O44: 3347.52 | P44: 3347.52 | Q44: 40024
B45: Sales Tax | D45: 0.025 | E45: 82.47 | F45: 82.47 | G45: 82.47 | H45: 83.69 | I45: 83.69 | J45: 83.69 | K45: 83.69 | L45: 83.69 | M45: 83.69 | N45: 83.69 | O45: 83.69 | P45: 83.69 | Q45: 1001
C46: Total | E46: 82.47 | F46: 82.47 | G46: 82.47 | H46: 83.69 | I46: 83.69 | J46: 83.69 | K46: 83.69 | L46: 83.69 | M46: 83.69 | N46: 83.69 | O46: 83.69 | P46: 83.69 | Q46: 1001
A48: Adapt Chiropractic | B48: B109 | C48: 1734 | Q48: -
B49: Total Monthly Charges | E49: 4181.29 | F49: 4181.29 | G49: 4181.29 | H49: 4181.29 | I49: 4181.29 | J49: 4181.29 | K49: 4181.29 | L49: 4181.29 | M49: 4181.29 | N49: 4181.29 | O49: 4181.29 | P49: 4181.29 | Q49: 50175
B50: Sales Tax | D50: 0.025 | E50: 104.53 | F50: 104.53 | G50: 104.53 | H50: 104.53 | I50: 104.53 | J50: 104.53 | K50: 104.53 | L50: 104.53 | M50: 104.53 | N50: 104.53 | O50: 104.53 | P50: 104.53 | Q50: 1254
C51: Total | E51: 104.53 | F51: 104.53 | G51: 104.53 | H51: 104.53 | I51: 104.53 | J51: 104.53 | K51: 104.53 | L51: 104.53 | M51: 104.53 | N51: 104.53 | O51: 104.53 | P51: 104.53 | Q51: 1254
A53: Speakeasy Suites | B53: B111 | C53: 3900 | Q53: -
B54: Total Monthly Charges | E54: 8097.34 | F54: 8097.34 | G54: 8097.34 | H54: 8097.34 | I54: 8097.34 | J54: 8097.34 | K54: 8097.34 | L54: 8097.34 | M54: 8097.34 | N54: 8097.34 | O54: 8272.92 | P54: 8272.92 | Q54: 97519
B55: Sales Tax | D55: 0.025 | E55: 202.43 | F55: 202.43 | G55: 202.43 | H55: 202.43 | I55: 202.43 | J55: 202.43 | K55: 202.43 | L55: 202.43 | M55: 202.43 | N55: 202.43 | O55: 206.82 | P55: 206.82 | Q55: 2438
C56: Total | E56: 202.43 | F56: 202.43 | G56: 202.43 | H56: 202.43 | I56: 202.43 | J56: 202.43 | K56: 202.43 | L56: 202.43 | M56: 202.43 | N56: 202.43 | O56: 206.82 | P56: 206.82 | Q56: 2438
A58: Kachina Stained Glass | B58: 101 | C58: 1287 | Q58: -
B59: Total Monthly Charges | E59: 3210.69 | F59: 3210.69 | G59: 3210.69 | H59: 3210.69 | I59: 3210.69 | J59: 3210.69 | K59: 3259.11 | L59: 3259.11 | M59: 3259.11 | N59: 3259.11 | O59: 3259.11 | P59: 3259.11 | Q59: 38819
B60: Sales Tax | D60: 0.025 | E60: 80.27 | F60: 80.27 | G60: 80.27 | H60: 80.27 | I60: 80.27 | J60: 80.27 | K60: 81.48 | L60: 81.48 | M60: 81.48 | N60: 81.48 | O60: 81.48 | P60: 81.48 | Q60: 970
C61: Total | E61: 80.27 | F61: 80.27 | G61: 80.27 | H61: 80.27 | I61: 80.27 | J61: 80.27 | K61: 81.48 | L61: 81.48 | M61: 81.48 | N61: 81.48 | O61: 81.48 | P61: 81.48 | Q61: 970
A63: Zanders Creations | B63: 102 | C63: 1639 | Q63: -
B64: Total Monthly Charges | E64: 3710.49 | F64: 3710.49 | G64: 3710.49 | H64: 3710.49 | I64: 3710.49 | J64: 3710.49 | K64: 3710.49 | L64: 3710.49 | M64: 3710.49 | N64: 3710.49 | O64: 3710.49 | P64: 3710.49 | Q64: 44526
B65: Sales Tax | D65: 0.025 | E65: 92.76 | F65: 92.76 | G65: 92.76 | H65: 92.76 | I65: 92.76 | J65: 92.76 | K65: 92.76 | L65: 92.76 | M65: 92.76 | N65: 92.76 | O65: 92.76 | P65: 92.76 | Q65: 1113
C66: Total | E66: 92.76 | F66: 92.76 | G66: 92.76 | H66: 92.76 | I66: 92.76 | J66: 92.76 | K66: 92.76 | L66: 92.76 | M66: 92.76 | N66: 92.76 | O66: 92.76 | P66: 92.76 | Q66: 1113
A68: Brightnow Dental | B68: 103 | C68: 3600 | Q68: -
B69: Total Monthly Charges | E69: 9279.61 | F69: 9279.61 | G69: 9279.61 | H69: 9279.61 | I69: 9279.61 | J69: 9279.61 | K69: 9279.61 | L69: 9279.61 | M69: 9279.61 | N69: 9279.61 | O69: 9279.61 | P69: 9279.61 | Q69: 111355
B70: Sales Tax | D70: 0.025 | E70: 231.99 | F70: 231.99 | G70: 231.99 | H70: 231.99 | I70: 231.99 | J70: 231.99 | K70: 231.99 | L70: 231.99 | M70: 231.99 | N70: 231.99 | O70: 231.99 | P70: 231.99 | Q70: 2784
C71: Total | E71: 231.99 | F71: 231.99 | G71: 231.99 | H71: 231.99 | I71: 231.99 | J71: 231.99 | K71: 231.99 | L71: 231.99 | M71: 231.99 | N71: 231.99 | O71: 231.99 | P71: 231.99 | Q71: 2784
A73: Carr Animal Care | B73: 106 | C73: 1587 | Q73: -
B74: Total Monthly Charges | E74: 3454.46 | F74: 3454.46 | G74: 3454.46 | H74: 3454.46 | I74: 3454.46 | J74: 3454.46 | K74: 3454.46 | L74: 3454.46 | M74: 3454.46 | N74: 3745.41 | O74: 3745.41 | P74: 3745.41 | Q74: 42326
B75: Sales Tax | D75: 0.025 | E75: 86.36 | F75: 86.36 | G75: 86.36 | H75: 86.36 | I75: 86.36 | J75: 86.36 | K75: 86.36 | L75: 86.36 | M75: 86.36 | N75: 93.64 | O75: 93.64 | P75: 93.64 | Q75: 1058
C76: Total | E76: 86.36 | F76: 86.36 | G76: 86.36 | H76: 86.36 | I76: 86.36 | J76: 86.36 | K76: 86.36 | L76: 86.36 | M76: 86.36 | N76: 93.64 | O76: 93.64 | P76: 93.64 | Q76: 1058
A78: Razors Barber Shop | B78: 107 | C78: 1300 | Q78: -
B79: Total Monthly Charges | E79: 2657.24 | F79: 2657.24 | G79: 2657.24 | H79: 2715.77 | I79: 2715.77 | J79: 2715.77 | K79: 2715.77 | L79: 2715.77 | M79: 2715.77 | N79: 2715.77 | O79: 2715.77 | P79: 2715.77 | Q79: 32414
B80: Sales Tax | D80: 0.025 | E80: 66.43 | F80: 66.43 | G80: 66.43 | H80: 67.89 | I80: 67.89 | J80: 67.89 | K80: 67.89 | L80: 67.89 | M80: 67.89 | N80: 67.89 | O80: 67.89 | P80: 67.89 | Q80: 810
C81: Total | E81: 66.43 | F81: 66.43 | G81: 66.43 | H81: 67.89 | I81: 67.89 | J81: 67.89 | K81: 67.89 | L81: 67.89 | M81: 67.89 | N81: 67.89 | O81: 67.89 | P81: 67.89 | Q81: 810
A83: CrossFit New Strength | B83: 108 | C83: 3524 | Q83: -
B84: Total Monthly Charges | E84: 6731.36 | F84: 6731.36 | G84: 6731.36 | H84: 6731.36 | I84: 6731.36 | J84: 6731.36 | K84: 6731.36 | L84: 6731.36 | M84: 6731.36 | N84: 6731.36 | O84: 6731.36 | P84: 6731.36 | Q84: 80776
B85: Sales Tax | D85: 0.025 | E85: 168.28 | F85: 168.28 | G85: 168.28 | H85: 168.28 | I85: 168.28 | J85: 168.28 | K85: 168.28 | L85: 168.28 | M85: 168.28 | N85: 168.28 | O85: 168.28 | P85: 168.28 | Q85: 2019
C86: Total | E86: 168.28 | F86: 168.28 | G86: 168.28 | H86: 168.28 | I86: 168.28 | J86: 168.28 | K86: 168.28 | L86: 168.28 | M86: 168.28 | N86: 168.28 | O86: 168.28 | P86: 168.28 | Q86: 2019
A88: Vacant (Time Out Bar) | B88: 111 | C88: 3007 | Q88: -
B89: Total Monthly Charges | E89: - | F89: - | G89: - | H89: - | I89: - | J89: - | K89: 7775.32 | L89: 7775.32 | M89: 7775.32 | N89: 7775.32 | O89: 7775.32 | P89: 7775.32 | Q89: 46652
B90: Sales Tax | D90: 0.025 | E90: - | F90: - | G90: - | H90: - | I90: - | J90: - | K90: 194.38 | L90: 194.38 | M90: 194.38 | N90: 194.38 | O90: 194.38 | P90: 194.38 | Q90: 1166
C91: Total | E91: - | F91: - | G91: - | H91: - | I91: - | J91: - | K91: 194.38 | L91: 194.38 | M91: 194.38 | N91: 194.38 | O91: 194.38 | P91: 194.38 | Q91: 1166
A93: Walmart | B93: 0 | C93: NAP | Q93: -
A94: Signage Only | B94: Total Monthly Charges | E94: 2000 | F94: 2000 | G94: 2000 | H94: 2000 | I94: 2000 | J94: 2000 | K94: 2000 | L94: 2000 | M94: 2000 | N94: 2000 | O94: 2000 | P94: 2000 | Q94: 24000
B95: Sales Tax | D95: 0.025 | E95: 50 | F95: 50 | G95: 50 | H95: 50 | I95: 50 | J95: 50 | K95: 50 | L95: 50 | M95: 50 | N95: 50 | O95: 50 | P95: 50 | Q95: 600
C96: Total | E96: 50 | F96: 50 | G96: 50 | H96: 50 | I96: 50 | J96: 50 | K96: 50 | L96: 50 | M96: 50 | N96: 50 | O96: 50 | P96: 50 | Q96: 600
A98: Sportsman's Warehouse | B98: 0 | C98: NAP | Q98: -
A99: Signage Only | B99: Total Monthly Charges | E99: 1500 | F99: 1500 | G99: 1500 | H99: 1500 | I99: 1500 | J99: 1500 | K99: 1500 | L99: 1500 | M99: 1500 | N99: 1500 | O99: 1500 | P99: 1500 | Q99: 18000
B100: Sales Tax | D100: 0.025 | E100: 37.5 | F100: 37.5 | G100: 37.5 | H100: 37.5 | I100: 37.5 | J100: 37.5 | K100: 37.5 | L100: 37.5 | M100: 37.5 | N100: 37.5 | O100: 37.5 | P100: 37.5 | Q100: 450
C101: Total | E101: 37.5 | F101: 37.5 | G101: 37.5 | H101: 37.5 | I101: 37.5 | J101: 37.5 | K101: 37.5 | L101: 37.5 | M101: 37.5 | N101: 37.5 | O101: 37.5 | P101: 37.5 | Q101: 450
A103: John F. Long Foundation | B103: 0 | C103: NAP | Q103: -
A104: Signage Only | B104: Total Monthly Charges | E104: 15 | F104: 15 | G104: 15 | H104: 15 | I104: 15 | J104: 15 | K104: 15 | L104: 15 | M104: 15 | N104: 15 | O104: 15 | P104: 4585.83 | Q104: 4751
B105: Sales Tax | D105: 0.025 | E105: 0.38 | F105: 0.38 | G105: 0.38 | H105: 0.38 | I105: 0.38 | J105: 0.38 | K105: 0.38 | L105: 0.38 | M105: 0.38 | N105: 0.38 | O105: 0.38 | P105: 114.65 | Q105: 119
C106: Total | E106: 0.38 | F106: 0.38 | G106: 0.38 | H106: 0.38 | I106: 0.38 | J106: 0.38 | K106: 0.38 | L106: 0.38 | M106: 0.38 | N106: 0.38 | O106: 0.38 | P106: 114.65 | Q106: 119
A109: Grand Total | E109: 3421.18 | F109: 3421.18 | G109: 3421.18 | H109: 3424.92 | I109: 3426.77 | J109: 3426.77 | K109: 3622.37 | L109: 3622.37 | M109: 3622.37 | N109: 3634.28 | O109: 3638.67 | P109: 3752.94 | Q109: 42435.02 | R109: See Rent Tab - Matches Total
B111: NMK Tie-Out | E111: - | F111: - | G111: - | H111: - | I111: - | J111: - | K111: - | L111: - | M111: - | N111: - | O111: - | P111: -

Sheet Sales Tax
A2: ATHENA PROPERTY MANAGEMENT
A3: =Summary!A3 -> GREENFIELD GATEWAY MESA, ARIZONA
A4: =Summary!A4 -> PROJECT NO. 801
A5: =Summary!A5 -> 01/01/26-12/31/26
A6: =Rent!A6 -> 2026 OPERATING BUDGET
Q8: YEARLY TOTAL
A9: TENANT | B9: SUITE | C9: SQUARE | D9: RATE | E9: JAN | F9: FEB | G9: MARCH | H9: APRIL | I9: MAY | J9: JUNE | K9: JULY | L9: AUGUST | M9: SEPT | N9: OCT | O9: NOV | P9: DEC | R9: ANN | S9: MON
B10: # | C10: FOOTAGE
A11: Rental Sales Tax | D11: 0.025
A13: =Rent!A14 -> EOS Fitness | B13: =Rent!B14 -> Major A | C13: 28159 | Q13: =SUM(E13:P13) -> 0
B14: Total Monthly Charges | E14: =IF(Rent!E14=0,0,(Rent!E14+(SUM('Tenant Charges'!$F10:$K10)))) -> 64560.806 | F14: =IF(Rent!F14=0,0,(Rent!F14+(SUM('Tenant Charges'!$F10:$K10)))) -> 64560.806 | G14: =IF(Rent!G14=0,0,(Rent!G14+(SUM('Tenant Charges'!$F10:$K10)))) -> 64560.806 | H14: =IF(Rent!H14=0,0,(Rent!H14+(SUM('Tenant Charges'!$F10:$K10)))) -> 64560.806 | I14: =IF(Rent!I14=0,0,(Rent!I14+(SUM('Tenant Charges'!$F10:$K10)))) -> 64560.806 | J14: =IF(Rent!J14=0,0,(Rent!J14+(SUM('Tenant Charges'!$F10:$K10)))) -> 64560.806 | K14: =IF(Rent!K14=0,0,(Rent!K14+(SUM('Tenant Charges'!$F10:$K10)))) -> 64560.806 | L14: =IF(Rent!L14=0,0,(Rent!L14+(SUM('Tenant Charges'!$F10:$K10)))) -> 64560.806 | ... P14: =IF(Rent!P14=0,0,(Rent!P14+(SUM('Tenant Charges'!$F10:$K10)))) -> 64560.806 | Q14: =SUM(E14:P14) -> 774729.67
D15: =$D$11 -> 0.025 | E15: =E14*$D$15 -> 1614.0201 | F15: =F14*$D$15 -> 1614.0201 | G15: =G14*$D$15 -> 1614.0201 | H15: =H14*$D$15 -> 1614.0201 | I15: =I14*$D$15 -> 1614.0201 | J15: =J14*$D$15 -> 1614.0201 | K15: =K14*$D$15 -> 1614.0201 | L15: =L14*$D$15 -> 1614.0201 | ... P15: =P14*$D$15 -> 1614.0201 | Q15: =SUM(E15:P15) -> 19368.242
C16: Total Tax | E16: =E15 -> 1614.0201 | F16: =F15 -> 1614.0201 | G16: =G15 -> 1614.0201 | H16: =H15 -> 1614.0201 | I16: =I15 -> 1614.0201 | J16: =J15 -> 1614.0201 | K16: =K15 -> 1614.0201 | L16: =L15 -> 1614.0201 | ... Q16: =Q15 -> 19368.242
A18: =Rent!A15 -> Third Pasrty MVS | B18: =Rent!B15 -> B101 | C18: =Rent!C15 -> 3000 | Q18: =SUM(E18:P18) -> 0
B19: Total Monthly Charges | E19: =IF(Rent!E15=0,0,(Rent!E15+(SUM('Tenant Charges'!$F11:$K11)))) -> 8024.5025 | F19: =IF(Rent!F15=0,0,(Rent!F15+(SUM('Tenant Charges'!$F11:$K11)))) -> 8024.5025 | G19: =IF(Rent!G15=0,0,(Rent!G15+(SUM('Tenant Charges'!$F11:$K11)))) -> 8024.5025 | H19: =IF(Rent!H15=0,0,(Rent!H15+(SUM('Tenant Charges'!$F11:$K11)))) -> 8024.5025 | I19: =IF(Rent!I15=0,0,(Rent!I15+(SUM('Tenant Charges'!$F11:$K11)))) -> 8024.5025 | J19: =IF(Rent!J15=0,0,(Rent!J15+(SUM('Tenant Charges'!$F11:$K11)))) -> 8024.5025 | K19: =IF(Rent!K15=0,0,(Rent!K15+(SUM('Tenant Charges'!$F11:$K11)))) -> 8024.5025 | L19: =IF(Rent!L15=0,0,(Rent!L15+(SUM('Tenant Charges'!$F11:$K11)))) -> 8024.5025 | ... P19: =IF(Rent!P15=0,0,(Rent!P15+(SUM('Tenant Charges'!$F11:$K11)))) -> 8210.2125 | Q19: =SUM(E19:P19) -> 96851.16
B20: Sales Tax | D20: =$D$11 -> 0.025 | E20: =E19*$D$20 -> 200.61256 | F20: =F19*$D$20 -> 200.61256 | G20: =G19*$D$20 -> 200.61256 | H20: =H19*$D$20 -> 200.61256 | I20: =I19*$D$20 -> 200.61256 | J20: =J19*$D$20 -> 200.61256 | K20: =K19*$D$20 -> 200.61256 | L20: =L19*$D$20 -> 200.61256 | ... P20: =P19*$D$20 -> 205.25531 | Q20: =SUM(E20:P20) -> 2421.279
C21: Total | E21: =SUM(E20:E20) -> 200.61256 | F21: =SUM(F20:F20) -> 200.61256 | G21: =SUM(G20:G20) -> 200.61256 | H21: =SUM(H20:H20) -> 200.61256 | I21: =SUM(I20:I20) -> 200.61256 | J21: =SUM(J20:J20) -> 200.61256 | K21: =SUM(K20:K20) -> 200.61256 | L21: =SUM(L20:L20) -> 200.61256 | ... P21: =SUM(P20:P20) -> 205.25531 | Q21: =Q20 -> 2421.279
A23: =Rent!A16 -> Sally Beauty Supply | B23: =Rent!B16 -> B103 | C23: =Rent!C16 -> 1625 | Q23: =SUM(E23:P23) -> 0
B24: Total Monthly Charges | E24: =IF(Rent!E16=0,0,(Rent!E16+(SUM('Tenant Charges'!$F12:$K12)))) -> 3230.8028 | F24: =IF(Rent!F16=0,0,(Rent!F16+(SUM('Tenant Charges'!$F12:$K12)))) -> 3230.8028 | G24: =IF(Rent!G16=0,0,(Rent!G16+(SUM('Tenant Charges'!$F12:$K12)))) -> 3230.8028 | H24: =IF(Rent!H16=0,0,(Rent!H16+(SUM('Tenant Charges'!$F12:$K12)))) -> 3230.8028 | I24: =IF(Rent!I16=0,0,(Rent!I16+(SUM('Tenant Charges'!$F12:$K12)))) -> 3230.8028 | J24: =IF(Rent!J16=0,0,(Rent!J16+(SUM('Tenant Charges'!$F12:$K12)))) -> 3230.8028 | K24: =IF(Rent!K16=0,0,(Rent!K16+(SUM('Tenant Charges'!$F12:$K12)))) -> 3230.8028 | L24: =IF(Rent!L16=0,0,(Rent!L16+(SUM('Tenant Charges'!$F12:$K12)))) -> 3230.8028 | ... P24: =IF(Rent!P16=0,0,(Rent!P16+(SUM('Tenant Charges'!$F12:$K12)))) -> 3230.8028 | Q24: =SUM(E24:P24) -> 38769.634
B25: Sales Tax | D25: =$D$11 -> 0.025 | E25: =E24*$D$25 -> 80.770071 | F25: =F24*$D$25 -> 80.770071 | G25: =G24*$D$25 -> 80.770071 | H25: =H24*$D$25 -> 80.770071 | I25: =I24*$D$25 -> 80.770071 | J25: =J24*$D$25 -> 80.770071 | K25: =K24*$D$25 -> 80.770071 | L25: =L24*$D$25 -> 80.770071 | ... P25: =P24*$D$25 -> 80.770071 | Q25: =SUM(E25:P25) -> 969.24085
C26: Total | E26: =E25 -> 80.770071 | F26: =F25 -> 80.770071 | G26: =G25 -> 80.770071 | H26: =H25 -> 80.770071 | I26: =I25 -> 80.770071 | J26: =J25 -> 80.770071 | K26: =K25 -> 80.770071 | L26: =L25 -> 80.770071 | ... P26: =P25 -> 80.770071 | Q26: =SUM(E26:P26) -> 969.24085
A28: =Rent!A17 -> Wild Side Smoke Shop | B28: =Rent!B17 -> B104 | C28: =Rent!C17 -> 1400 | Q28: =SUM(E28:P28) -> 0
B29: Total Monthly Charges | E29: =IF(Rent!E17=0,0,(Rent!E17+(SUM('Tenant Charges'!$F13:$K13)))) -> 3281.2165 | F29: =IF(Rent!F17=0,0,(Rent!F17+(SUM('Tenant Charges'!$F13:$K13)))) -> 3281.2165 | G29: =IF(Rent!G17=0,0,(Rent!G17+(SUM('Tenant Charges'!$F13:$K13)))) -> 3281.2165 | H29: =IF(Rent!H17=0,0,(Rent!H17+(SUM('Tenant Charges'!$F13:$K13)))) -> 3281.2165 | I29: =IF(Rent!I17=0,0,(Rent!I17+(SUM('Tenant Charges'!$F13:$K13)))) -> 3355.4765 | J29: =IF(Rent!J17=0,0,(Rent!J17+(SUM('Tenant Charges'!$F13:$K13)))) -> 3355.4765 | K29: =IF(Rent!K17=0,0,(Rent!K17+(SUM('Tenant Charges'!$F13:$K13)))) -> 3355.4765 | L29: =IF(Rent!L17=0,0,(Rent!L17+(SUM('Tenant Charges'!$F13:$K13)))) -> 3355.4765 | ... P29: =IF(Rent!P17=0,0,(Rent!P17+(SUM('Tenant Charges'!$F13:$K13)))) -> 3355.4765 | Q29: =SUM(E29:P29) -> 39968.677
B30: Sales Tax | D30: =$D$11 -> 0.025 | E30: =E29*$D$30 -> 82.030411 | F30: =F29*$D$30 -> 82.030411 | G30: =G29*$D$30 -> 82.030411 | H30: =H29*$D$30 -> 82.030411 | I30: =I29*$D$30 -> 83.886911 | J30: =J29*$D$30 -> 83.886911 | K30: =K29*$D$30 -> 83.886911 | L30: =L29*$D$30 -> 83.886911 | ... P30: =P29*$D$30 -> 83.886911 | Q30: =SUM(E30:P30) -> 999.21694
C31: Total | E31: =E30 -> 82.030411 | F31: =F30 -> 82.030411 | G31: =G30 -> 82.030411 | H31: =H30 -> 82.030411 | I31: =I30 -> 83.886911 | J31: =J30 -> 83.886911 | K31: =K30 -> 83.886911 | L31: =L30 -> 83.886911 | ... P31: =P30 -> 83.886911 | Q31: =SUM(E31:P31) -> 999.21694
A33: =Rent!A18 -> Green Spa, LLC | B33: =Rent!B18 -> B105 | C33: =Rent!C18 -> 1112 | Q33: =SUM(E33:P33) -> 0
B34: Total Monthly Charges | E34: =IF(Rent!E18=0,0,(Rent!E18+(SUM('Tenant Charges'!$F14:$K14)))) -> 2746.4347 | F34: =IF(Rent!F18=0,0,(Rent!F18+(SUM('Tenant Charges'!$F14:$K14)))) -> 2746.4347 | G34: =IF(Rent!G18=0,0,(Rent!G18+(SUM('Tenant Charges'!$F14:$K14)))) -> 2746.4347 | H34: =IF(Rent!H18=0,0,(Rent!H18+(SUM('Tenant Charges'!$F14:$K14)))) -> 2788.5647 | I34: =IF(Rent!I18=0,0,(Rent!I18+(SUM('Tenant Charges'!$F14:$K14)))) -> 2788.5647 | J34: =IF(Rent!J18=0,0,(Rent!J18+(SUM('Tenant Charges'!$F14:$K14)))) -> 2788.5647 | K34: =IF(Rent!K18=0,0,(Rent!K18+(SUM('Tenant Charges'!$F14:$K14)))) -> 2788.5647 | L34: =IF(Rent!L18=0,0,(Rent!L18+(SUM('Tenant Charges'!$F14:$K14)))) -> 2788.5647 | ... P34: =IF(Rent!P18=0,0,(Rent!P18+(SUM('Tenant Charges'!$F14:$K14)))) -> 2788.5647 | Q34: =SUM(E34:P34) -> 33336.386
B35: Sales Tax | D35: =$D$11 -> 0.025 | E35: =E34*$D$35 -> 68.660867 | F35: =F34*$D$35 -> 68.660867 | G35: =G34*$D$35 -> 68.660867 | H35: =H34*$D$35 -> 69.714117 | I35: =I34*$D$35 -> 69.714117 | J35: =J34*$D$35 -> 69.714117 | K35: =K34*$D$35 -> 69.714117 | L35: =L34*$D$35 -> 69.714117 | ... P35: =P34*$D$35 -> 69.714117 | Q35: =SUM(E35:P35) -> 833.40965
C36: Total | E36: =E35 -> 68.660867 | F36: =F35 -> 68.660867 | G36: =G35 -> 68.660867 | H36: =H35 -> 69.714117 | I36: =I35 -> 69.714117 | J36: =J35 -> 69.714117 | K36: =K35 -> 69.714117 | L36: =L35 -> 69.714117 | ... P36: =P35 -> 69.714117 | Q36: =SUM(E36:P36) -> 833.40965
A38: =Rent!A19 -> AT&T Mobility | B38: =Rent!B19 -> B106 | C38: =Rent!C19 -> 2494 | Q38: =SUM(E38:P38) -> 0
B39: Total Monthly Charges | E39: =IF(Rent!E19=0,0,(Rent!E19+(SUM('Tenant Charges'!$F15:$K15)))) -> 6867.2881 | F39: =IF(Rent!F19=0,0,(Rent!F19+(SUM('Tenant Charges'!$F15:$K15)))) -> 6867.2881 | G39: =IF(Rent!G19=0,0,(Rent!G19+(SUM('Tenant Charges'!$F15:$K15)))) -> 6867.2881 | H39: =IF(Rent!H19=0,0,(Rent!H19+(SUM('Tenant Charges'!$F15:$K15)))) -> 6867.2881 | I39: =IF(Rent!I19=0,0,(Rent!I19+(SUM('Tenant Charges'!$F15:$K15)))) -> 6867.2881 | J39: =IF(Rent!J19=0,0,(Rent!J19+(SUM('Tenant Charges'!$F15:$K15)))) -> 6867.2881 | K39: =IF(Rent!K19=0,0,(Rent!K19+(SUM('Tenant Charges'!$F15:$K15)))) -> 6867.2881 | L39: =IF(Rent!L19=0,0,(Rent!L19+(SUM('Tenant Charges'!$F15:$K15)))) -> 6867.2881 | ... P39: =IF(Rent!P19=0,0,(Rent!P19+(SUM('Tenant Charges'!$F15:$K15)))) -> 6867.2881 | Q39: =SUM(E39:P39) -> 82407.457
B40: Sales Tax | D40: =$D$11 -> 0.025 | E40: =E39*$D$40 -> 171.6822 | F40: =F39*$D$40 -> 171.6822 | G40: =G39*$D$40 -> 171.6822 | H40: =H39*$D$40 -> 171.6822 | I40: =I39*$D$40 -> 171.6822 | J40: =J39*$D$40 -> 171.6822 | K40: =K39*$D$40 -> 171.6822 | L40: =L39*$D$40 -> 171.6822 | ... P40: =P39*$D$40 -> 171.6822 | Q40: =SUM(E40:P40) -> 2060.1864
C41: Total | E41: =E40 -> 171.6822 | F41: =F40 -> 171.6822 | G41: =G40 -> 171.6822 | H41: =H40 -> 171.6822 | I41: =I40 -> 171.6822 | J41: =J40 -> 171.6822 | K41: =K40 -> 171.6822 | L41: =L40 -> 171.6822 | ... P41: =P40 -> 171.6822 | Q41: =SUM(E41:P41) -> 2060.1864
A43: =Rent!A20 -> Discount Nutrition | B43: =Rent!B20 -> B108 | C43: =Rent!C20 -> 1500 | Q43: =SUM(E43:P43) -> 0
B44: Total Monthly Charges | E44: =IF(Rent!E20=0,0,(Rent!E20+(SUM('Tenant Charges'!$F16:$K16)))) -> 3298.8126 | F44: =IF(Rent!F20=0,0,(Rent!F20+(SUM('Tenant Charges'!$F16:$K16)))) -> 3298.8126 | G44: =IF(Rent!G20=0,0,(Rent!G20+(SUM('Tenant Charges'!$F16:$K16)))) -> 3298.8126 | H44: =IF(Rent!H20=0,0,(Rent!H20+(SUM('Tenant Charges'!$F16:$K16)))) -> 3347.5226 | I44: =IF(Rent!I20=0,0,(Rent!I20+(SUM('Tenant Charges'!$F16:$K16)))) -> 3347.5226 | J44: =IF(Rent!J20=0,0,(Rent!J20+(SUM('Tenant Charges'!$F16:$K16)))) -> 3347.5226 | K44: =IF(Rent!K20=0,0,(Rent!K20+(SUM('Tenant Charges'!$F16:$K16)))) -> 3347.5226 | L44: =IF(Rent!L20=0,0,(Rent!L20+(SUM('Tenant Charges'!$F16:$K16)))) -> 3347.5226 | ... P44: =IF(Rent!P20=0,0,(Rent!P20+(SUM('Tenant Charges'!$F16:$K16)))) -> 3347.5226 | Q44: =SUM(E44:P44) -> 40024.142
B45: Sales Tax | D45: =$D$11 -> 0.025 | E45: =E44*$D$45 -> 82.470316 | F45: =F44*$D$45 -> 82.470316 | G45: =G44*$D$45 -> 82.470316 | H45: =H44*$D$45 -> 83.688066 | I45: =I44*$D$45 -> 83.688066 | J45: =J44*$D$45 -> 83.688066 | K45: =K44*$D$45 -> 83.688066 | L45: =L44*$D$45 -> 83.688066 | ... P45: =P44*$D$45 -> 83.688066 | Q45: =SUM(E45:P45) -> 1000.6035
C46: Total | E46: =E45 -> 82.470316 | F46: =F45 -> 82.470316 | G46: =G45 -> 82.470316 | H46: =H45 -> 83.688066 | I46: =I45 -> 83.688066 | J46: =J45 -> 83.688066 | K46: =K45 -> 83.688066 | L46: =L45 -> 83.688066 | ... P46: =P45 -> 83.688066 | Q46: =SUM(E46:P46) -> 1000.6035
A48: =Rent!A21 -> Adapt Chiropractic | B48: =Rent!B21 -> B109 | C48: =Rent!C21 -> 1734 | Q48: =SUM(E48:P48) -> 0
B49: Total Monthly Charges | E49: =IF(Rent!E21=0,0,(Rent!E21+(SUM('Tenant Charges'!$F17:$K17)))) -> 4181.2861 | F49: =IF(Rent!F21=0,0,(Rent!F21+(SUM('Tenant Charges'!$F17:$K17)))) -> 4181.2861 | G49: =IF(Rent!G21=0,0,(Rent!G21+(SUM('Tenant Charges'!$F17:$K17)))) -> 4181.2861 | H49: =IF(Rent!H21=0,0,(Rent!H21+(SUM('Tenant Charges'!$F17:$K17)))) -> 4181.2861 | I49: =IF(Rent!I21=0,0,(Rent!I21+(SUM('Tenant Charges'!$F17:$K17)))) -> 4181.2861 | J49: =IF(Rent!J21=0,0,(Rent!J21+(SUM('Tenant Charges'!$F17:$K17)))) -> 4181.2861 | K49: =IF(Rent!K21=0,0,(Rent!K21+(SUM('Tenant Charges'!$F17:$K17)))) -> 4181.2861 | L49: =IF(Rent!L21=0,0,(Rent!L21+(SUM('Tenant Charges'!$F17:$K17)))) -> 4181.2861 | ... P49: =IF(Rent!P21=0,0,(Rent!P21+(SUM('Tenant Charges'!$F17:$K17)))) -> 4181.2861 | Q49: =SUM(E49:P49) -> 50175.433
B50: Sales Tax | D50: =$D$11 -> 0.025 | E50: =E49*$D$50 -> 104.53215 | F50: =F49*$D$50 -> 104.53215 | G50: =G49*$D$50 -> 104.53215 | H50: =H49*$D$50 -> 104.53215 | I50: =I49*$D$50 -> 104.53215 | J50: =J49*$D$50 -> 104.53215 | K50: =K49*$D$50 -> 104.53215 | L50: =L49*$D$50 -> 104.53215 | ... P50: =P49*$D$50 -> 104.53215 | Q50: =SUM(E50:P50) -> 1254.3858
C51: Total | E51: =E50 -> 104.53215 | F51: =F50 -> 104.53215 | G51: =G50 -> 104.53215 | H51: =H50 -> 104.53215 | I51: =I50 -> 104.53215 | J51: =J50 -> 104.53215 | K51: =K50 -> 104.53215 | L51: =L50 -> 104.53215 | ... P51: =P50 -> 104.53215 | Q51: =SUM(E51:P51) -> 1254.3858
A53: =Rent!A22 -> Speakeasy Suites | B53: =Rent!B22 -> B111 | C53: =Rent!C22 -> 3900 | Q53: =SUM(E53:P53) -> 0
B54: Total Monthly Charges | E54: =IF(Rent!E22=0,0,(Rent!E22+(SUM('Tenant Charges'!$F18:$K18)))) -> 8097.3408 | F54: =IF(Rent!F22=0,0,(Rent!F22+(SUM('Tenant Charges'!$F18:$K18)))) -> 8097.3408 | G54: =IF(Rent!G22=0,0,(Rent!G22+(SUM('Tenant Charges'!$F18:$K18)))) -> 8097.3408 | H54: =IF(Rent!H22=0,0,(Rent!H22+(SUM('Tenant Charges'!$F18:$K18)))) -> 8097.3408 | I54: =IF(Rent!I22=0,0,(Rent!I22+(SUM('Tenant Charges'!$F18:$K18)))) -> 8097.3408 | J54: =IF(Rent!J22=0,0,(Rent!J22+(SUM('Tenant Charges'!$F18:$K18)))) -> 8097.3408 | K54: =IF(Rent!K22=0,0,(Rent!K22+(SUM('Tenant Charges'!$F18:$K18)))) -> 8097.3408 | L54: =IF(Rent!L22=0,0,(Rent!L22+(SUM('Tenant Charges'!$F18:$K18)))) -> 8097.3408 | ... P54: =IF(Rent!P22=0,0,(Rent!P22+(SUM('Tenant Charges'!$F18:$K18)))) -> 8272.9208 | Q54: =SUM(E54:P54) -> 97519.25
B55: Sales Tax | D55: =$D$11 -> 0.025 | E55: =E54*$D$55 -> 202.43352 | F55: =F54*$D$55 -> 202.43352 | G55: =G54*$D$55 -> 202.43352 | H55: =H54*$D$55 -> 202.43352 | I55: =I54*$D$55 -> 202.43352 | J55: =J54*$D$55 -> 202.43352 | K55: =K54*$D$55 -> 202.43352 | L55: =L54*$D$55 -> 202.43352 | ... P55: =P54*$D$55 -> 206.82302 | Q55: =SUM(E55:P55) -> 2437.9813
C56: Total | E56: =E55 -> 202.43352 | F56: =F55 -> 202.43352 | G56: =G55 -> 202.43352 | H56: =H55 -> 202.43352 | I56: =I55 -> 202.43352 | J56: =J55 -> 202.43352 | K56: =K55 -> 202.43352 | L56: =L55 -> 202.43352 | ... P56: =P55 -> 206.82302 | Q56: =SUM(E56:P56) -> 2437.9813
A58: =Rent!A23 -> Kachina Stained Glass | B58: =Rent!B23 -> 101 | C58: =Rent!C23 -> 1287 | Q58: =SUM(E58:P58) -> 0
B59: Total Monthly Charges | E59: =IF(Rent!E23=0,0,(Rent!E23+(SUM('Tenant Charges'!$F19:$K19)))) -> 3210.6913 | F59: =IF(Rent!F23=0,0,(Rent!F23+(SUM('Tenant Charges'!$F19:$K19)))) -> 3210.6913 | G59: =IF(Rent!G23=0,0,(Rent!G23+(SUM('Tenant Charges'!$F19:$K19)))) -> 3210.6913 | H59: =IF(Rent!H23=0,0,(Rent!H23+(SUM('Tenant Charges'!$F19:$K19)))) -> 3210.6913 | I59: =IF(Rent!I23=0,0,(Rent!I23+(SUM('Tenant Charges'!$F19:$K19)))) -> 3210.6913 | J59: =IF(Rent!J23=0,0,(Rent!J23+(SUM('Tenant Charges'!$F19:$K19)))) -> 3210.6913 | K59: =IF(Rent!K23=0,0,(Rent!K23+(SUM('Tenant Charges'!$F19:$K19)))) -> 3259.1113 | L59: =IF(Rent!L23=0,0,(Rent!L23+(SUM('Tenant Charges'!$F19:$K19)))) -> 3259.1113 | ... P59: =IF(Rent!P23=0,0,(Rent!P23+(SUM('Tenant Charges'!$F19:$K19)))) -> 3259.1113 | Q59: =SUM(E59:P59) -> 38818.816
B60: Sales Tax | D60: =$D$11 -> 0.025 | E60: =E59*$D$60 -> 80.267283 | F60: =F59*$D$60 -> 80.267283 | G60: =G59*$D$60 -> 80.267283 | H60: =H59*$D$60 -> 80.267283 | I60: =I59*$D$60 -> 80.267283 | J60: =J59*$D$60 -> 80.267283 | K60: =K59*$D$60 -> 81.477783 | L60: =L59*$D$60 -> 81.477783 | ... P60: =P59*$D$60 -> 81.477783 | Q60: =SUM(E60:P60) -> 970.47039
C61: Total | E61: =E60 -> 80.267283 | F61: =F60 -> 80.267283 | G61: =G60 -> 80.267283 | H61: =H60 -> 80.267283 | I61: =I60 -> 80.267283 | J61: =J60 -> 80.267283 | K61: =K60 -> 81.477783 | L61: =L60 -> 81.477783 | ... P61: =P60 -> 81.477783 | Q61: =SUM(E61:P61) -> 970.47039
A63: =Rent!A24 -> Zanders Creations | B63: =Rent!B24 -> 102 | C63: =Rent!C24 -> 1639 | Q63: =SUM(E63:P63) -> 0
B64: Total Monthly Charges | E64: =IF(Rent!E24=0,0,(Rent!E24+(SUM('Tenant Charges'!$F20:$K20)))) -> 3710.4891 | F64: =IF(Rent!F23=0,0,(SUM('Tenant Charges'!$E20:$K20))) -> 3710.4891 | G64: =IF(Rent!G23=0,0,(SUM('Tenant Charges'!$E20:$K20))) -> 3710.4891 | H64: =IF(Rent!H23=0,0,(SUM('Tenant Charges'!$E20:$K20))) -> 3710.4891 | I64: =IF(Rent!I23=0,0,(SUM('Tenant Charges'!$E20:$K20))) -> 3710.4891 | J64: =IF(Rent!J23=0,0,(SUM('Tenant Charges'!$E20:$K20))) -> 3710.4891 | K64: =IF(Rent!K23=0,0,(SUM('Tenant Charges'!$E20:$K20))) -> 3710.4891 | L64: =IF(Rent!L23=0,0,(SUM('Tenant Charges'!$E20:$K20))) -> 3710.4891 | M64: =IF(Rent!M23=0,0,(SUM('Tenant Charges'!$E20:$K20))) -> 3710.4891 | ... P64: =IF(Rent!P23=0,0,(SUM('Tenant Charges'!$E20:$K20))) -> 3710.4891 | Q64: =SUM(E64:P64) -> 44525.869
B65: Sales Tax | D65: =$D$11 -> 0.025 | E65: =E64*$D$65 -> 92.762226 | F65: =F64*$D$65 -> 92.762226 | G65: =G64*$D$65 -> 92.762226 | H65: =H64*$D$65 -> 92.762226 | I65: =I64*$D$65 -> 92.762226 | J65: =J64*$D$65 -> 92.762226 | K65: =K64*$D$65 -> 92.762226 | L65: =L64*$D$65 -> 92.762226 | ... P65: =P64*$D$65 -> 92.762226 | Q65: =SUM(E65:P65) -> 1113.1467
C66: Total | E66: =E65 -> 92.762226 | F66: =F65 -> 92.762226 | G66: =G65 -> 92.762226 | H66: =H65 -> 92.762226 | I66: =I65 -> 92.762226 | J66: =J65 -> 92.762226 | K66: =K65 -> 92.762226 | L66: =L65 -> 92.762226 | ... P66: =P65 -> 92.762226 | Q66: =SUM(E66:P66) -> 1113.1467
A68: =Rent!A25 -> Brightnow Dental | B68: =Rent!B25 -> 103 | C68: =Rent!C25 -> 3600 | Q68: =SUM(E68:P68) -> 0
B69: Total Monthly Charges | E69: =IF(Rent!E25=0,0,(Rent!E25+(SUM('Tenant Charges'!$F21:$K21)))) -> 9279.6104 | F69: =IF(Rent!F25=0,0,(Rent!F25+(SUM('Tenant Charges'!$F21:$K21)))) -> 9279.6104 | G69: =IF(Rent!G25=0,0,(Rent!G25+(SUM('Tenant Charges'!$F21:$K21)))) -> 9279.6104 | H69: =IF(Rent!H25=0,0,(Rent!H25+(SUM('Tenant Charges'!$F21:$K21)))) -> 9279.6104 | I69: =IF(Rent!I25=0,0,(Rent!I25+(SUM('Tenant Charges'!$F21:$K21)))) -> 9279.6104 | J69: =IF(Rent!J25=0,0,(Rent!J25+(SUM('Tenant Charges'!$F21:$K21)))) -> 9279.6104 | K69: =IF(Rent!K25=0,0,(Rent!K25+(SUM('Tenant Charges'!$F21:$K21)))) -> 9279.6104 | L69: =IF(Rent!L25=0,0,(Rent!L25+(SUM('Tenant Charges'!$F21:$K21)))) -> 9279.6104 | ... P69: =IF(Rent!P25=0,0,(Rent!P25+(SUM('Tenant Charges'!$F21:$K21)))) -> 9279.6104 | Q69: =SUM(E69:P69) -> 111355.32
B70: Sales Tax | D70: =$D$11 -> 0.025 | E70: =E69*$D$70 -> 231.99026 | F70: =F69*$D$70 -> 231.99026 | G70: =G69*$D$70 -> 231.99026 | H70: =H69*$D$70 -> 231.99026 | I70: =I69*$D$70 -> 231.99026 | J70: =J69*$D$70 -> 231.99026 | K70: =K69*$D$70 -> 231.99026 | L70: =L69*$D$70 -> 231.99026 | ... P70: =P69*$D$70 -> 231.99026 | Q70: =SUM(E70:P70) -> 2783.8831
C71: Total | E71: =E70 -> 231.99026 | F71: =F70 -> 231.99026 | G71: =G70 -> 231.99026 | H71: =H70 -> 231.99026 | I71: =I70 -> 231.99026 | J71: =J70 -> 231.99026 | K71: =K70 -> 231.99026 | L71: =L70 -> 231.99026 | ... P71: =P70 -> 231.99026 | Q71: =SUM(E71:P71) -> 2783.8831
A73: =Rent!A26 -> Carr Animal Care | B73: =Rent!B26 -> 106 | C73: =Rent!C26 -> 1587 | Q73: =SUM(E73:P73) -> 0
B74: Total Monthly Charges | E74: =IF(Rent!E26=0,0,(Rent!E26+(SUM('Tenant Charges'!$F22:$K22)))) -> 3454.4639 | F74: =IF(Rent!F26=0,0,(Rent!F26+(SUM('Tenant Charges'!$F22:$K22)))) -> 3454.4639 | G74: =IF(Rent!G26=0,0,(Rent!G26+(SUM('Tenant Charges'!$F22:$K22)))) -> 3454.4639 | H74: =IF(Rent!H26=0,0,(Rent!H26+(SUM('Tenant Charges'!$F22:$K22)))) -> 3454.4639 | I74: =IF(Rent!I26=0,0,(Rent!I26+(SUM('Tenant Charges'!$F22:$K22)))) -> 3454.4639 | J74: =IF(Rent!J26=0,0,(Rent!J26+(SUM('Tenant Charges'!$F22:$K22)))) -> 3454.4639 | K74: =IF(Rent!K26=0,0,(Rent!K26+(SUM('Tenant Charges'!$F22:$K22)))) -> 3454.4639 | L74: =IF(Rent!L26=0,0,(Rent!L26+(SUM('Tenant Charges'!$F22:$K22)))) -> 3454.4639 | ... P74: =IF(Rent!P26=0,0,(Rent!P26+(SUM('Tenant Charges'!$F22:$K22)))) -> 3745.4139 | Q74: =SUM(E74:P74) -> 42326.417
B75: Sales Tax | D75: =$D$11 -> 0.025 | E75: =E74*$D$75 -> 86.361599 | F75: =F74*$D$75 -> 86.361599 | G75: =G74*$D$75 -> 86.361599 | H75: =H74*$D$75 -> 86.361599 | I75: =I74*$D$75 -> 86.361599 | J75: =J74*$D$75 -> 86.361599 | K75: =K74*$D$75 -> 86.361599 | L75: =L74*$D$75 -> 86.361599 | ... P75: =P74*$D$75 -> 93.635349 | Q75: =SUM(E75:P75) -> 1058.1604
C76: Total | E76: =E75 -> 86.361599 | F76: =F75 -> 86.361599 | G76: =G75 -> 86.361599 | H76: =H75 -> 86.361599 | I76: =I75 -> 86.361599 | J76: =J75 -> 86.361599 | K76: =K75 -> 86.361599 | L76: =L75 -> 86.361599 | ... P76: =P75 -> 93.635349 | Q76: =SUM(E76:P76) -> 1058.1604
A78: =Rent!A27 -> Razors Barber Shop | B78: =Rent!B27 -> 107 | C78: =Rent!C27 -> 1300 | Q78: =SUM(E78:P78) -> 0
B79: Total Monthly Charges | E79: =IF(Rent!E27=0,0,(Rent!E27+(SUM('Tenant Charges'!$F23:$K23)))) -> 2657.2395 | F79: =IF(Rent!F27=0,0,(Rent!F27+(SUM('Tenant Charges'!$F23:$K23)))) -> 2657.2395 | G79: =IF(Rent!G27=0,0,(Rent!G27+(SUM('Tenant Charges'!$F23:$K23)))) -> 2657.2395 | H79: =IF(Rent!H27=0,0,(Rent!H27+(SUM('Tenant Charges'!$F23:$K23)))) -> 2715.7695 | I79: =IF(Rent!I27=0,0,(Rent!I27+(SUM('Tenant Charges'!$F23:$K23)))) -> 2715.7695 | J79: =IF(Rent!J27=0,0,(Rent!J27+(SUM('Tenant Charges'!$F23:$K23)))) -> 2715.7695 | K79: =IF(Rent!K27=0,0,(Rent!K27+(SUM('Tenant Charges'!$F23:$K23)))) -> 2715.7695 | L79: =IF(Rent!L27=0,0,(Rent!L27+(SUM('Tenant Charges'!$F23:$K23)))) -> 2715.7695 | ... P79: =IF(Rent!P27=0,0,(Rent!P27+(SUM('Tenant Charges'!$F23:$K23)))) -> 2715.7695 | Q79: =SUM(E79:P79) -> 32413.643
B80: Sales Tax | D80: =$D$11 -> 0.025 | E80: =E79*$D$80 -> 66.430986 | F80: =F79*$D$80 -> 66.430986 | G80: =G79*$D$80 -> 66.430986 | H80: =H79*$D$80 -> 67.894236 | I80: =I79*$D$80 -> 67.894236 | J80: =J79*$D$80 -> 67.894236 | K80: =K79*$D$80 -> 67.894236 | L80: =L79*$D$80 -> 67.894236 | ... P80: =P79*$D$80 -> 67.894236 | Q80: =SUM(E80:P80) -> 810.34109
C81: Total | E81: =E80 -> 66.430986 | F81: =F80 -> 66.430986 | G81: =G80 -> 66.430986 | H81: =H80 -> 67.894236 | I81: =I80 -> 67.894236 | J81: =J80 -> 67.894236 | K81: =K80 -> 67.894236 | L81: =L80 -> 67.894236 | ... P81: =P80 -> 67.894236 | Q81: =SUM(E81:P81) -> 810.34109
A83: =Rent!A28 -> CrossFit New Strength | B83: =Rent!B28 -> 108 | C83: =Rent!C28 -> 3524 | Q83: =SUM(E83:P83) -> 0
B84: Total Monthly Charges | E84: =IF(Rent!E28=0,0,(Rent!E28+(SUM('Tenant Charges'!$F24:$K24)))) -> 6731.3581 | F84: =IF(Rent!F28=0,0,(Rent!F28+(SUM('Tenant Charges'!$F24:$K24)))) -> 6731.3581 | G84: =IF(Rent!G28=0,0,(Rent!G28+(SUM('Tenant Charges'!$F24:$K24)))) -> 6731.3581 | H84: =IF(Rent!H28=0,0,(Rent!H28+(SUM('Tenant Charges'!$F24:$K24)))) -> 6731.3581 | I84: =IF(Rent!I28=0,0,(Rent!I28+(SUM('Tenant Charges'!$F24:$K24)))) -> 6731.3581 | J84: =IF(Rent!J28=0,0,(Rent!J28+(SUM('Tenant Charges'!$F24:$K24)))) -> 6731.3581 | K84: =IF(Rent!K28=0,0,(Rent!K28+(SUM('Tenant Charges'!$F24:$K24)))) -> 6731.3581 | L84: =IF(Rent!L28=0,0,(Rent!L28+(SUM('Tenant Charges'!$F24:$K24)))) -> 6731.3581 | ... P84: =IF(Rent!P28=0,0,(Rent!P28+(SUM('Tenant Charges'!$F24:$K24)))) -> 6731.3581 | Q84: =SUM(E84:P84) -> 80776.297
B85: Sales Tax | D85: =$D$11 -> 0.025 | E85: =E84*$D$85 -> 168.28395 | F85: =F84*$D$85 -> 168.28395 | G85: =G84*$D$85 -> 168.28395 | H85: =H84*$D$85 -> 168.28395 | I85: =I84*$D$85 -> 168.28395 | J85: =J84*$D$85 -> 168.28395 | K85: =K84*$D$85 -> 168.28395 | L85: =L84*$D$85 -> 168.28395 | ... P85: =P84*$D$85 -> 168.28395 | Q85: =SUM(E85:P85) -> 2019.4074
C86: Total | E86: =E85 -> 168.28395 | F86: =F85 -> 168.28395 | G86: =G85 -> 168.28395 | H86: =H85 -> 168.28395 | I86: =I85 -> 168.28395 | J86: =J85 -> 168.28395 | K86: =K85 -> 168.28395 | L86: =L85 -> 168.28395 | ... P86: =P85 -> 168.28395 | Q86: =SUM(E86:P86) -> 2019.4074
A88: =Rent!A29 -> Vacant (Time Out Bar) | B88: =Rent!B29 -> 111 | C88: =Rent!C29 -> 3007 | Q88: =SUM(E88:P88) -> 0
B89: Total Monthly Charges | E89: =IF(Rent!E29=0,0,(Rent!E29+(SUM('Tenant Charges'!$F25:$K25)))) -> 0 | F89: =IF(Rent!F29=0,0,(Rent!F29+(SUM('Tenant Charges'!$F25:$K25)))) -> 0 | G89: =IF(Rent!G29=0,0,(Rent!G29+(SUM('Tenant Charges'!$F25:$K25)))) -> 0 | H89: =IF(Rent!H29=0,0,(Rent!H29+(SUM('Tenant Charges'!$F25:$K25)))) -> 0 | I89: =IF(Rent!I29=0,0,(Rent!I29+(SUM('Tenant Charges'!$F25:$K25)))) -> 0 | J89: =IF(Rent!J29=0,0,(Rent!J29+(SUM('Tenant Charges'!$F25:$K25)))) -> 0 | K89: =IF(Rent!K29=0,0,(Rent!K29+(SUM('Tenant Charges'!$F25:$K25)))) -> 7775.3207 | L89: =IF(Rent!L29=0,0,(Rent!L29+(SUM('Tenant Charges'!$F25:$K25)))) -> 7775.3207 | ... P89: =IF(Rent!P29=0,0,(Rent!P29+(SUM('Tenant Charges'!$F25:$K25)))) -> 7775.3207 | Q89: =SUM(E89:P89) -> 46651.924
B90: Sales Tax | D90: =$D$11 -> 0.025 | E90: =E89*$D$90 -> 0 | F90: =F89*$D$90 -> 0 | G90: =G89*$D$90 -> 0 | H90: =H89*$D$90 -> 0 | I90: =I89*$D$90 -> 0 | J90: =J89*$D$90 -> 0 | K90: =K89*$D$90 -> 194.38302 | L90: =L89*$D$90 -> 194.38302 | ... P90: =P89*$D$90 -> 194.38302 | Q90: =SUM(E90:P90) -> 1166.2981
C91: Total | E91: =E90 -> 0 | F91: =F90 -> 0 | G91: =G90 -> 0 | H91: =H90 -> 0 | I91: =I90 -> 0 | J91: =J90 -> 0 | K91: =K90 -> 194.38302 | L91: =L90 -> 194.38302 | ... P91: =P90 -> 194.38302 | Q91: =SUM(E91:P91) -> 1166.2981
A93: =Signage!A31 -> Walmart | B93: =Signage!B31 -> 0 | C93: =Signage!C31 -> NAP | Q93: =SUM(E93:P93) -> 0
A94: Signage Only | B94: Total Monthly Charges | E94: =Signage!E31 -> 2000 | F94: =Signage!F31 -> 2000 | G94: =Signage!G31 -> 2000 | H94: =Signage!H31 -> 2000 | I94: =Signage!I31 -> 2000 | J94: =Signage!J31 -> 2000 | K94: =Signage!K31 -> 2000 | L94: =Signage!L31 -> 2000 | ... P94: =Signage!P31 -> 2000 | Q94: =SUM(E94:P94) -> 24000
B95: Sales Tax | D95: =$D$11 -> 0.025 | E95: =E94*$D$90 -> 50 | F95: =F94*$D$90 -> 50 | G95: =G94*$D$90 -> 50 | H95: =H94*$D$90 -> 50 | I95: =I94*$D$90 -> 50 | J95: =J94*$D$90 -> 50 | K95: =K94*$D$90 -> 50 | L95: =L94*$D$90 -> 50 | ... P95: =P94*$D$90 -> 50 | Q95: =SUM(E95:P95) -> 600
C96: Total | E96: =E95 -> 50 | F96: =F95 -> 50 | G96: =G95 -> 50 | H96: =H95 -> 50 | I96: =I95 -> 50 | J96: =J95 -> 50 | K96: =K95 -> 50 | L96: =L95 -> 50 | ... P96: =P95 -> 50 | Q96: =SUM(E96:P96) -> 600
A98: =Signage!A32 -> Sportsman's Warehouse | B98: =Signage!B32 -> 0 | C98: =Signage!C32 -> NAP | Q98: =SUM(E98:P98) -> 0
A99: Signage Only | B99: Total Monthly Charges | E99: =Signage!E32 -> 1500 | F99: =Signage!F32 -> 1500 | G99: =Signage!G32 -> 1500 | H99: =Signage!H32 -> 1500 | I99: =Signage!I32 -> 1500 | J99: =Signage!J32 -> 1500 | K99: =Signage!K32 -> 1500 | L99: =Signage!L32 -> 1500 | ... P99: =Signage!P32 -> 1500 | Q99: =SUM(E99:P99) -> 18000
B100: Sales Tax | D100: =$D$11 -> 0.025 | E100: =E99*$D$90 -> 37.5 | F100: =F99*$D$90 -> 37.5 | G100: =G99*$D$90 -> 37.5 | H100: =H99*$D$90 -> 37.5 | I100: =I99*$D$90 -> 37.5 | J100: =J99*$D$90 -> 37.5 | K100: =K99*$D$90 -> 37.5 | L100: =L99*$D$90 -> 37.5 | ... P100: =P99*$D$90 -> 37.5 | Q100: =SUM(E100:P100) -> 450
C101: Total | E101: =E100 -> 37.5 | F101: =F100 -> 37.5 | G101: =G100 -> 37.5 | H101: =H100 -> 37.5 | I101: =I100 -> 37.5 | J101: =J100 -> 37.5 | K101: =K100 -> 37.5 | L101: =L100 -> 37.5 | ... P101: =P100 -> 37.5 | Q101: =SUM(E101:P101) -> 450
A103: =Signage!A33 -> John F. Long Foundation | B103: =Signage!B33 -> 0 | C103: =Signage!C33 -> NAP | Q103: =SUM(E103:P103) -> 0
A104: Signage Only | B104: Total Monthly Charges | E104: =Signage!E33 -> 15 | F104: =Signage!F33 -> 15 | G104: =Signage!G33 -> 15 | H104: =Signage!H33 -> 15 | I104: =Signage!I33 -> 15 | J104: =Signage!J33 -> 15 | K104: =Signage!K33 -> 15 | L104: =Signage!L33 -> 15 | ... O104: =Signage!O33 -> 15 | P104: =Signage!P37 -> 4585.83 | Q104: =SUM(E104:P104) -> 4750.83
B105: Sales Tax | D105: =$D$11 -> 0.025 | E105: =E104*$D$90 -> 0.375 | F105: =F104*$D$90 -> 0.375 | G105: =G104*$D$90 -> 0.375 | H105: =H104*$D$90 -> 0.375 | I105: =I104*$D$90 -> 0.375 | J105: =J104*$D$90 -> 0.375 | K105: =K104*$D$90 -> 0.375 | L105: =L104*$D$90 -> 0.375 | ... P105: =P104*$D$90 -> 114.64575 | Q105: =SUM(E105:P105) -> 118.77075
C106: Total | E106: =E105 -> 0.375 | F106: =F105 -> 0.375 | G106: =G105 -> 0.375 | H106: =H105 -> 0.375 | I106: =I105 -> 0.375 | J106: =J105 -> 0.375 | K106: =K105 -> 0.375 | L106: =L105 -> 0.375 | ... P106: =P105 -> 114.64575 | Q106: =SUM(E106:P106) -> 118.77075
A109: Grand Total | E109: =E16+E21+E26+E31+E36+E41+E46+E51+E56+E61+E66+E71+E76+E81+E86+E91+E96+E101+E106 -> 3421.1835 | F109: =F16+F21+F26+F31+F36+F41+F46+F51+F56+F61+F66+F71+F76+F81+F86+F91+F96+F101+F106 -> 3421.1835 | G109: =G16+G21+G26+G31+G36+G41+G46+G51+G56+G61+G66+G71+G76+G81+G86+G91+G96+G101+G106 -> 3421.1835 | H109: =H16+H21+H26+H31+H36+H41+H46+H51+H56+H61+H66+H71+H76+H81+H86+H91+H96+H101+H106 -> 3424.9178 | I109: =I16+I21+I26+I31+I36+I41+I46+I51+I56+I61+I66+I71+I76+I81+I86+I91+I96+I101+I106 -> 3426.7743 | J109: =J16+J21+J26+J31+J36+J41+J46+J51+J56+J61+J66+J71+J76+J81+J86+J91+J96+J101+J106 -> 3426.7743 | K109: =K16+K21+K26+K31+K36+K41+K46+K51+K56+K61+K66+K71+K76+K81+K86+K91+K96+K101+K106 -> 3622.3678 | L109: =L16+L21+L26+L31+L36+L41+L46+L51+L56+L61+L66+L71+L76+L81+L86+L91+L96+L101+L106 -> 3622.3678 | ... P109: =P16+P21+P26+P31+P36+P41+P46+P51+P56+P61+P66+P71+P76+P81+P86+P91+P96+P101+P106 -> 3752.9446 | Q109: =SUM(E109:P109) -> 42435.023 | T109: See Rent Tab - Matches Total
B111: NMK Tie-Out | E111: =E109-Summary!C15 -> 0 | F111: =F109-Summary!D15 -> 0 | G111: =G109-Summary!E15 -> 0 | H111: =H109-Summary!F15 -> 0 | I111: =I109-Summary!G15 -> 0 | J111: =J109-Summary!H15 -> 0 | K111: =K109-Summary!I15 -> 0 | L111: =L109-Summary!J15 -> 0 | ... P111: =P109-Summary!N15 -> 0

Sheet Occup,
O1: =Summary!T4 -> Date Revised: | P1: =Summary!U4 -> 46269 | Q1: =Summary!W4 -> 0
A2: =Summary!$A2 -> ATHENA PROPERTY MANAGEMENT
A3: =Summary!$A3 -> GREENFIELD GATEWAY MESA, ARIZONA
A4: =Summary!$A4 -> PROJECT NO. 801
A5: =Summary!$A5 -> 01/01/26-12/31/26
A6: =Summary!$A6 -> 2026 OPERATING BUDGET
A9: TENANT | B9: SUITE | C9: SQUARE | D9: JAN | E9: FEB | F9: MARCH | G9: APRIL | H9: MAY | I9: JUNE | J9: JULY | K9: AUGUST | L9: SEPT | M9: OCT | N9: NOV | O9: DEC | P9: TOTALS
B10: # | C10: FOOTAGE
A12: ESTIMATED MONTHLY SQUARE FOOTAGE OCCUPIED
A14: =Rent!A14 -> EOS Fitness | B14: =Rent!B14 -> Major A | C14: =Rent!C14 -> 35000 | D14: =IF(Rent!E14=0,0,($C14)) -> 35000 | E14: =IF(Rent!F14=0,0,($C14)) -> 35000 | F14: =IF(Rent!G14=0,0,($C14)) -> 35000 | G14: =IF(Rent!H14=0,0,($C14)) -> 35000 | H14: =IF(Rent!I14=0,0,($C14)) -> 35000 | I14: =IF(Rent!J14=0,0,($C14)) -> 35000 | J14: =IF(Rent!K14=0,0,($C14)) -> 35000 | K14: =IF(Rent!L14=0,0,($C14)) -> 35000 | ... O14: =IF(Rent!P14=0,0,($C14)) -> 35000 | P14: =(SUM(D14:O14)/12)/C14 -> 1
A15: =Rent!A15 -> Third Pasrty MVS | B15: =Rent!B15 -> B101 | C15: =Rent!C15 -> 3000 | D15: =IF(Rent!E15=0,0,($C15)) -> 3000 | E15: =IF(Rent!F15=0,0,($C15)) -> 3000 | F15: =IF(Rent!G15=0,0,($C15)) -> 3000 | G15: =IF(Rent!H15=0,0,($C15)) -> 3000 | H15: =IF(Rent!I15=0,0,($C15)) -> 3000 | I15: =IF(Rent!J15=0,0,($C15)) -> 3000 | J15: =IF(Rent!K15=0,0,($C15)) -> 3000 | K15: =IF(Rent!L15=0,0,($C15)) -> 3000 | ... O15: =IF(Rent!P15=0,0,($C15)) -> 3000 | P15: =(SUM(D15:O15)/12)/C15 -> 1
A16: =Rent!A16 -> Sally Beauty Supply | B16: =Rent!B16 -> B103 | C16: =Rent!C16 -> 1625 | D16: =IF(Rent!E16=0,0,($C16)) -> 1625 | E16: =IF(Rent!F16=0,0,($C16)) -> 1625 | F16: =IF(Rent!G16=0,0,($C16)) -> 1625 | G16: =IF(Rent!H16=0,0,($C16)) -> 1625 | H16: =IF(Rent!I16=0,0,($C16)) -> 1625 | I16: =IF(Rent!J16=0,0,($C16)) -> 1625 | J16: =IF(Rent!K16=0,0,($C16)) -> 1625 | K16: =IF(Rent!L16=0,0,($C16)) -> 1625 | ... O16: =IF(Rent!P16=0,0,($C16)) -> 1625 | P16: =(SUM(D16:O16)/12)/C16 -> 1
