Workbook
Name _Builtin0: #N/A

Sheet 2026
B1: 165
B2: VARIANCE REPORT
B3: 2026
C4: JAN | H4: FEB | M4: MARCH | R4: APRIL | W4: MAY | AB4: JUNE | AG4: JULY | AL4: AUGUST | AQ4: SEPTEMBER | AV4: OCTOBER | BA4: NOVEMBER | BF4: DECEMBER | BK4: YTD
B6: Tenant | C6: Budget | D6: Cash Receipts | E6: Variance | F6: Comments | H6: Budget | I6: Cash Receipts | J6: Variance | K6: Comments | M6: Budget | N6: Cash Receipts | O6: Variance | P6: Comments | R6: Budget | S6: Cash Receipts | T6: Variance | U6: Comments | W6: Budget | X6: Cash Receipts | Y6: Variance | Z6: Comments | AB6: Budget | AC6: Cash Receipts | AD6: Variance | AE6: Comments | AG6: Budget | AH6: Cash Receipts | AI6: Variance | AJ6: Comments | AL6: Budget | AM6: Cash Receipts | AN6: Variance | AO6: Comments | AQ6: Budget | AR6: Cash Receipts | AS6: Variance | AT6: Comments | AV6: Budget | AW6: Cash Receipts | AX6: Variance | AY6: Comments | BA6: Budget | BB6: Cash Receipts | BC6: Variance | BD6: Comments | BF6: Budget | BG6: Cash Receipts | BH6: Variance | BI6: Comments | BL6: Budget | BM6: Cash Receipts | BN6: Variance
A7: =Rent!B14 -> A 1-4 | B7: =Rent!A14 -> ISLAND LAVA JAVA | C7: =VLOOKUP(B7,'Final Data'!A:B,2,0)+942 -> 49863.183 | D7: 45483.44 | E7: =D7-C7 -> -4379.743 | F7: GET ($196.7) Budget vs Pmt PCR ($4,183.04) Budget vs Pmt | H7: =VLOOKUP(B7,'Final Data'!$A$3:$C$35,3,0)+942 -> 49863.183 | I7: 47223.98 | J7: =I7-H7 -> -2639.203 | K7: GET ($118.38) Short Pmt PCR ($2,520.82) Budget vs Pmt | M7: =VLOOKUP(B7,'Final Data'!$A$3:$D$31,4,0)+942 -> 49863.183 | N7: =44637.21-15376.01 -> 29261.2 | O7: =N7-M7 -> -20601.983 | P7: GET ($926.7) Budget Vs Pmt. PCR ($20,000) Budget vs Pmt PRO $824.72 Over Pmt MKT ($500.00) Budget vs Pmt | R7: =VLOOKUP(B7,'Final Data'!$A$3:$E$29,5,0)+942 -> 49863.183 | S7: =46931.45+15376.01 -> 62307.46 | T7: =S7-R7 -> 12444.277 | U7: GET $560.35 Budget Vs Pmt IFC $1,579.92 Budget Vs Pmt PCR $10,304.00 Budget Vs Pmt | W7: =VLOOKUP(B7,'Final Data'!$A$3:$F$37,6,0)+942 -> 49863.183 | X7: 42915.52 | Y7: =X7-W7 -> -6947.663 | Z7: GET ($312.26) Budget Vs Pmt PCR (6,635.40) Budget Vs Pmt | AB7: =VLOOKUP(B7,'Final Data'!$A$3:$G$37,7,0)+942 -> 49863.183 | AC7: 31044.65 | AD7: =AC7-AB7 -> -18818.533 | AE7: PCR ($7,699.03) Budget vs Pmt NNN ($10,273.05) SHORTPAID DUE TO PYC CREDIT APPLIED GET ($846.45) Budget Vs Pmt | AG7: =VLOOKUP(B7,'Final Data'!$A$3:$H$37,8,0)+942 -> 49863.183 | AH7: 40624.76 | AI7: =AH7-AG7 -> -9238.423 | AJ7: PCR ($8,823.08) Budget vs Pmt GET ($415.34) Budget Vs Pmt | AL7: =VLOOKUP(B7,'Final Data'!$A$3:$I$36,9,0)+942 -> 49863.183 | AM7: =41690.24-226.54 -> 41463.7 | AN7: =AM7-AL7 -> -8399.483 | AO7: PCR ($8,021.89) Budget vs Pmt GET ($377.59) Budget Vs Pmt | BK7: =B7 -> ISLAND LAVA JAVA | BL7: =C7+H7+M7+R7+W7+AB7+AG7+AL7+AQ7+AV7+BA7+BF7 -> 398905.46 | BM7: =D7+I7+N7+S7+X7+AC7+AH7+AM7+AR7+AW7+BB7+BG7 -> 340324.71 | BN7: =BM7-BL7 -> -58580.754 | BO7: PCR ($47,579.26) Budget vs Pmt Jan'26 to July'26 GET ($2,633.07) Budget Vs Pmt in Feb'26 to July'26 MKT ($500.00) Budget vs Pmt in Mar'26 PRO $824.72 Over Pmt in Mar'26 IFC $1,579.92 Budget Vs Pmt in Apr'26 NNN ($10,273.05) SHORTPAID DUE TO PYC CREDIT APPLIED in June'26
A8: =Rent!B15 -> B-5 | B8: =Rent!A15 -> TAKA SUSHI | C8: =VLOOKUP(B8,'Final Data'!A:B,2,0)+1.18+19.94 -> 7297.6182 | D8: 7271.44 | E8: =D8-C8 -> -26.178202 | F8: GET ($1.18) Budget vs Pmt PCR ($25.00) Budget vs Pmt | H8: =VLOOKUP(B8,'Final Data'!$A$3:$C$35,3,0)+1.18+19.94 -> 7297.6182 | I8: 7271.44 | J8: =I8-H8 -> -26.178202 | K8: GET ($1.18) Budget vs Pmt PCR ($25.00) Budget vs Pmt | M8: =VLOOKUP(B8,'Final Data'!$A$3:$D$31,4,0)+1.18+19.94 -> 7297.6182 | N8: 7271.44 | O8: =N8-M8 -> -26.178202 | P8: GET ($1.18) Budget vs Pmt PCR ($25.00) Budget vs Pmt | R8: =VLOOKUP(B8,'Final Data'!$A$3:$E$29,5,0)+1.18+19.94 -> 7297.6182 | S8: 7271.44 | T8: =S8-R8 -> -26.178202 | U8: GET ($1.18) Budget vs Pmt PCR ($25.00) Budget vs Pmt | W8: =VLOOKUP(B8,'Final Data'!$A$3:$F$37,6,0)+1.18+19.94 -> 7297.6182 | X8: 7271.44 | Y8: =X8-W8 -> -26.178202 | Z8: GET ($1.18) Budget vs Pmt PCR ($25.00) Budget vs Pmt | AB8: =VLOOKUP(B8,'Final Data'!$A$3:$G$37,7,0)+1.18+19.94 -> 7297.6182 | AC8: 4288.55 | AD8: =AC8-AB8 -> -3009.0682 | AE8: GET ($135.40) Budget vs Pmt PCR ($25.00) Budget vs Pmt NNN ($2,848.66) SHORTPAID DUE TO PYC CREDIT APPLIED | AG8: =VLOOKUP(B8,'Final Data'!$A$3:$H$37,8,0)+1.18+19.94 -> 7297.6182 | AH8: 7271.44 | AI8: =AH8-AG8 -> -26.178202 | AJ8: GET ($1.18) Budget vs Pmt PCR ($25.00) Budget vs Pmt | AL8: =VLOOKUP(B8,'Final Data'!$A$3:$I$36,9,0)+1.18+19.94 -> 7297.6182 | AM8: 7271.44 | AN8: =AM8-AL8 -> -26.178202 | AO8: GET ($1.18) Budget vs Pmt PCR ($25.00) Budget vs Pmt | BK8: =B8 -> TAKA SUSHI | BL8: =C8+H8+M8+R8+W8+AB8+AG8+AL8+AQ8+AV8+BA8+BF8 -> 58380.946 | BM8: =D8+I8+N8+S8+X8+AC8+AH8+AM8+AR8+AW8+BB8+BG8 -> 55188.63 | BN8: =BM8-BL8 -> -3192.3156 | BO8: GET ($143.65 ) Budget vs Pmt in Jan'26 to Aug'26 PCR ($200.00) Budget vs Pmt in Jan'26 to Aug'26 NNN ($2,848.66) SHORTPAID DUE TO PYC CREDIT APPLIED in June'26
A9: =Rent!B16 -> B-6 | B9: =Rent!A16 -> KANAKA KAVA | C9: =VLOOKUP(B9,'Final Data'!A:B,2,0)+9.42 -> 3208.7524 | D9: 2999.33 | E9: =D9-C9 -> -209.4224 | F9: GET ($9.42) Budget vs Pmt PCR ($200) Budget vs Pmt | H9: =VLOOKUP(B9,'Final Data'!$A$3:$C$35,3,0)+9.42 -> 3208.7524 | I9: 3520.14 | J9: =I9-H9 -> 311.3876 | K9: GET $14.01 Budget vs Pmt PCR $297.37 Budget vs Pmt | M9: =VLOOKUP(B9,'Final Data'!$A$3:$D$31,4,0)+9.42 -> 3208.7524 | N9: 2999.33 | O9: =N9-M9 -> -209.4224 | P9: GET ($9.42) Budget vs Pmt PCR ($200) Budget vs Pmt | R9: =VLOOKUP(B9,'Final Data'!$A$3:$E$29,5,0)+9.42 -> 3270.5524 | S9: 3764.64 | T9: =S9-R9 -> 494.0876 | U9: GET $25.01 Budget vs Pmt PCR $469.07 Budget vs Pmt | W9: =VLOOKUP(B9,'Final Data'!$A$3:$F$37,6,0)+9.42 -> 3270.5524 | X9: 3348.47 | Y9: =X9-W9 -> 77.917605 | Z9: GET $6.28 Budget vs Pmt PCR $71.63 Budget vs Pmt | AB9: =VLOOKUP(B9,'Final Data'!$A$3:$G$37,7,0)+9.42 -> 3270.5524 | AC9: 2604.11 | AD9: =AC9-AB9 -> -666.4424 | AE9: GET ($27.21) Budget vs Pmt PCR ($108.80) Budget vs Pmt NNN ($530.44) SHORTPAID DUE TO PYC CREDIT APPLIED | AG9: =VLOOKUP(B9,'Final Data'!$A$3:$H$37,8,0)+9.42 -> 3270.5524 | AH9: 3064.04 | AI9: =AH9-AG9 -> -206.5124 | AJ9: GET ($6.52) Budget vs Pmt PCR ($80.56) Budget vs Pmt PCR ($119.44) Short Pmt | AL9: =VLOOKUP(B9,'Final Data'!$A$3:$I$36,9,0)+9.42 -> 3270.5524 | AM9: 3189.11 | AN9: =AM9-AL9 -> -81.442395 | AO9: GET ($0.89) Budget vs Pmt PCR ($80.56) Budget vs Pmt | BK9: =B9 -> KANAKA KAVA | BL9: =C9+H9+M9+R9+W9+AB9+AG9+AL9+AQ9+AV9+BA9+BF9 -> 25979.019 | BM9: =D9+I9+N9+S9+X9+AC9+AH9+AM9+AR9+AW9+BB9+BG9 -> 25489.17 | BN9: =BM9-BL9 -> -489.84916 | BO9: GET ($8.16) Budget vs Pmt in Jan'26 to Aug'26 PCR $168.15 Budget vs Pmt in Jan'26 to Aug'26 PCR ($119.44) Short Pmt in July'26 NNN ($530.44) SHORTPAID DUE TO PYC CREDIT APPLIED in June'26
A10: =Rent!B17 -> C-7 | B10: =Rent!A17 -> GECKO GIRLZ SHAVE ICE SHACK | C10: =VLOOKUP(B10,'Final Data'!A:B,2,0)+42.39 -> 5174.1597 | D10: 4630.02 | E10: =D10-C10 -> -544.1397 | F10: GET ($55.64) Short Pmt GET $31.17 Budget vs Pmt PCR ($1,180.82) Short Pmt PCR $661.15 Budget vs Pmt | H10: =VLOOKUP(B10,'Final Data'!$A$3:$C$35,3,0)+42.39 -> 5174.1597 | I10: 5468.23 | J10: =I10-H10 -> 294.0703 | K10: GET $13.25 Over Pmt PCR $280.82 Over Pmt | M10: =VLOOKUP(B10,'Final Data'!$A$3:$D$31,4,0)+42.39 -> 5174.1597 | N10: 5679.04 | O10: =N10-M10 -> 504.8803 | P10: GET $22.74 Past due paid for Feb'26 PCR $1,382.14 past due paid for Feb'26 PCR ($900) Short Pmt Mar'26 | R10: =VLOOKUP(B10,'Final Data'!$A$3:$E$29,5,0)+42.39 -> 5174.1597 | S10: 5308.46 | T10: =S10-R10 -> 134.3003 | U10: GET $6.06 Past due paid for Mar'26 PCR $128.24 Budget vs Pmt | W10: =VLOOKUP(B10,'Final Data'!$A$3:$F$37,6,0)+42.39 -> 5174.1597 | X10: 6482.98 | Y10: =X10-W10 -> 1308.8203 | Z10: GET $ $58.91 Past due paid for Apr'26 PCR $1,249.91 Budget vs Pmt | AB10: =VLOOKUP(B10,'Final Data'!$A$3:$G$37,7,0)+42.39 -> 5249.9997 | AC10: 5718.71 | AD10: =AC10-AB10 -> 468.7103 | AE10: GET $ $24.52 Budget vs Pmt BAS ($45.51) Budget vs Pmt PCR $1,863.72 Budget vs Pmt NNN ($1,374.02) SHORTPAID DUE TO PYC CREDIT APPLIED | AG10: =VLOOKUP(B10,'Final Data'!$A$3:$H$37,8,0)+42.39 -> 5176.5997 | AH10: 4311.19 | AI10: =AH10-AG10 -> -865.4097 | AJ10: GET ($38.81) Budget vs Pmt BAS $73.40 Budget vs Pmt PCR ($900) Budget vs Pmt | AL10: =VLOOKUP(B10,'Final Data'!$A$3:$I$36,9,0)+42.39 -> 5176.5997 | AM10: 7305.67 | AN10: =AM10-AL10 -> 2129.0703 | AO10: GET $95.94 Budget vs Pmt BAS $73.40 Budget vs Pmt PCR $1,959.73 Budget vs Pmt | BK10: =B10 -> GECKO GIRLZ SHAVE ICE SHACK | BL10: =C10+H10+M10+R10+W10+AB10+AG10+AL10+AQ10+AV10+BA10+BF10 -> 41473.998 | BM10: =D10+I10+N10+S10+X10+AC10+AH10+AM10+AR10+AW10+BB10+BG10 -> 44904.3 | BN10: =BM10-BL10 -> 3430.3024 | BO10: GET $157.85 Budget Vs Pmt Mar'26 to Aug'26 PCR $4,545.89 Budget Vs Pmt Mar'26 to Aug'26 NNN ($1,374.02) SHORTPAID DUE TO PYC CREDIT APPLIED in June'26 BAS $101.29 Budget vs Pmt in June'26 to Aug'26
A11: =Rent!B18 -> C-8 | B11: =Rent!A18 -> BIG ISLAND RUNNING CO. | C11: =VLOOKUP(B11,'Final Data'!A:B,2,0)+44.75 -> 5382.4026 | D11: 6371.65 | E11: =D11-C11 -> 989.24741 | F11: GET $44.52 Budget vs Pmt PCR $944.73 Budget vs Pmt | H11: =VLOOKUP(B11,'Final Data'!$A$3:$C$35,3,0)+44.75 -> 5382.4026 | I11: 6272.23 | J11: =I11-H11 -> 889.82741 | K11: GET $40.05 Budget vs Pmt PCR $849.78 Budget vs Pmt | M11: =VLOOKUP(B11,'Final Data'!$A$3:$D$31,4,0)+44.75 -> 5382.4026 | N11: 5451.14 | O11: =N11-M11 -> 68.737405 | P11: GET $3.10 Budget vs Pmt PCR $65.64 Budget vs Pmt | R11: =VLOOKUP(B11,'Final Data'!$A$3:$E$29,5,0)+44.75 -> 5382.4026 | S11: 5606.61 | T11: =S11-R11 -> 224.20741 | U11: GET $10.09 Budget vs Pmt PCR $214.12 Budget vs Pmt | W11: =VLOOKUP(B11,'Final Data'!$A$3:$F$37,6,0)+44.75 -> 5382.4026 | X11: 5101.23 | Y11: =X11-W11 -> -281.17259 | Z11: GET ($12.65) Budget vs Pmt PCR ($268.52) Budget vs Pmt | AB11: =VLOOKUP(B11,'Final Data'!$A$3:$G$37,7,0)+44.75 -> 5382.4026 | AC11: 3932.12 | AD11: =AC11-AB11 -> -1450.2826 | AE11: GET ($65.26) Budget vs Pmt PCR ($92.13) Budget vs Pmt NNN ($1,292.89) SHORTPAID DUE TO PYC CREDIT APPLIED | AG11: =VLOOKUP(B11,'Final Data'!$A$3:$H$37,8,0)+44.75 -> 5382.4026 | AH11: 4976.7 | AI11: =AH11-AG11 -> -405.70259 | AJ11: GET ($18.25) Budget vs Pmt PCR ($387.45) Budget vs Pmt | AL11: =VLOOKUP(B11,'Final Data'!$A$3:$I$36,9,0)+44.75 -> 5382.4026 | AM11: 5783.98 | AN11: =AM11-AL11 -> 401.57741 | AO11: GET $18.07 Budget vs Pmt PCR $383.51 Budget vs Pmt | BK11: =B11 -> BIG ISLAND RUNNING CO. | BL11: =C11+H11+M11+R11+W11+AB11+AG11+AL11+AQ11+AV11+BA11+BF11 -> 43059.221 | BM11: =D11+I11+N11+S11+X11+AC11+AH11+AM11+AR11+AW11+BB11+BG11 -> 43495.66 | BN11: =BM11-BL11 -> 436.43924 | BO11: GET $19.66 Budget vs Pmt in Jan'26 to Aug'26 PCR $1,709.68 Budget vs Pmt in Jan'26 to Aug'26 NNN ($1,292.89) SHORTPAID DUE TO PYC CREDIT APPLIED in June'26
A12: =Rent!B19 -> D11-12 | B12: =Rent!A19 -> CAFE KONA | C12: =VLOOKUP(B12,'Final Data'!A:B,2,0) -> 7048.3605 | D12: 7650.79 | E12: =D12-C12 -> 602.42946 | F12: CAM $301.22 Over Pmt GET $13.55 Budget vs Pmt PCR $287.67 Budget vs Pmt | H12: =VLOOKUP(B12,'Final Data'!$A$3:$C$35,3,0) -> 7048.3605 | I12: =7425.16-340.02 -> 7085.14 | J12: =I12-H12 -> 36.77946 | K12: CAM ($301.22) PAST DUE PAID 01/26 GET $15.21 Budget vs Pmt PRO $322.80 Budget vs Pmt | M12: =VLOOKUP(B12,'Final Data'!$A$3:$D$31,4,0) -> 7048.3605 | N12: 7358.56 | O12: =N12-M12 -> 310.19946 | P12: GET $13.96 Budget vs Pmt PRO $296.25 Budget vs Pmt | R12: =VLOOKUP(B12,'Final Data'!$A$3:$E$29,5,0) -> 7048.3605 | S12: 7384.37 | T12: =S12-R12 -> 336.00946 | U12: GET $15.12 Budget vs Pmt PRO $320.90 Budget vs Pmt | W12: =VLOOKUP(B12,'Final Data'!$A$3:$F$37,6,0) -> 7048.3605 | X12: 7338.71 | Y12: =X12-W12 -> 290.34946 | Z12: GET $13.07 Budget vs Pmt PRO $277.29 Budget vs Pmt | AB12: =VLOOKUP(B12,'Final Data'!$A$3:$G$37,7,0) -> 7048.3605 | AC12: 7369.28 | AD12: =AC12-AB12 -> 320.91946 | AE12: GET $14.44 Budget vs Pmt PRO $306.49 Budget vs Pmt | AG12: =VLOOKUP(B12,'Final Data'!$A$3:$H$37,8,0) -> 7048.3605 | AH12: 7374.28 | AI12: =AH12-AG12 -> 325.91946 | AJ12: GET $14.67 Budget vs Pmt PRO $311.26 Budget vs Pmt | AL12: =VLOOKUP(B12,'Final Data'!$A$3:$I$36,9,0) -> 7048.3605 | AM12: 7048.35 | AN12: =AM12-AL12 -> -0.010540113 | BK12: =B12 -> CAFE KONA | BL12: =C12+H12+M12+R12+W12+AB12+AG12+AL12+AQ12+AV12+BA12+BF12 -> 56386.884 | BM12: =D12+I12+N12+S12+X12+AC12+AH12+AM12+AR12+AW12+BB12+BG12 -> 58609.48 | BN12: =BM12-BL12 -> 2222.5957 | BO12: GET $100.02 Budget vs Pmt in Jan'26 to July'26 PCR $287.67 Budget vs Pmt in Jan'26 & Feb'26 PRO $1,834.99 Budget vs Pmt in Feb'26 & July'26
A13: =Rent!B20 -> D9-D10 | B13: =Rent!A20 -> LUCASIE LTD | C13: =VLOOKUP(B13,'Final Data'!A:B,2,0) -> 10696.314 | D13: 8979.69 | E13: =D13-C13 -> -1716.6245 | F13: CAM ($1,639.41) Short Pmt GET ($77.25) Short Pmt | H13: =VLOOKUP(B13,'Final Data'!$A$3:$C$35,3,0) -> 10696.314 | I13: 10696.35 | J13: =I13-H13 -> 0.03552504 | M13: =VLOOKUP(B13,'Final Data'!$A$3:$D$31,4,0) -> 10998.824 | N13: 11013.08 | O13: =N13-M13 -> 14.255525 | P13: GET $14.26 Over Pmt | R13: =VLOOKUP(B13,'Final Data'!$A$3:$E$29,5,0) -> 10998.824 | S13: 0 | T13: =S13-R13 -> -10998.824 | U13: BAS ($7,895.51) No Pmt NNN ($3,103.31) No Pmt | W13: =VLOOKUP(B13,'Final Data'!$A$3:$F$37,6,0) -> 10998.824 | X13: 22163.96 | Y13: =X13-W13 -> 11165.136 | Z13: BAS $7,895.51 Past due paid NNN $3,269.63 Past due paid | AB13: =VLOOKUP(B13,'Final Data'!$A$3:$G$37,7,0) -> 10998.824 | AC13: 0 | AD13: =AC13-AB13 -> -10998.824 | AE13: BAS ($7,895.51) No Pmt NNN ($3,103.31) No Pmt | AG13: =VLOOKUP(B13,'Final Data'!$A$3:$H$37,8,0) -> 10998.824 | AH13: 22026.16 | AI13: =AH13-AG13 -> 11027.336 | AJ13: BAS $7,895.51 past due paid NNN $ $3,131.83 past due paid | AL13: =VLOOKUP(B13,'Final Data'!$A$3:$I$36,9,0) -> 10998.824 | AM13: 11013.08 | AN13: =AM13-AL13 -> 14.255525 | AO13: GET $14.26 Budget vs Pmt | BK13: =B13 -> LUCASIE LTD | BL13: =C13+H13+M13+R13+W13+AB13+AG13+AL13+AQ13+AV13+BA13+BF13 -> 87385.576 | BM13: =D13+I13+N13+S13+X13+AC13+AH13+AM13+AR13+AW13+BB13+BG13 -> 85892.32 | BN13: =BM13-BL13 -> -1493.2558 | BO13: CAM ($1,639.41) Short Pmt in Jan'26 GET ($34.42) Short Pmt in Jan'26 & Julyr'26 NNN $166.32 Budget Vs Pmt in May'26 GET $14.26 Budget vs Pmt in Aug'26
A14: =Rent!B21 -> DU-1 | B14: =Rent!A21 -> FOSTERS KITCHEN | C14: =VLOOKUP(B14,'Final Data'!A:B,2,0) -> 23777.974 | D14: 0 | E14: =D14-C14 -> -23777.974 | F14: BAS (11,905.63) No Pmt NNN ($11,372.34) No Pmt MKT ($500.00) No Pmt | H14: =VLOOKUP(B14,'Final Data'!$A$3:$C$35,3,0) -> 23777.974 | I14: 0 | J14: =I14-H14 -> -23777.974 | K14: BAS ($11,905.63) No Pmt NNN ($11,872.34) No Pmt | M14: =VLOOKUP(B14,'Final Data'!$A$3:$D$31,4,0) -> 23777.974 | N14: =190223.76-118889.85 -> 71333.91 | O14: =N14-M14 -> 47555.936 | P14: BAS $23,811.26 Past Due Paid for Jan'25 & Feb'26 NNN $23,744.68 Past Due Paid for Jan'25 & Feb'26 | R14: =VLOOKUP(B14,'Final Data'!$A$3:$E$29,5,0) -> 23777.974 | S14: 23777.97 | T14: =S14-R14 -> -0.0043720919 | W14: =VLOOKUP(B14,'Final Data'!$A$3:$F$37,6,0) -> 23777.974 | X14: 23777.97 | Y14: =X14-W14 -> -0.0043720919 | AB14: =VLOOKUP(B14,'Final Data'!$A$3:$G$37,7,0) -> 23777.974 | AC14: 23777.97 | AD14: =AC14-AB14 -> -0.0043720919 | AG14: =VLOOKUP(B14,'Final Data'!$A$3:$H$37,8,0) -> 24135.144 | AH14: 0 | AI14: =AH14-AG14 -> -24135.144 | AJ14: BAS ($12,262.80) No Pmt NNN ($11,872.34) No Pmt | AL14: =VLOOKUP(B14,'Final Data'!$A$3:$I$36,9,0)+211.95 -> 28847.094 | AM14: 47555.94 | AN14: =AM14-AL14 -> 18708.846 | AO14: BAS $12,262.80 Past due paid NNN $7,194.05 Past due paid CAM ($748.00) Short Pmt | BK14: =B14 -> FOSTERS KITCHEN | BL14: =C14+H14+M14+R14+W14+AB14+AG14+AL14+AQ14+AV14+BA14+BF14 -> 195650.08 | BM14: =D14+I14+N14+S14+X14+AC14+AH14+AM14+AR14+AW14+BB14+BG14 -> 190223.76 | BN14: =BM14-BL14 -> -5426.325 | BO14: NNN ($11,872.34) No Pmt in July'26 NNN $7,194.05 Past due paid in Aug'26 CAM ($748.00) Short Pmt in Aug'26
A15: =Rent!B22 -> E | B15: =Rent!A22 -> HUMPYS BIG ISLAND ALEHOUSE | C15: =VLOOKUP(B15,'Final Data'!A:B,2,0) -> 27656.092 | D15: 26178 | E15: =D15-C15 -> -1478.0923 | F15: GET ($1,478.09) Short Pmt | H15: =VLOOKUP(B15,'Final Data'!$A$3:$C$35,3,0) -> 27656.092 | I15: 26178 | J15: =I15-H15 -> -1478.0923 | K15: GET ($1,478.09) Budget vs Pmt | M15: =VLOOKUP(B15,'Final Data'!$A$3:$D$31,4,0) -> 27656.092 | N15: 26178 | O15: =N15-M15 -> -1478.0923 | P15: GET ($1,478.09) Budget vs Pmt | R15: =VLOOKUP(B15,'Final Data'!$A$3:$E$29,5,0) -> 27656.092 | S15: 26178 | T15: =S15-R15 -> -1478.0923 | U15: GET ($1,478.09) Budget vs Pmt | W15: =VLOOKUP(B15,'Final Data'!$A$3:$F$37,6,0) -> 27656.092 | X15: 26178 | Y15: =X15-W15 -> -1478.0923 | Z15: GET ($1,478.09) Budget vs Pmt | AB15: =VLOOKUP(B15,'Final Data'!$A$3:$G$37,7,0) -> 27656.092 | AC15: =91657.31-65479.31 -> 26178 | AD15: =AC15-AB15 -> -1478.0923 | AE15: GET $1,468.45 Budget vs Pmt RDR $62,532.77 SHORTPAID DUE TO PYC CREDIT APPLIED RDR ($62,532.77) 2025 CAM REC DEFERRAL RDR ($2,946.54) 2025 CAM GET DEFERRAL | AG15: =VLOOKUP(B15,'Final Data'!$A$3:$H$37,8,0) -> 27656.092 | AH15: 0 | AI15: =AH15-AG15 -> -27656.092 | AJ15: BAS ($25,000.00) No Pmt NNN ($2,656.09) No Pmt | AL15: =VLOOKUP(B15,'Final Data'!$A$3:$I$36,9,0) -> 27656.092 | AM15: =-13123.31+65479.31 -> 52356 | AN15: =AM15-AL15 -> 24699.908 | AO15: BAS $25,000.00 Past due paid GET ($300.09) Budget vs Pmt | BK15: =B15 -> HUMPYS BIG ISLAND ALEHOUSE | BL15: =C15+H15+M15+R15+W15+AB15+AG15+AL15+AQ15+AV15+BA15+BF15 -> 221248.74 | BM15: =D15+I15+N15+S15+X15+AC15+AH15+AM15+AR15+AW15+BB15+BG15 -> 209424 | BN15: =BM15-BL15 -> -11824.738 | BO15: GET ($6,222.10) Budget vs Pmt in Jan'26 to Aug'26 RDR ($2,946.54) 2025 CAM GET DEFERRAL in June'26 NNN ($2,656.09) No Pmt in July'26
A16: =Rent!B23 -> F15,17&A8 | B16: =Rent!A23 -> ABC STORE #75 | C16: =VLOOKUP(B16,'Final Data'!A:B,2,0)+2500+847.8-1000 -> 53899.272 | D16: =61535.66-991.58 -> 60544.08 | E16: =D16-C16 -> 6644.8075 | F16: GET $366.87 Budget vs Pmt PCR $5,277.93 Budget vs Pmt MIS $1,000 Budget vs MRI | H16: =VLOOKUP(B16,'Final Data'!$A$3:$C$35,3,0)+2500+847.8-1000 -> 53899.272 | I16: =54363.95+991.58 -> 55355.53 | J16: =I16-H16 -> 1456.2575 | K16: GET $133.38 Budget vs Pmt PCR $322.88 Budget vs Pmt MIS $1,000 Budget vs MRI | M16: =VLOOKUP(B16,'Final Data'!$A$3:$D$31,4,0)+2500+847.8-1000 -> 53899.272 | N16: 54567.28 | O16: =N16-M16 -> 668.00751 | P16: GET $97.91 Budget vs Pmt PCR $570.10 Budget vs Pmt | R16: =VLOOKUP(B16,'Final Data'!$A$3:$E$29,5,0)+2500+847.8-1000 -> 53899.272 | S16: 61312.36 | T16: =S16-R16 -> 7413.0875 | U16: GET ($1,098.56) Budget vs Pmt PCR $7,011.64 Budget vs Pmt MIS $1,500.00 Budget vs Pmt | W16: =VLOOKUP(B16,'Final Data'!$A$3:$F$37,6,0)+2500+847.8-1000 -> 53899.272 | X16: 54937.13 | Y16: =X16-W16 -> 1037.8575 | Z16: GET ($1,385.44) Budget vs Pmt PCR $923.29 Budget vs Pmt MIS $1,500.00 Budget vs Pmt | AB16: =VLOOKUP(B16,'Final Data'!$A$3:$G$37,7,0)+2500+847.8-1000 -> 53899.272 | AC16: 57039.44 | AD16: =AC16-AB16 -> 3140.1675 | AE16: GET ($1,290.84) Budget vs Pmt PCR $2,931.00 Budget vs Pmt MIS $1,500.00 Budget vs Pmt | AG16: =VLOOKUP(B16,'Final Data'!$A$3:$H$37,8,0)+2500+847.8-1000 -> 53899.272 | AH16: 27793.2 | AI16: =AH16-AG16 -> -26106.072 | AJ16: GET ($2,606.91) Budget vs Pmt PCR $2,936.94 Budget vs Pmt MIS $1,500.00 Budget vs Pmt NNN ($27,936.11) short pmt due to applied PYC | AL16: =VLOOKUP(B16,'Final Data'!$A$3:$I$36,9,0)+2500+847.8-1000 -> 53899.272 | AM16: 62473.27 | AN16: =AM16-AL16 -> 8573.9975 | AO16: GET ($1,046.32) Budget vs Pmt PCR $8,120.31 Budget vs Pmt MIS $1,500.00 Budget vs Pmt | BK16: =B16 -> ABC STORE #75 | BL16: =C16+H16+M16+R16+W16+AB16+AG16+AL16+AQ16+AV16+BA16+BF16 -> 431194.18 | BM16: =D16+I16+N16+S16+X16+AC16+AH16+AM16+AR16+AW16+BB16+BG16 -> 434022.29 | BN16: =BM16-BL16 -> 2828.11 | BO16: GET ($6,829.91) Budget vs Pmt in Jan'26 to Aug'26 PCR $28,094.09 Budget vs Pmt in Jan'26 to Aug'26 MIS $9,500 Budget vs MRI for Jan'26 to Aug'26 NNN ($27,936.11) short pmt due to applied PYC in July'26
A17: =Rent!B24 -> F-16 | B17: =Rent!A24 -> GYPSEA GALATO | C17: =VLOOKUP(B17,'Final Data'!A:B,2,0)+38.62 -> 5248.9125 | D17: 5260.52 | E17: =D17-C17 -> 11.60748 | F17: PCR ($80.89) Short Pmt PCR $91.97 Budget vs Pmt | H17: =VLOOKUP(B17,'Final Data'!$A$3:$C$35,3,0)+38.62 -> 5248.9125 | I17: 5962.06 | J17: =I17-H17 -> 713.14748 | K17: GET $32.10 Budget vs Pmt PCR $681.05 Budget vs Pmt | M17: =VLOOKUP(B17,'Final Data'!$A$3:$D$31,4,0)+38.62 -> 5248.9125 | N17: =6142.56-301.92 -> 5840.64 | O17: =N17-M17 -> 591.72748 | P17: GET $30.27 Budget vs Pmt PCR $642.34 Budget vs Pmt PCR ($80.89) Short Pmt | R17: =VLOOKUP(B17,'Final Data'!$A$3:$E$29,5,0)+38.62 -> 5248.9125 | S17: 5493.06 | T17: =S17-R17 -> 244.14748 | U17: CAM ($390.28) Short Pmt GET $32.20 Budget vs Pmt PCR $602.23 Budget vs Pmt | W17: =VLOOKUP(B17,'Final Data'!$A$3:$F$37,6,0)+38.62 -> 5248.9125 | X17: =5506.75-409.72 -> 5097.03 | Y17: =X17-W17 -> -151.88252 | Z17: GET ($38.63) Budget vs Pmt PCR ($113.25) Budget vs Pmt | AB17: =VLOOKUP(B17,'Final Data'!$A$3:$G$37,7,0)+38.62 -> 5330.8625 | AC17: 473.98 | AD17: =AC17-AB17 -> -4856.8825 | AE17: GET ($214.85) Budget vs Pmt PCR ($367.35) Budget vs Pmt NNN ($4,274.68) SHORTPAID DUE TO PYC CREDIT APPLIED | AG17: =VLOOKUP(B17,'Final Data'!$A$3:$H$37,8,0)+38.62 -> 5330.8625 | AH17: 5690.28 | AI17: =AH17-AG17 -> 359.41748 | AJ17: GET $19.87 Budget vs Pmt PCR $339.54 Budget vs Pmt | AL17: =VLOOKUP(B17,'Final Data'!$A$3:$I$36,9,0)+38.62 -> 5330.8625 | AM17: =4678.77+711.64 -> 5390.41 | AN17: =AM17-AL17 -> 59.54748 | AO17: GET ($8.14) Budget vs Pmt CAM $390.28 past due paid PCR $70.47 Budget vs Pmt NNN ($393.06) Short Paid due to PYC credit applied in Aug'26 | AP17: =-8.14+390.28+70.47-393.06 -> 59.55 | BK17: =B17 -> GYPSEA GALATO | BL17: =C17+H17+M17+R17+W17+AB17+AG17+AL17+AQ17+AV17+BA17+BF17 -> 42237.15 | BM17: =D17+I17+N17+S17+X17+AC17+AH17+AM17+AR17+AW17+BB17+BG17 -> 39207.98 | BN17: =BM17-BL17 -> -3029.1702 | BO17: GET ($147.18) Budget vs Pmt in Jan'26 to Aug'26 PCR $1,785.75 Budget vs Pmt in Jan'26 to Aug'26 NNN ($4,667.74) SHORTPAID DUE TO PYC CREDIT APPLIED in June'26 & Aug'26 | BS17: 139.04
A18: =Rent!B25 -> G | B18: =Rent!A25 -> OCEANS SPORTS BAR AND GRILL | C18: =VLOOKUP(B18,'Final Data'!A:B,2,0) -> 16707.224 | D18: 16707.22 | E18: =D18-C18 -> -0.0040942424 | H18: =VLOOKUP(B18,'Final Data'!$A$3:$C$35,3,0) -> 16707.224 | I18: 16707.22 | J18: =I18-H18 -> -0.0040942424 | M18: =VLOOKUP(B18,'Final Data'!$A$3:$D$31,4,0) -> 16707.224 | N18: 16707.22 | O18: =N18-M18 -> -0.0040942424 | R18: =VLOOKUP(B18,'Final Data'!$A$3:$E$29,5,0) -> 16707.224 | S18: 16707.22 | T18: =S18-R18 -> -0.0040942424 | W18: =VLOOKUP(B18,'Final Data'!$A$3:$F$37,6,0) -> 16707.224 | X18: 16707.22 | Y18: =X18-W18 -> -0.0040942424 | AB18: =VLOOKUP(B18,'Final Data'!$A$3:$G$37,7,0) -> 16707.224 | AC18: 16707.22 | AD18: =AC18-AB18 -> -0.0040942424 | AG18: =VLOOKUP(B18,'Final Data'!$A$3:$H$37,8,0) -> 16707.224 | AH18: 16707.22 | AI18: =AH18-AG18 -> -0.0040942424 | AL18: =VLOOKUP(B18,'Final Data'!$A$3:$I$36,9,0) -> 16707.224 | AM18: 16707.22 | AN18: =AM18-AL18 -> -0.0040942424 | BK18: =B18 -> OCEANS SPORTS BAR AND GRILL | BL18: =C18+H18+M18+R18+W18+AB18+AG18+AL18+AQ18+AV18+BA18+BF18 -> 133657.79 | BM18: =D18+I18+N18+S18+X18+AC18+AH18+AM18+AR18+AW18+BB18+BG18 -> 133657.76 | BN18: =BM18-BL18 -> -0.032753939 | BS18: 8.14
A19: =Rent!B26 -> H | B19: =Rent!A26 -> JACKS DIVE LOCKER | C19: =VLOOKUP(B19,'Final Data'!A:B,2,0) -> 35662.42 | D19: 35662.42 | E19: =D19-C19 -> 0.00032877734 | H19: =VLOOKUP(B19,'Final Data'!$A$3:$C$35,3,0) -> 35662.42 | I19: 35662.42 | J19: =I19-H19 -> 0.00032877734 | M19: =VLOOKUP(B19,'Final Data'!$A$3:$D$31,4,0) -> 35662.42 | N19: 35662.42 | O19: =N19-M19 -> 0.00032877734 | R19: =VLOOKUP(B19,'Final Data'!$A$3:$E$29,5,0) -> 35662.42 | S19: 35662.42 | T19: =S19-R19 -> 0.00032877734 | W19: =VLOOKUP(B19,'Final Data'!$A$3:$F$37,6,0) -> 35662.42 | X19: 35662.42 | Y19: =X19-W19 -> 0.00032877734 | AB19: =VLOOKUP(B19,'Final Data'!$A$3:$G$37,7,0) -> 35662.42 | AC19: 35662.42 | AD19: =AC19-AB19 -> 0.00032877734 | AG19: =VLOOKUP(B19,'Final Data'!$A$3:$H$37,8,0) -> 35662.42 | AH19: 17133.72 | AI19: =AH19-AG19 -> -18528.7 | AJ19: GET ($833.79) Budget vs Pmt NNN ($17,694.92) short pmt due to applied PYC | AL19: =VLOOKUP(B19,'Final Data'!$A$3:$I$36,9,0) -> 35662.42 | AM19: 35662.42 | AN19: =AM19-AL19 -> 0.00032877734 | BK19: =B19 -> JACKS DIVE LOCKER | BL19: =C19+H19+M19+R19+W19+AB19+AG19+AL19+AQ19+AV19+BA19+BF19 -> 285299.36 | BM19: =D19+I19+N19+S19+X19+AC19+AH19+AM19+AR19+AW19+BB19+BG19 -> 266770.66 | BN19: =BM19-BL19 -> -18528.697 | BO19: GET ($833.79) Budget vs Pmt in July'26 NNN ($17,694.92) short pmt due to applied PYC in July'26
A20: =Rent!B27 -> I | B20: =Rent!A27 -> QPOT | C20: =VLOOKUP(B20,'Final Data'!A:B,2,0) -> 0 | D20: 0 | E20: =D20-C20 -> 0 | H20: =VLOOKUP(B20,'Final Data'!$A$3:$C$35,3,0) -> 0 | I20: 0 | J20: =I20-H20 -> 0 | M20: =VLOOKUP(B20,'Final Data'!$A$3:$D$31,4,0) -> 0 | N20: 0 | O20: =N20-M20 -> 0 | R20: =VLOOKUP(B20,'Final Data'!$A$3:$E$29,5,0) -> 0 | S20: 0 | T20: =S20-R20 -> 0 | W20: =VLOOKUP(B20,'Final Data'!$A$3:$F$37,6,0) -> 0 | X20: 0 | Y20: =X20-W20 -> 0 | AB20: 0 | AC20: 0 | AD20: =AC20-AB20 -> 0 | AG20: =VLOOKUP(B20,'Final Data'!$A$3:$H$37,8,0) -> 27672.534 | AH20: 0 | AI20: =AH20-AG20 -> -27672.534 | AJ20: BAS ($13,000) No Pmt NNN ($14,672.53) No Pmt | AL20: =VLOOKUP(B20,'Final Data'!$A$3:$I$36,9,0) -> 27672.534 | AM20: 0 | AN20: =AM20-AL20 -> -27672.534 | AO20: BAS ($13,000) No Pmt NNN ($14,672.53) No Pmt | BK20: =B20 -> QPOT | BL20: =C20+H20+M20+R20+W20+AB20+AG20+AL20+AQ20+AV20+BA20+BF20 -> 55345.069 | BM20: =D20+I20+N20+S20+X20+AC20+AH20+AM20+AR20+AW20+BB20+BG20 -> 0 | BN20: =BM20-BL20 -> -55345.069 | BO20: BAS ($26,000) No Pmt in July'26 & Aug'26 NNN ($29,345.07) No Pmt in July'26 & Aug'26
A21: =Rent!B28 -> PC-1&2 | B21: =Rent!A28 -> BOWLS SUPERFOODS & ORALE TACOS | C21: =VLOOKUP(B21,'Final Data'!A:B,2,0) -> 0 | D21: 0 | E21: =D21-C21 -> 0 | H21: =VLOOKUP(B21,'Final Data'!$A$3:$C$35,3,0) -> 0 | I21: 0 | J21: =I21-H21 -> 0 | M21: =VLOOKUP(B21,'Final Data'!$A$3:$D$31,4,0) -> 0 | N21: 0 | O21: =N21-M21 -> 0 | R21: =VLOOKUP(B21,'Final Data'!$A$3:$E$29,5,0) -> 0 | S21: 0 | T21: =S21-R21 -> 0 | W21: =VLOOKUP(B21,'Final Data'!$A$3:$F$37,6,0) -> 0 | X21: 0 | Y21: =X21-W21 -> 0 | AB21: 0 | AC21: 0 | AD21: =AC21-AB21 -> 0 | AG21: =VLOOKUP(B21,'Final Data'!$A$3:$H$37,8,0) -> 0 | AH21: 0 | AI21: =AH21-AG21 -> 0 | AL21: =VLOOKUP(B21,'Final Data'!$A$3:$I$36,9,0) -> 0 | BK21: =B21 -> BOWLS SUPERFOODS & ORALE TACOS | BL21: =C21+H21+M21+R21+W21+AB21+AG21+AL21+AQ21+AV21+BA21+BF21 -> 0 | BM21: =D21+I21+N21+S21+X21+AC21+AH21+AM21+AR21+AW21+BB21+BG21 -> 0 | BN21: =BM21-BL21 -> 0
A22: =Rent!B29 -> PC 3&4 | B22: =Rent!A29 -> KONA GEAR INC. | C22: =VLOOKUP(B22,'Final Data'!A:B,2,0)+141.3 -> 12251.462 | D22: =11275.74-2165.57 -> 9110.17 | E22: =D22-C22 -> -3141.2918 | F22: GET ($141.3) Budget vs Pmt PCR ($3,000) Budget vs Pmt | H22: =VLOOKUP(B22,'Final Data'!$A$3:$C$35,3,0)+141.3 -> 12251.462 | I22: =14213.8-2938.06 -> 11275.74 | J22: =I22-H22 -> -975.72178 | K22: GET ($43.84) Budget vs Pmt PCR ($931.88) Budget vs Pmt | M22: =VLOOKUP(B22,'Final Data'!$A$3:$D$31,4,0)+141.3 -> 12251.462 | N22: =12863.85+5103.63+340.02 -> 18307.5 | O22: =N22-M22 -> 6056.0382 | P22: GET $272.58 Budget vs Pmt PCR $3,518.74 Budget vs Pmt PRO $2,264.72 Budget vs Pmt | R22: =VLOOKUP(B22,'Final Data'!$A$3:$E$29,5,0)+141.3 -> 12255.872 | S22: 16026.55 | T22: =S22-R22 -> 3770.6782 | U22: GET ($120.10) Budget vs Pmt PCR $2,678.47 Budget vs Pmt PRO $1,211.91 Budget vs Pmt | W22: =VLOOKUP(B22,'Final Data'!$A$3:$F$37,6,0)+141.3 -> 12255.872 | X22: 12950.67 | Y22: =X22-W22 -> 694.79822 | Z22: GET ($258.51) Budget vs Pmt PCR $8.05 Budget vs Pmt PRO $944.86 Budget vs Pmt | AB22: =VLOOKUP(B22,'Final Data'!$A$3:$G$37,7,0)+141.3 -> 12255.872 | AC22: 7915.58 | AD22: =AC22-AB22 -> -4340.2918 | AE22: GET ($485.09) Budget vs Pmt PCR $309.97 Budget vs Pmt PRO $975.06 Budget vs Pmt NNN ($5,140.63) SHORTPAID DUE TO PYC CREDIT APPLIED | AG22: =VLOOKUP(B22,'Final Data'!$A$3:$H$37,8,0)+141.3 -> 12255.872 | AH22: 13601.76 | AI22: =AH22-AG22 -> 1345.8882 | AJ22: GET ($229.24) Budget vs Pmt PCR $573.34 Budget vs Pmt PRO $1001.39 Budget vs Pmt | AL22: =VLOOKUP(B22,'Final Data'!$A$3:$I$36,9,0)+141.3 -> 12255.872 | AM22: 12875.45 | AN22: =AM22-AL22 -> 619.57822 | AO22: GET ($261.90)Budget vs Pmt PCR ($57.25) Budget vs Pmt PRO $938.33 Budget vs Pmt | BK22: =B22 -> KONA GEAR INC. | BL22: =C22+H22+M22+R22+W22+AB22+AG22+AL22+AQ22+AV22+BA22+BF22 -> 98033.744 | BM22: =D22+I22+N22+S22+X22+AC22+AH22+AM22+AR22+AW22+BB22+BG22 -> 102063.42 | BN22: =BM22-BL22 -> 4029.6758 | BO22: GET ($1,267.40) Budget vs Pmt in Jan'26 to Aug'26 PCR $3,099.44 Budget vs Pmt in Jan'26 to Aug'26 PRO $7,336.27 Budget vs Pmt in Apr'26 to Aug'26 NNN ($5,140.63) SHORTPAID DUE TO PYC CREDIT APPLIED in June'26
A23: =Rent!B30 -> PC/U1 | B23: =Rent!A30 -> LAVERNES | C23: =VLOOKUP(B23,'Final Data'!A:B,2,0) -> 18449.433 | D23: 18449.43 | E23: =D23-C23 -> -0.0028573606 | H23: =VLOOKUP(B23,'Final Data'!$A$3:$C$35,3,0) -> 18449.433 | I23: 18449.43 | J23: =I23-H23 -> -0.0028573606 | M23: =VLOOKUP(B23,'Final Data'!$A$3:$D$31,4,0) -> 18449.433 | N23: 18449.43 | O23: =N23-M23 -> -0.0028573606 | R23: =VLOOKUP(B23,'Final Data'!$A$3:$E$29,5,0) -> 18449.433 | S23: 18449.43 | T23: =S23-R23 -> -0.0028573606 | W23: =VLOOKUP(B23,'Final Data'!$A$3:$F$37,6,0) -> 18449.433 | X23: 18449.43 | Y23: =X23-W23 -> -0.0028573606 | AB23: =VLOOKUP(B23,'Final Data'!$A$3:$G$37,7,0) -> 18449.433 | AC23: 16726.85 | AD23: =AC23-AB23 -> -1722.5829 | AE23: GET ($77.53) Budget vs Pmt NNN ($1,645.06) SHORTPAID DUE TO PYC CREDIT APPLIED | AG23: =VLOOKUP(B23,'Final Data'!$A$3:$H$37,8,0) -> 18449.433 | AH23: 0 | AI23: =AH23-AG23 -> -18449.433 | AJ23: BAS ($7,408) No Pmt NNN ($11,041) No Pmt | AL23: =VLOOKUP(B23,'Final Data'!$A$3:$I$36,9,0) -> 18449.433 | AM23: 36898.86 | AN23: =AM23-AL23 -> 18449.427 | AO23: BAS $7,408 Past due paid for 07/26 in Aug'26 NNN $11,041 Past due paid for 07/26 in Aug'26 | BK23: =B23 -> LAVERNES | BL23: =C23+H23+M23+R23+W23+AB23+AG23+AL23+AQ23+AV23+BA23+BF23 -> 147595.46 | BM23: =D23+I23+N23+S23+X23+AC23+AH23+AM23+AR23+AW23+BB23+BG23 -> 145872.86 | BN23: =BM23-BL23 -> -1722.6029 | BO23: GET ($77.53) Budget vs Pmt in June'26 NNN ($1,645.06) SHORTPAID DUE TO PYC CREDIT APPLIED in June'26
B24: Parking Income | C24: 30000 | D24: 35803.84 | E24: =D24-C24 -> 5803.84 | F24: PARKLINQ RESERVA PAYOUT | H24: 30000 | I24: 42482.1 | J24: =I24-H24 -> 12482.1 | K24: PARKLINQ RESERVA PAYOUT | M24: 30000 | N24: 36409.48 | O24: =N24-M24 -> 6409.48 | P24: PARKING Budget Vs Pmt | R24: 30000 | S24: 37497.87 | T24: =S24-R24 -> 7497.87 | U24: PARKLINQ RESERVA PAYOUT | W24: ='Final Data'!F26 -> 30000 | X24: 32117.71 | Y24: =X24-W24 -> 2117.71 | Z24: PARKLINQ RESERVA PAYOUT | AB24: ='Final Data'!G26 -> 30000 | AC24: 35429.5 | AD24: =AC24-AB24 -> 5429.5 | AE24: PARKLINQ RESERVA PAYOUT | AG24: ='Final Data'!H26 -> 30000 | AH24: 42007.06 | AI24: =AH24-AG24 -> 12007.06 | AJ24: PARKLINQ RESERVA PAYOUT | AL24: ='Final Data'!I26 -> 30000 | AM24: 44202.54 | AN24: =AM24-AL24 -> 14202.54 | AO24: PARKLINQ RESERVA PAYOUT | BK24: =B24 -> Parking Income | BL24: =C24+H24+M24+R24+W24+AB24+AG24+AL24+AQ24+AV24+BA24+BF24 -> 240000 | BM24: =D24+I24+N24+S24+X24+AC24+AH24+AM24+AR24+AW24+BB24+BG24 -> 305950.1 | BN24: =BM24-BL24 -> 65950.1 | BO24: PARKLINQ RESERVA PAYOUT in Jan'26 to Aug'26 PARKING Budget Vs Pmt in Mar'26
AB25: 0 | AG25: 0 | AI25: =AH25-AG25 -> 0
E26: =D26-C26 -> 0 | BK26: BUDGET VS MRI | BL26: =C26+H26+M26+R26+W26+AB26+AG26+AL26+AQ26+AV26+BA26+BF26 -> 0 | BM26: =D26+I26+N26+S26+X26+AC26+AH26+AM26+AR26+AW26+BB26+BG26 -> 0 | BN26: =BM26-BL26 -> 0
B27: Totals | C27: =SUM(C7:C26) -> 312323.58 | D27: =SUM(D7:D26) -> 291102.04 | E27: =SUM(E7:E26) -> -21221.541 | H27: =SUM(H7:H26) -> 312323.58 | I27: =SUM(I7:I26) -> 299610.01 | J27: =SUM(J7:J26) -> -12713.571 | M27: =SUM(M7:M26) -> 312626.09 | N27: =SUM(N7:N26) -> 352489.67 | O27: =SUM(O7:O26) -> 39863.579 | R27: =SUM(R7:R26) -> 312692.3 | S27: =SUM(S7:S26) -> 332747.86 | T27: =SUM(T7:T26) -> 20055.559 | W27: =SUM(W7:W26) -> 312692.3 | X27: =SUM(X7:X26) -> 320499.89 | Y27: =SUM(Y7:Y26) -> 7807.589 | AB27: =SUM(AB7:AB26) -> 312850.09 | AC27: =SUM(AC7:AC26) -> 274868.38 | AD27: =SUM(AD7:AD26) -> -37981.711 | AG27: =SUM(AG7:AG26) -> 340806.4 | AH27: =SUM(AH7:AH26) -> 212581.81 | AI27: =SUM(AI7:AI26) -> -128224.59 | AL27: =SUM(AL7:AL26) -> 345518.35 | AM27: =SUM(AM7:AM26) -> 397197.44 | AN27: =SUM(AN7:AN26) -> 51679.095 | AQ27: =SUM(AQ7:AQ26) -> 0 | AR27: =SUM(AR7:AR26) -> 0 | AS27: =SUM(AS7:AS26) -> 0 | AV27: =SUM(AV7:AV26) -> 0 | AW27: =SUM(AW7:AW26) -> 0 | AX27: =SUM(AX7:AX26) -> 0 | BA27: =SUM(BA7:BA26) -> 0 | BB27: =SUM(BB7:BB26) -> 0 | BC27: =SUM(BC7:BC26) -> 0 | BF27: =SUM(BF7:BF26) -> 0 | BG27: =SUM(BG7:BG26) -> 0 | BH27: =SUM(BH7:BH26) -> 0 | BL27: =SUM(BL7:BL26) -> 2561832.7 | BM27: =SUM(BM7:BM26) -> 2481097.1 | BN27: =SUM(BN7:BN26) -> -80735.586
C29: 312325 | D29: 291102.04 | E29: -21222.96 | H29: 312325 | I29: 299610.01 | J29: -12714.99 | M29: 312627 | N29: 312627 | O29: 312627 | R29: 312693 | S29: 332747.86 | T29: 20054.86 | W29: 312693 | X29: 320499.89 | Y29: 7806.89 | AB29: 312851 | AC29: 274868.38 | AD29: -37982.62 | AG29: 340807 | AH29: 212581.81 | AI29: -128225.19 | AL29: 345519 | AM29: 397197.44 | AN29: 51678.44 | BL29: 2561840 | BM29: 2481097.1 | BN29: -80742.9
AB30: =AB29-AB27 -> 0.90904947 | AC30: =AC29-AC27 -> 0 | AD30: =AD29-AD27 -> -0.90904947 | AG30: =AG29-AG27 -> 0.60479938 | AH30: =AH29-AH27 -> 0 | AI30: =AI29-AI27 -> -0.60479938 | AL30: =AL29-AL27 -> 0.65479938 | AM30: =AM29-AM27 -> 0 | AN30: =AN29-AN27 -> -0.65479938
C31: =C29-C27 -> 1.4190495 | D31: =D29-D27 -> 0 | E31: =E29-E27 -> -1.4190495 | H31: =H29-H27 -> 1.4190495 | I31: =I29-I27 -> 0 | J31: =J29-J27 -> -1.4190495 | M31: =M29-M27 -> 0.90904947 | N31: =N29-N27 -> -39862.67 | O31: =O29-O27 -> 272763.42 | R31: =R29-R27 -> 0.69904947 | S31: =S29-S27 -> 0 | T31: =T29-T27 -> -0.69904947 | W31: =W29-W27 -> 0.69904947 | X31: =X29-X27 -> 0 | Y31: =Y29-Y27 -> -0.69904947 | BL31: =BL29-BL27 -> 7.3138956 | BM31: =BM29-BM27 -> 0 | BN31: =BN29-BN27 -> -7.3138956

Sheet Final Data
A3: Row Labels | B3: Sum of JAN | C3: Sum of FEB | D3: Sum of MARCH | E3: Sum of APRIL | F3: Sum of MAY | G3: Sum of JUNE | H3: Sum of JULY | I3: Sum of AUGUST | J3: Sum of SEPT | K3: Sum of OCT | L3: Sum of NOV | M3: Sum of DEC
A4: ABC STORE #75 | B4: 51551.472 | C4: 51551.472 | D4: 51551.472 | E4: 51551.472 | F4: 51551.472 | G4: 51551.472 | H4: 51551.472 | I4: 51551.472 | J4: 51551.472 | K4: 51551.472 | L4: 51551.472 | M4: 51551.472
A5: BIG ISLAND RUNNING CO. | B5: 5337.6526 | C5: 5337.6526 | D5: 5337.6526 | E5: 5337.6526 | F5: 5337.6526 | G5: 5337.6526 | H5: 5337.6526 | I5: 5337.6526 | J5: 5337.6526 | K5: 5337.6526 | L5: 5418.7626 | M5: 5418.7626
A6: BOWLS SUPERFOODS & ORALE TACOS | B6: 0 | C6: 0 | D6: 0 | E6: 0 | F6: 0 | G6: 0 | H6: 0 | I6: 0 | J6: 0 | K6: 0 | L6: 0 | M6: 19500
A7: CAFE KONA | B7: 7048.3605 | C7: 7048.3605 | D7: 7048.3605 | E7: 7048.3605 | F7: 7048.3605 | G7: 7048.3605 | H7: 7048.3605 | I7: 7048.3605 | J7: 7048.3605 | K7: 7048.3605 | L7: 7048.3605 | M7: 7048.3605
A8: FOSTERS KITCHEN | B8: 23777.974 | C8: 23777.974 | D8: 23777.974 | E8: 23777.974 | F8: 23777.974 | G8: 23777.974 | H8: 24135.144 | I8: 28635.144 | J8: 28635.144 | K8: 28635.144 | L8: 28635.144 | M8: 28635.144
A9: GECKO GIRLZ SHAVE ICE SHACK | B9: 5131.7697 | C9: 5131.7697 | D9: 5131.7697 | E9: 5131.7697 | F9: 5131.7697 | G9: 5207.6097 | H9: 5134.2097 | I9: 5134.2097 | J9: 5134.2097 | K9: 5134.2097 | L9: 5134.2097 | M9: 5134.2097
A10: GYPSEA GALATO | B10: 5210.2925 | C10: 5210.2925 | D10: 5210.2925 | E10: 5210.2925 | F10: 5210.2925 | G10: 5292.2425 | H10: 5292.2425 | I10: 5292.2425 | J10: 5292.2425 | K10: 5292.2425 | L10: 5292.2425 | M10: 5292.2425
A11: HUMPYS BIG ISLAND ALEHOUSE | B11: 27656.092 | C11: 27656.092 | D11: 27656.092 | E11: 27656.092 | F11: 27656.092 | G11: 27656.092 | H11: 27656.092 | I11: 27656.092 | J11: 57691.574 | K11: 57691.574 | L11: 57691.574 | M11: 57691.574
A12: ISLAND LAVA JAVA | B12: 48921.183 | C12: 48921.183 | D12: 48921.183 | E12: 48921.183 | F12: 48921.183 | G12: 48921.183 | H12: 48921.183 | I12: 48921.183 | J12: 48921.183 | K12: 48921.183 | L12: 48921.183 | M12: 48921.183
A13: JACKS DIVE LOCKER | B13: 35662.42 | C13: 35662.42 | D13: 35662.42 | E13: 35662.42 | F13: 35662.42 | G13: 35662.42 | H13: 35662.42 | I13: 35662.42 | J13: 35662.42 | K13: 35662.42 | L13: 36539.44 | M13: 36539.44
A14: KANAKA KAVA | B14: 3199.3324 | C14: 3199.3324 | D14: 3199.3324 | E14: 3261.1324 | F14: 3261.1324 | G14: 3261.1324 | H14: 3261.1324 | I14: 3261.1324 | J14: 3261.1324 | K14: 3261.1324 | L14: 3261.1324 | M14: 3261.1324
A15: KONA GEAR INC. | B15: 12110.162 | C15: 12110.162 | D15: 12110.162 | E15: 12114.572 | F15: 12114.572 | G15: 12114.572 | H15: 12114.572 | I15: 12114.572 | J15: 12114.572 | K15: 12114.572 | L15: 12114.572 | M15: 12114.572
... A20: TAKA SUSHI | B20: 7276.4982 | C20: 7276.4982 | D20: 7276.4982 | E20: 7276.4982 | F20: 7276.4982 | G20: 7276.4982 | H20: 7276.4982 | I20: 7276.4982 | J20: 7276.4982 | K20: 7276.4982 | L20: 7276.4982 | M20: 7276.4982
A21: (blank)
A22: Grand Total | B22: 278736.18 | C22: 278736.18 | D22: 279038.69 | E22: 279104.9 | F22: 279104.9 | G22: 279262.69 | H22: 307219 | I22: 311719 | J22: 341754.48 | K22: 341754.48 | L22: 342712.61 | M22: 362212.61
B24: 278736.18 | C24: 278736.18 | D24: 279038.69 | E24: 279104.9 | F24: 279104.9 | G24: 279262.69 | H24: 307219 | I24: 311719 | J24: 341754.48 | K24: 341754.48 | L24: 342712.61 | M24: 362212.61
A26: =Summ.!B16 -> Parking Income (PKG) | B26: =Summ.!C16 -> 30000 | C26: =Summ.!D16 -> 30000 | D26: =Summ.!E16 -> 30000 | E26: =Summ.!F16 -> 30000 | F26: =Summ.!G16 -> 30000 | G26: =Summ.!H16 -> 30000 | H26: =Summ.!I16 -> 30000 | ... M26: =Summ.!N16 -> 50000
A27: ='Excise Tax'!A32 -> Percentage Rent Excise Tax | B27: ='Excise Tax'!E32 -> 2067.4545 | C27: ='Excise Tax'!F32 -> 2067.4545 | D27: ='Excise Tax'!G32 -> 2067.4545 | E27: ='Excise Tax'!H32 -> 2067.4545 | F27: ='Excise Tax'!I32 -> 2067.4545 | G27: ='Excise Tax'!J32 -> 2067.4545 | H27: ='Excise Tax'!K32 -> 2067.4545 | I27: ='Excise Tax'!L32 -> 2279.4045 | ... M27: ='Excise Tax'!P32 -> 2420.7045
A28: =Summ.!B24 -> Miscellaneous Income | B28: =Summ.!C24 -> 2500 | C28: =Summ.!D24 -> 2500 | D28: =Summ.!E24 -> 2500 | E28: =Summ.!F24 -> 2500 | F28: =Summ.!G24 -> 2500 | G28: =Summ.!H24 -> 2500 | H28: =Summ.!I24 -> 2500 | ... M28: =Summ.!N24 -> 2500
A29: ='Rent Recovery'!A45 -> Excise Tax | B29: ='Rent Recovery'!E45 -> 19.936001 | C29: ='Rent Recovery'!F45 -> 19.936001 | D29: ='Rent Recovery'!G45 -> 19.936001 | E29: ='Rent Recovery'!H45 -> 19.936001 | F29: ='Rent Recovery'!I45 -> 19.936001 | G29: ='Rent Recovery'!J45 -> 19.936001 | H29: ='Rent Recovery'!K45 -> 19.936001 | I29: ='Rent Recovery'!L45 -> 19.936001 | ... M29: ='Rent Recovery'!P45 -> 19.936001
A31: Final Total | B31: =SUM(B24:B29) -> 313323.57 | C31: =SUM(C24:C29) -> 313323.57 | D31: =SUM(D24:D29) -> 313626.08 | E31: =SUM(E24:E29) -> 313692.29 | F31: =SUM(F24:F29) -> 313692.29 | G31: =SUM(G24:G29) -> 313850.08 | H31: =SUM(H24:H29) -> 341806.39 | I31: =SUM(I24:I29) -> 346518.34 | ... M31: =SUM(M24:M29) -> 417153.25
A33: Summary | B33: =Summ.!C30 -> 313323.57 | C33: =Summ.!D30 -> 313323.57 | D33: =Summ.!E30 -> 313626.08 | E33: =Summ.!F30 -> 313692.29 | F33: =Summ.!G30 -> 313692.29 | G33: =Summ.!H30 -> 313850.08 | H33: =Summ.!I30 -> 341806.39 | I33: =Summ.!J30 -> 346518.34 | ... M33: =Summ.!N30 -> 417153.25
A35: Difference | B35: =B33-B31 -> 0 | C35: =C33-C31 -> 0 | D35: =D33-D31 -> 0 | E35: =E33-E31 -> 0 | F35: =F33-F31 -> 0 | G35: =G33-G31 -> 0 | H35: =H33-H31 -> 0 | I35: =I33-I31 -> 0 | ... M35: =M33-M31 -> 0
I38: =I31-H31 -> 4711.95
I39: -4500

Sheet Pivot
A3: Row Labels | B3: Sum of JAN | C3: Sum of FEB | D3: Sum of MARCH | E3: Sum of APRIL | F3: Sum of MAY | G3: Sum of JUNE | H3: Sum of JULY | I3: Sum of AUGUST | J3: Sum of SEPT | K3: Sum of OCT | L3: Sum of NOV | M3: Sum of DEC
A4: ABC STORE #75 | B4: 51551.472 | C4: 51551.472 | D4: 51551.472 | E4: 51551.472 | F4: 51551.472 | G4: 51551.472 | H4: 51551.472 | I4: 51551.472 | J4: 51551.472 | K4: 51551.472 | L4: 51551.472 | M4: 51551.472
A5: BIG ISLAND RUNNING CO. | B5: 5337.6526 | C5: 5337.6526 | D5: 5337.6526 | E5: 5337.6526 | F5: 5337.6526 | G5: 5337.6526 | H5: 5337.6526 | I5: 5337.6526 | J5: 5337.6526 | K5: 5337.6526 | L5: 5418.7626 | M5: 5418.7626
A6: BOWLS SUPERFOODS & ORALE TACOS | B6: 0 | C6: 0 | D6: 0 | E6: 0 | F6: 0 | G6: 0 | H6: 0 | I6: 0 | J6: 0 | K6: 0 | L6: 0 | M6: 19500
A7: CAFE KONA | B7: 7048.3605 | C7: 7048.3605 | D7: 7048.3605 | E7: 7048.3605 | F7: 7048.3605 | G7: 7048.3605 | H7: 7048.3605 | I7: 7048.3605 | J7: 7048.3605 | K7: 7048.3605 | L7: 7048.3605 | M7: 7048.3605
A8: FOSTERS KITCHEN | B8: 23777.974 | C8: 23777.974 | D8: 23777.974 | E8: 23777.974 | F8: 23777.974 | G8: 23777.974 | H8: 24135.144 | I8: 28635.144 | J8: 28635.144 | K8: 28635.144 | L8: 28635.144 | M8: 28635.144
A9: GECKO GIRLZ SHAVE ICE SHACK | B9: 5131.7697 | C9: 5131.7697 | D9: 5131.7697 | E9: 5131.7697 | F9: 5131.7697 | G9: 5207.6097 | H9: 5134.2097 | I9: 5134.2097 | J9: 5134.2097 | K9: 5134.2097 | L9: 5134.2097 | M9: 5134.2097
A10: GYPSEA GALATO | B10: 5210.2925 | C10: 5210.2925 | D10: 5210.2925 | E10: 5210.2925 | F10: 5210.2925 | G10: 5292.2425 | H10: 5292.2425 | I10: 5292.2425 | J10: 5292.2425 | K10: 5292.2425 | L10: 5292.2425 | M10: 5292.2425
A11: HUMPYS BIG ISLAND ALEHOUSE | B11: 27656.092 | C11: 27656.092 | D11: 27656.092 | E11: 27656.092 | F11: 27656.092 | G11: 27656.092 | H11: 27656.092 | I11: 27656.092 | J11: 57691.574 | K11: 57691.574 | L11: 57691.574 | M11: 57691.574
A12: ISLAND LAVA JAVA | B12: 48921.183 | C12: 48921.183 | D12: 48921.183 | E12: 48921.183 | F12: 48921.183 | G12: 48921.183 | H12: 48921.183 | I12: 48921.183 | J12: 48921.183 | K12: 48921.183 | L12: 48921.183 | M12: 48921.183
A13: JACKS DIVE LOCKER | B13: 35662.42 | C13: 35662.42 | D13: 35662.42 | E13: 35662.42 | F13: 35662.42 | G13: 35662.42 | H13: 35662.42 | I13: 35662.42 | J13: 35662.42 | K13: 35662.42 | L13: 36539.44 | M13: 36539.44
A14: KANAKA KAVA | B14: 3199.3324 | C14: 3199.3324 | D14: 3199.3324 | E14: 3261.1324 | F14: 3261.1324 | G14: 3261.1324 | H14: 3261.1324 | I14: 3261.1324 | J14: 3261.1324 | K14: 3261.1324 | L14: 3261.1324 | M14: 3261.1324
A15: KONA GEAR INC. | B15: 12110.162 | C15: 12110.162 | D15: 12110.162 | E15: 12114.572 | F15: 12114.572 | G15: 12114.572 | H15: 12114.572 | I15: 12114.572 | J15: 12114.572 | K15: 12114.572 | L15: 12114.572 | M15: 12114.572
... A20: TAKA SUSHI | B20: 7276.4982 | C20: 7276.4982 | D20: 7276.4982 | E20: 7276.4982 | F20: 7276.4982 | G20: 7276.4982 | H20: 7276.4982 | I20: 7276.4982 | J20: 7276.4982 | K20: 7276.4982 | L20: 7276.4982 | M20: 7276.4982
A21: (blank)
A22: Grand Total | B22: 278736.18 | C22: 278736.18 | D22: 279038.69 | E22: 279104.9 | F22: 279104.9 | G22: 279262.69 | H22: 307219 | I22: 311719 | J22: 341754.48 | K22: 341754.48 | L22: 342712.61 | M22: 362212.61

Sheet DATA
A1: TENANT | B1: Particular | C1: JAN | D1: FEB | E1: MARCH | F1: APRIL | G1: ` | H1: JUNE | I1: JULY | J1: AUGUST | K1: SEPT | L1: OCT | M1: NOV | N1: DEC
A2: ISLAND LAVA JAVA | B2: ESTIMATED BASE RENT | C2: 15803.54 | D2: 15803.54 | E2: 15803.54 | F2: 15803.54 | G2: 15803.54 | H2: 15803.54 | I2: 15803.54 | J2: 15803.54 | K2: 15803.54 | L2: 15803.54 | M2: 15803.54 | N2: 15803.54
A3: TAKA SUSHI | B3: ESTIMATED BASE RENT | C3: 3383.1 | D3: 3383.1 | E3: 3383.1 | F3: 3383.1 | G3: 3383.1 | H3: 3383.1 | I3: 3383.1 | J3: 3383.1 | K3: 3383.1 | L3: 3383.1 | M3: 3383.1 | N3: 3383.1
A4: KANAKA KAVA | B4: ESTIMATED BASE RENT | C4: 2060 | D4: 2060 | E4: 2060 | F4: 2121.8 | G4: 2121.8 | H4: 2121.8 | I4: 2121.8 | J4: 2121.8 | K4: 2121.8 | L4: 2121.8 | M4: 2121.8 | N4: 2121.8
A5: GECKO GIRLZ SHAVE ICE SHACK | B5: ESTIMATED BASE RENT | C5: 2527.84 | D5: 2527.84 | E5: 2527.84 | F5: 2527.84 | G5: 2527.84 | H5: 2603.68 | I5: 2530.28 | J5: 2530.28 | K5: 2530.28 | L5: 2530.28 | M5: 2530.28 | N5: 2530.28
A6: BIG ISLAND RUNNING CO. | B6: ESTIMATED BASE RENT | C6: 2703.75 | D6: 2703.75 | E6: 2703.75 | F6: 2703.75 | G6: 2703.75 | H6: 2703.75 | I6: 2703.75 | J6: 2703.75 | K6: 2703.75 | L6: 2703.75 | M6: 2784.86 | N6: 2784.86
A7: CAFE KONA | B7: ESTIMATED BASE RENT | C7: 3826.9 | D7: 3826.9 | E7: 3826.9 | F7: 3826.9 | G7: 3826.9 | H7: 3826.9 | I7: 3826.9 | J7: 3826.9 | K7: 3826.9 | L7: 3826.9 | M7: 3826.9 | N7: 3826.9
A8: LUCASIE LTD | B8: ESTIMATED BASE RENT | C8: 7593 | D8: 7593 | E8: 7895.51 | F8: 7895.51 | G8: 7895.51 | H8: 7895.51 | I8: 7895.51 | J8: 7895.51 | K8: 7895.51 | L8: 7895.51 | M8: 7895.51 | N8: 7895.51
A9: FOSTERS KITCHEN | B9: ESTIMATED BASE RENT | C9: 11905.63 | D9: 11905.63 | E9: 11905.63 | F9: 11905.63 | G9: 11905.63 | H9: 11905.63 | I9: 12262.8 | J9: 12262.8 | K9: 12262.8 | L9: 12262.8 | M9: 12262.8 | N9: 12262.8
A10: HUMPYS BIG ISLAND ALEHOUSE | B10: ESTIMATED BASE RENT | C10: 25000 | D10: 25000 | E10: 25000 | F10: 25000 | G10: 25000 | H10: 25000 | I10: 25000 | J10: 25000 | K10: 20666.8 | L10: 20666.8 | M10: 20666.8 | N10: 20666.8
A11: ABC STORE #75 | B11: ESTIMATED BASE RENT | C11: 24000 | D11: 24000 | E11: 24000 | F11: 24000 | G11: 24000 | H11: 24000 | I11: 24000 | J11: 24000 | K11: 24000 | L11: 24000 | M11: 24000 | N11: 24000
A12: GYPSEA GALATO | B12: ESTIMATED BASE RENT | C12: 2731.82 | D12: 2731.82 | E12: 2731.82 | F12: 2731.82 | G12: 2731.82 | H12: 2813.77 | I12: 2813.77 | J12: 2813.77 | K12: 2813.77 | L12: 2813.77 | M12: 2813.77 | N12: 2813.77
A13: OCEANS SPORTS BAR AND GRILL | B13: ESTIMATED BASE RENT | C13: 10049.12 | D13: 10049.12 | E13: 10049.12 | F13: 10049.12 | G13: 10049.12 | H13: 10049.12 | I13: 10049.12 | J13: 10049.12 | K13: 10049.12 | L13: 10049.12 | M13: 10049.12 | N13: 10049.12
... A15: QPOT | B15: ESTIMATED BASE RENT | C15: 0 | D15: 0 | E15: 0 | F15: 0 | G15: 0 | H15: 0 | I15: 13000 | J15: 13000 | K15: 13000 | L15: 13000 | M15: 13000 | N15: 13000
A16: BOWLS SUPERFOODS & ORALE TACOS | B16: ESTIMATED BASE RENT | D16: 0 | E16: 0 | F16: 0 | G16: 0 | H16: 0 | J16: 0 | K16: 0 | L16: 0 | M16: 0 | N16: 19500
A17: KONA GEAR INC. | B17: ESTIMATED BASE RENT | C17: 6440.59 | D17: 6440.59 | E17: 6440.59 | F17: 6445 | G17: 6445 | H17: 6445 | I17: 6445 | J17: 6445 | K17: 6445 | L17: 6445 | M17: 6445 | N17: 6445
A18: LAVERNES | B18: ESTIMATED BASE RENT | C18: 7408 | D18: 7408 | E18: 7408 | F18: 7408 | G18: 7408 | H18: 7408 | I18: 7408 | J18: 7408 | K18: 7408 | L18: 7408 | M18: 7408 | N18: 7408
A19: TAKA SUSHI | B19: Rent Recovery | C19: 423.09 | D19: 423.09 | E19: 423.09 | F19: 423.09 | G19: 423.09 | H19: 423.09 | I19: 423.09 | J19: 423.09 | K19: 423.09 | L19: 423.09 | M19: 423.09 | N19: 423.09
A20: ISLAND LAVA JAVA | B20: COMMON AREA MAINTENANCE | C20: 6087.6782 | D20: 6087.6782 | E20: 6087.6782 | F20: 6087.6782 | G20: 6087.6782 | H20: 6087.6782 | I20: 6087.6782 | J20: 6087.6782 | K20: 6087.6782 | L20: 6087.6782 | M20: 6087.6782 | N20: 6087.6782
A21: TAKA SUSHI | B21: COMMON AREA MAINTENANCE | C21: 1688.1401 | D21: 1688.1401 | E21: 1688.1401 | F21: 1688.1401 | G21: 1688.1401 | H21: 1688.1401 | I21: 1688.1401 | J21: 1688.1401 | K21: 1688.1401 | L21: 1688.1401 | M21: 1688.1401 | N21: 1688.1401
A22: KANAKA KAVA | B22: COMMON AREA MAINTENANCE | C22: 314.365 | D22: 314.365 | E22: 314.365 | F22: 314.365 | G22: 314.365 | H22: 314.365 | I22: 314.365 | J22: 314.365 | K22: 314.365 | L22: 314.365 | M22: 314.365 | N22: 314.365
A23: GECKO GIRLZ SHAVE ICE SHACK | B23: COMMON AREA MAINTENANCE | C23: 814.20535 | D23: 814.20535 | E23: 814.20535 | F23: 814.20535 | G23: 814.20535 | H23: 814.20535 | I23: 814.20535 | J23: 814.20535 | K23: 814.20535 | L23: 814.20535 | M23: 814.20535 | N23: 814.20535
A24: BIG ISLAND RUNNING CO. | B24: COMMON AREA MAINTENANCE | C24: 825.20813 | D24: 825.20813 | E24: 825.20813 | F24: 825.20813 | G24: 825.20813 | H24: 825.20813 | I24: 825.20813 | J24: 825.20813 | K24: 825.20813 | L24: 825.20813 | M24: 825.20813 | N24: 825.20813
A25: CAFE KONA | B25: COMMON AREA MAINTENANCE | C25: 1562.3941 | D25: 1562.3941 | E25: 1562.3941 | F25: 1562.3941 | G25: 1562.3941 | H25: 1562.3941 | I25: 1562.3941 | J25: 1562.3941 | K25: 1562.3941 | L25: 1562.3941 | M25: 1562.3941 | N25: 1562.3941
A26: LUCASIE LTD | B26: COMMON AREA MAINTENANCE | C26: 1639.4135 | D26: 1639.4135 | E26: 1639.4135 | F26: 1639.4135 | G26: 1639.4135 | H26: 1639.4135 | I26: 1639.4135 | J26: 1639.4135 | K26: 1639.4135 | L26: 1639.4135 | M26: 1639.4135 | N26: 1639.4135
A27: FOSTERS KITCHEN | B27: COMMON AREA MAINTENANCE | C27: 5542.255 | D27: 5542.255 | E27: 5542.255 | F27: 5542.255 | G27: 5542.255 | H27: 5542.255 | I27: 5542.255 | J27: 5542.255 | K27: 5542.255 | L27: 5542.255 | M27: 5542.255 | N27: 5542.255
A28: HUMPYS BIG ISLAND ALEHOUSE | B28: COMMON AREA MAINTENANCE | C28: 0 | D28: 0 | E28: 0 | F28: 0 | G28: 0 | H28: 0 | I28: 0 | J28: 0 | K28: 16875.113 | L28: 16875.113 | M28: 16875.113 | N28: 16875.113
... A145: LUCASIE LTD | B145: ESTIMATED PERCENTAGE RENT | C145: 0 | D145: 0 | E145: 0 | F145: 0 | G145: 0 | H145: 0 | I145: 0 | J145: 0 | K145: 0 | L145: 0 | M145: 0 | N145: 0
A146: FOSTERS KITCHEN | B146: ESTIMATED PERCENTAGE RENT | D146: 0 | E146: 0 | F146: 0 | G146: 0 | H146: 0 | J146: 4500 | K146: 4500 | L146: 4500 | M146: 4500 | N146: 4500
A147: HUMPYS BIG ISLAND ALEHOUSE | B147: ESTIMATED PERCENTAGE RENT | C147: 0 | D147: 0 | E147: 0 | F147: 0 | G147: 0 | H147: 0 | I147: 0 | K147: 3000 | L147: 3000 | M147: 3000 | N147: 3000
A148: ABC STORE #75 | B148: ESTIMATED PERCENTAGE RENT | C148: 18000 | D148: 18000 | E148: 18000 | F148: 18000 | G148: 18000 | H148: 18000 | I148: 18000 | J148: 18000 | K148: 18000 | L148: 18000 | M148: 18000 | N148: 18000
A149: GYPSEA GALATO | B149: ESTIMATED PERCENTAGE RENT | C149: 820 | D149: 820 | E149: 820 | F149: 820 | G149: 820 | H149: 820 | I149: 820 | J149: 820 | K149: 820 | L149: 820 | M149: 820 | N149: 820
A150: OCEANS SPORTS BAR AND GRILL | B150: ESTIMATED PERCENTAGE RENT | C150: 0 | D150: 0 | E150: 0 | F150: 0 | G150: 0 | H150: 0 | I150: 0 | J150: 0 | K150: 0 | L150: 0 | M150: 0 | N150: 0
A151: JACKS DIVE LOCKER | B151: ESTIMATED PERCENTAGE RENT | C151: 0 | D151: 0 | E151: 0 | F151: 0 | G151: 0 | H151: 0 | I151: 0 | J151: 0 | K151: 0 | L151: 0 | M151: 0 | N151: 0
A152: QPOT | B152: ESTIMATED PERCENTAGE RENT | E152: 0 | H152: 0 | K152: 0 | N152: 0
A153: BOWLS SUPERFOODS & ORALE TACOS | B153: ESTIMATED PERCENTAGE RENT | C153: 0 | D153: 0 | E153: 0 | F153: 0 | G153: 0 | H153: 0 | I153: 0 | J153: 0 | K153: 0 | L153: 0 | M153: 0 | N153: 0
A154: KONA GEAR INC. | B154: ESTIMATED PERCENTAGE RENT | C154: 3000 | D154: 3000 | E154: 3000 | F154: 3000 | G154: 3000 | H154: 3000 | I154: 3000 | J154: 3000 | K154: 3000 | L154: 3000 | M154: 3000 | N154: 3000
A155: LAVERNES | B155: ESTIMATED PERCENTAGE RENT | C155: 0 | D155: 0 | E155: 0 | F155: 0 | G155: 0 | H155: 0 | I155: 0 | J155: 0 | K155: 0 | L155: 0 | M155: 0 | N155: 0

Sheet Summ.
R1: Date Revised:
A2: ATHENA PROPERTY MANAGEMENT
A3: Coconut Grove - Kona Hawaii
A4: PROJECT NO. 165
A5: 01/01/26- 12/31/26
A6: 2026 OPERATING BUDGET
A8: GL | O8: 2026 TOTALS | P8: 2025 | Q8: 2025 | S8: % +/- from 2025
A9: CODE | B9: DESCRIPTION | C9: JAN | D9: FEB | E9: MARCH | F9: APRIL | G9: MAY | H9: JUNE | I9: JULY | J9: AUGUST | K9: SEPT | L9: OCT | M9: NOV | N9: DEC | P9: Forecast | Q9: Budget | R9: Variance | T9: NOTES
P10: Totals | Q10: Totals
B12: INCOME
A13: 40100 | B13: Base Rent | C13: =Rent!F33 -> 148820.58 | D13: =Rent!G33 -> 148820.58 | E13: =Rent!H33 -> 149123.09 | F13: =Rent!I33 -> 149189.3 | G13: =Rent!J33 -> 149189.3 | H13: =Rent!K33 -> 149347.09 | I13: =Rent!L33 -> 162630.86 | J13: =Rent!M33 -> 162630.86 | ... N13: =Rent!Q33 -> 178755.79 | O13: =SUM(C13:N13) -> 1874358.6 | P13: 1722677 | Q13: 1782656 | R13: =+O13-P13 -> 151681.56 | S13: =(O13-Q13)/Q13 -> 0.051441534
A14: 40106 | B14: Rent Recovery | C14: ='Rent Recovery'!E38 -> 423.09 | D14: ='Rent Recovery'!F38 -> 423.09 | E14: ='Rent Recovery'!G38 -> 423.09 | F14: ='Rent Recovery'!H38 -> 423.09 | G14: ='Rent Recovery'!I38 -> 423.09 | H14: ='Rent Recovery'!J38 -> 423.09 | I14: ='Rent Recovery'!K38 -> 423.09 | J14: ='Rent Recovery'!L38 -> 423.09 | ... N14: ='Rent Recovery'!P38 -> 423.09 | O14: =SUM(C14:N14) -> 5077.08 | P14: 5077 | Q14: 5076 | S14: =(O14-Q14)/Q14 -> 0.00021276596
A15: 40110 | B15: Percentage Rent | C15: ='% Rent'!E36 -> 43895 | D15: ='% Rent'!F36 -> 43895 | E15: ='% Rent'!G36 -> 43895 | F15: ='% Rent'!H36 -> 43895 | G15: ='% Rent'!I36 -> 43895 | H15: ='% Rent'!J36 -> 43895 | I15: ='% Rent'!K36 -> 43895 | J15: ='% Rent'!L36 -> 48395 | ... N15: ='% Rent'!P36 -> 51395 | O15: =SUM(C15:N15) -> 561240 | P15: 609190 | Q15: 673152 | R15: =+O15-P15 -> -47950 | S15: =(O15-Q15)/Q15 -> -0.16625071 | T15: Need percentage
A16: 40129 | B16: Parking Income (PKG) | C16: 30000 | D16: =C16 -> 30000 | E16: =D16 -> 30000 | F16: =E16 -> 30000 | G16: =F16 -> 30000 | H16: =G16 -> 30000 | I16: =H16 -> 30000 | J16: =I16 -> 30000 | K16: 50000 | L16: =K16 -> 50000 | M16: =L16 -> 50000 | N16: =M16 -> 50000 | O16: =SUM(C16:N16) -> 440000 | P16: 344359 | Q16: 549996 | R16: =+O16-P16 -> 95641 | S16: =(O16-Q16)/Q16 -> -0.19999418 | T16: Based off of 2025 actuals
A17: 40143 | B17: CAM Recovery | C17: ='CAM Recovery'!E17 -> 0 | D17: ='CAM Recovery'!F17 -> 0 | E17: ='CAM Recovery'!G17 -> 0 | F17: ='CAM Recovery'!H17 -> 0 | G17: ='CAM Recovery'!I17 -> 0 | H17: ='CAM Recovery'!J17 -> 0 | I17: ='CAM Recovery'!K17 -> 0 | J17: ='CAM Recovery'!L17 -> 0 | ... N17: ='CAM Recovery'!P17 -> 0 | O17: =SUM(C17:N17) -> 0 | S17: =(O17-Q17)/Q17 -> #DIV/0!
A18: 40140 | B18: Common Area Collections (CAMS) | C18: =CAM!E33 -> 42081.776 | D18: =CAM!F33 -> 42081.776 | E18: =CAM!G33 -> 42081.776 | F18: =CAM!H33 -> 42081.776 | G18: =CAM!I33 -> 42081.776 | H18: =CAM!J33 -> 42081.776 | I18: =CAM!K33 -> 48580.862 | J18: =CAM!L33 -> 48580.862 | ... N18: =CAM!P33 -> 65455.975 | O18: =SUM(C18:N18) -> 611476.28 | P18: 768194 | Q18: 980252 | R18: =+O18-P18 -> -156717.72 | S18: =(O18-Q18)/Q18 -> -0.37620502
A19: 40150 | B19: Prior Year CAMS | C19: 0 | D19: 0 | E19: 0 | F19: 0 | G19: 0 | H19: 0 | I19: 0 | J19: 0 | K19: 0 | L19: 0 | M19: 0 | N19: 0 | O19: =SUM(C19:N19) -> 0 | P19: 41626 | R19: =+O19-P19 -> -41626 | S19: =(O19-Q19)/Q19 -> #DIV/0! | T19: as of 09/22 OPX over budget by $160k. Estimate for management fee discount as done in 2021 PYC.
A20: 40170 | B20: Building Recoveries | C20: ='Building Exp.'!E33 -> 4016.0574 | D20: ='Building Exp.'!F33 -> 4016.0574 | E20: ='Building Exp.'!G33 -> 4016.0574 | F20: ='Building Exp.'!H33 -> 4016.0574 | G20: ='Building Exp.'!I33 -> 4016.0574 | H20: ='Building Exp.'!J33 -> 4016.0574 | I20: ='Building Exp.'!K33 -> 4016.0574 | J20: ='Building Exp.'!L33 -> 4016.0574 | ... N20: ='Building Exp.'!P33 -> 6595.6558 | O20: =SUM(C20:N20) -> 58511.083 | P20: 91042 | Q20: 118234 | R20: =+O20-P20 -> -32530.917 | S20: =(O20-Q20)/Q20 -> -0.50512473
A21: 40180 | B21: Food Court | C21: ='Food Court'!E33 -> 7051.1113 | D21: ='Food Court'!F33 -> 7051.1113 | E21: ='Food Court'!G33 -> 7051.1113 | F21: ='Food Court'!H33 -> 7051.1113 | G21: ='Food Court'!I33 -> 7051.1113 | H21: ='Food Court'!J33 -> 7051.1113 | I21: ='Food Court'!K33 -> 9702.6718 | J21: ='Food Court'!L33 -> 9702.6718 | ... N21: ='Food Court'!P33 -> 14082.234 | O21: =SUM(C21:N21) -> 118040.95 | P21: 101411 | Q21: 135136 | R21: =+O21-P21 -> 16629.946 | S21: =(O21-Q21)/Q21 -> -0.12650259
A22: 40230 | B22: Insurance Income | C22: =Ins.!F33 -> 8139.0591 | D22: =Ins.!G33 -> 8139.0591 | E22: =Ins.!H33 -> 8139.0591 | F22: =Ins.!I33 -> 8139.0591 | G22: =Ins.!J33 -> 8139.0591 | H22: =Ins.!K33 -> 8139.0591 | I22: =Ins.!L33 -> 10677.984 | J22: =Ins.!M33 -> 10677.984 | ... N22: =Ins.!Q33 -> 14871.506 | O22: =SUM(C22:N22) -> 129676.35 | P22: 168681 | Q22: 213510 | R22: =+O22-P22 -> -39004.653 | S22: =(O22-Q22)/Q22 -> -0.39264509
A23: 40240 | B23: Property Tax Income | C23: ='RE Tax'!E33 -> 9593.5322 | D23: ='RE Tax'!F33 -> 9593.5322 | E23: ='RE Tax'!G33 -> 9593.5322 | F23: ='RE Tax'!H33 -> 9593.5322 | G23: ='RE Tax'!I33 -> 9593.5322 | H23: ='RE Tax'!J33 -> 9593.5322 | I23: ='RE Tax'!K33 -> 11616.237 | J23: ='RE Tax'!L33 -> 11616.237 | ... N23: ='RE Tax'!P33 -> 14957.122 | O23: =SUM(C23:N23) -> 140622.16 | P23: 152409 | Q23: 185396 | R23: =+O23-P23 -> -11786.844 | S23: =(O23-Q23)/Q23 -> -0.24150383
A24: 40250 | B24: Miscellaneous Income | C24: =Rent!D37 -> 2500 | D24: =Rent!E37 -> 2500 | E24: =Rent!F37 -> 2500 | F24: =Rent!G37 -> 2500 | G24: =Rent!H37 -> 2500 | H24: =Rent!I37 -> 2500 | I24: =Rent!J37 -> 2500 | J24: =Rent!K37 -> 2500 | ... N24: =Rent!O37 -> 2500 | O24: =SUM(C24:N24) -> 30000 | P24: 500 | R24: =+O24-P24 -> 29500 | S24: =(O24-Q24)/Q24 -> #DIV/0! | T24: ABC STORAGE UNIT
A25: 40600 | B25: Late Charge Income | C25: 0 | D25: 0 | E25: 0 | F25: 0 | G25: 0 | H25: 0 | I25: 0 | J25: 0 | K25: 0 | L25: 0 | M25: 0 | N25: 0 | O25: =SUM(C25:N25) -> 0 | R25: =+O25-P25 -> 0 | S25: =(O25-Q25)/Q25 -> #DIV/0!
A26: 40300 | B26: Promo Fee (Marketing Income) | C26: =Marketing!E33 -> 2755.67 | D26: =Marketing!F33 -> 2755.67 | E26: =Marketing!G33 -> 2755.67 | F26: =Marketing!H33 -> 2755.67 | G26: =Marketing!I33 -> 2755.67 | H26: =Marketing!J33 -> 2755.67 | I26: =Marketing!K33 -> 3055.67 | J26: =Marketing!L33 -> 3055.67 | ... N26: =Marketing!P33 -> 3055.67 | O26: =SUM(C26:N26) -> 34868.04 | P26: 48514 | Q26: 36672 | R26: =+O26-P26 -> -13645.96 | S26: =(O26-Q26)/Q26 -> -0.049191754 | T26: Pulls from "Marketing" tab (not marketing budget)
A27: 41100 | B27: Other Income/ Excise Tax | C27: ='Excise Tax'!E35+'Rent Recovery'!E45+'CAM Recovery'!E45 -> 14047.696 | D27: ='Excise Tax'!F35+'Rent Recovery'!F45+'CAM Recovery'!F45 -> 14047.696 | E27: ='Excise Tax'!G35+'Rent Recovery'!G45+'CAM Recovery'!G45 -> 14047.696 | F27: ='Excise Tax'!H35+'Rent Recovery'!H45+'CAM Recovery'!H45 -> 14047.696 | G27: ='Excise Tax'!I35+'Rent Recovery'!I45+'CAM Recovery'!I45 -> 14047.696 | H27: ='Excise Tax'!J35+'Rent Recovery'!J45+'CAM Recovery'!J45 -> 14047.696 | I27: ='Excise Tax'!K35+'Rent Recovery'!K45+'CAM Recovery'!K45 -> 14707.954 | J27: ='Excise Tax'!L35+'Rent Recovery'!L45+'CAM Recovery'!L45 -> 14919.904 | ... N27: ='Excise Tax'!P35+'Rent Recovery'!P45+'CAM Recovery'!P45 -> 15061.204 | O27: =SUM(C$27:N$27) -> 174158.85 | P27: 184054 | Q27: 197272 | R27: =+O27-P27 -> -9895.1529 | S27: =(O27-Q27)/Q27 -> -0.11716388 | T27: 4.71% of all income
O28: =SUM(C$28:N$28) -> 0 | R28: =+O28-P28 -> 0
B30: TOTAL INCOME | C30: =SUM(C13:C28) -> 313323.57 | D30: =SUM(D13:D28) -> 313323.57 | E30: =SUM(E13:E28) -> 313626.08 | F30: =SUM(F13:F28) -> 313692.29 | G30: =SUM(G13:G28) -> 313692.29 | H30: =SUM(H13:H28) -> 313850.08 | I30: =SUM(I13:I28) -> 341806.39 | J30: =SUM(J13:J28) -> 346518.34 | ... R30: =SUM(R13:R28) -> -59704.74 | S30: =(O30-Q30)/Q30 -> -0.14338163
B32: EXPENSES
A33: 50160 | B33: Landscape Consumables | D33: =(6835.6*3%)+6835.6 -> 7040.668 | E33: =(8654.458*3%)+8654 -> 8913.6337 | F33: 0 | G33: =(10000*3%)+10000 -> 10300 | H33: 0 | I33: 0 | J33: 0 | L33: 0 | M33: 0 | O33: =SUM(C33:N33) -> 26254.302 | P33: 12542 | Q33: 26255 | R33: =+O33-P33 -> 13712.302 | S33: =(O33-Q33)/Q33 -> -2.6595315e-05
A34: 50190 | B34: Landscape Sprinkler Repairs | C34: 250 | F34: 250 | I34: 250 | L34: 250 | O34: =SUM(C34:N34) -> 1000 | P34: 2472 | Q34: 8748 | R34: =+O34-P34 -> -1472 | S34: =(O34-Q34)/Q34 -> -0.88568816 | T34: Contingency for irrigation repairs based on PY actuals.
A35: 50170 | B35: Landscape Maintenance | C35: =(7506.4*1.03)+300 -> 8031.592 | D35: =C35 -> 8031.592 | E35: =D35 -> 8031.592 | F35: =E35 -> 8031.592 | G35: =F35 -> 8031.592 | H35: =G35 -> 8031.592 | I35: =H35 -> 8031.592 | J35: =I35 -> 8031.592 | K35: =J35 -> 8031.592 | ... N35: =M35 -> 8031.592 | O35: =SUM(C35:N35) -> 96379.104 | P35: 91884 | Q35: 92784 | R35: =+O35-P35 -> 4495.104 | S35: =(O35-Q35)/Q35 -> 0.038747025 | T35: Service with Hawaii Island Lawns budget assumes 3% increase over PY. + $300/mo Outback | U35: add Outback landscaping
A36: 50510 | B36: Parking Lot Lights Maintenance | C36: 0 | D36: 0 | E36: 0 | F36: 0 | G36: 0 | H36: 0 | I36: 0 | J36: 0 | K36: 0 | L36: 0 | M36: 0 | N36: 0 | O36: =SUM(C36:N36) -> 0 | R36: =+O36-P36 -> 0 | S36: =(O36-Q36)/Q36 -> #DIV/0!
A37: 50520 | B37: Parking Lot Maintenance | C37: 0 | D37: 500 | E37: 0 | F37: 0 | G37: 500 | H37: 0 | I37: 0 | J37: 500 | K37: 0 | L37: 0 | M37: 500 | O37: =SUM(C37:N37) -> 2000 | P37: 626 | Q37: 2000 | R37: =+O37-P37 -> 1374 | S37: =(O37-Q37)/Q37 -> 0 | T37: Contingency-Kept 2023 Numbers
A38: 50520 | B38: Parking Lot Amoritization | C38: 0 | D38: 0 | E38: 0 | F38: 0 | G38: 0 | H38: 0 | I38: 0 | J38: 0 | K38: 0 | L38: 0 | M38: 0 | O38: =SUM(C38:N38) -> 0 | R38: =+O38-P38 -> 0 | S38: =(O38-Q38)/Q38 -> #DIV/0! | T38: Amoritization for parkting lot repairs
A39: 50530 | B39: Parking Lot Lights Repair | C39: 0 | D39: 0 | E39: 500 | F39: 0 | G39: 0 | H39: 500 | I39: 4000 | J39: 0 | K39: 500 | L39: 0 | M39: 0 | N39: 500 | O39: =SUM(C39:N39) -> 6000 | P39: 11998 | Q39: 0 | R39: =+O39-P39 -> -5998 | S39: =(O39-Q39)/Q39 -> #DIV/0! | T39: Contingency funds + $4K South Entry Lights
A40: 50540 | B40: Parking Lot Repairs | C40: 0 | D40: 750 | E40: 0 | F40: 0 | G40: 28000 | H40: 0 | I40: 0 | J40: 750 | K40: 0 | L40: 0 | M40: 750 | N40: 0 | O40: =SUM(C40:N40) -> 30250 | P40: 4803 | Q40: 3000 | R40: =+O40-P40 -> 25447 | S40: =(O40-Q40)/Q40 -> 9.0833333 | T40: $28K budgeted for repairs & striping
A41: 50560 | B41: Fountain Maintenance | C41: 0 | D41: 0 | E41: 0 | F41: 0 | G41: 0 | H41: 0 | I41: 0 | J41: 0 | K41: 0 | L41: 0 | M41: 0 | N41: 0 | O41: =SUM(C41:N41) -> 0 | R41: =+O41-P41 -> 0 | S41: =(O41-Q41)/Q41 -> #DIV/0!
A42: 50570 | B42: Fountain Repair | C42: 0 | D42: 0 | E42: 0 | F42: 0 | G42: 0 | H42: 0 | I42: 0 | J42: 0 | K42: 0 | L42: 0 | M42: 0 | N42: 0 | O42: =SUM(C42:N42) -> 0 | R42: =+O42-P42 -> 0 | S42: =(O42-Q42)/Q42 -> #DIV/0!
A43: 50550 | B43: Sign Maintenance | C43: 0 | D43: 0 | E43: 0 | F43: 0 | G43: 0 | H43: 0 | I43: 0 | J43: 0 | K43: 0 | L43: 0 | M43: 0 | N43: 0 | O43: =SUM(C43:N43) -> 0 | R43: =+O43-P43 -> 0 | S43: =(O43-Q43)/Q43 -> #DIV/0!
A44: 50551 | B44: Sign Repairs | C44: 200 | D44: 0 | E44: 0 | F44: 200 | G44: 0 | H44: 0 | I44: 200 | J44: 0 | K44: 0 | L44: 200 | M44: 0 | N44: 0 | O44: =SUM(C44:N44) -> 800 | P44: 614 | Q44: 800 | R44: =+O44-P44 -> 186 | S44: =(O44-Q44)/Q44 -> 0 | T44: Contingency amount based on prior budgets.
A45: 51010 | B45: Awning Maintenance | C45: 0 | D45: 0 | E45: 0 | F45: 0 | G45: 0 | H45: 0 | I45: 0 | J45: 0 | K45: 0 | L45: 0 | M45: 0 | N45: 0 | O45: =SUM(C45:N45) -> 0 | R45: =+O45-P45 -> 0 | S45: =(O45-Q45)/Q45 -> #DIV/0!
A46: 51020 | B46: General Maintenance Site | C46: 1300 | D46: =C46 -> 1300 | E46: =D46 -> 1300 | F46: =E46 -> 1300 | G46: =F46 -> 1300 | H46: =G46 -> 1300 | I46: =H46 -> 1300 | J46: =I46 -> 1300 | K46: =J46 -> 1300 | ... N46: =M46 -> 1300 | O46: =SUM(C46:N46) -> 15600 | P46: 37169 | Q46: 36000 | R46: =+O46-P46 -> -21569 | S46: =(O46-Q46)/Q46 -> -0.56666667 | T46: Contigency amount for repairs as needed; less than 2025 due to common area repairs
A47: 51023 | B47: Site Furnishing-Repairs | C47: 0 | D47: 0 | E47: 0 | F47: 0 | G47: 0 | H47: 0 | I47: 0 | J47: 0 | K47: 0 | L47: 0 | M47: 0 | N47: 0 | O47: =SUM(C47:N47) -> 0 | P47: 1865 | R47: =+O47-P47 -> -1865 | S47: =(O47-Q47)/Q47 -> #DIV/0!
A48: 51030 | B48: Misc. Maintenance & Repairs | C48: 0 | D48: 0 | E48: 0 | F48: 0 | G48: 0 | H48: 0 | I48: 0 | J48: 0 | K48: 0 | L48: 0 | M48: 0 | N48: 0 | O48: =SUM(C48:N48) -> 0 | P48: 2082 | Q48: 8500 | R48: =+O48-P48 -> -2082 | S48: =(O48-Q48)/Q48 -> -1 | T48: no longer using this code
A49: 51040 | B49: Janitorial/Day porter | C49: =10872.62*1.03 -> 11198.799 | D49: =C49 -> 11198.799 | E49: =D49 -> 11198.799 | F49: =E49 -> 11198.799 | G49: =F49 -> 11198.799 | H49: =G49 -> 11198.799 | I49: =H49 -> 11198.799 | J49: =I49 -> 11198.799 | K49: =J49 -> 11198.799 | ... N49: =M49 -> 11198.799 | O49: =SUM(C49:N49) -> 134385.58 | P49: 130752 | Q49: 134388 | R49: =+O49-P49 -> 3633.5832 | S49: =(O49-Q49)/Q49 -> -1.7983749e-05 | T49: Service with JW Cleaning Systems budget assumes 3% increase over PY
A50: - | B50: Window Washing Maint. | C50: 0 | D50: 0 | E50: 0 | F50: 0 | G50: 0 | H50: 0 | I50: 0 | J50: 0 | K50: 0 | L50: 0 | M50: 0 | N50: 0 | O50: =SUM(C50:N50) -> 0 | R50: =+O50-P50 -> 0 | S50: =(O50-Q50)/Q50 -> #DIV/0!
A51: 51050 | B51: Pest Control Maintenance | C51: 295 | D51: 295 | E51: =295+500+1500 -> 2295 | F51: =D51 -> 295 | G51: =F51 -> 295 | H51: =E51 -> 2295 | I51: =G51 -> 295 | J51: =I51 -> 295 | K51: =H51 -> 2295 | L51: =J51 -> 295 | M51: =L51 -> 295 | N51: =K51 -> 2295 | O51: =SUM(C51:N51) -> 11540 | P51: 10636 | Q51: 5576 | R51: =+O51-P51 -> 904 | S51: =(O51-Q51)/Q51 -> 1.0695839 | T51: Service with Smart Pest Protection budget assumes 3% increase over PY; plus quarterly bee service
A52: 51055 | B52: Advertising/Promo | C52: 0 | D52: 0 | E52: 0 | F52: 0 | G52: 0 | H52: 0 | I52: 0 | J52: 0 | K52: 0 | L52: 0 | M52: 0 | N52: 0 | O52: =SUM(C52:N52) -> 0 | R52: =+O52-P52 -> 0 | S52: =(O52-Q52)/Q52 -> #DIV/0!
A53: 51074 | B53: Music System Maintenance | C53: 0 | D53: 0 | E53: 0 | F53: 0 | G53: 0 | H53: 0 | I53: 0 | J53: 0 | K53: 0 | L53: 0 | M53: 0 | N53: 0 | O53: =SUM(C53:N53) -> 0 | R53: =+O53-P53 -> 0 | S53: =(O53-Q53)/Q53 -> #DIV/0!
A54: 51075 | B54: Music System Repairs | C54: 0 | D54: 0 | E54: 0 | F54: 0 | G54: 0 | H54: 0 | I54: 0 | J54: 0 | K54: 0 | L54: 0 | M54: 0 | N54: 0 | O54: =SUM(C54:N54) -> 0 | R54: =+O54-P54 -> 0 | S54: =(O54-Q54)/Q54 -> #DIV/0!
A55: 51080 | B55: On-Site Management | C55: 12457 | D55: 12517 | E55: 1229 | F55: 12531 | G55: 12531 | H55: 12537 | I55: 13658 | J55: 13658 | K55: 15657 | L55: 15657 | M55: 15695 | N55: 16475 | O55: =SUM(C55:N55) -> 154602 | P55: 173817 | Q55: 211469 | R55: =+O55-P55 -> -19215 | S55: =(O55-Q55)/Q55 -> -0.26891412 | T55: 4% of income
A56: 51100 | B56: Sidewalk Maintenance | C56: 0 | D56: 0 | E56: 0 | F56: 0 | G56: 0 | H56: 0 | I56: 0 | K56: 0 | L56: 0 | M56: 0 | N56: 0 | O56: =SUM(C56:N56) -> 0 | R56: =+O56-P56 -> 0 | S56: =(O56-Q56)/Q56 -> #DIV/0!
A57: 55190 | B57: Ground Lease State | C57: 0 | D57: 0 | E57: 0 | F57: 0 | G57: 16200 | H57: 0 | I57: 0 | J57: 0 | K57: 0 | L57: 0 | M57: 16200 | N57: 0 | O57: =SUM(C57:N57) -> 32400 | R57: =+O57-P57 -> 32400 | S57: =(O57-Q57)/Q57 -> #DIV/0! | T57: Volleyball court
A58: 55190 | B58: Ground Lease Private | C58: 8802.81 | D58: =C58 -> 8802.81 | E58: =D58 -> 8802.81 | F58: =E58 -> 8802.81 | G58: =F58 -> 8802.81 | H58: =G58 -> 8802.81 | I58: =H58 -> 8802.81 | J58: =I58 -> 8802.81 | K58: =J58 -> 8802.81 | ... N58: =M58 -> 8802.81 | O58: =SUM(C58:N58) -> 105633.72 | P58: 138246 | Q58: 138036 | R58: =+O58-P58 -> -32612.28 | S58: =(O58-Q58)/Q58 -> -0.23473789 | T58: Parking lot by ABC is ground lease
A59: 51150 | B59: Sweeping | C59: =2501.94*1.03 -> 2576.9982 | D59: =C59 -> 2576.9982 | E59: =D59 -> 2576.9982 | F59: =E59 -> 2576.9982 | G59: =F59 -> 2576.9982 | H59: =G59 -> 2576.9982 | I59: =H59 -> 2576.9982 | J59: =I59 -> 2576.9982 | K59: =J59 -> 2576.9982 | ... N59: =M59 -> 2576.9982 | O59: =SUM(C59:N59) -> 30923.978 | P59: 30624 | Q59: 31474 | R59: =+O59-P59 -> 299.9784 | S59: =(O59-Q59)/Q59 -> -0.017475427 | T59: Service with Hawaii Island Lawns budget assumes 3% increase over PY.
A60: 51160 | B60: Security - Split 80% | C60: =(460+8900+3350)*80% -> 10168 | D60: =C60 -> 10168 | E60: =D60 -> 10168 | F60: =E60 -> 10168 | G60: =F60 -> 10168 | H60: =G60 -> 10168 | I60: =H60 -> 10168 | J60: =I60 -> 10168 | K60: =J60 -> 10168 | ... N60: =M60 -> 10168 | O60: =SUM(C60:N60) -> 122016 | P60: 188100 | Q60: 179160 | R60: =+O60-P60 -> -66084 | S60: =(O60-Q60)/Q60 -> -0.31895512 | T60: Internet $460/mo; Viking $8,900/mo; Elite $3350/mo + $6500 January install
A61: 51161 | B61: Security - Cameras | C61: 0 | D61: =C61 -> 0 | E61: =D61 -> 0 | F61: =E61 -> 0 | G61: =F61 -> 0 | H61: =G61 -> 0 | I61: =H61 -> 0 | J61: =I61 -> 0 | K61: =J61 -> 0 | ... N61: =M61 -> 0 | O61: =SUM(C61:N61) -> 0 | R61: =+O61-P61 -> 0 | S61: =(O61-Q61)/Q61 -> #DIV/0! | T61: no longer using this code
A62: 50103 | B62: Permits & Fee - Waste Insp. Fee | C62: 0 | D62: 0 | E62: 0 | F62: 0 | G62: 0 | H62: 0 | I62: 0 | J62: 0 | K62: 0 | L62: 0 | M62: 0 | N62: 0 | O62: =SUM(C62:N62) -> 0 | R62: =+O62-P62 -> 0 | S62: =(O62-Q62)/Q62 -> #DIV/0!
A63: 51170 | B63: Locksmith | C63: 0 | D63: 0 | E63: 0 | F63: 0 | G63: 0 | H63: 0 | I63: 0 | J63: 0 | K63: 0 | L63: 0 | M63: 0 | N63: 0 | O63: =SUM(C63:N63) -> 0 | R63: =+O63-P63 -> 0 | S63: =(O63-Q63)/Q63 -> #DIV/0!
A64: 0 | B64: Electrical Repairs/Building | C64: 0 | D64: 0 | E64: 0 | F64: 0 | G64: 0 | H64: 0 | I64: 0 | J64: 0 | K64: 0 | L64: 0 | M64: 0 | N64: 0 | O64: =SUM(C64:N64) -> 0 | R64: =+O64-P64 -> 0 | S64: =(O64-Q64)/Q64 -> #DIV/0!
A65: 51200 | B65: Electrical Repairs/Common Area | C65: 0 | D65: 0 | E65: 0 | F65: 0 | G65: =D65 -> 0 | H65: 0 | I65: 0 | J65: =G65 -> 0 | K65: 0 | L65: 0 | M65: =J65 -> 0 | N65: 0 | O65: =SUM(C65:N65) -> 0 | P65: 1500 | Q65: 6000 | R65: =+O65-P65 -> -1500 | S65: =(O65-Q65)/Q65 -> -1
A66: 0 | B66: Supplies Electrical | C66: 0 | D66: 0 | E66: 0 | F66: 0 | G66: 0 | H66: 0 | I66: 0 | J66: 0 | K66: 0 | L66: 0 | M66: 0 | N66: 0 | O66: =SUM(C66:N66) -> 0 | R66: =+O66-P66 -> 0 | S66: =(O66-Q66)/Q66 -> #DIV/0!
A67: 51210 | B67: Plumbing Repairs | C67: 1500 | D67: 0 | E67: 0 | F67: =C67 -> 1500 | G67: 0 | H67: 0 | I67: =F67 -> 1500 | J67: 0 | K67: 0 | L67: =I67 -> 1500 | M67: 0 | N67: 0 | O67: =SUM(C67:N67) -> 6000 | P67: 14377 | Q67: 6000 | R67: =+O67-P67 -> -8377 | S67: =(O67-Q67)/Q67 -> 0 | T67: Annual store drain maintenance and contingency for repairs if needed.
A68: 51220 | B68: Painting | C68: 0 | D68: 0 | F68: 0 | G68: 0 | H68: 0 | I68: 0 | J68: 0 | K68: 0 | L68: 0 | M68: 0 | N68: 0 | O68: =SUM(C68:N68) -> 0 | P68: 7055 | Q68: 2000 | R68: =+O68-P68 -> -7055 | S68: =(O68-Q68)/Q68 -> -1 | T68: Contingency
A69: 0 | B69: Wall & Block Repairs | C69: 0 | D69: 0 | E69: 0 | F69: 0 | G69: 0 | H69: 0 | I69: 0 | J69: 0 | K69: 0 | L69: 0 | M69: 0 | N69: 0 | O69: =SUM(C69:N69) -> 0 | R69: =+O69-P69 -> 0 | S69: =(O69-Q69)/Q69 -> #DIV/0!
A70: 0 | B70: Window Repairs | C70: 0 | D70: 0 | E70: 0 | F70: 0 | G70: 0 | H70: 0 | I70: 0 | J70: 0 | K70: 0 | L70: 0 | M70: 0 | N70: 0 | O70: =SUM(C70:N70) -> 0 | R70: =+O70-P70 -> 0 | S70: =(O70-Q70)/Q70 -> #DIV/0!
A71: 52010 | B71: Janitorial Supplies | C71: 2000 | D71: =C71 -> 2000 | E71: =D71 -> 2000 | F71: =E71 -> 2000 | G71: =F71 -> 2000 | H71: =G71 -> 2000 | I71: =H71 -> 2000 | J71: =I71 -> 2000 | K71: =J71 -> 2000 | ... N71: =M71 -> 2000 | O71: =SUM(C71:N71) -> 24000 | P71: 22798 | Q71: 22248 | R71: =+O71-P71 -> 1202 | S71: =(O71-Q71)/Q71 -> 0.078748652 | T71: Budget assumes 3% increase over PY
A72: 0 | B72: Banners - Seasonal | C72: 0 | D72: 0 | E72: 0 | F72: 0 | G72: 0 | H72: 0 | I72: 0 | J72: 0 | K72: 0 | L72: 0 | M72: 0 | N72: 0 | O72: =SUM(C72:N72) -> 0 | R72: =+O72-P72 -> 0 | S72: =(O72-Q72)/Q72 -> #DIV/0!
A73: 55120 | B73: Trash Common Area - Split 20% | C73: 1350 | D73: =C73 -> 1350 | E73: =D73 -> 1350 | F73: =E73 -> 1350 | G73: =F73 -> 1350 | H73: =G73 -> 1350 | I73: =H73 -> 1350 | J73: =I73 -> 1350 | K73: =J73 -> 1350 | ... N73: =M73 -> 1350 | O73: =SUM(C73:N73) -> 16200 | P73: 15724 | Q73: 19440 | R73: =+O73-P73 -> 476 | S73: =(O73-Q73)/Q73 -> -0.16666667 | T73: PY actuals plus 3% increase
A74: 50220 | B74: Street Light Maint. | C74: 0 | D74: 0 | E74: 0 | F74: 0 | G74: 0 | H74: 0 | I74: 0 | J74: 0 | K74: 0 | L74: 0 | M74: 0 | N74: 0 | O74: =SUM(C74:N74) -> 0 | R74: =+O74-P74 -> 0 | S74: =(O74-Q74)/Q74 -> #DIV/0!
A75: 55160 | B75: Gas | C75: 112 | D75: =C75 -> 112 | E75: =D75 -> 112 | F75: =E75 -> 112 | G75: =F75 -> 112 | H75: =G75 -> 112 | I75: =H75 -> 112 | J75: =I75 -> 112 | K75: =J75 -> 112 | ... N75: =M75 -> 112 | O75: =SUM(C75:N75) -> 1344 | P75: 1309 | Q75: 2412 | R75: =+O75-P75 -> 35 | S75: =(O75-Q75)/Q75 -> -0.44278607 | T75: PY actuals plus 3% increase
A76: 55110 | B76: Electric/Common Area | C76: 2810 | D76: =C76 -> 2810 | E76: =D76 -> 2810 | F76: =E76 -> 2810 | G76: =F76 -> 2810 | H76: =G76 -> 2810 | I76: =H76 -> 2810 | J76: =I76 -> 2810 | K76: =J76 -> 2810 | ... N76: =M76 -> 2810 | O76: =SUM(C76:N76) -> 33720 | P76: 32748 | Q76: 36264 | R76: =+O76-P76 -> 972 | S76: =(O76-Q76)/Q76 -> -0.070152217 | T76: PY actuals plus 3% increase
A77: 55140 | B77: Water/Common Area | C77: 460 | D77: 10400 | E77: 920 | F77: =D77 -> 10400 | G77: 460 | H77: =F77 -> 10400 | I77: 920 | J77: =H77 -> 10400 | K77: 460 | L77: =J77 -> 10400 | M77: 920 | N77: =L77 -> 10400 | O77: =SUM(C77:N77) -> 66540 | P77: 65102 | Q77: 70296 | R77: =+O77-P77 -> 1438 | S77: =(O77-Q77)/Q77 -> -0.053431205 | T77: PY actuals plus 3% increase
A78: 55180 | B78: Sewer (do not use) | D78: 0 | E78: 0 | F78: 0 | G78: 0 | H78: 0 | I78: 0 | J78: 0 | K78: 0 | L78: 0 | M78: 0 | N78: 0 | O78: =SUM(C78:N78) -> 0 | R78: =+O78-P78 -> 0 | S78: =(O78-Q78)/Q78 -> #DIV/0! | T78: Shifted to Water Building
A79: 70411 | B79: GET Tax Expense | C79: ='Excise Tax'!E35 -> 14027.76 | D79: ='Excise Tax'!F35 -> 14027.76 | E79: ='Excise Tax'!G35 -> 14027.76 | F79: ='Excise Tax'!H35 -> 14027.76 | G79: ='Excise Tax'!I35 -> 14027.76 | H79: ='Excise Tax'!J35 -> 14027.76 | I79: ='Excise Tax'!K35 -> 14688.018 | J79: ='Excise Tax'!L35 -> 14899.968 | ... N79: ='Excise Tax'!P35 -> 15041.268 | O79: =SUM(C79:N79) -> 173919.62 | P79: 193237 | Q79: 197034 | R79: =+O79-P79 -> -19317.385 | S79: =(O79-Q79)/Q79 -> -0.11731166 | T79: Must be a CAM to offset the GET Income and avoid overstating NOI
B81: SUBTOTAL COMMON AREA | C81: =SUM(C33:C80) -> 77539.958 | D81: =SUM(D33:D80) -> 93880.626 | E81: =SUM(E33:E80) -> 76235.592 | F81: =SUM(F33:F80) -> 87553.958 | G81: =SUM(G33:G80) -> 130663.96 | H81: =SUM(H33:H80) -> 88109.958 | I81: =SUM(I33:I80) -> 83861.217 | J81: =SUM(J33:J80) -> 88853.167 | ... R81: =SUM(R33:R80) -> -100571.7 | S81: =(O81-Q81)/Q81 -> -0.11966902
B83: FOOD COURT CAM
A84: 57110 | B84: Janitorial and Supplies | C84: 3300 | D84: =C84 -> 3300 | E84: =D84 -> 3300 | F84: =E84 -> 3300 | G84: =F84 -> 3300 | H84: =G84 -> 3300 | I84: =H84 -> 3300 | J84: =I84 -> 3300 | K84: =J84 -> 3300 | ... N84: =M84 -> 3300 | O84: =SUM(C84:N84) -> 39600 | P84: 37331 | Q84: 33600 | R84: =+O84-P84 -> 2269 | S84: =(O84-Q84)/Q84 -> 0.17857143 | T84: Service with JW Cleaning Systems budget assumes 3% increase over PY
A85: 57120 | B85: Gas | C85: =78*103% -> 80.34 | D85: =C85 -> 80.34 | E85: =D85 -> 80.34 | F85: =E85 -> 80.34 | G85: =F85 -> 80.34 | H85: =G85 -> 80.34 | I85: =H85 -> 80.34 | J85: =I85 -> 80.34 | K85: =J85 -> 80.34 | ... N85: =M85 -> 80.34 | O85: =SUM(C85:N85) -> 964.08 | P85: 1141 | Q85: 1740 | R85: =+O85-P85 -> -176.92 | S85: =(O85-Q85)/Q85 -> -0.44593103 | T85: Assumed 3% Incease
A86: 57130 | B86: Security - Split 20% | C86: =(460+8900+3350+6500)*20% -> 3842 | D86: =(460+8900+3350)*20% -> 2542 | E86: =D86 -> 2542 | F86: =E86 -> 2542 | G86: =F86 -> 2542 | H86: =G86 -> 2542 | I86: =H86 -> 2542 | J86: =I86 -> 2542 | K86: =J86 -> 2542 | L86: =K86 -> 2542 | ... N86: =M86 -> 2542 | O86: =SUM(C86:N86) -> 31804 | P86: 41554 | Q86: 35712 | R86: =+O86-P86 -> -9750 | S86: =(O86-Q86)/Q86 -> -0.109431 | T86: Service with Viking Services of Hawaii budget assumes 3% increase over PY (Viking only)
A87: 57140 | B87: Trash - Split 80% | C87: 5400 | D87: =C87 -> 5400 | E87: =D87 -> 5400 | F87: =E87 -> 5400 | G87: =F87 -> 5400 | H87: =G87 -> 5400 | I87: =H87 -> 5400 | J87: =I87 -> 5400 | K87: =J87 -> 5400 | ... N87: =M87 -> 5400 | O87: =SUM(C87:N87) -> 64800 | P87: 62781 | Q87: 78000 | R87: =+O87-P87 -> 2019 | S87: =(O87-Q87)/Q87 -> -0.16923077 | T87: PY actuals plus 3% increase
R88: =+O88-P88 -> 0
B89: SUBTOTAL FOOD COURT | C89: =SUM(C84:C87) -> 12622.34 | D89: =SUM(D84:D87) -> 11322.34 | E89: =SUM(E84:E87) -> 11322.34 | F89: =SUM(F84:F87) -> 11322.34 | G89: =SUM(G84:G87) -> 11322.34 | H89: =SUM(H84:H87) -> 11322.34 | I89: =SUM(I84:I87) -> 11322.34 | J89: =SUM(J84:J87) -> 11322.34 | ... N89: =SUM(N84:N87) -> 11322.34 | O89: =SUM(O84:O88) -> 137168.08 | P89: =SUM(P84:P88) -> 142807 | Q89: =SUM(Q84:Q87) -> 149052 | R89: =SUM(R84:R88) -> -5638.92 | S89: =(O89-Q89)/Q89 -> -0.079730027
B91: BUILDING EXPENSE
A92: 51060 | B92: Roof Maintenance | C92: 0 | D92: 2500 | E92: 0 | F92: 0 | G92: 0 | H92: 0 | I92: 0 | J92: 0 | K92: 0 | L92: 2500 | M92: 0 | N92: 0 | O92: =SUM(C92:N92) -> 5000 | P92: 4914 | Q92: 5000 | R92: =+O92-P92 -> 86 | S92: =(O92-Q92)/Q92 -> 0 | T92: Contingency
A93: 51070 | B93: Roof Repairs | C93: 0 | D93: 0 | E93: 0 | F93: 500 | G93: 0 | H93: 0 | I93: 0 | J93: 0 | K93: 0 | L93: 0 | M93: 0 | N93: 0 | O93: =SUM(C93:N93) -> 500 | P93: 581 | Q93: 500 | R93: =+O93-P93 -> -81 | S93: =(O93-Q93)/Q93 -> 0 | T93: Contingency
A94: 50210 | B94: Elevator Maint. | C94: =365+2500 -> 2865 | D94: =C94 -> 2865 | E94: 365 | F94: =D94 -> 2865 | G94: =F94 -> 2865 | H94: =E94 -> 365 | I94: =G94 -> 2865 | J94: =G94 -> 2865 | K94: =H94 -> 365 | L94: =J94 -> 2865 | M94: =L94 -> 2865 | N94: =K94 -> 365 | O94: =SUM(C94:N94) -> 24380 | P94: 23469 | Q94: 13892 | R94: =+O94-P94 -> 911 | S94: =(O94-Q94)/Q94 -> 0.75496689 | T94: Service with Otis Elevator billed quarterly, monthly phone lines with Hawaiin Telcom and annual testing in January.
A95: 51110 | B95: Monitor Fire Sprinklers | E95: =(700*10%)+700 -> 770 | I95: 2874 | O95: =SUM(C95:N95) -> 3644 | P95: 1445 | Q95: 3644 | R95: =+O95-P95 -> 2199 | S95: =(O95-Q95)/Q95 -> 0 | T95: Annnual fire alarm inspection and contingency for repairs if needed.
A96: 51120 | B96: Fire Protection Repairs | C96: 0 | D96: 0 | E96: 0 | F96: 603 | G96: 0 | H96: 0 | I96: 0 | J96: 600 | K96: 0 | L96: 0 | M96: 0 | N96: 0 | O96: =SUM(C96:N96) -> 1203 | P96: 16393 | Q96: 1203 | R96: =+O96-P96 -> -15190 | S96: =(O96-Q96)/Q96 -> 0 | T96: Contingency
A97: 51120 | B97: Elevator Repair | C97: 0 | D97: 0 | E97: 0 | F97: 0 | G97: 0 | H97: 0 | I97: 0 | J97: 0 | K97: 0 | L97: 0 | M97: 0 | N97: 0 | O97: =SUM(C97:N97) -> 0 | R97: =+O97-P97 -> 0 | S97: =(O97-Q97)/Q97 -> #DIV/0!
A98: 52020 | B98: Backflow Maintenance | C98: 0 | D98: 0 | E98: 0 | F98: 0 | G98: 0 | H98: 0 | I98: 1030 | J98: 0 | K98: 0 | L98: 0 | M98: 0 | N98: 0 | O98: =SUM(C98:N98) -> 1030 | P98: 0 | Q98: 1030 | R98: =+O98-P98 -> 1030 | S98: =(O98-Q98)/Q98 -> 0 | T98: Backflow Testing
B99: Backflow Repairs | C99: 0 | D99: 0 | E99: 0 | F99: 0 | G99: 500 | H99: 0 | I99: 0 | J99: 0 | K99: 0 | L99: 0 | M99: 0 | N99: 0 | O99: =SUM(C99:N99) -> 500 | R99: =+O99-P99 -> 500 | S99: =(O99-Q99)/Q99 -> #DIV/0! | T99: Contingency
B100: Building Paint | O100: =SUM(C100:N100) -> 0 | R100: =+O100-P100 -> 0 | S100: =(O100-Q100)/Q100 -> #DIV/0!
A101: 51400 | B101: Building Repair and Maint. | C101: 0 | D101: 0 | E101: 0 | F101: 0 | G101: 0 | H101: 0 | I101: 0 | J101: 0 | K101: 0 | L101: 0 | M101: 0 | N101: 0 | O101: =SUM(C101:N101) -> 0 | R101: =+O101-P101 -> 0 | S101: =(O101-Q101)/Q101 -> #DIV/0!
A102: 55120 | B102: Trash Removal Foodcourt | O102: =SUM(C102:N102) -> 0 | R102: =+O102-P102 -> 0 | S102: =(O102-Q102)/Q102 -> #DIV/0!
A103: 51180 | B103: Grease Trap Maintenance | C103: 0 | D103: 0 | E103: 0 | F103: 0 | G103: 0 | H103: 0 | I103: 0 | J103: 0 | K103: 0 | L103: 0 | M103: 0 | N103: 0 | O103: =SUM(C103:N103) -> 0 | R103: =+O103-P103 -> 0 | S103: =(O103-Q103)/Q103 -> #DIV/0!
A104: 55180 | B104: Water/Building and Sewer | C104: 13250 | E104: =C104 -> 13250 | G104: =E104 -> 13250 | I104: =G104 -> 13250 | K104: =I104 -> 13250 | M104: =K104 -> 13250 | O104: =SUM(C104:N104) -> 79500 | P104: 77439 | Q104: 122196 | R104: =+O104-P104 -> 2061 | S104: =(O104-Q104)/Q104 -> -0.34940587 | T104: PY actuals plus 3% increase
B106: SUBTOTAL BUILDING EXP. | C106: =SUM(C92:C104) -> 16115 | D106: =SUM(D92:D104) -> 5365 | E106: =SUM(E92:E104) -> 14385 | F106: =SUM(F92:F104) -> 3968 | G106: =SUM(G92:G104) -> 16615 | H106: =SUM(H92:H104) -> 365 | I106: =SUM(I92:I104) -> 20019 | J106: =SUM(J92:J104) -> 3465 | ... O106: =SUM(O92:O104) -> 115757 | P106: =SUM(P92:P105) -> 124241 | Q106: =SUM(Q92:Q105) -> 147465 | R106: =+O106-P106 -> -8484 | S106: =(O106-Q106)/Q106 -> -0.21502051
B108: INSURANCE
A109: 50111 | B109: Insurance - Property | C109: 10328 | D109: 10328 | E109: 0 | F109: =55277*110% -> 60804.7 | G109: =D109*110% -> 11360.8 | H109: =G109 -> 11360.8 | I109: =H109 -> 11360.8 | J109: =I109 -> 11360.8 | K109: =J109 -> 11360.8 | L109: =K109 -> 11360.8 | M109: =L109 -> 11360.8 | N109: =M109 -> 11360.8 | O109: =SUM(C109:N109) -> 172347.1 | P109: 159057 | Q109: 190827 | R109: =+O109-P109 -> 13290.1 | S109: 0.12 | T109: PY actuals plus 10% increase
...

Sheet Summ. (2)
O1: Date Revised: | P1: =TODAY() -> 46265
A2: ATHENA PROPERTY MANAGEMENT
A3: GARDENA VILLAGE - GARDENA, CA
A4: PROJECT NO. 151
A5: 01/01/16 - 12/31/16
A6: 2016 OPERATING BUDGET
A8: GL | P8: 2016 TOTALS | Q8: 2016 BUDGET | R8: 2015 | S8: 2015 | T8: Variance | U8: DENOM.
A9: CODE | B9: DESCRIPTION | C9: JAN | D9: FEB | E9: MARCH | F9: APRIL | G9: MAY | H9: JUNE | I9: JAN-JUN TOTALS | J9: JULY | K9: AUGUST | L9: SEPT | M9: OCT | N9: NOV | O9: DEC | Q9: $ PSF | R9: Forecast | S9: Total | U9: SQUARE | W9: SF
R10: Budget | S10: Budgeted | U10: FOOTG. | W10: Denominator
B12: INCOME
A14: 40100 | B14: Base Rent | C14: =101488.15-12333.33+4968.94 -> 94123.76 | D14: =103499.47+4968.94 -> 108468.41 | E14: =111248.8+4968.94-7430 -> 108787.74 | F14: =111436.66+4968.94-7430 -> 108975.6 | G14: =111594.16-7430 -> 104164.16 | H14: =111738.97-7430 -> 104308.97 | I14: =SUM(C14:H14) -> 628828.64 | J14: 111738.97 | K14: 112026.97 | L14: 112419.81 | M14: 112501.7 | N14: 112501.7 | O14: 112501.7 | P14: =SUM(C14:O14) -> 1931348.1 | Q14: =SUM((P14)/(Rent!D33-Rent!D14-Rent!#REF!)) -> #REF! | R14: 1031796 | S14: 1060644 | T14: =+P14-R14 -> 899552.13
A15: 40110 | B15: Percentage Rent | C15: 0 | D15: 0 | E15: 0 | F15: 0 | G15: 0 | H15: 0 | I15: =SUM(C15:H15) -> 0 | J15: 0 | K15: 0 | L15: 0 | M15: 0 | N15: 0 | O15: 0 | P15: =SUM(C15:O15) -> 0 | Q15: =P15/Rent!D24 -> 0 | S15: 0 | T15: =+P15-R15 -> 0
A16: 40140 | B16: Common Area Collections (CAMS) | C16: =20810.2446678818-1758.52+502.32 -> 19554.045 | D16: =20810.2446678818+502.32 -> 21312.565 | E16: 21312.565 | F16: =21312.5646302593-502.32 -> 20810.245 | G16: =21312.5646302593-502.32 -> 20810.245 | H16: =21312.5646302593-502.32 -> 20810.245 | I16: =SUM(C16:H16) -> 124609.91 | J16: 21312.565 | K16: 21312.565 | L16: 21312.565 | M16: 21312.565 | N16: 21312.565 | O16: 21312.565 | P16: =SUM(C16:O16) -> 377095.2 | Q16: =P16/'Occup,'!C33 -> 7.3856243 | R16: 201576 | S16: 205676 | T16: =+P16-R16 -> 175519.2
A17: 40150 | B17: Prior Year CAMS | C17: 0 | D17: 0 | E17: 0 | F17: 0 | G17: 0 | H17: 0 | I17: =SUM(C17:H17) -> 0 | J17: 0 | K17: 0 | L17: 0 | M17: 0 | N17: 0 | O17: 0 | P17: =SUM(C17:O17) -> 0 | Q17: 0 | R17: 3054 | S17: 0 | T17: =+P17-R17 -> -3054
A18: 40170 | B18: Other Recoveries | C18: =6511.54648066769-34.04+361.64 -> 6839.1465 | D18: =6511.54648066769+361.64 -> 6873.1865 | E18: =6873.18491186468 -> 6873.1849 | F18: =6873.18491186468-361.64 -> 6511.5449 | G18: =6873.18491186468-361.64 -> 6511.5449 | H18: =6873.18491186468-361.64 -> 6511.5449 | I18: =SUM(C18:H18) -> 40120.153 | J18: 6873.1849 | K18: 6873.1849 | L18: 6873.1849 | M18: 6873.1849 | N18: 6873.1849 | O18: 6873.1849 | P18: =SUM(C18:O18) -> 121479.41 | Q18: =P18/'Occup,'!$C$33 -> 2.3792435 | R18: 63135 | S18: 65790 | T18: =+P18-R18 -> 58344.415
A19: 40190 | B19: Reserve | C19: 0 | D19: 0 | E19: 0 | F19: 0 | G19: 0 | H19: 0 | I19: =SUM(C19:H19) -> 0 | J19: 0 | K19: 0 | L19: 0 | M19: 0 | N19: 0 | O19: 0 | P19: =SUM(C19:O19) -> 0 | Q19: 0 | S19: 0 | T19: =+P19-R19 -> 0
A20: 40230 | B20: Insurance Income | C20: =2889.40608837532-194.11+197.21 -> 2892.5061 | D20: =2889.40608837532+197.21 -> 3086.6161 | E20: 3086.6111 | F20: =3086.61113316872-197.21 -> 2889.4011 | G20: =3086.61113316872-197.21 -> 2889.4011 | H20: =3086.61113316872-197.21 -> 2889.4011 | I20: =SUM(C20:H20) -> 17733.937 | J20: 3086.6111 | K20: 3086.6111 | L20: 3086.6111 | M20: 3086.6111 | N20: 3086.6111 | O20: 3086.6111 | P20: =SUM(C20:O20) -> 53987.54 | Q20: =P20/'Occup,'!$C$33 -> 1.0573767 | R20: 19351 | S20: 19761 | T20: =+P20-R20 -> 34636.54
A21: 40240 | B21: Property Tax Income | C21: =16967.922717225+1175.41 -> 18143.333 | D21: =16967.922717225+1175.41 -> 18143.333 | E21: 18143.337 | F21: =18143.337-1175.41 -> 16967.927 | G21: =18143.337-1175.41 -> 16967.927 | H21: =18143.337-1175.41 -> 16967.927 | I21: =SUM(C21:H21) -> 105333.78 | J21: 18143.337 | K21: 18143.337 | L21: 18143.337 | M21: 18143.337 | N21: 18143.337 | O21: 18143.337 | P21: =SUM(C21:O21) -> 319527.59 | R21: 193387 | S21: 203978 | T21: =+P21-R21 -> 126140.59
A22: 40250 | B22: Miscellaneous Income | C22: 0 | D22: 0 | E22: 0 | F22: 0 | G22: 0 | H22: 0 | I22: =SUM(C22:H22) -> 0 | J22: 0 | K22: 0 | L22: 0 | M22: 0 | N22: 0 | O22: 0 | P22: =SUM(C22:O22) -> 0 | Q22: 0 | R22: 3098 | S22: 0 | T22: =+P22-R22 -> -3098
A23: 40330 | B23: Assignment Fee | C23: 0 | D23: 0 | E23: 0 | F23: 0 | G23: 0 | H23: 0 | I23: =SUM(C23:H23) -> 0 | J23: 0 | K23: 0 | L23: 0 | M23: 0 | N23: 0 | O23: 0 | P23: =SUM(C23:O23) -> 0 | Q23: 0 | S23: 0 | T23: =+P23-R23 -> 0
A24: 40600 | B24: Late Charge Income | C24: 0 | D24: 0 | E24: 0 | F24: 0 | G24: 0 | H24: 0 | I24: =SUM(C24:H24) -> 0 | J24: 0 | K24: 0 | L24: 0 | M24: 0 | N24: 0 | O24: 0 | P24: =SUM(C24:O24) -> 0 | Q24: 0 | R24: 1220 | S24: 0 | T24: =+P24-R24 -> -1220
A25: 40220 | B25: Rent Concessions | C25: -2000 | D25: 0 | E25: 0 | F25: 0 | G25: 0 | H25: 0 | I25: =SUM(C25:H25) -> -2000 | J25: 0 | K25: 0 | L25: 0 | M25: 0 | N25: 0 | O25: 0 | P25: =SUM(C25:O25) -> -4000 | Q25: 0 | R25: 6000 | S25: 0 | T25: =+P25-R25 -> -10000
A26: 40400 | B26: Management Fee Income | C26: =4018.52665102711-268.88+335.49 -> 4085.1367 | D26: =4018.52665102711+335.49 -> 4354.0167 | E26: 4354.0133 | F26: =4354.01330919855-335.49 -> 4018.5233 | G26: =4354.01330919855-335.49 -> 4018.5233 | H26: =4354.01330919855-335.49 -> 4018.5233 | I26: =SUM(C26:H26) -> 24848.737 | J26: 4354.0133 | K26: 4354.0133 | L26: 4354.0133 | M26: 4354.0133 | N26: 4354.0133 | O26: 4354.0133 | P26: =SUM(C26:O26) -> 75821.553 | Q26: =P26/'Occup,'!$C$33 -> 1.4850083 | R26: 35375 | S26: 37803 | T26: =+P26-R26 -> 40446.553
T27: =+P27-R27 -> 0
B28: TOTAL INCOME | C28: =SUM(C14:C27) -> 143637.93 | D28: =SUM(D14:D27) -> 162238.13 | E28: =SUM(E14:E27) -> 162557.45 | F28: =SUM(F14:F27) -> 160173.24 | G28: =SUM(G14:G27) -> 155361.8 | H28: =SUM(H14:H27) -> 155506.61 | I28: =SUM(I14:I27) -> 939475.16 | J28: =SUM(J14:J27) -> 165508.68 | ... S28: =SUM(S14:S27) -> 1593652 | T28: =+P28-R28 -> 1317267.4
B30: EXPENSES
A32: 50160 | B32: Landscape Consumables | C32: 410 | D32: 7180 | E32: 1895 | F32: 3455 | G32: 180 | H32: 2710 | I32: =SUM(C32:H32) -> 15830 | J32: 1060 | K32: 180 | L32: 2900 | M32: 9955 | N32: 830 | O32: 0 | P32: =SUM(C32:O32) -> 46585 | Q32: =P32/U32 -> 0.91239375 | R32: 16274 | S32: 42540 | T32: =+P32-R32 -> 30311 | U32: =Rent!D33 -> 51058 | W32: =Rent!D$33 -> 51058
A33: 50190 | B33: Landscape Sprinkler Repairs | C33: 75 | D33: 75 | E33: 75 | F33: 75 | G33: 75 | H33: 75 | I33: =SUM(C33:H33) -> 450 | J33: 75 | K33: 75 | L33: 75 | M33: 75 | N33: 75 | O33: 75 | P33: =SUM(C33:O33) -> 1350 | Q33: =P33/U33 -> #REF! | R33: 2560 | S33: 900 | T33: =+P33-R33 -> -1210 | U33: =Rent!D$33-Rent!#REF! -> #REF! | W33: =Rent!D$33 -> 51058
A34: 50170 | B34: Landscape Maintenance | C34: 3245 | D34: 3245 | E34: 3245 | F34: 3245 | G34: 3245 | H34: 3245 | I34: =SUM(C34:H34) -> 19470 | J34: 3245 | K34: 3245 | L34: 3245 | M34: 3245 | N34: 3245 | O34: 3245 | P34: =SUM(C34:O34) -> 58410 | Q34: =P34/U34 -> #REF! | R34: 37800 | S34: 37800 | T34: =+P34-R34 -> 20610 | U34: =Rent!D$33-Rent!#REF! -> #REF! | W34: =Rent!D$33 -> 51058
A35: 50510 | B35: Parking Lot Lights Maintenance | C35: 52 | D35: 52 | E35: 52 | F35: 52 | G35: 52 | H35: 52 | I35: =SUM(C35:H35) -> 312 | J35: 52 | K35: 52 | L35: 52 | M35: 52 | N35: 52 | O35: 52 | P35: =SUM(C35:O35) -> 936 | Q35: =P35/U35 -> #REF! | R35: 624 | S35: 624 | T35: =+P35-R35 -> 312 | U35: =Rent!D$33-Rent!#REF! -> #REF! | W35: =Rent!D$33 -> 51058
A36: 50520 | B36: Parking Lot Maintenance | C36: 750 | D36: 0 | E36: 0 | F36: 0 | G36: 750 | H36: 0 | I36: =SUM(C36:H36) -> 1500 | J36: 0 | K36: 0 | L36: 750 | M36: 0 | N36: 0 | O36: 0 | P36: =SUM(C36:O36) -> 3750 | Q36: =P36/U36 -> #REF! | R36: 56672 | S36: 35450 | T36: =+P36-R36 -> -52922 | U36: =Rent!D$33-Rent!#REF! -> #REF! | W36: =Rent!D$33 -> 51058
A37: 50530 | B37: Parking Lot Lights Repair | C37: 6879 | D37: 1000 | E37: 2830 | F37: 1000 | G37: 1000 | H37: 1000 | I37: =SUM(C37:H37) -> 13709 | J37: 1000 | K37: 1000 | L37: 1000 | M37: 1000 | N37: 1000 | O37: 1000 | P37: =SUM(C37:O37) -> 33418 | Q37: =P37/U37 -> #REF! | R37: 12189 | S37: 13200 | T37: =+P37-R37 -> 21229 | U37: =Rent!D$33-Rent!#REF! -> #REF! | W37: =Rent!D$33 -> 51058
A38: 50540 | B38: Parking Lot Repairs | C38: 0 | D38: 0 | E38: 0 | F38: 0 | H38: 0 | I38: =SUM(C38:H38) -> 0 | J38: 0 | K38: 0 | L38: 0 | M38: 0 | N38: 0 | O38: 18890 | P38: =SUM(C38:O38) -> 18890 | Q38: =P38/U38 -> #REF! | R38: 0 | S38: 0 | T38: =+P38-R38 -> 18890 | U38: =Rent!D$33-Rent!#REF! -> #REF! | W38: =Rent!D$33 -> 51058
A39: 50560 | B39: Fountain Maintenance | C39: 0 | D39: 0 | E39: 0 | F39: 0 | G39: 0 | H39: 0 | I39: =SUM(C39:H39) -> 0 | J39: 0 | K39: 0 | L39: 0 | M39: 0 | N39: 0 | O39: 0 | P39: =SUM(C39:O39) -> 0 | Q39: =P39/U39 -> #REF! | S39: 0 | T39: =+P39-R39 -> 0 | U39: =+U38 -> #REF! | W39: =Rent!D$33 -> 51058
A40: 50570 | B40: Fountain Repair | C40: 0 | D40: 0 | E40: 0 | F40: 0 | G40: 0 | H40: 0 | I40: =SUM(C40:H40) -> 0 | J40: 0 | K40: 0 | L40: 0 | M40: 0 | N40: 0 | O40: 0 | P40: =SUM(C40:O40) -> 0 | Q40: =P40/U40 -> #REF! | S40: 0 | T40: =+P40-R40 -> 0 | U40: =+U39 -> #REF! | W40: =Rent!D$33 -> 51058
A41: 50550 | B41: Sign Maintenance | C41: 0 | D41: 0 | I41: =SUM(C41:H41) -> 0 | M41: 0 | N41: 0 | O41: 0 | P41: =SUM(C41:O41) -> 0 | Q41: =P41/U41 -> #REF! | S41: 0 | T41: =+P41-R41 -> 0 | U41: =Rent!D$33-Rent!#REF! -> #REF! | W41: =Rent!D$33 -> 51058
A42: 50551 | B42: Sign Repairs | C42: 0 | D42: 0 | E42: 1000 | F42: 0 | G42: 0 | H42: 0 | I42: =SUM(C42:H42) -> 1000 | J42: 0 | K42: 0 | L42: 1000 | M42: 0 | N42: 0 | O42: 0 | P42: =SUM(C42:O42) -> 3000 | Q42: =P42/U42 -> #REF! | R42: 1718 | S42: 2000 | T42: =+P42-R42 -> 1282 | U42: =Rent!D$33-Rent!#REF! -> #REF! | W42: =Rent!D$33 -> 51058
A43: 51010 | B43: Awning Maintenance | C43: 0 | D43: 0 | E43: 0 | F43: 0 | G43: 0 | H43: 0 | I43: =SUM(C43:H43) -> 0 | J43: 0 | K43: 0 | L43: 0 | M43: 0 | N43: 0 | O43: 0 | P43: =SUM(C43:O43) -> 0 | Q43: =P43/U43 -> #REF! | S43: 0 | T43: =+P43-R43 -> 0 | U43: =Rent!D$33-Rent!#REF! -> #REF! | W43: =Rent!D$33 -> 51058
A44: 51020 | B44: General Maintenance | C44: 625 | D44: 625 | E44: 625 | F44: 625 | G44: 625 | H44: 625 | I44: =SUM(C44:H44) -> 3750 | J44: 625 | K44: 625 | L44: 625 | M44: 625 | N44: 625 | O44: 625 | P44: =SUM(C44:O44) -> 11250 | Q44: =P44/U44 -> #REF! | R44: 6880 | S44: 7500 | T44: =+P44-R44 -> 4370 | U44: =Rent!D$33-Rent!#REF! -> #REF! | W44: =Rent!D$33 -> 51058
A45: 51023 | B45: Site Furnishing-Repairs | D45: 0 | E45: 0 | F45: 0 | G45: 0 | H45: 0 | I45: =SUM(C45:H45) -> 0 | J45: 0 | K45: 0 | L45: 0 | M45: 0 | N45: 0 | O45: 0 | P45: =SUM(C45:O45) -> 0 | Q45: =P45/U45 -> #REF! | S45: 0 | T45: =+P45-R45 -> 0 | U45: =Rent!D$33-Rent!#REF! -> #REF! | W45: =Rent!D$33 -> 51058
A46: 51030 | B46: Misc. Maintenance & Repairs | C46: 0 | D46: 0 | E46: 0 | F46: 0 | G46: 0 | H46: 0 | I46: =SUM(C46:H46) -> 0 | J46: 0 | K46: 0 | L46: 0 | M46: 0 | N46: 0 | O46: 0 | P46: =SUM(C46:O46) -> 0 | Q46: =P46/U46 -> #REF! | S46: 0 | T46: =+P46-R46 -> 0 | U46: =Rent!D$33-Rent!#REF! -> #REF! | W46: =Rent!D$33 -> 51058
A47: 51040 | B47: Janitorial/Day porter | C47: 4024 | D47: 4024 | E47: 4024 | F47: 4024 | G47: 4024 | H47: 4024 | I47: =SUM(C47:H47) -> 24144 | J47: 4024 | K47: 4024 | L47: 4024 | M47: 4864 | N47: 4864 | O47: 4864 | P47: =SUM(C47:O47) -> 74952 | Q47: =P47/U47 -> #REF! | R47: 47112 | S47: 47112 | T47: =+P47-R47 -> 27840 | U47: =Rent!D$33-Rent!#REF! -> #REF! | W47: =Rent!D$33 -> 51058
A48: - | B48: Window Washing Maint. | C48: 0 | D48: 0 | E48: 0 | F48: 0 | G48: 0 | H48: 0 | I48: =SUM(C48:H48) -> 0 | J48: 0 | K48: 0 | L48: 0 | M48: 0 | N48: 0 | O48: 0 | P48: =SUM(C48:O48) -> 0 | Q48: =P48/U48 -> #REF! | S48: 0 | T48: =+P48-R48 -> 0 | U48: =Rent!D$33-Rent!#REF! -> #REF! | W48: =Rent!D$33 -> 51058
A49: 51050 | B49: Pest Control Maintenance | C49: 230 | D49: 230 | E49: 230 | F49: 230 | G49: 230 | H49: 230 | I49: =SUM(C49:H49) -> 1380 | J49: 230 | K49: 230 | L49: 230 | M49: 230 | N49: 230 | O49: 230 | P49: =SUM(C49:O49) -> 4140 | Q49: =P49/U49 -> #REF! | R49: 1860 | S49: 1860 | T49: =+P49-R49 -> 2280 | U49: =Rent!D$33-Rent!#REF! -> #REF! | W49: =Rent!D$33 -> 51058
A50: 51055 | B50: Advertising/Promo | C50: 0 | D50: 0 | E50: 0 | F50: 0 | G50: 0 | H50: 0 | I50: =SUM(C50:H50) -> 0 | J50: 0 | K50: 0 | L50: 0 | M50: 0 | N50: 0 | O50: 0 | P50: =SUM(C50:O50) -> 0 | Q50: =P50/U50 -> #REF! | S50: 0 | T50: =+P50-R50 -> 0 | U50: =Rent!D$33-Rent!#REF! -> #REF! | W50: =Rent!D$33 -> 51058
A51: 51074 | B51: Music System Maintenance | C51: 0 | D51: 0 | E51: 0 | F51: 0 | G51: 0 | H51: 0 | I51: =SUM(C51:H51) -> 0 | J51: 0 | K51: 0 | L51: 0 | M51: 0 | N51: 0 | O51: 0 | P51: =SUM(C51:O51) -> 0 | Q51: =P51/U51 -> #REF! | S51: 0 | T51: =+P51-R51 -> 0 | U51: =Rent!D$33-Rent!#REF! -> #REF! | W51: =Rent!D$33 -> 51058
A52: 51075 | B52: Music System Repairs | C52: 0 | D52: 0 | E52: 0 | F52: 0 | G52: 0 | H52: 0 | I52: =SUM(C52:H52) -> 0 | J52: 0 | K52: 0 | L52: 0 | M52: 0 | N52: 0 | O52: 0 | P52: =SUM(C52:O52) -> 0 | Q52: =P52/U52 -> #REF! | S52: 0 | T52: =+P52-R52 -> 0 | U52: =Rent!D$33-Rent!#REF! -> #REF! | W52: =Rent!D$33 -> 51058
A53: 51080 | B53: On-Site Management | C53: 5730 | D53: 5730 | E53: 5730 | F53: 5730 | G53: 5730 | H53: 5730 | I53: =SUM(C53:H53) -> 34380 | J53: 5730 | K53: 5730 | L53: 5730 | M53: 5730 | N53: 5730 | O53: 5730 | P53: =SUM(C53:O53) -> 103140 | Q53: =P53/U53 -> #REF! | R53: 56352 | S53: 56500 | T53: =+P53-R53 -> 46788 | U53: =Rent!D$33-Rent!#REF! -> #REF! | W53: =Rent!D$33 -> 51058
A54: 51100 | B54: Sidewalk Maintenance | C54: 0 | D54: 0 | E54: 0 | F54: 0 | G54: 0 | H54: 0 | I54: =SUM(C54:H54) -> 0 | J54: 0 | K54: 0 | L54: 0 | M54: 0 | N54: 0 | O54: 0 | P54: =SUM(C54:O54) -> 0 | Q54: =P54/U54 -> #REF! | S54: 0 | T54: =+P54-R54 -> 0 | U54: =Rent!D$33-Rent!#REF! -> #REF! | W54: =Rent!D$33 -> 51058
A55: 51130 | B55: HVAC Maintenance | C55: 1297 | D55: 0 | E55: 0 | F55: 1297 | G55: 0 | H55: 0 | I55: =SUM(C55:H55) -> 2594 | J55: 1297 | K55: 0 | L55: 0 | M55: 1297 | N55: 0 | O55: 0 | P55: =SUM(C55:O55) -> 7782 | Q55: =P55/U55 -> #REF! | S55: 0 | T55: =+P55-R55 -> 7782 | U55: =Rent!D$33-Rent!#REF! -> #REF! | W55: =Rent!D$33-Rent!D14-Rent!#REF!-Rent!#REF!-Rent!D23 -> #REF!
A56: 51140 | B56: HVAC Repairs/Labor | C56: 0 | D56: 0 | E56: 0 | F56: 0 | G56: 0 | H56: 0 | I56: =SUM(C56:H56) -> 0 | J56: 0 | K56: 0 | L56: 0 | M56: 0 | N56: 0 | O56: 0 | P56: =SUM(C56:O56) -> 0 | Q56: =P56/U56 -> #REF! | S56: 0 | T56: =+P56-R56 -> 0 | U56: =Rent!D$33-Rent!#REF! -> #REF! | W56: =Rent!D$33 -> 51058
A57: 51150 | B57: Sweeping | C57: 710.7 | D57: 710.7 | E57: 710.7 | F57: 710.7 | G57: 710.7 | H57: 710.7 | I57: =SUM(C57:H57) -> 4264.2 | J57: 710.7 | K57: 710.7 | L57: 710.7 | M57: 710.7 | N57: 710.7 | O57: 710.7 | P57: =SUM(C57:O57) -> 12792.6 | Q57: =P57/U57 -> #REF! | R57: 8280 | S57: 8280 | T57: =+P57-R57 -> 4512.6 | U57: =Rent!D$33-Rent!#REF! -> #REF! | W57: =Rent!D$33 -> 51058
A58: 51160 | B58: Security | D58: 0 | E58: 0 | F58: 0 | G58: 0 | H58: 0 | I58: =SUM(C58:H58) -> 0 | J58: 0 | K58: 0 | L58: 0 | M58: 0 | N58: 0 | O58: 0 | P58: =SUM(C58:O58) -> 0 | Q58: =P58/U58 -> #REF! | S58: 0 | T58: =+P58-R58 -> 0 | U58: =Rent!D$33-Rent!#REF! -> #REF! | W58: =Rent!D$33 -> 51058
A59: 51190 | B59: Concrete Repairs | C59: 0 | D59: 0 | E59: 0 | F59: 0 | G59: 0 | H59: 0 | I59: =SUM(C59:H59) -> 0 | J59: 0 | K59: 0 | L59: 0 | M59: 0 | N59: 0 | O59: 0 | P59: =SUM(C59:O59) -> 0 | Q59: =P59/U59 -> #REF! | S59: 0 | T59: =+P59-R59 -> 0 | U59: =Rent!D$33-Rent!#REF! -> #REF! | W59: =Rent!D$33 -> 51058
A60: 50103 | B60: Permits & Fee - Waste Insp. Fee | C60: 0 | D60: 0 | E60: 0 | F60: 0 | G60: 0 | H60: 0 | I60: =SUM(C60:H60) -> 0 | J60: 0 | K60: 0 | L60: 0 | M60: 0 | N60: 0 | O60: 0 | P60: =SUM(C60:O60) -> 0 | Q60: =P60/U60 -> #REF! | S60: 0 | T60: =+P60-R60 -> 0 | U60: =Rent!D$33-Rent!#REF! -> #REF! | W60: =Rent!D$33 -> 51058
A61: 51170 | B61: Locksmith | C61: 0 | D61: 0 | E61: 0 | F61: 0 | G61: 0 | H61: 0 | I61: =SUM(C61:H61) -> 0 | J61: 0 | K61: 0 | L61: 0 | M61: 0 | N61: 0 | O61: 0 | P61: =SUM(C61:O61) -> 0 | Q61: =P61/U61 -> #REF! | S61: 0 | T61: =+P61-R61 -> 0 | U61: =Rent!D$33-Rent!#REF! -> #REF! | W61: =Rent!D$33 -> 51058
A62: 0 | B62: Electrical Repairs/Building | C62: 0 | D62: 0 | E62: 0 | F62: 0 | G62: 0 | H62: 0 | I62: =SUM(C62:H62) -> 0 | J62: 0 | K62: 0 | L62: 0 | M62: 0 | N62: 0 | O62: 0 | P62: =SUM(C62:O62) -> 0 | Q62: =P62/U62 -> #REF! | S62: 0 | T62: =+P62-R62 -> 0 | U62: =Rent!D$33-Rent!#REF! -> #REF! | W62: =Rent!D$33 -> 51058
A63: 51200 | B63: Electrical Repairs/Common Area | C63: 0 | D63: 0 | E63: 0 | F63: 0 | G63: 0 | H63: 0 | I63: =SUM(C63:H63) -> 0 | J63: 0 | K63: 0 | L63: 0 | M63: 0 | N63: 0 | O63: 0 | P63: =SUM(C63:O63) -> 0 | Q63: =P63/U63 -> #REF! | S63: 0 | T63: =+P63-R63 -> 0 | U63: =Rent!D$33-Rent!#REF! -> #REF! | W63: =Rent!D$33 -> 51058
A64: 0 | B64: Supplies Electrical | C64: 0 | D64: 0 | E64: 0 | F64: 0 | G64: 0 | H64: 0 | I64: =SUM(C64:H64) -> 0 | J64: 0 | K64: 0 | L64: 0 | M64: 0 | N64: 0 | O64: 0 | P64: =SUM(C64:O64) -> 0 | Q64: =P64/U64 -> #REF! | S64: 0 | T64: =+P64-R64 -> 0 | U64: =Rent!D$33-Rent!#REF! -> #REF! | W64: =Rent!D$33 -> 51058
A65: 51210 | B65: Plumbing Repairs | D65: 0 | E65: 1000 | G65: 0 | H65: 1350 | I65: =SUM(C65:H65) -> 2350 | J65: 0 | K65: 0 | L65: 1000 | N65: 0 | O65: 0 | P65: =SUM(C65:O65) -> 5700 | Q65: =P65/U65 -> #REF! | R65: 500 | S65: 4550 | T65: =+P65-R65 -> 5200 | U65: =Rent!D$33-Rent!#REF! -> #REF! | W65: =Rent!D$33-Rent!#REF! -> #REF!
A66: 51220 | B66: Painting | C66: 0 | D66: 0 | E66: 0 | F66: 0 | G66: 0 | H66: 0 | I66: =SUM(C66:H66) -> 0 | J66: 0 | K66: 0 | L66: 0 | M66: 0 | N66: 0 | O66: 0 | P66: =SUM(C66:O66) -> 0 | Q66: =P66/U66 -> #REF! | S66: 0 | T66: =+P66-R66 -> 0 | U66: =Rent!D$33-Rent!#REF! -> #REF! | W66: =Rent!D$33-Rent!D14-Rent!#REF! -> #REF!
A67: 0 | B67: Wall & Block Repairs | C67: 0 | D67: 0 | E67: 0 | F67: 0 | G67: 0 | H67: 0 | I67: =SUM(C67:H67) -> 0 | J67: 0 | K67: 0 | L67: 0 | M67: 0 | N67: 0 | O67: 0 | P67: =SUM(C67:O67) -> 0 | Q67: =P67/U67 -> #REF! | S67: 0 | T67: =+P67-R67 -> 0 | U67: =Rent!D$33-Rent!#REF! -> #REF! | W67: =Rent!D$33 -> 51058
A68: 0 | B68: Window Repairs | C68: 0 | D68: 0 | E68: 0 | F68: 0 | G68: 0 | H68: 0 | I68: =SUM(C68:H68) -> 0 | J68: 0 | K68: 0 | L68: 0 | M68: 0 | N68: 0 | O68: 0 | P68: =SUM(C68:O68) -> 0 | Q68: =P68/U68 -> #REF! | S68: 0 | T68: =+P68-R68 -> 0 | U68: =Rent!D$33-Rent!#REF! -> #REF! | W68: =Rent!D$33 -> 51058
A69: 52010 | B69: Janitorial Supplies | C69: 100 | F69: 100 | I69: =SUM(C69:H69) -> 200 | J69: 100 | M69: 100 | P69: =SUM(C69:O69) -> 600 | Q69: =P69/U69 -> #REF! | R69: 425 | S69: 1200 | T69: =+P69-R69 -> 175 | U69: =Rent!D$33-Rent!#REF! -> #REF! | W69: =Rent!D$33 -> 51058
A70: 0 | B70: Banners - Seasonal | C70: 0 | D70: 0 | E70: 0 | F70: 0 | G70: 0 | H70: 0 | I70: =SUM(C70:H70) -> 0 | J70: 0 | K70: 0 | L70: 0 | M70: 0 | N70: 0 | O70: 0 | P70: =SUM(C70:O70) -> 0 | Q70: =P70/U70 -> #REF! | S70: 0 | T70: =+P70-R70 -> 0 | U70: =Rent!D$33-Rent!#REF! -> #REF! | W70: =Rent!D$33 -> 51058
A71: 51230 | B71: Christmas Decorations | C71: 0 | D71: 0 | E71: 0 | F71: 0 | G71: 0 | H71: 0 | I71: =SUM(C71:H71) -> 0 | J71: 0 | K71: 0 | L71: 0 | M71: 0 | N71: 0 | O71: 0 | P71: =SUM(C71:O71) -> 0 | Q71: =P71/U71 -> #REF! | S71: 0 | T71: =+P71-R71 -> 0 | U71: =Rent!D$33-Rent!#REF! -> #REF! | W71: =Rent!D$33 -> 51058
A72: 50220 | B72: Street Light Maint. | C72: 570 | D72: 570 | E72: 570 | F72: 570 | G72: 570 | H72: 570 | I72: =SUM(C72:H72) -> 3420 | J72: 570 | K72: 570 | L72: 570 | M72: 570 | N72: 570 | O72: 570 | P72: =SUM(C72:O72) -> 10260 | Q72: =P72/U72 -> #REF! | R72: 6800 | S72: 6840 | T72: =+P72-R72 -> 3460 | U72: =Rent!D$33-Rent!#REF! -> #REF! | W72: =Rent!D$33 -> 51058
A73: 55160 | B73: Gas | C73: 0 | D73: 0 | E73: 0 | F73: 0 | G73: 0 | H73: 0 | I73: =SUM(C73:H73) -> 0 | J73: 0 | K73: 0 | L73: 0 | M73: 0 | N73: 0 | O73: 0 | P73: =SUM(C73:O73) -> 0 | Q73: =P73/U73 -> #REF! | S73: 0 | T73: =+P73-R73 -> 0 | U73: =Rent!D$33-Rent!#REF! -> #REF! | W73: =Rent!D$33 -> 51058
A74: 55110 | B74: Electric/Common Area | C74: 3000 | D74: 3000 | E74: 3000 | F74: 3000 | G74: 3000 | H74: 3000 | I74: =SUM(C74:H74) -> 18000 | J74: 3000 | K74: 3000 | L74: 3000 | M74: 3000 | N74: 3000 | O74: 3000 | P74: =SUM(C74:O74) -> 54000 | Q74: =P74/U74 -> #REF! | R74: 33619 | S74: 38400 | T74: =+P74-R74 -> 20381 | U74: =+U73 -> #REF! | W74: =Rent!D$33 -> 51058
A75: 55140 | B75: Water/Common Area | C75: 850 | D75: 850 | E75: 850 | F75: 850 | G75: 850 | H75: 850 | I75: =SUM(C75:H75) -> 5100 | J75: 850 | K75: 850 | L75: 850 | M75: 850 | N75: 850 | O75: 850 | P75: =SUM(C75:O75) -> 15300 | Q75: =P75/U75 -> #REF! | R75: 11553 | S75: 20436 | T75: =+P75-R75 -> 3747 | U75: =+U74 -> #REF! | W75: =Rent!D$33 -> 51058
T76: =+P76-R76 -> 0
B77: SUBTOTAL COMMON AREA | C77: =SUM(C32:C76) -> 28547.7 | D77: =SUM(D32:D76) -> 27291.7 | E77: =SUM(E32:E76) -> 25836.7 | F77: =SUM(F32:F76) -> 24963.7 | G77: =SUM(G32:G76) -> 21041.7 | H77: =SUM(H32:H76) -> 24171.7 | I77: =SUM(I32:I76) -> 151853.2 | J77: =SUM(J32:J76) -> 22568.7 | ... S77: =SUM(S32:S76) -> 325192 | T77: =+P77-R77 -> 165037.6
B79: BUILDING EXPENSE
A81: 51060 | B81: Roof Maintenance | C81: 0 | D81: 0 | E81: 0 | G81: 1176.27 | H81: 0 | I81: =SUM(C81:H81) -> 1176.27 | J81: 0 | L81: 0 | M81: 0 | N81: 1176.27 | O81: 0 | P81: =SUM(C81:O81) -> 3528.81 | Q81: =+P81/U81 -> #REF! | R81: 2108 | S81: 1054 | T81: =+P81-R81 -> 1420.81 | U81: =+W81 -> #REF! | W81: =Rent!D$33-Rent!#REF!-Rent!D14 -> #REF! | Y81: Reroof?
A82: 51070 | B82: Roof Repairs | C82: 0 | D82: 0 | E82: 0 | F82: 0 | G82: 5562.5 | H82: 0 | I82: =SUM(C82:H82) -> 5562.5 | J82: 0 | K82: 0 | L82: 4746.5 | M82: 0 | N82: 0 | O82: 0 | P82: =SUM(C82:O82) -> 15871.5 | Q82: =+P82/U82 -> #REF! | R82: 6883 | S82: 3788 | T82: =+P82-R82 -> 8988.5 | U82: =+W82 -> #REF! | W82: =Rent!D$33-Rent!#REF!-Rent!D14 -> #REF!
A83: 51110 | B83: Monitor Fire Sprinklers | D83: 420 | G83: 420 | I83: =SUM(C83:H83) -> 840 | K83: 420 | N83: 420 | P83: =SUM(C83:O83) -> 2520 | Q83: =+P83/U83 -> #REF! | R83: 5147 | S83: 2904 | T83: =+P83-R83 -> -2627 | U83: =+W83 -> #REF! | W83: =Rent!D$33-Rent!D14-Rent!#REF! -> #REF!
A84: 51120 | B84: Fire Protection Repairs | C84: 0 | D84: 0 | E84: 250 | F84: 0 | G84: 0 | H84: 0 | I84: =SUM(C84:H84) -> 250 | J84: 0 | K84: 0 | L84: 250 | M84: 0 | N84: 0 | O84: 0 | P84: =SUM(C84:O84) -> 750 | Q84: =+P84/U84 -> #REF! | R84: 923 | S84: 0 | T84: =+P84-R84 -> -173 | U84: =+W84 -> #REF! | W84: =Rent!D$33-Rent!D14-Rent!#REF! -> #REF!
A85: 52020 | B85: Backflow Maintenance | C85: 0 | D85: 0 | E85: 0 | F85: 0 | G85: 0 | H85: 300 | I85: =SUM(C85:H85) -> 300 | J85: 0 | K85: 0 | L85: 0 | M85: 0 | N85: 0 | O85: 0 | P85: =SUM(C85:O85) -> 600 | Q85: =+P85/U85 -> #REF! | R85: 180 | S85: 300 | T85: =+P85-R85 -> 420 | U85: =+W85 -> #REF! | W85: =Rent!D$33-Rent!#REF! -> #REF!
A86: 52030 | B86: Backflow Repairs | C86: 0 | D86: 0 | E86: 0 | F86: 0 | G86: 0 | H86: 0 | I86: =SUM(C86:H86) -> 0 | J86: 500 | K86: 0 | L86: 0 | M86: 0 | N86: 0 | O86: 0 | P86: =SUM(C86:O86) -> 500 | Q86: =+P86/U86 -> #REF! | R86: 721 | S86: 500 | T86: =+P86-R86 -> -221 | U86: =+W86 -> #REF! | W86: =Rent!D$33-Rent!#REF! -> #REF!
A87: 55120 | B87: Trash Removal Shops 1 | C87: 1263.09 | D87: 1263.09 | E87: 1263.09 | F87: 1263.09 | G87: 1263.09 | H87: 1263.09 | I87: =SUM(C87:H87) -> 7578.54 | J87: 1263.09 | K87: 1263.09 | L87: 1263.09 | M87: 1263.09 | N87: 1263.09 | O87: 1263.09 | P87: =SUM(C87:O87) -> 22735.62 | Q87: =+P87/U87 -> #REF! | R87: 35712 | S87: 35748 | T87: =+P87-R87 -> -12976.38 | U87: =+#REF! -> #REF! | W87: =+#REF! -> #REF!
A88: 55120 | B88: Trash Removal Foodcourt | C88: 1894.65 | D88: 1894.65 | E88: 1894.65 | F88: 1894.65 | G88: 1894.65 | H88: 1894.65 | I88: =SUM(C88:H88) -> 11367.9 | J88: 1894.65 | K88: 1894.65 | L88: 1894.65 | M88: 1894.65 | N88: 1894.65 | O88: 1894.65 | P88: =SUM(C88:O88) -> 34103.7 | Q88: =+P88/U88 -> #REF! | R88: 35713 | S88: 35749 | T88: =+P88-R88 -> -1609.3 | U88: =+#REF! -> #REF! | W88: =+#REF! -> #REF!
A89: 51180 | B89: Grease Trap Maintenance | C89: 0 | D89: 0 | E89: 0 | F89: 0 | G89: 0 | H89: 0 | I89: =SUM(C89:H89) -> 0 | J89: 0 | K89: 0 | L89: 0 | M89: 0 | N89: 0 | O89: 0 | P89: =SUM(C89:O89) -> 0 | Q89: =+P89/U89 -> #REF! | S89: 0 | T89: =+P89-R89 -> 0 | U89: =+W89 -> #REF! | W89: =Rent!D$33-Rent!D14-Rent!#REF! -> #REF!
A90: 55130 | B90: Water/Building | C90: 2400 | D90: 2400 | E90: 2400 | F90: 2400 | G90: 2400 | H90: 2400 | I90: =SUM(C90:H90) -> 14400 | J90: 2400 | K90: 2400 | L90: 2400 | M90: 2400 | N90: 2400 | O90: 2400 | P90: =SUM(C90:O90) -> 43200 | Q90: =+P90/U90 -> #REF! | R90: 28453 | S90: 35400 | T90: =+P90-R90 -> 14747 | U90: =+W90 -> #REF! | W90: =Rent!D$33-Rent!D14-Rent!#REF! -> #REF!
T91: =+P91-R91 -> 0
B92: SUBTOTAL BUILDING EXP. | C92: =SUM(C81:C91) -> 5557.74 | D92: =SUM(D81:D91) -> 5977.74 | E92: =SUM(E81:E91) -> 5807.74 | F92: =SUM(F81:F91) -> 5557.74 | G92: =SUM(G81:G91) -> 12716.51 | H92: =SUM(H81:H91) -> 5857.74 | I92: =SUM(I81:I91) -> 41475.21 | J92: =SUM(J81:J91) -> 6057.74 | K92: =SUM(K82:K91) -> 5977.74 | L92: =SUM(L81:L91) -> 10554.24 | M92: =SUM(M81:M91) -> 5557.74 | N92: =SUM(N81:N91) -> 7154.01 | O92: =SUM(O81:O91) -> 5557.74 | P92: =SUM(P81:P91) -> 123809.63 | Q92: =SUM(Q81:Q91) -> #REF! | R92: =SUM(R81:R91) -> 115840 | S92: =SUM(S81:S91) -> 115443 | T92: =+P92-R92 -> 7969.63 | V92: =SUM(V81:V91) -> 0
B94: INSURANCE
A96: 50111 | B96: Insurance - Property | C96: 1035.6 | D96: 1035.6 | E96: 1035.6 | F96: 1035.6 | G96: 1035.6 | H96: 1035.6 | I96: =SUM(C96:H96) -> 6213.6 | J96: 1035.6 | K96: 1087.38 | L96: 1087 | M96: 1087 | N96: 1087 | O96: 1087 | P96: =SUM(C96:O96) -> 18898.18 | Q96: =P96/U96 -> #REF! | R96: 12936 | S96: 14640 | T96: =+P96-R96 -> 5962.18 | U96: =U86 -> #REF! | W96: =Rent!D$33-Rent!D$14-Rent!#REF! -> #REF!
A97: 50112 | B97: Insurance - General Liability | C97: 540 | D97: 540 | E97: 540 | F97: 540 | G97: 540 | H97: 540 | I97: =SUM(C97:H97) -> 3240 | J97: 540 | K97: 567 | L97: 567 | M97: 567 | N97: 567 | O97: 567 | P97: =SUM(C97:O97) -> 9855 | R97: 3170 | S97: 3264 | T97: =+P97-R97 -> 6685 | U97: =+U96 -> #REF! | W97: =Rent!D$33-Rent!D$14 -> 47185
A98: 50120 | B98: Insurance - Fire / Extd Covg | C98: 0 | D98: 0 | E98: 0 | F98: 0 | G98: 0 | H98: 0 | I98: =SUM(C98:H98) -> 0 | J98: 0 | K98: 0 | L98: 0 | M98: 0 | N98: 0 | O98: 0 | P98: =SUM(C98:O98) -> 0 | Q98: =P98/U98 -> #REF! | S98: 0 | T98: =+P98-R98 -> 0 | U98: =+U97 -> #REF! | W98: =Rent!D$33-Rent!D$14 -> 47185
A99: 50130 | B99: Insurance - Umbrella | C99: 236 | D99: 236 | E99: 236 | F99: 236 | G99: 236 | H99: 236 | I99: =SUM(C99:H99) -> 1416 | J99: 236 | K99: 247.8 | L99: 248 | M99: 248 | N99: 248 | O99: 248 | P99: =SUM(C99:O99) -> 4307.8 | Q99: =P99/U99 -> #REF! | R99: 2745 | S99: 2724 | T99: =+P99-R99 -> 1562.8 | U99: =U98 -> #REF! | W99: =Rent!D$33-Rent!D$14 -> 47185
A100: 50140 | B100: Insurance - Flood/Earthquake | C100: 0 | D100: 0 | E100: 0 | F100: 0 | G100: 0 | H100: 0 | I100: =SUM(C100:H100) -> 0 | J100: 0 | K100: 0 | L100: 0 | M100: 0 | N100: 0 | O100: 0 | P100: =SUM(C100:O100) -> 0 | Q100: =P100/U100 -> #REF! | S100: 0 | T100: =+P100-R100 -> 0 | U100: =U99 -> #REF! | W100: =Rent!D$33-Rent!D$14 -> 47185
A101: 50142 | B101: Insurance - Pollution | C101: 1388.83 | D101: 1388.83 | E101: 1388.83 | F101: 1388.83 | G101: 1388.83 | H101: 1388.83 | I101: =SUM(C101:H101) -> 8332.98 | J101: 1388.83 | K101: 1388.83 | L101: 1388.83 | M101: 1388.83 | N101: 1388.83 | O101: 1388.83 | P101: =SUM(C101:O101) -> 24998.94 | Q101: =P101/U101 -> #REF! | R101: 16666 | S101: 16668 | T101: =+P101-R101 -> 8332.94 | U101: =U99 -> #REF! | W101: =Rent!D$33-Rent!D$14 -> 47185
B102: Insurance - Miscellaneous | C102: 0 | D102: 0 | E102: 0 | F102: 0 | G102: 0 | H102: 0 | I102: =SUM(C102:H102) -> 0 | J102: 0 | K102: 0 | L102: 0 | M102: 0 | N102: 0 | O102: 0 | P102: =SUM(C102:O102) -> 0 | Q102: =P102/U102 -> #REF! | S102: 0 | T102: =+P102-R102 -> 0 | U102: =U99 -> #REF! | W102: =Rent!D$33-Rent!D$14 -> 47185
T103: =+P103-R103 -> 0
B104: SUBTOTAL INSURANCE | C104: =SUM(C96:C103) -> 3200.43 | D104: =SUM(D96:D103) -> 3200.43 | E104: =SUM(E96:E103) -> 3200.43 | F104: =SUM(F96:F103) -> 3200.43 | G104: =SUM(G96:G103) -> 3200.43 | H104: =SUM(H96:H103) -> 3200.43 | I104: =SUM(I96:I103) -> 19202.58 | J104: =SUM(J96:J103) -> 3200.43 | ... S104: =SUM(S96:S103) -> 37296 | T104: =+P104-R104 -> 22542.92
B106: PROPERTY TAXES
A108: 54000 | B108: Property Tax | F108: 122903.25 | I108: =SUM(C108:H108) -> 122903.25 | J108: 18322.974 | K108: 18322.974 | L108: 18322.974 | M108: 18322.974 | N108: 18322.974 | O108: 18322.974 | P108: =SUM(C108:O108) -> 355744.34 | Q108: =P108/U108 -> #REF! | R108: 265187 | S108: 247890 | T108: =+P108-R108 -> 90557.344 | U108: =+Rent!D33-Rent!#REF!-Rent!D14 -> #REF! | W108: =Rent!D33-Rent!D14-Rent!#REF! -> #REF!
B110: SUBTOTAL TAXES | C110: =SUM(C108:C109) -> 0 | D110: =SUM(D108:D109) -> 0 | E110: =SUM(E108:E109) -> 0 | F110: =SUM(F108:F109) -> 122903.25 | G110: =SUM(G108:G109) -> 0 | H110: =SUM(H108:H109) -> 0 | I110: =SUM(I108:I109) -> 122903.25 | J110: =SUM(J108:J109) -> 18322.974 | ... S110: =SUM(S108:S109) -> 247890 | T110: =+P110-R110 -> 90557.344 | Z110: 10708.03
Z111: 15769.75
B112: TOTAL COMMON AREA | C112: =C77+C92+C104+C110 -> 37305.87 | D112: =D77+D92+D104+D110 -> 36469.87 | E112: =E77+E92+E104+E110 -> 34844.87 | F112: =F77+F92+F104+F110 -> 156625.12 | G112: =G77+G92+G104+G110 -> 36958.64 | H112: =H77+H92+H104+H110 -> 33229.87 | I112: =I77+I92+I104+I110 -> 335434.24 | J112: =J77+J92+J104+J110 -> 50149.844 | ... Q112: =Q77+Q92+Q104+Q110 -> #REF! | R112: =+R110+R104+R92+R77 -> 717762 | S112: =+S110+S104+S92+S77 -> 725821 | T112: =+P112-R112 -> 286107.49 | U112: =U77+U92+U104+U110 -> 0 | V112: =V77+V92+V104+V110 -> 0 | Z112: 18497
...

Sheet CAPEX
B3: AMORTIZED PROJECTS
B5: DESCRIPTION | C5: GL CODE | D5: TOTAL PROJECT COST | F5: COST PER YR | G5: # OF YEARS | H5: DATES | K5: NOTES
B6: Asphalt Repair, Slurry Seal, & Stripe | D6: 85000 | F6: =D6/3 -> 28333.333 | G6: 0 | H6: 2025 | K6: projectt on hold - $28K for 2026 for repairs
B7: Paint
B8: Stairwell project
B13: CAP-EX
C15: ACTUAL | D15: ACTUAL | E15: FORECAST | F15: BUDGET | G15: PROJECTED | H15: PROJECTED | I15: PROJECTED | J15: PROJECTED
B16: DESCRIPTION | C16: 2023 | D16: 2024 | E16: 2025 | F16: 2026 | G16: 2027 | H16: 2028 | I16: 2029 | J16: 2030 | K16: NOTES
B17: Parking Lot/Garage | E17: 0 | F17: 28000 | K17: repairs & stripe
B18: Electrical/Lighting
B19: Roof
B20: Paint
B21: Landscape
B22: HVAC
B23: Plumbing
B28: MAINTENANCE TRACKING
B30: DESCRIPTION | D30: COMPLETED | E30: DUE | G30: VENDOR | I30: NOTES
B31: 5-Year Fire Inspection | E31: 2025 | F31: Guardian
B32: Slurry Seal | E32: 2025 | I32: Pricing provided by Manny with SVN - pushed to 2026
B33: Roof
B34: Paint
B35: LED
B36: Elevator | E36: 2024 | F36: Otis | I36: repairs completed 2024-2025

Sheet Rent
Q1: =Summ.!R1 -> Date Revised: | R1: =Summ.!#REF! -> #REF! | T1: =Summ.!T1 -> 0
A2: =Summ.!$A2 -> ATHENA PROPERTY MANAGEMENT
A3: =Summ.!$A3 -> Coconut Grove - Kona Hawaii
A4: =Summ.!$A4 -> PROJECT NO. 165
A5: =Summ.!$A5 -> 01/01/26- 12/31/26
A6: =Summ.!$A6 -> 2026 OPERATING BUDGET
A9: TENANT | B9: SUITE | C9: Expiration | D9: SQUARE | E9: RATE | F9: JAN | G9: FEB | H9: MARCH | I9: APRIL | J9: MAY | K9: JUNE | L9: JULY | M9: AUGUST | N9: SEPT | O9: OCT | P9: NOV | Q9: DEC | R9: TOTALS | S9: NOTES
B10: # | D10: FOOTAGE
A12: ESTIMATED BASE RENT
A14: ISLAND LAVA JAVA | B14: A 1-4 | C14: 48365 | D14: 3873 | E14: =Q14/D14*12 -> 48.965267 | F14: 15803.54 | G14: =F14 -> 15803.54 | H14: =G14 -> 15803.54 | I14: =H14 -> 15803.54 | J14: =I14 -> 15803.54 | K14: =J14 -> 15803.54 | L14: =K14 -> 15803.54 | M14: =L14 -> 15803.54 | N14: =M14 -> 15803.54 | ... Q14: =P14 -> 15803.54 | R14: =SUM(F14:Q14) -> 189642.48 | S14: Next increase 6/1/2027
A15: TAKA SUSHI | B15: B-5 | C15: 46752 | D15: 1074 | E15: =Q15/D15*12 -> 37.8 | F15: 3383.1 | G15: =F15 -> 3383.1 | H15: =G15 -> 3383.1 | I15: =H15 -> 3383.1 | J15: =I15 -> 3383.1 | K15: =J15 -> 3383.1 | L15: =K15 -> 3383.1 | M15: =L15 -> 3383.1 | N15: =M15 -> 3383.1 | ... Q15: =P15 -> 3383.1 | R15: =SUM(F15:Q15) -> 40597.2 | S15: Next increase 1/1/2027
A16: KANAKA KAVA | B16: B-6 | C16: 47208 | D16: 200 | E16: =Q16/D16*12 -> 127.308 | F16: 2060 | G16: =F16 -> 2060 | H16: =G16 -> 2060 | I16: 2121.8 | J16: =I16 -> 2121.8 | K16: =J16 -> 2121.8 | L16: =K16 -> 2121.8 | M16: =L16 -> 2121.8 | N16: =M16 -> 2121.8 | O16: =N16 -> 2121.8 | P16: =O16 -> 2121.8 | Q16: =P16 -> 2121.8 | R16: =SUM(F16:Q16) -> 25276.2 | S16: Next increase 4/1/2027
A17: GECKO GIRLZ SHAVE ICE SHACK | B17: C-7 | C17: 47652 | D17: 518 | E17: =Q17/D17*12 -> 58.616525 | F17: 2527.84 | G17: =F17 -> 2527.84 | H17: =G17 -> 2527.84 | I17: =H17 -> 2527.84 | J17: =I17 -> 2527.84 | K17: 2603.68 | L17: 2530.28 | M17: =L17 -> 2530.28 | N17: =M17 -> 2530.28 | O17: =N17 -> 2530.28 | P17: =O17 -> 2530.28 | Q17: =P17 -> 2530.28 | R17: =SUM(F17:Q17) -> 30424.56 | S17: Next increase 6/19/2027
A18: BIG ISLAND RUNNING CO. | B18: C-8 | C18: 47422 | D18: 525 | E18: =Q18/D18*12 -> 63.653943 | F18: 2703.75 | G18: =F18 -> 2703.75 | H18: =G18 -> 2703.75 | I18: =H18 -> 2703.75 | J18: =I18 -> 2703.75 | K18: =J18 -> 2703.75 | L18: =K18 -> 2703.75 | M18: =L18 -> 2703.75 | N18: =M18 -> 2703.75 | O18: =N18 -> 2703.75 | P18: 2784.86 | Q18: =P18 -> 2784.86 | R18: =SUM(F18:Q18) -> 32607.22 | S18: Next increase 11/1/2027
A19: CAFE KONA | B19: D11-12 | C19: 46265 | D19: 994 | E19: =Q19/D19*12 -> 46.2 | F19: 3826.9 | G19: =F19 -> 3826.9 | H19: =G19 -> 3826.9 | I19: =H19 -> 3826.9 | J19: =I19 -> 3826.9 | K19: =J19 -> 3826.9 | L19: =K19 -> 3826.9 | M19: =L19 -> 3826.9 | N19: =M19 -> 3826.9 | ... Q19: =P19 -> 3826.9 | R19: =SUM(F19:Q19) -> 45922.8 | S19: Rents fixed for first 3 years of renewal - Amendment pending
A20: LUCASIE LTD | B20: D9-D10 | C20: 46812 | D20: 1043 | E20: =Q20/D20*12 -> 90.84 | F20: 7593 | G20: =F20 -> 7593 | H20: 7895.51 | I20: =H20 -> 7895.51 | J20: =I20 -> 7895.51 | K20: =J20 -> 7895.51 | L20: =K20 -> 7895.51 | M20: =L20 -> 7895.51 | N20: =M20 -> 7895.51 | O20: =N20 -> 7895.51 | P20: =O20 -> 7895.51 | Q20: =P20 -> 7895.51 | R20: =SUM(F20:Q20) -> 94141.1 | S20: Next increase 3/1/2027
A21: FOSTERS KITCHEN | B21: DU-1 | C21: 48029 | D21: 3526 | E21: =Q21/D21*12 -> 41.733863 | F21: 11905.63 | G21: =F21 -> 11905.63 | H21: =G21 -> 11905.63 | I21: =H21 -> 11905.63 | J21: =I21 -> 11905.63 | K21: =J21 -> 11905.63 | L21: 12262.8 | M21: =L21 -> 12262.8 | N21: =M21 -> 12262.8 | O21: =N21 -> 12262.8 | P21: =O21 -> 12262.8 | Q21: =P21 -> 12262.8 | R21: =SUM(F21:Q21) -> 145010.58 | S21: Next increase 7/1/2027
A22: HUMPYS BIG ISLAND ALEHOUSE | B22: E | C22: 48457 | D22: 10736 | E22: =Q22/D22*12 -> 23.1 | F22: 25000 | G22: =F22 -> 25000 | H22: =G22 -> 25000 | I22: =H22 -> 25000 | J22: =I22 -> 25000 | K22: =J22 -> 25000 | L22: =K22 -> 25000 | M22: =L22 -> 25000 | N22: 20666.8 | O22: =N22 -> 20666.8 | P22: =O22 -> 20666.8 | Q22: =P22 -> 20666.8 | R22: =SUM(F22:Q22) -> 282667.2 | S22: NEW AMENDMENT SIGNED; ASSUME $25K/MO; full rents will resume 9/1/27
A23: ABC STORE #75 | B23: F15,17&A8 | C23: 47848 | D23: =3000+1000 -> 4000 | E23: =Q23/D23*12 -> 72 | F23: 24000 | G23: =F23 -> 24000 | H23: =G23 -> 24000 | I23: =H23 -> 24000 | J23: =I23 -> 24000 | K23: =J23 -> 24000 | L23: =K23 -> 24000 | M23: =L23 -> 24000 | N23: =M23 -> 24000 | ... Q23: =P23 -> 24000 | R23: =SUM(F23:Q23) -> 288000 | S23: Base Rent $24,000/mo through 12/31/30
A24: GYPSEA GALATO | B24: F-16 | C24: 46538 | D24: 500 | E24: =Q24/D24*12 -> 67.53048 | F24: 2731.82 | G24: =F24 -> 2731.82 | H24: =G24 -> 2731.82 | I24: =H24 -> 2731.82 | J24: =I24 -> 2731.82 | K24: 2813.77 | L24: =K24 -> 2813.77 | M24: =L24 -> 2813.77 | N24: =M24 -> 2813.77 | O24: =N24 -> 2813.77 | P24: =O24 -> 2813.77 | Q24: =P24 -> 2813.77 | R24: =SUM(F24:Q24) -> 33355.49 | S24: Lease expires 5/31/2027
A25: OCEANS SPORTS BAR AND GRILL | B25: G | C25: 52655 | D25: 2896 | E25: =Q25/D25*12 -> 41.64 | F25: 10049.12 | G25: =F25 -> 10049.12 | H25: =G25 -> 10049.12 | I25: =H25 -> 10049.12 | J25: =I25 -> 10049.12 | K25: =J25 -> 10049.12 | L25: =K25 -> 10049.12 | M25: =L25 -> 10049.12 | N25: =M25 -> 10049.12 | ... Q25: =P25 -> 10049.12 | R25: =SUM(F25:Q25) -> 120589.44 | S25: No Ground Lease increase through remainder of term
A26: JACKS DIVE LOCKER | B26: H | C26: 56157 | D26: 8014 | E26: =Q26/D26*12 -> 36.332882 | F26: 23387.29 | G26: =F26 -> 23387.29 | H26: =G26 -> 23387.29 | I26: =H26 -> 23387.29 | J26: =I26 -> 23387.29 | K26: =J26 -> 23387.29 | L26: =K26 -> 23387.29 | M26: =L26 -> 23387.29 | N26: =M26 -> 23387.29 | O26: =N26 -> 23387.29 | P26: 24264.31 | Q26: =P26 -> 24264.31 | R26: =SUM(F26:Q26) -> 282401.52 | S26: Ground lease; next increase 11/9/2027
A27: QPOT | B27: I | D27: 6500 | E27: =Q27/D27*12 -> 24 | F27: 0 | G27: =F27 -> 0 | H27: =G27 -> 0 | I27: =H27 -> 0 | J27: =I27 -> 0 | K27: =J27 -> 0 | L27: 13000 | M27: =L27 -> 13000 | N27: =M27 -> 13000 | O27: =N27 -> 13000 | P27: =O27 -> 13000 | Q27: =P27 -> 13000 | R27: =SUM(F27:Q27) -> 78000 | S27: ASSUMING NOVEMBER 1, 2025 POSSESSION DATE; JULY 1ST RENT COMMENCEMENT
A28: BOWLS SUPERFOODS & ORALE TACOS | B28: PC-1&2 | D28: 1993 | E28: =Q28/D28*12 -> 117.41094 | G28: =F28 -> 0 | H28: =G28 -> 0 | I28: =H28 -> 0 | J28: =I28 -> 0 | K28: =J28 -> 0 | M28: =L28 -> 0 | N28: =M28 -> 0 | O28: =N28 -> 0 | P28: =O28 -> 0 | Q28: =3*D27 -> 19500 | R28: =SUM(F28:Q28) -> 19500 | S28: NO ASSUMPTIONS FOR TH IS SPACE
A29: KONA GEAR INC. | B29: PC 3&4 | C29: 47208 | D29: 962 | E29: =Q29/D29*12 -> 80.39501 | F29: 6440.59 | G29: =F29 -> 6440.59 | H29: =G29 -> 6440.59 | I29: 6445 | J29: =I29 -> 6445 | K29: =J29 -> 6445 | L29: =K29 -> 6445 | M29: =L29 -> 6445 | N29: =M29 -> 6445 | O29: =N29 -> 6445 | P29: =O29 -> 6445 | Q29: =P29 -> 6445 | R29: =SUM(F29:Q29) -> 77326.77 | S29: PER 4TH AMENDMENT; RENT FIXED AT $6,445.40/MO 4/1/2026 THROUGH 3/31/2029
A30: LAVERNES | B30: PC/U1 | C30: 48457 | D30: 3704 | E30: =Q30/D30*12 -> 24 | F30: 7408 | G30: =F30 -> 7408 | H30: =G30 -> 7408 | I30: =H30 -> 7408 | J30: =I30 -> 7408 | K30: =J30 -> 7408 | L30: =K30 -> 7408 | M30: =L30 -> 7408 | N30: =M30 -> 7408 | ... Q30: =P30 -> 7408 | R30: =SUM(F30:Q30) -> 88896 | S30: Next increase 9/1/2027
A33: TOTALS | D33: =SUM(D14:D32) -> 51058 | F33: =SUM(F14:F32) -> 148820.58 | G33: =SUM(G14:G32) -> 148820.58 | H33: =SUM(H14:H32) -> 149123.09 | I33: =SUM(I14:I32) -> 149189.3 | J33: =SUM(J14:J32) -> 149189.3 | K33: =SUM(K14:K32) -> 149347.09 | L33: =SUM(L14:L32) -> 162630.86 | M33: =SUM(M14:M32) -> 162630.86 | ... Q33: =SUM(Q14:Q32) -> 178755.79 | R33: =SUM(R14:R30) -> 1874358.6
A37: ABC STORE #75 (sf added to rent above) | B37: Storage | D37: 2500 | E37: 2500 | F37: 2500 | G37: 2500 | H37: 2500 | I37: 2500 | J37: 2500 | K37: 2500 | L37: 2500 | M37: 2500 | N37: 2500 | O37: 2500 | P37: 2500 | Q37: 2500 | R37: =SUM(D37:Q37) -> 35000 | S37: BILLED AS MIS INCOME
A38: Café Kona renewal?
A41: Total Center | B41: =D33 -> 51058
A42: Property Insurance & Building (less Jack's & Oceans) | B42: =D33-D25-D26 -> 40148
A43: Food Court (see FC tab) | B43: ='Food Court'!C33 -> 28021
A44: Utilities - less vacancies | B44: =D33-D27-D28 -> 42565
D51: JACKS DIVE LOCKER NOVEMBER 2024 RENT CALCULATION
D53: =21727.19/30 -> 724.23967 | E53: =22541.96/30 -> 751.39867
E54: =D53*5 -> 3621.1983 | F54: =E53*25 -> 18784.967 | G54: =E54+F54 -> 22406.165

Sheet Marketing Budget
A1: Account | B1: Description | C1: Totals | D1: January | E1: February | F1: March | G1: April | H1: May | I1: June | J1: July | K1: August | L1: September | M1: October | N1: November | O1: December
A2: Income
B3: Website | C3: =SUM(C4:C5) -> 10800
B4: Creation | C4: =SUM(D4:O4) -> 0
B5: Management | C5: =SUM(D5:O5) -> 10800 | D5: 900 | E5: 900 | F5: 900 | G5: 900 | H5: 900 | I5: 900 | J5: 900 | K5: 900 | L5: 900 | M5: 900 | N5: 900 | O5: 900
B7: Social Media | C7: =SUM(C9:C10) -> 30150
B8: Photographer | C8: =SUM(D8:O8) -> 3200 | E8: 800 | H8: 800 | K8: 800 | N8: 800 | P8: capture content
B9: Management | C9: =SUM(D9:O9) -> 22500 | D9: 1875 | E9: 1875 | F9: 1875 | G9: 1875 | H9: 1875 | I9: 1875 | J9: 1875 | K9: 1875 | L9: 1875 | M9: 1875 | N9: 1875 | O9: 1875
B10: Paid Ads | C10: =SUM(D10:O10) -> 7650 | D10: 350 | E10: 350 | F10: 350 | G10: 350 | H10: 350 | I10: 1500 | J10: 1500 | K10: 1500 | L10: 350 | M10: 350 | N10: 350 | O10: 350
B12: Events | C12: =C13 -> 0
B13: Misc Promotion Event | C13: =SUM(D13:O13) -> 0 | G13: 0 | M13: 0
B15: Creative | C15: =C16 -> 600
B16: Design Fees | C16: =SUM(D16:O16) -> 600 | I16: 200 | J16: 200 | K16: 200 | P16: geofencing ad design
B18: Printed Material | C18: =C19 -> 5250
B19: Discovery MAP | C19: =SUM(D19:O19) -> 5250 | I19: 5250 | O19: 0 | P19: tourism map, updated annually
B21: TOTALS | C21: =C3+C7+C12+C15+C18 -> 46800 | D21: =SUM(D4:D20) -> 3125 | E21: =SUM(E4:E20) -> 3925 | F21: =SUM(F4:F20) -> 3125 | G21: =SUM(G4:G20) -> 3125 | H21: =SUM(H4:H20) -> 3925 | I21: =SUM(I4:I20) -> 9725 | J21: =SUM(J4:J20) -> 4475 | K21: =SUM(K4:K20) -> 5275 | ... O21: =SUM(O4:O20) -> 3125

Sheet CAM Recovery
P1: =Summ.!R1 -> Date Revised: | Q1: =Summ.!#REF! -> #REF! | S1: =Summ.!T1 -> 0
A2: =Summ.!$A2 -> ATHENA PROPERTY MANAGEMENT
A3: =Summ.!$A3 -> Coconut Grove - Kona Hawaii
A4: =Summ.!$A4 -> PROJECT NO. 165
A5: =Summ.!$A5 -> 01/01/26- 12/31/26
A6: =Summ.!$A6 -> 2026 OPERATING BUDGET
A9: TENANT | B9: SUITE | C9: SQUARE | D9: RATE | E9: JAN | F9: FEB | G9: MARCH | H9: APRIL | I9: MAY | J9: JUNE | K9: JULY | L9: AUGUST | M9: SEPT | N9: OCT | O9: NOV | P9: DEC | Q9: TOTALS | R9: NOTES
B10: # | C10: FOOTAGE
A12: ESTIMATED BASE RENT
A14: ISLAND LAVA JAVA | B14: A 1-4 | C14: 3873 | D14: =P14/C14*12 -> 0 | Q14: =SUM(E14:P14) -> 0
A15: TAKA SUSHI | B15: B-5 | C15: 1074 | D15: =P15/C15*12 -> 0 | Q15: =SUM(E15:P15) -> 0
A16: ZACH GIBSON (KANAKA KAVA) | B16: B-6 | C16: 200 | D16: =P16/C16*12 -> 0 | Q16: =SUM(E16:P16) -> 0
A17: GECKO GIRLZ SHAVE ICE SHACK | B17: C-7 | C17: 518 | D17: =P17/C17*12 -> 0 | Q17: =SUM(E17:P17) -> 0
A18: BIG ISLAND RUNNING CO. | B18: C-8 | C18: 525 | D18: =P18/C18*12 -> 0 | Q18: =SUM(E18:P18) -> 0
A19: COLORS OF PARADISE GALLERY | B19: D-9 | C19: 525 | D19: =P19/C19*12 -> 0 | Q19: =SUM(E19:P19) -> 0
A20: CAFE KONA | B20: D11-12 | C20: 994 | D20: =P20/C20*12 -> 0 | Q20: =SUM(E20:P20) -> 0
A21: VENTURE SOTHEBY INTERNATION | B21: D9 | C21: 518 | D21: =P21/C21*12 -> 0 | Q21: =SUM(E21:P21) -> 0
A22: MF KONA (FOSTERS KITCHEN) | B22: DU-1 | C22: 3526 | D22: =P22/C22*12 -> 0 | Q22: =SUM(E22:P22) -> 0
A23: BIG ISLAND ALEHOUSE (HUMPY'S ALEHOUSE) | B23: E | C23: 10736 | D23: =P23/C23*12 -> 0 | Q23: =SUM(E23:P23) -> 0
A24: MNS, LTD. (ABC STORE) | B24: F15,17&A8 | C24: 3000 | D24: =P24/C24*12 -> 0 | Q24: =SUM(E24:P24) -> 0
A25: GYPSEA GALATO | B25: F-16 | C25: 500 | D25: =P25/C25*12 -> 0 | Q25: =SUM(E25:P25) -> 0
... A31: KOHOLA, LLC (LAVERN'S) | B31: PC/U1 | C31: 3704 | D31: =P31/C31*12 -> 0 | Q31: =SUM(E31:P31) -> 0
A38: TOTALS | C38: =SUM(C14:C37) -> 49863 | E38: =SUM(E14:E37) -> 0 | F38: =SUM(F14:F37) -> 0 | G38: =SUM(G14:G37) -> 0 | H38: =SUM(H14:H37) -> 0 | I38: =SUM(I14:I37) -> 0 | J38: =SUM(J14:J37) -> 0 | K38: =SUM(K14:K37) -> 0 | L38: =SUM(L14:L37) -> 0 | ... P38: =SUM(P14:P37) -> 0 | Q38: =SUM(Q14:Q31) -> 0
A45: Excise Tax | B45: 0.04712 | E45: =SUM(E14:E31)*B45 -> 0 | F45: =SUM(F14:F31)*B45 -> 0 | G45: =SUM(G14:G31)*B45 -> 0 | H45: =SUM(H14:H31)*B45 -> 0 | I45: =SUM(I14:I31)*B45 -> 0 | J45: =SUM(J14:J31)*B45 -> 0 | K45: =SUM(K14:K31)*B45 -> 0 | L45: =SUM(L14:L31)*B45 -> 0 | M45: =SUM(M14:M31)*B45 -> 0 | N45: =SUM(N14:N31)*B45 -> 0 | O45: =SUM(O14:O31)*B45 -> 0 | P45: =SUM(P14:P31)*B45 -> 0 | Q45: =SUM(E45:P45) -> 0

Sheet Rent Recovery
P1: =Summ.!R1 -> Date Revised: | Q1: =Summ.!#REF! -> #REF! | S1: =Summ.!T1 -> 0
A2: =Summ.!$A2 -> ATHENA PROPERTY MANAGEMENT
A3: =Summ.!$A3 -> Coconut Grove - Kona Hawaii
A4: =Summ.!$A4 -> PROJECT NO. 165
A5: =Summ.!$A5 -> 01/01/26- 12/31/26
A6: =Summ.!$A6 -> 2026 OPERATING BUDGET
A9: TENANT | B9: SUITE | C9: SQUARE | D9: RATE | E9: JAN | F9: FEB | G9: MARCH | H9: APRIL | I9: MAY | J9: JUNE | K9: JULY | L9: AUGUST | M9: SEPT | N9: OCT | O9: NOV | P9: DEC | Q9: TOTALS | R9: NOTES
B10: # | C10: FOOTAGE
A12: ESTIMATED BASE RENT
A14: ISLAND LAVA JAVA | B14: A 1-4 | C14: 3873 | D14: =P14/C14*12 -> 0 | Q14: =SUM(E14:P14) -> 0
A15: TAKA SUSHI | B15: B-5 | C15: 1074 | D15: =P15/C15*12 -> 4.7272626 | E15: 423.09 | F15: 423.09 | G15: 423.09 | H15: 423.09 | I15: 423.09 | J15: 423.09 | K15: 423.09 | L15: 423.09 | M15: 423.09 | N15: 423.09 | O15: 423.09 | P15: 423.09 | Q15: =SUM(E15:P15) -> 5077.08 | R15: Rent Recovery ($423.09 until 12/31/27
A16: ZACH GIBSON (KANAKA KAVA) | B16: B-6 | C16: 200 | D16: =P16/C16*12 -> 0 | Q16: =SUM(E16:P16) -> 0
A17: GECKO GIRLZ SHAVE ICE SHACK | B17: C-7 | C17: 518 | D17: =P17/C17*12 -> 0 | Q17: =SUM(E17:P17) -> 0
A18: BIG ISLAND RUNNING CO. | B18: C-8 | C18: 525 | D18: =P18/C18*12 -> 0 | Q18: =SUM(E18:P18) -> 0
A19: COLORS OF PARADISE GALLERY | B19: D-9 | C19: 525 | D19: =P19/C19*12 -> 0 | Q19: =SUM(E19:P19) -> 0
A20: CAFE KONA | B20: D11-12 | C20: 994 | D20: =P20/C20*12 -> 0 | Q20: =SUM(E20:P20) -> 0
A21: VENTURE SOTHEBY INTERNATION | B21: D9 | C21: 518 | D21: =P21/C21*12 -> 0 | Q21: =SUM(E21:P21) -> 0
A22: MF KONA (FOSTERS KITCHEN) | B22: DU-1 | C22: 3526 | D22: =P22/C22*12 -> 0 | Q22: =SUM(E22:P22) -> 0
A23: BIG ISLAND ALEHOUSE (HUMPY'S ALEHOUSE) | B23: E | C23: 10736 | D23: =P23/C23*12 -> 0 | Q23: =SUM(E23:P23) -> 0
A24: MNS, LTD. (ABC STORE) | B24: F15,17&A8 | C24: 3000 | D24: =P24/C24*12 -> 0 | Q24: =SUM(E24:P24) -> 0
A25: GYPSEA GALATO | B25: F-16 | C25: 500 | D25: =P25/C25*12 -> 0 | Q25: =SUM(E25:P25) -> 0
A26: OCEANS, INC. (OCEAN SPORTS BAR AND GRILL) | B26: G | C26: 2896 | D26: =P26/C26*12 -> 0 | Q26: =SUM(E26:P26) -> 0
A27: L AND L, LLC (JACKS DIVE LOCKER) | B27: H | C27: 8014 | D27: =P27/C27*12 -> 0 | Q27: =SUM(E27:P27) -> 0
... A31: KOHOLA, LLC (LAVERN'S) | B31: PC/U1 | C31: 3704 | D31: =P31/C31*12 -> 0 | Q31: =SUM(E31:P31) -> 0
A38: TOTALS | C38: =SUM(C14:C37) -> 49863 | E38: =SUM(E14:E37) -> 423.09 | F38: =SUM(F14:F37) -> 423.09 | G38: =SUM(G14:G37) -> 423.09 | H38: =SUM(H14:H37) -> 423.09 | I38: =SUM(I14:I37) -> 423.09 | J38: =SUM(J14:J37) -> 423.09 | K38: =SUM(K14:K37) -> 423.09 | L38: =SUM(L14:L37) -> 423.09 | ... P38: =SUM(P14:P37) -> 423.09 | Q38: =SUM(Q14:Q31) -> 5077.08
A45: Excise Tax | B45: 0.04712 | E45: =SUM(E14:E31)*B45 -> 19.936001 | F45: =SUM(F14:F31)*B45 -> 19.936001 | G45: =SUM(G14:G31)*B45 -> 19.936001 | H45: =SUM(H14:H31)*B45 -> 19.936001 | I45: =SUM(I14:I31)*B45 -> 19.936001 | J45: =SUM(J14:J31)*B45 -> 19.936001 | K45: =SUM(K14:K31)*B45 -> 19.936001 | L45: =SUM(L14:L31)*B45 -> 19.936001 | M45: =SUM(M14:M31)*B45 -> 19.936001 | N45: =SUM(N14:N31)*B45 -> 19.936001 | O45: =SUM(O14:O31)*B45 -> 19.936001 | P45: =SUM(P14:P31)*B45 -> 19.936001 | Q45: =SUM(E45:P45) -> 239.23201

Sheet CAM
P1: =Summ.!R1 -> Date Revised: | Q1: =Summ.!#REF! -> #REF! | R1: =Summ.!T1 -> 0
A2: =Summ.!$A2 -> ATHENA PROPERTY MANAGEMENT
A3: =Summ.!$A3 -> Coconut Grove - Kona Hawaii
A4: =Summ.!$A4 -> PROJECT NO. 165
A5: =Summ.!$A5 -> 01/01/26- 12/31/26
A6: =Summ.!$A6 -> 2026 OPERATING BUDGET
T8: COMMENTS
A9: TENANT | B9: SUITE | C9: SQUARE | D9: % OF | E9: JAN | F9: FEB | G9: MARCH | H9: APRIL | I9: MAY | J9: JUNE | K9: JULY | L9: AUGUST | M9: SEPT | N9: OCT | O9: NOV | P9: DEC | Q9: TOTALS
B10: # | C10: FOOTAGE | D10: TOTAL
A12: COMMON AREA MAINTENANCE
A14: =Rent!A14 -> ISLAND LAVA JAVA | B14: =Rent!B14 -> A 1-4 | C14: =Rent!D14 -> 3873 | D14: =C14/$C$33 -> 0.07585491 | E14: =IF(Rent!F14=0,0,('TENANT CHARGES'!$G10)) -> 6087.6782 | F14: =IF(Rent!G14=0,0,('TENANT CHARGES'!$G10)) -> 6087.6782 | G14: =IF(Rent!H14=0,0,('TENANT CHARGES'!$G10)) -> 6087.6782 | H14: =IF(Rent!I14=0,0,('TENANT CHARGES'!$G10)) -> 6087.6782 | I14: =IF(Rent!J14=0,0,('TENANT CHARGES'!$G10)) -> 6087.6782 | J14: =IF(Rent!K14=0,0,('TENANT CHARGES'!$G10)) -> 6087.6782 | K14: =IF(Rent!L14=0,0,('TENANT CHARGES'!$G10)) -> 6087.6782 | L14: =IF(Rent!M14=0,0,('TENANT CHARGES'!$G10)) -> 6087.6782 | ... P14: =IF(Rent!Q14=0,0,('TENANT CHARGES'!$G10)) -> 6087.6782 | Q14: =SUM(E14:P14) -> 73052.139 | R14: =+P14/C14 -> 1.571825
A15: =Rent!A15 -> TAKA SUSHI | B15: =Rent!B15 -> B-5 | C15: =Rent!D15 -> 1074 | D15: =C15/$C$33 -> 0.021034901 | E15: =IF(Rent!F15=0,0,('TENANT CHARGES'!$G11)) -> 1688.1401 | F15: =IF(Rent!G15=0,0,('TENANT CHARGES'!$G11)) -> 1688.1401 | G15: =IF(Rent!H15=0,0,('TENANT CHARGES'!$G11)) -> 1688.1401 | H15: =IF(Rent!I15=0,0,('TENANT CHARGES'!$G11)) -> 1688.1401 | I15: =IF(Rent!J15=0,0,('TENANT CHARGES'!$G11)) -> 1688.1401 | J15: =IF(Rent!K15=0,0,('TENANT CHARGES'!$G11)) -> 1688.1401 | K15: =IF(Rent!L15=0,0,('TENANT CHARGES'!$G11)) -> 1688.1401 | L15: =IF(Rent!M15=0,0,('TENANT CHARGES'!$G11)) -> 1688.1401 | ... P15: =IF(Rent!Q15=0,0,('TENANT CHARGES'!$G11)) -> 1688.1401 | Q15: =SUM(E15:P15) -> 20257.681 | R15: =+P15/C15 -> 1.571825
A16: =Rent!A16 -> KANAKA KAVA | B16: =Rent!B16 -> B-6 | C16: =Rent!D16 -> 200 | D16: =C16/$C$33 -> 0.0039171139 | E16: =IF(Rent!F16=0,0,('TENANT CHARGES'!$G12)) -> 314.365 | F16: =IF(Rent!G16=0,0,('TENANT CHARGES'!$G12)) -> 314.365 | G16: =IF(Rent!H16=0,0,('TENANT CHARGES'!$G12)) -> 314.365 | H16: =IF(Rent!I16=0,0,('TENANT CHARGES'!$G12)) -> 314.365 | I16: =IF(Rent!J16=0,0,('TENANT CHARGES'!$G12)) -> 314.365 | J16: =IF(Rent!K16=0,0,('TENANT CHARGES'!$G12)) -> 314.365 | K16: =IF(Rent!L16=0,0,('TENANT CHARGES'!$G12)) -> 314.365 | L16: =IF(Rent!M16=0,0,('TENANT CHARGES'!$G12)) -> 314.365 | ... P16: =IF(Rent!Q16=0,0,('TENANT CHARGES'!$G12)) -> 314.365 | Q16: =SUM(E16:P16) -> 3772.38 | R16: =+P16/C16 -> 1.571825
A17: =Rent!A17 -> GECKO GIRLZ SHAVE ICE SHACK | B17: =Rent!B17 -> C-7 | C17: =Rent!D17 -> 518 | D17: =C17/$C$33 -> 0.010145325 | E17: =IF(Rent!F17=0,0,('TENANT CHARGES'!$G13)) -> 814.20535 | F17: =IF(Rent!G17=0,0,('TENANT CHARGES'!$G13)) -> 814.20535 | G17: =IF(Rent!H17=0,0,('TENANT CHARGES'!$G13)) -> 814.20535 | H17: =IF(Rent!I17=0,0,('TENANT CHARGES'!$G13)) -> 814.20535 | I17: =IF(Rent!J17=0,0,('TENANT CHARGES'!$G13)) -> 814.20535 | J17: =IF(Rent!K17=0,0,('TENANT CHARGES'!$G13)) -> 814.20535 | K17: =IF(Rent!L17=0,0,('TENANT CHARGES'!$G13)) -> 814.20535 | L17: =IF(Rent!M17=0,0,('TENANT CHARGES'!$G13)) -> 814.20535 | ... P17: =IF(Rent!Q17=0,0,('TENANT CHARGES'!$G13)) -> 814.20535 | Q17: =SUM(E17:P17) -> 9770.4642 | R17: =+P17/C17 -> 1.571825
A18: =Rent!A18 -> BIG ISLAND RUNNING CO. | B18: =Rent!B18 -> C-8 | C18: =Rent!D18 -> 525 | D18: =C18/$C$33 -> 0.010282424 | E18: =IF(Rent!F18=0,0,('TENANT CHARGES'!$G14)) -> 825.20813 | F18: =IF(Rent!G18=0,0,('TENANT CHARGES'!$G14)) -> 825.20813 | G18: =IF(Rent!H18=0,0,('TENANT CHARGES'!$G14)) -> 825.20813 | H18: =IF(Rent!I18=0,0,('TENANT CHARGES'!$G14)) -> 825.20813 | I18: =IF(Rent!J18=0,0,('TENANT CHARGES'!$G14)) -> 825.20813 | J18: =IF(Rent!K18=0,0,('TENANT CHARGES'!$G14)) -> 825.20813 | K18: =IF(Rent!L18=0,0,('TENANT CHARGES'!$G14)) -> 825.20813 | L18: =IF(Rent!M18=0,0,('TENANT CHARGES'!$G14)) -> 825.20813 | ... P18: =IF(Rent!Q18=0,0,('TENANT CHARGES'!$G14)) -> 825.20813 | Q18: =SUM(E18:P18) -> 9902.4975 | R18: =+P18/C18 -> 1.571825
A19: =Rent!A19 -> CAFE KONA | B19: =Rent!B19 -> D11-12 | C19: =Rent!D19 -> 994 | D19: =C19/$C$33 -> 0.019468056 | E19: =IF(Rent!F19=0,0,('TENANT CHARGES'!$G15)) -> 1562.3941 | F19: =IF(Rent!G19=0,0,('TENANT CHARGES'!$G15)) -> 1562.3941 | G19: =IF(Rent!H19=0,0,('TENANT CHARGES'!$G15)) -> 1562.3941 | H19: =IF(Rent!I19=0,0,('TENANT CHARGES'!$G15)) -> 1562.3941 | I19: =IF(Rent!J19=0,0,('TENANT CHARGES'!$G15)) -> 1562.3941 | J19: =IF(Rent!K19=0,0,('TENANT CHARGES'!$G15)) -> 1562.3941 | K19: =IF(Rent!L19=0,0,('TENANT CHARGES'!$G15)) -> 1562.3941 | L19: =IF(Rent!M19=0,0,('TENANT CHARGES'!$G15)) -> 1562.3941 | ... P19: =IF(Rent!Q19=0,0,('TENANT CHARGES'!$G15)) -> 1562.3941 | Q19: =SUM(E19:P19) -> 18748.729 | R19: =+P19/C19 -> 1.571825
A20: =Rent!A20 -> LUCASIE LTD | B20: =Rent!B20 -> D9-D10 | C20: =Rent!D20 -> 1043 | D20: =C20/$C$33 -> 0.020427749 | E20: =IF(Rent!F20=0,0,('TENANT CHARGES'!$G17)) -> 1639.4135 | F20: =IF(Rent!G20=0,0,('TENANT CHARGES'!$G17)) -> 1639.4135 | G20: =IF(Rent!H20=0,0,('TENANT CHARGES'!$G17)) -> 1639.4135 | H20: =IF(Rent!I20=0,0,('TENANT CHARGES'!$G17)) -> 1639.4135 | I20: =IF(Rent!J20=0,0,('TENANT CHARGES'!$G17)) -> 1639.4135 | J20: =IF(Rent!K20=0,0,('TENANT CHARGES'!$G17)) -> 1639.4135 | K20: =IF(Rent!L20=0,0,('TENANT CHARGES'!$G17)) -> 1639.4135 | L20: =IF(Rent!M20=0,0,('TENANT CHARGES'!$G17)) -> 1639.4135 | ... P20: =IF(Rent!Q20=0,0,('TENANT CHARGES'!$G17)) -> 1639.4135 | Q20: =SUM(E20:P20) -> 19672.962 | R20: =+P20/C20 -> 1.571825
A21: =Rent!A21 -> FOSTERS KITCHEN | B21: =Rent!B21 -> DU-1 | C21: =Rent!D21 -> 3526 | D21: =C21/$C$33 -> 0.069058718 | E21: =IF(Rent!F21=0,0,('TENANT CHARGES'!$G18)) -> 5542.255 | F21: =IF(Rent!G21=0,0,('TENANT CHARGES'!$G18)) -> 5542.255 | G21: =IF(Rent!H21=0,0,('TENANT CHARGES'!$G18)) -> 5542.255 | H21: =IF(Rent!I21=0,0,('TENANT CHARGES'!$G18)) -> 5542.255 | I21: =IF(Rent!J21=0,0,('TENANT CHARGES'!$G18)) -> 5542.255 | J21: =IF(Rent!K21=0,0,('TENANT CHARGES'!$G18)) -> 5542.255 | K21: =IF(Rent!L21=0,0,('TENANT CHARGES'!$G18)) -> 5542.255 | L21: =IF(Rent!M21=0,0,('TENANT CHARGES'!$G18)) -> 5542.255 | ... P21: =IF(Rent!Q21=0,0,('TENANT CHARGES'!$G18)) -> 5542.255 | Q21: =SUM(E21:P21) -> 66507.06 | R21: =+P21/C21 -> 1.571825
A22: =Rent!A22 -> HUMPYS BIG ISLAND ALEHOUSE | B22: =Rent!B22 -> E | C22: =Rent!D22 -> 10736 | D22: =C22/$C$33 -> 0.21027067 | E22: 0 | F22: 0 | G22: 0 | H22: 0 | I22: 0 | J22: 0 | K22: 0 | L22: 0 | M22: =IF(Rent!N22=0,0,('TENANT CHARGES'!$G19)) -> 16875.113 | N22: =IF(Rent!O22=0,0,('TENANT CHARGES'!$G19)) -> 16875.113 | O22: =IF(Rent!P22=0,0,('TENANT CHARGES'!$G19)) -> 16875.113 | P22: =IF(Rent!Q22=0,0,('TENANT CHARGES'!$G19)) -> 16875.113 | Q22: =SUM(E22:P22) -> 67500.453 | R22: =+P22/C22 -> 1.571825 | T22: NEW AMENDMENT SIGNED; ASSUME $25K/MO; full rents will resume 9/1/26
A23: =Rent!A23 -> ABC STORE #75 | B23: =Rent!B23 -> F15,17&A8 | C23: =Rent!D23 -> 4000 | D23: =C23/$C$33 -> 0.078342277 | E23: =IF(Rent!F23=0,0,('TENANT CHARGES'!$G20)) -> 4715.475 | F23: =IF(Rent!G23=0,0,('TENANT CHARGES'!$G20)) -> 4715.475 | G23: =IF(Rent!H23=0,0,('TENANT CHARGES'!$G20)) -> 4715.475 | H23: =IF(Rent!I23=0,0,('TENANT CHARGES'!$G20)) -> 4715.475 | I23: =IF(Rent!J23=0,0,('TENANT CHARGES'!$G20)) -> 4715.475 | J23: =IF(Rent!K23=0,0,('TENANT CHARGES'!$G20)) -> 4715.475 | K23: =IF(Rent!L23=0,0,('TENANT CHARGES'!$G20)) -> 4715.475 | L23: =IF(Rent!M23=0,0,('TENANT CHARGES'!$G20)) -> 4715.475 | ... P23: =IF(Rent!Q23=0,0,('TENANT CHARGES'!$G20)) -> 4715.475 | Q23: =SUM(E23:P23) -> 56585.7 | R23: =+P23/C23 -> 1.1788688
A24: =Rent!A24 -> GYPSEA GALATO | B24: =Rent!B24 -> F-16 | C24: =Rent!D24 -> 500 | D24: =C24/$C$33 -> 0.0097927847 | E24: =IF(Rent!F24=0,0,('TENANT CHARGES'!$G21)) -> 785.9125 | F24: =IF(Rent!G24=0,0,('TENANT CHARGES'!$G21)) -> 785.9125 | G24: =IF(Rent!H24=0,0,('TENANT CHARGES'!$G21)) -> 785.9125 | H24: =IF(Rent!I24=0,0,('TENANT CHARGES'!$G21)) -> 785.9125 | I24: =IF(Rent!J24=0,0,('TENANT CHARGES'!$G21)) -> 785.9125 | J24: =IF(Rent!K24=0,0,('TENANT CHARGES'!$G21)) -> 785.9125 | K24: =IF(Rent!L24=0,0,('TENANT CHARGES'!$G21)) -> 785.9125 | L24: =IF(Rent!M24=0,0,('TENANT CHARGES'!$G21)) -> 785.9125 | ... P24: =IF(Rent!Q24=0,0,('TENANT CHARGES'!$G21)) -> 785.9125 | Q24: =SUM(E24:P24) -> 9430.95 | R24: =+P24/C24 -> 1.571825
A25: =Rent!A25 -> OCEANS SPORTS BAR AND GRILL | B25: =Rent!B25 -> G | C25: =Rent!D25 -> 2896 | D25: =C25/$C$33 -> 0.056719809 | E25: =IF(Rent!F25=0,0,('TENANT CHARGES'!$G22)) -> 2859.5263 | F25: =IF(Rent!G25=0,0,('TENANT CHARGES'!$G22)) -> 2859.5263 | G25: =IF(Rent!H25=0,0,('TENANT CHARGES'!$G22)) -> 2859.5263 | H25: =IF(Rent!I25=0,0,('TENANT CHARGES'!$G22)) -> 2859.5263 | I25: =IF(Rent!J25=0,0,('TENANT CHARGES'!$G22)) -> 2859.5263 | J25: =IF(Rent!K25=0,0,('TENANT CHARGES'!$G22)) -> 2859.5263 | K25: =IF(Rent!L25=0,0,('TENANT CHARGES'!$G22)) -> 2859.5263 | L25: =IF(Rent!M25=0,0,('TENANT CHARGES'!$G22)) -> 2859.5263 | ... P25: =IF(Rent!Q25=0,0,('TENANT CHARGES'!$G22)) -> 2859.5263 | Q25: =SUM(E25:P25) -> 34314.315 | R25: =+P25/C25 -> 0.98740547
A26: =Rent!A26 -> JACKS DIVE LOCKER | B26: =Rent!B26 -> H | C26: =Rent!D26 -> 8014 | D26: =C26/$C$33 -> 0.15695875 | E26: =IF(Rent!F26=0,0,('TENANT CHARGES'!$G23)) -> 7913.0675 | F26: =IF(Rent!G26=0,0,('TENANT CHARGES'!$G23)) -> 7913.0675 | G26: =IF(Rent!H26=0,0,('TENANT CHARGES'!$G23)) -> 7913.0675 | H26: =IF(Rent!I26=0,0,('TENANT CHARGES'!$G23)) -> 7913.0675 | I26: =IF(Rent!J26=0,0,('TENANT CHARGES'!$G23)) -> 7913.0675 | J26: =IF(Rent!K26=0,0,('TENANT CHARGES'!$G23)) -> 7913.0675 | K26: =IF(Rent!L26=0,0,('TENANT CHARGES'!$G23)) -> 7913.0675 | L26: =IF(Rent!M26=0,0,('TENANT CHARGES'!$G23)) -> 7913.0675 | ... P26: =IF(Rent!Q26=0,0,('TENANT CHARGES'!$G23)) -> 7913.0675 | Q26: =SUM(E26:P26) -> 94956.81 | R26: =+P26/C26 -> 0.98740547
A27: =Rent!A27 -> QPOT | B27: =Rent!B27 -> I | C27: =Rent!D27 -> 6500 | D27: =C27/$C$33 -> 0.1273062 | E27: =IF(Rent!F27=0,0,('TENANT CHARGES'!$G24)) -> 0 | F27: =IF(Rent!G27=0,0,('TENANT CHARGES'!$G24)) -> 0 | G27: =IF(Rent!H27=0,0,('TENANT CHARGES'!$G24)) -> 0 | H27: =IF(Rent!I27=0,0,('TENANT CHARGES'!$G24)) -> 0 | I27: =IF(Rent!J27=0,0,('TENANT CHARGES'!$G24)) -> 0 | J27: =IF(Rent!K27=0,0,('TENANT CHARGES'!$G24)) -> 0 | K27: =IF(Rent!L27=0,0,('TENANT CHARGES'!$G24)) -> 6499.0861 | L27: =IF(Rent!M27=0,0,('TENANT CHARGES'!$G24)) -> 6499.0861 | ... P27: =IF(Rent!Q27=0,0,('TENANT CHARGES'!$G24)) -> 6499.0861 | Q27: =SUM(E27:P27) -> 38994.516 | R27: =+P27/C27 -> 0.99985939
A28: =Rent!A28 -> BOWLS SUPERFOODS & ORALE TACOS | B28: =Rent!B28 -> PC-1&2 | C28: =Rent!D28 -> 1993 | D28: =C28/$C$33 -> 0.03903404 | E28: =IF(Rent!F28=0,0,('TENANT CHARGES'!$G25)) -> 0 | F28: =IF(Rent!G28=0,0,('TENANT CHARGES'!$G25)) -> 0 | G28: =IF(Rent!H28=0,0,('TENANT CHARGES'!$G25)) -> 0 | H28: =IF(Rent!I28=0,0,('TENANT CHARGES'!$G25)) -> 0 | I28: =IF(Rent!J28=0,0,('TENANT CHARGES'!$G25)) -> 0 | J28: =IF(Rent!K28=0,0,('TENANT CHARGES'!$G25)) -> 0 | K28: =IF(Rent!L28=0,0,('TENANT CHARGES'!$G25)) -> 0 | L28: =IF(Rent!M28=0,0,('TENANT CHARGES'!$G25)) -> 0 | ... P28: =IF(Rent!Q28=0,0,('TENANT CHARGES'!$G25)) -> 0 | Q28: =SUM(E28:P28) -> 0 | R28: =+P28/C28 -> 0
A29: =Rent!A29 -> KONA GEAR INC. | B29: =Rent!B29 -> PC 3&4 | C29: =Rent!D29 -> 962 | D29: =C29/$C$33 -> 0.018841318 | E29: =IF(Rent!F29=0,0,('TENANT CHARGES'!$G26)) -> 1512.0957 | F29: =IF(Rent!G29=0,0,('TENANT CHARGES'!$G26)) -> 1512.0957 | G29: =IF(Rent!H29=0,0,('TENANT CHARGES'!$G26)) -> 1512.0957 | H29: =IF(Rent!I29=0,0,('TENANT CHARGES'!$G26)) -> 1512.0957 | I29: =IF(Rent!J29=0,0,('TENANT CHARGES'!$G26)) -> 1512.0957 | J29: =IF(Rent!K29=0,0,('TENANT CHARGES'!$G26)) -> 1512.0957 | K29: =IF(Rent!L29=0,0,('TENANT CHARGES'!$G26)) -> 1512.0957 | L29: =IF(Rent!M29=0,0,('TENANT CHARGES'!$G26)) -> 1512.0957 | ... P29: =IF(Rent!Q29=0,0,('TENANT CHARGES'!$G26)) -> 1512.0957 | Q29: =SUM(E29:P29) -> 18145.148 | R29: =+P29/C29 -> 1.571825
A30: =Rent!A30 -> LAVERNES | B30: =Rent!B30 -> PC/U1 | C30: =Rent!D30 -> 3704 | D30: =C30/$C$33 -> 0.072544949 | E30: =IF(Rent!F30=0,0,('TENANT CHARGES'!$G27)) -> 5822.0398 | F30: =IF(Rent!G30=0,0,('TENANT CHARGES'!$G27)) -> 5822.0398 | G30: =IF(Rent!H30=0,0,('TENANT CHARGES'!$G27)) -> 5822.0398 | H30: =IF(Rent!I30=0,0,('TENANT CHARGES'!$G27)) -> 5822.0398 | I30: =IF(Rent!J30=0,0,('TENANT CHARGES'!$G27)) -> 5822.0398 | J30: =IF(Rent!K30=0,0,('TENANT CHARGES'!$G27)) -> 5822.0398 | K30: =IF(Rent!L30=0,0,('TENANT CHARGES'!$G27)) -> 5822.0398 | L30: =IF(Rent!M30=0,0,('TENANT CHARGES'!$G27)) -> 5822.0398 | ... P30: =IF(Rent!Q30=0,0,('TENANT CHARGES'!$G27)) -> 5822.0398 | Q30: =SUM(E30:P30) -> 69864.478 | R30: =+P30/C30 -> 1.571825
A33: TOTALS | C33: =SUM(C14:C32) -> 51058 | D33: =SUM(D14:D32) -> 1 | E33: =SUM(E14:E32) -> 42081.776 | F33: =SUM(F14:F32) -> 42081.776 | G33: =SUM(G14:G32) -> 42081.776 | H33: =SUM(H14:H32) -> 42081.776 | I33: =SUM(I14:I32) -> 42081.776 | J33: =SUM(J14:J32) -> 42081.776 | ... Q33: =SUM(Q14:Q32) -> 611476.28
O35: TOTAL CAM | Q35: =Summ.!O81 -> 1091508.3
O36: RECAPTURE | Q36: =Q33/Q35 -> 0.56021221

Sheet Building Exp.
P1: =Summ.!R1 -> Date Revised: | Q1: =Summ.!#REF! -> #REF! | R1: =Summ.!T1 -> 0
A2: =Summ.!$A2 -> ATHENA PROPERTY MANAGEMENT
A3: =Summ.!$A3 -> Coconut Grove - Kona Hawaii
A4: =Summ.!$A4 -> PROJECT NO. 165
A5: =Summ.!$A5 -> 01/01/26- 12/31/26
A6: =Summ.!$A6 -> 2026 OPERATING BUDGET
A9: TENANT | B9: SUITE | C9: SQUARE | D9: % OF | E9: JAN | F9: FEB | G9: MARCH | H9: APRIL | I9: MAY | J9: JUNE | K9: JULY | L9: AUGUST | M9: SEPT | N9: OCT | O9: NOV | P9: DEC | Q9: TOTALS
B10: # | C10: FOOTAGE | D10: TOTAL
A12: BUILDING EXPENSES
A14: =Rent!A14 -> ISLAND LAVA JAVA | B14: =Rent!B14 -> A 1-4 | C14: =Rent!D14 -> 3873 | D14: =C14/$C$33 -> 0.07585491 | E14: =IF(Rent!F14=0,0,('TENANT CHARGES'!$H10)) -> 930.57118 | F14: =IF(Rent!G14=0,0,('TENANT CHARGES'!$H10)) -> 930.57118 | G14: =IF(Rent!H14=0,0,('TENANT CHARGES'!$H10)) -> 930.57118 | H14: =IF(Rent!I14=0,0,('TENANT CHARGES'!$H10)) -> 930.57118 | I14: =IF(Rent!J14=0,0,('TENANT CHARGES'!$H10)) -> 930.57118 | J14: =IF(Rent!K14=0,0,('TENANT CHARGES'!$H10)) -> 930.57118 | K14: =IF(Rent!L14=0,0,('TENANT CHARGES'!$H10)) -> 930.57118 | L14: =IF(Rent!M14=0,0,('TENANT CHARGES'!$H10)) -> 930.57118 | ... P14: =IF(Rent!Q14=0,0,('TENANT CHARGES'!$H10)) -> 930.57118 | Q14: =SUM(E14:P14) -> 11166.854 | R14: =P14/C14 -> 0.24027141
A15: =Rent!A15 -> TAKA SUSHI | B15: =Rent!B15 -> B-5 | C15: =Rent!D15 -> 1074 | D15: =C15/$C$33 -> 0.021034901 | E15: =IF(Rent!F15=0,0,('TENANT CHARGES'!$H11)) -> 258.0515 | F15: =IF(Rent!G15=0,0,('TENANT CHARGES'!$H11)) -> 258.0515 | G15: =IF(Rent!H15=0,0,('TENANT CHARGES'!$H11)) -> 258.0515 | H15: =IF(Rent!I15=0,0,('TENANT CHARGES'!$H11)) -> 258.0515 | I15: =IF(Rent!J15=0,0,('TENANT CHARGES'!$H11)) -> 258.0515 | J15: =IF(Rent!K15=0,0,('TENANT CHARGES'!$H11)) -> 258.0515 | K15: =IF(Rent!L15=0,0,('TENANT CHARGES'!$H11)) -> 258.0515 | L15: =IF(Rent!M15=0,0,('TENANT CHARGES'!$H11)) -> 258.0515 | ... P15: =IF(Rent!Q15=0,0,('TENANT CHARGES'!$H11)) -> 258.0515 | Q15: =SUM(E15:P15) -> 3096.618 | R15: =P15/C15 -> 0.24027141
A16: =Rent!A16 -> KANAKA KAVA | B16: =Rent!B16 -> B-6 | C16: =Rent!D16 -> 200 | D16: =C16/$C$33 -> 0.0039171139 | E16: =IF(Rent!F16=0,0,('TENANT CHARGES'!$H12)) -> 48.054282 | F16: =IF(Rent!G16=0,0,('TENANT CHARGES'!$H12)) -> 48.054282 | G16: =IF(Rent!H16=0,0,('TENANT CHARGES'!$H12)) -> 48.054282 | H16: =IF(Rent!I16=0,0,('TENANT CHARGES'!$H12)) -> 48.054282 | I16: =IF(Rent!J16=0,0,('TENANT CHARGES'!$H12)) -> 48.054282 | J16: =IF(Rent!K16=0,0,('TENANT CHARGES'!$H12)) -> 48.054282 | K16: =IF(Rent!L16=0,0,('TENANT CHARGES'!$H12)) -> 48.054282 | L16: =IF(Rent!M16=0,0,('TENANT CHARGES'!$H12)) -> 48.054282 | ... P16: =IF(Rent!Q16=0,0,('TENANT CHARGES'!$H12)) -> 48.054282 | Q16: =SUM(E16:P16) -> 576.65139 | R16: =P16/C16 -> 0.24027141
A17: =Rent!A17 -> GECKO GIRLZ SHAVE ICE SHACK | B17: =Rent!B17 -> C-7 | C17: =Rent!D17 -> 518 | D17: =C17/$C$33 -> 0.010145325 | E17: =IF(Rent!F17=0,0,('TENANT CHARGES'!$H13)) -> 124.46059 | F17: =IF(Rent!G17=0,0,('TENANT CHARGES'!$H13)) -> 124.46059 | G17: =IF(Rent!H17=0,0,('TENANT CHARGES'!$H13)) -> 124.46059 | H17: =IF(Rent!I17=0,0,('TENANT CHARGES'!$H13)) -> 124.46059 | I17: =IF(Rent!J17=0,0,('TENANT CHARGES'!$H13)) -> 124.46059 | J17: =IF(Rent!K17=0,0,('TENANT CHARGES'!$H13)) -> 124.46059 | K17: =IF(Rent!L17=0,0,('TENANT CHARGES'!$H13)) -> 124.46059 | L17: =IF(Rent!M17=0,0,('TENANT CHARGES'!$H13)) -> 124.46059 | ... P17: =IF(Rent!Q17=0,0,('TENANT CHARGES'!$H13)) -> 124.46059 | Q17: =SUM(E17:P17) -> 1493.5271 | R17: =P17/C17 -> 0.24027141
A18: =Rent!A18 -> BIG ISLAND RUNNING CO. | B18: =Rent!B18 -> C-8 | C18: =Rent!D18 -> 525 | D18: =C18/$C$33 -> 0.010282424 | E18: =IF(Rent!F18=0,0,('TENANT CHARGES'!$H14)) -> 126.14249 | F18: =IF(Rent!G18=0,0,('TENANT CHARGES'!$H14)) -> 126.14249 | G18: =IF(Rent!H18=0,0,('TENANT CHARGES'!$H14)) -> 126.14249 | H18: =IF(Rent!I18=0,0,('TENANT CHARGES'!$H14)) -> 126.14249 | I18: =IF(Rent!J18=0,0,('TENANT CHARGES'!$H14)) -> 126.14249 | J18: =IF(Rent!K18=0,0,('TENANT CHARGES'!$H14)) -> 126.14249 | K18: =IF(Rent!L18=0,0,('TENANT CHARGES'!$H14)) -> 126.14249 | L18: =IF(Rent!M18=0,0,('TENANT CHARGES'!$H14)) -> 126.14249 | ... P18: =IF(Rent!Q18=0,0,('TENANT CHARGES'!$H14)) -> 126.14249 | Q18: =SUM(E18:P18) -> 1513.7099 | R18: =P18/C18 -> 0.24027141
A19: =Rent!A19 -> CAFE KONA | B19: =Rent!B19 -> D11-12 | C19: =Rent!D19 -> 994 | D19: =C19/$C$33 -> 0.019468056 | E19: =IF(Rent!F19=0,0,('TENANT CHARGES'!$H15)) -> 238.82978 | F19: =IF(Rent!G19=0,0,('TENANT CHARGES'!$H15)) -> 238.82978 | G19: =IF(Rent!H19=0,0,('TENANT CHARGES'!$H15)) -> 238.82978 | H19: =IF(Rent!I19=0,0,('TENANT CHARGES'!$H15)) -> 238.82978 | I19: =IF(Rent!J19=0,0,('TENANT CHARGES'!$H15)) -> 238.82978 | J19: =IF(Rent!K19=0,0,('TENANT CHARGES'!$H15)) -> 238.82978 | K19: =IF(Rent!L19=0,0,('TENANT CHARGES'!$H15)) -> 238.82978 | L19: =IF(Rent!M19=0,0,('TENANT CHARGES'!$H15)) -> 238.82978 | ... P19: =IF(Rent!Q19=0,0,('TENANT CHARGES'!$H15)) -> 238.82978 | Q19: =SUM(E19:P19) -> 2865.9574 | R19: =P19/C19 -> 0.24027141
A20: =Rent!A20 -> LUCASIE LTD | B20: =Rent!B20 -> D9-D10 | C20: =Rent!D20 -> 1043 | D20: =C20/$C$33 -> 0.020427749 | E20: =IF(Rent!F20=0,0,('TENANT CHARGES'!$H17)) -> 250.60308 | F20: =IF(Rent!G20=0,0,('TENANT CHARGES'!$H17)) -> 250.60308 | G20: =IF(Rent!H20=0,0,('TENANT CHARGES'!$H17)) -> 250.60308 | H20: =IF(Rent!I20=0,0,('TENANT CHARGES'!$H17)) -> 250.60308 | I20: =IF(Rent!J20=0,0,('TENANT CHARGES'!$H17)) -> 250.60308 | J20: =IF(Rent!K20=0,0,('TENANT CHARGES'!$H17)) -> 250.60308 | K20: =IF(Rent!L20=0,0,('TENANT CHARGES'!$H17)) -> 250.60308 | L20: =IF(Rent!M20=0,0,('TENANT CHARGES'!$H17)) -> 250.60308 | ... P20: =IF(Rent!Q20=0,0,('TENANT CHARGES'!$H17)) -> 250.60308 | Q20: =SUM(E20:P20) -> 3007.237 | R20: =P20/C20 -> 0.24027141
A21: =Rent!A21 -> FOSTERS KITCHEN | B21: =Rent!B21 -> DU-1 | C21: =Rent!D21 -> 3526 | D21: =C21/$C$33 -> 0.069058718 | E21: =IF(Rent!F21=0,0,('TENANT CHARGES'!$H18)) -> 847.21164 | F21: =IF(Rent!G21=0,0,('TENANT CHARGES'!$H18)) -> 847.21164 | G21: =IF(Rent!H21=0,0,('TENANT CHARGES'!$H18)) -> 847.21164 | H21: =IF(Rent!I21=0,0,('TENANT CHARGES'!$H18)) -> 847.21164 | I21: =IF(Rent!J21=0,0,('TENANT CHARGES'!$H18)) -> 847.21164 | J21: =IF(Rent!K21=0,0,('TENANT CHARGES'!$H18)) -> 847.21164 | K21: =IF(Rent!L21=0,0,('TENANT CHARGES'!$H18)) -> 847.21164 | L21: =IF(Rent!M21=0,0,('TENANT CHARGES'!$H18)) -> 847.21164 | ... P21: =IF(Rent!Q21=0,0,('TENANT CHARGES'!$H18)) -> 847.21164 | Q21: =SUM(E21:P21) -> 10166.54 | R21: =P21/C21 -> 0.24027556
A22: =Rent!A22 -> HUMPYS BIG ISLAND ALEHOUSE | B22: =Rent!B22 -> E | C22: =Rent!D22 -> 10736 | D22: =C22/$C$33 -> 0.21027067 | E22: 0 | F22: 0 | G22: 0 | H22: 0 | I22: 0 | J22: 0 | K22: 0 | L22: 0 | M22: =IF(Rent!N22=0,0,('TENANT CHARGES'!$H19)) -> 2579.5985 | N22: =IF(Rent!O22=0,0,('TENANT CHARGES'!$H19)) -> 2579.5985 | O22: =IF(Rent!P22=0,0,('TENANT CHARGES'!$H19)) -> 2579.5985 | P22: =IF(Rent!Q22=0,0,('TENANT CHARGES'!$H19)) -> 2579.5985 | Q22: =SUM(E22:P22) -> 10318.394 | R22: =P22/C22 -> 0.24027556 | S22: NEW AMENDMENT SIGNED; ASSUME $25K/MO; full rents will resume 9/1/26
A23: =Rent!A23 -> ABC STORE #75 | B23: =Rent!B23 -> F15,17&A8 | C23: =Rent!D23 -> 4000 | D23: =C23/$C$33 -> 0.078342277 | E23: =IF(Rent!F23=0,0,('TENANT CHARGES'!$H20)) -> 720.82669 | F23: =IF(Rent!G23=0,0,('TENANT CHARGES'!$H20)) -> 720.82669 | G23: =IF(Rent!H23=0,0,('TENANT CHARGES'!$H20)) -> 720.82669 | H23: =IF(Rent!I23=0,0,('TENANT CHARGES'!$H20)) -> 720.82669 | I23: =IF(Rent!J23=0,0,('TENANT CHARGES'!$H20)) -> 720.82669 | J23: =IF(Rent!K23=0,0,('TENANT CHARGES'!$H20)) -> 720.82669 | K23: =IF(Rent!L23=0,0,('TENANT CHARGES'!$H20)) -> 720.82669 | L23: =IF(Rent!M23=0,0,('TENANT CHARGES'!$H20)) -> 720.82669 | ... P23: =IF(Rent!Q23=0,0,('TENANT CHARGES'!$H20)) -> 720.82669 | Q23: =SUM(E23:P23) -> 8649.9203 | R23: =P23/C23 -> 0.18020667
A24: =Rent!A24 -> GYPSEA GALATO | B24: =Rent!B24 -> F-16 | C24: =Rent!D24 -> 500 | D24: =C24/$C$33 -> 0.0097927847 | E24: =IF(Rent!F24=0,0,('TENANT CHARGES'!$H21)) -> 120.13778 | F24: =IF(Rent!G24=0,0,('TENANT CHARGES'!$H21)) -> 120.13778 | G24: =IF(Rent!H24=0,0,('TENANT CHARGES'!$H21)) -> 120.13778 | H24: =IF(Rent!I24=0,0,('TENANT CHARGES'!$H21)) -> 120.13778 | I24: =IF(Rent!J24=0,0,('TENANT CHARGES'!$H21)) -> 120.13778 | J24: =IF(Rent!K24=0,0,('TENANT CHARGES'!$H21)) -> 120.13778 | K24: =IF(Rent!L24=0,0,('TENANT CHARGES'!$H21)) -> 120.13778 | L24: =IF(Rent!M24=0,0,('TENANT CHARGES'!$H21)) -> 120.13778 | ... P24: =IF(Rent!Q24=0,0,('TENANT CHARGES'!$H21)) -> 120.13778 | Q24: =SUM(E24:P24) -> 1441.6534 | R24: =P24/C24 -> 0.24027556
A25: =Rent!A25 -> OCEANS SPORTS BAR AND GRILL | B25: =Rent!B25 -> G | C25: =Rent!D25 -> 2896 | D25: =C25/$C$33 -> 0.056719809 | E25: =IF(Rent!F25=0,0,('TENANT CHARGES'!$H22)) -> 0 | F25: =IF(Rent!G25=0,0,('TENANT CHARGES'!$H22)) -> 0 | G25: =IF(Rent!H25=0,0,('TENANT CHARGES'!$H22)) -> 0 | H25: =IF(Rent!I25=0,0,('TENANT CHARGES'!$H22)) -> 0 | I25: =IF(Rent!J25=0,0,('TENANT CHARGES'!$H22)) -> 0 | J25: =IF(Rent!K25=0,0,('TENANT CHARGES'!$H22)) -> 0 | K25: =IF(Rent!L25=0,0,('TENANT CHARGES'!$H22)) -> 0 | L25: =IF(Rent!M25=0,0,('TENANT CHARGES'!$H22)) -> 0 | ... P25: =IF(Rent!Q25=0,0,('TENANT CHARGES'!$H22)) -> 0 | Q25: =SUM(E25:P25) -> 0 | R25: =P25/C25 -> 0
A26: =Rent!A26 -> JACKS DIVE LOCKER | B26: =Rent!B26 -> H | C26: =Rent!D26 -> 8014 | D26: =C26/$C$33 -> 0.15695875 | E26: =IF(Rent!F26=0,0,('TENANT CHARGES'!$H23)) -> 0 | F26: =IF(Rent!G26=0,0,('TENANT CHARGES'!$H23)) -> 0 | G26: =IF(Rent!H26=0,0,('TENANT CHARGES'!$H23)) -> 0 | H26: =IF(Rent!I26=0,0,('TENANT CHARGES'!$H23)) -> 0 | I26: =IF(Rent!J26=0,0,('TENANT CHARGES'!$H23)) -> 0 | J26: =IF(Rent!K26=0,0,('TENANT CHARGES'!$H23)) -> 0 | K26: =IF(Rent!L26=0,0,('TENANT CHARGES'!$H23)) -> 0 | L26: =IF(Rent!M26=0,0,('TENANT CHARGES'!$H23)) -> 0 | ... P26: =IF(Rent!Q26=0,0,('TENANT CHARGES'!$H23)) -> 0 | Q26: =SUM(E26:P26) -> 0 | R26: =P26/C26 -> 0
A27: =Rent!A27 -> QPOT | B27: =Rent!B27 -> I | C27: =Rent!D27 -> 6500 | D27: =C27/$C$33 -> 0.1273062 | E27: =IF(Rent!F27=0,0,('TENANT CHARGES'!$H24)) -> 0 | F27: =IF(Rent!G27=0,0,('TENANT CHARGES'!$H24)) -> 0 | G27: =IF(Rent!H27=0,0,('TENANT CHARGES'!$H24)) -> 0 | H27: =IF(Rent!I27=0,0,('TENANT CHARGES'!$H24)) -> 0 | I27: =IF(Rent!J27=0,0,('TENANT CHARGES'!$H24)) -> 0 | J27: =IF(Rent!K27=0,0,('TENANT CHARGES'!$H24)) -> 0 | K27: =IF(Rent!L27=0,0,('TENANT CHARGES'!$H24)) -> 0 | L27: =IF(Rent!M27=0,0,('TENANT CHARGES'!$H24)) -> 0 | ... P27: =IF(Rent!Q27=0,0,('TENANT CHARGES'!$H24)) -> 0 | Q27: =SUM(E27:P27) -> 0 | R27: =P27/C27 -> 0
A28: =Rent!A28 -> BOWLS SUPERFOODS & ORALE TACOS | B28: =Rent!B28 -> PC-1&2 | C28: =Rent!D28 -> 1993 | D28: =C28/$C$33 -> 0.03903404 | E28: =IF(Rent!F28=0,0,('TENANT CHARGES'!$H25)) -> 0 | F28: =IF(Rent!G28=0,0,('TENANT CHARGES'!$H25)) -> 0 | G28: =IF(Rent!H28=0,0,('TENANT CHARGES'!$H25)) -> 0 | H28: =IF(Rent!I28=0,0,('TENANT CHARGES'!$H25)) -> 0 | I28: =IF(Rent!J28=0,0,('TENANT CHARGES'!$H25)) -> 0 | J28: =IF(Rent!K28=0,0,('TENANT CHARGES'!$H25)) -> 0 | K28: =IF(Rent!L28=0,0,('TENANT CHARGES'!$H25)) -> 0 | L28: =IF(Rent!M28=0,0,('TENANT CHARGES'!$H25)) -> 0 | ... P28: =IF(Rent!Q28=0,0,('TENANT CHARGES'!$H25)) -> 0 | Q28: =SUM(E28:P28) -> 0 | R28: =P28/C28 -> 0
A29: =Rent!A29 -> KONA GEAR INC. | B29: =Rent!B29 -> PC 3&4 | C29: =Rent!D29 -> 962 | D29: =C29/$C$33 -> 0.018841318 | E29: =IF(Rent!F29=0,0,('TENANT CHARGES'!$H26)) -> 72.401195 | F29: =IF(Rent!G29=0,0,('TENANT CHARGES'!$H26)) -> 72.401195 | G29: =IF(Rent!H29=0,0,('TENANT CHARGES'!$H26)) -> 72.401195 | H29: =IF(Rent!I29=0,0,('TENANT CHARGES'!$H26)) -> 72.401195 | I29: =IF(Rent!J29=0,0,('TENANT CHARGES'!$H26)) -> 72.401195 | J29: =IF(Rent!K29=0,0,('TENANT CHARGES'!$H26)) -> 72.401195 | K29: =IF(Rent!L29=0,0,('TENANT CHARGES'!$H26)) -> 72.401195 | L29: =IF(Rent!M29=0,0,('TENANT CHARGES'!$H26)) -> 72.401195 | ... P29: =IF(Rent!Q29=0,0,('TENANT CHARGES'!$H26)) -> 72.401195 | Q29: =SUM(E29:P29) -> 868.81434 | R29: =P29/C29 -> 0.075261117
A30: =Rent!A30 -> LAVERNES | B30: =Rent!B30 -> PC/U1 | C30: =Rent!D30 -> 3704 | D30: =C30/$C$33 -> 0.072544949 | E30: =IF(Rent!F30=0,0,('TENANT CHARGES'!$H27)) -> 278.76718 | F30: =IF(Rent!G30=0,0,('TENANT CHARGES'!$H27)) -> 278.76718 | G30: =IF(Rent!H30=0,0,('TENANT CHARGES'!$H27)) -> 278.76718 | H30: =IF(Rent!I30=0,0,('TENANT CHARGES'!$H27)) -> 278.76718 | I30: =IF(Rent!J30=0,0,('TENANT CHARGES'!$H27)) -> 278.76718 | J30: =IF(Rent!K30=0,0,('TENANT CHARGES'!$H27)) -> 278.76718 | K30: =IF(Rent!L30=0,0,('TENANT CHARGES'!$H27)) -> 278.76718 | L30: =IF(Rent!M30=0,0,('TENANT CHARGES'!$H27)) -> 278.76718 | ... P30: =IF(Rent!Q30=0,0,('TENANT CHARGES'!$H27)) -> 278.76718 | Q30: =SUM(E30:P30) -> 3345.2061 | R30: =P30/C30 -> 0.075261117
A33: TOTALS | C33: =SUM(C14:C32) -> 51058 | D33: =SUM(D14:D32) -> 1 | E33: =SUM(E14:E32) -> 4016.0574 | F33: =SUM(F14:F32) -> 4016.0574 | G33: =SUM(G14:G32) -> 4016.0574 | H33: =SUM(H14:H32) -> 4016.0574 | I33: =SUM(I14:I32) -> 4016.0574 | J33: =SUM(J14:J32) -> 4016.0574 | ... Q33: =SUM(Q14:Q32) -> 58511.083
O35: TOTAL BUILDING | Q35: =Summ.!O106 -> 115757
O36: RECAPTURE | Q36: =Q33/Q35 -> 0.50546475

Sheet % Rent
P1: =Summ.!R1 -> Date Revised: | Q1: =Summ.!#REF! -> #REF! | R1: =Summ.!T1 -> 0
A2: =Summ.!$A2 -> ATHENA PROPERTY MANAGEMENT
A3: =Summ.!$A3 -> Coconut Grove - Kona Hawaii
A4: =Summ.!$A4 -> PROJECT NO. 165
A5: =Summ.!$A5 -> 01/01/26- 12/31/26
A6: =Summ.!$A6 -> 2026 OPERATING BUDGET
A9: TENANT | B9: SUITE | C9: SQUARE | D9: RATE | E9: JAN | F9: FEB | G9: MARCH | H9: APRIL | I9: MAY | J9: JUNE | K9: JULY | L9: AUGUST | M9: SEPT | N9: OCT | O9: NOV | P9: DEC | Q9: TOTALS
B10: # | C10: FOOTAGE
A12: ESTIMATED PERCENTAGE RENT
V13: Aug
A14: =Rent!A14 -> ISLAND LAVA JAVA | B14: =Rent!B14 -> A 1-4 | C14: =Rent!D14 -> 3873 | D14: 0 | E14: 20000 | F14: =E14 -> 20000 | G14: =F14 -> 20000 | H14: =G14 -> 20000 | I14: =H14 -> 20000 | J14: =I14 -> 20000 | K14: =J14 -> 20000 | L14: =K14 -> 20000 | M14: =L14 -> 20000 | ... P14: =O14 -> 20000 | Q14: =SUM(E14:P14) -> 240000 | R14: Average of 2025 PCR | U14: =E14*4.71% -> 942 | V14: =L14*4.71% -> 942
A15: =Rent!A15 -> TAKA SUSHI | B15: =Rent!B15 -> B-5 | C15: =Rent!D15 -> 1074 | D15: 0 | E15: 25 | F15: =E15 -> 25 | G15: =F15 -> 25 | H15: =G15 -> 25 | I15: =H15 -> 25 | J15: =I15 -> 25 | K15: =J15 -> 25 | L15: =K15 -> 25 | M15: =L15 -> 25 | ... P15: =O15 -> 25 | Q15: =SUM(E15:P15) -> 300 | R15: Average of 2025 PCR | U15: =E15*4.71% -> 1.1775 | V15: =L15*4.71% -> 1.1775
A16: =Rent!A16 -> KANAKA KAVA | B16: =Rent!B16 -> B-6 | C16: =Rent!D16 -> 200 | D16: 0 | E16: 200 | F16: =E16 -> 200 | G16: =F16 -> 200 | H16: =G16 -> 200 | I16: =H16 -> 200 | J16: =I16 -> 200 | K16: =J16 -> 200 | L16: =K16 -> 200 | M16: =L16 -> 200 | ... P16: =O16 -> 200 | Q16: =SUM(E16:P16) -> 2400 | R16: Average of 2025 PCR | U16: =E16*4.71% -> 9.42 | V16: =L16*4.71% -> 9.42
A17: =Rent!A17 -> GECKO GIRLZ SHAVE ICE SHACK | B17: =Rent!B17 -> C-7 | C17: =Rent!D17 -> 518 | D17: 0 | E17: 900 | F17: =E17 -> 900 | G17: =F17 -> 900 | H17: =G17 -> 900 | I17: =H17 -> 900 | J17: =I17 -> 900 | K17: =J17 -> 900 | L17: =K17 -> 900 | M17: =L17 -> 900 | ... P17: =O17 -> 900 | Q17: =SUM(E17:P17) -> 10800 | R17: Average of 2025 PCR | U17: =E17*4.71% -> 42.39 | V17: =L17*4.71% -> 42.39
A18: =Rent!A18 -> BIG ISLAND RUNNING CO. | B18: =Rent!B18 -> C-8 | C18: =Rent!D18 -> 525 | D18: 0 | E18: 950 | F18: =E18 -> 950 | G18: =F18 -> 950 | H18: =G18 -> 950 | I18: =H18 -> 950 | J18: =I18 -> 950 | K18: =J18 -> 950 | L18: =K18 -> 950 | M18: =L18 -> 950 | ... P18: =O18 -> 950 | Q18: =SUM(E18:P18) -> 11400 | R18: Average of 2025 PCR | U18: =E18*4.71% -> 44.745 | V18: =L18*4.71% -> 44.745
A19: =Rent!A19 -> CAFE KONA | B19: =Rent!B19 -> D11-12 | C19: =Rent!D19 -> 994 | D19: 0 | E19: 0 | F19: =E19 -> 0 | G19: =F19 -> 0 | H19: =G19 -> 0 | I19: =H19 -> 0 | J19: =I19 -> 0 | K19: =J19 -> 0 | L19: =K19 -> 0 | M19: =L19 -> 0 | ... P19: =O19 -> 0 | Q19: =SUM(E19:P19) -> 0 | R19: Tenant does not pay PCR | U19: =E19*4.71% -> 0 | V19: =L19*4.71% -> 0
A20: =Rent!A20 -> LUCASIE LTD | B20: =Rent!B20 -> D9-D10 | C20: =Rent!D20 -> 1043 | D20: 0 | E20: 0 | F20: 0 | G20: 0 | H20: 0 | I20: 0 | J20: 0 | K20: 0 | L20: 0 | M20: 0 | N20: 0 | O20: 0 | P20: 0 | Q20: =SUM(E20:P20) -> 0 | R20: Tenant does not pay PCR | U20: =E20*4.71% -> 0 | V20: =L20*4.71% -> 0
A21: =Rent!A21 -> FOSTERS KITCHEN | B21: =Rent!B21 -> DU-1 | C21: =Rent!D21 -> 3526 | D21: 0 | F21: =E21 -> 0 | G21: =F21 -> 0 | H21: =G21 -> 0 | I21: =H21 -> 0 | J21: =I21 -> 0 | L21: 4500 | M21: =L21 -> 4500 | N21: =M21 -> 4500 | O21: =N21 -> 4500 | P21: =O21 -> 4500 | Q21: =SUM(E21:P21) -> 22500 | R21: Average of 2025 PCR; begin July due to fire damage | U21: =E21*4.71% -> 0 | V21: =L21*4.71% -> 211.95
A22: =Rent!A22 -> HUMPYS BIG ISLAND ALEHOUSE | B22: =Rent!B22 -> E | C22: =Rent!D22 -> 10736 | D22: 0 | E22: 0 | F22: 0 | G22: 0 | H22: 0 | I22: 0 | J22: 0 | K22: 0 | M22: 3000 | N22: 3000 | O22: 3000 | P22: 3000 | Q22: =SUM(E22:P22) -> 12000 | R22: Tenant paying substitute rent through 09/2027 | U22: =E22*4.71% -> 0 | V22: =L22*4.71% -> 0
A23: =Rent!A23 -> ABC STORE #75 | B23: =Rent!B23 -> F15,17&A8 | C23: =Rent!D23 -> 4000 | D23: 0.1 | E23: 18000 | F23: =E23 -> 18000 | G23: =F23 -> 18000 | H23: =G23 -> 18000 | I23: =H23 -> 18000 | J23: =I23 -> 18000 | K23: =J23 -> 18000 | L23: =K23 -> 18000 | M23: =L23 -> 18000 | ... P23: =O23 -> 18000 | Q23: =SUM(E23:P23) -> 216000 | R23: Average of 2025 PCR | U23: =E23*4.71% -> 847.8 | V23: =L23*4.71% -> 847.8
A24: =Rent!A24 -> GYPSEA GALATO | B24: =Rent!B24 -> F-16 | C24: =Rent!D24 -> 500 | D24: 0 | E24: 820 | F24: =E24 -> 820 | G24: =F24 -> 820 | H24: =G24 -> 820 | I24: =H24 -> 820 | J24: =I24 -> 820 | K24: =J24 -> 820 | L24: =K24 -> 820 | M24: =L24 -> 820 | ... P24: =O24 -> 820 | Q24: =SUM(E24:P24) -> 9840 | R24: Average of 2025 PCR | U24: =E24*4.71% -> 38.622 | V24: =L24*4.71% -> 38.622
A25: =Rent!A25 -> OCEANS SPORTS BAR AND GRILL | B25: =Rent!B25 -> G | C25: =Rent!D25 -> 2896 | D25: 0 | E25: 0 | F25: 0 | G25: 0 | H25: 0 | I25: 0 | J25: 0 | K25: 0 | L25: 0 | M25: 0 | N25: 0 | O25: 0 | P25: 0 | Q25: =SUM(E25:P25) -> 0 | R25: Tenant does not pay PCR | U25: =E25*4.71% -> 0 | V25: =L25*4.71% -> 0
A26: =Rent!A26 -> JACKS DIVE LOCKER | B26: =Rent!B26 -> H | C26: =Rent!D26 -> 8014 | D26: 0 | E26: 0 | F26: 0 | G26: 0 | H26: 0 | I26: 0 | J26: 0 | K26: 0 | L26: 0 | M26: 0 | N26: 0 | O26: 0 | P26: 0 | Q26: =SUM(E26:P26) -> 0 | R26: Tenant does not pay PCR | U26: =E26*4.71% -> 0 | V26: =L26*4.71% -> 0
A27: =Rent!A27 -> QPOT | B27: =Rent!B27 -> I | C27: =Rent!D27 -> 6500 | D27: 0 | G27: 0 | J27: 0 | M27: 0 | P27: 0 | Q27: =SUM(E27:P27) -> 0 | R27: Assume July 1st RCD; no PCR projected for 2026 (artifical breakpoint of $4.5M) | U27: =E27*4.71% -> 0 | V27: =L27*4.71% -> 0
A28: =Rent!A28 -> BOWLS SUPERFOODS & ORALE TACOS | B28: =Rent!B28 -> PC-1&2 | C28: =Rent!D28 -> 1993 | D28: 0 | E28: 0 | F28: 0 | G28: 0 | H28: 0 | I28: 0 | J28: 0 | K28: 0 | L28: 0 | M28: 0 | N28: 0 | O28: 0 | P28: 0 | Q28: =SUM(E28:P28) -> 0 | R28: Tenant is closed. | U28: =E28*4.71% -> 0 | V28: =L28*4.71% -> 0
A29: =Rent!A29 -> KONA GEAR INC. | B29: =Rent!B29 -> PC 3&4 | C29: =Rent!D29 -> 962 | D29: 0 | E29: 3000 | F29: =E29 -> 3000 | G29: =F29 -> 3000 | H29: =G29 -> 3000 | I29: =H29 -> 3000 | J29: =I29 -> 3000 | K29: =J29 -> 3000 | L29: =K29 -> 3000 | M29: =L29 -> 3000 | ... P29: =O29 -> 3000 | Q29: =SUM(E29:P29) -> 36000 | R29: Average of 2025 PCR | U29: =E29*4.71% -> 141.3 | V29: =L29*4.71% -> 141.3
A30: =Rent!A30 -> LAVERNES | B30: =Rent!B30 -> PC/U1 | C30: =Rent!D30 -> 3704 | D30: 0 | E30: 0 | F30: 0 | G30: 0 | H30: 0 | I30: 0 | J30: 0 | K30: 0 | L30: 0 | M30: 0 | N30: 0 | O30: 0 | P30: 0 | Q30: =SUM(E30:P30) -> 0 | R30: Tenant does not pay PCR
A36: TOTALS | C36: =SUM(C14:C35) -> 51058 | E36: =SUM(E14:E35) -> 43895 | F36: =SUM(F14:F35) -> 43895 | G36: =SUM(G14:G35) -> 43895 | H36: =SUM(H14:H35) -> 43895 | I36: =SUM(I14:I35) -> 43895 | J36: =SUM(J14:J35) -> 43895 | K36: =SUM(K14:K35) -> 43895 | L36: =SUM(L14:L35) -> 48395 | ... Q36: =SUM(Q14:Q35) -> 561240 | U36: =SUM(U14:U35) -> 2067.4545

Sheet Ins.
Q1: =Summ.!R1 -> Date Revised: | R1: =Summ.!#REF! -> #REF! | S1: =Summ.!T1 -> 0
A2: =Summ.!$A2 -> ATHENA PROPERTY MANAGEMENT
A3: =Summ.!$A3 -> Coconut Grove - Kona Hawaii
A4: =Summ.!$A4 -> PROJECT NO. 165
A5: =Summ.!$A5 -> 01/01/26- 12/31/26
A6: =Summ.!$A6 -> 2026 OPERATING BUDGET
D8: Liability | E8: Property
A9: TENANT | B9: SUITE | C9: SQUARE | D9: PRORATA | E9: PRORATA | F9: JAN | G9: FEB | H9: MARCH | I9: APRIL | J9: MAY | K9: JUNE | L9: JULY | M9: AUGUST | N9: SEPT | O9: OCT | P9: NOV | Q9: DEC | R9: TOTALS
B10: # | C10: FOOTAGE | D10: SHARE | E10: SHARE
A12: INSURANCE
A14: =Rent!A14 -> ISLAND LAVA JAVA | B14: =Rent!B14 -> A 1-4 | C14: =Rent!D14 -> 3873 | D14: 0 | E14: 0 | F14: =IF(Rent!F14=0,0,('TENANT CHARGES'!$J10)) -> 1512.8085 | G14: =IF(Rent!G14=0,0,('TENANT CHARGES'!$J10)) -> 1512.8085 | H14: =IF(Rent!H14=0,0,('TENANT CHARGES'!$J10)) -> 1512.8085 | I14: =IF(Rent!I14=0,0,('TENANT CHARGES'!$J10)) -> 1512.8085 | J14: =IF(Rent!J14=0,0,('TENANT CHARGES'!$J10)) -> 1512.8085 | K14: =IF(Rent!K14=0,0,('TENANT CHARGES'!$J10)) -> 1512.8085 | L14: =IF(Rent!L14=0,0,('TENANT CHARGES'!$J10)) -> 1512.8085 | M14: =IF(Rent!M14=0,0,('TENANT CHARGES'!$J10)) -> 1512.8085 | ... Q14: =IF(Rent!Q14=0,0,('TENANT CHARGES'!$J10)) -> 1512.8085 | R14: =SUM(F14:Q14) -> 18153.702 | S14: =Q14/C14 -> 0.3906038
A15: =Rent!A15 -> TAKA SUSHI | B15: =Rent!B15 -> B-5 | C15: =Rent!D15 -> 1074 | D15: =C15/$C$33 -> 0.021034901 | E15: =C15/$C$34 -> #REF! | F15: =IF(Rent!F15=0,0,('TENANT CHARGES'!$J11)) -> 419.50848 | G15: =IF(Rent!G15=0,0,('TENANT CHARGES'!$J11)) -> 419.50848 | H15: =IF(Rent!H15=0,0,('TENANT CHARGES'!$J11)) -> 419.50848 | I15: =IF(Rent!I15=0,0,('TENANT CHARGES'!$J11)) -> 419.50848 | J15: =IF(Rent!J15=0,0,('TENANT CHARGES'!$J11)) -> 419.50848 | K15: =IF(Rent!K15=0,0,('TENANT CHARGES'!$J11)) -> 419.50848 | L15: =IF(Rent!L15=0,0,('TENANT CHARGES'!$J11)) -> 419.50848 | M15: =IF(Rent!M15=0,0,('TENANT CHARGES'!$J11)) -> 419.50848 | ... Q15: =IF(Rent!Q15=0,0,('TENANT CHARGES'!$J11)) -> 419.50848 | R15: =SUM(F15:Q15) -> 5034.1017 | S15: =Q15/C15 -> 0.3906038
A16: =Rent!A16 -> KANAKA KAVA | B16: =Rent!B16 -> B-6 | C16: =Rent!D16 -> 200 | D16: =C16/$C$33 -> 0.0039171139 | E16: =C16/$C$34 -> #REF! | F16: =IF(Rent!F16=0,0,('TENANT CHARGES'!$J12)) -> 78.120759 | G16: =IF(Rent!G16=0,0,('TENANT CHARGES'!$J12)) -> 78.120759 | H16: =IF(Rent!H16=0,0,('TENANT CHARGES'!$J12)) -> 78.120759 | I16: =IF(Rent!I16=0,0,('TENANT CHARGES'!$J12)) -> 78.120759 | J16: =IF(Rent!J16=0,0,('TENANT CHARGES'!$J12)) -> 78.120759 | K16: =IF(Rent!K16=0,0,('TENANT CHARGES'!$J12)) -> 78.120759 | L16: =IF(Rent!L16=0,0,('TENANT CHARGES'!$J12)) -> 78.120759 | M16: =IF(Rent!M16=0,0,('TENANT CHARGES'!$J12)) -> 78.120759 | ... Q16: =IF(Rent!Q16=0,0,('TENANT CHARGES'!$J12)) -> 78.120759 | R16: =SUM(F16:Q16) -> 937.44911 | S16: =Q16/C16 -> 0.3906038
A17: =Rent!A17 -> GECKO GIRLZ SHAVE ICE SHACK | B17: =Rent!B17 -> C-7 | C17: =Rent!D17 -> 518 | D17: =C17/$C$33 -> 0.010145325 | E17: =C17/$C$34 -> #REF! | F17: =IF(Rent!F17=0,0,('TENANT CHARGES'!$J13)) -> 202.33277 | G17: =IF(Rent!G17=0,0,('TENANT CHARGES'!$J13)) -> 202.33277 | H17: =IF(Rent!H17=0,0,('TENANT CHARGES'!$J13)) -> 202.33277 | I17: =IF(Rent!I17=0,0,('TENANT CHARGES'!$J13)) -> 202.33277 | J17: =IF(Rent!J17=0,0,('TENANT CHARGES'!$J13)) -> 202.33277 | K17: =IF(Rent!K17=0,0,('TENANT CHARGES'!$J13)) -> 202.33277 | L17: =IF(Rent!L17=0,0,('TENANT CHARGES'!$J13)) -> 202.33277 | M17: =IF(Rent!M17=0,0,('TENANT CHARGES'!$J13)) -> 202.33277 | ... Q17: =IF(Rent!Q17=0,0,('TENANT CHARGES'!$J13)) -> 202.33277 | R17: =SUM(F17:Q17) -> 2427.9932 | S17: =Q17/C17 -> 0.3906038
A18: =Rent!A18 -> BIG ISLAND RUNNING CO. | B18: =Rent!B18 -> C-8 | C18: =Rent!D18 -> 525 | D18: =C18/$C$33 -> 0.010282424 | E18: =C18/$C$34 -> #REF! | F18: =IF(Rent!F18=0,0,('TENANT CHARGES'!$J14)) -> 205.06699 | G18: =IF(Rent!G18=0,0,('TENANT CHARGES'!$J14)) -> 205.06699 | H18: =IF(Rent!H18=0,0,('TENANT CHARGES'!$J14)) -> 205.06699 | I18: =IF(Rent!I18=0,0,('TENANT CHARGES'!$J14)) -> 205.06699 | J18: =IF(Rent!J18=0,0,('TENANT CHARGES'!$J14)) -> 205.06699 | K18: =IF(Rent!K18=0,0,('TENANT CHARGES'!$J14)) -> 205.06699 | L18: =IF(Rent!L18=0,0,('TENANT CHARGES'!$J14)) -> 205.06699 | M18: =IF(Rent!M18=0,0,('TENANT CHARGES'!$J14)) -> 205.06699 | ... Q18: =IF(Rent!Q18=0,0,('TENANT CHARGES'!$J14)) -> 205.06699 | R18: =SUM(F18:Q18) -> 2460.8039 | S18: =Q18/C18 -> 0.3906038
A19: =Rent!A19 -> CAFE KONA | B19: =Rent!B19 -> D11-12 | C19: =Rent!D19 -> 994 | D19: =C19/$C$33 -> 0.019468056 | E19: =C19/$C$34 -> #REF! | F19: =IF(Rent!F19=0,0,('TENANT CHARGES'!$J15)) -> 388.26017 | G19: =IF(Rent!G19=0,0,('TENANT CHARGES'!$J15)) -> 388.26017 | H19: =IF(Rent!H19=0,0,('TENANT CHARGES'!$J15)) -> 388.26017 | I19: =IF(Rent!I19=0,0,('TENANT CHARGES'!$J15)) -> 388.26017 | J19: =IF(Rent!J19=0,0,('TENANT CHARGES'!$J15)) -> 388.26017 | K19: =IF(Rent!K19=0,0,('TENANT CHARGES'!$J15)) -> 388.26017 | L19: =IF(Rent!L19=0,0,('TENANT CHARGES'!$J15)) -> 388.26017 | M19: =IF(Rent!M19=0,0,('TENANT CHARGES'!$J15)) -> 388.26017 | ... Q19: =IF(Rent!Q19=0,0,('TENANT CHARGES'!$J15)) -> 388.26017 | R19: =SUM(F19:Q19) -> 4659.1221 | S19: =Q19/C19 -> 0.3906038
A20: =Rent!A20 -> LUCASIE LTD | B20: =Rent!B20 -> D9-D10 | C20: =Rent!D20 -> 1043 | D20: =C20/$C$33 -> 0.020427749 | E20: =C20/$C$34 -> #REF! | F20: =IF(Rent!F20=0,0,('TENANT CHARGES'!$J17)) -> 407.39976 | G20: =IF(Rent!G20=0,0,('TENANT CHARGES'!$J17)) -> 407.39976 | H20: =IF(Rent!H20=0,0,('TENANT CHARGES'!$J17)) -> 407.39976 | I20: =IF(Rent!I20=0,0,('TENANT CHARGES'!$J17)) -> 407.39976 | J20: =IF(Rent!J20=0,0,('TENANT CHARGES'!$J17)) -> 407.39976 | K20: =IF(Rent!K20=0,0,('TENANT CHARGES'!$J17)) -> 407.39976 | L20: =IF(Rent!L20=0,0,('TENANT CHARGES'!$J17)) -> 407.39976 | M20: =IF(Rent!M20=0,0,('TENANT CHARGES'!$J17)) -> 407.39976 | ... Q20: =IF(Rent!Q20=0,0,('TENANT CHARGES'!$J17)) -> 407.39976 | R20: =SUM(F20:Q20) -> 4888.7971 | S20: =Q20/C20 -> 0.3906038
A21: =Rent!A21 -> FOSTERS KITCHEN | B21: =Rent!B21 -> DU-1 | C21: =Rent!D21 -> 3526 | D21: =C21/$C$33 -> 0.069058718 | E21: =C21/$C$34 -> #REF! | F21: =IF(Rent!F21=0,0,('TENANT CHARGES'!$J18)) -> 1377.269 | G21: =IF(Rent!G21=0,0,('TENANT CHARGES'!$J18)) -> 1377.269 | H21: =IF(Rent!H21=0,0,('TENANT CHARGES'!$J18)) -> 1377.269 | I21: =IF(Rent!I21=0,0,('TENANT CHARGES'!$J18)) -> 1377.269 | J21: =IF(Rent!J21=0,0,('TENANT CHARGES'!$J18)) -> 1377.269 | K21: =IF(Rent!K21=0,0,('TENANT CHARGES'!$J18)) -> 1377.269 | L21: =IF(Rent!L21=0,0,('TENANT CHARGES'!$J18)) -> 1377.269 | M21: =IF(Rent!M21=0,0,('TENANT CHARGES'!$J18)) -> 1377.269 | ... Q21: =IF(Rent!Q21=0,0,('TENANT CHARGES'!$J18)) -> 1377.269 | R21: =SUM(F21:Q21) -> 16527.228 | S21: =Q21/C21 -> 0.3906038
A22: =Rent!A22 -> HUMPYS BIG ISLAND ALEHOUSE | B22: =Rent!B22 -> E | C22: =Rent!D22 -> 10736 | D22: =C22/$C$33 -> 0.21027067 | E22: =C22/$C$34 -> #REF! | F22: 0 | G22: 0 | H22: 0 | I22: 0 | J22: 0 | K22: 0 | L22: 0 | M22: 0 | N22: =IF(Rent!N22=0,0,('TENANT CHARGES'!$J19)) -> 4193.5224 | O22: =IF(Rent!O22=0,0,('TENANT CHARGES'!$J19)) -> 4193.5224 | P22: =IF(Rent!P22=0,0,('TENANT CHARGES'!$J19)) -> 4193.5224 | Q22: =IF(Rent!Q22=0,0,('TENANT CHARGES'!$J19)) -> 4193.5224 | R22: =SUM(F22:Q22) -> 16774.089 | S22: =Q22/C22 -> 0.3906038 | T22: NEW AMENDMENT SIGNED; ASSUME $25K/MO; full rents will resume 9/1/26
A23: =Rent!A23 -> ABC STORE #75 | B23: =Rent!B23 -> F15,17&A8 | C23: =Rent!D23 -> 4000 | D23: =C23/$C$33 -> 0.078342277 | E23: =C23/$C$34 -> #REF! | F23: =IF(Rent!F23=0,0,('TENANT CHARGES'!$J20)) -> 1171.8114 | G23: =IF(Rent!G23=0,0,('TENANT CHARGES'!$J20)) -> 1171.8114 | H23: =IF(Rent!H23=0,0,('TENANT CHARGES'!$J20)) -> 1171.8114 | I23: =IF(Rent!I23=0,0,('TENANT CHARGES'!$J20)) -> 1171.8114 | J23: =IF(Rent!J23=0,0,('TENANT CHARGES'!$J20)) -> 1171.8114 | K23: =IF(Rent!K23=0,0,('TENANT CHARGES'!$J20)) -> 1171.8114 | L23: =IF(Rent!L23=0,0,('TENANT CHARGES'!$J20)) -> 1171.8114 | M23: =IF(Rent!M23=0,0,('TENANT CHARGES'!$J20)) -> 1171.8114 | ... Q23: =IF(Rent!Q23=0,0,('TENANT CHARGES'!$J20)) -> 1171.8114 | R23: =SUM(F23:Q23) -> 14061.737 | S23: =Q23/C23 -> 0.29295285
A24: =Rent!A24 -> GYPSEA GALATO | B24: =Rent!B24 -> F-16 | C24: =Rent!D24 -> 500 | D24: =C24/$C$33 -> 0.0097927847 | E24: =C24/$C$34 -> #REF! | F24: =IF(Rent!F24=0,0,('TENANT CHARGES'!$J21)) -> 195.3019 | G24: =IF(Rent!G24=0,0,('TENANT CHARGES'!$J21)) -> 195.3019 | H24: =IF(Rent!H24=0,0,('TENANT CHARGES'!$J21)) -> 195.3019 | I24: =IF(Rent!I24=0,0,('TENANT CHARGES'!$J21)) -> 195.3019 | J24: =IF(Rent!J24=0,0,('TENANT CHARGES'!$J21)) -> 195.3019 | K24: =IF(Rent!K24=0,0,('TENANT CHARGES'!$J21)) -> 195.3019 | L24: =IF(Rent!L24=0,0,('TENANT CHARGES'!$J21)) -> 195.3019 | M24: =IF(Rent!M24=0,0,('TENANT CHARGES'!$J21)) -> 195.3019 | ... Q24: =IF(Rent!Q24=0,0,('TENANT CHARGES'!$J21)) -> 195.3019 | R24: =SUM(F24:Q24) -> 2343.6228 | S24: =Q24/C24 -> 0.3906038
A25: =Rent!A25 -> OCEANS SPORTS BAR AND GRILL | B25: =Rent!B25 -> G | C25: =Rent!D25 -> 2896 | D25: =C25/$C$33 -> 0.056719809 | E25: =C25/$C$34 -> #REF! | F25: =IF(Rent!F25=0,0,('TENANT CHARGES'!$J22)) -> 95.194273 | G25: =IF(Rent!G25=0,0,('TENANT CHARGES'!$J22)) -> 95.194273 | H25: =IF(Rent!H25=0,0,('TENANT CHARGES'!$J22)) -> 95.194273 | I25: =IF(Rent!I25=0,0,('TENANT CHARGES'!$J22)) -> 95.194273 | J25: =IF(Rent!J25=0,0,('TENANT CHARGES'!$J22)) -> 95.194273 | K25: =IF(Rent!K25=0,0,('TENANT CHARGES'!$J22)) -> 95.194273 | L25: =IF(Rent!L25=0,0,('TENANT CHARGES'!$J22)) -> 95.194273 | M25: =IF(Rent!M25=0,0,('TENANT CHARGES'!$J22)) -> 95.194273 | ... Q25: =IF(Rent!Q25=0,0,('TENANT CHARGES'!$J22)) -> 95.194273 | R25: =SUM(F25:Q25) -> 1142.3313 | S25: =Q25/C25 -> 0.032870951
A26: =Rent!A26 -> JACKS DIVE LOCKER | B26: =Rent!B26 -> H | C26: =Rent!D26 -> 8014 | D26: =C26/$C$33 -> 0.15695875 | E26: =C26/$C$34 -> #REF! | F26: =IF(Rent!F26=0,0,('TENANT CHARGES'!$J23)) -> 263.4278 | G26: =IF(Rent!G26=0,0,('TENANT CHARGES'!$J23)) -> 263.4278 | H26: =IF(Rent!H26=0,0,('TENANT CHARGES'!$J23)) -> 263.4278 | I26: =IF(Rent!I26=0,0,('TENANT CHARGES'!$J23)) -> 263.4278 | J26: =IF(Rent!J26=0,0,('TENANT CHARGES'!$J23)) -> 263.4278 | K26: =IF(Rent!K26=0,0,('TENANT CHARGES'!$J23)) -> 263.4278 | L26: =IF(Rent!L26=0,0,('TENANT CHARGES'!$J23)) -> 263.4278 | M26: =IF(Rent!M26=0,0,('TENANT CHARGES'!$J23)) -> 263.4278 | ... Q26: =IF(Rent!Q26=0,0,('TENANT CHARGES'!$J23)) -> 263.4278 | R26: =SUM(F26:Q26) -> 3161.1336 | S26: =Q26/C26 -> 0.032870951
A27: =Rent!A27 -> QPOT | B27: =Rent!B27 -> I | C27: =Rent!D27 -> 6500 | D27: =C27/$C$33 -> 0.1273062 | E27: =C27/$C$34 -> #REF! | F27: =IF(Rent!F27=0,0,('TENANT CHARGES'!$J24)) -> 0 | G27: =IF(Rent!G27=0,0,('TENANT CHARGES'!$J24)) -> 0 | H27: =IF(Rent!H27=0,0,('TENANT CHARGES'!$J24)) -> 0 | I27: =IF(Rent!I27=0,0,('TENANT CHARGES'!$J24)) -> 0 | J27: =IF(Rent!J27=0,0,('TENANT CHARGES'!$J24)) -> 0 | K27: =IF(Rent!K27=0,0,('TENANT CHARGES'!$J24)) -> 0 | L27: =IF(Rent!L27=0,0,('TENANT CHARGES'!$J24)) -> 2538.9247 | M27: =IF(Rent!M27=0,0,('TENANT CHARGES'!$J24)) -> 2538.9247 | ... Q27: =IF(Rent!Q27=0,0,('TENANT CHARGES'!$J24)) -> 2538.9247 | R27: =SUM(F27:Q27) -> 15233.548 | S27: =Q27/C27 -> 0.3906038
A28: =Rent!A28 -> BOWLS SUPERFOODS & ORALE TACOS | B28: =Rent!B28 -> PC-1&2 | C28: =Rent!D28 -> 1993 | D28: =C28/$C$33 -> 0.03903404 | E28: =C28/$C$34 -> #REF! | F28: =IF(Rent!F28=0,0,('TENANT CHARGES'!$J25)) -> 0 | G28: =IF(Rent!G28=0,0,('TENANT CHARGES'!$J25)) -> 0 | H28: =IF(Rent!H28=0,0,('TENANT CHARGES'!$J25)) -> 0 | I28: =IF(Rent!I28=0,0,('TENANT CHARGES'!$J25)) -> 0 | J28: =IF(Rent!J28=0,0,('TENANT CHARGES'!$J25)) -> 0 | K28: =IF(Rent!K28=0,0,('TENANT CHARGES'!$J25)) -> 0 | L28: =IF(Rent!L28=0,0,('TENANT CHARGES'!$J25)) -> 0 | M28: =IF(Rent!M28=0,0,('TENANT CHARGES'!$J25)) -> 0 | ... Q28: =IF(Rent!Q28=0,0,('TENANT CHARGES'!$J25)) -> 0 | R28: =SUM(F28:Q28) -> 0 | S28: =Q28/C28 -> 0
A29: =Rent!A29 -> KONA GEAR INC. | B29: =Rent!B29 -> PC 3&4 | C29: =Rent!D29 -> 962 | D29: =C29/$C$33 -> 0.018841318 | E29: =C29/$C$34 -> #REF! | F29: =IF(Rent!F29=0,0,('TENANT CHARGES'!$J26)) -> 375.76085 | G29: =IF(Rent!G29=0,0,('TENANT CHARGES'!$J26)) -> 375.76085 | H29: =IF(Rent!H29=0,0,('TENANT CHARGES'!$J26)) -> 375.76085 | I29: =IF(Rent!I29=0,0,('TENANT CHARGES'!$J26)) -> 375.76085 | J29: =IF(Rent!J29=0,0,('TENANT CHARGES'!$J26)) -> 375.76085 | K29: =IF(Rent!K29=0,0,('TENANT CHARGES'!$J26)) -> 375.76085 | L29: =IF(Rent!L29=0,0,('TENANT CHARGES'!$J26)) -> 375.76085 | M29: =IF(Rent!M29=0,0,('TENANT CHARGES'!$J26)) -> 375.76085 | ... Q29: =IF(Rent!Q29=0,0,('TENANT CHARGES'!$J26)) -> 375.76085 | R29: =SUM(F29:Q29) -> 4509.1302 | S29: =Q29/C29 -> 0.3906038
A30: =Rent!A30 -> LAVERNES | B30: =Rent!B30 -> PC/U1 | C30: =Rent!D30 -> 3704 | D30: =C30/$C$33 -> 0.072544949 | E30: =C30/$C$34 -> #REF! | F30: =IF(Rent!F30=0,0,('TENANT CHARGES'!$J27)) -> 1446.7965 | G30: =IF(Rent!G30=0,0,('TENANT CHARGES'!$J27)) -> 1446.7965 | H30: =IF(Rent!H30=0,0,('TENANT CHARGES'!$J27)) -> 1446.7965 | I30: =IF(Rent!I30=0,0,('TENANT CHARGES'!$J27)) -> 1446.7965 | J30: =IF(Rent!J30=0,0,('TENANT CHARGES'!$J27)) -> 1446.7965 | K30: =IF(Rent!K30=0,0,('TENANT CHARGES'!$J27)) -> 1446.7965 | L30: =IF(Rent!L30=0,0,('TENANT CHARGES'!$J27)) -> 1446.7965 | M30: =IF(Rent!M30=0,0,('TENANT CHARGES'!$J27)) -> 1446.7965 | ... Q30: =IF(Rent!Q30=0,0,('TENANT CHARGES'!$J27)) -> 1446.7965 | R30: =SUM(F30:Q30) -> 17361.558 | S30: =Q30/C30 -> 0.3906038
A33: TOTALS | C33: =SUM(C14:C32) -> 51058 | D33: =SUM(D14:D32) -> 0.92414509 | E33: =SUM(E14:E30) -> #REF! | F33: =SUM(F14:F31) -> 8139.0591 | G33: =SUM(G14:G31) -> 8139.0591 | H33: =SUM(H14:H31) -> 8139.0591 | I33: =SUM(I14:I31) -> 8139.0591 | J33: =SUM(J14:J31) -> 8139.0591 | K33: =SUM(K14:K31) -> 8139.0591 | L33: =SUM(L14:L31) -> 10677.984 | M33: =SUM(M14:M31) -> 10677.984 | ... Q33: =SUM(Q14:Q31) -> 14871.506 | R33: =SUM(F33:Q33) -> 129676.35
A34: Total (Less Pads and Majors) | C34: =C33-(#REF!+C14) -> #REF!
P35: TOTAL INSURANCE | R35: =Summ.!O117 -> 192487
P36: RECAPTURE | R36: =R33/R35 -> 0.67368886

Sheet RE Tax
P1: =Summ.!R1 -> Date Revised: | Q1: =Summ.!#REF! -> #REF! | R1: =Summ.!T1 -> 0
A2: =Summ.!$A2 -> ATHENA PROPERTY MANAGEMENT
A3: =Summ.!$A3 -> Coconut Grove - Kona Hawaii
A4: =Summ.!$A4 -> PROJECT NO. 165
A5: =Summ.!$A5 -> 01/01/26- 12/31/26
A6: =Summ.!$A6 -> 2026 OPERATING BUDGET
A9: TENANT | B9: SUITE | C9: SQUARE | D9: PRORATA | E9: JAN | F9: FEB | G9: MARCH | H9: APRIL | I9: MAY | J9: JUNE | K9: JULY | L9: AUGUST | M9: SEPT | N9: OCT | O9: NOV | P9: DEC | Q9: TOTALS
B10: # | C10: FOOTAGE | D10: SHARE
A12: PROPERTY TAX
A14: =Rent!A14 -> ISLAND LAVA JAVA | B14: =Rent!B14 -> A 1-4 | C14: =Rent!D14 -> 3873 | D14: =C14/C$33 -> 0.07585491 | E14: =IF(Rent!F14=0,0,('TENANT CHARGES'!$K10)) -> 1205.2207 | F14: =IF(Rent!G14=0,0,('TENANT CHARGES'!$K10)) -> 1205.2207 | G14: =IF(Rent!H14=0,0,('TENANT CHARGES'!$K10)) -> 1205.2207 | H14: =IF(Rent!I14=0,0,('TENANT CHARGES'!$K10)) -> 1205.2207 | I14: =IF(Rent!J14=0,0,('TENANT CHARGES'!$K10)) -> 1205.2207 | J14: =IF(Rent!K14=0,0,('TENANT CHARGES'!$K10)) -> 1205.2207 | K14: =IF(Rent!L14=0,0,('TENANT CHARGES'!$K10)) -> 1205.2207 | L14: =IF(Rent!M14=0,0,('TENANT CHARGES'!$K10)) -> 1205.2207 | ... P14: =IF(Rent!Q14=0,0,('TENANT CHARGES'!$K10)) -> 1205.2207 | Q14: =SUM(E14:P14) -> 14462.649 | R14: =P14/C14 -> 0.31118532
A15: =Rent!A15 -> TAKA SUSHI | B15: =Rent!B15 -> B-5 | C15: =Rent!D15 -> 1074 | D15: =C15/C$33 -> 0.021034901 | E15: =IF(Rent!F15=0,0,('TENANT CHARGES'!$K11)) -> 334.21303 | F15: =IF(Rent!G15=0,0,('TENANT CHARGES'!$K11)) -> 334.21303 | G15: =IF(Rent!H15=0,0,('TENANT CHARGES'!$K11)) -> 334.21303 | H15: =IF(Rent!I15=0,0,('TENANT CHARGES'!$K11)) -> 334.21303 | I15: =IF(Rent!J15=0,0,('TENANT CHARGES'!$K11)) -> 334.21303 | J15: =IF(Rent!K15=0,0,('TENANT CHARGES'!$K11)) -> 334.21303 | K15: =IF(Rent!L15=0,0,('TENANT CHARGES'!$K11)) -> 334.21303 | L15: =IF(Rent!M15=0,0,('TENANT CHARGES'!$K11)) -> 334.21303 | ... P15: =IF(Rent!Q15=0,0,('TENANT CHARGES'!$K11)) -> 334.21303 | Q15: =SUM(E15:P15) -> 4010.5564 | R15: =P15/C15 -> 0.31118532
A16: =Rent!A16 -> KANAKA KAVA | B16: =Rent!B16 -> B-6 | C16: =Rent!D16 -> 200 | D16: =C16/C$33 -> 0.0039171139 | E16: =IF(Rent!F16=0,0,('TENANT CHARGES'!$K12)) -> 62.237064 | F16: =IF(Rent!G16=0,0,('TENANT CHARGES'!$K12)) -> 62.237064 | G16: =IF(Rent!H16=0,0,('TENANT CHARGES'!$K12)) -> 62.237064 | H16: =IF(Rent!I16=0,0,('TENANT CHARGES'!$K12)) -> 62.237064 | I16: =IF(Rent!J16=0,0,('TENANT CHARGES'!$K12)) -> 62.237064 | J16: =IF(Rent!K16=0,0,('TENANT CHARGES'!$K12)) -> 62.237064 | K16: =IF(Rent!L16=0,0,('TENANT CHARGES'!$K12)) -> 62.237064 | L16: =IF(Rent!M16=0,0,('TENANT CHARGES'!$K12)) -> 62.237064 | ... P16: =IF(Rent!Q16=0,0,('TENANT CHARGES'!$K12)) -> 62.237064 | Q16: =SUM(E16:P16) -> 746.84476 | R16: =P16/C16 -> 0.31118532
A17: =Rent!A17 -> GECKO GIRLZ SHAVE ICE SHACK | B17: =Rent!B17 -> C-7 | C17: =Rent!D17 -> 518 | D17: =C17/C$33 -> 0.010145325 | E17: =IF(Rent!F17=0,0,('TENANT CHARGES'!$K13)) -> 161.194 | F17: =IF(Rent!G17=0,0,('TENANT CHARGES'!$K13)) -> 161.194 | G17: =IF(Rent!H17=0,0,('TENANT CHARGES'!$K13)) -> 161.194 | H17: =IF(Rent!I17=0,0,('TENANT CHARGES'!$K13)) -> 161.194 | I17: =IF(Rent!J17=0,0,('TENANT CHARGES'!$K13)) -> 161.194 | J17: =IF(Rent!K17=0,0,('TENANT CHARGES'!$K13)) -> 161.194 | K17: =IF(Rent!L17=0,0,('TENANT CHARGES'!$K13)) -> 161.194 | L17: =IF(Rent!M17=0,0,('TENANT CHARGES'!$K13)) -> 161.194 | ... P17: =IF(Rent!Q17=0,0,('TENANT CHARGES'!$K13)) -> 161.194 | Q17: =SUM(E17:P17) -> 1934.3279 | R17: =P17/C17 -> 0.31118532
A18: =Rent!A18 -> BIG ISLAND RUNNING CO. | B18: =Rent!B18 -> C-8 | C18: =Rent!D18 -> 525 | D18: =C18/C$33 -> 0.010282424 | E18: =IF(Rent!F18=0,0,('TENANT CHARGES'!$K14)) -> 163.37229 | F18: =IF(Rent!G18=0,0,('TENANT CHARGES'!$K14)) -> 163.37229 | G18: =IF(Rent!H18=0,0,('TENANT CHARGES'!$K14)) -> 163.37229 | H18: =IF(Rent!I18=0,0,('TENANT CHARGES'!$K14)) -> 163.37229 | I18: =IF(Rent!J18=0,0,('TENANT CHARGES'!$K14)) -> 163.37229 | J18: =IF(Rent!K18=0,0,('TENANT CHARGES'!$K14)) -> 163.37229 | K18: =IF(Rent!L18=0,0,('TENANT CHARGES'!$K14)) -> 163.37229 | L18: =IF(Rent!M18=0,0,('TENANT CHARGES'!$K14)) -> 163.37229 | ... P18: =IF(Rent!Q18=0,0,('TENANT CHARGES'!$K14)) -> 163.37229 | Q18: =SUM(E18:P18) -> 1960.4675 | R18: =P18/C18 -> 0.31118532
A19: =Rent!A19 -> CAFE KONA | B19: =Rent!B19 -> D11-12 | C19: =Rent!D19 -> 994 | D19: =C19/C$33 -> 0.019468056 | E19: =IF(Rent!F19=0,0,('TENANT CHARGES'!$K15)) -> 309.31821 | F19: =IF(Rent!G19=0,0,('TENANT CHARGES'!$K15)) -> 309.31821 | G19: =IF(Rent!H19=0,0,('TENANT CHARGES'!$K15)) -> 309.31821 | H19: =IF(Rent!I19=0,0,('TENANT CHARGES'!$K15)) -> 309.31821 | I19: =IF(Rent!J19=0,0,('TENANT CHARGES'!$K15)) -> 309.31821 | J19: =IF(Rent!K19=0,0,('TENANT CHARGES'!$K15)) -> 309.31821 | K19: =IF(Rent!L19=0,0,('TENANT CHARGES'!$K15)) -> 309.31821 | L19: =IF(Rent!M19=0,0,('TENANT CHARGES'!$K15)) -> 309.31821 | ... P19: =IF(Rent!Q19=0,0,('TENANT CHARGES'!$K15)) -> 309.31821 | Q19: =SUM(E19:P19) -> 3711.8185 | R19: =P19/C19 -> 0.31118532
A20: =Rent!A20 -> LUCASIE LTD | B20: =Rent!B20 -> D9-D10 | C20: =Rent!D20 -> 1043 | D20: =C20/C$33 -> 0.020427749 | E20: =IF(Rent!F20=0,0,('TENANT CHARGES'!$K17)) -> 324.56629 | F20: =IF(Rent!G20=0,0,('TENANT CHARGES'!$K17)) -> 324.56629 | G20: =IF(Rent!H20=0,0,('TENANT CHARGES'!$K17)) -> 324.56629 | H20: =IF(Rent!I20=0,0,('TENANT CHARGES'!$K17)) -> 324.56629 | I20: =IF(Rent!J20=0,0,('TENANT CHARGES'!$K17)) -> 324.56629 | J20: =IF(Rent!K20=0,0,('TENANT CHARGES'!$K17)) -> 324.56629 | K20: =IF(Rent!L20=0,0,('TENANT CHARGES'!$K17)) -> 324.56629 | L20: =IF(Rent!M20=0,0,('TENANT CHARGES'!$K17)) -> 324.56629 | ... P20: =IF(Rent!Q20=0,0,('TENANT CHARGES'!$K17)) -> 324.56629 | Q20: =SUM(E20:P20) -> 3894.7954 | R20: =P20/C20 -> 0.31118532
A21: =Rent!A21 -> FOSTERS KITCHEN | B21: =Rent!B21 -> DU-1 | C21: =Rent!D21 -> 3526 | D21: =C21/C$33 -> 0.069058718 | E21: =IF(Rent!F21=0,0,('TENANT CHARGES'!$K18)) -> 1097.2394 | F21: =IF(Rent!G21=0,0,('TENANT CHARGES'!$K18)) -> 1097.2394 | G21: =IF(Rent!H21=0,0,('TENANT CHARGES'!$K18)) -> 1097.2394 | H21: =IF(Rent!I21=0,0,('TENANT CHARGES'!$K18)) -> 1097.2394 | I21: =IF(Rent!J21=0,0,('TENANT CHARGES'!$K18)) -> 1097.2394 | J21: =IF(Rent!K21=0,0,('TENANT CHARGES'!$K18)) -> 1097.2394 | K21: =IF(Rent!L21=0,0,('TENANT CHARGES'!$K18)) -> 1097.2394 | L21: =IF(Rent!M21=0,0,('TENANT CHARGES'!$K18)) -> 1097.2394 | ... P21: =IF(Rent!Q21=0,0,('TENANT CHARGES'!$K18)) -> 1097.2394 | Q21: =SUM(E21:P21) -> 13166.873 | R21: =P21/C21 -> 0.31118532
A22: =Rent!A22 -> HUMPYS BIG ISLAND ALEHOUSE | B22: =Rent!B22 -> E | C22: =Rent!D22 -> 10736 | D22: =C22/C$33 -> 0.21027067 | E22: 0 | F22: 0 | G22: 0 | H22: 0 | I22: 0 | J22: 0 | K22: 0 | L22: 0 | M22: =IF(Rent!N22=0,0,('TENANT CHARGES'!$K19)) -> 3340.8856 | N22: =IF(Rent!O22=0,0,('TENANT CHARGES'!$K19)) -> 3340.8856 | O22: =IF(Rent!P22=0,0,('TENANT CHARGES'!$K19)) -> 3340.8856 | P22: =IF(Rent!Q22=0,0,('TENANT CHARGES'!$K19)) -> 3340.8856 | Q22: =SUM(E22:P22) -> 13363.542 | R22: =P22/C22 -> 0.31118532 | S22: NEW AMENDMENT SIGNED; ASSUME $25K/MO; full rents will resume 9/1/26
A23: =Rent!A23 -> ABC STORE #75 | B23: =Rent!B23 -> F15,17&A8 | C23: =Rent!D23 -> 4000 | D23: =C23/C$33 -> 0.078342277 | E23: =IF(Rent!F23=0,0,('TENANT CHARGES'!$K20)) -> 933.55596 | F23: =IF(Rent!G23=0,0,('TENANT CHARGES'!$K20)) -> 933.55596 | G23: =IF(Rent!H23=0,0,('TENANT CHARGES'!$K20)) -> 933.55596 | H23: =IF(Rent!I23=0,0,('TENANT CHARGES'!$K20)) -> 933.55596 | I23: =IF(Rent!J23=0,0,('TENANT CHARGES'!$K20)) -> 933.55596 | J23: =IF(Rent!K23=0,0,('TENANT CHARGES'!$K20)) -> 933.55596 | K23: =IF(Rent!L23=0,0,('TENANT CHARGES'!$K20)) -> 933.55596 | L23: =IF(Rent!M23=0,0,('TENANT CHARGES'!$K20)) -> 933.55596 | ... P23: =IF(Rent!Q23=0,0,('TENANT CHARGES'!$K20)) -> 933.55596 | Q23: =SUM(E23:P23) -> 11202.671 | R23: =P23/C23 -> 0.23338899
A24: =Rent!A24 -> GYPSEA GALATO | B24: =Rent!B24 -> F-16 | C24: =Rent!D24 -> 500 | D24: =C24/C$33 -> 0.0097927847 | E24: =IF(Rent!F24=0,0,('TENANT CHARGES'!$K21)) -> 155.59266 | F24: =IF(Rent!G24=0,0,('TENANT CHARGES'!$K21)) -> 155.59266 | G24: =IF(Rent!H24=0,0,('TENANT CHARGES'!$K21)) -> 155.59266 | H24: =IF(Rent!I24=0,0,('TENANT CHARGES'!$K21)) -> 155.59266 | I24: =IF(Rent!J24=0,0,('TENANT CHARGES'!$K21)) -> 155.59266 | J24: =IF(Rent!K24=0,0,('TENANT CHARGES'!$K21)) -> 155.59266 | K24: =IF(Rent!L24=0,0,('TENANT CHARGES'!$K21)) -> 155.59266 | L24: =IF(Rent!M24=0,0,('TENANT CHARGES'!$K21)) -> 155.59266 | ... P24: =IF(Rent!Q24=0,0,('TENANT CHARGES'!$K21)) -> 155.59266 | Q24: =SUM(E24:P24) -> 1867.1119 | R24: =P24/C24 -> 0.31118532
A25: =Rent!A25 -> OCEANS SPORTS BAR AND GRILL | B25: =Rent!B25 -> G | C25: =Rent!D25 -> 2896 | D25: =C25/C$33 -> 0.056719809 | E25: =IF(Rent!F25=0,0,('TENANT CHARGES'!$K22)) -> 901.19268 | F25: =IF(Rent!G25=0,0,('TENANT CHARGES'!$K22)) -> 901.19268 | G25: =IF(Rent!H25=0,0,('TENANT CHARGES'!$K22)) -> 901.19268 | H25: =IF(Rent!I25=0,0,('TENANT CHARGES'!$K22)) -> 901.19268 | I25: =IF(Rent!J25=0,0,('TENANT CHARGES'!$K22)) -> 901.19268 | J25: =IF(Rent!K25=0,0,('TENANT CHARGES'!$K22)) -> 901.19268 | K25: =IF(Rent!L25=0,0,('TENANT CHARGES'!$K22)) -> 901.19268 | L25: =IF(Rent!M25=0,0,('TENANT CHARGES'!$K22)) -> 901.19268 | ... P25: =IF(Rent!Q25=0,0,('TENANT CHARGES'!$K22)) -> 901.19268 | Q25: =SUM(E25:P25) -> 10814.312 | R25: =P25/C25 -> 0.31118532
A26: =Rent!A26 -> JACKS DIVE LOCKER | B26: =Rent!B26 -> H | C26: =Rent!D26 -> 8014 | D26: =C26/C$33 -> 0.15695875 | E26: =IF(Rent!F26=0,0,('TENANT CHARGES'!$K23)) -> 2493.8391 | F26: =IF(Rent!G26=0,0,('TENANT CHARGES'!$K23)) -> 2493.8391 | G26: =IF(Rent!H26=0,0,('TENANT CHARGES'!$K23)) -> 2493.8391 | H26: =IF(Rent!I26=0,0,('TENANT CHARGES'!$K23)) -> 2493.8391 | I26: =IF(Rent!J26=0,0,('TENANT CHARGES'!$K23)) -> 2493.8391 | J26: =IF(Rent!K26=0,0,('TENANT CHARGES'!$K23)) -> 2493.8391 | K26: =IF(Rent!L26=0,0,('TENANT CHARGES'!$K23)) -> 2493.8391 | L26: =IF(Rent!M26=0,0,('TENANT CHARGES'!$K23)) -> 2493.8391 | ... P26: =IF(Rent!Q26=0,0,('TENANT CHARGES'!$K23)) -> 2493.8391 | Q26: =SUM(E26:P26) -> 29926.07 | R26: =P26/C26 -> 0.31118532
A27: =Rent!A27 -> QPOT | B27: =Rent!B27 -> I | C27: =Rent!D27 -> 6500 | D27: =C27/C$33 -> 0.1273062 | E27: =IF(Rent!F27=0,0,('TENANT CHARGES'!$K24)) -> 0 | F27: =IF(Rent!G27=0,0,('TENANT CHARGES'!$K24)) -> 0 | G27: =IF(Rent!H27=0,0,('TENANT CHARGES'!$K24)) -> 0 | H27: =IF(Rent!I27=0,0,('TENANT CHARGES'!$K24)) -> 0 | I27: =IF(Rent!J27=0,0,('TENANT CHARGES'!$K24)) -> 0 | J27: =IF(Rent!K27=0,0,('TENANT CHARGES'!$K24)) -> 0 | K27: =IF(Rent!L27=0,0,('TENANT CHARGES'!$K24)) -> 2022.7046 | L27: =IF(Rent!M27=0,0,('TENANT CHARGES'!$K24)) -> 2022.7046 | ... P27: =IF(Rent!Q27=0,0,('TENANT CHARGES'!$K24)) -> 2022.7046 | Q27: =SUM(E27:P27) -> 12136.227 | R27: =P27/C27 -> 0.31118532
A28: =Rent!A28 -> BOWLS SUPERFOODS & ORALE TACOS | B28: =Rent!B28 -> PC-1&2 | C28: =Rent!D28 -> 1993 | D28: =C28/C$33 -> 0.03903404 | E28: =IF(Rent!F28=0,0,('TENANT CHARGES'!$K25)) -> 0 | F28: =IF(Rent!G28=0,0,('TENANT CHARGES'!$K25)) -> 0 | G28: =IF(Rent!H28=0,0,('TENANT CHARGES'!$K25)) -> 0 | H28: =IF(Rent!I28=0,0,('TENANT CHARGES'!$K25)) -> 0 | I28: =IF(Rent!J28=0,0,('TENANT CHARGES'!$K25)) -> 0 | J28: =IF(Rent!K28=0,0,('TENANT CHARGES'!$K25)) -> 0 | K28: =IF(Rent!L28=0,0,('TENANT CHARGES'!$K25)) -> 0 | L28: =IF(Rent!M28=0,0,('TENANT CHARGES'!$K25)) -> 0 | ... P28: =IF(Rent!Q28=0,0,('TENANT CHARGES'!$K25)) -> 0 | Q28: =SUM(E28:P28) -> 0 | R28: =P28/C28 -> 0
A29: =Rent!A29 -> KONA GEAR INC. | B29: =Rent!B29 -> PC 3&4 | C29: =Rent!D29 -> 962 | D29: =C29/C$33 -> 0.018841318 | E29: =IF(Rent!F29=0,0,('TENANT CHARGES'!$K26)) -> 299.36028 | F29: =IF(Rent!G29=0,0,('TENANT CHARGES'!$K26)) -> 299.36028 | G29: =IF(Rent!H29=0,0,('TENANT CHARGES'!$K26)) -> 299.36028 | H29: =IF(Rent!I29=0,0,('TENANT CHARGES'!$K26)) -> 299.36028 | I29: =IF(Rent!J29=0,0,('TENANT CHARGES'!$K26)) -> 299.36028 | J29: =IF(Rent!K29=0,0,('TENANT CHARGES'!$K26)) -> 299.36028 | K29: =IF(Rent!L29=0,0,('TENANT CHARGES'!$K26)) -> 299.36028 | L29: =IF(Rent!M29=0,0,('TENANT CHARGES'!$K26)) -> 299.36028 | ... P29: =IF(Rent!Q29=0,0,('TENANT CHARGES'!$K26)) -> 299.36028 | Q29: =SUM(E29:P29) -> 3592.3233 | R29: =P29/C29 -> 0.31118532
A30: =Rent!A30 -> LAVERNES | B30: =Rent!B30 -> PC/U1 | C30: =Rent!D30 -> 3704 | D30: =C30/C$33 -> 0.072544949 | E30: =IF(Rent!F30=0,0,('TENANT CHARGES'!$K27)) -> 1152.6304 | F30: =IF(Rent!G30=0,0,('TENANT CHARGES'!$K27)) -> 1152.6304 | G30: =IF(Rent!H30=0,0,('TENANT CHARGES'!$K27)) -> 1152.6304 | H30: =IF(Rent!I30=0,0,('TENANT CHARGES'!$K27)) -> 1152.6304 | I30: =IF(Rent!J30=0,0,('TENANT CHARGES'!$K27)) -> 1152.6304 | J30: =IF(Rent!K30=0,0,('TENANT CHARGES'!$K27)) -> 1152.6304 | K30: =IF(Rent!L30=0,0,('TENANT CHARGES'!$K27)) -> 1152.6304 | L30: =IF(Rent!M30=0,0,('TENANT CHARGES'!$K27)) -> 1152.6304 | ... P30: =IF(Rent!Q30=0,0,('TENANT CHARGES'!$K27)) -> 1152.6304 | Q30: =SUM(E30:P30) -> 13831.565 | R30: =P30/C30 -> 0.31118532
A33: TOTALS | C33: =SUM(C14:C32) -> 51058 | D33: =SUM(D14:D32) -> 1 | E33: =SUM(E14:E31) -> 9593.5322 | F33: =SUM(F14:F31) -> 9593.5322 | G33: =SUM(G14:G31) -> 9593.5322 | H33: =SUM(H14:H31) -> 9593.5322 | I33: =SUM(I14:I31) -> 9593.5322 | J33: =SUM(J14:J31) -> 9593.5322 | K33: =SUM(K14:K31) -> 11616.237 | L33: =SUM(L14:L31) -> 11616.237 | ... P33: =SUM(P14:P31) -> 14957.122 | Q33: =SUM(E33:P33) -> 140622.16
O35: TOTAL PROP TAX | Q35: =Summ.!O122 -> 190662
O36: RECAPTURE | Q36: =Q33/Q35 -> 0.73754684

Sheet Excise Tax
P1: =Summ.!R1 -> Date Revised: | Q1: =Summ.!#REF! -> #REF! | R1: =Summ.!T1 -> 0
A2: =Summ.!$A2 -> ATHENA PROPERTY MANAGEMENT
A3: =Summ.!$A3 -> Coconut Grove - Kona Hawaii
A4: =Summ.!$A4 -> PROJECT NO. 165
A5: =Summ.!$A5 -> 01/01/26- 12/31/26
A6: =Summ.!$A6 -> 2026 OPERATING BUDGET
A9: TENANT | B9: SUITE | C9: SQUARE | D9: RATE | E9: JAN | F9: FEB | G9: MARCH | H9: APRIL | I9: MAY | J9: JUNE | K9: JULY | L9: AUGUST | M9: SEPT | N9: OCT | O9: NOV | P9: DEC | Q9: TOTALS
B10: # | C10: FOOTAGE
A12: EXCISE TAX (4.712%)
A14: =Rent!A14 -> ISLAND LAVA JAVA | B14: =Rent!B14 -> A 1-4 | C14: =Rent!D14 -> 3873 | D14: 0.04712 | E14: =IF(Rent!F14=0,0,('TENANT CHARGES'!$S10)) -> 1301.4422 | F14: =IF(Rent!G14=0,0,('TENANT CHARGES'!$S10)) -> 1301.4422 | G14: =IF(Rent!H14=0,0,('TENANT CHARGES'!$S10)) -> 1301.4422 | H14: =IF(Rent!I14=0,0,('TENANT CHARGES'!$S10)) -> 1301.4422 | I14: =IF(Rent!J14=0,0,('TENANT CHARGES'!$S10)) -> 1301.4422 | J14: =IF(Rent!K14=0,0,('TENANT CHARGES'!$S10)) -> 1301.4422 | K14: =IF(Rent!L14=0,0,('TENANT CHARGES'!$S10)) -> 1301.4422 | L14: =IF(Rent!M14=0,0,('TENANT CHARGES'!$S10)) -> 1301.4422 | ... P14: =IF(Rent!Q14=0,0,('TENANT CHARGES'!$S10)) -> 1301.4422 | Q14: =SUM(E14:P14) -> 15617.306
A15: =Rent!A15 -> TAKA SUSHI | B15: =Rent!B15 -> B-5 | C15: =Rent!D15 -> 1074 | D15: 0.04712 | E15: =IF(Rent!F15=0,0,('TENANT CHARGES'!$S11)) -> 307.27576 | F15: =IF(Rent!G15=0,0,('TENANT CHARGES'!$S11)) -> 307.27576 | G15: =IF(Rent!H15=0,0,('TENANT CHARGES'!$S11)) -> 307.27576 | H15: =IF(Rent!I15=0,0,('TENANT CHARGES'!$S11)) -> 307.27576 | I15: =IF(Rent!J15=0,0,('TENANT CHARGES'!$S11)) -> 307.27576 | J15: =IF(Rent!K15=0,0,('TENANT CHARGES'!$S11)) -> 307.27576 | K15: =IF(Rent!L15=0,0,('TENANT CHARGES'!$S11)) -> 307.27576 | L15: =IF(Rent!M15=0,0,('TENANT CHARGES'!$S11)) -> 307.27576 | ... P15: =IF(Rent!Q15=0,0,('TENANT CHARGES'!$S11)) -> 307.27576 | Q15: =SUM(E15:P15) -> 3687.3091
A16: =Rent!A16 -> KANAKA KAVA | B16: =Rent!B16 -> B-6 | C16: =Rent!D16 -> 200 | D16: 0.04712 | E16: =IF(Rent!F16=0,0,('TENANT CHARGES'!$S12)) -> 134.96881 | F16: =IF(Rent!G16=0,0,('TENANT CHARGES'!$S12)) -> 134.96881 | G16: =IF(Rent!H16=0,0,('TENANT CHARGES'!$S12)) -> 134.96881 | H16: =IF(Rent!I16=0,0,('TENANT CHARGES'!$S12)) -> 134.96881 | I16: =IF(Rent!J16=0,0,('TENANT CHARGES'!$S12)) -> 134.96881 | J16: =IF(Rent!K16=0,0,('TENANT CHARGES'!$S12)) -> 134.96881 | K16: =IF(Rent!L16=0,0,('TENANT CHARGES'!$S12)) -> 134.96881 | L16: =IF(Rent!M16=0,0,('TENANT CHARGES'!$S12)) -> 134.96881 | ... P16: =IF(Rent!Q16=0,0,('TENANT CHARGES'!$S12)) -> 134.96881 | Q16: =SUM(E16:P16) -> 1619.6257
A17: =Rent!A17 -> GECKO GIRLZ SHAVE ICE SHACK | B17: =Rent!B17 -> C-7 | C17: =Rent!D17 -> 518 | D17: 0.04712 | E17: =IF(Rent!F17=0,0,('TENANT CHARGES'!$S13)) -> 190.42802 | F17: =IF(Rent!G17=0,0,('TENANT CHARGES'!$S13)) -> 190.42802 | G17: =IF(Rent!H17=0,0,('TENANT CHARGES'!$S13)) -> 190.42802 | H17: =IF(Rent!I17=0,0,('TENANT CHARGES'!$S13)) -> 190.42802 | I17: =IF(Rent!J17=0,0,('TENANT CHARGES'!$S13)) -> 190.42802 | J17: =IF(Rent!K17=0,0,('TENANT CHARGES'!$S13)) -> 190.42802 | K17: =IF(Rent!L17=0,0,('TENANT CHARGES'!$S13)) -> 190.42802 | L17: =IF(Rent!M17=0,0,('TENANT CHARGES'!$S13)) -> 190.42802 | ... P17: =IF(Rent!Q17=0,0,('TENANT CHARGES'!$S13)) -> 190.42802 | Q17: =SUM(E17:P17) -> 2285.1362
A18: =Rent!A18 -> BIG ISLAND RUNNING CO. | B18: =Rent!B18 -> C-8 | C18: =Rent!D18 -> 525 | D18: 0.04712 | E18: =IF(Rent!F18=0,0,('TENANT CHARGES'!$S14)) -> 197.44269 | F18: =IF(Rent!G18=0,0,('TENANT CHARGES'!$S14)) -> 197.44269 | G18: =IF(Rent!H18=0,0,('TENANT CHARGES'!$S14)) -> 197.44269 | H18: =IF(Rent!I18=0,0,('TENANT CHARGES'!$S14)) -> 197.44269 | I18: =IF(Rent!J18=0,0,('TENANT CHARGES'!$S14)) -> 197.44269 | J18: =IF(Rent!K18=0,0,('TENANT CHARGES'!$S14)) -> 197.44269 | K18: =IF(Rent!L18=0,0,('TENANT CHARGES'!$S14)) -> 197.44269 | L18: =IF(Rent!M18=0,0,('TENANT CHARGES'!$S14)) -> 197.44269 | ... P18: =IF(Rent!Q18=0,0,('TENANT CHARGES'!$S14)) -> 197.44269 | Q18: =SUM(E18:P18) -> 2369.3123
A19: =Rent!A19 -> CAFE KONA | B19: =Rent!B19 -> D11-12 | C19: =Rent!D19 -> 994 | D19: 0.04712 | E19: =IF(Rent!F19=0,0,('TENANT CHARGES'!$S15)) -> 317.17353 | F19: =IF(Rent!G19=0,0,('TENANT CHARGES'!$S15)) -> 317.17353 | G19: =IF(Rent!H19=0,0,('TENANT CHARGES'!$S15)) -> 317.17353 | H19: =IF(Rent!I19=0,0,('TENANT CHARGES'!$S15)) -> 317.17353 | I19: =IF(Rent!J19=0,0,('TENANT CHARGES'!$S15)) -> 317.17353 | J19: =IF(Rent!K19=0,0,('TENANT CHARGES'!$S15)) -> 317.17353 | K19: =IF(Rent!L19=0,0,('TENANT CHARGES'!$S15)) -> 317.17353 | L19: =IF(Rent!M19=0,0,('TENANT CHARGES'!$S15)) -> 317.17353 | ... P19: =IF(Rent!Q19=0,0,('TENANT CHARGES'!$S15)) -> 317.17353 | Q19: =SUM(E19:P19) -> 3806.0824
A20: =Rent!A20 -> LUCASIE LTD | B20: =Rent!B20 -> D9-D10 | C20: =Rent!D20 -> 1043 | D20: 0.04712 | E20: =IF(Rent!F20=0,0,('TENANT CHARGES'!$S17)) -> 481.33187 | F20: =IF(Rent!G20=0,0,('TENANT CHARGES'!$S17)) -> 481.33187 | G20: =IF(Rent!H20=0,0,('TENANT CHARGES'!$S17)) -> 481.33187 | H20: =IF(Rent!I20=0,0,('TENANT CHARGES'!$S17)) -> 481.33187 | I20: =IF(Rent!J20=0,0,('TENANT CHARGES'!$S17)) -> 481.33187 | J20: =IF(Rent!K20=0,0,('TENANT CHARGES'!$S17)) -> 481.33187 | K20: =IF(Rent!L20=0,0,('TENANT CHARGES'!$S17)) -> 481.33187 | L20: =IF(Rent!M20=0,0,('TENANT CHARGES'!$S17)) -> 481.33187 | ... P20: =IF(Rent!Q20=0,0,('TENANT CHARGES'!$S17)) -> 481.33187 | Q20: =SUM(E20:P20) -> 5775.9824
A21: =Rent!A21 -> FOSTERS KITCHEN | B21: =Rent!B21 -> DU-1 | C21: =Rent!D21 -> 3526 | D21: 0.04712 | E21: =IF(Rent!F21=0,0,('TENANT CHARGES'!$S18)) -> 1069.9998 | F21: =IF(Rent!G21=0,0,('TENANT CHARGES'!$S18)) -> 1069.9998 | G21: =IF(Rent!H21=0,0,('TENANT CHARGES'!$S18)) -> 1069.9998 | H21: =IF(Rent!I21=0,0,('TENANT CHARGES'!$S18)) -> 1069.9998 | I21: =IF(Rent!J21=0,0,('TENANT CHARGES'!$S18)) -> 1069.9998 | J21: =IF(Rent!K21=0,0,('TENANT CHARGES'!$S18)) -> 1069.9998 | K21: =IF(Rent!L21=0,0,('TENANT CHARGES'!$S18)) -> 1069.9998 | L21: =IF(Rent!M21=0,0,('TENANT CHARGES'!$S18)) -> 1069.9998 | ... P21: =IF(Rent!Q21=0,0,('TENANT CHARGES'!$S18)) -> 1069.9998 | Q21: =SUM(E21:P21) -> 12839.997
A22: =Rent!A22 -> HUMPYS BIG ISLAND ALEHOUSE | B22: =Rent!B22 -> E | C22: =Rent!D22 -> 10736 | D22: 0.04712 | E22: =IF(Rent!F22=0,0,('TENANT CHARGES'!$S19)) -> 2656.0923 | F22: =IF(Rent!G22=0,0,('TENANT CHARGES'!$S19)) -> 2656.0923 | G22: =IF(Rent!H22=0,0,('TENANT CHARGES'!$S19)) -> 2656.0923 | H22: =IF(Rent!I22=0,0,('TENANT CHARGES'!$S19)) -> 2656.0923 | I22: =IF(Rent!J22=0,0,('TENANT CHARGES'!$S19)) -> 2656.0923 | J22: =IF(Rent!K22=0,0,('TENANT CHARGES'!$S19)) -> 2656.0923 | K22: =IF(Rent!L22=0,0,('TENANT CHARGES'!$S19)) -> 2656.0923 | L22: =IF(Rent!M22=0,0,('TENANT CHARGES'!$S19)) -> 2656.0923 | ... P22: =IF(Rent!Q22=0,0,('TENANT CHARGES'!$S19)) -> 2656.0923 | Q22: =SUM(E22:P22) -> 31873.107 | R22: NEW AMENDMENT SIGNED; ASSUME $25K/MO; full rents will resume 9/1/27
A23: =Rent!A23 -> ABC STORE #75 | B23: =Rent!B23 -> F15,17&A8 | C23: =Rent!D23 -> 4000 | D23: 0.04712 | E23: =IF(Rent!F23=0,0,('TENANT CHARGES'!$S20)) -> 1509.8034 | F23: =IF(Rent!G23=0,0,('TENANT CHARGES'!$S20)) -> 1509.8034 | G23: =IF(Rent!H23=0,0,('TENANT CHARGES'!$S20)) -> 1509.8034 | H23: =IF(Rent!I23=0,0,('TENANT CHARGES'!$S20)) -> 1509.8034 | I23: =IF(Rent!J23=0,0,('TENANT CHARGES'!$S20)) -> 1509.8034 | J23: =IF(Rent!K23=0,0,('TENANT CHARGES'!$S20)) -> 1509.8034 | K23: =IF(Rent!L23=0,0,('TENANT CHARGES'!$S20)) -> 1509.8034 | L23: =IF(Rent!M23=0,0,('TENANT CHARGES'!$S20)) -> 1509.8034 | ... P23: =IF(Rent!Q23=0,0,('TENANT CHARGES'!$S20)) -> 1509.8034 | Q23: =SUM(E23:P23) -> 18117.641
A24: =Rent!A24 -> GYPSEA GALATO | B24: =Rent!B24 -> F-16 | C24: =Rent!D24 -> 500 | D24: 0.04712 | E24: =IF(Rent!F24=0,0,('TENANT CHARGES'!$S21)) -> 197.56149 | F24: =IF(Rent!G24=0,0,('TENANT CHARGES'!$S21)) -> 197.56149 | G24: =IF(Rent!H24=0,0,('TENANT CHARGES'!$S21)) -> 197.56149 | H24: =IF(Rent!I24=0,0,('TENANT CHARGES'!$S21)) -> 197.56149 | I24: =IF(Rent!J24=0,0,('TENANT CHARGES'!$S21)) -> 197.56149 | J24: =IF(Rent!K24=0,0,('TENANT CHARGES'!$S21)) -> 197.56149 | K24: =IF(Rent!L24=0,0,('TENANT CHARGES'!$S21)) -> 197.56149 | L24: =IF(Rent!M24=0,0,('TENANT CHARGES'!$S21)) -> 197.56149 | ... P24: =IF(Rent!Q24=0,0,('TENANT CHARGES'!$S21)) -> 197.56149 | Q24: =SUM(E24:P24) -> 2370.7378
A25: =Rent!A25 -> OCEANS SPORTS BAR AND GRILL | B25: =Rent!B25 -> G | C25: =Rent!D25 -> 2896 | D25: 0.04712 | E25: =IF(Rent!F25=0,0,('TENANT CHARGES'!$S22)) -> 751.8187 | F25: =IF(Rent!G25=0,0,('TENANT CHARGES'!$S22)) -> 751.8187 | G25: =IF(Rent!H25=0,0,('TENANT CHARGES'!$S22)) -> 751.8187 | H25: =IF(Rent!I25=0,0,('TENANT CHARGES'!$S22)) -> 751.8187 | I25: =IF(Rent!J25=0,0,('TENANT CHARGES'!$S22)) -> 751.8187 | J25: =IF(Rent!K25=0,0,('TENANT CHARGES'!$S22)) -> 751.8187 | K25: =IF(Rent!L25=0,0,('TENANT CHARGES'!$S22)) -> 751.8187 | L25: =IF(Rent!M25=0,0,('TENANT CHARGES'!$S22)) -> 751.8187 | ... P25: =IF(Rent!Q25=0,0,('TENANT CHARGES'!$S22)) -> 751.8187 | Q25: =SUM(E25:P25) -> 9021.8244
A26: =Rent!A26 -> JACKS DIVE LOCKER | B26: =Rent!B26 -> H | C26: =Rent!D26 -> 8014 | D26: 0.04712 | E26: =IF(Rent!F26=0,0,('TENANT CHARGES'!$S23)) -> 1604.7953 | F26: =IF(Rent!G26=0,0,('TENANT CHARGES'!$S23)) -> 1604.7953 | G26: =IF(Rent!H26=0,0,('TENANT CHARGES'!$S23)) -> 1604.7953 | H26: =IF(Rent!I26=0,0,('TENANT CHARGES'!$S23)) -> 1604.7953 | I26: =IF(Rent!J26=0,0,('TENANT CHARGES'!$S23)) -> 1604.7953 | J26: =IF(Rent!K26=0,0,('TENANT CHARGES'!$S23)) -> 1604.7953 | K26: =IF(Rent!L26=0,0,('TENANT CHARGES'!$S23)) -> 1604.7953 | L26: =IF(Rent!M26=0,0,('TENANT CHARGES'!$S23)) -> 1604.7953 | ... P26: =IF(Rent!Q26=0,0,('TENANT CHARGES'!$S23)) -> 1604.7953 | Q26: =SUM(E26:P26) -> 19257.543
A27: =Rent!A27 -> QPOT | B27: =Rent!B27 -> I | C27: =Rent!D27 -> 6500 | D27: 0.04712 | E27: =IF(Rent!F27=0,0,('TENANT CHARGES'!$S24)) -> 0 | F27: =IF(Rent!G27=0,0,('TENANT CHARGES'!$S24)) -> 0 | G27: =IF(Rent!H27=0,0,('TENANT CHARGES'!$S24)) -> 0 | H27: =IF(Rent!I27=0,0,('TENANT CHARGES'!$S24)) -> 0 | I27: =IF(Rent!J27=0,0,('TENANT CHARGES'!$S24)) -> 0 | J27: =IF(Rent!K27=0,0,('TENANT CHARGES'!$S24)) -> 0 | K27: =IF(Rent!L27=0,0,('TENANT CHARGES'!$S24)) -> 660.25844 | L27: =IF(Rent!M27=0,0,('TENANT CHARGES'!$S24)) -> 660.25844 | ... P27: =IF(Rent!Q27=0,0,('TENANT CHARGES'!$S24)) -> 660.25844 | Q27: =SUM(E27:P27) -> 3961.5506
A28: =Rent!A28 -> BOWLS SUPERFOODS & ORALE TACOS | B28: =Rent!B28 -> PC-1&2 | C28: =Rent!D28 -> 1993 | D28: 0.04712 | E28: =IF(Rent!F28=0,0,('TENANT CHARGES'!$S25)) -> 0 | F28: =IF(Rent!G28=0,0,('TENANT CHARGES'!$S25)) -> 0 | G28: =IF(Rent!H28=0,0,('TENANT CHARGES'!$S25)) -> 0 | H28: =IF(Rent!I28=0,0,('TENANT CHARGES'!$S25)) -> 0 | I28: =IF(Rent!J28=0,0,('TENANT CHARGES'!$S25)) -> 0 | J28: =IF(Rent!K28=0,0,('TENANT CHARGES'!$S25)) -> 0 | K28: =IF(Rent!L28=0,0,('TENANT CHARGES'!$S25)) -> 0 | L28: =IF(Rent!M28=0,0,('TENANT CHARGES'!$S25)) -> 0 | ... P28: =IF(Rent!Q28=0,0,('TENANT CHARGES'!$S25)) -> 0 | Q28: =SUM(E28:P28) -> 0
A29: =Rent!A29 -> KONA GEAR INC. | B29: =Rent!B29 -> PC 3&4 | C29: =Rent!D29 -> 962 | D29: 0.04712 | E29: =IF(Rent!F29=0,0,('TENANT CHARGES'!$S26)) -> 409.9538 | F29: =IF(Rent!G29=0,0,('TENANT CHARGES'!$S26)) -> 409.9538 | G29: =IF(Rent!H29=0,0,('TENANT CHARGES'!$S26)) -> 409.9538 | H29: =IF(Rent!I29=0,0,('TENANT CHARGES'!$S26)) -> 409.9538 | I29: =IF(Rent!J29=0,0,('TENANT CHARGES'!$S26)) -> 409.9538 | J29: =IF(Rent!K29=0,0,('TENANT CHARGES'!$S26)) -> 409.9538 | K29: =IF(Rent!L29=0,0,('TENANT CHARGES'!$S26)) -> 409.9538 | L29: =IF(Rent!M29=0,0,('TENANT CHARGES'!$S26)) -> 409.9538 | ... P29: =IF(Rent!Q29=0,0,('TENANT CHARGES'!$S26)) -> 409.9538 | Q29: =SUM(E29:P29) -> 4919.4456
A30: =Rent!A30 -> LAVERNES | B30: =Rent!B30 -> PC/U1 | C30: =Rent!D30 -> 3704 | D30: 0.04712 | E30: =IF(Rent!F30=0,0,('TENANT CHARGES'!$S27)) -> 830.21743 | F30: =IF(Rent!G30=0,0,('TENANT CHARGES'!$S27)) -> 830.21743 | G30: =IF(Rent!H30=0,0,('TENANT CHARGES'!$S27)) -> 830.21743 | H30: =IF(Rent!I30=0,0,('TENANT CHARGES'!$S27)) -> 830.21743 | I30: =IF(Rent!J30=0,0,('TENANT CHARGES'!$S27)) -> 830.21743 | J30: =IF(Rent!K30=0,0,('TENANT CHARGES'!$S27)) -> 830.21743 | K30: =IF(Rent!L30=0,0,('TENANT CHARGES'!$S27)) -> 830.21743 | L30: =IF(Rent!M30=0,0,('TENANT CHARGES'!$S27)) -> 830.21743 | ... P30: =IF(Rent!Q30=0,0,('TENANT CHARGES'!$S27)) -> 830.21743 | Q30: =SUM(E30:P30) -> 9962.6092
