Workbook

Sheet Title Sheet
B6: Roosevelt Commons
B9: July 2026
B12: Monthly Report
B24: Prepared By:
B26: Athena Property Management

Sheet Executive Summary
A2: Executive Summary
A3: Roosevelt Commons
A4: July 2026
A7: Property Manager: | B7: Danielle Cebrero | G7: Square Feet: | H7: 54885
A8: Assistant Property Manager | B8: Jaie Benson | G8: % Leased: | H8: 1
A9: Cash
B11: Monthly Actual | C11: Monthly Budget | D11: Variance | E11: % Change | F11: YTD Actual | G11: YTD Budget | H11: Variance | I11: % Change
A12: Total Income | B12: 139349.43 | C12: 208168 | D12: =+B12-C12 -> -68818.57 | E12: =IF(C12=0,"N/A",D12/C12) -> -0.33059149 | F12: 299955.74 | G12: 208168 | H12: =+F12-G12 -> 91787.74 | I12: =IF(G12=0,"N/A",H12/G12) -> 0.44093107
A13: Total Operating Expenses | B13: 35781.01 | C13: 28857 | D13: =+C13-B13 -> -6924.01 | E13: =IF(C13=0,"N/A",D13/C13) -> -0.23994213 | F13: 11653.34 | G13: 28857 | H13: =+G13-F13 -> 17203.66 | I13: =IF(G13=0,"N/A",H13/G13) -> 0.59616939
A14: Gross Cash Flow | B14: =+B12-B13 -> 103568.42 | C14: =+C12-C13 -> 179311 | D14: =+B14-C14 -> -75742.58 | E14: =IF(C14=0,"N/A",D14/C14) -> -0.422409 | F14: =+F12-F13 -> 288302.4 | G14: =+G12-G13 -> 179311 | H14: =+F14-G14 -> 108991.4 | I14: =IF(G14=0,"N/A",H14/G14) -> 0.60783443
A15: Total Owners Expense | B15: 0 | C15: 5077 | D15: =+C15-B15 -> 5077 | E15: =IF(C15=0,"N/A",D15/C15) -> 1 | F15: 0 | G15: 5077 | H15: =+G15-F15 -> 5077 | I15: =IF(G15=0,"N/A",H15/G15) -> 1
A16: Total Interest Expense | B16: 0 | C16: 0 | D16: =+C16-B16 -> 0 | E16: =IF(C16=0,"N/A",D16/C16) -> N/A | F16: 0 | G16: 0 | H16: =+G16-F16 -> 0 | I16: =IF(G16=0,"N/A",H16/G16) -> N/A
A17: Net Income | B17: =+B14-B15-B16 -> 103568.42 | C17: =+C14-C15-C16 -> 174234 | D17: =+B17-C17 -> -70665.58 | E17: =IF(C17=0,"N/A",D17/C17) -> -0.40557859 | F17: =+F14-F15-F16 -> 288302.4 | G17: =+G14-G15-G16 -> 174234 | H17: =+F17-G17 -> 114068.4 | I17: =IF(G17=0,"N/A",H17/G17) -> 0.65468508
A20: Income Revenue
A21: MTD Income is under budget by ($68,818.57) or -33.06% due to: -($59K) First Watch, Mattress Firm, Heartland Dental, McDonalds, July rents paid after month end -($8.3K) The Buffalo Spot - No Pmt. -($4.9K) Common Area Income - same timing as base rent Offset by: -$4.6K Property Tax Income
A22: YTD Income is over budget by $91,787.74 or 44.09% due to: -($59K) First Watch, Mattress Firm, Heartland Dental, McDonalds, July rents paid after month end -($8.3K) The Buffalo Spot - No Pmt. -($4.9K) Common Area Income - same timing as base rent Offset by: -$4.6K Property Tax Income
A23: Operating Expenses
A24: MTD Operating Expenses are over budget by ($6,924.01) due to: -($15.6K) Insurance - Property -($1.6K) Landscape - Maintenance Offset by: -$3.2K Sweeping -$2.6K Insurance - Liability -$3.6K On Site Management Fees, Janitorial, Sidewalk Maintenance, Water/Common Area
A25: YTD Operating Expenses are under budget by $17,203.66 due to: -$24.1K Property Tax -$3.2K Sweeping -$2.6K Insurance - Liability -$5.3K On Site Management Fees, Janitorial, Sidewalk Maintenance, Water/Common Area Offset by: -($15.6K) Insurance - Property -($1.6K) Landscape - Maintenance -($0.8K) Trash Removal
A26: Owner Expenses
A27: MTD is favorable by $5,077.00 due to: -$5K City Sales Tax budgeted, none paid this period.
A28: YTD is favorable by $5,077.00 due to: -$5K City Sales Tax budgeted, none paid this period.
A29: Tenant Issues
A30: Buffalo Spot - working with tenant on construction. Will circle back on rent.
A32: Operational Issues
... A48: No capital scheduled for this year. Buffalo Spot is only tenant under construction.

Sheet Tenant Delinquency
A2: Executive Summary
A3: =+'Executive Summary'!A3:I3 -> Roosevelt Commons
A4: July 2026
A7: Property Manager: | B7: Danielle Cebrero | F7: Square Feet: | G7: 51159
A8: Assistant Property Manager | B8: Jaie Benson | F8: % Leased: | G8: ='Executive Summary'!H8 -> 1
A11: Tenant Delinquency
A13: Tenant | B13: Balances over $2,000 | C13: Action Taken / Legal Update
A14: Heartland Dental | B14: 19103.35 | C14: Tenant paid July rents after month closed.
A15: McDonald's | B15: 13026.2 | C15: Tenant owes July and August. Funds approved for release the last week of August. September rents will be paid ontime.
A16: The Buffalo Spot | B16: 8299.7 | C16: Working with tenant to collect rents
A17: First Watch | B17: 19586.04 | C17: Tenant paid July rents after month closed.
A18: Mattress Firm | B18: 18486.63 | C18: Tenant paid July rents after month closed.
A19: TOTAL | B19: =SUM(B14:B18) -> 78501.92

Sheet Photos
A2: Executive Summary
A3: ='Executive Summary'!A3 -> Roosevelt Commons
A4: ='Executive Summary'!A4 -> July 2026 | K4: NOTES
A7: Manager: | B7: ='Executive Summary'!B7 -> Danielle Cebrero | G7: Square Feet: | H7: ='Executive Summary'!H7 -> 54885
A8: Assistant Manager: | B8: ='Executive Summary'!B8 -> Jaie Benson | G8: % Leased: | H8: ='Executive Summary'!H8 -> 1
G9: % Occupied:
A12: Photos

Sheet COI
A2: Executive Summary
A3: Roosevelt Commons
A4: July 2026
A7: Property Manager: | B7: Danielle Cebrero | E7: Square Feet: | F7: 64702
A8: Assistant Property Manager | B8: Jaie Benson | E8: % Leased: | F8: 0.9556
A11: Group | B11: Tracked | C11: COIonFile | D11: COIinCompliance | E11: DOConFile | F11: DOCinCompliance | G11: Notes

Sheet COI Tab
B2: COI Tracking
B3: Greenfield Gateway
B4: August 2025
B8: Property Manager: | C8: Danielle Cebrero | H8: Square Feet: | I8: 51159
B9: Assistant Property Manager | C9: Jaie Benson | H9: % Leased: | I9: 1
B14: Tracked Tenants | D14: COI on File | E14: COI in Compliance | F14: Notes
B15: KACHINA STAINED GLASS
B16: ZANDERS CREATIONS JEWELRY
B17: BRIGHT NOW DENTAL
B18: CARR ANIMAL CARE PLLC
B19: RAZORS BARBER SHOP
B20: CROSSFIT NEW STRENGTH
B21: TIME OUT BAR AND GRILL LLC
B22: THIRD PARTY MVS
B23: SALLY BEAUTY SUPPLY
B24: WILD SIDE SMOKE SHOP
B25: GREEN SPA
B26: MY WIRELESS NATIONAL LLC
... B30: EOS FITNESS

Sheet Tenant Maintenance Tracking. 
A1: Executive Summary
A2: ='Executive Summary'!A3 -> Roosevelt Commons
A3: ='Executive Summary'!A4 -> July 2026
A6: Sr. Property Manager | B6: ='Executive Summary'!B7 -> Danielle Cebrero | C6: Square Feet: | D6: ='Executive Summary'!H7 -> 54885
A7: Assistant Property Manager: | B7: ='Executive Summary'!B8 -> Jaie Benson | C7: % Leased: | D7: ='Executive Summary'!H8 -> 1
A10: Tenant | B10: Service | C10: Doc on File | D10: Doc in Compliance | E10: Notes
