Workbook

Sheet Title Sheet
B6: Goodyear
B9: July 2026
B12: Monthly Report
B24: Prepared By:
B26: Athena Property Management

Sheet Executive Summary
A2: Executive Summary
A3: Goodyear
A4: July 2026
A7: Property Manager: | B7: Danielle Cebrero | G7: Square Feet: | H7: 51159
A8: Assistant Property Manager | B8: Jaie Benson | G8: % Leased: | H8: 0.4412
A9: Cash
B11: Monthly Actual | C11: Monthly Budget | D11: Variance | E11: % Change | F11: YTD Actual | G11: YTD Budget | H11: Variance | I11: % Change
A12: Total Income | B12: 31004.57 | C12: 30771 | D12: 233.57 | E12: =IF(C12=0,"N/A",D12/C12) -> 0.0075905885 | F12: 238463.32 | G12: 215289 | H12: =+F12-G12 -> 23174.32 | I12: =IF(G12=0,"N/A",H12/G12) -> 0.10764284
A13: Total Operating Expenses | B13: 7629.1 | C13: 8785 | D13: =+C13-B13 -> 1155.9 | E13: =IF(C13=0,"N/A",D13/C13) -> 0.13157655 | F13: 80737.49 | G13: 101990 | H13: 21252.51 | I13: =IF(G13=0,"N/A",H13/G13) -> 0.20837837
A14: Gross Cash Flow | B14: =+B12-B13 -> 23375.47 | C14: =+C12-C13 -> 21986 | D14: =+B14-C14 -> 1389.47 | E14: =IF(C14=0,"N/A",D14/C14) -> 0.063197944 | F14: =+F12-F13 -> 157725.83 | G14: =+G12-G13 -> 113299 | H14: =+F14-G14 -> 44426.83 | I14: =IF(G14=0,"N/A",H14/G14) -> 0.39212023
A15: Total Owners Expense | B15: 5688.12 | C15: 1838 | D15: =+C15-B15 -> -3850.12 | E15: =IF(C15=0,"N/A",D15/C15) -> -2.0947334 | F15: 45718.74 | G15: 13689 | H15: =+G15-F15 -> -32029.74 | I15: =IF(G15=0,"N/A",H15/G15) -> -2.3398159
A16: Total Interest Expense | B16: 11514 | C16: 13000 | D16: =+C16-B16 -> 1486 | E16: =IF(C16=0,"N/A",D16/C16) -> 0.11430769 | F16: 82577.98 | G16: 91000 | H16: =+G16-F16 -> 8422.02 | I16: =IF(G16=0,"N/A",H16/G16) -> 0.09254967
A17: Net Income | B17: =+B14-B15-B16 -> 6173.35 | C17: =+C14-C15-C16 -> 7148 | D17: =+B17-C17 -> -974.65 | E17: =IF(C17=0,"N/A",D17/C17) -> -0.13635283 | F17: =+F14-F15-F16 -> 29429.11 | G17: =+G14-G15-G16 -> 8610 | H17: =+F17-G17 -> 20819.11 | I17: =IF(G17=0,"N/A",H17/G17) -> 2.4180151
A19: This month's ending operating cash balance is $535,214.84
A21: Income Revenue
A22: MTD Income Revenue is within budget this period
A23: YTD Income is over budget by $22,940.75 or 12.43% due to: -$21.1K Spirit Halloween - $21,086.29 Utilities charged and received during short trm rent in Jan -$1.5K Utilities Income - $1,504.93 Budget vs pmt for regular utilities in Jan'26 - May'26
A24: Operating Expenses
A25: MTD Operating Expenses are within budget this period
A26: YTD Operating Expenses are under budget by $21,252.51 or 20.84% due to: -$18.9K Common Area Association -$4K General Maintenance Offset by: -($1.8K) Fire Protection Repairs
A27: Owner Expenses
A28: MTD Owner Expenses are over budget by ($3,850.12) or -209.47% due to: -($1.8K) Utilities Expense -($1.8K) Legal Fees, General Repairs & Maint | J28: =42675/5 -> 8535
A29: YTD Owner Expenses are over budget by ($32,029.74) or -233.98% due to: -($15.5K) Utilities Expense -($8.8K) Legal Fees -($3.2K) Other Professional Fees -($2.8K) General Repairs & Maint -($2.1K) HVAC Repair/Labor, City Sales Tax
A30: Loan Status
A31: Loan is current and the ending statement balance is $2,138,006.57
A33: Tenant Issues
A34: None at this time
A36: Operational Issues
A37: None at this time
A39: Renewals (12 months from current period)
A40: None at this time.
A42: Leasing
A43: SuperPlay (Former Big Lots) | B43: Term: 10 years Expiration: 03/31/2037 Current Rent: $29,369.79 (to commence April 2027) Termination Option: None Option Period: Two 5-year optons (4/1/2037-3/31/2042 and 4/1/2042-3/31/2047) Option: 2 successive 5-yr renewals; written notice 210-360 days prior to expiration.
A45: Legal
A46: None at this time.
A48: Property Highlights and Trends
A49: None.
A51: Capital Projects / Tenant Improvements
A52: None.

Sheet Tenant Delinquency
A2: Executive Summary
A3: =+'Executive Summary'!A3:I3 -> Goodyear
A4: July 2026
A7: Property Manager: | B7: Danielle Cebrero | F7: Square Feet: | G7: 51159
A8: Assistant Property Manager | B8: Jaie Benson | F8: % Leased: | G8: ='Executive Summary'!H8 -> 0.4412
A11: Tenant Delinquency
A13: Tenant | B13: Balances over $2,000 | C13: Action Taken / Legal Update
A14: Planet Fitness | B14: 15437.96 | C14: Outstanding charges for PYC ($15K - likely revised to $4K) and sales tax assessments ($500). Working with Senior Accountant to satisfy PF's questions in order to make payment.
A15: TOTAL | B15: =SUM(B14:B14) -> 15437.96

Sheet Photos
A2: Executive Summary
A3: ='Executive Summary'!A3 -> Goodyear
A4: ='Executive Summary'!A4 -> July 2026 | K4: NOTES
A7: Manager: | B7: ='Executive Summary'!B7 -> Danielle Cebrero | G7: Square Feet: | H7: ='Executive Summary'!H7 -> 51159
A8: Assistant Manager: | B8: ='Executive Summary'!B8 -> Jaie Benson | G8: % Leased: | H8: ='Executive Summary'!H8 -> 0.4412
G9: % Occupied:
A12: Photos | K12: Paste photos of any recent work - slurry, tree trimming, paint, new tenants, etc
K13: Include any other updates or areas of concern

Sheet Tenant COI Tracking
B2: COI Tracking
B3: Goodyear
B4: July 2026
B8: Property Manager: | C8: Danielle Cebrero | H8: Square Feet: | I8: 51159
B9: Assistant Property Manager | C9: Jaie Benson | H9: % Leased: | I9: 1
B14: Tracked Tenants | D14: COI on File | E14: COI in Compliance | F14: Notes
B15: Evgo Services, LLC | D15: Yes | E15: Yes
B16: Planet Fitness | D16: Yes | E16: No | F16: Missing Additional Insurance - tenant has been contacted

Sheet Tenant Maintenance Tracking. 
A1: Executive Summary
A2: ='Executive Summary'!A3 -> Goodyear
A3: ='Executive Summary'!A4 -> July 2026
A6: Sr. Property Manager | B6: ='Executive Summary'!B7 -> Danielle Cebrero | C6: Square Feet: | D6: ='Executive Summary'!H7 -> 51159
A7: Assistant Property Manager: | B7: ='Executive Summary'!B8 -> Jaie Benson | C7: % Leased: | D7: ='Executive Summary'!H8 -> 0.4412
A10: Tenant | B10: Service | C10: Doc on File | D10: Doc in Compliance | E10: Notes
