Workbook
Name __dat1: #REF!
Name _1: #REF!
Name _1: #REF!
Name _1: #REF!
Name _1: '[1]Square (The)'!$D$18:$D$22
Name _1: '[1]Square (The)'!$D$18:$D$22
Name _1_245118304: #REF!
Name _10: #REF!
Name _10: #REF!
Name _2: #REF!
Name _2: #REF!
Name _2: [2]data!$J$22:$BR$22
Name _2: '[1]Square (The)'!$J$22:$BR$22
Name _2: '[1]Square (The)'!$J$22:$BR$22
Name _2_245118304: #REF!
Name _245118304: #REF!
Name _245118304BDR: #REF!
Name _265329000: #REF!
Name _3_245118304BDR: #REF!
Name _4_245118304BDR: #REF!
Name _5_265329000: #REF!
Name _6_265329000: #REF!
Name _dat1: [3]data!$A$2:$Q$1000
Name _dat1: [4]data!$A$2:$Q$1000
Name account_data: [7]Menu!$U$36
Name account_data: [8]Menu!$U$36
Name account_data: [9]Menu!$U$36
Name Actual_Rent: 'MR-Stat Data Sheet Bud'!$U$8:$AF$1326
Name Actual_Sqft: #REF!
Name Actual_Sqft: '[10]MR-Stat Data Sheet Bud'!$I$8:$T$402
Name Actual_Sqft: 'MR-Stat Data Sheet Bud'!$I$8:$T$402
Name ActualMonth: '[11]Min Rent Bud '!$V$8:$AG$10
Name ActualMonth: 'MR-Stat Data Sheet Bud'!$AG$8:$AR$9
Name ActualMonth: 'Min Rent Bud'!$V$8:$AG$10
Name amt_class_type_data: [7]Menu!$U$33
Name amt_class_type_data: [8]Menu!$U$33
Name amt_class_type_data: [9]Menu!$U$33
Name amy: '[6]Newport Hills'!$A$2:$J$477
Name amy: [12]variance!$A$2:$J$476
Name amy: [6]data!$A$2:$J$476
Name amy: [13]variance!$A$2:$J$476
Name annual_data: [7]Menu!$U$23
Name annual_data: [8]Menu!$U$23
Name annual_data: [9]Menu!$U$23
Name Bay: [14]Bluffs!$A$2:$J$1340
Name Bay: [15]Bluffs!$A$2:$J$1340
Name Bay: [16]Bluffs!$A$2:$J$1340
Name Bayside: #REF!
Name BS: #REF!
Name BS: #REF!
Name Budget_Type: [7]Menu!$N$13
Name Budget_Type: [8]Menu!$N$13
Name Budget_Type: [9]Menu!$N$13
Name CC_Name: [7]Menu!$N$15
Name CC_Name: [8]Menu!$N$15
Name CC_Name: [9]Menu!$N$15
Name cdm: '[6]Newport Hills'!$A$2:$J$1341
Name cdm: [17]variance!$A$2:$J$1340
Name cdm: [6]data!$A$2:$J$1340
Name cdm: [18]variance!$A$2:$J$1340

Sheet XXXX

Sheet Review Comments
B8: Monthly Financial Analysis
B9: Review Comments
A11: Property: | B11: ABI PROPERTIES
A13: Month: | B13: FOR THE MONTH ENDED 08/31/26
A16: 1.
A22: 2.
A28: 3.
A34: 4.
A40: 5.
A46: 6.
A52: 7.
A58: 8.
A64: 9.
A70: 10.

Sheet Min Rent Plan
N1: =+$M$10 -> 1 | O1: =+$M$10+0.1 -> 1.1 | Q1: =+$M$10+0.2 -> 1.2 | R1: =+$M$10+0.3 -> 1.3 | W1: =+$V$10 -> 2 | X1: =+$V$10+0.1 -> 2.1 | Z1: =+$V$10+0.2 -> 2.2 | AA1: =+$V$10+0.3 -> 2.3 | AF1: =+$AE$10 -> 3 | AG1: =+$AE$10+0.1 -> 3.1 | AI1: =+$AE$10+0.2 -> 3.2 | AJ1: =+$AE$10+0.3 -> 3.3 | AO1: =+$AN$10 -> 4 | AP1: =+$AN$10+0.1 -> 4.1 | AR1: =+$AN$10+0.2 -> 4.2 | AS1: =+$AN$10+0.3 -> 4.3 | AX1: =+$AW$10 -> 5 | AY1: =+$AW$10+0.1 -> 5.1 | BA1: =+$AW$10+0.2 -> 5.2 | BB1: =+$AW$10+0.3 -> 5.3 | BG1: =+$BF$10 -> 6 | BH1: =+$BF$10+0.1 -> 6.1 | BJ1: =+$BF$10+0.2 -> 6.2 | BK1: =+$BF$10+0.3 -> 6.3 | BP1: =+$BO$10 -> 7 | BQ1: =+$BO$10+0.1 -> 7.1 | BS1: =+$BO$10+0.2 -> 7.2 | BT1: =+$BO$10+0.3 -> 7.3 | BY1: =+$BX$10 -> 8 | BZ1: =+$BX$10+0.1 -> 8.1 | CB1: =+$BX$10+0.2 -> 8.2 | CC1: =+$BX$10+0.3 -> 8.3 | CH1: =+$CG$10 -> 9 | CI1: =+$CG$10+0.1 -> 9.1 | CK1: =+$CG$10+0.2 -> 9.2 | CL1: =+$CG$10+0.3 -> 9.3 | CQ1: =+$CP$10 -> 10 | CR1: =+CQ1+0.1 -> 10.1 | CT1: =+CQ1+0.2 -> 10.2 | CU1: =+CQ1+0.3 -> 10.3 | CZ1: 11 | DA1: 11.1 | DC1: 11.2 | DD1: 11.3 | DI1: 12 | DJ1: 12.1 | DL1: 12.2 | DM1: 12.3
C2: =+'Review Comments'!B11 -> ABI PROPERTIES | N2: Month to Date | Q2: Weighted Average | W2: Month to Date | Z2: Weighted Average | AF2: Month to Date | AI2: Weighted Average | AO2: Month to Date | AR2: Weighted Average | AX2: Month to Date | BA2: Weighted Average | BG2: Month to Date | BJ2: Weighted Average | BP2: Month to Date | BS2: Weighted Average | BY2: Month to Date | CB2: Weighted Average | CH2: Month to Date | CK2: Weighted Average | CQ2: Month to Date | CT2: Weighted Average | CZ2: Month to Date | DC2: Weighted Average | DI2: Month to Date | DL2: Weighted Average
C3: MINIMUM RENT VARIANCE REPORT 2009/2010 | N3: Inline | O3: Overall | Q3: Inline | R3: Overall | W3: Inline | X3: Overall | Z3: Inline | AA3: Overall | AF3: Inline | AG3: Overall | AI3: Inline | AJ3: Overall | AO3: Inline | AP3: Overall | AR3: Inline | AS3: Overall | AX3: Inline | AY3: Overall | BA3: Inline | BB3: Overall | BG3: Inline | BH3: Overall | BJ3: Inline | BK3: Overall | BP3: Inline | BQ3: Overall | BS3: Inline | BT3: Overall | BY3: Inline | BZ3: Overall | CB3: Inline | CC3: Overall | CH3: Inline | CI3: Overall | CK3: Inline | CL3: Overall | CQ3: Inline | CR3: Overall | CT3: Inline | CU3: Overall | CZ3: Inline | DA3: Overall | DC3: Inline | DD3: Overall | DI3: Inline | DJ3: Overall | DL3: Inline | DM3: Overall
C4: ACTUAL VS. PLAN | J4: Occupied Sq Ft | N4: ='Inline Rates'!J3 -> 12056 | O4: =+'Inline Rates'!J14 -> 63153 | Q4: ='Inline Rates'!K3 -> 12056 | R4: =+O4 -> 63153 | W4: =+'Inline Rates'!P3 -> 12056 | X4: =+'Inline Rates'!P14 -> 63153 | Z4: =+'Inline Rates'!Q3/2 -> 12056 | AA4: =('Inline Rates'!P18)/2 -> 63153 | AF4: =+'Inline Rates'!V3 -> 12056 | AG4: =+'Inline Rates'!V14 -> 63153 | AI4: =+'Inline Rates'!W3/3 -> 12056 | AJ4: =('Inline Rates'!V18)/3 -> 63153 | AO4: =+'Inline Rates'!AB3 -> 12056 | AP4: =+'Inline Rates'!AB14 -> 63153 | AR4: =+'Inline Rates'!AC3/4 -> 12056 | AS4: =('Inline Rates'!AB18)/4 -> 63153 | AX4: =+'Inline Rates'!AH3 -> 12056 | AY4: =+'Inline Rates'!AH14 -> 63153 | BA4: =+'Inline Rates'!AI3/5 -> 12056 | BB4: =('Inline Rates'!AH18)/5 -> 63153 | BG4: =+'Inline Rates'!AN3 -> 12056 | BH4: =+'Inline Rates'!AN14 -> 63153 | BJ4: =+'Inline Rates'!AO3/6 -> 12056 | BK4: =('Inline Rates'!AN18)/6 -> 63153 | BP4: =+'Inline Rates'!AT3 -> 12056 | BQ4: =+'Inline Rates'!AT14 -> 63153 | BS4: =+'Inline Rates'!AU3/7 -> 12056 | BT4: =('Inline Rates'!AT18)/7 -> 63153 | BY4: =+'Inline Rates'!AZ3 -> 12056 | BZ4: =+'Inline Rates'!AZ14 -> 63153 | CB4: =+'Inline Rates'!BA3/8 -> 12056 | CC4: =('Inline Rates'!AZ18)/8 -> 63153 | CH4: =+'Inline Rates'!BF3 -> 12056 | CI4: =+'Inline Rates'!BF14 -> 63153 | CK4: =+'Inline Rates'!BG3/9 -> 12056 | CL4: =('Inline Rates'!BF18)/9 -> 63153 | CQ4: =+'Inline Rates'!BL3 -> 12056 | CR4: =+'Inline Rates'!BL14 -> 63153 | CT4: =+'Inline Rates'!BM3/10 -> 12056 | CU4: =('Inline Rates'!BL18)/10 -> 63153 | CZ4: =+'Inline Rates'!BR3 -> 12056 | DA4: =+'Inline Rates'!BR14 -> 63153 | DC4: =+'Inline Rates'!BS3/11 -> 12056 | DD4: =('Inline Rates'!BR18)/11 -> 63153 | DI4: =+'Inline Rates'!BX3 -> 12056 | DJ4: =+'Inline Rates'!BX14 -> 63153 | DL4: =+'Inline Rates'!BY3/12 -> 12056 | DM4: =('Inline Rates'!BX18)/12 -> 63153
J5: Vacant Sq Ft | N5: ='Inline Rates'!J4-N4 -> 1200 | O5: =+'Inline Rates'!K14-O4 -> 1200 | Q5: ='Inline Rates'!K4-Q4 -> 1200 | R5: =+O5 -> 1200 | W5: ='Inline Rates'!P4-W4 -> 1200 | X5: =+'Inline Rates'!Q14-'Min Rent Plan'!X4 -> 1200 | Z5: =+'Inline Rates'!Q4/2-Z4 -> 1200 | AA5: =(('Inline Rates'!Q18)/2)-AA4 -> 1200 | AF5: ='Inline Rates'!V4-AF4 -> 1200 | AG5: =+'Inline Rates'!W14-AG4 -> 1200 | AI5: =+'Inline Rates'!W4/3-AI4 -> 1200 | AJ5: =(('Inline Rates'!W18)/3)-AJ4 -> 1200 | AO5: =+'Inline Rates'!AB4-AO4 -> 1200 | AP5: =+'Inline Rates'!AC14-AP4 -> 1200 | AR5: =+'Inline Rates'!AC4/4-AR4 -> 1200 | AS5: =(('Inline Rates'!AC18)/4)-AS4 -> 1200 | AX5: =+'Inline Rates'!AH4-AX4 -> 1200 | AY5: =+'Inline Rates'!AI14-AY4 -> 1200 | BA5: =+'Inline Rates'!AI4/5-BA4 -> 1200 | BB5: =(('Inline Rates'!AI18)/5)-BB4 -> 1200 | BG5: =+'Inline Rates'!AN4-BG4 -> 1200 | BH5: =+'Inline Rates'!AO14-BH4 -> 1200 | BJ5: =+'Inline Rates'!AO4/6-BJ4 -> 1200 | BK5: =(('Inline Rates'!AO18)/6)-BK4 -> 1200 | BP5: =+'Inline Rates'!AT4-BP4 -> 1200 | BQ5: =+'Inline Rates'!AU14-BQ4 -> 1200 | BS5: =+'Inline Rates'!AU4/7-BS4 -> 1200 | BT5: =(('Inline Rates'!AU18)/7)-BT4 -> 1200 | BY5: =+'Inline Rates'!AZ4-BY4 -> 1200 | BZ5: =+'Inline Rates'!BA14-BZ4 -> 1200 | CB5: =+'Inline Rates'!BA4/8-CB4 -> 1200 | CC5: =(('Inline Rates'!BA18)/8)-CC4 -> 1200 | CH5: =+'Inline Rates'!BF4-CH4 -> 1200 | CI5: =+'Inline Rates'!BG14-CI4 -> 1200 | CK5: =+'Inline Rates'!BG4/9-CK4 -> 1200 | CL5: =(('Inline Rates'!BG18)/9)-CL4 -> 1200 | CQ5: =+'Inline Rates'!BL4-CQ4 -> 1200 | CR5: =+'Inline Rates'!BM14-CR4 -> 1200 | CT5: =+'Inline Rates'!BM4/10-'Min Rent Plan'!CT4 -> 1200 | CU5: =(('Inline Rates'!BM18)/10)-CU4 -> 1200 | CZ5: =+'Inline Rates'!BR4-CZ4 -> 1200 | DA5: =+'Inline Rates'!BS14-DA4 -> 1200 | DC5: =+'Inline Rates'!BS4/11-DC4 -> 1200 | DD5: =(('Inline Rates'!BS18)/11)-DD4 -> 1200 | DI5: =+'Inline Rates'!BX4-DI4 -> 1200 | DJ5: =+'Inline Rates'!BY14-DJ4 -> 1200 | DL5: =+'Inline Rates'!BY4/12-DL4 -> 1200 | DM5: =(('Inline Rates'!BY18)/12)-DM4 -> 1200
J6: Total Sq Ft | N6: =SUM(N4:N5) -> 13256 | O6: =SUM(O4:O5) -> 64353 | Q6: =SUM(Q4:Q5) -> 13256 | R6: =SUM(R4:R5) -> 64353 | W6: =SUM(W4:W5) -> 13256 | X6: =SUM(X4:X5) -> 64353 | Z6: =SUM(Z4:Z5) -> 13256 | AA6: =SUM(AA4:AA5) -> 64353 | AF6: =SUM(AF4:AF5) -> 13256 | AG6: =SUM(AG4:AG5) -> 64353 | AI6: =SUM(AI4:AI5) -> 13256 | AJ6: =SUM(AJ4:AJ5) -> 64353 | AO6: =SUM(AO4:AO5) -> 13256 | AP6: =SUM(AP4:AP5) -> 64353 | AR6: =SUM(AR4:AR5) -> 13256 | AS6: =SUM(AS4:AS5) -> 64353 | AX6: =SUM(AX4:AX5) -> 13256 | AY6: =SUM(AY4:AY5) -> 64353 | BA6: =SUM(BA4:BA5) -> 13256 | BB6: =SUM(BB4:BB5) -> 64353 | BG6: =SUM(BG4:BG5) -> 13256 | BH6: =SUM(BH4:BH5) -> 64353 | BJ6: =SUM(BJ4:BJ5) -> 13256 | BK6: =SUM(BK4:BK5) -> 64353 | BP6: =SUM(BP4:BP5) -> 13256 | BQ6: =SUM(BQ4:BQ5) -> 64353 | BS6: =SUM(BS4:BS5) -> 13256 | BT6: =SUM(BT4:BT5) -> 64353 | BY6: =SUM(BY4:BY5) -> 13256 | BZ6: =SUM(BZ4:BZ5) -> 64353 | CB6: =SUM(CB4:CB5) -> 13256 | CC6: =SUM(CC4:CC5) -> 64353 | CH6: =SUM(CH4:CH5) -> 13256 | CI6: =SUM(CI4:CI5) -> 64353 | CK6: =SUM(CK4:CK5) -> 13256 | CL6: =SUM(CL4:CL5) -> 64353 | CQ6: =SUM(CQ4:CQ5) -> 13256 | CR6: =SUM(CR4:CR5) -> 64353 | CT6: =SUM(CT4:CT5) -> 13256 | CU6: =SUM(CU4:CU5) -> 64353 | CZ6: =SUM(CZ4:CZ5) -> 13256 | DA6: =SUM(DA4:DA5) -> 64353 | DC6: =SUM(DC4:DC5) -> 13256 | DD6: =SUM(DD4:DD5) -> 64353 | DI6: =SUM(DI4:DI5) -> 13256 | DJ6: =SUM(DJ4:DJ5) -> 64353 | DL6: =SUM(DL4:DL5) -> 13256 | DM6: =SUM(DM4:DM5) -> 64353
I7: Percentage Occupied | J7: Pct Occupied | N7: =+N4/N6 -> 0.90947495 | O7: =+O4/O6 -> 0.98135285 | Q7: =+Q4/Q6 -> 0.90947495 | R7: =+R4/R6 -> 0.98135285 | W7: =+W4/W6 -> 0.90947495 | X7: =+X4/X6 -> 0.98135285 | Z7: =+Z4/Z6 -> 0.90947495 | AA7: =+AA4/AA6 -> 0.98135285 | AF7: =+AF4/AF6 -> 0.90947495 | AG7: =+AG4/AG6 -> 0.98135285 | AI7: =+AI4/AI6 -> 0.90947495 | AJ7: =+AJ4/AJ6 -> 0.98135285 | AO7: =+AO4/AO6 -> 0.90947495 | AP7: =+AP4/AP6 -> 0.98135285 | AR7: =+AR4/AR6 -> 0.90947495 | AS7: =+AS4/AS6 -> 0.98135285 | AX7: =+AX4/AX6 -> 0.90947495 | AY7: =+AY4/AY6 -> 0.98135285 | BA7: =+BA4/BA6 -> 0.90947495 | BB7: =+BB4/BB6 -> 0.98135285 | BG7: =+BG4/BG6 -> 0.90947495 | BH7: =+BH4/BH6 -> 0.98135285 | BJ7: =+BJ4/BJ6 -> 0.90947495 | BK7: =+BK4/BK6 -> 0.98135285 | BP7: =+BP4/BP6 -> 0.90947495 | BQ7: =+BQ4/BQ6 -> 0.98135285 | BS7: =+BS4/BS6 -> 0.90947495 | BT7: =+BT4/BT6 -> 0.98135285 | BY7: =+BY4/BY6 -> 0.90947495 | BZ7: =+BZ4/BZ6 -> 0.98135285 | CB7: =+CB4/CB6 -> 0.90947495 | CC7: =+CC4/CC6 -> 0.98135285 | CH7: =+CH4/CH6 -> 0.90947495 | CI7: =+CI4/CI6 -> 0.98135285 | CK7: =+CK4/CK6 -> 0.90947495 | CL7: =+CL4/CL6 -> 0.98135285 | CQ7: =+CQ4/CQ6 -> 0.90947495 | CR7: =+CR4/CR6 -> 0.98135285 | CT7: =+CT4/CT6 -> 0.90947495 | CU7: =+CU4/CU6 -> 0.98135285 | CZ7: =+CZ4/CZ6 -> 0.90947495 | DA7: =+DA4/DA6 -> 0.98135285 | DC7: =+DC4/DC6 -> 0.90947495 | DD7: =+DD4/DD6 -> 0.98135285 | DI7: =+DI4/DI6 -> 0.90947495 | DJ7: =+DJ4/DJ6 -> 0.98135285 | DL7: =+DL4/DL6 -> 0.90947495 | DM7: =+DM4/DM6 -> 0.98135285
J8: Inline Rate | N8: ='Inline Rates'!J8 -> 52.953932 | O8: N/A | Q8: ='Inline Rates'!K8 -> 52.953932 | R8: N/A | W8: =+'Inline Rates'!P8 -> 52.953932 | X8: N/A | Z8: =+'Inline Rates'!Q8 -> 52.953932 | AA8: N/A | AF8: =+'Inline Rates'!V8 -> 53.171666 | AG8: N/A | AI8: =+'Inline Rates'!W8 -> 53.02651 | AJ8: N/A | AO8: =+'Inline Rates'!AB8 -> 53.171666 | AP8: N/A | AR8: =+'Inline Rates'!AC8 -> 53.062799 | AS8: N/A | AX8: =+'Inline Rates'!AH8 -> 49.305956 | AY8: N/A | BA8: =+'Inline Rates'!AI8 -> 49.667419 | BB8: N/A | BG8: =+'Inline Rates'!AN8 -> 48.775352 | BH8: N/A | BJ8: =+'Inline Rates'!AO8 -> 51.943864 | BK8: N/A | BP8: =+'Inline Rates'!AT8 -> 54.436812 | BQ8: N/A | BS8: =+'Inline Rates'!AU8 -> 52.694099 | BT8: N/A | BY8: =+'Inline Rates'!AZ8 -> 54.436812 | BZ8: N/A | CB8: =+'Inline Rates'!BA8 -> 52.911938 | CC8: N/A | CH8: =+'Inline Rates'!BF8 -> 54.436812 | CI8: N/A | CK8: =+'Inline Rates'!BG8 -> 53.081368 | CL8: N/A | CQ8: =+'Inline Rates'!BL8 -> 53.227455 | CR8: N/A | CT8: =+'Inline Rates'!BM8 -> 52.926259 | CU8: N/A | CZ8: =+'Inline Rates'!BR8 -> 53.227455 | DA8: N/A | DC8: =+'Inline Rates'!BS8 -> 52.946736 | DD8: N/A | DI8: =+'Inline Rates'!BX8 -> 51.29149 | DJ8: N/A | DL8: =+'Inline Rates'!BY8 -> 52.256344 | DM8: N/A
I10: 12 | M10: 1 | V10: 2 | AE10: 3 | AN10: 4 | AW10: 5 | BF10: 6 | BO10: 7 | BX10: 8 | CG10: 9 | CP10: 10 | CY10: 11 | DH10: 12
C11: Tenant | F11: Suite | K11: July | L11: July | M11: JULY | Q11: Year to Date | T11: Aug | U11: Aug | V11: AUGUST | Z11: Year to Date | AC11: Sep | AD11: Sep | AE11: SEPT | AI11: Year to Date | AL11: Oct | AM11: Oct | AN11: OCT | AR11: Year to Date | AU11: Nov | AV11: Nov | AW11: NOV | BA11: Year to Date | BD11: Dec | BE11: Dec | BF11: DEC | BJ11: Year to Date | BM11: Jan | BN11: Jan | BO11: JAN | BS11: Year to Date | BV11: Feb | BW11: Feb | BX11: FEB | CB11: Year to Date | CE11: Mar | CF11: Mar | CG11: MAR | CK11: Year to Date | CN11: Apr | CO11: Apr | CP11: APR | CT11: Year to Date | CW11: May | CX11: May | CY11: MAY | DC11: Year to Date | DF11: June | DG11: June | DH11: JUNE | DL11: Year to Date | DO11: Year to Date | DQ11: Annual
C12: Name | D12: Lse Start | E12: Lse Exp. | F12: Status | G12: No. | H12: Sq Ft | I12: Month | K12: MRI | L12: Adjustment | M12: Actual | N12: Plan | O12: Variance | Q12: Actual | R12: Plan | S12: Variance | T12: MRI | U12: Adjustment | V12: Actual | W12: Plan | X12: Variance | Z12: Actual | AA12: Plan | AB12: Variance | AC12: MRI | AD12: Adjustment | AE12: Actual | AF12: Plan | AG12: Variance | AI12: Actual | AJ12: Plan | AK12: Variance | AL12: MRI | AM12: Adjustment | AN12: Actual | AO12: Plan | AP12: Variance | AR12: Actual | AS12: Plan | AT12: Variance | AU12: MRI | AV12: Adjustment | AW12: Actual | AX12: Plan | AY12: Variance | BA12: Actual | BB12: Plan | BC12: Variance | BD12: MRI | BE12: Adjustment | BF12: Actual | BG12: Plan | BH12: Variance | BJ12: Actual | BK12: Plan | BL12: Variance | BM12: MRI | BN12: Adjustment | BO12: Actual | BP12: Plan | BQ12: Variance | BS12: Actual | BT12: Plan | BU12: Variance | BV12: MRI | BW12: Adjustment | BX12: Actual | BY12: Plan | BZ12: Variance | CB12: Actual | CC12: Plan | CD12: Variance | CE12: MRI | CF12: Adjustment | CG12: Actual | CH12: Plan | CI12: Variance | CK12: Actual | CL12: Plan | CM12: Variance | CN12: MRI | CO12: Adjustment | CP12: Actual | CQ12: Plan | CR12: Variance | CT12: Actual | CU12: Plan | CV12: Variance | CW12: MRI | CX12: Adjustment | CY12: Actual | CZ12: Plan | DA12: Variance | DC12: Actual | DD12: Plan | DE12: Variance | DF12: MRI | DG12: Adjustment | DH12: Actual | DI12: Plan | DJ12: Variance | DL12: Actual | DM12: Plan | DN12: Variance | DO12: Explanation | DQ12: Plan | DR12: Var. to Plan | DS12: Explanation
C13: Inline
A14: 1 | B14: 621201-000001 | C14: Bayside Cleaners | D14: 32295 | E14: 40694 | F14: Occupied | G14: 1056 | H14: 1500 | I14: =HLOOKUP(I$10,M$10:DI$53,ROW()-9,FALSE) -> 11843.75 | K14: =IF(ISERROR(VLOOKUP($B14,'MRI Data'!$A:$P,M$10+3,FALSE)),0,VLOOKUP($B14,'MRI Data'!$A:$P,M$10+3,FALSE)) -> 11388.75 | M14: =SUM(K14:L14) -> 11388.75 | N14: 11389 | O14: =+M14-N14 -> -0.25 | Q14: =+M14 -> 11388.75 | R14: =+N14 -> 11389 | S14: =O14 -> -0.25 | T14: =IF(ISERROR(VLOOKUP($B14,'MRI Data'!$A:$P,V$10+3,FALSE)),0,VLOOKUP($B14,'MRI Data'!$A:$P,V$10+3,FALSE)) -> 11388.75 | V14: =SUM(T14:U14) -> 11388.75 | W14: 11389 | X14: =+V14-W14 -> -0.25 | Z14: =+Q14+V14 -> 22777.5 | AA14: =+R14+W14 -> 22778 | AB14: =+Z14-AA14 -> -0.5 | AC14: =IF(ISERROR(VLOOKUP($B14,'MRI Data'!$A:$P,AE$10+3,FALSE)),0,VLOOKUP($B14,'MRI Data'!$A:$P,AE$10+3,FALSE)) -> 11388.75 | AE14: =SUM(AC14:AD14) -> 11388.75 | AF14: 11389 | AG14: =+AE14-AF14 -> -0.25 | AI14: =+Z14+AE14 -> 34166.25 | AJ14: =+AA14+AF14 -> 34167 | AK14: =+AI14-AJ14 -> -0.75 | AL14: =IF(ISERROR(VLOOKUP($B14,'MRI Data'!$A:$P,AN$10+3,FALSE)),0,VLOOKUP($B14,'MRI Data'!$A:$P,AN$10+3,FALSE)) -> 11388.75 | AN14: =SUM(AL14:AM14) -> 11388.75 | AO14: 11389 | AP14: =+AN14-AO14 -> -0.25 | AR14: =+AI14+AN14 -> 45555 | AS14: =+AJ14+AO14 -> 45556 | AT14: =+AR14-AS14 -> -1 | AU14: =IF(ISERROR(VLOOKUP($B14,'MRI Data'!$A:$P,AW$10+3,FALSE)),0,VLOOKUP($B14,'MRI Data'!$A:$P,AW$10+3,FALSE)) -> 11388.75 | AW14: =SUM(AU14:AV14) -> 11388.75 | AX14: 11389 | AY14: =+AW14-AX14 -> -0.25 | BA14: =+AR14+AW14 -> 56943.75 | BB14: =+AS14+AX14 -> 56945 | BC14: =+BA14-BB14 -> -1.25 | BD14: =IF(ISERROR(VLOOKUP($B14,'MRI Data'!$A:$P,BF$10+3,FALSE)),0,VLOOKUP($B14,'MRI Data'!$A:$P,BF$10+3,FALSE)) -> 11388.75 | BF14: =SUM(BD14:BE14) -> 11388.75 | BG14: 11389 | BH14: =+BF14-BG14 -> -0.25 | BJ14: =+BA14+BF14 -> 68332.5 | BK14: =+BB14+BG14 -> 68334 | BL14: =+BJ14-BK14 -> -1.5 | BM14: =IF(ISERROR(VLOOKUP($B14,'MRI Data'!$A:$P,BO$10+3,FALSE)),0,VLOOKUP($B14,'MRI Data'!$A:$P,BO$10+3,FALSE)) -> 11388.75 | BO14: =SUM(BM14:BN14) -> 11388.75 | BP14: 11389 | BQ14: =+BO14-BP14 -> -0.25 | BS14: =+BJ14+BO14 -> 79721.25 | BT14: =+BK14+BP14 -> 79723 | BU14: =+BS14-BT14 -> -1.75 | BV14: =IF(ISERROR(VLOOKUP($B14,'MRI Data'!$A:$P,BX$10+3,FALSE)),0,VLOOKUP($B14,'MRI Data'!$A:$P,BX$10+3,FALSE)) -> 11388.75 | BX14: =SUM(BV14:BW14) -> 11388.75 | BY14: 11389 | BZ14: =+BX14-BY14 -> -0.25 | CB14: =+BS14+BX14 -> 91110 | CC14: =+BT14+BY14 -> 91112 | CD14: =+CB14-CC14 -> -2 | CE14: =IF(ISERROR(VLOOKUP($B14,'MRI Data'!$A:$P,CG$10+3,FALSE)),0,VLOOKUP($B14,'MRI Data'!$A:$P,CG$10+3,FALSE)) -> 11388.75 | CG14: =SUM(CE14:CF14) -> 11388.75 | CH14: 11389 | CI14: =+CG14-CH14 -> -0.25 | CK14: =+CB14+CG14 -> 102498.75 | CL14: =+CC14+CH14 -> 102501 | CM14: =+CK14-CL14 -> -2.25 | CN14: =IF(ISERROR(VLOOKUP($B14,'MRI Data'!$A:$P,CP$10+3,FALSE)),0,VLOOKUP($B14,'MRI Data'!$A:$P,CP$10+3,FALSE)) -> 11388.75 | CP14: =SUM(CN14:CO14) -> 11388.75 | CQ14: 11389 | CR14: =+CP14-CQ14 -> -0.25 | CT14: =+CK14+CP14 -> 113887.5 | CU14: =+CL14+CQ14 -> 113890 | CV14: =+CT14-CU14 -> -2.5 | CW14: =IF(ISERROR(VLOOKUP($B14,'MRI Data'!$A:$P,CY$10+3,FALSE)),0,VLOOKUP($B14,'MRI Data'!$A:$P,CY$10+3,FALSE)) -> 11388.75 | CY14: =SUM(CW14:CX14) -> 11388.75 | CZ14: 11389 | DA14: =+CY14-CZ14 -> -0.25 | DC14: =+CT14+CY14 -> 125276.25 | DD14: =+CU14+CZ14 -> 125279 | DE14: =+DC14-DD14 -> -2.75 | DF14: =IF(ISERROR(VLOOKUP($B14,'MRI Data'!$A:$P,DH$10+3,FALSE)),0,VLOOKUP($B14,'MRI Data'!$A:$P,DH$10+3,FALSE)) -> 11843.75 | DH14: =SUM(DF14:DG14) -> 11843.75 | DI14: 11844 | DJ14: =+DH14-DI14 -> -0.25 | DL14: =+DC14+DH14 -> 137120 | DM14: =+DD14+DI14 -> 137123 | DN14: =+DL14-DM14 -> -3 | DQ14: =+DM14 -> 137123 | DR14: 0
A15: 2 | B15: 621201-000013 | C15: Carol Klein Fine Jewelry 1028 | D15: 35223 | E15: 40724 | F15: Occupied | G15: 1028 | H15: 1055 | I15: =HLOOKUP(I$10,M$10:DI$53,ROW()-9,FALSE) -> 5417.43 | K15: =IF(ISERROR(VLOOKUP($B15,'MRI Data'!$A:$P,M$10+3,FALSE)),0,VLOOKUP($B15,'MRI Data'!$A:$P,M$10+3,FALSE)) -> 5417.43 | M15: =SUM(K15:L15) -> 5417.43 | N15: 5417 | O15: =+M15-N15 -> 0.43 | Q15: =+M15 -> 5417.43 | R15: =+N15 -> 5417 | S15: =O15 -> 0.43 | T15: =IF(ISERROR(VLOOKUP($B15,'MRI Data'!$A:$P,V$10+3,FALSE)),0,VLOOKUP($B15,'MRI Data'!$A:$P,V$10+3,FALSE)) -> 5417.43 | V15: =SUM(T15:U15) -> 5417.43 | W15: 5417 | X15: =+V15-W15 -> 0.43 | Z15: =+Q15+V15 -> 10834.86 | AA15: =+R15+W15 -> 10834 | AB15: =+Z15-AA15 -> 0.86 | AC15: =IF(ISERROR(VLOOKUP($B15,'MRI Data'!$A:$P,AE$10+3,FALSE)),0,VLOOKUP($B15,'MRI Data'!$A:$P,AE$10+3,FALSE)) -> 5417.43 | AE15: =SUM(AC15:AD15) -> 5417.43 | AF15: 5417 | AG15: =+AE15-AF15 -> 0.43 | AI15: =+Z15+AE15 -> 16252.29 | AJ15: =+AA15+AF15 -> 16251 | AK15: =+AI15-AJ15 -> 1.29 | AL15: =IF(ISERROR(VLOOKUP($B15,'MRI Data'!$A:$P,AN$10+3,FALSE)),0,VLOOKUP($B15,'MRI Data'!$A:$P,AN$10+3,FALSE)) -> 5417.43 | AN15: =SUM(AL15:AM15) -> 5417.43 | AO15: 5417 | AP15: =+AN15-AO15 -> 0.43 | AR15: =+AI15+AN15 -> 21669.72 | AS15: =+AJ15+AO15 -> 21668 | AT15: =+AR15-AS15 -> 1.72 | AU15: =IF(ISERROR(VLOOKUP($B15,'MRI Data'!$A:$P,AW$10+3,FALSE)),0,VLOOKUP($B15,'MRI Data'!$A:$P,AW$10+3,FALSE)) -> 5417.43 | AW15: =SUM(AU15:AV15) -> 5417.43 | AX15: 5417 | AY15: =+AW15-AX15 -> 0.43 | BA15: =+AR15+AW15 -> 27087.15 | BB15: =+AS15+AX15 -> 27085 | BC15: =+BA15-BB15 -> 2.15 | BD15: =IF(ISERROR(VLOOKUP($B15,'MRI Data'!$A:$P,BF$10+3,FALSE)),0,VLOOKUP($B15,'MRI Data'!$A:$P,BF$10+3,FALSE)) -> 5417.43 | BF15: =SUM(BD15:BE15) -> 5417.43 | BG15: 5417 | BH15: =+BF15-BG15 -> 0.43 | BJ15: =+BA15+BF15 -> 32504.58 | BK15: =+BB15+BG15 -> 32502 | BL15: =+BJ15-BK15 -> 2.58 | BM15: =IF(ISERROR(VLOOKUP($B15,'MRI Data'!$A:$P,BO$10+3,FALSE)),0,VLOOKUP($B15,'MRI Data'!$A:$P,BO$10+3,FALSE)) -> 5417.43 | BO15: =SUM(BM15:BN15) -> 5417.43 | BP15: 5417 | BQ15: =+BO15-BP15 -> 0.43 | BS15: =+BJ15+BO15 -> 37922.01 | BT15: =+BK15+BP15 -> 37919 | BU15: =+BS15-BT15 -> 3.01 | BV15: =IF(ISERROR(VLOOKUP($B15,'MRI Data'!$A:$P,BX$10+3,FALSE)),0,VLOOKUP($B15,'MRI Data'!$A:$P,BX$10+3,FALSE)) -> 5417.43 | BX15: =SUM(BV15:BW15) -> 5417.43 | BY15: 5417 | BZ15: =+BX15-BY15 -> 0.43 | CB15: =+BS15+BX15 -> 43339.44 | CC15: =+BT15+BY15 -> 43336 | CD15: =+CB15-CC15 -> 3.44 | CE15: =IF(ISERROR(VLOOKUP($B15,'MRI Data'!$A:$P,CG$10+3,FALSE)),0,VLOOKUP($B15,'MRI Data'!$A:$P,CG$10+3,FALSE)) -> 5417.43 | CG15: =SUM(CE15:CF15) -> 5417.43 | CH15: 5417 | CI15: =+CG15-CH15 -> 0.43 | CK15: =+CB15+CG15 -> 48756.87 | CL15: =+CC15+CH15 -> 48753 | CM15: =+CK15-CL15 -> 3.87 | CN15: =IF(ISERROR(VLOOKUP($B15,'MRI Data'!$A:$P,CP$10+3,FALSE)),0,VLOOKUP($B15,'MRI Data'!$A:$P,CP$10+3,FALSE)) -> 5417.43 | CP15: =SUM(CN15:CO15) -> 5417.43 | CQ15: 5417 | CR15: =+CP15-CQ15 -> 0.43 | CT15: =+CK15+CP15 -> 54174.3 | CU15: =+CL15+CQ15 -> 54170 | CV15: =+CT15-CU15 -> 4.3 | CW15: =IF(ISERROR(VLOOKUP($B15,'MRI Data'!$A:$P,CY$10+3,FALSE)),0,VLOOKUP($B15,'MRI Data'!$A:$P,CY$10+3,FALSE)) -> 5417.43 | CY15: =SUM(CW15:CX15) -> 5417.43 | CZ15: 5417 | DA15: =+CY15-CZ15 -> 0.43 | DC15: =+CT15+CY15 -> 59591.73 | DD15: =+CU15+CZ15 -> 59587 | DE15: =+DC15-DD15 -> 4.73 | DF15: =IF(ISERROR(VLOOKUP($B15,'MRI Data'!$A:$P,DH$10+3,FALSE)),0,VLOOKUP($B15,'MRI Data'!$A:$P,DH$10+3,FALSE)) -> 5417.43 | DH15: =SUM(DF15:DG15) -> 5417.43 | DI15: 5417 | DJ15: =+DH15-DI15 -> 0.43 | DL15: =+DC15+DH15 -> 65009.16 | DM15: =+DD15+DI15 -> 65004 | DN15: =+DL15-DM15 -> 5.16 | DQ15: =+DM15 -> 65004 | DR15: 0
A16: 3 | B16: 621201-000004 | C16: Java City Bakery Café | D16: 34700 | E16: 41820 | F16: Occupied | G16: 1064 | H16: 1320 | I16: =HLOOKUP(I$10,M$10:DI$53,ROW()-9,FALSE) -> 6490 | K16: =IF(ISERROR(VLOOKUP($B16,'MRI Data'!$A:$P,M$10+3,FALSE)),0,VLOOKUP($B16,'MRI Data'!$A:$P,M$10+3,FALSE)) -> 6490 | M16: =SUM(K16:L16) -> 6490 | N16: 6490 | O16: =+M16-N16 -> 0 | Q16: =+M16 -> 6490 | R16: =+N16 -> 6490 | S16: =O16 -> 0 | T16: =IF(ISERROR(VLOOKUP($B16,'MRI Data'!$A:$P,V$10+3,FALSE)),0,VLOOKUP($B16,'MRI Data'!$A:$P,V$10+3,FALSE)) -> 6490 | V16: =SUM(T16:U16) -> 6490 | W16: 6490 | X16: =+V16-W16 -> 0 | Z16: =+Q16+V16 -> 12980 | AA16: =+R16+W16 -> 12980 | AB16: =+Z16-AA16 -> 0 | AC16: =IF(ISERROR(VLOOKUP($B16,'MRI Data'!$A:$P,AE$10+3,FALSE)),0,VLOOKUP($B16,'MRI Data'!$A:$P,AE$10+3,FALSE)) -> 6490 | AE16: =SUM(AC16:AD16) -> 6490 | AF16: 6490 | AG16: =+AE16-AF16 -> 0 | AI16: =+Z16+AE16 -> 19470 | AJ16: =+AA16+AF16 -> 19470 | AK16: =+AI16-AJ16 -> 0 | AL16: =IF(ISERROR(VLOOKUP($B16,'MRI Data'!$A:$P,AN$10+3,FALSE)),0,VLOOKUP($B16,'MRI Data'!$A:$P,AN$10+3,FALSE)) -> 6490 | AN16: =SUM(AL16:AM16) -> 6490 | AO16: 6490 | AP16: =+AN16-AO16 -> 0 | AR16: =+AI16+AN16 -> 25960 | AS16: =+AJ16+AO16 -> 25960 | AT16: =+AR16-AS16 -> 0 | AU16: =IF(ISERROR(VLOOKUP($B16,'MRI Data'!$A:$P,AW$10+3,FALSE)),0,VLOOKUP($B16,'MRI Data'!$A:$P,AW$10+3,FALSE)) -> 6490 | AW16: =SUM(AU16:AV16) -> 6490 | AX16: 6490 | AY16: =+AW16-AX16 -> 0 | BA16: =+AR16+AW16 -> 32450 | BB16: =+AS16+AX16 -> 32450 | BC16: =+BA16-BB16 -> 0 | BD16: =IF(ISERROR(VLOOKUP($B16,'MRI Data'!$A:$P,BF$10+3,FALSE)),0,VLOOKUP($B16,'MRI Data'!$A:$P,BF$10+3,FALSE)) -> 6490 | BF16: =SUM(BD16:BE16) -> 6490 | BG16: 6490 | BH16: =+BF16-BG16 -> 0 | BJ16: =+BA16+BF16 -> 38940 | BK16: =+BB16+BG16 -> 38940 | BL16: =+BJ16-BK16 -> 0 | BM16: =IF(ISERROR(VLOOKUP($B16,'MRI Data'!$A:$P,BO$10+3,FALSE)),0,VLOOKUP($B16,'MRI Data'!$A:$P,BO$10+3,FALSE)) -> 6490 | BO16: =SUM(BM16:BN16) -> 6490 | BP16: 6490 | BQ16: =+BO16-BP16 -> 0 | BS16: =+BJ16+BO16 -> 45430 | BT16: =+BK16+BP16 -> 45430 | BU16: =+BS16-BT16 -> 0 | BV16: =IF(ISERROR(VLOOKUP($B16,'MRI Data'!$A:$P,BX$10+3,FALSE)),0,VLOOKUP($B16,'MRI Data'!$A:$P,BX$10+3,FALSE)) -> 6490 | BX16: =SUM(BV16:BW16) -> 6490 | BY16: 6490 | BZ16: =+BX16-BY16 -> 0 | CB16: =+BS16+BX16 -> 51920 | CC16: =+BT16+BY16 -> 51920 | CD16: =+CB16-CC16 -> 0 | CE16: =IF(ISERROR(VLOOKUP($B16,'MRI Data'!$A:$P,CG$10+3,FALSE)),0,VLOOKUP($B16,'MRI Data'!$A:$P,CG$10+3,FALSE)) -> 6490 | CG16: =SUM(CE16:CF16) -> 6490 | CH16: 6490 | CI16: =+CG16-CH16 -> 0 | CK16: =+CB16+CG16 -> 58410 | CL16: =+CC16+CH16 -> 58410 | CM16: =+CK16-CL16 -> 0 | CN16: =IF(ISERROR(VLOOKUP($B16,'MRI Data'!$A:$P,CP$10+3,FALSE)),0,VLOOKUP($B16,'MRI Data'!$A:$P,CP$10+3,FALSE)) -> 6490 | CP16: =SUM(CN16:CO16) -> 6490 | CQ16: 6490 | CR16: =+CP16-CQ16 -> 0 | CT16: =+CK16+CP16 -> 64900 | CU16: =+CL16+CQ16 -> 64900 | CV16: =+CT16-CU16 -> 0 | CW16: =IF(ISERROR(VLOOKUP($B16,'MRI Data'!$A:$P,CY$10+3,FALSE)),0,VLOOKUP($B16,'MRI Data'!$A:$P,CY$10+3,FALSE)) -> 6490 | CY16: =SUM(CW16:CX16) -> 6490 | CZ16: 6490 | DA16: =+CY16-CZ16 -> 0 | DC16: =+CT16+CY16 -> 71390 | DD16: =+CU16+CZ16 -> 71390 | DE16: =+DC16-DD16 -> 0 | DF16: =IF(ISERROR(VLOOKUP($B16,'MRI Data'!$A:$P,DH$10+3,FALSE)),0,VLOOKUP($B16,'MRI Data'!$A:$P,DH$10+3,FALSE)) -> 6490 | DH16: =SUM(DF16:DG16) -> 6490 | DI16: 6490 | DJ16: =+DH16-DI16 -> 0 | DL16: =+DC16+DH16 -> 77880 | DM16: =+DD16+DI16 -> 77880 | DN16: =+DL16-DM16 -> 0 | DQ16: =+DM16 -> 77880 | DR16: 0
A17: =+A16+1 -> 4 | B17: 621201-000005 | C17: Just Alterations | D17: 35217 | E17: 41243 | F17: Occupied | G17: 1032A | H17: 650 | I17: =HLOOKUP(I$10,M$10:DI$53,ROW()-9,FALSE) -> 3690.92 | K17: =IF(ISERROR(VLOOKUP($B17,'MRI Data'!$A:$P,M$10+3,FALSE)),0,VLOOKUP($B17,'MRI Data'!$A:$P,M$10+3,FALSE)) -> 3549 | M17: =SUM(K17:L17) -> 3549 | N17: 3549 | O17: =+M17-N17 -> 0 | Q17: =+M17 -> 3549 | R17: =+N17 -> 3549 | S17: =O17 -> 0 | T17: =IF(ISERROR(VLOOKUP($B17,'MRI Data'!$A:$P,V$10+3,FALSE)),0,VLOOKUP($B17,'MRI Data'!$A:$P,V$10+3,FALSE)) -> 3549 | V17: =SUM(T17:U17) -> 3549 | W17: 3549 | X17: =+V17-W17 -> 0 | Z17: =+Q17+V17 -> 7098 | AA17: =+R17+W17 -> 7098 | AB17: =+Z17-AA17 -> 0 | AC17: =IF(ISERROR(VLOOKUP($B17,'MRI Data'!$A:$P,AE$10+3,FALSE)),0,VLOOKUP($B17,'MRI Data'!$A:$P,AE$10+3,FALSE)) -> 3549 | AE17: =SUM(AC17:AD17) -> 3549 | AF17: 3549 | AG17: =+AE17-AF17 -> 0 | AI17: =+Z17+AE17 -> 10647 | AJ17: =+AA17+AF17 -> 10647 | AK17: =+AI17-AJ17 -> 0 | AL17: =IF(ISERROR(VLOOKUP($B17,'MRI Data'!$A:$P,AN$10+3,FALSE)),0,VLOOKUP($B17,'MRI Data'!$A:$P,AN$10+3,FALSE)) -> 3549 | AN17: =SUM(AL17:AM17) -> 3549 | AO17: 3549 | AP17: =+AN17-AO17 -> 0 | AR17: =+AI17+AN17 -> 14196 | AS17: =+AJ17+AO17 -> 14196 | AT17: =+AR17-AS17 -> 0 | AU17: =IF(ISERROR(VLOOKUP($B17,'MRI Data'!$A:$P,AW$10+3,FALSE)),0,VLOOKUP($B17,'MRI Data'!$A:$P,AW$10+3,FALSE)) -> 3549 | AW17: =SUM(AU17:AV17) -> 3549 | AX17: 3549 | AY17: =+AW17-AX17 -> 0 | BA17: =+AR17+AW17 -> 17745 | BB17: =+AS17+AX17 -> 17745 | BC17: =+BA17-BB17 -> 0 | BD17: =IF(ISERROR(VLOOKUP($B17,'MRI Data'!$A:$P,BF$10+3,FALSE)),0,VLOOKUP($B17,'MRI Data'!$A:$P,BF$10+3,FALSE)) -> 3690.92 | BF17: =SUM(BD17:BE17) -> 3690.92 | BG17: 3691 | BH17: =+BF17-BG17 -> -0.08 | BJ17: =+BA17+BF17 -> 21435.92 | BK17: =+BB17+BG17 -> 21436 | BL17: =+BJ17-BK17 -> -0.08 | BM17: =IF(ISERROR(VLOOKUP($B17,'MRI Data'!$A:$P,BO$10+3,FALSE)),0,VLOOKUP($B17,'MRI Data'!$A:$P,BO$10+3,FALSE)) -> 3690.92 | BO17: =SUM(BM17:BN17) -> 3690.92 | BP17: 3691 | BQ17: =+BO17-BP17 -> -0.08 | BS17: =+BJ17+BO17 -> 25126.84 | BT17: =+BK17+BP17 -> 25127 | BU17: =+BS17-BT17 -> -0.16 | BV17: =IF(ISERROR(VLOOKUP($B17,'MRI Data'!$A:$P,BX$10+3,FALSE)),0,VLOOKUP($B17,'MRI Data'!$A:$P,BX$10+3,FALSE)) -> 3690.92 | BX17: =SUM(BV17:BW17) -> 3690.92 | BY17: 3691 | BZ17: =+BX17-BY17 -> -0.08 | CB17: =+BS17+BX17 -> 28817.76 | CC17: =+BT17+BY17 -> 28818 | CD17: =+CB17-CC17 -> -0.24 | CE17: =IF(ISERROR(VLOOKUP($B17,'MRI Data'!$A:$P,CG$10+3,FALSE)),0,VLOOKUP($B17,'MRI Data'!$A:$P,CG$10+3,FALSE)) -> 3690.92 | CG17: =SUM(CE17:CF17) -> 3690.92 | CH17: 3691 | CI17: =+CG17-CH17 -> -0.08 | CK17: =+CB17+CG17 -> 32508.68 | CL17: =+CC17+CH17 -> 32509 | CM17: =+CK17-CL17 -> -0.32 | CN17: =IF(ISERROR(VLOOKUP($B17,'MRI Data'!$A:$P,CP$10+3,FALSE)),0,VLOOKUP($B17,'MRI Data'!$A:$P,CP$10+3,FALSE)) -> 3690.92 | CP17: =SUM(CN17:CO17) -> 3690.92 | CQ17: 3691 | CR17: =+CP17-CQ17 -> -0.08 | CT17: =+CK17+CP17 -> 36199.6 | CU17: =+CL17+CQ17 -> 36200 | CV17: =+CT17-CU17 -> -0.4 | CW17: =IF(ISERROR(VLOOKUP($B17,'MRI Data'!$A:$P,CY$10+3,FALSE)),0,VLOOKUP($B17,'MRI Data'!$A:$P,CY$10+3,FALSE)) -> 3690.92 | CY17: =SUM(CW17:CX17) -> 3690.92 | CZ17: 3691 | DA17: =+CY17-CZ17 -> -0.08 | DC17: =+CT17+CY17 -> 39890.52 | DD17: =+CU17+CZ17 -> 39891 | DE17: =+DC17-DD17 -> -0.48 | DF17: =IF(ISERROR(VLOOKUP($B17,'MRI Data'!$A:$P,DH$10+3,FALSE)),0,VLOOKUP($B17,'MRI Data'!$A:$P,DH$10+3,FALSE)) -> 3690.92 | DH17: =SUM(DF17:DG17) -> 3690.92 | DI17: 3691 | DJ17: =+DH17-DI17 -> -0.08 | DL17: =+DC17+DH17 -> 43581.44 | DM17: =+DD17+DI17 -> 43582 | DN17: =+DL17-DM17 -> -0.56 | DQ17: =+DM17 -> 43582 | DR17: 0
A18: =+A17+1 -> 5 | B18: 621201-000006 | C18: Pacific Coast Floral | D18: 33574 | E18: 41090 | F18: Occupied | G18: 1072 | H18: 1080 | I18: =HLOOKUP(I$10,M$10:DI$53,ROW()-9,FALSE) -> 4825.85 | K18: =IF(ISERROR(VLOOKUP($B18,'MRI Data'!$A:$P,M$10+3,FALSE)),0,VLOOKUP($B18,'MRI Data'!$A:$P,M$10+3,FALSE)) -> 4554.24 | M18: =SUM(K18:L18) -> 4554.24 | N18: 4860 | O18: =+M18-N18 -> -305.76 | Q18: =+M18 -> 4554.24 | R18: =+N18 -> 4860 | S18: =O18 -> -305.76 | T18: =IF(ISERROR(VLOOKUP($B18,'MRI Data'!$A:$P,V$10+3,FALSE)),0,VLOOKUP($B18,'MRI Data'!$A:$P,V$10+3,FALSE)) -> 4860 | V18: =SUM(T18:U18) -> 4860 | W18: 4860 | X18: =+V18-W18 -> 0 | Z18: =+Q18+V18 -> 9414.24 | AA18: =+R18+W18 -> 9720 | AB18: =+Z18-AA18 -> -305.76 | AC18: =IF(ISERROR(VLOOKUP($B18,'MRI Data'!$A:$P,AE$10+3,FALSE)),0,VLOOKUP($B18,'MRI Data'!$A:$P,AE$10+3,FALSE)) -> 4860 | AE18: =SUM(AC18:AD18) -> 4860 | AF18: 4860 | AG18: =+AE18-AF18 -> 0 | AI18: =+Z18+AE18 -> 14274.24 | AJ18: =+AA18+AF18 -> 14580 | AK18: =+AI18-AJ18 -> -305.76 | AL18: =IF(ISERROR(VLOOKUP($B18,'MRI Data'!$A:$P,AN$10+3,FALSE)),0,VLOOKUP($B18,'MRI Data'!$A:$P,AN$10+3,FALSE)) -> 4860 | AN18: =SUM(AL18:AM18) -> 4860 | AO18: 4860 | AP18: =+AN18-AO18 -> 0 | AR18: =+AI18+AN18 -> 19134.24 | AS18: =+AJ18+AO18 -> 19440 | AT18: =+AR18-AS18 -> -305.76 | AU18: =IF(ISERROR(VLOOKUP($B18,'MRI Data'!$A:$P,AW$10+3,FALSE)),0,VLOOKUP($B18,'MRI Data'!$A:$P,AW$10+3,FALSE)) -> 4860 | AV18: =-12150+6075 -> -6075 | AW18: =SUM(AU18:AV18) -> -1215 | AX18: 4860 | AY18: =+AW18-AX18 -> -6075 | BA18: =+AR18+AW18 -> 17919.24 | BB18: =+AS18+AX18 -> 24300 | BC18: =+BA18-BB18 -> -6380.76 | BD18: =IF(ISERROR(VLOOKUP($B18,'MRI Data'!$A:$P,BF$10+3,FALSE)),0,VLOOKUP($B18,'MRI Data'!$A:$P,BF$10+3,FALSE)) -> -9720 | BE18: 18711 | BF18: =SUM(BD18:BE18) -> 8991 | BG18: 4860 | BH18: =+BF18-BG18 -> 4131 | BJ18: =+BA18+BF18 -> 26910.24 | BK18: =+BB18+BG18 -> 29160 | BL18: =+BJ18-BK18 -> -2249.76 | BM18: =IF(ISERROR(VLOOKUP($B18,'MRI Data'!$A:$P,BO$10+3,FALSE)),0,VLOOKUP($B18,'MRI Data'!$A:$P,BO$10+3,FALSE)) -> 4860 | BN18: 0 | BO18: =SUM(BM18:BN18) -> 4860 | BP18: 4860 | BQ18: =+BO18-BP18 -> 0 | BS18: =+BJ18+BO18 -> 31770.24 | BT18: =+BK18+BP18 -> 34020 | BU18: =+BS18-BT18 -> -2249.76 | BV18: =IF(ISERROR(VLOOKUP($B18,'MRI Data'!$A:$P,BX$10+3,FALSE)),0,VLOOKUP($B18,'MRI Data'!$A:$P,BX$10+3,FALSE)) -> 4860 | BW18: 0 | BX18: =SUM(BV18:BW18) -> 4860 | BY18: 4860 | BZ18: =+BX18-BY18 -> 0 | CB18: =+BS18+BX18 -> 36630.24 | CC18: =+BT18+BY18 -> 38880 | CD18: =+CB18-CC18 -> -2249.76 | CE18: =IF(ISERROR(VLOOKUP($B18,'MRI Data'!$A:$P,CG$10+3,FALSE)),0,VLOOKUP($B18,'MRI Data'!$A:$P,CG$10+3,FALSE)) -> 4860 | CF18: 0 | CG18: =SUM(CE18:CF18) -> 4860 | CH18: 4860 | CI18: =+CG18-CH18 -> 0 | CK18: =+CB18+CG18 -> 41490.24 | CL18: =+CC18+CH18 -> 43740 | CM18: =+CK18-CL18 -> -2249.76 | CN18: =IF(ISERROR(VLOOKUP($B18,'MRI Data'!$A:$P,CP$10+3,FALSE)),0,VLOOKUP($B18,'MRI Data'!$A:$P,CP$10+3,FALSE)) -> -980.2 | CO18: 2920.1 | CP18: =SUM(CN18:CO18) -> 1939.9 | CQ18: 4860 | CR18: =+CP18-CQ18 -> -2920.1 | CT18: =+CK18+CP18 -> 43430.14 | CU18: =+CL18+CQ18 -> 48600 | CV18: =+CT18-CU18 -> -5169.86 | CW18: =IF(ISERROR(VLOOKUP($B18,'MRI Data'!$A:$P,CY$10+3,FALSE)),0,VLOOKUP($B18,'MRI Data'!$A:$P,CY$10+3,FALSE)) -> 3492.4 | CX18: =-2920.1+3603.9 -> 683.8 | CY18: =SUM(CW18:CX18) -> 4176.2 | CZ18: 4860 | DA18: =+CY18-CZ18 -> -683.8 | DC18: =+CT18+CY18 -> 47606.34 | DD18: =+CU18+CZ18 -> 53460 | DE18: =+DC18-DD18 -> -5853.66 | DF18: =IF(ISERROR(VLOOKUP($B18,'MRI Data'!$A:$P,DH$10+3,FALSE)),0,VLOOKUP($B18,'MRI Data'!$A:$P,DH$10+3,FALSE)) -> 5174.2 | DG18: =-3603.9+3255.55 -> -348.35 | DH18: =SUM(DF18:DG18) -> 4825.85 | DI18: 4860 | DJ18: =+DH18-DI18 -> -34.15 | DL18: =+DC18+DH18 -> 52432.19 | DM18: =+DD18+DI18 -> 58320 | DN18: =+DL18-DM18 -> -5887.81 | DO18: Tenant on rent relief 7/09-12/09 pay greater of 10% of sales or 50% of base rent. TT security deposit $5,346 was applied to the Deferral amount. TT repay 1/2 of the deferral amount in a promissory note. TT rent relief extended 01/10-6/10 pay greater of 20% of sales or 50% of base rent. TT repay 1/2 of the deferral amount in a promissory note. | DQ18: =+DM18 -> 58320 | DR18: -5888 | DS18: Tenant on rent relief 7/09-12/09 pay greater of 10% of sales or 50% of base rent. TT security deposit $5,346 was applied to the Deferral amount. TT repay 1/2 of the deferral amount in a promissory note. TT rent relief extended 01/10-6/10 pay greater of 20% of sales or 50% of base rent. TT repay 1/2 of the deferral amount in a promissory note.
A19: =+A18+1 -> 6 | B19: 621201-000008 | C19: Photo Lab - The | D19: 35217 | E19: 41060 | F19: Occupied | G19: 1048 | H19: 900 | I19: =HLOOKUP(I$10,M$10:DI$53,ROW()-9,FALSE) -> -875 | K19: =IF(ISERROR(VLOOKUP($B19,'MRI Data'!$A:$P,M$10+3,FALSE)),0,VLOOKUP($B19,'MRI Data'!$A:$P,M$10+3,FALSE)) -> -2475 | L19: 4950 | M19: =SUM(K19:L19) -> 2475 | N19: 4950 | O19: =+M19-N19 -> -2475 | Q19: =+M19 -> 2475 | R19: =+N19 -> 4950 | S19: =O19 -> -2475 | T19: =IF(ISERROR(VLOOKUP($B19,'MRI Data'!$A:$P,V$10+3,FALSE)),0,VLOOKUP($B19,'MRI Data'!$A:$P,V$10+3,FALSE)) -> 2475 | V19: =SUM(T19:U19) -> 2475 | W19: 4950 | X19: =+V19-W19 -> -2475 | Z19: =+Q19+V19 -> 4950 | AA19: =+R19+W19 -> 9900 | AB19: =+Z19-AA19 -> -4950 | AC19: =IF(ISERROR(VLOOKUP($B19,'MRI Data'!$A:$P,AE$10+3,FALSE)),0,VLOOKUP($B19,'MRI Data'!$A:$P,AE$10+3,FALSE)) -> 2475 | AE19: =SUM(AC19:AD19) -> 2475 | AF19: 4950 | AG19: =+AE19-AF19 -> -2475 | AI19: =+Z19+AE19 -> 7425 | AJ19: =+AA19+AF19 -> 14850 | AK19: =+AI19-AJ19 -> -7425 | AL19: =IF(ISERROR(VLOOKUP($B19,'MRI Data'!$A:$P,AN$10+3,FALSE)),0,VLOOKUP($B19,'MRI Data'!$A:$P,AN$10+3,FALSE)) -> 2475 | AN19: =SUM(AL19:AM19) -> 2475 | AO19: 4950 | AP19: =+AN19-AO19 -> -2475 | AR19: =+AI19+AN19 -> 9900 | AS19: =+AJ19+AO19 -> 19800 | AT19: =+AR19-AS19 -> -9900 | AU19: =IF(ISERROR(VLOOKUP($B19,'MRI Data'!$A:$P,AW$10+3,FALSE)),0,VLOOKUP($B19,'MRI Data'!$A:$P,AW$10+3,FALSE)) -> 2475 | AW19: =SUM(AU19:AV19) -> 2475 | AX19: 4950 | AY19: =+AW19-AX19 -> -2475 | BA19: =+AR19+AW19 -> 12375 | BB19: =+AS19+AX19 -> 24750 | BC19: =+BA19-BB19 -> -12375 | BD19: =IF(ISERROR(VLOOKUP($B19,'MRI Data'!$A:$P,BF$10+3,FALSE)),0,VLOOKUP($B19,'MRI Data'!$A:$P,BF$10+3,FALSE)) -> 2659.39 | BF19: =SUM(BD19:BE19) -> 2659.39 | BG19: 4950 | BH19: =+BF19-BG19 -> -2290.61 | BJ19: =+BA19+BF19 -> 15034.39 | BK19: =+BB19+BG19 -> 29700 | BL19: =+BJ19-BK19 -> -14665.61 | BM19: =IF(ISERROR(VLOOKUP($B19,'MRI Data'!$A:$P,BO$10+3,FALSE)),0,VLOOKUP($B19,'MRI Data'!$A:$P,BO$10+3,FALSE)) -> 4950 | BN19: 2771.57 | BO19: =SUM(BM19:BN19) -> 7721.57 | BP19: 4950 | BQ19: =+BO19-BP19 -> 2771.57 | BS19: =+BJ19+BO19 -> 22755.96 | BT19: =+BK19+BP19 -> 34650 | BU19: =+BS19-BT19 -> -11894.04 | BV19: =IF(ISERROR(VLOOKUP($B19,'MRI Data'!$A:$P,BX$10+3,FALSE)),0,VLOOKUP($B19,'MRI Data'!$A:$P,BX$10+3,FALSE)) -> 7721.57 | BW19: =-2772 -> -2772 | BX19: =SUM(BV19:BW19) -> 4949.57 | BY19: 4950 | BZ19: =+BX19-BY19 -> -0.43 | CB19: =+BS19+BX19 -> 27705.53 | CC19: =+BT19+BY19 -> 39600 | CD19: =+CB19-CC19 -> -11894.47 | CE19: =IF(ISERROR(VLOOKUP($B19,'MRI Data'!$A:$P,CG$10+3,FALSE)),0,VLOOKUP($B19,'MRI Data'!$A:$P,CG$10+3,FALSE)) -> 4950 | CF19: 0 | CG19: =SUM(CE19:CF19) -> 4950 | CH19: 4950 | CI19: =+CG19-CH19 -> 0 | CK19: =+CB19+CG19 -> 32655.53 | CL19: =+CC19+CH19 -> 44550 | CM19: =+CK19-CL19 -> -11894.47 | CN19: =IF(ISERROR(VLOOKUP($B19,'MRI Data'!$A:$P,CP$10+3,FALSE)),0,VLOOKUP($B19,'MRI Data'!$A:$P,CP$10+3,FALSE)) -> 4950 | CO19: 0 | CP19: =SUM(CN19:CO19) -> 4950 | CQ19: 4950 | CR19: =+CP19-CQ19 -> 0 | CT19: =+CK19+CP19 -> 37605.53 | CU19: =+CL19+CQ19 -> 49500 | CV19: =+CT19-CU19 -> -11894.47 | CW19: =IF(ISERROR(VLOOKUP($B19,'MRI Data'!$A:$P,CY$10+3,FALSE)),0,VLOOKUP($B19,'MRI Data'!$A:$P,CY$10+3,FALSE)) -> 4950 | CX19: 0 | CY19: =SUM(CW19:CX19) -> 4950 | CZ19: 4950 | DA19: =+CY19-CZ19 -> 0 | DC19: =+CT19+CY19 -> 42555.53 | DD19: =+CU19+CZ19 -> 54450 | DE19: =+DC19-DD19 -> -11894.47 | DF19: =IF(ISERROR(VLOOKUP($B19,'MRI Data'!$A:$P,DH$10+3,FALSE)),0,VLOOKUP($B19,'MRI Data'!$A:$P,DH$10+3,FALSE)) -> -4875 | DG19: 4000 | DH19: =SUM(DF19:DG19) -> -875 | DI19: 5100 | DJ19: =+DH19-DI19 -> -5975 | DL19: =+DC19+DH19 -> 41680.53 | DM19: =+DD19+DI19 -> 59550 | DN19: =+DL19-DM19 -> -17869.47 | DO19: Tenant on rent relief 5/09-12/09 pay the greater of 10% of sales or 50% of base rent. Per 6th Amendment dated 5/14/10, tenant on rent relief 3/10-9/10 pay the greater of 15% of sales or 50% of base rent. Retained SD $4K. | DQ19: =+DM19 -> 59550 | DR19: -17869 | DS19: Tenant on rent relief 5/09-12/09 pay the greater of 10% of sales or 50% of base rent. Per 6th Amendment dated 5/14/10, tenant on rent relief 3/10-9/10 pay the greater of 15% of sales or 50% of base rent. Retained SD $4K.
A20: =+A19+1 -> 7 | B20: 621201-S44199 | C20: Salon "L" | D20: 37838 | E20: 40786 | F20: Occupied | G20: 1040 | H20: 1500 | I20: =HLOOKUP(I$10,M$10:DI$53,ROW()-9,FALSE) -> 6468.75 | K20: =IF(ISERROR(VLOOKUP($B20,'MRI Data'!$A:$P,M$10+3,FALSE)),0,VLOOKUP($B20,'MRI Data'!$A:$P,M$10+3,FALSE)) -> 6250 | M20: =SUM(K20:L20) -> 6250 | N20: 6250 | O20: =+M20-N20 -> 0 | Q20: =+M20 -> 6250 | R20: =+N20 -> 6250 | S20: =O20 -> 0 | T20: =IF(ISERROR(VLOOKUP($B20,'MRI Data'!$A:$P,V$10+3,FALSE)),0,VLOOKUP($B20,'MRI Data'!$A:$P,V$10+3,FALSE)) -> 6250 | V20: =SUM(T20:U20) -> 6250 | W20: 6250 | X20: =+V20-W20 -> 0 | Z20: =+Q20+V20 -> 12500 | AA20: =+R20+W20 -> 12500 | AB20: =+Z20-AA20 -> 0 | AC20: =IF(ISERROR(VLOOKUP($B20,'MRI Data'!$A:$P,AE$10+3,FALSE)),0,VLOOKUP($B20,'MRI Data'!$A:$P,AE$10+3,FALSE)) -> 6468.75 | AE20: =SUM(AC20:AD20) -> 6468.75 | AF20: 6469 | AG20: =+AE20-AF20 -> -0.25 | AI20: =+Z20+AE20 -> 18968.75 | AJ20: =+AA20+AF20 -> 18969 | AK20: =+AI20-AJ20 -> -0.25 | AL20: =IF(ISERROR(VLOOKUP($B20,'MRI Data'!$A:$P,AN$10+3,FALSE)),0,VLOOKUP($B20,'MRI Data'!$A:$P,AN$10+3,FALSE)) -> 6468.75 | AN20: =SUM(AL20:AM20) -> 6468.75 | AO20: 6469 | AP20: =+AN20-AO20 -> -0.25 | AR20: =+AI20+AN20 -> 25437.5 | AS20: =+AJ20+AO20 -> 25438 | AT20: =+AR20-AS20 -> -0.5 | AU20: =IF(ISERROR(VLOOKUP($B20,'MRI Data'!$A:$P,AW$10+3,FALSE)),0,VLOOKUP($B20,'MRI Data'!$A:$P,AW$10+3,FALSE)) -> 6468.75 | AV20: =-12828.13+1737.62 -> -11090.51 | AW20: =SUM(AU20:AV20) -> -4621.76 | AX20: 6469 | AY20: =+AW20-AX20 -> -11090.76 | BA20: =+AR20+AW20 -> 20815.74 | BB20: =+AS20+AX20 -> 31907 | BC20: =+BA20-BB20 -> -11091.26 | BD20: =IF(ISERROR(VLOOKUP($B20,'MRI Data'!$A:$P,BF$10+3,FALSE)),0,VLOOKUP($B20,'MRI Data'!$A:$P,BF$10+3,FALSE)) -> -8640.5 | BE20: 26200 | BF20: =SUM(BD20:BE20) -> 17559.5 | BG20: 6469 | BH20: =+BF20-BG20 -> 11090.5 | BJ20: =+BA20+BF20 -> 38375.24 | BK20: =+BB20+BG20 -> 38376 | BL20: =+BJ20-BK20 -> -0.76 | BM20: =IF(ISERROR(VLOOKUP($B20,'MRI Data'!$A:$P,BO$10+3,FALSE)),0,VLOOKUP($B20,'MRI Data'!$A:$P,BO$10+3,FALSE)) -> 6250 | BN20: 219 | BO20: =SUM(BM20:BN20) -> 6469 | BP20: 6469 | BQ20: =+BO20-BP20 -> 0 | BS20: =+BJ20+BO20 -> 44844.24 | BT20: =+BK20+BP20 -> 44845 | BU20: =+BS20-BT20 -> -0.76 | BV20: =IF(ISERROR(VLOOKUP($B20,'MRI Data'!$A:$P,BX$10+3,FALSE)),0,VLOOKUP($B20,'MRI Data'!$A:$P,BX$10+3,FALSE)) -> 7794.17 | BW20: -1325 | BX20: =SUM(BV20:BW20) -> 6469.17 | BY20: 6469 | BZ20: =+BX20-BY20 -> 0.17 | CB20: =+BS20+BX20 -> 51313.41 | CC20: =+BT20+BY20 -> 51314 | CD20: =+CB20-CC20 -> -0.59 | CE20: =IF(ISERROR(VLOOKUP($B20,'MRI Data'!$A:$P,CG$10+3,FALSE)),0,VLOOKUP($B20,'MRI Data'!$A:$P,CG$10+3,FALSE)) -> 6250 | CF20: =219 -> 219 | CG20: =SUM(CE20:CF20) -> 6469 | CH20: 6469 | CI20: =+CG20-CH20 -> 0 | CK20: =+CB20+CG20 -> 57782.41 | CL20: =+CC20+CH20 -> 57783 | CM20: =+CK20-CL20 -> -0.59 | CN20: =IF(ISERROR(VLOOKUP($B20,'MRI Data'!$A:$P,CP$10+3,FALSE)),0,VLOOKUP($B20,'MRI Data'!$A:$P,CP$10+3,FALSE)) -> 6250 | CO20: =219 -> 219 | CP20: =SUM(CN20:CO20) -> 6469 | CQ20: 6469 | CR20: =+CP20-CQ20 -> 0 | CT20: =+CK20+CP20 -> 64251.41 | CU20: =+CL20+CQ20 -> 64252 | CV20: =+CT20-CU20 -> -0.59 | CW20: =IF(ISERROR(VLOOKUP($B20,'MRI Data'!$A:$P,CY$10+3,FALSE)),0,VLOOKUP($B20,'MRI Data'!$A:$P,CY$10+3,FALSE)) -> 6250 | CX20: 218.75 | CY20: =SUM(CW20:CX20) -> 6468.75 | CZ20: 6469 | DA20: =+CY20-CZ20 -> -0.25 | DC20: =+CT20+CY20 -> 70720.16 | DD20: =+CU20+CZ20 -> 70721 | DE20: =+DC20-DD20 -> -0.84 | DF20: =IF(ISERROR(VLOOKUP($B20,'MRI Data'!$A:$P,DH$10+3,FALSE)),0,VLOOKUP($B20,'MRI Data'!$A:$P,DH$10+3,FALSE)) -> 6250 | DG20: 218.75 | DH20: =SUM(DF20:DG20) -> 6468.75 | DI20: 6469 | DJ20: =+DH20-DI20 -> -0.25 | DL20: =+DC20+DH20 -> 77188.91 | DM20: =+DD20+DI20 -> 77190 | DN20: =+DL20-DM20 -> -1.09 | DO20: Tenant on rent relief 8/09-12/09 pay greater of 10% of sales or 50% of base rent. TT repay the deferral amount in a promissory note. | DQ20: =+DM20 -> 77190 | DR20: 0
A21: =+A20+1 -> 8 | B21: 621201-000007 | C21: Sapori Restaurant Italiano | D21: 32674 | E21: 42735 | F21: Occupied | G21: 1080 | H21: 2742 | I21: =HLOOKUP(I$10,M$10:DI$53,ROW()-9,FALSE) -> 11425 | K21: =IF(ISERROR(VLOOKUP($B21,'MRI Data'!$A:$P,M$10+3,FALSE)),0,VLOOKUP($B21,'MRI Data'!$A:$P,M$10+3,FALSE)) -> 12770.87 | M21: =SUM(K21:L21) -> 12770.87 | N21: 12771 | O21: =+M21-N21 -> -0.13 | Q21: =+M21 -> 12770.87 | R21: =+N21 -> 12771 | S21: =O21 -> -0.13 | T21: =IF(ISERROR(VLOOKUP($B21,'MRI Data'!$A:$P,V$10+3,FALSE)),0,VLOOKUP($B21,'MRI Data'!$A:$P,V$10+3,FALSE)) -> 12770.87 | V21: =SUM(T21:U21) -> 12770.87 | W21: 12771 | X21: =+V21-W21 -> -0.13 | Z21: =+Q21+V21 -> 25541.74 | AA21: =+R21+W21 -> 25542 | AB21: =+Z21-AA21 -> -0.26 | AC21: =IF(ISERROR(VLOOKUP($B21,'MRI Data'!$A:$P,AE$10+3,FALSE)),0,VLOOKUP($B21,'MRI Data'!$A:$P,AE$10+3,FALSE)) -> 12770.87 | AE21: =SUM(AC21:AD21) -> 12770.87 | AF21: 12771 | AG21: =+AE21-AF21 -> -0.13 | AI21: =+Z21+AE21 -> 38312.61 | AJ21: =+AA21+AF21 -> 38313 | AK21: =+AI21-AJ21 -> -0.39 | AL21: =IF(ISERROR(VLOOKUP($B21,'MRI Data'!$A:$P,AN$10+3,FALSE)),0,VLOOKUP($B21,'MRI Data'!$A:$P,AN$10+3,FALSE)) -> 12770.87 | AN21: =SUM(AL21:AM21) -> 12770.87 | AO21: 12771 | AP21: =+AN21-AO21 -> -0.13 | AR21: =+AI21+AN21 -> 51083.48 | AS21: =+AJ21+AO21 -> 51084 | AT21: =+AR21-AS21 -> -0.52 | AU21: =IF(ISERROR(VLOOKUP($B21,'MRI Data'!$A:$P,AW$10+3,FALSE)),0,VLOOKUP($B21,'MRI Data'!$A:$P,AW$10+3,FALSE)) -> 12770.87 | AW21: =SUM(AU21:AV21) -> 12770.87 | AX21: 12771 | AY21: =+AW21-AX21 -> -0.13 | BA21: =+AR21+AW21 -> 63854.35 | BB21: =+AS21+AX21 -> 63855 | BC21: =+BA21-BB21 -> -0.65 | BD21: =IF(ISERROR(VLOOKUP($B21,'MRI Data'!$A:$P,BF$10+3,FALSE)),0,VLOOKUP($B21,'MRI Data'!$A:$P,BF$10+3,FALSE)) -> 12770.87 | BF21: =SUM(BD21:BE21) -> 12770.87 | BG21: 12771 | BH21: =+BF21-BG21 -> -0.13 | BJ21: =+BA21+BF21 -> 76625.22 | BK21: =+BB21+BG21 -> 76626 | BL21: =+BJ21-BK21 -> -0.78 | BM21: =IF(ISERROR(VLOOKUP($B21,'MRI Data'!$A:$P,BO$10+3,FALSE)),0,VLOOKUP($B21,'MRI Data'!$A:$P,BO$10+3,FALSE)) -> 11425 | BO21: =SUM(BM21:BN21) -> 11425 | BP21: 12771 | BQ21: =+BO21-BP21 -> -1346 | BS21: =+BJ21+BO21 -> 88050.22 | BT21: =+BK21+BP21 -> 89397 | BU21: =+BS21-BT21 -> -1346.78 | BV21: =IF(ISERROR(VLOOKUP($B21,'MRI Data'!$A:$P,BX$10+3,FALSE)),0,VLOOKUP($B21,'MRI Data'!$A:$P,BX$10+3,FALSE)) -> 11425 | BX21: =SUM(BV21:BW21) -> 11425 | BY21: 12771 | BZ21: =+BX21-BY21 -> -1346 | CB21: =+BS21+BX21 -> 99475.22 | CC21: =+BT21+BY21 -> 102168 | CD21: =+CB21-CC21 -> -2692.78 | CE21: =IF(ISERROR(VLOOKUP($B21,'MRI Data'!$A:$P,CG$10+3,FALSE)),0,VLOOKUP($B21,'MRI Data'!$A:$P,CG$10+3,FALSE)) -> 11425 | CG21: =SUM(CE21:CF21) -> 11425 | CH21: 12771 | CI21: =+CG21-CH21 -> -1346 | CK21: =+CB21+CG21 -> 110900.22 | CL21: =+CC21+CH21 -> 114939 | CM21: =+CK21-CL21 -> -4038.78 | CN21: =IF(ISERROR(VLOOKUP($B21,'MRI Data'!$A:$P,CP$10+3,FALSE)),0,VLOOKUP($B21,'MRI Data'!$A:$P,CP$10+3,FALSE)) -> 11425 | CP21: =SUM(CN21:CO21) -> 11425 | CQ21: 12771 | CR21: =+CP21-CQ21 -> -1346 | CT21: =+CK21+CP21 -> 122325.22 | CU21: =+CL21+CQ21 -> 127710 | CV21: =+CT21-CU21 -> -5384.78 | CW21: =IF(ISERROR(VLOOKUP($B21,'MRI Data'!$A:$P,CY$10+3,FALSE)),0,VLOOKUP($B21,'MRI Data'!$A:$P,CY$10+3,FALSE)) -> 11425 | CY21: =SUM(CW21:CX21) -> 11425 | CZ21: 12771 | DA21: =+CY21-CZ21 -> -1346 | DC21: =+CT21+CY21 -> 133750.22 | DD21: =+CU21+CZ21 -> 140481 | DE21: =+DC21-DD21 -> -6730.78 | DF21: =IF(ISERROR(VLOOKUP($B21,'MRI Data'!$A:$P,DH$10+3,FALSE)),0,VLOOKUP($B21,'MRI Data'!$A:$P,DH$10+3,FALSE)) -> 11425 | DH21: =SUM(DF21:DG21) -> 11425 | DI21: 12771 | DJ21: =+DH21-DI21 -> -1346 | DL21: =+DC21+DH21 -> 145175.22 | DM21: =+DD21+DI21 -> 153252 | DN21: =+DL21-DM21 -> -8076.78 | DO21: Per 7th Amendment dated 10/13/09, tenant renewed eff 1/1/10 @ $50/sf vs. Plan @ $56/sf | DQ21: =+DM21 -> 153252 | DR21: =(11425-12771)*6 -> -8076 | DS21: Per 7th Amendment dated 10/13/09, tenant renewed eff 1/1/10 @ $50/sf vs. Plan @ $56/sf
A22: =+A21+1 -> 9 | C22: Sapori Restaurant Italiano-Patio | D22: 39234 | E22: 42735 | F22: Occupied | G22: 1080A | H22: 1309 | I22: =HLOOKUP(I$10,M$10:DI$53,ROW()-9,FALSE) -> 0.0001 | K22: =IF(ISERROR(VLOOKUP($B22,'MRI Data'!$A:$P,M$10+3,FALSE)),0,VLOOKUP($B22,'MRI Data'!$A:$P,M$10+3,FALSE)) -> 0 | L22: 0.0001 | M22: =SUM(K22:L22) -> 0.0001 | N22: 0 | O22: =+M22-N22 -> 0.0001 | Q22: =+M22 -> 0.0001 | R22: =+N22 -> 0 | S22: =O22 -> 0.0001 | T22: =IF(ISERROR(VLOOKUP($B22,'MRI Data'!$A:$P,V$10+3,FALSE)),0,VLOOKUP($B22,'MRI Data'!$A:$P,V$10+3,FALSE)) -> 0 | U22: 0.0001 | V22: =SUM(T22:U22) -> 0.0001 | W22: 0 | X22: =+V22-W22 -> 0.0001 | Z22: =+Q22+V22 -> 0.0002 | AA22: =+R22+W22 -> 0 | AB22: =+Z22-AA22 -> 0.0002 | AC22: =IF(ISERROR(VLOOKUP($B22,'MRI Data'!$A:$P,AE$10+3,FALSE)),0,VLOOKUP($B22,'MRI Data'!$A:$P,AE$10+3,FALSE)) -> 0 | AD22: 0.0001 | AE22: =SUM(AC22:AD22) -> 0.0001 | AF22: 0 | AG22: =+AE22-AF22 -> 0.0001 | AI22: =+Z22+AE22 -> 0.0003 | AJ22: =+AA22+AF22 -> 0 | AK22: =+AI22-AJ22 -> 0.0003 | AL22: =IF(ISERROR(VLOOKUP($B22,'MRI Data'!$A:$P,AN$10+3,FALSE)),0,VLOOKUP($B22,'MRI Data'!$A:$P,AN$10+3,FALSE)) -> 0 | AM22: 0.0001 | AN22: =SUM(AL22:AM22) -> 0.0001 | AO22: 0 | AP22: =+AN22-AO22 -> 0.0001 | AR22: =+AI22+AN22 -> 0.0004 | AS22: =+AJ22+AO22 -> 0 | AT22: =+AR22-AS22 -> 0.0004 | AU22: =IF(ISERROR(VLOOKUP($B22,'MRI Data'!$A:$P,AW$10+3,FALSE)),0,VLOOKUP($B22,'MRI Data'!$A:$P,AW$10+3,FALSE)) -> 0 | AV22: 0.0001 | AW22: =SUM(AU22:AV22) -> 0.0001 | AX22: 0 | AY22: =+AW22-AX22 -> 0.0001 | BA22: =+AR22+AW22 -> 0.0005 | BB22: =+AS22+AX22 -> 0 | BC22: =+BA22-BB22 -> 0.0005 | BD22: =IF(ISERROR(VLOOKUP($B22,'MRI Data'!$A:$P,BF$10+3,FALSE)),0,VLOOKUP($B22,'MRI Data'!$A:$P,BF$10+3,FALSE)) -> 0 | BE22: 0.0001 | BF22: =SUM(BD22:BE22) -> 0.0001 | BG22: 0 | BH22: =+BF22-BG22 -> 0.0001 | BJ22: =+BA22+BF22 -> 0.0006 | BK22: =+BB22+BG22 -> 0 | BL22: =+BJ22-BK22 -> 0.0006 | BM22: =IF(ISERROR(VLOOKUP($B22,'MRI Data'!$A:$P,BO$10+3,FALSE)),0,VLOOKUP($B22,'MRI Data'!$A:$P,BO$10+3,FALSE)) -> 0 | BN22: 0.0001 | BO22: =SUM(BM22:BN22) -> 0.0001 | BP22: 0 | BQ22: =+BO22-BP22 -> 0.0001 | BS22: =+BJ22+BO22 -> 0.0007 | BT22: =+BK22+BP22 -> 0 | BU22: =+BS22-BT22 -> 0.0007 | BV22: =IF(ISERROR(VLOOKUP($B22,'MRI Data'!$A:$P,BX$10+3,FALSE)),0,VLOOKUP($B22,'MRI Data'!$A:$P,BX$10+3,FALSE)) -> 0 | BW22: 0.0001 | BX22: =SUM(BV22:BW22) -> 0.0001 | BY22: 0 | BZ22: =+BX22-BY22 -> 0.0001 | CB22: =+BS22+BX22 -> 0.0008 | CC22: =+BT22+BY22 -> 0 | CD22: =+CB22-CC22 -> 0.0008 | CE22: =IF(ISERROR(VLOOKUP($B22,'MRI Data'!$A:$P,CG$10+3,FALSE)),0,VLOOKUP($B22,'MRI Data'!$A:$P,CG$10+3,FALSE)) -> 0 | CF22: 0.0001 | CG22: =SUM(CE22:CF22) -> 0.0001 | CH22: 0 | CI22: =+CG22-CH22 -> 0.0001 | CK22: =+CB22+CG22 -> 0.0009 | CL22: =+CC22+CH22 -> 0 | CM22: =+CK22-CL22 -> 0.0009 | CN22: =IF(ISERROR(VLOOKUP($B22,'MRI Data'!$A:$P,CP$10+3,FALSE)),0,VLOOKUP($B22,'MRI Data'!$A:$P,CP$10+3,FALSE)) -> 0 | CO22: 0.0001 | CP22: =SUM(CN22:CO22) -> 0.0001 | CQ22: 0 | CR22: =+CP22-CQ22 -> 0.0001 | CT22: =+CK22+CP22 -> 0.001 | CU22: =+CL22+CQ22 -> 0 | CV22: =+CT22-CU22 -> 0.001 | CW22: =IF(ISERROR(VLOOKUP($B22,'MRI Data'!$A:$P,CY$10+3,FALSE)),0,VLOOKUP($B22,'MRI Data'!$A:$P,CY$10+3,FALSE)) -> 0 | CX22: 0.0001 | CY22: =SUM(CW22:CX22) -> 0.0001 | CZ22: 0 | DA22: =+CY22-CZ22 -> 0.0001 | DC22: =+CT22+CY22 -> 0.0011 | DD22: =+CU22+CZ22 -> 0 | DE22: =+DC22-DD22 -> 0.0011 | DF22: =IF(ISERROR(VLOOKUP($B22,'MRI Data'!$A:$P,DH$10+3,FALSE)),0,VLOOKUP($B22,'MRI Data'!$A:$P,DH$10+3,FALSE)) -> 0 | DG22: 0.0001 | DH22: =SUM(DF22:DG22) -> 0.0001 | DI22: 0 | DJ22: =+DH22-DI22 -> 0.0001 | DL22: =+DC22+DH22 -> 0.0012 | DM22: =+DD22+DI22 -> 0 | DN22: =+DL22-DM22 -> 0.0012 | DQ22: =+DM22 -> 0 | DR22: 0
A23: =+A22+1 -> 10 | C23: Vacant | F23: Vacant | G23: 1024 | H23: 1200 | I23: =HLOOKUP(I$10,M$10:DI$53,ROW()-9,FALSE) -> 0 | K23: =IF(ISERROR(VLOOKUP($B23,'MRI Data'!$A:$P,M$10+3,FALSE)),0,VLOOKUP($B23,'MRI Data'!$A:$P,M$10+3,FALSE)) -> 0 | M23: =SUM(K23:L23) -> 0 | N23: 0 | O23: =+M23-N23 -> 0 | Q23: =+M23 -> 0 | R23: =+N23 -> 0 | S23: =O23 -> 0 | T23: =IF(ISERROR(VLOOKUP($B23,'MRI Data'!$A:$P,V$10+3,FALSE)),0,VLOOKUP($B23,'MRI Data'!$A:$P,V$10+3,FALSE)) -> 0 | V23: =SUM(T23:U23) -> 0 | W23: 0 | X23: =+V23-W23 -> 0 | Z23: =+Q23+V23 -> 0 | AA23: =+R23+W23 -> 0 | AB23: =+Z23-AA23 -> 0 | AC23: =IF(ISERROR(VLOOKUP($B23,'MRI Data'!$A:$P,AE$10+3,FALSE)),0,VLOOKUP($B23,'MRI Data'!$A:$P,AE$10+3,FALSE)) -> 0 | AE23: =SUM(AC23:AD23) -> 0 | AF23: 0 | AG23: =+AE23-AF23 -> 0 | AI23: =+Z23+AE23 -> 0 | AJ23: =+AA23+AF23 -> 0 | AK23: =+AI23-AJ23 -> 0 | AL23: =IF(ISERROR(VLOOKUP($B23,'MRI Data'!$A:$P,AN$10+3,FALSE)),0,VLOOKUP($B23,'MRI Data'!$A:$P,AN$10+3,FALSE)) -> 0 | AN23: =SUM(AL23:AM23) -> 0 | AO23: 0 | AP23: =+AN23-AO23 -> 0 | AR23: =+AI23+AN23 -> 0 | AS23: =+AJ23+AO23 -> 0 | AT23: =+AR23-AS23 -> 0 | AU23: =IF(ISERROR(VLOOKUP($B23,'MRI Data'!$A:$P,AW$10+3,FALSE)),0,VLOOKUP($B23,'MRI Data'!$A:$P,AW$10+3,FALSE)) -> 0 | AW23: =SUM(AU23:AV23) -> 0 | AX23: 0 | AY23: =+AW23-AX23 -> 0 | BA23: =+AR23+AW23 -> 0 | BB23: =+AS23+AX23 -> 0 | BC23: =+BA23-BB23 -> 0 | BD23: =IF(ISERROR(VLOOKUP($B23,'MRI Data'!$A:$P,BF$10+3,FALSE)),0,VLOOKUP($B23,'MRI Data'!$A:$P,BF$10+3,FALSE)) -> 0 | BF23: =SUM(BD23:BE23) -> 0 | BG23: 5500 | BH23: =+BF23-BG23 -> -5500 | BJ23: =+BA23+BF23 -> 0 | BK23: =+BB23+BG23 -> 5500 | BL23: =+BJ23-BK23 -> -5500 | BM23: =IF(ISERROR(VLOOKUP($B23,'MRI Data'!$A:$P,BO$10+3,FALSE)),0,VLOOKUP($B23,'MRI Data'!$A:$P,BO$10+3,FALSE)) -> 0 | BO23: =SUM(BM23:BN23) -> 0 | BP23: 5500 | BQ23: =+BO23-BP23 -> -5500 | BS23: =+BJ23+BO23 -> 0 | BT23: =+BK23+BP23 -> 11000 | BU23: =+BS23-BT23 -> -11000 | BV23: =IF(ISERROR(VLOOKUP($B23,'MRI Data'!$A:$P,BX$10+3,FALSE)),0,VLOOKUP($B23,'MRI Data'!$A:$P,BX$10+3,FALSE)) -> 0 | BX23: =SUM(BV23:BW23) -> 0 | BY23: 5500 | BZ23: =+BX23-BY23 -> -5500 | CB23: =+BS23+BX23 -> 0 | CC23: =+BT23+BY23 -> 16500 | CD23: =+CB23-CC23 -> -16500 | CE23: =IF(ISERROR(VLOOKUP($B23,'MRI Data'!$A:$P,CG$10+3,FALSE)),0,VLOOKUP($B23,'MRI Data'!$A:$P,CG$10+3,FALSE)) -> 0 | CG23: =SUM(CE23:CF23) -> 0 | CH23: 5500 | CI23: =+CG23-CH23 -> -5500 | CK23: =+CB23+CG23 -> 0 | CL23: =+CC23+CH23 -> 22000 | CM23: =+CK23-CL23 -> -22000 | CN23: =IF(ISERROR(VLOOKUP($B23,'MRI Data'!$A:$P,CP$10+3,FALSE)),0,VLOOKUP($B23,'MRI Data'!$A:$P,CP$10+3,FALSE)) -> 0 | CP23: =SUM(CN23:CO23) -> 0 | CQ23: 5500 | CR23: =+CP23-CQ23 -> -5500 | CT23: =+CK23+CP23 -> 0 | CU23: =+CL23+CQ23 -> 27500 | CV23: =+CT23-CU23 -> -27500 | CW23: =IF(ISERROR(VLOOKUP($B23,'MRI Data'!$A:$P,CY$10+3,FALSE)),0,VLOOKUP($B23,'MRI Data'!$A:$P,CY$10+3,FALSE)) -> 0 | CY23: =SUM(CW23:CX23) -> 0 | CZ23: 5500 | DA23: =+CY23-CZ23 -> -5500 | DC23: =+CT23+CY23 -> 0 | DD23: =+CU23+CZ23 -> 33000 | DE23: =+DC23-DD23 -> -33000 | DF23: =IF(ISERROR(VLOOKUP($B23,'MRI Data'!$A:$P,DH$10+3,FALSE)),0,VLOOKUP($B23,'MRI Data'!$A:$P,DH$10+3,FALSE)) -> 0 | DH23: =SUM(DF23:DG23) -> 0 | DI23: 5500 | DJ23: =+DH23-DI23 -> -5500 | DL23: =+DC23+DH23 -> 0 | DM23: =+DD23+DI23 -> 38500 | DN23: =+DL23-DM23 -> -38500 | DO23: Space vacant, planned for occupancy 12/09 | DQ23: =+DM23 -> 38500 | DR23: -38500 | DS23: Space vacant, planned for occupancy 12/09
A24: =+A23+1 -> 11 | I24: =HLOOKUP(I$10,M$10:DI$53,ROW()-9,FALSE) -> 0 | M24: =SUM(K24:L24) -> 0 | O24: =+M24-N24 -> 0 | Q24: =+M24 -> 0 | R24: =+N24 -> 0 | S24: =O24 -> 0 | V24: =SUM(T24:U24) -> 0 | X24: =+V24-W24 -> 0 | Z24: =+Q24+V24 -> 0 | AA24: =+R24+W24 -> 0 | AB24: =+Z24-AA24 -> 0 | AE24: =SUM(AC24:AD24) -> 0 | AG24: =+AE24-AF24 -> 0 | AI24: =+Z24+AE24 -> 0 | AJ24: =+AA24+AF24 -> 0 | AK24: =+AI24-AJ24 -> 0 | AN24: =SUM(AL24:AM24) -> 0 | AP24: =+AN24-AO24 -> 0 | AR24: =+AI24+AN24 -> 0 | AS24: =+AJ24+AO24 -> 0 | AT24: =+AR24-AS24 -> 0 | AW24: =SUM(AU24:AV24) -> 0 | AY24: =+AW24-AX24 -> 0 | BA24: =+AR24+AW24 -> 0 | BB24: =+AS24+AX24 -> 0 | BC24: =+BA24-BB24 -> 0 | BF24: =SUM(BD24:BE24) -> 0 | BH24: =+BF24-BG24 -> 0 | BJ24: =+BA24+BF24 -> 0 | BK24: =+BB24+BG24 -> 0 | BL24: =+BJ24-BK24 -> 0 | BO24: =SUM(BM24:BN24) -> 0 | BQ24: =+BO24-BP24 -> 0 | BS24: =+BJ24+BO24 -> 0 | BT24: =+BK24+BP24 -> 0 | BU24: =+BS24-BT24 -> 0 | BX24: =SUM(BV24:BW24) -> 0 | BZ24: =+BX24-BY24 -> 0 | CB24: =+BS24+BX24 -> 0 | CC24: =+BT24+BY24 -> 0 | CD24: =+CB24-CC24 -> 0 | CG24: =SUM(CE24:CF24) -> 0 | CI24: =+CG24-CH24 -> 0 | CK24: =+CB24+CG24 -> 0 | CL24: =+CC24+CH24 -> 0 | CM24: =+CK24-CL24 -> 0 | CP24: =SUM(CN24:CO24) -> 0 | CR24: =+CP24-CQ24 -> 0 | CT24: =+CK24+CP24 -> 0 | CU24: =+CL24+CQ24 -> 0 | CV24: =+CT24-CU24 -> 0 | CY24: =SUM(CW24:CX24) -> 0 | DA24: =+CY24-CZ24 -> 0 | DC24: =+CT24+CY24 -> 0 | DD24: =+CU24+CZ24 -> 0 | DE24: =+DC24-DD24 -> 0 | DH24: =SUM(DF24:DG24) -> 0 | DJ24: =+DH24-DI24 -> 0 | DL24: =+DC24+DH24 -> 0 | DM24: =+DD24+DI24 -> 0 | DN24: =+DL24-DM24 -> 0 | DQ24: =+DM24 -> 0 | DR24: 0
A25: =+A24+1 -> 12 | I25: =HLOOKUP(I$10,M$10:DI$53,ROW()-9,FALSE) -> 0 | M25: =SUM(K25:L25) -> 0 | O25: =+M25-N25 -> 0 | Q25: =+M25 -> 0 | R25: =+N25 -> 0 | S25: =O25 -> 0 | V25: =SUM(T25:U25) -> 0 | X25: =+V25-W25 -> 0 | Z25: =+Q25+V25 -> 0 | AA25: =+R25+W25 -> 0 | AB25: =+Z25-AA25 -> 0 | AE25: =SUM(AC25:AD25) -> 0 | AG25: =+AE25-AF25 -> 0 | AI25: =+Z25+AE25 -> 0 | AJ25: =+AA25+AF25 -> 0 | AK25: =+AI25-AJ25 -> 0 | AN25: =SUM(AL25:AM25) -> 0 | AP25: =+AN25-AO25 -> 0 | AR25: =+AI25+AN25 -> 0 | AS25: =+AJ25+AO25 -> 0 | AT25: =+AR25-AS25 -> 0 | AW25: =SUM(AU25:AV25) -> 0 | AY25: =+AW25-AX25 -> 0 | BA25: =+AR25+AW25 -> 0 | BB25: =+AS25+AX25 -> 0 | BC25: =+BA25-BB25 -> 0 | BF25: =SUM(BD25:BE25) -> 0 | BH25: =+BF25-BG25 -> 0 | BJ25: =+BA25+BF25 -> 0 | BK25: =+BB25+BG25 -> 0 | BL25: =+BJ25-BK25 -> 0 | BO25: =SUM(BM25:BN25) -> 0 | BQ25: =+BO25-BP25 -> 0 | BS25: =+BJ25+BO25 -> 0 | BT25: =+BK25+BP25 -> 0 | BU25: =+BS25-BT25 -> 0 | BX25: =SUM(BV25:BW25) -> 0 | BZ25: =+BX25-BY25 -> 0 | CB25: =+BS25+BX25 -> 0 | CC25: =+BT25+BY25 -> 0 | CD25: =+CB25-CC25 -> 0 | CG25: =SUM(CE25:CF25) -> 0 | CI25: =+CG25-CH25 -> 0 | CK25: =+CB25+CG25 -> 0 | CL25: =+CC25+CH25 -> 0 | CM25: =+CK25-CL25 -> 0 | CP25: =SUM(CN25:CO25) -> 0 | CR25: =+CP25-CQ25 -> 0 | CT25: =+CK25+CP25 -> 0 | CU25: =+CL25+CQ25 -> 0 | CV25: =+CT25-CU25 -> 0 | CY25: =SUM(CW25:CX25) -> 0 | DA25: =+CY25-CZ25 -> 0 | DC25: =+CT25+CY25 -> 0 | DD25: =+CU25+CZ25 -> 0 | DE25: =+DC25-DD25 -> 0 | DH25: =SUM(DF25:DG25) -> 0 | DJ25: =+DH25-DI25 -> 0 | DL25: =+DC25+DH25 -> 0 | DM25: =+DD25+DI25 -> 0 | DN25: =+DL25-DM25 -> 0 | DQ25: =+DM25 -> 0 | DR25: 0
A26: =+A25+1 -> 13 | I26: =HLOOKUP(I$10,M$10:DI$53,ROW()-9,FALSE) -> 0 | M26: =SUM(K26:L26) -> 0 | O26: =+M26-N26 -> 0 | Q26: =+M26 -> 0 | R26: =+N26 -> 0 | S26: =O26 -> 0 | V26: =SUM(T26:U26) -> 0 | X26: =+V26-W26 -> 0 | Z26: =+Q26+V26 -> 0 | AA26: =+R26+W26 -> 0 | AB26: =+Z26-AA26 -> 0 | AE26: =SUM(AC26:AD26) -> 0 | AG26: =+AE26-AF26 -> 0 | AI26: =+Z26+AE26 -> 0 | AJ26: =+AA26+AF26 -> 0 | AK26: =+AI26-AJ26 -> 0 | AN26: =SUM(AL26:AM26) -> 0 | AP26: =+AN26-AO26 -> 0 | AR26: =+AI26+AN26 -> 0 | AS26: =+AJ26+AO26 -> 0 | AT26: =+AR26-AS26 -> 0 | AW26: =SUM(AU26:AV26) -> 0 | AY26: =+AW26-AX26 -> 0 | BA26: =+AR26+AW26 -> 0 | BB26: =+AS26+AX26 -> 0 | BC26: =+BA26-BB26 -> 0 | BF26: =SUM(BD26:BE26) -> 0 | BH26: =+BF26-BG26 -> 0 | BJ26: =+BA26+BF26 -> 0 | BK26: =+BB26+BG26 -> 0 | BL26: =+BJ26-BK26 -> 0 | BO26: =SUM(BM26:BN26) -> 0 | BQ26: =+BO26-BP26 -> 0 | BS26: =+BJ26+BO26 -> 0 | BT26: =+BK26+BP26 -> 0 | BU26: =+BS26-BT26 -> 0 | BX26: =SUM(BV26:BW26) -> 0 | BZ26: =+BX26-BY26 -> 0 | CB26: =+BS26+BX26 -> 0 | CC26: =+BT26+BY26 -> 0 | CD26: =+CB26-CC26 -> 0 | CG26: =SUM(CE26:CF26) -> 0 | CI26: =+CG26-CH26 -> 0 | CK26: =+CB26+CG26 -> 0 | CL26: =+CC26+CH26 -> 0 | CM26: =+CK26-CL26 -> 0 | CP26: =SUM(CN26:CO26) -> 0 | CR26: =+CP26-CQ26 -> 0 | CT26: =+CK26+CP26 -> 0 | CU26: =+CL26+CQ26 -> 0 | CV26: =+CT26-CU26 -> 0 | CY26: =SUM(CW26:CX26) -> 0 | DA26: =+CY26-CZ26 -> 0 | DC26: =+CT26+CY26 -> 0 | DD26: =+CU26+CZ26 -> 0 | DE26: =+DC26-DD26 -> 0 | DH26: =SUM(DF26:DG26) -> 0 | DJ26: =+DH26-DI26 -> 0 | DL26: =+DC26+DH26 -> 0 | DM26: =+DD26+DI26 -> 0 | DN26: =+DL26-DM26 -> 0 | DQ26: =+DM26 -> 0 | DR26: 0
A27: =+A26+1 -> 14 | I27: =HLOOKUP(I$10,M$10:DI$53,ROW()-9,FALSE) -> 0 | M27: =SUM(K27:L27) -> 0 | O27: =+M27-N27 -> 0 | Q27: =+M27 -> 0 | R27: =+N27 -> 0 | S27: =O27 -> 0 | V27: =SUM(T27:U27) -> 0 | X27: =+V27-W27 -> 0 | Z27: =+Q27+V27 -> 0 | AA27: =+R27+W27 -> 0 | AB27: =+Z27-AA27 -> 0 | AE27: =SUM(AC27:AD27) -> 0 | AG27: =+AE27-AF27 -> 0 | AI27: =+Z27+AE27 -> 0 | AJ27: =+AA27+AF27 -> 0 | AK27: =+AI27-AJ27 -> 0 | AN27: =SUM(AL27:AM27) -> 0 | AP27: =+AN27-AO27 -> 0 | AR27: =+AI27+AN27 -> 0 | AS27: =+AJ27+AO27 -> 0 | AT27: =+AR27-AS27 -> 0 | AW27: =SUM(AU27:AV27) -> 0 | AY27: =+AW27-AX27 -> 0 | BA27: =+AR27+AW27 -> 0 | BB27: =+AS27+AX27 -> 0 | BC27: =+BA27-BB27 -> 0 | BF27: =SUM(BD27:BE27) -> 0 | BH27: =+BF27-BG27 -> 0 | BJ27: =+BA27+BF27 -> 0 | BK27: =+BB27+BG27 -> 0 | BL27: =+BJ27-BK27 -> 0 | BO27: =SUM(BM27:BN27) -> 0 | BQ27: =+BO27-BP27 -> 0 | BS27: =+BJ27+BO27 -> 0 | BT27: =+BK27+BP27 -> 0 | BU27: =+BS27-BT27 -> 0 | BX27: =SUM(BV27:BW27) -> 0 | BZ27: =+BX27-BY27 -> 0 | CB27: =+BS27+BX27 -> 0 | CC27: =+BT27+BY27 -> 0 | CD27: =+CB27-CC27 -> 0 | CG27: =SUM(CE27:CF27) -> 0 | CI27: =+CG27-CH27 -> 0 | CK27: =+CB27+CG27 -> 0 | CL27: =+CC27+CH27 -> 0 | CM27: =+CK27-CL27 -> 0 | CP27: =SUM(CN27:CO27) -> 0 | CR27: =+CP27-CQ27 -> 0 | CT27: =+CK27+CP27 -> 0 | CU27: =+CL27+CQ27 -> 0 | CV27: =+CT27-CU27 -> 0 | CY27: =SUM(CW27:CX27) -> 0 | DA27: =+CY27-CZ27 -> 0 | DC27: =+CT27+CY27 -> 0 | DD27: =+CU27+CZ27 -> 0 | DE27: =+DC27-DD27 -> 0 | DH27: =SUM(DF27:DG27) -> 0 | DJ27: =+DH27-DI27 -> 0 | DL27: =+DC27+DH27 -> 0 | DM27: =+DD27+DI27 -> 0 | DN27: =+DL27-DM27 -> 0 | DQ27: =+DM27 -> 0 | DR27: 0
A28: =+A27+1 -> 15 | I28: =HLOOKUP(I$10,M$10:DI$53,ROW()-9,FALSE) -> 0 | M28: =SUM(K28:L28) -> 0 | O28: =+M28-N28 -> 0 | Q28: =+M28 -> 0 | R28: =+N28 -> 0 | S28: =O28 -> 0 | V28: =SUM(T28:U28) -> 0 | X28: =+V28-W28 -> 0 | Z28: =+Q28+V28 -> 0 | AA28: =+R28+W28 -> 0 | AB28: =+Z28-AA28 -> 0 | AE28: =SUM(AC28:AD28) -> 0 | AG28: =+AE28-AF28 -> 0 | AI28: =+Z28+AE28 -> 0 | AJ28: =+AA28+AF28 -> 0 | AK28: =+AI28-AJ28 -> 0 | AN28: =SUM(AL28:AM28) -> 0 | AP28: =+AN28-AO28 -> 0 | AR28: =+AI28+AN28 -> 0 | AS28: =+AJ28+AO28 -> 0 | AT28: =+AR28-AS28 -> 0 | AW28: =SUM(AU28:AV28) -> 0 | AY28: =+AW28-AX28 -> 0 | BA28: =+AR28+AW28 -> 0 | BB28: =+AS28+AX28 -> 0 | BC28: =+BA28-BB28 -> 0 | BF28: =SUM(BD28:BE28) -> 0 | BH28: =+BF28-BG28 -> 0 | BJ28: =+BA28+BF28 -> 0 | BK28: =+BB28+BG28 -> 0 | BL28: =+BJ28-BK28 -> 0 | BO28: =SUM(BM28:BN28) -> 0 | BQ28: =+BO28-BP28 -> 0 | BS28: =+BJ28+BO28 -> 0 | BT28: =+BK28+BP28 -> 0 | BU28: =+BS28-BT28 -> 0 | BX28: =SUM(BV28:BW28) -> 0 | BZ28: =+BX28-BY28 -> 0 | CB28: =+BS28+BX28 -> 0 | CC28: =+BT28+BY28 -> 0 | CD28: =+CB28-CC28 -> 0 | CG28: =SUM(CE28:CF28) -> 0 | CI28: =+CG28-CH28 -> 0 | CK28: =+CB28+CG28 -> 0 | CL28: =+CC28+CH28 -> 0 | CM28: =+CK28-CL28 -> 0 | CP28: =SUM(CN28:CO28) -> 0 | CR28: =+CP28-CQ28 -> 0 | CT28: =+CK28+CP28 -> 0 | CU28: =+CL28+CQ28 -> 0 | CV28: =+CT28-CU28 -> 0 | CY28: =SUM(CW28:CX28) -> 0 | DA28: =+CY28-CZ28 -> 0 | DC28: =+CT28+CY28 -> 0 | DD28: =+CU28+CZ28 -> 0 | DE28: =+DC28-DD28 -> 0 | DH28: =SUM(DF28:DG28) -> 0 | DJ28: =+DH28-DI28 -> 0 | DL28: =+DC28+DH28 -> 0 | DM28: =+DD28+DI28 -> 0 | DN28: =+DL28-DM28 -> 0 | DQ28: =+DM28 -> 0
A29: =+A28+1 -> 16 | I29: =HLOOKUP(I$10,M$10:DI$53,ROW()-9,FALSE) -> 0 | M29: =SUM(K29:L29) -> 0 | O29: =+M29-N29 -> 0 | Q29: =+M29 -> 0 | R29: =+N29 -> 0 | V29: =SUM(T29:U29) -> 0 | X29: =+V29-W29 -> 0 | Z29: =+Q29+V29 -> 0 | AA29: =+R29+W29 -> 0 | AB29: =+Z29-AA29 -> 0 | AE29: =SUM(AC29:AD29) -> 0 | AG29: =+AE29-AF29 -> 0 | AI29: =+Z29+AE29 -> 0 | AJ29: =+AA29+AF29 -> 0 | AK29: =+AI29-AJ29 -> 0 | AN29: =SUM(AL29:AM29) -> 0 | AP29: =+AN29-AO29 -> 0 | AR29: =+AI29+AN29 -> 0 | AS29: =+AJ29+AO29 -> 0 | AT29: =+AR29-AS29 -> 0 | AW29: =SUM(AU29:AV29) -> 0 | AY29: =+AW29-AX29 -> 0 | BA29: =+AR29+AW29 -> 0 | BB29: =+AS29+AX29 -> 0 | BC29: =+BA29-BB29 -> 0 | BF29: =SUM(BD29:BE29) -> 0 | BH29: =+BF29-BG29 -> 0 | BJ29: =+BA29+BF29 -> 0 | BK29: =+BB29+BG29 -> 0 | BL29: =+BJ29-BK29 -> 0 | BO29: =SUM(BM29:BN29) -> 0 | BQ29: =+BO29-BP29 -> 0 | BS29: =+BJ29+BO29 -> 0 | BT29: =+BK29+BP29 -> 0 | BU29: =+BS29-BT29 -> 0 | BX29: =SUM(BV29:BW29) -> 0 | BZ29: =+BX29-BY29 -> 0 | CB29: =+BS29+BX29 -> 0 | CC29: =+BT29+BY29 -> 0 | CD29: =+CB29-CC29 -> 0 | CG29: =SUM(CE29:CF29) -> 0 | CI29: =+CG29-CH29 -> 0 | CK29: =+CB29+CG29 -> 0 | CL29: =+CC29+CH29 -> 0 | CM29: =+CK29-CL29 -> 0 | CP29: =SUM(CN29:CO29) -> 0 | CR29: =+CP29-CQ29 -> 0 | CT29: =+CK29+CP29 -> 0 | CU29: =+CL29+CQ29 -> 0 | CV29: =+CT29-CU29 -> 0 | CY29: =SUM(CW29:CX29) -> 0 | DA29: =+CY29-CZ29 -> 0 | DC29: =+CT29+CY29 -> 0 | DD29: =+CU29+CZ29 -> 0 | DE29: =+DC29-DD29 -> 0 | DH29: =SUM(DF29:DG29) -> 0 | DJ29: =+DH29-DI29 -> 0 | DL29: =+DC29+DH29 -> 0 | DM29: =+DD29+DI29 -> 0 | DN29: =+DL29-DM29 -> 0 | DQ29: =+DM29 -> 0 | DR29: 0
A30: =+A29+1 -> 17 | I30: =HLOOKUP(I$10,M$10:DI$53,ROW()-9,FALSE) -> 0 | M30: =SUM(K30:L30) -> 0 | O30: =+M30-N30 -> 0 | Q30: =+M30 -> 0 | R30: =+N30 -> 0 | S30: =O30 -> 0 | V30: =SUM(T30:U30) -> 0 | X30: =+V30-W30 -> 0 | Z30: =+Q30+V30 -> 0 | AA30: =+R30+W30 -> 0 | AB30: =+Z30-AA30 -> 0 | AE30: =SUM(AC30:AD30) -> 0 | AG30: =+AE30-AF30 -> 0 | AI30: =+Z30+AE30 -> 0 | AJ30: =+AA30+AF30 -> 0 | AK30: =+AI30-AJ30 -> 0 | AN30: =SUM(AL30:AM30) -> 0 | AP30: =+AN30-AO30 -> 0 | AR30: =+AI30+AN30 -> 0 | AS30: =+AJ30+AO30 -> 0 | AT30: =+AR30-AS30 -> 0 | AW30: =SUM(AU30:AV30) -> 0 | AY30: =+AW30-AX30 -> 0 | BA30: =+AR30+AW30 -> 0 | BB30: =+AS30+AX30 -> 0 | BC30: =+BA30-BB30 -> 0 | BF30: =SUM(BD30:BE30) -> 0 | BH30: =+BF30-BG30 -> 0 | BJ30: =+BA30+BF30 -> 0 | BK30: =+BB30+BG30 -> 0 | BL30: =+BJ30-BK30 -> 0 | BO30: =SUM(BM30:BN30) -> 0 | BQ30: =+BO30-BP30 -> 0 | BS30: =+BJ30+BO30 -> 0 | BT30: =+BK30+BP30 -> 0 | BU30: =+BS30-BT30 -> 0 | BX30: =SUM(BV30:BW30) -> 0 | BZ30: =+BX30-BY30 -> 0 | CB30: =+BS30+BX30 -> 0 | CC30: =+BT30+BY30 -> 0 | CD30: =+CB30-CC30 -> 0 | CG30: =SUM(CE30:CF30) -> 0 | CI30: =+CG30-CH30 -> 0 | CK30: =+CB30+CG30 -> 0 | CL30: =+CC30+CH30 -> 0 | CM30: =+CK30-CL30 -> 0 | CP30: =SUM(CN30:CO30) -> 0 | CR30: =+CP30-CQ30 -> 0 | CT30: =+CK30+CP30 -> 0 | CU30: =+CL30+CQ30 -> 0 | CV30: =+CT30-CU30 -> 0 | CY30: =SUM(CW30:CX30) -> 0 | DA30: =+CY30-CZ30 -> 0 | DC30: =+CT30+CY30 -> 0 | DD30: =+CU30+CZ30 -> 0 | DE30: =+DC30-DD30 -> 0 | DH30: =SUM(DF30:DG30) -> 0 | DJ30: =+DH30-DI30 -> 0 | DL30: =+DC30+DH30 -> 0 | DM30: =+DD30+DI30 -> 0 | DN30: =+DL30-DM30 -> 0 | DQ30: =+DM30 -> 0 | DR30: 0
A31: =+A30+1 -> 18 | I31: =HLOOKUP(I$10,M$10:DI$53,ROW()-9,FALSE) -> 0 | M31: =SUM(K31:L31) -> 0 | O31: =+M31-N31 -> 0 | Q31: =+M31 -> 0 | R31: =+N31 -> 0 | S31: =O31 -> 0 | V31: =SUM(T31:U31) -> 0 | X31: =+V31-W31 -> 0 | Z31: =+Q31+V31 -> 0 | AA31: =+R31+W31 -> 0 | AB31: =+Z31-AA31 -> 0 | AE31: =SUM(AC31:AD31) -> 0 | AG31: =+AE31-AF31 -> 0 | AI31: =+Z31+AE31 -> 0 | AJ31: =+AA31+AF31 -> 0 | AK31: =+AI31-AJ31 -> 0 | AN31: =SUM(AL31:AM31) -> 0 | AP31: =+AN31-AO31 -> 0 | AR31: =+AI31+AN31 -> 0 | AS31: =+AJ31+AO31 -> 0 | AT31: =+AR31-AS31 -> 0 | AW31: =SUM(AU31:AV31) -> 0 | AY31: =+AW31-AX31 -> 0 | BA31: =+AR31+AW31 -> 0 | BB31: =+AS31+AX31 -> 0 | BC31: =+BA31-BB31 -> 0 | BF31: =SUM(BD31:BE31) -> 0 | BH31: =+BF31-BG31 -> 0 | BJ31: =+BA31+BF31 -> 0 | BK31: =+BB31+BG31 -> 0 | BL31: =+BJ31-BK31 -> 0 | BO31: =SUM(BM31:BN31) -> 0 | BQ31: =+BO31-BP31 -> 0 | BS31: =+BJ31+BO31 -> 0 | BT31: =+BK31+BP31 -> 0 | BU31: =+BS31-BT31 -> 0 | BX31: =SUM(BV31:BW31) -> 0 | BZ31: =+BX31-BY31 -> 0 | CB31: =+BS31+BX31 -> 0 | CC31: =+BT31+BY31 -> 0 | CD31: =+CB31-CC31 -> 0 | CG31: =SUM(CE31:CF31) -> 0 | CI31: =+CG31-CH31 -> 0 | CK31: =+CB31+CG31 -> 0 | CL31: =+CC31+CH31 -> 0 | CM31: =+CK31-CL31 -> 0 | CP31: =SUM(CN31:CO31) -> 0 | CR31: =+CP31-CQ31 -> 0 | CT31: =+CK31+CP31 -> 0 | CU31: =+CL31+CQ31 -> 0 | CV31: =+CT31-CU31 -> 0 | CY31: =SUM(CW31:CX31) -> 0 | DA31: =+CY31-CZ31 -> 0 | DC31: =+CT31+CY31 -> 0 | DD31: =+CU31+CZ31 -> 0 | DE31: =+DC31-DD31 -> 0 | DH31: =SUM(DF31:DG31) -> 0 | DJ31: =+DH31-DI31 -> 0 | DL31: =+DC31+DH31 -> 0 | DM31: =+DD31+DI31 -> 0 | DN31: =+DL31-DM31 -> 0 | DQ31: =+DM31 -> 0 | DR31: 0
A32: =+A31+1 -> 19 | I32: =HLOOKUP(I$10,M$10:DI$53,ROW()-9,FALSE) -> 0 | M32: =SUM(K32:L32) -> 0 | O32: =+M32-N32 -> 0 | Q32: =+M32 -> 0 | R32: =+N32 -> 0 | S32: =O32 -> 0 | V32: =SUM(T32:U32) -> 0 | X32: =+V32-W32 -> 0 | Z32: =+Q32+V32 -> 0 | AA32: =+R32+W32 -> 0 | AB32: =+Z32-AA32 -> 0 | AE32: =SUM(AC32:AD32) -> 0 | AG32: =+AE32-AF32 -> 0 | AI32: =+Z32+AE32 -> 0 | AJ32: =+AA32+AF32 -> 0 | AK32: =+AI32-AJ32 -> 0 | AN32: =SUM(AL32:AM32) -> 0 | AP32: =+AN32-AO32 -> 0 | AR32: =+AI32+AN32 -> 0 | AS32: =+AJ32+AO32 -> 0 | AT32: =+AR32-AS32 -> 0 | AW32: =SUM(AU32:AV32) -> 0 | AY32: =+AW32-AX32 -> 0 | BA32: =+AR32+AW32 -> 0 | BB32: =+AS32+AX32 -> 0 | BC32: =+BA32-BB32 -> 0 | BF32: =SUM(BD32:BE32) -> 0 | BH32: =+BF32-BG32 -> 0 | BJ32: =+BA32+BF32 -> 0 | BK32: =+BB32+BG32 -> 0 | BL32: =+BJ32-BK32 -> 0 | BO32: =SUM(BM32:BN32) -> 0 | BQ32: =+BO32-BP32 -> 0 | BS32: =+BJ32+BO32 -> 0 | BT32: =+BK32+BP32 -> 0 | BU32: =+BS32-BT32 -> 0 | BX32: =SUM(BV32:BW32) -> 0 | BZ32: =+BX32-BY32 -> 0 | CB32: =+BS32+BX32 -> 0 | CC32: =+BT32+BY32 -> 0 | CD32: =+CB32-CC32 -> 0 | CG32: =SUM(CE32:CF32) -> 0 | CI32: =+CG32-CH32 -> 0 | CK32: =+CB32+CG32 -> 0 | CL32: =+CC32+CH32 -> 0 | CM32: =+CK32-CL32 -> 0 | CP32: =SUM(CN32:CO32) -> 0 | CR32: =+CP32-CQ32 -> 0 | CT32: =+CK32+CP32 -> 0 | CU32: =+CL32+CQ32 -> 0 | CV32: =+CT32-CU32 -> 0 | CY32: =SUM(CW32:CX32) -> 0 | DA32: =+CY32-CZ32 -> 0 | DC32: =+CT32+CY32 -> 0 | DD32: =+CU32+CZ32 -> 0 | DE32: =+DC32-DD32 -> 0 | DH32: =SUM(DF32:DG32) -> 0 | DJ32: =+DH32-DI32 -> 0 | DL32: =+DC32+DH32 -> 0 | DM32: =+DD32+DI32 -> 0 | DN32: =+DL32-DM32 -> 0 | DQ32: =+DM32 -> 0 | DR32: 0
A33: =+A32+1 -> 20 | I33: =HLOOKUP(I$10,M$10:DI$53,ROW()-9,FALSE) -> 0 | M33: =SUM(K33:L33) -> 0 | O33: =+M33-N33 -> 0 | Q33: =+M33 -> 0 | R33: =+N33 -> 0 | S33: =O33 -> 0 | V33: =SUM(T33:U33) -> 0 | X33: =+V33-W33 -> 0 | Z33: =+Q33+V33 -> 0 | AA33: =+R33+W33 -> 0 | AB33: =+Z33-AA33 -> 0 | AE33: =SUM(AC33:AD33) -> 0 | AG33: =+AE33-AF33 -> 0 | AI33: =+Z33+AE33 -> 0 | AJ33: =+AA33+AF33 -> 0 | AK33: =+AI33-AJ33 -> 0 | AN33: =SUM(AL33:AM33) -> 0 | AP33: =+AN33-AO33 -> 0 | AR33: =+AI33+AN33 -> 0 | AS33: =+AJ33+AO33 -> 0 | AT33: =+AR33-AS33 -> 0 | AW33: =SUM(AU33:AV33) -> 0 | AY33: =+AW33-AX33 -> 0 | BA33: =+AR33+AW33 -> 0 | BB33: =+AS33+AX33 -> 0 | BC33: =+BA33-BB33 -> 0 | BF33: =SUM(BD33:BE33) -> 0 | BH33: =+BF33-BG33 -> 0 | BJ33: =+BA33+BF33 -> 0 | BK33: =+BB33+BG33 -> 0 | BL33: =+BJ33-BK33 -> 0 | BO33: =SUM(BM33:BN33) -> 0 | BQ33: =+BO33-BP33 -> 0 | BS33: =+BJ33+BO33 -> 0 | BT33: =+BK33+BP33 -> 0 | BU33: =+BS33-BT33 -> 0 | BX33: =SUM(BV33:BW33) -> 0 | BZ33: =+BX33-BY33 -> 0 | CB33: =+BS33+BX33 -> 0 | CC33: =+BT33+BY33 -> 0 | CD33: =+CB33-CC33 -> 0 | CG33: =SUM(CE33:CF33) -> 0 | CI33: =+CG33-CH33 -> 0 | CK33: =+CB33+CG33 -> 0 | CL33: =+CC33+CH33 -> 0 | CM33: =+CK33-CL33 -> 0 | CP33: =SUM(CN33:CO33) -> 0 | CR33: =+CP33-CQ33 -> 0 | CT33: =+CK33+CP33 -> 0 | CU33: =+CL33+CQ33 -> 0 | CV33: =+CT33-CU33 -> 0 | CY33: =SUM(CW33:CX33) -> 0 | DA33: =+CY33-CZ33 -> 0 | DC33: =+CT33+CY33 -> 0 | DD33: =+CU33+CZ33 -> 0 | DE33: =+DC33-DD33 -> 0 | DH33: =SUM(DF33:DG33) -> 0 | DJ33: =+DH33-DI33 -> 0 | DL33: =+DC33+DH33 -> 0 | DM33: =+DD33+DI33 -> 0 | DN33: =+DL33-DM33 -> 0 | DQ33: =+DM33 -> 0 | DR33: 0
A34: =+A33+1 -> 21 | I34: =HLOOKUP(I$10,M$10:DI$53,ROW()-9,FALSE) -> 0 | M34: =SUM(K34:L34) -> 0 | O34: =+M34-N34 -> 0 | Q34: =+M34 -> 0 | R34: =+N34 -> 0 | S34: =O34 -> 0 | V34: =SUM(T34:U34) -> 0 | X34: =+V34-W34 -> 0 | Z34: =+Q34+V34 -> 0 | AA34: =+R34+W34 -> 0 | AB34: =+Z34-AA34 -> 0 | AE34: =SUM(AC34:AD34) -> 0 | AG34: =+AE34-AF34 -> 0 | AI34: =+Z34+AE34 -> 0 | AJ34: =+AA34+AF34 -> 0 | AK34: =+AI34-AJ34 -> 0 | AN34: =SUM(AL34:AM34) -> 0 | AP34: =+AN34-AO34 -> 0 | AR34: =+AI34+AN34 -> 0 | AS34: =+AJ34+AO34 -> 0 | AT34: =+AR34-AS34 -> 0 | AW34: =SUM(AU34:AV34) -> 0 | AY34: =+AW34-AX34 -> 0 | BA34: =+AR34+AW34 -> 0 | BB34: =+AS34+AX34 -> 0 | BC34: =+BA34-BB34 -> 0 | BF34: =SUM(BD34:BE34) -> 0 | BH34: =+BF34-BG34 -> 0 | BJ34: =+BA34+BF34 -> 0 | BK34: =+BB34+BG34 -> 0 | BL34: =+BJ34-BK34 -> 0 | BO34: =SUM(BM34:BN34) -> 0 | BQ34: =+BO34-BP34 -> 0 | BS34: =+BJ34+BO34 -> 0 | BT34: =+BK34+BP34 -> 0 | BU34: =+BS34-BT34 -> 0 | BX34: =SUM(BV34:BW34) -> 0 | BZ34: =+BX34-BY34 -> 0 | CB34: =+BS34+BX34 -> 0 | CC34: =+BT34+BY34 -> 0 | CD34: =+CB34-CC34 -> 0 | CG34: =SUM(CE34:CF34) -> 0 | CI34: =+CG34-CH34 -> 0 | CK34: =+CB34+CG34 -> 0 | CL34: =+CC34+CH34 -> 0 | CM34: =+CK34-CL34 -> 0 | CP34: =SUM(CN34:CO34) -> 0 | CR34: =+CP34-CQ34 -> 0 | CT34: =+CK34+CP34 -> 0 | CU34: =+CL34+CQ34 -> 0 | CV34: =+CT34-CU34 -> 0 | CY34: =SUM(CW34:CX34) -> 0 | DA34: =+CY34-CZ34 -> 0 | DC34: =+CT34+CY34 -> 0 | DD34: =+CU34+CZ34 -> 0 | DE34: =+DC34-DD34 -> 0 | DH34: =SUM(DF34:DG34) -> 0 | DJ34: =+DH34-DI34 -> 0 | DL34: =+DC34+DH34 -> 0 | DM34: =+DD34+DI34 -> 0 | DN34: =+DL34-DM34 -> 0 | DQ34: =+DM34 -> 0 | DR34: 0
A35: =+A34+1 -> 22 | I35: =HLOOKUP(I$10,M$10:DI$53,ROW()-9,FALSE) -> 0 | M35: =SUM(K35:L35) -> 0 | O35: =+M35-N35 -> 0 | Q35: =+M35 -> 0 | R35: =+N35 -> 0 | S35: =O35 -> 0 | V35: =SUM(T35:U35) -> 0 | X35: =+V35-W35 -> 0 | Z35: =+Q35+V35 -> 0 | AA35: =+R35+W35 -> 0 | AB35: =+Z35-AA35 -> 0 | AE35: =SUM(AC35:AD35) -> 0 | AG35: =+AE35-AF35 -> 0 | AI35: =+Z35+AE35 -> 0 | AJ35: =+AA35+AF35 -> 0 | AK35: =+AI35-AJ35 -> 0 | AN35: =SUM(AL35:AM35) -> 0 | AP35: =+AN35-AO35 -> 0 | AR35: =+AI35+AN35 -> 0 | AS35: =+AJ35+AO35 -> 0 | AT35: =+AR35-AS35 -> 0 | AW35: =SUM(AU35:AV35) -> 0 | AY35: =+AW35-AX35 -> 0 | BA35: =+AR35+AW35 -> 0 | BB35: =+AS35+AX35 -> 0 | BC35: =+BA35-BB35 -> 0 | BF35: =SUM(BD35:BE35) -> 0 | BH35: =+BF35-BG35 -> 0 | BJ35: =+BA35+BF35 -> 0 | BK35: =+BB35+BG35 -> 0 | BL35: =+BJ35-BK35 -> 0 | BO35: =SUM(BM35:BN35) -> 0 | BQ35: =+BO35-BP35 -> 0 | BS35: =+BJ35+BO35 -> 0 | BT35: =+BK35+BP35 -> 0 | BU35: =+BS35-BT35 -> 0 | BX35: =SUM(BV35:BW35) -> 0 | BZ35: =+BX35-BY35 -> 0 | CB35: =+BS35+BX35 -> 0 | CC35: =+BT35+BY35 -> 0 | CD35: =+CB35-CC35 -> 0 | CG35: =SUM(CE35:CF35) -> 0 | CI35: =+CG35-CH35 -> 0 | CK35: =+CB35+CG35 -> 0 | CL35: =+CC35+CH35 -> 0 | CM35: =+CK35-CL35 -> 0 | CP35: =SUM(CN35:CO35) -> 0 | CR35: =+CP35-CQ35 -> 0 | CT35: =+CK35+CP35 -> 0 | CU35: =+CL35+CQ35 -> 0 | CV35: =+CT35-CU35 -> 0 | CY35: =SUM(CW35:CX35) -> 0 | DA35: =+CY35-CZ35 -> 0 | DC35: =+CT35+CY35 -> 0 | DD35: =+CU35+CZ35 -> 0 | DE35: =+DC35-DD35 -> 0 | DH35: =SUM(DF35:DG35) -> 0 | DJ35: =+DH35-DI35 -> 0 | DL35: =+DC35+DH35 -> 0 | DM35: =+DD35+DI35 -> 0 | DN35: =+DL35-DM35 -> 0 | DQ35: =+DM35 -> 0 | DR35: 0
A36: =+A35+1 -> 23 | I36: =HLOOKUP(I$10,M$10:DI$53,ROW()-9,FALSE) -> 0 | M36: =SUM(K36:L36) -> 0 | O36: =+M36-N36 -> 0 | Q36: =+M36 -> 0 | R36: =+N36 -> 0 | S36: =O36 -> 0 | V36: =SUM(T36:U36) -> 0 | X36: =+V36-W36 -> 0 | Z36: =+Q36+V36 -> 0 | AA36: =+R36+W36 -> 0 | AB36: =+Z36-AA36 -> 0 | AE36: =SUM(AC36:AD36) -> 0 | AG36: =+AE36-AF36 -> 0 | AI36: =+Z36+AE36 -> 0 | AJ36: =+AA36+AF36 -> 0 | AK36: =+AI36-AJ36 -> 0 | AN36: =SUM(AL36:AM36) -> 0 | AP36: =+AN36-AO36 -> 0 | AR36: =+AI36+AN36 -> 0 | AS36: =+AJ36+AO36 -> 0 | AT36: =+AR36-AS36 -> 0 | AW36: =SUM(AU36:AV36) -> 0 | AY36: =+AW36-AX36 -> 0 | BA36: =+AR36+AW36 -> 0 | BB36: =+AS36+AX36 -> 0 | BC36: =+BA36-BB36 -> 0 | BF36: =SUM(BD36:BE36) -> 0 | BH36: =+BF36-BG36 -> 0 | BJ36: =+BA36+BF36 -> 0 | BK36: =+BB36+BG36 -> 0 | BL36: =+BJ36-BK36 -> 0 | BO36: =SUM(BM36:BN36) -> 0 | BQ36: =+BO36-BP36 -> 0 | BS36: =+BJ36+BO36 -> 0 | BT36: =+BK36+BP36 -> 0 | BU36: =+BS36-BT36 -> 0 | BX36: =SUM(BV36:BW36) -> 0 | BZ36: =+BX36-BY36 -> 0 | CB36: =+BS36+BX36 -> 0 | CC36: =+BT36+BY36 -> 0 | CD36: =+CB36-CC36 -> 0 | CG36: =SUM(CE36:CF36) -> 0 | CI36: =+CG36-CH36 -> 0 | CK36: =+CB36+CG36 -> 0 | CL36: =+CC36+CH36 -> 0 | CM36: =+CK36-CL36 -> 0 | CP36: =SUM(CN36:CO36) -> 0 | CR36: =+CP36-CQ36 -> 0 | CT36: =+CK36+CP36 -> 0 | CU36: =+CL36+CQ36 -> 0 | CV36: =+CT36-CU36 -> 0 | CY36: =SUM(CW36:CX36) -> 0 | DA36: =+CY36-CZ36 -> 0 | DC36: =+CT36+CY36 -> 0 | DD36: =+CU36+CZ36 -> 0 | DE36: =+DC36-DD36 -> 0 | DH36: =SUM(DF36:DG36) -> 0 | DJ36: =+DH36-DI36 -> 0 | DL36: =+DC36+DH36 -> 0 | DM36: =+DD36+DI36 -> 0 | DN36: =+DL36-DM36 -> 0 | DQ36: =+DM36 -> 0 | DR36: 0
A37: =+A36+1 -> 24 | I37: =HLOOKUP(I$10,M$10:DI$53,ROW()-9,FALSE) -> 0 | M37: =SUM(K37:L37) -> 0 | O37: =+M37-N37 -> 0 | Q37: =+M37 -> 0 | R37: =+N37 -> 0 | S37: =O37 -> 0 | V37: =SUM(T37:U37) -> 0 | X37: =+V37-W37 -> 0 | Z37: =+Q37+V37 -> 0 | AA37: =+R37+W37 -> 0 | AB37: =+Z37-AA37 -> 0 | AE37: =SUM(AC37:AD37) -> 0 | AG37: =+AE37-AF37 -> 0 | AI37: =+Z37+AE37 -> 0 | AJ37: =+AA37+AF37 -> 0 | AK37: =+AI37-AJ37 -> 0 | AN37: =SUM(AL37:AM37) -> 0 | AP37: =+AN37-AO37 -> 0 | AR37: =+AI37+AN37 -> 0 | AS37: =+AJ37+AO37 -> 0 | AT37: =+AR37-AS37 -> 0 | AW37: =SUM(AU37:AV37) -> 0 | AY37: =+AW37-AX37 -> 0 | BA37: =+AR37+AW37 -> 0 | BB37: =+AS37+AX37 -> 0 | BC37: =+BA37-BB37 -> 0 | BF37: =SUM(BD37:BE37) -> 0 | BH37: =+BF37-BG37 -> 0 | BJ37: =+BA37+BF37 -> 0 | BK37: =+BB37+BG37 -> 0 | BL37: =+BJ37-BK37 -> 0 | BO37: =SUM(BM37:BN37) -> 0 | BQ37: =+BO37-BP37 -> 0 | BS37: =+BJ37+BO37 -> 0 | BT37: =+BK37+BP37 -> 0 | BU37: =+BS37-BT37 -> 0 | BX37: =SUM(BV37:BW37) -> 0 | BZ37: =+BX37-BY37 -> 0 | CB37: =+BS37+BX37 -> 0 | CC37: =+BT37+BY37 -> 0 | CD37: =+CB37-CC37 -> 0 | CG37: =SUM(CE37:CF37) -> 0 | CI37: =+CG37-CH37 -> 0 | CK37: =+CB37+CG37 -> 0 | CL37: =+CC37+CH37 -> 0 | CM37: =+CK37-CL37 -> 0 | CP37: =SUM(CN37:CO37) -> 0 | CR37: =+CP37-CQ37 -> 0 | CT37: =+CK37+CP37 -> 0 | CU37: =+CL37+CQ37 -> 0 | CV37: =+CT37-CU37 -> 0 | CY37: =SUM(CW37:CX37) -> 0 | DA37: =+CY37-CZ37 -> 0 | DC37: =+CT37+CY37 -> 0 | DD37: =+CU37+CZ37 -> 0 | DE37: =+DC37-DD37 -> 0 | DH37: =SUM(DF37:DG37) -> 0 | DJ37: =+DH37-DI37 -> 0 | DL37: =+DC37+DH37 -> 0 | DM37: =+DD37+DI37 -> 0 | DN37: =+DL37-DM37 -> 0 | DQ37: =+DM37 -> 0 | DR37: 0
A38: =+A37+1 -> 25 | I38: =HLOOKUP(I$10,M$10:DI$53,ROW()-9,FALSE) -> 0 | M38: =SUM(K38:L38) -> 0 | O38: =+M38-N38 -> 0 | Q38: =+M38 -> 0 | R38: =+N38 -> 0 | S38: =O38 -> 0 | V38: =SUM(T38:U38) -> 0 | X38: =+V38-W38 -> 0 | Z38: =+Q38+V38 -> 0 | AA38: =+R38+W38 -> 0 | AB38: =+Z38-AA38 -> 0 | AE38: =SUM(AC38:AD38) -> 0 | AG38: =+AE38-AF38 -> 0 | AI38: =+Z38+AE38 -> 0 | AJ38: =+AA38+AF38 -> 0 | AK38: =+AI38-AJ38 -> 0 | AN38: =SUM(AL38:AM38) -> 0 | AP38: =+AN38-AO38 -> 0 | AR38: =+AI38+AN38 -> 0 | AS38: =+AJ38+AO38 -> 0 | AT38: =+AR38-AS38 -> 0 | AW38: =SUM(AU38:AV38) -> 0 | AY38: =+AW38-AX38 -> 0 | BA38: =+AR38+AW38 -> 0 | BB38: =+AS38+AX38 -> 0 | BC38: =+BA38-BB38 -> 0 | BF38: =SUM(BD38:BE38) -> 0 | BH38: =+BF38-BG38 -> 0 | BJ38: =+BA38+BF38 -> 0 | BK38: =+BB38+BG38 -> 0 | BL38: =+BJ38-BK38 -> 0 | BO38: =SUM(BM38:BN38) -> 0 | BQ38: =+BO38-BP38 -> 0 | BS38: =+BJ38+BO38 -> 0 | BT38: =+BK38+BP38 -> 0 | BU38: =+BS38-BT38 -> 0 | BX38: =SUM(BV38:BW38) -> 0 | BZ38: =+BX38-BY38 -> 0 | CB38: =+BS38+BX38 -> 0 | CC38: =+BT38+BY38 -> 0 | CD38: =+CB38-CC38 -> 0 | CG38: =SUM(CE38:CF38) -> 0 | CI38: =+CG38-CH38 -> 0 | CK38: =+CB38+CG38 -> 0 | CL38: =+CC38+CH38 -> 0 | CM38: =+CK38-CL38 -> 0 | CP38: =SUM(CN38:CO38) -> 0 | CR38: =+CP38-CQ38 -> 0 | CT38: =+CK38+CP38 -> 0 | CU38: =+CL38+CQ38 -> 0 | CV38: =+CT38-CU38 -> 0 | CY38: =SUM(CW38:CX38) -> 0 | DA38: =+CY38-CZ38 -> 0 | DC38: =+CT38+CY38 -> 0 | DD38: =+CU38+CZ38 -> 0 | DE38: =+DC38-DD38 -> 0 | DH38: =SUM(DF38:DG38) -> 0 | DJ38: =+DH38-DI38 -> 0 | DL38: =+DC38+DH38 -> 0 | DM38: =+DD38+DI38 -> 0 | DN38: =+DL38-DM38 -> 0 | DQ38: =+DM38 -> 0 | DR38: 0
A39: =+A38+1 -> 26 | I39: =HLOOKUP(I$10,M$10:DI$53,ROW()-9,FALSE) -> 0 | M39: =SUM(K39:L39) -> 0 | N39: 0 | O39: =+M39-N39 -> 0 | Q39: =+M39 -> 0 | R39: =+N39 -> 0 | S39: =O39 -> 0 | V39: =SUM(T39:U39) -> 0 | X39: =+V39-W39 -> 0 | Z39: =+Q39+V39 -> 0 | AA39: =+R39+W39 -> 0 | AB39: =+Z39-AA39 -> 0 | AE39: =SUM(AC39:AD39) -> 0 | AG39: =+AE39-AF39 -> 0 | AI39: =+Z39+AE39 -> 0 | AJ39: =+AA39+AF39 -> 0 | AK39: =+AI39-AJ39 -> 0 | AN39: =SUM(AL39:AM39) -> 0 | AP39: =+AN39-AO39 -> 0 | AR39: =+AI39+AN39 -> 0 | AS39: =+AJ39+AO39 -> 0 | AT39: =+AR39-AS39 -> 0 | AW39: =SUM(AU39:AV39) -> 0 | AY39: =+AW39-AX39 -> 0 | BA39: =+AR39+AW39 -> 0 | BB39: =+AS39+AX39 -> 0 | BC39: =+BA39-BB39 -> 0 | BF39: =SUM(BD39:BE39) -> 0 | BH39: =+BF39-BG39 -> 0 | BJ39: =+BA39+BF39 -> 0 | BK39: =+BB39+BG39 -> 0 | BL39: =+BJ39-BK39 -> 0 | BO39: =SUM(BM39:BN39) -> 0 | BQ39: =+BO39-BP39 -> 0 | BS39: =+BJ39+BO39 -> 0 | BT39: =+BK39+BP39 -> 0 | BU39: =+BS39-BT39 -> 0 | BX39: =SUM(BV39:BW39) -> 0 | BZ39: =+BX39-BY39 -> 0 | CB39: =+BS39+BX39 -> 0 | CC39: =+BT39+BY39 -> 0 | CD39: =+CB39-CC39 -> 0 | CG39: =SUM(CE39:CF39) -> 0 | CI39: =+CG39-CH39 -> 0 | CK39: =+CB39+CG39 -> 0 | CL39: =+CC39+CH39 -> 0 | CM39: =+CK39-CL39 -> 0 | CP39: =SUM(CN39:CO39) -> 0 | CR39: =+CP39-CQ39 -> 0 | CT39: =+CK39+CP39 -> 0 | CU39: =+CL39+CQ39 -> 0 | CV39: =+CT39-CU39 -> 0 | CY39: =SUM(CW39:CX39) -> 0 | DA39: =+CY39-CZ39 -> 0 | DC39: =+CT39+CY39 -> 0 | DD39: =+CU39+CZ39 -> 0 | DE39: =+DC39-DD39 -> 0 | DH39: =SUM(DF39:DG39) -> 0 | DJ39: =+DH39-DI39 -> 0 | DL39: =+DC39+DH39 -> 0 | DM39: =+DD39+DI39 -> 0 | DN39: =+DL39-DM39 -> 0 | DQ39: =+DM39 -> 0 | DR39: 0
C42: Total In-Line | H42: =SUM(H14:H41) -> 13256 | I42: =SUM(I14:I41) -> 49286.7 | K42: =SUM(K14:K41) -> 47945.29 | L42: =SUM(L14:L41) -> 4950.0001 | M42: =SUM(M14:M41) -> 52895.29 | N42: =SUM(N14:N41) -> 55676 | O42: =SUM(O14:O41) -> -2780.7099 | Q42: =SUM(Q14:Q41) -> 52895.29 | R42: =SUM(R14:R41) -> 55676 | S42: =SUM(S14:S41) -> -2780.7099 | T42: =SUM(T14:T41) -> 53201.05 | U42: =SUM(U14:U41) -> 0.0001 | V42: =SUM(V14:V41) -> 53201.05 | W42: =SUM(W14:W41) -> 55676 | X42: =SUM(X14:X41) -> -2474.9499 | Z42: =SUM(Z14:Z41) -> 106096.34 | AA42: =SUM(AA14:AA41) -> 111352 | AB42: =SUM(AB14:AB41) -> -5255.6598 | AC42: =SUM(AC14:AC41) -> 53419.8 | AD42: =SUM(AD14:AD41) -> 0.0001 | AE42: =SUM(AE14:AE41) -> 53419.8 | AF42: =SUM(AF14:AF41) -> 55895 | AG42: =SUM(AG14:AG41) -> -2475.1999 | AI42: =SUM(AI14:AI41) -> 159516.14 | AJ42: =SUM(AJ14:AJ41) -> 167247 | AK42: =SUM(AK14:AK41) -> -7730.8597 | AL42: =SUM(AL14:AL41) -> 53419.8 | AM42: =SUM(AM14:AM41) -> 0.0001 | AN42: =SUM(AN14:AN41) -> 53419.8 | AO42: =SUM(AO14:AO41) -> 55895 | AP42: =SUM(AP14:AP41) -> -2475.1999 | AR42: =SUM(AR14:AR41) -> 212935.94 | AS42: =SUM(AS14:AS41) -> 223142 | AT42: =SUM(AT14:AT41) -> -10206.06 | AU42: =SUM(AU14:AU41) -> 53419.8 | AV42: =SUM(AV14:AV41) -> -17165.51 | AW42: =SUM(AW14:AW41) -> 36254.29 | AX42: =SUM(AX14:AX41) -> 55895 | AY42: =SUM(AY14:AY41) -> -19640.71 | BA42: =SUM(BA14:BA41) -> 249190.23 | BB42: =SUM(BB14:BB41) -> 279037 | BC42: =SUM(BC14:BC41) -> -29846.769 | BD42: =SUM(BD14:BD41) -> 24056.86 | BE42: =SUM(BE14:BE41) -> 44911 | BF42: =SUM(BF14:BF41) -> 68967.86 | BG42: =SUM(BG14:BG41) -> 61537 | BH42: =SUM(BH14:BH41) -> 7430.8601 | BJ42: =SUM(BJ14:BJ41) -> 318158.09 | BK42: =SUM(BK14:BK41) -> 340574 | BL42: =SUM(BL14:BL41) -> -22415.909 | BM42: =SUM(BM14:BM41) -> 54472.1 | BN42: =SUM(BN14:BN41) -> 2990.5701 | BO42: =SUM(BO14:BO41) -> 57462.67 | BP42: =SUM(BP14:BP41) -> 61537 | BQ42: =SUM(BQ14:BQ41) -> -4074.3299 | BS42: =SUM(BS14:BS41) -> 375620.76 | BT42: =SUM(BT14:BT41) -> 402111 | BU42: =SUM(BU14:BU41) -> -26490.239 | BV42: =SUM(BV14:BV41) -> 58787.84 | BW42: =SUM(BW14:BW41) -> -4096.9999 | BX42: =SUM(BX14:BX41) -> 54690.84 | BY42: =SUM(BY14:BY41) -> 61537 | BZ42: =SUM(BZ14:BZ41) -> -6846.1599 | CB42: =SUM(CB14:CB41) -> 430311.6 | CC42: =SUM(CC14:CC41) -> 463648 | CD42: =SUM(CD14:CD41) -> -33336.399 | CE42: =SUM(CE14:CE41) -> 54472.1 | CF42: =SUM(CF14:CF41) -> 219.0001 | CG42: =SUM(CG14:CG41) -> 54691.1 | CH42: =SUM(CH14:CH41) -> 61537 | CI42: =SUM(CI14:CI41) -> -6845.8999 | CK42: =SUM(CK14:CK41) -> 485002.7 | CL42: =SUM(CL14:CL41) -> 525185 | CM42: =SUM(CM14:CM41) -> -40182.299 | CN42: =SUM(CN14:CN41) -> 48631.9 | CO42: =SUM(CO14:CO41) -> 3139.1001 | CP42: =SUM(CP14:CP41) -> 51771 | CQ42: =SUM(CQ14:CQ41) -> 61537 | CR42: =SUM(CR14:CR41) -> -9765.9999 | CT42: =SUM(CT14:CT41) -> 536773.7 | CU42: =SUM(CU14:CU41) -> 586722 | CV42: =SUM(CV14:CV41) -> -49948.299 | CW42: =SUM(CW14:CW41) -> 53104.5 | CX42: =SUM(CX14:CX41) -> 902.5501 | CY42: =SUM(CY14:CY41) -> 54007.05 | CZ42: =SUM(CZ14:CZ41) -> 61537 | DA42: =SUM(DA14:DA41) -> -7529.9499 | DC42: =SUM(DC14:DC41) -> 590780.75 | DD42: =SUM(DD14:DD41) -> 648259 | DE42: =SUM(DE14:DE41) -> -57478.249 | DF42: =SUM(DF14:DF41) -> 45416.3 | DG42: =SUM(DG14:DG41) -> 3870.4001 | DH42: =SUM(DH14:DH41) -> 49286.7 | DI42: =SUM(DI14:DI41) -> 62142 | DJ42: =SUM(DJ14:DJ41) -> -12855.3 | DL42: =SUM(DL14:DL41) -> 640067.45 | DM42: =SUM(DM14:DM41) -> 710401 | DN42: =SUM(DN14:DN41) -> -70333.549 | DQ42: =SUM(DQ14:DQ41) -> 710401 | DR42: =SUM(DR14:DR41) -> -70333
C44: Anchor/Pads/Storage
B45: 621201-000016 | C45: Bayside Restaurant | D45: 36161 | E45: 41882 | F45: Occupied | G45: 900 | H45: 8000 | I45: =HLOOKUP(I$10,M$10:DI$53,ROW()-9,FALSE) -> 10000 | K45: =IF(ISERROR(VLOOKUP($B45,'MRI Data'!$A:$P,M$10+3,FALSE)),0,VLOOKUP($B45,'MRI Data'!$A:$P,M$10+3,FALSE)) -> 10000 | M45: =SUM(K45:L45) -> 10000 | N45: 10000 | O45: =+M45-N45 -> 0 | Q45: =+M45 -> 10000 | R45: =+N45 -> 10000 | S45: =O45 -> 0 | T45: =IF(ISERROR(VLOOKUP($B45,'MRI Data'!$A:$P,V$10+3,FALSE)),0,VLOOKUP($B45,'MRI Data'!$A:$P,V$10+3,FALSE)) -> 10000 | V45: =SUM(T45:U45) -> 10000 | W45: 10000 | X45: =+V45-W45 -> 0 | Z45: =+Q45+V45 -> 20000 | AA45: =+R45+W45 -> 20000 | AB45: =+Z45-AA45 -> 0 | AC45: =IF(ISERROR(VLOOKUP($B45,'MRI Data'!$A:$P,AE$10+3,FALSE)),0,VLOOKUP($B45,'MRI Data'!$A:$P,AE$10+3,FALSE)) -> 10000 | AE45: =SUM(AC45:AD45) -> 10000 | AF45: 10000 | AG45: =+AE45-AF45 -> 0 | AI45: =+Z45+AE45 -> 30000 | AJ45: =+AA45+AF45 -> 30000 | AK45: =+AI45-AJ45 -> 0 | AL45: =IF(ISERROR(VLOOKUP($B45,'MRI Data'!$A:$P,AN$10+3,FALSE)),0,VLOOKUP($B45,'MRI Data'!$A:$P,AN$10+3,FALSE)) -> 10000 | AN45: =SUM(AL45:AM45) -> 10000 | AO45: 10000 | AP45: =+AN45-AO45 -> 0 | AR45: =+AI45+AN45 -> 40000 | AS45: =+AJ45+AO45 -> 40000 | AT45: =+AR45-AS45 -> 0 | AU45: =IF(ISERROR(VLOOKUP($B45,'MRI Data'!$A:$P,AW$10+3,FALSE)),0,VLOOKUP($B45,'MRI Data'!$A:$P,AW$10+3,FALSE)) -> 10000 | AW45: =SUM(AU45:AV45) -> 10000 | AX45: 10000 | AY45: =+AW45-AX45 -> 0 | BA45: =+AR45+AW45 -> 50000 | BB45: =+AS45+AX45 -> 50000 | BC45: =+BA45-BB45 -> 0 | BD45: =IF(ISERROR(VLOOKUP($B45,'MRI Data'!$A:$P,BF$10+3,FALSE)),0,VLOOKUP($B45,'MRI Data'!$A:$P,BF$10+3,FALSE)) -> 10000 | BF45: =SUM(BD45:BE45) -> 10000 | BG45: 10000 | BH45: =+BF45-BG45 -> 0 | BJ45: =+BA45+BF45 -> 60000 | BK45: =+BB45+BG45 -> 60000 | BL45: =+BJ45-BK45 -> 0 | BM45: =IF(ISERROR(VLOOKUP($B45,'MRI Data'!$A:$P,BO$10+3,FALSE)),0,VLOOKUP($B45,'MRI Data'!$A:$P,BO$10+3,FALSE)) -> 10000 | BO45: =SUM(BM45:BN45) -> 10000 | BP45: 10000 | BQ45: =+BO45-BP45 -> 0 | BS45: =+BJ45+BO45 -> 70000 | BT45: =+BK45+BP45 -> 70000 | BU45: =+BS45-BT45 -> 0 | BV45: =IF(ISERROR(VLOOKUP($B45,'MRI Data'!$A:$P,BX$10+3,FALSE)),0,VLOOKUP($B45,'MRI Data'!$A:$P,BX$10+3,FALSE)) -> 10000 | BX45: =SUM(BV45:BW45) -> 10000 | BY45: 10000 | BZ45: =+BX45-BY45 -> 0 | CB45: =+BS45+BX45 -> 80000 | CC45: =+BT45+BY45 -> 80000 | CD45: =+CB45-CC45 -> 0 | CE45: =IF(ISERROR(VLOOKUP($B45,'MRI Data'!$A:$P,CG$10+3,FALSE)),0,VLOOKUP($B45,'MRI Data'!$A:$P,CG$10+3,FALSE)) -> 10000 | CG45: =SUM(CE45:CF45) -> 10000 | CH45: 10000 | CI45: =+CG45-CH45 -> 0 | CK45: =+CB45+CG45 -> 90000 | CL45: =+CC45+CH45 -> 90000 | CM45: =+CK45-CL45 -> 0 | CN45: =IF(ISERROR(VLOOKUP($B45,'MRI Data'!$A:$P,CP$10+3,FALSE)),0,VLOOKUP($B45,'MRI Data'!$A:$P,CP$10+3,FALSE)) -> 10000 | CP45: =SUM(CN45:CO45) -> 10000 | CQ45: 10000 | CR45: =+CP45-CQ45 -> 0 | CT45: =+CK45+CP45 -> 100000 | CU45: =+CL45+CQ45 -> 100000 | CV45: =+CT45-CU45 -> 0 | CW45: =IF(ISERROR(VLOOKUP($B45,'MRI Data'!$A:$P,CY$10+3,FALSE)),0,VLOOKUP($B45,'MRI Data'!$A:$P,CY$10+3,FALSE)) -> 10000 | CY45: =SUM(CW45:CX45) -> 10000 | CZ45: 10000 | DA45: =+CY45-CZ45 -> 0 | DC45: =+CT45+CY45 -> 110000 | DD45: =+CU45+CZ45 -> 110000 | DE45: =+DC45-DD45 -> 0 | DF45: =IF(ISERROR(VLOOKUP($B45,'MRI Data'!$A:$P,DH$10+3,FALSE)),0,VLOOKUP($B45,'MRI Data'!$A:$P,DH$10+3,FALSE)) -> 10000 | DH45: =SUM(DF45:DG45) -> 10000 | DI45: 10000 | DJ45: =+DH45-DI45 -> 0 | DL45: =+DC45+DH45 -> 120000 | DM45: =+DD45+DI45 -> 120000 | DN45: =+DL45-DM45 -> 0 | DQ45: =+DM45 -> 120000 | DR45: 0
B46: 621201-000009 | C46: Pavilions #235 | D46: 31564 | E46: 42521 | F46: Occupied | G46: 1000 | H46: 28734 | I46: =HLOOKUP(I$10,M$10:DI$53,ROW()-9,FALSE) -> 57468 | K46: =IF(ISERROR(VLOOKUP($B46,'MRI Data'!$A:$P,M$10+3,FALSE)),0,VLOOKUP($B46,'MRI Data'!$A:$P,M$10+3,FALSE)) -> 57468 | M46: =SUM(K46:L46) -> 57468 | N46: 57468 | O46: =+M46-N46 -> 0 | Q46: =+M46 -> 57468 | R46: =+N46 -> 57468 | S46: =O46 -> 0 | T46: =IF(ISERROR(VLOOKUP($B46,'MRI Data'!$A:$P,V$10+3,FALSE)),0,VLOOKUP($B46,'MRI Data'!$A:$P,V$10+3,FALSE)) -> 57468 | V46: =SUM(T46:U46) -> 57468 | W46: 57468 | X46: =+V46-W46 -> 0 | Z46: =+Q46+V46 -> 114936 | AA46: =+R46+W46 -> 114936 | AB46: =+Z46-AA46 -> 0 | AC46: =IF(ISERROR(VLOOKUP($B46,'MRI Data'!$A:$P,AE$10+3,FALSE)),0,VLOOKUP($B46,'MRI Data'!$A:$P,AE$10+3,FALSE)) -> 57468 | AE46: =SUM(AC46:AD46) -> 57468 | AF46: 57468 | AG46: =+AE46-AF46 -> 0 | AI46: =+Z46+AE46 -> 172404 | AJ46: =+AA46+AF46 -> 172404 | AK46: =+AI46-AJ46 -> 0 | AL46: =IF(ISERROR(VLOOKUP($B46,'MRI Data'!$A:$P,AN$10+3,FALSE)),0,VLOOKUP($B46,'MRI Data'!$A:$P,AN$10+3,FALSE)) -> 57468 | AN46: =SUM(AL46:AM46) -> 57468 | AO46: 57468 | AP46: =+AN46-AO46 -> 0 | AR46: =+AI46+AN46 -> 229872 | AS46: =+AJ46+AO46 -> 229872 | AT46: =+AR46-AS46 -> 0 | AU46: =IF(ISERROR(VLOOKUP($B46,'MRI Data'!$A:$P,AW$10+3,FALSE)),0,VLOOKUP($B46,'MRI Data'!$A:$P,AW$10+3,FALSE)) -> 57468 | AW46: =SUM(AU46:AV46) -> 57468 | AX46: 57468 | AY46: =+AW46-AX46 -> 0 | BA46: =+AR46+AW46 -> 287340 | BB46: =+AS46+AX46 -> 287340 | BC46: =+BA46-BB46 -> 0 | BD46: =IF(ISERROR(VLOOKUP($B46,'MRI Data'!$A:$P,BF$10+3,FALSE)),0,VLOOKUP($B46,'MRI Data'!$A:$P,BF$10+3,FALSE)) -> 57468 | BF46: =SUM(BD46:BE46) -> 57468 | BG46: 57468 | BH46: =+BF46-BG46 -> 0 | BJ46: =+BA46+BF46 -> 344808 | BK46: =+BB46+BG46 -> 344808 | BL46: =+BJ46-BK46 -> 0 | BM46: =IF(ISERROR(VLOOKUP($B46,'MRI Data'!$A:$P,BO$10+3,FALSE)),0,VLOOKUP($B46,'MRI Data'!$A:$P,BO$10+3,FALSE)) -> 57468 | BO46: =SUM(BM46:BN46) -> 57468 | BP46: 57468 | BQ46: =+BO46-BP46 -> 0 | BS46: =+BJ46+BO46 -> 402276 | BT46: =+BK46+BP46 -> 402276 | BU46: =+BS46-BT46 -> 0 | BV46: =IF(ISERROR(VLOOKUP($B46,'MRI Data'!$A:$P,BX$10+3,FALSE)),0,VLOOKUP($B46,'MRI Data'!$A:$P,BX$10+3,FALSE)) -> 57468 | BX46: =SUM(BV46:BW46) -> 57468 | BY46: 57468 | BZ46: =+BX46-BY46 -> 0 | CB46: =+BS46+BX46 -> 459744 | CC46: =+BT46+BY46 -> 459744 | CD46: =+CB46-CC46 -> 0 | CE46: =IF(ISERROR(VLOOKUP($B46,'MRI Data'!$A:$P,CG$10+3,FALSE)),0,VLOOKUP($B46,'MRI Data'!$A:$P,CG$10+3,FALSE)) -> 57468 | CG46: =SUM(CE46:CF46) -> 57468 | CH46: 57468 | CI46: =+CG46-CH46 -> 0 | CK46: =+CB46+CG46 -> 517212 | CL46: =+CC46+CH46 -> 517212 | CM46: =+CK46-CL46 -> 0 | CN46: =IF(ISERROR(VLOOKUP($B46,'MRI Data'!$A:$P,CP$10+3,FALSE)),0,VLOOKUP($B46,'MRI Data'!$A:$P,CP$10+3,FALSE)) -> 57468 | CP46: =SUM(CN46:CO46) -> 57468 | CQ46: 57468 | CR46: =+CP46-CQ46 -> 0 | CT46: =+CK46+CP46 -> 574680 | CU46: =+CL46+CQ46 -> 574680 | CV46: =+CT46-CU46 -> 0 | CW46: =IF(ISERROR(VLOOKUP($B46,'MRI Data'!$A:$P,CY$10+3,FALSE)),0,VLOOKUP($B46,'MRI Data'!$A:$P,CY$10+3,FALSE)) -> 57468 | CY46: =SUM(CW46:CX46) -> 57468 | CZ46: 57468 | DA46: =+CY46-CZ46 -> 0 | DC46: =+CT46+CY46 -> 632148 | DD46: =+CU46+CZ46 -> 632148 | DE46: =+DC46-DD46 -> 0 | DF46: =IF(ISERROR(VLOOKUP($B46,'MRI Data'!$A:$P,DH$10+3,FALSE)),0,VLOOKUP($B46,'MRI Data'!$A:$P,DH$10+3,FALSE)) -> 57468 | DH46: =SUM(DF46:DG46) -> 57468 | DI46: 57468 | DJ46: =+DH46-DI46 -> 0 | DL46: =+DC46+DH46 -> 689616 | DM46: =+DD46+DI46 -> 689616 | DN46: =+DL46-DM46 -> 0 | DQ46: =+DM46 -> 689616 | DR46: 0
B47: 621201-000015 | C47: Rite-Aid #5747 | D47: 35324 | E47: 45716 | F47: Occupied | G47: 1016 | H47: 8986 | I47: =HLOOKUP(I$10,M$10:DI$53,ROW()-9,FALSE) -> 56797.27 | K47: =IF(ISERROR(VLOOKUP($B47,'MRI Data'!$A:$P,M$10+3,FALSE)),0,VLOOKUP($B47,'MRI Data'!$A:$P,M$10+3,FALSE)) -> 14699.95 | M47: =SUM(K47:L47) -> 14699.95 | N47: 14700 | O47: =+M47-N47 -> -0.05 | Q47: =+M47 -> 14699.95 | R47: =+N47 -> 14700 | S47: =O47 -> -0.05 | T47: =IF(ISERROR(VLOOKUP($B47,'MRI Data'!$A:$P,V$10+3,FALSE)),0,VLOOKUP($B47,'MRI Data'!$A:$P,V$10+3,FALSE)) -> 14699.95 | V47: =SUM(T47:U47) -> 14699.95 | W47: 14700 | X47: =+V47-W47 -> -0.05 | Z47: =+Q47+V47 -> 29399.9 | AA47: =+R47+W47 -> 29400 | AB47: =+Z47-AA47 -> -0.1 | AC47: =IF(ISERROR(VLOOKUP($B47,'MRI Data'!$A:$P,AE$10+3,FALSE)),0,VLOOKUP($B47,'MRI Data'!$A:$P,AE$10+3,FALSE)) -> 14699.95 | AE47: =SUM(AC47:AD47) -> 14699.95 | AF47: 14700 | AG47: =+AE47-AF47 -> -0.05 | AI47: =+Z47+AE47 -> 44099.85 | AJ47: =+AA47+AF47 -> 44100 | AK47: =+AI47-AJ47 -> -0.15 | AL47: =IF(ISERROR(VLOOKUP($B47,'MRI Data'!$A:$P,AN$10+3,FALSE)),0,VLOOKUP($B47,'MRI Data'!$A:$P,AN$10+3,FALSE)) -> 14699.95 | AN47: =SUM(AL47:AM47) -> 14699.95 | AO47: 14700 | AP47: =+AN47-AO47 -> -0.05 | AR47: =+AI47+AN47 -> 58799.8 | AS47: =+AJ47+AO47 -> 58800 | AT47: =+AR47-AS47 -> -0.2 | AU47: =IF(ISERROR(VLOOKUP($B47,'MRI Data'!$A:$P,AW$10+3,FALSE)),0,VLOOKUP($B47,'MRI Data'!$A:$P,AW$10+3,FALSE)) -> 14699.95 | AW47: =SUM(AU47:AV47) -> 14699.95 | AX47: 14700 | AY47: =+AW47-AX47 -> -0.05 | BA47: =+AR47+AW47 -> 73499.75 | BB47: =+AS47+AX47 -> 73500 | BC47: =+BA47-BB47 -> -0.25 | BD47: =IF(ISERROR(VLOOKUP($B47,'MRI Data'!$A:$P,BF$10+3,FALSE)),0,VLOOKUP($B47,'MRI Data'!$A:$P,BF$10+3,FALSE)) -> 14699.95 | BF47: =SUM(BD47:BE47) -> 14699.95 | BG47: 14700 | BH47: =+BF47-BG47 -> -0.05 | BJ47: =+BA47+BF47 -> 88199.7 | BK47: =+BB47+BG47 -> 88200 | BL47: =+BJ47-BK47 -> -0.3 | BM47: =IF(ISERROR(VLOOKUP($B47,'MRI Data'!$A:$P,BO$10+3,FALSE)),0,VLOOKUP($B47,'MRI Data'!$A:$P,BO$10+3,FALSE)) -> 14699.95 | BO47: =SUM(BM47:BN47) -> 14699.95 | BP47: 14700 | BQ47: =+BO47-BP47 -> -0.05 | BS47: =+BJ47+BO47 -> 102899.65 | BT47: =+BK47+BP47 -> 102900 | BU47: =+BS47-BT47 -> -0.35 | BV47: =IF(ISERROR(VLOOKUP($B47,'MRI Data'!$A:$P,BX$10+3,FALSE)),0,VLOOKUP($B47,'MRI Data'!$A:$P,BX$10+3,FALSE)) -> 14699.95 | BX47: =SUM(BV47:BW47) -> 14699.95 | BY47: 14700 | BZ47: =+BX47-BY47 -> -0.05 | CB47: =+BS47+BX47 -> 117599.6 | CC47: =+BT47+BY47 -> 117600 | CD47: =+CB47-CC47 -> -0.4 | CE47: =IF(ISERROR(VLOOKUP($B47,'MRI Data'!$A:$P,CG$10+3,FALSE)),0,VLOOKUP($B47,'MRI Data'!$A:$P,CG$10+3,FALSE)) -> 14699.95 | CG47: =SUM(CE47:CF47) -> 14699.95 | CH47: 14700 | CI47: =+CG47-CH47 -> -0.05 | CK47: =+CB47+CG47 -> 132299.55 | CL47: =+CC47+CH47 -> 132300 | CM47: =+CK47-CL47 -> -0.45 | CN47: =IF(ISERROR(VLOOKUP($B47,'MRI Data'!$A:$P,CP$10+3,FALSE)),0,VLOOKUP($B47,'MRI Data'!$A:$P,CP$10+3,FALSE)) -> 14699.95 | CP47: =SUM(CN47:CO47) -> 14699.95 | CQ47: 14700 | CR47: =+CP47-CQ47 -> -0.05 | CT47: =+CK47+CP47 -> 146999.5 | CU47: =+CL47+CQ47 -> 147000 | CV47: =+CT47-CU47 -> -0.5 | CW47: =IF(ISERROR(VLOOKUP($B47,'MRI Data'!$A:$P,CY$10+3,FALSE)),0,VLOOKUP($B47,'MRI Data'!$A:$P,CY$10+3,FALSE)) -> 14699.95 | CY47: =SUM(CW47:CX47) -> 14699.95 | CZ47: 14700 | DA47: =+CY47-CZ47 -> -0.05 | DC47: =+CT47+CY47 -> 161699.45 | DD47: =+CU47+CZ47 -> 161700 | DE47: =+DC47-DD47 -> -0.55 | DF47: =IF(ISERROR(VLOOKUP($B47,'MRI Data'!$A:$P,DH$10+3,FALSE)),0,VLOOKUP($B47,'MRI Data'!$A:$P,DH$10+3,FALSE)) -> 56797.27 | DH47: =SUM(DF47:DG47) -> 56797.27 | DI47: 14700 | DJ47: =+DH47-DI47 -> 42097.27 | DL47: =+DC47+DH47 -> 218496.72 | DM47: =+DD47+DI47 -> 176400 | DN47: =+DL47-DM47 -> 42096.72 | DO47: Per 1st Amendment dated 6/1/10, tenant renewed eff 1/1/10 @ $29/sf vs. Plan @ $20/sf. | DQ47: =+DM47 -> 176400 | DR47: 42097 | DS47: Per 1st Amendment dated 6/1/10, tenant renewed eff 1/1/10 @ $29/sf vs. Plan @ $20/sf.
B48: 621201-000010 | C48: Union Bank #062 | D48: 33055 | E48: 42185 | F48: Occupied | G48: 1090 | H48: 5377 | I48: =HLOOKUP(I$10,M$10:DI$53,ROW()-9,FALSE) -> 26208.39 | K48: =IF(ISERROR(VLOOKUP($B48,'MRI Data'!$A:$P,M$10+3,FALSE)),0,VLOOKUP($B48,'MRI Data'!$A:$P,M$10+3,FALSE)) -> 26208.39 | M48: =SUM(K48:L48) -> 26208.39 | N48: 26209 | O48: =+M48-N48 -> -0.61 | Q48: =+M48 -> 26208.39 | R48: =+N48 -> 26209 | S48: =O48 -> -0.61 | T48: =IF(ISERROR(VLOOKUP($B48,'MRI Data'!$A:$P,V$10+3,FALSE)),0,VLOOKUP($B48,'MRI Data'!$A:$P,V$10+3,FALSE)) -> 26208.39 | V48: =SUM(T48:U48) -> 26208.39 | W48: 26209 | X48: =+V48-W48 -> -0.61 | Z48: =+Q48+V48 -> 52416.78 | AA48: =+R48+W48 -> 52418 | AB48: =+Z48-AA48 -> -1.22 | AC48: =IF(ISERROR(VLOOKUP($B48,'MRI Data'!$A:$P,AE$10+3,FALSE)),0,VLOOKUP($B48,'MRI Data'!$A:$P,AE$10+3,FALSE)) -> 26208.39 | AE48: =SUM(AC48:AD48) -> 26208.39 | AF48: 26209 | AG48: =+AE48-AF48 -> -0.61 | AI48: =+Z48+AE48 -> 78625.17 | AJ48: =+AA48+AF48 -> 78627 | AK48: =+AI48-AJ48 -> -1.83 | AL48: =IF(ISERROR(VLOOKUP($B48,'MRI Data'!$A:$P,AN$10+3,FALSE)),0,VLOOKUP($B48,'MRI Data'!$A:$P,AN$10+3,FALSE)) -> 26208.39 | AN48: =SUM(AL48:AM48) -> 26208.39 | AO48: 26209 | AP48: =+AN48-AO48 -> -0.61 | AR48: =+AI48+AN48 -> 104833.56 | AS48: =+AJ48+AO48 -> 104836 | AT48: =+AR48-AS48 -> -2.44 | AU48: =IF(ISERROR(VLOOKUP($B48,'MRI Data'!$A:$P,AW$10+3,FALSE)),0,VLOOKUP($B48,'MRI Data'!$A:$P,AW$10+3,FALSE)) -> 26208.39 | AW48: =SUM(AU48:AV48) -> 26208.39 | AX48: 26209 | AY48: =+AW48-AX48 -> -0.61 | BA48: =+AR48+AW48 -> 131041.95 | BB48: =+AS48+AX48 -> 131045 | BC48: =+BA48-BB48 -> -3.05 | BD48: =IF(ISERROR(VLOOKUP($B48,'MRI Data'!$A:$P,BF$10+3,FALSE)),0,VLOOKUP($B48,'MRI Data'!$A:$P,BF$10+3,FALSE)) -> 26208.39 | BF48: =SUM(BD48:BE48) -> 26208.39 | BG48: 26209 | BH48: =+BF48-BG48 -> -0.61 | BJ48: =+BA48+BF48 -> 157250.34 | BK48: =+BB48+BG48 -> 157254 | BL48: =+BJ48-BK48 -> -3.66 | BM48: =IF(ISERROR(VLOOKUP($B48,'MRI Data'!$A:$P,BO$10+3,FALSE)),0,VLOOKUP($B48,'MRI Data'!$A:$P,BO$10+3,FALSE)) -> 26208.39 | BO48: =SUM(BM48:BN48) -> 26208.39 | BP48: 26209 | BQ48: =+BO48-BP48 -> -0.61 | BS48: =+BJ48+BO48 -> 183458.73 | BT48: =+BK48+BP48 -> 183463 | BU48: =+BS48-BT48 -> -4.27 | BV48: =IF(ISERROR(VLOOKUP($B48,'MRI Data'!$A:$P,BX$10+3,FALSE)),0,VLOOKUP($B48,'MRI Data'!$A:$P,BX$10+3,FALSE)) -> 26208.39 | BX48: =SUM(BV48:BW48) -> 26208.39 | BY48: 26209 | BZ48: =+BX48-BY48 -> -0.61 | CB48: =+BS48+BX48 -> 209667.12 | CC48: =+BT48+BY48 -> 209672 | CD48: =+CB48-CC48 -> -4.88 | CE48: =IF(ISERROR(VLOOKUP($B48,'MRI Data'!$A:$P,CG$10+3,FALSE)),0,VLOOKUP($B48,'MRI Data'!$A:$P,CG$10+3,FALSE)) -> 26208.39 | CG48: =SUM(CE48:CF48) -> 26208.39 | CH48: 26209 | CI48: =+CG48-CH48 -> -0.61 | CK48: =+CB48+CG48 -> 235875.51 | CL48: =+CC48+CH48 -> 235881 | CM48: =+CK48-CL48 -> -5.49 | CN48: =IF(ISERROR(VLOOKUP($B48,'MRI Data'!$A:$P,CP$10+3,FALSE)),0,VLOOKUP($B48,'MRI Data'!$A:$P,CP$10+3,FALSE)) -> 26208.39 | CP48: =SUM(CN48:CO48) -> 26208.39 | CQ48: 26209 | CR48: =+CP48-CQ48 -> -0.61 | CT48: =+CK48+CP48 -> 262083.9 | CU48: =+CL48+CQ48 -> 262090 | CV48: =+CT48-CU48 -> -6.1 | CW48: =IF(ISERROR(VLOOKUP($B48,'MRI Data'!$A:$P,CY$10+3,FALSE)),0,VLOOKUP($B48,'MRI Data'!$A:$P,CY$10+3,FALSE)) -> 26208.39 | CY48: =SUM(CW48:CX48) -> 26208.39 | CZ48: 26209 | DA48: =+CY48-CZ48 -> -0.61 | DC48: =+CT48+CY48 -> 288292.29 | DD48: =+CU48+CZ48 -> 288299 | DE48: =+DC48-DD48 -> -6.71 | DF48: =IF(ISERROR(VLOOKUP($B48,'MRI Data'!$A:$P,DH$10+3,FALSE)),0,VLOOKUP($B48,'MRI Data'!$A:$P,DH$10+3,FALSE)) -> 26208.39 | DH48: =SUM(DF48:DG48) -> 26208.39 | DI48: 26209 | DJ48: =+DH48-DI48 -> -0.61 | DL48: =+DC48+DH48 -> 314500.68 | DM48: =+DD48+DI48 -> 314508 | DN48: =+DL48-DM48 -> -7.32 | DQ48: =+DM48 -> 314508 | DR48: 0
I49: =HLOOKUP(I$10,M$10:DI$53,ROW()-9,FALSE) -> 0 | O49: =+M49-N49 -> 0 | Q49: =+M49 -> 0 | R49: =+N49 -> 0 | S49: =O49 -> 0 | X49: =+V49-W49 -> 0 | Z49: =+Q49+V49 -> 0 | AA49: =+R49+W49 -> 0 | AB49: =+Z49-AA49 -> 0 | AG49: =+AE49-AF49 -> 0 | AI49: =+Z49+AE49 -> 0 | AJ49: =+AA49+AF49 -> 0 | AK49: =+AI49-AJ49 -> 0 | AP49: =+AN49-AO49 -> 0 | AR49: =+AI49+AN49 -> 0 | AS49: =+AJ49+AO49 -> 0 | AT49: =+AR49-AS49 -> 0 | AY49: =+AW49-AX49 -> 0 | BA49: =+AR49+AW49 -> 0 | BB49: =+AS49+AX49 -> 0 | BC49: =+BA49-BB49 -> 0 | BH49: =+BF49-BG49 -> 0 | BJ49: =+BA49+BF49 -> 0 | BK49: =+BB49+BG49 -> 0 | BL49: =+BJ49-BK49 -> 0 | BQ49: =+BO49-BP49 -> 0 | BS49: =+BJ49+BO49 -> 0 | BT49: =+BK49+BP49 -> 0 | BU49: =+BS49-BT49 -> 0 | BZ49: =+BX49-BY49 -> 0 | CB49: =+BS49+BX49 -> 0 | CC49: =+BT49+BY49 -> 0 | CD49: =+CB49-CC49 -> 0 | CI49: =+CG49-CH49 -> 0 | CK49: =+CB49+CG49 -> 0 | CL49: =+CC49+CH49 -> 0 | CM49: =+CK49-CL49 -> 0 | CR49: =+CP49-CQ49 -> 0 | CT49: =+CK49+CP49 -> 0 | CU49: =+CL49+CQ49 -> 0 | CV49: =+CT49-CU49 -> 0 | DA49: =+CY49-CZ49 -> 0 | DC49: =+CT49+CY49 -> 0 | DD49: =+CU49+CZ49 -> 0 | DE49: =+DC49-DD49 -> 0 | DJ49: =+DH49-DI49 -> 0 | DL49: =+DC49+DH49 -> 0 | DM49: =+DD49+DI49 -> 0 | DN49: =+DL49-DM49 -> 0 | DQ49: =+DM49 -> 0 | DR49: 0
I50: =HLOOKUP(I$10,M$10:DI$53,ROW()-9,FALSE) -> 0 | O50: =+M50-N50 -> 0 | Q50: =+M50 -> 0 | R50: =+N50 -> 0 | S50: =O50 -> 0 | X50: =+V50-W50 -> 0 | Z50: =+Q50+V50 -> 0 | AA50: =+R50+W50 -> 0 | AB50: =+Z50-AA50 -> 0 | AG50: =+AE50-AF50 -> 0 | AI50: =+Z50+AE50 -> 0 | AJ50: =+AA50+AF50 -> 0 | AK50: =+AI50-AJ50 -> 0 | AP50: =+AN50-AO50 -> 0 | AR50: =+AI50+AN50 -> 0 | AS50: =+AJ50+AO50 -> 0 | AT50: =+AR50-AS50 -> 0 | AY50: =+AW50-AX50 -> 0 | BA50: =+AR50+AW50 -> 0 | BB50: =+AS50+AX50 -> 0 | BC50: =+BA50-BB50 -> 0 | BH50: =+BF50-BG50 -> 0 | BJ50: =+BA50+BF50 -> 0 | BK50: =+BB50+BG50 -> 0 | BL50: =+BJ50-BK50 -> 0 | BQ50: =+BO50-BP50 -> 0 | BS50: =+BJ50+BO50 -> 0 | BT50: =+BK50+BP50 -> 0 | BU50: =+BS50-BT50 -> 0 | BZ50: =+BX50-BY50 -> 0 | CB50: =+BS50+BX50 -> 0 | CC50: =+BT50+BY50 -> 0 | CD50: =+CB50-CC50 -> 0 | CI50: =+CG50-CH50 -> 0 | CK50: =+CB50+CG50 -> 0 | CL50: =+CC50+CH50 -> 0 | CM50: =+CK50-CL50 -> 0 | CR50: =+CP50-CQ50 -> 0 | CT50: =+CK50+CP50 -> 0 | CU50: =+CL50+CQ50 -> 0 | CV50: =+CT50-CU50 -> 0 | DA50: =+CY50-CZ50 -> 0 | DC50: =+CT50+CY50 -> 0 | DD50: =+CU50+CZ50 -> 0 | DE50: =+DC50-DD50 -> 0 | DJ50: =+DH50-DI50 -> 0 | DL50: =+DC50+DH50 -> 0 | DM50: =+DD50+DI50 -> 0 | DN50: =+DL50-DM50 -> 0 | DQ50: =+DM50 -> 0 | DR50: 0
I51: =HLOOKUP(I$10,M$10:DI$53,ROW()-9,FALSE) -> 0 | O51: =+M51-N51 -> 0 | Q51: =+M51 -> 0 | R51: =+N51 -> 0 | S51: =O51 -> 0 | X51: =+V51-W51 -> 0 | Z51: =+Q51+V51 -> 0 | AA51: =+R51+W51 -> 0 | AB51: =+Z51-AA51 -> 0 | AG51: =+AE51-AF51 -> 0 | AI51: =+Z51+AE51 -> 0 | AJ51: =+AA51+AF51 -> 0 | AK51: =+AI51-AJ51 -> 0 | AP51: =+AN51-AO51 -> 0 | AR51: =+AI51+AN51 -> 0 | AS51: =+AJ51+AO51 -> 0 | AT51: =+AR51-AS51 -> 0 | AY51: =+AW51-AX51 -> 0 | BA51: =+AR51+AW51 -> 0 | BB51: =+AS51+AX51 -> 0 | BC51: =+BA51-BB51 -> 0 | BH51: =+BF51-BG51 -> 0 | BJ51: =+BA51+BF51 -> 0 | BK51: =+BB51+BG51 -> 0 | BL51: =+BJ51-BK51 -> 0 | BQ51: =+BO51-BP51 -> 0 | BS51: =+BJ51+BO51 -> 0 | BT51: =+BK51+BP51 -> 0 | BU51: =+BS51-BT51 -> 0 | BZ51: =+BX51-BY51 -> 0 | CB51: =+BS51+BX51 -> 0 | CC51: =+BT51+BY51 -> 0 | CD51: =+CB51-CC51 -> 0 | CI51: =+CG51-CH51 -> 0 | CK51: =+CB51+CG51 -> 0 | CL51: =+CC51+CH51 -> 0 | CM51: =+CK51-CL51 -> 0 | CR51: =+CP51-CQ51 -> 0 | CT51: =+CK51+CP51 -> 0 | CU51: =+CL51+CQ51 -> 0 | CV51: =+CT51-CU51 -> 0 | DA51: =+CY51-CZ51 -> 0 | DC51: =+CT51+CY51 -> 0 | DD51: =+CU51+CZ51 -> 0 | DE51: =+DC51-DD51 -> 0 | DJ51: =+DH51-DI51 -> 0 | DL51: =+DC51+DH51 -> 0 | DM51: =+DD51+DI51 -> 0 | DN51: =+DL51-DM51 -> 0 | DQ51: =+DM51 -> 0 | DR51: 0
C52: ROUNDING | O52: =N52-M52 -> 0 | S52: =O52 -> 0 | X52: =W52-V52 -> 0 | AB52: =+Z52-AA52 -> 0 | AG52: =AF52-AE52 -> 0 | AI52: =+Z52+AE52 -> 0 | AJ52: =+AA52+AF52 -> 0 | AK52: =+AI52-AJ52 -> 0 | AP52: =+AN52-AO52 -> 0 | AR52: =+AI52+AN52 -> 0 | AS52: =+AJ52+AO52 -> 0 | AT52: =+AR52-AS52 -> 0 | AY52: =+AW52-AX52 -> 0 | BA52: =+AR52+AW52 -> 0 | BB52: =+AS52+AX52 -> 0 | BC52: =+BA52-BB52 -> 0 | BG52: -1 | BH52: =+BF52-BG52 -> 1 | BJ52: =+BA52+BF52 -> 0 | BK52: =+BB52+BG52 -> -1 | BL52: =+BJ52-BK52 -> 1 | BP52: -1 | BQ52: =+BO52-BP52 -> 1 | BS52: =+BJ52+BO52 -> 0 | BT52: =+BK52+BP52 -> -2 | BU52: =+BS52-BT52 -> 2 | BY52: -1 | BZ52: =+BX52-BY52 -> 1 | CB52: =+BS52+BX52 -> 0 | CC52: =+BT52+BY52 -> -3 | CD52: =+CB52-CC52 -> 3 | CH52: -1 | CI52: =+CG52-CH52 -> 1 | CK52: =+CB52+CG52 -> 0 | CL52: =+CC52+CH52 -> -4 | CM52: =+CK52-CL52 -> 4 | CQ52: -1 | CR52: =+CP52-CQ52 -> 1 | CT52: =+CK52+CP52 -> 0 | CU52: =+CL52+CQ52 -> -5 | CV52: =+CT52-CU52 -> 5 | DA52: =+CY52-CZ52 -> 0 | DC52: =+CT52+CY52 -> 0 | DD52: =+CU52+CZ52 -> -5 | DE52: =+DC52-DD52 -> 5 | DI52: -1 | DJ52: =+DH52-DI52 -> 1 | DL52: =+DC52+DH52 -> 0 | DM52: =+DD52+DI52 -> -6 | DN52: =+DL52-DM52 -> 6 | DQ52: =+DM52 -> -6 | DR52: 0
C54: Total Anchors/Pads/Storage | H54: =SUM(H45:H53) -> 51097 | I54: =SUM(I45:I53) -> 150473.66 | K54: =SUM(K45:K53) -> 108376.34 | L54: =SUM(L45:L53) -> 0 | M54: =SUM(M45:M53) -> 108376.34 | N54: =SUM(N45:N53) -> 108377 | O54: =SUM(O46:O53) -> -0.66 | Q54: =SUM(Q45:Q53) -> 108376.34 | R54: =SUM(R45:R53) -> 108377 | S54: =SUM(S46:S53) -> -0.66 | T54: =SUM(T45:T53) -> 108376.34 | U54: =SUM(U45:U53) -> 0 | V54: =SUM(V45:V53) -> 108376.34 | W54: =SUM(W45:W52) -> 108377 | X54: =SUM(X45:X52) -> -0.66 | Z54: =SUM(Z45:Z52) -> 216752.68 | AA54: =SUM(AA45:AA52) -> 216754 | AB54: =SUM(AB45:AB52) -> -1.32 | AC54: =SUM(AC45:AC53) -> 108376.34 | AD54: =SUM(AD45:AD53) -> 0 | AE54: =SUM(AE45:AE53) -> 108376.34 | AF54: =SUM(AF45:AF52) -> 108377 | AG54: =SUM(AG46:AG53) -> -0.66 | AI54: =SUM(AI45:AI52) -> 325129.02 | AJ54: =SUM(AJ45:AJ52) -> 325131 | AK54: =SUM(AK45:AK52) -> -1.98 | AL54: =SUM(AL45:AL53) -> 108376.34 | AM54: =SUM(AM45:AM53) -> 0 | AN54: =SUM(AN45:AN53) -> 108376.34 | AO54: =SUM(AO45:AO52) -> 108377 | AP54: =SUM(AP45:AP52) -> -0.66 | AR54: =SUM(AR45:AR52) -> 433505.36 | AS54: =SUM(AS45:AS52) -> 433508 | AT54: =SUM(AT45:AT52) -> -2.64 | AU54: =SUM(AU45:AU53) -> 108376.34 | AV54: =SUM(AV45:AV53) -> 0 | AW54: =SUM(AW45:AW53) -> 108376.34 | AX54: =SUM(AX45:AX52) -> 108377 | AY54: =SUM(AY45:AY52) -> -0.66 | BA54: =SUM(BA45:BA52) -> 541881.7 | BB54: =SUM(BB45:BB52) -> 541885 | BC54: =SUM(BC45:BC52) -> -3.3 | BD54: =SUM(BD45:BD53) -> 108376.34 | BE54: =SUM(BE45:BE53) -> 0 | BF54: =SUM(BF45:BF53) -> 108376.34 | BG54: =SUM(BG45:BG52) -> 108376 | BH54: =SUM(BH45:BH52) -> 0.34 | BJ54: =SUM(BJ45:BJ52) -> 650258.04 | BK54: =SUM(BK45:BK52) -> 650261 | BL54: =SUM(BL45:BL52) -> -2.96 | BM54: =SUM(BM45:BM53) -> 108376.34 | BN54: =SUM(BN45:BN53) -> 0 | BO54: =SUM(BO45:BO53) -> 108376.34 | BP54: =SUM(BP45:BP52) -> 108376 | BQ54: =SUM(BQ45:BQ52) -> 0.34 | BS54: =SUM(BS45:BS52) -> 758634.38 | BT54: =SUM(BT45:BT52) -> 758637 | BU54: =SUM(BU45:BU52) -> -2.62 | BV54: =SUM(BV45:BV53) -> 108376.34 | BW54: =SUM(BW45:BW53) -> 0 | BX54: =SUM(BX45:BX53) -> 108376.34 | BY54: =SUM(BY45:BY52) -> 108376 | BZ54: =SUM(BZ45:BZ52) -> 0.34 | CB54: =SUM(CB45:CB52) -> 867010.72 | CC54: =SUM(CC45:CC52) -> 867013 | CD54: =SUM(CD45:CD52) -> -2.28 | CE54: =SUM(CE45:CE53) -> 108376.34 | CF54: =SUM(CF45:CF53) -> 0 | CG54: =SUM(CG45:CG53) -> 108376.34 | CH54: =SUM(CH45:CH52) -> 108376 | CI54: =SUM(CI45:CI52) -> 0.34 | CK54: =SUM(CK45:CK52) -> 975387.06 | CL54: =SUM(CL45:CL52) -> 975389 | CM54: =SUM(CM45:CM52) -> -1.94 | CN54: =SUM(CN45:CN53) -> 108376.34 | CO54: =SUM(CO45:CO53) -> 0 | CP54: =SUM(CP45:CP53) -> 108376.34 | CQ54: =SUM(CQ45:CQ52) -> 108376 | CR54: =SUM(CR45:CR52) -> 0.34 | CT54: =SUM(CT45:CT52) -> 1083763.4 | CU54: =SUM(CU45:CU52) -> 1083765 | CV54: =SUM(CV45:CV52) -> -1.6 | CW54: =SUM(CW45:CW53) -> 108376.34 | CX54: =SUM(CX45:CX53) -> 0 | CY54: =SUM(CY45:CY53) -> 108376.34 | CZ54: =SUM(CZ45:CZ52) -> 108377 | DA54: =SUM(DA45:DA52) -> -0.66 | DC54: =SUM(DC44:DC53) -> 1192139.7 | DD54: =SUM(DD44:DD53) -> 1192142 | DE54: =SUM(DE44:DE53) -> -2.26 | DF54: =SUM(DF45:DF53) -> 150473.66 | DG54: =SUM(DG45:DG53) -> 0 | DH54: =SUM(DH45:DH53) -> 150473.66 | DI54: =SUM(DI45:DI53) -> 108376 | DJ54: =SUM(DJ45:DJ53) -> 42097.66 | DL54: =SUM(DL45:DL53) -> 1342613.4 | DM54: =SUM(DM45:DM53) -> 1300518 | DN54: =SUM(DN45:DN53) -> 42095.4 | DQ54: =SUM(DQ45:DQ53) -> 1300518 | DR54: =SUM(DR45:DR53) -> 42097
C56: TOTAL | H56: =+H42+H54 -> 64353 | K56: =+K42+K54 -> 156321.63 | L56: =+L42+L54 -> 4950.0001 | M56: =+M42+M54 -> 161271.63 | N56: =+N42+N54 -> 164053 | O56: =+O42+O54 -> -2781.3699 | Q56: =+Q42+Q54 -> 161271.63 | R56: =+R42+R54 -> 164053 | S56: =+S42+S54 -> -2781.3699 | T56: =+T42+T54 -> 161577.39 | U56: =+U42+U54 -> 0.0001 | V56: =+V42+V54 -> 161577.39 | W56: =+W42+W54 -> 164053 | X56: =+X42+X54 -> -2475.6099 | Z56: =+Z42+Z54 -> 322849.02 | AA56: =+AA42+AA54 -> 328106 | AB56: =+AB42+AB54 -> -5256.9798 | AC56: =+AC42+AC54 -> 161796.14 | AD56: =+AD42+AD54 -> 0.0001 | AE56: =+AE42+AE54 -> 161796.14 | AF56: =+AF42+AF54 -> 164272 | AG56: =+AG42+AG54 -> -2475.8599 | AI56: =+AI42+AI54 -> 484645.16 | AJ56: =+AJ42+AJ54 -> 492378 | AK56: =+AK42+AK54 -> -7732.8397 | AL56: =+AL42+AL54 -> 161796.14 | AM56: =+AM42+AM54 -> 0.0001 | AN56: =+AN42+AN54 -> 161796.14 | AO56: =+AO42+AO54 -> 164272 | AP56: =+AP42+AP54 -> -2475.8599 | AR56: =+AR42+AR54 -> 646441.3 | AS56: =+AS42+AS54 -> 656650 | AT56: =+AT42+AT54 -> -10208.7 | AU56: =+AU42+AU54 -> 161796.14 | AV56: =+AV42+AV54 -> -17165.51 | AW56: =+AW42+AW54 -> 144630.63 | AX56: =+AX42+AX54 -> 164272 | AY56: =+AY42+AY54 -> -19641.37 | BA56: =+BA42+BA54 -> 791071.93 | BB56: =+BB42+BB54 -> 820922 | BC56: =+BC42+BC54 -> -29850.069 | BD56: =+BD42+BD54 -> 132433.2 | BE56: =+BE42+BE54 -> 44911 | BF56: =+BF42+BF54 -> 177344.2 | BG56: =+BG42+BG54 -> 169913 | BH56: =+BH42+BH54 -> 7431.2001 | BJ56: =+BJ42+BJ54 -> 968416.13 | BK56: =+BK42+BK54 -> 990835 | BL56: =+BL42+BL54 -> -22418.869 | BM56: =+BM42+BM54 -> 162848.44 | BN56: =+BN42+BN54 -> 2990.5701 | BO56: =+BO42+BO54 -> 165839.01 | BP56: =+BP42+BP54 -> 169913 | BQ56: =+BQ42+BQ54 -> -4073.9899 | BS56: =+BS42+BS54 -> 1134255.1 | BT56: =+BT42+BT54 -> 1160748 | BU56: =+BU42+BU54 -> -26492.859 | BV56: =+BV42+BV54 -> 167164.18 | BW56: =+BW42+BW54 -> -4096.9999 | BX56: =+BX42+BX54 -> 163067.18 | BY56: =+BY42+BY54 -> 169913 | BZ56: =+BZ42+BZ54 -> -6845.8199 | CB56: =+CB42+CB54 -> 1297322.3 | CC56: =+CC42+CC54 -> 1330661 | CD56: =+CD42+CD54 -> -33338.679 | CE56: =+CE42+CE54 -> 162848.44 | CF56: =+CF42+CF54 -> 219.0001 | CG56: =+CG42+CG54 -> 163067.44 | CH56: =+CH42+CH54 -> 169913 | CI56: =+CI42+CI54 -> -6845.5599 | CK56: =+CK42+CK54 -> 1460389.8 | CL56: =+CL42+CL54 -> 1500574 | CM56: =+CM42+CM54 -> -40184.239 | CN56: =+CN42+CN54 -> 157008.24 | CO56: =+CO42+CO54 -> 3139.1001 | CP56: =+CP42+CP54 -> 160147.34 | CQ56: =+CQ42+CQ54 -> 169913 | CR56: =+CR42+CR54 -> -9765.6599 | CT56: =+CT42+CT54 -> 1620537.1 | CU56: =+CU42+CU54 -> 1670487 | CV56: =+CV42+CV54 -> -49949.899 | CW56: =+CW42+CW54 -> 161480.84 | CX56: =+CX42+CX54 -> 902.5501 | CY56: =+CY42+CY54 -> 162383.39 | CZ56: =+CZ42+CZ54 -> 169914 | DA56: =+DA42+DA54 -> -7530.6099 | DC56: =+DC42+DC54 -> 1782920.5 | DD56: =+DD42+DD54 -> 1840401 | DE56: =+DE42+DE54 -> -57480.509 | DF56: =+DF42+DF54 -> 195889.96 | DG56: =+DG42+DG54 -> 3870.4001 | DH56: =+DH42+DH54 -> 199760.36 | DI56: =+DI42+DI54 -> 170518 | DJ56: =+DJ42+DJ54 -> 29242.36 | DL56: =+DL42+DL54 -> 1982680.9 | DM56: =+DM42+DM54 -> 2010919 | DN56: =+DN42+DN54 -> -28238.149 | DQ56: =+DQ42+DQ54 -> 2010919 | DR56: =+DR42+DR54 -> -28236

Sheet Min Rent Forecast
N1: =+$M$10 -> 1 | O1: =+$M$10+0.1 -> 1.1 | Q1: =+$M$10+0.2 -> 1.2 | R1: =+$M$10+0.3 -> 1.3 | W1: =+$V$10 -> 2 | X1: =+$V$10+0.1 -> 2.1 | Z1: =+$V$10+0.2 -> 2.2 | AA1: =+$V$10+0.3 -> 2.3 | AF1: =+$AE$10 -> 3 | AG1: =+$AE$10+0.1 -> 3.1 | AI1: =+$AE$10+0.2 -> 3.2 | AJ1: =+$AE$10+0.3 -> 3.3 | AO1: =+$AN$10 -> 4 | AP1: =+$AN$10+0.1 -> 4.1 | AR1: =+$AN$10+0.2 -> 4.2 | AS1: =+$AN$10+0.3 -> 4.3 | AX1: =+$AW$10 -> 5 | AY1: =+$AW$10+0.1 -> 5.1 | BA1: =+$AW$10+0.2 -> 5.2 | BB1: =+$AW$10+0.3 -> 5.3 | BG1: =+$BF$10 -> 6 | BH1: =+$BF$10+0.1 -> 6.1 | BJ1: =+$BF$10+0.2 -> 6.2 | BK1: =+$BF$10+0.3 -> 6.3 | BP1: =+$BO$10 -> 7 | BQ1: =+$BO$10+0.1 -> 7.1 | BS1: =+$BO$10+0.2 -> 7.2 | BT1: =+$BO$10+0.3 -> 7.3 | BY1: =+$BX$10 -> 8 | BZ1: =+$BX$10+0.1 -> 8.1 | CB1: =+$BX$10+0.2 -> 8.2 | CC1: =+$BX$10+0.3 -> 8.3 | CH1: =+$CG$10 -> 9 | CI1: =+$CG$10+0.1 -> 9.1 | CK1: =+$CG$10+0.2 -> 9.2 | CL1: =+$CG$10+0.3 -> 9.3 | CQ1: =+$CP$10 -> 10 | CR1: =+CQ1+0.1 -> 10.1 | CT1: =+CQ1+0.2 -> 10.2 | CU1: =+CQ1+0.3 -> 10.3 | CZ1: 11 | DA1: 11.1 | DC1: 11.2 | DD1: 11.3 | DI1: 12 | DJ1: 12.1 | DL1: 12.2 | DM1: 12.3
C2: =+'Review Comments'!B11 -> ABI PROPERTIES | N2: Month to Date | Q2: Weighted Average | W2: Month to Date | Z2: Weighted Average | AF2: Month to Date | AI2: Weighted Average | AO2: Month to Date | AR2: Weighted Average | AX2: Month to Date | BA2: Weighted Average | BG2: Month to Date | BJ2: Weighted Average | BP2: Month to Date | BS2: Weighted Average | BY2: Month to Date | CB2: Weighted Average | CH2: Month to Date | CK2: Weighted Average | CQ2: Month to Date | CT2: Weighted Average | CZ2: Month to Date | DC2: Weighted Average | DI2: Month to Date | DL2: Weighted Average
C3: MINIMUM RENT VARIANCE REPORT 2009/2010 | N3: Inline | O3: Overall | Q3: Inline | R3: Overall | W3: Inline | X3: Overall | Z3: Inline | AA3: Overall | AF3: Inline | AG3: Overall | AI3: Inline | AJ3: Overall | AO3: Inline | AP3: Overall | AR3: Inline | AS3: Overall | AX3: Inline | AY3: Overall | BA3: Inline | BB3: Overall | BG3: Inline | BH3: Overall | BJ3: Inline | BK3: Overall | BP3: Inline | BQ3: Overall | BS3: Inline | BT3: Overall | BY3: Inline | BZ3: Overall | CB3: Inline | CC3: Overall | CH3: Inline | CI3: Overall | CK3: Inline | CL3: Overall | CQ3: Inline | CR3: Overall | CT3: Inline | CU3: Overall | CZ3: Inline | DA3: Overall | DC3: Inline | DD3: Overall | DI3: Inline | DJ3: Overall | DL3: Inline | DM3: Overall
C4: ACTUAL VS. FORECAST | J4: Occupied Sq Ft | N4: ='Inline Rates'!J3 -> 12056 | O4: =+'Inline Rates'!J14 -> 63153 | Q4: ='Inline Rates'!K3 -> 12056 | R4: =+O4 -> 63153 | W4: =+'Inline Rates'!P3 -> 12056 | X4: =+'Inline Rates'!P14 -> 63153 | Z4: =+'Inline Rates'!Q3/2 -> 12056 | AA4: =('Inline Rates'!P18)/2 -> 63153 | AF4: =+'Inline Rates'!V3 -> 12056 | AG4: =+'Inline Rates'!V14 -> 63153 | AI4: =+'Inline Rates'!W3/3 -> 12056 | AJ4: =('Inline Rates'!V18)/3 -> 63153 | AO4: =+'Inline Rates'!AB3 -> 12056 | AP4: =+'Inline Rates'!AB14 -> 63153 | AR4: =+'Inline Rates'!AC3/4 -> 12056 | AS4: =('Inline Rates'!AB18)/4 -> 63153 | AX4: =+'Inline Rates'!AH3 -> 12056 | AY4: =+'Inline Rates'!AH14 -> 63153 | BA4: =+'Inline Rates'!AI3/5 -> 12056 | BB4: =('Inline Rates'!AH18)/5 -> 63153 | BG4: =+'Inline Rates'!AN3 -> 12056 | BH4: =+'Inline Rates'!AN14 -> 63153 | BJ4: =+'Inline Rates'!AO3/6 -> 12056 | BK4: =('Inline Rates'!AN18)/6 -> 63153 | BP4: =+'Inline Rates'!AT3 -> 12056 | BQ4: =+'Inline Rates'!AT14 -> 63153 | BS4: =+'Inline Rates'!AU3/7 -> 12056 | BT4: =('Inline Rates'!AT18)/7 -> 63153 | BY4: =+'Inline Rates'!AZ3 -> 12056 | BZ4: =+'Inline Rates'!AZ14 -> 63153 | CB4: =+'Inline Rates'!BA3/8 -> 12056 | CC4: =('Inline Rates'!AZ18)/8 -> 63153 | CH4: =+'Inline Rates'!BF3 -> 12056 | CI4: =+'Inline Rates'!BF14 -> 63153 | CK4: =+'Inline Rates'!BG3/9 -> 12056 | CL4: =('Inline Rates'!BF18)/9 -> 63153 | CQ4: =+'Inline Rates'!BL3 -> 12056 | CR4: =+'Inline Rates'!BL14 -> 63153 | CT4: =+'Inline Rates'!BM3/10 -> 12056 | CU4: =('Inline Rates'!BL18)/10 -> 63153 | CZ4: =+'Inline Rates'!BR3 -> 12056 | DA4: =+'Inline Rates'!BR14 -> 63153 | DC4: =+'Inline Rates'!BS3/11 -> 12056 | DD4: =('Inline Rates'!BR18)/11 -> 63153 | DI4: =+'Inline Rates'!BX3 -> 12056 | DJ4: =+'Inline Rates'!BX14 -> 63153 | DL4: =+'Inline Rates'!BY3/12 -> 12056 | DM4: =('Inline Rates'!BX18)/12 -> 63153
J5: Vacant Sq Ft | N5: ='Inline Rates'!J4-N4 -> 1200 | O5: =+'Inline Rates'!K14-O4 -> 1200 | Q5: ='Inline Rates'!K4-Q4 -> 1200 | R5: =+O5 -> 1200 | W5: ='Inline Rates'!P4-W4 -> 1200 | X5: =+'Inline Rates'!Q14-'Min Rent Forecast'!X4 -> 1200 | Z5: =+'Inline Rates'!Q4/2-Z4 -> 1200 | AA5: =(('Inline Rates'!Q18)/2)-AA4 -> 1200 | AF5: ='Inline Rates'!V4-AF4 -> 1200 | AG5: =+'Inline Rates'!W14-AG4 -> 1200 | AI5: =+'Inline Rates'!W4/3-AI4 -> 1200 | AJ5: =(('Inline Rates'!W18)/3)-AJ4 -> 1200 | AO5: =+'Inline Rates'!AB4-AO4 -> 1200 | AP5: =+'Inline Rates'!AC14-AP4 -> 1200 | AR5: =+'Inline Rates'!AC4/4-AR4 -> 1200 | AS5: =(('Inline Rates'!AC18)/4)-AS4 -> 1200 | AX5: =+'Inline Rates'!AH4-AX4 -> 1200 | AY5: =+'Inline Rates'!AI14-AY4 -> 1200 | BA5: =+'Inline Rates'!AI4/5-BA4 -> 1200 | BB5: =(('Inline Rates'!AI18)/5)-BB4 -> 1200 | BG5: =+'Inline Rates'!AN4-BG4 -> 1200 | BH5: =+'Inline Rates'!AO14-BH4 -> 1200 | BJ5: =+'Inline Rates'!AO4/6-BJ4 -> 1200 | BK5: =(('Inline Rates'!AO18)/6)-BK4 -> 1200 | BP5: =+'Inline Rates'!AT4-BP4 -> 1200 | BQ5: =+'Inline Rates'!AU14-BQ4 -> 1200 | BS5: =+'Inline Rates'!AU4/7-BS4 -> 1200 | BT5: =(('Inline Rates'!AU18)/7)-BT4 -> 1200 | BY5: =+'Inline Rates'!AZ4-BY4 -> 1200 | BZ5: =+'Inline Rates'!BA14-BZ4 -> 1200 | CB5: =+'Inline Rates'!BA4/8-CB4 -> 1200 | CC5: =(('Inline Rates'!BA18)/8)-CC4 -> 1200 | CH5: =+'Inline Rates'!BF4-CH4 -> 1200 | CI5: =+'Inline Rates'!BG14-CI4 -> 1200 | CK5: =+'Inline Rates'!BG4/9-CK4 -> 1200 | CL5: =(('Inline Rates'!BG18)/9)-CL4 -> 1200 | CQ5: =+'Inline Rates'!BL4-CQ4 -> 1200 | CR5: =+'Inline Rates'!BM14-CR4 -> 1200 | CT5: =+'Inline Rates'!BM4/10-'Min Rent Forecast'!CT4 -> 1200 | CU5: =(('Inline Rates'!BM18)/10)-CU4 -> 1200 | CZ5: =+'Inline Rates'!BR4-CZ4 -> 1200 | DA5: =+'Inline Rates'!BS14-DA4 -> 1200 | DC5: =+'Inline Rates'!BS4/11-DC4 -> 1200 | DD5: =(('Inline Rates'!BS18)/11)-DD4 -> 1200 | DI5: =+'Inline Rates'!BX4-DI4 -> 1200 | DJ5: =+'Inline Rates'!BY14-DJ4 -> 1200 | DL5: =+'Inline Rates'!BY4/12-DL4 -> 1200 | DM5: =(('Inline Rates'!BY18)/12)-DM4 -> 1200
J6: Total Sq Ft | N6: =SUM(N4:N5) -> 13256 | O6: =SUM(O4:O5) -> 64353 | Q6: =SUM(Q4:Q5) -> 13256 | R6: =SUM(R4:R5) -> 64353 | W6: =SUM(W4:W5) -> 13256 | X6: =SUM(X4:X5) -> 64353 | Z6: =SUM(Z4:Z5) -> 13256 | AA6: =SUM(AA4:AA5) -> 64353 | AF6: =SUM(AF4:AF5) -> 13256 | AG6: =SUM(AG4:AG5) -> 64353 | AI6: =SUM(AI4:AI5) -> 13256 | AJ6: =SUM(AJ4:AJ5) -> 64353 | AO6: =SUM(AO4:AO5) -> 13256 | AP6: =SUM(AP4:AP5) -> 64353 | AR6: =SUM(AR4:AR5) -> 13256 | AS6: =SUM(AS4:AS5) -> 64353 | AX6: =SUM(AX4:AX5) -> 13256 | AY6: =SUM(AY4:AY5) -> 64353 | BA6: =SUM(BA4:BA5) -> 13256 | BB6: =SUM(BB4:BB5) -> 64353 | BG6: =SUM(BG4:BG5) -> 13256 | BH6: =SUM(BH4:BH5) -> 64353 | BJ6: =SUM(BJ4:BJ5) -> 13256 | BK6: =SUM(BK4:BK5) -> 64353 | BP6: =SUM(BP4:BP5) -> 13256 | BQ6: =SUM(BQ4:BQ5) -> 64353 | BS6: =SUM(BS4:BS5) -> 13256 | BT6: =SUM(BT4:BT5) -> 64353 | BY6: =SUM(BY4:BY5) -> 13256 | BZ6: =SUM(BZ4:BZ5) -> 64353 | CB6: =SUM(CB4:CB5) -> 13256 | CC6: =SUM(CC4:CC5) -> 64353 | CH6: =SUM(CH4:CH5) -> 13256 | CI6: =SUM(CI4:CI5) -> 64353 | CK6: =SUM(CK4:CK5) -> 13256 | CL6: =SUM(CL4:CL5) -> 64353 | CQ6: =SUM(CQ4:CQ5) -> 13256 | CR6: =SUM(CR4:CR5) -> 64353 | CT6: =SUM(CT4:CT5) -> 13256 | CU6: =SUM(CU4:CU5) -> 64353 | CZ6: =SUM(CZ4:CZ5) -> 13256 | DA6: =SUM(DA4:DA5) -> 64353 | DC6: =SUM(DC4:DC5) -> 13256 | DD6: =SUM(DD4:DD5) -> 64353 | DI6: =SUM(DI4:DI5) -> 13256 | DJ6: =SUM(DJ4:DJ5) -> 64353 | DL6: =SUM(DL4:DL5) -> 13256 | DM6: =SUM(DM4:DM5) -> 64353
I7: Percentage Occupied | J7: Pct Occupied | N7: =+N4/N6 -> 0.90947495 | O7: =+O4/O6 -> 0.98135285 | Q7: =+Q4/Q6 -> 0.90947495 | R7: =+R4/R6 -> 0.98135285 | W7: =+W4/W6 -> 0.90947495 | X7: =+X4/X6 -> 0.98135285 | Z7: =+Z4/Z6 -> 0.90947495 | AA7: =+AA4/AA6 -> 0.98135285 | AF7: =+AF4/AF6 -> 0.90947495 | AG7: =+AG4/AG6 -> 0.98135285 | AI7: =+AI4/AI6 -> 0.90947495 | AJ7: =+AJ4/AJ6 -> 0.98135285 | AO7: =+AO4/AO6 -> 0.90947495 | AP7: =+AP4/AP6 -> 0.98135285 | AR7: =+AR4/AR6 -> 0.90947495 | AS7: =+AS4/AS6 -> 0.98135285 | AX7: =+AX4/AX6 -> 0.90947495 | AY7: =+AY4/AY6 -> 0.98135285 | BA7: =+BA4/BA6 -> 0.90947495 | BB7: =+BB4/BB6 -> 0.98135285 | BG7: =+BG4/BG6 -> 0.90947495 | BH7: =+BH4/BH6 -> 0.98135285 | BJ7: =+BJ4/BJ6 -> 0.90947495 | BK7: =+BK4/BK6 -> 0.98135285 | BP7: =+BP4/BP6 -> 0.90947495 | BQ7: =+BQ4/BQ6 -> 0.98135285 | BS7: =+BS4/BS6 -> 0.90947495 | BT7: =+BT4/BT6 -> 0.98135285 | BY7: =+BY4/BY6 -> 0.90947495 | BZ7: =+BZ4/BZ6 -> 0.98135285 | CB7: =+CB4/CB6 -> 0.90947495 | CC7: =+CC4/CC6 -> 0.98135285 | CH7: =+CH4/CH6 -> 0.90947495 | CI7: =+CI4/CI6 -> 0.98135285 | CK7: =+CK4/CK6 -> 0.90947495 | CL7: =+CL4/CL6 -> 0.98135285 | CQ7: =+CQ4/CQ6 -> 0.90947495 | CR7: =+CR4/CR6 -> 0.98135285 | CT7: =+CT4/CT6 -> 0.90947495 | CU7: =+CU4/CU6 -> 0.98135285 | CZ7: =+CZ4/CZ6 -> 0.90947495 | DA7: =+DA4/DA6 -> 0.98135285 | DC7: =+DC4/DC6 -> 0.90947495 | DD7: =+DD4/DD6 -> 0.98135285 | DI7: =+DI4/DI6 -> 0.90947495 | DJ7: =+DJ4/DJ6 -> 0.98135285 | DL7: =+DL4/DL6 -> 0.90947495 | DM7: =+DM4/DM6 -> 0.98135285
J8: Inline Rate | N8: ='Inline Rates'!J8 -> 52.953932 | O8: N/A | Q8: ='Inline Rates'!K8 -> 52.953932 | R8: N/A | W8: =+'Inline Rates'!P8 -> 52.953932 | X8: N/A | Z8: =+'Inline Rates'!Q8 -> 52.953932 | AA8: N/A | AF8: =+'Inline Rates'!V8 -> 53.171666 | AG8: N/A | AI8: =+'Inline Rates'!W8 -> 53.02651 | AJ8: N/A | AO8: =+'Inline Rates'!AB8 -> 53.171666 | AP8: N/A | AR8: =+'Inline Rates'!AC8 -> 53.062799 | AS8: N/A | AX8: =+'Inline Rates'!AH8 -> 49.305956 | AY8: N/A | BA8: =+'Inline Rates'!AI8 -> 49.667419 | BB8: N/A | BG8: =+'Inline Rates'!AN8 -> 48.775352 | BH8: N/A | BJ8: =+'Inline Rates'!AO8 -> 51.943864 | BK8: N/A | BP8: =+'Inline Rates'!AT8 -> 54.436812 | BQ8: N/A | BS8: =+'Inline Rates'!AU8 -> 52.694099 | BT8: N/A | BY8: =+'Inline Rates'!AZ8 -> 54.436812 | BZ8: N/A | CB8: =+'Inline Rates'!BA8 -> 52.911938 | CC8: N/A | CH8: =+'Inline Rates'!BF8 -> 54.436812 | CI8: N/A | CK8: =+'Inline Rates'!BG8 -> 53.081368 | CL8: N/A | CQ8: =+'Inline Rates'!BL8 -> 53.227455 | CR8: N/A | CT8: =+'Inline Rates'!BM8 -> 52.926259 | CU8: N/A | CZ8: =+'Inline Rates'!BR8 -> 53.227455 | DA8: N/A | DC8: =+'Inline Rates'!BS8 -> 52.946736 | DD8: N/A | DI8: =+'Inline Rates'!BX8 -> 51.29149 | DJ8: N/A | DL8: =+'Inline Rates'!BY8 -> 52.256344 | DM8: N/A
I10: 12 | M10: 1 | V10: 2 | AE10: 3 | AN10: 4 | AW10: 5 | BF10: 6 | BO10: 7 | BX10: 8 | CG10: 9 | CP10: 10 | CY10: 11 | DH10: 12
C11: Tenant | F11: Suite | K11: July | L11: July | M11: JULY | Q11: Year to Date | T11: Aug | U11: Aug | V11: AUGUST | Z11: Year to Date | AC11: Sep | AD11: Sep | AE11: SEPT | AI11: Year to Date | AL11: Oct | AM11: Oct | AN11: OCT | AR11: Year to Date | AU11: Nov | AV11: Nov | AW11: NOV | BA11: Year to Date | BD11: Dec | BE11: Dec | BF11: DEC | BJ11: Year to Date | BM11: Jan | BN11: Jan | BO11: JAN | BS11: Year to Date | BV11: Feb | BW11: Feb | BX11: FEB | CB11: Year to Date | CE11: Mar | CF11: Mar | CG11: MAR | CK11: Year to Date | CN11: Apr | CO11: Apr | CP11: APR | CT11: Year to Date | CW11: May | CX11: May | CY11: MAY | DC11: Year to Date | DF11: June | DG11: June | DH11: JUNE | DL11: Year to Date | DO11: Year to Date | DQ11: Annual
C12: Name | D12: Lse Start | E12: Lse Exp. | F12: Status | G12: No. | H12: Sq Ft | I12: Month | K12: MRI | L12: Adjustment | M12: Actual | N12: Forecast | O12: Variance | Q12: Actual | R12: Forecast | S12: Variance | T12: MRI | U12: Adjustment | V12: Actual | W12: Forecast | X12: Variance | Z12: Actual | AA12: Forecast | AB12: Variance | AC12: MRI | AD12: Adjustment | AE12: Actual | AF12: Forecast | AG12: Variance | AI12: Actual | AJ12: Forecast | AK12: Variance | AL12: MRI | AM12: Adjustment | AN12: Actual | AO12: Forecast | AP12: Variance | AR12: Actual | AS12: Forecast | AT12: Variance | AU12: MRI | AV12: Adjustment | AW12: Actual | AX12: Forecast | AY12: Variance | BA12: Actual | BB12: Forecast | BC12: Variance | BD12: MRI | BE12: Adjustment | BF12: Actual | BG12: Forecast | BH12: Variance | BJ12: Actual | BK12: Forecast | BL12: Variance | BM12: MRI | BN12: Adjustment | BO12: Actual | BP12: Forecast | BQ12: Variance | BS12: Actual | BT12: Forecast | BU12: Variance | BV12: MRI | BW12: Adjustment | BX12: Actual | BY12: Forecast | BZ12: Variance | CB12: Actual | CC12: Forecast | CD12: Variance | CE12: MRI | CF12: Adjustment | CG12: Actual | CH12: Forecast | CI12: Variance | CK12: Actual | CL12: Forecast | CM12: Variance | CN12: MRI | CO12: Adjustment | CP12: Actual | CQ12: Forecast | CR12: Variance | CT12: Actual | CU12: Forecast | CV12: Variance | CW12: MRI | CX12: Adjustment | CY12: Actual | CZ12: Forecast | DA12: Variance | DC12: Actual | DD12: Forecast | DE12: Variance | DF12: MRI | DG12: Adjustment | DH12: Actual | DI12: Forecast | DJ12: Variance | DL12: Actual | DM12: Forecast | DN12: Variance | DO12: Explanation | DQ12: Forecast | DR12: Var. to FC | DS12: Explanation
C13: Inline
A14: 1 | B14: 621201-000001 | C14: Bayside Cleaners | D14: 32295 | E14: 40694 | F14: Occupied | G14: 1056 | H14: 1500 | I14: =HLOOKUP(I$10,M$10:DI$53,ROW()-9,FALSE) -> 11843.75 | K14: =IF(ISERROR(VLOOKUP($B14,'MRI Data'!$A:$P,M$10+3,FALSE)),0,VLOOKUP($B14,'MRI Data'!$A:$P,M$10+3,FALSE)) -> 11388.75 | M14: =SUM(K14:L14) -> 11388.75 | N14: 11388.75 | O14: =+M14-N14 -> 0 | Q14: =+M14 -> 11388.75 | R14: =+N14 -> 11388.75 | S14: =O14 -> 0 | T14: =IF(ISERROR(VLOOKUP($B14,'MRI Data'!$A:$P,V$10+3,FALSE)),0,VLOOKUP($B14,'MRI Data'!$A:$P,V$10+3,FALSE)) -> 11388.75 | V14: =SUM(T14:U14) -> 11388.75 | W14: 11388.75 | X14: =+V14-W14 -> 0 | Z14: =+Q14+V14 -> 22777.5 | AA14: =+R14+W14 -> 22777.5 | AB14: =+Z14-AA14 -> 0 | AC14: =IF(ISERROR(VLOOKUP($B14,'MRI Data'!$A:$P,AE$10+3,FALSE)),0,VLOOKUP($B14,'MRI Data'!$A:$P,AE$10+3,FALSE)) -> 11388.75 | AE14: =SUM(AC14:AD14) -> 11388.75 | AF14: 11388.75 | AG14: =+AE14-AF14 -> 0 | AI14: =+Z14+AE14 -> 34166.25 | AJ14: =+AA14+AF14 -> 34166.25 | AK14: =+AI14-AJ14 -> 0 | AL14: =IF(ISERROR(VLOOKUP($B14,'MRI Data'!$A:$P,AN$10+3,FALSE)),0,VLOOKUP($B14,'MRI Data'!$A:$P,AN$10+3,FALSE)) -> 11388.75 | AN14: =SUM(AL14:AM14) -> 11388.75 | AO14: 11388.75 | AP14: =+AN14-AO14 -> 0 | AR14: =+AI14+AN14 -> 45555 | AS14: =+AJ14+AO14 -> 45555 | AT14: =+AR14-AS14 -> 0 | AU14: =IF(ISERROR(VLOOKUP($B14,'MRI Data'!$A:$P,AW$10+3,FALSE)),0,VLOOKUP($B14,'MRI Data'!$A:$P,AW$10+3,FALSE)) -> 11388.75 | AW14: =SUM(AU14:AV14) -> 11388.75 | AX14: 11388.75 | AY14: =+AW14-AX14 -> 0 | BA14: =+AR14+AW14 -> 56943.75 | BB14: =+AS14+AX14 -> 56943.75 | BC14: =+BA14-BB14 -> 0 | BD14: =IF(ISERROR(VLOOKUP($B14,'MRI Data'!$A:$P,BF$10+3,FALSE)),0,VLOOKUP($B14,'MRI Data'!$A:$P,BF$10+3,FALSE)) -> 11388.75 | BF14: =SUM(BD14:BE14) -> 11388.75 | BG14: 11388.75 | BH14: =+BF14-BG14 -> 0 | BJ14: =+BA14+BF14 -> 68332.5 | BK14: =+BB14+BG14 -> 68332.5 | BL14: =+BJ14-BK14 -> 0 | BM14: =IF(ISERROR(VLOOKUP($B14,'MRI Data'!$A:$P,BO$10+3,FALSE)),0,VLOOKUP($B14,'MRI Data'!$A:$P,BO$10+3,FALSE)) -> 11388.75 | BO14: =SUM(BM14:BN14) -> 11388.75 | BP14: 11389 | BQ14: =+BO14-BP14 -> -0.25 | BS14: =+BJ14+BO14 -> 79721.25 | BT14: =+BK14+BP14 -> 79721.5 | BU14: =+BS14-BT14 -> -0.25 | BV14: =IF(ISERROR(VLOOKUP($B14,'MRI Data'!$A:$P,BX$10+3,FALSE)),0,VLOOKUP($B14,'MRI Data'!$A:$P,BX$10+3,FALSE)) -> 11388.75 | BX14: =SUM(BV14:BW14) -> 11388.75 | BY14: 11389 | BZ14: =+BX14-BY14 -> -0.25 | CB14: =+BS14+BX14 -> 91110 | CC14: =+BT14+BY14 -> 91110.5 | CD14: =+CB14-CC14 -> -0.5 | CE14: =IF(ISERROR(VLOOKUP($B14,'MRI Data'!$A:$P,CG$10+3,FALSE)),0,VLOOKUP($B14,'MRI Data'!$A:$P,CG$10+3,FALSE)) -> 11388.75 | CG14: =SUM(CE14:CF14) -> 11388.75 | CH14: 11389 | CI14: =+CG14-CH14 -> -0.25 | CK14: =+CB14+CG14 -> 102498.75 | CL14: =+CC14+CH14 -> 102499.5 | CM14: =+CK14-CL14 -> -0.75 | CN14: =IF(ISERROR(VLOOKUP($B14,'MRI Data'!$A:$P,CP$10+3,FALSE)),0,VLOOKUP($B14,'MRI Data'!$A:$P,CP$10+3,FALSE)) -> 11388.75 | CP14: =SUM(CN14:CO14) -> 11388.75 | CQ14: 11389 | CR14: =+CP14-CQ14 -> -0.25 | CT14: =+CK14+CP14 -> 113887.5 | CU14: =+CL14+CQ14 -> 113888.5 | CV14: =+CT14-CU14 -> -1 | CW14: =IF(ISERROR(VLOOKUP($B14,'MRI Data'!$A:$P,CY$10+3,FALSE)),0,VLOOKUP($B14,'MRI Data'!$A:$P,CY$10+3,FALSE)) -> 11388.75 | CY14: =SUM(CW14:CX14) -> 11388.75 | CZ14: 11389 | DA14: =+CY14-CZ14 -> -0.25 | DC14: =+CT14+CY14 -> 125276.25 | DD14: =+CU14+CZ14 -> 125277.5 | DE14: =+DC14-DD14 -> -1.25 | DF14: =IF(ISERROR(VLOOKUP($B14,'MRI Data'!$A:$P,DH$10+3,FALSE)),0,VLOOKUP($B14,'MRI Data'!$A:$P,DH$10+3,FALSE)) -> 11843.75 | DH14: =SUM(DF14:DG14) -> 11843.75 | DI14: 11844 | DJ14: =+DH14-DI14 -> -0.25 | DL14: =+DC14+DH14 -> 137120 | DM14: =+DD14+DI14 -> 137121.5 | DN14: =+DL14-DM14 -> -1.5 | DQ14: =+DM14 -> 137121.5 | DR14: 0
A15: 2 | B15: 621201-000013 | C15: Carol Klein Fine Jewelry 1028 | D15: 35223 | E15: 40724 | F15: Occupied | G15: 1028 | H15: 1055 | I15: =HLOOKUP(I$10,M$10:DI$53,ROW()-9,FALSE) -> 5417.43 | K15: =IF(ISERROR(VLOOKUP($B15,'MRI Data'!$A:$P,M$10+3,FALSE)),0,VLOOKUP($B15,'MRI Data'!$A:$P,M$10+3,FALSE)) -> 5417.43 | M15: =SUM(K15:L15) -> 5417.43 | N15: 5417.43 | O15: =+M15-N15 -> 0 | Q15: =+M15 -> 5417.43 | R15: =+N15 -> 5417.43 | S15: =O15 -> 0 | T15: =IF(ISERROR(VLOOKUP($B15,'MRI Data'!$A:$P,V$10+3,FALSE)),0,VLOOKUP($B15,'MRI Data'!$A:$P,V$10+3,FALSE)) -> 5417.43 | V15: =SUM(T15:U15) -> 5417.43 | W15: 5417.43 | X15: =+V15-W15 -> 0 | Z15: =+Q15+V15 -> 10834.86 | AA15: =+R15+W15 -> 10834.86 | AB15: =+Z15-AA15 -> 0 | AC15: =IF(ISERROR(VLOOKUP($B15,'MRI Data'!$A:$P,AE$10+3,FALSE)),0,VLOOKUP($B15,'MRI Data'!$A:$P,AE$10+3,FALSE)) -> 5417.43 | AE15: =SUM(AC15:AD15) -> 5417.43 | AF15: 5417.43 | AG15: =+AE15-AF15 -> 0 | AI15: =+Z15+AE15 -> 16252.29 | AJ15: =+AA15+AF15 -> 16252.29 | AK15: =+AI15-AJ15 -> 0 | AL15: =IF(ISERROR(VLOOKUP($B15,'MRI Data'!$A:$P,AN$10+3,FALSE)),0,VLOOKUP($B15,'MRI Data'!$A:$P,AN$10+3,FALSE)) -> 5417.43 | AN15: =SUM(AL15:AM15) -> 5417.43 | AO15: 5417.43 | AP15: =+AN15-AO15 -> 0 | AR15: =+AI15+AN15 -> 21669.72 | AS15: =+AJ15+AO15 -> 21669.72 | AT15: =+AR15-AS15 -> 0 | AU15: =IF(ISERROR(VLOOKUP($B15,'MRI Data'!$A:$P,AW$10+3,FALSE)),0,VLOOKUP($B15,'MRI Data'!$A:$P,AW$10+3,FALSE)) -> 5417.43 | AW15: =SUM(AU15:AV15) -> 5417.43 | AX15: 5417.43 | AY15: =+AW15-AX15 -> 0 | BA15: =+AR15+AW15 -> 27087.15 | BB15: =+AS15+AX15 -> 27087.15 | BC15: =+BA15-BB15 -> 0 | BD15: =IF(ISERROR(VLOOKUP($B15,'MRI Data'!$A:$P,BF$10+3,FALSE)),0,VLOOKUP($B15,'MRI Data'!$A:$P,BF$10+3,FALSE)) -> 5417.43 | BF15: =SUM(BD15:BE15) -> 5417.43 | BG15: 5417.43 | BH15: =+BF15-BG15 -> 0 | BJ15: =+BA15+BF15 -> 32504.58 | BK15: =+BB15+BG15 -> 32504.58 | BL15: =+BJ15-BK15 -> 0 | BM15: =IF(ISERROR(VLOOKUP($B15,'MRI Data'!$A:$P,BO$10+3,FALSE)),0,VLOOKUP($B15,'MRI Data'!$A:$P,BO$10+3,FALSE)) -> 5417.43 | BO15: =SUM(BM15:BN15) -> 5417.43 | BP15: 5417 | BQ15: =+BO15-BP15 -> 0.43 | BS15: =+BJ15+BO15 -> 37922.01 | BT15: =+BK15+BP15 -> 37921.58 | BU15: =+BS15-BT15 -> 0.43 | BV15: =IF(ISERROR(VLOOKUP($B15,'MRI Data'!$A:$P,BX$10+3,FALSE)),0,VLOOKUP($B15,'MRI Data'!$A:$P,BX$10+3,FALSE)) -> 5417.43 | BX15: =SUM(BV15:BW15) -> 5417.43 | BY15: 5417 | BZ15: =+BX15-BY15 -> 0.43 | CB15: =+BS15+BX15 -> 43339.44 | CC15: =+BT15+BY15 -> 43338.58 | CD15: =+CB15-CC15 -> 0.86 | CE15: =IF(ISERROR(VLOOKUP($B15,'MRI Data'!$A:$P,CG$10+3,FALSE)),0,VLOOKUP($B15,'MRI Data'!$A:$P,CG$10+3,FALSE)) -> 5417.43 | CG15: =SUM(CE15:CF15) -> 5417.43 | CH15: 5417 | CI15: =+CG15-CH15 -> 0.43 | CK15: =+CB15+CG15 -> 48756.87 | CL15: =+CC15+CH15 -> 48755.58 | CM15: =+CK15-CL15 -> 1.29 | CN15: =IF(ISERROR(VLOOKUP($B15,'MRI Data'!$A:$P,CP$10+3,FALSE)),0,VLOOKUP($B15,'MRI Data'!$A:$P,CP$10+3,FALSE)) -> 5417.43 | CP15: =SUM(CN15:CO15) -> 5417.43 | CQ15: 5417 | CR15: =+CP15-CQ15 -> 0.43 | CT15: =+CK15+CP15 -> 54174.3 | CU15: =+CL15+CQ15 -> 54172.58 | CV15: =+CT15-CU15 -> 1.72 | CW15: =IF(ISERROR(VLOOKUP($B15,'MRI Data'!$A:$P,CY$10+3,FALSE)),0,VLOOKUP($B15,'MRI Data'!$A:$P,CY$10+3,FALSE)) -> 5417.43 | CY15: =SUM(CW15:CX15) -> 5417.43 | CZ15: 5417 | DA15: =+CY15-CZ15 -> 0.43 | DC15: =+CT15+CY15 -> 59591.73 | DD15: =+CU15+CZ15 -> 59589.58 | DE15: =+DC15-DD15 -> 2.15 | DF15: =IF(ISERROR(VLOOKUP($B15,'MRI Data'!$A:$P,DH$10+3,FALSE)),0,VLOOKUP($B15,'MRI Data'!$A:$P,DH$10+3,FALSE)) -> 5417.43 | DH15: =SUM(DF15:DG15) -> 5417.43 | DI15: 5417 | DJ15: =+DH15-DI15 -> 0.43 | DL15: =+DC15+DH15 -> 65009.16 | DM15: =+DD15+DI15 -> 65006.58 | DN15: =+DL15-DM15 -> 2.58 | DQ15: =+DM15 -> 65006.58 | DR15: 0
A16: 3 | B16: 621201-000004 | C16: Java City Bakery Café | D16: 34700 | E16: 41820 | F16: Occupied | G16: 1064 | H16: 1320 | I16: =HLOOKUP(I$10,M$10:DI$53,ROW()-9,FALSE) -> 6490 | K16: =IF(ISERROR(VLOOKUP($B16,'MRI Data'!$A:$P,M$10+3,FALSE)),0,VLOOKUP($B16,'MRI Data'!$A:$P,M$10+3,FALSE)) -> 6490 | M16: =SUM(K16:L16) -> 6490 | N16: 6490 | O16: =+M16-N16 -> 0 | Q16: =+M16 -> 6490 | R16: =+N16 -> 6490 | S16: =O16 -> 0 | T16: =IF(ISERROR(VLOOKUP($B16,'MRI Data'!$A:$P,V$10+3,FALSE)),0,VLOOKUP($B16,'MRI Data'!$A:$P,V$10+3,FALSE)) -> 6490 | V16: =SUM(T16:U16) -> 6490 | W16: 6490 | X16: =+V16-W16 -> 0 | Z16: =+Q16+V16 -> 12980 | AA16: =+R16+W16 -> 12980 | AB16: =+Z16-AA16 -> 0 | AC16: =IF(ISERROR(VLOOKUP($B16,'MRI Data'!$A:$P,AE$10+3,FALSE)),0,VLOOKUP($B16,'MRI Data'!$A:$P,AE$10+3,FALSE)) -> 6490 | AE16: =SUM(AC16:AD16) -> 6490 | AF16: 6490 | AG16: =+AE16-AF16 -> 0 | AI16: =+Z16+AE16 -> 19470 | AJ16: =+AA16+AF16 -> 19470 | AK16: =+AI16-AJ16 -> 0 | AL16: =IF(ISERROR(VLOOKUP($B16,'MRI Data'!$A:$P,AN$10+3,FALSE)),0,VLOOKUP($B16,'MRI Data'!$A:$P,AN$10+3,FALSE)) -> 6490 | AN16: =SUM(AL16:AM16) -> 6490 | AO16: 6490 | AP16: =+AN16-AO16 -> 0 | AR16: =+AI16+AN16 -> 25960 | AS16: =+AJ16+AO16 -> 25960 | AT16: =+AR16-AS16 -> 0 | AU16: =IF(ISERROR(VLOOKUP($B16,'MRI Data'!$A:$P,AW$10+3,FALSE)),0,VLOOKUP($B16,'MRI Data'!$A:$P,AW$10+3,FALSE)) -> 6490 | AW16: =SUM(AU16:AV16) -> 6490 | AX16: 6490 | AY16: =+AW16-AX16 -> 0 | BA16: =+AR16+AW16 -> 32450 | BB16: =+AS16+AX16 -> 32450 | BC16: =+BA16-BB16 -> 0 | BD16: =IF(ISERROR(VLOOKUP($B16,'MRI Data'!$A:$P,BF$10+3,FALSE)),0,VLOOKUP($B16,'MRI Data'!$A:$P,BF$10+3,FALSE)) -> 6490 | BF16: =SUM(BD16:BE16) -> 6490 | BG16: 6490 | BH16: =+BF16-BG16 -> 0 | BJ16: =+BA16+BF16 -> 38940 | BK16: =+BB16+BG16 -> 38940 | BL16: =+BJ16-BK16 -> 0 | BM16: =IF(ISERROR(VLOOKUP($B16,'MRI Data'!$A:$P,BO$10+3,FALSE)),0,VLOOKUP($B16,'MRI Data'!$A:$P,BO$10+3,FALSE)) -> 6490 | BO16: =SUM(BM16:BN16) -> 6490 | BP16: 6490 | BQ16: =+BO16-BP16 -> 0 | BS16: =+BJ16+BO16 -> 45430 | BT16: =+BK16+BP16 -> 45430 | BU16: =+BS16-BT16 -> 0 | BV16: =IF(ISERROR(VLOOKUP($B16,'MRI Data'!$A:$P,BX$10+3,FALSE)),0,VLOOKUP($B16,'MRI Data'!$A:$P,BX$10+3,FALSE)) -> 6490 | BX16: =SUM(BV16:BW16) -> 6490 | BY16: 6490 | BZ16: =+BX16-BY16 -> 0 | CB16: =+BS16+BX16 -> 51920 | CC16: =+BT16+BY16 -> 51920 | CD16: =+CB16-CC16 -> 0 | CE16: =IF(ISERROR(VLOOKUP($B16,'MRI Data'!$A:$P,CG$10+3,FALSE)),0,VLOOKUP($B16,'MRI Data'!$A:$P,CG$10+3,FALSE)) -> 6490 | CG16: =SUM(CE16:CF16) -> 6490 | CH16: 6490 | CI16: =+CG16-CH16 -> 0 | CK16: =+CB16+CG16 -> 58410 | CL16: =+CC16+CH16 -> 58410 | CM16: =+CK16-CL16 -> 0 | CN16: =IF(ISERROR(VLOOKUP($B16,'MRI Data'!$A:$P,CP$10+3,FALSE)),0,VLOOKUP($B16,'MRI Data'!$A:$P,CP$10+3,FALSE)) -> 6490 | CP16: =SUM(CN16:CO16) -> 6490 | CQ16: 6490 | CR16: =+CP16-CQ16 -> 0 | CT16: =+CK16+CP16 -> 64900 | CU16: =+CL16+CQ16 -> 64900 | CV16: =+CT16-CU16 -> 0 | CW16: =IF(ISERROR(VLOOKUP($B16,'MRI Data'!$A:$P,CY$10+3,FALSE)),0,VLOOKUP($B16,'MRI Data'!$A:$P,CY$10+3,FALSE)) -> 6490 | CY16: =SUM(CW16:CX16) -> 6490 | CZ16: 6490 | DA16: =+CY16-CZ16 -> 0 | DC16: =+CT16+CY16 -> 71390 | DD16: =+CU16+CZ16 -> 71390 | DE16: =+DC16-DD16 -> 0 | DF16: =IF(ISERROR(VLOOKUP($B16,'MRI Data'!$A:$P,DH$10+3,FALSE)),0,VLOOKUP($B16,'MRI Data'!$A:$P,DH$10+3,FALSE)) -> 6490 | DH16: =SUM(DF16:DG16) -> 6490 | DI16: 6490 | DJ16: =+DH16-DI16 -> 0 | DL16: =+DC16+DH16 -> 77880 | DM16: =+DD16+DI16 -> 77880 | DN16: =+DL16-DM16 -> 0 | DQ16: =+DM16 -> 77880 | DR16: 0
A17: =+A16+1 -> 4 | B17: 621201-000005 | C17: Just Alterations | D17: 35217 | E17: 41243 | F17: Occupied | G17: 1032A | H17: 650 | I17: =HLOOKUP(I$10,M$10:DI$53,ROW()-9,FALSE) -> 3690.92 | K17: =IF(ISERROR(VLOOKUP($B17,'MRI Data'!$A:$P,M$10+3,FALSE)),0,VLOOKUP($B17,'MRI Data'!$A:$P,M$10+3,FALSE)) -> 3549 | M17: =SUM(K17:L17) -> 3549 | N17: 3549 | O17: =+M17-N17 -> 0 | Q17: =+M17 -> 3549 | R17: =+N17 -> 3549 | S17: =O17 -> 0 | T17: =IF(ISERROR(VLOOKUP($B17,'MRI Data'!$A:$P,V$10+3,FALSE)),0,VLOOKUP($B17,'MRI Data'!$A:$P,V$10+3,FALSE)) -> 3549 | V17: =SUM(T17:U17) -> 3549 | W17: =3549 -> 3549 | X17: =+V17-W17 -> 0 | Z17: =+Q17+V17 -> 7098 | AA17: =+R17+W17 -> 7098 | AB17: =+Z17-AA17 -> 0 | AC17: =IF(ISERROR(VLOOKUP($B17,'MRI Data'!$A:$P,AE$10+3,FALSE)),0,VLOOKUP($B17,'MRI Data'!$A:$P,AE$10+3,FALSE)) -> 3549 | AE17: =SUM(AC17:AD17) -> 3549 | AF17: =3549 -> 3549 | AG17: =+AE17-AF17 -> 0 | AI17: =+Z17+AE17 -> 10647 | AJ17: =+AA17+AF17 -> 10647 | AK17: =+AI17-AJ17 -> 0 | AL17: =IF(ISERROR(VLOOKUP($B17,'MRI Data'!$A:$P,AN$10+3,FALSE)),0,VLOOKUP($B17,'MRI Data'!$A:$P,AN$10+3,FALSE)) -> 3549 | AN17: =SUM(AL17:AM17) -> 3549 | AO17: =3549 -> 3549 | AP17: =+AN17-AO17 -> 0 | AR17: =+AI17+AN17 -> 14196 | AS17: =+AJ17+AO17 -> 14196 | AT17: =+AR17-AS17 -> 0 | AU17: =IF(ISERROR(VLOOKUP($B17,'MRI Data'!$A:$P,AW$10+3,FALSE)),0,VLOOKUP($B17,'MRI Data'!$A:$P,AW$10+3,FALSE)) -> 3549 | AW17: =SUM(AU17:AV17) -> 3549 | AX17: =3549 -> 3549 | AY17: =+AW17-AX17 -> 0 | BA17: =+AR17+AW17 -> 17745 | BB17: =+AS17+AX17 -> 17745 | BC17: =+BA17-BB17 -> 0 | BD17: =IF(ISERROR(VLOOKUP($B17,'MRI Data'!$A:$P,BF$10+3,FALSE)),0,VLOOKUP($B17,'MRI Data'!$A:$P,BF$10+3,FALSE)) -> 3690.92 | BF17: =SUM(BD17:BE17) -> 3690.92 | BG17: 3690.92 | BH17: =+BF17-BG17 -> 0 | BJ17: =+BA17+BF17 -> 21435.92 | BK17: =+BB17+BG17 -> 21435.92 | BL17: =+BJ17-BK17 -> 0 | BM17: =IF(ISERROR(VLOOKUP($B17,'MRI Data'!$A:$P,BO$10+3,FALSE)),0,VLOOKUP($B17,'MRI Data'!$A:$P,BO$10+3,FALSE)) -> 3690.92 | BO17: =SUM(BM17:BN17) -> 3690.92 | BP17: 3691 | BQ17: =+BO17-BP17 -> -0.08 | BS17: =+BJ17+BO17 -> 25126.84 | BT17: =+BK17+BP17 -> 25126.92 | BU17: =+BS17-BT17 -> -0.08 | BV17: =IF(ISERROR(VLOOKUP($B17,'MRI Data'!$A:$P,BX$10+3,FALSE)),0,VLOOKUP($B17,'MRI Data'!$A:$P,BX$10+3,FALSE)) -> 3690.92 | BX17: =SUM(BV17:BW17) -> 3690.92 | BY17: 3691 | BZ17: =+BX17-BY17 -> -0.08 | CB17: =+BS17+BX17 -> 28817.76 | CC17: =+BT17+BY17 -> 28817.92 | CD17: =+CB17-CC17 -> -0.16 | CE17: =IF(ISERROR(VLOOKUP($B17,'MRI Data'!$A:$P,CG$10+3,FALSE)),0,VLOOKUP($B17,'MRI Data'!$A:$P,CG$10+3,FALSE)) -> 3690.92 | CG17: =SUM(CE17:CF17) -> 3690.92 | CH17: 3691 | CI17: =+CG17-CH17 -> -0.08 | CK17: =+CB17+CG17 -> 32508.68 | CL17: =+CC17+CH17 -> 32508.92 | CM17: =+CK17-CL17 -> -0.24 | CN17: =IF(ISERROR(VLOOKUP($B17,'MRI Data'!$A:$P,CP$10+3,FALSE)),0,VLOOKUP($B17,'MRI Data'!$A:$P,CP$10+3,FALSE)) -> 3690.92 | CP17: =SUM(CN17:CO17) -> 3690.92 | CQ17: 3691 | CR17: =+CP17-CQ17 -> -0.08 | CT17: =+CK17+CP17 -> 36199.6 | CU17: =+CL17+CQ17 -> 36199.92 | CV17: =+CT17-CU17 -> -0.32 | CW17: =IF(ISERROR(VLOOKUP($B17,'MRI Data'!$A:$P,CY$10+3,FALSE)),0,VLOOKUP($B17,'MRI Data'!$A:$P,CY$10+3,FALSE)) -> 3690.92 | CY17: =SUM(CW17:CX17) -> 3690.92 | CZ17: 3691 | DA17: =+CY17-CZ17 -> -0.08 | DC17: =+CT17+CY17 -> 39890.52 | DD17: =+CU17+CZ17 -> 39890.92 | DE17: =+DC17-DD17 -> -0.4 | DF17: =IF(ISERROR(VLOOKUP($B17,'MRI Data'!$A:$P,DH$10+3,FALSE)),0,VLOOKUP($B17,'MRI Data'!$A:$P,DH$10+3,FALSE)) -> 3690.92 | DH17: =SUM(DF17:DG17) -> 3690.92 | DI17: 3691 | DJ17: =+DH17-DI17 -> -0.08 | DL17: =+DC17+DH17 -> 43581.44 | DM17: =+DD17+DI17 -> 43581.92 | DN17: =+DL17-DM17 -> -0.48 | DQ17: =+DM17 -> 43581.92 | DR17: 0
A18: =+A17+1 -> 5 | B18: 621201-000006 | C18: Pacific Coast Floral | D18: 33574 | E18: 41090 | F18: Occupied | G18: 1072 | H18: 1080 | I18: =HLOOKUP(I$10,M$10:DI$53,ROW()-9,FALSE) -> 4825.85 | K18: =IF(ISERROR(VLOOKUP($B18,'MRI Data'!$A:$P,M$10+3,FALSE)),0,VLOOKUP($B18,'MRI Data'!$A:$P,M$10+3,FALSE)) -> 4554.24 | M18: =SUM(K18:L18) -> 4554.24 | N18: =4860-305.76 -> 4554.24 | O18: =+M18-N18 -> 0 | Q18: =+M18 -> 4554.24 | R18: =+N18 -> 4554.24 | S18: =O18 -> 0 | T18: =IF(ISERROR(VLOOKUP($B18,'MRI Data'!$A:$P,V$10+3,FALSE)),0,VLOOKUP($B18,'MRI Data'!$A:$P,V$10+3,FALSE)) -> 4860 | V18: =SUM(T18:U18) -> 4860 | W18: =4860 -> 4860 | X18: =+V18-W18 -> 0 | Z18: =+Q18+V18 -> 9414.24 | AA18: =+R18+W18 -> 9414.24 | AB18: =+Z18-AA18 -> 0 | AC18: =IF(ISERROR(VLOOKUP($B18,'MRI Data'!$A:$P,AE$10+3,FALSE)),0,VLOOKUP($B18,'MRI Data'!$A:$P,AE$10+3,FALSE)) -> 4860 | AE18: =SUM(AC18:AD18) -> 4860 | AF18: =4860 -> 4860 | AG18: =+AE18-AF18 -> 0 | AI18: =+Z18+AE18 -> 14274.24 | AJ18: =+AA18+AF18 -> 14274.24 | AK18: =+AI18-AJ18 -> 0 | AL18: =IF(ISERROR(VLOOKUP($B18,'MRI Data'!$A:$P,AN$10+3,FALSE)),0,VLOOKUP($B18,'MRI Data'!$A:$P,AN$10+3,FALSE)) -> 4860 | AN18: =SUM(AL18:AM18) -> 4860 | AO18: =4860 -> 4860 | AP18: =+AN18-AO18 -> 0 | AR18: =+AI18+AN18 -> 19134.24 | AS18: =+AJ18+AO18 -> 19134.24 | AT18: =+AR18-AS18 -> 0 | AU18: =IF(ISERROR(VLOOKUP($B18,'MRI Data'!$A:$P,AW$10+3,FALSE)),0,VLOOKUP($B18,'MRI Data'!$A:$P,AW$10+3,FALSE)) -> 4860 | AV18: =-12150+6075 -> -6075 | AW18: =SUM(AU18:AV18) -> -1215 | AX18: =4860-4860*5+2430*5+1215*5 -> -1215 | AY18: =+AW18-AX18 -> 0 | BA18: =+AR18+AW18 -> 17919.24 | BB18: =+AS18+AX18 -> 17919.24 | BC18: =+BA18-BB18 -> 0 | BD18: =IF(ISERROR(VLOOKUP($B18,'MRI Data'!$A:$P,BF$10+3,FALSE)),0,VLOOKUP($B18,'MRI Data'!$A:$P,BF$10+3,FALSE)) -> -9720 | BE18: 18711 | BF18: =SUM(BD18:BE18) -> 8991 | BG18: =4860-2430+5346-6075+7290 -> 8991 | BH18: =+BF18-BG18 -> 0 | BJ18: =+BA18+BF18 -> 26910.24 | BK18: =+BB18+BG18 -> 26910.24 | BL18: =+BJ18-BK18 -> 0 | BM18: =IF(ISERROR(VLOOKUP($B18,'MRI Data'!$A:$P,BO$10+3,FALSE)),0,VLOOKUP($B18,'MRI Data'!$A:$P,BO$10+3,FALSE)) -> 4860 | BN18: 0 | BO18: =SUM(BM18:BN18) -> 4860 | BP18: 4860 | BQ18: =+BO18-BP18 -> 0 | BS18: =+BJ18+BO18 -> 31770.24 | BT18: =+BK18+BP18 -> 31770.24 | BU18: =+BS18-BT18 -> 0 | BV18: =IF(ISERROR(VLOOKUP($B18,'MRI Data'!$A:$P,BX$10+3,FALSE)),0,VLOOKUP($B18,'MRI Data'!$A:$P,BX$10+3,FALSE)) -> 4860 | BW18: 0 | BX18: =SUM(BV18:BW18) -> 4860 | BY18: 4860 | BZ18: =+BX18-BY18 -> 0 | CB18: =+BS18+BX18 -> 36630.24 | CC18: =+BT18+BY18 -> 36630.24 | CD18: =+CB18-CC18 -> 0 | CE18: =IF(ISERROR(VLOOKUP($B18,'MRI Data'!$A:$P,CG$10+3,FALSE)),0,VLOOKUP($B18,'MRI Data'!$A:$P,CG$10+3,FALSE)) -> 4860 | CF18: 0 | CG18: =SUM(CE18:CF18) -> 4860 | CH18: 4860 | CI18: =+CG18-CH18 -> 0 | CK18: =+CB18+CG18 -> 41490.24 | CL18: =+CC18+CH18 -> 41490.24 | CM18: =+CK18-CL18 -> 0 | CN18: =IF(ISERROR(VLOOKUP($B18,'MRI Data'!$A:$P,CP$10+3,FALSE)),0,VLOOKUP($B18,'MRI Data'!$A:$P,CP$10+3,FALSE)) -> -980.2 | CO18: 2920.1 | CP18: =SUM(CN18:CO18) -> 1939.9 | CQ18: 4860 | CR18: =+CP18-CQ18 -> -2920.1 | CT18: =+CK18+CP18 -> 43430.14 | CU18: =+CL18+CQ18 -> 46350.24 | CV18: =+CT18-CU18 -> -2920.1 | CW18: =IF(ISERROR(VLOOKUP($B18,'MRI Data'!$A:$P,CY$10+3,FALSE)),0,VLOOKUP($B18,'MRI Data'!$A:$P,CY$10+3,FALSE)) -> 3492.4 | CX18: =-2920.1+3603.9 -> 683.8 | CY18: =SUM(CW18:CX18) -> 4176.2 | CZ18: 4860 | DA18: =+CY18-CZ18 -> -683.8 | DC18: =+CT18+CY18 -> 47606.34 | DD18: =+CU18+CZ18 -> 51210.24 | DE18: =+DC18-DD18 -> -3603.9 | DF18: =IF(ISERROR(VLOOKUP($B18,'MRI Data'!$A:$P,DH$10+3,FALSE)),0,VLOOKUP($B18,'MRI Data'!$A:$P,DH$10+3,FALSE)) -> 5174.2 | DG18: =-3603.9+3255.55 -> -348.35 | DH18: =SUM(DF18:DG18) -> 4825.85 | DI18: 4860 | DJ18: =+DH18-DI18 -> -34.15 | DL18: =+DC18+DH18 -> 52432.19 | DM18: =+DD18+DI18 -> 56070.24 | DN18: =+DL18-DM18 -> -3638.05 | DO18: TT rent relief extended 01/10-6/10 pay greater of 20% of sales or 50% of base rent. TT repay 1/2 of the deferral amount in a promissory note. TT rent relief extended 01/10-6/10 pay greater of 20% of sales or 50% of base rent. TT repay 1/2 of the deferral amount in a promissory note. | DQ18: =+DM18 -> 56070.24 | DR18: -3638 | DS18: TT rent relief extended 01/10-6/10 pay greater of 20% of sales or 50% of base rent. TT repay 1/2 of the deferral amount in a promissory note. TT rent relief extended 01/10-6/10 pay greater of 20% of sales or 50% of base rent. TT repay 1/2 of the deferral amount in a promissory note.
A19: =+A18+1 -> 6 | B19: 621201-000008 | C19: Photo Lab - The | D19: 35217 | E19: 41060 | F19: Occupied | G19: 1048 | H19: 900 | I19: =HLOOKUP(I$10,M$10:DI$53,ROW()-9,FALSE) -> -875 | K19: =IF(ISERROR(VLOOKUP($B19,'MRI Data'!$A:$P,M$10+3,FALSE)),0,VLOOKUP($B19,'MRI Data'!$A:$P,M$10+3,FALSE)) -> -2475 | L19: 4950 | M19: =SUM(K19:L19) -> 2475 | N19: =4950-2475 -> 2475 | O19: =+M19-N19 -> 0 | Q19: =+M19 -> 2475 | R19: =+N19 -> 2475 | S19: =O19 -> 0 | T19: =IF(ISERROR(VLOOKUP($B19,'MRI Data'!$A:$P,V$10+3,FALSE)),0,VLOOKUP($B19,'MRI Data'!$A:$P,V$10+3,FALSE)) -> 2475 | V19: =SUM(T19:U19) -> 2475 | W19: =2475 -> 2475 | X19: =+V19-W19 -> 0 | Z19: =+Q19+V19 -> 4950 | AA19: =+R19+W19 -> 4950 | AB19: =+Z19-AA19 -> 0 | AC19: =IF(ISERROR(VLOOKUP($B19,'MRI Data'!$A:$P,AE$10+3,FALSE)),0,VLOOKUP($B19,'MRI Data'!$A:$P,AE$10+3,FALSE)) -> 2475 | AE19: =SUM(AC19:AD19) -> 2475 | AF19: =2475 -> 2475 | AG19: =+AE19-AF19 -> 0 | AI19: =+Z19+AE19 -> 7425 | AJ19: =+AA19+AF19 -> 7425 | AK19: =+AI19-AJ19 -> 0 | AL19: =IF(ISERROR(VLOOKUP($B19,'MRI Data'!$A:$P,AN$10+3,FALSE)),0,VLOOKUP($B19,'MRI Data'!$A:$P,AN$10+3,FALSE)) -> 2475 | AN19: =SUM(AL19:AM19) -> 2475 | AO19: =2475 -> 2475 | AP19: =+AN19-AO19 -> 0 | AR19: =+AI19+AN19 -> 9900 | AS19: =+AJ19+AO19 -> 9900 | AT19: =+AR19-AS19 -> 0 | AU19: =IF(ISERROR(VLOOKUP($B19,'MRI Data'!$A:$P,AW$10+3,FALSE)),0,VLOOKUP($B19,'MRI Data'!$A:$P,AW$10+3,FALSE)) -> 2475 | AW19: =SUM(AU19:AV19) -> 2475 | AX19: =2475 -> 2475 | AY19: =+AW19-AX19 -> 0 | BA19: =+AR19+AW19 -> 12375 | BB19: =+AS19+AX19 -> 12375 | BC19: =+BA19-BB19 -> 0 | BD19: =IF(ISERROR(VLOOKUP($B19,'MRI Data'!$A:$P,BF$10+3,FALSE)),0,VLOOKUP($B19,'MRI Data'!$A:$P,BF$10+3,FALSE)) -> 2659.39 | BF19: =SUM(BD19:BE19) -> 2659.39 | BG19: =4950-2475+184.39 -> 2659.39 | BH19: =+BF19-BG19 -> 0 | BJ19: =+BA19+BF19 -> 15034.39 | BK19: =+BB19+BG19 -> 15034.39 | BL19: =+BJ19-BK19 -> 0 | BM19: =IF(ISERROR(VLOOKUP($B19,'MRI Data'!$A:$P,BO$10+3,FALSE)),0,VLOOKUP($B19,'MRI Data'!$A:$P,BO$10+3,FALSE)) -> 4950 | BN19: 2771.57 | BO19: =SUM(BM19:BN19) -> 7721.57 | BP19: 4950 | BQ19: =+BO19-BP19 -> 2771.57 | BS19: =+BJ19+BO19 -> 22755.96 | BT19: =+BK19+BP19 -> 19984.39 | BU19: =+BS19-BT19 -> 2771.57 | BV19: =IF(ISERROR(VLOOKUP($B19,'MRI Data'!$A:$P,BX$10+3,FALSE)),0,VLOOKUP($B19,'MRI Data'!$A:$P,BX$10+3,FALSE)) -> 7721.57 | BW19: =-2772 -> -2772 | BX19: =SUM(BV19:BW19) -> 4949.57 | BY19: 4950 | BZ19: =+BX19-BY19 -> -0.43 | CB19: =+BS19+BX19 -> 27705.53 | CC19: =+BT19+BY19 -> 24934.39 | CD19: =+CB19-CC19 -> 2771.14 | CE19: =IF(ISERROR(VLOOKUP($B19,'MRI Data'!$A:$P,CG$10+3,FALSE)),0,VLOOKUP($B19,'MRI Data'!$A:$P,CG$10+3,FALSE)) -> 4950 | CF19: 0 | CG19: =SUM(CE19:CF19) -> 4950 | CH19: 4950 | CI19: =+CG19-CH19 -> 0 | CK19: =+CB19+CG19 -> 32655.53 | CL19: =+CC19+CH19 -> 29884.39 | CM19: =+CK19-CL19 -> 2771.14 | CN19: =IF(ISERROR(VLOOKUP($B19,'MRI Data'!$A:$P,CP$10+3,FALSE)),0,VLOOKUP($B19,'MRI Data'!$A:$P,CP$10+3,FALSE)) -> 4950 | CO19: 0 | CP19: =SUM(CN19:CO19) -> 4950 | CQ19: 4950 | CR19: =+CP19-CQ19 -> 0 | CT19: =+CK19+CP19 -> 37605.53 | CU19: =+CL19+CQ19 -> 34834.39 | CV19: =+CT19-CU19 -> 2771.14 | CW19: =IF(ISERROR(VLOOKUP($B19,'MRI Data'!$A:$P,CY$10+3,FALSE)),0,VLOOKUP($B19,'MRI Data'!$A:$P,CY$10+3,FALSE)) -> 4950 | CX19: 0 | CY19: =SUM(CW19:CX19) -> 4950 | CZ19: 4950 | DA19: =+CY19-CZ19 -> 0 | DC19: =+CT19+CY19 -> 42555.53 | DD19: =+CU19+CZ19 -> 39784.39 | DE19: =+DC19-DD19 -> 2771.14 | DF19: =IF(ISERROR(VLOOKUP($B19,'MRI Data'!$A:$P,DH$10+3,FALSE)),0,VLOOKUP($B19,'MRI Data'!$A:$P,DH$10+3,FALSE)) -> -4875 | DG19: 4000 | DH19: =SUM(DF19:DG19) -> -875 | DI19: 5100 | DJ19: =+DH19-DI19 -> -5975 | DL19: =+DC19+DH19 -> 41680.53 | DM19: =+DD19+DI19 -> 44884.39 | DN19: =+DL19-DM19 -> -3203.86 | DO19: Tenant on rent relief 5/09-12/09 pay the greater of 10% of sales or 50% of base rent, actual sales greater than estimated sales. Per 6th Amendment dated 5/14/10, tenant on rent relief 3/10-9/10 pay the greater of 15% of sales or 50% of base rent. Retained SD $4K | DQ19: =+DM19 -> 44884.39 | DR19: -3204 | DS19: Per 6th Amendment dated 5/14/10, tenant on rent relief 3/10-9/10 pay the greater of 15% of sales or 50% of base rent. Retained SD $4K.
A20: =+A19+1 -> 7 | B20: 621201-S44199 | C20: Salon "L" | D20: 37838 | E20: 40786 | F20: Occupied | G20: 1040 | H20: 1500 | I20: =HLOOKUP(I$10,M$10:DI$53,ROW()-9,FALSE) -> 6468.75 | K20: =IF(ISERROR(VLOOKUP($B20,'MRI Data'!$A:$P,M$10+3,FALSE)),0,VLOOKUP($B20,'MRI Data'!$A:$P,M$10+3,FALSE)) -> 6250 | M20: =SUM(K20:L20) -> 6250 | N20: 6250 | O20: =+M20-N20 -> 0 | Q20: =+M20 -> 6250 | R20: =+N20 -> 6250 | S20: =O20 -> 0 | T20: =IF(ISERROR(VLOOKUP($B20,'MRI Data'!$A:$P,V$10+3,FALSE)),0,VLOOKUP($B20,'MRI Data'!$A:$P,V$10+3,FALSE)) -> 6250 | V20: =SUM(T20:U20) -> 6250 | W20: 6250 | X20: =+V20-W20 -> 0 | Z20: =+Q20+V20 -> 12500 | AA20: =+R20+W20 -> 12500 | AB20: =+Z20-AA20 -> 0 | AC20: =IF(ISERROR(VLOOKUP($B20,'MRI Data'!$A:$P,AE$10+3,FALSE)),0,VLOOKUP($B20,'MRI Data'!$A:$P,AE$10+3,FALSE)) -> 6468.75 | AE20: =SUM(AC20:AD20) -> 6468.75 | AF20: 6468.75 | AG20: =+AE20-AF20 -> 0 | AI20: =+Z20+AE20 -> 18968.75 | AJ20: =+AA20+AF20 -> 18968.75 | AK20: =+AI20-AJ20 -> 0 | AL20: =IF(ISERROR(VLOOKUP($B20,'MRI Data'!$A:$P,AN$10+3,FALSE)),0,VLOOKUP($B20,'MRI Data'!$A:$P,AN$10+3,FALSE)) -> 6468.75 | AN20: =SUM(AL20:AM20) -> 6468.75 | AO20: 6468.75 | AP20: =+AN20-AO20 -> 0 | AR20: =+AI20+AN20 -> 25437.5 | AS20: =+AJ20+AO20 -> 25437.5 | AT20: =+AR20-AS20 -> 0 | AU20: =IF(ISERROR(VLOOKUP($B20,'MRI Data'!$A:$P,AW$10+3,FALSE)),0,VLOOKUP($B20,'MRI Data'!$A:$P,AW$10+3,FALSE)) -> 6468.75 | AV20: =-12828.13+1737.62 -> -11090.51 | AW20: =SUM(AU20:AV20) -> -4621.76 | AX20: =6468.75-6468.75*3-6250+3828.66+3542.52+3394.57+3800 -> -4621.75 | AY20: =+AW20-AX20 -> -0.01 | BA20: =+AR20+AW20 -> 20815.74 | BB20: =+AS20+AX20 -> 20815.75 | BC20: =+BA20-BB20 -> -0.01 | BD20: =IF(ISERROR(VLOOKUP($B20,'MRI Data'!$A:$P,BF$10+3,FALSE)),0,VLOOKUP($B20,'MRI Data'!$A:$P,BF$10+3,FALSE)) -> -8640.5 | BE20: 26200 | BF20: =SUM(BD20:BE20) -> 17559.5 | BG20: =-1737.62+12828.13-13156.25+269.57+417.52+703.66+6468.75-3343.75+13534.26+1574.99 -> 17559.26 | BH20: =+BF20-BG20 -> 0.24 | BJ20: =+BA20+BF20 -> 38375.24 | BK20: =+BB20+BG20 -> 38375.01 | BL20: =+BJ20-BK20 -> 0.23 | BM20: =IF(ISERROR(VLOOKUP($B20,'MRI Data'!$A:$P,BO$10+3,FALSE)),0,VLOOKUP($B20,'MRI Data'!$A:$P,BO$10+3,FALSE)) -> 6250 | BN20: 219 | BO20: =SUM(BM20:BN20) -> 6469 | BP20: 6250 | BQ20: =+BO20-BP20 -> 219 | BS20: =+BJ20+BO20 -> 44844.24 | BT20: =+BK20+BP20 -> 44625.01 | BU20: =+BS20-BT20 -> 219.23 | BV20: =IF(ISERROR(VLOOKUP($B20,'MRI Data'!$A:$P,BX$10+3,FALSE)),0,VLOOKUP($B20,'MRI Data'!$A:$P,BX$10+3,FALSE)) -> 7794.17 | BW20: -1325 | BX20: =SUM(BV20:BW20) -> 6469.17 | BY20: 6250 | BZ20: =+BX20-BY20 -> 219.17 | CB20: =+BS20+BX20 -> 51313.41 | CC20: =+BT20+BY20 -> 50875.01 | CD20: =+CB20-CC20 -> 438.4 | CE20: =IF(ISERROR(VLOOKUP($B20,'MRI Data'!$A:$P,CG$10+3,FALSE)),0,VLOOKUP($B20,'MRI Data'!$A:$P,CG$10+3,FALSE)) -> 6250 | CF20: =219 -> 219 | CG20: =SUM(CE20:CF20) -> 6469 | CH20: 6250 | CI20: =+CG20-CH20 -> 219 | CK20: =+CB20+CG20 -> 57782.41 | CL20: =+CC20+CH20 -> 57125.01 | CM20: =+CK20-CL20 -> 657.4 | CN20: =IF(ISERROR(VLOOKUP($B20,'MRI Data'!$A:$P,CP$10+3,FALSE)),0,VLOOKUP($B20,'MRI Data'!$A:$P,CP$10+3,FALSE)) -> 6250 | CO20: =219 -> 219 | CP20: =SUM(CN20:CO20) -> 6469 | CQ20: 6250 | CR20: =+CP20-CQ20 -> 219 | CT20: =+CK20+CP20 -> 64251.41 | CU20: =+CL20+CQ20 -> 63375.01 | CV20: =+CT20-CU20 -> 876.4 | CW20: =IF(ISERROR(VLOOKUP($B20,'MRI Data'!$A:$P,CY$10+3,FALSE)),0,VLOOKUP($B20,'MRI Data'!$A:$P,CY$10+3,FALSE)) -> 6250 | CX20: 218.75 | CY20: =SUM(CW20:CX20) -> 6468.75 | CZ20: 6250 | DA20: =+CY20-CZ20 -> 218.75 | DC20: =+CT20+CY20 -> 70720.16 | DD20: =+CU20+CZ20 -> 69625.01 | DE20: =+DC20-DD20 -> 1095.15 | DF20: =IF(ISERROR(VLOOKUP($B20,'MRI Data'!$A:$P,DH$10+3,FALSE)),0,VLOOKUP($B20,'MRI Data'!$A:$P,DH$10+3,FALSE)) -> 6250 | DG20: 218.75 | DH20: =SUM(DF20:DG20) -> 6468.75 | DI20: 6250 | DJ20: =+DH20-DI20 -> 218.75 | DL20: =+DC20+DH20 -> 77188.91 | DM20: =+DD20+DI20 -> 75875.01 | DN20: =+DL20-DM20 -> 1313.9 | DO20: Increase in base rent scheduled to occur on 9/1/09 deferred until 9/1/10 | DQ20: =+DM20 -> 75875.01 | DR20: 1314 | DS20: Increase in base rent scheduled to occur on 9/1/09 deferred until 9/1/10
A21: =+A20+1 -> 8 | B21: 621201-000007 | C21: Sapori Restaurant Italiano | D21: 32674 | E21: 42735 | F21: Occupied | G21: 1080 | H21: 2742 | I21: =HLOOKUP(I$10,M$10:DI$53,ROW()-9,FALSE) -> 11425 | K21: =IF(ISERROR(VLOOKUP($B21,'MRI Data'!$A:$P,M$10+3,FALSE)),0,VLOOKUP($B21,'MRI Data'!$A:$P,M$10+3,FALSE)) -> 12770.87 | M21: =SUM(K21:L21) -> 12770.87 | N21: 12770.87 | O21: =+M21-N21 -> 0 | Q21: =+M21 -> 12770.87 | R21: =+N21 -> 12770.87 | S21: =O21 -> 0 | T21: =IF(ISERROR(VLOOKUP($B21,'MRI Data'!$A:$P,V$10+3,FALSE)),0,VLOOKUP($B21,'MRI Data'!$A:$P,V$10+3,FALSE)) -> 12770.87 | V21: =SUM(T21:U21) -> 12770.87 | W21: 12770.87 | X21: =+V21-W21 -> 0 | Z21: =+Q21+V21 -> 25541.74 | AA21: =+R21+W21 -> 25541.74 | AB21: =+Z21-AA21 -> 0 | AC21: =IF(ISERROR(VLOOKUP($B21,'MRI Data'!$A:$P,AE$10+3,FALSE)),0,VLOOKUP($B21,'MRI Data'!$A:$P,AE$10+3,FALSE)) -> 12770.87 | AE21: =SUM(AC21:AD21) -> 12770.87 | AF21: 12770.87 | AG21: =+AE21-AF21 -> 0 | AI21: =+Z21+AE21 -> 38312.61 | AJ21: =+AA21+AF21 -> 38312.61 | AK21: =+AI21-AJ21 -> 0 | AL21: =IF(ISERROR(VLOOKUP($B21,'MRI Data'!$A:$P,AN$10+3,FALSE)),0,VLOOKUP($B21,'MRI Data'!$A:$P,AN$10+3,FALSE)) -> 12770.87 | AN21: =SUM(AL21:AM21) -> 12770.87 | AO21: 12770.87 | AP21: =+AN21-AO21 -> 0 | AR21: =+AI21+AN21 -> 51083.48 | AS21: =+AJ21+AO21 -> 51083.48 | AT21: =+AR21-AS21 -> 0 | AU21: =IF(ISERROR(VLOOKUP($B21,'MRI Data'!$A:$P,AW$10+3,FALSE)),0,VLOOKUP($B21,'MRI Data'!$A:$P,AW$10+3,FALSE)) -> 12770.87 | AW21: =SUM(AU21:AV21) -> 12770.87 | AX21: 12770.87 | AY21: =+AW21-AX21 -> 0 | BA21: =+AR21+AW21 -> 63854.35 | BB21: =+AS21+AX21 -> 63854.35 | BC21: =+BA21-BB21 -> 0 | BD21: =IF(ISERROR(VLOOKUP($B21,'MRI Data'!$A:$P,BF$10+3,FALSE)),0,VLOOKUP($B21,'MRI Data'!$A:$P,BF$10+3,FALSE)) -> 12770.87 | BF21: =SUM(BD21:BE21) -> 12770.87 | BG21: 12770.87 | BH21: =+BF21-BG21 -> 0 | BJ21: =+BA21+BF21 -> 76625.22 | BK21: =+BB21+BG21 -> 76625.22 | BL21: =+BJ21-BK21 -> 0 | BM21: =IF(ISERROR(VLOOKUP($B21,'MRI Data'!$A:$P,BO$10+3,FALSE)),0,VLOOKUP($B21,'MRI Data'!$A:$P,BO$10+3,FALSE)) -> 11425 | BO21: =SUM(BM21:BN21) -> 11425 | BP21: 11425 | BQ21: =+BO21-BP21 -> 0 | BS21: =+BJ21+BO21 -> 88050.22 | BT21: =+BK21+BP21 -> 88050.22 | BU21: =+BS21-BT21 -> 0 | BV21: =IF(ISERROR(VLOOKUP($B21,'MRI Data'!$A:$P,BX$10+3,FALSE)),0,VLOOKUP($B21,'MRI Data'!$A:$P,BX$10+3,FALSE)) -> 11425 | BX21: =SUM(BV21:BW21) -> 11425 | BY21: 11425 | BZ21: =+BX21-BY21 -> 0 | CB21: =+BS21+BX21 -> 99475.22 | CC21: =+BT21+BY21 -> 99475.22 | CD21: =+CB21-CC21 -> 0 | CE21: =IF(ISERROR(VLOOKUP($B21,'MRI Data'!$A:$P,CG$10+3,FALSE)),0,VLOOKUP($B21,'MRI Data'!$A:$P,CG$10+3,FALSE)) -> 11425 | CG21: =SUM(CE21:CF21) -> 11425 | CH21: 11425 | CI21: =+CG21-CH21 -> 0 | CK21: =+CB21+CG21 -> 110900.22 | CL21: =+CC21+CH21 -> 110900.22 | CM21: =+CK21-CL21 -> 0 | CN21: =IF(ISERROR(VLOOKUP($B21,'MRI Data'!$A:$P,CP$10+3,FALSE)),0,VLOOKUP($B21,'MRI Data'!$A:$P,CP$10+3,FALSE)) -> 11425 | CP21: =SUM(CN21:CO21) -> 11425 | CQ21: 11425 | CR21: =+CP21-CQ21 -> 0 | CT21: =+CK21+CP21 -> 122325.22 | CU21: =+CL21+CQ21 -> 122325.22 | CV21: =+CT21-CU21 -> 0 | CW21: =IF(ISERROR(VLOOKUP($B21,'MRI Data'!$A:$P,CY$10+3,FALSE)),0,VLOOKUP($B21,'MRI Data'!$A:$P,CY$10+3,FALSE)) -> 11425 | CY21: =SUM(CW21:CX21) -> 11425 | CZ21: 11425 | DA21: =+CY21-CZ21 -> 0 | DC21: =+CT21+CY21 -> 133750.22 | DD21: =+CU21+CZ21 -> 133750.22 | DE21: =+DC21-DD21 -> 0 | DF21: =IF(ISERROR(VLOOKUP($B21,'MRI Data'!$A:$P,DH$10+3,FALSE)),0,VLOOKUP($B21,'MRI Data'!$A:$P,DH$10+3,FALSE)) -> 11425 | DH21: =SUM(DF21:DG21) -> 11425 | DI21: 11425 | DJ21: =+DH21-DI21 -> 0 | DL21: =+DC21+DH21 -> 145175.22 | DM21: =+DD21+DI21 -> 145175.22 | DN21: =+DL21-DM21 -> 0 | DQ21: =+DM21 -> 145175.22 | DR21: 0
A22: =+A21+1 -> 9 | C22: Sapori Restaurant Italiano-Patio | D22: 39234 | E22: 42735 | F22: Occupied | G22: 1080A | H22: 1309 | I22: =HLOOKUP(I$10,M$10:DI$53,ROW()-9,FALSE) -> 0.0001 | K22: =IF(ISERROR(VLOOKUP($B22,'MRI Data'!$A:$P,M$10+3,FALSE)),0,VLOOKUP($B22,'MRI Data'!$A:$P,M$10+3,FALSE)) -> 0 | L22: 0.0001 | M22: =SUM(K22:L22) -> 0.0001 | N22: 0.0001 | O22: =+M22-N22 -> 0 | Q22: =+M22 -> 0.0001 | R22: =+N22 -> 0.0001 | S22: =O22 -> 0 | T22: =IF(ISERROR(VLOOKUP($B22,'MRI Data'!$A:$P,V$10+3,FALSE)),0,VLOOKUP($B22,'MRI Data'!$A:$P,V$10+3,FALSE)) -> 0 | U22: 0.0001 | V22: =SUM(T22:U22) -> 0.0001 | W22: 0.0001 | X22: =+V22-W22 -> 0 | Z22: =+Q22+V22 -> 0.0002 | AA22: =+R22+W22 -> 0.0002 | AB22: =+Z22-AA22 -> 0 | AC22: =IF(ISERROR(VLOOKUP($B22,'MRI Data'!$A:$P,AE$10+3,FALSE)),0,VLOOKUP($B22,'MRI Data'!$A:$P,AE$10+3,FALSE)) -> 0 | AD22: 0.0001 | AE22: =SUM(AC22:AD22) -> 0.0001 | AF22: 0.0001 | AG22: =+AE22-AF22 -> 0 | AI22: =+Z22+AE22 -> 0.0003 | AJ22: =+AA22+AF22 -> 0.0003 | AK22: =+AI22-AJ22 -> 0 | AL22: =IF(ISERROR(VLOOKUP($B22,'MRI Data'!$A:$P,AN$10+3,FALSE)),0,VLOOKUP($B22,'MRI Data'!$A:$P,AN$10+3,FALSE)) -> 0 | AM22: 0.0001 | AN22: =SUM(AL22:AM22) -> 0.0001 | AO22: 0.0001 | AP22: =+AN22-AO22 -> 0 | AR22: =+AI22+AN22 -> 0.0004 | AS22: =+AJ22+AO22 -> 0.0004 | AT22: =+AR22-AS22 -> 0 | AU22: =IF(ISERROR(VLOOKUP($B22,'MRI Data'!$A:$P,AW$10+3,FALSE)),0,VLOOKUP($B22,'MRI Data'!$A:$P,AW$10+3,FALSE)) -> 0 | AV22: 0.0001 | AW22: =SUM(AU22:AV22) -> 0.0001 | AX22: 0.0001 | AY22: =+AW22-AX22 -> 0 | BA22: =+AR22+AW22 -> 0.0005 | BB22: =+AS22+AX22 -> 0.0005 | BC22: =+BA22-BB22 -> 0 | BD22: =IF(ISERROR(VLOOKUP($B22,'MRI Data'!$A:$P,BF$10+3,FALSE)),0,VLOOKUP($B22,'MRI Data'!$A:$P,BF$10+3,FALSE)) -> 0 | BE22: 0.0001 | BF22: =SUM(BD22:BE22) -> 0.0001 | BG22: 0.0001 | BH22: =+BF22-BG22 -> 0 | BJ22: =+BA22+BF22 -> 0.0006 | BK22: =+BB22+BG22 -> 0.0006 | BL22: =+BJ22-BK22 -> 0 | BM22: =IF(ISERROR(VLOOKUP($B22,'MRI Data'!$A:$P,BO$10+3,FALSE)),0,VLOOKUP($B22,'MRI Data'!$A:$P,BO$10+3,FALSE)) -> 0 | BN22: 0.0001 | BO22: =SUM(BM22:BN22) -> 0.0001 | BP22: 0 | BQ22: =+BO22-BP22 -> 0.0001 | BS22: =+BJ22+BO22 -> 0.0007 | BT22: =+BK22+BP22 -> 0.0006 | BU22: =+BS22-BT22 -> 0.0001 | BV22: =IF(ISERROR(VLOOKUP($B22,'MRI Data'!$A:$P,BX$10+3,FALSE)),0,VLOOKUP($B22,'MRI Data'!$A:$P,BX$10+3,FALSE)) -> 0 | BW22: 0.0001 | BX22: =SUM(BV22:BW22) -> 0.0001 | BY22: 0 | BZ22: =+BX22-BY22 -> 0.0001 | CB22: =+BS22+BX22 -> 0.0008 | CC22: =+BT22+BY22 -> 0.0006 | CD22: =+CB22-CC22 -> 0.0002 | CE22: =IF(ISERROR(VLOOKUP($B22,'MRI Data'!$A:$P,CG$10+3,FALSE)),0,VLOOKUP($B22,'MRI Data'!$A:$P,CG$10+3,FALSE)) -> 0 | CF22: 0.0001 | CG22: =SUM(CE22:CF22) -> 0.0001 | CH22: 0 | CI22: =+CG22-CH22 -> 0.0001 | CK22: =+CB22+CG22 -> 0.0009 | CL22: =+CC22+CH22 -> 0.0006 | CM22: =+CK22-CL22 -> 0.0003 | CN22: =IF(ISERROR(VLOOKUP($B22,'MRI Data'!$A:$P,CP$10+3,FALSE)),0,VLOOKUP($B22,'MRI Data'!$A:$P,CP$10+3,FALSE)) -> 0 | CO22: 0.0001 | CP22: =SUM(CN22:CO22) -> 0.0001 | CQ22: 0 | CR22: =+CP22-CQ22 -> 0.0001 | CT22: =+CK22+CP22 -> 0.001 | CU22: =+CL22+CQ22 -> 0.0006 | CV22: =+CT22-CU22 -> 0.0004 | CW22: =IF(ISERROR(VLOOKUP($B22,'MRI Data'!$A:$P,CY$10+3,FALSE)),0,VLOOKUP($B22,'MRI Data'!$A:$P,CY$10+3,FALSE)) -> 0 | CX22: 0.0001 | CY22: =SUM(CW22:CX22) -> 0.0001 | CZ22: 0 | DA22: =+CY22-CZ22 -> 0.0001 | DC22: =+CT22+CY22 -> 0.0011 | DD22: =+CU22+CZ22 -> 0.0006 | DE22: =+DC22-DD22 -> 0.0005 | DF22: =IF(ISERROR(VLOOKUP($B22,'MRI Data'!$A:$P,DH$10+3,FALSE)),0,VLOOKUP($B22,'MRI Data'!$A:$P,DH$10+3,FALSE)) -> 0 | DG22: 0.0001 | DH22: =SUM(DF22:DG22) -> 0.0001 | DI22: 0 | DJ22: =+DH22-DI22 -> 0.0001 | DL22: =+DC22+DH22 -> 0.0012 | DM22: =+DD22+DI22 -> 0.0006 | DN22: =+DL22-DM22 -> 0.0006 | DQ22: =+DM22 -> 0.0006 | DR22: 0
A23: =+A22+1 -> 10 | C23: Vacant | F23: Vacant | G23: 1024 | H23: 1200 | I23: =HLOOKUP(I$10,M$10:DI$53,ROW()-9,FALSE) -> 0 | K23: =IF(ISERROR(VLOOKUP($B23,'MRI Data'!$A:$P,M$10+3,FALSE)),0,VLOOKUP($B23,'MRI Data'!$A:$P,M$10+3,FALSE)) -> 0 | M23: =SUM(K23:L23) -> 0 | N23: 0 | O23: =+M23-N23 -> 0 | Q23: =+M23 -> 0 | R23: =+N23 -> 0 | S23: =O23 -> 0 | T23: =IF(ISERROR(VLOOKUP($B23,'MRI Data'!$A:$P,V$10+3,FALSE)),0,VLOOKUP($B23,'MRI Data'!$A:$P,V$10+3,FALSE)) -> 0 | V23: =SUM(T23:U23) -> 0 | W23: 0 | X23: =+V23-W23 -> 0 | Z23: =+Q23+V23 -> 0 | AA23: =+R23+W23 -> 0 | AB23: =+Z23-AA23 -> 0 | AC23: =IF(ISERROR(VLOOKUP($B23,'MRI Data'!$A:$P,AE$10+3,FALSE)),0,VLOOKUP($B23,'MRI Data'!$A:$P,AE$10+3,FALSE)) -> 0 | AE23: =SUM(AC23:AD23) -> 0 | AF23: 0 | AG23: =+AE23-AF23 -> 0 | AI23: =+Z23+AE23 -> 0 | AJ23: =+AA23+AF23 -> 0 | AK23: =+AI23-AJ23 -> 0 | AL23: =IF(ISERROR(VLOOKUP($B23,'MRI Data'!$A:$P,AN$10+3,FALSE)),0,VLOOKUP($B23,'MRI Data'!$A:$P,AN$10+3,FALSE)) -> 0 | AN23: =SUM(AL23:AM23) -> 0 | AO23: 0 | AP23: =+AN23-AO23 -> 0 | AR23: =+AI23+AN23 -> 0 | AS23: =+AJ23+AO23 -> 0 | AT23: =+AR23-AS23 -> 0 | AU23: =IF(ISERROR(VLOOKUP($B23,'MRI Data'!$A:$P,AW$10+3,FALSE)),0,VLOOKUP($B23,'MRI Data'!$A:$P,AW$10+3,FALSE)) -> 0 | AW23: =SUM(AU23:AV23) -> 0 | AX23: 0 | AY23: =+AW23-AX23 -> 0 | BA23: =+AR23+AW23 -> 0 | BB23: =+AS23+AX23 -> 0 | BC23: =+BA23-BB23 -> 0 | BD23: =IF(ISERROR(VLOOKUP($B23,'MRI Data'!$A:$P,BF$10+3,FALSE)),0,VLOOKUP($B23,'MRI Data'!$A:$P,BF$10+3,FALSE)) -> 0 | BF23: =SUM(BD23:BE23) -> 0 | BG23: 0 | BH23: =+BF23-BG23 -> 0 | BJ23: =+BA23+BF23 -> 0 | BK23: =+BB23+BG23 -> 0 | BL23: =+BJ23-BK23 -> 0 | BM23: =IF(ISERROR(VLOOKUP($B23,'MRI Data'!$A:$P,BO$10+3,FALSE)),0,VLOOKUP($B23,'MRI Data'!$A:$P,BO$10+3,FALSE)) -> 0 | BO23: =SUM(BM23:BN23) -> 0 | BP23: 0 | BQ23: =+BO23-BP23 -> 0 | BS23: =+BJ23+BO23 -> 0 | BT23: =+BK23+BP23 -> 0 | BU23: =+BS23-BT23 -> 0 | BV23: =IF(ISERROR(VLOOKUP($B23,'MRI Data'!$A:$P,BX$10+3,FALSE)),0,VLOOKUP($B23,'MRI Data'!$A:$P,BX$10+3,FALSE)) -> 0 | BX23: =SUM(BV23:BW23) -> 0 | BY23: 0 | BZ23: =+BX23-BY23 -> 0 | CB23: =+BS23+BX23 -> 0 | CC23: =+BT23+BY23 -> 0 | CD23: =+CB23-CC23 -> 0 | CE23: =IF(ISERROR(VLOOKUP($B23,'MRI Data'!$A:$P,CG$10+3,FALSE)),0,VLOOKUP($B23,'MRI Data'!$A:$P,CG$10+3,FALSE)) -> 0 | CG23: =SUM(CE23:CF23) -> 0 | CH23: 0 | CI23: =+CG23-CH23 -> 0 | CK23: =+CB23+CG23 -> 0 | CL23: =+CC23+CH23 -> 0 | CM23: =+CK23-CL23 -> 0 | CN23: =IF(ISERROR(VLOOKUP($B23,'MRI Data'!$A:$P,CP$10+3,FALSE)),0,VLOOKUP($B23,'MRI Data'!$A:$P,CP$10+3,FALSE)) -> 0 | CP23: =SUM(CN23:CO23) -> 0 | CQ23: 0 | CR23: =+CP23-CQ23 -> 0 | CT23: =+CK23+CP23 -> 0 | CU23: =+CL23+CQ23 -> 0 | CV23: =+CT23-CU23 -> 0 | CW23: =IF(ISERROR(VLOOKUP($B23,'MRI Data'!$A:$P,CY$10+3,FALSE)),0,VLOOKUP($B23,'MRI Data'!$A:$P,CY$10+3,FALSE)) -> 0 | CY23: =SUM(CW23:CX23) -> 0 | CZ23: 4500 | DA23: =+CY23-CZ23 -> -4500 | DC23: =+CT23+CY23 -> 0 | DD23: =+CU23+CZ23 -> 4500 | DE23: =+DC23-DD23 -> -4500 | DF23: =IF(ISERROR(VLOOKUP($B23,'MRI Data'!$A:$P,DH$10+3,FALSE)),0,VLOOKUP($B23,'MRI Data'!$A:$P,DH$10+3,FALSE)) -> 0 | DH23: =SUM(DF23:DG23) -> 0 | DI23: 4500 | DJ23: =+DH23-DI23 -> -4500 | DL23: =+DC23+DH23 -> 0 | DM23: =+DD23+DI23 -> 9000 | DN23: =+DL23-DM23 -> -9000 | DO23: Space vacant, forecasted for occupancy 5/10 | DQ23: =+DM23 -> 9000 | DR23: -9000 | DS23: Space vacant, forecasted for occupancy 5/10
A24: =+A23+1 -> 11 | I24: =HLOOKUP(I$10,M$10:DI$53,ROW()-9,FALSE) -> 0 | M24: =SUM(K24:L24) -> 0 | O24: =+M24-N24 -> 0 | Q24: =+M24 -> 0 | R24: =+N24 -> 0 | S24: =O24 -> 0 | V24: =SUM(T24:U24) -> 0 | X24: =+V24-W24 -> 0 | Z24: =+Q24+V24 -> 0 | AA24: =+R24+W24 -> 0 | AB24: =+Z24-AA24 -> 0 | AE24: =SUM(AC24:AD24) -> 0 | AG24: =+AE24-AF24 -> 0 | AI24: =+Z24+AE24 -> 0 | AJ24: =+AA24+AF24 -> 0 | AK24: =+AI24-AJ24 -> 0 | AN24: =SUM(AL24:AM24) -> 0 | AP24: =+AN24-AO24 -> 0 | AR24: =+AI24+AN24 -> 0 | AS24: =+AJ24+AO24 -> 0 | AT24: =+AR24-AS24 -> 0 | AW24: =SUM(AU24:AV24) -> 0 | AY24: =+AW24-AX24 -> 0 | BA24: =+AR24+AW24 -> 0 | BB24: =+AS24+AX24 -> 0 | BC24: =+BA24-BB24 -> 0 | BF24: =SUM(BD24:BE24) -> 0 | BH24: =+BF24-BG24 -> 0 | BJ24: =+BA24+BF24 -> 0 | BK24: =+BB24+BG24 -> 0 | BL24: =+BJ24-BK24 -> 0 | BO24: =SUM(BM24:BN24) -> 0 | BQ24: =+BO24-BP24 -> 0 | BS24: =+BJ24+BO24 -> 0 | BT24: =+BK24+BP24 -> 0 | BU24: =+BS24-BT24 -> 0 | BX24: =SUM(BV24:BW24) -> 0 | BZ24: =+BX24-BY24 -> 0 | CB24: =+BS24+BX24 -> 0 | CC24: =+BT24+BY24 -> 0 | CD24: =+CB24-CC24 -> 0 | CG24: =SUM(CE24:CF24) -> 0 | CI24: =+CG24-CH24 -> 0 | CK24: =+CB24+CG24 -> 0 | CL24: =+CC24+CH24 -> 0 | CM24: =+CK24-CL24 -> 0 | CP24: =SUM(CN24:CO24) -> 0 | CR24: =+CP24-CQ24 -> 0 | CT24: =+CK24+CP24 -> 0 | CU24: =+CL24+CQ24 -> 0 | CV24: =+CT24-CU24 -> 0 | CY24: =SUM(CW24:CX24) -> 0 | DA24: =+CY24-CZ24 -> 0 | DC24: =+CT24+CY24 -> 0 | DD24: =+CU24+CZ24 -> 0 | DE24: =+DC24-DD24 -> 0 | DH24: =SUM(DF24:DG24) -> 0 | DJ24: =+DH24-DI24 -> 0 | DL24: =+DC24+DH24 -> 0 | DM24: =+DD24+DI24 -> 0 | DN24: =+DL24-DM24 -> 0 | DQ24: =+DM24 -> 0 | DR24: 0
A25: =+A24+1 -> 12 | I25: =HLOOKUP(I$10,M$10:DI$53,ROW()-9,FALSE) -> 0 | M25: =SUM(K25:L25) -> 0 | O25: =+M25-N25 -> 0 | Q25: =+M25 -> 0 | R25: =+N25 -> 0 | S25: =O25 -> 0 | V25: =SUM(T25:U25) -> 0 | X25: =+V25-W25 -> 0 | Z25: =+Q25+V25 -> 0 | AA25: =+R25+W25 -> 0 | AB25: =+Z25-AA25 -> 0 | AE25: =SUM(AC25:AD25) -> 0 | AG25: =+AE25-AF25 -> 0 | AI25: =+Z25+AE25 -> 0 | AJ25: =+AA25+AF25 -> 0 | AK25: =+AI25-AJ25 -> 0 | AN25: =SUM(AL25:AM25) -> 0 | AP25: =+AN25-AO25 -> 0 | AR25: =+AI25+AN25 -> 0 | AS25: =+AJ25+AO25 -> 0 | AT25: =+AR25-AS25 -> 0 | AW25: =SUM(AU25:AV25) -> 0 | AY25: =+AW25-AX25 -> 0 | BA25: =+AR25+AW25 -> 0 | BB25: =+AS25+AX25 -> 0 | BC25: =+BA25-BB25 -> 0 | BF25: =SUM(BD25:BE25) -> 0 | BH25: =+BF25-BG25 -> 0 | BJ25: =+BA25+BF25 -> 0 | BK25: =+BB25+BG25 -> 0 | BL25: =+BJ25-BK25 -> 0 | BO25: =SUM(BM25:BN25) -> 0 | BQ25: =+BO25-BP25 -> 0 | BS25: =+BJ25+BO25 -> 0 | BT25: =+BK25+BP25 -> 0 | BU25: =+BS25-BT25 -> 0 | BX25: =SUM(BV25:BW25) -> 0 | BZ25: =+BX25-BY25 -> 0 | CB25: =+BS25+BX25 -> 0 | CC25: =+BT25+BY25 -> 0 | CD25: =+CB25-CC25 -> 0 | CG25: =SUM(CE25:CF25) -> 0 | CI25: =+CG25-CH25 -> 0 | CK25: =+CB25+CG25 -> 0 | CL25: =+CC25+CH25 -> 0 | CM25: =+CK25-CL25 -> 0 | CP25: =SUM(CN25:CO25) -> 0 | CR25: =+CP25-CQ25 -> 0 | CT25: =+CK25+CP25 -> 0 | CU25: =+CL25+CQ25 -> 0 | CV25: =+CT25-CU25 -> 0 | CY25: =SUM(CW25:CX25) -> 0 | DA25: =+CY25-CZ25 -> 0 | DC25: =+CT25+CY25 -> 0 | DD25: =+CU25+CZ25 -> 0 | DE25: =+DC25-DD25 -> 0 | DH25: =SUM(DF25:DG25) -> 0 | DJ25: =+DH25-DI25 -> 0 | DL25: =+DC25+DH25 -> 0 | DM25: =+DD25+DI25 -> 0 | DN25: =+DL25-DM25 -> 0 | DQ25: =+DM25 -> 0 | DR25: 0
A26: =+A25+1 -> 13 | I26: =HLOOKUP(I$10,M$10:DI$53,ROW()-9,FALSE) -> 0 | M26: =SUM(K26:L26) -> 0 | O26: =+M26-N26 -> 0 | Q26: =+M26 -> 0 | R26: =+N26 -> 0 | S26: =O26 -> 0 | V26: =SUM(T26:U26) -> 0 | X26: =+V26-W26 -> 0 | Z26: =+Q26+V26 -> 0 | AA26: =+R26+W26 -> 0 | AB26: =+Z26-AA26 -> 0 | AE26: =SUM(AC26:AD26) -> 0 | AG26: =+AE26-AF26 -> 0 | AI26: =+Z26+AE26 -> 0 | AJ26: =+AA26+AF26 -> 0 | AK26: =+AI26-AJ26 -> 0 | AN26: =SUM(AL26:AM26) -> 0 | AP26: =+AN26-AO26 -> 0 | AR26: =+AI26+AN26 -> 0 | AS26: =+AJ26+AO26 -> 0 | AT26: =+AR26-AS26 -> 0 | AW26: =SUM(AU26:AV26) -> 0 | AY26: =+AW26-AX26 -> 0 | BA26: =+AR26+AW26 -> 0 | BB26: =+AS26+AX26 -> 0 | BC26: =+BA26-BB26 -> 0 | BF26: =SUM(BD26:BE26) -> 0 | BH26: =+BF26-BG26 -> 0 | BJ26: =+BA26+BF26 -> 0 | BK26: =+BB26+BG26 -> 0 | BL26: =+BJ26-BK26 -> 0 | BO26: =SUM(BM26:BN26) -> 0 | BQ26: =+BO26-BP26 -> 0 | BS26: =+BJ26+BO26 -> 0 | BT26: =+BK26+BP26 -> 0 | BU26: =+BS26-BT26 -> 0 | BX26: =SUM(BV26:BW26) -> 0 | BZ26: =+BX26-BY26 -> 0 | CB26: =+BS26+BX26 -> 0 | CC26: =+BT26+BY26 -> 0 | CD26: =+CB26-CC26 -> 0 | CG26: =SUM(CE26:CF26) -> 0 | CI26: =+CG26-CH26 -> 0 | CK26: =+CB26+CG26 -> 0 | CL26: =+CC26+CH26 -> 0 | CM26: =+CK26-CL26 -> 0 | CP26: =SUM(CN26:CO26) -> 0 | CR26: =+CP26-CQ26 -> 0 | CT26: =+CK26+CP26 -> 0 | CU26: =+CL26+CQ26 -> 0 | CV26: =+CT26-CU26 -> 0 | CY26: =SUM(CW26:CX26) -> 0 | DA26: =+CY26-CZ26 -> 0 | DC26: =+CT26+CY26 -> 0 | DD26: =+CU26+CZ26 -> 0 | DE26: =+DC26-DD26 -> 0 | DH26: =SUM(DF26:DG26) -> 0 | DJ26: =+DH26-DI26 -> 0 | DL26: =+DC26+DH26 -> 0 | DM26: =+DD26+DI26 -> 0 | DN26: =+DL26-DM26 -> 0 | DQ26: =+DM26 -> 0 | DR26: 0
A27: =+A26+1 -> 14 | I27: =HLOOKUP(I$10,M$10:DI$53,ROW()-9,FALSE) -> 0 | M27: =SUM(K27:L27) -> 0 | O27: =+M27-N27 -> 0 | Q27: =+M27 -> 0 | R27: =+N27 -> 0 | S27: =O27 -> 0 | V27: =SUM(T27:U27) -> 0 | X27: =+V27-W27 -> 0 | Z27: =+Q27+V27 -> 0 | AA27: =+R27+W27 -> 0 | AB27: =+Z27-AA27 -> 0 | AE27: =SUM(AC27:AD27) -> 0 | AG27: =+AE27-AF27 -> 0 | AI27: =+Z27+AE27 -> 0 | AJ27: =+AA27+AF27 -> 0 | AK27: =+AI27-AJ27 -> 0 | AN27: =SUM(AL27:AM27) -> 0 | AP27: =+AN27-AO27 -> 0 | AR27: =+AI27+AN27 -> 0 | AS27: =+AJ27+AO27 -> 0 | AT27: =+AR27-AS27 -> 0 | AW27: =SUM(AU27:AV27) -> 0 | AY27: =+AW27-AX27 -> 0 | BA27: =+AR27+AW27 -> 0 | BB27: =+AS27+AX27 -> 0 | BC27: =+BA27-BB27 -> 0 | BF27: =SUM(BD27:BE27) -> 0 | BH27: =+BF27-BG27 -> 0 | BJ27: =+BA27+BF27 -> 0 | BK27: =+BB27+BG27 -> 0 | BL27: =+BJ27-BK27 -> 0 | BO27: =SUM(BM27:BN27) -> 0 | BQ27: =+BO27-BP27 -> 0 | BS27: =+BJ27+BO27 -> 0 | BT27: =+BK27+BP27 -> 0 | BU27: =+BS27-BT27 -> 0 | BX27: =SUM(BV27:BW27) -> 0 | BZ27: =+BX27-BY27 -> 0 | CB27: =+BS27+BX27 -> 0 | CC27: =+BT27+BY27 -> 0 | CD27: =+CB27-CC27 -> 0 | CG27: =SUM(CE27:CF27) -> 0 | CI27: =+CG27-CH27 -> 0 | CK27: =+CB27+CG27 -> 0 | CL27: =+CC27+CH27 -> 0 | CM27: =+CK27-CL27 -> 0 | CP27: =SUM(CN27:CO27) -> 0 | CR27: =+CP27-CQ27 -> 0 | CT27: =+CK27+CP27 -> 0 | CU27: =+CL27+CQ27 -> 0 | CV27: =+CT27-CU27 -> 0 | CY27: =SUM(CW27:CX27) -> 0 | DA27: =+CY27-CZ27 -> 0 | DC27: =+CT27+CY27 -> 0 | DD27: =+CU27+CZ27 -> 0 | DE27: =+DC27-DD27 -> 0 | DH27: =SUM(DF27:DG27) -> 0 | DJ27: =+DH27-DI27 -> 0 | DL27: =+DC27+DH27 -> 0 | DM27: =+DD27+DI27 -> 0 | DN27: =+DL27-DM27 -> 0 | DQ27: =+DM27 -> 0 | DR27: 0
A28: =+A27+1 -> 15 | I28: =HLOOKUP(I$10,M$10:DI$53,ROW()-9,FALSE) -> 0 | M28: =SUM(K28:L28) -> 0 | O28: =+M28-N28 -> 0 | Q28: =+M28 -> 0 | R28: =+N28 -> 0 | S28: =O28 -> 0 | V28: =SUM(T28:U28) -> 0 | X28: =+V28-W28 -> 0 | Z28: =+Q28+V28 -> 0 | AA28: =+R28+W28 -> 0 | AB28: =+Z28-AA28 -> 0 | AE28: =SUM(AC28:AD28) -> 0 | AG28: =+AE28-AF28 -> 0 | AI28: =+Z28+AE28 -> 0 | AJ28: =+AA28+AF28 -> 0 | AK28: =+AI28-AJ28 -> 0 | AN28: =SUM(AL28:AM28) -> 0 | AP28: =+AN28-AO28 -> 0 | AR28: =+AI28+AN28 -> 0 | AS28: =+AJ28+AO28 -> 0 | AT28: =+AR28-AS28 -> 0 | AW28: =SUM(AU28:AV28) -> 0 | AY28: =+AW28-AX28 -> 0 | BA28: =+AR28+AW28 -> 0 | BB28: =+AS28+AX28 -> 0 | BC28: =+BA28-BB28 -> 0 | BF28: =SUM(BD28:BE28) -> 0 | BH28: =+BF28-BG28 -> 0 | BJ28: =+BA28+BF28 -> 0 | BK28: =+BB28+BG28 -> 0 | BL28: =+BJ28-BK28 -> 0 | BO28: =SUM(BM28:BN28) -> 0 | BQ28: =+BO28-BP28 -> 0 | BS28: =+BJ28+BO28 -> 0 | BT28: =+BK28+BP28 -> 0 | BU28: =+BS28-BT28 -> 0 | BX28: =SUM(BV28:BW28) -> 0 | BZ28: =+BX28-BY28 -> 0 | CB28: =+BS28+BX28 -> 0 | CC28: =+BT28+BY28 -> 0 | CD28: =+CB28-CC28 -> 0 | CG28: =SUM(CE28:CF28) -> 0 | CI28: =+CG28-CH28 -> 0 | CK28: =+CB28+CG28 -> 0 | CL28: =+CC28+CH28 -> 0 | CM28: =+CK28-CL28 -> 0 | CP28: =SUM(CN28:CO28) -> 0 | CR28: =+CP28-CQ28 -> 0 | CT28: =+CK28+CP28 -> 0 | CU28: =+CL28+CQ28 -> 0 | CV28: =+CT28-CU28 -> 0 | CY28: =SUM(CW28:CX28) -> 0 | DA28: =+CY28-CZ28 -> 0 | DC28: =+CT28+CY28 -> 0 | DD28: =+CU28+CZ28 -> 0 | DE28: =+DC28-DD28 -> 0 | DH28: =SUM(DF28:DG28) -> 0 | DJ28: =+DH28-DI28 -> 0 | DL28: =+DC28+DH28 -> 0 | DM28: =+DD28+DI28 -> 0 | DN28: =+DL28-DM28 -> 0 | DQ28: =+DM28 -> 0
A29: =+A28+1 -> 16 | I29: =HLOOKUP(I$10,M$10:DI$53,ROW()-9,FALSE) -> 0 | M29: =SUM(K29:L29) -> 0 | O29: =+M29-N29 -> 0 | Q29: =+M29 -> 0 | R29: =+N29 -> 0 | V29: =SUM(T29:U29) -> 0 | X29: =+V29-W29 -> 0 | Z29: =+Q29+V29 -> 0 | AA29: =+R29+W29 -> 0 | AB29: =+Z29-AA29 -> 0 | AE29: =SUM(AC29:AD29) -> 0 | AG29: =+AE29-AF29 -> 0 | AI29: =+Z29+AE29 -> 0 | AJ29: =+AA29+AF29 -> 0 | AK29: =+AI29-AJ29 -> 0 | AN29: =SUM(AL29:AM29) -> 0 | AP29: =+AN29-AO29 -> 0 | AR29: =+AI29+AN29 -> 0 | AS29: =+AJ29+AO29 -> 0 | AT29: =+AR29-AS29 -> 0 | AW29: =SUM(AU29:AV29) -> 0 | AY29: =+AW29-AX29 -> 0 | BA29: =+AR29+AW29 -> 0 | BB29: =+AS29+AX29 -> 0 | BC29: =+BA29-BB29 -> 0 | BF29: =SUM(BD29:BE29) -> 0 | BH29: =+BF29-BG29 -> 0 | BJ29: =+BA29+BF29 -> 0 | BK29: =+BB29+BG29 -> 0 | BL29: =+BJ29-BK29 -> 0 | BO29: =SUM(BM29:BN29) -> 0 | BQ29: =+BO29-BP29 -> 0 | BS29: =+BJ29+BO29 -> 0 | BT29: =+BK29+BP29 -> 0 | BU29: =+BS29-BT29 -> 0 | BX29: =SUM(BV29:BW29) -> 0 | BZ29: =+BX29-BY29 -> 0 | CB29: =+BS29+BX29 -> 0 | CC29: =+BT29+BY29 -> 0 | CD29: =+CB29-CC29 -> 0 | CG29: =SUM(CE29:CF29) -> 0 | CI29: =+CG29-CH29 -> 0 | CK29: =+CB29+CG29 -> 0 | CL29: =+CC29+CH29 -> 0 | CM29: =+CK29-CL29 -> 0 | CP29: =SUM(CN29:CO29) -> 0 | CR29: =+CP29-CQ29 -> 0 | CT29: =+CK29+CP29 -> 0 | CU29: =+CL29+CQ29 -> 0 | CV29: =+CT29-CU29 -> 0 | CY29: =SUM(CW29:CX29) -> 0 | DA29: =+CY29-CZ29 -> 0 | DC29: =+CT29+CY29 -> 0 | DD29: =+CU29+CZ29 -> 0 | DE29: =+DC29-DD29 -> 0 | DH29: =SUM(DF29:DG29) -> 0 | DJ29: =+DH29-DI29 -> 0 | DL29: =+DC29+DH29 -> 0 | DM29: =+DD29+DI29 -> 0 | DN29: =+DL29-DM29 -> 0 | DQ29: =+DM29 -> 0 | DR29: 0
A30: =+A29+1 -> 17 | I30: =HLOOKUP(I$10,M$10:DI$53,ROW()-9,FALSE) -> 0 | M30: =SUM(K30:L30) -> 0 | O30: =+M30-N30 -> 0 | Q30: =+M30 -> 0 | R30: =+N30 -> 0 | S30: =O30 -> 0 | V30: =SUM(T30:U30) -> 0 | X30: =+V30-W30 -> 0 | Z30: =+Q30+V30 -> 0 | AA30: =+R30+W30 -> 0 | AB30: =+Z30-AA30 -> 0 | AE30: =SUM(AC30:AD30) -> 0 | AG30: =+AE30-AF30 -> 0 | AI30: =+Z30+AE30 -> 0 | AJ30: =+AA30+AF30 -> 0 | AK30: =+AI30-AJ30 -> 0 | AN30: =SUM(AL30:AM30) -> 0 | AP30: =+AN30-AO30 -> 0 | AR30: =+AI30+AN30 -> 0 | AS30: =+AJ30+AO30 -> 0 | AT30: =+AR30-AS30 -> 0 | AW30: =SUM(AU30:AV30) -> 0 | AY30: =+AW30-AX30 -> 0 | BA30: =+AR30+AW30 -> 0 | BB30: =+AS30+AX30 -> 0 | BC30: =+BA30-BB30 -> 0 | BF30: =SUM(BD30:BE30) -> 0 | BH30: =+BF30-BG30 -> 0 | BJ30: =+BA30+BF30 -> 0 | BK30: =+BB30+BG30 -> 0 | BL30: =+BJ30-BK30 -> 0 | BO30: =SUM(BM30:BN30) -> 0 | BQ30: =+BO30-BP30 -> 0 | BS30: =+BJ30+BO30 -> 0 | BT30: =+BK30+BP30 -> 0 | BU30: =+BS30-BT30 -> 0 | BX30: =SUM(BV30:BW30) -> 0 | BZ30: =+BX30-BY30 -> 0 | CB30: =+BS30+BX30 -> 0 | CC30: =+BT30+BY30 -> 0 | CD30: =+CB30-CC30 -> 0 | CG30: =SUM(CE30:CF30) -> 0 | CI30: =+CG30-CH30 -> 0 | CK30: =+CB30+CG30 -> 0 | CL30: =+CC30+CH30 -> 0 | CM30: =+CK30-CL30 -> 0 | CP30: =SUM(CN30:CO30) -> 0 | CR30: =+CP30-CQ30 -> 0 | CT30: =+CK30+CP30 -> 0 | CU30: =+CL30+CQ30 -> 0 | CV30: =+CT30-CU30 -> 0 | CY30: =SUM(CW30:CX30) -> 0 | DA30: =+CY30-CZ30 -> 0 | DC30: =+CT30+CY30 -> 0 | DD30: =+CU30+CZ30 -> 0 | DE30: =+DC30-DD30 -> 0 | DH30: =SUM(DF30:DG30) -> 0 | DJ30: =+DH30-DI30 -> 0 | DL30: =+DC30+DH30 -> 0 | DM30: =+DD30+DI30 -> 0 | DN30: =+DL30-DM30 -> 0 | DQ30: =+DM30 -> 0 | DR30: 0
A31: =+A30+1 -> 18 | I31: =HLOOKUP(I$10,M$10:DI$53,ROW()-9,FALSE) -> 0 | M31: =SUM(K31:L31) -> 0 | O31: =+M31-N31 -> 0 | Q31: =+M31 -> 0 | R31: =+N31 -> 0 | S31: =O31 -> 0 | V31: =SUM(T31:U31) -> 0 | X31: =+V31-W31 -> 0 | Z31: =+Q31+V31 -> 0 | AA31: =+R31+W31 -> 0 | AB31: =+Z31-AA31 -> 0 | AE31: =SUM(AC31:AD31) -> 0 | AG31: =+AE31-AF31 -> 0 | AI31: =+Z31+AE31 -> 0 | AJ31: =+AA31+AF31 -> 0 | AK31: =+AI31-AJ31 -> 0 | AN31: =SUM(AL31:AM31) -> 0 | AP31: =+AN31-AO31 -> 0 | AR31: =+AI31+AN31 -> 0 | AS31: =+AJ31+AO31 -> 0 | AT31: =+AR31-AS31 -> 0 | AW31: =SUM(AU31:AV31) -> 0 | AY31: =+AW31-AX31 -> 0 | BA31: =+AR31+AW31 -> 0 | BB31: =+AS31+AX31 -> 0 | BC31: =+BA31-BB31 -> 0 | BF31: =SUM(BD31:BE31) -> 0 | BH31: =+BF31-BG31 -> 0 | BJ31: =+BA31+BF31 -> 0 | BK31: =+BB31+BG31 -> 0 | BL31: =+BJ31-BK31 -> 0 | BO31: =SUM(BM31:BN31) -> 0 | BQ31: =+BO31-BP31 -> 0 | BS31: =+BJ31+BO31 -> 0 | BT31: =+BK31+BP31 -> 0 | BU31: =+BS31-BT31 -> 0 | BX31: =SUM(BV31:BW31) -> 0 | BZ31: =+BX31-BY31 -> 0 | CB31: =+BS31+BX31 -> 0 | CC31: =+BT31+BY31 -> 0 | CD31: =+CB31-CC31 -> 0 | CG31: =SUM(CE31:CF31) -> 0 | CI31: =+CG31-CH31 -> 0 | CK31: =+CB31+CG31 -> 0 | CL31: =+CC31+CH31 -> 0 | CM31: =+CK31-CL31 -> 0 | CP31: =SUM(CN31:CO31) -> 0 | CR31: =+CP31-CQ31 -> 0 | CT31: =+CK31+CP31 -> 0 | CU31: =+CL31+CQ31 -> 0 | CV31: =+CT31-CU31 -> 0 | CY31: =SUM(CW31:CX31) -> 0 | DA31: =+CY31-CZ31 -> 0 | DC31: =+CT31+CY31 -> 0 | DD31: =+CU31+CZ31 -> 0 | DE31: =+DC31-DD31 -> 0 | DH31: =SUM(DF31:DG31) -> 0 | DJ31: =+DH31-DI31 -> 0 | DL31: =+DC31+DH31 -> 0 | DM31: =+DD31+DI31 -> 0 | DN31: =+DL31-DM31 -> 0 | DQ31: =+DM31 -> 0 | DR31: 0
A32: =+A31+1 -> 19 | I32: =HLOOKUP(I$10,M$10:DI$53,ROW()-9,FALSE) -> 0 | M32: =SUM(K32:L32) -> 0 | O32: =+M32-N32 -> 0 | Q32: =+M32 -> 0 | R32: =+N32 -> 0 | S32: =O32 -> 0 | V32: =SUM(T32:U32) -> 0 | X32: =+V32-W32 -> 0 | Z32: =+Q32+V32 -> 0 | AA32: =+R32+W32 -> 0 | AB32: =+Z32-AA32 -> 0 | AE32: =SUM(AC32:AD32) -> 0 | AG32: =+AE32-AF32 -> 0 | AI32: =+Z32+AE32 -> 0 | AJ32: =+AA32+AF32 -> 0 | AK32: =+AI32-AJ32 -> 0 | AN32: =SUM(AL32:AM32) -> 0 | AP32: =+AN32-AO32 -> 0 | AR32: =+AI32+AN32 -> 0 | AS32: =+AJ32+AO32 -> 0 | AT32: =+AR32-AS32 -> 0 | AW32: =SUM(AU32:AV32) -> 0 | AY32: =+AW32-AX32 -> 0 | BA32: =+AR32+AW32 -> 0 | BB32: =+AS32+AX32 -> 0 | BC32: =+BA32-BB32 -> 0 | BF32: =SUM(BD32:BE32) -> 0 | BH32: =+BF32-BG32 -> 0 | BJ32: =+BA32+BF32 -> 0 | BK32: =+BB32+BG32 -> 0 | BL32: =+BJ32-BK32 -> 0 | BO32: =SUM(BM32:BN32) -> 0 | BQ32: =+BO32-BP32 -> 0 | BS32: =+BJ32+BO32 -> 0 | BT32: =+BK32+BP32 -> 0 | BU32: =+BS32-BT32 -> 0 | BX32: =SUM(BV32:BW32) -> 0 | BZ32: =+BX32-BY32 -> 0 | CB32: =+BS32+BX32 -> 0 | CC32: =+BT32+BY32 -> 0 | CD32: =+CB32-CC32 -> 0 | CG32: =SUM(CE32:CF32) -> 0 | CI32: =+CG32-CH32 -> 0 | CK32: =+CB32+CG32 -> 0 | CL32: =+CC32+CH32 -> 0 | CM32: =+CK32-CL32 -> 0 | CP32: =SUM(CN32:CO32) -> 0 | CR32: =+CP32-CQ32 -> 0 | CT32: =+CK32+CP32 -> 0 | CU32: =+CL32+CQ32 -> 0 | CV32: =+CT32-CU32 -> 0 | CY32: =SUM(CW32:CX32) -> 0 | DA32: =+CY32-CZ32 -> 0 | DC32: =+CT32+CY32 -> 0 | DD32: =+CU32+CZ32 -> 0 | DE32: =+DC32-DD32 -> 0 | DH32: =SUM(DF32:DG32) -> 0 | DJ32: =+DH32-DI32 -> 0 | DL32: =+DC32+DH32 -> 0 | DM32: =+DD32+DI32 -> 0 | DN32: =+DL32-DM32 -> 0 | DQ32: =+DM32 -> 0 | DR32: 0
A33: =+A32+1 -> 20 | I33: =HLOOKUP(I$10,M$10:DI$53,ROW()-9,FALSE) -> 0 | M33: =SUM(K33:L33) -> 0 | O33: =+M33-N33 -> 0 | Q33: =+M33 -> 0 | R33: =+N33 -> 0 | S33: =O33 -> 0 | V33: =SUM(T33:U33) -> 0 | X33: =+V33-W33 -> 0 | Z33: =+Q33+V33 -> 0 | AA33: =+R33+W33 -> 0 | AB33: =+Z33-AA33 -> 0 | AE33: =SUM(AC33:AD33) -> 0 | AG33: =+AE33-AF33 -> 0 | AI33: =+Z33+AE33 -> 0 | AJ33: =+AA33+AF33 -> 0 | AK33: =+AI33-AJ33 -> 0 | AN33: =SUM(AL33:AM33) -> 0 | AP33: =+AN33-AO33 -> 0 | AR33: =+AI33+AN33 -> 0 | AS33: =+AJ33+AO33 -> 0 | AT33: =+AR33-AS33 -> 0 | AW33: =SUM(AU33:AV33) -> 0 | AY33: =+AW33-AX33 -> 0 | BA33: =+AR33+AW33 -> 0 | BB33: =+AS33+AX33 -> 0 | BC33: =+BA33-BB33 -> 0 | BF33: =SUM(BD33:BE33) -> 0 | BH33: =+BF33-BG33 -> 0 | BJ33: =+BA33+BF33 -> 0 | BK33: =+BB33+BG33 -> 0 | BL33: =+BJ33-BK33 -> 0 | BO33: =SUM(BM33:BN33) -> 0 | BQ33: =+BO33-BP33 -> 0 | BS33: =+BJ33+BO33 -> 0 | BT33: =+BK33+BP33 -> 0 | BU33: =+BS33-BT33 -> 0 | BX33: =SUM(BV33:BW33) -> 0 | BZ33: =+BX33-BY33 -> 0 | CB33: =+BS33+BX33 -> 0 | CC33: =+BT33+BY33 -> 0 | CD33: =+CB33-CC33 -> 0 | CG33: =SUM(CE33:CF33) -> 0 | CI33: =+CG33-CH33 -> 0 | CK33: =+CB33+CG33 -> 0 | CL33: =+CC33+CH33 -> 0 | CM33: =+CK33-CL33 -> 0 | CP33: =SUM(CN33:CO33) -> 0 | CR33: =+CP33-CQ33 -> 0 | CT33: =+CK33+CP33 -> 0 | CU33: =+CL33+CQ33 -> 0 | CV33: =+CT33-CU33 -> 0 | CY33: =SUM(CW33:CX33) -> 0 | DA33: =+CY33-CZ33 -> 0 | DC33: =+CT33+CY33 -> 0 | DD33: =+CU33+CZ33 -> 0 | DE33: =+DC33-DD33 -> 0 | DH33: =SUM(DF33:DG33) -> 0 | DJ33: =+DH33-DI33 -> 0 | DL33: =+DC33+DH33 -> 0 | DM33: =+DD33+DI33 -> 0 | DN33: =+DL33-DM33 -> 0 | DQ33: =+DM33 -> 0 | DR33: 0
A34: =+A33+1 -> 21 | I34: =HLOOKUP(I$10,M$10:DI$53,ROW()-9,FALSE) -> 0 | M34: =SUM(K34:L34) -> 0 | O34: =+M34-N34 -> 0 | Q34: =+M34 -> 0 | R34: =+N34 -> 0 | S34: =O34 -> 0 | V34: =SUM(T34:U34) -> 0 | X34: =+V34-W34 -> 0 | Z34: =+Q34+V34 -> 0 | AA34: =+R34+W34 -> 0 | AB34: =+Z34-AA34 -> 0 | AE34: =SUM(AC34:AD34) -> 0 | AG34: =+AE34-AF34 -> 0 | AI34: =+Z34+AE34 -> 0 | AJ34: =+AA34+AF34 -> 0 | AK34: =+AI34-AJ34 -> 0 | AN34: =SUM(AL34:AM34) -> 0 | AP34: =+AN34-AO34 -> 0 | AR34: =+AI34+AN34 -> 0 | AS34: =+AJ34+AO34 -> 0 | AT34: =+AR34-AS34 -> 0 | AW34: =SUM(AU34:AV34) -> 0 | AY34: =+AW34-AX34 -> 0 | BA34: =+AR34+AW34 -> 0 | BB34: =+AS34+AX34 -> 0 | BC34: =+BA34-BB34 -> 0 | BF34: =SUM(BD34:BE34) -> 0 | BH34: =+BF34-BG34 -> 0 | BJ34: =+BA34+BF34 -> 0 | BK34: =+BB34+BG34 -> 0 | BL34: =+BJ34-BK34 -> 0 | BO34: =SUM(BM34:BN34) -> 0 | BQ34: =+BO34-BP34 -> 0 | BS34: =+BJ34+BO34 -> 0 | BT34: =+BK34+BP34 -> 0 | BU34: =+BS34-BT34 -> 0 | BX34: =SUM(BV34:BW34) -> 0 | BZ34: =+BX34-BY34 -> 0 | CB34: =+BS34+BX34 -> 0 | CC34: =+BT34+BY34 -> 0 | CD34: =+CB34-CC34 -> 0 | CG34: =SUM(CE34:CF34) -> 0 | CI34: =+CG34-CH34 -> 0 | CK34: =+CB34+CG34 -> 0 | CL34: =+CC34+CH34 -> 0 | CM34: =+CK34-CL34 -> 0 | CP34: =SUM(CN34:CO34) -> 0 | CR34: =+CP34-CQ34 -> 0 | CT34: =+CK34+CP34 -> 0 | CU34: =+CL34+CQ34 -> 0 | CV34: =+CT34-CU34 -> 0 | CY34: =SUM(CW34:CX34) -> 0 | DA34: =+CY34-CZ34 -> 0 | DC34: =+CT34+CY34 -> 0 | DD34: =+CU34+CZ34 -> 0 | DE34: =+DC34-DD34 -> 0 | DH34: =SUM(DF34:DG34) -> 0 | DJ34: =+DH34-DI34 -> 0 | DL34: =+DC34+DH34 -> 0 | DM34: =+DD34+DI34 -> 0 | DN34: =+DL34-DM34 -> 0 | DQ34: =+DM34 -> 0 | DR34: 0
A35: =+A34+1 -> 22 | I35: =HLOOKUP(I$10,M$10:DI$53,ROW()-9,FALSE) -> 0 | M35: =SUM(K35:L35) -> 0 | O35: =+M35-N35 -> 0 | Q35: =+M35 -> 0 | R35: =+N35 -> 0 | S35: =O35 -> 0 | V35: =SUM(T35:U35) -> 0 | X35: =+V35-W35 -> 0 | Z35: =+Q35+V35 -> 0 | AA35: =+R35+W35 -> 0 | AB35: =+Z35-AA35 -> 0 | AE35: =SUM(AC35:AD35) -> 0 | AG35: =+AE35-AF35 -> 0 | AI35: =+Z35+AE35 -> 0 | AJ35: =+AA35+AF35 -> 0 | AK35: =+AI35-AJ35 -> 0 | AN35: =SUM(AL35:AM35) -> 0 | AP35: =+AN35-AO35 -> 0 | AR35: =+AI35+AN35 -> 0 | AS35: =+AJ35+AO35 -> 0 | AT35: =+AR35-AS35 -> 0 | AW35: =SUM(AU35:AV35) -> 0 | AY35: =+AW35-AX35 -> 0 | BA35: =+AR35+AW35 -> 0 | BB35: =+AS35+AX35 -> 0 | BC35: =+BA35-BB35 -> 0 | BF35: =SUM(BD35:BE35) -> 0 | BH35: =+BF35-BG35 -> 0 | BJ35: =+BA35+BF35 -> 0 | BK35: =+BB35+BG35 -> 0 | BL35: =+BJ35-BK35 -> 0 | BO35: =SUM(BM35:BN35) -> 0 | BQ35: =+BO35-BP35 -> 0 | BS35: =+BJ35+BO35 -> 0 | BT35: =+BK35+BP35 -> 0 | BU35: =+BS35-BT35 -> 0 | BX35: =SUM(BV35:BW35) -> 0 | BZ35: =+BX35-BY35 -> 0 | CB35: =+BS35+BX35 -> 0 | CC35: =+BT35+BY35 -> 0 | CD35: =+CB35-CC35 -> 0 | CG35: =SUM(CE35:CF35) -> 0 | CI35: =+CG35-CH35 -> 0 | CK35: =+CB35+CG35 -> 0 | CL35: =+CC35+CH35 -> 0 | CM35: =+CK35-CL35 -> 0 | CP35: =SUM(CN35:CO35) -> 0 | CR35: =+CP35-CQ35 -> 0 | CT35: =+CK35+CP35 -> 0 | CU35: =+CL35+CQ35 -> 0 | CV35: =+CT35-CU35 -> 0 | CY35: =SUM(CW35:CX35) -> 0 | DA35: =+CY35-CZ35 -> 0 | DC35: =+CT35+CY35 -> 0 | DD35: =+CU35+CZ35 -> 0 | DE35: =+DC35-DD35 -> 0 | DH35: =SUM(DF35:DG35) -> 0 | DJ35: =+DH35-DI35 -> 0 | DL35: =+DC35+DH35 -> 0 | DM35: =+DD35+DI35 -> 0 | DN35: =+DL35-DM35 -> 0 | DQ35: =+DM35 -> 0 | DR35: 0
A36: =+A35+1 -> 23 | I36: =HLOOKUP(I$10,M$10:DI$53,ROW()-9,FALSE) -> 0 | M36: =SUM(K36:L36) -> 0 | O36: =+M36-N36 -> 0 | Q36: =+M36 -> 0 | R36: =+N36 -> 0 | S36: =O36 -> 0 | V36: =SUM(T36:U36) -> 0 | X36: =+V36-W36 -> 0 | Z36: =+Q36+V36 -> 0 | AA36: =+R36+W36 -> 0 | AB36: =+Z36-AA36 -> 0 | AE36: =SUM(AC36:AD36) -> 0 | AG36: =+AE36-AF36 -> 0 | AI36: =+Z36+AE36 -> 0 | AJ36: =+AA36+AF36 -> 0 | AK36: =+AI36-AJ36 -> 0 | AN36: =SUM(AL36:AM36) -> 0 | AP36: =+AN36-AO36 -> 0 | AR36: =+AI36+AN36 -> 0 | AS36: =+AJ36+AO36 -> 0 | AT36: =+AR36-AS36 -> 0 | AW36: =SUM(AU36:AV36) -> 0 | AY36: =+AW36-AX36 -> 0 | BA36: =+AR36+AW36 -> 0 | BB36: =+AS36+AX36 -> 0 | BC36: =+BA36-BB36 -> 0 | BF36: =SUM(BD36:BE36) -> 0 | BH36: =+BF36-BG36 -> 0 | BJ36: =+BA36+BF36 -> 0 | BK36: =+BB36+BG36 -> 0 | BL36: =+BJ36-BK36 -> 0 | BO36: =SUM(BM36:BN36) -> 0 | BQ36: =+BO36-BP36 -> 0 | BS36: =+BJ36+BO36 -> 0 | BT36: =+BK36+BP36 -> 0 | BU36: =+BS36-BT36 -> 0 | BX36: =SUM(BV36:BW36) -> 0 | BZ36: =+BX36-BY36 -> 0 | CB36: =+BS36+BX36 -> 0 | CC36: =+BT36+BY36 -> 0 | CD36: =+CB36-CC36 -> 0 | CG36: =SUM(CE36:CF36) -> 0 | CI36: =+CG36-CH36 -> 0 | CK36: =+CB36+CG36 -> 0 | CL36: =+CC36+CH36 -> 0 | CM36: =+CK36-CL36 -> 0 | CP36: =SUM(CN36:CO36) -> 0 | CR36: =+CP36-CQ36 -> 0 | CT36: =+CK36+CP36 -> 0 | CU36: =+CL36+CQ36 -> 0 | CV36: =+CT36-CU36 -> 0 | CY36: =SUM(CW36:CX36) -> 0 | DA36: =+CY36-CZ36 -> 0 | DC36: =+CT36+CY36 -> 0 | DD36: =+CU36+CZ36 -> 0 | DE36: =+DC36-DD36 -> 0 | DH36: =SUM(DF36:DG36) -> 0 | DJ36: =+DH36-DI36 -> 0 | DL36: =+DC36+DH36 -> 0 | DM36: =+DD36+DI36 -> 0 | DN36: =+DL36-DM36 -> 0 | DQ36: =+DM36 -> 0 | DR36: 0
A37: =+A36+1 -> 24 | I37: =HLOOKUP(I$10,M$10:DI$53,ROW()-9,FALSE) -> 0 | M37: =SUM(K37:L37) -> 0 | O37: =+M37-N37 -> 0 | Q37: =+M37 -> 0 | R37: =+N37 -> 0 | S37: =O37 -> 0 | V37: =SUM(T37:U37) -> 0 | X37: =+V37-W37 -> 0 | Z37: =+Q37+V37 -> 0 | AA37: =+R37+W37 -> 0 | AB37: =+Z37-AA37 -> 0 | AE37: =SUM(AC37:AD37) -> 0 | AG37: =+AE37-AF37 -> 0 | AI37: =+Z37+AE37 -> 0 | AJ37: =+AA37+AF37 -> 0 | AK37: =+AI37-AJ37 -> 0 | AN37: =SUM(AL37:AM37) -> 0 | AP37: =+AN37-AO37 -> 0 | AR37: =+AI37+AN37 -> 0 | AS37: =+AJ37+AO37 -> 0 | AT37: =+AR37-AS37 -> 0 | AW37: =SUM(AU37:AV37) -> 0 | AY37: =+AW37-AX37 -> 0 | BA37: =+AR37+AW37 -> 0 | BB37: =+AS37+AX37 -> 0 | BC37: =+BA37-BB37 -> 0 | BF37: =SUM(BD37:BE37) -> 0 | BH37: =+BF37-BG37 -> 0 | BJ37: =+BA37+BF37 -> 0 | BK37: =+BB37+BG37 -> 0 | BL37: =+BJ37-BK37 -> 0 | BO37: =SUM(BM37:BN37) -> 0 | BQ37: =+BO37-BP37 -> 0 | BS37: =+BJ37+BO37 -> 0 | BT37: =+BK37+BP37 -> 0 | BU37: =+BS37-BT37 -> 0 | BX37: =SUM(BV37:BW37) -> 0 | BZ37: =+BX37-BY37 -> 0 | CB37: =+BS37+BX37 -> 0 | CC37: =+BT37+BY37 -> 0 | CD37: =+CB37-CC37 -> 0 | CG37: =SUM(CE37:CF37) -> 0 | CI37: =+CG37-CH37 -> 0 | CK37: =+CB37+CG37 -> 0 | CL37: =+CC37+CH37 -> 0 | CM37: =+CK37-CL37 -> 0 | CP37: =SUM(CN37:CO37) -> 0 | CR37: =+CP37-CQ37 -> 0 | CT37: =+CK37+CP37 -> 0 | CU37: =+CL37+CQ37 -> 0 | CV37: =+CT37-CU37 -> 0 | CY37: =SUM(CW37:CX37) -> 0 | DA37: =+CY37-CZ37 -> 0 | DC37: =+CT37+CY37 -> 0 | DD37: =+CU37+CZ37 -> 0 | DE37: =+DC37-DD37 -> 0 | DH37: =SUM(DF37:DG37) -> 0 | DJ37: =+DH37-DI37 -> 0 | DL37: =+DC37+DH37 -> 0 | DM37: =+DD37+DI37 -> 0 | DN37: =+DL37-DM37 -> 0 | DQ37: =+DM37 -> 0 | DR37: 0
A38: =+A37+1 -> 25 | I38: =HLOOKUP(I$10,M$10:DI$53,ROW()-9,FALSE) -> 0 | M38: =SUM(K38:L38) -> 0 | O38: =+M38-N38 -> 0 | Q38: =+M38 -> 0 | R38: =+N38 -> 0 | S38: =O38 -> 0 | V38: =SUM(T38:U38) -> 0 | X38: =+V38-W38 -> 0 | Z38: =+Q38+V38 -> 0 | AA38: =+R38+W38 -> 0 | AB38: =+Z38-AA38 -> 0 | AE38: =SUM(AC38:AD38) -> 0 | AG38: =+AE38-AF38 -> 0 | AI38: =+Z38+AE38 -> 0 | AJ38: =+AA38+AF38 -> 0 | AK38: =+AI38-AJ38 -> 0 | AN38: =SUM(AL38:AM38) -> 0 | AP38: =+AN38-AO38 -> 0 | AR38: =+AI38+AN38 -> 0 | AS38: =+AJ38+AO38 -> 0 | AT38: =+AR38-AS38 -> 0 | AW38: =SUM(AU38:AV38) -> 0 | AY38: =+AW38-AX38 -> 0 | BA38: =+AR38+AW38 -> 0 | BB38: =+AS38+AX38 -> 0 | BC38: =+BA38-BB38 -> 0 | BF38: =SUM(BD38:BE38) -> 0 | BH38: =+BF38-BG38 -> 0 | BJ38: =+BA38+BF38 -> 0 | BK38: =+BB38+BG38 -> 0 | BL38: =+BJ38-BK38 -> 0 | BO38: =SUM(BM38:BN38) -> 0 | BQ38: =+BO38-BP38 -> 0 | BS38: =+BJ38+BO38 -> 0 | BT38: =+BK38+BP38 -> 0 | BU38: =+BS38-BT38 -> 0 | BX38: =SUM(BV38:BW38) -> 0 | BZ38: =+BX38-BY38 -> 0 | CB38: =+BS38+BX38 -> 0 | CC38: =+BT38+BY38 -> 0 | CD38: =+CB38-CC38 -> 0 | CG38: =SUM(CE38:CF38) -> 0 | CI38: =+CG38-CH38 -> 0 | CK38: =+CB38+CG38 -> 0 | CL38: =+CC38+CH38 -> 0 | CM38: =+CK38-CL38 -> 0 | CP38: =SUM(CN38:CO38) -> 0 | CR38: =+CP38-CQ38 -> 0 | CT38: =+CK38+CP38 -> 0 | CU38: =+CL38+CQ38 -> 0 | CV38: =+CT38-CU38 -> 0 | CY38: =SUM(CW38:CX38) -> 0 | DA38: =+CY38-CZ38 -> 0 | DC38: =+CT38+CY38 -> 0 | DD38: =+CU38+CZ38 -> 0 | DE38: =+DC38-DD38 -> 0 | DH38: =SUM(DF38:DG38) -> 0 | DJ38: =+DH38-DI38 -> 0 | DL38: =+DC38+DH38 -> 0 | DM38: =+DD38+DI38 -> 0 | DN38: =+DL38-DM38 -> 0 | DQ38: =+DM38 -> 0 | DR38: 0
A39: =+A38+1 -> 26 | I39: =HLOOKUP(I$10,M$10:DI$53,ROW()-9,FALSE) -> 0 | M39: =SUM(K39:L39) -> 0 | N39: 0 | O39: =+M39-N39 -> 0 | Q39: =+M39 -> 0 | R39: =+N39 -> 0 | S39: =O39 -> 0 | V39: =SUM(T39:U39) -> 0 | X39: =+V39-W39 -> 0 | Z39: =+Q39+V39 -> 0 | AA39: =+R39+W39 -> 0 | AB39: =+Z39-AA39 -> 0 | AE39: =SUM(AC39:AD39) -> 0 | AG39: =+AE39-AF39 -> 0 | AI39: =+Z39+AE39 -> 0 | AJ39: =+AA39+AF39 -> 0 | AK39: =+AI39-AJ39 -> 0 | AN39: =SUM(AL39:AM39) -> 0 | AP39: =+AN39-AO39 -> 0 | AR39: =+AI39+AN39 -> 0 | AS39: =+AJ39+AO39 -> 0 | AT39: =+AR39-AS39 -> 0 | AW39: =SUM(AU39:AV39) -> 0 | AY39: =+AW39-AX39 -> 0 | BA39: =+AR39+AW39 -> 0 | BB39: =+AS39+AX39 -> 0 | BC39: =+BA39-BB39 -> 0 | BF39: =SUM(BD39:BE39) -> 0 | BH39: =+BF39-BG39 -> 0 | BJ39: =+BA39+BF39 -> 0 | BK39: =+BB39+BG39 -> 0 | BL39: =+BJ39-BK39 -> 0 | BO39: =SUM(BM39:BN39) -> 0 | BQ39: =+BO39-BP39 -> 0 | BS39: =+BJ39+BO39 -> 0 | BT39: =+BK39+BP39 -> 0 | BU39: =+BS39-BT39 -> 0 | BX39: =SUM(BV39:BW39) -> 0 | BZ39: =+BX39-BY39 -> 0 | CB39: =+BS39+BX39 -> 0 | CC39: =+BT39+BY39 -> 0 | CD39: =+CB39-CC39 -> 0 | CG39: =SUM(CE39:CF39) -> 0 | CI39: =+CG39-CH39 -> 0 | CK39: =+CB39+CG39 -> 0 | CL39: =+CC39+CH39 -> 0 | CM39: =+CK39-CL39 -> 0 | CP39: =SUM(CN39:CO39) -> 0 | CR39: =+CP39-CQ39 -> 0 | CT39: =+CK39+CP39 -> 0 | CU39: =+CL39+CQ39 -> 0 | CV39: =+CT39-CU39 -> 0 | CY39: =SUM(CW39:CX39) -> 0 | DA39: =+CY39-CZ39 -> 0 | DC39: =+CT39+CY39 -> 0 | DD39: =+CU39+CZ39 -> 0 | DE39: =+DC39-DD39 -> 0 | DH39: =SUM(DF39:DG39) -> 0 | DJ39: =+DH39-DI39 -> 0 | DL39: =+DC39+DH39 -> 0 | DM39: =+DD39+DI39 -> 0 | DN39: =+DL39-DM39 -> 0 | DQ39: =+DM39 -> 0 | DR39: 0
C42: Total In-Line | H42: =SUM(H14:H41) -> 13256 | I42: =SUM(I14:I41) -> 49286.7 | K42: =SUM(K14:K41) -> 47945.29 | L42: =SUM(L14:L41) -> 4950.0001 | M42: =SUM(M14:M41) -> 52895.29 | N42: =SUM(N14:N41) -> 52895.29 | O42: =SUM(O14:O41) -> 0 | Q42: =SUM(Q14:Q41) -> 52895.29 | R42: =SUM(R14:R41) -> 52895.29 | S42: =SUM(S14:S41) -> 0 | T42: =SUM(T14:T41) -> 53201.05 | U42: =SUM(U14:U41) -> 0.0001 | V42: =SUM(V14:V41) -> 53201.05 | W42: =SUM(W14:W41) -> 53201.05 | X42: =SUM(X14:X41) -> 0 | Z42: =SUM(Z14:Z41) -> 106096.34 | AA42: =SUM(AA14:AA41) -> 106096.34 | AB42: =SUM(AB14:AB41) -> 0 | AC42: =SUM(AC14:AC41) -> 53419.8 | AD42: =SUM(AD14:AD41) -> 0.0001 | AE42: =SUM(AE14:AE41) -> 53419.8 | AF42: =SUM(AF14:AF41) -> 53419.8 | AG42: =SUM(AG14:AG41) -> 0 | AI42: =SUM(AI14:AI41) -> 159516.14 | AJ42: =SUM(AJ14:AJ41) -> 159516.14 | AK42: =SUM(AK14:AK41) -> 0 | AL42: =SUM(AL14:AL41) -> 53419.8 | AM42: =SUM(AM14:AM41) -> 0.0001 | AN42: =SUM(AN14:AN41) -> 53419.8 | AO42: =SUM(AO14:AO41) -> 53419.8 | AP42: =SUM(AP14:AP41) -> 0 | AR42: =SUM(AR14:AR41) -> 212935.94 | AS42: =SUM(AS14:AS41) -> 212935.94 | AT42: =SUM(AT14:AT41) -> 0 | AU42: =SUM(AU14:AU41) -> 53419.8 | AV42: =SUM(AV14:AV41) -> -17165.51 | AW42: =SUM(AW14:AW41) -> 36254.29 | AX42: =SUM(AX14:AX41) -> 36254.3 | AY42: =SUM(AY14:AY41) -> -0.01 | BA42: =SUM(BA14:BA41) -> 249190.23 | BB42: =SUM(BB14:BB41) -> 249190.24 | BC42: =SUM(BC14:BC41) -> -0.01 | BD42: =SUM(BD14:BD41) -> 24056.86 | BE42: =SUM(BE14:BE41) -> 44911 | BF42: =SUM(BF14:BF41) -> 68967.86 | BG42: =SUM(BG14:BG41) -> 68967.62 | BH42: =SUM(BH14:BH41) -> 0.24 | BJ42: =SUM(BJ14:BJ41) -> 318158.09 | BK42: =SUM(BK14:BK41) -> 318157.86 | BL42: =SUM(BL14:BL41) -> 0.23 | BM42: =SUM(BM14:BM41) -> 54472.1 | BN42: =SUM(BN14:BN41) -> 2990.5701 | BO42: =SUM(BO14:BO41) -> 57462.67 | BP42: =SUM(BP14:BP41) -> 54472 | BQ42: =SUM(BQ14:BQ41) -> 2990.6701 | BS42: =SUM(BS14:BS41) -> 375620.76 | BT42: =SUM(BT14:BT41) -> 372629.86 | BU42: =SUM(BU14:BU41) -> 2990.9001 | BV42: =SUM(BV14:BV41) -> 58787.84 | BW42: =SUM(BW14:BW41) -> -4096.9999 | BX42: =SUM(BX14:BX41) -> 54690.84 | BY42: =SUM(BY14:BY41) -> 54472 | BZ42: =SUM(BZ14:BZ41) -> 218.8401 | CB42: =SUM(CB14:CB41) -> 430311.6 | CC42: =SUM(CC14:CC41) -> 427101.86 | CD42: =SUM(CD14:CD41) -> 3209.7402 | CE42: =SUM(CE14:CE41) -> 54472.1 | CF42: =SUM(CF14:CF41) -> 219.0001 | CG42: =SUM(CG14:CG41) -> 54691.1 | CH42: =SUM(CH14:CH41) -> 54472 | CI42: =SUM(CI14:CI41) -> 219.1001 | CK42: =SUM(CK14:CK41) -> 485002.7 | CL42: =SUM(CL14:CL41) -> 481573.86 | CM42: =SUM(CM14:CM41) -> 3428.8403 | CN42: =SUM(CN14:CN41) -> 48631.9 | CO42: =SUM(CO14:CO41) -> 3139.1001 | CP42: =SUM(CP14:CP41) -> 51771 | CQ42: =SUM(CQ14:CQ41) -> 54472 | CR42: =SUM(CR14:CR41) -> -2700.9999 | CT42: =SUM(CT14:CT41) -> 536773.7 | CU42: =SUM(CU14:CU41) -> 536045.86 | CV42: =SUM(CV14:CV41) -> 727.8404 | CW42: =SUM(CW14:CW41) -> 53104.5 | CX42: =SUM(CX14:CX41) -> 902.5501 | CY42: =SUM(CY14:CY41) -> 54007.05 | CZ42: =SUM(CZ14:CZ41) -> 58972 | DA42: =SUM(DA14:DA41) -> -4964.9499 | DC42: =SUM(DC14:DC41) -> 590780.75 | DD42: =SUM(DD14:DD41) -> 595017.86 | DE42: =SUM(DE14:DE41) -> -4237.1095 | DF42: =SUM(DF14:DF41) -> 45416.3 | DG42: =SUM(DG14:DG41) -> 3870.4001 | DH42: =SUM(DH14:DH41) -> 49286.7 | DI42: =SUM(DI14:DI41) -> 59577 | DJ42: =SUM(DJ14:DJ41) -> -10290.3 | DL42: =SUM(DL14:DL41) -> 640067.45 | DM42: =SUM(DM14:DM41) -> 654594.86 | DN42: =SUM(DN14:DN41) -> -14527.409 | DQ42: =SUM(DQ14:DQ41) -> 654594.86 | DR42: =SUM(DR14:DR41) -> -14528
C44: Anchor/Pads/Storage
B45: 621201-000016 | C45: Bayside Restaurant | D45: 36161 | E45: 41882 | F45: Occupied | G45: 900 | H45: 8000 | I45: =HLOOKUP(I$10,M$10:DI$53,ROW()-9,FALSE) -> 10000 | K45: =IF(ISERROR(VLOOKUP($B45,'MRI Data'!$A:$P,M$10+3,FALSE)),0,VLOOKUP($B45,'MRI Data'!$A:$P,M$10+3,FALSE)) -> 10000 | M45: =SUM(K45:L45) -> 10000 | N45: 10000 | O45: =+M45-N45 -> 0 | Q45: =+M45 -> 10000 | R45: =+N45 -> 10000 | S45: =O45 -> 0 | T45: =IF(ISERROR(VLOOKUP($B45,'MRI Data'!$A:$P,V$10+3,FALSE)),0,VLOOKUP($B45,'MRI Data'!$A:$P,V$10+3,FALSE)) -> 10000 | V45: =SUM(T45:U45) -> 10000 | W45: 10000 | X45: =+V45-W45 -> 0 | Z45: =+Q45+V45 -> 20000 | AA45: =+R45+W45 -> 20000 | AB45: =+Z45-AA45 -> 0 | AC45: =IF(ISERROR(VLOOKUP($B45,'MRI Data'!$A:$P,AE$10+3,FALSE)),0,VLOOKUP($B45,'MRI Data'!$A:$P,AE$10+3,FALSE)) -> 10000 | AE45: =SUM(AC45:AD45) -> 10000 | AF45: 10000 | AG45: =+AE45-AF45 -> 0 | AI45: =+Z45+AE45 -> 30000 | AJ45: =+AA45+AF45 -> 30000 | AK45: =+AI45-AJ45 -> 0 | AL45: =IF(ISERROR(VLOOKUP($B45,'MRI Data'!$A:$P,AN$10+3,FALSE)),0,VLOOKUP($B45,'MRI Data'!$A:$P,AN$10+3,FALSE)) -> 10000 | AN45: =SUM(AL45:AM45) -> 10000 | AO45: 10000 | AP45: =+AN45-AO45 -> 0 | AR45: =+AI45+AN45 -> 40000 | AS45: =+AJ45+AO45 -> 40000 | AT45: =+AR45-AS45 -> 0 | AU45: =IF(ISERROR(VLOOKUP($B45,'MRI Data'!$A:$P,AW$10+3,FALSE)),0,VLOOKUP($B45,'MRI Data'!$A:$P,AW$10+3,FALSE)) -> 10000 | AW45: =SUM(AU45:AV45) -> 10000 | AX45: 10000 | AY45: =+AW45-AX45 -> 0 | BA45: =+AR45+AW45 -> 50000 | BB45: =+AS45+AX45 -> 50000 | BC45: =+BA45-BB45 -> 0 | BD45: =IF(ISERROR(VLOOKUP($B45,'MRI Data'!$A:$P,BF$10+3,FALSE)),0,VLOOKUP($B45,'MRI Data'!$A:$P,BF$10+3,FALSE)) -> 10000 | BF45: =SUM(BD45:BE45) -> 10000 | BG45: 10000 | BH45: =+BF45-BG45 -> 0 | BJ45: =+BA45+BF45 -> 60000 | BK45: =+BB45+BG45 -> 60000 | BL45: =+BJ45-BK45 -> 0 | BM45: =IF(ISERROR(VLOOKUP($B45,'MRI Data'!$A:$P,BO$10+3,FALSE)),0,VLOOKUP($B45,'MRI Data'!$A:$P,BO$10+3,FALSE)) -> 10000 | BO45: =SUM(BM45:BN45) -> 10000 | BP45: 10000 | BQ45: =+BO45-BP45 -> 0 | BS45: =+BJ45+BO45 -> 70000 | BT45: =+BK45+BP45 -> 70000 | BU45: =+BS45-BT45 -> 0 | BV45: =IF(ISERROR(VLOOKUP($B45,'MRI Data'!$A:$P,BX$10+3,FALSE)),0,VLOOKUP($B45,'MRI Data'!$A:$P,BX$10+3,FALSE)) -> 10000 | BX45: =SUM(BV45:BW45) -> 10000 | BY45: 10000 | BZ45: =+BX45-BY45 -> 0 | CB45: =+BS45+BX45 -> 80000 | CC45: =+BT45+BY45 -> 80000 | CD45: =+CB45-CC45 -> 0 | CE45: =IF(ISERROR(VLOOKUP($B45,'MRI Data'!$A:$P,CG$10+3,FALSE)),0,VLOOKUP($B45,'MRI Data'!$A:$P,CG$10+3,FALSE)) -> 10000 | CG45: =SUM(CE45:CF45) -> 10000 | CH45: 10000 | CI45: =+CG45-CH45 -> 0 | CK45: =+CB45+CG45 -> 90000 | CL45: =+CC45+CH45 -> 90000 | CM45: =+CK45-CL45 -> 0 | CN45: =IF(ISERROR(VLOOKUP($B45,'MRI Data'!$A:$P,CP$10+3,FALSE)),0,VLOOKUP($B45,'MRI Data'!$A:$P,CP$10+3,FALSE)) -> 10000 | CP45: =SUM(CN45:CO45) -> 10000 | CQ45: 10000 | CR45: =+CP45-CQ45 -> 0 | CT45: =+CK45+CP45 -> 100000 | CU45: =+CL45+CQ45 -> 100000 | CV45: =+CT45-CU45 -> 0 | CW45: =IF(ISERROR(VLOOKUP($B45,'MRI Data'!$A:$P,CY$10+3,FALSE)),0,VLOOKUP($B45,'MRI Data'!$A:$P,CY$10+3,FALSE)) -> 10000 | CY45: =SUM(CW45:CX45) -> 10000 | CZ45: 10000 | DA45: =+CY45-CZ45 -> 0 | DC45: =+CT45+CY45 -> 110000 | DD45: =+CU45+CZ45 -> 110000 | DE45: =+DC45-DD45 -> 0 | DF45: =IF(ISERROR(VLOOKUP($B45,'MRI Data'!$A:$P,DH$10+3,FALSE)),0,VLOOKUP($B45,'MRI Data'!$A:$P,DH$10+3,FALSE)) -> 10000 | DH45: =SUM(DF45:DG45) -> 10000 | DI45: 10000 | DJ45: =+DH45-DI45 -> 0 | DL45: =+DC45+DH45 -> 120000 | DM45: =+DD45+DI45 -> 120000 | DN45: =+DL45-DM45 -> 0 | DQ45: =+DM45 -> 120000 | DR45: 0
B46: 621201-000009 | C46: Pavilions #235 | D46: 31564 | E46: 42521 | F46: Occupied | G46: 1000 | H46: 28734 | I46: =HLOOKUP(I$10,M$10:DI$53,ROW()-9,FALSE) -> 57468 | K46: =IF(ISERROR(VLOOKUP($B46,'MRI Data'!$A:$P,M$10+3,FALSE)),0,VLOOKUP($B46,'MRI Data'!$A:$P,M$10+3,FALSE)) -> 57468 | M46: =SUM(K46:L46) -> 57468 | N46: 57468 | O46: =+M46-N46 -> 0 | Q46: =+M46 -> 57468 | R46: =+N46 -> 57468 | S46: =O46 -> 0 | T46: =IF(ISERROR(VLOOKUP($B46,'MRI Data'!$A:$P,V$10+3,FALSE)),0,VLOOKUP($B46,'MRI Data'!$A:$P,V$10+3,FALSE)) -> 57468 | V46: =SUM(T46:U46) -> 57468 | W46: 57468 | X46: =+V46-W46 -> 0 | Z46: =+Q46+V46 -> 114936 | AA46: =+R46+W46 -> 114936 | AB46: =+Z46-AA46 -> 0 | AC46: =IF(ISERROR(VLOOKUP($B46,'MRI Data'!$A:$P,AE$10+3,FALSE)),0,VLOOKUP($B46,'MRI Data'!$A:$P,AE$10+3,FALSE)) -> 57468 | AE46: =SUM(AC46:AD46) -> 57468 | AF46: 57468 | AG46: =+AE46-AF46 -> 0 | AI46: =+Z46+AE46 -> 172404 | AJ46: =+AA46+AF46 -> 172404 | AK46: =+AI46-AJ46 -> 0 | AL46: =IF(ISERROR(VLOOKUP($B46,'MRI Data'!$A:$P,AN$10+3,FALSE)),0,VLOOKUP($B46,'MRI Data'!$A:$P,AN$10+3,FALSE)) -> 57468 | AN46: =SUM(AL46:AM46) -> 57468 | AO46: 57468 | AP46: =+AN46-AO46 -> 0 | AR46: =+AI46+AN46 -> 229872 | AS46: =+AJ46+AO46 -> 229872 | AT46: =+AR46-AS46 -> 0 | AU46: =IF(ISERROR(VLOOKUP($B46,'MRI Data'!$A:$P,AW$10+3,FALSE)),0,VLOOKUP($B46,'MRI Data'!$A:$P,AW$10+3,FALSE)) -> 57468 | AW46: =SUM(AU46:AV46) -> 57468 | AX46: 57468 | AY46: =+AW46-AX46 -> 0 | BA46: =+AR46+AW46 -> 287340 | BB46: =+AS46+AX46 -> 287340 | BC46: =+BA46-BB46 -> 0 | BD46: =IF(ISERROR(VLOOKUP($B46,'MRI Data'!$A:$P,BF$10+3,FALSE)),0,VLOOKUP($B46,'MRI Data'!$A:$P,BF$10+3,FALSE)) -> 57468 | BF46: =SUM(BD46:BE46) -> 57468 | BG46: 57468 | BH46: =+BF46-BG46 -> 0 | BJ46: =+BA46+BF46 -> 344808 | BK46: =+BB46+BG46 -> 344808 | BL46: =+BJ46-BK46 -> 0 | BM46: =IF(ISERROR(VLOOKUP($B46,'MRI Data'!$A:$P,BO$10+3,FALSE)),0,VLOOKUP($B46,'MRI Data'!$A:$P,BO$10+3,FALSE)) -> 57468 | BO46: =SUM(BM46:BN46) -> 57468 | BP46: 57468 | BQ46: =+BO46-BP46 -> 0 | BS46: =+BJ46+BO46 -> 402276 | BT46: =+BK46+BP46 -> 402276 | BU46: =+BS46-BT46 -> 0 | BV46: =IF(ISERROR(VLOOKUP($B46,'MRI Data'!$A:$P,BX$10+3,FALSE)),0,VLOOKUP($B46,'MRI Data'!$A:$P,BX$10+3,FALSE)) -> 57468 | BX46: =SUM(BV46:BW46) -> 57468 | BY46: 57468 | BZ46: =+BX46-BY46 -> 0 | CB46: =+BS46+BX46 -> 459744 | CC46: =+BT46+BY46 -> 459744 | CD46: =+CB46-CC46 -> 0 | CE46: =IF(ISERROR(VLOOKUP($B46,'MRI Data'!$A:$P,CG$10+3,FALSE)),0,VLOOKUP($B46,'MRI Data'!$A:$P,CG$10+3,FALSE)) -> 57468 | CG46: =SUM(CE46:CF46) -> 57468 | CH46: 57468 | CI46: =+CG46-CH46 -> 0 | CK46: =+CB46+CG46 -> 517212 | CL46: =+CC46+CH46 -> 517212 | CM46: =+CK46-CL46 -> 0 | CN46: =IF(ISERROR(VLOOKUP($B46,'MRI Data'!$A:$P,CP$10+3,FALSE)),0,VLOOKUP($B46,'MRI Data'!$A:$P,CP$10+3,FALSE)) -> 57468 | CP46: =SUM(CN46:CO46) -> 57468 | CQ46: 57468 | CR46: =+CP46-CQ46 -> 0 | CT46: =+CK46+CP46 -> 574680 | CU46: =+CL46+CQ46 -> 574680 | CV46: =+CT46-CU46 -> 0 | CW46: =IF(ISERROR(VLOOKUP($B46,'MRI Data'!$A:$P,CY$10+3,FALSE)),0,VLOOKUP($B46,'MRI Data'!$A:$P,CY$10+3,FALSE)) -> 57468 | CY46: =SUM(CW46:CX46) -> 57468 | CZ46: 57468 | DA46: =+CY46-CZ46 -> 0 | DC46: =+CT46+CY46 -> 632148 | DD46: =+CU46+CZ46 -> 632148 | DE46: =+DC46-DD46 -> 0 | DF46: =IF(ISERROR(VLOOKUP($B46,'MRI Data'!$A:$P,DH$10+3,FALSE)),0,VLOOKUP($B46,'MRI Data'!$A:$P,DH$10+3,FALSE)) -> 57468 | DH46: =SUM(DF46:DG46) -> 57468 | DI46: 57468 | DJ46: =+DH46-DI46 -> 0 | DL46: =+DC46+DH46 -> 689616 | DM46: =+DD46+DI46 -> 689616 | DN46: =+DL46-DM46 -> 0 | DQ46: =+DM46 -> 689616 | DR46: 0
B47: 621201-000015 | C47: Rite-Aid #5747 | D47: 35324 | E47: 45716 | F47: Occupied | G47: 1016 | H47: 8986 | I47: =HLOOKUP(I$10,M$10:DI$53,ROW()-9,FALSE) -> 56797.27 | K47: =IF(ISERROR(VLOOKUP($B47,'MRI Data'!$A:$P,M$10+3,FALSE)),0,VLOOKUP($B47,'MRI Data'!$A:$P,M$10+3,FALSE)) -> 14699.95 | M47: =SUM(K47:L47) -> 14699.95 | N47: 14699.95 | O47: =+M47-N47 -> 0 | Q47: =+M47 -> 14699.95 | R47: =+N47 -> 14699.95 | S47: =O47 -> 0 | T47: =IF(ISERROR(VLOOKUP($B47,'MRI Data'!$A:$P,V$10+3,FALSE)),0,VLOOKUP($B47,'MRI Data'!$A:$P,V$10+3,FALSE)) -> 14699.95 | V47: =SUM(T47:U47) -> 14699.95 | W47: 14699.95 | X47: =+V47-W47 -> 0 | Z47: =+Q47+V47 -> 29399.9 | AA47: =+R47+W47 -> 29399.9 | AB47: =+Z47-AA47 -> 0 | AC47: =IF(ISERROR(VLOOKUP($B47,'MRI Data'!$A:$P,AE$10+3,FALSE)),0,VLOOKUP($B47,'MRI Data'!$A:$P,AE$10+3,FALSE)) -> 14699.95 | AE47: =SUM(AC47:AD47) -> 14699.95 | AF47: 14699.95 | AG47: =+AE47-AF47 -> 0 | AI47: =+Z47+AE47 -> 44099.85 | AJ47: =+AA47+AF47 -> 44099.85 | AK47: =+AI47-AJ47 -> 0 | AL47: =IF(ISERROR(VLOOKUP($B47,'MRI Data'!$A:$P,AN$10+3,FALSE)),0,VLOOKUP($B47,'MRI Data'!$A:$P,AN$10+3,FALSE)) -> 14699.95 | AN47: =SUM(AL47:AM47) -> 14699.95 | AO47: 14699.95 | AP47: =+AN47-AO47 -> 0 | AR47: =+AI47+AN47 -> 58799.8 | AS47: =+AJ47+AO47 -> 58799.8 | AT47: =+AR47-AS47 -> 0 | AU47: =IF(ISERROR(VLOOKUP($B47,'MRI Data'!$A:$P,AW$10+3,FALSE)),0,VLOOKUP($B47,'MRI Data'!$A:$P,AW$10+3,FALSE)) -> 14699.95 | AW47: =SUM(AU47:AV47) -> 14699.95 | AX47: 14699.95 | AY47: =+AW47-AX47 -> 0 | BA47: =+AR47+AW47 -> 73499.75 | BB47: =+AS47+AX47 -> 73499.75 | BC47: =+BA47-BB47 -> 0 | BD47: =IF(ISERROR(VLOOKUP($B47,'MRI Data'!$A:$P,BF$10+3,FALSE)),0,VLOOKUP($B47,'MRI Data'!$A:$P,BF$10+3,FALSE)) -> 14699.95 | BF47: =SUM(BD47:BE47) -> 14699.95 | BG47: 14699.95 | BH47: =+BF47-BG47 -> 0 | BJ47: =+BA47+BF47 -> 88199.7 | BK47: =+BB47+BG47 -> 88199.7 | BL47: =+BJ47-BK47 -> 0 | BM47: =IF(ISERROR(VLOOKUP($B47,'MRI Data'!$A:$P,BO$10+3,FALSE)),0,VLOOKUP($B47,'MRI Data'!$A:$P,BO$10+3,FALSE)) -> 14699.95 | BO47: =SUM(BM47:BN47) -> 14699.95 | BP47: 21716 | BQ47: =+BO47-BP47 -> -7016.05 | BS47: =+BJ47+BO47 -> 102899.65 | BT47: =+BK47+BP47 -> 109915.7 | BU47: =+BS47-BT47 -> -7016.05 | BV47: =IF(ISERROR(VLOOKUP($B47,'MRI Data'!$A:$P,BX$10+3,FALSE)),0,VLOOKUP($B47,'MRI Data'!$A:$P,BX$10+3,FALSE)) -> 14699.95 | BX47: =SUM(BV47:BW47) -> 14699.95 | BY47: 21716 | BZ47: =+BX47-BY47 -> -7016.05 | CB47: =+BS47+BX47 -> 117599.6 | CC47: =+BT47+BY47 -> 131631.7 | CD47: =+CB47-CC47 -> -14032.1 | CE47: =IF(ISERROR(VLOOKUP($B47,'MRI Data'!$A:$P,CG$10+3,FALSE)),0,VLOOKUP($B47,'MRI Data'!$A:$P,CG$10+3,FALSE)) -> 14699.95 | CG47: =SUM(CE47:CF47) -> 14699.95 | CH47: 21716 | CI47: =+CG47-CH47 -> -7016.05 | CK47: =+CB47+CG47 -> 132299.55 | CL47: =+CC47+CH47 -> 153347.7 | CM47: =+CK47-CL47 -> -21048.15 | CN47: =IF(ISERROR(VLOOKUP($B47,'MRI Data'!$A:$P,CP$10+3,FALSE)),0,VLOOKUP($B47,'MRI Data'!$A:$P,CP$10+3,FALSE)) -> 14699.95 | CP47: =SUM(CN47:CO47) -> 14699.95 | CQ47: 21716 | CR47: =+CP47-CQ47 -> -7016.05 | CT47: =+CK47+CP47 -> 146999.5 | CU47: =+CL47+CQ47 -> 175063.7 | CV47: =+CT47-CU47 -> -28064.2 | CW47: =IF(ISERROR(VLOOKUP($B47,'MRI Data'!$A:$P,CY$10+3,FALSE)),0,VLOOKUP($B47,'MRI Data'!$A:$P,CY$10+3,FALSE)) -> 14699.95 | CY47: =SUM(CW47:CX47) -> 14699.95 | CZ47: 21716 | DA47: =+CY47-CZ47 -> -7016.05 | DC47: =+CT47+CY47 -> 161699.45 | DD47: =+CU47+CZ47 -> 196779.7 | DE47: =+DC47-DD47 -> -35080.25 | DF47: =IF(ISERROR(VLOOKUP($B47,'MRI Data'!$A:$P,DH$10+3,FALSE)),0,VLOOKUP($B47,'MRI Data'!$A:$P,DH$10+3,FALSE)) -> 56797.27 | DH47: =SUM(DF47:DG47) -> 56797.27 | DI47: 21716 | DJ47: =+DH47-DI47 -> 35081.27 | DL47: =+DC47+DH47 -> 218496.72 | DM47: =+DD47+DI47 -> 218495.7 | DN47: =+DL47-DM47 -> 1.02 | DQ47: =+DM47 -> 218495.7 | DR47: 0
