Workbook
Name _1: #REF!
Name _1: #REF!
Name _1_245118304: #REF!
Name _1_245118304: #REF!
Name _10: #REF!
Name _10: #REF!
Name _10: #REF!
Name _10: #REF!
Name _10: #REF!
Name _10: #REF!
Name _10: #REF!
Name _10: #REF!
Name _10: #REF!
Name _10: #REF!
Name _10_245118304: #REF!
Name _10_245118304BDR: #REF!
Name _11_245118304BDR: #REF!
Name _12_245118304BDR: #REF!
Name _13_245118304BDR: #REF!
Name _14_245118304BDR: #REF!
Name _14_245118304BDR: #REF!
Name _15_245118304BDR: #REF!
Name _15_265329000: #REF!
Name _16_245118304BDR: #REF!
Name _17_245118304BDR: #REF!
Name _18_245118304BDR: #REF!
Name _19_245118304BDR: #REF!
Name _2: #REF!
Name _2: #REF!
Name _2_245118304: #REF!
Name _2_245118304BDR: #REF!
Name _20_245118304BDR: #REF!
Name _21_265329000: #REF!
Name _21_265329000: #REF!
Name _22_265329000: #REF!
Name _23_265329000: #REF!
Name _24_265329000: #REF!
Name _25_265329000: #REF!
Name _26_265329000: #REF!
Name _27_265329000: #REF!
Name _28_265329000: #REF!
Name _29_265329000: #REF!
Name _3_245118304: #REF!
Name _3_265329000: #REF!
Name _30_265329000: #REF!
Name _4_245118304: #REF!
Name _5_245118304: #REF!
Name _5_245118304: #REF!
Name _6_245118304: #REF!
Name _7_245118304: #REF!
Name _7_245118304: #REF!
Name _8_245118304: #REF!
Name _9_245118304: #REF!
Name _dat1: #REF!
Name _dat1: #REF!
Name account_data: #REF!
Name account_data: #REF!
Name Actual_Sqft: #REF!
Name Actual_Sqft: #REF!
Name Actual_Sqft: #REF!

Sheet Pet-cash
A1: MONTHLY REPORTING REQUIREMENTS | E1: Site Reports
A6: REGENCY BRESSI, LLC
A8: Petty Cash Reconciliation
A10: For the month ended :
A11: 40816
A14: Beginning Cash Balance | F14: 0
A16: Add
A17: Funding from Chase Account | F17: 0
A20: Deduct
A21: Current Month Receipts
A23: Description | B23: Amount
F30: =SUM(B24:B30) -> 0
A35: Ending Cash Balance | F35: =SUM(F14+F17-F30) -> 0
A49: 9 | D49: MRI Implementation for Cornerstone

Sheet Bank Rec
D3: Athena Management, Inc
D4: REGENCY BRESSI, LLC - #3502
D5: Bank Reconciliation
D6: ='Pet-cash'!$A$11 -> 40816
F10: BANK NAME: | H10: JP Morgan Chase
F12: ACCOUNT #: | H12: 937301091
B13: BANK STATEMENT
B15: Bank Balance | C15: 40770 | H15: 341284.95
B17: Plus: Deposits in Transit | H17: 0
B19: Less: Outstanding Checks (See Outstanding Check Listing) | H19: 25631.26
B21: Adjustment:
B23: Adjusted Bank Balance | H23: =+H15+H17-H19 -> 315653.69
B25: GENERAL LEDGER
B28: Balance per General Ledger A/C #1020-000: | H28: 315653.69
B30: BANK REC ADJUSTMENTS TO BE RECORDED ON CASH BKS IN NEXT MONTH
F32: DIVIDEND PAID | H32: 0
F33: SWEEP FEE | H33: 0
F34: ANALYSIS CHARGE | H34: 0
H38: =+H28+H32+H33+H34 -> 315653.69
B41: Prepared by: | E41: Prelim Approval:
B42: Date: | E42: Final Approval:
E43: Date:

Sheet Sec-Dep
A1: MONTHLY REPORTING REQUIREMENTS | E1: Site Reports
A5: REGENCY BRESSI, LLC
A7: Security Deposit Cash Account- Account 21100000
A9: Statutory Report for the period ending:
A10: ='Pet-cash'!$A$11 -> 40816
B12: Date | C12: Property Name | D12: Amount Earned
B13: 39659 | C13: Board and Brew | D13: 5445
B14: 39673 | C14: Cha Dry Cleaners | D14: 4925.75
B15: 39873 | C15: Carisbad Optometry | D15: 3714.75
B16: 39904 | C16: Happiness Nails | D16: 4346.25
B17: 39934 | C17: Xtreme Frozen Yogurt | D17: 3479
B18: 39996 | C18: Jojo Be, LLC | D18: 5554.5
B19: 40081 | C19: Tomaso Restaurant Group | D19: 12608.4
B20: 40118 | C20: FROOTS 4 U, LLC | D20: 3981.2
B21: 40126 | C21: Postal Annex | D21: 3339
B22: 40155 | C22: Kyss Boutique, LLC | D22: 4991.2
B23: 40228 | C23: Perfectly at Home | D23: 8428
B24: 40366 | C24: Premier Food Concepts | D24: 8583.25
... B31: 40718 | C31: Elevation Burger | D31: 6610.1
B37: Total | D37: =SUM(D13:D36) -> 108922.86
B44: 10 | E44: MRI Implementation for Cornerstone

Sheet Util-Dep
A1: MONTHLY REPORTING REQUIREMENTS | D1: Site Reports
A5: REGENCY BRESSI, LLC
A7: Utility Deposits
A9: As of:_________
B12: Utility Company | D12: Total Deposit | G12: Total
B26: Total per GL | D26: =SUM(D13:D25) -> 0
A33: 11 | D33: MRI Implementation for Cornerstone
G39: SKYLINE Implementation for Cornerstone

Sheet All-Doubt
A1: MONTHLY REPORTING REQUIREMENTS Site Reports
A4: REGENCY BRESSI, LLC
A6: Allowance for Doubtful Accounts - 10900000
A8: As of
A9: ='Pet-cash'!$A$11 -> 40816
A11: The Property Manager has performed a review of all delinquent rents with the following findings and
A12: recommendations.
A15: Tenant Name | B15: Amount Reserved | D15: Comments/Status of Collection
A16: Kyss Boutique | B16: 3673.12 | D16: Tenant downsize. Suggest to write-off balance.
A17: JPMorgan Chase | B17: 19043.71 | D17: Review tenant account to confirm correct charges.
A18: Hendo's Local Pizza | B18: 1767.21 | D18: Review tenant account to confirm correct charges.
A20: Total Reserve per G/L | B20: =SUM(B16:B19) -> 24484.04
A39: 12 | D39: MRI Implementation for Cornerstone

Sheet Bad-D
A1: MONTHLY REPORTING REQUIREMENTS | D1: Site Reports
A5: REGENCY BRESSI, LLC
A7: YTD Bad Debt Write-Offs
A9: As of:
A10: ='Pet-cash'!$A$11 -> 40816
A12: Name of Tenant | B12: Total Write-off | D12: Reason for Write-off
A13: (List by Tenant) | B13: (Total of all charges) | D13: (Summary of Reasons)
A24: Total Accounts written off YTD | B24: =SUM(B13:B23) -> 0
A26: *YTD Bad Expense per the G/L should equal the sum of:
A27: (1) All direct write-offs of accounts receivable balances (amounts NOT previously reserved).
A28: (2) The Net Current Year provision to account 1090 - Allowance for Doubtful Accounts.
A33: 13 | D33: MRI Implementation for Cornerstone
G39: SKYLINE Implementation for Cornerstone

Sheet Receiv
A1: MONTHLY REPORTING REQUIREMENTS | D1: Site Reports
A5: REGENCY BRESSI, LLC
A7: Other Receivables - Account 11000000
A9: As of
A10: ='Pet-cash'!$A$11 -> 40816
A12: Receivable Due From | B12: Total Amount | D12: Description
A13: ELEVATION BURGER | B13: 2214 | D13: MONUMENT SIGN REIMBURSEMENTS
A14: TOMMY V'S | B14: 2214 | D14: MONUMENT SIGN REIMBURSEMENTS
A15: THE BAR METHOD | B15: 2214 | D15: MONUMENT SIGN REIMBURSEMENTS
A16: CHASE BANK | B16: 10000 | D16: MONUMENT SIGN REIMBURSEMENTS
A17: SUPERCUTS | B17: 2214 | D17: MONUMENT SIGN REIMBURSEMENTS
A18: EUROPEAN WAX CENTER | B18: 2214 | D18: MONUMENT SIGN REIMBURSEMENTS
A25: General Ledger Balance | B25: =SUM(B13:B24) -> 21070
A29: 16 | D29: MRI Implementation for Cornerstone
G36: SKYLINE Implementation for Cornerstone

Sheet PreP-Ins
A1: MONTHLY REPORTING REQUIREMENTS | I1: Site Reports
A5: REGENCY BRESSI, LLC
A7: Prepaid Insurance - Account 11200000
A9: As of :
A10: ='Pet-cash'!$A$11 -> 40816
A12: Prepaid To: | B12: Period | C12: Days/Mo | D12: Total Amount Paid | F12: Monthly Exp | G12: YTD Exp | H12: Prepaid Bal | I12: Description
A14: Marsh USA | B14: 5/24/11-2/15/13 | C14: 633 | D14: 1089 | F14: =D14/C14*30 -> 51.611374 | G14: =D14/C14*(8+30+31+31+30) -> 223.64929 | H14: =+D14-G14 -> 865.35071 | I14: Pollution Legal Liability Insurance
A15: Marsh USA | B15: 8/01/11-8/01/12 | C15: 12 | D15: 46441 | F15: =+D15/12 -> 3870.0833 | G15: =+F15*2 -> 7740.1667 | H15: =+D15-G15 -> 38700.833 | I15: Property Insurance
A16: Marsh USA | B16: 8/01/11-8/01/12 | C16: 12 | D16: 8885 | F16: =+D16/12 -> 740.41667 | G16: =+F16*2 -> 1480.8333 | H16: =+D16-G16 -> 7404.1667 | I16: General Liability Insurance
A17: Marsh USA | B17: 8/01/11-8/01/12 | C17: 12 | D17: 3993 | F17: =+D17/12 -> 332.75 | G17: =+F17*2 -> 665.5 | H17: =+D17-G17 -> 3327.5 | I17: Excess Liability Insurance
A28: General Ledger Balance | H28: =SUM(H14:H27) -> 50297.851
A35: 18 | I35: MRI Implementation for Cornerstone
L37: SKYLINE Implementation for Cornerstone

Sheet PreP-Other
A1: MONTHLY REPORTING REQUIREMENTS | D1: Site Reports
A5: REGENCY BRESSI, LLC
A7: Other Prepaids - Account 11300000
A9: As of :
A10: ='Pet-cash'!$A$11 -> 40816
A12: Prepaid To: | B12: Total Amount | D12: Description
A29: General Ledger Balance | B29: =SUM(B13:B28) -> 0
A36: 18 | D36: MRI Implementation for Cornerstone
G38: SKYLINE Implementation for Cornerstone

Sheet O-Asset
A1: MONTHLY REPORTING REQUIREMENTS | E1: Site Reports
E2: \
A5: "Property Name"
A7: Other Assets - Account 11900000
A9: As of:
A10: ='Pet-cash'!A11:F11 -> 40816
A12: Definition | B12: Total Amount | D12: Description
D13: <Type Of Asset>
A28: General Ledger Balance | B28: =SUM(B14:B27) -> 0
A31: 19 | D31: MRI Implementation for Cornerstone
G39: SKYLINE Implementation for Cornerstone

Sheet TT-Costs
A1: MONTHLY REPORTING REQUIREMENTS | E1: Site Reports
E2: \
A5: REGENCY BRESSI, LLC
A7: Tenant Installation Cost - Account 13200000
A9: As of: 9/30/11
A12: Tenant | B12: Total Amount | D12: Description
A14: 4G Wireless | B14: 45570 | D14: Tenant Improvement Reimbursement
A15: Hendo's Local Pizza & Pint | B15: 42315 | D15: Tenant Improvement Reimbursement
A16: Supercuts | B16: 26000 | D16: Tenant Improvement Reimbursement
A25: General Ledger Balance | B25: =SUM(B14:B24) -> 113885
A28: 19 | D28: MRI Implementation for Cornerstone
G36: SKYLINE Implementation for Cornerstone

Sheet Leas-Costs
A1: MONTHLY REPORTING REQUIREMENTS | G1: Site Reports
A4: "Property Name"
A6: Leasing Costs Schedule - 13250000
A8: As of: 9/30/11
A10: Tenant | B10: Broker(s) Name | C10: Lease Terms Start Date | D10: Lease Terms End Date | E10: Actual $ MTD | F10: Actual $ YTD | G10: YTD Budget | K10: Actual vs. Budget
A61: Total | E61: =SUM(E12:E25) -> 0 | F61: =SUM(F12:F60) -> 0 | G61: =SUM(G11:G23) -> 0 | K61: =SUM(K11:K23) -> 0
A63: Note: This schedule should include not only new monthly expenditures, but also a history of what has been spent YTD (a carry forward type schedule).
A64: 20 | F64: MRI Implementation for Cornerstone

Sheet Amort-Leas
A1: MONTHLY REPORTING REQUIREMENTS | J1: Site Reports
A4: REGENCY BRESSI, LLC
A6: Amortization Lease Costs - 13350000
A8: As of: 9/30/11
A10: Tenant | B10: Amount | C10: Life/Term | D10: # of Months | E10: Monthly Depr/Amort Exp | F10: Total Lease Cost Paid | J10: YTD Expense | K10: Accum Depreciation
B66: =SUM(B12:B63) -> 0 | E66: =SUM(E12:E65) -> 0 | F66: =SUM(F12:F65) -> 0 | J66: =SUM(J12:J65) -> 0 | K66: =SUM(K12:K65) -> 0
A74: 21 | F74: MRI Implementation for Cornerstone

Sheet Amort-Finance
A1: MONTHLY REPORTING REQUIREMENTS | J1: Site Reports
A4: REGENCY BRESSI, LLC
A6: Amortization Finance Costs - 13910000
A8: As of: 9/30/11
A10: Loan | B10: Amount | C10: Life/Term | D10: # of Months | E10: Monthly Depr/Amort Exp | F10: Total Lease Cost Paid | J10: YTD Expense | K10: Accum Depreciation
A11: Midland Loan #770000314 | B11: 173042.12 | C11: 5 | D11: =5*12 -> 60 | E11: =+B11/D11 -> 2884.0353 | J11: =+E11*1 -> 2884.0353 | K11: =-E11*1 -> -2884.0353
B66: =SUM(B11:B63) -> 173042.12 | C66: 5 | D66: =SUM(D11:D63) -> 60 | E66: =SUM(E11:E63) -> 2884.0353 | F66: =SUM(F11:F63) -> 0 | G66: =SUM(G11:G63) -> 0 | H66: =SUM(H11:H63) -> 0 | I66: =SUM(I11:I63) -> 0 | J66: =SUM(J11:J63) -> 2884.0353 | K66: =SUM(K11:K63) -> -2884.0353
A74: 21 | F74: MRI Implementation for Cornerstone

Sheet Free-R
A1: MONTHLY REPORTING REQUIREMENTS | F1: Site Reports
A5: REGENCY BRESSI, LLC
A7: Free Rent
A9: As of: 9/30/11
A14: Tenant | B14: Commence Date | C14: Expiration Date | D14: Commence Date | E14: Expiration Date | F14: Unamortized Balance | G14: Amortization
A15: <List by Tenant> | F15: (Calculation of net amortized
F16: free rent Tenant Balance
F17: in Account 1195)
A27: Total | F27: =SUM(F15:F26) -> 0 | G27: =SUM(G15:G26) -> 0
A29: Note: This schedule should include not only new monthly expenditures, but also a history of what has been spent to Date (a carry forward type schedule).
A31: 22 | F31: MRI Implementation for Cornerstone

Sheet Accr-Sale
A1: MONTHLY REPORTING REQUIREMENTS | C1: Site Reports
A5: <Enter Property Name Here>
A7: Accrued Sales Tax - Account 20300000
A9: As of:_________
A13: Name of Taxing Authority | B13: Aging of Balance Due 30, 60 or 90 day | C13: Current Balance per the GL
A24: Total | B24: =SUM(B14:B23) -> 0 | C24: =SUM(C14:C23) -> 0
A33: 23 | C33: MRI Implementation for Cornerstone

Sheet Accr-Leas
A1: MONTHLY REPORTING REQUIREMENTS | E1: Site Reports
A5: REGENCY BRESSI, LLC
A7: Accrued Leasing Commission - Account 20600000
A9: As of
A10: ='Pet-cash'!$A$11 -> 40816
A12: Broker Name | B12: Amount Due | C12: Due Date | D12: Tenant Name | E12: Lease Effective Date | F12: Lease Expiration Date
A25: Total | B25: =SUM(B13:B24) -> 0
A27: *Total must tie to balance per the G\L.
A34: 24 | E34: MRI Implementation for Cornerstone

Sheet Mgmt-Fee
A1: MONTHLY REPORTING REQUIREMENTS | E1: Site Reports
A4: REGENCY BRESSI, LLC
A6: Management Fee - Account 2094000
A8: For the month ending:
A9: ='Pet-cash'!$A$11 -> 40816
C14: Basis for Calculation | D14: Management Fee % | E14: Fee Due
B15: January
B16: February
B17: March
B18: April
B19: May
B20: June
B21: July | C21: 390331.42 | D21: 0.025 | E21: =C21*D21 -> 9758.2855
B22: August | C22: 296986.19 | D22: 0.025 | E22: =C22*D22 -> 7424.6548
B23: September | C23: 299807.31 | D23: 0.025 | E23: =C23*D23 -> 7495.1827
B24: October
B25: November
B26: December
B27: Total | E27: =SUM(E15:E26) -> 24678.123
A34: 27 | E34: MRI Implementation for Cornerstone

Sheet Accr Ins
A1: MONTHLY REPORTING REQUIREMENTS | G1: Site Reports
A5: REGENCY BRESSI, LLC
A7: Prepaid Insurance - Account 2100000
A9: As of :
A10: ='Pet-cash'!$A$11 -> 40816
A12: CoverageType | B12: Preminum Commence Date | C12: Premium Expiration Date | D12: Number of Months | E12: Amount Due | F12: Monthly Amortization | G12: Accumulated Insurance Exp. | H12: General Ledger Balance | I12: Months Remaining
A13: Property Insurance
A14: Liability Premium
A15: Umbrella Premium
A16: Property/All Risk Premium
A17: General Liability Premium
A18: Environmental Premium
A21: Total | E21: =SUM(E13:E20) -> 0 | F21: =SUM(F13:F20) -> 0 | G21: =SUM(G13:G20) -> 0 | H21: =SUM(H13:H20) -> 0
A23: Note: This schedule should include not only new monthly expenditures, but also a history of what has been spent to Date (a carry forward type schedule).
A25: 22 | H25: MRI Implementation for Cornerstone

Sheet O-Liabil
A1: MONTHLY REPORTING REQUIREMENTS | C1: Site Reports
A5: REGENCY BRESSI, LLC
A7: Other Liabilities - Account 21000000
A9: As of
A10: ='Pet-cash'!$A$11 -> 40816
A13: Vendor Name | B13: Amount Accrued | C13: Description of Work - Type of Expense
C14: LNR Contribution to Grand Opening Fund
C15: Grand Opening Fund
C16: Promotional Fund
C17: Property/Liability Insurance (see Accr Ins)
B18: 2065.48 | C18: Tommy V, May Late Fee
B19: 2156.47 | C19: Souplantation, May Rent
B20: 1789.51 | C20: Community Utility Billing Services 07/11
B21: 1709.7 | C21: Community Utility Billing Services 08/11
C22: 2011 Estimated CAM Rec
B23: =SUM(B14:B16) -> 0
A30: Total | B30: =SUM(B14:B29) -> 7721.16

Sheet Legal-Fee
A1: MONTHLY REPORTING REQUIREMENTS | E1: Site Reports
A5: "Property Name"
A7: Legal Fees- Account 61600000
A9: Period ending:
A12: Name of Law Firm | B12: Date Paid | C12: Total Amount Paid | D12: Professional Fees | E12: Out of Pocket Expenses | I12: Allocation of Total
A29: Total | C29: =SUM(C13:C28) -> 0 | D29: =SUM(D13:D28) -> 0 | E29: =SUM(E13:E28) -> 0 | I29: =SUM(I13:I28) -> 0
A31: Note: Total must tie to YTD expense per G/L.
A33: 28 | E33: MRI Implementation for Cornerstone

Sheet Leas-Costs (2)
A1: MONTHLY REPORTING REQUIREMENTS | F1: Home Office Reports
A5: <Enter Property Name Here>
A7: Leasing Costs Schedule - 13250000
A9: As of:_________
A12: Tenant | B12: Broker(s) Name | C12: Lease Terms Start Date | D12: Lease Terms End Date | E12: Actual $ MTD | F12: Actual $ YTD | G12: YTD Budget | K12: Actual vs. Budget
A13: List by Tenant | B13: Broker/Cost Descr.*
A27: Total | E27: =SUM(E13:E26) -> 0 | F27: =SUM(F13:F26) -> 0 | G27: =SUM(G13:G26) -> 0 | K27: =SUM(K13:K26) -> 0
A29: Note: This schedule should include not only new monthly expenditures, but also a history of what has been spent to date (a carry forward type schedule).
A31: 37 | F31: MRI Implementation for Cornerstone

Sheet Legal-Fee (2)
A1: MONTHLY REPORTING REQUIREMENTS | E1: Home Office Reports
A5: <Enter Property Name Here>
A7: Legal Fees
A9: As of:____________
A12: Name of Law Firm | B12: Date Paid | C12: Total Amount Paid | D12: Professional Fees | E12: Out of Pocket Expenses | I12: Allocation of Total
A27: Total | C27: =SUM(C13:C26) -> 0 | D27: =SUM(D13:D26) -> 0 | E27: =SUM(E13:E26) -> 0 | I27: =SUM(I13:I26) -> 0
A29: Note: Total must tie to YTD expense per G/L.
A32: 38 | E32: MRI Implementation for Cornerstone

Sheet Fixed
A1: MONTHLY REPORTING REQUIREMENTS | G1: Home Office Reports
A5: Fixed Asset Identification Form
A6: Property Name:
A7: Property #
A8: Month:
A10: MRI | D10: Suite | E10: Project Description/include Job Ledger | I10: Placed in Service
A11: Account # | C11: Account Name | D11: Number | E11: (Tenant Name if applicable) | G11: Amount | I11: (A)
A30: (A) TI's=lease start date All Other=Date project/fixed asset was placed in service (not final invoice payment date).
A33: 39 | E33: SKYLINE Implementation for Cornerstone

Sheet Chk list
A1: MONTHLY REPORTING REQUIREMENTS | K1: Home Office Reports
A5: MRI - PRE-CLOSE AUDIT CHECKLIST
A6: For the period ending:
C8:  Compare the cash balance from the Bank Reconciliation to the General Ledger Cash account (A/C 1020)
C10:  Compare the Cash Receipts Journal to the Total Cash Receipts per the G/L (A/C 1020)
C12:  Compare the cash balance from the Bank Reconciliation to the General Ledger Cash account (A/C 1025)
C14:  Compare the A/P Check Register to the Total Cash Disbursed per the G/L (A/C 1020).
C16:  Compare the Net Change Column of the CM Ledger to the Net Total of Accounts Receivable and Prepaid Rent (A/C 1080 & 2040).
C18:  Compare the totals on the Aged Delinquencies Report to the accounts receivable (A/C 1080) balance per the General Ledger
C20:  Compare over 90 days balance per Aged Delinquencies to Reserve for Doubtful Accounts (A/C 1090) and prepare Journal Entry
C22:  Compare the balance on the A/P Open Invoice Report to the accounts payable (A/C 2020) balance on the General Ledger.
C24:  Compare the security deposit balance on the CM Security Deposits Ledger to the Security Deposit G/L account (A/C 2110)
C26:  Test Real Estate Tax Expense (A/C 6010) for correct number of months expense.
C28:  Test Accrued Real Estate Taxes (A/C 2070) for correct number of the months expense.
C30:  Test Insurance Expense (A/C 6060) for correct number of months expense.
... C51: DO NOT PROCEED WITH THE CLOSE IF THE ABOVE CHECKLIST IS NOT COMPLETE AND RECONCILED.
L54: MRI Implementation for Cornerstone

Sheet 10420
A1: ='Review Comments'!B9 -> COCONUT GROVE RETAIL XIII, LLC
A2: ESCROW- GROUND RENT- 10450
A3: ='Review Comments'!B11 -> FOR THE MONTH 07/31/2026
A9: Origination Date | C9: Description | E9: Amount | F9: Total Amount
A11: 42978 | C11: Escrow Ground Rent | E11: 17605.67 | F11: =E11 -> 17605.67
A12: 43038 | C12: 09/17 Mortgage Payment | E12: 8802.83 | F12: =F11+E12 -> 26408.5
C17: Account Total: | F17: =F12 -> 26408.5

Sheet Review Comments
B2: Monthly Financial Analysis
B3: Review Comments
A9: Property: | B9: COCONUT GROVE RETAIL XIII, LLC
A11: Month: | B11: FOR THE MONTH 07/31/2026
A13: Books | B13: Accrual / Cash
A16: 1.
A19: 2.
A22: 3.
A25: 4.
A28: 5.
A31: 6.
A34: 7.
A37: 8.
A40: 9.

Sheet TB 
A1: Database: ATHENA | B1: Trial Balance | E1: Page: | F1: 1
A2: ENTITY: 165 | B2: Athena Property Management | E2: Date: | F2: 46239.7
B3: COCONUT GROVE RETAIL XIII, LLC | E3: Time: | F3: 46239.7
A6: Accrual | B6: Year to Date Balances for period 07/26
B7: Report includes an open period. Entries are not final.
A9: Account | B9: Description | C9: Debit | E9: Credit
A12: No Department
A14: 10175-000000 | B14: CASH OPERATING-MECHANICS BANK | C14: 228492.74 | G14: =C14-E14 -> 228492.74
A15: 12010-000000 | B15: ACCOUNTS RECEIVABLE | C15: 122046.05 | G15: =C15-E15 -> 122046.05
A16: 12100-000000 | B16: LOAN RECEIVABLE | C16: 160000 | G16: =C16-E16 -> 160000
A17: 12410-000000 | B17: ALLOWANCE FOR BAD DEBT | E17: 7086.08 | G17: =C17-E17 -> -7086.08
A18: 13100-000000 | B18: MISCELLANEOUS DEPOSITS | C18: 150 | G18: =C18-E18 -> 150
A19: 14000-000000 | B19: LAND COSTS | C19: 4369592.2 | G19: =C19-E19 -> 4369592.2
A20: 15000-000000 | B20: BUILDING | C20: 17478369 | G20: =C20-E20 -> 17478369
A21: 15010-000000 | B21: BUILDING IMPROVEMENTS | C21: 2052989.6 | G21: =C21-E21 -> 2052989.6
A22: 15100-000000 | B22: TENANT IMPROVEMENTS | C22: 237334.8 | G22: =C22-E22 -> 237334.8
A23: 15400-000000 | B23: CAPITAL IMPROVEMENT | C23: 11648 | G23: =C23-E23 -> 11648
A24: 15500-000000 | B24: CONSTRUCTION IN PROGRESS | C24: 2200 | G24: =C24-E24 -> 2200
A25: 16500-000000 | B25: LEASING COMMISSIONS | C25: 239044.55 | G25: =C25-E25 -> 239044.55
A26: 16700-000000 | B26: REFINANCE COSTS | C26: 355176.83 | G26: =C26-E26 -> 355176.83
A27: 17600-000000 | B27: LOAN FEES | C27: 442910.74 | G27: =C27-E27 -> 442910.74
A28: 18300-000000 | B28: ACCUM DEPR-BUILDING | E28: 3314956 | G28: =C28-E28 -> -3314956
A29: 18500-000000 | B29: ACCUM DEPR-TENANT IMPROVEMENTS | C29: 130514 | G29: =C29-E29 -> 130514
A30: 18900-000000 | B30: ACCUM AMORT-LOAN FEES | E30: 144746.19 | G30: =C30-E30 -> -144746.19
A31: 20100-000000 | B31: ACCOUNTS PAYABLE | E31: 19358.47 | G31: =C31-E31 -> -19358.47
A32: 20650-000000 | B32: ACCRUED OPERATING EXP | E32: 9365.57 | G32: =C32-E32 -> -9365.57
A33: 20660-000000 | B33: ACCRUED INTEREST EXPENSE | E33: 139242.09 | G33: =C33-E33 -> -139242.09
A34: 20800-000000 | B34: TENANT SECURITY DEPOSIT | E34: 149779.54 | G34: =C34-E34 -> -149779.54
A35: 20900-000000 | B35: PREPAID RENT | E35: 142581.84 | G35: =C35-E35 -> -142581.84
A36: 25420-000000 | B36: NOTES PAYABLE-MORGAN STANLEY | E36: 28000000 | G36: =C36-E36 -> -28000000
A37: 25500-000000 | B37: AP - AFFILIATES | E37: 66144.74 | G37: =C37-E37 -> -66144.74
A38: 30400-000000 | B38: PRIOR YR RETAINED EARNING | E38: 7824551.2 | G38: =C38-E38 -> -7824551.2
A39: 35000-000000 | B39: OWNER'S DISTRIBUTION | C39: 14597709 | G39: =C39-E39 -> 14597709
A40: 36000-000000 | B40: OWNER'S CONTRIBUTION | E40: 342383.2 | G40: =C40-E40 -> -342383.2
A41: 40100-000000 | B41: BASE RENTAL INCOME | E41: 1059750.4 | G41: =C41-E41 -> -1059750.4
A42: 40102-000000 | B42: RENT DEFERRAL | C42: 65479.31 | G42: =C42-E42 -> 65479.31
A43: 40106-000000 | B43: DEFERRED RENT RECOVERY | E43: 2961.63 | G43: =C43-E43 -> -2961.63
A44: 40110-000000 | B44: PERCENTAGE RENT | E44: 302030.92 | G44: =C44-E44 -> -302030.92
A45: 40129-000000 | B45: PARKING RENT | E45: 261747.56 | G45: =C45-E45 -> -261747.56
A46: 40140-000000 | B46: COMMON AREA INCOME | E46: 298223.66 | G46: =C46-E46 -> -298223.66
A47: 40150-000000 | B47: PRIOR YEAR CAM | C47: 21949.05 | G47: =C47-E47 -> 21949.05
A48: 40170-000000 | B48: OTHER RECOVERIES | E48: 28112.35 | G48: =C48-E48 -> -28112.35
A49: 40180-000000 | B49: FOOD COURT CAM | E49: 52509.49 | G49: =C49-E49 -> -52509.49
A50: 40230-000000 | B50: INSURANCE INCOME | E50: 60020.12 | G50: =C50-E50 -> -60020.12
A51: 40240-000000 | B51: PROPERTY TAX INCOME | E51: 69581.95 | G51: =C51-E51 -> -69581.95
A52: 40250-000000 | B52: MISCELLANEOUS INCOME | E52: 10500 | G52: =C52-E52 -> -10500
A53: 40300-000000 | B53: MARKETING INCOME | E53: 28980.85 | G53: =C53-E53 -> -28980.85
A54: 41100-000000 | B54: OTHER INCOME | E54: 87875.84 | G54: =C54-E54 -> -87875.84
A55: 50111-000000 | B55: INSURANCE-PROPERTY | C55: 126056.83 | G55: =C55-E55 -> 126056.83
A56: 50112-000000 | B56: INSURANCE-LIABILITY | C56: 10611.19 | G56: =C56-E56 -> 10611.19
A57: 50130-000000 | B57: INSURANCE-UMBRELLA | C57: 5238.46 | G57: =C57-E57 -> 5238.46
A58: 50160-000000 | B58: LANDSCAPE-CONSUMABLES | C58: 6282.72 | G58: =C58-E58 -> 6282.72
A59: 50170-000000 | B59: LANDSCAPE-MAINTENANCE | C59: 56931.11 | G59: =C59-E59 -> 56931.11
A60: 50210-000000 | B60: ELEVATOR MAINTENANCE | C60: 17041.71 | G60: =C60-E60 -> 17041.71
A61: 50530-000000 | B61: PARKING LOT LIGHT REPAIRS | C61: 5201.54 | G61: =C61-E61 -> 5201.54
A62: 50540-000000 | B62: PARKING LOT REPAIRS | C62: 1570.03 | G62: =C62-E62 -> 1570.03
A63: 50551-000000 | B63: SIGN REPAIRS | C63: 431.94 | G63: =C63-E63 -> 431.94
A64: 51020-000000 | B64: GENERAL MAINTENANCE | C64: 6265.12 | G64: =C64-E64 -> 6265.12
A65: 51023-000000 | B65: SITE FURNISHING-REPAIRS | C65: 17580.25 | G65: =C65-E65 -> 17580.25
A66: 51040-000000 | B66: JANITORIAL | C66: 79984.43 | G66: =C66-E66 -> 79984.43
... A73: 51160-000000 | B73: SECURITY | C73: 49569.67 | G73: =C73-E73 -> 49569.67
A74: 51210-000000 | B74: PLUMBING REPAIRS | E74: 2625.79 | G74: =C74-E74 -> -2625.79
A75: 52010-000000 | B75: JANITORIAL SUPPLIES | C75: 10430.26 | G75: =C75-E75 -> 10430.26
A76: 52020-000000 | B76: BACKFLOW-MAINTENANCE | C76: 1209.42 | G76: =C76-E76 -> 1209.42
A77: 54000-000000 | B77: PROPERTY TAX | C77: 95320.22 | G77: =C77-E77 -> 95320.22
A78: 55110-000000 | B78: ELECTRIC/COMMON AREA | C78: 14827.64 | G78: =C78-E78 -> 14827.64
A79: 55120-000000 | B79: TRASH REMOVAL | C79: 5491.41 | G79: =C79-E79 -> 5491.41
A80: 55140-000000 | B80: WATER/COMMON AREA | C80: 28483.55 | G80: =C80-E80 -> 28483.55
A81: 55160-000000 | B81: GAS | C81: 362.37 | G81: =C81-E81 -> 362.37
A82: 55180-000000 | B82: WATER/SEWER | C82: 26250.28 | G82: =C82-E82 -> 26250.28
A83: 55190-000000 | B83: GROUND RENT | C83: 78031.81 | G83: =C83-E83 -> 78031.81
A84: 57110-000000 | B84: FOOD COURT-JANITORIAL&SUPPLIES | C84: 21845.1 | G84: =C84-E84 -> 21845.1
A85: 57120-000000 | B85: FOOD COURT-GAS | C85: 362.37 | G85: =C85-E85 -> 362.37
A86: 57130-000000 | B86: FOOD COURT-SECURITY | C86: 15080.02 | G86: =C86-E86 -> 15080.02
... A100: 70420-000000 | B100: BOND | C100: 1296 | G100: =C100-E100 -> 1296
A101: 70463-000000 | B101: LOSS AGAINST INS CLAIMS | E101: 157053.51 | G101: =C101-E101 -> -157053.51
B102: Total: | C102: 42582169 | E102: 42582169 | G102: =C102-E102 -> 0
G103: =C103-E103 -> 0
G104: =C104-E104 -> 0
G105: =C105-E105 -> 0
G106: =C106-E106 -> 0
G107: =C107-E107 -> 0
G108: =C108-E108 -> 0
G109: =C109-E109 -> 0
G110: =C110-E110 -> 0
G111: =C111-E111 -> 0
G112: =C112-E112 -> 0

Sheet 10410
A1: ='Review Comments'!B9 -> COCONUT GROVE RETAIL XIII, LLC
A2: PROPERTY TAX RESERVE- 10410
A3: ='Review Comments'!B11 -> FOR THE MONTH 07/31/2026
A9: Origination Date | C9: Description | E9: Amount | F9: Total Amount
A11: 42978 | C11: Escrow Property Tax Reserve | E11: 32580.99 | F11: =+E11 -> 32580.99
A12: 43038 | C12: 09/17 Mortgage Payment | E12: 12531.15 | F12: =F11+E12 -> 45112.14
A13: 43068 | C13: 10/17 Mortgage Payment | E13: 12531.15 | F13: =F12+E13 -> 57643.29
A14: 43098 | C14: 11/17 Mortgage Payment | E14: 12531.15 | F14: =F13+E14 -> 70174.44
A15: 43117 | C15: 12/17 Mortgage Payment | E15: 12531.15 | F15: =F14+E15 -> 82705.59
A16: 43159 | C16: 01/18 Mortgage Payment | E16: 12531.15 | F16: =F15+E16 -> 95236.74
A17: 43151 | C17: Tax Payment #75009025000 | E17: -45856.41 | F17: =F16+E17 -> 49380.33
A18: 43151 | C18: Tax Payment #75009027000 | E18: -9144.41 | F18: =F17+E18 -> 40235.92
A19: 43151 | C19: Tax Payment #75009028000 | E19: -19884.82 | F19: =F18+E19 -> 20351.1
A20: 43190 | C20: 02/18 Mortgage Payment | E20: 12531.15 | F20: =F19+E20 -> 32882.25
A21: 43220 | C21: 03/18 Mortgage Payment | E21: 12531.15 | F21: =F20+E21 -> 45413.4
A22: 43251 | C22: 04/18 Mortgage Payment | E22: 12531.15 | F22: =F21+E22 -> 57944.55
A23: 43281 | C23: 05/18 Mortgage Payment | E23: 12531.15 | F23: =F22+E23 -> 70475.7
... A137: 45509 | C137: 07/24 MORTGAGE PMT | E137: 15658.43 | F137: =F136+E137 -> 130345.02
A138: 45497 | C138: 24/25 1ST PROP TAX 7500902500 | E138: -57695.79 | F138: =F137+E138 -> 72649.23 | H138: p
A139: 45497 | C139: 24/25 1ST PROP TAX 7500902700 | E139: -12344.81 | F139: =F138+E139 -> 60304.42
A140: 45497 | C140: 24/25 1ST PROP TAX 7500902800 | E140: -26240.25 | F140: =F139+E140 -> 34064.17
A141: 9/6/2024 | C141: CAPITAL DISBURSEMENT | E141: -34064.17 | F141: =F140+E141 -> -7.2759576e-11
C143: Account Total: | F143: =F141 -> -7.2759576e-11

Sheet 10530
A1: ='Review Comments'!B9 -> COCONUT GROVE RETAIL XIII, LLC
A2: LOAN RESERVES - TI/LC 10530
A3: ='Review Comments'!B11 -> FOR THE MONTH 07/31/2026
A9: Origination Date | C9: Description | E9: Amount | F9: Total Amount
H10: Beginning Bal | I10: =151900.41 -> 151900.41 | J10: =I10+20.78+38.96-24208.19 -> 127751.96 | K10: TI
A11: 42719 | C11: Escrow-TI/LC Holdback (Loan Reserve) | F11: =+E11 -> 0 | H11: Beginning Bal | I11: 334767.5 | J11: =I11+45.79+85.86 -> 334899.15 | K11: TI/ LC
I13: Acct# 10530 | J13: =F34 -> 0 | K13: TI& TI/LC BAL
I14: Acct# 10520 | J14: ='10470'!F65 -> 0
I15: Acct# 10510 | J15: ='10490'!F40 -> 1.2369128e-10
I16: Acct# 10420 | J16: ='10420'!F17 -> 26408.5
J18: =SUM(J13:J17) -> 26408.5
J33: =SUM(J13:J16) -> 26408.5 | K33: Bank Reserve act bal
C34: Account Total: | F34: =SUM(F11:F33) -> 0
A45: Origination Date
E52: çç CASH BOOK BALANCE

Sheet 10450
A1: ='Review Comments'!B9 -> COCONUT GROVE RETAIL XIII, LLC
A2: ESCROW GROUND RENT- 10450
A3: ='Review Comments'!B11 -> FOR THE MONTH 07/31/2026
A9: Origination Date | C9: Description | E9: Amount | F9: Total Amount
A11: 42978 | C11: Escrow Ground Rent | F11: 17605.67
A12: 43038 | C12: 09/17 Mortgage Payment | E12: 8802.83 | F12: =F11+E12 -> 26408.5
A13: 43068 | C13: 10/17 Mortgage Payment | E13: 8802.83 | F13: =F12+E13 -> 35211.33
A14: 43098 | C14: 11/17 Mortgage Payment | E14: 8802.83 | F14: =F13+E14 -> 44014.16
A15: 43117 | C15: 12/17 Mortgage Payment | E15: -35211.33 | F15: =F14+E15 -> 8802.83
A16: 43117 | C16: 12/17 Mortgage Payment | E16: 8802.83 | F16: =F15+E16 -> 17605.66
A17: 43131 | C17: Marcella Gregory pmt | E17: -8802.83 | F17: =F16+E17 -> 8802.83
A18: 43159 | C18: 01/18 Mortgage Payment | E18: 8802.83 | F18: =F17+E18 -> 17605.66
A19: 43159 | C19: Marcella Gregory pmt | E19: -8802.83 | F19: =F18+E19 -> 8802.83
A20: 43190 | C20: 02/18 Mortgage Payment | E20: 8802.83 | F20: =F19+E20 -> 17605.66
A21: 43190 | C21: Marcella Gregory pmt | E21: -8802.83 | F21: =F20+E21 -> 8802.83
A22: 43220 | C22: 03/18 Mortgage Payment | E22: 8802.83 | F22: =F21+E22 -> 17605.66
A23: 43220 | C23: Marcella Gregory pmt | E23: -8802.83 | F23: =F22+E23 -> 8802.83
... A85: 44165 | C85: Marcella Gregory pmt | E85: -8802.83 | F85: =F84+E85 -> 8802.83
A86: 44169 | C86: 11/20 Mortgage Payment | E86: 8802.83 | F86: =F83+E86 -> 17605.66
A87: 44196 | C87: Marcella Gregory pmt | E87: -8802.83 | F87: =F86+E87 -> 8802.83
A88: 44201 | C88: 12/20 Mortgage Payment | E88: 8802.83 | F88: =F85+E88 -> 17605.66
A89: 44227 | C89: Marcella Gregory pmt | E89: -8802.83 | F89: =F88+E89 -> 8802.83
A90: 44232 | C90: 1/21 Mortgage Payment | E90: 8802.83 | F90: =F87+E90 -> 17605.66
A91: 44255 | C91: Marcella Gregory pmt | E91: -8802.83 | F91: =F90+E91 -> 8802.83
A92: 44260 | C92: 1/21 Mortgage Payment | E92: 8802.83 | F92: =F91+E92 -> 17605.66
A93: 44286 | C93: Marcella Gregory pmt | E93: -8802.83 | F93: =F92+E93 -> 8802.83
A94: 44291 | C94: 3/21 Mortgage Payment | E94: 8802.83 | F94: =F93+E94 -> 17605.66
A95: 44316 | C95: Marcella Gregory pmt | E95: -8802.83 | F95: =F94+E95 -> 8802.83
A96: 44321 | C96: 4/21 Mortgage Payment | E96: 8802.83 | F96: =F95+E96 -> 17605.66
A97: 44346 | C97: Marcella Gregory pmt | E97: -8802.83 | F97: =F96+E97 -> 8802.83
A98: 44351 | C98: 5/21 Mortgage Payment | E98: 8802.83 | F98: =F97+E98 -> 17605.66
A99: 44377 | C99: Marcella Gregory pmt | E99: -8802.83 | F99: =F98+E99 -> 8802.83
A100: 44379 | C100: 06/21 Mortgage Payment | E100: 8802.83 | F100: =F99+E100 -> 17605.66
A101: 44407 | C101: Marcella Gregory pmt | E101: -8802.83 | F101: =F100+E101 -> 8802.83
A102: 44413 | C102: 07/21 Mortgage Payment | E102: 8802.83 | F102: =F101+E102 -> 17605.66
... A174: 45534 | C174: MARCELLA GREGORY PMT | E174: -8802.83 | F174: =F173+E174 -> 0
C178: Account Total: | F178: =F174 -> 0

Sheet 10460
A1: ='Review Comments'!B9 -> COCONUT GROVE RETAIL XIII, LLC
A2: ESCROW- INSURANCE ACT- 10460
A3: ='Review Comments'!B11 -> FOR THE MONTH 07/31/2026
A9: Origination Date | C9: Description | E9: Amount | F9: Total Amount
A11: 42978 | C11: Escrow Insurance | F11: 27653.6
A12: 43038 | C12: 09/17 Mortgage Payment | E12: 2880.58 | F12: =F11+E12 -> 30534.18
A13: 43068 | C13: 10/17 Mortgage Payment | E13: 2880.58 | F13: =F12+E13 -> 33414.76
A14: 43098 | C14: 11/17 Mortgage Payment | E14: 2880.58 | F14: =F13+E14 -> 36295.34
A15: 43117 | C15: 12/17 Mortgage Payment | E15: 2880.58 | F15: =F14+E15 -> 39175.92
A16: 43159 | C16: 01/18 Mortgage Payment | E16: 2880.58 | F16: =F15+E16 -> 42056.5
A17: 43159 | C17: Annual Premium 12/31/17-12/31/18 | E17: -27045 | F17: =F16+E17 -> 15011.5
A18: 43159 | C18: Add'l Insurance | E18: -901.65 | F18: =F17+E18 -> 14109.85
A19: 43188 | C19: 02/18 Mortgage Payment | E19: 2880.58 | F19: =F18+E19 -> 16990.43
A20: 43188 | C20: Add'l Insurance | E20: -51.29 | F20: =F19+E20 -> 16939.14
A21: 43220 | C21: 03/18 Mortgage Payment | E21: 2880.58 | F21: =F20+E21 -> 19819.72
A22: 43251 | C22: 04/18 Mortgage Payment | E22: 2880.58 | F22: =F21+E22 -> 22700.3
A23: 43281 | C23: 05/18 Mortgage Payment | E23: 2880.58 | F23: =F22+E23 -> 25580.88
... A60: 44232 | C60: 1/21 Mortgage Payment | E60: 3236.94 | F60: =F59+E60 -> 39532.8
A61: 2/11/21 | C61: Annual Premium 12/31/20-12/31/21 | E61: -29925.76 | F61: =F60+E61 -> 9607.04
A62: 44260 | C62: 2/21 Mortgage Payment | E62: 3236.94 | F62: =F61+E62 -> 12843.98
A63: 44291 | C63: 3/21 Mortgage Payment | E63: 3236.94 | F63: =F62+E63 -> 16080.92
A64: 44291 | C64: Annual Premium 12/31/20-12/31/21 | E64: -486 | F64: =F63+E64 -> 15594.92
A65: 44321 | C65: 4/21 Mortgage Payment | E65: 3236.94 | F65: =F64+E65 -> 18831.86
A66: 44351 | C66: 5/21 Mortgage Payment | E66: 3236.94 | F66: =F65+E66 -> 22068.8
A67: 44379 | C67: 06/21 Mortgage Payment | E67: 3236.94 | F67: =F66+E67 -> 25305.74
A68: 44413 | C68: 07/21 Mortgage Payment | E68: 3236.94 | F68: =F67+E68 -> 28542.68
A69: 44442 | C69: 08/21 Mortgage Payment | E69: 2661.03 | F69: =F68+E69 -> 31203.71
A70: 44474 | C70: 09/21 Mortgage Payment | E70: 2661.03 | F70: =F69+E70 -> 33864.74
A71: 44505 | C71: 10/21 Mortgage Payment | E71: 2661.03 | F71: =F70+E71 -> 36525.77
A72: 44536 | C72: 11/21 Mortgage Payment | E72: 2661.03 | F72: =F71+E72 -> 39186.8
A73: 44592 | C73: 12/21 Mortgage Payment | E73: 2661.03 | F73: =F72+E73 -> 41847.83
... A114: 45541 | C114: CAPITAL DISBURSEMENT | E114: -61823.99 | F114: =F113+E114 -> 0
C116: Account Total: | F116: =F114 -> 0

Sheet 10470
A1: ='Review Comments'!B9 -> COCONUT GROVE RETAIL XIII, LLC
A2: ESCROW- OTHER
A3: ='Review Comments'!B11 -> FOR THE MONTH 07/31/2026
A9: Origination Date | C9: Description | E9: Amount | F9: Total Amount
A11: 42978 | C11: Escrow Other | E11: 45746.93 | F11: =E11 -> 45746.93
A12: 43038 | C12: 09/17 Mortgage Payment | E12: 4985.73 | F12: =F11+E12 -> 50732.66
A13: 43068 | C13: 10/17 Mortgage Payment | E13: 4985.73 | F13: =F12+E13 -> 55718.39
A14: 43098 | C14: 11/17 Mortgage Payment | E14: 4985.73 | F14: =F13+E14 -> 60704.12
A15: 43117 | C15: 12/17 Mortgage Payment | E15: 4985.73 | F15: =F14+E15 -> 65689.85
A16: 43159 | C16: 01/18 Mortgage Payment | E16: 4985.73 | F16: =F15+E16 -> 70675.58
A17: 43190 | C17: 02/18 Mortgage Payment | E17: 4985.73 | F17: =F16+E17 -> 75661.31
A18: 43220 | C18: 03/18 Mortgage Payment | E18: 4985.73 | F18: =F17+E18 -> 80647.04
A19: 43251 | C19: 04/18 Mortgage Payment | E19: 4985.73 | F19: =F18+E19 -> 85632.77
A20: 43281 | C20: 05/18 Mortgage Payment | E20: 4985.73 | F20: =F19+E20 -> 90618.5
A21: 43312 | C21: 06/18 Mortgage Payment | E21: 4985.73 | F21: =F20+E21 -> 95604.23
A22: 43343 | C22: 07/18 Mortgage Payment | E22: 4985.73 | F22: =F21+E22 -> 100589.96
A23: 43373 | C23: 08/18 Mortgage Payment | E23: 4985.73 | F23: =F22+E23 -> 105575.69
... A63: 45541 | C63: CAPITAL DISBURSEMENT | E63: -285061.99 | F63: =F62+E63 -> 0
C65: Account Total: | F65: =F63 -> 0

Sheet 10490
A1: ='Review Comments'!B9 -> COCONUT GROVE RETAIL XIII, LLC
A2: CAPITAL EXP HOLDBACK-10490
A3: ='Review Comments'!B11 -> FOR THE MONTH 07/31/2026
A9: Origination Date | C9: Description | E9: Amount | F9: Total Amount
A11: 42978 | C11: Escrow Cap Exp Holdback | E11: 85920 | F11: =+E11 -> 85920
A12: 43038 | C12: 09/17 Mortgage Payment | E12: 797.71 | F12: =F11+E12 -> 86717.71 | H12: Total reserve & Other/ repair | I12: =F40+'10450'!F178+'10470'!F65 -> 1.2369128e-10
A13: 43068 | C13: 10/17 Mortgage Payment | E13: 797.71 | F13: =F12+E13 -> 87515.42
A14: 43098 | C14: 11/17 Mortgage Payment | E14: 797.71 | F14: =F13+E14 -> 88313.13
A15: 43117 | C15: 12/17 Mortgage Payment | E15: 797.71 | F15: =F14+E15 -> 89110.84
A16: 43159 | C16: 01/18 Mortgage Payment | E16: 797.71 | F16: =F15+E16 -> 89908.55
A17: 43190 | C17: 02/18 Mortgage Payment | E17: 797.71 | F17: =F16+E17 -> 90706.26
A18: 43220 | C18: 03/18 Mortgage Payment | E18: 797.71 | F18: =F17+E18 -> 91503.97
A19: 43251 | C19: 04/18 Mortgage Payment | E19: 797.71 | F19: =F18+E19 -> 92301.68
A20: 43281 | C20: 05/18 Mortgage Payment | E20: 797.71 | F20: =F19+E20 -> 93099.39
A21: 43312 | C21: 06/18 Mortgage Payment | E21: 797.71 | F21: =F20+E21 -> 93897.1
A22: 43343 | C22: 07/18 Mortgage Payment | E22: 797.71 | F22: =F21+E22 -> 94694.81
A23: 43373 | C23: 08/18 Mortgage Payment | E23: 797.71 | F23: =F22+E23 -> 95492.52
A24: 43404 | C24: 09/18 Mortgage Payment | E24: 797.71 | F24: =F23+E24 -> 96290.23
... A38: 45541 | C38: CAPITAL DISBURSEMENT | E38: -19145.04 | F38: =F37+E38 -> 1.2369128e-10
C40: Account Total: | F40: =F38 -> 1.2369128e-10

Sheet Summary
A2: Property# | B2: 165
A3: Property Name | B3: COCONUT GROVE RETAIL XIII, LLC
A4: Month | B4: 46234
A6: Account# | B6: Account Name | C6: Balance from Schedule | D6: Balance from TB | E6: Balance | F6: Comments
A7: 10410-000000 | B7: ESCROW-PROPERTY TAX | C7: 0 | D7: {=IFERROR(INDEX('TB '!G:G,MATCH(A7,'TB '!A:A,0),0),0)} -> 0 | E7: =C7-D7 -> 0
A8: 10420-000000 | B8: ESCROW-RESERVE ACT | C8: 0 | D8: {=IFERROR(INDEX('TB '!G:G,MATCH(A8,'TB '!A:A,0),0),0)} -> 0 | E8: =C8-D8 -> 0
A9: 10432-000000 | B9: ESCROW-LC RESERVE | C9: 0 | D9: {=IFERROR(INDEX('TB '!G:G,MATCH(A9,'TB '!A:A,0),0),0)} -> 0 | E9: =C9-D9 -> 0
A10: 10445-000000 | B10: ESCROW-CASH MANAGEMENT | C10: 0 | D10: {=IFERROR(INDEX('TB '!G:G,MATCH(A10,'TB '!A:A,0),0),0)} -> 0 | E10: =C10-D10 -> 0
A11: 12020-000000 | B11: ACCOUNTS RECEIVABLE OTHER | C11: ='12020'!E13 -> 0 | D11: {=IFERROR(INDEX('TB '!G:G,MATCH(A11,'TB '!A:A,0),0),0)} -> 0 | E11: =C11-D11 -> 0
A12: 12100-000000 | B12: LOAN RECEIVABLE | C12: ='12100'!E13 -> 160000 | D12: {=IFERROR(INDEX('TB '!G:G,MATCH(A12,'TB '!A:A,0),0),0)} -> 160000 | E12: =C12-D12 -> 0
A13: 12410-000000 | B13: ALLOWANCE FOR BAD DEBT | C13: ='12410 '!G33 -> 7086.08 | D13: {=IFERROR(INDEX('TB '!G:G,MATCH(A13,'TB '!A:A,0),0),0)} -> -7086.08 | E13: =C13+D13 -> 0
A14: 13000-000000 | B14: SUSPENSE | C14: ='13000'!F13 -> 0 | D14: {=IFERROR(INDEX('TB '!G:G,MATCH(A14,'TB '!A:A,0),0),0)} -> 0 | E14: =C14-D14 -> 0
A15: 13100-000000 | B15: MISC DEPOSIT | C15: ='13100'!F23 -> 150 | D15: {=IFERROR(INDEX('TB '!G:G,MATCH(A15,'TB '!A:A,0),0),0)} -> 150 | E15: =C15-D15 -> 0
A16: 13120-000000 | B16: PREPAID PROPERTY TAXES | C16: ='Tax '!G16 -> 0 | D16: {=IFERROR(INDEX('TB '!G:G,MATCH(A16,'TB '!A:A,0),0),0)} -> 0 | E16: =C16-D16 -> 0
A17: 13130-000000 | B17: PREPAID PROPERTY TAXES | C17: ='13130'!F16 -> 0 | D17: {=IFERROR(INDEX('TB '!G:G,MATCH(A17,'TB '!A:A,0),0),0)} -> 0
A18: 13150-000000 | B18: FROM 801 MAIN STREET | C18: 0 | D18: {=IFERROR(INDEX('TB '!G:G,MATCH(A18,'TB '!A:A,0),0),0)} -> 0 | E18: =C18-D18 -> 0
A19: 14000-000000 | B19: LAND COSTS | C19: ='Fixed Asset'!F13 -> 4369592.2 | D19: {=IFERROR(INDEX('TB '!G:G,MATCH(A19,'TB '!A:A,0),0),0)} -> 4369592.2 | E19: =C19-D19 -> 0
A20: 15000-000000 | B20: BUILDING | C20: ='Fixed Asset'!F18 -> 17478369 | D20: {=IFERROR(INDEX('TB '!G:G,MATCH(A20,'TB '!A:A,0),0),0)} -> 17478369 | E20: =C20-D20 -> 0
A21: 15010-000000 | B21: BUILDING IMPROVEMENTS | C21: ='Fixed Asset'!F141 -> 2052989.6 | D21: {=IFERROR(INDEX('TB '!G:G,MATCH(A21,'TB '!A:A,0),0),0)} -> 2052989.6 | E21: =C21-D21 -> 0
A22: 15100-000000 | B22: TENANT IMPROVEMENTS | C22: ='Fixed Asset'!F154 -> 237334.8 | D22: {=IFERROR(INDEX('TB '!G:G,MATCH(A22,'TB '!A:A,0),0),0)} -> 237334.8 | E22: =C22-D22 -> 0
A23: 16500-000000 | B23: LEASING COMMISSIONS | C23: ='Fixed Asset'!F201 -> 239044.55 | D23: {=IFERROR(INDEX('TB '!G:G,MATCH(A23,'TB '!A:A,0),0),0)} -> 239044.55 | E23: =C23-D23 -> 0
A24: 17600-000000 | B24: LOAN FEES | C24: ='Fixed Asset'!F219 -> 442910.74 | D24: {=IFERROR(INDEX('TB '!G:G,MATCH(A24,'TB '!A:A,0),0),0)} -> 442910.74 | E24: =C24-D24 -> 0
A25: 18100-000000 | B25: ACCUMULATED DEPRECIATION | C25: 0 | D25: {=IFERROR(INDEX('TB '!G:G,MATCH(A25,'TB '!A:A,0),0),0)} -> 0 | E25: =C25-D25 -> 0
A26: 18200-000000 | B26: ACCUMULATED AMORTIZATION | C26: 0 | D26: {=IFERROR(INDEX('TB '!G:G,MATCH(A26,'TB '!A:A,0),0),0)} -> 0 | E26: =C26-D26 -> 0
A27: 20100-000000 | B27: ACCOUNTS PAYABLE | C27: ='20100'!F19 -> -19358.47 | D27: {=IFERROR(INDEX('TB '!G:G,MATCH(A27,'TB '!A:A,0),0),0)} -> -19358.47 | E27: =C27-D27 -> 0
A28: 20650-000000 | B28: ACCRUED OPERATING EXP | C28: ='20650'!T47 -> 9365.57 | D28: {=IFERROR(INDEX('TB '!G:G,MATCH(A28,'TB '!A:A,0),0),0)} -> -9365.57 | E28: =-C28-D28 -> 0
A29: 20660-000000 | B29: ACCRUED INTEREST EXPENSE | C29: ='20660'!G13 -> 139242.09 | D29: {=-IFERROR(INDEX('TB '!G:G,MATCH(A29,'TB '!A:A,0),0),0)} -> 139242.09 | E29: =C29-D29 -> 0
A30: 20800-000000 | B30: TENANT SECURITY DEPOSIT | C30: 0 | D30: {=IFERROR(INDEX('TB '!G:G,MATCH(A30,'TB '!A:A,0),0),0)} -> -149779.54 | E30: =C30-D30 -> 149779.54 | F30: NA
A31: 20900-000000 | B31: PREPAID RENT | C31: 0 | D31: {=IFERROR(INDEX('TB '!G:G,MATCH(A31,'TB '!A:A,0),0),0)} -> -142581.84 | E31: =C31-D31 -> 142581.84 | F31: NA
A32: 23800-000000 | B32: NOTES PAYABLE-GOLDMAN SACHS | C32: 0 | D32: {=IFERROR(INDEX('TB '!G:G,MATCH(A32,'TB '!A:A,0),0),0)} -> 0 | E32: =C32-D32 -> 0
A33: 25500-000000 | B33: AP - AFFILIATES | C33: 0 | D33: {=IFERROR(INDEX('TB '!G:G,MATCH(A33,'TB '!A:A,0),0),0)} -> -66144.74 | E33: =C33-D33 -> 66144.74 | F33: NA
A34: 25910-000000 | B34: NOTE PAYABLE-OSTERMAN | C34: 0 | D34: {=IFERROR(INDEX('TB '!G:G,MATCH(A34,'TB '!A:A,0),0),0)} -> 0 | E34: =C34-D34 -> 0
A35: 30100-000000 | B35: EQUITY | C35: 0 | D35: {=IFERROR(INDEX('TB '!G:G,MATCH(A35,'TB '!A:A,0),0),0)} -> 0 | E35: =C35-D35 -> 0
A36: 30400-000000 | B36: PRIOR YR RETAINED EARNING | C36: 0 | D36: {=IFERROR(INDEX('TB '!G:G,MATCH(A36,'TB '!A:A,0),0),0)} -> -7824551.2 | E36: =C36-D36 -> 7824551.2 | F36: NA
A37: 35000-000000 | B37: OWNER'S DISTRIBUTION | C37: ='35000'!E95 -> 14597709 | D37: {=IFERROR(INDEX('TB '!G:G,MATCH(A37,'TB '!A:A,0),0),0)} -> 14597709 | E37: =C37-D37 -> 0
A38: 36000-000000 | B38: OWNER'S CONTRIBUTION | C38: ='36000'!E20 -> -342383.2 | D38: {=IFERROR(INDEX('TB '!G:G,MATCH(A38,'TB '!A:A,0),0),0)} -> -342383.2 | E38: =C38-D38 -> 0
A39: 40250-000000 | B39: MISCELLANEOUS INCOME | C39: 0 | D39: {=IFERROR(INDEX('TB '!G:G,MATCH(A39,'TB '!A:A,0),0),0)} -> -10500 | E39: =C39-D39 -> 10500 | F39: NA
A40: 70300-000000 | B40: BAD DEBT EXPENSE | C40: ='12410 '!H33 -> 0 | D40: {=IFERROR(INDEX('TB '!G:G,MATCH(A40,'TB '!A:A,0),0),0)} -> 0 | E40: =C40-D40 -> 0
A42: Insurance
A43: 50111-000000 | B43: INSURANCE-PROPERTY | C43: ='INSURANCE '!C20 -> 126056.83 | D43: {=IFERROR(INDEX('TB '!G:G,MATCH(A43,'TB '!A:A,0),0),0)} -> 126056.83 | E43: =C43-D43 -> 0
A44: 50112-000000 | B44: INSURANCE-LIABILITY | C44: ='INSURANCE '!D20 -> 10611.19 | D44: {=IFERROR(INDEX('TB '!G:G,MATCH(A44,'TB '!A:A,0),0),0)} -> 10611.19 | E44: =C44-D44 -> 0
A45: 50130-000000 | B45: INSURANCE-UMBRELLA | C45: ='INSURANCE '!E20 -> 5238.46 | D45: {=IFERROR(INDEX('TB '!G:G,MATCH(A45,'TB '!A:A,0),0),0)} -> 5238.46 | E45: =C45-D45 -> 0

Sheet 12020
A1: ='Review Comments'!B9 -> COCONUT GROVE RETAIL XIII, LLC
A2: ACCOUNTS RECEIVABLE OTHER- 12020
A3: ='Review Comments'!B11 -> FOR THE MONTH 07/31/2026
A7: Origination Date | C7: Description | E7: Total Amount
C13: Account Total: | E13: =SUM(E9:E11) -> 0
C15: 12020-000000 | D15: 0 | E15: {=IFERROR(INDEX('TB '!G:G,MATCH(12020,'TB '!A:A,0),0),0)} -> 0
C16: S/B zero | D16: =+D13-D15 -> 0 | E16: =E13-E15 -> 0

Sheet 13000 (2)
A1: ='Review Comments'!B9 -> COCONUT GROVE RETAIL XIII, LLC
A2: SUSPENSE - 13000
A3: ='Review Comments'!B11 -> FOR THE MONTH 07/31/2026
A6: Date | C6: Tenant | D6: Vendor | F6: Amount | H6: Description
A8: 44033 | C8: Sotherbys (New Tenant) | F8: 0 | H8: 1st month rent and security deposit
A9: 44406 | C9: Kana Haven (Café Kona) | D9: Big Island Electric Inc | F9: 480.54 | H9: Tenant is not billed yet
A10: 44462 | C10: Fosters Kitchen | D10: TARYN BREEN | F10: -394.12 | H10: tenant charged
A11: 44469 | C11: Fosters Kitchen | D11: TARYN BREEN | F11: 394.12 | H11: exp paid
D13: TOTAL Per Accrual | F13: =SUM(F8:F12) -> 480.54
A18: Date | C18: Tenant | D18: Vendor | F18: Amount | H18: Description
A20: 44033 | C20: Sotherbys (New Tenant) | F20: 0 | H20: 1st month rent and security deposit
A21: 44376 | C21: Foster Kitchen | D21: Bsc Kona LLC | F21: 1136.13 | H21: Tenant was billed not paid yet
A22: 44376 | C22: Foster Kitchen | D22: Bsc Kona LLC | F22: 1385.55 | H22: Tenant was billed not paid yet
A23: 43308 | C23: MF Kona, LLC | D23: Big Island Electric Inc | H23: Tenant was billed in 07/18,
A24: 43308 | C24: MF Kona, LLC | D24: Big Island Electric Inc | H24: Tenant was billed in 07/18,
A25: 43308 | C25: MF Kona, LLC | D25: Big Island Electric Inc | H25: Tenant was billed in 07/18,
A26: 43308 | C26: MF Kona, LLC | D26: Big Island Electric Inc | H26: Tenant was billed in 07/18,
A27: 43308 | C27: MF Kona, LLC | D27: Big Island Electric Inc | H27: Tenant was billed in 07/18,
A28: 44406 | C28: Kana Haven (Café Kona) | D28: Big Island Electric Inc | F28: 480.54 | H28: Tenant is not billed yet
A29: 44433 | C29: Foster Kitchen | D29: Bsc Kona LLC | F29: -2521.68 | H29: CASH RECIPTS
A30: 44462 | C30: Fosters Kitchen | D30: TARYN BREEN | F30: -394.12 | H30: CASH RECIPTS
A31: 44469 | C31: Fosters Kitchen | D31: TARYN BREEN | F31: 394.12 | H31: Exp paid
D33: TOTAL Per Cash | F33: =SUM(F20:F32) -> 480.54

Sheet 12410
A1: ='Review Comments'!B9 -> COCONUT GROVE RETAIL XIII, LLC
A2: BAD DEBT RESERVE - 12410
A3: ='Review Comments'!B11 -> FOR THE MONTH 07/31/2026
A6: Tenant Name | B6: O/S AR Balance | C6: Less Security Deposit | D6: Adjusted O/S Balance | E6: Beginning Bal | F6: Current Reserve | G6: Ending Bal | H6: Bad Debt Exp #70300 | I6: Comments/Status of Collection | K6: Prior | L6: 12584.32 | M6: 8717.22 | N6: 5111.25
B7: 0 | G7: =SUM(E7:F7) -> 0 | H7: =G7 -> 0
A8: Gecko Girlz | B8: 0 | C8: -7044.8 | D8: 0 | E8: 0 | F8: =D8-E8 -> 0 | G8: =E8+F8 -> 0 | H8: =-G8+5539.52 -> 5539.52 | I8: ($5,539.52) reserved in 2020 | K8: New Bal | L8: 8717.22 | M8: 3605.97 | N8: -5539.52
A9: Bongo Bens | B9: 0 | C9: 0 | D9: =B9+C9 -> 0 | E9: 0 | F9: =D9-E9 -> 0 | G9: =E9+F9 -> 0 | H9: 0 | K9: Adj | L9: =+L8-L6 -> -3867.1 | M9: =+M6+M8 -> 12323.19 | N9: =+N6+N8 -> -428.27
A10: Humpy's Big Island Alehouse | B10: 45204.79 | C10: -11000 | D10: =B10+C10 -> 34204.79 | E10: 154866.78 | F10: =D10-E10 -> -120661.99 | G10: =E10+F10 -> 34204.79 | H10: =-G10+100013.47+64010.01 -> 129818.69 | I10: ($164,023.48) reserved in 2020 | K10: add: 3mths | L10: 3605.97
A11: Big Island Running | C11: -1585.93 | D11: 0 | E11: 0 | F11: =D11-E11 -> 0 | G11: =E11+F11 -> 0 | H11: =-G11 -> 0 | K11: balance | L11: =+L9+L10 -> -261.13
A12: Colors of Paradise Gallery | B12: =19598.69+2737.56+2145.33+2145.33 -> 26626.91 | C12: -2123.64 | D12: =B12+C12 -> 24503.27 | E12: 24503.27 | F12: =D12-E12 -> 0 | G12: =E12+F12 -> 24503.27 | H12: =-G12+9910.1 -> -14593.17 | I12: ($9,910.10) reserved in 2020
A13: Island Lava Java | C13: -20937.35 | D13: =B13+C13 -> -20937.35 | E13: -17219.18 | F13: =D13-E13 -> -3718.17 | G13: =E13+F13 -> -20937.35 | H13: =-G13+83766.22-83766.22 -> 20937.35 | I13: ($83,766.22) reserved in 2020
A14: Lavernes | B14: =10097.75+6997.72 -> 17095.47 | C14: -30857.87 | D14: 0 | E14: 32375.84 | F14: =D14-E14 -> -32375.84 | G14: =E14+F14 -> 0 | H14: =-G14+49193.79 -> 49193.79 | I14: ($49,193.79) reserved in 2020 | K14: Prior | L14: 49468.93
A15: Kona Gear | B15: =40460.31+8.26 -> 40468.57 | C15: -7184.49 | D15: =B15+C15 -> 33284.08 | E15: 33284.08 | F15: =D15-E15 -> 0 | G15: =E15+F15 -> 33284.08 | H15: =-G15+18769.72 -> -14514.36 | I15: ($18,769.72) reserved in 2020 | K15: New Bal | L15: 42668.31
A16: Jacks Dive Locker | B16: 0 | D16: =B16+C16 -> 0 | E16: 0 | F16: =D16-E16 -> 0 | G16: =E16+F16 -> 0 | H16: =-G16+24425.06 -> 24425.06 | I16: ($24,425.06) reserved in 2020 | K16: Adj | L16: =+L15-L14 -> -6800.62
A17: Fosters Kitchen | B17: 0 | C17: -12641.5 | D17: 0 | E17: 22142.42 | F17: =D17-E17 -> -22142.42 | G17: =E17+F17 -> 0 | H17: =-G17 -> 0 | K17: add: 3mths | L17: 20401.86
A18: ABC Store | B18: 0 | C18: 0 | D18: =B18+C18 -> 0 | E18: 46527 | F18: =D18-E18 -> -46527 | G18: =E18+F18 -> 0 | H18: =-G18+46870.01+2598.92+47967.84 -> 97436.77 | I18: ($49,468.93) reserved in 2020 | K18: balance | L18: =+L16+L17 -> 13601.24
A19: Oceans Sports Bar and Grill | B19: =4593.84+49269.94+4605.74 -> 58469.52 | C19: 0 | D19: =B19+C19 -> 58469.52 | E19: 58469.52 | F19: =D19-E19 -> 0 | G19: =E19+F19 -> 58469.52 | H19: =-G19+39309.92 -> -19159.6 | I19: ($39,309.92) reserved in 2020
A20: Café Kona | B20: 33597.36 | C20: -2116.11 | D20: =B20+C20 -> 31481.25 | E20: 31713.04 | F20: =D20-E20 -> -231.79 | G20: =E20+F20 -> 31481.25 | H20: =-G20+18708.57 -> -12772.68 | I20: ($18,708.57) reserved in 2020
D21: =B21+C21 -> 0 | E21: 0 | F21: =D21-E21 -> 0 | G21: =E21+F21 -> 0 | H21: =-G21 -> 0
D22: =B22+C22 -> 0 | F22: =D22-E22 -> 0 | G22: =E22+F22 -> 0 | H22: =-G22 -> 0
D23: =B23+C23 -> 0 | F23: =D23-E23 -> 0 | G23: =E23+F23 -> 0 | H23: =-G23 -> 0
D24: =B24+C24 -> 0 | F24: =D24-E24 -> 0 | G24: =E24+F24 -> 0 | H24: =-G24 -> 0
D25: =B25+C25 -> 0 | F25: =D25-E25 -> 0 | G25: =E25+F25 -> 0 | H25: =-G25 -> 0
D26: =B26+C26 -> 0 | F26: =D26-E26 -> 0 | G26: =E26+F26 -> 0 | H26: =-G26 -> 0
A28: Total Reserve per G/L | B28: =SUM(B7:B27) -> 221462.62 | D28: =SUM(D7:D27) -> 161005.56 | E28: =SUM(E7:E27) -> 386662.77 | F28: =SUM(F7:F27) -> -225657.21 | G28: =SUM(G7:G27) -> 161005.56 | H28: =SUM(H7:H27) -> 266311.37
G29: =+G28-D28 -> 0
J32: 19626.81
J33: 8669.57
J34: 42669.89
J35: =SUM(J32:J34) -> 70966.27
J36: =J35/6 -> 11827.712 | L36: =J36*2 -> 23655.423 | M36: =J35-L36 -> 47310.847

Sheet 12500
A1: ='Review Comments'!B9 -> COCONUT GROVE RETAIL XIII, LLC
A2: INTEREST RATE CAP- 12500
A3: ='Review Comments'!B11 -> FOR THE MONTH 07/31/2026
A9: Origination Date | C9: Description | E9: Amount | F9: Total Amount
A11: 42719 | C11: Interest Rate Cap Cost | F11: =+E11 -> 0
C15: Account Total: | F15: =SUM(F11:F14) -> 0

Sheet 12410 
A1: ='Review Comments'!B9 -> COCONUT GROVE RETAIL XIII, LLC
A2: BAD DEBT RESERVE - 12410
A3: ='Review Comments'!B11 -> FOR THE MONTH 07/31/2026
A6: Tenant Name | B6: O/S AR Balance | C6: Less Security Deposit | D6: Adjusted O/S Balance | E6: Beginning Bal | F6: Current Reserve | G6: Ending Bal | H6: Bad Debt Exp | I6: Comments/Status of Collection | K6: Prior | L6: 12584.32 | M6: 8717.22 | N6: 5111.25
G7: 12410-000000 | H7: 70300-000000
B8: 0 | E8: 0 | G8: =SUM(E8:F8) -> 0
A9: Lucasie Ltd | B9: 4288.87 | C9: -4713.8 | D9: =IF((B9+C9)>0,B9+C9,0) -> 0 | E9: 0 | F9: =D9-E9 -> 0 | G9: =E9+F9 -> 0
A10: Taka Sushi | B10: 0 | C10: 0 | D10: =IF((B10+C10)>0,B10+C10,0) -> 0 | E10: 0 | F10: =D10-E10 -> 0 | G10: =E10+F10 -> 0 | I10: (8,825.41) 2022, 2023 Rent Abatement-8,825.41 | K10: New Bal | L10: 8717.22 | M10: 3605.97 | N10: -5539.52
A11: Gecko Girlz | B11: 0 | C11: 0 | D11: =IF((B11+C11)>0,B11+C11,0) -> 0 | E11: 0 | F11: =D11-E11 -> 0 | G11: =E11+F11 -> 0
A12: Bongo Bens | B12: 0 | C12: 0 | D12: =IF((B12+C12)>0,B12+C12,0) -> 0 | E12: 0 | F12: =D12-E12 -> 0 | G12: =E12+F12 -> 0 | K12: Adj | L12: =+L10-L6 -> -3867.1 | M12: =+M6+M10 -> 12323.19 | N12: =+N6+N10 -> -428.27
A13: Humpy's Big Island Alehouse | B13: 0 | C13: 0 | D13: =IF((B13+C13)>0,B13+C13,0) -> 0 | E13: 0 | F13: =D13-E13 -> 0 | G13: =E13+F13 -> 0 | K13: add: 3mths | L13: 3605.97
A14: Big Island Running | C14: 0 | D14: =IF((B14+C14)>0,B14+C14,0) -> 0 | E14: 0 | F14: =D14-E14 -> 0 | G14: =E14+F14 -> 0 | K14: balance | L14: =+L12+L13 -> -261.13
A15: Colors of Paradise Gallery | B15: 0 | C15: 0 | D15: =IF((B15+C15)>0,B15+C15,0) -> 0 | E15: 0 | F15: =D15-E15 -> 0 | G15: =E15+F15 -> 0 | I15: ($9,910.10) reserved in 2020, (24502.96) 2022 , ADJ in 07.23 $24,502.96 & $12,237.40
A16: Island Lava Java | C16: 0 | D16: =IF((B16+C16)>0,B16+C16,0) -> 0 | E16: 0 | F16: =D16-E16 -> 0 | G16: =E16+F16 -> 0
A17: Lavernes | C17: 0 | D17: =IF((B17+C17)>0,B17+C17,0) -> 0 | E17: 0 | F17: 0 | G17: =E17+F17 -> 0 | K17: Prior | L17: 49468.93
A18: Kona Gear | B18: 0 | C18: 0 | D18: =IF((B18+C18)>0,B18+C18,0) -> 0 | E18: 0 | F18: =D18-E18 -> 0 | G18: =E18+F18 -> 0 | K18: New Bal | L18: 42668.31
A19: Jacks Dive Locker | B19: 0 | C19: 0 | D19: =IF((B19+C19)>0,B19+C19,0) -> 0 | E19: 0 | F19: =D19-E19 -> 0 | G19: =E19+F19 -> 0 | K19: Adj | L19: =+L18-L17 -> -6800.62
A20: Fosters Kitchen | B20: 15113.98 | C20: -12641.5 | D20: =IF((B20+C20)>0,B20+C20,0) -> 2472.48 | E20: 5569.78 | F20: =D20-E20 -> -3097.3 | G20: =E20+F20 -> 2472.48 | K20: add: 3mths | L20: 20401.86
A21: ABC Store | B21: 0 | C21: 0 | D21: =IF((B21+C21)>0,B21+C21,0) -> 0 | E21: 1930.38 | F21: =D21-E21 -> -1930.38 | G21: =E21+F21 -> 0 | K21: balance | L21: =+L19+L20 -> 13601.24
A22: Oceans Sports Bar and Grill | B22: 4613.6 | C22: 0 | D22: =IF((B22+C22)>0,B22+C22,0) -> 4613.6 | E22: 4813.6 | F22: =D22-E22 -> -200 | G22: =E22+F22 -> 4613.6
A23: Kanaka Kava | B23: 0 | C23: 0 | D23: =IF((B23+C23)>0,B23+C23,0) -> 0 | E23: 0 | G23: =E23+F23 -> 0
C24: 0 | D24: =IF((B24+C24)>0,B24+C24,0) -> 0 | E24: 0 | G24: =E24+F24 -> 0 | I24: ($18,708.57) reserved in 2021
C25: 0 | D25: =IF((B25+C25)>0,B25+C25,0) -> 0 | E25: 0 | G25: =E25+F25 -> 0 | I25: ($18,708.57) reserved in 2022
C26: 0 | D26: =IF((B26+C26)>0,B26+C26,0) -> 0 | E26: 0 | G26: =E26+F26 -> 0 | I26: ($18,708.57) reserved in 2023
C27: 0 | D27: =IF((B27+C27)>0,B27+C27,0) -> 0 | E27: 0 | G27: =E27+F27 -> 0 | I27: ($18,708.57) reserved in 2024
C28: 0 | D28: =IF((B28+C28)>0,B28+C28,0) -> 0 | E28: 0 | G28: =E28+F28 -> 0 | I28: ($18,708.57) reserved in 2025
C29: 0 | D29: =IF((B29+C29)>0,B29+C29,0) -> 0 | E29: 0 | G29: =E29+F29 -> 0 | I29: ($18,708.57) reserved in 2026
A30: CAFE KONA | B30: 6958.31 | C30: -22116.11 | D30: =IF((B30+C30)>0,B30+C30,0) -> 0 | E30: 0 | F30: =D30-E30 -> 0 | G30: =E30+F30 -> 0
A31: Outback Steakhouse | B31: 0 | C31: 0 | D31: =IF((B31+C31)>0,B31+C31,0) -> 0 | E31: 0 | F31: =D31-E31 -> 0 | G31: =E31+F31 -> 0 | H31: =F31+6408.23+2552.35-872.78+1745.56-9833.36 -> 0
A33: Total Reserve per G/L | B33: =SUM(B8:B32) -> 30974.76 | C33: =SUM(C8:C32) -> -39471.41 | D33: =SUM(D8:D32) -> 7086.08 | E33: =SUM(E8:E32) -> 12313.76 | F33: =SUM(F8:F32) -> -5227.68 | G33: =SUM(G8:G32) -> 7086.08 | H33: =SUM(H8:H32) -> 0
F35: PER TB | G35: {=IFERROR(INDEX('TB '!G:G,MATCH(G7,'TB '!A:A,0),0),0)} -> -7086.08 | H35: {=IFERROR(INDEX('TB '!G:G,MATCH(H7,'TB '!A:A,0),0),0)} -> 0
F36: S/B zero | G36: =-G35-G33 -> 0 | H36: =+H33-H35 -> 0

Sheet 12100
A1: ='Review Comments'!B9 -> COCONUT GROVE RETAIL XIII, LLC
A2: LOAN RECEIVABLE - 12100
A3: ='Review Comments'!B11 -> FOR THE MONTH 07/31/2026
A9: Origination Date | C9: Description | E9: Amount | F9: Comment
A11: 45981 | C11: SHORT TERM LOAN PAYMENT | E11: 160000
C13: Account Total | E13: =SUM(E11:E12) -> 160000
D15: 12100-000000 | E15: {=IFERROR(INDEX('TB '!G:G,MATCH(D15,'TB '!A:A,0),0),0)} -> 160000
D16: S/B zero | E16: =E15-E13 -> 0

Sheet 13000
A1: ='Review Comments'!B9 -> COCONUT GROVE RETAIL XIII, LLC
A2: SUSPENSE - 13000
A3: ='Review Comments'!B11 -> FOR THE MONTH 07/31/2026
A6: Date | C6: Tenant | D6: Vendor | F6: Amount | H6: Description
J8: IF BALANCE IS 0 DELETE HISTORY
D13: TOTAL Per Accrual | F13: =SUM(F8:F10) -> 0
A18: Date | C18: Tenant | D18: Vendor | F18: Amount | H18: Description
J20: NOTE:
A21: 46199 | C21: ISLAND LAVA JAVA | D21: JW CLEANING SYSTEMS LLC | F21: 226.54 | H21: 6104 6/24/2026 TBB ISLAND LAVA JAVA JW CLEANING SYSTEMS LLC | J21: IF BALANCE IS 0 DELETE HISTORY
D25: TOTAL Per Cash | F25: =SUM(F20:F23) -> 226.54
D28: 13000-000000 | F28: {=IFERROR(INDEX('TB '!G:G,MATCH(D28,'TB '!A:A,0),0),0)} -> 0 | H28: Per CM ledger
C29: Invoices paid but not billed to Tenants | D29: S/B zero | F29: =F13-F28 -> 0 | H29: Difference

Sheet 13100
A1: ='Review Comments'!B9 -> COCONUT GROVE RETAIL XIII, LLC
A2: MISC DEPOSIT-13100
A3: ='Review Comments'!B11 -> FOR THE MONTH 07/31/2026
F7: 13100-000000
A9: Origination Date | C9: Vendor | D9: Description | F9: Amount | G9: Comment
A11: 46022 | D11: 00127459 Cash Recpt NON-TENANT | F11: 150
A12: 43068 | C12: Hawaii Electric Light Co, Inc | D12: Acct# 201014742377 | F12: 0 | G12: SD Applied
A13: 43068 | C13: Hawaii Electric Light Co, Inc | D13: Acct# 201014743508 | F13: 0 | G13: SD Applied
A14: 43068 | C14: Hawaii Electric Light Co, Inc | D14: Acct# 201014744019 | F14: 0 | G14: SD Applied
A15: 43068 | C15: Hawaii Electric Light Co, Inc | D15: Acct# 201014744704 | F15: =-530+74.31+74.46+74.39+74.46-267.62+500 -> 0 | G15: SD Applied
A16: 43068 | C16: Hawaii Electric Light Co, Inc | D16: Acct# 201014744977 | F16: 0 | G16: SD Applied
A17: 43068 | C17: Hawaii Electric Light Co, Inc | D17: Acct# 201014745941 | F17: 0 | G17: SD Applied
A18: 43068 | C18: Hawaii Electric Light Co, Inc | D18: Acct# 201014746048 | F18: =500-500 -> 0 | G18: SD Applied
A19: 43087 | C19: Hawaii Electric Light Co, Inc | D19: Acct# 201014743508 | F19: 0 | G19: SD Applied
A20: 43087 | C20: Hawaii Electric Light Co, Inc | D20: Acct# 201014746048 | F20: 0 | G20: SD Applied
D23: Account Total | F23: =SUM(F11:F22) -> 150
E25: 13100-000000 | F25: {=IFERROR(INDEX('TB '!G:G,MATCH(E25,'TB '!A:A,0),0),0)} -> 150
E26: S/B zero | F26: =F25-F23 -> 0

Sheet 13130
A1: ='Review Comments'!B9 -> COCONUT GROVE RETAIL XIII, LLC
A2: PREPAID EXPENSE-13130
A3: ='Review Comments'!B11 -> FOR THE MONTH 07/31/2026
A9: Origination Date | C9: Vendor | D9: Description | F9: Amount | G9: Comment
D16: Account Total | F16: =SUM(F10:F15) -> 0
E18: 13130-000000 | F18: {=IFERROR(INDEX('TB '!G:G,MATCH(E18,'TB '!A:A,0),0),0)} -> 0
E19: S/B zero | F19: =F18-F16 -> 0

Sheet Fixed Asset
A1: ='Review Comments'!B9 -> COCONUT GROVE RETAIL XIII, LLC
A2: FIXED ASSETS SCHEDULE
A3: ='Review Comments'!B11 -> FOR THE MONTH 07/31/2026
A9: Origination Date | C9: Account Number | D9: Description | E9: Lease Term | F9: Amount
A11: 42978 | C11: 14000 | D11: Land Costs | F11: 18505428
A12: 43100 | D12: Adjust 2017 Recording of Property Purchase - CPA AJE | F12: -14135836
F13: =SUM(F11:F12) -> 4369592.2
A16: 42978 | C16: 15000 | D16: Building | F16: 3265663.7
A17: 43100 | D17: Adjust 2017 Recording of Property Purchase - CPA AJE | F17: 14212705
F18: =SUM(F16:F17) -> 17478369
C21: 15010 | D21: Building Improvement
A22: 43279 | D22: Elevator Upgrades - Otis Elevator Company (Owners paid) | F22: 77883
A23: 43341 | D23: Replace Parking Lot Light 50% Dep - Big Island Electric | F23: 13385.41
A24: 43341 | D24: Replace Parking Lot Light 50% Final Pmt - Big Island Electric | F24: 13385.41
A25: 43402 | D25: New Elevator Cab - Otis Elevator Company | F25: 17366
A26: 43456 | D26: Pre-construction Research - Tinguely Development (Inv #18-320-01) | F26: 2200
A27: 43465 | D27: 2018 CPA AJE #3 - To expense Minor Capitalized Items | F27: =-13385.41-13385.41 -> -26770.82
A28: 43465 | D28: 2018 CPA AJE #4 - To Reclass CIP | F28: -2200
A29: 43494 | D29: Exterior Paint - Kawika's Painting (Inv #38-11-25) | F29: 31022.1
A30: 43494 | D30: Exterior Paint - Kawika's Painting (Inv #38-12-13) | F30: 9900
A31: 43494 | D31: Pre-construction Research - Tinguely Development (Inv #18-405-01) | F31: 2311.6
A32: 43522 | D32: Security Camera Equipment 50% Dep. - Elite Interactive Solutions (Inv. 165-010819) | F32: 34169.35
A33: 43522 | D33: Fire Monitor System - 50% Dep. - Pacific Rim Fire Protection | F33: 10371.65
A34: 43532 | D34: Pre-construction Research - Tinguely Development | F34: 1100
A35: 43532 | D35: Development Permit/ Constr. V-Ball Design - Tinguely Development (Inv #18-405-03 R1) | F35: 3500
A36: 43538 | D36: Development Permit/ Constr. V-Ball Design - Tinguely Development (Inv #18-405-02 R3) | F36: 7250.86
A37: 43538 | D37: Exterior Paint and Sprinkler Piping - Kawika's Painting (Inv. #39-02-09) | F37: 68868.77
A38: 43546 | D38: Construction Management Fee - Athena Management | F38: 21317.41
A39: 43546 | D39: Elevator Upgrades - Otis Elevator Company | F39: 77883
... A139: 46141 | D139: 6050 4/23/2026 ELEVATOR MOD PAY APP 2 OTIS ELEVATOR COMPANY | F139: 58984.23
F141: =SUM(F22:F139) -> 2052989.6
C144: 15100 | D144: Tenant Improvement
A145: 44347 | D145: Gecko Girlz - TI Reimb | E145: 06/19/2025-06/18/2030 | F145: 35000
A146: 45258 | D146: Taka Sushi | E146: 01/01/2023-12/31/2027 | F146: 10740
A147: 45562 | D147: 5471 9/11/2024 HUMPY'S RENO | E147: 09/01/2022-08/31/2032 | F147: 804
A148: 45562 | D148: 5470 9/11/2024 HUMPY'S RENOVATION | E148: 09/01/2022-08/31/2032 | F148: 69294.33
A149: 45562 | D149: 5469 9/11/2024 HUMPY'S RENOVATION | E149: 09/01/2022-08/31/2032 | F149: 98991.9
A150: 45562 | D150: 5468 9/11/2024 HUMPY'S RENO APP1 | E150: 09/01/2022-08/31/2032 | F150: 29697.57
A151: 45594 | D151: 5516 10/24/2024 HUMPY'S TI REIMB | E151: 09/01/2022-08/31/2032 | F151: 125000
A152: 45657 | D152: CPA YEAR AJE # 7 | F152: -804
A153: 45657 | D153: CPA YEAR AJE # 11 | F153: -131389
F154: =SUM(F145:F153) -> 237334.8
A157: 43190 | C157: 15200 | D157: Other Capital Items - Seal Coating/Patch | F157: 36458
A158: 43308 | D158: Loeffler Construction, Inc.Owners paid | F158: 3150.5
A159: 43308 | D159: Replace doors | F159: 6301
A160: 43350 | D160: Wall Plan Design - Gene T Power and Assoc. | F160: 578.12
A161: 43357 | D161: 1st Landscape Design - Gene T Power and Assoc. | F161: 1927.07
A162: 43465 | D162: 2018 CPA AJE #3 - To expense Minor Capitalized Items | F162: -48414.69
A163: 44651 | D163: Walkway Repair Phase 1 | F163: 8320
A164: 44651 | D164: Walkway Repair Phase 2 | F164: 3328
A165: 44926 | D165: Prior Yr Adj 12/22 | F165: -11648
F166: =SUM(F157:F165) -> 0
C168: 15400 | D168: CAPITAL IMPROVEMENT
A169: 46049 | D169: Opening Balance for Year | F169: 11648
F170: =F169 -> 11648
C172: 15500 | D172: Construction In Progress
A173: 43456 | D173: Pre-construction Research - Tinguely Development (Inv #18-320-01) - 2018 CPA AJE #3 | F173: 2200
F174: =SUM(F173) -> 2200
C177: 16500 | D177: Leasing Commission
A178: 43783 | D178: Big Island Running (11/01/19-10/31/24) - Athena Management Inc | E178: 11/01/2024-10/31/2029 | F178: 1181.25
A179: 44133 | D179: Gecko Girlz (6/19/20-6/18/25) - SVN Go Commercial | E179: 06/19/2025-06/18/2030 | F179: 9744.92
A180: 44225 | D180: Venture Sotheby's (8/5/20-2/28/26)- SVN Go Commercial | F180: 12719.43
A181: 44225 | D181: Taka Sushi (12/1/21-11/30/26) - SVN Go Commercial | E181: 01/01/2023-12/31/2027 | F181: 11216.63
A182: 44340 | D182: Kanaka Kava (4/1/21-3/31/24) - Athena Management, Inc. | E182: 04/01/2024-03/31/2029 | F182: 681.12
A183: 44523 | D183: Fosters Kitchen - Athena Management, Inc. | E183: 07/01/2021-06/30/2031 | F183: 6671.81
A184: 44645 | D184: Kanaka Kava (4/1/21-3/31/24) - SVN Go Commercial | E184: 04/01/2024-03/31/2029 | F184: 2768.34
A185: 44720 | D185: Humpy Big Island Alehouse (07/01/22-04/30/23) - Athena Management, Inc. | E185: 09/01/2022-08/31/2032 | F185: 2096.94
A186: 44720 | D186: Café Kona (09/01/21-08/31/26) - Athena Management,Inc | E186: 09/01/2021-08/31/2026 | F186: 1610.4
A187: 44720 | D187: Gypsea Gelato (06/01/22-06/31/27) - Athena Management, Inc. | E187: 06/1/2022- 05/31/2027 | F187: 1592.74
A188: 44770 | D188: Taka Sushi (12/1/21-11/30/26)2ND 1/2 - SVN Go Commercial | E188: 01/01/2023-12/31/2027 | F188: 11216.62
A189: 44855 | D189: humpy Big Island Alehouse (09/01/22-08/31/32) - Athena Management, Inc. | E189: 09/01/2022-08/31/2032 | F189: 23672.88
A190: 44855 | D190: Lavernes Kohola (09/01/22-0831/32) - Athena Management, Inc. | E190: 09/01/2022-08/31/2032 | F190: 9334.08
A191: 45258 | D191: Lucaise LC (08/01/23 - 02/29/28) Athena Management, Inc. | E191: 08/01/2023-02/29/2028 | F191: 1872.36
A192: 45378 | D192: 5261 3/7/2024 Kanaka Kava - Athena Management, Inc. | E192: 04/01/2024-03/31/2029 | F192: 1261.45
... A196: 45960 | D196: 5873 10/29/2025 ISLAND LAVA JAVA | E196: 6/05/2025-5/31/2037 | F196: 17028.55
A197: 11/21/2025 | D197: HOT POT SVNGO COMMERCIAL | E197: 6/25/2026-6/30/2036 | F197: 92878.96
A198: 46014 | D198: 5918 12/18/2025 ABC LC RNWL | E198: 9/1/2005-12/31/2030 | F198: 21600
A199: 46101 | D199: 5996 3/5/2026 4/26-3/29 RNWL KONA GE ATHENA MANAGEMENT INC | E199: 4/1/2026-3/31/2029 | F199: 3480.51
F201: =SUM(F178:F199) -> 239044.55
C203: 16700 | D203: REFINANCE COSTS
A204: 45161 | D204: Good Faith Deposit - Refinance | F204: 23600
A205: 45539 | D205: LOAN FEES | F205: 140000
A206: 45539 | D206: OTHER LOAN COSTS | F206: 77996.9
A207: 45539 | D207: LEGAL FEES | F207: 113579.93
F209: =SUM(F204:F207) -> 355176.83
A211: 42978 | C211: 17000 | D211: Legal Fees | F211: 263681.19
A212: 43100 | D212: Adjust 2017 Recording of Property Purchase - CPA AJE | F212: -263681.19
F213: =SUM(F211:F212) -> 0
A215: 42978 | C215: 17600 | D215: Loan Fees | F215: 130700.02
A216: 43100 | D216: Adjust 2017 Recording of Property Purchase - CPA AJE | F216: 278062.79
A217: 45565 | D217: RCLS LOAN FEES TO 70270 DUE TO REFI | F217: -408762.81
A218: 45657 | D218: CPA YEAR AJE # 9 | F218: 442910.74
F219: =SUM(F215:F218) -> 442910.74
D223: 14000-000000 | F223: {=IFERROR(INDEX('TB '!G:G,MATCH(D223,'TB '!A:A,0),0),0)} -> 4369592.2
D224: S/B zero | F224: =F223-F13 -> 0
D225: 15000-000000 | F225: {=IFERROR(INDEX('TB '!G:G,MATCH(D225,'TB '!A:A,0),0),0)} -> 17478369
D226: S/B zero | F226: =F225-F18 -> 0
D227: 15010-000000 | F227: {=IFERROR(INDEX('TB '!G:G,MATCH(D227,'TB '!A:A,0),0),0)} -> 2052989.6
D228: S/B zero | F228: =F227-F141 -> 0
D229: 15100-000000 | F229: {=IFERROR(INDEX('TB '!G:G,MATCH(D229,'TB '!A:A,0),0),0)} -> 237334.8
...

Sheet 16500
A1: Coconut Grove Retail
A2: LEASING COMMISSIONS - 16500
A3: FOR THE MONTH ENDED 05/31/2026
A9: Origination Date | B9: Vendor | C9: Lease Term | D9: Description | E9: Amount | F9: Total Amount
G10: Comments
D11: OpeningBalanceforYear | E11: 104056.53
A12: 45960 | B12: ISLAND LAVA JAVA | C12: 06/01/2032-5/31/2037 | D12: 5873 10/29/2025 ISLAND LAVA JAVA | E12: 17028.55 | F12: =E11+E12 -> 121085.08
A13: 45982 | B13: HOT POT SVN GO COMMERCIAL | C13: 6/25/2026-6/30/2036 | D13: 5900 11/20/2025 LC1ST 1/2 Q | E13: 92878.96 | F13: =F12+E13 -> 213964.04
A14: 46014 | B14: ABC STORE | C14: 01/01/2026-12/31/2030 | D14: 5918 12/18/2025 ABC LC RNWL | E14: 21600 | F14: =F13+E14 -> 235564.04
A15: 46101 | B15: KONA GE | C15: 4/1/2026-3/31/2029 | D15: 5996 3/5/2026 4/26-3/29 RNWL | E15: 3480.51 | F15: =F14+E15 -> 239044.55
D18: Account Total: | F18: =F15 -> 239044.55
E20: =RIGHT(A2,5)&"-000000" -> 16500-000000 | F20: {=IFERROR(INDEX('TB '!G:G,MATCH(E20,'TB '!A:A,0),0),0)} -> 239044.55
E21: S/B zero | F21: =+F18-F20 -> 0

Sheet 17600
A1: ='Review Comments'!B9 -> COCONUT GROVE RETAIL XIII, LLC
A2: LOAN FEES - 17600
A3: ='Review Comments'!B11 -> FOR THE MONTH 07/31/2026
A9: Origination Date | C9: Description | E9: Amount | F9: Comment
A11: 45657 | C11: TO CAPITALIZE LOAN FEES ORGINATED FROM NEW LOAN | E11: 442910.74
C13: Account Total | E13: =SUM(E11:E12) -> 442910.74
D15: 17600-000000 | E15: {=IFERROR(INDEX('TB '!G:G,MATCH(D15,'TB '!A:A,0),0),0)} -> 442910.74
D16: S/B zero | E16: =E15-E13 -> 0

Sheet 15500
A1: ='Review Comments'!B9 -> COCONUT GROVE RETAIL XIII, LLC
A2: CIP- 15500
A3: ='Review Comments'!B11 -> FOR THE MONTH 07/31/2026
A9: Date | C9: Description | D9: Vendor | E9: Total Amount
D33: Account Total: | E33: =SUM(E11:E32) -> 0

Sheet 13000-
A1: ='Review Comments'!B9 -> COCONUT GROVE RETAIL XIII, LLC
A2: SUSPENSE-13000
A3: FOR THE ONE MONTH ENDED 01/31/17
B7: Date | C7: Tenant | D7: Description | F7: Amount | G7: Comment
D11: Account Total per Cash | F11: =SUM(F9:F10) -> 0

Sheet 17650
A1: ='Review Comments'!B9 -> COCONUT GROVE RETAIL XIII, LLC
A2: LOAN COSTS-17650
A3: ='Review Comments'!B11 -> FOR THE MONTH 07/31/2026
A9: Origination Date | C9: Vendor | D9: Description | F9: Amount | G9: Comment
A11: 43068 | C11: Hawaii Electric Light Co, Inc | D11: Acct# 201014742377 | F11: 0 | G11: SD Applied
A12: 43068 | C12: Hawaii Electric Light Co, Inc | D12: Acct# 201014743508 | F12: 0 | G12: SD Applied
A13: 43068 | C13: Hawaii Electric Light Co, Inc | D13: Acct# 201014744019 | F13: 0 | G13: SD Applied
A14: 43068 | C14: Hawaii Electric Light Co, Inc | D14: Acct# 201014744704 | F14: =-530+74.31+74.46+74.39+74.46-267.62+500 -> 0 | G14: SD Applied
A15: 43068 | C15: Hawaii Electric Light Co, Inc | D15: Acct# 201014744977 | F15: 0 | G15: SD Applied
A16: 43068 | C16: Hawaii Electric Light Co, Inc | D16: Acct# 201014745941 | F16: 0 | G16: SD Applied
A17: 43068 | C17: Hawaii Electric Light Co, Inc | D17: Acct# 201014746048 | F17: =500-500 -> 0 | G17: SD Applied
A18: 43087 | C18: Hawaii Electric Light Co, Inc | D18: Acct# 201014743508 | F18: 0 | G18: SD Applied
A19: 43087 | C19: Hawaii Electric Light Co, Inc | D19: Acct# 201014746048 | F19: 0 | G19: SD Applied
A20: 45455 | C20: MORGAN STANLEY | D20: RCD WIRE LOAN REFI | F20: 75000
A21: 45539 | D21: LOAN APPLICATION DEP | F21: -75000
D23: Account Total | F23: =SUM(F11:F21) -> 0

Sheet 12530
A1: ='Review Comments'!B9 -> COCONUT GROVE RETAIL XIII, LLC
A2: LOAN DEPOSIT - 12530
A3: ='Review Comments'!B11 -> FOR THE MONTH 07/31/2026
A7: Origination Date | B7: Account Number | C7: Period | D7: Vendor | E7: Description | G7: Amount
B9: 70110 | C9: 45503 | D9: Northmarq Capital | E9: NORTHMARQ CAPITAL LOAN DEPOSIT | G9: 25000
C10: 45565 | E10: RCLS NMC LOAN DEPOSIT | G10: -25000
G12: =SUM(G9:G10) -> 0
B46: Water
B47: Meter# | C47: Acct# | D47: GL
C48: 5500873513 | D48: 55140 | E48: Water/CAM
C49: 5500874513 | D49: 55140 | E49: Water/CAM
C50: 8546278012 | D50: 55140 | E50: Water/CAM
C51: 8546278910 | D51: 55140 | E51: Water/CAM
C52: 8546274910 | D52: 55140 | E52: Water/CAM
C53: 8546276013 | D53: 55140 | E53: Water/CAM
C54: 8546360013 | D54: 55140 | E54: Water/CAM
B57: 0008036548 | C57: 097-55008735-13 | D57: 55150 | E57: Fire Hydrent | G57: 097-55008745-12 | H57: old acct#
B58: 0008041574 | C58: 097-55008745-13 | D58: 55150 | E58: Fire Hydrent | G58: 097-55008735-12 | H58: old acct#
C60: 854-62750034 | D60: 55180 | E60: Water/Sewer
C61: 854-62760034 | D61: 55180 | E61: Water/Sewer
C62: 854-62790034 | D62: 55180 | E62: Water/Sewer
B67: Electric
B68: Meter# | C68: Acct# | D68: GL
B70: mhx000141323 | C70: 202011253806 | D70: 55110
B71: mhx000090356 | C71: 202010554280 | D71: 55110
B72: mhx000137834 | C72: 202014338760 | D72: 55110
B73: mhx000139327 | C73: 202014338802 | D73: 55110
B74: mhx000134811 | C74: 202011120534 | D74: 55110
B75: mhx000137526 | C75: 202011287648 | D75: 55110
B76: mhx000132532 | C76: 202011019009 | D76: 55110
C78: NEW ACCT'S
B80: mhx000090356 | C80: 201014742377 | D80: x
B81: mhx000141323 | C81: 201014744019
B82: mhx000134811 | C82: 201014744704 | D82: x
B83: mhx000132532 | C83: 201014744977
B84: mhx000139327 | C84: 201014745941
B85: mhx000137834 | C85: 201014746048
B86: mhx000137526 | C86: 201014743508 | D86: x

Sheet 20100
A1: ='Review Comments'!B9 -> COCONUT GROVE RETAIL XIII, LLC
A2: ACCOUNTS PAYABLE - 20100
A3: ='Review Comments'!B11 -> FOR THE MONTH 07/31/2026
A9: Origination Date | B9: Account Number | C9: Vendor | D9: Description | F9: Amount
A10: 46204 | B10: 50111-000000 | C10: CYPRESS PREMIUM FUNDING, INC. | D10: PROPERTY INS | F10: -11558.03
A11: 46213 | B11: 55140-000000 | C11: DEPT OF WATER SUPPLY | D11: 0506-0708 85463600-13 | F11: -4145.93
A12: 46213 | B12: 55140-000000 | C12: DEPT OF WATER SUPPLY | D12: 0506-0708 85462749-10 | F12: -327.72
A13: 46213 | B13: 55140-000000 | C13: DEPT OF WATER SUPPLY | D13: 0506-0708 8546276013 | F13: -422.28
A14: 46213 | B14: 55140-000000 | C14: DEPT OF WATER SUPPLY | D14: 0506-0708 8546278012 | F14: -830.68
A15: 46213 | B15: 55140-000000 | C15: DEPT OF WATER SUPPLY | D15: 0506-0708 85462789-10 | F15: -2073.83
C19: Account Total: | F19: =SUM(F10:F17) -> -19358.47
D20: 20100-000000 | F20: {=IFERROR(INDEX('TB '!$G:$G,MATCH(D20,'TB '!$A:$A,0),0),0)} -> -19358.47
D21: S/B zero | F21: =F20-F19 -> 0
F24: NOTE:
F25: IF BALANCE IS 0 DELETE HISTORY

Sheet 20650
A1: PORTER RANCH RETAIL II, INC.
A2: ACCRUE OPERATING EXPENSE-20650
A3: FOR THE MONTH ENDED 01/31/26
W4: 053294
A6: GL Code | B6: GL Desc. | C6: 45658 | D6: 45689 | E6: 45717 | F6: 45748 | G6: 45778 | H6: 45809 | I6: 45839 | J6: 45870 | K6: 45901 | L6: 45931 | M6: 45962 | N6: 45992 | O6: Total Budget | P6: Exp Type | Q6: Actual Trend | R6: Accrl Svc | S6: Vendor | T6: Amount Accrued | U6: Description of Work | W6: Notes
A8: 50160-000000 | B8: LANDSCAPE-CONSUMABLES | C8: 0 | D8: 7041 | E8: 8914 | F8: 0 | G8: 10300 | H8: 0 | I8: 0 | J8: 0 | K8: 0 | L8: 0 | M8: 0 | N8: 0 | O8: =SUM(C8:N8) -> 26255 | P8: Contigency | S8: HAWAII ISLAND LAWNS | U8: =IF((T8=0),"","ACCRUE "&R8&" "&B8)
A9: 50170-000000 | B9: LANDSCAPE-MAINTENANCE | C9: 7732 | D9: 7732 | E9: 7732 | F9: 7732 | G9: 7732 | H9: 7732 | I9: 7732 | J9: 7732 | K9: 7732 | L9: 7732 | M9: 7732 | N9: 7732 | O9: =SUM(C9:N9) -> 92784 | P9: Contract | R9: Paid | T9: 0 | U9: =IF((T9=0),"","ACCRUE "&R9&" "&B9)
A10: 50190-000000 | B10: LANDSCAPE-SPRINKLER REPAIRS | C10: 729 | D10: 729 | E10: 729 | F10: 729 | G10: 729 | H10: 729 | I10: 729 | J10: 729 | K10: 729 | L10: 729 | M10: 729 | N10: 729 | O10: =SUM(C10:N10) -> 8748 | P10: Contigency | T10: 0 | U10: =IF((T10=0),"","ACCRUE "&R10&" "&B10)
A11: 50210-000000 | B11: ELEVATOR MAINTENANCE | C11: 972 | D11: 2754 | E11: 272 | F11: 272 | G11: 2754 | H11: 272 | I11: 272 | J11: 2754 | K11: 272 | L11: 272 | M11: 2754 | N11: 272 | O11: =SUM(C11:N11) -> 13892 | P11: Contract | R11: Paid | T11: 0 | U11: =IF((T11=0),"","ACCRUE "&R11&" "&B11)
A12: 50520-000000 | B12: PARKING LOT MAINTENANCE | C12: 0 | D12: 500 | E12: 0 | F12: 0 | G12: 500 | H12: 0 | I12: 0 | J12: 500 | K12: 0 | L12: 0 | M12: 500 | N12: 0 | O12: =SUM(C12:N12) -> 2000 | P12: Contract | R12: - | T12: 0 | U12: =IF((T12=0),"","ACCRUE "&R12&" "&B12)
A13: 50540-000000 | B13: PARKING LOT REPAIRS | C13: 0 | D13: 750 | E13: 0 | F13: 0 | G13: 750 | H13: 0 | I13: 0 | J13: 750 | K13: 0 | L13: 0 | M13: 750 | N13: 0 | O13: =SUM(C13:N13) -> 3000 | P13: Contigency | T13: 0 | U13: =IF((T13=0),"","ACCRUE "&R13&" "&B13)
A14: 50551-000000 | B14: SIGN REPAIRS | C14: 200 | D14: 0 | E14: 0 | F14: 200 | G14: 0 | H14: 0 | I14: 200 | J14: 0 | K14: 0 | L14: 200 | M14: 0 | N14: 0 | O14: =SUM(C14:N14) -> 800 | P14: Contigency | T14: 0 | U14: =IF((T14=0),"","ACCRUE "&R14&" "&B14)
A15: 51020-000000 | B15: GENERAL MAINTENANCE | C15: 3000 | D15: 3000 | E15: 3000 | F15: 3000 | G15: 3000 | H15: 3000 | I15: 3000 | J15: 3000 | K15: 3000 | L15: 3000 | M15: 3000 | N15: 3000 | O15: =SUM(C15:N15) -> 36000 | P15: Contract | R15: Paid | T15: 0 | U15: =IF((T15=0),"","ACCRUE "&R15&" "&B15)
A16: 51030-000000 | B16: MISC MAINT & REPAIRS | C16: 0 | D16: 0 | E16: 0 | F16: 3750 | G16: 1000 | H16: 0 | I16: 0 | J16: 3750 | K16: 0 | L16: 0 | M16: 0 | N16: 0 | O16: =SUM(C16:N16) -> 8500 | P16: Contigency | T16: 0 | U16: =IF((T16=0),"","ACCRUE "&R16&" "&B16)
A17: 51040-000000 | B17: JANITORIAL | C17: 11199 | D17: 11199 | E17: 11199 | F17: 11199 | G17: 11199 | H17: 11199 | I17: 11199 | J17: 11199 | K17: 11199 | L17: 11199 | M17: 11199 | N17: 11199 | O17: =SUM(C17:N17) -> 134388 | P17: Contract | R17: Paid | U17: =IF((T17=0),"","ACCRUE "&R17&" "&B17)
A18: 51050-000000 | B18: PEST CONTROL MAINT-RODENT | C18: 297 | D18: 297 | E18: 800 | F18: 297 | G18: 297 | H18: 800 | I18: 297 | J18: 297 | K18: 800 | L18: 297 | M18: 297 | N18: 800 | O18: =SUM(C18:N18) -> 5576 | P18: Contract | R18: Paid | S18: SMART PEST PREVENTION | T18: 0 | U18: =IF((T18=0),"","ACCRUE "&R18&" "&B18) | W18: *** Run Standard income Statement for month. (Cash)
A19: 51060-000000 | B19: ROOF MAINTENANCE | C19: 0 | D19: 2500 | E19: 0 | F19: 0 | G19: 0 | H19: 0 | I19: 0 | J19: 0 | K19: 0 | L19: 2500 | M19: 0 | N19: 0 | O19: =SUM(C19:N19) -> 5000 | P19: Contigency | U19: =IF((T19=0),"","ACCRUE "&R19&" "&B19)
A20: 51070-000000 | B20: ROOF REPAIRS | C20: 0 | D20: 0 | E20: 0 | F20: 500 | G20: 0 | H20: 0 | I20: 0 | J20: 0 | K20: 0 | L20: 0 | M20: 0 | N20: 0 | O20: =SUM(C20:N20) -> 500 | P20: Contigency | T20: 0 | U20: =IF((T20=0),"","ACCRUE "&R20&" "&B20)
A21: 51110-000000 | B21: MONITOR FIRE SPRINKLERS | C21: 0 | D21: 0 | E21: 770 | F21: 0 | G21: 0 | H21: 0 | I21: 2874 | J21: 0 | K21: 0 | L21: 0 | M21: 0 | N21: 0 | O21: =SUM(C21:N21) -> 3644 | P21: Contigency | T21: 0 | U21: =IF((T21=0),"","ACCRUE "&R21&" "&B21)
A22: 51120-000000 | B22: FIRE PROTECTION REPAIRS | C22: 0 | D22: 0 | E22: 0 | F22: 603 | G22: 0 | H22: 0 | I22: 0 | J22: 600 | K22: 0 | L22: 0 | M22: 0 | N22: 0 | O22: =SUM(C22:N22) -> 1203 | P22: Contigency | R22: Paid | T22: 0 | U22: =IF((T22=0),"","ACCRUE "&R22&" "&B22)
A23: 51150-000000 | B23: SWEEPING | C23: 2577 | D23: 2627 | E23: 2627 | F23: 2627 | G23: 2627 | H23: 2627 | I23: 2627 | J23: 2627 | K23: 2627 | L23: 2627 | M23: 2627 | N23: 2627 | O23: =SUM(C23:N23) -> 31474 | P23: Contract | R23: Paid | T23: 0 | U23: =IF((T23=0),"","ACCRUE "&R23&" "&B23)
A24: 51160-000000 | B24: SECURITY | C24: 14930 | D24: 14930 | E24: 14930 | F24: 14930 | G24: 14930 | H24: 14930 | I24: 14930 | J24: 14930 | K24: 14930 | L24: 14930 | M24: 14930 | N24: 14930 | O24: =SUM(C24:N24) -> 179160 | P24: Contract | R24: 12/25 | T24: 7500 | U24: =IF((T24=0),"","ACCRUE "&R24&" "&B24) -> ACCRUE 12/25 SECURITY
A25: 51200-000000 | B25: ELECTRICAL REPAIRS/CAM | C25: 0 | D25: 1500 | E25: 0 | F25: 0 | G25: 1500 | H25: 0 | I25: 0 | J25: 1500 | K25: 0 | L25: 0 | M25: 1500 | N25: 0 | O25: =SUM(C25:N25) -> 6000 | P25: Contract | R25: Paid | T25: 0 | U25: =IF((T25=0),"","ACCRUE "&R25&" "&B25)
A26: 51210-000000 | B26: PLUMBING REPAIRS | C26: 1500 | D26: 0 | E26: 0 | F26: 1500 | G26: 0 | H26: 0 | I26: 1500 | J26: 0 | K26: 0 | L26: 1500 | M26: 0 | N26: 0 | O26: =SUM(C26:N26) -> 6000 | P26: Contigency | R26: Paid | T26: 0 | U26: =IF((T26=0),"","ACCRUE "&R26&" "&B26)
A27: 51220-000000 | B27: PAINTING | C27: 0 | D27: 500 | E27: 0 | F27: 0 | G27: 500 | H27: 0 | I27: 0 | J27: 500 | K27: 0 | L27: 0 | M27: 500 | N27: 0 | O27: =SUM(C27:N27) -> 2000 | P27: Contigency | T27: 0 | U27: =IF((T27=0),"","ACCRUE "&R27&" "&B27)
A28: 52010-000000 | B28: JANITORIAL SUPPLIES | C28: 1854 | D28: 1854 | E28: 1854 | F28: 1854 | G28: 1854 | H28: 1854 | I28: 1854 | J28: 1854 | K28: 1854 | L28: 1854 | M28: 1854 | N28: 1854 | O28: =SUM(C28:N28) -> 22248 | P28: Contigency | R28: 12/25 | T28: 0 | U28: =IF((T28=0),"","ACCRUE "&R28&" "&B28)
A29: 52020-000000 | B29: BACKFLOW-MAINTENANCE | C29: 0 | D29: 0 | E29: 0 | F29: 0 | G29: 0 | H29: 0 | I29: 1030 | J29: 0 | K29: 0 | L29: 0 | M29: 0 | N29: 0 | O29: =SUM(C29:N29) -> 1030 | P29: Contigency | T29: 0
A31: 55110-000000 | B31: ELECTRIC/COMMON AREA | C31: 3022 | D31: 3022 | E31: 3022 | F31: 3022 | G31: 3022 | H31: 3022 | I31: 3022 | J31: 3022 | K31: 3022 | L31: 3022 | M31: 3022 | N31: 3022 | O31: =SUM(C31:N31) -> 36264 | P31: Contract | R31: 12/12-12/31 | T31: 0 | U31: ACCRUE 12/12-12/31/25 ELECTRIC/CAM | W31: 8 accts | Y31: =149.09+106+57.15+57.15+491.86+682.74+82.77 -> 1626.76 | Z31: 45974 | AA31: 46002 | AB31: 46022 | AC31: =+AA31-Z31+1 -> 29 | AD31: =+Y31/AC31 -> 56.095172 | AE31: =+AB31-AA31 -> 20 | AF31: =+AD31*AE31 -> 1121.9034
A32: 55120-000000 | B32: TRASH REMOVAL | C32: 1620 | D32: 1620 | E32: 1620 | F32: 1620 | G32: 1620 | H32: 1620 | I32: 1620 | J32: 1620 | K32: 1620 | L32: 1620 | M32: 1620 | N32: 1620 | O32: =SUM(C32:N32) -> 19440 | P32: Contract | R32: 12/25 | S32: PACIFIC WASTE | T32: 0 | U32: =IF((T32=0),"","ACCRUE "&R32&" "&B32) | W32: based on actual
A33: 55140-000000 | B33: WATER/COMMON AREA | C33: 11330 | D33: 386 | E33: 11330 | F33: 386 | G33: 11330 | H33: 386 | I33: 11330 | J33: 386 | K33: 11330 | L33: 386 | M33: 11330 | N33: 386 | O33: =SUM(C33:N33) -> 70296 | P33: Contract | R33: 11/06/25-12/31/25 | S33: DEPT OF WATER SUPPLY | T33: 0 | U33: ACCRUE 09/06-12/31/25 WATER/CAM | W33: 3 accts | X33: every other month | Y33: =5998.77+340.24+2021.75+799.3+510.21 -> 9670.27 | Z33: 45906 | AA33: 45967 | AB33: 46022 | AC33: =+AA33-Z33+1 -> 62 | AD33: =+Y33/AC33 -> 155.9721 | AE33: =+AB33-AA33 -> 55 | AF33: =+AD33*AE33 -> 8578.4653
A34: 55140-000000 | B34: WATER/COMMON AREA | O34: =SUM(C34:N34) -> 0 | P34: Contract | R34: 11/26-12/31/25 | S34: DEPT OF WATER SUPPLY | T34: 0 | U34: ACCRUE 11/26-12/31/25 WATER/CAM | W34: 2 accts | X34: water/cam & water/fire are the same acct | Y34: =294.05+193.32 -> 487.37 | Z34: 45959 | AA34: 45986 | AB34: 46022 | AC34: =+AA34-Z34+1 -> 28 | AD34: =+Y34/AC34 -> 17.406071 | AE34: =+AB34-AA34 -> 36 | AF34: =+AD34*AE34 -> 626.61857
A35: 55160-000000 | B35: GAS | C35: 201 | D35: 201 | E35: 201 | F35: 201 | G35: 201 | H35: 201 | I35: 201 | J35: 201 | K35: 201 | L35: 201 | M35: 201 | N35: 201 | O35: =SUM(C35:N35) -> 2412 | P35: Contract | R35: 10/02-11/30 | S35: HAWAII GAS | U35: ACCRUE 10/02-11/30 GAS | W35: 1 acct | Y35: 73.04 | Z35: 45902 | AA35: 45931 | AB35: 45963 | AC35: =+AA35-Z35+1 -> 30 | AD35: =+Y35/AC35 -> 2.4346667 | AE35: =+AB35-AA35 -> 32 | AF35: =+AD35*AE35 -> 77.909333
A36: 55160-000000 | B36: GAS | R36: 11/03-12/31 | S36: HAWAII GAS | T36: 0 | U36: ACCRUE 10/02-11/30 GAS | Y36: 73.04 | Z36: 45964 | AA36: 45993 | AB36: 46022 | AC36: =+AA36-Z36+1 -> 30 | AD36: =+Y36/AC36 -> 2.4346667 | AE36: =+AB36-AA36 -> 29 | AF36: =+AD36*AE36 -> 70.605333
A37: 55180-000000 | B37: WATER/SEWER #85462 | C37: 10183 | D37: 10183 | E37: 10183 | F37: 10183 | G37: 10183 | H37: 10183 | I37: 10183 | J37: 10183 | K37: 10183 | L37: 10183 | M37: 10183 | N37: 10183 | O37: =SUM(C37:N37) -> 122196 | P37: Contract | R37: 10/01-12/31/25 | S37: COUNTY DIRECTOR | T37: 0 | U37: ACCRUE 10/01-12/31/25 WATER/SEWER | W37: 85462760034, 85462780033, 85463600, 85462789 | Y37: =1259.59+109.65+917.59+2429.77+9135.1 -> 13851.7 | Z37: 45870 | AA37: 45930 | AB37: 46022 | AC37: =+AA37-Z37+1 -> 61 | AD37: =+Y37/AC37 -> 227.07705 | AE37: =+AB37-AA37 -> 92 | AF37: =+AD37*AE37 -> 20891.089
A38: 55190-000000 | B38: GROUND RENT | C38: 8803 | D38: 8803 | E38: 8803 | F38: 8803 | G38: 25003 | H38: 8803 | I38: 8803 | J38: 8803 | K38: 8803 | L38: 8803 | M38: 25003 | N38: 8803 | O38: =SUM(C38:N38) -> 138036 | P38: Contract | R38: Paid | T38: 0 | U38: =IF((T38=0),"","ACCRUE "&R38&" "&B38)
A39: 57110-000000 | B39: FOOD COURT-JANITORIAL&SUPPLIES | C39: 2800 | D39: 2800 | E39: 2800 | F39: 2800 | G39: 2800 | H39: 2800 | I39: 2800 | J39: 2800 | K39: 2800 | L39: 2800 | M39: 2800 | N39: 2800 | O39: =SUM(C39:N39) -> 33600 | P39: Contract | R39: Paid | T39: 0 | U39: =IF((T39=0),"","ACCRUE "&R39&" "&B39) | Y39: 0
A40: 57120-000000 | B40: FOOD COURT-GAS | C40: 145 | D40: 145 | E40: 145 | F40: 145 | G40: 145 | H40: 145 | I40: 145 | J40: 145 | K40: 145 | L40: 145 | M40: 145 | N40: 145 | O40: =SUM(C40:N40) -> 1740 | P40: Contract | R40: 10/02-11/30/25 | S40: HAWAII GAS | U40: ACCRUE 10/02-11/30/25 FOOD COURT-GAS | W40: 1acct | Y40: 73.04 | Z40: 45902 | AA40: 45931 | AB40: 45963 | AC40: =+AA40-Z40+1 -> 30 | AD40: =+Y40/AC40 -> 2.4346667 | AE40: =+AB40-AA40 -> 32 | AF40: =+AD40*AE40 -> 77.909333
A41: 57120-000000 | B41: FOOD COURT-GAS | R41: 11/03-12/31 | S41: HAWAII GAS | T41: 0 | U41: ACCRUE 10/02-11/30/25 FOOD COURT-GAS | Y41: 73.04 | Z41: 45964 | AA41: 45993 | AB41: 46022 | AC41: =+AA41-Z41+1 -> 30 | AD41: =+Y41/AC41 -> 2.4346667 | AE41: =+AB41-AA41 -> 29 | AF41: =+AD41*AE41 -> 70.605333
A42: 51160-000000 | B42: Secuirty | T42: 0
A43: 57130-000000 | B43: FOOD COURT-SECURITY | C43: 2976 | D43: 2976 | E43: 2976 | F43: 2976 | G43: 2976 | H43: 2976 | I43: 2976 | J43: 2976 | K43: 2976 | L43: 2976 | M43: 2976 | N43: 2976 | O43: =SUM(C43:N43) -> 35712 | P43: Contract | R43: 12/25 | T43: 1865.58 | U43: ACCRUE 12/25 FOOD COURT-SECURITY
A44: 57140-000000 | B44: FOOD COURT-TRASH | C44: 6500 | D44: 6500 | E44: 6500 | F44: 6500 | G44: 6500 | H44: 6500 | I44: 6500 | J44: 6500 | K44: 6500 | L44: 6500 | M44: 6500 | N44: 6500 | O44: =SUM(C44:N44) -> 78000 | P44: Contract | R44: 12/25 | S44: PACIFIC WASTE | T44: 0 | U44: ACCRUE 12/25 FOOD COURT-TRASH | W44: based on actual
A45: 70411-000000 | B45: GENERAL EXCISE TAX PAYMENTS | C45: 16337 | D45: 16337 | E45: 16337 | F45: 16337 | G45: 16337 | H45: 16337 | I45: 16337 | J45: 16337 | K45: 16337 | L45: 16337 | M45: 16832 | N45: 16832 | O45: =SUM(C45:N45) -> 197034 | P45: Contract | R45: 12/25 | S45: CITY OF HAWAII | T45: 0 | U45: ACCRUE 12/25 GET | W45: total rental income X 0.045
U46: =IF((T46=0),"","ACCRUE "&R46&" "&B46)
A47: 20650-000000 | B47: ACCRUE OPERATING EXPENSES | T47: =SUM(T8:T46)-0.01 -> 9365.57
S49: =RIGHT(A2,5)&"-000000" -> 20650-000000 | T49: {=-IFERROR(INDEX('TB '!$G:$G,MATCH(S49,'TB '!$A:$A,0),0),0)} -> 9365.57 | W49: Water
S50: S/B zero | T50: =+T47-T49 -> 0 | W50: Meter# | X50: Acct# | Y50: GL
X51: 5500873513 | Y51: 55140 | Z51: Water/CAM
X52: 5500874513 | Y52: 55140 | Z52: Water/CAM
X53: 8546278012 | Y53: 55140 | Z53: Water/CAM
X54: 8546278910 | Y54: 55140 | Z54: Water/CAM
S55: =381020.77 -> 381020.77 | X55: 8546274910 | Y55: 55140 | Z55: Water/CAM
X56: 8546276013 | Y56: 55140 | Z56: Water/CAM
S57: =S55*0.045 -> 17145.935 | X57: 8546360013 | Y57: 55140 | Z57: Water/CAM
W60: 0008036548 | X60: 097-55008735-13 | Y60: 55150 | Z60: Fire Hydrent | AA60: 097-55008745-12 | AB60: old acct#
W61: 0008041574 | X61: 097-55008745-13 | Y61: 55150 | Z61: Fire Hydrent | AA61: 097-55008735-12 | AB61: old acct#
X63: 854-62750034 | Y63: 55180 | Z63: Water/Sewer
X64: 854-62760034 | Y64: 55180 | Z64: Water/Sewer
X65: 854-62790034 | Y65: 55180 | Z65: Water/Sewer
W70: Electric
W71: Meter# | X71: Acct# | Y71: GL
W73: mhx000141323 | X73: 202011253806 | Y73: 55110
W74: mhx000090356 | X74: 202010554280 | Y74: 55110
W75: mhx000137834 | X75: 202014338760 | Y75: 55110
W76: mhx000139327 | X76: 202014338802 | Y76: 55110
W77: mhx000134811 | X77: 202011120534 | Y77: 55110
W78: mhx000137526 | X78: 202011287648 | Y78: 55110
W79: mhx000132532 | X79: 202011019009 | Y79: 55110
X81: NEW ACCT'S
W83: mhx000090356 | X83: 201014742377 | Y83: x
W84: mhx000141323 | X84: 201014744019
W85: mhx000134811 | X85: 201014744704 | Y85: x
W86: mhx000132532 | X86: 201014744977
W87: mhx000139327 | X87: 201014745941
W88: mhx000137834 | X88: 201014746048
W89: mhx000137526 | X89: 201014743508 | Y89: x
W125: SAMPLE:

Sheet 20650 old
A1: ='Review Comments'!B9 -> COCONUT GROVE RETAIL XIII, LLC
A2: EXPENSE ACCRUALS - 20650
A3: ='Review Comments'!B11 -> FOR THE MONTH 07/31/2026
A7: Origination Date | B7: Account Number | D7: Vendor | E7: Description | F7: Amount
B9: 50170 | E9: ACCRUE 09/24 LANDSCAPE MAINT | F9: 0 | AI9: New Aded
B10: 51040 | E10: ACCRUE 08/24 JANITORIAL | F10: 0
B12: 50160 | D12: Hawaii Island Lawns | E12: ACCRUE LANDSCAPE CONSUMABLES | F12: 25000
B13: 50210 | D13: Hawaiian Telecom | E13: 02/25-05/25 Elevator Phone Lines | F13: 0
B14: 51050 | D14: Smart Pest Prevention | E14: ACCRUE 06/25 PEST CONTROL
B15: 51060 | G15: Per Jan stop accruing
B16: 51110 | D16: Rim Fire Protection | E16: ACCRUE MONITOR FIRE SPRINKLERS | F16: 0 | AI16: ASK
B18: 51120 | D18: National Fire Proctection | E18: 2 Fire Extinguishers | F18: 0
B19: 51160 | D19: Hawaiian Telecom | E19: 04/23 WIFI | F19: 0
B20: 51161 | D20: Elite Interactive Solutions | F20: 0
B21: 51210 | D21: Tropical Marine Environments | E21: ACCRUE 3Q24 STORM WATER | F21: 0
B22: 51050 | E22: ACCRUE 06/25 RODENT | F22: 0
B23: 52010 | E23: ACCRUE JANITORIAL SUPPLIES | F23: 0
B24: 52020 | E24: ACCRUE BACKFLOW-MAINTENANCE | F24: 1030
B25: 51160 | E25: ACCRUE 04/25 SECURITY | F25: 0 | I25: Last Paid Amt | J25: Start date | K25: End Date | L25: Accrual end date | M25: Days | N25: Per day Amt | O25: Accrual days | P25: To be Accrued
B26: 55110 | D26: Hawaii Electric Light Co. | E26: ACCRUE 8/13/25 TO 08/31/25 ELECTRIC/CAM | F26: =P26 -> 1554.6979 | G26: 8 accts | I26: =136.31+263.56+94.24+57.15+765.26+419+554.67+82.77 -> 2372.96 | J26: 45853 | K26: 45881 | L26: 45900 | M26: =+K26-J26+1 -> 29 | N26: =+I26/M26 -> 81.826207 | O26: =+L26-K26 -> 19 | P26: =+N26*O26 -> 1554.6979
B27: 55120 | D27: Pacific Waste Inc | E27: ACCRUE 08/25 TRASH | F27: 1393.86 | G27: based on actual
B28: 55140 | D28: Dept of Water Supply | E28: ACCRUE 07/08 - 08/31/25 WATER/CAM | F28: =P28+Y28 -> 6940.3858 | G28: 3 accts | H28: every other month | I28: =5026.89+307.14+2237.3 -> 7571.33 | J28: 45786 | K28: 45845 | L28: 45900 | M28: =+K28-J28+1 -> 60 | N28: =+I28/M28 -> 126.18883 | O28: =+L28-K28 -> 55 | P28: =+N28*O28 -> 6940.3858
B29: 55140 | D29: Dept of Water Supply | E29: ACCRUE 07/08 - 08/31/25 WATER/CAM | F29: =P29 -> 670.27583 | G29: #8546278012 | I29: 731.21 | J29: 45786 | K29: 45845 | L29: 45900 | M29: =+K29-J29+1 -> 60 | N29: =+I29/M29 -> 12.186833 | O29: =+L29-K29 -> 55 | P29: =+N29*O29 -> 670.27583
B30: 55140 | D30: Dept of Water Supply | E30: ACCRUE 07/08 - 08/31/25 WATER/CAM | F30: =P30 -> 400.62 | G30: #8546276013 | I30: 437.04 | J30: 45786 | K30: 45845 | L30: 45900 | M30: =+K30-J30+1 -> 60 | N30: =+I30/M30 -> 7.284 | O30: =+L30-K30 -> 55 | P30: =+N30*O30 -> 400.62
B31: 55140 | D31: Dept of Water Supply | E31: ACCRUE 07/29 - 08/31/25 WATER/FIRE | F31: =P31 -> 494.88545 | G31: 2 accts | H31: water/cam & water/fire are the same acct | I31: =289.8+190.53 -> 480.33 | J31: 45834 | K31: 45866 | L31: 45900 | M31: =+K31-J31+1 -> 33 | N31: =+I31/M31 -> 14.555455 | O31: =+L31-K31 -> 34 | P31: =+N31*O31 -> 494.88545
B32: 55160 | D32: Hawaii Gas | E32: ACCRUE 07/02/25 TO 08/31/25 GAS | F32: =P32 -> 135.80633 | G32: 1 acct | I32: 66.79 | J32: 45810 | K32: 45839 | L32: 45900 | M32: =+K32-J32+1 -> 30 | N32: =+I32/M32 -> 2.2263333 | O32: =+L32-K32 -> 61 | P32: =+N32*O32 -> 135.80633
B33: 55190 | D33: Land and Natural Resources | E33: Semi-Annual Ground Rent | F33: 0 | L33: 45900
B34: 55180 | D34: COUNTY DIRECTOR OF FINANCE | E34: ACCRUE 06/01/2025- 08/31/25 WATER/SEWER | F34: =P34 -> 19820.827 | G34: 85462760034, 85462780033, 85463600, 85462789 | I34: =471.88+3718.28+7959.09+111.23+881.59 -> 13142.07 | J34: 45748 | K34: 45808 | L34: 45900 | M34: =+K34-J34+1 -> 61 | N34: =+I34/M34 -> 215.44377 | O34: =+L34-K34 -> 92 | P34: =+N34*O34 -> 19820.827
B35: 57120 | D35: Hawaii Gas | E35: ACCRUE 07/02/25 to 08/31/25 FOOD COURT GAS | F35: =P35 -> 135.80633 | G35: 1acct | I35: 66.79 | J35: 45810 | K35: 45839 | L35: 45900 | M35: =+K35-J35+1 -> 30 | N35: =+I35/M35 -> 2.2263333 | O35: =+L35-K35 -> 61 | P35: =+N35*O35 -> 135.80633
B36: 57110 | E36: ACCRUE 08/24 JANITORIAL | F36: 0
B37: 57130 | D37: Viking svc of hawaii | E37: ACCRUE 02/25 SECURITY
B38: 57130 | E38: ACCRUE 07/24 SECURITY | F38: 0
B39: 57140 | D39: Pacific Waste Inc | E39: ACCRUE 08/25 FC TRASH | F39: 5575.42 | G39: based on actual
B40: 70210 | D40: Calvin's Plumbing | E40: Water Line Repairs | H40: 400229.86
B41: 70260 | D41: Hawaii Tours Inc | E41: 01/01-01/15 Shuttle Svc | F41: 0 | G41: No shuttle svc for 04/20-09/20
B42: 70260 | D42: Edward Repair Handyman Services | E42: Online Map Directory | F42: 0
B43: 70260 | D43: Placewise Digital | E43: Data Insight Report | F43: 0
B44: 70411 | D44: City of Hawaii | E44: ACCRUE 08/25 GET | F44: =286425.43*0.045 -> 12889.144 | G44: *** Run Standard income Statement for month. (Cash)
B45: 51050 | D45: SMART PEST PREVENTION LLC | E45: ACCRUE 08/25 RODENT | F45: 297 | G45: total rental income X 0.045
G47: ` | J47: Sample ------>
F49: =SUM(F9:F45)+0.02 -> 76338.749
F50: 20650-000000
E51: 20650-000000 | F51: {=-IFERROR(INDEX('TB '!G:G,MATCH('20650 old'!E51,'TB '!A:A,0),0),0)} -> 9365.57
E52: S/B zero | F52: =F49-F51 -> 66973.179
B54: Water
B55: Meter# | C55: Acct# | D55: GL
C56: 5500873513 | D56: 55140 | E56: Water/CAM
C57: 5500874513 | D57: 55140 | E57: Water/CAM
C58: 8546278012 | D58: 55140 | E58: Water/CAM
C59: 8546278910 | D59: 55140 | E59: Water/CAM
C60: 8546274910 | D60: 55140 | E60: Water/CAM
C61: 8546276013 | D61: 55140 | E61: Water/CAM
C62: 8546360013 | D62: 55140 | E62: Water/CAM
B65: 0008036548 | C65: 097-55008735-13 | D65: 55150 | E65: Fire Hydrent | F65: 097-55008745-12 | G65: old acct#
B66: 0008041574 | C66: 097-55008745-13 | D66: 55150 | E66: Fire Hydrent | F66: 097-55008735-12 | G66: old acct#
C68: 854-62750034 | D68: 55180 | E68: Water/Sewer
C69: 854-62760034 | D69: 55180 | E69: Water/Sewer
C70: 854-62790034 | D70: 55180 | E70: Water/Sewer
B75: Electric
B76: Meter# | C76: Acct# | D76: GL
B78: mhx000141323 | C78: 202011253806 | D78: 55110
B79: mhx000090356 | C79: 202010554280 | D79: 55110
B80: mhx000137834 | C80: 202014338760 | D80: 55110
B81: mhx000139327 | C81: 202014338802 | D81: 55110
B82: mhx000134811 | C82: 202011120534 | D82: 55110
B83: mhx000137526 | C83: 202011287648 | D83: 55110
B84: mhx000132532 | C84: 202011019009 | D84: 55110
C86: NEW ACCT'S
B88: mhx000090356 | C88: 201014742377 | D88: x
B89: mhx000141323 | C89: 201014744019
B90: mhx000134811 | C90: 201014744704 | D90: x
B91: mhx000132532 | C91: 201014744977
B92: mhx000139327 | C92: 201014745941
B93: mhx000137834 | C93: 201014746048
B94: mhx000137526 | C94: 201014743508 | D94: x

Sheet 20620
A1: ='Review Comments'!B9 -> COCONUT GROVE RETAIL XIII, LLC
A2: LEASE COMMISSION PAYABLE 20620
A3: ='Review Comments'!B11 -> FOR THE MONTH 07/31/2026
A9: Origination Date | C9: Description | E9: Amount | F9: Total Amount
C15: Account Total: | F15: =F12 -> 0

Sheet 26300
A1: ='Review Comments'!B9 -> COCONUT GROVE RETAIL XIII, LLC
A2: TENANT CREDITS FROM SELLER- 26300
A3: ='Review Comments'!B11 -> FOR THE MONTH 07/31/2026
A9: Date | C9: Account Number | D9: Description | E9: Total Amount
D18: Account Total: | E18: =SUM(E11:E17) -> 0

Sheet 20110
A1: ='Review Comments'!B9 -> COCONUT GROVE RETAIL XIII, LLC
A2: ACCOUNTS PAYABLE OTHER- 20110
A3: ='Review Comments'!B11 -> FOR THE MONTH 07/31/2026
A9: Origination Date | C9: Description | E9: Amount | F9: Total Amount
A11: 42998 | C11: Loan from San Carlos | E11: 20000 | F11: =E11 -> 20000
A12: 43039 | C12: Payback San Carlos Loan | E12: -20000 | F12: =F11+E12 -> 0
C14: Account Total: | F14: =F12 -> 0

Sheet 25300
A1: ='Review Comments'!B9 -> COCONUT GROVE RETAIL XIII, LLC
A2: NOTE PAYABLE - 25300
A3: ='Review Comments'!B11 -> FOR THE MONTH 07/31/2026
A9: Origination Date | C9: Description | E9: Amount | F9: Comment
A11: 42978 | C11: Beginning Balance | E11: 15116000 | F11: Northmarq Bank
A12: 44110 | C12: 09/20 Mortgage Payment | E12: -19369.16 | F12: Northmarq Bank
A13: 44140 | C13: 10/20 Mortgage Payment | E13: -17494.23 | F13: Northmarq Bank
A14: 44169 | C14: 11/20 Mortgage Payment | E14: -19512.01 | F14: Northmarq Bank
A15: 44201 | C15: 12/20 Mortgage Payment | E15: -17642.41 | F15: Northmarq Bank
A16: 44232 | C16: 1/21 Mortgage Payment | E16: -17713.06 | F16: Northmarq Bank
A17: 44260 | C17: 2/21 Mortgage Payment | E17: -23605.89 | F17: Northmarq Bank
A18: 44291 | C18: 3/21 Mortgage Payment | E18: -17878.5 | F18: Northmarq Bank
A19: 44321 | C19: 4/21 Mortgage Payment | E19: -19885.37 | F19: Northmarq Bank
A20: 44351 | C20: 5/21 Mortgage Payment | E20: -18029.72 | F20: Northmarq Bank
A21: 44379 | C21: 6/21 Mortgage Payment | E21: -20032.29 | F21: Northmarq Bank
A22: 44413 | C22: 7/21 Mortgage Payment | E22: -18182.12 | F22: Northmarq Bank
... A26: 44532 | C26: 11/21 Mortgage Payment | E26: -20400.92 | F26: Northmarq Bank
A27: 01/58/22 | C27: 12/21 Mortgage Payment | E27: -18564.51 | F27: Northmarq Bank
A28: 44597 | C28: 01/22 Mortgage Payment | E28: -18638.85 | F28: Northmarq Bank
A29: 44625 | C29: 02/22 Mortgage Payment | E29: -24445.44 | F29: Northmarq Bank
A30: 44656 | C30: 03/22 Mortgage Payment | E30: -18811.37 | F30: Northmarq Bank
A31: 44686 | C31: 04/22 Mortgage Payment | E31: -20791.75 | F31: Northmarq Bank
A32: 44716 | C32: 05/22 Mortgage Payment | E32: -18969.94 | F32: Northmarq Bank
A33: 44744 | C33: 06/22 Mortgage Payment | E33: -20945.83 | F33: Northmarq Bank
A34: 44778 | C34: 07/22 Mortgage Payment | E34: -19129.77 | F34: Northmarq Bank
A35: 44806 | C35: 08/22 Mortgage Payment | E35: -19206.37 | F35: Northmarq Bank
A36: 44836 | C36: 09/22 Mortgage Payment | E36: -21175.55 | F36: Northmarq Bank
A37: 44867 | C37: 10/22 Mortgage Payment | E37: -19368.07 | F37: Northmarq Bank
A38: 37595 | C38: 11/22 Mortgage Payment | E38: -21332.65 | F38: Northmarq Bank
A39: 44931 | C39: 12/22 Mortgage Payment | E39: -19609.25 | F39: Northmarq Bank
A40: 44960 | C40: 01/23 Mortgage Payment | E40: -19609.25 | F40: Northmarq Bank
A41: 44988 | C41: 02/23 Mortgage Payment | E41: =-25325.43 -> -25325.43 | F41: Northmarq Bank
A42: 45016 | C42: ADJ 12/22 Mortgage Payment | E42: 78.21 | F42: Northmarq Bank
A43: 45021 | C43: 03/23 Mortgage Payment | E43: -19789.17 | F43: Northmarq Bank
A44: 45051 | C44: 04/23 Mortgage Payment | E44: -21741.81 | F44: Northmarq Bank
A45: 45082 | C45: 05/23 Mortgage Payment | E45: -19955.47 | F45: Northmarq Bank
A46: 45112 | C46: 06/23 Mortgage Payment | E46: -21903.38 | F46: Northmarq Bank
A47: 45142 | C47: 07/23 Mortgage Payment | E47: -20123.08 | F47: Northmarq Bank
A48: 45174 | C48: 08/23 Mortgage Payment | E48: -20203.65 | F48: Northmarq Bank
A49: 45204 | C49: 09/23 Mortgage Payment | E49: -22144.52 | F49: Northmarq Bank
A50: 45233 | C50: 10/23 Mortgage Payment | E50: -20373.22 | F50: Northmarq Bank
A51: 45265 | C51: 11/23 Mortgage Payment | E51: -22309.28 | F51: Northmarq Bank
A52: 45296 | C52: 12/23 Mortgage Payment | E52: -20544.13 | F52: Northmarq Bank
A53: 45327 | C53: 01/24 Mortgage Payment | E53: -20626.39 | F53: Northmarq Bank
... A59: 45509 | C59: 07/24 MORTGAGE PMT | E59: -21156.73 | F59: Northmarq Bank
A60: 45539 | C60: TO PAY OFF THE NOTE BALANCE | E60: -14160803
C61: Account Total | E61: =SUM(E11:E60) -> 0

Sheet Equity
A1: ='Review Comments'!B9 -> COCONUT GROVE RETAIL XIII, LLC
A2: CAPITAL SCHEDULE
A3: ='Review Comments'!B11 -> FOR THE MONTH 07/31/2026
A9: Date | C9: Account Number | D9: Description | F9: Amount
D28: Account Total: | F28: =SUM(F11:F27) -> 0

Sheet 25420
A1: ='Review Comments'!B9 -> COCONUT GROVE RETAIL XIII, LLC
A2: NOTES PAYABLE-MORGAN STANL - 25420
A3: ='Review Comments'!B11 -> FOR THE MONTH 07/31/2026
F7: 25420-000000
A9: Origination Date | C9: Description | E9: Amount | F9: Comment
C10: Beginning Balance
A11: 45539 | C11: NEW LOAN MORGAN STANLEY | E11: -28000000
C13: Account Total | E13: =SUM(E11:E11) -> -28000000
C15: 25420-000000 | E15: {=IFERROR(INDEX('TB '!$G:$G,MATCH(C15,'TB '!$A:$A,0),0),0)} -> -28000000
C16: S/B zero | E16: =E13-E15 -> 0

Sheet 25500
A1: ='Review Comments'!B9 -> COCONUT GROVE RETAIL XIII, LLC
A2: AP - AFFILIATES - 25500
A3: ='Review Comments'!B11 -> FOR THE MONTH 07/31/2026
A6: Origination Date | C6: Description | E6: Amount | F6: Comment
A8: 45685 | C8: Beginning Balance | E8: -66144.74
C11: Account Total | E11: =SUM(E7:E10) -> -66144.74
C13: 25500-000000 | E13: {=IFERROR(INDEX('TB '!$G:$G,MATCH(C13,'TB '!$A:$A,0),0),0)} -> -66144.74
C14: S/B zero | E14: =E11-E13 -> 0

Sheet 20660
A1: ='Review Comments'!B9 -> COCONUT GROVE RETAIL XIII, LLC
A2: INTERST ACCRUALS - 20660
A3: ='Review Comments'!B11 -> FOR THE MONTH 07/31/2026 | H3: 056035
G5: 20660-000000
A7: Origination Date | B7: Account Number | C7: Period | D7: Vendor | E7: Description | G7: Amount
B9: 70125 | C9: =RIGHT(A3,10) -> 07/31/2026 | D9: Morgan Stanley | E9: ACCRUE 07/26 INTEREST EXPENSE | G9: 139242.09
G13: =SUM(G9:G10) -> 139242.09
E15: 20660-000000 | G15: {=-IFERROR(INDEX('TB '!$G:$G,MATCH(E15,'TB '!$A:$A,0),0),0)} -> 139242.09
E16: S/B zero | G16: =G13-G15 -> 0
B47: Water
B48: Meter# | C48: Acct# | D48: GL
C49: 5500873513 | D49: 55140 | E49: Water/CAM
C50: 5500874513 | D50: 55140 | E50: Water/CAM
C51: 8546278012 | D51: 55140 | E51: Water/CAM
C52: 8546278910 | D52: 55140 | E52: Water/CAM
C53: 8546274910 | D53: 55140 | E53: Water/CAM
C54: 8546276013 | D54: 55140 | E54: Water/CAM
C55: 8546360013 | D55: 55140 | E55: Water/CAM
B58: 0008036548 | C58: 097-55008735-13 | D58: 55150 | E58: Fire Hydrent | G58: 097-55008745-12 | H58: old acct#
B59: 0008041574 | C59: 097-55008745-13 | D59: 55150 | E59: Fire Hydrent | G59: 097-55008735-12 | H59: old acct#
C61: 854-62750034 | D61: 55180 | E61: Water/Sewer
C62: 854-62760034 | D62: 55180 | E62: Water/Sewer
C63: 854-62790034 | D63: 55180 | E63: Water/Sewer
B68: Electric
B69: Meter# | C69: Acct# | D69: GL
B71: mhx000141323 | C71: 202011253806 | D71: 55110
B72: mhx000090356 | C72: 202010554280 | D72: 55110
B73: mhx000137834 | C73: 202014338760 | D73: 55110
B74: mhx000139327 | C74: 202014338802 | D74: 55110
B75: mhx000134811 | C75: 202011120534 | D75: 55110
B76: mhx000137526 | C76: 202011287648 | D76: 55110
B77: mhx000132532 | C77: 202011019009 | D77: 55110
C79: NEW ACCT'S
B81: mhx000090356 | C81: 201014742377 | D81: x
B82: mhx000141323 | C82: 201014744019
B83: mhx000134811 | C83: 201014744704 | D83: x
B84: mhx000132532 | C84: 201014744977
B85: mhx000139327 | C85: 201014745941
B86: mhx000137834 | C86: 201014746048
B87: mhx000137526 | C87: 201014743508 | D87: x

Sheet 35000
A1: ='Review Comments'!B9 -> COCONUT GROVE RETAIL XIII, LLC
A2: OWNER'S DISTRIBUTION - 35000
A3: ='Review Comments'!B11 -> FOR THE MONTH 07/31/2026
E7: 35000-000000
A9: Date | C9: Account Number | D9: Description | E9: Amount
A12: 43027 | D12: 10/17 Owners Distribution | E12: 45000
A13: 43055 | D13: 11/17 Owners Distribution | E13: 60000
A14: 43088 | D14: 12/17 Owners Distribution | E14: 55000
A15: 43124 | D15: 01/18 Owners Distribution | E15: 55000
A16: 43154 | D16: 02/18 Owners Distribution | E16: 60000
A17: 43175 | D17: 03/18 Owners Distribution | E17: 55000
A18: 43213 | D18: 04/18 Owners Distribution | E18: 80000
A19: 43238 | D19: 05/18 Owners Distribution | E19: 85000
A20: 43271 | D20: 06/18 Owners Distribution | E20: 175000
A21: 43301 | D21: 07/18 Owners Distribution | E21: 90000
A22: 43329 | D22: 08/18 Owners Distribution | E22: 80000
A23: 43362 | D23: 09/18 Owners Distribution | E23: =60000+50000 -> 110000
A24: 43395 | D24: 10/18 Owners Distribution | E24: 40000
A25: 43423 | D25: 11/18 Owners Distribution | E25: 85000
A26: 43452 | D26: 12/18 Owners Distribution | E26: 125000
A27: 43465 | D27: 2018 CPA AJE #2 - To Close out PY Distr. & Contr. | E27: -160000
A28: 43483 | D28: 01/19 Owners Distribution | E28: 80000
A29: 43515 | D29: 02/19 Owners Distribution | E29: 75000
A30: 43543 | D30: 03/19 Owners Distribution | E30: 50000
A31: 43572 | D31: 04/19 Owners Distribution | E31: 100000
A32: 43601 | D32: 05/19 Owners Distribution | E32: 100000
A33: 43636 | D33: 06/19 Owners Distribution | E33: 80000
A34: 43664 | D34: 07/19 Owners Distribution | E34: 30000
A35: 43733 | D35: 09/19 Owners Distribution | E35: 170000
... A93: 46101 | D93: OWNER DISTRIBUTION | E93: 35000
D95: Account Total: | E95: =SUM(E12:E93) -> 14597709
D97: 35000-000000 | E97: {=IFERROR(INDEX('TB '!$G:$G,MATCH(D97,'TB '!$A:$A,0),0),0)} -> 14597709
D98: S/B zero | E98: =E97-E95 -> 0

Sheet 36000
A1: ='Review Comments'!B9 -> COCONUT GROVE RETAIL XIII, LLC
A2: OWNER'S CONTRIBUTION - 36000
A3: ='Review Comments'!B11 -> FOR THE MONTH 07/31/2026
E7: 36000-000000
A9: Date | C9: Account Number | D9: Description | E9: Amount
A11: 43496 | D11: Owners Contribution - Capex | E11: -80000
A12: 43539 | D12: Owners Contribution - Capex | E12: -200000
A13: 43578 | D13: Owners Contribution - Capex | E13: -70000
A14: 43621 | D14: Owners Contribution - Capex | E14: -100000
A15: 43733 | D15: Owners Contribution - Capex | E15: -350000 | F15: Owners paid for Common Area Improvement
A16: 44196 | D16: 2020 CPA AJE #1 - To Close out PY Distr. & Contr. | E16: 800000
A17: 45590 | D17: OWNER CONTRIBUTION | E17: -125000
A18: 45604 | D18: CAPEX FUNDING | E18: -97383.2
A19: 45644 | D19: OWNER CONTRIBUTION | E19: -120000
D20: Account Total: | E20: =SUM(E11:E19) -> -342383.2
D22: 36000-000000 | E22: {=IFERROR(INDEX('TB '!$G:$G,MATCH(D22,'TB '!$A:$A,0),0),0)} -> -342383.2
D23: S/B zero | E23: =E22-E20 -> 0

Sheet Insurance
A1: ='Review Comments'!B9 -> COCONUT GROVE RETAIL XIII, LLC
A2: PREPAID INS- 13110 / ACCRUED INSURANCE- 20500
A3: ='Review Comments'!B11 -> FOR THE MONTH 07/31/2026
A6: Period | B6: Property Insurance Paid 50111 | C6: Liability Insurance Paid 50112 | D6: Umbrella Insurance Paid 50130 | E6: Total Insurance Paid | F6: Accrued Insurance 20500 | G6: Prepaid Insurance 13110 | H6: YTD Balance 50111 | I6: YTD Balance 50112 | J6: Accumulated Insurance Exp. | K6: Months Remaining | M6: Accumulated R.E. Tax Expense | N6: General Ledger Balance
H7: =B7 -> 0 | I7: =C7 -> 0
A8: 42035 | H8: =H7+B8 -> 0 | I8: =I7+C8 -> 0 | M8: =I8*3 -> 0 | N8: =SUM(M8) -> 0
A9: 42063 | H9: =H8+B9 -> 0 | I9: =I8+C9 -> 0
A10: 42094 | H10: =H9+B10 -> 0 | I10: =I9+C10 -> 0
A11: 42124 | H11: =H10+B11 -> 0 | I11: =I10+C11 -> 0
A12: 42155
A13: 42185 | G13: 16895
A14: 42216 | B14: 2626.85 | C14: 1204.12 | D14: 973.92 | E14: =SUM(B14:D14) -> 4804.89 | G14: =-E14 -> -4804.89
A15: 42247
A16: 42277
A17: 42308
A18: 42338
A19: 42369
B26: =SUM(B7:B25) -> 2626.85 | C26: =SUM(C7:C25) -> 1204.12 | D26: =SUM(D7:D25) -> 973.92 | E26: =SUM(E7:E25) -> 4804.89 | F26: =SUM(F7:F25) -> 0 | G26: =SUM(G9:G24) -> 12090.11 | H26: =H11 -> 0 | I26: =I11 -> 0 | J26: =SUM(J7:J25) -> 0 | K26: =SUM(K7:K25) -> 0 | L26: =SUM(L7:L25) -> 0 | M26: =SUM(M7:M25) -> 0 | N26: =SUM(N7:N25) -> 0
A29: Effective Feb 24, 2015 to Dec 31, 2015
A30: 2014-2015 Property Premium | C30: 26353.26 | D30: =C30/311 -> 84.73717 | E30: =D30*31 -> 2626.8523
A31: 2014-2015 Liability Premium | C31: 12080.09 | D31: =C31/311 -> 38.842733 | E31: =D31*31 -> 1204.1247
A32: 2014-2015 Umbrella Premium | C32: 9770.65 | D32: =C32/311 -> 31.416881 | E32: =D32*31 -> 973.92331
C33: =SUM(C30:C32) -> 48204 | D33: =C33/311 -> 154.99678 | E33: =D33*31 -> 4804.9003
A36: 5
A37: 31
A38: 30
A39: 31
A40: 30
A41: 31
A42: 31
A43: 30 | D43: 42369 | E43: 42060
A44: 31 | E44: =+D43-E43 -> 309
A45: 30
A46: 31
A47: =SUM(A36:A46) -> 311

Sheet INS PH 2 
A1: ='Review Comments'!B9 -> COCONUT GROVE RETAIL XIII, LLC
A2: INSURANCE SCHEDULE
A3: FOR THE ONE MONTH ENDED 01/31/17
B5: Policy Period
C6: Annual Premium | D6: Monthly
B7: Property Ins. PH2 | C7: =17208.93+942.92 -> 18151.85 | D7: =C7/12 -> 1512.6542
B8: Liability Ins. PH2 | C8: 4305.53 | D8: =C8/12 -> 358.79417
B9: Umbrella Ins. PH2 | C9: 3646.94 | D9: =C9/12 -> 303.91167
B10: Total | C10: =SUM(C7:C9) -> 26104.32 | D10: =SUM(D7:D9) -> 2175.36
C13: Property Insurance Paid | D13: Liability Insurance Paid | E13: Umbrella Insurance- Paid | F13: Environmental Insurance Paid | G13: Total Expense | H13: Accrual Balance | I13: Prepaid Insurance
B14: Month | C14: 60111 | D14: 60112 | E14: 60131 | F14: 60145 | H14: 20500 | I14: 13110
B17: 42736 | C17: =D7 -> 1512.6542 | D17: =D8 -> 358.79417 | E17: =D9 -> 303.91167 | G17: =SUM(C17:F17) -> 2175.36
B18: =+B17+31 -> 42767 | G18: =SUM(C18:F18) -> 0
B19: =+B18+31 -> 42798 | G19: =SUM(C19:F19) -> 0
B20: =+B19+31 -> 42829 | G20: =SUM(C20:F20) -> 0
B21: =+B20+31 -> 42860 | G21: =SUM(C21:F21) -> 0
B22: =+B21+31 -> 42891 | G22: =SUM(C22:F22) -> 0
B23: =+B22+31-2 -> 42920 | G23: =SUM(C23:F23) -> 0
B24: =+B23+31 -> 42951 | G24: =SUM(C24:F24) -> 0
B25: =+B24+31 -> 42982 | G25: =SUM(C25:F25) -> 0
B26: =+B25+31 -> 43013 | G26: =SUM(C26:F26) -> 0
B27: =+B26+31 -> 43044
B28: =+B27+31 -> 43075
B30: YTD Total | C30: =SUM(C17:C29) -> 1512.6542 | D30: =SUM(D17:D29) -> 358.79417 | E30: =SUM(E17:E29) -> 303.91167 | G30: =SUM(G17:G29) -> 2175.36 | H30: =SUM(H17:H22) -> 0 | I30: =SUM(I16:I29) -> 0

Sheet Note
A3: ACCOUNTS REC | B3: 173537.29
A5: PREPAID RENT | B5: -51119.2
B8: =SUM(B3:B5) -> 122418.09
A11: Aged | B11: 122418.09

Sheet Variance
A1: Acc# | B1: Account Name | C1: Actual | D1: Budget | E1: Variance | G1: Variance Explaination
A3: 40100 | B3: Base Rent | C3: 105632.61 | D3: 107484 | E3: =C3-D3 -> -1851.39 | G3: Variance is due to Pagoda Inn Rent Credit fr 07/12-12/12 in the amount of $308.55 per month.

Sheet Sheet2

Sheet Tax PH2
A1: ='Review Comments'!B9 -> COCONUT GROVE RETAIL XIII, LLC
A2: PROPERTY TAX SCHEDULE
A3: FOR THE ONE MONTH ENDED 01/31/17
B12: Month | C12: Property Tax | D12: Property Tax | E12: Supplemental Prop Tax | F12: Total Expense | G12: Prepaid | H12: Accrual
C13: 54000 | D13: Payment/ Credit | E13: 54000 | F13: 54000 | G13: 13120 | H13: 20200
B15: 42736 | F15: =C15 -> 0 | H15: =-F15 -> 0
B16: =+B15+31 -> 42767
B17: =+B16+31 -> 42798
B18: =+B17+31 -> 42829
B19: =+B18+31 -> 42860
B20: =+B19+31 -> 42891
B21: =+B20+31 -> 42922
B22: =+B21+31 -> 42953
B23: =+B22+31 -> 42984
B24: =+B23+31 -> 43015
B25: =+B24+31 -> 43046
B26: =+B25+31 -> 43077
B29: YTD Total | C29: =SUM(C15:C28)-0.03 -> -0.03 | D29: =D18 -> 0 | E29: =E15 -> 0 | F29: =SUM(F15:F28)-0.03 -> -0.03 | G29: =G20 -> 0 | H29: =H15 -> 0
B32: Parcel# | C32: 2015-2016 Actual | D32: Per Month
B33: 957330046-5 | D33: =C33/12 -> 0
B34: 957330047-6 | D34: =C34/12 -> 0
B35: 957330048-7 | D35: =C35/12 -> 0
B36: 957330049-8 | D36: =C36/12 -> 0
B38: Total | C38: =SUM(C33:C37) -> 0 | D38: =SUM(D32:D36) -> 0 | E38: =C38/12 -> 0
C41: =C38/2 -> 0

Sheet 36100
A1: ='Review Comments'!B9 -> COCONUT GROVE RETAIL XIII, LLC
A2: CAPITAL CONTRIBUTION - 36100
A3: ='Review Comments'!B11 -> FOR THE MONTH 07/31/2026
A9: Date | C9: Account Number | D9: Description | E9: Amount
A11: 42978 | D11: Capital Contribution | E11: -7181814.1
A12: 43201 | D12: Owners Contribution | E12: -37000 | F12: Owners paid for Patching/seal coating
A13: 43262 | D13: Owners Contribution | E13: -77883 | F13: Owners paid for Elevator upgrades
A14: 43332 | D14: Owners Contribution | E14: -26770.82 | F14: Owners paid for Replace Parking Lot Lights
A15: 43465 | D15: 2018 CPA AJE #2 - To Close out PY Distr. & Contr. | E15: 7181814.1
A16: 43830 | D16: 2019 CPA AJE #1 - To Close out PY Distr. & Contr. | E16: 141653.82
D18: Account Total: | E18: =SUM(E11:E17) -> -2.910383e-10

Sheet Tax 
A1: ='Review Comments'!B9 -> COCONUT GROVE RETAIL XIII, LLC
A2: PROPERTY TAX SCHEDULE
A3: ='Review Comments'!B11 -> FOR THE MONTH 07/31/2026
I4: 052830
B7: Month | C7: Property Tax | D7: Supplemental Prop Tax | E7: Total Expense | F7: Propert Tax | G7: Prepaid | H7: Accrual
C8: 54000 | D8: 54000 | E8: 54000 | F8: Payment/ Credit | G8: 13120-000000 | H8: 20200-000000
B12: 46023 | C12: 94720.22 | I12: Payment received
B13: 46204 | C13: 600 | I13: Payment received
E15: =SUM(C15:D15) -> 0
B16: YTD Total | C16: =SUM(C11:C15) -> 95320.22 | D16: =SUM(D11:D15) -> 0 | E16: =SUM(E11:E15) -> 0 | F16: =SUM(F11:F12) -> 0 | G16: =SUM(G11:G15) -> 0 | H16: =SUM(H11:H15) -> 0
C17: 54000-000000 | G17: 13120-000000
B18: Parcel# | D18: Per Month | E18: Paid by | G18: Parcel# | H18: 2022-2023 Actual | I18: Per Month | J18: Paid by | K18: 2022-2023 Actual
K19: 2nd Half
B20: 750090250000 | D20: =C20/6 -> 0 | E20: Lender | G20: 750090250000 | H20: 57695.79 | I20: =H20/6 -> 9615.965 | J20: Lender | K20: 57695.79 | L20: =K20/6 -> 9615.965
B21: 750090280000 | D21: =C21/6 -> 0 | E21: Lender | G21: 750090280000 | H21: 26240.65 | I21: =H21/6 -> 4373.4417 | J21: Lender | K21: 26240.24 | L21: =K21/6 -> 4373.3733
B22: 750090270000 | D22: =C22/6 -> 0 | E22: Lender | G22: 750090270000 | H22: 12344.81 | I22: =H22/6 -> 2057.4683 | J22: Lender | K22: 12344.79 | L22: =K22/6 -> 2057.465
B23: 750090430000 | E23: Athena | G23: 750090430000 | H23: 758.25 | J23: Athena
B25: Total | D25: =SUM(D20:D23) -> 0 | G25: Total | H25: =SUM(H20:H24) -> 97039.5 | I25: =SUM(I20:I23) -> 16046.875 | K25: =SUM(K20:K24) -> 96280.82 | L25: =SUM(L20:L24) -> 16046.803
B27: Parcel# | D27: Per Month | E27: Paid by
G28: Parcel# | H28: 2023-2024 Actual | I28: Per Month | J28: Paid by | K28: 2023-2024 Actual | N28: 2023-2024 Actual
B29: 750090250000 | D29: =C29/6 -> 0 | E29: Lender | K29: Second | N29: 1st Half
B30: 750090280000 | D30: =C30/6 -> 0 | E30: Lender | G30: 750090250000 | H30: =-'10410'!E119 -> 57695.79 | I30: =H30/6 -> 9615.965 | J30: Lender | K30: =-'10410'!E119 -> 57695.79 | L30: =ROUNDDOWN(K30/6,2)+0.005 -> 9615.965 | N30: =-'10410'!E129 -> 57695.79 | O30: =ROUNDDOWN(N30/6,2)+0.005 -> 9615.965
B31: 750090270000 | D31: =C31/6 -> 0 | E31: Lender | G31: 750090280000 | H31: =-'10410'!E120 -> 26240.25 | I31: =H31/6 -> 4373.375 | J31: Lender | K31: =-'10410'!E120 -> 26240.25 | L31: =ROUNDDOWN(K31/6,2)+0.0025 -> 4373.3725 | N31: =-'10410'!E131 -> 26240.24 | O31: =ROUNDDOWN(N31/6,2)+0.0025 -> 4373.3725
B32: 750090430000 | E32: Athena | G32: 750090270000 | H32: =-'10410'!E121 -> 12344.81 | I32: =H32/6 -> 2057.4683 | J32: Lender | K32: =-'10410'!E121 -> 12344.81 | L32: =ROUNDDOWN(K32/6,2)+0.0025 -> 2057.4625 | N32: =-'10410'!E130 -> 12344.79 | O32: =ROUNDDOWN(N32/6,2)+0.0025 -> 2057.4625
G33: 750090430000 | H33: 758.25 | J33: Athena
B34: Total | D34: =SUM(D29:D31) -> 0
G35: Total | H35: =SUM(H30:H33) -> 97039.1 | I35: =SUM(I30:I33) -> 16046.808 | K35: =SUM(K30:K34) -> 96280.85 | L35: =SUM(L30:L33) -> 16046.8 | N35: =SUM(N30:N34) -> 96280.82 | O35: =SUM(O30:O33) -> 16046.8
B36: 54000-000000 | C36: {=IFERROR(INDEX('TB '!$G:$G,MATCH(B36,'TB '!$A:$A,0),0),0)} -> 95320.22 | G36: {=IFERROR(INDEX('TB '!$G:$G,MATCH(G8,'TB '!$A:$A,0),0),0)} -> 0 | H36: {=IFERROR(INDEX('TB '!G:G,MATCH('Tax '!H8,'TB '!A:A,0),0),0)} -> 0
B37: S/B zero | C37: =C16-C36 -> 0 | G37: =G16-G36 -> 0 | H37: =H16-H36 -> 0
G39: Parcel# | H39: 2024-2025 Actual | I39: Per Month | J39: Paid by | K39: 2024-2025 Actual
K40: 1st Half
G41: 750090250000 | H41: =-'10410'!E138 -> 57695.79 | I41: =H41/6 -> 9615.965 | J41: Lender | K41: =-'10410'!E138 -> 57695.79 | L41: =ROUNDDOWN(K41/6,2)+0.005 -> 9615.965
G42: 750090280000 | H42: =-'10410'!E139 -> 12344.81 | I42: =H42/6 -> 2057.4683 | J42: Lender | K42: =-'10410'!E139 -> 12344.81 | L42: =ROUNDDOWN(K42/6,2)+0.005 -> 2057.465
G43: 750090270000 | H43: =-'10410'!E140 -> 26240.25 | I43: =H43/6 -> 4373.375 | J43: Lender | K43: =-'10410'!E140 -> 26240.25 | L43: =ROUNDDOWN(K43/6,2)+0.005 -> 4373.375
G44: 750090430000 | H44: =359.18+359.19 -> 718.37 | J44: Athena
G46: Total | H46: =SUM(H41:H44) -> 96999.22 | I46: =SUM(I41:I44) -> 16046.808 | K46: =SUM(K41:K45) -> 96280.85 | L46: =SUM(L41:L44)+0.005 -> 16046.81
G48: Parcel# | H48: 2024-2025 Actual | I48: Per Month | J48: Paid by | K48: 2024-2025 Actual
K49: 2nd Half
G50: 375009028 | H50: 26240.25 | I50: =H50/6 -> 4373.375 | J50: Lender | K50: =H50 -> 26240.25 | L50: =ROUNDDOWN(K50/6,2)+0.005 -> 4373.375
G51: 375009025 | H51: 57695.79 | I51: =H51/6 -> 9615.965 | J51: Lender | K51: =H51 -> 57695.79 | L51: =ROUNDDOWN(K51/6,2)+0.005 -> 9615.965
G52: 375009027 | H52: =12344.81 -> 12344.81 | I52: =H52/6 -> 2057.4683 | J52: Lender | K52: =H52 -> 12344.81 | L52: =ROUNDDOWN(K52/6,2)+0.005 -> 2057.465
G55: Total | H55: =SUM(H50:H53) -> 96280.85 | I55: =SUM(I50:I53) -> 16046.808 | K55: =SUM(K50:K54) -> 96280.85 | L55: =SUM(L50:L53)+0.005 -> 16046.81
G57: Parcel# | H57: 2025-2026 Actual | I57: Per Month | J57: Paid by | K57: 2025-2026 Actual
K58: 1st Half
G59: 375009028 | H59: 25921.52 | I59: =H59/6 -> 4320.2533 | J59: Lender | K59: =H59 -> 25921.52 | L59: =ROUNDDOWN(K59/6,2)+0.005 -> 4320.255
G60: 375009025 | H60: 25921.52 | I60: =H60/6 -> 4320.2533 | J60: Lender | K60: =H60 -> 25921.52 | L60: =ROUNDDOWN(K60/6,2)+0.005 -> 4320.255
G61: 375009027 | H61: 12101.4 | I61: =H61/6 -> 2016.9 | J61: Lender | K61: =H61 -> 12101.4 | L61: =ROUNDDOWN(K61/6,2)+0.005 -> 2016.905
G64: Total | H64: =SUM(H59:H62) -> 63944.44 | I64: =SUM(I59:I62) -> 10657.407 | K64: =SUM(K59:K63) -> 63944.44 | L64: =SUM(L59:L62)+0.005 -> 10657.42

Sheet INSURANCE 
A1: ='Review Comments'!B9 -> COCONUT GROVE RETAIL XIII, LLC
A2: INSURANCE SCHEDULE
A3: ='Review Comments'!B11 -> FOR THE MONTH 07/31/2026
R6: Query: Insurance Payment period to be asked from the Client
C7: Property Insurance Paid | D7: Liability Insurance Paid | E7: Umbrella Insurance- Paid | F7: Total Expense | G7: Property Insurance Paid | H7: Liability Insurance Paid | I7: Umbrella Insurance- Paid | J7: Total Expense-PH2 | K7: Accrual Balance | L7: Prepaid Insurance | M7: Accrued Insurance
B8: Month | C8: 50111-000000 | D8: 50112-000000 | E8: 50130-000000 | G8: 60111 | H8: 60112 | I8: 60131 | K8: 20500 | L8: 13110-000000 | M8: 20500-000000
B11: 46048 | D11: 2058.73 | E11: 1016.34 | F11: =SUM(C11:E11) -> 3075.07 | N11: Reclass
B12: 46048 | C12: 10328.48 | D12: 1221.78 | E12: 603.16 | F12: =SUM(C12:E12) -> 12153.42 | N12: 01/26 INSURANCE
B13: 46079 | C13: 0 | D13: 1221.78 | E13: 603.16 | F13: =SUM(C13:E13) -> 1824.94 | N13: 02/26 INSURANCE
B14: 46112 | C14: 0 | D14: 1221.78 | E14: 603.16 | F14: =SUM(C14:E14) -> 1824.94 | N14: 03/26 INSURANCE
B15: 46142 | C15: =69496.23+11558.03 -> 81054.26 | D15: 1221.78 | E15: 603.16 | F15: =SUM(C15:E15) -> 82879.2 | N15: 04/26 INSURANCE
B16: 46170 | C16: 11558.03 | D16: 1221.78 | E16: 603.16 | F16: =SUM(C16:E16) -> 13382.97 | N16: 05/26 INSURANCE
B17: 46203 | C17: 11558.03 | D17: 1221.78 | E17: 603.16 | F17: =SUM(C17:E17) -> 13382.97 | N17: 06/26 INSURANCE
B18: 46234 | C18: 11558.03 | D18: 1221.78 | E18: 603.16 | F18: =SUM(C18:E18) -> 13382.97 | N18: 07/26 INSURANCE
B20: YTD Total | C20: =SUM(C11:C18) -> 126056.83 | D20: =SUM(D11:D18) -> 10611.19 | E20: =SUM(E11:E18) -> 5238.46 | F20: 0 | G20: =SUM(G10:G10) -> 0 | H20: =SUM(H10:H10) -> 0 | I20: =SUM(I10:I10) -> 0 | J20: =SUM(J10:J10) -> 0 | K20: =SUM(K10:K10) -> 0 | L20: =SUM(L10) -> 0 | M20: =SUM(M10:M10) -> 0
B22: TB | C22: {=IFERROR(INDEX('TB '!$G:$G,MATCH(C8,'TB '!$A:$A,0),0),0)} -> 126056.83 | D22: {=IFERROR(INDEX('TB '!$G:$G,MATCH(D8,'TB '!$A:$A,0),0),0)} -> 10611.19 | E22: {=IFERROR(INDEX('TB '!$G:$G,MATCH(E8,'TB '!$A:$A,0),0),0)} -> 5238.46 | L22: {=IFERROR(INDEX('TB '!$G:$G,MATCH(L8,'TB '!$A:$A,0),0),0)} -> 0 | M22: {=IFERROR(INDEX('TB '!$G:$G,MATCH(M8,'TB '!$A:$A,0),0),0)} -> 0
B23: S/B zero | C23: =C20-C22 -> 0 | D23: =D20-D22 -> 0 | E23: =E20-E22 -> 0 | L23: =L20-L22 -> 0

Sheet Notes
A2: Base Rent | B2: 40100 | C2: =162704.66 -> 162704.66
B3: 40100 | C3: 0
A6: Total | C6: =SUM(C2:C5) -> 162704.66
A8: Rent Roll | C8: 162704.66
A10: Difference | C10: =+C6-C8 -> 0
A13: Account Receivable | B13: 12010-000000 | C13: {=IFERROR(INDEX('TB '!$G:$G,MATCH(B13,'TB '!$A:$A,0),0),0)} -> 122046.05
A14: Prepaid Rent | B14: 20900-000000 | C14: {=IFERROR(INDEX('TB '!$G:$G,MATCH(B14,'TB '!$A:$A,0),0),0)} -> -142581.84
A15: Deferred Rent Recovery | B15: 12060-000000 | C15: {=IFERROR(INDEX('TB '!G:G,MATCH(Notes!B15,'TB '!A:A,0),0),0)} -> 0
C16: {=IFERROR(INDEX('TB '!G:G,MATCH(Notes!B16,'TB '!A:A,0),0),0)} -> 0
A17: Total | C17: =SUM(C13:C16) -> -20535.79
A19: Aged Deliquencies | C19: -20535.79
A22: Difference | C22: =C17-C19 -> 0

Sheet Cash Income
A2: IS | B2: CM Ledger | C2: PER I/S | D2: PER R/L | E2: VARIANCE | F2: VARIANCE EXPLANATION
A3: 40100-000000 - BASE RENTAL INCOME | B3: BAS BASE RENT | C3: {=IFERROR(INDEX(IS!B:B,MATCH(A3,IS!A:A,0),0),0)} -> 112929.37 | D3: {=IFERROR(INDEX('CM Ledger'!G:G,MATCH(B3,'CM Ledger'!A:A,0),0),0)} -> 112929.37 | E3: =C3-D3 -> 0
A4: 40106-000000 - DEFERRED RENT RECOVERY | B4: RRC RENT RECOVERY | C4: {=IFERROR(INDEX(IS!B:B,MATCH(A4,IS!A:A,0),0),0)} -> 423.09 | D4: {=IFERROR(INDEX('CM Ledger'!G:G,MATCH(B4,'CM Ledger'!A:A,0),0),0)} -> 423.09 | E4: =C4-D4 -> 0
A5: 40110-000000 - PERCENTAGE RENT | B5: PCR PERCENTAGE RENT | C5: {=IFERROR(INDEX(IS!B:B,MATCH(A5,IS!A:A,0),0),0)} -> 37409.29 | D5: {=IFERROR(INDEX('CM Ledger'!G:G,MATCH(B5,'CM Ledger'!A:A,0),0),0)} -> 37409.29 | E5: =C5-D5 -> 0
A6: 40129-000000 - PARKING RENT | B6: PKG PARKING RENT | C6: {=IFERROR(INDEX(IS!B:B,MATCH(A6,IS!A:A,0),0),0)} -> 42007.06 | D6: {=IFERROR(INDEX('CM Ledger'!G:G,MATCH(B6,'CM Ledger'!A:A,0),0),0)} -> 0 | E6: =C6-D6 -> 42007.06 | F6: NOT IN R/L
A7: 40140-000000 - COMMON AREA INCOME | B7: CAM COMMON AREA MAINT | C7: {=IFERROR(INDEX(IS!B:B,MATCH(A7,IS!A:A,0),0),0)} -> 32356.92 | D7: {=IFERROR(INDEX('CM Ledger'!G:G,MATCH(B7,'CM Ledger'!A:A,0),0),0)} -> 32356.92 | E7: =C7-D7 -> 0
A8: 40150-000000 - PRIOR YEAR CAM | B8: PYC PRIOR YEAR CAM | C8: {=IFERROR(INDEX(IS!B:B,MATCH(A8,IS!A:A,0),0),0)} -> -45631.03 | D8: {=IFERROR(INDEX('CM Ledger'!G:G,MATCH(B8,'CM Ledger'!A:A,0),0),0)} -> -45631.03 | E8: =C8-D8 -> 0
A9: 40160-000000 - TENANT BILL BACKS | B9: TBB TENANT BILL BACKS | C9: {=IFERROR(INDEX(IS!B:B,MATCH(A9,IS!A:A,0),0),0)} -> 0 | D9: {=IFERROR(INDEX('CM Ledger'!G:G,MATCH(B9,'CM Ledger'!A:A,0),0),0)} -> 0 | E9: =C9-D9 -> 0
A10: 40170-000000 - OTHER RECOVERIES | B10: NCA OTHER RECOVERIES | C10: {=IFERROR(INDEX(IS!B:B,MATCH(A10,IS!A:A,0),0),0)} -> 3140.67 | D10: {=IFERROR(INDEX('CM Ledger'!G:G,MATCH(B10,'CM Ledger'!A:A,0),0),0)} -> 3140.67 | E10: =C10-D10 -> 0
A11: 40180-000000 - FOOD COURT CAM | B11: IFC FOOD COURT CAM | C11: {=IFERROR(INDEX(IS!B:B,MATCH(A11,IS!A:A,0),0),0)} -> 4101.76 | D11: {=IFERROR(INDEX('CM Ledger'!G:G,MATCH(B11,'CM Ledger'!A:A,0),0),0)} -> 4101.76 | E11: =C11-D11 -> 0
A12: 40220-000000 - RENT CONCESSIONS | B12: ABA RENT CONCESSIONS | C12: {=IFERROR(INDEX(IS!B:B,MATCH(A12,IS!A:A,0),0),0)} -> 0 | D12: {=IFERROR(INDEX('CM Ledger'!G:G,MATCH(B12,'CM Ledger'!A:A,0),0),0)} -> 0 | E12: =C12-D12 -> 0
A13: 40230-000000 - INSURANCE INCOME | B13: INS INSURANCE-CAM | C13: {=IFERROR(INDEX(IS!B:B,MATCH(A13,IS!A:A,0),0),0)} -> 5722.39 | D13: {=IFERROR(INDEX('CM Ledger'!G:G,MATCH(B13,'CM Ledger'!A:A,0),0),0)} -> 5722.39 | E13: =C13-D13 -> 0
A14: 40240-000000 - PROPERTY TAX INCOME | B14: RET REAL ESTATE TAX | C14: {=IFERROR(INDEX(IS!B:B,MATCH(A14,IS!A:A,0),0),0)} -> 7668.23 | D14: {=IFERROR(INDEX('CM Ledger'!G:G,MATCH(B14,'CM Ledger'!A:A,0),0),0)} -> 7668.23 | E14: =C14-D14 -> 0
A15: 40250-000000 - MISCELLANEOUS INCOME | B15: MIS MISCELLANEOUS INCOME | C15: {=IFERROR(INDEX(IS!B:B,MATCH(A15,IS!A:A,0),0),0)} -> 1500 | D15: {=IFERROR(INDEX('CM Ledger'!G:G,MATCH(B15,'CM Ledger'!A:A,0),0),0)} -> 1500 | E15: =C15-D15 -> 0
A16: 40300-000000 - MARKETING INCOME | B16: PRO PROMOTION FUND CHARGE | C16: {=IFERROR(INDEX(IS!B:B,MATCH(A16,IS!A:A,0),0),0)} -> 3568.32 | D16: {=IFERROR(INDEX('CM Ledger'!G:G,MATCH(B16,'CM Ledger'!A:A,0),0),0)} -> 3568.32 | E16: =C16-D16 -> 0
A17: 41100-000000 - OTHER INCOME | B17: GET GENERAL EXCISE TAX | C17: {=IFERROR(INDEX(IS!B:B,MATCH(A17,IS!A:A,0),0),0)} -> 7385.74 | D17: {=IFERROR(INDEX('CM Ledger'!G:G,MATCH(B17,'CM Ledger'!A:A,0),0),0)} -> 7385.74 | E17: =C17-D17 -> 0
B18: PPR PREPAID RENT | C18: {=IFERROR(INDEX(IS!B:B,MATCH(A18,IS!A:A,0),0),0)} -> 0 | D18: {=IFERROR(INDEX('CM Ledger'!G:G,MATCH(B18,'CM Ledger'!A:A,0),0),0)} -> 0 | E18: =C18-D18 -> 0
A19: 40102-000000 - RENT DEFERRAL | B19: RDR RENT DEFERRAL | C19: {=IFERROR(INDEX(IS!B:B,MATCH(A19,IS!A:A,0),0),0)} -> 0 | D19: {=IFERROR(INDEX('CM Ledger'!G:G,MATCH(B19,'CM Ledger'!A:A,0),0),0)} -> 0 | E19: =C19-D19 -> 0
C21: =SUM(C3:C20) -> 212581.81 | D21: =SUM(D3:D20) -> 170574.75 | E21: =SUM(E3:E20) -> 42007.06
C22: {=INDEX(IS!B:B,MATCH("Total Rental Income",IS!A:A,0),0)} -> 212581.81 | D22: {=INDEX('CM Ledger'!G:G,MATCH("Grand Total:",'CM Ledger'!B:B,0),0)} -> 170574.75
C23: =+C21-C22 -> 0 | D23: =+D21-D22 -> 0

Sheet IS
A1: Database: ATHENA | B1: Comparative Income Statement | H1: Page: | I1: 1
A2: ENTITY: 165 | B2: MONTHLY OPERATING STATEMENTS | H2: Date: | I2: 46239.564
B3: Athena Property Management | H3: Time: | I3: 46239.564
B4: COCONUT GROVE RETAIL XIII, LLC
A5: Cash
B6: Report includes an open period. Entries are not final.
B8: Current Period | G8: Year-To-Date
B9: Actual | C9: Budget | F9: Actual | G9: Budget
A10: Thru: | B10: 46234 | C10: 46234 | D10: Variance | F10: 46234 | G10: 46234 | H10: Variance
A11: RENTAL INCOME
A12: 40100-000000 - BASE RENTAL INCOME | B12: 112929.37 | C12: 162631 | D12: -49701.63 | E12: -0.3056 | F12: 999479.57 | G12: 1057121 | H12: -57641.43 | I12: -0.0545
A13: 40102-000000 - RENT DEFERRAL | B13: 0 | C13: 0 | D13: 0 | E13: 0 | F13: -65479.31 | G13: 0 | H13: -65479.31 | I13: 0
A14: 40106-000000 - DEFERRED RENT RECOVERY | B14: 423.09 | C14: 423 | D14: 0.09 | E14: 0.0002 | F14: 2961.63 | G14: 2961 | H14: 0.63 | I14: 0.0002
A15: 40110-000000 - PERCENTAGE RENT | B15: 37409.29 | C15: 43895 | D15: -6485.71 | E15: -0.1478 | F15: 299224.86 | G15: 307265 | H15: -8040.14 | I15: -0.0262
A16: 40129-000000 - PARKING RENT | B16: 42007.06 | C16: 30000 | D16: 12007.06 | E16: 0.4002 | F16: 261747.56 | G16: 210000 | H16: 51747.56 | I16: 0.2464
A17: 40140-000000 - COMMON AREA INCOME | B17: 32356.92 | C17: 48581 | D17: -16224.08 | E17: -0.334 | F17: 281178.54 | G17: 301073 | H17: -19894.46 | I17: -0.0661
A18: 40150-000000 - PRIOR YEAR CAM | B18: -45631.03 | C18: 0 | D18: -45631.03 | E18: 0 | F18: -10477.69 | G18: 0 | H18: -10477.69 | I18: 0
A19: 40170-000000 - OTHER RECOVERIES | B19: 3140.67 | C19: 4016 | D19: -875.33 | E19: -0.218 | F19: 27117.97 | G19: 28112 | H19: -994.03 | I19: -0.0354
A20: 40180-000000 - FOOD COURT CAM | B20: 4101.76 | C20: 9703 | D20: -5601.24 | E20: -0.5773 | F20: 46408.42 | G20: 52009 | H20: -5600.58 | I20: -0.1077
A21: 40230-000000 - INSURANCE INCOME | B21: 5722.39 | C21: 10678 | D21: -4955.61 | E21: -0.4641 | F21: 54149.35 | G21: 59512 | H21: -5362.65 | I21: -0.0901
A22: 40240-000000 - PROPERTY TAX INCOME | B22: 7668.23 | C22: 11616 | D22: -3947.77 | E22: -0.3399 | F22: 64904.84 | G22: 69180 | H22: -4275.16 | I22: -0.0618
A23: 40250-000000 - MISCELLANEOUS INCOME | B23: 1500 | C23: 1500 | D23: 0 | E23: 0 | F23: 10500 | G23: 10500 | H23: 0 | I23: 0
... A28: TOTAL INCOME | B28: 212581.81 | C28: 340807 | D28: -128225.19 | E28: -0.3762 | F28: 2083899.7 | G28: 2216321 | H28: -132421.34 | I28: -0.0597
A30: COMMON AREA EXPENSES
A31: 50111-000000 - INSURANCE-PROPERTY | B31: 0 | C31: 11361 | D31: 11361 | E31: 1 | F31: 114498.8 | G31: 115544 | H31: 1045.2 | I31: 0.009
A32: 50112-000000 - INSURANCE-LIABILITY | B32: 1221.78 | C32: 1221.75 | D32: -0.03 | E32: 0 | F32: 10611.19 | G32: 10611.01 | H32: -0.18 | I32: 0
A33: 50130-000000 - INSURANCE-UMBRELLA | B33: 603.16 | C33: 603.16 | D33: 0 | E33: 0 | F33: 5238.46 | G33: 5238.46 | H33: 0 | I33: 0
A34: 50160-000000 - LANDSCAPE-CONSUMABLES | B34: 0 | C34: 0 | D34: 0 | E34: 0 | F34: 6282.72 | G34: 26255 | H34: 19972.28 | I34: 0.7607
A35: 50170-000000 - LANDSCAPE-MAINTENANCE | B35: 8490.23 | C35: 8032 | D35: -458.23 | E35: -0.0571 | F35: 56931.11 | G35: 56224 | H35: -707.11 | I35: -0.0126
A36: 50190-000000 - LANDSCAPE-SPRINKLER REPAIRS | B36: 0 | C36: 250 | D36: 250 | E36: 1 | F36: 0 | G36: 750 | H36: 750 | I36: 1
A37: 50210-000000 - ELEVATOR MAINTENANCE | B37: 2996.69 | C37: 2865 | D37: -131.69 | E37: -0.046 | F37: 17041.71 | G37: 15055 | H37: -1986.71 | I37: -0.132
A38: 50520-000000 - PARKING LOT MAINTENANCE | B38: 0 | C38: 0 | D38: 0 | E38: 0 | F38: 0 | G38: 1000 | H38: 1000 | I38: 1
A39: 50530-000000 - PARKING LOT LIGHT REPAIRS | B39: 0 | C39: 4000 | D39: 4000 | E39: 1 | F39: 5201.54 | G39: 5000 | H39: -201.54 | I39: -0.0403
A40: 50540-000000 - PARKING LOT REPAIRS | B40: 0 | C40: 0 | D40: 0 | E40: 0 | F40: 1570.03 | G40: 28750 | H40: 27179.97 | I40: 0.9454
A41: 50551-000000 - SIGN REPAIRS | B41: 0 | C41: 200 | D41: 200 | E41: 1 | F41: 431.94 | G41: 600 | H41: 168.06 | I41: 0.2801
A42: 51020-000000 - GENERAL MAINTENANCE | B42: 2310.04 | C42: 1300 | D42: -1010.04 | E42: -0.777 | F42: 6265.12 | G42: 9100 | H42: 2834.88 | I42: 0.3115
... A71: NET OPERATING INCOME | B71: 96298.92 | C71: 212418.09 | D71: -116119.17 | E71: -0.5467 | F71: 1142672.4 | G71: 1183357.5 | H71: -40685.18 | I71: -0.0344
A73: OWNER EXPENSES
A74: 70210-000000 - GENERAL REPAIRS & MAINT | B74: 0 | C74: 0 | D74: 0 | E74: 0 | F74: 552.17 | G74: 2000 | H74: 1447.83 | I74: 0.7239
A75: 70220-000000 - LEGAL FEES | B75: 3220 | C75: 0 | D75: -3220 | E75: 0 | F75: 5968.75 | G75: 1000 | H75: -4968.75 | I75: -4.9688
A76: 70230-000000 - OTHER PROFESSIONAL FEES | B76: 3927.72 | C76: 0 | D76: -3927.72 | E76: 0 | F76: 13310.96 | G76: 3000 | H76: -10310.96 | I76: -3.437
A77: 70260-000000 - ADVERTISING/MARKETING | B77: 3125 | C77: 4475 | D77: 1350 | E77: 0.3017 | F77: 27225 | G77: 31425 | H77: 4200 | I77: 0.1337
A78: 70280-000000 - BANK CHARGES | B78: 30 | C78: 50 | D78: 20 | E78: 0.4 | F78: 230.5 | G78: 350 | H78: 119.5 | I78: 0.3414
A79: 70320-000000 - UTILITIES EXPENSE | B79: 0 | C79: 500 | D79: 500 | E79: 1 | F79: 147.23 | G79: 3500 | H79: 3352.77 | I79: 0.9579
A80: 70340-000000 - POSTAGE & SHIPPING | B80: 0 | C80: 0 | D80: 0 | E80: 0 | F80: 1606.04 | G80: 1000 | H80: -606.04 | I80: -0.606
A81: 70370-000000 - LICENSE & PERMIT FEES | B81: 0 | C81: 0 | D81: 0 | E81: 0 | F81: 500 | G81: 2800 | H81: 2300 | I81: 0.8214
A82: 70420-000000 - BOND | B82: 0 | C82: 0 | D82: 0 | E82: 0 | F82: 1296 | G82: 0 | H82: -1296 | I82: 0
A83: 70463-000000 - LOSS AGAINST INS CLAIMS | B83: 239946.6 | C83: 0 | D83: -239946.6 | E83: 0 | F83: -157053.51 | G83: 0 | H83: 157053.51 | I83: 0
A84: TOTAL OWNER EXPENSES | B84: 250249.32 | C84: 5025 | D84: -245224.32 | E84: -48.8009 | F84: -106216.86 | G84: 45075 | H84: 151291.86 | I84: 3.3564
A86: ADJUSTED NET OPERATING INCOME | B86: -153950.4 | C86: 207393.09 | D86: -361343.49 | E86: -1.7423 | F86: 1248889.2 | G86: 1138282.5 | H86: 110606.68 | I86: 0.0972
A88: CORPORATE G&A EXPENSES
A89: 70360-000000 - ASSET MANAGEMENT FEES | B89: 10629.09 | C89: 18458 | D89: 7828.91 | E89: 0.4241 | F89: 111321.52 | G89: 120058 | H89: 8736.48 | I89: 0.0728
A90: 70400-000000 - STATE FRANCHISE TAXES | B90: 0 | C90: 0 | D90: 0 | E90: 0 | F90: 0 | G90: 800 | H90: 800 | I90: 1
A91: TOTAL CORP. G&A EXPENSES | B91: 10629.09 | C91: 18458 | D91: 7828.91 | E91: 0.4241 | F91: 111321.52 | G91: 120858 | H91: 9536.48 | I91: 0.0789
A93: ADJUSTED NOI AFTER G&A EXP | B93: -164579.49 | C93: 188935.09 | D93: -353514.58 | E93: -1.8711 | F93: 1137567.7 | G93: 1017424.5 | H93: 120143.16 | I93: 0.1181
A95: INTEREST EXPENSE
A96: 70125-000000 - NTEREST EXPENSE-MORGAN STANLEY | B96: 134340.72 | C96: 155000 | D96: 20659.28 | E96: 0.1333 | F96: 963555.66 | G96: 1085000 | H96: 121444.34 | I96: 0.1119
A97: 70186-000000 - SWAP INTEREST | B97: 5833 | C97: 5833 | D97: 0 | E97: 0 | F97: 40831 | G97: 40831 | H97: 0 | I97: 0
A98: TOTAL INTEREST EXPENSE | B98: 140173.72 | C98: 160833 | D98: 20659.28 | E98: 0.1285 | F98: 1004386.7 | G98: 1125831 | H98: 121444.34 | I98: 0.1079
A100: NOI AFTER INT. EXPENSE & G&A EXP | B100: -304753.21 | C100: 28102.09 | D100: -332855.3 | E100: -11.8445 | F100: 133181.03 | G100: -108406.47 | H100: 241587.5 | I100: 2.2285
A102: NET INCOME | B102: -304753.21 | C102: 28102.09 | D102: -332855.3 | E102: -11.8445 | F102: 133181.03 | G102: -108406.47 | H102: 241587.5 | I102: 2.2285
A104: CAPITAL EXPENSES
A105: 12100-000000 - LOAN RECEIVABLE | B105: -300000 | C105: 0 | D105: 300000 | E105: 0 | F105: 0 | G105: 0 | H105: 0 | I105: 0
A106: 15010-000000 - BUILDING IMPROVEMENTS | B106: 0 | C106: 0 | D106: 0 | E106: 0 | F106: 58984.23 | G106: 0 | H106: -58984.23 | I106: 0
A107: 15100-000000 - TENANT IMPROVEMENTS | B107: 0 | C107: 0 | D107: 0 | E107: 0 | F107: 0 | G107: 353334 | H107: 353334 | I107: 1
A108: 16500-000000 - LEASING COMMISSIONS | B108: 0 | C108: 0 | D108: 0 | E108: 0 | F108: 3480.51 | G108: 0 | H108: -3480.51 | I108: 0
A109: 35000-000000 - OWNER'S DISTRIBUTION | B109: 0 | C109: 0 | D109: 0 | E109: 0 | F109: 35000 | G109: 0 | H109: -35000 | I109: 0
A110: TOTAL CAPITAL EXPENSES | B110: -300000 | C110: 0 | D110: 300000 | F110: 97464.74 | G110: 353334 | H110: 255869.26 | I110: 0.7242
A112: NET CASH FLOW | B112: -4753.21 | C112: 28102.09 | D112: -32855.3 | E112: -1.1691 | F112: 35716.29 | G112: -461740.47 | H112: 497456.76 | I112: 1.0774

Sheet CM Ledger
A1: Grand Totals:
A2: Category | D2: Mo. Rep Charges | E2: Beg Balance | G2: Charges Cash Receipts | H2: N/C Credits | I2: Refunds | J2: End Balance | K2: Sec Dep Bal
A3: BAS BASE RENT | D3: 171489.24 | E3: 10495.51 | F3: 162704.66 | G3: 112929.37 | H3: 0 | I3: 0 | J3: 60270.8
A4: CAM COMMON AREA MAINT | D4: 55013.55 | E4: 4960.43 | F4: 48538.45 | G4: 32356.92 | H4: 0 | I4: 0 | J4: 21141.96
A5: GET GENERAL EXCISE TAX | D5: 12478.62 | E5: -1584.43 | F5: 13545.34 | G5: 7385.74 | H5: 0 | I5: 0 | J5: 4575.17
A6: IFC FOOD COURT CAM | D6: 11367.61 | E6: 525.29 | F6: 9677.54 | G6: 4101.76 | H6: 0 | I6: 0 | J6: 6101.07
A7: INS INSURANCE-CAM | D7: 10838.32 | E7: 915.18 | F7: 10677.98 | G7: 5722.39 | H7: 0 | I7: 0 | J7: 5870.77
A8: MIS MISCELLANEOUS INCOME | D8: 1500 | E8: 0 | F8: 1500 | G8: 1500 | H8: 0 | I8: 0 | J8: 0
A9: NCA OTHER RECOVERIES | D9: 4016.05 | E9: 501.2 | F9: 4016.05 | G9: 3140.67 | H9: 0 | I9: 0 | J9: 1376.58
A10: PCR PERCENTAGE RENT | D10: 0 | E10: 288.11 | F10: 40388.46 | G10: 37409.29 | H10: 0 | I10: 0 | J10: 3267.28
A11: PPR PREPAID RENT | D11: 0 | E11: -142581.84 | F11: 0 | G11: 0 | H11: 0 | I11: 0 | J11: -142581.84
A12: PRO PROMOTION FUND CHARGE | D12: 3355.67 | E12: 60 | F12: 4368.32 | G12: 3568.32 | H12: 0 | I12: 0 | J12: 860
A13: PYC PRIOR YEAR CAM | D13: 0 | E13: -31952.26 | F13: 0 | G13: -45631.03 | H13: 0 | I13: 0 | J13: 13678.77
A14: RET REAL ESTATE TAX | D14: 13268.13 | E14: 729.11 | F14: 11616.23 | G14: 7668.23 | H14: 0 | I14: 0 | J14: 4677.11
... A16: TBB TENANT BILL BACKS | D16: 0 | E16: 0 | F16: 226.54 | G16: 0 | H16: 0 | I16: 0 | J16: 226.54
B17: Grand Total: | D17: 283750.28 | E17: -157643.7 | F17: 307682.66 | G17: 170574.75 | H17: 0 | I17: 0 | J17: -20535.79 | K17: 149779.54

Sheet Tenant Credits
A1: AR Credits/CAM Credit AC #40140 | K1: ONLY MAKE JOURNAL ENTRIES FOR CASH BOOK WHEN TENANTS TAKE THE CREDITS
K2: DO NOT MAKE ANY JES FOR ACCRUAL BOOKS
C5: Aging Set
A6: Tenant Name | B6: Unit Number | C6: 0 | D6: 1 – 30 | E6: 31 – 60 | F6: 61 – 90 | G6: 91 – 120 | H6: 121 + | I6: Grand Total | J6: Credit Amount | L6: DR 26300
B7: 002 (BU3700202) | C7: 166.36 | D7: 438.1 | E7: -40.27 | F7: -40.27 | G7: -40.27 | H7: -887.76 | I7: -404.11 | J7: =-404.11+404.11 -> 0 | L7: CR 40140
B8: 011 (BU3700201) | H8: -19653.76 | I8: -19653.76 | J8: 0 | L8: OR CR 40150 (USE THIS ACT ONLY FOR HOMEGOODS)
B9: 001 (BU3700202) | C9: -143.95 | I9: -143.95
B10: 005 (BU3700202) | C10: -115.16 | D10: -778.64 | I10: -893.8
B11: 016 (BU3700201) | D11: 789.04 | H11: -1383.93 | I11: -594.82 | J11: 0
B12: 002 (BU3700201) | C12: 19.68 | E12: -379.17 | I12: -359.49
B13: 017 (BU3700201) | C13: 44.75 | H13: -114.87 | I13: -70.13 | J13: =-70.13+70.13 -> 0
B14: 006 (BU3700201) | C14: 14.76 | E14: -286.37 | F14: -2 | G14: -3 | H14: 224.22 | I14: -52.49 | J14: =-52.49+52.49 -> 0
B15: 016 (BU3700202) | C15: -12.53 | E15: -838.54 | F15: -1734.5 | I15: -2585.57 | J15: =-2585.57+2585.57 -> 0
B16: 008 (BU3700201) | C16: 14.76 | D16: 84.64 | E16: -249.73 | F16: 34.64 | G16: 34.64 | H16: -65.39 | I16: -146.47 | J16: =-146.47+146.47 -> 0
B17: 007 (BU3700202) | C17: -132.43 | I17: -132.43
B18: 009 (BU3700202) | C18: 458.16 | D18: -1973.67 | E18: -404.57 | F18: -441.59 | G18: -404.57 | H18: -3486.54 | I18: -6252.78 | J18: 0
A19: Grand Total | C19: 1498.33 | D19: 97504.41 | E19: -198.01 | F19: -3291.94 | G19: -440.24 | H19: -24846.1 | I19: 70226.45 | J19: =SUM(J7:J18) -> 0
A22: PYC Credit AC #40150
A23: 0 | J23: 0
A26: Total AC #26300 | J26: =+J19+J23 -> 0
M1432: 25.982462

Sheet INCOME VAR
A1: CASH BASIS:
B3: Comp IS | D3: Cash Receipts
A4: BASE RENTAL | B4: 144710.62 | D4: 132398.22 | F4: =B4-D4 -> 12312.4 | G4: Jewelry Unlimited $2,532.40 + Togo's $9,780 Security Deposit Applied
A5: PERCENTAGE RENT | B5: 988.53 | D5: 988.53 | F5: =B5-D5 -> 0
A6: OTHER RENT | B6: 0 | D6: 0 | F6: =B6-D6 -> 0
A7: COMMON AREA INCOME | B7: 34830.53 | D7: 34830.53 | F7: =B7-D7 -> 0
A8: PRIOR YEAR CAM | B8: -2633.27 | D8: -2633.27 | F8: =B8-D8 -> 0
A9: OTHER RECOVERIES | B9: 3211.1 | D9: 3211.1 | F9: =B9-D9 -> 0
A10: INSURANCE INCOME | B10: 996.19 | D10: 996.19 | F10: =B10-D10 -> 0
A11: REAL ESTATE TAX | B11: 32956.25 | D11: 32956.25 | F11: =B11-D11 -> 0
A12: MANAGEMENT FEE INCOME | B12: 3559.18 | D12: 3559.18 | F12: =B12-D12 -> 0
A13: LATE CHARGE | B13: 63.32 | D13: 63.32 | F13: =B13-D13 -> 0
A14: PREPAID RENT | B14: 0 | D14: 498.99 | F14: =B14-D14 -> -498.99 | G14: Tuesday Morning ($246) + Burlington Coat ($106.81) + Aaron Brother ($116.08) + Fitzone ($30.10)
A15: TENANT BILL BACKS | B15: 0 | D15: 0 | F15: =B15-D15 -> 0
A16: TOTAL | B16: =SUM(B4:B15) -> 218682.45 | D16: =SUM(D4:D15) -> 206869.04
A18: ACCRUAL BASIS:
B21: Rent Up | D21: Rent Roll
A22: BASE RENTAL | B22: 143398.99 | D22: 130217.25 | F22: =B22-D22 -> 13181.74 | G22: Togo's $3,594.15 + Jewelry Unlimited $1,670.92 + Applebees $7,916.67
