Workbook
Name __dat1: #REF!
Name _1: #REF!
Name _1: '[1]Square (The)'!$D$18:$D$22
Name _1: '[2]Square (The)'!$D$18:$D$22
Name _1_245118304: #REF!
Name _10: #REF!
Name _10: #REF!
Name _10: #REF!
Name _10: #REF!
Name _10: #REF!
Name _10: #REF!
Name _10: #REF!
Name _10: #REF!
Name _10: #REF!
Name _10: #REF!
Name _10_245118304: #REF!
Name _10_245118304BDR: #REF!
Name _11_245118304BDR: #REF!
Name _13_245118304BDR: #REF!
Name _15_245118304BDR: #REF!
Name _15_265329000: #REF!
Name _16_245118304BDR: #REF!
Name _16_245118304BDR: #REF!
Name _18_245118304BDR: #REF!
Name _18_245118304BDR: #REF!
Name _18_245118304BDR: #REF!
Name _18_245118304BDR: #REF!
Name _2: #REF!
Name _2: '[1]Square (The)'!$J$22:$BR$22
Name _2: '[2]Square (The)'!$J$22:$BR$22
Name _2_245118304: #REF!
Name _20_245118304BDR: #REF!
Name _21_265329000: #REF!
Name _23_265329000: #REF!
Name _245118304: #REF!
Name _245118304BDR: #REF!
Name _25_265329000: #REF!
Name _26_265329000: #REF!
Name _26_265329000: #REF!
Name _265329000: #REF!
Name _28_265329000: #REF!
Name _28_265329000: #REF!
Name _28_265329000: #REF!
Name _28_265329000: #REF!
Name _3_245118304: #REF!
Name _3_245118304: #REF!
Name _30_265329000: #REF!
Name _4_245118304BDR: #REF!
Name _5_245118304: #REF!
Name _5_245118304: #REF!
Name _6_245118304: #REF!
Name _6_245118304: #REF!
Name _6_245118304BDR: #REF!
Name _6_265329000: #REF!
Name _8_245118304: #REF!
Name _8_245118304: #REF!
Name _8_245118304: #REF!
Name _8_245118304: #REF!
Name _9_265329000: #REF!
Name _dat1: #REF!

Sheet Pet-cash
A1: MONTHLY REPORTING REQUIREMENTS | E1: Site Reports
A6: REGENCY BRESSI, LLC
A8: Petty Cash Reconciliation
A10: For the month ended :
A11: 40816
A14: Beginning Cash Balance | F14: 0
A16: Add
A17: Funding from Chase Account | F17: 0
A20: Deduct
A21: Current Month Receipts
A23: Description | B23: Amount
F30: =SUM(B24:B30) -> 0
A35: Ending Cash Balance | F35: =SUM(F14+F17-F30) -> 0
A49: 9 | D49: MRI Implementation for Cornerstone

Sheet Bank Rec
D3: Athena Management, Inc
D4: REGENCY BRESSI, LLC - #3502
D5: Bank Reconciliation
D6: ='Pet-cash'!$A$11 -> 40816
F10: BANK NAME: | H10: JP Morgan Chase
F12: ACCOUNT #: | H12: 937301091
B13: BANK STATEMENT
B15: Bank Balance | C15: 40770 | H15: 341284.95
B17: Plus: Deposits in Transit | H17: 0
B19: Less: Outstanding Checks (See Outstanding Check Listing) | H19: 25631.26
B21: Adjustment:
B23: Adjusted Bank Balance | H23: =+H15+H17-H19 -> 315653.69
B25: GENERAL LEDGER
B28: Balance per General Ledger A/C #1020-000: | H28: 315653.69
B30: BANK REC ADJUSTMENTS TO BE RECORDED ON CASH BKS IN NEXT MONTH
F32: DIVIDEND PAID | H32: 0
F33: SWEEP FEE | H33: 0
F34: ANALYSIS CHARGE | H34: 0
H38: =+H28+H32+H33+H34 -> 315653.69
B41: Prepared by: | E41: Prelim Approval:
B42: Date: | E42: Final Approval:
E43: Date:

Sheet Sec-Dep
A1: MONTHLY REPORTING REQUIREMENTS | E1: Site Reports
A5: REGENCY BRESSI, LLC
A7: Security Deposit Cash Account- Account 21100000
A9: Statutory Report for the period ending:
A10: ='Pet-cash'!$A$11 -> 40816
B12: Date | C12: Property Name | D12: Amount Earned
B13: 39659 | C13: Board and Brew | D13: 5445
B14: 39673 | C14: Cha Dry Cleaners | D14: 4925.75
B15: 39873 | C15: Carisbad Optometry | D15: 3714.75
B16: 39904 | C16: Happiness Nails | D16: 4346.25
B17: 39934 | C17: Xtreme Frozen Yogurt | D17: 3479
B18: 39996 | C18: Jojo Be, LLC | D18: 5554.5
B19: 40081 | C19: Tomaso Restaurant Group | D19: 12608.4
B20: 40118 | C20: FROOTS 4 U, LLC | D20: 3981.2
B21: 40126 | C21: Postal Annex | D21: 3339
B22: 40155 | C22: Kyss Boutique, LLC | D22: 4991.2
B23: 40228 | C23: Perfectly at Home | D23: 8428
B24: 40366 | C24: Premier Food Concepts | D24: 8583.25
... B31: 40718 | C31: Elevation Burger | D31: 6610.1
B37: Total | D37: =SUM(D13:D36) -> 108922.86
B44: 10 | E44: MRI Implementation for Cornerstone

Sheet Util-Dep
A1: MONTHLY REPORTING REQUIREMENTS | D1: Site Reports
A5: REGENCY BRESSI, LLC
A7: Utility Deposits
A9: As of:_________
B12: Utility Company | D12: Total Deposit | G12: Total
B26: Total per GL | D26: =SUM(D13:D25) -> 0
A33: 11 | D33: MRI Implementation for Cornerstone
G39: SKYLINE Implementation for Cornerstone

Sheet All-Doubt
A1: MONTHLY REPORTING REQUIREMENTS Site Reports
A4: REGENCY BRESSI, LLC
A6: Allowance for Doubtful Accounts - 10900000
A8: As of
A9: ='Pet-cash'!$A$11 -> 40816
A11: The Property Manager has performed a review of all delinquent rents with the following findings and
A12: recommendations.
A15: Tenant Name | B15: Amount Reserved | D15: Comments/Status of Collection
A16: Kyss Boutique | B16: 3673.12 | D16: Tenant downsize. Suggest to write-off balance.
A17: JPMorgan Chase | B17: 19043.71 | D17: Review tenant account to confirm correct charges.
A18: Hendo's Local Pizza | B18: 1767.21 | D18: Review tenant account to confirm correct charges.
A20: Total Reserve per G/L | B20: =SUM(B16:B19) -> 24484.04
A39: 12 | D39: MRI Implementation for Cornerstone

Sheet Bad-D
A1: MONTHLY REPORTING REQUIREMENTS | D1: Site Reports
A5: REGENCY BRESSI, LLC
A7: YTD Bad Debt Write-Offs
A9: As of:
A10: ='Pet-cash'!$A$11 -> 40816
A12: Name of Tenant | B12: Total Write-off | D12: Reason for Write-off
A13: (List by Tenant) | B13: (Total of all charges) | D13: (Summary of Reasons)
A24: Total Accounts written off YTD | B24: =SUM(B13:B23) -> 0
A26: *YTD Bad Expense per the G/L should equal the sum of:
A27: (1) All direct write-offs of accounts receivable balances (amounts NOT previously reserved).
A28: (2) The Net Current Year provision to account 1090 - Allowance for Doubtful Accounts.
A33: 13 | D33: MRI Implementation for Cornerstone
G39: SKYLINE Implementation for Cornerstone

Sheet Receiv
A1: MONTHLY REPORTING REQUIREMENTS | D1: Site Reports
A5: REGENCY BRESSI, LLC
A7: Other Receivables - Account 11000000
A9: As of
A10: ='Pet-cash'!$A$11 -> 40816
A12: Receivable Due From | B12: Total Amount | D12: Description
A13: ELEVATION BURGER | B13: 2214 | D13: MONUMENT SIGN REIMBURSEMENTS
A14: TOMMY V'S | B14: 2214 | D14: MONUMENT SIGN REIMBURSEMENTS
A15: THE BAR METHOD | B15: 2214 | D15: MONUMENT SIGN REIMBURSEMENTS
A16: CHASE BANK | B16: 10000 | D16: MONUMENT SIGN REIMBURSEMENTS
A17: SUPERCUTS | B17: 2214 | D17: MONUMENT SIGN REIMBURSEMENTS
A18: EUROPEAN WAX CENTER | B18: 2214 | D18: MONUMENT SIGN REIMBURSEMENTS
A25: General Ledger Balance | B25: =SUM(B13:B24) -> 21070
A29: 16 | D29: MRI Implementation for Cornerstone
G36: SKYLINE Implementation for Cornerstone

Sheet PreP-Ins
A1: MONTHLY REPORTING REQUIREMENTS | I1: Site Reports
A5: REGENCY BRESSI, LLC
A7: Prepaid Insurance - Account 11200000
A9: As of :
A10: ='Pet-cash'!$A$11 -> 40816
A12: Prepaid To: | B12: Period | C12: Days/Mo | D12: Total Amount Paid | F12: Monthly Exp | G12: YTD Exp | H12: Prepaid Bal | I12: Description
A14: Marsh USA | B14: 5/24/11-2/15/13 | C14: 633 | D14: 1089 | F14: =D14/C14*30 -> 51.611374 | G14: =D14/C14*(8+30+31+31+30) -> 223.64929 | H14: =+D14-G14 -> 865.35071 | I14: Pollution Legal Liability Insurance
A15: Marsh USA | B15: 8/01/11-8/01/12 | C15: 12 | D15: 46441 | F15: =+D15/12 -> 3870.0833 | G15: =+F15*2 -> 7740.1667 | H15: =+D15-G15 -> 38700.833 | I15: Property Insurance
A16: Marsh USA | B16: 8/01/11-8/01/12 | C16: 12 | D16: 8885 | F16: =+D16/12 -> 740.41667 | G16: =+F16*2 -> 1480.8333 | H16: =+D16-G16 -> 7404.1667 | I16: General Liability Insurance
A17: Marsh USA | B17: 8/01/11-8/01/12 | C17: 12 | D17: 3993 | F17: =+D17/12 -> 332.75 | G17: =+F17*2 -> 665.5 | H17: =+D17-G17 -> 3327.5 | I17: Excess Liability Insurance
A28: General Ledger Balance | H28: =SUM(H14:H27) -> 50297.851
A35: 18 | I35: MRI Implementation for Cornerstone
L37: SKYLINE Implementation for Cornerstone

Sheet PreP-Other
A1: MONTHLY REPORTING REQUIREMENTS | D1: Site Reports
A5: REGENCY BRESSI, LLC
A7: Other Prepaids - Account 11300000
A9: As of :
A10: ='Pet-cash'!$A$11 -> 40816
A12: Prepaid To: | B12: Total Amount | D12: Description
A29: General Ledger Balance | B29: =SUM(B13:B28) -> 0
A36: 18 | D36: MRI Implementation for Cornerstone
G38: SKYLINE Implementation for Cornerstone

Sheet O-Asset
A1: MONTHLY REPORTING REQUIREMENTS | E1: Site Reports
E2: \
A5: "Property Name"
A7: Other Assets - Account 11900000
A9: As of:
A10: ='Pet-cash'!A11:F11 -> 40816
A12: Definition | B12: Total Amount | D12: Description
D13: <Type Of Asset>
A28: General Ledger Balance | B28: =SUM(B14:B27) -> 0
A31: 19 | D31: MRI Implementation for Cornerstone
G39: SKYLINE Implementation for Cornerstone

Sheet TT-Costs
A1: MONTHLY REPORTING REQUIREMENTS | E1: Site Reports
E2: \
A5: REGENCY BRESSI, LLC
A7: Tenant Installation Cost - Account 13200000
A9: As of: 9/30/11
A12: Tenant | B12: Total Amount | D12: Description
A14: 4G Wireless | B14: 45570 | D14: Tenant Improvement Reimbursement
A15: Hendo's Local Pizza & Pint | B15: 42315 | D15: Tenant Improvement Reimbursement
A16: Supercuts | B16: 26000 | D16: Tenant Improvement Reimbursement
A25: General Ledger Balance | B25: =SUM(B14:B24) -> 113885
A28: 19 | D28: MRI Implementation for Cornerstone
G36: SKYLINE Implementation for Cornerstone

Sheet Leas-Costs
A1: MONTHLY REPORTING REQUIREMENTS | G1: Site Reports
A4: "Property Name"
A6: Leasing Costs Schedule - 13250000
A8: As of: 9/30/11
A10: Tenant | B10: Broker(s) Name | C10: Lease Terms Start Date | D10: Lease Terms End Date | E10: Actual $ MTD | F10: Actual $ YTD | G10: YTD Budget | K10: Actual vs. Budget
A61: Total | E61: =SUM(E12:E25) -> 0 | F61: =SUM(F12:F60) -> 0 | G61: =SUM(G11:G23) -> 0 | K61: =SUM(K11:K23) -> 0
A63: Note: This schedule should include not only new monthly expenditures, but also a history of what has been spent YTD (a carry forward type schedule).
A64: 20 | F64: MRI Implementation for Cornerstone

Sheet Amort-Leas
A1: MONTHLY REPORTING REQUIREMENTS | J1: Site Reports
A4: REGENCY BRESSI, LLC
A6: Amortization Lease Costs - 13350000
A8: As of: 9/30/11
A10: Tenant | B10: Amount | C10: Life/Term | D10: # of Months | E10: Monthly Depr/Amort Exp | F10: Total Lease Cost Paid | J10: YTD Expense | K10: Accum Depreciation
B66: =SUM(B12:B63) -> 0 | E66: =SUM(E12:E65) -> 0 | F66: =SUM(F12:F65) -> 0 | J66: =SUM(J12:J65) -> 0 | K66: =SUM(K12:K65) -> 0
A74: 21 | F74: MRI Implementation for Cornerstone

Sheet Amort-Finance
A1: MONTHLY REPORTING REQUIREMENTS | J1: Site Reports
A4: REGENCY BRESSI, LLC
A6: Amortization Finance Costs - 13910000
A8: As of: 9/30/11
A10: Loan | B10: Amount | C10: Life/Term | D10: # of Months | E10: Monthly Depr/Amort Exp | F10: Total Lease Cost Paid | J10: YTD Expense | K10: Accum Depreciation
A11: Midland Loan #770000314 | B11: 173042.12 | C11: 5 | D11: =5*12 -> 60 | E11: =+B11/D11 -> 2884.0353 | J11: =+E11*1 -> 2884.0353 | K11: =-E11*1 -> -2884.0353
B66: =SUM(B11:B63) -> 173042.12 | C66: 5 | D66: =SUM(D11:D63) -> 60 | E66: =SUM(E11:E63) -> 2884.0353 | F66: =SUM(F11:F63) -> 0 | G66: =SUM(G11:G63) -> 0 | H66: =SUM(H11:H63) -> 0 | I66: =SUM(I11:I63) -> 0 | J66: =SUM(J11:J63) -> 2884.0353 | K66: =SUM(K11:K63) -> -2884.0353
A74: 21 | F74: MRI Implementation for Cornerstone

Sheet Free-R
A1: MONTHLY REPORTING REQUIREMENTS | F1: Site Reports
A5: REGENCY BRESSI, LLC
A7: Free Rent
A9: As of: 9/30/11
A14: Tenant | B14: Commence Date | C14: Expiration Date | D14: Commence Date | E14: Expiration Date | F14: Unamortized Balance | G14: Amortization
A15: <List by Tenant> | F15: (Calculation of net amortized
F16: free rent Tenant Balance
F17: in Account 1195)
A27: Total | F27: =SUM(F15:F26) -> 0 | G27: =SUM(G15:G26) -> 0
A29: Note: This schedule should include not only new monthly expenditures, but also a history of what has been spent to Date (a carry forward type schedule).
A31: 22 | F31: MRI Implementation for Cornerstone

Sheet Accr-Sale
A1: MONTHLY REPORTING REQUIREMENTS | C1: Site Reports
A5: <Enter Property Name Here>
A7: Accrued Sales Tax - Account 20300000
A9: As of:_________
A13: Name of Taxing Authority | B13: Aging of Balance Due 30, 60 or 90 day | C13: Current Balance per the GL
A24: Total | B24: =SUM(B14:B23) -> 0 | C24: =SUM(C14:C23) -> 0
A33: 23 | C33: MRI Implementation for Cornerstone

Sheet Accr-Leas
A1: MONTHLY REPORTING REQUIREMENTS | E1: Site Reports
A5: REGENCY BRESSI, LLC
A7: Accrued Leasing Commission - Account 20600000
A9: As of
A10: ='Pet-cash'!$A$11 -> 40816
A12: Broker Name | B12: Amount Due | C12: Due Date | D12: Tenant Name | E12: Lease Effective Date | F12: Lease Expiration Date
A25: Total | B25: =SUM(B13:B24) -> 0
A27: *Total must tie to balance per the G\L.
A34: 24 | E34: MRI Implementation for Cornerstone

Sheet Mgmt-Fee
A1: MONTHLY REPORTING REQUIREMENTS | E1: Site Reports
A4: REGENCY BRESSI, LLC
A6: Management Fee - Account 2094000
A8: For the month ending:
A9: ='Pet-cash'!$A$11 -> 40816
C14: Basis for Calculation | D14: Management Fee % | E14: Fee Due
B15: January
B16: February
B17: March
B18: April
B19: May
B20: June
B21: July | C21: 390331.42 | D21: 0.025 | E21: =C21*D21 -> 9758.2855
B22: August | C22: 296986.19 | D22: 0.025 | E22: =C22*D22 -> 7424.6548
B23: September | C23: 299807.31 | D23: 0.025 | E23: =C23*D23 -> 7495.1827
B24: October
B25: November
B26: December
B27: Total | E27: =SUM(E15:E26) -> 24678.123
A34: 27 | E34: MRI Implementation for Cornerstone

Sheet Accr Ins
A1: MONTHLY REPORTING REQUIREMENTS | G1: Site Reports
A5: REGENCY BRESSI, LLC
A7: Prepaid Insurance - Account 2100000
A9: As of :
A10: ='Pet-cash'!$A$11 -> 40816
A12: CoverageType | B12: Preminum Commence Date | C12: Premium Expiration Date | D12: Number of Months | E12: Amount Due | F12: Monthly Amortization | G12: Accumulated Insurance Exp. | H12: General Ledger Balance | I12: Months Remaining
A13: Property Insurance
A14: Liability Premium
A15: Umbrella Premium
A16: Property/All Risk Premium
A17: General Liability Premium
A18: Environmental Premium
A21: Total | E21: =SUM(E13:E20) -> 0 | F21: =SUM(F13:F20) -> 0 | G21: =SUM(G13:G20) -> 0 | H21: =SUM(H13:H20) -> 0
A23: Note: This schedule should include not only new monthly expenditures, but also a history of what has been spent to Date (a carry forward type schedule).
A25: 22 | H25: MRI Implementation for Cornerstone

Sheet O-Liabil
A1: MONTHLY REPORTING REQUIREMENTS | C1: Site Reports
A5: REGENCY BRESSI, LLC
A7: Other Liabilities - Account 21000000
A9: As of
A10: ='Pet-cash'!$A$11 -> 40816
A13: Vendor Name | B13: Amount Accrued | C13: Description of Work - Type of Expense
C14: LNR Contribution to Grand Opening Fund
C15: Grand Opening Fund
C16: Promotional Fund
C17: Property/Liability Insurance (see Accr Ins)
B18: 2065.48 | C18: Tommy V, May Late Fee
B19: 2156.47 | C19: Souplantation, May Rent
B20: 1789.51 | C20: Community Utility Billing Services 07/11
B21: 1709.7 | C21: Community Utility Billing Services 08/11
C22: 2011 Estimated CAM Rec
B23: =SUM(B14:B16) -> 0
A30: Total | B30: =SUM(B14:B29) -> 7721.16

Sheet Legal-Fee
A1: MONTHLY REPORTING REQUIREMENTS | E1: Site Reports
A5: "Property Name"
A7: Legal Fees- Account 61600000
A9: Period ending:
A12: Name of Law Firm | B12: Date Paid | C12: Total Amount Paid | D12: Professional Fees | E12: Out of Pocket Expenses | I12: Allocation of Total
A29: Total | C29: =SUM(C13:C28) -> 0 | D29: =SUM(D13:D28) -> 0 | E29: =SUM(E13:E28) -> 0 | I29: =SUM(I13:I28) -> 0
A31: Note: Total must tie to YTD expense per G/L.
A33: 28 | E33: MRI Implementation for Cornerstone

Sheet Leas-Costs (2)
A1: MONTHLY REPORTING REQUIREMENTS | F1: Home Office Reports
A5: <Enter Property Name Here>
A7: Leasing Costs Schedule - 13250000
A9: As of:_________
A12: Tenant | B12: Broker(s) Name | C12: Lease Terms Start Date | D12: Lease Terms End Date | E12: Actual $ MTD | F12: Actual $ YTD | G12: YTD Budget | K12: Actual vs. Budget
A13: List by Tenant | B13: Broker/Cost Descr.*
A27: Total | E27: =SUM(E13:E26) -> 0 | F27: =SUM(F13:F26) -> 0 | G27: =SUM(G13:G26) -> 0 | K27: =SUM(K13:K26) -> 0
A29: Note: This schedule should include not only new monthly expenditures, but also a history of what has been spent to date (a carry forward type schedule).
A31: 37 | F31: MRI Implementation for Cornerstone

Sheet Legal-Fee (2)
A1: MONTHLY REPORTING REQUIREMENTS | E1: Home Office Reports
A5: <Enter Property Name Here>
A7: Legal Fees
A9: As of:____________
A12: Name of Law Firm | B12: Date Paid | C12: Total Amount Paid | D12: Professional Fees | E12: Out of Pocket Expenses | I12: Allocation of Total
A27: Total | C27: =SUM(C13:C26) -> 0 | D27: =SUM(D13:D26) -> 0 | E27: =SUM(E13:E26) -> 0 | I27: =SUM(I13:I26) -> 0
A29: Note: Total must tie to YTD expense per G/L.
A32: 38 | E32: MRI Implementation for Cornerstone

Sheet Fixed
A1: MONTHLY REPORTING REQUIREMENTS | G1: Home Office Reports
A5: Fixed Asset Identification Form
A6: Property Name:
A7: Property #
A8: Month:
A10: MRI | D10: Suite | E10: Project Description/include Job Ledger | I10: Placed in Service
A11: Account # | C11: Account Name | D11: Number | E11: (Tenant Name if applicable) | G11: Amount | I11: (A)
A30: (A) TI's=lease start date All Other=Date project/fixed asset was placed in service (not final invoice payment date).
A33: 39 | E33: SKYLINE Implementation for Cornerstone

Sheet Chk list
A1: MONTHLY REPORTING REQUIREMENTS | K1: Home Office Reports
A5: MRI - PRE-CLOSE AUDIT CHECKLIST
A6: For the period ending:
C8:  Compare the cash balance from the Bank Reconciliation to the General Ledger Cash account (A/C 1020)
C10:  Compare the Cash Receipts Journal to the Total Cash Receipts per the G/L (A/C 1020)
C12:  Compare the cash balance from the Bank Reconciliation to the General Ledger Cash account (A/C 1025)
C14:  Compare the A/P Check Register to the Total Cash Disbursed per the G/L (A/C 1020).
C16:  Compare the Net Change Column of the CM Ledger to the Net Total of Accounts Receivable and Prepaid Rent (A/C 1080 & 2040).
C18:  Compare the totals on the Aged Delinquencies Report to the accounts receivable (A/C 1080) balance per the General Ledger
C20:  Compare over 90 days balance per Aged Delinquencies to Reserve for Doubtful Accounts (A/C 1090) and prepare Journal Entry
C22:  Compare the balance on the A/P Open Invoice Report to the accounts payable (A/C 2020) balance on the General Ledger.
C24:  Compare the security deposit balance on the CM Security Deposits Ledger to the Security Deposit G/L account (A/C 2110)
C26:  Test Real Estate Tax Expense (A/C 6010) for correct number of months expense.
C28:  Test Accrued Real Estate Taxes (A/C 2070) for correct number of the months expense.
C30:  Test Insurance Expense (A/C 6060) for correct number of months expense.
... C51: DO NOT PROCEED WITH THE CLOSE IF THE ABOVE CHECKLIST IS NOT COMPLETE AND RECONCILED.
L54: MRI Implementation for Cornerstone

Sheet Review Comments
B8: Monthly Financial Analysis
B9: Review Comments
A11: Property: | B11: GREENFIELD GATEWAY
A13: Month: | B13: FOR THE MONTH ENDED 07/31/2026
A15: Books | B15: Cash
A17: 1
A21: 2
A26: 3
A31: 4
A36: 5
A41: 6
A44: 7 | B44: CASH-SWEEP ACCOUNT #10190 :- There is a Diference of $450.33 in Closing balance of General Ledger & Cash flow Balance as per MRI :- $226,574.20 Balance as Cash Flow :- $227024.53

Sheet Summary
A2: Property# | B2: 801
A3: Property Name | B3: GREENFIELD GATEWAY
A4: Month | B4: 46234
A6: Account# | B6: Account Name | C6: Balance from Schedule | D6: Balance from TB | E6: Balance | F6: Comments
A7: 10410-000000 | B7: ESCROW-PROPERTY TAX | C7: ='10410'!E30 -> 132471.44 | D7: {=IFERROR(INDEX(TB!G:G,MATCH(Summary!A7,TB!A:A,0),0),0)} -> 132471.44 | E7: =C7-D7 -> 0
A8: 10420-000000 | B8: ESCROW-RESERVE ACT | C8: ='10420'!F46 -> 377979.02 | D8: {=IFERROR(INDEX(TB!G:G,MATCH(Summary!A8,TB!A:A,0),0),0)} -> 377979.02 | E8: =C8-D8 -> 0
A9: 10432-000000 | B9: ESCROW-LC RESERVE | C9: 0 | D9: {=IFERROR(INDEX(TB!G:G,MATCH(Summary!A9,TB!A:A,0),0),0)} -> 0 | E9: =C9-D9 -> 0
A10: 10460-000000 | B10: ESCROW-INSURANCE ACT | C10: ='10460'!F29 -> 31633.8 | D10: {=IFERROR(INDEX(TB!G:G,MATCH(Summary!A10,TB!A:A,0),0),0)} -> 31633.8 | E10: =C10-D10 -> 0
A11: 12020-000000 | B11: ACCOUNTS RECEIVABLE OTHER | C11: 0 | D11: {=IFERROR(INDEX(TB!G:G,MATCH(Summary!A11,TB!A:A,0),0),0)} -> 0 | E11: =C11-D11 -> 0
A12: 12100-000000 | B12: LOAN RECEIVABLE | C12: 0 | D12: {=IFERROR(INDEX(TB!G:G,MATCH(Summary!A12,TB!A:A,0),0),0)} -> 0 | E12: =C12-D12 -> 0
A13: 12530-000000 | B13: LOAN DEPOSIT | C13: ='12530'!F15 -> -8909920 | D13: {=IFERROR(INDEX(TB!G:G,MATCH(Summary!A13,TB!A:A,0),0),0)} -> -8909920 | E13: =C13-D13 -> 0
A14: 13000-000000 | B14: SUSPENSE | C14: ='13000'!F11 -> 875.4 | D14: {=IFERROR(INDEX(TB!G:G,MATCH(Summary!A14,TB!A:A,0),0),0)} -> 875.4 | E14: =C14-D14 -> 0
A15: 13150-000000 | B15: FROM 801 MAIN STREET | C15: 0 | D15: {=IFERROR(INDEX(TB!G:G,MATCH(Summary!A15,TB!A:A,0),0),0)} -> 0 | E15: =C15-D15 -> 0
A16: 14000-000000 | B16: LAND COSTS | C16: ='Fixed Asset'!#REF! -> #REF! | D16: {=IFERROR(INDEX(TB!G:G,MATCH(Summary!A16,TB!A:A,0),0),0)} -> 0 | E16: =C16-D16 -> #REF!
A17: 15000-000000 | B17: BUILDING | C17: ='Fixed Asset'!F11 -> 0 | D17: {=IFERROR(INDEX(TB!G:G,MATCH(Summary!A17,TB!A:A,0),0),0)} -> 0 | E17: =C17-D17 -> 0
A18: 15100-000000 | B18: TENANT IMPROVEMENTS | C18: ='15100'!F16 -> 26880 | D18: {=IFERROR(INDEX(TB!G:G,MATCH(Summary!A18,TB!A:A,0),0),0)} -> 26880 | E18: =C18-D18 -> 0
A19: 15200-000000 | B19: OTHER CAPITAL ITEMS | C19: 0 | D19: {=IFERROR(INDEX(TB!G:G,MATCH(Summary!A19,TB!A:A,0),0),0)} -> 0 | E19: =C19-D19 -> 0
A20: 16500-000000 | B20: LEASE COMMISSION | C20: ='16500'!F15 -> 61893.81 | D20: {=IFERROR(INDEX(TB!G:G,MATCH(Summary!A20,TB!A:A,0),0),0)} -> 61893.81 | E20: =C20-D20 -> 0
A21: 17000-000000 | B21: LEGAL FEES | C21: ='Fixed Asset'!#REF! -> #REF! | D21: {=IFERROR(INDEX(TB!G:G,MATCH(Summary!A21,TB!A:A,0),0),0)} -> 0 | E21: =C21-D21 -> #REF!
A22: 17100-000000 | B22: CLOSING COST | C22: ='Fixed Asset'!F16 -> 1130.89 | D22: {=IFERROR(INDEX(TB!G:G,MATCH(Summary!A22,TB!A:A,0),0),0)} -> 1130.89 | E22: =C22-D22 -> 0
A23: 17300-000000 | B23: TITLE & ESCROW FEES | C23: ='Fixed Asset'!#REF! -> #REF! | D23: {=IFERROR(INDEX(TB!G:G,MATCH(Summary!A23,TB!A:A,0),0),0)} -> 0 | E23: =C23-D23 -> #REF!
A24: 18100-000000 | B24: ACCUMULATED DEPRECIATION | C24: 0 | D24: {=IFERROR(INDEX(TB!G:G,MATCH(Summary!A24,TB!A:A,0),0),0)} -> 0 | E24: =C24-D24 -> 0
A25: 18200-000000 | B25: ACCUMULATED AMORTIZATION | C25: 0 | D25: {=IFERROR(INDEX(TB!G:G,MATCH(Summary!A25,TB!A:A,0),0),0)} -> 0 | E25: =C25-D25 -> 0
A26: 16500-000000 | B26: LEASING COMMISSIONS | C26: ='16500'!F15 -> 61893.81 | D26: {=IFERROR(INDEX(TB!G:G,MATCH(Summary!A26,TB!A:A,0),0),0)} -> 61893.81 | E26: =C26-D26 -> 0
A27: 16700-000000 | B27: REFINANCE COSTS | C27: 0 | D27: {=IFERROR(INDEX(TB!G:G,MATCH(Summary!A27,TB!A:A,0),0),0)} -> 0 | E27: =C27-D27 -> 0
A28: 25300-000000 | B28: NOTE PAYABLE | C28: ='25300'!E28 -> -9498624.9 | D28: {=IFERROR(INDEX(TB!G:G,MATCH(Summary!A28,TB!A:A,0),0),0)} -> -9498624.9 | E28: =C28-D28 -> 0
A29: 20620-000000 | B29: LEASE COMMISSION | C29: ='20620'!E11 -> 0 | D29: {=IFERROR(INDEX(TB!G:G,MATCH(Summary!A29,TB!A:A,0),0),0)} -> 0 | E29: =C29-D29 -> 0
A30: 20660-000000 | B30: ACCRUED INTEREST EXPENSE | C30: 0 | D30: {=IFERROR(INDEX(TB!G:G,MATCH(Summary!A30,TB!A:A,0),0),0)} -> 0 | E30: =C30-D30 -> 0
A31: 20800-000000 | B31: TENANT SECURITY DEPOSIT | C31: 0 | D31: {=IFERROR(INDEX(TB!G:G,MATCH(Summary!A31,TB!A:A,0),0),0)} -> -44847.89 | E31: =C31-D31 -> 44847.89 | F31: NA
A32: 20900-000000 | B32: PREPAID RENT | C32: 0 | D32: {=IFERROR(INDEX(TB!G:G,MATCH(Summary!A32,TB!A:A,0),0),0)} -> 0 | E32: =C32-D32 -> 0
A33: 25100-000000 | B33: NOTES PAYABLE-PRINCIPAL LIFE INS CO | C33: 0 | D33: {=IFERROR(INDEX(TB!G:G,MATCH(Summary!A33,TB!A:A,0),0),0)} -> 0 | E33: =C33-D33 -> 0
A34: 30100-000000 | B34: EQUITY | C34: 0 | D34: {=IFERROR(INDEX(TB!G:G,MATCH(Summary!A34,TB!A:A,0),0),0)} -> 0 | E34: =C34-D34 -> 0
A35: 30400-000000 | B35: PRIOR YR RETAINED EARNING | C35: 0 | D35: {=IFERROR(INDEX(TB!G:G,MATCH(Summary!A35,TB!A:A,0),0),0)} -> 16268345 | E35: =C35-D35 -> -16268345 | F35: NA
A36: 35000-000000 | B36: CAPITAL DIST | C36: ='35000'!E19 -> 1950677.4 | D36: {=IFERROR(INDEX(TB!G:G,MATCH(Summary!A36,TB!A:A,0),0),0)} -> 1950677.4 | E36: =C36-D36 -> 0
A37: 36000-000000 | B37: OWNER'S CONTRIBUTION | C37: ='36000'!E16 -> 31363.96 | D37: {=IFERROR(INDEX(TB!G:G,MATCH(Summary!A37,TB!A:A,0),0),0)} -> 31363.96 | E37: =C37-D37 -> 0
A39: Insurance
A40: 50111-000000 | B40: INSURANCE-PROPERTY | C40: 0 | D40: {=IFERROR(INDEX(TB!G:G,MATCH(Summary!A40,TB!A:A,0),0),0)} -> 0 | E40: =C40-D40 -> 0
A41: 50112-000000 | B41: INSURANCE-LIABILITY | C41: 0 | D41: {=IFERROR(INDEX(TB!G:G,MATCH(Summary!A41,TB!A:A,0),0),0)} -> 0 | E41: =C41-D41 -> 0
A42: 50130-000000 | B42: INSURANCE-UMBRELLA | C42: 0 | D42: {=IFERROR(INDEX(TB!G:G,MATCH(Summary!A42,TB!A:A,0),0),0)} -> 0 | E42: =C42-D42 -> 0

Sheet TB
A1: Database: ATHENA | B1: Trial Balance | E1: Page: | F1: 1
A2: ENTITY: 801 | B2: Athena Property Management | E2: Date: | F2: 46247.666
B3: GREENFIELD GATEWAY LLC | E3: Time: | F3: 46247.666
A6: Cash | B6: Year to Date Balances for period 07/26
B7: Report includes an open period. Entries are not final.
A9: Account | B9: Description | C9: Debit | E9: Credit
A12: No Department
A14: 10170-000000 | B14: LOCKBOX DEPOSIT ACCOUNT | C14: 3008.53 | G14: =C14-E14 -> 3008.53
A15: 10180-000000 | B15: CASH-OPERATING | C15: 32450.11 | G15: =C15-E15 -> 32450.11
A16: 10410-000000 | B16: ESCROW-PROPERTY TAX | C16: 132471.44 | G16: =C16-E16 -> 132471.44
A17: 10420-000000 | B17: ESCROW-RESERVE ACT | C17: 377979.02 | G17: =C17-E17 -> 377979.02
A18: 10460-000000 | B18: ESCROW-INSURANCE | C18: 31633.8 | G18: =C18-E18 -> 31633.8
A19: 12530-000000 | B19: LOAN DEPOSIT | E19: 8909920 | G19: =C19-E19 -> -8909920
A20: 13000-000000 | B20: SUSPENSE | C20: 875.4 | G20: =C20-E20 -> 875.4
A21: 13100-000000 | B21: MISCELLANEOUS DEPOSITS | C21: 14985 | G21: =C21-E21 -> 14985
A22: 15010-000000 | B22: BUILDING IMPROVEMENTS | C22: 26000 | G22: =C22-E22 -> 26000
A23: 15100-000000 | B23: TENANT IMPROVEMENTS | C23: 26880 | G23: =C23-E23 -> 26880
A24: 16500-000000 | B24: LEASING COMMISSIONS | C24: 61893.81 | G24: =C24-E24 -> 61893.81
A25: 17100-000000 | B25: CLOSING COSTS | C25: 1130.89 | G25: =C25-E25 -> 1130.89
A26: 20800-000000 | B26: TENANT SECURITY DEPOSIT | E26: 44847.89 | G26: =C26-E26 -> -44847.89
A27: 25300-000000 | B27: NOTES PAYABLE | E27: 9498624.9 | G27: =C27-E27 -> -9498624.9
A28: 30400-000000 | B28: PRIOR YR RETAINED EARNING | C28: 16268345 | G28: =C28-E28 -> 16268345
A29: 35000-000000 | B29: OWNER'S DISTRIBUTION | C29: 1950677.4 | G29: =C29-E29 -> 1950677.4
A30: 36000-000000 | B30: OWNER'S CONTRIBUTION | C30: 31363.96 | G30: =C30-E30 -> 31363.96
A31: 40100-000000 | B31: BASE RENTAL INCOME | E31: 695796.84 | G31: =C31-E31 -> -695796.84
A32: 40140-000000 | B32: COMMON AREA INCOME | E32: 61940.57 | G32: =C32-E32 -> -61940.57
A33: 40150-000000 | B33: PRIOR YEAR CAM | E33: 11115.79 | G33: =C33-E33 -> -11115.79
A34: 40170-000000 | B34: OTHER RECOVERIES | E34: 16867.64 | G34: =C34-E34 -> -16867.64
A35: 40220-000000 | B35: RENT CONCESSIONS | C35: 7758.06 | G35: =C35-E35 -> 7758.06
A36: 40230-000000 | B36: INSURANCE INCOME | E36: 16929.57 | G36: =C36-E36 -> -16929.57
A37: 40240-000000 | B37: PROPERTY TAX INCOME | E37: 77265.02 | G37: =C37-E37 -> -77265.02
A38: 40390-000000 | B38: ADMINISTRATIVE FEE INCOME | E38: 2564.41 | G38: =C38-E38 -> -2564.41
A39: 40500-000000 | B39: SIGNAGE INCOME | E39: 28518.3 | G39: =C39-E39 -> -28518.3
A40: 40610-000000 | B40: CAM UTILITY REIMBURSEMENT | E40: 60 | G40: =C40-E40 -> -60
A41: 41000-000000 | B41: SETTLEMENT/TERMINATION INCOME | E41: 93000 | G41: =C41-E41 -> -93000
A42: 41300-000000 | B42: SALES TAX COLLECTIONS | E42: 24231.66 | G42: =C42-E42 -> -24231.66
A43: 45000-000000 | B43: INVESTMENT INTEREST | E43: 126.22 | G43: =C43-E43 -> -126.22
A44: 50150-000000 | B44: LANDSCAPE-TREE TRIMMINGS | C44: 6500 | G44: =C44-E44 -> 6500
A45: 50160-000000 | B45: LANDSCAPE-CONSUMABLES | C45: 3408.08 | G45: =C45-E45 -> 3408.08
A46: 50170-000000 | B46: LANDSCAPE-MAINTENANCE | C46: 18445 | G46: =C46-E46 -> 18445
A47: 50190-000000 | B47: LANDSCAPE-SPRINKLER REPAIRS | C47: 150 | G47: =C47-E47 -> 150
A48: 50510-000000 | B48: PARKING- LIGHTING MAINT | C48: 485 | G48: =C48-E48 -> 485
A49: 50530-000000 | B49: PARKING LOT LIGHT REPAIRS | C49: 1078 | G49: =C49-E49 -> 1078
A50: 50540-000000 | B50: PARKING LOT REPAIRS | C50: 44165.74 | G50: =C50-E50 -> 44165.74
A51: 50550-000000 | B51: SIGN MAINTENANCE | C51: 1230 | G51: =C51-E51 -> 1230
A52: 51020-000000 | B52: GENERAL MAINTENANCE | C52: 1092.5 | G52: =C52-E52 -> 1092.5
A53: 51040-000000 | B53: JANITORIAL | C53: 6928.5 | G53: =C53-E53 -> 6928.5
A54: 51050-000000 | B54: PEST CONTROL MAINTENANCE | C54: 693 | G54: =C54-E54 -> 693
A55: 51080-000000 | B55: ON SITE MANAGEMENT FEES | C55: 31253.42 | G55: =C55-E55 -> 31253.42
... A72: 70410-000000 | B72: CITY SALES TAX | C72: 25229.58 | G72: =C72-E72 -> 25229.58
B73: Total: | C73: 19481809 | E73: 19481809 | G73: =C73-E73 -> 0
G74: =C74-E74 -> 0
G75: =C75-E75 -> 0
G76: =C76-E76 -> 0
G77: =C77-E77 -> 0
G78: =C78-E78 -> 0
G79: =C79-E79 -> 0
G80: =C80-E80 -> 0
G81: =C81-E81 -> 0

Sheet 10410
A1: ='Review Comments'!B11 -> GREENFIELD GATEWAY
A2: PROPERTY TAX RESERVE - 10410
A3: ='Review Comments'!B13 -> FOR THE MONTH ENDED 07/31/2026
A9: Origination Date | C9: Description | E9: Total Amount
A11: 45808 | C11: Beginning Balance - Property Acquistion | E11: 108995.37
A12: 45809 | C12: Mortgage Payment | E12: 12764.18
A13: 45839 | C13: Mortgage Payment | E13: 12764.18
A14: 45869 | C14: Balance Transfer to 10460 | E14: -6785.15
A15: 45873 | C15: Mortgage Payment | E15: 12316.25
A16: 45901 | C16: Mortgage Payment | E16: 12316.25
A17: 45933 | C17: Mortgage Payment | E17: 12316.25
A18: 45964 | C18: Mortgage Payment | E18: 12316.25
A19: 45991 | C19: 07/25-12/25 PROPERTY TAX | E19: -71531.07
A20: 45994 | C20: Mortgage Payment | E20: 12316.25
A21: 46027 | C21: Mortgage Payment | E21: 12316.25
A22: 46056 | C22: Mortgage Payment | E22: 12316.25
... A28: 46209 | C28: Mortgage Payment | E28: 12316.25
C30: Account Total: | E30: =SUM(E11:E28) -> 132471.44
C32: 10410-000000 | E32: {=IFERROR(INDEX(TB!G:G,MATCH('10410'!C32,TB!A:A,0),0),0)} -> 132471.44
C33: S/B ZERO | E33: =E30-E32 -> 0
C34: Statement Amount | E34: 132471.44
E36: =E32-E34 -> 0

Sheet 10450
A1: ='Review Comments'!B11 -> GREENFIELD GATEWAY
A2: ESCROW GROUND RENT- 10460
A3: ='Review Comments'!B13 -> FOR THE MONTH ENDED 07/31/2026
A9: Origination Date | C9: Description | E9: Amount | F9: Total Amount
A11: 42978 | C11: Escrow Ground Rent
A12: 43038 | C12: 09/17 Mortgage Payment | F12: =F11+E12 -> 0
A13: 43068 | C13: 10/17 Mortgage Payment | F13: =F12+E13 -> 0
A14: 43098 | C14: 11/17 Mortgage Payment | F14: =F13+E14 -> 0
A15: 43117 | C15: 12/17 Mortgage Payment | F15: =F14+E15 -> 0
A16: 43117 | C16: 12/17 Mortgage Payment | F16: =F15+E16 -> 0
A17: 43131 | C17: Marcella Gregory pmt | F17: =F16+E17 -> 0
A18: 43159 | C18: 01/18 Mortgage Payment | F18: =F17+E18 -> 0
A19: 43159 | C19: Marcella Gregory pmt | F19: =F18+E19 -> 0
A20: 43190 | C20: 02/18 Mortgage Payment | F20: =F19+E20 -> 0
A21: 43190 | C21: Marcella Gregory pmt | F21: =F20+E21 -> 0
A22: 43220 | C22: 03/18 Mortgage Payment | F22: =F21+E22 -> 0
A23: 43220 | C23: Marcella Gregory pmt | F23: =F22+E23 -> 0
... A25: 43251 | C25: Marcella Gregory pmt | F25: =F24+E25 -> 0
C27: Account Total: | F27: =F19 -> 0

Sheet 10420
A1: ='Review Comments'!B11 -> GREENFIELD GATEWAY
A2: ESCROW-RESERVE ACCOUNT - 10420
A3: ='Review Comments'!B13 -> FOR THE MONTH ENDED 07/31/2026
A9: Origination Date | C9: Description | E9: Amount | F9: Total Amount
A11: 45808 | C11: YTD Balance Transfer from Eagle Comm | F11: 394440
A12: 45808 | C12: True Up Escrow reserve bal | F12: 35
A13: 45809 | C13: 05/25 Mortage payment | F13: 564.24
A14: 45838 | C14: 06/25 Escrow interest income | F14: 17.83
A15: 45839 | C15: 06/25 Mortage payment | F15: 564.24
A16: 45869 | C16: 07/25 Escrow interest income | F16: 17.27
A17: 45873 | C17: 07/25 Mortage payment | F17: 564.24
A18: 45900 | C18: 08/25 Escrow interest income | F18: 17.88
A19: 45901 | C19: 08/25 Mortage payment | F19: 564.24
A20: 45930 | C20: 09/25 Escrow interest income | F20: 17.9
A21: 45933 | C21: 09/25 Mortage payment | F21: 564.24
A22: 45961 | C22: 10/25 Escrow interest income | F22: 17.36
... A44: 46234 | C44: 07/26 Escrow interest income | F44: 16.51
C46: Account Total: | F46: =SUM(F11:F45) -> 377979.02
E48: 10420-000000 | F48: {=IFERROR(INDEX(TB!G:G,MATCH('10420'!E48,TB!A:A,0),0),0)} -> 377979.02
E49: S/B ZERO | F49: =F46-F48 -> 0
E50: Statement Amount | F50: 377979.02
F51: =F46-F50 -> 0

Sheet 10460
A1: ='Review Comments'!B11 -> GREENFIELD GATEWAY
A2: ESCROW- INSURANCE ACT- 10460
A3: ='Review Comments'!B13 -> FOR THE MONTH ENDED 07/31/2026
A9: Origination Date | C9: Description | E9: Amount | F9: Total Amount
A11: 45808 | C11: YTD Balance Transfer from Eagle Comm | F11: 16425.67
A12: 45809 | C12: 05/25 Mortgage Payment | F12: 2074.23
A13: 45839 | C13: 06/25 Mortgage Payment | F13: 2074.23
A14: 45869 | C14: BALANCE TRANSFER FR 10410 | F14: 6785.15
A15: 45873 | C15: 0725 Mortgage Payment | F15: 2487.21
A16: 45901 | C16: 0825 Mortgage Payment | F16: 2487.21
A17: 45933 | C17: 0925 Mortgage Payment | F17: 2487.21
A18: 45961 | C18: INSURANCE DISBURSEMENT 9/29/25-9/29/26 | F18: -25572
A19: 45991 | C19: 1025 Mortgage Payment | F19: 2487.21
A20: 45994 | C20: 1125 Mortgage Payment | F20: 2487.21
A21: 46027 | C21: 1225 Mortgage Payment | F21: 2487.21
A22: 46056 | C22: 0126 Mortgage Payment | F22: 2487.21
... A27: 46209 | C27: 0626 Mortgage Payment | F27: 2487.21
C29: Account Total: | F29: =SUM(F11:F27) -> 31633.8
E31: 10460-000000 | F31: {=IFERROR(INDEX(TB!G:G,MATCH(E31,TB!A:A,0),0),0)} -> 31633.8
E32: S/B ZERO | F32: =F29-F31 -> 0
E33: Statement Amount | F33: 31633.8
F34: =F29-F33 -> 0

Sheet 12020
A1: ='Review Comments'!B11 -> GREENFIELD GATEWAY
A2: A/R OTHER - 12020
A3: ='Review Comments'!B13 -> FOR THE MONTH ENDED 07/31/2026
A9: Date | C9: Description | E9: Amount
A12: 45547 | C12: Prior Ownership Balance | E12: 173500.35
A13: 45684 | C13: Prior Ownership Receipt | E13: =-5543.62-8018.48-3706.53+1479.41 -> -15789.22
A14: 45737 | C14: Prior Ownership Receipt | E14: -78912.23
A15: 45769.373 | C15: Prior Ownership Receipt | E15: -1632.92
A16: 45769.373 | C16: Prior Ownership Receipt | E16: -670.86
C18: Account Total: | E18: =SUM(E12:E17) -> 76495.12
A20: 12020-000000 | C20: Per TB | E20: {=IFERROR(INDEX(#REF!,MATCH(A20,#REF!,0),0),0)} -> 0
C21: S/B zero | E21: =E18-E20 -> 76495.12

Sheet 12410
A1: ='Review Comments'!B11 -> GREENFIELD GATEWAY
A2: BAD DEBT RESERVE - 12410
A3: ='Review Comments'!B13 -> FOR THE MONTH ENDED 07/31/2026
F4: MTD | G4: YTD | H4: YTD
F5: 70300 | G5: 12410-000000
A6: Tenant Name | B6: O/S AR Balance 90 Days & Over | C6: Less Security Deposit | D6: Adjusted O/S Balance | E6: Beginning Bal | F6: Current Reserve | G6: Ending Bal | H6: Bad Debt Exp #70300 | I6: Comments/Status of Collection
D7: =B7+C7 -> 0 | E7: 0 | F7: =D7-E7 -> 0 | G7: =E7+F7 -> 0
C8: 0 | D8: =IF((B8+C8)>0,B8+C8,0) -> 0 | F8: =D8-E8 -> 0 | G8: =E8+F8 -> 0
C9: 0 | D9: =IF((B9+C9)>0,B9+C9,0) -> 0 | F9: =D9-E9 -> 0 | G9: =E9+F9 -> 0
C10: 0 | D10: =IF((B10+C10)>0,B10+C10,0) -> 0 | F10: =D10-E10 -> 0 | G10: =E10+F10 -> 0
C11: 0 | D11: =IF((B11+C11)>0,B11+C11,0) -> 0 | F11: =D11-E11 -> 0 | G11: =E11+F11 -> 0 | I11: ($50,108.55) reserved in 2020
C12: 0 | D12: =IF((B12+C12)>0,B12+C12,0) -> 0 | F12: =D12-E12 -> 0 | G12: =E12+F12 -> 0
C13: 0 | D13: =IF((B13+C13)>0,B13+C13,0) -> 0 | F13: =D13-E13 -> 0 | G13: =E13+F13 -> 0 | H13: =F13 -> 0
C14: 0 | D14: =IF((B14+C14)>0,B14+C14,0) -> 0 | F14: =D14-E14 -> 0 | G14: =E14+F14 -> 0
A16: Total Reserve per G/L | B16: =SUM(B7:B15) -> 0 | C16: =SUM(C7:C15) -> 0 | D16: =SUM(D7:D15) -> 0 | E16: =SUM(E7:E15) -> 0 | F16: =SUM(F7:F15) -> 0 | G16: =SUM(G7:G15) -> 0 | H16: =SUM(H7:H15) -> 0

Sheet 12530
A1: ='Review Comments'!B11 -> GREENFIELD GATEWAY
A2: LOAN DEPOSIT - 12530
A3: ='Review Comments'!B13 -> FOR THE MONTH ENDED 07/31/2026
A9: Origination Date | C9: Description | E9: Amount | F9: Total Amount
A11: 45808 | C11: YTD Balance Transfer from Eagle Comm | F11: -200000
A12: 45808 | C12: YTD Balance Transfer from Eagle Comm | F12: -8709920
C15: Account Total: | F15: =SUM(F11:F14) -> -8909920
E17: 12530-000000 | F17: {=IFERROR(INDEX(TB!G:G,MATCH(E17,TB!A:A,0),0),0)} -> -8909920
E18: S/B ZERO | F18: =F15-F17 -> 0

Sheet 13000-
A1: ='Review Comments'!B11 -> GREENFIELD GATEWAY
A2: SUSPENSE-13000
A3: FOR THE ONE MONTH ENDED 01/31/17
B7: Date | C7: Tenant | D7: Description | F7: Amount | G7: Comment
D11: Account Total per Cash | F11: =SUM(F9:F10) -> 0

Sheet 13000
A1: ='Review Comments'!B11 -> GREENFIELD GATEWAY
A2: SUSPENSE - 13000
A3: ='Review Comments'!B13 -> FOR THE MONTH ENDED 07/31/2026
A7: Date | C7: Tenant | D7: Vendor | F7: Amount | H7: Description
A9: 46079 | C9: BRIGHT NOW | D9: WHITEHILL LAW OFFICES P.C. | F9: 875.4 | H9: 872 2/12/2026 LEGAL - BRIGHTNOW. Ask Hari to process TBB on 3/9/26 | J9: =PROPER(I9)
D11: TOTAL Per Accural | F11: =SUM(F8:F10) -> 875.4
D13: 13000-000000 | F13: {=IFERROR(INDEX(TB!G:G,MATCH(D13,TB!A:A,0),0),0)} -> 875.4
D14: S/B ZERO | F14: =F11-F13 -> 0

Sheet 13100
A1: ='Review Comments'!B11 -> GREENFIELD GATEWAY
A2: MISC DEPOSIT-13100
A3: ='Review Comments'!B13 -> FOR THE MONTH ENDED 07/31/2026
A9: Date | C9: Vendor | D9: Description | F9: Amount | G9: Comment
A11: 45808 | F11: 14125 | G11: TRFR FR EAGLE COMM
A12: 46203 | C12: SRP | D12: A06172602 6/17/2026 DEPOSIT 50104 | F12: 200
A13: 46203 | C13: SRP | D13: A06172603 6/17/2026 DEPOSIT 69000 | F13: 660
D16: Account Total | F16: =SUM(F11:F15) -> 14985
C18: 13100-000000 | D18: Per TB | F18: {=IFERROR(INDEX(TB!G:G,MATCH(C18,TB!A:A,0),0),0)} -> 14985
D19: S/B zero | F19: =F16-F18 -> 0

Sheet 13130
A1: ='Review Comments'!B11 -> GREENFIELD GATEWAY
A2: PREPAID EXPENSE-13130
A3: ='Review Comments'!B13 -> FOR THE MONTH ENDED 07/31/2026
A9: Date | C9: Vendor | D9: Description | F9: Amount | G9: Comment
A11: 44104 | C11: Mission Landscape Companies, Inc | D11: 10/20 Landscape Maintenance | F11: 0
D14: Account Total | F14: =SUM(F11:F13) -> 0
A16: 44439 | C16: American Alarm Systems Inc | D16: 0921-1121 Fire Monitoring-Phase I
A17: 44439 | C17: American Alarm Systems Inc | D17: 0921-1121 Fire Monitoring-Phase II
D19: Account Total | F19: =SUM(F14:F18) -> 0

Sheet 13130A
A1: ='Review Comments'!B11 -> GREENFIELD GATEWAY
A2: PREPAID EXPENSES - 13130-000000
A3: ='Review Comments'!B13 -> FOR THE MONTH ENDED 07/31/2026
A9: Date | C9: Vendor | D9: Description | F9: Amount | G9: Comment
D15: Account Total | F15: =SUM(F11:F14) -> 0

Sheet 15010
A1: ='Review Comments'!B11 -> GREENFIELD GATEWAY
A2: Building Improvement - 15010
A3: ='Review Comments'!B13 -> FOR THE MONTH ENDED 07/31/2026
A9: Date | C9: Vendor | D9: Description | F9: Amount | G9: Comment
A11: 46141 | C11: TEMP CONTROL INC | D11: 882 4/9/2026 HVAC RPL - TAILGATE | F11: 26000
D13: Account Total | F13: =SUM(F11:F12) -> 26000
D15: 15010-000000 | F15: {=IFERROR(INDEX(TB!G:G,MATCH(D15,TB!A:A,0),0),0)} -> 26000
D16: S/B ZERO | F16: =F15-F13 -> 0

Sheet 15100
A1: ='Review Comments'!B11 -> GREENFIELD GATEWAY
A2: TENANT IMPROVEMENT - 15100
A3: ='Review Comments'!B13 -> FOR THE MONTH ENDED 07/31/2026
A9: Date | C9: Tenant | D9: Description | F9: Amount | G9: Comment
A11: 45900 | C11: DISCOUNT NUTRITION LLC | D11: RCLS 825 HVAC INSTALL | F11: 12800 | G11: TEMP CONTROL INC
A12: 45930 | C12: DISCOUNT NUTRITION LLC | D12: RCLS 828 CMF HVAC INSTALL | F12: 640 | G12: ATHENA MGM T INC
A13: 46022 | C13: CROSSFIT | D13: RCLS 837 HVAC RPLCE CROSSFIT FR 70390 | F13: 12800 | G13: TEMP CONTROL INC
A14: 46022 | C14: CROSSFIT | D14: RCLS 853 CMF CROSSFIT HVAC FR 70352 | F14: 640 | G14: ATHENA MGM T INC
D16: Account Total | F16: =SUM(F11:F15) -> 26880
D18: 15100-000000 | F18: {=IFERROR(INDEX(TB!G:G,MATCH('15100'!D18,TB!A:A,0),0),0)} -> 26880
D19: S/B ZERO | F19: =F18-F16 -> 0

Sheet 16500
A1: ='Review Comments'!B11 -> GREENFIELD GATEWAY
A2: LEASE COMMISSION - 16500
A3: ='Review Comments'!B13 -> FOR THE MONTH ENDED 07/31/2026
A9: Date | C9: Tenant | D9: Term | E9: Vendor | F9: Amount | G9: Comment
A11: 45808 | C11: n/a | D11: n/a | E11: n/a | F11: 9504.65 | G11: YTD 0525 Balance Transfer from Eagle Comm
A12: 46170 | C12: TAILGATE BAR | D12: 03/06/2026 - 03/31/2037 | E12: VELOCITY RETAIL GROUP LLC | F12: 26194.58 | G12: 892 5/14/2026 LC 1/2 TAILGATE BAR
A13: 46233 | C13: TAILGATE BAR | D13: 03/06/2026 - 03/31/2037 | E13: VELOCITY RETAIL GROUP LLC | F13: 26194.58 | G13: 911 7/23/2026 LC 2/2 TAILGATE BAR
D15: Account Total | F15: =SUM(F11:F14) -> 61893.81
E17: 16500-000000 | F17: {=IFERROR(INDEX(TB!G:G,MATCH(E17,TB!A:A,0),0),0)} -> 61893.81
E18: S/B ZERO | F18: =F15-F17 -> 0

Sheet 17100
A1: ='Review Comments'!B11 -> GREENFIELD GATEWAY
A2: CLOSING COSTS - 17100
A3: ='Review Comments'!B13 -> FOR THE MONTH ENDED 07/31/2026
A9: Origination Date | C9: Description | E9: Amount | F9: Total Amount
C11: Beginning Balance | E11: 1130.89 | F11: =E11 -> 1130.89
C15: Account Total: | F15: =SUM(F11:F14) -> 1130.89
E17: 17100-000000 | F17: {=IFERROR(INDEX(TB!G:G,MATCH(E17,TB!A:A,0),0),0)} -> 1130.89
E18: S/B ZERO | F18: =F15-F17 -> 0

Sheet Fixed Asset
A1: ='Review Comments'!B11 -> GREENFIELD GATEWAY
A2: FIXED ASSETS SCHEDULE
A3: ='Review Comments'!B13 -> FOR THE MONTH ENDED 07/31/2026
A9: Origination Date | C9: Account Number | D9: Description | F9: Amount
C11: 15010-000000 | D11: Building Improvements
A12: 46141 | D12: HVAC Repalced-TailGate | F12: 26000
A14: 45808 | C14: 17100-000000 | D14: Closing Cost | F14: 2130.89
A15: 45901 | D15: Past Due Paid Adj 0825 Mortgage Payment | F15: -1000
F16: =SUM(F14:F15) -> 1130.89
D21: 15010-000000 | F21: {=IFERROR(INDEX(TB!G:G,MATCH(D21,TB!A:A,0),0),0)} -> 26000
D22: S/B ZERO | F22: =F21-F12 -> 0
D24: 17100-000000 | F24: {=IFERROR(INDEX(TB!G:G,MATCH(D24,TB!A:A,0),0),0)} -> 1130.89
D25: S/B ZERO | F25: =F24-F16 -> 0

Sheet 15410
A1: ='Review Comments'!B11 -> GREENFIELD GATEWAY
A2: DEFERRED GAIN-LAND-HOFER INVt - 15410
A3: ='Review Comments'!B13 -> FOR THE MONTH ENDED 07/31/2026
A7: Date | C7: Description | E7: Amount | F7: Comment
C13: Account Total | E13: =SUM(E9:E12) -> 0
A16: 15410-000000 | C16: Per TB | E16: {=IFERROR(INDEX(#REF!,MATCH(15410,#REF!,0),0),0)} -> 0
C17: S/B zero | E17: =E13-E16 -> 0

Sheet 20110
A1: ='Review Comments'!B11 -> GREENFIELD GATEWAY
A2: A/P Other- 20110
A3: ='Review Comments'!B13 -> FOR THE MONTH ENDED 07/31/2026
A9: Origination Date | B9: Description | D9: Total Amount
B17: Account Total: | D17: =SUM(D11:D15) -> 0

Sheet 20610
A1: ='Review Comments'!B11 -> GREENFIELD GATEWAY
A2: TIA PAYABLE- 20610
A3: ='Review Comments'!B13 -> FOR THE MONTH ENDED 07/31/2026
A6: Origination Date | C6: Description | E6: Total Amount
A8: 45547 | C8: Beginning Balance - Property Acquistion | E8: -254600
A9: 45695 | C9: Outstanding TI 34131 PAD SALE | E9: 66600
C13: Account Total:

Sheet 20620
A1: ='Review Comments'!B11 -> GREENFIELD GATEWAY
A2: LEASE COMMISSION PAYABLE- 20620
A3: ='Review Comments'!B13 -> FOR THE MONTH ENDED 07/31/2026
A7: Origination Date | C7: Description | E7: Total Amount
C11: Account Total: | E11: =SUM(E9:E10) -> 0
C13: 20620-000000 | E13: {=IFERROR(INDEX(TB!G:G,MATCH(C13,TB!A:A,0),0),0)} -> 0
C14: S/B zero | E14: =E11-E13 -> 0
C19: Dutch Bros | E19: 30000
C20: Coachella Valley Optometry | E20: 11345.79
C21: Western Wear | E21: 9181.88
C22: H&R Block | E22: 9455.49
E25: =SUM(E19:E24) -> 59983.16

Sheet 20650
A1: CATHEDRAL CITY
A2: EXPENSE ACCRUALS - 20650
A3: ='Review Comments'!B13 -> FOR THE MONTH ENDED 07/31/2026
A7: Account Number | B7: Period | C7: Vendor | D7: Description | F7: Amount
F26: =SUM(F9:F24) -> 0

Sheet 20660
A1: ='Review Comments'!B11 -> GREENFIELD GATEWAY
A2: ACCRUED INTEREST EXPENSE- 20660
A3: ='Review Comments'!B13 -> FOR THE MONTH ENDED 07/31/2026
A9: Origination Date | C9: Description | E9: Total Amount
C15: Account Total: | E15: =SUM(E11:E14) -> 0

Sheet 20800
A1: ='Review Comments'!B11 -> GREENFIELD GATEWAY
A2: TENANT SECURITY DEPOSIT- 20800
A3: ='Review Comments'!B13 -> FOR THE MONTH ENDED 07/31/2026
A6: Origination Date | C6: Description | E6: Total Amount
C13: Account Total: | E13: =SUM(E8:E12) -> 0

Sheet 25300
A1: ='Review Comments'!B11 -> GREENFIELD GATEWAY
A2: NOTE PAYABLE - 25300
A3: ='Review Comments'!B13 -> FOR THE MONTH ENDED 07/31/2026
A9: Origination Date | C9: Description | E9: Amount | F9: Comment
A11: 45808 | C11: YTD Balance Transfer from Eagle Comm | E11: -9772721.7
A12: 45808 | C12: True Up Loan Balance | E12: 1139.55
A13: 45809 | C13: Mortgage Payment | E13: 18466.12
A14: 45839 | C14: Mortgage Payment | E14: 19601.94
A15: 45873 | C15: Mortgage Payment | E15: 18595.94
A16: 45901 | C16: Mortgage Payment | E16: 18659.35
A17: 45933 | C17: Mortgage Payment | E17: 19789.57
A18: 45964 | C18: Mortgage Payment | E18: 18790.46
A19: 45994 | C19: Mortgage Payment | E19: 19916.88
A20: 46027 | C20: Mortgage Payment | E20: 18922.45
A21: 46056 | C21: Mortgage Payment | E21: 18986.98
A22: 46084 | C22: Mortgage Payment | E22: 22219.67
... A26: 46209 | C26: Mortgage Payment | E26: 20374.52
C28: Account Total | E28: =SUM(E11:E27) -> -9498624.9
C31: 25300-000000 | E31: {=IFERROR(INDEX(TB!G:G,MATCH(C31,TB!A:A,0),0),0)} -> -9498624.9
C32: S/B ZERO | E32: =E28-E31 -> 0

Sheet 25700
A1: ='Review Comments'!B11 -> GREENFIELD GATEWAY
A2: NOTE PAYABLE JHREOP - 25700
A3: ='Review Comments'!B13 -> FOR THE MONTH ENDED 07/31/2026
A9: Origination Date | C9: Description | E9: Amount | F9: Comment
A11: 43676 | C11: Beginning Balance: | E11: 70000 | F11: Lender Deposit/ Temp Loan
A12: 25700 | E12: -70000
C15: Account Total | E15: =SUM(E11:E14) -> 0

Sheet Equity
A1: ='Review Comments'!B11 -> GREENFIELD GATEWAY
A2: EQUITY-30100
A3: ='Review Comments'!B13 -> FOR THE MONTH ENDED 07/31/2026
A9: Date | C9: Description | E9: Amount
A11: 43228 | C11: Property Acquisition
A12: 43228 | C12: Property Acquisition
A13: 43228 | C13: Refund JHREOP Loan for Escrow Deposit
C15: Account Total: | E15: =SUM(E11:E14) -> 0

Sheet 26430
A1: ='Review Comments'!B11 -> GREENFIELD GATEWAY
A2: ESCROW- TI/LC FUNDS - 26430
A3: ='Review Comments'!B13 -> FOR THE MONTH ENDED 07/31/2026
A6: Origination Date | C6: Description | E6: Total Amount
C9: Account Total: | E9: =SUM(E8:E8) -> 0

Sheet 26440
A1: ='Review Comments'!B11 -> GREENFIELD GATEWAY
A2: ESCROW- INTEREST HOLDBACK- 26440
A3: ='Review Comments'!B13 -> FOR THE MONTH ENDED 07/31/2026
A9: Origination Date | C9: Description | E9: Total Amount
C13: Account Total: | E13: =SUM(E11:E12) -> 0

Sheet 26450
A1: ='Review Comments'!B11 -> GREENFIELD GATEWAY
A2: CAPITAL EXP HOLDBACK-26450
A3: ='Review Comments'!B13 -> FOR THE MONTH ENDED 07/31/2026
A9: Origination Date | C9: Description | E9: Amount | F9: Total Amount
C15: Account Total: | F15: =SUM(F11:F14) -> 0

Sheet 35000
A1: ='Review Comments'!B11 -> GREENFIELD GATEWAY
A2: OWNER'S DISTRIBUTION - 35000
A3: ='Review Comments'!B13 -> FOR THE MONTH ENDED 07/31/2026
A6: Date | C6: Account Number | D6: Description | E6: Amount
A7: 45808 | D7: YTD Balance Transfer from Eagle Comm | E7: 1470677.4
A8: 45946 | D8: Owner's Distribution | E8: 50000
A9: 45978 | D9: Owner's Distribution | E9: 50000
A10: 46008 | D10: Owner's Distribution | E10: 75000
A11: 46038 | D11: Owner's Distribution | E11: 50000
A12: 46071 | D12: Owner's Distribution | E12: 50000
A13: 46098 | D13: Owner's Distribution | E13: 50000
A14: 46128 | D14: Owner's Distribution | E14: 50000
A15: 46160 | D15: Owner's Distribution | E15: 50000
A16: 46190 | D16: Owner's Distribution | E16: 40000
A17: 46219 | D17: Owner's Distribution | E17: 15000
D19: Account Total: | E19: =SUM(E7:E17) -> 1950677.4
D22: 35000-000000 | E22: {=IFERROR(INDEX(TB!G:G,MATCH(D22,TB!A:A,0),0),0)} -> 1950677.4
D23: S/B zero | E23: =E19-E22 -> 0

Sheet Insurance.
A1: ='Review Comments'!B11 -> GREENFIELD GATEWAY
A2: PREPAID INS- 13110 / ACCRUED INSURANCE- 20500
A3: ='Review Comments'!B13 -> FOR THE MONTH ENDED 07/31/2026
A6: Period | B6: Property Insurance Paid 50111 | C6: Liability Insurance Paid 50112 | D6: Umbrella Insurance Paid 50130 | E6: Total Insurance Paid | F6: Accrued Insurance 20500 | G6: Prepaid Insurance 13110 | H6: YTD Balance 50111 | I6: YTD Balance 50112 | J6: Accumulated Insurance Exp. | K6: Months Remaining | M6: Accumulated R.E. Tax Expense | N6: General Ledger Balance
H7: =B7 -> 0 | I7: =C7 -> 0
A8: 42035 | H8: =H7+B8 -> 0 | I8: =I7+C8 -> 0 | M8: =I8*3 -> 0 | N8: =SUM(M8) -> 0
A9: 42063 | H9: =H8+B9 -> 0 | I9: =I8+C9 -> 0
A10: 42094 | H10: =H9+B10 -> 0 | I10: =I9+C10 -> 0
A11: 42124 | H11: =H10+B11 -> 0 | I11: =I10+C11 -> 0
A12: 42155
A13: 42185 | G13: 16895
A14: 42216 | B14: 2626.85 | C14: 1204.12 | D14: 973.92 | E14: =SUM(B14:D14) -> 4804.89 | G14: =-E14 -> -4804.89
A15: 42247
A16: 42277
A17: 42308
A18: 42338
A19: 42369
B26: =SUM(B7:B25) -> 2626.85 | C26: =SUM(C7:C25) -> 1204.12 | D26: =SUM(D7:D25) -> 973.92 | E26: =SUM(E7:E25) -> 4804.89 | F26: =SUM(F7:F25) -> 0 | G26: =SUM(G9:G24) -> 12090.11 | H26: =H11 -> 0 | I26: =I11 -> 0 | J26: =SUM(J7:J25) -> 0 | K26: =SUM(K7:K25) -> 0 | L26: =SUM(L7:L25) -> 0 | M26: =SUM(M7:M25) -> 0 | N26: =SUM(N7:N25) -> 0
A29: Effective Feb 24, 2015 to Dec 31, 2015
A30: 2014-2015 Property Premium | C30: 26353.26 | D30: =C30/311 -> 84.73717 | E30: =D30*31 -> 2626.8523
A31: 2014-2015 Liability Premium | C31: 12080.09 | D31: =C31/311 -> 38.842733 | E31: =D31*31 -> 1204.1247
A32: 2014-2015 Umbrella Premium | C32: 9770.65 | D32: =C32/311 -> 31.416881 | E32: =D32*31 -> 973.92331
C33: =SUM(C30:C32) -> 48204 | D33: =C33/311 -> 154.99678 | E33: =D33*31 -> 4804.9003
A36: 5
A37: 31
A38: 30
A39: 31
A40: 30
A41: 31
A42: 31
A43: 30 | D43: 42369 | E43: 42060
A44: 31 | E44: =+D43-E43 -> 309
A45: 30
A46: 31
A47: =SUM(A36:A46) -> 311

Sheet INS PH 2 
A1: ='Review Comments'!B11 -> GREENFIELD GATEWAY
A2: INSURANCE SCHEDULE
A3: FOR THE ONE MONTH ENDED 01/31/17
B5: Policy Period
C6: Annual Premium | D6: Monthly
B7: Property Ins. PH2 | C7: =17208.93+942.92 -> 18151.85 | D7: =C7/12 -> 1512.6542
B8: Liability Ins. PH2 | C8: 4305.53 | D8: =C8/12 -> 358.79417
B9: Umbrella Ins. PH2 | C9: 3646.94 | D9: =C9/12 -> 303.91167
B10: Total | C10: =SUM(C7:C9) -> 26104.32 | D10: =SUM(D7:D9) -> 2175.36
C13: Property Insurance Paid | D13: Liability Insurance Paid | E13: Umbrella Insurance- Paid | F13: Environmental Insurance Paid | G13: Total Expense | H13: Accrual Balance | I13: Prepaid Insurance
B14: Month | C14: 60111 | D14: 60112 | E14: 60131 | F14: 60145 | H14: 20500 | I14: 13110
B17: 42736 | C17: =D7 -> 1512.6542 | D17: =D8 -> 358.79417 | E17: =D9 -> 303.91167 | G17: =SUM(C17:F17) -> 2175.36
B18: =+B17+31 -> 42767 | G18: =SUM(C18:F18) -> 0
B19: =+B18+31 -> 42798 | G19: =SUM(C19:F19) -> 0
B20: =+B19+31 -> 42829 | G20: =SUM(C20:F20) -> 0
B21: =+B20+31 -> 42860 | G21: =SUM(C21:F21) -> 0
B22: =+B21+31 -> 42891 | G22: =SUM(C22:F22) -> 0
B23: =+B22+31-2 -> 42920 | G23: =SUM(C23:F23) -> 0
B24: =+B23+31 -> 42951 | G24: =SUM(C24:F24) -> 0
B25: =+B24+31 -> 42982 | G25: =SUM(C25:F25) -> 0
B26: =+B25+31 -> 43013 | G26: =SUM(C26:F26) -> 0
B27: =+B26+31 -> 43044
B28: =+B27+31 -> 43075
B30: YTD Total | C30: =SUM(C17:C29) -> 1512.6542 | D30: =SUM(D17:D29) -> 358.79417 | E30: =SUM(E17:E29) -> 303.91167 | G30: =SUM(G17:G29) -> 2175.36 | H30: =SUM(H17:H22) -> 0 | I30: =SUM(I16:I29) -> 0

Sheet Note
A3: ACCOUNTS REC | B3: 173537.29
A5: PREPAID RENT | B5: -51119.2
B8: =SUM(B3:B5) -> 122418.09
A11: Aged | B11: 122418.09

Sheet Variance
A1: Acc# | B1: Account Name | C1: Actual | D1: Budget | E1: Variance | G1: Variance Explaination
A3: 40100 | B3: Base Rent | C3: 105632.61 | D3: 107484 | E3: =C3-D3 -> -1851.39 | G3: Variance is due to Pagoda Inn Rent Credit fr 07/12-12/12 in the amount of $308.55 per month.

Sheet Sheet2

Sheet Tax PH2
A1: ='Review Comments'!B11 -> GREENFIELD GATEWAY
A2: PROPERTY TAX SCHEDULE
A3: FOR THE ONE MONTH ENDED 01/31/17
B12: Month | C12: Property Tax | D12: Property Tax | E12: Supplemental Prop Tax | F12: Total Expense | G12: Prepaid | H12: Accrual
C13: 54000 | D13: Payment/ Credit | E13: 54000 | F13: 54000 | G13: 13120 | H13: 20200
B15: 42736 | F15: =C15 -> 0 | H15: =-F15 -> 0
B16: =+B15+31 -> 42767
B17: =+B16+31 -> 42798
B18: =+B17+31 -> 42829
B19: =+B18+31 -> 42860
B20: =+B19+31 -> 42891
B21: =+B20+31 -> 42922
B22: =+B21+31 -> 42953
B23: =+B22+31 -> 42984
B24: =+B23+31 -> 43015
B25: =+B24+31 -> 43046
B26: =+B25+31 -> 43077
B29: YTD Total | C29: =SUM(C15:C28)-0.03 -> -0.03 | D29: =D18 -> 0 | E29: =E15 -> 0 | F29: =SUM(F15:F28)-0.03 -> -0.03 | G29: =G20 -> 0 | H29: =H15 -> 0
B32: Parcel# | C32: 2015-2016 Actual | D32: Per Month
B33: 957330046-5 | D33: =C33/12 -> 0
B34: 957330047-6 | D34: =C34/12 -> 0
B35: 957330048-7 | D35: =C35/12 -> 0
B36: 957330049-8 | D36: =C36/12 -> 0
B38: Total | C38: =SUM(C33:C37) -> 0 | D38: =SUM(D32:D36) -> 0 | E38: =C38/12 -> 0
C41: =C38/2 -> 0

Sheet 36000
A1: ='Review Comments'!B11 -> GREENFIELD GATEWAY
A2: OWNER'S CONTRIBUTION - 36000
A3: ='Review Comments'!B13 -> FOR THE MONTH ENDED 07/31/2026
A9: Date | C9: Account Number | D9: Description | E9: Amount
A11: 45808 | C11: Beginning Balance - Property Acquistion | D11: YTD Balance Transfer from Eagle Comm | E11: -140153.04
A12: 45819 | D12: Owners Contribution | E12: -25000
A13: 45916 | D13: Owners Contribution | E13: 200000
A14: 45961 | D14: 09/29/25-09/29/26 UMBRELLA INS- IOA | E14: -3483
D16: Account Total: | E16: =SUM(E11:E15) -> 31363.96
D18: 36000-000000 | E18: {=IFERROR(INDEX(TB!G:G,MATCH(D18,TB!A:A,0),0),0)} -> 31363.96
D19: S/B ZERO | E19: =E16-E18 -> 0

Sheet Tax 
A1: ='Review Comments'!B11 -> GREENFIELD GATEWAY
A2: PROPERTY TAX SCHEDULE
A3: ='Review Comments'!B13 -> FOR THE MONTH ENDED 07/31/2026
B7: Month | C7: Property Tax | D7: Total Expense | E7: Property Tax
C8: 54000-000000 | D8: 54000-000000 | E8: Payment/ Credit
B10: 46048 | C10: 0 | D10: 0 | E10: 0
B15: YTD Total | C15: =SUM(C10:C14) -> 0 | D15: =SUM(D10:D14) -> 0
B16: TB TOTAL | C16: {=IFERROR(INDEX(TB!G:G,MATCH('Tax '!C8,TB!A:A,0),0),0)} -> 71531.07 | D16: {=IFERROR(INDEX(TB!G:G,MATCH('Tax '!D8,TB!A:A,0),0),0)} -> 71531.07
B17: S/B ZERO | C17: =C15-C16 -> -71531.07 | D17: =D15-D16 -> -71531.07

Sheet Insurance
A1: ='Review Comments'!B11 -> GREENFIELD GATEWAY
A2: INSURANCE SCHEDULE
A3: ='Review Comments'!B13 -> FOR THE MONTH ENDED 07/31/2026
C6: Annual Premium | D6: Monthly | H6: Cover Period
B7: Property Ins | C7: 51116.27 | D7: =(C7*0.63390428)/8.8159-0.01 -> 3675.4879 | H7: 01/01/19-12/31/19
B8: Liability Ins | C8: 51116.27 | D8: =(C8*0.21213499)/8.8159 -> 1229.9991 | H8: 01/01/19-12/31/19
B9: Umbrella Ins | C9: 51116.27 | D9: =(C9*0.15396073)/8.8159+0.01 -> 892.70368 | H9: 01/01/19-12/31/19
B10: Total | D10: =SUM(D7:D9) -> 5798.1908
C13: Property Insurance | D13: Liability Insurance | E13: Flood Insurance | F13: Total Expense
B14: Month | C14: 50111-000000 | D14: 50112-000000 | E14: 50140
B24: YTD Total | C24: =SUM(C18:C22) -> 0 | D24: =SUM(D18:D22) -> 0 | E24: =SUM(E18:E22) -> 0 | F24: =SUM(F18:F22) -> 0

Sheet CR VAR
A2: IS | B2: Cash | C2: PER I/S | D2: PER R/L | E2: VARIANCE | F2: VARIANCE EXPLANATION
A3: 40100-000000 - BASE RENTAL INCOME | B3: BAS BASE RENT | C3: {=IFERROR(INDEX(IS!B:B,MATCH(A3,IS!A:A,0),0),0)} -> 98684.9 | D3: {=IFERROR(INDEX('CM '!G:G,MATCH('CR VAR'!B3,'CM '!A:A,0),0),0)} -> 98684.9 | E3: =D3-C3 -> 0
A4: 40140-000000 - COMMON AREA INCOME | B4: CAM COMMON AREA MAINT | C4: {=IFERROR(INDEX(IS!B:B,MATCH(A4,IS!A:A,0),0),0)} -> 8803.92 | D4: {=IFERROR(INDEX('CM '!G:G,MATCH('CR VAR'!B4,'CM '!A:A,0),0),0)} -> 8803.92 | E4: =D4-C4 -> 0
A5: 40230-000000 - INSURANCE INCOME | B5: INS INSURANCE-CAM | C5: {=IFERROR(INDEX(IS!B:B,MATCH(A5,IS!A:A,0),0),0)} -> 2403.49 | D5: {=IFERROR(INDEX('CM '!G:G,MATCH('CR VAR'!B5,'CM '!A:A,0),0),0)} -> 2403.49 | E5: =D5-C5 -> 0
A6: 40240-000000 - PROPERTY TAX INCOME | B6: RET REAL ESTATE TAX | C6: {=IFERROR(INDEX(IS!B:B,MATCH(A6,IS!A:A,0),0),0)} -> 10866.09 | D6: {=IFERROR(INDEX('CM '!G:G,MATCH('CR VAR'!B6,'CM '!A:A,0),0),0)} -> 10866.09 | E6: =D6-C6 -> 0
A7: 40250-000000 - MISCELLANEOUS INCOME | B7: MIS MISCELLANEOUS INCOME | C7: {=IFERROR(INDEX(IS!B:B,MATCH(A7,IS!A:A,0),0),0)} -> 0 | D7: {=IFERROR(INDEX('CM '!G:G,MATCH('CR VAR'!B7,'CM '!A:A,0),0),0)} -> 0 | E7: =D7-C7 -> 0
A8: 40390-000000 - ADMINISTRATIVE FEE INCOME | B8: ADM ADMINISTRATIVE FEES | C8: {=IFERROR(INDEX(IS!B:B,MATCH(A8,IS!A:A,0),0),0)} -> 170.67 | D8: {=IFERROR(INDEX('CM '!G:G,MATCH('CR VAR'!B8,'CM '!A:A,0),0),0)} -> 170.67 | E8: =D8-C8 -> 0
A9: 40500-000000 - SIGNAGE INCOME | B9: SGN PYLON SIGN | C9: {=IFERROR(INDEX(IS!B:B,MATCH(A9,IS!A:A,0),0),0)} -> 4070.83 | D9: {=IFERROR(INDEX('CM '!G:G,MATCH('CR VAR'!B9,'CM '!A:A,0),0),0)} -> 4070.83 | E9: =D9-C9 -> 0
A10: 40600-000000 - LATE CHARGE | B10: LAT LATE CHARGES | C10: {=IFERROR(INDEX(IS!B:B,MATCH(A10,IS!A:A,0),0),0)} -> 0 | D10: {=IFERROR(INDEX('CM '!G:G,MATCH('CR VAR'!B10,'CM '!A:A,0),0),0)} -> 0 | E10: =D10-C10 -> 0
A11: 40610-000000 - CAM UTILITY REIMBURSEMENT | B11: ELC UTILITY ELECTRIC | C11: {=IFERROR(INDEX(IS!B:B,MATCH(A11,IS!A:A,0),0),0)} -> 0 | D11: {=IFERROR(INDEX('CM '!G:G,MATCH('CR VAR'!B11,'CM '!A:A,0),0),0)} -> 0 | E11: =D11-C11 -> 0
A12: 41000-000000 - SETTLEMENT/TERMINATION INCOME | B12: STM SETTLEMENT/TERMINATION | C12: {=IFERROR(INDEX(IS!B:B,MATCH(A12,IS!A:A,0),0),0)} -> 0 | D12: {=IFERROR(INDEX('CM '!G:G,MATCH('CR VAR'!B12,'CM '!A:A,0),0),0)} -> 0 | E12: =D12-C12 -> 0
A13: 41200-000000 - GENERAL EXCISE TAX COLLECTED | B13: GET GENERAL EXCISE TAX | C13: {=IFERROR(INDEX(IS!B:B,MATCH(A13,IS!A:A,0),0),0)} -> 0 | D13: {=IFERROR(INDEX('CM '!G:G,MATCH('CR VAR'!B13,'CM '!A:A,0),0),0)} -> 0 | E13: =D13-C13 -> 0
A14: 41300-000000 - SALES TAX COLLECTIONS | B14: STX SALES TAX | C14: {=IFERROR(INDEX(IS!B:B,MATCH(A14,IS!A:A,0),0),0)} -> 3219.42 | D14: {=IFERROR(INDEX('CM '!G:G,MATCH('CR VAR'!B14,'CM '!A:A,0),0),0)} -> 3219.42 | E14: =D14-C14 -> 0
A15: 40150-000000 - PRIOR YEAR CAM | B15: PYC PRIOR YEAR CAM | C15: {=IFERROR(INDEX(IS!B:B,MATCH(A15,IS!A:A,0),0),0)} -> 1530.38 | D15: {=IFERROR(INDEX('CM '!G:G,MATCH('CR VAR'!B15,'CM '!A:A,0),0),0)} -> 1530.38 | E15: =D15-C15 -> 0
B16: IUE UTILITY | C16: {=IFERROR(INDEX(IS!B:B,MATCH(A16,IS!A:A,0),0),0)} -> 0 | D16: {=IFERROR(INDEX('CM '!G:G,MATCH('CR VAR'!B16,'CM '!A:A,0),0),0)} -> 0 | E16: =D16-C16 -> 0
A17: 40220-000000 - RENT CONCESSIONS | B17: ABA RENT CONCESSIONS | C17: {=IFERROR(INDEX(IS!B:B,MATCH(A17,IS!A:A,0),0),0)} -> 0 | D17: {=IFERROR(INDEX('CM '!G:G,MATCH('CR VAR'!B17,'CM '!A:A,0),0),0)} -> 0
B18: PPR PREPAID RENT | C18: {=IFERROR(INDEX(IS!B:B,MATCH(A18,IS!A:A,0),0),0)} -> 0 | D18: {=IFERROR(INDEX('CM '!G:G,MATCH('CR VAR'!B18,'CM '!A:A,0),0),0)} -> 0 | E18: =D18-C18 -> 0
A19: 40170-000000 - OTHER RECOVERIES | B19: NCA OTHER RECOVERIES | C19: {=IFERROR(INDEX(IS!B:B,MATCH(A19,IS!A:A,0),0),0)} -> 2444.78 | D19: {=IFERROR(INDEX('CM '!G:G,MATCH('CR VAR'!B19,'CM '!A:A,0),0),0)} -> 2444.78 | E19: =D19-C19 -> 0
C22: =SUM(C3:C21) -> 132194.48 | D22: =SUM(D3:D21) -> 132194.48 | E22: =SUM(E3:E21) -> 0
B23: Per Report | C23: =IS!B24 -> 132194.48 | D23: ='CM '!G15 -> 132194.48
C24: =+C22-C23 -> 0 | D24: =+D22-D23 -> 0

Sheet IS
A1: Database: ATHENA | B1: Comparative Income Statement | H1: Page: | I1: 1
A2: ENTITY: 801 | B2: MONTHLY OPERATING STATEMENTS | H2: Date: | I2: 46247.668
B3: Athena Property Management | H3: Time: | I3: 46247.668
B4: GREENFIELD GATEWAY LLC
A5: Cash
B6: Report includes an open period. Entries are not final.
B8: Current Period | G8: Year-To-Date
B9: Actual | C9: Budget | F9: Actual | G9: Budget
A10: Thru: | B10: 46234 | C10: 46234 | D10: Variance | F10: 46234 | G10: 46234 | H10: Variance
A11: RENTAL INCOME
A12: 40100-000000 - BASE RENTAL INCOME | B12: 98684.9 | C12: 112024 | D12: -13339.1 | E12: -0.1191 | F12: 695796.84 | G12: 745739 | H12: -49942.16 | I12: -0.067
A13: 40140-000000 - COMMON AREA INCOME | B13: 8803.92 | C13: 10110 | D13: -1306.08 | E13: -0.1292 | F13: 61940.57 | G13: 68406 | H13: -6465.43 | I13: -0.0945
A14: 40150-000000 - PRIOR YEAR CAM | B14: 1530.38 | C14: 0 | D14: 1530.38 | E14: 0 | F14: 11115.79 | G14: 0 | H14: 11115.79 | I14: 0
A15: 40170-000000 - OTHER RECOVERIES | B15: 2444.78 | C15: 3338 | D15: -893.22 | E15: -0.2676 | F15: 16867.64 | G15: 20408 | H15: -3540.36 | I15: -0.1735
A16: 40220-000000 - RENT CONCESSIONS | B16: 0 | C16: 0 | D16: 0 | E16: 0 | F16: -7758.06 | G16: 0 | H16: -7758.06 | I16: 0
A17: 40230-000000 - INSURANCE INCOME | B17: 2403.49 | C17: 2663 | D17: -259.51 | E17: -0.0975 | F17: 16929.57 | G17: 17933 | H17: -1003.43 | I17: -0.056
A18: 40240-000000 - PROPERTY TAX INCOME | B18: 10866.09 | C18: 12041 | D18: -1174.91 | E18: -0.0976 | F18: 77265.02 | G18: 81077 | H18: -3811.98 | I18: -0.047
A19: 40390-000000 - ADMINISTRATIVE FEE INCOME | B19: 170.67 | C19: 215 | D19: -44.33 | E19: -0.2062 | F19: 2564.41 | G19: 1241 | H19: 1323.41 | I19: 1.0664
A20: 40500-000000 - SIGNAGE INCOME | B20: 4070.83 | C20: 4586 | D20: -515.17 | E20: -0.1123 | F20: 28518.3 | G20: 32102 | H20: -3583.7 | I20: -0.1116
A21: 40610-000000 - CAM UTILITY REIMBURSEMENT | B21: 0 | C21: 0 | D21: 0 | E21: 0 | F21: 60 | G21: 0 | H21: 60 | I21: 0
A22: 41000-000000 - SETTLEMENT/TERMINATION INCOME | B22: 0 | C22: 0 | D22: 0 | E22: 0 | F22: 93000 | G22: 0 | H22: 93000 | I22: 0
A23: 41300-000000 - SALES TAX COLLECTIONS | B23: 3219.42 | C23: 3622 | D23: -402.58 | E23: -0.1111 | F23: 24231.66 | G23: 24164 | H23: 67.66 | I23: 0.0028
A24: TOTAL RENTAL INCOME | B24: 132194.48 | C24: 148599 | D24: -16404.52 | E24: -0.1104 | F24: 1020531.7 | G24: 991070 | H24: 29461.74 | I24: 0.0297
A26: OTHER INCOME
A27: 45000-000000 - INVESTMENT INTEREST | B27: 16.51 | C27: 0 | D27: 16.51 | E27: 0 | F27: 126.22 | G27: 0 | H27: 126.22 | I27: 0
A28: TOTAL OTHER INCOME | B28: 16.51 | C28: 0 | D28: 16.51 | F28: 126.22 | G28: 0 | H28: 126.22
A30: TOTAL INCOME | B30: 132210.99 | C30: 148599 | D30: -16388.01 | E30: -0.1103 | F30: 1020658 | G30: 991070 | H30: 29587.96 | I30: 0.0299
A32: COMMON AREA EXPENSES
A33: 50150-000000 - LANDSCAPE-TREE TRIMMINGS | B33: 6500 | C33: 0 | D33: -6500 | E33: 0 | F33: 6500 | G33: 0 | H33: -6500 | I33: 0
A34: 50160-000000 - LANDSCAPE-CONSUMABLES | B34: 0 | C34: 0 | D34: 0 | E34: 0 | F34: 3408.08 | G34: 1500 | H34: -1908.08 | I34: -1.2721
A35: 50170-000000 - LANDSCAPE-MAINTENANCE | B35: 2744 | C35: 1560 | D35: -1184 | E35: -0.759 | F35: 18445 | G35: 10920 | H35: -7525 | I35: -0.6891
A36: 50190-000000 - LANDSCAPE-SPRINKLER REPAIRS | B36: 0 | C36: 0 | D36: 0 | E36: 0 | F36: 150 | G36: 600 | H36: 450 | I36: 0.75
A37: 50510-000000 - PARKING- LIGHTING MAINT | B37: 165 | C37: 125 | D37: -40 | E37: -0.32 | F37: 485 | G37: 875 | H37: 390 | I37: 0.4457
A38: 50520-000000 - PARKING LOT MAINTENANCE | B38: 0 | C38: 0 | D38: 0 | E38: 0 | F38: 0 | G38: 5000 | H38: 5000 | I38: 1
A39: 50530-000000 - PARKING LOT LIGHT REPAIRS | B39: 830 | C39: 300 | D39: -530 | E39: -1.7667 | F39: 1078 | G39: 2100 | H39: 1022 | I39: 0.4867
A40: 50540-000000 - PARKING LOT REPAIRS | B40: 43420.86 | C40: 0 | D40: -43420.86 | E40: 0 | F40: 44165.74 | G40: 0 | H40: -44165.74 | I40: 0
A41: 50550-000000 - SIGN MAINTENANCE | B41: 1230 | C41: 205 | D41: -1025 | E41: -5 | F41: 1230 | G41: 1435 | H41: 205 | I41: 0.1429
A42: 51020-000000 - GENERAL MAINTENANCE | B42: 140 | C42: 300 | D42: 160 | E42: 0.5333 | F42: 1092.5 | G42: 2100 | H42: 1007.5 | I42: 0.4798
A43: 51040-000000 - JANITORIAL | B43: 1030 | C43: 875 | D43: -155 | E43: -0.1771 | F43: 6928.5 | G43: 6125 | H43: -803.5 | I43: -0.1312
A44: 51050-000000 - PEST CONTROL MAINTENANCE | B44: 198 | C44: 99 | D44: -99 | E44: -1 | F44: 693 | G44: 693 | H44: 0 | I44: 0
... A60: GROSS CASH FLOW | B60: 66343.75 | C60: 134148 | D60: -67804.25 | E60: -0.5054 | F60: 790982.34 | G60: 803469 | H60: -12486.66 | I60: -0.0155
A62: OWNER EXPENSES
A63: 70210-000000 - GENERAL REPAIRS & MAINT | B63: 985 | C63: 0 | D63: -985 | E63: 0 | F63: 11739 | G63: 0 | H63: -11739 | I63: 0
A64: 70220-000000 - LEGAL FEES | B64: 120 | C64: 0 | D64: -120 | E64: 0 | F64: 7475.11 | G64: 0 | H64: -7475.11 | I64: 0
A65: 70280-000000 - BANK CHARGES | B65: 1991.47 | C65: 2000 | D65: 8.53 | E65: 0.0043 | F65: 14609.98 | G65: 14000 | H65: -609.98 | I65: -0.0436
A66: 70320-000000 - UTILITIES EXPENSE | B66: 114.27 | C66: 0 | D66: -114.27 | E66: 0 | F66: 2243.54 | G66: 0 | H66: -2243.54 | I66: 0
A67: 70370-000000 - LICENSE & PERMIT FEES | B67: 10.24 | C67: 0 | D67: -10.24 | E67: 0 | F67: 10.24 | G67: 0 | H67: -10.24 | I67: 0
A68: 70410-000000 - CITY SALES TAX | B68: 3172.54 | C68: 3622 | D68: 449.46 | E68: 0.1241 | F68: 25229.58 | G68: 24164 | H68: -1065.58 | I68: -0.0441
A69: TOTAL OWNER EXPENSES | B69: 6393.52 | C69: 5622 | D69: -771.52 | E69: -0.1372 | F69: 61307.45 | G69: 38164 | H69: -23143.45 | I69: -0.6064
A71: NET OPERATING INCOME | B71: 59950.23 | C71: 128526 | D71: -68575.77 | E71: -0.5336 | F71: 729674.89 | G71: 765305 | H71: -35630.11 | I71: -0.0466
A73: INTEREST EXPENSE
A74: 70110-000000 - INTEREST EXPENSE | B74: 31412.7 | C74: 33450 | D74: 2037.3 | E74: 0.0609 | F74: 223373.53 | G74: 234150 | H74: 10776.47 | I74: 0.046
A75: TOTAL INTEREST EXPENSE | B75: 31412.7 | C75: 33450 | D75: 2037.3 | E75: 0.0609 | F75: 223373.53 | G75: 234150 | H75: 10776.47 | I75: 0.046
A77: INVESTING ACTIVITIES
A78: TOTAL INVESTING ACTIVITIES | B78: 0 | C78: 0 | D78: 0 | F78: 0 | G78: 0 | H78: 0
A80: NOI AFTER INT. EXPENSE | B80: 28537.53 | C80: 95076 | D80: -66538.47 | E80: -0.6998 | F80: 506301.36 | G80: 531155 | H80: -24853.64 | I80: -0.0468
A82: NET INCOME | B82: 28537.53 | C82: 95076 | D82: -66538.47 | E82: -0.6998 | F82: 506301.36 | G82: 531155 | H82: -24853.64 | I82: -0.0468
A84: CAPITAL EXPENSES
A85: 10410-000000 - ESCROW-PROPERTY TAX | B85: 12316.25 | C85: 12316 | D85: -0.25 | E85: 0 | F85: 14682.68 | G85: 14681 | H85: -1.68 | I85: -0.0001
A86: 10420-000000 - ESCROW-RESERVE ACT | B86: 580.75 | C86: 564 | D86: -16.75 | E86: -0.0297 | F86: -3429.34 | G86: 13965 | H86: 17394.34 | I86: 1.2456
A87: 10460-000000 - ESCROW-INSURANCE | B87: 2487.21 | C87: 2487 | D87: -0.21 | E87: -0.0001 | F87: 17410.47 | G87: 17409 | H87: -1.47 | I87: -0.0001
A88: 13000-000000 - SUSPENSE | B88: 0 | C88: 0 | D88: 0 | E88: 0 | F88: 875.4 | G88: 0 | H88: -875.4 | I88: 0
A89: 13100-000000 - MISCELLANEOUS DEPOSITS | B89: 0 | C89: 0 | D89: 0 | E89: 0 | F89: 860 | G89: 0 | H89: -860 | I89: 0
A90: 15010-000000 - BUILDING IMPROVEMENTS | B90: 0 | C90: 0 | D90: 0 | E90: 0 | F90: 26000 | G90: 0 | H90: -26000 | I90: 0
A91: 16500-000000 - LEASING COMMISSIONS | B91: 26194.58 | C91: 0 | D91: -26194.58 | E91: 0 | F91: 52389.16 | G91: 11831 | H91: -40558.16 | I91: -3.4281
A92: 25300-000000 - NOTES PAYABLE | B92: 20374.52 | C92: 19040 | D92: -1334.52 | E92: -0.0701 | F92: 139137.01 | G92: 133280 | H92: -5857.01 | I92: -0.0439
A93: 35000-000000 - OWNER'S DISTRIBUTION | B93: 15000 | C93: 0 | D93: -15000 | E93: 0 | F93: 305000 | G93: 0 | H93: -305000 | I93: 0
A94: TOTAL CAPITAL EXPENSES | B94: 76953.31 | C94: 34407 | D94: -42546.31 | E94: -1.2366 | F94: 552925.38 | G94: 191166 | H94: -361759.38 | I94: -1.8924
A96: NET CASH FLOW | B96: -48415.78 | C96: 60669 | D96: -109084.78 | E96: -1.798 | F96: -46624.02 | G96: 339989 | H96: -386613.02 | I96: -1.1371

Sheet CM 
A1: Grand Totals:
A2: Category | D2: Mo. Rep Charges | E2: Beg Balance | G2: Charges Cash Receipts | H2: N/C Credits | I2: Refunds | J2: End Balance | K2: Sec Dep Bal
A3: ABA RENT CONCESSIONS | D3: 0 | E3: 0 | F3: 0 | G3: 0 | H3: 1251.3 | I3: 0 | J3: -1251.3
A4: ADM ADMINISTRATIVE FEES | D4: 170.67 | E4: 2371.39 | F4: 170.67 | G4: 170.67 | H4: 0 | I4: 0 | J4: 2371.39
A5: BAS BASE RENT | D5: 113549.32 | E5: 37316.25 | F5: 106349.32 | G5: 98684.9 | H5: 0 | I5: 0 | J5: 44980.67
A6: CAM COMMON AREA MAINT | D6: 10793.3 | E6: 6061.78 | F6: 9821.7 | G6: 8803.92 | H6: 0.01 | I6: 0 | J6: 7079.55
A7: HLD HOLDOVER RENT | D7: 2687.7 | E7: 8063.1 | F7: 2687.7 | G7: 0 | H7: 0 | I7: 0 | J7: 10750.8
A8: INS INSURANCE-CAM | D8: 2663.38 | E8: 701.64 | F8: 2502.69 | G8: 2403.49 | H8: 0 | I8: 0 | J8: 800.84
A9: LAT LATE CHARGES | D9: 0 | E9: 177.33 | F9: 2.31 | G9: 0 | H9: 0 | I9: 0 | J9: 179.64
A10: NCA OTHER RECOVERIES | D10: 2845.32 | E10: 2649.06 | F10: 2845.32 | G10: 2444.78 | H10: 0 | I10: 0 | J10: 3049.6
A11: PYC PRIOR YEAR CAM | D11: 0 | E11: 10816.31 | F11: 0 | G11: 1530.38 | H11: 0 | I11: 0 | J11: 9285.93
A12: RET REAL ESTATE TAX | D12: 12041.05 | E12: 6019.23 | F12: 11314.59 | G12: 10866.09 | H12: 0 | I12: 0 | J12: 6467.73
A13: SGN PYLON SIGN | D13: 4585.83 | E13: 2067.5 | F13: 4085.83 | G13: 4070.83 | H13: 0 | I13: 0 | J13: 2082.5
A14: STX SALES TAX | D14: 3733.5 | E14: 255.35 | F14: 3494.53 | G14: 3219.42 | H14: 31.28 | I14: 0 | J14: 499.18
B15: Grand Total: | D15: 153070.07 | E15: 76498.94 | F15: 143274.66 | G15: 132194.48 | H15: 1282.59 | I15: 0 | J15: 86296.53 | K15: 49599.39

Sheet Sheet1
A2: Secrity Deposit.
A6: 34413.6
A7: -39165.1
A9: =SUM(A6:A8) -> -4751.5 | B9: differnce between the GL and security Deposit Ledger

Sheet 01.25
A2: Database: | B2: ATHENA | E2: Rent Roll | P2: Page: | Q2: 1
A3: Bldg Status: | B3: Active only | E3: CATHEDRAL CITY MARKETPLACE | P3: Date: | Q3: 45692
A4: CATHEDRAL CITY VENTURE LLC | E4: 45688 | P4: Time: | Q4: 0.47569444
F7: GLA | G7: Monthly | H7: CM LEDGER | I7: VARIANCE | J7: Annual | K7: Monthly | L7: Expense | M7: Monthly | N7: ------------------- Future Rent Increases ------------------------------------------------
A8: Bldg Id | B8: Suit Id | C8: Occupant Name | D8: Rent Start | E8: Expiration | F8: Sqft | G8: Base Rent | J8: Rate PSF | K8: Cost Recovery | L8: Stop | M8: Other Income | N8: Cat | O8: Date | P8: Monthly Amount | Q8: PSF
A10: New Leases
A12: 720 | B12: 4351-J | C12: H AND R BLOCK | D12: 45693 | E12: 47603 | F12: 1360
A14: 720 | B14: 4475-AB | C14: CATHEDRAL CITY MEGA DOLLAR | D14: 45689 | E14: 48213 | F14: 3506
A16: Vacant Suites
A18: 720 | B18: 4041-C | C18: Vacant | F18: 1705
A20: 720 | B20: 4081 | C20: Vacant | F20: 5259
A22: 720 | B22: 4151-E | C22: Vacant | F22: 1190
A24: 720 | B24: 4351-C | C24: Vacant | F24: 1950
A26: 720 | B26: 4351-J | C26: Vacant | F26: 1360
A28: 720 | B28: 4475-AB | C28: Vacant | F28: 3506
A30: 720 | B30: 4481-C | C30: Vacant | F30: 400
A32: 720 | B32: 4481-F | C32: Vacant | F32: 1200
A34: 720 | B34: 4491 | C34: Vacant | F34: 29397
A36: Occupied Suites
A38: 720 | B38: 4041-6A | C38: SUBWAY | D38: 40787 | E38: 46326 | F38: 1700 | G38: 3819.32 | H38: 3819.32 | I38: =H38-G38 -> 0 | J38: 26.96 | K38: 942.42 | N38: BAS | O38: 45962 | P38: 3934.18 | Q38: 27.77
A40: 720 | B40: 4041-B | C40: SKY NAILS AND SPA | D40: 42339 | E40: 48244 | F40: 1400 | G40: 2599.21 | H40: 2599.21 | I40: =H40-G40 -> 0 | J40: 22.28 | K40: 776.11 | N40: BAS | O40: 45689 | P40: 2677.18 | Q40: 22.95
N41: BAS | O41: 46054 | P41: 2757.5 | Q41: 23.64
N42: BAS | O42: 46419 | P42: 2840.74 | Q42: 24.35
N43: BAS | O43: 46784 | P43: 2925.96 | Q43: 25.08
N44: BAS | O44: 47150 | P44: 3013.74 | Q44: 25.83
N45: BAS | O45: 47515 | P45: 3104.15 | Q45: 26.61
N46: BAS | O46: 47880 | P46: 3197.28 | Q46: 27.41
A47: 720 | B47: 4041-D | C47: MINTY TEA HOUSE | D47: 44175 | E47: 47208 | F47: 1195 | G47: 2290.42 | H47: 2290.42 | I47: =H47-G47 -> 0 | J47: 23 | K47: 662.47 | N47: BAS | O47: 45748 | P47: 2359.13 | Q47: 23.69
N48: BAS | O48: 46113 | P48: 2429.83 | Q48: 24.4
N49: BAS | O49: 46478 | P49: 2502.53 | Q49: 25.13
N50: BAS | O50: 46844 | P50: 2578.21 | Q50: 25.89
A52: 720 | B52: 4051 | C52: DUTCH BROS COFFEE | D52: 44821 | E52: 50313 | F52: 4000 | G52: 7916.67 | H52: 7916.67 | I52: =H52-G52 -> 0 | J52: 23.75 | K52: 1273.22 | N52: BAS | O52: 46661 | P52: 8708.33 | Q52: 26.12
N53: BAS | O53: 48488 | P53: 9579.17 | Q53: 28.74
A57: Database: | B57: ATHENA | E57: Rent Roll | P57: Page: | Q57: 2
A58: Bldg Status: | B58: Active only | E58: CATHEDRAL CITY MARKETPLACE | P58: Date: | Q58: 45692
A59: CATHEDRAL CITY VENTURE LLC | E59: 45688 | P59: Time: | Q59: 0.47569444
F62: GLA | G62: Monthly | J62: Annual | K62: Monthly | L62: Expense | M62: Monthly | N62: ------------------- Future Rent Increases ------------------------------------------------
A63: Bldg Id | B63: Suit Id | C63: Occupant Name | D63: Rent Start | E63: Expiration | F63: Sqft | G63: Base Rent | J63: Rate PSF | K63: Cost Recovery | L63: Stop | M63: Other Income | N63: Cat | O63: Date | P63: Monthly Amount | Q63: PSF
A65: 720 | B65: 4091-A | C65: WINCHELLS DONUT HOUSE | D65: 41548 | E65: 46418 | F65: 1200 | G65: 1680.47 | H65: 1680.47 | I65: =H65-G65 -> 0 | J65: 16.8 | K65: 665.25 | N65: BAS | O65: 45689 | P65: 1730.88 | Q65: 17.31
N66: BAS | O66: 46054 | P66: 1782.81 | Q66: 17.83
A67: 720 | B67: 4091-B | C67: MENGS FILIPINO CUISINE | D67: 43235 | E67: 46873 | F67: 1200 | G67: 1854 | H67: 1854 | I67: =H67-G67 -> 0 | J67: 18.54 | K67: 665.25 | N67: BAS | O67: 45778 | P67: 1909.62 | Q67: 19.1
N68: BAS | O68: 46143 | P68: 1966.91 | Q68: 19.67
N69: BAS | O69: 46508 | P69: 2025.92 | Q69: 20.26
A71: 720 | B71: 4101 | C71: DD S DISCOUNT STORE 5313 | D71: 44014 | E71: 47879 | F71: 19300 | G71: 18371.25 | H71: 18371.25 | I71: =H71-G71 -> 0 | J71: 11.42 | K71: 6997.42 | N71: BAS | O71: 45870 | P71: 19968.75 | Q71: 12.42
A73: 720 | B73: 4131-F1 | C73: COACHELLA VALLEY OPTOMETRY | D73: 45626 | E73: 49278 | F73: 1865 | G73: 3541.6 | H73: 3541.6 | I73: =H73-G73 -> 0 | J73: 22.79 | K73: 1033.9 | N73: BAS | O73: 45992 | P73: 3647.23 | Q73: 23.47
N74: BAS | O74: 46357 | P74: 3757.51 | Q74: 24.18
N75: BAS | O75: 46722 | P75: 3869.35 | Q75: 24.9
N76: BAS | O76: 47088 | P76: 3985.85 | Q76: 25.65
N77: BAS | O77: 47453 | P77: 4105.46 | Q77: 26.42
N78: BAS | O78: 47818 | P78: 4228.17 | Q78: 27.21
N79: BAS | O79: 48183 | P79: 4355.55 | Q79: 28.02
N80: BAS | O80: 48549 | P80: 4486.03 | Q80: 28.86
N81: BAS | O81: 48914 | P81: 4621.17 | Q81: 29.73
A82: 720 | B82: 4131-F2 | C82: CLINICA MEDICA FAMILAR | D82: 40113 | E82: 46691 | F82: 3606 | G82: 7428.36 | H82: 7428.36 | I82: =H82-G82 -> 0 | J82: 24.72 | K82: 1999.05 | N82: BAS | O82: 45962 | P82: 7650.73 | Q82: 25.46
N83: BAS | O83: 46327 | P83: 7882.12 | Q83: 26.23
A84: 720 | B84: 4151-AD | C84: PARRANDERO ELEGANTE VIP | D84: 45685 | E84: 47514 | F84: 4804 | G84: 4804 | H84: 619.87 | I84: =H84-G84 -> -4184.13 | J84: 12 | K84: 2663.18 | N84: BAS | O84: 46054 | P84: 4948.12 | Q84: 12.36
N85: BAS | O85: 46419 | P85: 5096.24 | Q85: 12.73
N86: BAS | O86: 46784 | P86: 5248.37 | Q86: 13.11
N87: BAS | O87: 47150 | P87: 5408.5 | Q87: 13.51
A89: 720 | B89: 4151-F | C89: THE SALON | D89: 42912 | E89: 46418 | F89: 1190 | G89: 1893.71 | H89: 1893.71 | I89: =H89-G89 -> 0 | J89: 19.1 | K89: 659.71 | N89: BAS | O89: 45689 | P89: 1950.52 | Q89: 19.67
N90: BAS | O90: 46054 | P90: 2009.03 | Q90: 20.26
A91: 720 | B91: 4151-G | C91: DATE PALM DRUGS | D91: 45193 | E91: 46326 | F91: 1190 | G91: 2083.69 | H91: 2083.69 | I91: =H91-G91 -> 0 | J91: 21.01 | K91: 656.79 | N91: BAS | O91: 45931 | P91: 2146.2 | Q91: 21.64
A93: 720 | B93: 4151-H | C93: TOBACCO FOR LESS | D93: 41487 | E93: 46326 | F93: 1120 | G93: 2141.74 | H93: 2141.74 | I93: =H93-G93 -> 0 | J93: 22.95 | K93: 548.26 | N93: BAS | O93: 45962 | P93: 2206 | Q93: 23.64
A95: 720 | B95: 4251 | C95: FOODS 4 LESS | D95: 33178 | E95: 49613 | F95: 52924 | G95: 32916.67 | H95: 32916.67 | I95: =H95-G95 -> 0 | J95: 7.46 | K95: 18625.24
A97: 720 | B97: 4331 | C97: DJS SPORTS BAR | D97: 44953 | E97: 48610 | F97: 7500 | G97: 6375 | H97: 6375 | I97: =H97-G97 -> 0 | J97: 10.2 | K97: 2394.35 | N97: BAS | O97: 45689 | P97: 8250 | Q97: 13.2
N98: BAS | O98: 46054 | P98: 8662.5 | Q98: 13.86
N99: BAS | O99: 46419 | P99: 9095.63 | Q99: 14.55
N100: BAS | O100: 46784 | P100: 9550.41 | Q100: 15.28
N101: BAS | O101: 47150 | P101: 10027.93 | Q101: 16.04
N102: BAS | O102: 47515 | P102: 10529.32 | Q102: 16.85
N103: BAS | O103: 47880 | P103: 11055.79 | Q103: 17.69
N104: BAS | O104: 48245 | P104: 11608.58 | Q104: 18.57
A106: 720 | B106: 4351-A | C106: LA PALAPA MEXICAN RESTAURANT | D106: 40550 | E106: 46326 | F106: 2055 | G106: 3368.33 | H106: 3368.33 | I106: =H106-G106 -> 0 | J106: 19.67 | K106: 1005.95 | N106: BAS | O106: 45962 | P106: 3469.38 | Q106: 20.26
A108: 720 | B108: 4351-B | C108: FERNANDAS SALVADORIAN FOOD | D108: 41367 | E108: 47026 | F108: 1436 | G108: 2218.62 | H108: 2218.62 | I108: =H108-G108 -> 0 | J108: 18.54 | K108: 702.94 | N108: BAS | O108: 45931 | P108: 2285.18 | Q108: 19.1
A112: Database: | B112: ATHENA | E112: Rent Roll | P112: Page: | Q112: 3
A113: Bldg Status: | B113: Active only | E113: CATHEDRAL CITY MARKETPLACE | P113: Date: | Q113: 45692
A114: CATHEDRAL CITY VENTURE LLC | E114: 45688 | P114: Time: | Q114: 0.47569444
F117: GLA | G117: Monthly | J117: Annual | K117: Monthly | L117: Expense | M117: Monthly | N117: ------------------- Future Rent Increases ------------------------------------------------
A118: Bldg Id | B118: Suit Id | C118: Occupant Name | D118: Rent Start | E118: Expiration | F118: Sqft | G118: Base Rent | J118: Rate PSF | K118: Cost Recovery | L118: Stop | M118: Other Income | N118: Cat | O118: Date | P118: Monthly Amount | Q118: PSF
N120: BAS | O120: 46296 | P120: 2353.73 | Q120: 19.67
N121: BAS | O121: 46661 | P121: 2424.35 | Q121: 20.26
A123: 720 | B123: 4351-E | C123: ROSA ALTERATIONS AND MORE | D123: 44804 | E123: 46721 | F123: 975 | G123: 1603.29 | H123: 1603.29 | I123: =H123-G123 -> 0 | J123: 19.73 | K123: 477.27 | N123: BAS | O123: 45901 | P123: 1651.38 | Q123: 20.32
N124: BAS | O124: 46266 | P124: 1700.93 | Q124: 20.93
N125: BAS | O125: 46631 | P125: 1751.95 | Q125: 21.56
A126: 720 | B126: 4351-F | C126: HOLLYWOOD BEAUTY | D126: 42325 | E126: 47452 | F126: 975 | H126: 1900 | I126: =H126-G126 -> 1900 | K126: 415.02 | N126: BAS | O126: 45992 | P126: 1957 | Q126: 24.09
N127: BAS | O127: 46357 | P127: 2015.71 | Q127: 24.81
N128: BAS | O128: 46722 | P128: 2076.18 | Q128: 25.55
N129: BAS | O129: 47088 | P129: 2138.47 | Q129: 26.32
A130: 720 | B130: 4351-G | C130: METRO BY T MOBILE | D130: 42837 | E130: 46783 | F130: 975 | G130: 2435.31 | H130: 2435.31 | I130: =H130-G130 -> 0 | J130: 29.97 | K130: 477.27 | N130: BAS | O130: 45689 | P130: 2508.37 | Q130: 30.87
N131: BAS | O131: 46054 | P131: 2583.61 | Q131: 31.8
N132: BAS | O132: 46419 | P132: 2661.12 | Q132: 32.75
A134: 720 | B134: 4351-H | C134: A AND A FLOWERS | D134: 44841 | E134: 46783 | F134: 975 | G134: 2008.5 | H134: 2008.5 | I134: =H134-G134 -> 0 | J134: 24.72 | K134: 477.27 | N134: BAS | O134: 45689 | P134: 2068.76 | Q134: 25.46
N135: BAS | O135: 46054 | P135: 2130.82 | Q135: 26.23
N136: BAS | O136: 46419 | P136: 2194.74 | Q136: 27.01
A137: 720 | B137: 4351-K | C137: IN DAN OUT WATER | D137: 35898 | E137: 46418 | F137: 743 | G137: 1552.85 | H137: 1552.85 | I137: =H137-G137 -> 0 | J137: 25.08 | K137: 361.85 | N137: BAS | O137: 45689 | P137: 1599.44 | Q137: 25.83
N138: BAS | O138: 46054 | P138: 1647.42 | Q138: 26.61
A140: 720 | B140: 4451 | C140: TODA MODA | D140: 35414 | E140: 45596 | F140: 7847 | G140: 7193.08 | H140: 7193.08 | I140: =H140-G140 -> 0 | J140: 11 | K140: 2149.02
A142: 720 | B142: 4461 | C142: PLANET FITNESS | D142: 42898 | E142: 47999 | F142: 20000 | G142: 23333.33 | H142: 23333.33 | I142: =H142-G142 -> 0 | J142: 14 | K142: 11080.37 | N142: BAS | O142: 46174 | P142: 23500 | Q142: 14.1
A144: 720 | B144: 4481-AB | C144: ONEMAIN FINANCIAL | D144: 39519 | E144: 47149 | F144: 2400 | G144: 5270.55 | H144: 5270.55 | I144: =H144-G144 -> 0 | J144: 26.35 | K144: 1174.84 | N144: BAS | O144: 45689 | P144: 5428.67 | Q144: 27.14
N145: BAS | O145: 46419 | P145: 5591.53 | Q145: 27.96
...

Sheet 11.24
A2: Database: | B2: ATHENA | E2: Rent Roll | P2: Page: | Q2: 1
A3: Bldg Status: | B3: Active only | E3: CATHEDRAL CITY MARKETPLACE | P3: Date: | Q3: 45692
A4: CATHEDRAL CITY VENTURE LLC | E4: 45688 | P4: Time: | Q4: 0.47569444
F7: GLA | G7: Monthly | H7: CM LEDGER | I7: VARIANCE | J7: Annual | K7: Monthly | L7: Expense | M7: Monthly | N7: ------------------- Future Rent Increases ------------------------------------------------
A8: Bldg Id | B8: Suit Id | C8: Occupant Name | D8: Rent Start | E8: Expiration | F8: Sqft | G8: Base Rent | J8: Rate PSF | K8: Cost Recovery | L8: Stop | M8: Other Income | N8: Cat | O8: Date | P8: Monthly Amount | Q8: PSF
A10: New Leases
A12: 720 | B12: 4351-J | C12: H AND R BLOCK | D12: 45693 | E12: 47603 | F12: 1360
A14: 720 | B14: 4475-AB | C14: CATHEDRAL CITY MEGA DOLLAR | D14: 45689 | E14: 48213 | F14: 3506
A16: Vacant Suites
A18: 720 | B18: 4041-C | C18: Vacant | F18: 1705
A20: 720 | B20: 4081 | C20: Vacant | F20: 5259
A22: 720 | B22: 4151-E | C22: Vacant | F22: 1190
A24: 720 | B24: 4351-C | C24: Vacant | F24: 1950
A26: 720 | B26: 4351-J | C26: Vacant | F26: 1360
A28: 720 | B28: 4475-AB | C28: Vacant | F28: 3506
A30: 720 | B30: 4481-C | C30: Vacant | F30: 400
A32: 720 | B32: 4481-F | C32: Vacant | F32: 1200
A34: 720 | B34: 4491 | C34: Vacant | F34: 29397
A36: Occupied Suites
A38: 720 | B38: 4041-6A | C38: SUBWAY | D38: 40787 | E38: 46326 | F38: 1700 | G38: 3819.32 | H38: 3819.32 | I38: =H38-G38 -> 0 | J38: 26.96 | K38: 942.42 | N38: BAS | O38: 45962 | P38: 3934.18 | Q38: 27.77
A40: 720 | B40: 4041-B | C40: SKY NAILS AND SPA | D40: 42339 | E40: 48244 | F40: 1400 | G40: 2599.21 | H40: 2599.21 | I40: =H40-G40 -> 0 | J40: 22.28 | K40: 776.11 | N40: BAS | O40: 45689 | P40: 2677.18 | Q40: 22.95
N41: BAS | O41: 46054 | P41: 2757.5 | Q41: 23.64
N42: BAS | O42: 46419 | P42: 2840.74 | Q42: 24.35
N43: BAS | O43: 46784 | P43: 2925.96 | Q43: 25.08
N44: BAS | O44: 47150 | P44: 3013.74 | Q44: 25.83
N45: BAS | O45: 47515 | P45: 3104.15 | Q45: 26.61
N46: BAS | O46: 47880 | P46: 3197.28 | Q46: 27.41
A47: 720 | B47: 4041-D | C47: MINTY TEA HOUSE | D47: 44175 | E47: 47208 | F47: 1195 | G47: 2290.42 | H47: 2290.42 | I47: =H47-G47 -> 0 | J47: 23 | K47: 662.47 | N47: BAS | O47: 45748 | P47: 2359.13 | Q47: 23.69
N48: BAS | O48: 46113 | P48: 2429.83 | Q48: 24.4
N49: BAS | O49: 46478 | P49: 2502.53 | Q49: 25.13
N50: BAS | O50: 46844 | P50: 2578.21 | Q50: 25.89
A52: 720 | B52: 4051 | C52: DUTCH BROS COFFEE | D52: 44821 | E52: 50313 | F52: 4000 | G52: 7916.67 | H52: 7916.67 | I52: =H52-G52 -> 0 | J52: 23.75 | K52: 1273.22 | N52: BAS | O52: 46661 | P52: 8708.33 | Q52: 26.12
N53: BAS | O53: 48488 | P53: 9579.17 | Q53: 28.74
A57: Database: | B57: ATHENA | E57: Rent Roll | P57: Page: | Q57: 2
A58: Bldg Status: | B58: Active only | E58: CATHEDRAL CITY MARKETPLACE | P58: Date: | Q58: 45692
A59: CATHEDRAL CITY VENTURE LLC | E59: 45688 | P59: Time: | Q59: 0.47569444
F62: GLA | G62: Monthly | J62: Annual | K62: Monthly | L62: Expense | M62: Monthly | N62: ------------------- Future Rent Increases ------------------------------------------------
A63: Bldg Id | B63: Suit Id | C63: Occupant Name | D63: Rent Start | E63: Expiration | F63: Sqft | G63: Base Rent | J63: Rate PSF | K63: Cost Recovery | L63: Stop | M63: Other Income | N63: Cat | O63: Date | P63: Monthly Amount | Q63: PSF
A65: 720 | B65: 4091-A | C65: WINCHELLS DONUT HOUSE | D65: 41548 | E65: 46418 | F65: 1200 | G65: 1680.47 | H65: 1680.47 | I65: =H65-G65 -> 0 | J65: 16.8 | K65: 665.25 | N65: BAS | O65: 45689 | P65: 1730.88 | Q65: 17.31
N66: BAS | O66: 46054 | P66: 1782.81 | Q66: 17.83
A67: 720 | B67: 4091-B | C67: MENGS FILIPINO CUISINE | D67: 43235 | E67: 46873 | F67: 1200 | G67: 1854 | H67: 1854 | I67: =H67-G67 -> 0 | J67: 18.54 | K67: 665.25 | N67: BAS | O67: 45778 | P67: 1909.62 | Q67: 19.1
N68: BAS | O68: 46143 | P68: 1966.91 | Q68: 19.67
N69: BAS | O69: 46508 | P69: 2025.92 | Q69: 20.26
A71: 720 | B71: 4101 | C71: DD S DISCOUNT STORE 5313 | D71: 44014 | E71: 47879 | F71: 19300 | G71: 18371.25 | H71: 18371.25 | I71: =H71-G71 -> 0 | J71: 11.42 | K71: 6997.42 | N71: BAS | O71: 45870 | P71: 19968.75 | Q71: 12.42
A73: 720 | B73: 4131-F1 | C73: COACHELLA VALLEY OPTOMETRY | D73: 45626 | E73: 49278 | F73: 1865 | G73: 3541.6 | H73: 3541.6 | I73: =H73-G73 -> 0 | J73: 22.79 | K73: 1033.9 | N73: BAS | O73: 45992 | P73: 3647.23 | Q73: 23.47
N74: BAS | O74: 46357 | P74: 3757.51 | Q74: 24.18
N75: BAS | O75: 46722 | P75: 3869.35 | Q75: 24.9
N76: BAS | O76: 47088 | P76: 3985.85 | Q76: 25.65
N77: BAS | O77: 47453 | P77: 4105.46 | Q77: 26.42
N78: BAS | O78: 47818 | P78: 4228.17 | Q78: 27.21
N79: BAS | O79: 48183 | P79: 4355.55 | Q79: 28.02
N80: BAS | O80: 48549 | P80: 4486.03 | Q80: 28.86
N81: BAS | O81: 48914 | P81: 4621.17 | Q81: 29.73
A82: 720 | B82: 4131-F2 | C82: CLINICA MEDICA FAMILAR | D82: 40113 | E82: 46691 | F82: 3606 | G82: 7428.36 | H82: 7428.36 | I82: =H82-G82 -> 0 | J82: 24.72 | K82: 1999.05 | N82: BAS | O82: 45962 | P82: 7650.73 | Q82: 25.46
N83: BAS | O83: 46327 | P83: 7882.12 | Q83: 26.23
A84: 720 | B84: 4151-AD | C84: PARRANDERO ELEGANTE VIP | D84: 45685 | E84: 47514 | F84: 4804 | G84: 4804 | H84: 619.87 | I84: =H84-G84 -> -4184.13 | J84: 12 | K84: 2663.18 | N84: BAS | O84: 46054 | P84: 4948.12 | Q84: 12.36
N85: BAS | O85: 46419 | P85: 5096.24 | Q85: 12.73
N86: BAS | O86: 46784 | P86: 5248.37 | Q86: 13.11
N87: BAS | O87: 47150 | P87: 5408.5 | Q87: 13.51
A89: 720 | B89: 4151-F | C89: THE SALON | D89: 42912 | E89: 46418 | F89: 1190 | G89: 1893.71 | H89: 1893.71 | I89: =H89-G89 -> 0 | J89: 19.1 | K89: 659.71 | N89: BAS | O89: 45689 | P89: 1950.52 | Q89: 19.67
N90: BAS | O90: 46054 | P90: 2009.03 | Q90: 20.26
A91: 720 | B91: 4151-G | C91: DATE PALM DRUGS | D91: 45193 | E91: 46326 | F91: 1190 | G91: 2083.69 | H91: 2083.69 | I91: =H91-G91 -> 0 | J91: 21.01 | K91: 656.79 | N91: BAS | O91: 45931 | P91: 2146.2 | Q91: 21.64
A93: 720 | B93: 4151-H | C93: TOBACCO FOR LESS | D93: 41487 | E93: 46326 | F93: 1120 | G93: 2141.74 | H93: 2141.74 | I93: =H93-G93 -> 0 | J93: 22.95 | K93: 548.26 | N93: BAS | O93: 45962 | P93: 2206 | Q93: 23.64
A95: 720 | B95: 4251 | C95: FOODS 4 LESS | D95: 33178 | E95: 49613 | F95: 52924 | G95: 32916.67 | H95: 32916.67 | I95: =H95-G95 -> 0 | J95: 7.46 | K95: 18625.24
A97: 720 | B97: 4331 | C97: DJS SPORTS BAR | D97: 44953 | E97: 48610 | F97: 7500 | G97: 6375 | H97: 6375 | I97: =H97-G97 -> 0 | J97: 10.2 | K97: 2394.35 | N97: BAS | O97: 45689 | P97: 8250 | Q97: 13.2
N98: BAS | O98: 46054 | P98: 8662.5 | Q98: 13.86
N99: BAS | O99: 46419 | P99: 9095.63 | Q99: 14.55
N100: BAS | O100: 46784 | P100: 9550.41 | Q100: 15.28
N101: BAS | O101: 47150 | P101: 10027.93 | Q101: 16.04
N102: BAS | O102: 47515 | P102: 10529.32 | Q102: 16.85
N103: BAS | O103: 47880 | P103: 11055.79 | Q103: 17.69
N104: BAS | O104: 48245 | P104: 11608.58 | Q104: 18.57
A106: 720 | B106: 4351-A | C106: LA PALAPA MEXICAN RESTAURANT | D106: 40550 | E106: 46326 | F106: 2055 | G106: 3368.33 | H106: 3368.33 | I106: =H106-G106 -> 0 | J106: 19.67 | K106: 1005.95 | N106: BAS | O106: 45962 | P106: 3469.38 | Q106: 20.26
A108: 720 | B108: 4351-B | C108: FERNANDAS SALVADORIAN FOOD | D108: 41367 | E108: 47026 | F108: 1436 | G108: 2218.62 | H108: 2218.62 | I108: =H108-G108 -> 0 | J108: 18.54 | K108: 702.94 | N108: BAS | O108: 45931 | P108: 2285.18 | Q108: 19.1
A112: Database: | B112: ATHENA | E112: Rent Roll | P112: Page: | Q112: 3
A113: Bldg Status: | B113: Active only | E113: CATHEDRAL CITY MARKETPLACE | P113: Date: | Q113: 45692
A114: CATHEDRAL CITY VENTURE LLC | E114: 45688 | P114: Time: | Q114: 0.47569444
F117: GLA | G117: Monthly | J117: Annual | K117: Monthly | L117: Expense | M117: Monthly | N117: ------------------- Future Rent Increases ------------------------------------------------
A118: Bldg Id | B118: Suit Id | C118: Occupant Name | D118: Rent Start | E118: Expiration | F118: Sqft | G118: Base Rent | J118: Rate PSF | K118: Cost Recovery | L118: Stop | M118: Other Income | N118: Cat | O118: Date | P118: Monthly Amount | Q118: PSF
N120: BAS | O120: 46296 | P120: 2353.73 | Q120: 19.67
N121: BAS | O121: 46661 | P121: 2424.35 | Q121: 20.26
A123: 720 | B123: 4351-E | C123: ROSA ALTERATIONS AND MORE | D123: 44804 | E123: 46721 | F123: 975 | G123: 1603.29 | H123: 1603.29 | I123: =H123-G123 -> 0 | J123: 19.73 | K123: 477.27 | N123: BAS | O123: 45901 | P123: 1651.38 | Q123: 20.32
N124: BAS | O124: 46266 | P124: 1700.93 | Q124: 20.93
N125: BAS | O125: 46631 | P125: 1751.95 | Q125: 21.56
A126: 720 | B126: 4351-F | C126: HOLLYWOOD BEAUTY | D126: 42325 | E126: 47452 | F126: 975 | H126: 1900 | I126: =H126-G126 -> 1900 | K126: 415.02 | N126: BAS | O126: 45992 | P126: 1957 | Q126: 24.09
N127: BAS | O127: 46357 | P127: 2015.71 | Q127: 24.81
N128: BAS | O128: 46722 | P128: 2076.18 | Q128: 25.55
N129: BAS | O129: 47088 | P129: 2138.47 | Q129: 26.32
A130: 720 | B130: 4351-G | C130: METRO BY T MOBILE | D130: 42837 | E130: 46783 | F130: 975 | G130: 2435.31 | H130: 2435.31 | I130: =H130-G130 -> 0 | J130: 29.97 | K130: 477.27 | N130: BAS | O130: 45689 | P130: 2508.37 | Q130: 30.87
N131: BAS | O131: 46054 | P131: 2583.61 | Q131: 31.8
N132: BAS | O132: 46419 | P132: 2661.12 | Q132: 32.75
A134: 720 | B134: 4351-H | C134: A AND A FLOWERS | D134: 44841 | E134: 46783 | F134: 975 | G134: 2008.5 | H134: 2008.5 | I134: =H134-G134 -> 0 | J134: 24.72 | K134: 477.27 | N134: BAS | O134: 45689 | P134: 2068.76 | Q134: 25.46
N135: BAS | O135: 46054 | P135: 2130.82 | Q135: 26.23
N136: BAS | O136: 46419 | P136: 2194.74 | Q136: 27.01
A137: 720 | B137: 4351-K | C137: IN DAN OUT WATER | D137: 35898 | E137: 46418 | F137: 743 | G137: 1552.85 | H137: 1552.85 | I137: =H137-G137 -> 0 | J137: 25.08 | K137: 361.85 | N137: BAS | O137: 45689 | P137: 1599.44 | Q137: 25.83
N138: BAS | O138: 46054 | P138: 1647.42 | Q138: 26.61
A140: 720 | B140: 4451 | C140: TODA MODA | D140: 35414 | E140: 45596 | F140: 7847 | G140: 7193.08 | H140: 7193.08 | I140: =H140-G140 -> 0 | J140: 11 | K140: 2149.02
A142: 720 | B142: 4461 | C142: PLANET FITNESS | D142: 42898 | E142: 47999 | F142: 20000 | G142: 23333.33 | H142: 23333.33 | I142: =H142-G142 -> 0 | J142: 14 | K142: 11080.37 | N142: BAS | O142: 46174 | P142: 23500 | Q142: 14.1
A144: 720 | B144: 4481-AB | C144: ONEMAIN FINANCIAL | D144: 39519 | E144: 47149 | F144: 2400 | G144: 5270.55 | H144: 5270.55 | I144: =H144-G144 -> 0 | J144: 26.35 | K144: 1174.84 | N144: BAS | O144: 45689 | P144: 5428.67 | Q144: 27.14
N145: BAS | O145: 46419 | P145: 5591.53 | Q145: 27.96
...

Sheet Tenant Credits
A1: AR Credits/CAM Credit AC #40140 | K1: ONLY MAKE JOURNAL ENTRIES FOR CASH BOOK WHEN TENANTS TAKE THE CREDITS
K2: DO NOT MAKE ANY JES FOR ACCRUAL BOOKS
C5: Aging Set
A6: Tenant Name | B6: Unit Number | C6: 0 | D6: 1 – 30 | E6: 31 – 60 | F6: 61 – 90 | G6: 91 – 120 | H6: 121 + | I6: Grand Total | J6: Credit Amount | L6: DR 26300
B7: 002 (BU3700202) | C7: 166.36 | D7: 438.1 | E7: -40.27 | F7: -40.27 | G7: -40.27 | H7: -887.76 | I7: -404.11 | J7: =-404.11+404.11 -> 0 | L7: CR 40140
B8: 011 (BU3700201) | H8: -19653.76 | I8: -19653.76 | J8: 0 | L8: OR CR 40150 (USE THIS ACT ONLY FOR HOMEGOODS)
B9: 001 (BU3700202) | C9: -143.95 | I9: -143.95
B10: 005 (BU3700202) | C10: -115.16 | D10: -778.64 | I10: -893.8
B11: 016 (BU3700201) | D11: 789.04 | H11: -1383.93 | I11: -594.82 | J11: 0
B12: 002 (BU3700201) | C12: 19.68 | E12: -379.17 | I12: -359.49
B13: 017 (BU3700201) | C13: 44.75 | H13: -114.87 | I13: -70.13 | J13: =-70.13+70.13 -> 0
B14: 006 (BU3700201) | C14: 14.76 | E14: -286.37 | F14: -2 | G14: -3 | H14: 224.22 | I14: -52.49 | J14: =-52.49+52.49 -> 0
B15: 016 (BU3700202) | C15: -12.53 | E15: -838.54 | F15: -1734.5 | I15: -2585.57 | J15: =-2585.57+2585.57 -> 0
B16: 008 (BU3700201) | C16: 14.76 | D16: 84.64 | E16: -249.73 | F16: 34.64 | G16: 34.64 | H16: -65.39 | I16: -146.47 | J16: =-146.47+146.47 -> 0
B17: 007 (BU3700202) | C17: -132.43 | I17: -132.43
B18: 009 (BU3700202) | C18: 458.16 | D18: -1973.67 | E18: -404.57 | F18: -441.59 | G18: -404.57 | H18: -3486.54 | I18: -6252.78 | J18: 0
A19: Grand Total | C19: 1498.33 | D19: 97504.41 | E19: -198.01 | F19: -3291.94 | G19: -440.24 | H19: -24846.1 | I19: 70226.45 | J19: =SUM(J7:J18) -> 0
A22: PYC Credit AC #40150
A23: 0 | J23: 0
A26: Total AC #26300 | J26: =+J19+J23 -> 0
M1432: 25.982462

Sheet INCOME VAR
A1: CASH BASIS:
B3: Comp IS | D3: Cash Receipts
A4: BASE RENTAL | B4: 144710.62 | D4: 132398.22 | F4: =B4-D4 -> 12312.4 | G4: Jewelry Unlimited $2,532.40 + Togo's $9,780 Security Deposit Applied
A5: PERCENTAGE RENT | B5: 988.53 | D5: 988.53 | F5: =B5-D5 -> 0
A6: OTHER RENT | B6: 0 | D6: 0 | F6: =B6-D6 -> 0
A7: COMMON AREA INCOME | B7: 34830.53 | D7: 34830.53 | F7: =B7-D7 -> 0
A8: PRIOR YEAR CAM | B8: -2633.27 | D8: -2633.27 | F8: =B8-D8 -> 0
A9: OTHER RECOVERIES | B9: 3211.1 | D9: 3211.1 | F9: =B9-D9 -> 0
A10: INSURANCE INCOME | B10: 996.19 | D10: 996.19 | F10: =B10-D10 -> 0
A11: REAL ESTATE TAX | B11: 32956.25 | D11: 32956.25 | F11: =B11-D11 -> 0
A12: MANAGEMENT FEE INCOME | B12: 3559.18 | D12: 3559.18 | F12: =B12-D12 -> 0
A13: LATE CHARGE | B13: 63.32 | D13: 63.32 | F13: =B13-D13 -> 0
A14: PREPAID RENT | B14: 0 | D14: 498.99 | F14: =B14-D14 -> -498.99 | G14: Tuesday Morning ($246) + Burlington Coat ($106.81) + Aaron Brother ($116.08) + Fitzone ($30.10)
A15: TENANT BILL BACKS | B15: 0 | D15: 0 | F15: =B15-D15 -> 0
A16: TOTAL | B16: =SUM(B4:B15) -> 218682.45 | D16: =SUM(D4:D15) -> 206869.04
A18: ACCRUAL BASIS:
B21: Rent Up | D21: Rent Roll
A22: BASE RENTAL | B22: 143398.99 | D22: 130217.25 | F22: =B22-D22 -> 13181.74 | G22: Togo's $3,594.15 + Jewelry Unlimited $1,670.92 + Applebees $7,916.67
